package com.google.android.gms.dynamic;

import android.os.IBinder;
import android.os.Parcel;

class zzc$zza$zza
  implements zzc
{
  private IBinder zzoz;
  
  zzc$zza$zza(IBinder paramIBinder)
  {
    this.zzoz = paramIBinder;
  }
  
  public IBinder asBinder()
  {
    return this.zzoz;
  }
  
  /* Error */
  public android.os.Bundle getArguments()
  {
    // Byte code:
    //   0: invokestatic 20	android/os/Parcel:obtain	()Landroid/os/Parcel;
    //   3: astore_1
    //   4: invokestatic 20	android/os/Parcel:obtain	()Landroid/os/Parcel;
    //   7: astore_2
    //   8: ldc 22
    //   10: astore_3
    //   11: aload_1
    //   12: aload_3
    //   13: invokevirtual 26	android/os/Parcel:writeInterfaceToken	(Ljava/lang/String;)V
    //   16: aload_0
    //   17: getfield 14	com/google/android/gms/dynamic/zzc$zza$zza:zzoz	Landroid/os/IBinder;
    //   20: astore_3
    //   21: iconst_3
    //   22: istore 4
    //   24: aload_3
    //   25: iload 4
    //   27: aload_1
    //   28: aload_2
    //   29: iconst_0
    //   30: invokeinterface 33 5 0
    //   35: pop
    //   36: aload_2
    //   37: invokevirtual 36	android/os/Parcel:readException	()V
    //   40: aload_2
    //   41: invokevirtual 40	android/os/Parcel:readInt	()I
    //   44: istore 5
    //   46: iload 5
    //   48: ifeq +30 -> 78
    //   51: getstatic 46	android/os/Bundle:CREATOR	Landroid/os/Parcelable$Creator;
    //   54: astore_3
    //   55: aload_3
    //   56: aload_2
    //   57: invokeinterface 52 2 0
    //   62: astore_3
    //   63: aload_3
    //   64: checkcast 42	android/os/Bundle
    //   67: astore_3
    //   68: aload_2
    //   69: invokevirtual 55	android/os/Parcel:recycle	()V
    //   72: aload_1
    //   73: invokevirtual 55	android/os/Parcel:recycle	()V
    //   76: aload_3
    //   77: areturn
    //   78: iconst_0
    //   79: istore 5
    //   81: aconst_null
    //   82: astore_3
    //   83: goto -15 -> 68
    //   86: astore_3
    //   87: aload_2
    //   88: invokevirtual 55	android/os/Parcel:recycle	()V
    //   91: aload_1
    //   92: invokevirtual 55	android/os/Parcel:recycle	()V
    //   95: aload_3
    //   96: athrow
    // Local variable table:
    //   start	length	slot	name	signature
    //   0	97	0	this	zza
    //   3	89	1	localParcel1	Parcel
    //   7	81	2	localParcel2	Parcel
    //   10	73	3	localObject1	Object
    //   86	10	3	localObject2	Object
    //   22	4	4	i	int
    //   44	36	5	j	int
    // Exception table:
    //   from	to	target	type
    //   12	16	86	finally
    //   16	20	86	finally
    //   29	36	86	finally
    //   36	40	86	finally
    //   40	44	86	finally
    //   51	54	86	finally
    //   56	62	86	finally
    //   63	67	86	finally
  }
  
  public int getId()
  {
    Parcel localParcel1 = Parcel.obtain();
    Parcel localParcel2 = Parcel.obtain();
    Object localObject1 = "com.google.android.gms.dynamic.IFragmentWrapper";
    try
    {
      localParcel1.writeInterfaceToken((String)localObject1);
      localObject1 = this.zzoz;
      int i = 4;
      ((IBinder)localObject1).transact(i, localParcel1, localParcel2, 0);
      localParcel2.readException();
      int j = localParcel2.readInt();
      return j;
    }
    finally
    {
      localParcel2.recycle();
      localParcel1.recycle();
    }
  }
  
  public boolean getRetainInstance()
  {
    boolean bool = false;
    Object localObject1 = null;
    Parcel localParcel1 = Parcel.obtain();
    Parcel localParcel2 = Parcel.obtain();
    Object localObject3 = "com.google.android.gms.dynamic.IFragmentWrapper";
    try
    {
      localParcel1.writeInterfaceToken((String)localObject3);
      localObject3 = this.zzoz;
      int i = 7;
      ((IBinder)localObject3).transact(i, localParcel1, localParcel2, 0);
      localParcel2.readException();
      int j = localParcel2.readInt();
      if (j != 0) {
        bool = true;
      }
      return bool;
    }
    finally
    {
      localParcel2.recycle();
      localParcel1.recycle();
    }
  }
  
  public String getTag()
  {
    Parcel localParcel1 = Parcel.obtain();
    Parcel localParcel2 = Parcel.obtain();
    Object localObject1 = "com.google.android.gms.dynamic.IFragmentWrapper";
    try
    {
      localParcel1.writeInterfaceToken((String)localObject1);
      localObject1 = this.zzoz;
      int i = 8;
      ((IBinder)localObject1).transact(i, localParcel1, localParcel2, 0);
      localParcel2.readException();
      localObject1 = localParcel2.readString();
      return (String)localObject1;
    }
    finally
    {
      localParcel2.recycle();
      localParcel1.recycle();
    }
  }
  
  public int getTargetRequestCode()
  {
    Parcel localParcel1 = Parcel.obtain();
    Parcel localParcel2 = Parcel.obtain();
    Object localObject1 = "com.google.android.gms.dynamic.IFragmentWrapper";
    try
    {
      localParcel1.writeInterfaceToken((String)localObject1);
      localObject1 = this.zzoz;
      int i = 10;
      ((IBinder)localObject1).transact(i, localParcel1, localParcel2, 0);
      localParcel2.readException();
      int j = localParcel2.readInt();
      return j;
    }
    finally
    {
      localParcel2.recycle();
      localParcel1.recycle();
    }
  }
  
  public boolean getUserVisibleHint()
  {
    boolean bool = false;
    Object localObject1 = null;
    Parcel localParcel1 = Parcel.obtain();
    Parcel localParcel2 = Parcel.obtain();
    Object localObject3 = "com.google.android.gms.dynamic.IFragmentWrapper";
    try
    {
      localParcel1.writeInterfaceToken((String)localObject3);
      localObject3 = this.zzoz;
      int i = 11;
      ((IBinder)localObject3).transact(i, localParcel1, localParcel2, 0);
      localParcel2.readException();
      int j = localParcel2.readInt();
      if (j != 0) {
        bool = true;
      }
      return bool;
    }
    finally
    {
      localParcel2.recycle();
      localParcel1.recycle();
    }
  }
  
  public zzd getView()
  {
    Parcel localParcel1 = Parcel.obtain();
    Parcel localParcel2 = Parcel.obtain();
    Object localObject1 = "com.google.android.gms.dynamic.IFragmentWrapper";
    try
    {
      localParcel1.writeInterfaceToken((String)localObject1);
      localObject1 = this.zzoz;
      int i = 12;
      ((IBinder)localObject1).transact(i, localParcel1, localParcel2, 0);
      localParcel2.readException();
      localObject1 = localParcel2.readStrongBinder();
      localObject1 = zzd.zza.zzbs((IBinder)localObject1);
      return (zzd)localObject1;
    }
    finally
    {
      localParcel2.recycle();
      localParcel1.recycle();
    }
  }
  
  public boolean isAdded()
  {
    boolean bool = false;
    Object localObject1 = null;
    Parcel localParcel1 = Parcel.obtain();
    Parcel localParcel2 = Parcel.obtain();
    Object localObject3 = "com.google.android.gms.dynamic.IFragmentWrapper";
    try
    {
      localParcel1.writeInterfaceToken((String)localObject3);
      localObject3 = this.zzoz;
      int i = 13;
      ((IBinder)localObject3).transact(i, localParcel1, localParcel2, 0);
      localParcel2.readException();
      int j = localParcel2.readInt();
      if (j != 0) {
        bool = true;
      }
      return bool;
    }
    finally
    {
      localParcel2.recycle();
      localParcel1.recycle();
    }
  }
  
  public boolean isDetached()
  {
    boolean bool = false;
    Object localObject1 = null;
    Parcel localParcel1 = Parcel.obtain();
    Parcel localParcel2 = Parcel.obtain();
    Object localObject3 = "com.google.android.gms.dynamic.IFragmentWrapper";
    try
    {
      localParcel1.writeInterfaceToken((String)localObject3);
      localObject3 = this.zzoz;
      int i = 14;
      ((IBinder)localObject3).transact(i, localParcel1, localParcel2, 0);
      localParcel2.readException();
      int j = localParcel2.readInt();
      if (j != 0) {
        bool = true;
      }
      return bool;
    }
    finally
    {
      localParcel2.recycle();
      localParcel1.recycle();
    }
  }
  
  public boolean isHidden()
  {
    boolean bool = false;
    Object localObject1 = null;
    Parcel localParcel1 = Parcel.obtain();
    Parcel localParcel2 = Parcel.obtain();
    Object localObject3 = "com.google.android.gms.dynamic.IFragmentWrapper";
    try
    {
      localParcel1.writeInterfaceToken((String)localObject3);
      localObject3 = this.zzoz;
      int i = 15;
      ((IBinder)localObject3).transact(i, localParcel1, localParcel2, 0);
      localParcel2.readException();
      int j = localParcel2.readInt();
      if (j != 0) {
        bool = true;
      }
      return bool;
    }
    finally
    {
      localParcel2.recycle();
      localParcel1.recycle();
    }
  }
  
  public boolean isInLayout()
  {
    boolean bool = false;
    Object localObject1 = null;
    Parcel localParcel1 = Parcel.obtain();
    Parcel localParcel2 = Parcel.obtain();
    Object localObject3 = "com.google.android.gms.dynamic.IFragmentWrapper";
    try
    {
      localParcel1.writeInterfaceToken((String)localObject3);
      localObject3 = this.zzoz;
      int i = 16;
      ((IBinder)localObject3).transact(i, localParcel1, localParcel2, 0);
      localParcel2.readException();
      int j = localParcel2.readInt();
      if (j != 0) {
        bool = true;
      }
      return bool;
    }
    finally
    {
      localParcel2.recycle();
      localParcel1.recycle();
    }
  }
  
  public boolean isRemoving()
  {
    boolean bool = false;
    Object localObject1 = null;
    Parcel localParcel1 = Parcel.obtain();
    Parcel localParcel2 = Parcel.obtain();
    Object localObject3 = "com.google.android.gms.dynamic.IFragmentWrapper";
    try
    {
      localParcel1.writeInterfaceToken((String)localObject3);
      localObject3 = this.zzoz;
      int i = 17;
      ((IBinder)localObject3).transact(i, localParcel1, localParcel2, 0);
      localParcel2.readException();
      int j = localParcel2.readInt();
      if (j != 0) {
        bool = true;
      }
      return bool;
    }
    finally
    {
      localParcel2.recycle();
      localParcel1.recycle();
    }
  }
  
  public boolean isResumed()
  {
    boolean bool = false;
    Object localObject1 = null;
    Parcel localParcel1 = Parcel.obtain();
    Parcel localParcel2 = Parcel.obtain();
    Object localObject3 = "com.google.android.gms.dynamic.IFragmentWrapper";
    try
    {
      localParcel1.writeInterfaceToken((String)localObject3);
      localObject3 = this.zzoz;
      int i = 18;
      ((IBinder)localObject3).transact(i, localParcel1, localParcel2, 0);
      localParcel2.readException();
      int j = localParcel2.readInt();
      if (j != 0) {
        bool = true;
      }
      return bool;
    }
    finally
    {
      localParcel2.recycle();
      localParcel1.recycle();
    }
  }
  
  public boolean isVisible()
  {
    boolean bool = false;
    Object localObject1 = null;
    Parcel localParcel1 = Parcel.obtain();
    Parcel localParcel2 = Parcel.obtain();
    Object localObject3 = "com.google.android.gms.dynamic.IFragmentWrapper";
    try
    {
      localParcel1.writeInterfaceToken((String)localObject3);
      localObject3 = this.zzoz;
      int i = 19;
      ((IBinder)localObject3).transact(i, localParcel1, localParcel2, 0);
      localParcel2.readException();
      int j = localParcel2.readInt();
      if (j != 0) {
        bool = true;
      }
      return bool;
    }
    finally
    {
      localParcel2.recycle();
      localParcel1.recycle();
    }
  }
  
  public void setHasOptionsMenu(boolean paramBoolean)
  {
    int i = 0;
    IBinder localIBinder = null;
    Parcel localParcel1 = Parcel.obtain();
    Parcel localParcel2 = Parcel.obtain();
    String str = "com.google.android.gms.dynamic.IFragmentWrapper";
    try
    {
      localParcel1.writeInterfaceToken(str);
      if (paramBoolean) {
        i = 1;
      }
      localParcel1.writeInt(i);
      localIBinder = this.zzoz;
      int j = 21;
      localIBinder.transact(j, localParcel1, localParcel2, 0);
      localParcel2.readException();
      return;
    }
    finally
    {
      localParcel2.recycle();
      localParcel1.recycle();
    }
  }
  
  public void setMenuVisibility(boolean paramBoolean)
  {
    int i = 0;
    IBinder localIBinder = null;
    Parcel localParcel1 = Parcel.obtain();
    Parcel localParcel2 = Parcel.obtain();
    String str = "com.google.android.gms.dynamic.IFragmentWrapper";
    try
    {
      localParcel1.writeInterfaceToken(str);
      if (paramBoolean) {
        i = 1;
      }
      localParcel1.writeInt(i);
      localIBinder = this.zzoz;
      int j = 22;
      localIBinder.transact(j, localParcel1, localParcel2, 0);
      localParcel2.readException();
      return;
    }
    finally
    {
      localParcel2.recycle();
      localParcel1.recycle();
    }
  }
  
  public void setRetainInstance(boolean paramBoolean)
  {
    int i = 0;
    IBinder localIBinder = null;
    Parcel localParcel1 = Parcel.obtain();
    Parcel localParcel2 = Parcel.obtain();
    String str = "com.google.android.gms.dynamic.IFragmentWrapper";
    try
    {
      localParcel1.writeInterfaceToken(str);
      if (paramBoolean) {
        i = 1;
      }
      localParcel1.writeInt(i);
      localIBinder = this.zzoz;
      int j = 23;
      localIBinder.transact(j, localParcel1, localParcel2, 0);
      localParcel2.readException();
      return;
    }
    finally
    {
      localParcel2.recycle();
      localParcel1.recycle();
    }
  }
  
  public void setUserVisibleHint(boolean paramBoolean)
  {
    int i = 0;
    IBinder localIBinder = null;
    Parcel localParcel1 = Parcel.obtain();
    Parcel localParcel2 = Parcel.obtain();
    String str = "com.google.android.gms.dynamic.IFragmentWrapper";
    try
    {
      localParcel1.writeInterfaceToken(str);
      if (paramBoolean) {
        i = 1;
      }
      localParcel1.writeInt(i);
      localIBinder = this.zzoz;
      int j = 24;
      localIBinder.transact(j, localParcel1, localParcel2, 0);
      localParcel2.readException();
      return;
    }
    finally
    {
      localParcel2.recycle();
      localParcel1.recycle();
    }
  }
  
  /* Error */
  public void startActivity(android.content.Intent paramIntent)
  {
    // Byte code:
    //   0: invokestatic 20	android/os/Parcel:obtain	()Landroid/os/Parcel;
    //   3: astore_2
    //   4: invokestatic 20	android/os/Parcel:obtain	()Landroid/os/Parcel;
    //   7: astore_3
    //   8: ldc 22
    //   10: astore 4
    //   12: aload_2
    //   13: aload 4
    //   15: invokevirtual 26	android/os/Parcel:writeInterfaceToken	(Ljava/lang/String;)V
    //   18: aload_1
    //   19: ifnull +60 -> 79
    //   22: iconst_1
    //   23: istore 5
    //   25: aload_2
    //   26: iload 5
    //   28: invokevirtual 87	android/os/Parcel:writeInt	(I)V
    //   31: iconst_0
    //   32: istore 5
    //   34: aconst_null
    //   35: astore 4
    //   37: aload_1
    //   38: aload_2
    //   39: iconst_0
    //   40: invokevirtual 97	android/content/Intent:writeToParcel	(Landroid/os/Parcel;I)V
    //   43: aload_0
    //   44: getfield 14	com/google/android/gms/dynamic/zzc$zza$zza:zzoz	Landroid/os/IBinder;
    //   47: astore 4
    //   49: bipush 25
    //   51: istore 6
    //   53: aload 4
    //   55: iload 6
    //   57: aload_2
    //   58: aload_3
    //   59: iconst_0
    //   60: invokeinterface 33 5 0
    //   65: pop
    //   66: aload_3
    //   67: invokevirtual 36	android/os/Parcel:readException	()V
    //   70: aload_3
    //   71: invokevirtual 55	android/os/Parcel:recycle	()V
    //   74: aload_2
    //   75: invokevirtual 55	android/os/Parcel:recycle	()V
    //   78: return
    //   79: iconst_0
    //   80: istore 5
    //   82: aconst_null
    //   83: astore 4
    //   85: aload_2
    //   86: iconst_0
    //   87: invokevirtual 87	android/os/Parcel:writeInt	(I)V
    //   90: goto -47 -> 43
    //   93: astore 4
    //   95: aload_3
    //   96: invokevirtual 55	android/os/Parcel:recycle	()V
    //   99: aload_2
    //   100: invokevirtual 55	android/os/Parcel:recycle	()V
    //   103: aload 4
    //   105: athrow
    // Local variable table:
    //   start	length	slot	name	signature
    //   0	106	0	this	zza
    //   0	106	1	paramIntent	android.content.Intent
    //   3	97	2	localParcel1	Parcel
    //   7	89	3	localParcel2	Parcel
    //   10	74	4	localObject1	Object
    //   93	11	4	localObject2	Object
    //   23	58	5	i	int
    //   51	5	6	j	int
    // Exception table:
    //   from	to	target	type
    //   13	18	93	finally
    //   26	31	93	finally
    //   39	43	93	finally
    //   43	47	93	finally
    //   59	66	93	finally
    //   66	70	93	finally
    //   86	90	93	finally
  }
  
  /* Error */
  public void startActivityForResult(android.content.Intent paramIntent, int paramInt)
  {
    // Byte code:
    //   0: invokestatic 20	android/os/Parcel:obtain	()Landroid/os/Parcel;
    //   3: astore_3
    //   4: invokestatic 20	android/os/Parcel:obtain	()Landroid/os/Parcel;
    //   7: astore 4
    //   9: ldc 22
    //   11: astore 5
    //   13: aload_3
    //   14: aload 5
    //   16: invokevirtual 26	android/os/Parcel:writeInterfaceToken	(Ljava/lang/String;)V
    //   19: aload_1
    //   20: ifnull +68 -> 88
    //   23: iconst_1
    //   24: istore 6
    //   26: aload_3
    //   27: iload 6
    //   29: invokevirtual 87	android/os/Parcel:writeInt	(I)V
    //   32: iconst_0
    //   33: istore 6
    //   35: aconst_null
    //   36: astore 5
    //   38: aload_1
    //   39: aload_3
    //   40: iconst_0
    //   41: invokevirtual 97	android/content/Intent:writeToParcel	(Landroid/os/Parcel;I)V
    //   44: aload_3
    //   45: iload_2
    //   46: invokevirtual 87	android/os/Parcel:writeInt	(I)V
    //   49: aload_0
    //   50: getfield 14	com/google/android/gms/dynamic/zzc$zza$zza:zzoz	Landroid/os/IBinder;
    //   53: astore 5
    //   55: bipush 26
    //   57: istore 7
    //   59: aload 5
    //   61: iload 7
    //   63: aload_3
    //   64: aload 4
    //   66: iconst_0
    //   67: invokeinterface 33 5 0
    //   72: pop
    //   73: aload 4
    //   75: invokevirtual 36	android/os/Parcel:readException	()V
    //   78: aload 4
    //   80: invokevirtual 55	android/os/Parcel:recycle	()V
    //   83: aload_3
    //   84: invokevirtual 55	android/os/Parcel:recycle	()V
    //   87: return
    //   88: iconst_0
    //   89: istore 6
    //   91: aconst_null
    //   92: astore 5
    //   94: aload_3
    //   95: iconst_0
    //   96: invokevirtual 87	android/os/Parcel:writeInt	(I)V
    //   99: goto -55 -> 44
    //   102: astore 5
    //   104: aload 4
    //   106: invokevirtual 55	android/os/Parcel:recycle	()V
    //   109: aload_3
    //   110: invokevirtual 55	android/os/Parcel:recycle	()V
    //   113: aload 5
    //   115: athrow
    // Local variable table:
    //   start	length	slot	name	signature
    //   0	116	0	this	zza
    //   0	116	1	paramIntent	android.content.Intent
    //   0	116	2	paramInt	int
    //   3	107	3	localParcel1	Parcel
    //   7	98	4	localParcel2	Parcel
    //   11	82	5	localObject1	Object
    //   102	12	5	localObject2	Object
    //   24	66	6	i	int
    //   57	5	7	j	int
    // Exception table:
    //   from	to	target	type
    //   14	19	102	finally
    //   27	32	102	finally
    //   40	44	102	finally
    //   45	49	102	finally
    //   49	53	102	finally
    //   66	73	102	finally
    //   73	78	102	finally
    //   95	99	102	finally
  }
  
  /* Error */
  public void zzn(zzd paramzzd)
  {
    // Byte code:
    //   0: invokestatic 20	android/os/Parcel:obtain	()Landroid/os/Parcel;
    //   3: astore_2
    //   4: invokestatic 20	android/os/Parcel:obtain	()Landroid/os/Parcel;
    //   7: astore_3
    //   8: ldc 22
    //   10: astore 4
    //   12: aload_2
    //   13: aload 4
    //   15: invokevirtual 26	android/os/Parcel:writeInterfaceToken	(Ljava/lang/String;)V
    //   18: aload_1
    //   19: ifnull +53 -> 72
    //   22: aload_1
    //   23: invokeinterface 104 1 0
    //   28: astore 4
    //   30: aload_2
    //   31: aload 4
    //   33: invokevirtual 108	android/os/Parcel:writeStrongBinder	(Landroid/os/IBinder;)V
    //   36: aload_0
    //   37: getfield 14	com/google/android/gms/dynamic/zzc$zza$zza:zzoz	Landroid/os/IBinder;
    //   40: astore 4
    //   42: bipush 20
    //   44: istore 5
    //   46: aload 4
    //   48: iload 5
    //   50: aload_2
    //   51: aload_3
    //   52: iconst_0
    //   53: invokeinterface 33 5 0
    //   58: pop
    //   59: aload_3
    //   60: invokevirtual 36	android/os/Parcel:readException	()V
    //   63: aload_3
    //   64: invokevirtual 55	android/os/Parcel:recycle	()V
    //   67: aload_2
    //   68: invokevirtual 55	android/os/Parcel:recycle	()V
    //   71: return
    //   72: aconst_null
    //   73: astore 4
    //   75: goto -45 -> 30
    //   78: astore 4
    //   80: aload_3
    //   81: invokevirtual 55	android/os/Parcel:recycle	()V
    //   84: aload_2
    //   85: invokevirtual 55	android/os/Parcel:recycle	()V
    //   88: aload 4
    //   90: athrow
    // Local variable table:
    //   start	length	slot	name	signature
    //   0	91	0	this	zza
    //   0	91	1	paramzzd	zzd
    //   3	82	2	localParcel1	Parcel
    //   7	74	3	localParcel2	Parcel
    //   10	64	4	localObject1	Object
    //   78	11	4	localObject2	Object
    //   44	5	5	i	int
    // Exception table:
    //   from	to	target	type
    //   13	18	78	finally
    //   22	28	78	finally
    //   31	36	78	finally
    //   36	40	78	finally
    //   52	59	78	finally
    //   59	63	78	finally
  }
  
  /* Error */
  public void zzo(zzd paramzzd)
  {
    // Byte code:
    //   0: invokestatic 20	android/os/Parcel:obtain	()Landroid/os/Parcel;
    //   3: astore_2
    //   4: invokestatic 20	android/os/Parcel:obtain	()Landroid/os/Parcel;
    //   7: astore_3
    //   8: ldc 22
    //   10: astore 4
    //   12: aload_2
    //   13: aload 4
    //   15: invokevirtual 26	android/os/Parcel:writeInterfaceToken	(Ljava/lang/String;)V
    //   18: aload_1
    //   19: ifnull +53 -> 72
    //   22: aload_1
    //   23: invokeinterface 104 1 0
    //   28: astore 4
    //   30: aload_2
    //   31: aload 4
    //   33: invokevirtual 108	android/os/Parcel:writeStrongBinder	(Landroid/os/IBinder;)V
    //   36: aload_0
    //   37: getfield 14	com/google/android/gms/dynamic/zzc$zza$zza:zzoz	Landroid/os/IBinder;
    //   40: astore 4
    //   42: bipush 27
    //   44: istore 5
    //   46: aload 4
    //   48: iload 5
    //   50: aload_2
    //   51: aload_3
    //   52: iconst_0
    //   53: invokeinterface 33 5 0
    //   58: pop
    //   59: aload_3
    //   60: invokevirtual 36	android/os/Parcel:readException	()V
    //   63: aload_3
    //   64: invokevirtual 55	android/os/Parcel:recycle	()V
    //   67: aload_2
    //   68: invokevirtual 55	android/os/Parcel:recycle	()V
    //   71: return
    //   72: aconst_null
    //   73: astore 4
    //   75: goto -45 -> 30
    //   78: astore 4
    //   80: aload_3
    //   81: invokevirtual 55	android/os/Parcel:recycle	()V
    //   84: aload_2
    //   85: invokevirtual 55	android/os/Parcel:recycle	()V
    //   88: aload 4
    //   90: athrow
    // Local variable table:
    //   start	length	slot	name	signature
    //   0	91	0	this	zza
    //   0	91	1	paramzzd	zzd
    //   3	82	2	localParcel1	Parcel
    //   7	74	3	localParcel2	Parcel
    //   10	64	4	localObject1	Object
    //   78	11	4	localObject2	Object
    //   44	5	5	i	int
    // Exception table:
    //   from	to	target	type
    //   13	18	78	finally
    //   22	28	78	finally
    //   31	36	78	finally
    //   36	40	78	finally
    //   52	59	78	finally
    //   59	63	78	finally
  }
  
  public zzd zztV()
  {
    Parcel localParcel1 = Parcel.obtain();
    Parcel localParcel2 = Parcel.obtain();
    Object localObject1 = "com.google.android.gms.dynamic.IFragmentWrapper";
    try
    {
      localParcel1.writeInterfaceToken((String)localObject1);
      localObject1 = this.zzoz;
      int i = 2;
      ((IBinder)localObject1).transact(i, localParcel1, localParcel2, 0);
      localParcel2.readException();
      localObject1 = localParcel2.readStrongBinder();
      localObject1 = zzd.zza.zzbs((IBinder)localObject1);
      return (zzd)localObject1;
    }
    finally
    {
      localParcel2.recycle();
      localParcel1.recycle();
    }
  }
  
  public zzc zztW()
  {
    Parcel localParcel1 = Parcel.obtain();
    Parcel localParcel2 = Parcel.obtain();
    Object localObject1 = "com.google.android.gms.dynamic.IFragmentWrapper";
    try
    {
      localParcel1.writeInterfaceToken((String)localObject1);
      localObject1 = this.zzoz;
      int i = 5;
      ((IBinder)localObject1).transact(i, localParcel1, localParcel2, 0);
      localParcel2.readException();
      localObject1 = localParcel2.readStrongBinder();
      localObject1 = zzc.zza.zzbr((IBinder)localObject1);
      return (zzc)localObject1;
    }
    finally
    {
      localParcel2.recycle();
      localParcel1.recycle();
    }
  }
  
  public zzd zztX()
  {
    Parcel localParcel1 = Parcel.obtain();
    Parcel localParcel2 = Parcel.obtain();
    Object localObject1 = "com.google.android.gms.dynamic.IFragmentWrapper";
    try
    {
      localParcel1.writeInterfaceToken((String)localObject1);
      localObject1 = this.zzoz;
      int i = 6;
      ((IBinder)localObject1).transact(i, localParcel1, localParcel2, 0);
      localParcel2.readException();
      localObject1 = localParcel2.readStrongBinder();
      localObject1 = zzd.zza.zzbs((IBinder)localObject1);
      return (zzd)localObject1;
    }
    finally
    {
      localParcel2.recycle();
      localParcel1.recycle();
    }
  }
  
  public zzc zztY()
  {
    Parcel localParcel1 = Parcel.obtain();
    Parcel localParcel2 = Parcel.obtain();
    Object localObject1 = "com.google.android.gms.dynamic.IFragmentWrapper";
    try
    {
      localParcel1.writeInterfaceToken((String)localObject1);
      localObject1 = this.zzoz;
      int i = 9;
      ((IBinder)localObject1).transact(i, localParcel1, localParcel2, 0);
      localParcel2.readException();
      localObject1 = localParcel2.readStrongBinder();
      localObject1 = zzc.zza.zzbr((IBinder)localObject1);
      return (zzc)localObject1;
    }
    finally
    {
      localParcel2.recycle();
      localParcel1.recycle();
    }
  }
}


/* Location:              C:\Users\haryo\Desktop\enjarify-master\presensi-enjarify.jar!\com\google\android\gms\dynamic\zzc$zza$zza.class
 * Java compiler version: 5 (49.0)
 * JD-Core Version:       0.7.1
 */