package com.google.android.gms.internal;

import android.content.Context;
import android.util.DisplayMetrics;
import android.view.MotionEvent;
import com.google.ads.afma.nano.NanoAdshieldEvent.AdShieldEvent;
import com.google.android.gms.clearcut.zzb;
import com.google.android.gms.clearcut.zzb.zza;
import com.google.android.gms.common.api.Api;
import com.google.android.gms.common.api.GoogleApiClient;
import com.google.android.gms.common.api.GoogleApiClient.Builder;
import com.google.android.gms.common.zzc;
import dalvik.system.DexClassLoader;
import java.io.File;
import java.io.FileNotFoundException;
import java.io.FileOutputStream;
import java.io.IOException;
import java.io.UnsupportedEncodingException;
import java.lang.reflect.InvocationTargetException;
import java.lang.reflect.Method;
import java.nio.ByteBuffer;
import java.util.ArrayList;
import java.util.Random;
import java.util.concurrent.TimeUnit;

public abstract class zzal
  extends zzak
{
  private static long startTime = 0L;
  private static Method zznH;
  private static Method zznI;
  private static Method zznJ;
  private static Method zznK;
  private static Method zznL;
  private static Method zznM;
  private static Method zznN;
  private static Method zznO;
  private static Method zznP;
  private static Method zznQ;
  private static Method zznR;
  private static Method zznS;
  private static Method zznT;
  private static String zznU;
  private static String zznV;
  private static String zznW;
  private static zzaq zznX;
  static boolean zznY = false;
  protected static zzb zznZ = null;
  protected static NanoAdshieldEvent.AdShieldEvent zzoa;
  protected static int zzob;
  private static Random zzoc;
  private static zzc zzod = zzc.zzoK();
  private static boolean zzoe;
  protected static boolean zzof = false;
  protected static boolean zzog = false;
  protected static boolean zzoh = false;
  protected static boolean zzoi = false;
  private static boolean zzoj = false;
  
  static
  {
    Random localRandom = new java/util/Random;
    localRandom.<init>();
    zzoc = localRandom;
  }
  
  protected zzal(Context paramContext, zzap paramzzap)
  {
    super(paramContext, paramzzap);
    NanoAdshieldEvent.AdShieldEvent localAdShieldEvent = new com/google/ads/afma/nano/NanoAdshieldEvent$AdShieldEvent;
    localAdShieldEvent.<init>();
    zzoa = localAdShieldEvent;
    localAdShieldEvent = zzoa;
    String str = paramContext.getPackageName();
    localAdShieldEvent.appId = str;
  }
  
  private void zzT()
  {
    boolean bool = zzoi;
    if (bool)
    {
      Object localObject = zznZ;
      if (localObject != null)
      {
        localObject = zznZ;
        GoogleApiClient localGoogleApiClient = zznG;
        long l = 100;
        TimeUnit localTimeUnit = TimeUnit.MILLISECONDS;
        ((zzb)localObject).zza(localGoogleApiClient, l, localTimeUnit);
        localObject = zznG;
        ((GoogleApiClient)localObject).disconnect();
      }
    }
  }
  
  static String zzU()
  {
    Object localObject = zznU;
    if (localObject == null)
    {
      localObject = new com/google/android/gms/internal/zzal$zza;
      ((zzal.zza)localObject).<init>();
      throw ((Throwable)localObject);
    }
    return zznU;
  }
  
  static Long zzV()
  {
    Object localObject = zznH;
    if (localObject == null)
    {
      localObject = new com/google/android/gms/internal/zzal$zza;
      ((zzal.zza)localObject).<init>();
      throw ((Throwable)localObject);
    }
    try
    {
      localObject = zznH;
      localzza = null;
      Object[] arrayOfObject = null;
      arrayOfObject = new Object[0];
      localObject = ((Method)localObject).invoke(null, arrayOfObject);
      return (Long)localObject;
    }
    catch (IllegalAccessException localIllegalAccessException)
    {
      localzza = new com/google/android/gms/internal/zzal$zza;
      localzza.<init>(localIllegalAccessException);
      throw localzza;
    }
    catch (InvocationTargetException localInvocationTargetException)
    {
      zzal.zza localzza = new com/google/android/gms/internal/zzal$zza;
      localzza.<init>(localInvocationTargetException);
      throw localzza;
    }
  }
  
  static String zzW()
  {
    Object localObject = zznJ;
    if (localObject == null)
    {
      localObject = new com/google/android/gms/internal/zzal$zza;
      ((zzal.zza)localObject).<init>();
      throw ((Throwable)localObject);
    }
    try
    {
      localObject = zznJ;
      localzza = null;
      Object[] arrayOfObject = null;
      arrayOfObject = new Object[0];
      localObject = ((Method)localObject).invoke(null, arrayOfObject);
      return (String)localObject;
    }
    catch (IllegalAccessException localIllegalAccessException)
    {
      localzza = new com/google/android/gms/internal/zzal$zza;
      localzza.<init>(localIllegalAccessException);
      throw localzza;
    }
    catch (InvocationTargetException localInvocationTargetException)
    {
      zzal.zza localzza = new com/google/android/gms/internal/zzal$zza;
      localzza.<init>(localInvocationTargetException);
      throw localzza;
    }
  }
  
  static Long zzX()
  {
    Object localObject = zznI;
    if (localObject == null)
    {
      localObject = new com/google/android/gms/internal/zzal$zza;
      ((zzal.zza)localObject).<init>();
      throw ((Throwable)localObject);
    }
    try
    {
      localObject = zznI;
      localzza = null;
      Object[] arrayOfObject = null;
      arrayOfObject = new Object[0];
      localObject = ((Method)localObject).invoke(null, arrayOfObject);
      return (Long)localObject;
    }
    catch (IllegalAccessException localIllegalAccessException)
    {
      localzza = new com/google/android/gms/internal/zzal$zza;
      localzza.<init>(localIllegalAccessException);
      throw localzza;
    }
    catch (InvocationTargetException localInvocationTargetException)
    {
      zzal.zza localzza = new com/google/android/gms/internal/zzal$zza;
      localzza.<init>(localInvocationTargetException);
      throw localzza;
    }
  }
  
  static String zza(Context paramContext, zzap paramzzap)
  {
    Object localObject1 = zznV;
    if (localObject1 != null) {
      localObject1 = zznV;
    }
    for (;;)
    {
      return (String)localObject1;
      localObject1 = zznK;
      if (localObject1 == null)
      {
        localObject1 = new com/google/android/gms/internal/zzal$zza;
        ((zzal.zza)localObject1).<init>();
        throw ((Throwable)localObject1);
      }
      try
      {
        localObject1 = zznK;
        bool = false;
        localzza = null;
        int i = 1;
        Object[] arrayOfObject = new Object[i];
        arrayOfObject[0] = paramContext;
        localObject1 = ((Method)localObject1).invoke(null, arrayOfObject);
        localObject1 = (ByteBuffer)localObject1;
        if (localObject1 == null)
        {
          localObject1 = new com/google/android/gms/internal/zzal$zza;
          ((zzal.zza)localObject1).<init>();
          throw ((Throwable)localObject1);
        }
      }
      catch (IllegalAccessException localIllegalAccessException)
      {
        localzza = new com/google/android/gms/internal/zzal$zza;
        localzza.<init>(localIllegalAccessException);
        throw localzza;
        Object localObject2 = localIllegalAccessException.array();
        boolean bool = true;
        localObject2 = paramzzap.zza((byte[])localObject2, bool);
        zznV = (String)localObject2;
        localObject2 = zznV;
      }
      catch (InvocationTargetException localInvocationTargetException)
      {
        zzal.zza localzza = new com/google/android/gms/internal/zzal$zza;
        localzza.<init>(localInvocationTargetException);
        throw localzza;
      }
    }
  }
  
  static ArrayList zza(MotionEvent paramMotionEvent, DisplayMetrics paramDisplayMetrics)
  {
    Object localObject = zznL;
    if ((localObject == null) || (paramMotionEvent == null))
    {
      localObject = new com/google/android/gms/internal/zzal$zza;
      ((zzal.zza)localObject).<init>();
      throw ((Throwable)localObject);
    }
    try
    {
      localObject = zznL;
      localzza = null;
      int i = 2;
      Object[] arrayOfObject = new Object[i];
      int j = 0;
      arrayOfObject[0] = paramMotionEvent;
      j = 1;
      arrayOfObject[j] = paramDisplayMetrics;
      localObject = ((Method)localObject).invoke(null, arrayOfObject);
      return (ArrayList)localObject;
    }
    catch (IllegalAccessException localIllegalAccessException)
    {
      localzza = new com/google/android/gms/internal/zzal$zza;
      localzza.<init>(localIllegalAccessException);
      throw localzza;
    }
    catch (InvocationTargetException localInvocationTargetException)
    {
      zzal.zza localzza = new com/google/android/gms/internal/zzal$zza;
      localzza.<init>(localInvocationTargetException);
      throw localzza;
    }
  }
  
  protected static void zza(int paramInt1, int paramInt2)
  {
    boolean bool = zzoi;
    if (bool)
    {
      bool = zzof;
      if (bool)
      {
        Object localObject1 = zznZ;
        if (localObject1 != null)
        {
          localObject1 = zznZ;
          Object localObject2 = zzsu.toByteArray(zzoa);
          localObject1 = ((zzb)localObject1).zzi((byte[])localObject2);
          ((zzb.zza)localObject1).zzbr(paramInt2);
          ((zzb.zza)localObject1).zzbq(paramInt1);
          localObject2 = zznG;
          ((zzb.zza)localObject1).zzd((GoogleApiClient)localObject2);
        }
      }
    }
  }
  
  protected static void zza(String paramString, Context paramContext, zzap paramzzap)
  {
    int i = 1;
    synchronized (zzal.class)
    {
      boolean bool1 = zznY;
      if (!bool1) {}
      for (;;)
      {
        try
        {
          localObject1 = new com/google/android/gms/internal/zzaq;
          localObject3 = null;
          ((zzaq)localObject1).<init>(paramzzap, null);
          zznX = (zzaq)localObject1;
          zznU = paramString;
          zzbt.initialize(paramContext);
          zzm(paramContext);
          localObject1 = zzV();
          long l = ((Long)localObject1).longValue();
          startTime = l;
          localObject1 = new java/util/Random;
          ((Random)localObject1).<init>();
          zzoc = (Random)localObject1;
        }
        catch (UnsupportedOperationException localUnsupportedOperationException)
        {
          Object localObject1;
          Object localObject3;
          int j;
          boolean bool2;
          int k;
          continue;
        }
        catch (zzal.zza localzza)
        {
          continue;
        }
        try
        {
          localObject1 = new com/google/android/gms/common/api/GoogleApiClient$Builder;
          ((GoogleApiClient.Builder)localObject1).<init>(paramContext);
          localObject3 = zzb.API;
          localObject1 = ((GoogleApiClient.Builder)localObject1).addApi((Api)localObject3);
          localObject1 = ((GoogleApiClient.Builder)localObject1).build();
          zznG = (GoogleApiClient)localObject1;
          localObject1 = zzc.zzoK();
          zzod = (zzc)localObject1;
          localObject1 = zzod;
          j = ((zzc)localObject1).isGooglePlayServicesAvailable(paramContext);
          if (j != 0) {
            continue;
          }
          j = i;
          zzoe = j;
          zzbt.initialize(paramContext);
          localObject1 = zzbt.zzwZ;
          localObject1 = ((zzbp)localObject1).get();
          localObject1 = (Boolean)localObject1;
          bool2 = ((Boolean)localObject1).booleanValue();
          zzof = bool2;
          localObject1 = new com/google/android/gms/clearcut/zzb;
          localObject3 = "ADSHIELD";
          ((zzb)localObject1).<init>(paramContext, (String)localObject3, null, null);
          zznZ = (zzb)localObject1;
        }
        catch (NoClassDefFoundError localNoClassDefFoundError)
        {
          continue;
        }
        localObject1 = zzod;
        k = ((zzc)localObject1).zzaj(paramContext);
        if (k <= 0) {
          continue;
        }
        k = i;
        zzoj = k;
        k = 1;
        zznY = k;
        return;
        k = 0;
        localObject1 = null;
      }
      k = 0;
      localObject1 = null;
    }
  }
  
  static String zzb(Context paramContext, zzap paramzzap)
  {
    Object localObject1 = zznW;
    if (localObject1 != null) {
      localObject1 = zznW;
    }
    for (;;)
    {
      return (String)localObject1;
      localObject1 = zznN;
      if (localObject1 == null)
      {
        localObject1 = new com/google/android/gms/internal/zzal$zza;
        ((zzal.zza)localObject1).<init>();
        throw ((Throwable)localObject1);
      }
      try
      {
        localObject1 = zznN;
        bool = false;
        localzza = null;
        int i = 1;
        Object[] arrayOfObject = new Object[i];
        arrayOfObject[0] = paramContext;
        localObject1 = ((Method)localObject1).invoke(null, arrayOfObject);
        localObject1 = (ByteBuffer)localObject1;
        if (localObject1 == null)
        {
          localObject1 = new com/google/android/gms/internal/zzal$zza;
          ((zzal.zza)localObject1).<init>();
          throw ((Throwable)localObject1);
        }
      }
      catch (IllegalAccessException localIllegalAccessException)
      {
        localzza = new com/google/android/gms/internal/zzal$zza;
        localzza.<init>(localIllegalAccessException);
        throw localzza;
        Object localObject2 = localIllegalAccessException.array();
        boolean bool = true;
        localObject2 = paramzzap.zza((byte[])localObject2, bool);
        zznW = (String)localObject2;
        localObject2 = zznW;
      }
      catch (InvocationTargetException localInvocationTargetException)
      {
        zzal.zza localzza = new com/google/android/gms/internal/zzal$zza;
        localzza.<init>(localInvocationTargetException);
        throw localzza;
      }
    }
  }
  
  private static String zzb(byte[] paramArrayOfByte, String paramString)
  {
    try
    {
      String str1 = new java/lang/String;
      localObject = zznX;
      localObject = ((zzaq)localObject).zzc(paramArrayOfByte, paramString);
      String str2 = "UTF-8";
      str1.<init>((byte[])localObject, str2);
      return str1;
    }
    catch (zzaq.zza localzza)
    {
      localObject = new com/google/android/gms/internal/zzal$zza;
      ((zzal.zza)localObject).<init>(localzza);
      throw ((Throwable)localObject);
    }
    catch (UnsupportedEncodingException localUnsupportedEncodingException)
    {
      Object localObject = new com/google/android/gms/internal/zzal$zza;
      ((zzal.zza)localObject).<init>(localUnsupportedEncodingException);
      throw ((Throwable)localObject);
    }
  }
  
  private void zze(Context paramContext)
  {
    boolean bool = zzoe;
    GoogleApiClient localGoogleApiClient;
    if (bool)
    {
      localGoogleApiClient = zznG;
      localGoogleApiClient.connect();
      bool = true;
    }
    for (zzoi = bool;; zzoi = false)
    {
      return;
      bool = false;
      localGoogleApiClient = null;
    }
  }
  
  static String zzf(Context paramContext)
  {
    Object localObject = zznM;
    if (localObject == null)
    {
      localObject = new com/google/android/gms/internal/zzal$zza;
      ((zzal.zza)localObject).<init>();
      throw ((Throwable)localObject);
    }
    try
    {
      localObject = zznM;
      localzza = null;
      int i = 1;
      Object[] arrayOfObject = new Object[i];
      arrayOfObject[0] = paramContext;
      localObject = ((Method)localObject).invoke(null, arrayOfObject);
      localObject = (String)localObject;
      if (localObject == null)
      {
        localObject = new com/google/android/gms/internal/zzal$zza;
        ((zzal.zza)localObject).<init>();
        throw ((Throwable)localObject);
      }
    }
    catch (IllegalAccessException localIllegalAccessException)
    {
      localzza = new com/google/android/gms/internal/zzal$zza;
      localzza.<init>(localIllegalAccessException);
      throw localzza;
    }
    catch (InvocationTargetException localInvocationTargetException)
    {
      zzal.zza localzza = new com/google/android/gms/internal/zzal$zza;
      localzza.<init>(localInvocationTargetException);
      throw localzza;
    }
    return localInvocationTargetException;
  }
  
  static String zzg(Context paramContext)
  {
    Object localObject = zznQ;
    if (localObject == null)
    {
      localObject = new com/google/android/gms/internal/zzal$zza;
      ((zzal.zza)localObject).<init>();
      throw ((Throwable)localObject);
    }
    try
    {
      localObject = zznQ;
      localzza = null;
      int i = 1;
      Object[] arrayOfObject = new Object[i];
      arrayOfObject[0] = paramContext;
      localObject = ((Method)localObject).invoke(null, arrayOfObject);
      return (String)localObject;
    }
    catch (IllegalAccessException localIllegalAccessException)
    {
      localzza = new com/google/android/gms/internal/zzal$zza;
      localzza.<init>(localIllegalAccessException);
      throw localzza;
    }
    catch (InvocationTargetException localInvocationTargetException)
    {
      zzal.zza localzza = new com/google/android/gms/internal/zzal$zza;
      localzza.<init>(localInvocationTargetException);
      throw localzza;
    }
  }
  
  static Long zzh(Context paramContext)
  {
    Object localObject = zznR;
    if (localObject == null)
    {
      localObject = new com/google/android/gms/internal/zzal$zza;
      ((zzal.zza)localObject).<init>();
      throw ((Throwable)localObject);
    }
    try
    {
      localObject = zznR;
      localzza = null;
      int i = 1;
      Object[] arrayOfObject = new Object[i];
      arrayOfObject[0] = paramContext;
      localObject = ((Method)localObject).invoke(null, arrayOfObject);
      return (Long)localObject;
    }
    catch (IllegalAccessException localIllegalAccessException)
    {
      localzza = new com/google/android/gms/internal/zzal$zza;
      localzza.<init>(localIllegalAccessException);
      throw localzza;
    }
    catch (InvocationTargetException localInvocationTargetException)
    {
      zzal.zza localzza = new com/google/android/gms/internal/zzal$zza;
      localzza.<init>(localInvocationTargetException);
      throw localzza;
    }
  }
  
  static ArrayList zzi(Context paramContext)
  {
    Object localObject = zznO;
    if (localObject == null)
    {
      localObject = new com/google/android/gms/internal/zzal$zza;
      ((zzal.zza)localObject).<init>();
      throw ((Throwable)localObject);
    }
    try
    {
      localObject = zznO;
      int i = 0;
      localzza = null;
      int j = 1;
      Object[] arrayOfObject = new Object[j];
      arrayOfObject[0] = paramContext;
      localObject = ((Method)localObject).invoke(null, arrayOfObject);
      localObject = (ArrayList)localObject;
      if (localObject != null)
      {
        i = ((ArrayList)localObject).size();
        j = 2;
        if (i == j) {}
      }
      else
      {
        localObject = new com/google/android/gms/internal/zzal$zza;
        ((zzal.zza)localObject).<init>();
        throw ((Throwable)localObject);
      }
    }
    catch (IllegalAccessException localIllegalAccessException)
    {
      localzza = new com/google/android/gms/internal/zzal$zza;
      localzza.<init>(localIllegalAccessException);
      throw localzza;
    }
    catch (InvocationTargetException localInvocationTargetException)
    {
      zzal.zza localzza = new com/google/android/gms/internal/zzal$zza;
      localzza.<init>(localInvocationTargetException);
      throw localzza;
    }
    return localInvocationTargetException;
  }
  
  static int[] zzj(Context paramContext)
  {
    Object localObject = zznP;
    if (localObject == null)
    {
      localObject = new com/google/android/gms/internal/zzal$zza;
      ((zzal.zza)localObject).<init>();
      throw ((Throwable)localObject);
    }
    try
    {
      localObject = zznP;
      localzza = null;
      int i = 1;
      Object[] arrayOfObject = new Object[i];
      arrayOfObject[0] = paramContext;
      localObject = ((Method)localObject).invoke(null, arrayOfObject);
      return (int[])localObject;
    }
    catch (IllegalAccessException localIllegalAccessException)
    {
      localzza = new com/google/android/gms/internal/zzal$zza;
      localzza.<init>(localIllegalAccessException);
      throw localzza;
    }
    catch (InvocationTargetException localInvocationTargetException)
    {
      zzal.zza localzza = new com/google/android/gms/internal/zzal$zza;
      localzza.<init>(localInvocationTargetException);
      throw localzza;
    }
  }
  
  static int zzk(Context paramContext)
  {
    Object localObject = zznS;
    if (localObject == null)
    {
      localObject = new com/google/android/gms/internal/zzal$zza;
      ((zzal.zza)localObject).<init>();
      throw ((Throwable)localObject);
    }
    try
    {
      localObject = zznS;
      localzza = null;
      int i = 1;
      Object[] arrayOfObject = new Object[i];
      arrayOfObject[0] = paramContext;
      localObject = ((Method)localObject).invoke(null, arrayOfObject);
      localObject = (Integer)localObject;
      return ((Integer)localObject).intValue();
    }
    catch (IllegalAccessException localIllegalAccessException)
    {
      localzza = new com/google/android/gms/internal/zzal$zza;
      localzza.<init>(localIllegalAccessException);
      throw localzza;
    }
    catch (InvocationTargetException localInvocationTargetException)
    {
      zzal.zza localzza = new com/google/android/gms/internal/zzal$zza;
      localzza.<init>(localInvocationTargetException);
      throw localzza;
    }
  }
  
  static int zzl(Context paramContext)
  {
    Object localObject = zznT;
    if (localObject == null)
    {
      localObject = new com/google/android/gms/internal/zzal$zza;
      ((zzal.zza)localObject).<init>();
      throw ((Throwable)localObject);
    }
    try
    {
      localObject = zznT;
      localzza = null;
      int i = 1;
      Object[] arrayOfObject = new Object[i];
      arrayOfObject[0] = paramContext;
      localObject = ((Method)localObject).invoke(null, arrayOfObject);
      localObject = (Integer)localObject;
      return ((Integer)localObject).intValue();
    }
    catch (IllegalAccessException localIllegalAccessException)
    {
      localzza = new com/google/android/gms/internal/zzal$zza;
      localzza.<init>(localIllegalAccessException);
      throw localzza;
    }
    catch (InvocationTargetException localInvocationTargetException)
    {
      zzal.zza localzza = new com/google/android/gms/internal/zzal$zza;
      localzza.<init>(localInvocationTargetException);
      throw localzza;
    }
  }
  
  private static void zzm(Context paramContext)
  {
    try
    {
      Object localObject1 = zznX;
      localObject4 = zzar.getKey();
      localObject5 = ((zzaq)localObject1).zzl((String)localObject4);
      localObject1 = zznX;
      localObject4 = zzar.zzac();
      localObject6 = ((zzaq)localObject1).zzc((byte[])localObject5, (String)localObject4);
      localObject1 = paramContext.getCacheDir();
      if (localObject1 == null)
      {
        localObject1 = "dex";
        localObject4 = null;
        localObject7 = paramContext;
        localObject1 = paramContext.getDir((String)localObject1, 0);
        if (localObject1 == null)
        {
          localObject1 = new com/google/android/gms/internal/zzal$zza;
          ((zzal.zza)localObject1).<init>();
          throw ((Throwable)localObject1);
        }
      }
    }
    catch (FileNotFoundException localFileNotFoundException)
    {
      Object localObject5;
      Object localObject6;
      Object localObject7;
      localObject4 = new com/google/android/gms/internal/zzal$zza;
      ((zzal.zza)localObject4).<init>(localFileNotFoundException);
      throw ((Throwable)localObject4);
      localObject4 = localFileNotFoundException;
      Object localObject2 = "ads";
      Object localObject8 = ".jar";
      localObject8 = File.createTempFile((String)localObject2, (String)localObject8, (File)localObject4);
      localObject2 = new java/io/FileOutputStream;
      ((FileOutputStream)localObject2).<init>((File)localObject8);
      int i = 0;
      Object localObject9 = null;
      int j = localObject6.length;
      ((FileOutputStream)localObject2).write((byte[])localObject6, 0, j);
      ((FileOutputStream)localObject2).close();
      try
      {
        localObject2 = new dalvik/system/DexClassLoader;
        localObject6 = ((File)localObject8).getAbsolutePath();
        localObject9 = ((File)localObject4).getAbsolutePath();
        j = 0;
        Object localObject10 = null;
        Object localObject11 = paramContext.getClassLoader();
        ((DexClassLoader)localObject2).<init>((String)localObject6, (String)localObject9, null, (ClassLoader)localObject11);
        localObject6 = zzar.zzal();
        localObject6 = zzb((byte[])localObject5, (String)localObject6);
        localObject6 = ((DexClassLoader)localObject2).loadClass((String)localObject6);
        localObject9 = zzar.zzaz();
        localObject9 = zzb((byte[])localObject5, (String)localObject9);
        localObject9 = ((DexClassLoader)localObject2).loadClass((String)localObject9);
        localObject10 = zzar.zzat();
        localObject10 = zzb((byte[])localObject5, (String)localObject10);
        localObject10 = ((DexClassLoader)localObject2).loadClass((String)localObject10);
        localObject11 = zzar.zzap();
        localObject11 = zzb((byte[])localObject5, (String)localObject11);
        localObject11 = ((DexClassLoader)localObject2).loadClass((String)localObject11);
        Object localObject12 = zzar.zzaB();
        localObject12 = zzb((byte[])localObject5, (String)localObject12);
        localObject12 = ((DexClassLoader)localObject2).loadClass((String)localObject12);
        Object localObject13 = zzar.zzan();
        localObject13 = zzb((byte[])localObject5, (String)localObject13);
        localObject13 = ((DexClassLoader)localObject2).loadClass((String)localObject13);
        Object localObject14 = zzar.zzax();
        localObject14 = zzb((byte[])localObject5, (String)localObject14);
        localObject14 = ((DexClassLoader)localObject2).loadClass((String)localObject14);
        Object localObject15 = zzar.zzav();
        localObject15 = zzb((byte[])localObject5, (String)localObject15);
        localObject15 = ((DexClassLoader)localObject2).loadClass((String)localObject15);
        Object localObject16 = zzar.zzaj();
        localObject16 = zzb((byte[])localObject5, (String)localObject16);
        localObject16 = ((DexClassLoader)localObject2).loadClass((String)localObject16);
        Object localObject17 = zzar.zzah();
        localObject17 = zzb((byte[])localObject5, (String)localObject17);
        localObject17 = ((DexClassLoader)localObject2).loadClass((String)localObject17);
        Object localObject18 = zzar.zzaf();
        localObject7 = localObject18;
        localObject18 = zzb((byte[])localObject5, (String)localObject18);
        localObject7 = localObject18;
        localObject18 = ((DexClassLoader)localObject2).loadClass((String)localObject18);
        Object localObject19 = zzar.zzar();
        localObject7 = localObject19;
        localObject19 = zzb((byte[])localObject5, (String)localObject19);
        localObject7 = localObject19;
        localObject19 = ((DexClassLoader)localObject2).loadClass((String)localObject19);
        Object localObject20 = zzar.zzad();
        localObject7 = localObject20;
        localObject20 = zzb((byte[])localObject5, (String)localObject20);
        localObject7 = localObject20;
        localObject2 = ((DexClassLoader)localObject2).loadClass((String)localObject20);
        localObject20 = zzar.zzam();
        localObject7 = localObject20;
        localObject20 = zzb((byte[])localObject5, (String)localObject20);
        Class[] arrayOfClass = null;
        localObject7 = null;
        arrayOfClass = new Class[0];
        localObject7 = localObject20;
        localObject6 = ((Class)localObject6).getMethod((String)localObject20, arrayOfClass);
        zznH = (Method)localObject6;
        localObject6 = zzar.zzaA();
        localObject6 = zzb((byte[])localObject5, (String)localObject6);
        localObject20 = null;
        localObject7 = null;
        localObject7 = new Class[0];
        localObject20 = localObject7;
        localObject6 = ((Class)localObject9).getMethod((String)localObject6, (Class[])localObject7);
        zznI = (Method)localObject6;
        localObject6 = zzar.zzau();
        localObject6 = zzb((byte[])localObject5, (String)localObject6);
        i = 0;
        localObject9 = null;
        localObject9 = new Class[0];
        localObject6 = ((Class)localObject10).getMethod((String)localObject6, (Class[])localObject9);
        zznJ = (Method)localObject6;
        localObject6 = zzar.zzaq();
        localObject6 = zzb((byte[])localObject5, (String)localObject6);
        i = 1;
        localObject9 = new Class[i];
        j = 0;
        localObject10 = null;
        localObject20 = Context.class;
        localObject9[0] = localObject20;
        localObject6 = ((Class)localObject11).getMethod((String)localObject6, (Class[])localObject9);
        zznK = (Method)localObject6;
        localObject6 = zzar.zzaC();
        localObject6 = zzb((byte[])localObject5, (String)localObject6);
        i = 2;
        localObject9 = new Class[i];
        j = 0;
        localObject10 = null;
        localObject11 = MotionEvent.class;
        localObject9[0] = localObject11;
        j = 1;
        localObject11 = DisplayMetrics.class;
        localObject9[j] = localObject11;
        localObject6 = ((Class)localObject12).getMethod((String)localObject6, (Class[])localObject9);
        zznL = (Method)localObject6;
        localObject6 = zzar.zzao();
        localObject6 = zzb((byte[])localObject5, (String)localObject6);
        i = 1;
        localObject9 = new Class[i];
        j = 0;
        localObject10 = null;
        localObject11 = Context.class;
        localObject9[0] = localObject11;
        localObject6 = ((Class)localObject13).getMethod((String)localObject6, (Class[])localObject9);
        zznM = (Method)localObject6;
        localObject6 = zzar.zzay();
        localObject6 = zzb((byte[])localObject5, (String)localObject6);
        i = 1;
        localObject9 = new Class[i];
        j = 0;
        localObject10 = null;
        localObject11 = Context.class;
        localObject9[0] = localObject11;
        localObject6 = ((Class)localObject14).getMethod((String)localObject6, (Class[])localObject9);
        zznN = (Method)localObject6;
        localObject6 = zzar.zzaw();
        localObject6 = zzb((byte[])localObject5, (String)localObject6);
        i = 1;
        localObject9 = new Class[i];
        j = 0;
        localObject10 = null;
        localObject11 = Context.class;
        localObject9[0] = localObject11;
        localObject6 = ((Class)localObject15).getMethod((String)localObject6, (Class[])localObject9);
        zznO = (Method)localObject6;
        localObject6 = zzar.zzak();
        localObject6 = zzb((byte[])localObject5, (String)localObject6);
        i = 1;
        localObject9 = new Class[i];
        j = 0;
        localObject10 = null;
        localObject11 = Context.class;
        localObject9[0] = localObject11;
        localObject6 = ((Class)localObject16).getMethod((String)localObject6, (Class[])localObject9);
        zznP = (Method)localObject6;
        localObject6 = zzar.zzai();
        localObject6 = zzb((byte[])localObject5, (String)localObject6);
        i = 1;
        localObject9 = new Class[i];
        j = 0;
        localObject10 = null;
        localObject11 = Context.class;
        localObject9[0] = localObject11;
        localObject6 = ((Class)localObject17).getMethod((String)localObject6, (Class[])localObject9);
        zznQ = (Method)localObject6;
        localObject6 = zzar.zzag();
        localObject6 = zzb((byte[])localObject5, (String)localObject6);
        i = 1;
        localObject9 = new Class[i];
        j = 0;
        localObject10 = null;
        localObject11 = Context.class;
        localObject9[0] = localObject11;
        localObject7 = localObject18;
        localObject6 = ((Class)localObject18).getMethod((String)localObject6, (Class[])localObject9);
        zznR = (Method)localObject6;
        localObject6 = zzar.zzas();
        localObject6 = zzb((byte[])localObject5, (String)localObject6);
        i = 1;
        localObject9 = new Class[i];
        j = 0;
        localObject10 = null;
        localObject11 = Context.class;
        localObject9[0] = localObject11;
        localObject7 = localObject19;
        localObject6 = ((Class)localObject19).getMethod((String)localObject6, (Class[])localObject9);
        zznS = (Method)localObject6;
        localObject6 = zzar.zzae();
        localObject5 = zzb((byte[])localObject5, (String)localObject6);
        int k = 1;
        localObject6 = new Class[k];
        i = 0;
        localObject9 = null;
        localObject10 = Context.class;
        localObject6[0] = localObject10;
        localObject2 = ((Class)localObject2).getMethod((String)localObject5, (Class[])localObject6);
        zznT = (Method)localObject2;
        return;
      }
      finally
      {
        localObject5 = ((File)localObject8).getName();
        ((File)localObject8).delete();
        localObject6 = new java/io/File;
        localObject8 = ".jar";
        localObject9 = ".dex";
        localObject5 = ((String)localObject5).replace((CharSequence)localObject8, (CharSequence)localObject9);
        ((File)localObject6).<init>((File)localObject4, (String)localObject5);
        ((File)localObject6).delete();
      }
    }
    catch (IOException localIOException)
    {
      localObject4 = new com/google/android/gms/internal/zzal$zza;
      ((zzal.zza)localObject4).<init>(localIOException);
      throw ((Throwable)localObject4);
    }
    catch (ClassNotFoundException localClassNotFoundException)
    {
      localObject4 = new com/google/android/gms/internal/zzal$zza;
      ((zzal.zza)localObject4).<init>(localClassNotFoundException);
      throw ((Throwable)localObject4);
    }
    catch (zzaq.zza localzza)
    {
      localObject4 = new com/google/android/gms/internal/zzal$zza;
      ((zzal.zza)localObject4).<init>(localzza);
      throw ((Throwable)localObject4);
    }
    catch (NoSuchMethodException localNoSuchMethodException)
    {
      localObject4 = new com/google/android/gms/internal/zzal$zza;
      ((zzal.zza)localObject4).<init>(localNoSuchMethodException);
      throw ((Throwable)localObject4);
    }
    catch (NullPointerException localNullPointerException)
    {
      Object localObject4 = new com/google/android/gms/internal/zzal$zza;
      ((zzal.zza)localObject4).<init>(localNullPointerException);
      throw ((Throwable)localObject4);
    }
  }
  
  protected boolean zzS()
  {
    return zzoj;
  }
  
  /* Error */
  protected com.google.ads.afma.nano.NanoAfmaSignals.AFMASignals zzc(Context paramContext)
  {
    // Byte code:
    //   0: new 487	com/google/ads/afma/nano/NanoAfmaSignals$AFMASignals
    //   3: astore_2
    //   4: aload_2
    //   5: invokespecial 488	com/google/ads/afma/nano/NanoAfmaSignals$AFMASignals:<init>	()V
    //   8: aload_0
    //   9: aload_1
    //   10: invokespecial 491	com/google/android/gms/internal/zzal:zze	(Landroid/content/Context;)V
    //   13: getstatic 58	com/google/android/gms/internal/zzal:zzoc	Ljava/util/Random;
    //   16: astore_3
    //   17: aload_3
    //   18: invokevirtual 494	java/util/Random:nextInt	()I
    //   21: istore 4
    //   23: iload 4
    //   25: putstatic 496	com/google/android/gms/internal/zzal:zzob	I
    //   28: iconst_0
    //   29: istore 4
    //   31: aconst_null
    //   32: astore_3
    //   33: getstatic 496	com/google/android/gms/internal/zzal:zzob	I
    //   36: istore 5
    //   38: iconst_0
    //   39: iload 5
    //   41: invokestatic 499	com/google/android/gms/internal/zzal:zza	(II)V
    //   44: invokestatic 502	com/google/android/gms/internal/zzal:zzW	()Ljava/lang/String;
    //   47: astore_3
    //   48: aload_2
    //   49: aload_3
    //   50: putfield 505	com/google/ads/afma/nano/NanoAfmaSignals$AFMASignals:osVersion	Ljava/lang/String;
    //   53: iconst_1
    //   54: istore 4
    //   56: getstatic 496	com/google/android/gms/internal/zzal:zzob	I
    //   59: istore 5
    //   61: iload 4
    //   63: iload 5
    //   65: invokestatic 499	com/google/android/gms/internal/zzal:zza	(II)V
    //   68: invokestatic 508	com/google/android/gms/internal/zzal:zzU	()Ljava/lang/String;
    //   71: astore_3
    //   72: aload_2
    //   73: aload_3
    //   74: putfield 511	com/google/ads/afma/nano/NanoAfmaSignals$AFMASignals:afmaVersion	Ljava/lang/String;
    //   77: iconst_2
    //   78: istore 4
    //   80: getstatic 496	com/google/android/gms/internal/zzal:zzob	I
    //   83: istore 5
    //   85: iload 4
    //   87: iload 5
    //   89: invokestatic 499	com/google/android/gms/internal/zzal:zza	(II)V
    //   92: invokestatic 210	com/google/android/gms/internal/zzal:zzV	()Ljava/lang/Long;
    //   95: astore_3
    //   96: aload_3
    //   97: invokevirtual 214	java/lang/Long:longValue	()J
    //   100: lstore 6
    //   102: lload 6
    //   104: invokestatic 515	java/lang/Long:valueOf	(J)Ljava/lang/Long;
    //   107: astore_3
    //   108: aload_2
    //   109: aload_3
    //   110: putfield 519	com/google/ads/afma/nano/NanoAfmaSignals$AFMASignals:evtTime	Ljava/lang/Long;
    //   113: getstatic 46	com/google/android/gms/internal/zzal:startTime	J
    //   116: lstore 8
    //   118: lconst_0
    //   119: lstore 10
    //   121: lload 8
    //   123: lload 10
    //   125: lcmp
    //   126: istore 4
    //   128: iload 4
    //   130: ifeq +42 -> 172
    //   133: getstatic 46	com/google/android/gms/internal/zzal:startTime	J
    //   136: lstore 8
    //   138: lload 6
    //   140: lload 8
    //   142: lsub
    //   143: lstore 6
    //   145: lload 6
    //   147: invokestatic 515	java/lang/Long:valueOf	(J)Ljava/lang/Long;
    //   150: astore_3
    //   151: aload_2
    //   152: aload_3
    //   153: putfield 522	com/google/ads/afma/nano/NanoAfmaSignals$AFMASignals:uptSignal	Ljava/lang/Long;
    //   156: getstatic 46	com/google/android/gms/internal/zzal:startTime	J
    //   159: lstore 6
    //   161: lload 6
    //   163: invokestatic 515	java/lang/Long:valueOf	(J)Ljava/lang/Long;
    //   166: astore_3
    //   167: aload_2
    //   168: aload_3
    //   169: putfield 525	com/google/ads/afma/nano/NanoAfmaSignals$AFMASignals:usgSignal	Ljava/lang/Long;
    //   172: bipush 25
    //   174: istore 4
    //   176: getstatic 496	com/google/android/gms/internal/zzal:zzob	I
    //   179: istore 5
    //   181: iload 4
    //   183: iload 5
    //   185: invokestatic 499	com/google/android/gms/internal/zzal:zza	(II)V
    //   188: aload_1
    //   189: invokestatic 529	com/google/android/gms/internal/zzal:zzi	(Landroid/content/Context;)Ljava/util/ArrayList;
    //   192: astore 12
    //   194: iconst_0
    //   195: istore 4
    //   197: aconst_null
    //   198: astore_3
    //   199: aload 12
    //   201: iconst_0
    //   202: invokevirtual 532	java/util/ArrayList:get	(I)Ljava/lang/Object;
    //   205: astore_3
    //   206: aload_3
    //   207: checkcast 133	java/lang/Long
    //   210: astore_3
    //   211: aload_3
    //   212: invokevirtual 214	java/lang/Long:longValue	()J
    //   215: lstore 8
    //   217: lload 8
    //   219: invokestatic 515	java/lang/Long:valueOf	(J)Ljava/lang/Long;
    //   222: astore_3
    //   223: aload_2
    //   224: aload_3
    //   225: putfield 535	com/google/ads/afma/nano/NanoAfmaSignals$AFMASignals:uwSignal	Ljava/lang/Long;
    //   228: iconst_1
    //   229: istore 4
    //   231: aload 12
    //   233: iload 4
    //   235: invokevirtual 532	java/util/ArrayList:get	(I)Ljava/lang/Object;
    //   238: astore_3
    //   239: aload_3
    //   240: checkcast 133	java/lang/Long
    //   243: astore_3
    //   244: aload_3
    //   245: invokevirtual 214	java/lang/Long:longValue	()J
    //   248: lstore 6
    //   250: lload 6
    //   252: invokestatic 515	java/lang/Long:valueOf	(J)Ljava/lang/Long;
    //   255: astore_3
    //   256: aload_2
    //   257: aload_3
    //   258: putfield 538	com/google/ads/afma/nano/NanoAfmaSignals$AFMASignals:uhSignal	Ljava/lang/Long;
    //   261: bipush 31
    //   263: istore 4
    //   265: getstatic 496	com/google/android/gms/internal/zzal:zzob	I
    //   268: istore 5
    //   270: iload 4
    //   272: iload 5
    //   274: invokestatic 499	com/google/android/gms/internal/zzal:zza	(II)V
    //   277: invokestatic 542	com/google/android/gms/internal/zzal:zzX	()Ljava/lang/Long;
    //   280: astore_3
    //   281: aload_2
    //   282: aload_3
    //   283: putfield 545	com/google/ads/afma/nano/NanoAfmaSignals$AFMASignals:utzSignal	Ljava/lang/Long;
    //   286: bipush 33
    //   288: istore 4
    //   290: getstatic 496	com/google/android/gms/internal/zzal:zzob	I
    //   293: istore 5
    //   295: iload 4
    //   297: iload 5
    //   299: invokestatic 499	com/google/android/gms/internal/zzal:zza	(II)V
    //   302: getstatic 70	com/google/android/gms/internal/zzal:zzog	Z
    //   305: istore 4
    //   307: iload 4
    //   309: ifeq +252 -> 561
    //   312: getstatic 72	com/google/android/gms/internal/zzal:zzoh	Z
    //   315: istore 4
    //   317: iload 4
    //   319: ifeq +242 -> 561
    //   322: aload_0
    //   323: getfield 550	com/google/android/gms/internal/zzal:zznF	Lcom/google/android/gms/internal/zzap;
    //   326: astore_3
    //   327: aload_1
    //   328: aload_3
    //   329: invokestatic 553	com/google/android/gms/internal/zzal:zzb	(Landroid/content/Context;Lcom/google/android/gms/internal/zzap;)Ljava/lang/String;
    //   332: astore_3
    //   333: aload_2
    //   334: aload_3
    //   335: putfield 556	com/google/ads/afma/nano/NanoAfmaSignals$AFMASignals:cerSignal	Ljava/lang/String;
    //   338: bipush 29
    //   340: istore 4
    //   342: getstatic 496	com/google/android/gms/internal/zzal:zzob	I
    //   345: istore 5
    //   347: iload 4
    //   349: iload 5
    //   351: invokestatic 499	com/google/android/gms/internal/zzal:zza	(II)V
    //   354: aload_1
    //   355: invokestatic 561	com/google/android/gms/internal/zzal:zzj	(Landroid/content/Context;)[I
    //   358: astore_3
    //   359: iconst_0
    //   360: istore 5
    //   362: aconst_null
    //   363: astore 12
    //   365: aload_3
    //   366: iconst_0
    //   367: iaload
    //   368: istore 5
    //   370: iload 5
    //   372: i2l
    //   373: lstore 6
    //   375: lload 6
    //   377: invokestatic 515	java/lang/Long:valueOf	(J)Ljava/lang/Long;
    //   380: astore 12
    //   382: aload_2
    //   383: aload 12
    //   385: putfield 564	com/google/ads/afma/nano/NanoAfmaSignals$AFMASignals:btsSignal	Ljava/lang/Long;
    //   388: iconst_1
    //   389: istore 5
    //   391: aload_3
    //   392: iload 5
    //   394: iaload
    //   395: istore 4
    //   397: iload 4
    //   399: i2l
    //   400: lstore 6
    //   402: lload 6
    //   404: invokestatic 515	java/lang/Long:valueOf	(J)Ljava/lang/Long;
    //   407: astore_3
    //   408: aload_2
    //   409: aload_3
    //   410: putfield 567	com/google/ads/afma/nano/NanoAfmaSignals$AFMASignals:btlSignal	Ljava/lang/Long;
    //   413: iconst_5
    //   414: istore 4
    //   416: getstatic 496	com/google/android/gms/internal/zzal:zzob	I
    //   419: istore 5
    //   421: iload 4
    //   423: iload 5
    //   425: invokestatic 499	com/google/android/gms/internal/zzal:zza	(II)V
    //   428: aload_1
    //   429: invokestatic 571	com/google/android/gms/internal/zzal:zzk	(Landroid/content/Context;)I
    //   432: istore 4
    //   434: iload 4
    //   436: i2l
    //   437: lstore 6
    //   439: lload 6
    //   441: invokestatic 515	java/lang/Long:valueOf	(J)Ljava/lang/Long;
    //   444: astore_3
    //   445: aload_2
    //   446: aload_3
    //   447: putfield 574	com/google/ads/afma/nano/NanoAfmaSignals$AFMASignals:ornSignal	Ljava/lang/Long;
    //   450: bipush 12
    //   452: istore 4
    //   454: getstatic 496	com/google/android/gms/internal/zzal:zzob	I
    //   457: istore 5
    //   459: iload 4
    //   461: iload 5
    //   463: invokestatic 499	com/google/android/gms/internal/zzal:zza	(II)V
    //   466: aload_1
    //   467: invokestatic 577	com/google/android/gms/internal/zzal:zzl	(Landroid/content/Context;)I
    //   470: istore 4
    //   472: iload 4
    //   474: i2l
    //   475: lstore 6
    //   477: lload 6
    //   479: invokestatic 515	java/lang/Long:valueOf	(J)Ljava/lang/Long;
    //   482: astore_3
    //   483: aload_2
    //   484: aload_3
    //   485: putfield 580	com/google/ads/afma/nano/NanoAfmaSignals$AFMASignals:atvSignal	Ljava/lang/Long;
    //   488: iconst_3
    //   489: istore 4
    //   491: getstatic 496	com/google/android/gms/internal/zzal:zzob	I
    //   494: istore 5
    //   496: iload 4
    //   498: iload 5
    //   500: invokestatic 499	com/google/android/gms/internal/zzal:zza	(II)V
    //   503: aload_1
    //   504: invokestatic 585	com/google/android/gms/internal/zzal:zzg	(Landroid/content/Context;)Ljava/lang/String;
    //   507: astore_3
    //   508: aload_2
    //   509: aload_3
    //   510: putfield 588	com/google/ads/afma/nano/NanoAfmaSignals$AFMASignals:vnmSignal	Ljava/lang/String;
    //   513: bipush 34
    //   515: istore 4
    //   517: getstatic 496	com/google/android/gms/internal/zzal:zzob	I
    //   520: istore 5
    //   522: iload 4
    //   524: iload 5
    //   526: invokestatic 499	com/google/android/gms/internal/zzal:zza	(II)V
    //   529: aload_1
    //   530: invokestatic 593	com/google/android/gms/internal/zzal:zzh	(Landroid/content/Context;)Ljava/lang/Long;
    //   533: astore_3
    //   534: aload_2
    //   535: aload_3
    //   536: putfield 596	com/google/ads/afma/nano/NanoAfmaSignals$AFMASignals:vcdSignal	Ljava/lang/Long;
    //   539: bipush 35
    //   541: istore 4
    //   543: getstatic 496	com/google/android/gms/internal/zzal:zzob	I
    //   546: istore 5
    //   548: iload 4
    //   550: iload 5
    //   552: invokestatic 499	com/google/android/gms/internal/zzal:zza	(II)V
    //   555: aload_0
    //   556: invokespecial 600	com/google/android/gms/internal/zzal:zzT	()V
    //   559: aload_2
    //   560: areturn
    //   561: aload_0
    //   562: getfield 550	com/google/android/gms/internal/zzal:zznF	Lcom/google/android/gms/internal/zzap;
    //   565: astore_3
    //   566: aload_1
    //   567: aload_3
    //   568: invokestatic 602	com/google/android/gms/internal/zzal:zza	(Landroid/content/Context;Lcom/google/android/gms/internal/zzap;)Ljava/lang/String;
    //   571: astore_3
    //   572: aload_2
    //   573: aload_3
    //   574: putfield 605	com/google/ads/afma/nano/NanoAfmaSignals$AFMASignals:intSignal	Ljava/lang/String;
    //   577: bipush 27
    //   579: istore 4
    //   581: getstatic 496	com/google/android/gms/internal/zzal:zzob	I
    //   584: istore 5
    //   586: iload 4
    //   588: iload 5
    //   590: invokestatic 499	com/google/android/gms/internal/zzal:zza	(II)V
    //   593: goto -271 -> 322
    //   596: astore_3
    //   597: goto -275 -> 322
    //   600: astore_3
    //   601: goto -42 -> 559
    //   604: astore_3
    //   605: goto -50 -> 555
    //   608: astore_3
    //   609: goto -80 -> 529
    //   612: astore_3
    //   613: goto -110 -> 503
    //   616: astore_3
    //   617: goto -151 -> 466
    //   620: astore_3
    //   621: goto -193 -> 428
    //   624: astore_3
    //   625: goto -271 -> 354
    //   628: astore_3
    //   629: goto -327 -> 302
    //   632: astore_3
    //   633: goto -356 -> 277
    //   636: astore_3
    //   637: goto -449 -> 188
    //   640: astore_3
    //   641: goto -549 -> 92
    //   644: astore_3
    //   645: goto -577 -> 68
    // Local variable table:
    //   start	length	slot	name	signature
    //   0	648	0	this	zzal
    //   0	648	1	paramContext	Context
    //   3	570	2	localAFMASignals	com.google.ads.afma.nano.NanoAfmaSignals.AFMASignals
    //   16	558	3	localObject1	Object
    //   596	1	3	localzza1	zzal.zza
    //   600	1	3	localIOException	IOException
    //   604	1	3	localzza2	zzal.zza
    //   608	1	3	localzza3	zzal.zza
    //   612	1	3	localzza4	zzal.zza
    //   616	1	3	localzza5	zzal.zza
    //   620	1	3	localzza6	zzal.zza
    //   624	1	3	localzza7	zzal.zza
    //   628	1	3	localzza8	zzal.zza
    //   632	1	3	localzza9	zzal.zza
    //   636	1	3	localzza10	zzal.zza
    //   640	1	3	localzza11	zzal.zza
    //   644	1	3	localzza12	zzal.zza
    //   21	65	4	i	int
    //   126	3	4	bool1	boolean
    //   174	122	4	j	int
    //   305	13	4	bool2	boolean
    //   340	247	4	k	int
    //   36	553	5	m	int
    //   100	378	6	l1	long
    //   116	102	8	l2	long
    //   119	5	10	l3	long
    //   192	192	12	localObject2	Object
    // Exception table:
    //   from	to	target	type
    //   302	305	596	com/google/android/gms/internal/zzal$zza
    //   312	315	596	com/google/android/gms/internal/zzal$zza
    //   561	565	596	com/google/android/gms/internal/zzal$zza
    //   567	571	596	com/google/android/gms/internal/zzal$zza
    //   573	577	596	com/google/android/gms/internal/zzal$zza
    //   581	584	596	com/google/android/gms/internal/zzal$zza
    //   588	593	596	com/google/android/gms/internal/zzal$zza
    //   9	13	600	java/io/IOException
    //   13	16	600	java/io/IOException
    //   17	21	600	java/io/IOException
    //   23	28	600	java/io/IOException
    //   33	36	600	java/io/IOException
    //   39	44	600	java/io/IOException
    //   44	47	600	java/io/IOException
    //   49	53	600	java/io/IOException
    //   56	59	600	java/io/IOException
    //   63	68	600	java/io/IOException
    //   68	71	600	java/io/IOException
    //   73	77	600	java/io/IOException
    //   80	83	600	java/io/IOException
    //   87	92	600	java/io/IOException
    //   92	95	600	java/io/IOException
    //   96	100	600	java/io/IOException
    //   102	107	600	java/io/IOException
    //   109	113	600	java/io/IOException
    //   113	116	600	java/io/IOException
    //   133	136	600	java/io/IOException
    //   145	150	600	java/io/IOException
    //   152	156	600	java/io/IOException
    //   156	159	600	java/io/IOException
    //   161	166	600	java/io/IOException
    //   168	172	600	java/io/IOException
    //   176	179	600	java/io/IOException
    //   183	188	600	java/io/IOException
    //   188	192	600	java/io/IOException
    //   201	205	600	java/io/IOException
    //   206	210	600	java/io/IOException
    //   211	215	600	java/io/IOException
    //   217	222	600	java/io/IOException
    //   224	228	600	java/io/IOException
    //   233	238	600	java/io/IOException
    //   239	243	600	java/io/IOException
    //   244	248	600	java/io/IOException
    //   250	255	600	java/io/IOException
    //   257	261	600	java/io/IOException
    //   265	268	600	java/io/IOException
    //   272	277	600	java/io/IOException
    //   277	280	600	java/io/IOException
    //   282	286	600	java/io/IOException
    //   290	293	600	java/io/IOException
    //   297	302	600	java/io/IOException
    //   302	305	600	java/io/IOException
    //   312	315	600	java/io/IOException
    //   322	326	600	java/io/IOException
    //   328	332	600	java/io/IOException
    //   334	338	600	java/io/IOException
    //   342	345	600	java/io/IOException
    //   349	354	600	java/io/IOException
    //   354	358	600	java/io/IOException
    //   366	368	600	java/io/IOException
    //   375	380	600	java/io/IOException
    //   383	388	600	java/io/IOException
    //   392	395	600	java/io/IOException
    //   402	407	600	java/io/IOException
    //   409	413	600	java/io/IOException
    //   416	419	600	java/io/IOException
    //   423	428	600	java/io/IOException
    //   428	432	600	java/io/IOException
    //   439	444	600	java/io/IOException
    //   446	450	600	java/io/IOException
    //   454	457	600	java/io/IOException
    //   461	466	600	java/io/IOException
    //   466	470	600	java/io/IOException
    //   477	482	600	java/io/IOException
    //   484	488	600	java/io/IOException
    //   491	494	600	java/io/IOException
    //   498	503	600	java/io/IOException
    //   503	507	600	java/io/IOException
    //   509	513	600	java/io/IOException
    //   517	520	600	java/io/IOException
    //   524	529	600	java/io/IOException
    //   529	533	600	java/io/IOException
    //   535	539	600	java/io/IOException
    //   543	546	600	java/io/IOException
    //   550	555	600	java/io/IOException
    //   555	559	600	java/io/IOException
    //   561	565	600	java/io/IOException
    //   567	571	600	java/io/IOException
    //   573	577	600	java/io/IOException
    //   581	584	600	java/io/IOException
    //   588	593	600	java/io/IOException
    //   529	533	604	com/google/android/gms/internal/zzal$zza
    //   535	539	604	com/google/android/gms/internal/zzal$zza
    //   543	546	604	com/google/android/gms/internal/zzal$zza
    //   550	555	604	com/google/android/gms/internal/zzal$zza
    //   503	507	608	com/google/android/gms/internal/zzal$zza
    //   509	513	608	com/google/android/gms/internal/zzal$zza
    //   517	520	608	com/google/android/gms/internal/zzal$zza
    //   524	529	608	com/google/android/gms/internal/zzal$zza
    //   466	470	612	com/google/android/gms/internal/zzal$zza
    //   477	482	612	com/google/android/gms/internal/zzal$zza
    //   484	488	612	com/google/android/gms/internal/zzal$zza
    //   491	494	612	com/google/android/gms/internal/zzal$zza
    //   498	503	612	com/google/android/gms/internal/zzal$zza
    //   428	432	616	com/google/android/gms/internal/zzal$zza
    //   439	444	616	com/google/android/gms/internal/zzal$zza
    //   446	450	616	com/google/android/gms/internal/zzal$zza
    //   454	457	616	com/google/android/gms/internal/zzal$zza
    //   461	466	616	com/google/android/gms/internal/zzal$zza
    //   354	358	620	com/google/android/gms/internal/zzal$zza
    //   366	368	620	com/google/android/gms/internal/zzal$zza
    //   375	380	620	com/google/android/gms/internal/zzal$zza
    //   383	388	620	com/google/android/gms/internal/zzal$zza
    //   392	395	620	com/google/android/gms/internal/zzal$zza
    //   402	407	620	com/google/android/gms/internal/zzal$zza
    //   409	413	620	com/google/android/gms/internal/zzal$zza
    //   416	419	620	com/google/android/gms/internal/zzal$zza
    //   423	428	620	com/google/android/gms/internal/zzal$zza
    //   322	326	624	com/google/android/gms/internal/zzal$zza
    //   328	332	624	com/google/android/gms/internal/zzal$zza
    //   334	338	624	com/google/android/gms/internal/zzal$zza
    //   342	345	624	com/google/android/gms/internal/zzal$zza
    //   349	354	624	com/google/android/gms/internal/zzal$zza
    //   277	280	628	com/google/android/gms/internal/zzal$zza
    //   282	286	628	com/google/android/gms/internal/zzal$zza
    //   290	293	628	com/google/android/gms/internal/zzal$zza
    //   297	302	628	com/google/android/gms/internal/zzal$zza
    //   188	192	632	com/google/android/gms/internal/zzal$zza
    //   201	205	632	com/google/android/gms/internal/zzal$zza
    //   206	210	632	com/google/android/gms/internal/zzal$zza
    //   211	215	632	com/google/android/gms/internal/zzal$zza
    //   217	222	632	com/google/android/gms/internal/zzal$zza
    //   224	228	632	com/google/android/gms/internal/zzal$zza
    //   233	238	632	com/google/android/gms/internal/zzal$zza
    //   239	243	632	com/google/android/gms/internal/zzal$zza
    //   244	248	632	com/google/android/gms/internal/zzal$zza
    //   250	255	632	com/google/android/gms/internal/zzal$zza
    //   257	261	632	com/google/android/gms/internal/zzal$zza
    //   265	268	632	com/google/android/gms/internal/zzal$zza
    //   272	277	632	com/google/android/gms/internal/zzal$zza
    //   92	95	636	com/google/android/gms/internal/zzal$zza
    //   96	100	636	com/google/android/gms/internal/zzal$zza
    //   102	107	636	com/google/android/gms/internal/zzal$zza
    //   109	113	636	com/google/android/gms/internal/zzal$zza
    //   113	116	636	com/google/android/gms/internal/zzal$zza
    //   133	136	636	com/google/android/gms/internal/zzal$zza
    //   145	150	636	com/google/android/gms/internal/zzal$zza
    //   152	156	636	com/google/android/gms/internal/zzal$zza
    //   156	159	636	com/google/android/gms/internal/zzal$zza
    //   161	166	636	com/google/android/gms/internal/zzal$zza
    //   168	172	636	com/google/android/gms/internal/zzal$zza
    //   176	179	636	com/google/android/gms/internal/zzal$zza
    //   183	188	636	com/google/android/gms/internal/zzal$zza
    //   68	71	640	com/google/android/gms/internal/zzal$zza
    //   73	77	640	com/google/android/gms/internal/zzal$zza
    //   80	83	640	com/google/android/gms/internal/zzal$zza
    //   87	92	640	com/google/android/gms/internal/zzal$zza
    //   44	47	644	com/google/android/gms/internal/zzal$zza
    //   49	53	644	com/google/android/gms/internal/zzal$zza
    //   56	59	644	com/google/android/gms/internal/zzal$zza
    //   63	68	644	com/google/android/gms/internal/zzal$zza
  }
  
  /* Error */
  protected com.google.ads.afma.nano.NanoAfmaSignals.AFMASignals zzd(Context paramContext)
  {
    // Byte code:
    //   0: iconst_0
    //   1: istore_2
    //   2: lconst_0
    //   3: lstore_3
    //   4: new 487	com/google/ads/afma/nano/NanoAfmaSignals$AFMASignals
    //   7: astore 5
    //   9: aload 5
    //   11: invokespecial 488	com/google/ads/afma/nano/NanoAfmaSignals$AFMASignals:<init>	()V
    //   14: aload_0
    //   15: aload_1
    //   16: invokespecial 491	com/google/android/gms/internal/zzal:zze	(Landroid/content/Context;)V
    //   19: getstatic 58	com/google/android/gms/internal/zzal:zzoc	Ljava/util/Random;
    //   22: astore 6
    //   24: aload 6
    //   26: invokevirtual 494	java/util/Random:nextInt	()I
    //   29: istore 7
    //   31: iload 7
    //   33: putstatic 496	com/google/android/gms/internal/zzal:zzob	I
    //   36: invokestatic 508	com/google/android/gms/internal/zzal:zzU	()Ljava/lang/String;
    //   39: astore 6
    //   41: aload 5
    //   43: aload 6
    //   45: putfield 511	com/google/ads/afma/nano/NanoAfmaSignals$AFMASignals:afmaVersion	Ljava/lang/String;
    //   48: invokestatic 502	com/google/android/gms/internal/zzal:zzW	()Ljava/lang/String;
    //   51: astore 6
    //   53: aload 5
    //   55: aload 6
    //   57: putfield 505	com/google/ads/afma/nano/NanoAfmaSignals$AFMASignals:osVersion	Ljava/lang/String;
    //   60: invokestatic 210	com/google/android/gms/internal/zzal:zzV	()Ljava/lang/Long;
    //   63: astore 6
    //   65: aload 5
    //   67: aload 6
    //   69: putfield 519	com/google/ads/afma/nano/NanoAfmaSignals$AFMASignals:evtTime	Ljava/lang/Long;
    //   72: iconst_0
    //   73: istore 7
    //   75: aconst_null
    //   76: astore 6
    //   78: getstatic 496	com/google/android/gms/internal/zzal:zzob	I
    //   81: istore 8
    //   83: iconst_0
    //   84: iload 8
    //   86: invokestatic 499	com/google/android/gms/internal/zzal:zza	(II)V
    //   89: aload_0
    //   90: getfield 610	com/google/android/gms/internal/zzal:zznx	Landroid/view/MotionEvent;
    //   93: astore 6
    //   95: aload_0
    //   96: getfield 614	com/google/android/gms/internal/zzal:zznE	Landroid/util/DisplayMetrics;
    //   99: astore 9
    //   101: aload 6
    //   103: aload 9
    //   105: invokestatic 617	com/google/android/gms/internal/zzal:zza	(Landroid/view/MotionEvent;Landroid/util/DisplayMetrics;)Ljava/util/ArrayList;
    //   108: astore 9
    //   110: iconst_0
    //   111: istore 7
    //   113: aconst_null
    //   114: astore 6
    //   116: aload 9
    //   118: iconst_0
    //   119: invokevirtual 532	java/util/ArrayList:get	(I)Ljava/lang/Object;
    //   122: astore 6
    //   124: aload 6
    //   126: checkcast 133	java/lang/Long
    //   129: astore 6
    //   131: aload 5
    //   133: aload 6
    //   135: putfield 620	com/google/ads/afma/nano/NanoAfmaSignals$AFMASignals:tcxSignal	Ljava/lang/Long;
    //   138: iconst_1
    //   139: istore 7
    //   141: aload 9
    //   143: iload 7
    //   145: invokevirtual 532	java/util/ArrayList:get	(I)Ljava/lang/Object;
    //   148: astore 6
    //   150: aload 6
    //   152: checkcast 133	java/lang/Long
    //   155: astore 6
    //   157: aload 5
    //   159: aload 6
    //   161: putfield 623	com/google/ads/afma/nano/NanoAfmaSignals$AFMASignals:tcySignal	Ljava/lang/Long;
    //   164: iconst_2
    //   165: istore 7
    //   167: aload 9
    //   169: iload 7
    //   171: invokevirtual 532	java/util/ArrayList:get	(I)Ljava/lang/Object;
    //   174: astore 6
    //   176: aload 6
    //   178: checkcast 133	java/lang/Long
    //   181: astore 6
    //   183: aload 6
    //   185: invokevirtual 214	java/lang/Long:longValue	()J
    //   188: lstore 10
    //   190: lload 10
    //   192: lload_3
    //   193: lcmp
    //   194: istore 7
    //   196: iload 7
    //   198: iflt +29 -> 227
    //   201: iconst_2
    //   202: istore 7
    //   204: aload 9
    //   206: iload 7
    //   208: invokevirtual 532	java/util/ArrayList:get	(I)Ljava/lang/Object;
    //   211: astore 6
    //   213: aload 6
    //   215: checkcast 133	java/lang/Long
    //   218: astore 6
    //   220: aload 5
    //   222: aload 6
    //   224: putfield 626	com/google/ads/afma/nano/NanoAfmaSignals$AFMASignals:tctSignal	Ljava/lang/Long;
    //   227: iconst_3
    //   228: istore 7
    //   230: aload 9
    //   232: iload 7
    //   234: invokevirtual 532	java/util/ArrayList:get	(I)Ljava/lang/Object;
    //   237: astore 6
    //   239: aload 6
    //   241: checkcast 133	java/lang/Long
    //   244: astore 6
    //   246: aload 5
    //   248: aload 6
    //   250: putfield 629	com/google/ads/afma/nano/NanoAfmaSignals$AFMASignals:tcpSignal	Ljava/lang/Long;
    //   253: iconst_4
    //   254: istore 7
    //   256: aload 9
    //   258: iload 7
    //   260: invokevirtual 532	java/util/ArrayList:get	(I)Ljava/lang/Object;
    //   263: astore 6
    //   265: aload 6
    //   267: checkcast 133	java/lang/Long
    //   270: astore 6
    //   272: aload 5
    //   274: aload 6
    //   276: putfield 633	com/google/ads/afma/nano/NanoAfmaSignals$AFMASignals:tcdSignal	Ljava/lang/Long;
    //   279: bipush 14
    //   281: istore 7
    //   283: getstatic 496	com/google/android/gms/internal/zzal:zzob	I
    //   286: istore 8
    //   288: iload 7
    //   290: iload 8
    //   292: invokestatic 499	com/google/android/gms/internal/zzal:zza	(II)V
    //   295: aload_0
    //   296: getfield 637	com/google/android/gms/internal/zzal:zznz	J
    //   299: lstore 10
    //   301: lload 10
    //   303: lload_3
    //   304: lcmp
    //   305: istore 7
    //   307: iload 7
    //   309: ifle +23 -> 332
    //   312: aload_0
    //   313: getfield 637	com/google/android/gms/internal/zzal:zznz	J
    //   316: lstore 10
    //   318: lload 10
    //   320: invokestatic 515	java/lang/Long:valueOf	(J)Ljava/lang/Long;
    //   323: astore 6
    //   325: aload 5
    //   327: aload 6
    //   329: putfield 640	com/google/ads/afma/nano/NanoAfmaSignals$AFMASignals:tcdnSignal	Ljava/lang/Long;
    //   332: aload_0
    //   333: getfield 643	com/google/android/gms/internal/zzal:zznA	J
    //   336: lstore 10
    //   338: lload 10
    //   340: lload_3
    //   341: lcmp
    //   342: istore 7
    //   344: iload 7
    //   346: ifle +23 -> 369
    //   349: aload_0
    //   350: getfield 643	com/google/android/gms/internal/zzal:zznA	J
    //   353: lstore 10
    //   355: lload 10
    //   357: invokestatic 515	java/lang/Long:valueOf	(J)Ljava/lang/Long;
    //   360: astore 6
    //   362: aload 5
    //   364: aload 6
    //   366: putfield 646	com/google/ads/afma/nano/NanoAfmaSignals$AFMASignals:tcmSignal	Ljava/lang/Long;
    //   369: aload_0
    //   370: getfield 649	com/google/android/gms/internal/zzal:zznB	J
    //   373: lstore 10
    //   375: lload 10
    //   377: lload_3
    //   378: lcmp
    //   379: istore 7
    //   381: iload 7
    //   383: ifle +23 -> 406
    //   386: aload_0
    //   387: getfield 649	com/google/android/gms/internal/zzal:zznB	J
    //   390: lstore 10
    //   392: lload 10
    //   394: invokestatic 515	java/lang/Long:valueOf	(J)Ljava/lang/Long;
    //   397: astore 6
    //   399: aload 5
    //   401: aload 6
    //   403: putfield 652	com/google/ads/afma/nano/NanoAfmaSignals$AFMASignals:tcuSignal	Ljava/lang/Long;
    //   406: aload_0
    //   407: getfield 655	com/google/android/gms/internal/zzal:zznC	J
    //   410: lstore 10
    //   412: lload 10
    //   414: lload_3
    //   415: lcmp
    //   416: istore 7
    //   418: iload 7
    //   420: ifle +23 -> 443
    //   423: aload_0
    //   424: getfield 655	com/google/android/gms/internal/zzal:zznC	J
    //   427: lstore 10
    //   429: lload 10
    //   431: invokestatic 515	java/lang/Long:valueOf	(J)Ljava/lang/Long;
    //   434: astore 6
    //   436: aload 5
    //   438: aload 6
    //   440: putfield 658	com/google/ads/afma/nano/NanoAfmaSignals$AFMASignals:tccSignal	Ljava/lang/Long;
    //   443: aload_0
    //   444: getfield 662	com/google/android/gms/internal/zzal:zzny	Ljava/util/LinkedList;
    //   447: astore 6
    //   449: aload 6
    //   451: invokevirtual 665	java/util/LinkedList:size	()I
    //   454: istore 7
    //   456: iload 7
    //   458: iconst_m1
    //   459: iadd
    //   460: istore 8
    //   462: iload 8
    //   464: ifle +161 -> 625
    //   467: iload 8
    //   469: anewarray 667	com/google/ads/afma/nano/NanoAfmaSignals$AFMASignals$TouchInfo
    //   472: astore 6
    //   474: aload 5
    //   476: aload 6
    //   478: putfield 671	com/google/ads/afma/nano/NanoAfmaSignals$AFMASignals:previousTouches	[Lcom/google/ads/afma/nano/NanoAfmaSignals$AFMASignals$TouchInfo;
    //   481: iload_2
    //   482: iload 8
    //   484: if_icmpge +141 -> 625
    //   487: aload_0
    //   488: getfield 662	com/google/android/gms/internal/zzal:zzny	Ljava/util/LinkedList;
    //   491: astore 6
    //   493: aload 6
    //   495: iload_2
    //   496: invokevirtual 672	java/util/LinkedList:get	(I)Ljava/lang/Object;
    //   499: astore 6
    //   501: aload 6
    //   503: checkcast 434	android/view/MotionEvent
    //   506: astore 6
    //   508: aload_0
    //   509: getfield 614	com/google/android/gms/internal/zzal:zznE	Landroid/util/DisplayMetrics;
    //   512: astore 12
    //   514: aload 6
    //   516: aload 12
    //   518: invokestatic 617	com/google/android/gms/internal/zzal:zza	(Landroid/view/MotionEvent;Landroid/util/DisplayMetrics;)Ljava/util/ArrayList;
    //   521: astore 12
    //   523: new 667	com/google/ads/afma/nano/NanoAfmaSignals$AFMASignals$TouchInfo
    //   526: astore 13
    //   528: aload 13
    //   530: invokespecial 673	com/google/ads/afma/nano/NanoAfmaSignals$AFMASignals$TouchInfo:<init>	()V
    //   533: iconst_0
    //   534: istore 7
    //   536: aconst_null
    //   537: astore 6
    //   539: aload 12
    //   541: iconst_0
    //   542: invokevirtual 532	java/util/ArrayList:get	(I)Ljava/lang/Object;
    //   545: astore 6
    //   547: aload 6
    //   549: checkcast 133	java/lang/Long
    //   552: astore 6
    //   554: aload 13
    //   556: aload 6
    //   558: putfield 674	com/google/ads/afma/nano/NanoAfmaSignals$AFMASignals$TouchInfo:tcxSignal	Ljava/lang/Long;
    //   561: iconst_1
    //   562: istore 7
    //   564: aload 12
    //   566: iload 7
    //   568: invokevirtual 532	java/util/ArrayList:get	(I)Ljava/lang/Object;
    //   571: astore 6
    //   573: aload 6
    //   575: checkcast 133	java/lang/Long
    //   578: astore 6
    //   580: aload 13
    //   582: aload 6
    //   584: putfield 675	com/google/ads/afma/nano/NanoAfmaSignals$AFMASignals$TouchInfo:tcySignal	Ljava/lang/Long;
    //   587: aload 5
    //   589: getfield 671	com/google/ads/afma/nano/NanoAfmaSignals$AFMASignals:previousTouches	[Lcom/google/ads/afma/nano/NanoAfmaSignals$AFMASignals$TouchInfo;
    //   592: astore 6
    //   594: aload 6
    //   596: iload_2
    //   597: aload 13
    //   599: aastore
    //   600: iload_2
    //   601: iconst_1
    //   602: iadd
    //   603: istore 7
    //   605: iload 7
    //   607: istore_2
    //   608: goto -127 -> 481
    //   611: astore 6
    //   613: iconst_0
    //   614: istore 7
    //   616: aconst_null
    //   617: astore 6
    //   619: aload 5
    //   621: aconst_null
    //   622: putfield 671	com/google/ads/afma/nano/NanoAfmaSignals$AFMASignals:previousTouches	[Lcom/google/ads/afma/nano/NanoAfmaSignals$AFMASignals$TouchInfo;
    //   625: aload_1
    //   626: invokestatic 585	com/google/android/gms/internal/zzal:zzg	(Landroid/content/Context;)Ljava/lang/String;
    //   629: astore 6
    //   631: aload 5
    //   633: aload 6
    //   635: putfield 588	com/google/ads/afma/nano/NanoAfmaSignals$AFMASignals:vnmSignal	Ljava/lang/String;
    //   638: aload_1
    //   639: invokestatic 593	com/google/android/gms/internal/zzal:zzh	(Landroid/content/Context;)Ljava/lang/Long;
    //   642: astore 6
    //   644: aload 5
    //   646: aload 6
    //   648: putfield 596	com/google/ads/afma/nano/NanoAfmaSignals$AFMASignals:vcdSignal	Ljava/lang/Long;
    //   651: aload_0
    //   652: invokespecial 600	com/google/android/gms/internal/zzal:zzT	()V
    //   655: aload 5
    //   657: areturn
    //   658: astore 6
    //   660: goto -5 -> 655
    //   663: astore 6
    //   665: goto -14 -> 651
    //   668: astore 6
    //   670: goto -32 -> 638
    //   673: astore 6
    //   675: goto -380 -> 295
    //   678: astore 6
    //   680: goto -608 -> 72
    //   683: astore 6
    //   685: goto -625 -> 60
    //   688: astore 6
    //   690: goto -642 -> 48
    // Local variable table:
    //   start	length	slot	name	signature
    //   0	693	0	this	zzal
    //   0	693	1	paramContext	Context
    //   1	607	2	i	int
    //   3	412	3	l1	long
    //   7	649	5	localAFMASignals	com.google.ads.afma.nano.NanoAfmaSignals.AFMASignals
    //   22	573	6	localObject1	Object
    //   611	1	6	localzza1	zzal.zza
    //   617	30	6	localObject2	Object
    //   658	1	6	localIOException	IOException
    //   663	1	6	localzza2	zzal.zza
    //   668	1	6	localzza3	zzal.zza
    //   673	1	6	localzza4	zzal.zza
    //   678	1	6	localzza5	zzal.zza
    //   683	1	6	localzza6	zzal.zza
    //   688	1	6	localzza7	zzal.zza
    //   29	141	7	j	int
    //   194	3	7	bool1	boolean
    //   202	87	7	k	int
    //   305	114	7	bool2	boolean
    //   454	161	7	m	int
    //   81	404	8	n	int
    //   99	158	9	localObject3	Object
    //   188	242	10	l2	long
    //   512	53	12	localObject4	Object
    //   526	72	13	localTouchInfo	com.google.ads.afma.nano.NanoAfmaSignals.AFMASignals.TouchInfo
    // Exception table:
    //   from	to	target	type
    //   443	447	611	com/google/android/gms/internal/zzal$zza
    //   449	454	611	com/google/android/gms/internal/zzal$zza
    //   467	472	611	com/google/android/gms/internal/zzal$zza
    //   476	481	611	com/google/android/gms/internal/zzal$zza
    //   487	491	611	com/google/android/gms/internal/zzal$zza
    //   495	499	611	com/google/android/gms/internal/zzal$zza
    //   501	506	611	com/google/android/gms/internal/zzal$zza
    //   508	512	611	com/google/android/gms/internal/zzal$zza
    //   516	521	611	com/google/android/gms/internal/zzal$zza
    //   523	526	611	com/google/android/gms/internal/zzal$zza
    //   528	533	611	com/google/android/gms/internal/zzal$zza
    //   541	545	611	com/google/android/gms/internal/zzal$zza
    //   547	552	611	com/google/android/gms/internal/zzal$zza
    //   556	561	611	com/google/android/gms/internal/zzal$zza
    //   566	571	611	com/google/android/gms/internal/zzal$zza
    //   573	578	611	com/google/android/gms/internal/zzal$zza
    //   582	587	611	com/google/android/gms/internal/zzal$zza
    //   587	592	611	com/google/android/gms/internal/zzal$zza
    //   597	600	611	com/google/android/gms/internal/zzal$zza
    //   15	19	658	java/io/IOException
    //   19	22	658	java/io/IOException
    //   24	29	658	java/io/IOException
    //   31	36	658	java/io/IOException
    //   36	39	658	java/io/IOException
    //   43	48	658	java/io/IOException
    //   48	51	658	java/io/IOException
    //   55	60	658	java/io/IOException
    //   60	63	658	java/io/IOException
    //   67	72	658	java/io/IOException
    //   78	81	658	java/io/IOException
    //   84	89	658	java/io/IOException
    //   89	93	658	java/io/IOException
    //   95	99	658	java/io/IOException
    //   103	108	658	java/io/IOException
    //   118	122	658	java/io/IOException
    //   124	129	658	java/io/IOException
    //   133	138	658	java/io/IOException
    //   143	148	658	java/io/IOException
    //   150	155	658	java/io/IOException
    //   159	164	658	java/io/IOException
    //   169	174	658	java/io/IOException
    //   176	181	658	java/io/IOException
    //   183	188	658	java/io/IOException
    //   206	211	658	java/io/IOException
    //   213	218	658	java/io/IOException
    //   222	227	658	java/io/IOException
    //   232	237	658	java/io/IOException
    //   239	244	658	java/io/IOException
    //   248	253	658	java/io/IOException
    //   258	263	658	java/io/IOException
    //   265	270	658	java/io/IOException
    //   274	279	658	java/io/IOException
    //   283	286	658	java/io/IOException
    //   290	295	658	java/io/IOException
    //   295	299	658	java/io/IOException
    //   312	316	658	java/io/IOException
    //   318	323	658	java/io/IOException
    //   327	332	658	java/io/IOException
    //   332	336	658	java/io/IOException
    //   349	353	658	java/io/IOException
    //   355	360	658	java/io/IOException
    //   364	369	658	java/io/IOException
    //   369	373	658	java/io/IOException
    //   386	390	658	java/io/IOException
    //   392	397	658	java/io/IOException
    //   401	406	658	java/io/IOException
    //   406	410	658	java/io/IOException
    //   423	427	658	java/io/IOException
    //   429	434	658	java/io/IOException
    //   438	443	658	java/io/IOException
    //   443	447	658	java/io/IOException
    //   449	454	658	java/io/IOException
    //   467	472	658	java/io/IOException
    //   476	481	658	java/io/IOException
    //   487	491	658	java/io/IOException
    //   495	499	658	java/io/IOException
    //   501	506	658	java/io/IOException
    //   508	512	658	java/io/IOException
    //   516	521	658	java/io/IOException
    //   523	526	658	java/io/IOException
    //   528	533	658	java/io/IOException
    //   541	545	658	java/io/IOException
    //   547	552	658	java/io/IOException
    //   556	561	658	java/io/IOException
    //   566	571	658	java/io/IOException
    //   573	578	658	java/io/IOException
    //   582	587	658	java/io/IOException
    //   587	592	658	java/io/IOException
    //   597	600	658	java/io/IOException
    //   621	625	658	java/io/IOException
    //   625	629	658	java/io/IOException
    //   633	638	658	java/io/IOException
    //   638	642	658	java/io/IOException
    //   646	651	658	java/io/IOException
    //   651	655	658	java/io/IOException
    //   638	642	663	com/google/android/gms/internal/zzal$zza
    //   646	651	663	com/google/android/gms/internal/zzal$zza
    //   625	629	668	com/google/android/gms/internal/zzal$zza
    //   633	638	668	com/google/android/gms/internal/zzal$zza
    //   89	93	673	com/google/android/gms/internal/zzal$zza
    //   95	99	673	com/google/android/gms/internal/zzal$zza
    //   103	108	673	com/google/android/gms/internal/zzal$zza
    //   118	122	673	com/google/android/gms/internal/zzal$zza
    //   124	129	673	com/google/android/gms/internal/zzal$zza
    //   133	138	673	com/google/android/gms/internal/zzal$zza
    //   143	148	673	com/google/android/gms/internal/zzal$zza
    //   150	155	673	com/google/android/gms/internal/zzal$zza
    //   159	164	673	com/google/android/gms/internal/zzal$zza
    //   169	174	673	com/google/android/gms/internal/zzal$zza
    //   176	181	673	com/google/android/gms/internal/zzal$zza
    //   183	188	673	com/google/android/gms/internal/zzal$zza
    //   206	211	673	com/google/android/gms/internal/zzal$zza
    //   213	218	673	com/google/android/gms/internal/zzal$zza
    //   222	227	673	com/google/android/gms/internal/zzal$zza
    //   232	237	673	com/google/android/gms/internal/zzal$zza
    //   239	244	673	com/google/android/gms/internal/zzal$zza
    //   248	253	673	com/google/android/gms/internal/zzal$zza
    //   258	263	673	com/google/android/gms/internal/zzal$zza
    //   265	270	673	com/google/android/gms/internal/zzal$zza
    //   274	279	673	com/google/android/gms/internal/zzal$zza
    //   283	286	673	com/google/android/gms/internal/zzal$zza
    //   290	295	673	com/google/android/gms/internal/zzal$zza
    //   60	63	678	com/google/android/gms/internal/zzal$zza
    //   67	72	678	com/google/android/gms/internal/zzal$zza
    //   48	51	683	com/google/android/gms/internal/zzal$zza
    //   55	60	683	com/google/android/gms/internal/zzal$zza
    //   36	39	688	com/google/android/gms/internal/zzal$zza
    //   43	48	688	com/google/android/gms/internal/zzal$zza
  }
}


/* Location:              C:\Users\haryo\Desktop\enjarify-master\presensi-enjarify.jar!\com\google\android\gms\internal\zzal.class
 * Java compiler version: 5 (49.0)
 * JD-Core Version:       0.7.1
 */