package com.google.android.gms.internal;

final class zzde$5
  implements zzdf
{
  /* Error */
  public void zza(zzjp paramzzjp, java.util.Map paramMap)
  {
    // Byte code:
    //   0: aload_1
    //   1: invokeinterface 16 1 0
    //   6: invokevirtual 22	android/content/Context:getPackageManager	()Landroid/content/pm/PackageManager;
    //   9: astore_3
    //   10: aload_2
    //   11: ldc 24
    //   13: invokeinterface 30 2 0
    //   18: checkcast 32	java/lang/String
    //   21: astore 4
    //   23: new 34	org/json/JSONObject
    //   26: astore 5
    //   28: aload 5
    //   30: aload 4
    //   32: invokespecial 37	org/json/JSONObject:<init>	(Ljava/lang/String;)V
    //   35: ldc 39
    //   37: astore 4
    //   39: aload 5
    //   41: aload 4
    //   43: invokevirtual 43	org/json/JSONObject:getJSONArray	(Ljava/lang/String;)Lorg/json/JSONArray;
    //   46: astore 6
    //   48: new 34	org/json/JSONObject
    //   51: astore 7
    //   53: aload 7
    //   55: invokespecial 44	org/json/JSONObject:<init>	()V
    //   58: iconst_0
    //   59: istore 8
    //   61: aconst_null
    //   62: astore 4
    //   64: aload 6
    //   66: invokevirtual 50	org/json/JSONArray:length	()I
    //   69: istore 9
    //   71: iload 8
    //   73: iload 9
    //   75: if_icmpge +399 -> 474
    //   78: aload 6
    //   80: iload 8
    //   82: invokevirtual 54	org/json/JSONArray:getJSONObject	(I)Lorg/json/JSONObject;
    //   85: astore 5
    //   87: aload 5
    //   89: ldc 56
    //   91: invokevirtual 60	org/json/JSONObject:optString	(Ljava/lang/String;)Ljava/lang/String;
    //   94: astore 10
    //   96: aload 5
    //   98: ldc 62
    //   100: invokevirtual 60	org/json/JSONObject:optString	(Ljava/lang/String;)Ljava/lang/String;
    //   103: astore 11
    //   105: aload 5
    //   107: ldc 64
    //   109: invokevirtual 60	org/json/JSONObject:optString	(Ljava/lang/String;)Ljava/lang/String;
    //   112: astore 12
    //   114: aload 5
    //   116: ldc 66
    //   118: invokevirtual 60	org/json/JSONObject:optString	(Ljava/lang/String;)Ljava/lang/String;
    //   121: astore 13
    //   123: aload 5
    //   125: ldc 68
    //   127: invokevirtual 60	org/json/JSONObject:optString	(Ljava/lang/String;)Ljava/lang/String;
    //   130: astore 14
    //   132: aload 5
    //   134: ldc 70
    //   136: invokevirtual 60	org/json/JSONObject:optString	(Ljava/lang/String;)Ljava/lang/String;
    //   139: astore 15
    //   141: aload 5
    //   143: ldc 72
    //   145: invokevirtual 60	org/json/JSONObject:optString	(Ljava/lang/String;)Ljava/lang/String;
    //   148: pop
    //   149: ldc 74
    //   151: astore 16
    //   153: aload 5
    //   155: aload 16
    //   157: invokevirtual 60	org/json/JSONObject:optString	(Ljava/lang/String;)Ljava/lang/String;
    //   160: pop
    //   161: new 76	android/content/Intent
    //   164: astore 5
    //   166: aload 5
    //   168: invokespecial 77	android/content/Intent:<init>	()V
    //   171: aload 11
    //   173: invokestatic 83	android/text/TextUtils:isEmpty	(Ljava/lang/CharSequence;)Z
    //   176: istore 17
    //   178: iload 17
    //   180: ifne +18 -> 198
    //   183: aload 11
    //   185: invokestatic 89	android/net/Uri:parse	(Ljava/lang/String;)Landroid/net/Uri;
    //   188: astore 11
    //   190: aload 5
    //   192: aload 11
    //   194: invokevirtual 93	android/content/Intent:setData	(Landroid/net/Uri;)Landroid/content/Intent;
    //   197: pop
    //   198: aload 12
    //   200: invokestatic 83	android/text/TextUtils:isEmpty	(Ljava/lang/CharSequence;)Z
    //   203: istore 18
    //   205: iload 18
    //   207: ifne +11 -> 218
    //   210: aload 5
    //   212: aload 12
    //   214: invokevirtual 97	android/content/Intent:setAction	(Ljava/lang/String;)Landroid/content/Intent;
    //   217: pop
    //   218: aload 13
    //   220: invokestatic 83	android/text/TextUtils:isEmpty	(Ljava/lang/CharSequence;)Z
    //   223: istore 18
    //   225: iload 18
    //   227: ifne +11 -> 238
    //   230: aload 5
    //   232: aload 13
    //   234: invokevirtual 100	android/content/Intent:setType	(Ljava/lang/String;)Landroid/content/Intent;
    //   237: pop
    //   238: aload 14
    //   240: invokestatic 83	android/text/TextUtils:isEmpty	(Ljava/lang/CharSequence;)Z
    //   243: istore 18
    //   245: iload 18
    //   247: ifne +11 -> 258
    //   250: aload 5
    //   252: aload 14
    //   254: invokevirtual 103	android/content/Intent:setPackage	(Ljava/lang/String;)Landroid/content/Intent;
    //   257: pop
    //   258: aload 15
    //   260: invokestatic 83	android/text/TextUtils:isEmpty	(Ljava/lang/CharSequence;)Z
    //   263: istore 18
    //   265: iload 18
    //   267: ifne +69 -> 336
    //   270: aload 15
    //   272: ldc 105
    //   274: iconst_2
    //   275: invokevirtual 110	java/lang/String:split	(Ljava/lang/String;I)[Ljava/lang/String;
    //   278: astore 11
    //   280: aload 11
    //   282: arraylength
    //   283: istore 19
    //   285: iconst_2
    //   286: istore 20
    //   288: iload 19
    //   290: iload 20
    //   292: if_icmpne +44 -> 336
    //   295: new 112	android/content/ComponentName
    //   298: astore 12
    //   300: iconst_0
    //   301: istore 20
    //   303: aload 11
    //   305: iconst_0
    //   306: aaload
    //   307: astore 13
    //   309: iconst_1
    //   310: istore 21
    //   312: aload 11
    //   314: iload 21
    //   316: aaload
    //   317: astore 11
    //   319: aload 12
    //   321: aload 13
    //   323: aload 11
    //   325: invokespecial 116	android/content/ComponentName:<init>	(Ljava/lang/String;Ljava/lang/String;)V
    //   328: aload 5
    //   330: aload 12
    //   332: invokevirtual 120	android/content/Intent:setComponent	(Landroid/content/ComponentName;)Landroid/content/Intent;
    //   335: pop
    //   336: ldc 121
    //   338: istore 18
    //   340: aload_3
    //   341: aload 5
    //   343: iload 18
    //   345: invokevirtual 128	android/content/pm/PackageManager:resolveActivity	(Landroid/content/Intent;I)Landroid/content/pm/ResolveInfo;
    //   348: astore 5
    //   350: aload 5
    //   352: ifnull +97 -> 449
    //   355: iconst_1
    //   356: istore 9
    //   358: aload 7
    //   360: aload 10
    //   362: iload 9
    //   364: invokevirtual 132	org/json/JSONObject:put	(Ljava/lang/String;Z)Lorg/json/JSONObject;
    //   367: pop
    //   368: iload 8
    //   370: iconst_1
    //   371: iadd
    //   372: istore 8
    //   374: goto -310 -> 64
    //   377: astore 4
    //   379: ldc -122
    //   381: astore 4
    //   383: new 34	org/json/JSONObject
    //   386: astore 5
    //   388: aload 5
    //   390: invokespecial 44	org/json/JSONObject:<init>	()V
    //   393: aload_1
    //   394: aload 4
    //   396: aload 5
    //   398: invokeinterface 138 3 0
    //   403: return
    //   404: astore 4
    //   406: ldc -122
    //   408: astore 4
    //   410: new 34	org/json/JSONObject
    //   413: astore 5
    //   415: aload 5
    //   417: invokespecial 44	org/json/JSONObject:<init>	()V
    //   420: aload_1
    //   421: aload 4
    //   423: aload 5
    //   425: invokeinterface 138 3 0
    //   430: goto -27 -> 403
    //   433: astore 5
    //   435: ldc -116
    //   437: astore 10
    //   439: aload 10
    //   441: aload 5
    //   443: invokestatic 145	com/google/android/gms/internal/zzin:zzb	(Ljava/lang/String;Ljava/lang/Throwable;)V
    //   446: goto -78 -> 368
    //   449: iconst_0
    //   450: istore 9
    //   452: aconst_null
    //   453: astore 5
    //   455: goto -97 -> 358
    //   458: astore 5
    //   460: ldc -109
    //   462: astore 10
    //   464: aload 10
    //   466: aload 5
    //   468: invokestatic 145	com/google/android/gms/internal/zzin:zzb	(Ljava/lang/String;Ljava/lang/Throwable;)V
    //   471: goto -103 -> 368
    //   474: ldc -122
    //   476: astore 4
    //   478: aload_1
    //   479: aload 4
    //   481: aload 7
    //   483: invokeinterface 138 3 0
    //   488: goto -85 -> 403
    // Local variable table:
    //   start	length	slot	name	signature
    //   0	491	0	this	5
    //   0	491	1	paramzzjp	zzjp
    //   0	491	2	paramMap	java.util.Map
    //   9	332	3	localPackageManager	android.content.pm.PackageManager
    //   21	42	4	str1	String
    //   377	1	4	localJSONException1	org.json.JSONException
    //   381	14	4	str2	String
    //   404	1	4	localJSONException2	org.json.JSONException
    //   408	72	4	str3	String
    //   26	398	5	localObject1	Object
    //   433	9	5	localJSONException3	org.json.JSONException
    //   453	1	5	localObject2	Object
    //   458	9	5	localJSONException4	org.json.JSONException
    //   46	33	6	localJSONArray	org.json.JSONArray
    //   51	431	7	localJSONObject	org.json.JSONObject
    //   59	314	8	i	int
    //   69	294	9	j	int
    //   450	1	9	k	int
    //   94	371	10	str4	String
    //   103	221	11	localObject3	Object
    //   112	219	12	localObject4	Object
    //   121	201	13	str5	String
    //   130	123	14	str6	String
    //   139	132	15	str7	String
    //   151	5	16	str8	String
    //   176	3	17	bool1	boolean
    //   203	63	18	bool2	boolean
    //   338	6	18	m	int
    //   283	10	19	n	int
    //   286	16	20	i1	int
    //   310	5	21	i2	int
    // Exception table:
    //   from	to	target	type
    //   23	26	377	org/json/JSONException
    //   30	35	377	org/json/JSONException
    //   41	46	404	org/json/JSONException
    //   80	85	433	org/json/JSONException
    //   362	368	458	org/json/JSONException
  }
}


/* Location:              C:\Users\haryo\Desktop\enjarify-master\presensi-enjarify.jar!\com\google\android\gms\internal\zzde$5.class
 * Java compiler version: 5 (49.0)
 * JD-Core Version:       0.7.1
 */