package com.google.android.gms.internal;

import android.content.Context;
import java.io.File;
import java.io.IOException;
import java.text.DecimalFormat;
import java.util.Collections;
import java.util.HashSet;
import java.util.Set;

public class zzdu
  extends zzdr
{
  private static final Set zzzX;
  private static final DecimalFormat zzzY;
  private boolean zzAa;
  private File zzzZ;
  
  static
  {
    Object localObject = new java/util/HashSet;
    ((HashSet)localObject).<init>();
    zzzX = Collections.synchronizedSet((Set)localObject);
    localObject = new java/text/DecimalFormat;
    ((DecimalFormat)localObject).<init>("#,###");
    zzzY = (DecimalFormat)localObject;
  }
  
  public zzdu(zzjp paramzzjp)
  {
    super(paramzzjp);
    Object localObject1 = this.mContext.getCacheDir();
    if (localObject1 == null)
    {
      localObject1 = "Context.getCacheDir() returned null";
      zzin.zzaK((String)localObject1);
    }
    for (;;)
    {
      return;
      Object localObject2 = new java/io/File;
      String str = "admobVideoStreams";
      ((File)localObject2).<init>((File)localObject1, str);
      this.zzzZ = ((File)localObject2);
      localObject1 = this.zzzZ;
      boolean bool2 = ((File)localObject1).isDirectory();
      if (!bool2)
      {
        localObject1 = this.zzzZ;
        bool2 = ((File)localObject1).mkdirs();
        if (!bool2)
        {
          localObject1 = new java/lang/StringBuilder;
          ((StringBuilder)localObject1).<init>();
          localObject1 = ((StringBuilder)localObject1).append("Could not create preload cache directory at ");
          localObject2 = this.zzzZ.getAbsolutePath();
          localObject1 = (String)localObject2;
          zzin.zzaK((String)localObject1);
          this.zzzZ = null;
          continue;
        }
      }
      localObject1 = this.zzzZ;
      bool2 = ((File)localObject1).setReadable(bool1, false);
      if (bool2)
      {
        localObject1 = this.zzzZ;
        bool2 = ((File)localObject1).setExecutable(bool1, false);
        if (bool2) {}
      }
      else
      {
        localObject1 = new java/lang/StringBuilder;
        ((StringBuilder)localObject1).<init>();
        localObject1 = ((StringBuilder)localObject1).append("Could not set cache file permissions at ");
        localObject2 = this.zzzZ.getAbsolutePath();
        localObject1 = (String)localObject2;
        zzin.zzaK((String)localObject1);
        this.zzzZ = null;
      }
    }
  }
  
  private File zza(File paramFile)
  {
    File localFile1 = new java/io/File;
    File localFile2 = this.zzzZ;
    Object localObject = new java/lang/StringBuilder;
    ((StringBuilder)localObject).<init>();
    String str = paramFile.getName();
    localObject = str + ".done";
    localFile1.<init>(localFile2, (String)localObject);
    return localFile1;
  }
  
  private static void zzb(File paramFile)
  {
    boolean bool = paramFile.isFile();
    if (bool)
    {
      long l = System.currentTimeMillis();
      paramFile.setLastModified(l);
    }
    for (;;)
    {
      return;
      try
      {
        paramFile.createNewFile();
      }
      catch (IOException localIOException) {}
    }
  }
  
  public void abort()
  {
    this.zzAa = true;
  }
  
  /* Error */
  public boolean zzU(String paramString)
  {
    // Byte code:
    //   0: aload_0
    //   1: astore_2
    //   2: aload_0
    //   3: getfield 65	com/google/android/gms/internal/zzdu:zzzZ	Ljava/io/File;
    //   6: astore_3
    //   7: aload_3
    //   8: ifnonnull +30 -> 38
    //   11: ldc 124
    //   13: astore 4
    //   15: iconst_0
    //   16: istore 5
    //   18: aconst_null
    //   19: astore 6
    //   21: aload_0
    //   22: aload_1
    //   23: aconst_null
    //   24: aload 4
    //   26: aconst_null
    //   27: invokevirtual 128	com/google/android/gms/internal/zzdu:zza	(Ljava/lang/String;Ljava/lang/String;Ljava/lang/String;Ljava/lang/String;)V
    //   30: iconst_0
    //   31: istore 7
    //   33: aconst_null
    //   34: astore_3
    //   35: iload 7
    //   37: ireturn
    //   38: aload_0
    //   39: invokevirtual 132	com/google/android/gms/internal/zzdu:zzea	()I
    //   42: istore 8
    //   44: getstatic 138	com/google/android/gms/internal/zzbt:zzvO	Lcom/google/android/gms/internal/zzbp;
    //   47: invokevirtual 144	com/google/android/gms/internal/zzbp:get	()Ljava/lang/Object;
    //   50: checkcast 146	java/lang/Integer
    //   53: astore_3
    //   54: aload_3
    //   55: invokevirtual 149	java/lang/Integer:intValue	()I
    //   58: istore 7
    //   60: iload 8
    //   62: iload 7
    //   64: if_icmple +48 -> 112
    //   67: aload_0
    //   68: invokevirtual 152	com/google/android/gms/internal/zzdu:zzeb	()Z
    //   71: istore 7
    //   73: iload 7
    //   75: ifne -37 -> 38
    //   78: ldc -102
    //   80: invokestatic 56	com/google/android/gms/internal/zzin:zzaK	(Ljava/lang/String;)V
    //   83: ldc -100
    //   85: astore 4
    //   87: iconst_0
    //   88: istore 5
    //   90: aconst_null
    //   91: astore 6
    //   93: aload_0
    //   94: astore_2
    //   95: aload_0
    //   96: aload_1
    //   97: aconst_null
    //   98: aload 4
    //   100: aconst_null
    //   101: invokevirtual 128	com/google/android/gms/internal/zzdu:zza	(Ljava/lang/String;Ljava/lang/String;Ljava/lang/String;Ljava/lang/String;)V
    //   104: iconst_0
    //   105: istore 7
    //   107: aconst_null
    //   108: astore_3
    //   109: goto -74 -> 35
    //   112: aload_0
    //   113: aload_1
    //   114: invokevirtual 160	com/google/android/gms/internal/zzdu:zzV	(Ljava/lang/String;)Ljava/lang/String;
    //   117: astore_3
    //   118: new 58	java/io/File
    //   121: astore 9
    //   123: aload_0
    //   124: astore_2
    //   125: aload_0
    //   126: getfield 65	com/google/android/gms/internal/zzdu:zzzZ	Ljava/io/File;
    //   129: astore 4
    //   131: aload 9
    //   133: aload 4
    //   135: aload_3
    //   136: invokespecial 63	java/io/File:<init>	(Ljava/io/File;Ljava/lang/String;)V
    //   139: aload_0
    //   140: aload 9
    //   142: invokespecial 163	com/google/android/gms/internal/zzdu:zza	(Ljava/io/File;)Ljava/io/File;
    //   145: astore 10
    //   147: aload 9
    //   149: invokevirtual 105	java/io/File:isFile	()Z
    //   152: istore 7
    //   154: iload 7
    //   156: ifeq +88 -> 244
    //   159: aload 10
    //   161: invokevirtual 105	java/io/File:isFile	()Z
    //   164: istore 7
    //   166: iload 7
    //   168: ifeq +76 -> 244
    //   171: aload 9
    //   173: invokevirtual 166	java/io/File:length	()J
    //   176: lstore 11
    //   178: lload 11
    //   180: l2i
    //   181: istore 7
    //   183: new 74	java/lang/StringBuilder
    //   186: astore 4
    //   188: aload 4
    //   190: invokespecial 75	java/lang/StringBuilder:<init>	()V
    //   193: ldc -88
    //   195: astore 6
    //   197: aload 4
    //   199: aload 6
    //   201: invokevirtual 81	java/lang/StringBuilder:append	(Ljava/lang/String;)Ljava/lang/StringBuilder;
    //   204: astore 4
    //   206: aload_1
    //   207: astore_2
    //   208: aload 4
    //   210: aload_1
    //   211: invokevirtual 81	java/lang/StringBuilder:append	(Ljava/lang/String;)Ljava/lang/StringBuilder;
    //   214: invokevirtual 88	java/lang/StringBuilder:toString	()Ljava/lang/String;
    //   217: invokestatic 171	com/google/android/gms/internal/zzin:zzaI	(Ljava/lang/String;)V
    //   220: aload 9
    //   222: invokevirtual 85	java/io/File:getAbsolutePath	()Ljava/lang/String;
    //   225: astore 4
    //   227: aload_0
    //   228: astore_2
    //   229: aload_0
    //   230: aload_1
    //   231: aload 4
    //   233: iload 7
    //   235: invokevirtual 174	com/google/android/gms/internal/zzdu:zza	(Ljava/lang/String;Ljava/lang/String;I)V
    //   238: iconst_1
    //   239: istore 7
    //   241: goto -206 -> 35
    //   244: new 74	java/lang/StringBuilder
    //   247: astore_3
    //   248: aload_3
    //   249: invokespecial 75	java/lang/StringBuilder:<init>	()V
    //   252: aload_0
    //   253: astore_2
    //   254: aload_0
    //   255: getfield 65	com/google/android/gms/internal/zzdu:zzzZ	Ljava/io/File;
    //   258: invokevirtual 85	java/io/File:getAbsolutePath	()Ljava/lang/String;
    //   261: astore 4
    //   263: aload_3
    //   264: aload 4
    //   266: invokevirtual 81	java/lang/StringBuilder:append	(Ljava/lang/String;)Ljava/lang/StringBuilder;
    //   269: astore_3
    //   270: aload_1
    //   271: astore_2
    //   272: aload_3
    //   273: aload_1
    //   274: invokevirtual 81	java/lang/StringBuilder:append	(Ljava/lang/String;)Ljava/lang/StringBuilder;
    //   277: astore_3
    //   278: aload_3
    //   279: invokevirtual 88	java/lang/StringBuilder:toString	()Ljava/lang/String;
    //   282: astore 13
    //   284: getstatic 26	com/google/android/gms/internal/zzdu:zzzX	Ljava/util/Set;
    //   287: astore 4
    //   289: aload 4
    //   291: monitorenter
    //   292: getstatic 26	com/google/android/gms/internal/zzdu:zzzX	Ljava/util/Set;
    //   295: astore_3
    //   296: aload_3
    //   297: aload 13
    //   299: invokeinterface 180 2 0
    //   304: istore 7
    //   306: iload 7
    //   308: ifeq +81 -> 389
    //   311: new 74	java/lang/StringBuilder
    //   314: astore_3
    //   315: aload_3
    //   316: invokespecial 75	java/lang/StringBuilder:<init>	()V
    //   319: ldc -74
    //   321: astore 6
    //   323: aload_3
    //   324: aload 6
    //   326: invokevirtual 81	java/lang/StringBuilder:append	(Ljava/lang/String;)Ljava/lang/StringBuilder;
    //   329: astore_3
    //   330: aload_3
    //   331: aload_1
    //   332: invokevirtual 81	java/lang/StringBuilder:append	(Ljava/lang/String;)Ljava/lang/StringBuilder;
    //   335: astore_3
    //   336: aload_3
    //   337: invokevirtual 88	java/lang/StringBuilder:toString	()Ljava/lang/String;
    //   340: astore_3
    //   341: aload_3
    //   342: invokestatic 56	com/google/android/gms/internal/zzin:zzaK	(Ljava/lang/String;)V
    //   345: aload 9
    //   347: invokevirtual 85	java/io/File:getAbsolutePath	()Ljava/lang/String;
    //   350: astore_3
    //   351: ldc -72
    //   353: astore 6
    //   355: iconst_0
    //   356: istore 14
    //   358: aconst_null
    //   359: astore 15
    //   361: aload_0
    //   362: astore_2
    //   363: aload_0
    //   364: aload_1
    //   365: aload_3
    //   366: aload 6
    //   368: aconst_null
    //   369: invokevirtual 128	com/google/android/gms/internal/zzdu:zza	(Ljava/lang/String;Ljava/lang/String;Ljava/lang/String;Ljava/lang/String;)V
    //   372: iconst_0
    //   373: istore 7
    //   375: aconst_null
    //   376: astore_3
    //   377: aload 4
    //   379: monitorexit
    //   380: goto -345 -> 35
    //   383: astore_3
    //   384: aload 4
    //   386: monitorexit
    //   387: aload_3
    //   388: athrow
    //   389: getstatic 26	com/google/android/gms/internal/zzdu:zzzX	Ljava/util/Set;
    //   392: astore_3
    //   393: aload_3
    //   394: aload 13
    //   396: invokeinterface 187 2 0
    //   401: pop
    //   402: aload 4
    //   404: monitorexit
    //   405: iconst_0
    //   406: istore 14
    //   408: aconst_null
    //   409: astore 15
    //   411: ldc -67
    //   413: astore 16
    //   415: aconst_null
    //   416: astore 17
    //   418: new 191	java/net/URL
    //   421: astore_3
    //   422: aload_3
    //   423: aload_1
    //   424: invokespecial 192	java/net/URL:<init>	(Ljava/lang/String;)V
    //   427: aload_3
    //   428: invokevirtual 196	java/net/URL:openConnection	()Ljava/net/URLConnection;
    //   431: astore 4
    //   433: getstatic 199	com/google/android/gms/internal/zzbt:zzvT	Lcom/google/android/gms/internal/zzbp;
    //   436: astore_3
    //   437: aload_3
    //   438: invokevirtual 144	com/google/android/gms/internal/zzbp:get	()Ljava/lang/Object;
    //   441: astore_3
    //   442: aload_3
    //   443: checkcast 146	java/lang/Integer
    //   446: astore_3
    //   447: aload_3
    //   448: invokevirtual 149	java/lang/Integer:intValue	()I
    //   451: istore 7
    //   453: aload 4
    //   455: iload 7
    //   457: invokevirtual 205	java/net/URLConnection:setConnectTimeout	(I)V
    //   460: aload 4
    //   462: iload 7
    //   464: invokevirtual 208	java/net/URLConnection:setReadTimeout	(I)V
    //   467: aload 4
    //   469: instanceof 210
    //   472: istore 7
    //   474: iload 7
    //   476: ifeq +339 -> 815
    //   479: aload 4
    //   481: astore_2
    //   482: aload 4
    //   484: checkcast 210	java/net/HttpURLConnection
    //   487: astore_2
    //   488: aload_2
    //   489: astore_3
    //   490: aload_2
    //   491: invokevirtual 213	java/net/HttpURLConnection:getResponseCode	()I
    //   494: istore 7
    //   496: sipush 400
    //   499: istore 5
    //   501: iload 7
    //   503: iload 5
    //   505: if_icmplt +310 -> 815
    //   508: ldc -40
    //   510: astore 6
    //   512: new 74	java/lang/StringBuilder
    //   515: astore 4
    //   517: aload 4
    //   519: invokespecial 75	java/lang/StringBuilder:<init>	()V
    //   522: ldc -38
    //   524: astore 18
    //   526: aload 4
    //   528: aload 18
    //   530: invokevirtual 81	java/lang/StringBuilder:append	(Ljava/lang/String;)Ljava/lang/StringBuilder;
    //   533: astore 4
    //   535: iload 7
    //   537: invokestatic 221	java/lang/Integer:toString	(I)Ljava/lang/String;
    //   540: astore 18
    //   542: aload 4
    //   544: aload 18
    //   546: invokevirtual 81	java/lang/StringBuilder:append	(Ljava/lang/String;)Ljava/lang/StringBuilder;
    //   549: astore 4
    //   551: aload 4
    //   553: invokevirtual 88	java/lang/StringBuilder:toString	()Ljava/lang/String;
    //   556: astore 4
    //   558: new 120	java/io/IOException
    //   561: astore 18
    //   563: new 74	java/lang/StringBuilder
    //   566: astore 19
    //   568: aload 19
    //   570: invokespecial 75	java/lang/StringBuilder:<init>	()V
    //   573: ldc -33
    //   575: astore 17
    //   577: aload 19
    //   579: aload 17
    //   581: invokevirtual 81	java/lang/StringBuilder:append	(Ljava/lang/String;)Ljava/lang/StringBuilder;
    //   584: astore 19
    //   586: aload 19
    //   588: iload 7
    //   590: invokevirtual 226	java/lang/StringBuilder:append	(I)Ljava/lang/StringBuilder;
    //   593: astore_3
    //   594: ldc -28
    //   596: astore 19
    //   598: aload_3
    //   599: aload 19
    //   601: invokevirtual 81	java/lang/StringBuilder:append	(Ljava/lang/String;)Ljava/lang/StringBuilder;
    //   604: astore_3
    //   605: aload_1
    //   606: astore_2
    //   607: aload_3
    //   608: aload_1
    //   609: invokevirtual 81	java/lang/StringBuilder:append	(Ljava/lang/String;)Ljava/lang/StringBuilder;
    //   612: astore_3
    //   613: aload_3
    //   614: invokevirtual 88	java/lang/StringBuilder:toString	()Ljava/lang/String;
    //   617: astore_3
    //   618: aload 18
    //   620: aload_3
    //   621: invokespecial 229	java/io/IOException:<init>	(Ljava/lang/String;)V
    //   624: aload 18
    //   626: athrow
    //   627: astore_3
    //   628: aload_3
    //   629: instanceof 231
    //   632: istore 20
    //   634: iload 20
    //   636: ifeq +22 -> 658
    //   639: invokestatic 237	com/google/android/gms/ads/internal/zzr:zzbF	()Lcom/google/android/gms/internal/zzih;
    //   642: astore 18
    //   644: iconst_1
    //   645: istore 21
    //   647: aload 18
    //   649: aload_3
    //   650: checkcast 239	java/lang/Throwable
    //   653: iload 21
    //   655: invokevirtual 245	com/google/android/gms/internal/zzih:zzb	(Ljava/lang/Throwable;Z)V
    //   658: aload 15
    //   660: invokevirtual 250	java/io/FileOutputStream:close	()V
    //   663: aload_0
    //   664: astore_2
    //   665: aload_0
    //   666: getfield 122	com/google/android/gms/internal/zzdu:zzAa	Z
    //   669: istore 14
    //   671: iload 14
    //   673: ifeq +1106 -> 1779
    //   676: new 74	java/lang/StringBuilder
    //   679: astore_3
    //   680: aload_3
    //   681: invokespecial 75	java/lang/StringBuilder:<init>	()V
    //   684: aload_3
    //   685: ldc -4
    //   687: invokevirtual 81	java/lang/StringBuilder:append	(Ljava/lang/String;)Ljava/lang/StringBuilder;
    //   690: astore_3
    //   691: aload_1
    //   692: astore_2
    //   693: aload_3
    //   694: aload_1
    //   695: invokevirtual 81	java/lang/StringBuilder:append	(Ljava/lang/String;)Ljava/lang/StringBuilder;
    //   698: astore_3
    //   699: ldc -2
    //   701: astore 15
    //   703: aload_3
    //   704: aload 15
    //   706: invokevirtual 81	java/lang/StringBuilder:append	(Ljava/lang/String;)Ljava/lang/StringBuilder;
    //   709: invokevirtual 88	java/lang/StringBuilder:toString	()Ljava/lang/String;
    //   712: astore_3
    //   713: aload_3
    //   714: invokestatic 257	com/google/android/gms/internal/zzin:zzaJ	(Ljava/lang/String;)V
    //   717: aload 9
    //   719: invokevirtual 260	java/io/File:exists	()Z
    //   722: istore 7
    //   724: iload 7
    //   726: ifeq +52 -> 778
    //   729: aload 9
    //   731: invokevirtual 263	java/io/File:delete	()Z
    //   734: istore 7
    //   736: iload 7
    //   738: ifne +40 -> 778
    //   741: new 74	java/lang/StringBuilder
    //   744: astore_3
    //   745: aload_3
    //   746: invokespecial 75	java/lang/StringBuilder:<init>	()V
    //   749: aload_3
    //   750: ldc_w 265
    //   753: invokevirtual 81	java/lang/StringBuilder:append	(Ljava/lang/String;)Ljava/lang/StringBuilder;
    //   756: astore_3
    //   757: aload 9
    //   759: invokevirtual 85	java/io/File:getAbsolutePath	()Ljava/lang/String;
    //   762: astore 15
    //   764: aload_3
    //   765: aload 15
    //   767: invokevirtual 81	java/lang/StringBuilder:append	(Ljava/lang/String;)Ljava/lang/StringBuilder;
    //   770: invokevirtual 88	java/lang/StringBuilder:toString	()Ljava/lang/String;
    //   773: astore_3
    //   774: aload_3
    //   775: invokestatic 56	com/google/android/gms/internal/zzin:zzaK	(Ljava/lang/String;)V
    //   778: aload 9
    //   780: invokevirtual 85	java/io/File:getAbsolutePath	()Ljava/lang/String;
    //   783: astore_3
    //   784: aload_0
    //   785: astore_2
    //   786: aload_0
    //   787: aload_1
    //   788: aload_3
    //   789: aload 6
    //   791: aload 4
    //   793: invokevirtual 128	com/google/android/gms/internal/zzdu:zza	(Ljava/lang/String;Ljava/lang/String;Ljava/lang/String;Ljava/lang/String;)V
    //   796: getstatic 26	com/google/android/gms/internal/zzdu:zzzX	Ljava/util/Set;
    //   799: aload 13
    //   801: invokeinterface 268 2 0
    //   806: pop
    //   807: iconst_0
    //   808: istore 7
    //   810: aconst_null
    //   811: astore_3
    //   812: goto -777 -> 35
    //   815: aload 4
    //   817: checkcast 201	java/net/URLConnection
    //   820: invokevirtual 271	java/net/URLConnection:getContentLength	()I
    //   823: istore 20
    //   825: iload 20
    //   827: ifge +89 -> 916
    //   830: new 74	java/lang/StringBuilder
    //   833: astore_3
    //   834: aload_3
    //   835: invokespecial 75	java/lang/StringBuilder:<init>	()V
    //   838: ldc_w 273
    //   841: astore 4
    //   843: aload_3
    //   844: aload 4
    //   846: invokevirtual 81	java/lang/StringBuilder:append	(Ljava/lang/String;)Ljava/lang/StringBuilder;
    //   849: astore_3
    //   850: aload_1
    //   851: astore_2
    //   852: aload_3
    //   853: aload_1
    //   854: invokevirtual 81	java/lang/StringBuilder:append	(Ljava/lang/String;)Ljava/lang/StringBuilder;
    //   857: astore_3
    //   858: aload_3
    //   859: invokevirtual 88	java/lang/StringBuilder:toString	()Ljava/lang/String;
    //   862: astore_3
    //   863: aload_3
    //   864: invokestatic 56	com/google/android/gms/internal/zzin:zzaK	(Ljava/lang/String;)V
    //   867: aload 9
    //   869: invokevirtual 85	java/io/File:getAbsolutePath	()Ljava/lang/String;
    //   872: astore_3
    //   873: ldc_w 275
    //   876: astore 4
    //   878: iconst_0
    //   879: istore 5
    //   881: aconst_null
    //   882: astore 6
    //   884: aload_0
    //   885: astore_2
    //   886: aload_0
    //   887: aload_1
    //   888: aload_3
    //   889: aload 4
    //   891: aconst_null
    //   892: invokevirtual 128	com/google/android/gms/internal/zzdu:zza	(Ljava/lang/String;Ljava/lang/String;Ljava/lang/String;Ljava/lang/String;)V
    //   895: getstatic 26	com/google/android/gms/internal/zzdu:zzzX	Ljava/util/Set;
    //   898: astore_3
    //   899: aload_3
    //   900: aload 13
    //   902: invokeinterface 268 2 0
    //   907: pop
    //   908: iconst_0
    //   909: istore 7
    //   911: aconst_null
    //   912: astore_3
    //   913: goto -878 -> 35
    //   916: getstatic 35	com/google/android/gms/internal/zzdu:zzzY	Ljava/text/DecimalFormat;
    //   919: astore_3
    //   920: iload 20
    //   922: i2l
    //   923: lstore 22
    //   925: aload_3
    //   926: lload 22
    //   928: invokevirtual 279	java/text/DecimalFormat:format	(J)Ljava/lang/String;
    //   931: astore 6
    //   933: getstatic 282	com/google/android/gms/internal/zzbt:zzvP	Lcom/google/android/gms/internal/zzbp;
    //   936: astore_3
    //   937: aload_3
    //   938: invokevirtual 144	com/google/android/gms/internal/zzbp:get	()Ljava/lang/Object;
    //   941: astore_3
    //   942: aload_3
    //   943: checkcast 146	java/lang/Integer
    //   946: astore_3
    //   947: aload_3
    //   948: invokevirtual 149	java/lang/Integer:intValue	()I
    //   951: istore 24
    //   953: iload 20
    //   955: iload 24
    //   957: if_icmple +136 -> 1093
    //   960: new 74	java/lang/StringBuilder
    //   963: astore_3
    //   964: aload_3
    //   965: invokespecial 75	java/lang/StringBuilder:<init>	()V
    //   968: ldc_w 284
    //   971: astore 4
    //   973: aload_3
    //   974: aload 4
    //   976: invokevirtual 81	java/lang/StringBuilder:append	(Ljava/lang/String;)Ljava/lang/StringBuilder;
    //   979: astore_3
    //   980: aload_3
    //   981: aload 6
    //   983: invokevirtual 81	java/lang/StringBuilder:append	(Ljava/lang/String;)Ljava/lang/StringBuilder;
    //   986: astore_3
    //   987: ldc_w 286
    //   990: astore 4
    //   992: aload_3
    //   993: aload 4
    //   995: invokevirtual 81	java/lang/StringBuilder:append	(Ljava/lang/String;)Ljava/lang/StringBuilder;
    //   998: astore_3
    //   999: aload_1
    //   1000: astore_2
    //   1001: aload_3
    //   1002: aload_1
    //   1003: invokevirtual 81	java/lang/StringBuilder:append	(Ljava/lang/String;)Ljava/lang/StringBuilder;
    //   1006: astore_3
    //   1007: aload_3
    //   1008: invokevirtual 88	java/lang/StringBuilder:toString	()Ljava/lang/String;
    //   1011: astore_3
    //   1012: aload_3
    //   1013: invokestatic 56	com/google/android/gms/internal/zzin:zzaK	(Ljava/lang/String;)V
    //   1016: new 74	java/lang/StringBuilder
    //   1019: astore_3
    //   1020: aload_3
    //   1021: invokespecial 75	java/lang/StringBuilder:<init>	()V
    //   1024: ldc_w 288
    //   1027: astore 4
    //   1029: aload_3
    //   1030: aload 4
    //   1032: invokevirtual 81	java/lang/StringBuilder:append	(Ljava/lang/String;)Ljava/lang/StringBuilder;
    //   1035: astore_3
    //   1036: aload_3
    //   1037: aload 6
    //   1039: invokevirtual 81	java/lang/StringBuilder:append	(Ljava/lang/String;)Ljava/lang/StringBuilder;
    //   1042: astore_3
    //   1043: aload_3
    //   1044: invokevirtual 88	java/lang/StringBuilder:toString	()Ljava/lang/String;
    //   1047: astore_3
    //   1048: aload 9
    //   1050: invokevirtual 85	java/io/File:getAbsolutePath	()Ljava/lang/String;
    //   1053: astore 4
    //   1055: ldc_w 290
    //   1058: astore 6
    //   1060: aload_0
    //   1061: astore_2
    //   1062: aload_0
    //   1063: aload_1
    //   1064: aload 4
    //   1066: aload 6
    //   1068: aload_3
    //   1069: invokevirtual 128	com/google/android/gms/internal/zzdu:zza	(Ljava/lang/String;Ljava/lang/String;Ljava/lang/String;Ljava/lang/String;)V
    //   1072: getstatic 26	com/google/android/gms/internal/zzdu:zzzX	Ljava/util/Set;
    //   1075: astore_3
    //   1076: aload_3
    //   1077: aload 13
    //   1079: invokeinterface 268 2 0
    //   1084: pop
    //   1085: iconst_0
    //   1086: istore 7
    //   1088: aconst_null
    //   1089: astore_3
    //   1090: goto -1055 -> 35
    //   1093: new 74	java/lang/StringBuilder
    //   1096: astore_3
    //   1097: aload_3
    //   1098: invokespecial 75	java/lang/StringBuilder:<init>	()V
    //   1101: ldc_w 292
    //   1104: astore 19
    //   1106: aload_3
    //   1107: aload 19
    //   1109: invokevirtual 81	java/lang/StringBuilder:append	(Ljava/lang/String;)Ljava/lang/StringBuilder;
    //   1112: astore_3
    //   1113: aload_3
    //   1114: aload 6
    //   1116: invokevirtual 81	java/lang/StringBuilder:append	(Ljava/lang/String;)Ljava/lang/StringBuilder;
    //   1119: astore_3
    //   1120: ldc_w 294
    //   1123: astore 6
    //   1125: aload_3
    //   1126: aload 6
    //   1128: invokevirtual 81	java/lang/StringBuilder:append	(Ljava/lang/String;)Ljava/lang/StringBuilder;
    //   1131: astore_3
    //   1132: aload_1
    //   1133: astore_2
    //   1134: aload_3
    //   1135: aload_1
    //   1136: invokevirtual 81	java/lang/StringBuilder:append	(Ljava/lang/String;)Ljava/lang/StringBuilder;
    //   1139: astore_3
    //   1140: aload_3
    //   1141: invokevirtual 88	java/lang/StringBuilder:toString	()Ljava/lang/String;
    //   1144: astore_3
    //   1145: aload_3
    //   1146: invokestatic 171	com/google/android/gms/internal/zzin:zzaI	(Ljava/lang/String;)V
    //   1149: aload 4
    //   1151: checkcast 201	java/net/URLConnection
    //   1154: invokevirtual 298	java/net/URLConnection:getInputStream	()Ljava/io/InputStream;
    //   1157: astore_3
    //   1158: aload_3
    //   1159: invokestatic 304	java/nio/channels/Channels:newChannel	(Ljava/io/InputStream;)Ljava/nio/channels/ReadableByteChannel;
    //   1162: astore 25
    //   1164: new 247	java/io/FileOutputStream
    //   1167: astore 26
    //   1169: aload 26
    //   1171: aload 9
    //   1173: invokespecial 307	java/io/FileOutputStream:<init>	(Ljava/io/File;)V
    //   1176: aload 26
    //   1178: invokevirtual 311	java/io/FileOutputStream:getChannel	()Ljava/nio/channels/FileChannel;
    //   1181: astore 27
    //   1183: ldc_w 312
    //   1186: istore 7
    //   1188: iload 7
    //   1190: invokestatic 319	java/nio/ByteBuffer:allocate	(I)Ljava/nio/ByteBuffer;
    //   1193: astore 28
    //   1195: invokestatic 323	com/google/android/gms/ads/internal/zzr:zzbG	()Lcom/google/android/gms/internal/zzmq;
    //   1198: astore 29
    //   1200: iconst_0
    //   1201: istore 14
    //   1203: aconst_null
    //   1204: astore 15
    //   1206: aload 29
    //   1208: invokeinterface 326 1 0
    //   1213: lstore 30
    //   1215: getstatic 329	com/google/android/gms/internal/zzbt:zzvS	Lcom/google/android/gms/internal/zzbp;
    //   1218: astore_3
    //   1219: aload_3
    //   1220: invokevirtual 144	com/google/android/gms/internal/zzbp:get	()Ljava/lang/Object;
    //   1223: astore_3
    //   1224: aload_3
    //   1225: checkcast 331	java/lang/Long
    //   1228: astore_3
    //   1229: aload_3
    //   1230: invokevirtual 334	java/lang/Long:longValue	()J
    //   1233: lstore 11
    //   1235: new 336	com/google/android/gms/internal/zziz
    //   1238: astore 32
    //   1240: aload 32
    //   1242: astore_2
    //   1243: aload 32
    //   1245: lload 11
    //   1247: invokespecial 339	com/google/android/gms/internal/zziz:<init>	(J)V
    //   1250: getstatic 342	com/google/android/gms/internal/zzbt:zzvR	Lcom/google/android/gms/internal/zzbp;
    //   1253: astore_3
    //   1254: aload_3
    //   1255: invokevirtual 144	com/google/android/gms/internal/zzbp:get	()Ljava/lang/Object;
    //   1258: astore_3
    //   1259: aload_3
    //   1260: checkcast 331	java/lang/Long
    //   1263: astore_3
    //   1264: aload_3
    //   1265: invokevirtual 334	java/lang/Long:longValue	()J
    //   1268: lstore 33
    //   1270: aload 28
    //   1272: astore_2
    //   1273: aload 25
    //   1275: aload 28
    //   1277: invokeinterface 348 2 0
    //   1282: istore 7
    //   1284: iload 7
    //   1286: iflt +339 -> 1625
    //   1289: iload 14
    //   1291: iload 7
    //   1293: iadd
    //   1294: istore 14
    //   1296: iload 14
    //   1298: iload 24
    //   1300: if_icmple +73 -> 1373
    //   1303: ldc_w 290
    //   1306: astore 6
    //   1308: new 74	java/lang/StringBuilder
    //   1311: astore_3
    //   1312: aload_3
    //   1313: invokespecial 75	java/lang/StringBuilder:<init>	()V
    //   1316: ldc_w 288
    //   1319: astore 4
    //   1321: aload_3
    //   1322: aload 4
    //   1324: invokevirtual 81	java/lang/StringBuilder:append	(Ljava/lang/String;)Ljava/lang/StringBuilder;
    //   1327: astore_3
    //   1328: iload 14
    //   1330: invokestatic 221	java/lang/Integer:toString	(I)Ljava/lang/String;
    //   1333: astore 4
    //   1335: aload_3
    //   1336: aload 4
    //   1338: invokevirtual 81	java/lang/StringBuilder:append	(Ljava/lang/String;)Ljava/lang/StringBuilder;
    //   1341: astore_3
    //   1342: aload_3
    //   1343: invokevirtual 88	java/lang/StringBuilder:toString	()Ljava/lang/String;
    //   1346: astore 4
    //   1348: new 120	java/io/IOException
    //   1351: astore_3
    //   1352: ldc_w 350
    //   1355: astore 15
    //   1357: aload_3
    //   1358: aload 15
    //   1360: invokespecial 229	java/io/IOException:<init>	(Ljava/lang/String;)V
    //   1363: aload_3
    //   1364: athrow
    //   1365: astore_3
    //   1366: aload 26
    //   1368: astore 15
    //   1370: goto -742 -> 628
    //   1373: aload 28
    //   1375: invokevirtual 354	java/nio/ByteBuffer:flip	()Ljava/nio/Buffer;
    //   1378: pop
    //   1379: aload 27
    //   1381: aload 28
    //   1383: invokevirtual 359	java/nio/channels/FileChannel:write	(Ljava/nio/ByteBuffer;)I
    //   1386: istore 7
    //   1388: iload 7
    //   1390: ifgt -11 -> 1379
    //   1393: aload 28
    //   1395: invokevirtual 362	java/nio/ByteBuffer:clear	()Ljava/nio/Buffer;
    //   1398: pop
    //   1399: aload 29
    //   1401: invokeinterface 326 1 0
    //   1406: lload 30
    //   1408: lsub
    //   1409: lstore 11
    //   1411: ldc2_w 363
    //   1414: lload 33
    //   1416: lmul
    //   1417: lstore 35
    //   1419: lload 11
    //   1421: lload 35
    //   1423: lcmp
    //   1424: istore 7
    //   1426: iload 7
    //   1428: ifle +85 -> 1513
    //   1431: ldc_w 368
    //   1434: astore 6
    //   1436: new 74	java/lang/StringBuilder
    //   1439: astore_3
    //   1440: aload_3
    //   1441: invokespecial 75	java/lang/StringBuilder:<init>	()V
    //   1444: ldc_w 370
    //   1447: astore 4
    //   1449: aload_3
    //   1450: aload 4
    //   1452: invokevirtual 81	java/lang/StringBuilder:append	(Ljava/lang/String;)Ljava/lang/StringBuilder;
    //   1455: astore_3
    //   1456: lload 33
    //   1458: invokestatic 372	java/lang/Long:toString	(J)Ljava/lang/String;
    //   1461: astore 4
    //   1463: aload_3
    //   1464: aload 4
    //   1466: invokevirtual 81	java/lang/StringBuilder:append	(Ljava/lang/String;)Ljava/lang/StringBuilder;
    //   1469: astore_3
    //   1470: ldc_w 374
    //   1473: astore 4
    //   1475: aload_3
    //   1476: aload 4
    //   1478: invokevirtual 81	java/lang/StringBuilder:append	(Ljava/lang/String;)Ljava/lang/StringBuilder;
    //   1481: astore_3
    //   1482: aload_3
    //   1483: invokevirtual 88	java/lang/StringBuilder:toString	()Ljava/lang/String;
    //   1486: astore 4
    //   1488: new 120	java/io/IOException
    //   1491: astore_3
    //   1492: ldc_w 376
    //   1495: astore 15
    //   1497: aload_3
    //   1498: aload 15
    //   1500: invokespecial 229	java/io/IOException:<init>	(Ljava/lang/String;)V
    //   1503: aload_3
    //   1504: athrow
    //   1505: astore_3
    //   1506: aload 26
    //   1508: astore 15
    //   1510: goto -882 -> 628
    //   1513: aload_0
    //   1514: astore_2
    //   1515: aload_0
    //   1516: getfield 122	com/google/android/gms/internal/zzdu:zzAa	Z
    //   1519: istore 7
    //   1521: iload 7
    //   1523: ifeq +39 -> 1562
    //   1526: ldc_w 378
    //   1529: astore 6
    //   1531: new 120	java/io/IOException
    //   1534: astore_3
    //   1535: ldc_w 380
    //   1538: astore 4
    //   1540: aload_3
    //   1541: aload 4
    //   1543: invokespecial 229	java/io/IOException:<init>	(Ljava/lang/String;)V
    //   1546: aload_3
    //   1547: athrow
    //   1548: astore_3
    //   1549: iconst_0
    //   1550: istore 8
    //   1552: aconst_null
    //   1553: astore 4
    //   1555: aload 26
    //   1557: astore 15
    //   1559: goto -931 -> 628
    //   1562: aload 32
    //   1564: invokevirtual 383	com/google/android/gms/internal/zziz:tryAcquire	()Z
    //   1567: istore 7
    //   1569: iload 7
    //   1571: ifeq -301 -> 1270
    //   1574: aload 9
    //   1576: invokevirtual 85	java/io/File:getAbsolutePath	()Ljava/lang/String;
    //   1579: astore 6
    //   1581: iconst_0
    //   1582: istore 21
    //   1584: aconst_null
    //   1585: astore 19
    //   1587: aload_0
    //   1588: astore_3
    //   1589: aload_1
    //   1590: astore 4
    //   1592: aload_0
    //   1593: aload_1
    //   1594: aload 6
    //   1596: iload 14
    //   1598: iload 20
    //   1600: iconst_0
    //   1601: invokevirtual 386	com/google/android/gms/internal/zzdu:zza	(Ljava/lang/String;Ljava/lang/String;IIZ)V
    //   1604: goto -334 -> 1270
    //   1607: astore_3
    //   1608: iconst_0
    //   1609: istore 8
    //   1611: aconst_null
    //   1612: astore 4
    //   1614: aload 16
    //   1616: astore 6
    //   1618: aload 26
    //   1620: astore 15
    //   1622: goto -994 -> 628
    //   1625: aload 26
    //   1627: invokevirtual 250	java/io/FileOutputStream:close	()V
    //   1630: iconst_3
    //   1631: istore 7
    //   1633: iload 7
    //   1635: invokestatic 391	com/google/android/gms/internal/zzin:zzQ	(I)Z
    //   1638: istore 7
    //   1640: iload 7
    //   1642: ifeq +79 -> 1721
    //   1645: getstatic 35	com/google/android/gms/internal/zzdu:zzzY	Ljava/text/DecimalFormat;
    //   1648: astore_3
    //   1649: iload 14
    //   1651: i2l
    //   1652: lstore 37
    //   1654: aload_3
    //   1655: lload 37
    //   1657: invokevirtual 279	java/text/DecimalFormat:format	(J)Ljava/lang/String;
    //   1660: astore_3
    //   1661: new 74	java/lang/StringBuilder
    //   1664: astore 4
    //   1666: aload 4
    //   1668: invokespecial 75	java/lang/StringBuilder:<init>	()V
    //   1671: ldc_w 393
    //   1674: astore 6
    //   1676: aload 4
    //   1678: aload 6
    //   1680: invokevirtual 81	java/lang/StringBuilder:append	(Ljava/lang/String;)Ljava/lang/StringBuilder;
    //   1683: astore 4
    //   1685: aload 4
    //   1687: aload_3
    //   1688: invokevirtual 81	java/lang/StringBuilder:append	(Ljava/lang/String;)Ljava/lang/StringBuilder;
    //   1691: astore_3
    //   1692: ldc_w 294
    //   1695: astore 4
    //   1697: aload_3
    //   1698: aload 4
    //   1700: invokevirtual 81	java/lang/StringBuilder:append	(Ljava/lang/String;)Ljava/lang/StringBuilder;
    //   1703: astore_3
    //   1704: aload_1
    //   1705: astore_2
    //   1706: aload_3
    //   1707: aload_1
    //   1708: invokevirtual 81	java/lang/StringBuilder:append	(Ljava/lang/String;)Ljava/lang/StringBuilder;
    //   1711: astore_3
    //   1712: aload_3
    //   1713: invokevirtual 88	java/lang/StringBuilder:toString	()Ljava/lang/String;
    //   1716: astore_3
    //   1717: aload_3
    //   1718: invokestatic 171	com/google/android/gms/internal/zzin:zzaI	(Ljava/lang/String;)V
    //   1721: iconst_1
    //   1722: istore 7
    //   1724: iconst_0
    //   1725: istore 8
    //   1727: aconst_null
    //   1728: astore 4
    //   1730: aload 9
    //   1732: iload 7
    //   1734: iconst_0
    //   1735: invokevirtual 92	java/io/File:setReadable	(ZZ)Z
    //   1738: pop
    //   1739: aload 10
    //   1741: invokestatic 395	com/google/android/gms/internal/zzdu:zzb	(Ljava/io/File;)V
    //   1744: aload 9
    //   1746: invokevirtual 85	java/io/File:getAbsolutePath	()Ljava/lang/String;
    //   1749: astore_3
    //   1750: aload_0
    //   1751: astore_2
    //   1752: aload_0
    //   1753: aload_1
    //   1754: aload_3
    //   1755: iload 14
    //   1757: invokevirtual 174	com/google/android/gms/internal/zzdu:zza	(Ljava/lang/String;Ljava/lang/String;I)V
    //   1760: getstatic 26	com/google/android/gms/internal/zzdu:zzzX	Ljava/util/Set;
    //   1763: astore_3
    //   1764: aload_3
    //   1765: aload 13
    //   1767: invokeinterface 268 2 0
    //   1772: pop
    //   1773: iconst_1
    //   1774: istore 7
    //   1776: goto -1741 -> 35
    //   1779: new 74	java/lang/StringBuilder
    //   1782: astore 15
    //   1784: aload 15
    //   1786: invokespecial 75	java/lang/StringBuilder:<init>	()V
    //   1789: aload 15
    //   1791: ldc_w 397
    //   1794: invokevirtual 81	java/lang/StringBuilder:append	(Ljava/lang/String;)Ljava/lang/StringBuilder;
    //   1797: astore 15
    //   1799: aload_1
    //   1800: astore_2
    //   1801: aload 15
    //   1803: aload_1
    //   1804: invokevirtual 81	java/lang/StringBuilder:append	(Ljava/lang/String;)Ljava/lang/StringBuilder;
    //   1807: astore 15
    //   1809: ldc -2
    //   1811: astore 18
    //   1813: aload 15
    //   1815: aload 18
    //   1817: invokevirtual 81	java/lang/StringBuilder:append	(Ljava/lang/String;)Ljava/lang/StringBuilder;
    //   1820: invokevirtual 88	java/lang/StringBuilder:toString	()Ljava/lang/String;
    //   1823: astore 15
    //   1825: aload 15
    //   1827: aload_3
    //   1828: checkcast 239	java/lang/Throwable
    //   1831: invokestatic 401	com/google/android/gms/internal/zzin:zzd	(Ljava/lang/String;Ljava/lang/Throwable;)V
    //   1834: goto -1117 -> 717
    //   1837: astore 15
    //   1839: goto -1176 -> 663
    //   1842: astore 15
    //   1844: goto -1181 -> 663
    //   1847: astore_3
    //   1848: iconst_0
    //   1849: istore 8
    //   1851: aconst_null
    //   1852: astore 4
    //   1854: aload 16
    //   1856: astore 6
    //   1858: goto -1230 -> 628
    //   1861: astore_3
    //   1862: iconst_0
    //   1863: istore 8
    //   1865: aconst_null
    //   1866: astore 4
    //   1868: goto -1240 -> 628
    //   1871: astore_3
    //   1872: goto -1244 -> 628
    //   1875: astore_3
    //   1876: iconst_0
    //   1877: istore 8
    //   1879: aconst_null
    //   1880: astore 4
    //   1882: aload 16
    //   1884: astore 6
    //   1886: aload 26
    //   1888: astore 15
    //   1890: goto -1262 -> 628
    //   1893: astore_3
    //   1894: iconst_0
    //   1895: istore 8
    //   1897: aconst_null
    //   1898: astore 4
    //   1900: aload 26
    //   1902: astore 15
    //   1904: goto -1276 -> 628
    //   1907: astore_3
    //   1908: iconst_0
    //   1909: istore 8
    //   1911: aconst_null
    //   1912: astore 4
    //   1914: aload 16
    //   1916: astore 6
    //   1918: goto -1290 -> 628
    //   1921: astore_3
    //   1922: iconst_0
    //   1923: istore 8
    //   1925: aconst_null
    //   1926: astore 4
    //   1928: goto -1300 -> 628
    // Local variable table:
    //   start	length	slot	name	signature
    //   0	1931	0	this	zzdu
    //   0	1931	1	paramString	String
    //   1	1800	2	localObject1	Object
    //   6	371	3	localObject2	Object
    //   383	5	3	localObject3	Object
    //   392	229	3	localObject4	Object
    //   627	23	3	localIOException1	IOException
    //   679	685	3	localObject5	Object
    //   1365	1	3	localIOException2	IOException
    //   1439	65	3	localObject6	Object
    //   1505	1	3	localRuntimeException1	RuntimeException
    //   1534	13	3	localIOException3	IOException
    //   1548	1	3	localIOException4	IOException
    //   1588	1	3	localzzdu	zzdu
    //   1607	1	3	localIOException5	IOException
    //   1648	180	3	localObject7	Object
    //   1847	1	3	localRuntimeException2	RuntimeException
    //   1861	1	3	localRuntimeException3	RuntimeException
    //   1871	1	3	localRuntimeException4	RuntimeException
    //   1875	1	3	localRuntimeException5	RuntimeException
    //   1893	1	3	localRuntimeException6	RuntimeException
    //   1907	1	3	localIOException6	IOException
    //   1921	1	3	localIOException7	IOException
    //   13	1914	4	localObject8	Object
    //   16	864	5	i	int
    //   19	1898	6	localObject9	Object
    //   31	5	7	bool1	boolean
    //   58	7	7	j	int
    //   71	96	7	bool2	boolean
    //   181	59	7	k	int
    //   304	70	7	bool3	boolean
    //   451	12	7	m	int
    //   472	3	7	bool4	boolean
    //   494	95	7	n	int
    //   722	365	7	bool5	boolean
    //   1186	203	7	i1	int
    //   1424	146	7	bool6	boolean
    //   1631	3	7	i2	int
    //   1638	137	7	bool7	boolean
    //   42	1882	8	i3	int
    //   121	1624	9	localFile1	File
    //   145	1595	10	localFile2	File
    //   176	1244	11	l1	long
    //   282	1484	13	str1	String
    //   356	938	14	i4	int
    //   1294	462	14	i5	int
    //   359	1467	15	localObject10	Object
    //   1837	1	15	localIOException8	IOException
    //   1842	1	15	localNullPointerException	NullPointerException
    //   1888	15	15	localObject11	Object
    //   413	1502	16	str2	String
    //   416	164	17	str3	String
    //   524	1292	18	localObject12	Object
    //   566	1020	19	localObject13	Object
    //   632	3	20	bool8	boolean
    //   823	776	20	i6	int
    //   645	938	21	bool9	boolean
    //   923	4	22	l2	long
    //   951	350	24	i7	int
    //   1162	112	25	localReadableByteChannel	java.nio.channels.ReadableByteChannel
    //   1167	734	26	localFileOutputStream	java.io.FileOutputStream
    //   1181	199	27	localFileChannel	java.nio.channels.FileChannel
    //   1193	201	28	localByteBuffer	java.nio.ByteBuffer
    //   1198	202	29	localzzmq	zzmq
    //   1213	194	30	l3	long
    //   1238	325	32	localzziz	zziz
    //   1268	189	33	l4	long
    //   1417	5	35	l5	long
    //   1652	4	37	l6	long
    // Exception table:
    //   from	to	target	type
    //   292	295	383	finally
    //   297	304	383	finally
    //   311	314	383	finally
    //   315	319	383	finally
    //   324	329	383	finally
    //   331	335	383	finally
    //   336	340	383	finally
    //   341	345	383	finally
    //   345	350	383	finally
    //   368	372	383	finally
    //   377	380	383	finally
    //   384	387	383	finally
    //   389	392	383	finally
    //   394	402	383	finally
    //   402	405	383	finally
    //   558	561	627	java/io/IOException
    //   563	566	627	java/io/IOException
    //   568	573	627	java/io/IOException
    //   579	584	627	java/io/IOException
    //   588	593	627	java/io/IOException
    //   599	604	627	java/io/IOException
    //   608	612	627	java/io/IOException
    //   613	617	627	java/io/IOException
    //   620	624	627	java/io/IOException
    //   624	627	627	java/io/IOException
    //   1348	1351	1365	java/io/IOException
    //   1358	1363	1365	java/io/IOException
    //   1363	1365	1365	java/io/IOException
    //   1488	1491	1365	java/io/IOException
    //   1498	1503	1365	java/io/IOException
    //   1503	1505	1365	java/io/IOException
    //   1348	1351	1505	java/lang/RuntimeException
    //   1358	1363	1505	java/lang/RuntimeException
    //   1363	1365	1505	java/lang/RuntimeException
    //   1488	1491	1505	java/lang/RuntimeException
    //   1498	1503	1505	java/lang/RuntimeException
    //   1503	1505	1505	java/lang/RuntimeException
    //   1308	1311	1548	java/io/IOException
    //   1312	1316	1548	java/io/IOException
    //   1322	1327	1548	java/io/IOException
    //   1328	1333	1548	java/io/IOException
    //   1336	1341	1548	java/io/IOException
    //   1342	1346	1548	java/io/IOException
    //   1436	1439	1548	java/io/IOException
    //   1440	1444	1548	java/io/IOException
    //   1450	1455	1548	java/io/IOException
    //   1456	1461	1548	java/io/IOException
    //   1464	1469	1548	java/io/IOException
    //   1476	1481	1548	java/io/IOException
    //   1482	1486	1548	java/io/IOException
    //   1531	1534	1548	java/io/IOException
    //   1541	1546	1548	java/io/IOException
    //   1546	1548	1548	java/io/IOException
    //   1176	1181	1607	java/io/IOException
    //   1188	1193	1607	java/io/IOException
    //   1195	1198	1607	java/io/IOException
    //   1206	1213	1607	java/io/IOException
    //   1215	1218	1607	java/io/IOException
    //   1219	1223	1607	java/io/IOException
    //   1224	1228	1607	java/io/IOException
    //   1229	1233	1607	java/io/IOException
    //   1235	1238	1607	java/io/IOException
    //   1245	1250	1607	java/io/IOException
    //   1250	1253	1607	java/io/IOException
    //   1254	1258	1607	java/io/IOException
    //   1259	1263	1607	java/io/IOException
    //   1264	1268	1607	java/io/IOException
    //   1275	1282	1607	java/io/IOException
    //   1373	1379	1607	java/io/IOException
    //   1381	1386	1607	java/io/IOException
    //   1393	1399	1607	java/io/IOException
    //   1399	1406	1607	java/io/IOException
    //   1515	1519	1607	java/io/IOException
    //   1562	1567	1607	java/io/IOException
    //   1574	1579	1607	java/io/IOException
    //   1600	1604	1607	java/io/IOException
    //   1625	1630	1607	java/io/IOException
    //   1633	1638	1607	java/io/IOException
    //   1645	1648	1607	java/io/IOException
    //   1655	1660	1607	java/io/IOException
    //   1661	1664	1607	java/io/IOException
    //   1666	1671	1607	java/io/IOException
    //   1678	1683	1607	java/io/IOException
    //   1687	1691	1607	java/io/IOException
    //   1698	1703	1607	java/io/IOException
    //   1707	1711	1607	java/io/IOException
    //   1712	1716	1607	java/io/IOException
    //   1717	1721	1607	java/io/IOException
    //   1734	1739	1607	java/io/IOException
    //   1739	1744	1607	java/io/IOException
    //   1744	1749	1607	java/io/IOException
    //   1755	1760	1607	java/io/IOException
    //   1760	1763	1607	java/io/IOException
    //   1765	1773	1607	java/io/IOException
    //   658	663	1837	java/io/IOException
    //   658	663	1842	java/lang/NullPointerException
    //   418	421	1847	java/lang/RuntimeException
    //   423	427	1847	java/lang/RuntimeException
    //   427	431	1847	java/lang/RuntimeException
    //   433	436	1847	java/lang/RuntimeException
    //   437	441	1847	java/lang/RuntimeException
    //   442	446	1847	java/lang/RuntimeException
    //   447	451	1847	java/lang/RuntimeException
    //   455	460	1847	java/lang/RuntimeException
    //   462	467	1847	java/lang/RuntimeException
    //   482	487	1847	java/lang/RuntimeException
    //   490	494	1847	java/lang/RuntimeException
    //   815	823	1847	java/lang/RuntimeException
    //   830	833	1847	java/lang/RuntimeException
    //   834	838	1847	java/lang/RuntimeException
    //   844	849	1847	java/lang/RuntimeException
    //   853	857	1847	java/lang/RuntimeException
    //   858	862	1847	java/lang/RuntimeException
    //   863	867	1847	java/lang/RuntimeException
    //   867	872	1847	java/lang/RuntimeException
    //   891	895	1847	java/lang/RuntimeException
    //   895	898	1847	java/lang/RuntimeException
    //   900	908	1847	java/lang/RuntimeException
    //   916	919	1847	java/lang/RuntimeException
    //   926	931	1847	java/lang/RuntimeException
    //   933	936	1847	java/lang/RuntimeException
    //   937	941	1847	java/lang/RuntimeException
    //   942	946	1847	java/lang/RuntimeException
    //   947	951	1847	java/lang/RuntimeException
    //   960	963	1847	java/lang/RuntimeException
    //   964	968	1847	java/lang/RuntimeException
    //   974	979	1847	java/lang/RuntimeException
    //   981	986	1847	java/lang/RuntimeException
    //   993	998	1847	java/lang/RuntimeException
    //   1002	1006	1847	java/lang/RuntimeException
    //   1007	1011	1847	java/lang/RuntimeException
    //   1012	1016	1847	java/lang/RuntimeException
    //   1016	1019	1847	java/lang/RuntimeException
    //   1020	1024	1847	java/lang/RuntimeException
    //   1030	1035	1847	java/lang/RuntimeException
    //   1037	1042	1847	java/lang/RuntimeException
    //   1043	1047	1847	java/lang/RuntimeException
    //   1048	1053	1847	java/lang/RuntimeException
    //   1068	1072	1847	java/lang/RuntimeException
    //   1072	1075	1847	java/lang/RuntimeException
    //   1077	1085	1847	java/lang/RuntimeException
    //   1093	1096	1847	java/lang/RuntimeException
    //   1097	1101	1847	java/lang/RuntimeException
    //   1107	1112	1847	java/lang/RuntimeException
    //   1114	1119	1847	java/lang/RuntimeException
    //   1126	1131	1847	java/lang/RuntimeException
    //   1135	1139	1847	java/lang/RuntimeException
    //   1140	1144	1847	java/lang/RuntimeException
    //   1145	1149	1847	java/lang/RuntimeException
    //   1149	1157	1847	java/lang/RuntimeException
    //   1158	1162	1847	java/lang/RuntimeException
    //   1164	1167	1847	java/lang/RuntimeException
    //   1171	1176	1847	java/lang/RuntimeException
    //   512	515	1861	java/lang/RuntimeException
    //   517	522	1861	java/lang/RuntimeException
    //   528	533	1861	java/lang/RuntimeException
    //   535	540	1861	java/lang/RuntimeException
    //   544	549	1861	java/lang/RuntimeException
    //   551	556	1861	java/lang/RuntimeException
    //   558	561	1871	java/lang/RuntimeException
    //   563	566	1871	java/lang/RuntimeException
    //   568	573	1871	java/lang/RuntimeException
    //   579	584	1871	java/lang/RuntimeException
    //   588	593	1871	java/lang/RuntimeException
    //   599	604	1871	java/lang/RuntimeException
    //   608	612	1871	java/lang/RuntimeException
    //   613	617	1871	java/lang/RuntimeException
    //   620	624	1871	java/lang/RuntimeException
    //   624	627	1871	java/lang/RuntimeException
    //   1176	1181	1875	java/lang/RuntimeException
    //   1188	1193	1875	java/lang/RuntimeException
    //   1195	1198	1875	java/lang/RuntimeException
    //   1206	1213	1875	java/lang/RuntimeException
    //   1215	1218	1875	java/lang/RuntimeException
    //   1219	1223	1875	java/lang/RuntimeException
    //   1224	1228	1875	java/lang/RuntimeException
    //   1229	1233	1875	java/lang/RuntimeException
    //   1235	1238	1875	java/lang/RuntimeException
    //   1245	1250	1875	java/lang/RuntimeException
    //   1250	1253	1875	java/lang/RuntimeException
    //   1254	1258	1875	java/lang/RuntimeException
    //   1259	1263	1875	java/lang/RuntimeException
    //   1264	1268	1875	java/lang/RuntimeException
    //   1275	1282	1875	java/lang/RuntimeException
    //   1373	1379	1875	java/lang/RuntimeException
    //   1381	1386	1875	java/lang/RuntimeException
    //   1393	1399	1875	java/lang/RuntimeException
    //   1399	1406	1875	java/lang/RuntimeException
    //   1515	1519	1875	java/lang/RuntimeException
    //   1562	1567	1875	java/lang/RuntimeException
    //   1574	1579	1875	java/lang/RuntimeException
    //   1600	1604	1875	java/lang/RuntimeException
    //   1625	1630	1875	java/lang/RuntimeException
    //   1633	1638	1875	java/lang/RuntimeException
    //   1645	1648	1875	java/lang/RuntimeException
    //   1655	1660	1875	java/lang/RuntimeException
    //   1661	1664	1875	java/lang/RuntimeException
    //   1666	1671	1875	java/lang/RuntimeException
    //   1678	1683	1875	java/lang/RuntimeException
    //   1687	1691	1875	java/lang/RuntimeException
    //   1698	1703	1875	java/lang/RuntimeException
    //   1707	1711	1875	java/lang/RuntimeException
    //   1712	1716	1875	java/lang/RuntimeException
    //   1717	1721	1875	java/lang/RuntimeException
    //   1734	1739	1875	java/lang/RuntimeException
    //   1739	1744	1875	java/lang/RuntimeException
    //   1744	1749	1875	java/lang/RuntimeException
    //   1755	1760	1875	java/lang/RuntimeException
    //   1760	1763	1875	java/lang/RuntimeException
    //   1765	1773	1875	java/lang/RuntimeException
    //   1308	1311	1893	java/lang/RuntimeException
    //   1312	1316	1893	java/lang/RuntimeException
    //   1322	1327	1893	java/lang/RuntimeException
    //   1328	1333	1893	java/lang/RuntimeException
    //   1336	1341	1893	java/lang/RuntimeException
    //   1342	1346	1893	java/lang/RuntimeException
    //   1436	1439	1893	java/lang/RuntimeException
    //   1440	1444	1893	java/lang/RuntimeException
    //   1450	1455	1893	java/lang/RuntimeException
    //   1456	1461	1893	java/lang/RuntimeException
    //   1464	1469	1893	java/lang/RuntimeException
    //   1476	1481	1893	java/lang/RuntimeException
    //   1482	1486	1893	java/lang/RuntimeException
    //   1531	1534	1893	java/lang/RuntimeException
    //   1541	1546	1893	java/lang/RuntimeException
    //   1546	1548	1893	java/lang/RuntimeException
    //   418	421	1907	java/io/IOException
    //   423	427	1907	java/io/IOException
    //   427	431	1907	java/io/IOException
    //   433	436	1907	java/io/IOException
    //   437	441	1907	java/io/IOException
    //   442	446	1907	java/io/IOException
    //   447	451	1907	java/io/IOException
    //   455	460	1907	java/io/IOException
    //   462	467	1907	java/io/IOException
    //   482	487	1907	java/io/IOException
    //   490	494	1907	java/io/IOException
    //   815	823	1907	java/io/IOException
    //   830	833	1907	java/io/IOException
    //   834	838	1907	java/io/IOException
    //   844	849	1907	java/io/IOException
    //   853	857	1907	java/io/IOException
    //   858	862	1907	java/io/IOException
    //   863	867	1907	java/io/IOException
    //   867	872	1907	java/io/IOException
    //   891	895	1907	java/io/IOException
    //   895	898	1907	java/io/IOException
    //   900	908	1907	java/io/IOException
    //   916	919	1907	java/io/IOException
    //   926	931	1907	java/io/IOException
    //   933	936	1907	java/io/IOException
    //   937	941	1907	java/io/IOException
    //   942	946	1907	java/io/IOException
    //   947	951	1907	java/io/IOException
    //   960	963	1907	java/io/IOException
    //   964	968	1907	java/io/IOException
    //   974	979	1907	java/io/IOException
    //   981	986	1907	java/io/IOException
    //   993	998	1907	java/io/IOException
    //   1002	1006	1907	java/io/IOException
    //   1007	1011	1907	java/io/IOException
    //   1012	1016	1907	java/io/IOException
    //   1016	1019	1907	java/io/IOException
    //   1020	1024	1907	java/io/IOException
    //   1030	1035	1907	java/io/IOException
    //   1037	1042	1907	java/io/IOException
    //   1043	1047	1907	java/io/IOException
    //   1048	1053	1907	java/io/IOException
    //   1068	1072	1907	java/io/IOException
    //   1072	1075	1907	java/io/IOException
    //   1077	1085	1907	java/io/IOException
    //   1093	1096	1907	java/io/IOException
    //   1097	1101	1907	java/io/IOException
    //   1107	1112	1907	java/io/IOException
    //   1114	1119	1907	java/io/IOException
    //   1126	1131	1907	java/io/IOException
    //   1135	1139	1907	java/io/IOException
    //   1140	1144	1907	java/io/IOException
    //   1145	1149	1907	java/io/IOException
    //   1149	1157	1907	java/io/IOException
    //   1158	1162	1907	java/io/IOException
    //   1164	1167	1907	java/io/IOException
    //   1171	1176	1907	java/io/IOException
    //   512	515	1921	java/io/IOException
    //   517	522	1921	java/io/IOException
    //   528	533	1921	java/io/IOException
    //   535	540	1921	java/io/IOException
    //   544	549	1921	java/io/IOException
    //   551	556	1921	java/io/IOException
  }
  
  public int zzea()
  {
    int i = 0;
    File localFile = this.zzzZ;
    if (localFile == null) {}
    for (;;)
    {
      return i;
      File[] arrayOfFile = this.zzzZ.listFiles();
      int j = arrayOfFile.length;
      int k = 0;
      localFile = null;
      while (k < j)
      {
        String str1 = arrayOfFile[k].getName();
        String str2 = ".done";
        boolean bool = str1.endsWith(str2);
        if (!bool) {
          i += 1;
        }
        k += 1;
      }
    }
  }
  
  public boolean zzeb()
  {
    boolean bool1 = false;
    Object localObject1 = this.zzzZ;
    if (localObject1 == null) {
      return bool1;
    }
    Object localObject2 = null;
    long l1 = Long.MAX_VALUE;
    localObject1 = this.zzzZ;
    File[] arrayOfFile = ((File)localObject1).listFiles();
    int i = arrayOfFile.length;
    int j = 0;
    label39:
    File localFile;
    Object localObject3;
    boolean bool2;
    long l2;
    if (j < i)
    {
      localFile = arrayOfFile[j];
      localObject1 = localFile.getName();
      localObject3 = ".done";
      bool2 = ((String)localObject1).endsWith((String)localObject3);
      if (bool2) {
        break label176;
      }
      l2 = localFile.lastModified();
      boolean bool3 = l2 < l1;
      if (!bool3) {
        break label176;
      }
    }
    for (Object localObject4 = localFile;; localObject4 = localObject2)
    {
      int k = j + 1;
      j = k;
      localObject2 = localObject4;
      l1 = l2;
      break label39;
      if (localObject2 != null)
      {
        bool2 = ((File)localObject2).delete();
        localObject3 = zza((File)localObject2);
        boolean bool4 = ((File)localObject3).isFile();
        if (bool4)
        {
          boolean bool5 = ((File)localObject3).delete();
          bool2 &= bool5;
        }
      }
      for (;;)
      {
        bool1 = bool2;
        break;
        bool2 = false;
        localObject1 = null;
      }
      label176:
      l2 = l1;
    }
  }
}


/* Location:              C:\Users\haryo\Desktop\enjarify-master\presensi-enjarify.jar!\com\google\android\gms\internal\zzdu.class
 * Java compiler version: 5 (49.0)
 * JD-Core Version:       0.7.1
 */