package com.google.android.gms.internal;

import android.content.Context;
import android.os.Handler;
import com.google.android.gms.ads.internal.client.AdRequestParcel;
import com.google.android.gms.ads.internal.client.AdSizeParcel;
import com.google.android.gms.ads.internal.formats.NativeAdOptionsParcel;
import com.google.android.gms.ads.internal.request.AdRequestInfoParcel;
import com.google.android.gms.ads.internal.util.client.VersionInfoParcel;
import java.util.ArrayList;
import java.util.Collection;
import java.util.HashMap;
import java.util.Iterator;
import java.util.List;
import java.util.Map;
import java.util.concurrent.Callable;
import java.util.concurrent.ExecutionException;
import java.util.concurrent.ExecutorService;
import java.util.concurrent.Executors;

public class zzeu
  implements zzem
{
  private final Context mContext;
  private final zzeo zzCf;
  private final AdRequestInfoParcel zzCu;
  private final long zzCv;
  private final long zzCw;
  private final int zzCx;
  private boolean zzCy;
  private final Map zzCz;
  private final Object zzpV;
  private final zzex zzpn;
  private final boolean zzsA;
  private final boolean zzuS;
  
  public zzeu(Context paramContext, AdRequestInfoParcel paramAdRequestInfoParcel, zzex paramzzex, zzeo paramzzeo, boolean paramBoolean1, boolean paramBoolean2, long paramLong1, long paramLong2, int paramInt)
  {
    Object localObject = new java/lang/Object;
    localObject.<init>();
    this.zzpV = localObject;
    this.zzCy = false;
    localObject = new java/util/HashMap;
    ((HashMap)localObject).<init>();
    this.zzCz = ((Map)localObject);
    this.mContext = paramContext;
    this.zzCu = paramAdRequestInfoParcel;
    this.zzpn = paramzzex;
    this.zzCf = paramzzeo;
    this.zzsA = paramBoolean1;
    this.zzuS = paramBoolean2;
    this.zzCv = paramLong1;
    this.zzCw = paramLong2;
    this.zzCx = paramInt;
  }
  
  private void zza(zzjg paramzzjg)
  {
    Handler localHandler = zzir.zzMc;
    zzeu.2 local2 = new com/google/android/gms/internal/zzeu$2;
    local2.<init>(this, paramzzjg);
    localHandler.post(local2);
  }
  
  private zzes zzd(List paramList)
  {
    for (;;)
    {
      Object localObject2;
      int j;
      zzjg localzzjg;
      synchronized (this.zzpV)
      {
        boolean bool = this.zzCy;
        if (bool)
        {
          localObject2 = new com/google/android/gms/internal/zzes;
          int i = -1;
          ((zzes)localObject2).<init>(i);
          return (zzes)localObject2;
        }
        ??? = paramList.iterator();
        j = ((Iterator)???).hasNext();
        if (j != 0) {
          localzzjg = (zzjg)((Iterator)???).next();
        }
      }
      try
      {
        localObject2 = localzzjg.get();
        localObject2 = (zzes)localObject2;
        if (localObject2 == null) {
          continue;
        }
        int k = ((zzes)localObject2).zzCo;
        if (k != 0) {
          continue;
        }
        zza(localzzjg);
      }
      catch (InterruptedException localInterruptedException)
      {
        localObject2 = "Exception while processing an adapter; continuing with other adapters";
        zzin.zzd((String)localObject2, localInterruptedException);
        continue;
        localObject3 = finally;
        throw ((Throwable)localObject3);
        Object localObject4 = null;
        zza(null);
        localObject2 = new com/google/android/gms/internal/zzes;
        j = 1;
        ((zzes)localObject2).<init>(j);
      }
      catch (ExecutionException localExecutionException)
      {
        for (;;) {}
      }
    }
  }
  
  /* Error */
  private zzes zze(List paramList)
  {
    // Byte code:
    //   0: aload_0
    //   1: getfield 33	com/google/android/gms/internal/zzeu:zzpV	Ljava/lang/Object;
    //   4: astore_2
    //   5: aload_2
    //   6: monitorenter
    //   7: aload_0
    //   8: getfield 35	com/google/android/gms/internal/zzeu:zzCy	Z
    //   11: istore_3
    //   12: iload_3
    //   13: ifeq +21 -> 34
    //   16: new 77	com/google/android/gms/internal/zzes
    //   19: astore 4
    //   21: iconst_m1
    //   22: istore_3
    //   23: aload 4
    //   25: iload_3
    //   26: invokespecial 80	com/google/android/gms/internal/zzes:<init>	(I)V
    //   29: aload_2
    //   30: monitorexit
    //   31: aload 4
    //   33: areturn
    //   34: aload_2
    //   35: monitorexit
    //   36: iconst_m1
    //   37: istore 5
    //   39: aconst_null
    //   40: astore 6
    //   42: iconst_0
    //   43: istore 7
    //   45: aconst_null
    //   46: astore 4
    //   48: aload_0
    //   49: getfield 48	com/google/android/gms/internal/zzeu:zzCf	Lcom/google/android/gms/internal/zzeo;
    //   52: astore 8
    //   54: aload 8
    //   56: getfield 126	com/google/android/gms/internal/zzeo:zzBY	J
    //   59: lstore 9
    //   61: iconst_m1
    //   62: i2l
    //   63: lstore 11
    //   65: lload 9
    //   67: lload 11
    //   69: lcmp
    //   70: istore_3
    //   71: iload_3
    //   72: ifeq +232 -> 304
    //   75: aload_0
    //   76: getfield 48	com/google/android/gms/internal/zzeu:zzCf	Lcom/google/android/gms/internal/zzeo;
    //   79: astore 8
    //   81: aload 8
    //   83: getfield 126	com/google/android/gms/internal/zzeo:zzBY	J
    //   86: lstore 9
    //   88: aload_1
    //   89: invokeinterface 86 1 0
    //   94: astore 13
    //   96: lload 9
    //   98: lstore 11
    //   100: aload 13
    //   102: invokeinterface 92 1 0
    //   107: istore_3
    //   108: iload_3
    //   109: ifeq +304 -> 413
    //   112: aload 13
    //   114: invokeinterface 96 1 0
    //   119: checkcast 98	com/google/android/gms/internal/zzjg
    //   122: astore 8
    //   124: invokestatic 132	com/google/android/gms/ads/internal/zzr:zzbG	()Lcom/google/android/gms/internal/zzmq;
    //   127: astore_2
    //   128: aload_2
    //   129: invokeinterface 138 1 0
    //   134: lstore 14
    //   136: lconst_0
    //   137: lstore 16
    //   139: lload 11
    //   141: lload 16
    //   143: lcmp
    //   144: istore 18
    //   146: iload 18
    //   148: ifne +164 -> 312
    //   151: aload 8
    //   153: invokeinterface 141 1 0
    //   158: istore 18
    //   160: iload 18
    //   162: ifeq +150 -> 312
    //   165: aload 8
    //   167: invokeinterface 101 1 0
    //   172: astore_2
    //   173: aload_2
    //   174: checkcast 77	com/google/android/gms/internal/zzes
    //   177: astore_2
    //   178: aload_2
    //   179: ifnull +276 -> 455
    //   182: aload_2
    //   183: getfield 104	com/google/android/gms/internal/zzes:zzCo	I
    //   186: istore 19
    //   188: iload 19
    //   190: ifne +265 -> 455
    //   193: aload_2
    //   194: getfield 145	com/google/android/gms/internal/zzes:zzCt	Lcom/google/android/gms/internal/zzfa;
    //   197: astore 20
    //   199: aload 20
    //   201: ifnull +254 -> 455
    //   204: aload 20
    //   206: invokeinterface 151 1 0
    //   211: istore 21
    //   213: iload 21
    //   215: iload 5
    //   217: if_icmple +238 -> 455
    //   220: aload 20
    //   222: invokeinterface 151 1 0
    //   227: istore 7
    //   229: aload_2
    //   230: astore 22
    //   232: aload 8
    //   234: astore_2
    //   235: aload 22
    //   237: astore 8
    //   239: invokestatic 132	com/google/android/gms/ads/internal/zzr:zzbG	()Lcom/google/android/gms/internal/zzmq;
    //   242: invokeinterface 138 1 0
    //   247: lload 14
    //   249: lsub
    //   250: lstore 23
    //   252: lload 11
    //   254: lload 23
    //   256: lsub
    //   257: lstore 23
    //   259: lconst_0
    //   260: lstore 11
    //   262: lload 23
    //   264: lload 11
    //   266: invokestatic 157	java/lang/Math:max	(JJ)J
    //   269: lstore 23
    //   271: aload_2
    //   272: astore 6
    //   274: aload 8
    //   276: astore 22
    //   278: lload 23
    //   280: lstore 9
    //   282: iload 7
    //   284: istore 5
    //   286: aload 8
    //   288: astore 4
    //   290: lload 9
    //   292: lstore 11
    //   294: goto -194 -> 100
    //   297: astore 8
    //   299: aload_2
    //   300: monitorexit
    //   301: aload 8
    //   303: athrow
    //   304: ldc2_w 158
    //   307: lstore 9
    //   309: goto -221 -> 88
    //   312: getstatic 167	java/util/concurrent/TimeUnit:MILLISECONDS	Ljava/util/concurrent/TimeUnit;
    //   315: astore_2
    //   316: aload 8
    //   318: lload 11
    //   320: aload_2
    //   321: invokeinterface 170 4 0
    //   326: astore_2
    //   327: aload_2
    //   328: checkcast 77	com/google/android/gms/internal/zzes
    //   331: astore_2
    //   332: goto -154 -> 178
    //   335: astore 8
    //   337: ldc 110
    //   339: astore_2
    //   340: aload_2
    //   341: aload 8
    //   343: invokestatic 116	com/google/android/gms/internal/zzin:zzd	(Ljava/lang/String;Ljava/lang/Throwable;)V
    //   346: invokestatic 132	com/google/android/gms/ads/internal/zzr:zzbG	()Lcom/google/android/gms/internal/zzmq;
    //   349: astore 8
    //   351: aload 8
    //   353: invokeinterface 138 1 0
    //   358: lload 14
    //   360: lsub
    //   361: lstore 9
    //   363: lload 11
    //   365: lload 9
    //   367: lsub
    //   368: lstore 9
    //   370: lconst_0
    //   371: lstore 11
    //   373: lload 9
    //   375: lload 11
    //   377: invokestatic 157	java/lang/Math:max	(JJ)J
    //   380: lstore 9
    //   382: goto -92 -> 290
    //   385: astore 8
    //   387: invokestatic 132	com/google/android/gms/ads/internal/zzr:zzbG	()Lcom/google/android/gms/internal/zzmq;
    //   390: invokeinterface 138 1 0
    //   395: lload 14
    //   397: lsub
    //   398: lstore 25
    //   400: lload 11
    //   402: lload 25
    //   404: lsub
    //   405: lconst_0
    //   406: invokestatic 157	java/lang/Math:max	(JJ)J
    //   409: pop2
    //   410: aload 8
    //   412: athrow
    //   413: aload_0
    //   414: aload 6
    //   416: invokespecial 108	com/google/android/gms/internal/zzeu:zza	(Lcom/google/android/gms/internal/zzjg;)V
    //   419: aload 4
    //   421: ifnonnull -390 -> 31
    //   424: new 77	com/google/android/gms/internal/zzes
    //   427: astore 4
    //   429: iconst_1
    //   430: istore_3
    //   431: aload 4
    //   433: iload_3
    //   434: invokespecial 80	com/google/android/gms/internal/zzes:<init>	(I)V
    //   437: goto -406 -> 31
    //   440: astore 8
    //   442: goto -105 -> 337
    //   445: astore 8
    //   447: goto -110 -> 337
    //   450: astore 8
    //   452: goto -115 -> 337
    //   455: aload 4
    //   457: astore 8
    //   459: aload 6
    //   461: astore_2
    //   462: iload 5
    //   464: istore 7
    //   466: goto -227 -> 239
    // Local variable table:
    //   start	length	slot	name	signature
    //   0	469	0	this	zzeu
    //   0	469	1	paramList	List
    //   4	458	2	localObject1	Object
    //   11	2	3	bool1	boolean
    //   22	4	3	i	int
    //   70	364	3	j	int
    //   19	437	4	localObject2	Object
    //   37	426	5	k	int
    //   40	420	6	localObject3	Object
    //   43	422	7	m	int
    //   52	235	8	localObject4	Object
    //   297	20	8	localObject5	Object
    //   335	7	8	localRemoteException	android.os.RemoteException
    //   349	3	8	localzzmq	zzmq
    //   385	26	8	localObject6	Object
    //   440	1	8	localInterruptedException	InterruptedException
    //   445	1	8	localExecutionException	ExecutionException
    //   450	1	8	localTimeoutException	java.util.concurrent.TimeoutException
    //   457	1	8	localObject7	Object
    //   59	322	9	l1	long
    //   63	338	11	l2	long
    //   94	19	13	localIterator	Iterator
    //   134	262	14	l3	long
    //   137	5	16	l4	long
    //   144	17	18	bool2	boolean
    //   186	3	19	n	int
    //   197	24	20	localzzfa	zzfa
    //   211	7	21	i1	int
    //   230	47	22	localObject8	Object
    //   250	29	23	l5	long
    //   398	5	25	l6	long
    // Exception table:
    //   from	to	target	type
    //   7	11	297	finally
    //   16	19	297	finally
    //   25	29	297	finally
    //   29	31	297	finally
    //   34	36	297	finally
    //   299	301	297	finally
    //   151	158	335	android/os/RemoteException
    //   165	172	335	android/os/RemoteException
    //   173	177	335	android/os/RemoteException
    //   182	186	335	android/os/RemoteException
    //   193	197	335	android/os/RemoteException
    //   204	211	335	android/os/RemoteException
    //   220	227	335	android/os/RemoteException
    //   312	315	335	android/os/RemoteException
    //   320	326	335	android/os/RemoteException
    //   327	331	335	android/os/RemoteException
    //   151	158	385	finally
    //   165	172	385	finally
    //   173	177	385	finally
    //   182	186	385	finally
    //   193	197	385	finally
    //   204	211	385	finally
    //   220	227	385	finally
    //   312	315	385	finally
    //   320	326	385	finally
    //   327	331	385	finally
    //   341	346	385	finally
    //   151	158	440	java/lang/InterruptedException
    //   165	172	440	java/lang/InterruptedException
    //   173	177	440	java/lang/InterruptedException
    //   182	186	440	java/lang/InterruptedException
    //   193	197	440	java/lang/InterruptedException
    //   204	211	440	java/lang/InterruptedException
    //   220	227	440	java/lang/InterruptedException
    //   312	315	440	java/lang/InterruptedException
    //   320	326	440	java/lang/InterruptedException
    //   327	331	440	java/lang/InterruptedException
    //   151	158	445	java/util/concurrent/ExecutionException
    //   165	172	445	java/util/concurrent/ExecutionException
    //   173	177	445	java/util/concurrent/ExecutionException
    //   182	186	445	java/util/concurrent/ExecutionException
    //   193	197	445	java/util/concurrent/ExecutionException
    //   204	211	445	java/util/concurrent/ExecutionException
    //   220	227	445	java/util/concurrent/ExecutionException
    //   312	315	445	java/util/concurrent/ExecutionException
    //   320	326	445	java/util/concurrent/ExecutionException
    //   327	331	445	java/util/concurrent/ExecutionException
    //   151	158	450	java/util/concurrent/TimeoutException
    //   165	172	450	java/util/concurrent/TimeoutException
    //   173	177	450	java/util/concurrent/TimeoutException
    //   182	186	450	java/util/concurrent/TimeoutException
    //   193	197	450	java/util/concurrent/TimeoutException
    //   204	211	450	java/util/concurrent/TimeoutException
    //   220	227	450	java/util/concurrent/TimeoutException
    //   312	315	450	java/util/concurrent/TimeoutException
    //   320	326	450	java/util/concurrent/TimeoutException
    //   327	331	450	java/util/concurrent/TimeoutException
  }
  
  public void cancel()
  {
    Object localObject1 = this.zzpV;
    boolean bool = true;
    try
    {
      this.zzCy = bool;
      Object localObject2 = this.zzCz;
      localObject2 = ((Map)localObject2).values();
      Iterator localIterator = ((Collection)localObject2).iterator();
      for (;;)
      {
        bool = localIterator.hasNext();
        if (!bool) {
          break;
        }
        localObject2 = localIterator.next();
        localObject2 = (zzer)localObject2;
        ((zzer)localObject2).cancel();
      }
    }
    finally {}
  }
  
  public zzes zzc(List paramList)
  {
    Object localObject1 = "Starting mediation.";
    zzin.zzaI((String)localObject1);
    ExecutorService localExecutorService = Executors.newCachedThreadPool();
    ArrayList localArrayList = new java/util/ArrayList;
    localArrayList.<init>();
    Iterator localIterator1 = paramList.iterator();
    boolean bool1 = localIterator1.hasNext();
    if (bool1)
    {
      zzen localzzen = (zzen)localIterator1.next();
      localObject1 = new java/lang/StringBuilder;
      ((StringBuilder)localObject1).<init>();
      localObject1 = ((StringBuilder)localObject1).append("Trying mediation network: ");
      Object localObject2 = localzzen.zzBA;
      zzin.zzaJ((String)localObject2);
      localObject1 = localzzen.zzBB;
      Iterator localIterator2 = ((List)localObject1).iterator();
      for (;;)
      {
        bool1 = localIterator2.hasNext();
        if (!bool1) {
          break;
        }
        Object localObject3 = (String)localIterator2.next();
        localObject1 = new com/google/android/gms/internal/zzer;
        localObject2 = this.mContext;
        zzex localzzex = this.zzpn;
        zzeo localzzeo = this.zzCf;
        AdRequestParcel localAdRequestParcel = this.zzCu.zzHt;
        AdSizeParcel localAdSizeParcel = this.zzCu.zzrp;
        VersionInfoParcel localVersionInfoParcel = this.zzCu.zzrl;
        boolean bool2 = this.zzsA;
        boolean bool3 = this.zzuS;
        NativeAdOptionsParcel localNativeAdOptionsParcel = this.zzCu.zzrD;
        List localList = this.zzCu.zzrH;
        ((zzer)localObject1).<init>((Context)localObject2, (String)localObject3, localzzex, localzzeo, localzzen, localAdRequestParcel, localAdSizeParcel, localVersionInfoParcel, bool2, bool3, localNativeAdOptionsParcel, localList);
        localObject2 = new com/google/android/gms/internal/zzeu$1;
        ((zzeu.1)localObject2).<init>(this, (zzer)localObject1);
        localObject2 = zziq.zza(localExecutorService, (Callable)localObject2);
        localObject3 = this.zzCz;
        ((Map)localObject3).put(localObject2, localObject1);
        localArrayList.add(localObject2);
      }
    }
    int i = this.zzCx;
    switch (i)
    {
    }
    for (localObject1 = zzd(localArrayList);; localObject1 = zze(localArrayList)) {
      return (zzes)localObject1;
    }
  }
}


/* Location:              C:\Users\haryo\Desktop\enjarify-master\presensi-enjarify.jar!\com\google\android\gms\internal\zzeu.class
 * Java compiler version: 5 (49.0)
 * JD-Core Version:       0.7.1
 */