package com.google.android.gms.internal;

import android.os.IBinder;
import android.os.Parcel;
import com.google.android.gms.ads.internal.client.AdRequestParcel;
import com.google.android.gms.ads.internal.client.AdSizeParcel;
import com.google.android.gms.ads.internal.formats.NativeAdOptionsParcel;
import com.google.android.gms.dynamic.zzd;
import com.google.android.gms.dynamic.zzd.zza;
import java.util.List;

class zzey$zza$zza
  implements zzey
{
  private IBinder zzoz;
  
  zzey$zza$zza(IBinder paramIBinder)
  {
    this.zzoz = paramIBinder;
  }
  
  public IBinder asBinder()
  {
    return this.zzoz;
  }
  
  public void destroy()
  {
    Parcel localParcel1 = Parcel.obtain();
    Parcel localParcel2 = Parcel.obtain();
    Object localObject1 = "com.google.android.gms.ads.internal.mediation.client.IMediationAdapter";
    try
    {
      localParcel1.writeInterfaceToken((String)localObject1);
      localObject1 = this.zzoz;
      int i = 5;
      ((IBinder)localObject1).transact(i, localParcel1, localParcel2, 0);
      localParcel2.readException();
      return;
    }
    finally
    {
      localParcel2.recycle();
      localParcel1.recycle();
    }
  }
  
  /* Error */
  public android.os.Bundle getInterstitialAdapterInfo()
  {
    // Byte code:
    //   0: invokestatic 20	android/os/Parcel:obtain	()Landroid/os/Parcel;
    //   3: astore_1
    //   4: invokestatic 20	android/os/Parcel:obtain	()Landroid/os/Parcel;
    //   7: astore_2
    //   8: ldc 22
    //   10: astore_3
    //   11: aload_1
    //   12: aload_3
    //   13: invokevirtual 26	android/os/Parcel:writeInterfaceToken	(Ljava/lang/String;)V
    //   16: aload_0
    //   17: getfield 14	com/google/android/gms/internal/zzey$zza$zza:zzoz	Landroid/os/IBinder;
    //   20: astore_3
    //   21: bipush 18
    //   23: istore 4
    //   25: aload_3
    //   26: iload 4
    //   28: aload_1
    //   29: aload_2
    //   30: iconst_0
    //   31: invokeinterface 33 5 0
    //   36: pop
    //   37: aload_2
    //   38: invokevirtual 36	android/os/Parcel:readException	()V
    //   41: aload_2
    //   42: invokevirtual 44	android/os/Parcel:readInt	()I
    //   45: istore 5
    //   47: iload 5
    //   49: ifeq +30 -> 79
    //   52: getstatic 50	android/os/Bundle:CREATOR	Landroid/os/Parcelable$Creator;
    //   55: astore_3
    //   56: aload_3
    //   57: aload_2
    //   58: invokeinterface 56 2 0
    //   63: astore_3
    //   64: aload_3
    //   65: checkcast 46	android/os/Bundle
    //   68: astore_3
    //   69: aload_2
    //   70: invokevirtual 39	android/os/Parcel:recycle	()V
    //   73: aload_1
    //   74: invokevirtual 39	android/os/Parcel:recycle	()V
    //   77: aload_3
    //   78: areturn
    //   79: iconst_0
    //   80: istore 5
    //   82: aconst_null
    //   83: astore_3
    //   84: goto -15 -> 69
    //   87: astore_3
    //   88: aload_2
    //   89: invokevirtual 39	android/os/Parcel:recycle	()V
    //   92: aload_1
    //   93: invokevirtual 39	android/os/Parcel:recycle	()V
    //   96: aload_3
    //   97: athrow
    // Local variable table:
    //   start	length	slot	name	signature
    //   0	98	0	this	zza
    //   3	90	1	localParcel1	Parcel
    //   7	82	2	localParcel2	Parcel
    //   10	74	3	localObject1	Object
    //   87	10	3	localObject2	Object
    //   23	4	4	i	int
    //   45	36	5	j	int
    // Exception table:
    //   from	to	target	type
    //   12	16	87	finally
    //   16	20	87	finally
    //   30	37	87	finally
    //   37	41	87	finally
    //   41	45	87	finally
    //   52	55	87	finally
    //   57	63	87	finally
    //   64	68	87	finally
  }
  
  public zzd getView()
  {
    Parcel localParcel1 = Parcel.obtain();
    Parcel localParcel2 = Parcel.obtain();
    Object localObject1 = "com.google.android.gms.ads.internal.mediation.client.IMediationAdapter";
    try
    {
      localParcel1.writeInterfaceToken((String)localObject1);
      localObject1 = this.zzoz;
      int i = 2;
      ((IBinder)localObject1).transact(i, localParcel1, localParcel2, 0);
      localParcel2.readException();
      localObject1 = localParcel2.readStrongBinder();
      localObject1 = zzd.zza.zzbs((IBinder)localObject1);
      return (zzd)localObject1;
    }
    finally
    {
      localParcel2.recycle();
      localParcel1.recycle();
    }
  }
  
  public boolean isInitialized()
  {
    boolean bool = false;
    Object localObject1 = null;
    Parcel localParcel1 = Parcel.obtain();
    Parcel localParcel2 = Parcel.obtain();
    Object localObject3 = "com.google.android.gms.ads.internal.mediation.client.IMediationAdapter";
    try
    {
      localParcel1.writeInterfaceToken((String)localObject3);
      localObject3 = this.zzoz;
      int i = 13;
      ((IBinder)localObject3).transact(i, localParcel1, localParcel2, 0);
      localParcel2.readException();
      int j = localParcel2.readInt();
      if (j != 0) {
        bool = true;
      }
      return bool;
    }
    finally
    {
      localParcel2.recycle();
      localParcel1.recycle();
    }
  }
  
  public void pause()
  {
    Parcel localParcel1 = Parcel.obtain();
    Parcel localParcel2 = Parcel.obtain();
    Object localObject1 = "com.google.android.gms.ads.internal.mediation.client.IMediationAdapter";
    try
    {
      localParcel1.writeInterfaceToken((String)localObject1);
      localObject1 = this.zzoz;
      int i = 8;
      ((IBinder)localObject1).transact(i, localParcel1, localParcel2, 0);
      localParcel2.readException();
      return;
    }
    finally
    {
      localParcel2.recycle();
      localParcel1.recycle();
    }
  }
  
  public void resume()
  {
    Parcel localParcel1 = Parcel.obtain();
    Parcel localParcel2 = Parcel.obtain();
    Object localObject1 = "com.google.android.gms.ads.internal.mediation.client.IMediationAdapter";
    try
    {
      localParcel1.writeInterfaceToken((String)localObject1);
      localObject1 = this.zzoz;
      int i = 9;
      ((IBinder)localObject1).transact(i, localParcel1, localParcel2, 0);
      localParcel2.readException();
      return;
    }
    finally
    {
      localParcel2.recycle();
      localParcel1.recycle();
    }
  }
  
  public void showInterstitial()
  {
    Parcel localParcel1 = Parcel.obtain();
    Parcel localParcel2 = Parcel.obtain();
    Object localObject1 = "com.google.android.gms.ads.internal.mediation.client.IMediationAdapter";
    try
    {
      localParcel1.writeInterfaceToken((String)localObject1);
      localObject1 = this.zzoz;
      int i = 4;
      ((IBinder)localObject1).transact(i, localParcel1, localParcel2, 0);
      localParcel2.readException();
      return;
    }
    finally
    {
      localParcel2.recycle();
      localParcel1.recycle();
    }
  }
  
  public void showVideo()
  {
    Parcel localParcel1 = Parcel.obtain();
    Parcel localParcel2 = Parcel.obtain();
    Object localObject1 = "com.google.android.gms.ads.internal.mediation.client.IMediationAdapter";
    try
    {
      localParcel1.writeInterfaceToken((String)localObject1);
      localObject1 = this.zzoz;
      int i = 12;
      ((IBinder)localObject1).transact(i, localParcel1, localParcel2, 0);
      localParcel2.readException();
      return;
    }
    finally
    {
      localParcel2.recycle();
      localParcel1.recycle();
    }
  }
  
  /* Error */
  public void zza(AdRequestParcel paramAdRequestParcel, String paramString1, String paramString2)
  {
    // Byte code:
    //   0: invokestatic 20	android/os/Parcel:obtain	()Landroid/os/Parcel;
    //   3: astore 4
    //   5: invokestatic 20	android/os/Parcel:obtain	()Landroid/os/Parcel;
    //   8: astore 5
    //   10: ldc 22
    //   12: astore 6
    //   14: aload 4
    //   16: aload 6
    //   18: invokevirtual 26	android/os/Parcel:writeInterfaceToken	(Ljava/lang/String;)V
    //   21: aload_1
    //   22: ifnull +79 -> 101
    //   25: iconst_1
    //   26: istore 7
    //   28: aload 4
    //   30: iload 7
    //   32: invokevirtual 77	android/os/Parcel:writeInt	(I)V
    //   35: iconst_0
    //   36: istore 7
    //   38: aconst_null
    //   39: astore 6
    //   41: aload_1
    //   42: aload 4
    //   44: iconst_0
    //   45: invokevirtual 83	com/google/android/gms/ads/internal/client/AdRequestParcel:writeToParcel	(Landroid/os/Parcel;I)V
    //   48: aload 4
    //   50: aload_2
    //   51: invokevirtual 86	android/os/Parcel:writeString	(Ljava/lang/String;)V
    //   54: aload 4
    //   56: aload_3
    //   57: invokevirtual 86	android/os/Parcel:writeString	(Ljava/lang/String;)V
    //   60: aload_0
    //   61: getfield 14	com/google/android/gms/internal/zzey$zza$zza:zzoz	Landroid/os/IBinder;
    //   64: astore 6
    //   66: bipush 20
    //   68: istore 8
    //   70: aload 6
    //   72: iload 8
    //   74: aload 4
    //   76: aload 5
    //   78: iconst_0
    //   79: invokeinterface 33 5 0
    //   84: pop
    //   85: aload 5
    //   87: invokevirtual 36	android/os/Parcel:readException	()V
    //   90: aload 5
    //   92: invokevirtual 39	android/os/Parcel:recycle	()V
    //   95: aload 4
    //   97: invokevirtual 39	android/os/Parcel:recycle	()V
    //   100: return
    //   101: iconst_0
    //   102: istore 7
    //   104: aconst_null
    //   105: astore 6
    //   107: aload 4
    //   109: iconst_0
    //   110: invokevirtual 77	android/os/Parcel:writeInt	(I)V
    //   113: goto -65 -> 48
    //   116: astore 6
    //   118: aload 5
    //   120: invokevirtual 39	android/os/Parcel:recycle	()V
    //   123: aload 4
    //   125: invokevirtual 39	android/os/Parcel:recycle	()V
    //   128: aload 6
    //   130: athrow
    // Local variable table:
    //   start	length	slot	name	signature
    //   0	131	0	this	zza
    //   0	131	1	paramAdRequestParcel	AdRequestParcel
    //   0	131	2	paramString1	String
    //   0	131	3	paramString2	String
    //   3	121	4	localParcel1	Parcel
    //   8	111	5	localParcel2	Parcel
    //   12	94	6	localObject1	Object
    //   116	13	6	localObject2	Object
    //   26	77	7	i	int
    //   68	5	8	j	int
    // Exception table:
    //   from	to	target	type
    //   16	21	116	finally
    //   30	35	116	finally
    //   44	48	116	finally
    //   50	54	116	finally
    //   56	60	116	finally
    //   60	64	116	finally
    //   78	85	116	finally
    //   85	90	116	finally
    //   109	113	116	finally
  }
  
  /* Error */
  public void zza(zzd paramzzd, AdRequestParcel paramAdRequestParcel, String paramString1, com.google.android.gms.ads.internal.reward.mediation.client.zza paramzza, String paramString2)
  {
    // Byte code:
    //   0: aconst_null
    //   1: astore 6
    //   3: invokestatic 20	android/os/Parcel:obtain	()Landroid/os/Parcel;
    //   6: astore 7
    //   8: invokestatic 20	android/os/Parcel:obtain	()Landroid/os/Parcel;
    //   11: astore 8
    //   13: ldc 22
    //   15: astore 9
    //   17: aload 7
    //   19: aload 9
    //   21: invokevirtual 26	android/os/Parcel:writeInterfaceToken	(Ljava/lang/String;)V
    //   24: aload_1
    //   25: ifnull +120 -> 145
    //   28: aload_1
    //   29: invokeinterface 92 1 0
    //   34: astore 9
    //   36: aload 7
    //   38: aload 9
    //   40: invokevirtual 96	android/os/Parcel:writeStrongBinder	(Landroid/os/IBinder;)V
    //   43: aload_2
    //   44: ifnull +110 -> 154
    //   47: iconst_1
    //   48: istore 10
    //   50: aload 7
    //   52: iload 10
    //   54: invokevirtual 77	android/os/Parcel:writeInt	(I)V
    //   57: iconst_0
    //   58: istore 10
    //   60: aconst_null
    //   61: astore 9
    //   63: aload_2
    //   64: aload 7
    //   66: iconst_0
    //   67: invokevirtual 83	com/google/android/gms/ads/internal/client/AdRequestParcel:writeToParcel	(Landroid/os/Parcel;I)V
    //   70: aload 7
    //   72: aload_3
    //   73: invokevirtual 86	android/os/Parcel:writeString	(Ljava/lang/String;)V
    //   76: aload 4
    //   78: ifnull +12 -> 90
    //   81: aload 4
    //   83: invokeinterface 99 1 0
    //   88: astore 6
    //   90: aload 7
    //   92: aload 6
    //   94: invokevirtual 96	android/os/Parcel:writeStrongBinder	(Landroid/os/IBinder;)V
    //   97: aload 7
    //   99: aload 5
    //   101: invokevirtual 86	android/os/Parcel:writeString	(Ljava/lang/String;)V
    //   104: aload_0
    //   105: getfield 14	com/google/android/gms/internal/zzey$zza$zza:zzoz	Landroid/os/IBinder;
    //   108: astore 6
    //   110: bipush 10
    //   112: istore 10
    //   114: aload 6
    //   116: iload 10
    //   118: aload 7
    //   120: aload 8
    //   122: iconst_0
    //   123: invokeinterface 33 5 0
    //   128: pop
    //   129: aload 8
    //   131: invokevirtual 36	android/os/Parcel:readException	()V
    //   134: aload 8
    //   136: invokevirtual 39	android/os/Parcel:recycle	()V
    //   139: aload 7
    //   141: invokevirtual 39	android/os/Parcel:recycle	()V
    //   144: return
    //   145: iconst_0
    //   146: istore 10
    //   148: aconst_null
    //   149: astore 9
    //   151: goto -115 -> 36
    //   154: iconst_0
    //   155: istore 10
    //   157: aconst_null
    //   158: astore 9
    //   160: aload 7
    //   162: iconst_0
    //   163: invokevirtual 77	android/os/Parcel:writeInt	(I)V
    //   166: goto -96 -> 70
    //   169: astore 6
    //   171: aload 8
    //   173: invokevirtual 39	android/os/Parcel:recycle	()V
    //   176: aload 7
    //   178: invokevirtual 39	android/os/Parcel:recycle	()V
    //   181: aload 6
    //   183: athrow
    // Local variable table:
    //   start	length	slot	name	signature
    //   0	184	0	this	zza
    //   0	184	1	paramzzd	zzd
    //   0	184	2	paramAdRequestParcel	AdRequestParcel
    //   0	184	3	paramString1	String
    //   0	184	4	paramzza	com.google.android.gms.ads.internal.reward.mediation.client.zza
    //   0	184	5	paramString2	String
    //   1	114	6	localIBinder	IBinder
    //   169	13	6	localObject1	Object
    //   6	171	7	localParcel1	Parcel
    //   11	161	8	localParcel2	Parcel
    //   15	144	9	localObject2	Object
    //   48	108	10	i	int
    // Exception table:
    //   from	to	target	type
    //   19	24	169	finally
    //   28	34	169	finally
    //   38	43	169	finally
    //   52	57	169	finally
    //   66	70	169	finally
    //   72	76	169	finally
    //   81	88	169	finally
    //   92	97	169	finally
    //   99	104	169	finally
    //   104	108	169	finally
    //   122	129	169	finally
    //   129	134	169	finally
    //   162	166	169	finally
  }
  
  /* Error */
  public void zza(zzd paramzzd, AdRequestParcel paramAdRequestParcel, String paramString, zzez paramzzez)
  {
    // Byte code:
    //   0: aconst_null
    //   1: astore 5
    //   3: invokestatic 20	android/os/Parcel:obtain	()Landroid/os/Parcel;
    //   6: astore 6
    //   8: invokestatic 20	android/os/Parcel:obtain	()Landroid/os/Parcel;
    //   11: astore 7
    //   13: ldc 22
    //   15: astore 8
    //   17: aload 6
    //   19: aload 8
    //   21: invokevirtual 26	android/os/Parcel:writeInterfaceToken	(Ljava/lang/String;)V
    //   24: aload_1
    //   25: ifnull +112 -> 137
    //   28: aload_1
    //   29: invokeinterface 92 1 0
    //   34: astore 8
    //   36: aload 6
    //   38: aload 8
    //   40: invokevirtual 96	android/os/Parcel:writeStrongBinder	(Landroid/os/IBinder;)V
    //   43: aload_2
    //   44: ifnull +102 -> 146
    //   47: iconst_1
    //   48: istore 9
    //   50: aload 6
    //   52: iload 9
    //   54: invokevirtual 77	android/os/Parcel:writeInt	(I)V
    //   57: iconst_0
    //   58: istore 9
    //   60: aconst_null
    //   61: astore 8
    //   63: aload_2
    //   64: aload 6
    //   66: iconst_0
    //   67: invokevirtual 83	com/google/android/gms/ads/internal/client/AdRequestParcel:writeToParcel	(Landroid/os/Parcel;I)V
    //   70: aload 6
    //   72: aload_3
    //   73: invokevirtual 86	android/os/Parcel:writeString	(Ljava/lang/String;)V
    //   76: aload 4
    //   78: ifnull +12 -> 90
    //   81: aload 4
    //   83: invokeinterface 103 1 0
    //   88: astore 5
    //   90: aload 6
    //   92: aload 5
    //   94: invokevirtual 96	android/os/Parcel:writeStrongBinder	(Landroid/os/IBinder;)V
    //   97: aload_0
    //   98: getfield 14	com/google/android/gms/internal/zzey$zza$zza:zzoz	Landroid/os/IBinder;
    //   101: astore 5
    //   103: iconst_3
    //   104: istore 9
    //   106: aload 5
    //   108: iload 9
    //   110: aload 6
    //   112: aload 7
    //   114: iconst_0
    //   115: invokeinterface 33 5 0
    //   120: pop
    //   121: aload 7
    //   123: invokevirtual 36	android/os/Parcel:readException	()V
    //   126: aload 7
    //   128: invokevirtual 39	android/os/Parcel:recycle	()V
    //   131: aload 6
    //   133: invokevirtual 39	android/os/Parcel:recycle	()V
    //   136: return
    //   137: iconst_0
    //   138: istore 9
    //   140: aconst_null
    //   141: astore 8
    //   143: goto -107 -> 36
    //   146: iconst_0
    //   147: istore 9
    //   149: aconst_null
    //   150: astore 8
    //   152: aload 6
    //   154: iconst_0
    //   155: invokevirtual 77	android/os/Parcel:writeInt	(I)V
    //   158: goto -88 -> 70
    //   161: astore 5
    //   163: aload 7
    //   165: invokevirtual 39	android/os/Parcel:recycle	()V
    //   168: aload 6
    //   170: invokevirtual 39	android/os/Parcel:recycle	()V
    //   173: aload 5
    //   175: athrow
    // Local variable table:
    //   start	length	slot	name	signature
    //   0	176	0	this	zza
    //   0	176	1	paramzzd	zzd
    //   0	176	2	paramAdRequestParcel	AdRequestParcel
    //   0	176	3	paramString	String
    //   0	176	4	paramzzez	zzez
    //   1	106	5	localIBinder	IBinder
    //   161	13	5	localObject1	Object
    //   6	163	6	localParcel1	Parcel
    //   11	153	7	localParcel2	Parcel
    //   15	136	8	localObject2	Object
    //   48	100	9	i	int
    // Exception table:
    //   from	to	target	type
    //   19	24	161	finally
    //   28	34	161	finally
    //   38	43	161	finally
    //   52	57	161	finally
    //   66	70	161	finally
    //   72	76	161	finally
    //   81	88	161	finally
    //   92	97	161	finally
    //   97	101	161	finally
    //   114	121	161	finally
    //   121	126	161	finally
    //   154	158	161	finally
  }
  
  /* Error */
  public void zza(zzd paramzzd, AdRequestParcel paramAdRequestParcel, String paramString1, String paramString2, zzez paramzzez)
  {
    // Byte code:
    //   0: aconst_null
    //   1: astore 6
    //   3: invokestatic 20	android/os/Parcel:obtain	()Landroid/os/Parcel;
    //   6: astore 7
    //   8: invokestatic 20	android/os/Parcel:obtain	()Landroid/os/Parcel;
    //   11: astore 8
    //   13: ldc 22
    //   15: astore 9
    //   17: aload 7
    //   19: aload 9
    //   21: invokevirtual 26	android/os/Parcel:writeInterfaceToken	(Ljava/lang/String;)V
    //   24: aload_1
    //   25: ifnull +120 -> 145
    //   28: aload_1
    //   29: invokeinterface 92 1 0
    //   34: astore 9
    //   36: aload 7
    //   38: aload 9
    //   40: invokevirtual 96	android/os/Parcel:writeStrongBinder	(Landroid/os/IBinder;)V
    //   43: aload_2
    //   44: ifnull +110 -> 154
    //   47: iconst_1
    //   48: istore 10
    //   50: aload 7
    //   52: iload 10
    //   54: invokevirtual 77	android/os/Parcel:writeInt	(I)V
    //   57: iconst_0
    //   58: istore 10
    //   60: aconst_null
    //   61: astore 9
    //   63: aload_2
    //   64: aload 7
    //   66: iconst_0
    //   67: invokevirtual 83	com/google/android/gms/ads/internal/client/AdRequestParcel:writeToParcel	(Landroid/os/Parcel;I)V
    //   70: aload 7
    //   72: aload_3
    //   73: invokevirtual 86	android/os/Parcel:writeString	(Ljava/lang/String;)V
    //   76: aload 7
    //   78: aload 4
    //   80: invokevirtual 86	android/os/Parcel:writeString	(Ljava/lang/String;)V
    //   83: aload 5
    //   85: ifnull +12 -> 97
    //   88: aload 5
    //   90: invokeinterface 103 1 0
    //   95: astore 6
    //   97: aload 7
    //   99: aload 6
    //   101: invokevirtual 96	android/os/Parcel:writeStrongBinder	(Landroid/os/IBinder;)V
    //   104: aload_0
    //   105: getfield 14	com/google/android/gms/internal/zzey$zza$zza:zzoz	Landroid/os/IBinder;
    //   108: astore 6
    //   110: bipush 7
    //   112: istore 10
    //   114: aload 6
    //   116: iload 10
    //   118: aload 7
    //   120: aload 8
    //   122: iconst_0
    //   123: invokeinterface 33 5 0
    //   128: pop
    //   129: aload 8
    //   131: invokevirtual 36	android/os/Parcel:readException	()V
    //   134: aload 8
    //   136: invokevirtual 39	android/os/Parcel:recycle	()V
    //   139: aload 7
    //   141: invokevirtual 39	android/os/Parcel:recycle	()V
    //   144: return
    //   145: iconst_0
    //   146: istore 10
    //   148: aconst_null
    //   149: astore 9
    //   151: goto -115 -> 36
    //   154: iconst_0
    //   155: istore 10
    //   157: aconst_null
    //   158: astore 9
    //   160: aload 7
    //   162: iconst_0
    //   163: invokevirtual 77	android/os/Parcel:writeInt	(I)V
    //   166: goto -96 -> 70
    //   169: astore 6
    //   171: aload 8
    //   173: invokevirtual 39	android/os/Parcel:recycle	()V
    //   176: aload 7
    //   178: invokevirtual 39	android/os/Parcel:recycle	()V
    //   181: aload 6
    //   183: athrow
    // Local variable table:
    //   start	length	slot	name	signature
    //   0	184	0	this	zza
    //   0	184	1	paramzzd	zzd
    //   0	184	2	paramAdRequestParcel	AdRequestParcel
    //   0	184	3	paramString1	String
    //   0	184	4	paramString2	String
    //   0	184	5	paramzzez	zzez
    //   1	114	6	localIBinder	IBinder
    //   169	13	6	localObject1	Object
    //   6	171	7	localParcel1	Parcel
    //   11	161	8	localParcel2	Parcel
    //   15	144	9	localObject2	Object
    //   48	108	10	i	int
    // Exception table:
    //   from	to	target	type
    //   19	24	169	finally
    //   28	34	169	finally
    //   38	43	169	finally
    //   52	57	169	finally
    //   66	70	169	finally
    //   72	76	169	finally
    //   78	83	169	finally
    //   88	95	169	finally
    //   99	104	169	finally
    //   104	108	169	finally
    //   122	129	169	finally
    //   129	134	169	finally
    //   162	166	169	finally
  }
  
  public void zza(zzd paramzzd, AdRequestParcel paramAdRequestParcel, String paramString1, String paramString2, zzez paramzzez, NativeAdOptionsParcel paramNativeAdOptionsParcel, List paramList)
  {
    int i = 0;
    IBinder localIBinder = null;
    Parcel localParcel1 = Parcel.obtain();
    Parcel localParcel2 = Parcel.obtain();
    Object localObject3 = "com.google.android.gms.ads.internal.mediation.client.IMediationAdapter";
    for (;;)
    {
      try
      {
        localParcel1.writeInterfaceToken((String)localObject3);
        if (paramzzd != null)
        {
          localObject3 = paramzzd.asBinder();
          localParcel1.writeStrongBinder((IBinder)localObject3);
          if (paramAdRequestParcel != null)
          {
            j = 1;
            localParcel1.writeInt(j);
            j = 0;
            localObject3 = null;
            paramAdRequestParcel.writeToParcel(localParcel1, 0);
            localParcel1.writeString(paramString1);
            localParcel1.writeString(paramString2);
            if (paramzzez != null) {
              localIBinder = paramzzez.asBinder();
            }
            localParcel1.writeStrongBinder(localIBinder);
            if (paramNativeAdOptionsParcel == null) {
              break label223;
            }
            i = 1;
            localParcel1.writeInt(i);
            i = 0;
            localIBinder = null;
            paramNativeAdOptionsParcel.writeToParcel(localParcel1, 0);
            localParcel1.writeStringList(paramList);
            localIBinder = this.zzoz;
            j = 14;
            localIBinder.transact(j, localParcel1, localParcel2, 0);
            localParcel2.readException();
          }
        }
        else
        {
          j = 0;
          localObject3 = null;
          continue;
        }
        int j = 0;
        localObject3 = null;
        localParcel1.writeInt(0);
        continue;
        i = 0;
      }
      finally
      {
        localParcel2.recycle();
        localParcel1.recycle();
      }
      label223:
      Object localObject2 = null;
      localParcel1.writeInt(0);
    }
  }
  
  public void zza(zzd paramzzd, AdSizeParcel paramAdSizeParcel, AdRequestParcel paramAdRequestParcel, String paramString, zzez paramzzez)
  {
    IBinder localIBinder = null;
    Parcel localParcel1 = Parcel.obtain();
    Parcel localParcel2 = Parcel.obtain();
    Object localObject2 = "com.google.android.gms.ads.internal.mediation.client.IMediationAdapter";
    for (;;)
    {
      try
      {
        localParcel1.writeInterfaceToken((String)localObject2);
        if (paramzzd != null)
        {
          localObject2 = paramzzd.asBinder();
          localParcel1.writeStrongBinder((IBinder)localObject2);
          if (paramAdSizeParcel != null)
          {
            i = 1;
            localParcel1.writeInt(i);
            i = 0;
            localObject2 = null;
            paramAdSizeParcel.writeToParcel(localParcel1, 0);
            if (paramAdRequestParcel == null) {
              break label204;
            }
            i = 1;
            localParcel1.writeInt(i);
            i = 0;
            localObject2 = null;
            paramAdRequestParcel.writeToParcel(localParcel1, 0);
            localParcel1.writeString(paramString);
            if (paramzzez != null) {
              localIBinder = paramzzez.asBinder();
            }
            localParcel1.writeStrongBinder(localIBinder);
            localIBinder = this.zzoz;
            i = 1;
            localIBinder.transact(i, localParcel1, localParcel2, 0);
            localParcel2.readException();
          }
        }
        else
        {
          i = 0;
          localObject2 = null;
          continue;
        }
        int i = 0;
        localObject2 = null;
        localParcel1.writeInt(0);
        continue;
        i = 0;
      }
      finally
      {
        localParcel2.recycle();
        localParcel1.recycle();
      }
      label204:
      localObject2 = null;
      localParcel1.writeInt(0);
    }
  }
  
  public void zza(zzd paramzzd, AdSizeParcel paramAdSizeParcel, AdRequestParcel paramAdRequestParcel, String paramString1, String paramString2, zzez paramzzez)
  {
    IBinder localIBinder = null;
    Parcel localParcel1 = Parcel.obtain();
    Parcel localParcel2 = Parcel.obtain();
    Object localObject2 = "com.google.android.gms.ads.internal.mediation.client.IMediationAdapter";
    for (;;)
    {
      try
      {
        localParcel1.writeInterfaceToken((String)localObject2);
        if (paramzzd != null)
        {
          localObject2 = paramzzd.asBinder();
          localParcel1.writeStrongBinder((IBinder)localObject2);
          if (paramAdSizeParcel != null)
          {
            i = 1;
            localParcel1.writeInt(i);
            i = 0;
            localObject2 = null;
            paramAdSizeParcel.writeToParcel(localParcel1, 0);
            if (paramAdRequestParcel == null) {
              break label212;
            }
            i = 1;
            localParcel1.writeInt(i);
            i = 0;
            localObject2 = null;
            paramAdRequestParcel.writeToParcel(localParcel1, 0);
            localParcel1.writeString(paramString1);
            localParcel1.writeString(paramString2);
            if (paramzzez != null) {
              localIBinder = paramzzez.asBinder();
            }
            localParcel1.writeStrongBinder(localIBinder);
            localIBinder = this.zzoz;
            i = 6;
            localIBinder.transact(i, localParcel1, localParcel2, 0);
            localParcel2.readException();
          }
        }
        else
        {
          i = 0;
          localObject2 = null;
          continue;
        }
        int i = 0;
        localObject2 = null;
        localParcel1.writeInt(0);
        continue;
        i = 0;
      }
      finally
      {
        localParcel2.recycle();
        localParcel1.recycle();
      }
      label212:
      localObject2 = null;
      localParcel1.writeInt(0);
    }
  }
  
  /* Error */
  public void zzb(AdRequestParcel paramAdRequestParcel, String paramString)
  {
    // Byte code:
    //   0: invokestatic 20	android/os/Parcel:obtain	()Landroid/os/Parcel;
    //   3: astore_3
    //   4: invokestatic 20	android/os/Parcel:obtain	()Landroid/os/Parcel;
    //   7: astore 4
    //   9: ldc 22
    //   11: astore 5
    //   13: aload_3
    //   14: aload 5
    //   16: invokevirtual 26	android/os/Parcel:writeInterfaceToken	(Ljava/lang/String;)V
    //   19: aload_1
    //   20: ifnull +68 -> 88
    //   23: iconst_1
    //   24: istore 6
    //   26: aload_3
    //   27: iload 6
    //   29: invokevirtual 77	android/os/Parcel:writeInt	(I)V
    //   32: iconst_0
    //   33: istore 6
    //   35: aconst_null
    //   36: astore 5
    //   38: aload_1
    //   39: aload_3
    //   40: iconst_0
    //   41: invokevirtual 83	com/google/android/gms/ads/internal/client/AdRequestParcel:writeToParcel	(Landroid/os/Parcel;I)V
    //   44: aload_3
    //   45: aload_2
    //   46: invokevirtual 86	android/os/Parcel:writeString	(Ljava/lang/String;)V
    //   49: aload_0
    //   50: getfield 14	com/google/android/gms/internal/zzey$zza$zza:zzoz	Landroid/os/IBinder;
    //   53: astore 5
    //   55: bipush 11
    //   57: istore 7
    //   59: aload 5
    //   61: iload 7
    //   63: aload_3
    //   64: aload 4
    //   66: iconst_0
    //   67: invokeinterface 33 5 0
    //   72: pop
    //   73: aload 4
    //   75: invokevirtual 36	android/os/Parcel:readException	()V
    //   78: aload 4
    //   80: invokevirtual 39	android/os/Parcel:recycle	()V
    //   83: aload_3
    //   84: invokevirtual 39	android/os/Parcel:recycle	()V
    //   87: return
    //   88: iconst_0
    //   89: istore 6
    //   91: aconst_null
    //   92: astore 5
    //   94: aload_3
    //   95: iconst_0
    //   96: invokevirtual 77	android/os/Parcel:writeInt	(I)V
    //   99: goto -55 -> 44
    //   102: astore 5
    //   104: aload 4
    //   106: invokevirtual 39	android/os/Parcel:recycle	()V
    //   109: aload_3
    //   110: invokevirtual 39	android/os/Parcel:recycle	()V
    //   113: aload 5
    //   115: athrow
    // Local variable table:
    //   start	length	slot	name	signature
    //   0	116	0	this	zza
    //   0	116	1	paramAdRequestParcel	AdRequestParcel
    //   0	116	2	paramString	String
    //   3	107	3	localParcel1	Parcel
    //   7	98	4	localParcel2	Parcel
    //   11	82	5	localObject1	Object
    //   102	12	5	localObject2	Object
    //   24	66	6	i	int
    //   57	5	7	j	int
    // Exception table:
    //   from	to	target	type
    //   14	19	102	finally
    //   27	32	102	finally
    //   40	44	102	finally
    //   45	49	102	finally
    //   49	53	102	finally
    //   66	73	102	finally
    //   73	78	102	finally
    //   95	99	102	finally
  }
  
  public zzfb zzeF()
  {
    Parcel localParcel1 = Parcel.obtain();
    Parcel localParcel2 = Parcel.obtain();
    Object localObject1 = "com.google.android.gms.ads.internal.mediation.client.IMediationAdapter";
    try
    {
      localParcel1.writeInterfaceToken((String)localObject1);
      localObject1 = this.zzoz;
      int i = 15;
      ((IBinder)localObject1).transact(i, localParcel1, localParcel2, 0);
      localParcel2.readException();
      localObject1 = localParcel2.readStrongBinder();
      localObject1 = zzfb.zza.zzI((IBinder)localObject1);
      return (zzfb)localObject1;
    }
    finally
    {
      localParcel2.recycle();
      localParcel1.recycle();
    }
  }
  
  public zzfc zzeG()
  {
    Parcel localParcel1 = Parcel.obtain();
    Parcel localParcel2 = Parcel.obtain();
    Object localObject1 = "com.google.android.gms.ads.internal.mediation.client.IMediationAdapter";
    try
    {
      localParcel1.writeInterfaceToken((String)localObject1);
      localObject1 = this.zzoz;
      int i = 16;
      ((IBinder)localObject1).transact(i, localParcel1, localParcel2, 0);
      localParcel2.readException();
      localObject1 = localParcel2.readStrongBinder();
      localObject1 = zzfc.zza.zzJ((IBinder)localObject1);
      return (zzfc)localObject1;
    }
    finally
    {
      localParcel2.recycle();
      localParcel1.recycle();
    }
  }
  
  /* Error */
  public android.os.Bundle zzeH()
  {
    // Byte code:
    //   0: invokestatic 20	android/os/Parcel:obtain	()Landroid/os/Parcel;
    //   3: astore_1
    //   4: invokestatic 20	android/os/Parcel:obtain	()Landroid/os/Parcel;
    //   7: astore_2
    //   8: ldc 22
    //   10: astore_3
    //   11: aload_1
    //   12: aload_3
    //   13: invokevirtual 26	android/os/Parcel:writeInterfaceToken	(Ljava/lang/String;)V
    //   16: aload_0
    //   17: getfield 14	com/google/android/gms/internal/zzey$zza$zza:zzoz	Landroid/os/IBinder;
    //   20: astore_3
    //   21: bipush 17
    //   23: istore 4
    //   25: aload_3
    //   26: iload 4
    //   28: aload_1
    //   29: aload_2
    //   30: iconst_0
    //   31: invokeinterface 33 5 0
    //   36: pop
    //   37: aload_2
    //   38: invokevirtual 36	android/os/Parcel:readException	()V
    //   41: aload_2
    //   42: invokevirtual 44	android/os/Parcel:readInt	()I
    //   45: istore 5
    //   47: iload 5
    //   49: ifeq +30 -> 79
    //   52: getstatic 50	android/os/Bundle:CREATOR	Landroid/os/Parcelable$Creator;
    //   55: astore_3
    //   56: aload_3
    //   57: aload_2
    //   58: invokeinterface 56 2 0
    //   63: astore_3
    //   64: aload_3
    //   65: checkcast 46	android/os/Bundle
    //   68: astore_3
    //   69: aload_2
    //   70: invokevirtual 39	android/os/Parcel:recycle	()V
    //   73: aload_1
    //   74: invokevirtual 39	android/os/Parcel:recycle	()V
    //   77: aload_3
    //   78: areturn
    //   79: iconst_0
    //   80: istore 5
    //   82: aconst_null
    //   83: astore_3
    //   84: goto -15 -> 69
    //   87: astore_3
    //   88: aload_2
    //   89: invokevirtual 39	android/os/Parcel:recycle	()V
    //   92: aload_1
    //   93: invokevirtual 39	android/os/Parcel:recycle	()V
    //   96: aload_3
    //   97: athrow
    // Local variable table:
    //   start	length	slot	name	signature
    //   0	98	0	this	zza
    //   3	90	1	localParcel1	Parcel
    //   7	82	2	localParcel2	Parcel
    //   10	74	3	localObject1	Object
    //   87	10	3	localObject2	Object
    //   23	4	4	i	int
    //   45	36	5	j	int
    // Exception table:
    //   from	to	target	type
    //   12	16	87	finally
    //   16	20	87	finally
    //   30	37	87	finally
    //   37	41	87	finally
    //   41	45	87	finally
    //   52	55	87	finally
    //   57	63	87	finally
    //   64	68	87	finally
  }
  
  /* Error */
  public android.os.Bundle zzeI()
  {
    // Byte code:
    //   0: invokestatic 20	android/os/Parcel:obtain	()Landroid/os/Parcel;
    //   3: astore_1
    //   4: invokestatic 20	android/os/Parcel:obtain	()Landroid/os/Parcel;
    //   7: astore_2
    //   8: ldc 22
    //   10: astore_3
    //   11: aload_1
    //   12: aload_3
    //   13: invokevirtual 26	android/os/Parcel:writeInterfaceToken	(Ljava/lang/String;)V
    //   16: aload_0
    //   17: getfield 14	com/google/android/gms/internal/zzey$zza$zza:zzoz	Landroid/os/IBinder;
    //   20: astore_3
    //   21: bipush 19
    //   23: istore 4
    //   25: aload_3
    //   26: iload 4
    //   28: aload_1
    //   29: aload_2
    //   30: iconst_0
    //   31: invokeinterface 33 5 0
    //   36: pop
    //   37: aload_2
    //   38: invokevirtual 36	android/os/Parcel:readException	()V
    //   41: aload_2
    //   42: invokevirtual 44	android/os/Parcel:readInt	()I
    //   45: istore 5
    //   47: iload 5
    //   49: ifeq +30 -> 79
    //   52: getstatic 50	android/os/Bundle:CREATOR	Landroid/os/Parcelable$Creator;
    //   55: astore_3
    //   56: aload_3
    //   57: aload_2
    //   58: invokeinterface 56 2 0
    //   63: astore_3
    //   64: aload_3
    //   65: checkcast 46	android/os/Bundle
    //   68: astore_3
    //   69: aload_2
    //   70: invokevirtual 39	android/os/Parcel:recycle	()V
    //   73: aload_1
    //   74: invokevirtual 39	android/os/Parcel:recycle	()V
    //   77: aload_3
    //   78: areturn
    //   79: iconst_0
    //   80: istore 5
    //   82: aconst_null
    //   83: astore_3
    //   84: goto -15 -> 69
    //   87: astore_3
    //   88: aload_2
    //   89: invokevirtual 39	android/os/Parcel:recycle	()V
    //   92: aload_1
    //   93: invokevirtual 39	android/os/Parcel:recycle	()V
    //   96: aload_3
    //   97: athrow
    // Local variable table:
    //   start	length	slot	name	signature
    //   0	98	0	this	zza
    //   3	90	1	localParcel1	Parcel
    //   7	82	2	localParcel2	Parcel
    //   10	74	3	localObject1	Object
    //   87	10	3	localObject2	Object
    //   23	4	4	i	int
    //   45	36	5	j	int
    // Exception table:
    //   from	to	target	type
    //   12	16	87	finally
    //   16	20	87	finally
    //   30	37	87	finally
    //   37	41	87	finally
    //   41	45	87	finally
    //   52	55	87	finally
    //   57	63	87	finally
    //   64	68	87	finally
  }
}


/* Location:              C:\Users\haryo\Desktop\enjarify-master\presensi-enjarify.jar!\com\google\android\gms\internal\zzey$zza$zza.class
 * Java compiler version: 5 (49.0)
 * JD-Core Version:       0.7.1
 */