package com.google.android.gms.internal;

import android.os.IBinder;
import android.os.Parcel;

class zzfv$zza$zza
  implements zzfv
{
  private IBinder zzoz;
  
  zzfv$zza$zza(IBinder paramIBinder)
  {
    this.zzoz = paramIBinder;
  }
  
  public IBinder asBinder()
  {
    return this.zzoz;
  }
  
  public void onBackPressed()
  {
    Parcel localParcel1 = Parcel.obtain();
    Parcel localParcel2 = Parcel.obtain();
    Object localObject1 = "com.google.android.gms.ads.internal.overlay.client.IAdOverlay";
    try
    {
      localParcel1.writeInterfaceToken((String)localObject1);
      localObject1 = this.zzoz;
      int i = 10;
      ((IBinder)localObject1).transact(i, localParcel1, localParcel2, 0);
      localParcel2.readException();
      return;
    }
    finally
    {
      localParcel2.recycle();
      localParcel1.recycle();
    }
  }
  
  /* Error */
  public void onCreate(android.os.Bundle paramBundle)
  {
    // Byte code:
    //   0: invokestatic 20	android/os/Parcel:obtain	()Landroid/os/Parcel;
    //   3: astore_2
    //   4: invokestatic 20	android/os/Parcel:obtain	()Landroid/os/Parcel;
    //   7: astore_3
    //   8: ldc 22
    //   10: astore 4
    //   12: aload_2
    //   13: aload 4
    //   15: invokevirtual 26	android/os/Parcel:writeInterfaceToken	(Ljava/lang/String;)V
    //   18: aload_1
    //   19: ifnull +59 -> 78
    //   22: iconst_1
    //   23: istore 5
    //   25: aload_2
    //   26: iload 5
    //   28: invokevirtual 44	android/os/Parcel:writeInt	(I)V
    //   31: iconst_0
    //   32: istore 5
    //   34: aconst_null
    //   35: astore 4
    //   37: aload_1
    //   38: aload_2
    //   39: iconst_0
    //   40: invokevirtual 50	android/os/Bundle:writeToParcel	(Landroid/os/Parcel;I)V
    //   43: aload_0
    //   44: getfield 14	com/google/android/gms/internal/zzfv$zza$zza:zzoz	Landroid/os/IBinder;
    //   47: astore 4
    //   49: iconst_1
    //   50: istore 6
    //   52: aload 4
    //   54: iload 6
    //   56: aload_2
    //   57: aload_3
    //   58: iconst_0
    //   59: invokeinterface 33 5 0
    //   64: pop
    //   65: aload_3
    //   66: invokevirtual 36	android/os/Parcel:readException	()V
    //   69: aload_3
    //   70: invokevirtual 39	android/os/Parcel:recycle	()V
    //   73: aload_2
    //   74: invokevirtual 39	android/os/Parcel:recycle	()V
    //   77: return
    //   78: iconst_0
    //   79: istore 5
    //   81: aconst_null
    //   82: astore 4
    //   84: aload_2
    //   85: iconst_0
    //   86: invokevirtual 44	android/os/Parcel:writeInt	(I)V
    //   89: goto -46 -> 43
    //   92: astore 4
    //   94: aload_3
    //   95: invokevirtual 39	android/os/Parcel:recycle	()V
    //   98: aload_2
    //   99: invokevirtual 39	android/os/Parcel:recycle	()V
    //   102: aload 4
    //   104: athrow
    // Local variable table:
    //   start	length	slot	name	signature
    //   0	105	0	this	zza
    //   0	105	1	paramBundle	android.os.Bundle
    //   3	96	2	localParcel1	Parcel
    //   7	88	3	localParcel2	Parcel
    //   10	73	4	localObject1	Object
    //   92	11	4	localObject2	Object
    //   23	57	5	i	int
    //   50	5	6	j	int
    // Exception table:
    //   from	to	target	type
    //   13	18	92	finally
    //   26	31	92	finally
    //   39	43	92	finally
    //   43	47	92	finally
    //   58	65	92	finally
    //   65	69	92	finally
    //   85	89	92	finally
  }
  
  public void onDestroy()
  {
    Parcel localParcel1 = Parcel.obtain();
    Parcel localParcel2 = Parcel.obtain();
    Object localObject1 = "com.google.android.gms.ads.internal.overlay.client.IAdOverlay";
    try
    {
      localParcel1.writeInterfaceToken((String)localObject1);
      localObject1 = this.zzoz;
      int i = 8;
      ((IBinder)localObject1).transact(i, localParcel1, localParcel2, 0);
      localParcel2.readException();
      return;
    }
    finally
    {
      localParcel2.recycle();
      localParcel1.recycle();
    }
  }
  
  public void onPause()
  {
    Parcel localParcel1 = Parcel.obtain();
    Parcel localParcel2 = Parcel.obtain();
    Object localObject1 = "com.google.android.gms.ads.internal.overlay.client.IAdOverlay";
    try
    {
      localParcel1.writeInterfaceToken((String)localObject1);
      localObject1 = this.zzoz;
      int i = 5;
      ((IBinder)localObject1).transact(i, localParcel1, localParcel2, 0);
      localParcel2.readException();
      return;
    }
    finally
    {
      localParcel2.recycle();
      localParcel1.recycle();
    }
  }
  
  public void onRestart()
  {
    Parcel localParcel1 = Parcel.obtain();
    Parcel localParcel2 = Parcel.obtain();
    Object localObject1 = "com.google.android.gms.ads.internal.overlay.client.IAdOverlay";
    try
    {
      localParcel1.writeInterfaceToken((String)localObject1);
      localObject1 = this.zzoz;
      int i = 2;
      ((IBinder)localObject1).transact(i, localParcel1, localParcel2, 0);
      localParcel2.readException();
      return;
    }
    finally
    {
      localParcel2.recycle();
      localParcel1.recycle();
    }
  }
  
  public void onResume()
  {
    Parcel localParcel1 = Parcel.obtain();
    Parcel localParcel2 = Parcel.obtain();
    Object localObject1 = "com.google.android.gms.ads.internal.overlay.client.IAdOverlay";
    try
    {
      localParcel1.writeInterfaceToken((String)localObject1);
      localObject1 = this.zzoz;
      int i = 4;
      ((IBinder)localObject1).transact(i, localParcel1, localParcel2, 0);
      localParcel2.readException();
      return;
    }
    finally
    {
      localParcel2.recycle();
      localParcel1.recycle();
    }
  }
  
  /* Error */
  public void onSaveInstanceState(android.os.Bundle paramBundle)
  {
    // Byte code:
    //   0: invokestatic 20	android/os/Parcel:obtain	()Landroid/os/Parcel;
    //   3: astore_2
    //   4: invokestatic 20	android/os/Parcel:obtain	()Landroid/os/Parcel;
    //   7: astore_3
    //   8: ldc 22
    //   10: astore 4
    //   12: aload_2
    //   13: aload 4
    //   15: invokevirtual 26	android/os/Parcel:writeInterfaceToken	(Ljava/lang/String;)V
    //   18: aload_1
    //   19: ifnull +76 -> 95
    //   22: iconst_1
    //   23: istore 5
    //   25: aload_2
    //   26: iload 5
    //   28: invokevirtual 44	android/os/Parcel:writeInt	(I)V
    //   31: iconst_0
    //   32: istore 5
    //   34: aconst_null
    //   35: astore 4
    //   37: aload_1
    //   38: aload_2
    //   39: iconst_0
    //   40: invokevirtual 50	android/os/Bundle:writeToParcel	(Landroid/os/Parcel;I)V
    //   43: aload_0
    //   44: getfield 14	com/google/android/gms/internal/zzfv$zza$zza:zzoz	Landroid/os/IBinder;
    //   47: astore 4
    //   49: bipush 6
    //   51: istore 6
    //   53: aload 4
    //   55: iload 6
    //   57: aload_2
    //   58: aload_3
    //   59: iconst_0
    //   60: invokeinterface 33 5 0
    //   65: pop
    //   66: aload_3
    //   67: invokevirtual 36	android/os/Parcel:readException	()V
    //   70: aload_3
    //   71: invokevirtual 59	android/os/Parcel:readInt	()I
    //   74: istore 5
    //   76: iload 5
    //   78: ifeq +8 -> 86
    //   81: aload_1
    //   82: aload_3
    //   83: invokevirtual 63	android/os/Bundle:readFromParcel	(Landroid/os/Parcel;)V
    //   86: aload_3
    //   87: invokevirtual 39	android/os/Parcel:recycle	()V
    //   90: aload_2
    //   91: invokevirtual 39	android/os/Parcel:recycle	()V
    //   94: return
    //   95: iconst_0
    //   96: istore 5
    //   98: aconst_null
    //   99: astore 4
    //   101: aload_2
    //   102: iconst_0
    //   103: invokevirtual 44	android/os/Parcel:writeInt	(I)V
    //   106: goto -63 -> 43
    //   109: astore 4
    //   111: aload_3
    //   112: invokevirtual 39	android/os/Parcel:recycle	()V
    //   115: aload_2
    //   116: invokevirtual 39	android/os/Parcel:recycle	()V
    //   119: aload 4
    //   121: athrow
    // Local variable table:
    //   start	length	slot	name	signature
    //   0	122	0	this	zza
    //   0	122	1	paramBundle	android.os.Bundle
    //   3	113	2	localParcel1	Parcel
    //   7	105	3	localParcel2	Parcel
    //   10	90	4	localObject1	Object
    //   109	11	4	localObject2	Object
    //   23	74	5	i	int
    //   51	5	6	j	int
    // Exception table:
    //   from	to	target	type
    //   13	18	109	finally
    //   26	31	109	finally
    //   39	43	109	finally
    //   43	47	109	finally
    //   59	66	109	finally
    //   66	70	109	finally
    //   70	74	109	finally
    //   82	86	109	finally
    //   102	106	109	finally
  }
  
  public void onStart()
  {
    Parcel localParcel1 = Parcel.obtain();
    Parcel localParcel2 = Parcel.obtain();
    Object localObject1 = "com.google.android.gms.ads.internal.overlay.client.IAdOverlay";
    try
    {
      localParcel1.writeInterfaceToken((String)localObject1);
      localObject1 = this.zzoz;
      int i = 3;
      ((IBinder)localObject1).transact(i, localParcel1, localParcel2, 0);
      localParcel2.readException();
      return;
    }
    finally
    {
      localParcel2.recycle();
      localParcel1.recycle();
    }
  }
  
  public void onStop()
  {
    Parcel localParcel1 = Parcel.obtain();
    Parcel localParcel2 = Parcel.obtain();
    Object localObject1 = "com.google.android.gms.ads.internal.overlay.client.IAdOverlay";
    try
    {
      localParcel1.writeInterfaceToken((String)localObject1);
      localObject1 = this.zzoz;
      int i = 7;
      ((IBinder)localObject1).transact(i, localParcel1, localParcel2, 0);
      localParcel2.readException();
      return;
    }
    finally
    {
      localParcel2.recycle();
      localParcel1.recycle();
    }
  }
  
  public void zzaD()
  {
    Parcel localParcel1 = Parcel.obtain();
    Parcel localParcel2 = Parcel.obtain();
    Object localObject1 = "com.google.android.gms.ads.internal.overlay.client.IAdOverlay";
    try
    {
      localParcel1.writeInterfaceToken((String)localObject1);
      localObject1 = this.zzoz;
      int i = 9;
      ((IBinder)localObject1).transact(i, localParcel1, localParcel2, 0);
      localParcel2.readException();
      return;
    }
    finally
    {
      localParcel2.recycle();
      localParcel1.recycle();
    }
  }
  
  public boolean zzfn()
  {
    boolean bool = false;
    Object localObject1 = null;
    Parcel localParcel1 = Parcel.obtain();
    Parcel localParcel2 = Parcel.obtain();
    Object localObject3 = "com.google.android.gms.ads.internal.overlay.client.IAdOverlay";
    try
    {
      localParcel1.writeInterfaceToken((String)localObject3);
      localObject3 = this.zzoz;
      int i = 11;
      ((IBinder)localObject3).transact(i, localParcel1, localParcel2, 0);
      localParcel2.readException();
      int j = localParcel2.readInt();
      if (j != 0) {
        bool = true;
      }
      return bool;
    }
    finally
    {
      localParcel2.recycle();
      localParcel1.recycle();
    }
  }
}


/* Location:              C:\Users\haryo\Desktop\enjarify-master\presensi-enjarify.jar!\com\google\android\gms\internal\zzfv$zza$zza.class
 * Java compiler version: 5 (49.0)
 * JD-Core Version:       0.7.1
 */