package com.google.android.gms.internal;

import android.content.Context;
import com.google.android.gms.ads.internal.request.AdRequestInfoParcel;
import com.google.android.gms.ads.internal.request.AdResponseParcel;
import com.google.android.gms.ads.internal.request.zzj.zza;
import com.google.android.gms.ads.internal.request.zzk;
import com.google.android.gms.ads.internal.util.client.VersionInfoParcel;
import com.google.android.gms.ads.internal.zzr;
import java.util.Iterator;
import java.util.List;
import java.util.Map;
import java.util.Set;

public final class zzhd
  extends zzj.zza
{
  private static zzhd zzIQ;
  private static final Object zzqy;
  private final Context mContext;
  private final zzhc zzIR;
  private final zzbm zzIS;
  private final zzeg zzIT;
  
  static
  {
    Object localObject = new java/lang/Object;
    localObject.<init>();
    zzqy = localObject;
  }
  
  zzhd(Context paramContext, zzbm paramzzbm, zzhc paramzzhc)
  {
    this.mContext = paramContext;
    this.zzIR = paramzzhc;
    this.zzIS = paramzzbm;
    zzeg localzzeg = new com/google/android/gms/internal/zzeg;
    Context localContext = paramContext.getApplicationContext();
    if (localContext != null) {}
    for (localContext = paramContext.getApplicationContext();; localContext = paramContext)
    {
      VersionInfoParcel localVersionInfoParcel = new com/google/android/gms/ads/internal/util/client/VersionInfoParcel;
      localVersionInfoParcel.<init>(i, i, true);
      String str = paramzzbm.zzdp();
      zzhd.6 local6 = new com/google/android/gms/internal/zzhd$6;
      local6.<init>(this);
      zzeg.zzc localzzc = new com/google/android/gms/internal/zzeg$zzc;
      localzzc.<init>();
      localzzeg.<init>(localContext, localVersionInfoParcel, str, local6, localzzc);
      this.zzIT = localzzeg;
      return;
    }
  }
  
  /* Error */
  private static AdResponseParcel zza(Context paramContext, zzeg paramzzeg, zzbm paramzzbm, zzhc paramzzhc, AdRequestInfoParcel paramAdRequestInfoParcel)
  {
    // Byte code:
    //   0: ldc 68
    //   2: invokestatic 74	com/google/android/gms/internal/zzin:zzaI	(Ljava/lang/String;)V
    //   5: aload_0
    //   6: invokestatic 80	com/google/android/gms/internal/zzbt:initialize	(Landroid/content/Context;)V
    //   9: new 82	com/google/android/gms/internal/zzcb
    //   12: astore 5
    //   14: getstatic 86	com/google/android/gms/internal/zzbt:zzwg	Lcom/google/android/gms/internal/zzbp;
    //   17: invokevirtual 92	com/google/android/gms/internal/zzbp:get	()Ljava/lang/Object;
    //   20: checkcast 94	java/lang/Boolean
    //   23: astore 6
    //   25: aload 6
    //   27: invokevirtual 98	java/lang/Boolean:booleanValue	()Z
    //   30: istore 7
    //   32: ldc 100
    //   34: astore 8
    //   36: aload 4
    //   38: astore 9
    //   40: aload 4
    //   42: getfield 106	com/google/android/gms/ads/internal/request/AdRequestInfoParcel:zzrp	Lcom/google/android/gms/ads/internal/client/AdSizeParcel;
    //   45: getfield 112	com/google/android/gms/ads/internal/client/AdSizeParcel:zzuh	Ljava/lang/String;
    //   48: astore 10
    //   50: aload 5
    //   52: iload 7
    //   54: aload 8
    //   56: aload 10
    //   58: invokespecial 115	com/google/android/gms/internal/zzcb:<init>	(ZLjava/lang/String;Ljava/lang/String;)V
    //   61: aload 4
    //   63: getfield 119	com/google/android/gms/ads/internal/request/AdRequestInfoParcel:versionCode	I
    //   66: istore 7
    //   68: bipush 10
    //   70: istore 11
    //   72: iload 7
    //   74: iload 11
    //   76: if_icmple +78 -> 154
    //   79: aload 4
    //   81: getfield 124	com/google/android/gms/ads/internal/request/AdRequestInfoParcel:zzHL	J
    //   84: lstore 12
    //   86: iconst_m1
    //   87: i2l
    //   88: lstore 14
    //   90: lload 12
    //   92: lload 14
    //   94: lcmp
    //   95: istore 7
    //   97: iload 7
    //   99: ifeq +55 -> 154
    //   102: aload 4
    //   104: getfield 124	com/google/android/gms/ads/internal/request/AdRequestInfoParcel:zzHL	J
    //   107: lstore 12
    //   109: aload 5
    //   111: lload 12
    //   113: invokevirtual 128	com/google/android/gms/internal/zzcb:zzb	(J)Lcom/google/android/gms/internal/zzbz;
    //   116: astore 6
    //   118: iconst_1
    //   119: istore 11
    //   121: iload 11
    //   123: anewarray 130	java/lang/String
    //   126: astore 8
    //   128: iconst_0
    //   129: istore 16
    //   131: aconst_null
    //   132: astore 10
    //   134: ldc -124
    //   136: astore 17
    //   138: aload 8
    //   140: iconst_0
    //   141: aload 17
    //   143: aastore
    //   144: aload 5
    //   146: aload 6
    //   148: aload 8
    //   150: invokevirtual 136	com/google/android/gms/internal/zzcb:zza	(Lcom/google/android/gms/internal/zzbz;[Ljava/lang/String;)Z
    //   153: pop
    //   154: aload 5
    //   156: invokevirtual 140	com/google/android/gms/internal/zzcb:zzdB	()Lcom/google/android/gms/internal/zzbz;
    //   159: astore 18
    //   161: iconst_0
    //   162: istore 7
    //   164: aconst_null
    //   165: astore 6
    //   167: aload 4
    //   169: astore 9
    //   171: aload 4
    //   173: getfield 119	com/google/android/gms/ads/internal/request/AdRequestInfoParcel:versionCode	I
    //   176: istore 11
    //   178: iconst_4
    //   179: istore 16
    //   181: iload 11
    //   183: iload 16
    //   185: if_icmplt +1513 -> 1698
    //   188: aload 4
    //   190: getfield 145	com/google/android/gms/ads/internal/request/AdRequestInfoParcel:zzHA	Landroid/os/Bundle;
    //   193: astore 8
    //   195: aload 8
    //   197: ifnull +1501 -> 1698
    //   200: aload 4
    //   202: getfield 145	com/google/android/gms/ads/internal/request/AdRequestInfoParcel:zzHA	Landroid/os/Bundle;
    //   205: astore 6
    //   207: aload 6
    //   209: astore 8
    //   211: iconst_0
    //   212: istore 16
    //   214: aconst_null
    //   215: astore 10
    //   217: getstatic 148	com/google/android/gms/internal/zzbt:zzwp	Lcom/google/android/gms/internal/zzbp;
    //   220: invokevirtual 92	com/google/android/gms/internal/zzbp:get	()Ljava/lang/Object;
    //   223: checkcast 94	java/lang/Boolean
    //   226: astore 6
    //   228: aload 6
    //   230: invokevirtual 98	java/lang/Boolean:booleanValue	()Z
    //   233: istore 7
    //   235: iload 7
    //   237: ifeq +1448 -> 1685
    //   240: aload_3
    //   241: astore 9
    //   243: aload_3
    //   244: getfield 154	com/google/android/gms/internal/zzhc:zzIP	Lcom/google/android/gms/internal/zzhh;
    //   247: astore 6
    //   249: aload 6
    //   251: ifnull +1434 -> 1685
    //   254: aload 8
    //   256: ifnonnull +45 -> 301
    //   259: getstatic 157	com/google/android/gms/internal/zzbt:zzwq	Lcom/google/android/gms/internal/zzbp;
    //   262: invokevirtual 92	com/google/android/gms/internal/zzbp:get	()Ljava/lang/Object;
    //   265: checkcast 94	java/lang/Boolean
    //   268: astore 6
    //   270: aload 6
    //   272: invokevirtual 98	java/lang/Boolean:booleanValue	()Z
    //   275: istore 7
    //   277: iload 7
    //   279: ifeq +22 -> 301
    //   282: ldc -97
    //   284: astore 6
    //   286: aload 6
    //   288: invokestatic 162	com/google/android/gms/internal/zzin:v	(Ljava/lang/String;)V
    //   291: new 164	android/os/Bundle
    //   294: astore 8
    //   296: aload 8
    //   298: invokespecial 165	android/os/Bundle:<init>	()V
    //   301: aload 8
    //   303: ifnull +1369 -> 1672
    //   306: new 167	com/google/android/gms/internal/zzhd$1
    //   309: astore 6
    //   311: aload_3
    //   312: astore 9
    //   314: aload 6
    //   316: aload_3
    //   317: aload_0
    //   318: aload 4
    //   320: aload 8
    //   322: invokespecial 170	com/google/android/gms/internal/zzhd$1:<init>	(Lcom/google/android/gms/internal/zzhc;Landroid/content/Context;Lcom/google/android/gms/ads/internal/request/AdRequestInfoParcel;Landroid/os/Bundle;)V
    //   325: aload 6
    //   327: invokestatic 175	com/google/android/gms/internal/zziq:zza	(Ljava/util/concurrent/Callable;)Lcom/google/android/gms/internal/zzjg;
    //   330: astore 6
    //   332: aload 8
    //   334: astore 19
    //   336: aload 6
    //   338: astore 8
    //   340: aload_3
    //   341: astore 9
    //   343: aload_3
    //   344: getfield 179	com/google/android/gms/internal/zzhc:zzIK	Lcom/google/android/gms/internal/zzek;
    //   347: invokeinterface 184 1 0
    //   352: invokestatic 190	com/google/android/gms/ads/internal/zzr:zzbI	()Lcom/google/android/gms/internal/zzhk;
    //   355: astore 6
    //   357: aload_0
    //   358: astore 9
    //   360: aload 6
    //   362: aload_0
    //   363: invokevirtual 196	com/google/android/gms/internal/zzhk:zzE	(Landroid/content/Context;)Lcom/google/android/gms/internal/zzhj;
    //   366: astore 10
    //   368: aload 10
    //   370: getfield 201	com/google/android/gms/internal/zzhj:zzKc	I
    //   373: istore 7
    //   375: iconst_m1
    //   376: istore 20
    //   378: iload 7
    //   380: iload 20
    //   382: if_icmpne +26 -> 408
    //   385: ldc -53
    //   387: invokestatic 74	com/google/android/gms/internal/zzin:zzaI	(Ljava/lang/String;)V
    //   390: new 205	com/google/android/gms/ads/internal/request/AdResponseParcel
    //   393: astore 6
    //   395: iconst_2
    //   396: istore 11
    //   398: aload 6
    //   400: iload 11
    //   402: invokespecial 209	com/google/android/gms/ads/internal/request/AdResponseParcel:<init>	(I)V
    //   405: aload 6
    //   407: areturn
    //   408: aload 4
    //   410: astore 9
    //   412: aload 4
    //   414: getfield 119	com/google/android/gms/ads/internal/request/AdRequestInfoParcel:versionCode	I
    //   417: istore 7
    //   419: bipush 7
    //   421: istore 20
    //   423: iload 7
    //   425: iload 20
    //   427: if_icmplt +109 -> 536
    //   430: aload 4
    //   432: getfield 213	com/google/android/gms/ads/internal/request/AdRequestInfoParcel:zzHI	Ljava/lang/String;
    //   435: astore 6
    //   437: aload 6
    //   439: astore 21
    //   441: new 215	com/google/android/gms/internal/zzhf
    //   444: astore 22
    //   446: aload 4
    //   448: astore 9
    //   450: aload 4
    //   452: getfield 219	com/google/android/gms/ads/internal/request/AdRequestInfoParcel:applicationInfo	Landroid/content/pm/ApplicationInfo;
    //   455: getfield 224	android/content/pm/ApplicationInfo:packageName	Ljava/lang/String;
    //   458: astore 6
    //   460: aload 21
    //   462: astore 9
    //   464: aload 22
    //   466: aload 21
    //   468: aload 6
    //   470: invokespecial 227	com/google/android/gms/internal/zzhf:<init>	(Ljava/lang/String;Ljava/lang/String;)V
    //   473: aload 4
    //   475: astore 9
    //   477: aload 4
    //   479: getfield 231	com/google/android/gms/ads/internal/request/AdRequestInfoParcel:zzHt	Lcom/google/android/gms/ads/internal/client/AdRequestParcel;
    //   482: getfield 236	com/google/android/gms/ads/internal/client/AdRequestParcel:extras	Landroid/os/Bundle;
    //   485: astore 6
    //   487: aload 6
    //   489: ifnull +62 -> 551
    //   492: aload 4
    //   494: getfield 231	com/google/android/gms/ads/internal/request/AdRequestInfoParcel:zzHt	Lcom/google/android/gms/ads/internal/client/AdRequestParcel;
    //   497: getfield 236	com/google/android/gms/ads/internal/client/AdRequestParcel:extras	Landroid/os/Bundle;
    //   500: astore 6
    //   502: ldc -18
    //   504: astore 17
    //   506: aload 6
    //   508: aload 17
    //   510: invokevirtual 242	android/os/Bundle:getString	(Ljava/lang/String;)Ljava/lang/String;
    //   513: astore 6
    //   515: aload 6
    //   517: ifnull +34 -> 551
    //   520: aload_0
    //   521: astore 9
    //   523: aload_0
    //   524: aload 4
    //   526: aload 6
    //   528: invokestatic 247	com/google/android/gms/internal/zzhe:zza	(Landroid/content/Context;Lcom/google/android/gms/ads/internal/request/AdRequestInfoParcel;Ljava/lang/String;)Lcom/google/android/gms/ads/internal/request/AdResponseParcel;
    //   531: astore 6
    //   533: goto -128 -> 405
    //   536: invokestatic 253	java/util/UUID:randomUUID	()Ljava/util/UUID;
    //   539: invokevirtual 256	java/util/UUID:toString	()Ljava/lang/String;
    //   542: astore 6
    //   544: aload 6
    //   546: astore 21
    //   548: goto -107 -> 441
    //   551: aload_3
    //   552: astore 9
    //   554: aload_3
    //   555: getfield 179	com/google/android/gms/internal/zzhc:zzIK	Lcom/google/android/gms/internal/zzek;
    //   558: astore 6
    //   560: ldc2_w 257
    //   563: lstore 23
    //   565: aload 6
    //   567: lload 23
    //   569: invokeinterface 264 3 0
    //   574: astore 25
    //   576: aload_3
    //   577: getfield 268	com/google/android/gms/internal/zzhc:zzIL	Lcom/google/android/gms/internal/zzfy;
    //   580: astore 6
    //   582: aload 4
    //   584: astore 9
    //   586: aload 4
    //   588: getfield 271	com/google/android/gms/ads/internal/request/AdRequestInfoParcel:zzrj	Ljava/lang/String;
    //   591: astore 17
    //   593: aload 4
    //   595: getfield 275	com/google/android/gms/ads/internal/request/AdRequestInfoParcel:zzHu	Landroid/content/pm/PackageInfo;
    //   598: getfield 278	android/content/pm/PackageInfo:packageName	Ljava/lang/String;
    //   601: astore 26
    //   603: aload_0
    //   604: astore 9
    //   606: aload 6
    //   608: aload_0
    //   609: aload 17
    //   611: aload 26
    //   613: invokeinterface 284 4 0
    //   618: astore 27
    //   620: aload_3
    //   621: astore 9
    //   623: aload_3
    //   624: getfield 288	com/google/android/gms/internal/zzhc:zzII	Lcom/google/android/gms/internal/zzbo;
    //   627: astore 6
    //   629: aload 4
    //   631: astore 9
    //   633: aload 6
    //   635: aload 4
    //   637: invokeinterface 293 2 0
    //   642: astore 28
    //   644: aload_3
    //   645: astore 9
    //   647: aload_3
    //   648: getfield 297	com/google/android/gms/internal/zzhc:zzIM	Lcom/google/android/gms/internal/zzie;
    //   651: astore 6
    //   653: aload 4
    //   655: astore 9
    //   657: aload 6
    //   659: aload 4
    //   661: invokeinterface 303 2 0
    //   666: astore 29
    //   668: aload_3
    //   669: astore 9
    //   671: aload_3
    //   672: getfield 307	com/google/android/gms/internal/zzhc:zzIN	Lcom/google/android/gms/internal/zzhn;
    //   675: astore 6
    //   677: aload_0
    //   678: astore 9
    //   680: aload 6
    //   682: aload_0
    //   683: invokeinterface 313 2 0
    //   688: astore 17
    //   690: aload 8
    //   692: ifnull +66 -> 758
    //   695: ldc_w 315
    //   698: astore 6
    //   700: aload 6
    //   702: invokestatic 162	com/google/android/gms/internal/zzin:v	(Ljava/lang/String;)V
    //   705: getstatic 318	com/google/android/gms/internal/zzbt:zzwr	Lcom/google/android/gms/internal/zzbp;
    //   708: astore 6
    //   710: aload 6
    //   712: invokevirtual 92	com/google/android/gms/internal/zzbp:get	()Ljava/lang/Object;
    //   715: astore 6
    //   717: aload 6
    //   719: checkcast 320	java/lang/Long
    //   722: astore 6
    //   724: aload 6
    //   726: invokevirtual 324	java/lang/Long:longValue	()J
    //   729: lstore 30
    //   731: getstatic 330	java/util/concurrent/TimeUnit:MILLISECONDS	Ljava/util/concurrent/TimeUnit;
    //   734: astore 6
    //   736: aload 8
    //   738: lload 30
    //   740: aload 6
    //   742: invokeinterface 335 4 0
    //   747: pop
    //   748: ldc_w 337
    //   751: astore 6
    //   753: aload 6
    //   755: invokestatic 162	com/google/android/gms/internal/zzin:v	(Ljava/lang/String;)V
    //   758: aload_0
    //   759: astore 6
    //   761: aload 4
    //   763: astore 8
    //   765: aload_2
    //   766: astore 26
    //   768: aload_0
    //   769: aload 4
    //   771: aload 10
    //   773: aload 17
    //   775: aload 25
    //   777: aload_2
    //   778: aload 27
    //   780: aload 29
    //   782: aload 28
    //   784: aload 19
    //   786: invokestatic 340	com/google/android/gms/internal/zzhe:zza	(Landroid/content/Context;Lcom/google/android/gms/ads/internal/request/AdRequestInfoParcel;Lcom/google/android/gms/internal/zzhj;Lcom/google/android/gms/internal/zzhn$zza;Landroid/location/Location;Lcom/google/android/gms/internal/zzbm;Ljava/lang/String;Ljava/lang/String;Ljava/util/List;Landroid/os/Bundle;)Lorg/json/JSONObject;
    //   789: astore 6
    //   791: aload 4
    //   793: astore 9
    //   795: aload 4
    //   797: getfield 119	com/google/android/gms/ads/internal/request/AdRequestInfoParcel:versionCode	I
    //   800: istore 11
    //   802: bipush 7
    //   804: istore 16
    //   806: iload 11
    //   808: iload 16
    //   810: if_icmpge +22 -> 832
    //   813: ldc_w 342
    //   816: astore 8
    //   818: aload 21
    //   820: astore 9
    //   822: aload 6
    //   824: aload 8
    //   826: aload 21
    //   828: invokevirtual 348	org/json/JSONObject:put	(Ljava/lang/String;Ljava/lang/Object;)Lorg/json/JSONObject;
    //   831: pop
    //   832: aload 6
    //   834: ifnonnull +55 -> 889
    //   837: new 205	com/google/android/gms/ads/internal/request/AdResponseParcel
    //   840: astore 6
    //   842: iconst_0
    //   843: istore 11
    //   845: aconst_null
    //   846: astore 8
    //   848: aload 6
    //   850: iconst_0
    //   851: invokespecial 209	com/google/android/gms/ads/internal/request/AdResponseParcel:<init>	(I)V
    //   854: goto -449 -> 405
    //   857: astore 6
    //   859: ldc_w 350
    //   862: astore 8
    //   864: aload 8
    //   866: aload 6
    //   868: invokestatic 353	com/google/android/gms/internal/zzin:zzd	(Ljava/lang/String;Ljava/lang/Throwable;)V
    //   871: goto -113 -> 758
    //   874: astore 6
    //   876: ldc_w 355
    //   879: astore 6
    //   881: aload 6
    //   883: invokestatic 74	com/google/android/gms/internal/zzin:zzaI	(Ljava/lang/String;)V
    //   886: goto -128 -> 758
    //   889: aload 6
    //   891: invokevirtual 356	org/json/JSONObject:toString	()Ljava/lang/String;
    //   894: astore 26
    //   896: iconst_1
    //   897: anewarray 130	java/lang/String
    //   900: astore 6
    //   902: iconst_0
    //   903: istore 11
    //   905: aconst_null
    //   906: astore 8
    //   908: ldc_w 358
    //   911: astore 10
    //   913: aload 6
    //   915: iconst_0
    //   916: aload 10
    //   918: aastore
    //   919: aload 18
    //   921: astore 9
    //   923: aload 5
    //   925: aload 18
    //   927: aload 6
    //   929: invokevirtual 136	com/google/android/gms/internal/zzcb:zza	(Lcom/google/android/gms/internal/zzbz;[Ljava/lang/String;)Z
    //   932: pop
    //   933: aload 5
    //   935: invokevirtual 140	com/google/android/gms/internal/zzcb:zzdB	()Lcom/google/android/gms/internal/zzbz;
    //   938: astore 25
    //   940: getstatic 361	com/google/android/gms/internal/zzbt:zzvC	Lcom/google/android/gms/internal/zzbp;
    //   943: invokevirtual 92	com/google/android/gms/internal/zzbp:get	()Ljava/lang/Object;
    //   946: checkcast 94	java/lang/Boolean
    //   949: astore 6
    //   951: aload 6
    //   953: invokevirtual 98	java/lang/Boolean:booleanValue	()Z
    //   956: istore 7
    //   958: iload 7
    //   960: ifeq +148 -> 1108
    //   963: getstatic 367	com/google/android/gms/internal/zzir:zzMc	Landroid/os/Handler;
    //   966: astore 29
    //   968: new 369	com/google/android/gms/internal/zzhd$2
    //   971: astore 6
    //   973: aload_1
    //   974: astore 8
    //   976: aload 22
    //   978: astore 10
    //   980: aload 5
    //   982: astore 17
    //   984: aload 6
    //   986: aload_1
    //   987: aload 22
    //   989: aload 5
    //   991: aload 25
    //   993: aload 26
    //   995: invokespecial 372	com/google/android/gms/internal/zzhd$2:<init>	(Lcom/google/android/gms/internal/zzeg;Lcom/google/android/gms/internal/zzhf;Lcom/google/android/gms/internal/zzcb;Lcom/google/android/gms/internal/zzbz;Ljava/lang/String;)V
    //   998: aload 29
    //   1000: aload 6
    //   1002: invokevirtual 378	android/os/Handler:post	(Ljava/lang/Runnable;)Z
    //   1005: pop
    //   1006: aload 22
    //   1008: invokevirtual 382	com/google/android/gms/internal/zzhf:zzgC	()Ljava/util/concurrent/Future;
    //   1011: astore 6
    //   1013: bipush 10
    //   1015: i2l
    //   1016: lstore 14
    //   1018: getstatic 387	java/util/concurrent/TimeUnit:SECONDS	Ljava/util/concurrent/TimeUnit;
    //   1021: astore 8
    //   1023: aload 6
    //   1025: lload 14
    //   1027: aload 8
    //   1029: invokeinterface 335 4 0
    //   1034: astore 6
    //   1036: aload 6
    //   1038: astore 9
    //   1040: aload 6
    //   1042: checkcast 389	com/google/android/gms/internal/zzhi
    //   1045: astore 9
    //   1047: aload 9
    //   1049: astore 29
    //   1051: aload 9
    //   1053: ifnonnull +158 -> 1211
    //   1056: new 205	com/google/android/gms/ads/internal/request/AdResponseParcel
    //   1059: astore 6
    //   1061: iconst_0
    //   1062: istore 11
    //   1064: aconst_null
    //   1065: astore 8
    //   1067: aload 6
    //   1069: iconst_0
    //   1070: invokespecial 209	com/google/android/gms/ads/internal/request/AdResponseParcel:<init>	(I)V
    //   1073: getstatic 367	com/google/android/gms/internal/zzir:zzMc	Landroid/os/Handler;
    //   1076: astore 8
    //   1078: new 391	com/google/android/gms/internal/zzhd$4
    //   1081: astore 10
    //   1083: aload_3
    //   1084: astore 9
    //   1086: aload 10
    //   1088: aload_3
    //   1089: aload_0
    //   1090: aload 22
    //   1092: aload 4
    //   1094: invokespecial 394	com/google/android/gms/internal/zzhd$4:<init>	(Lcom/google/android/gms/internal/zzhc;Landroid/content/Context;Lcom/google/android/gms/internal/zzhf;Lcom/google/android/gms/ads/internal/request/AdRequestInfoParcel;)V
    //   1097: aload 8
    //   1099: aload 10
    //   1101: invokevirtual 378	android/os/Handler:post	(Ljava/lang/Runnable;)Z
    //   1104: pop
    //   1105: goto -700 -> 405
    //   1108: getstatic 367	com/google/android/gms/internal/zzir:zzMc	Landroid/os/Handler;
    //   1111: astore 6
    //   1113: new 396	com/google/android/gms/internal/zzhd$3
    //   1116: astore 29
    //   1118: aload_0
    //   1119: astore 28
    //   1121: aload 4
    //   1123: astore 19
    //   1125: aload 25
    //   1127: astore 21
    //   1129: aload 29
    //   1131: aload_0
    //   1132: aload 4
    //   1134: aload 22
    //   1136: aload 5
    //   1138: aload 25
    //   1140: aload 26
    //   1142: aload_2
    //   1143: invokespecial 399	com/google/android/gms/internal/zzhd$3:<init>	(Landroid/content/Context;Lcom/google/android/gms/ads/internal/request/AdRequestInfoParcel;Lcom/google/android/gms/internal/zzhf;Lcom/google/android/gms/internal/zzcb;Lcom/google/android/gms/internal/zzbz;Ljava/lang/String;Lcom/google/android/gms/internal/zzbm;)V
    //   1146: aload 6
    //   1148: aload 29
    //   1150: invokevirtual 378	android/os/Handler:post	(Ljava/lang/Runnable;)Z
    //   1153: pop
    //   1154: goto -148 -> 1006
    //   1157: astore 6
    //   1159: new 205	com/google/android/gms/ads/internal/request/AdResponseParcel
    //   1162: astore 6
    //   1164: iconst_0
    //   1165: istore 11
    //   1167: aconst_null
    //   1168: astore 8
    //   1170: aload 6
    //   1172: iconst_0
    //   1173: invokespecial 209	com/google/android/gms/ads/internal/request/AdResponseParcel:<init>	(I)V
    //   1176: getstatic 367	com/google/android/gms/internal/zzir:zzMc	Landroid/os/Handler;
    //   1179: astore 8
    //   1181: new 391	com/google/android/gms/internal/zzhd$4
    //   1184: astore 10
    //   1186: aload_3
    //   1187: astore 9
    //   1189: aload 10
    //   1191: aload_3
    //   1192: aload_0
    //   1193: aload 22
    //   1195: aload 4
    //   1197: invokespecial 394	com/google/android/gms/internal/zzhd$4:<init>	(Lcom/google/android/gms/internal/zzhc;Landroid/content/Context;Lcom/google/android/gms/internal/zzhf;Lcom/google/android/gms/ads/internal/request/AdRequestInfoParcel;)V
    //   1200: aload 8
    //   1202: aload 10
    //   1204: invokevirtual 378	android/os/Handler:post	(Ljava/lang/Runnable;)Z
    //   1207: pop
    //   1208: goto -803 -> 405
    //   1211: aload 9
    //   1213: invokevirtual 403	com/google/android/gms/internal/zzhi:getErrorCode	()I
    //   1216: istore 7
    //   1218: bipush -2
    //   1220: istore 11
    //   1222: iload 7
    //   1224: iload 11
    //   1226: if_icmpeq +57 -> 1283
    //   1229: new 205	com/google/android/gms/ads/internal/request/AdResponseParcel
    //   1232: astore 6
    //   1234: aload 9
    //   1236: invokevirtual 403	com/google/android/gms/internal/zzhi:getErrorCode	()I
    //   1239: istore 11
    //   1241: aload 6
    //   1243: iload 11
    //   1245: invokespecial 209	com/google/android/gms/ads/internal/request/AdResponseParcel:<init>	(I)V
    //   1248: getstatic 367	com/google/android/gms/internal/zzir:zzMc	Landroid/os/Handler;
    //   1251: astore 8
    //   1253: new 391	com/google/android/gms/internal/zzhd$4
    //   1256: astore 10
    //   1258: aload_3
    //   1259: astore 9
    //   1261: aload 10
    //   1263: aload_3
    //   1264: aload_0
    //   1265: aload 22
    //   1267: aload 4
    //   1269: invokespecial 394	com/google/android/gms/internal/zzhd$4:<init>	(Lcom/google/android/gms/internal/zzhc;Landroid/content/Context;Lcom/google/android/gms/internal/zzhf;Lcom/google/android/gms/ads/internal/request/AdRequestInfoParcel;)V
    //   1272: aload 8
    //   1274: aload 10
    //   1276: invokevirtual 378	android/os/Handler:post	(Ljava/lang/Runnable;)Z
    //   1279: pop
    //   1280: goto -875 -> 405
    //   1283: aload 5
    //   1285: invokevirtual 406	com/google/android/gms/internal/zzcb:zzdE	()Lcom/google/android/gms/internal/zzbz;
    //   1288: astore 6
    //   1290: aload 6
    //   1292: ifnull +47 -> 1339
    //   1295: aload 5
    //   1297: invokevirtual 406	com/google/android/gms/internal/zzcb:zzdE	()Lcom/google/android/gms/internal/zzbz;
    //   1300: astore 6
    //   1302: iconst_1
    //   1303: istore 11
    //   1305: iload 11
    //   1307: anewarray 130	java/lang/String
    //   1310: astore 8
    //   1312: iconst_0
    //   1313: istore 16
    //   1315: aconst_null
    //   1316: astore 10
    //   1318: ldc_w 408
    //   1321: astore 17
    //   1323: aload 8
    //   1325: iconst_0
    //   1326: aload 17
    //   1328: aastore
    //   1329: aload 5
    //   1331: aload 6
    //   1333: aload 8
    //   1335: invokevirtual 136	com/google/android/gms/internal/zzcb:zza	(Lcom/google/android/gms/internal/zzbz;[Ljava/lang/String;)Z
    //   1338: pop
    //   1339: aconst_null
    //   1340: astore 25
    //   1342: aload 29
    //   1344: invokevirtual 411	com/google/android/gms/internal/zzhi:zzgG	()Z
    //   1347: istore 7
    //   1349: iload 7
    //   1351: ifeq +41 -> 1392
    //   1354: aload_3
    //   1355: astore 9
    //   1357: aload_3
    //   1358: getfield 415	com/google/android/gms/internal/zzhc:zzIH	Lcom/google/android/gms/internal/zzib;
    //   1361: astore 6
    //   1363: aload 4
    //   1365: astore 9
    //   1367: aload 4
    //   1369: getfield 275	com/google/android/gms/ads/internal/request/AdRequestInfoParcel:zzHu	Landroid/content/pm/PackageInfo;
    //   1372: astore 8
    //   1374: aload 8
    //   1376: getfield 278	android/content/pm/PackageInfo:packageName	Ljava/lang/String;
    //   1379: astore 8
    //   1381: aload 6
    //   1383: aload 8
    //   1385: invokeinterface 420 2 0
    //   1390: astore 25
    //   1392: aload 4
    //   1394: astore 9
    //   1396: aload 4
    //   1398: getfield 424	com/google/android/gms/ads/internal/request/AdRequestInfoParcel:zzrl	Lcom/google/android/gms/ads/internal/util/client/VersionInfoParcel;
    //   1401: astore 6
    //   1403: aload 6
    //   1405: getfield 427	com/google/android/gms/ads/internal/util/client/VersionInfoParcel:afmaVersion	Ljava/lang/String;
    //   1408: astore 10
    //   1410: aload 29
    //   1412: invokevirtual 430	com/google/android/gms/internal/zzhi:getUrl	()Ljava/lang/String;
    //   1415: astore 17
    //   1417: aload 29
    //   1419: invokevirtual 433	com/google/android/gms/internal/zzhi:zzgH	()Z
    //   1422: istore 7
    //   1424: iload 7
    //   1426: ifeq +193 -> 1619
    //   1429: aload 27
    //   1431: astore 26
    //   1433: aload 4
    //   1435: astore 6
    //   1437: aload_0
    //   1438: astore 8
    //   1440: aload 29
    //   1442: astore 27
    //   1444: aload 5
    //   1446: astore 29
    //   1448: aload_3
    //   1449: astore 28
    //   1451: aload 4
    //   1453: aload_0
    //   1454: aload 10
    //   1456: aload 17
    //   1458: aload 25
    //   1460: aload 26
    //   1462: aload 27
    //   1464: aload 5
    //   1466: aload_3
    //   1467: invokestatic 436	com/google/android/gms/internal/zzhd:zza	(Lcom/google/android/gms/ads/internal/request/AdRequestInfoParcel;Landroid/content/Context;Ljava/lang/String;Ljava/lang/String;Ljava/lang/String;Ljava/lang/String;Lcom/google/android/gms/internal/zzhi;Lcom/google/android/gms/internal/zzcb;Lcom/google/android/gms/internal/zzhc;)Lcom/google/android/gms/ads/internal/request/AdResponseParcel;
    //   1470: astore 6
    //   1472: aload 6
    //   1474: getfield 439	com/google/android/gms/ads/internal/request/AdResponseParcel:zzIf	I
    //   1477: istore 11
    //   1479: iconst_1
    //   1480: istore 16
    //   1482: iload 11
    //   1484: iload 16
    //   1486: if_icmpne +43 -> 1529
    //   1489: aload_3
    //   1490: astore 9
    //   1492: aload_3
    //   1493: getfield 268	com/google/android/gms/internal/zzhc:zzIL	Lcom/google/android/gms/internal/zzfy;
    //   1496: astore 8
    //   1498: aload 4
    //   1500: astore 9
    //   1502: aload 4
    //   1504: getfield 275	com/google/android/gms/ads/internal/request/AdRequestInfoParcel:zzHu	Landroid/content/pm/PackageInfo;
    //   1507: astore 10
    //   1509: aload 10
    //   1511: getfield 278	android/content/pm/PackageInfo:packageName	Ljava/lang/String;
    //   1514: astore 10
    //   1516: aload_0
    //   1517: astore 9
    //   1519: aload 8
    //   1521: aload_0
    //   1522: aload 10
    //   1524: invokeinterface 443 3 0
    //   1529: iconst_1
    //   1530: istore 11
    //   1532: iload 11
    //   1534: anewarray 130	java/lang/String
    //   1537: astore 8
    //   1539: iconst_0
    //   1540: istore 16
    //   1542: aconst_null
    //   1543: astore 10
    //   1545: ldc_w 445
    //   1548: astore 17
    //   1550: aload 8
    //   1552: iconst_0
    //   1553: aload 17
    //   1555: aastore
    //   1556: aload 18
    //   1558: astore 9
    //   1560: aload 5
    //   1562: aload 18
    //   1564: aload 8
    //   1566: invokevirtual 136	com/google/android/gms/internal/zzcb:zza	(Lcom/google/android/gms/internal/zzbz;[Ljava/lang/String;)Z
    //   1569: pop
    //   1570: aload 5
    //   1572: invokevirtual 448	com/google/android/gms/internal/zzcb:zzdD	()Ljava/lang/String;
    //   1575: astore 8
    //   1577: aload 6
    //   1579: aload 8
    //   1581: putfield 451	com/google/android/gms/ads/internal/request/AdResponseParcel:zzIh	Ljava/lang/String;
    //   1584: getstatic 367	com/google/android/gms/internal/zzir:zzMc	Landroid/os/Handler;
    //   1587: astore 8
    //   1589: new 391	com/google/android/gms/internal/zzhd$4
    //   1592: astore 10
    //   1594: aload_3
    //   1595: astore 9
    //   1597: aload 10
    //   1599: aload_3
    //   1600: aload_0
    //   1601: aload 22
    //   1603: aload 4
    //   1605: invokespecial 394	com/google/android/gms/internal/zzhd$4:<init>	(Lcom/google/android/gms/internal/zzhc;Landroid/content/Context;Lcom/google/android/gms/internal/zzhf;Lcom/google/android/gms/ads/internal/request/AdRequestInfoParcel;)V
    //   1608: aload 8
    //   1610: aload 10
    //   1612: invokevirtual 378	android/os/Handler:post	(Ljava/lang/Runnable;)Z
    //   1615: pop
    //   1616: goto -1211 -> 405
    //   1619: aconst_null
    //   1620: astore 26
    //   1622: goto -189 -> 1433
    //   1625: astore 6
    //   1627: getstatic 367	com/google/android/gms/internal/zzir:zzMc	Landroid/os/Handler;
    //   1630: astore 8
    //   1632: new 391	com/google/android/gms/internal/zzhd$4
    //   1635: astore 10
    //   1637: aload_3
    //   1638: astore 9
    //   1640: aload 10
    //   1642: aload_3
    //   1643: aload_0
    //   1644: aload 22
    //   1646: aload 4
    //   1648: invokespecial 394	com/google/android/gms/internal/zzhd$4:<init>	(Lcom/google/android/gms/internal/zzhc;Landroid/content/Context;Lcom/google/android/gms/internal/zzhf;Lcom/google/android/gms/ads/internal/request/AdRequestInfoParcel;)V
    //   1651: aload 8
    //   1653: aload 10
    //   1655: invokevirtual 378	android/os/Handler:post	(Ljava/lang/Runnable;)Z
    //   1658: pop
    //   1659: aload 6
    //   1661: athrow
    //   1662: astore 8
    //   1664: goto -832 -> 832
    //   1667: astore 6
    //   1669: goto -810 -> 859
    //   1672: aload 8
    //   1674: astore 19
    //   1676: iconst_0
    //   1677: istore 11
    //   1679: aconst_null
    //   1680: astore 8
    //   1682: goto -1342 -> 340
    //   1685: aload 8
    //   1687: astore 19
    //   1689: iconst_0
    //   1690: istore 11
    //   1692: aconst_null
    //   1693: astore 8
    //   1695: goto -1355 -> 340
    //   1698: iconst_0
    //   1699: istore 11
    //   1701: aconst_null
    //   1702: astore 8
    //   1704: goto -1493 -> 211
    // Local variable table:
    //   start	length	slot	name	signature
    //   0	1707	0	paramContext	Context
    //   0	1707	1	paramzzeg	zzeg
    //   0	1707	2	paramzzbm	zzbm
    //   0	1707	3	paramzzhc	zzhc
    //   0	1707	4	paramAdRequestInfoParcel	AdRequestInfoParcel
    //   12	1559	5	localzzcb	zzcb
    //   23	826	6	localObject1	Object
    //   857	10	6	localInterruptedException	InterruptedException
    //   874	1	6	localTimeoutException	java.util.concurrent.TimeoutException
    //   879	268	6	localObject2	Object
    //   1157	1	6	localException	Exception
    //   1162	416	6	localObject3	Object
    //   1625	35	6	localObject4	Object
    //   1667	1	6	localExecutionException	java.util.concurrent.ExecutionException
    //   30	23	7	bool1	boolean
    //   66	11	7	i	int
    //   95	183	7	bool2	boolean
    //   373	55	7	j	int
    //   956	3	7	bool3	boolean
    //   1216	11	7	k	int
    //   1347	78	7	bool4	boolean
    //   34	1618	8	localObject5	Object
    //   1662	11	8	localJSONException	org.json.JSONException
    //   1680	23	8	localObject6	Object
    //   38	1601	9	localObject7	Object
    //   48	1606	10	localObject8	Object
    //   70	1630	11	m	int
    //   84	28	12	l1	long
    //   88	938	14	l2	long
    //   129	1412	16	n	int
    //   136	1418	17	localObject9	Object
    //   159	1404	18	localzzbz	zzbz
    //   334	1354	19	localObject10	Object
    //   376	52	20	i1	int
    //   439	689	21	localObject11	Object
    //   444	1201	22	localzzhf	zzhf
    //   563	5	23	l3	long
    //   574	885	25	localObject12	Object
    //   601	1020	26	localObject13	Object
    //   618	845	27	localObject14	Object
    //   642	808	28	localObject15	Object
    //   666	781	29	localObject16	Object
    //   729	10	30	l4	long
    // Exception table:
    //   from	to	target	type
    //   700	705	857	java/lang/InterruptedException
    //   705	708	857	java/lang/InterruptedException
    //   710	715	857	java/lang/InterruptedException
    //   717	722	857	java/lang/InterruptedException
    //   724	729	857	java/lang/InterruptedException
    //   731	734	857	java/lang/InterruptedException
    //   740	748	857	java/lang/InterruptedException
    //   753	758	857	java/lang/InterruptedException
    //   700	705	874	java/util/concurrent/TimeoutException
    //   705	708	874	java/util/concurrent/TimeoutException
    //   710	715	874	java/util/concurrent/TimeoutException
    //   717	722	874	java/util/concurrent/TimeoutException
    //   724	729	874	java/util/concurrent/TimeoutException
    //   731	734	874	java/util/concurrent/TimeoutException
    //   740	748	874	java/util/concurrent/TimeoutException
    //   753	758	874	java/util/concurrent/TimeoutException
    //   1006	1011	1157	java/lang/Exception
    //   1018	1021	1157	java/lang/Exception
    //   1027	1034	1157	java/lang/Exception
    //   1040	1045	1157	java/lang/Exception
    //   1006	1011	1625	finally
    //   1018	1021	1625	finally
    //   1027	1034	1625	finally
    //   1040	1045	1625	finally
    //   1056	1059	1625	finally
    //   1069	1073	1625	finally
    //   1159	1162	1625	finally
    //   1172	1176	1625	finally
    //   1211	1216	1625	finally
    //   1229	1232	1625	finally
    //   1234	1239	1625	finally
    //   1243	1248	1625	finally
    //   1283	1288	1625	finally
    //   1295	1300	1625	finally
    //   1305	1310	1625	finally
    //   1326	1329	1625	finally
    //   1333	1339	1625	finally
    //   1342	1347	1625	finally
    //   1357	1361	1625	finally
    //   1367	1372	1625	finally
    //   1374	1379	1625	finally
    //   1383	1390	1625	finally
    //   1396	1401	1625	finally
    //   1403	1408	1625	finally
    //   1410	1415	1625	finally
    //   1417	1422	1625	finally
    //   1466	1470	1625	finally
    //   1472	1477	1625	finally
    //   1492	1496	1625	finally
    //   1502	1507	1625	finally
    //   1509	1514	1625	finally
    //   1522	1529	1625	finally
    //   1532	1537	1625	finally
    //   1553	1556	1625	finally
    //   1564	1570	1625	finally
    //   1570	1575	1625	finally
    //   1579	1584	1625	finally
    //   826	832	1662	org/json/JSONException
    //   700	705	1667	java/util/concurrent/ExecutionException
    //   705	708	1667	java/util/concurrent/ExecutionException
    //   710	715	1667	java/util/concurrent/ExecutionException
    //   717	722	1667	java/util/concurrent/ExecutionException
    //   724	729	1667	java/util/concurrent/ExecutionException
    //   731	734	1667	java/util/concurrent/ExecutionException
    //   740	748	1667	java/util/concurrent/ExecutionException
    //   753	758	1667	java/util/concurrent/ExecutionException
  }
  
  /* Error */
  public static AdResponseParcel zza(AdRequestInfoParcel paramAdRequestInfoParcel, Context paramContext, String paramString1, String paramString2, String paramString3, String paramString4, zzhi paramzzhi, zzcb paramzzcb, zzhc paramzzhc)
  {
    // Byte code:
    //   0: aload 7
    //   2: ifnull +543 -> 545
    //   5: aload 7
    //   7: invokevirtual 140	com/google/android/gms/internal/zzcb:zzdB	()Lcom/google/android/gms/internal/zzbz;
    //   10: astore 9
    //   12: aload 9
    //   14: astore 10
    //   16: new 463	com/google/android/gms/internal/zzhg
    //   19: astore 11
    //   21: aload 11
    //   23: aload_0
    //   24: invokespecial 466	com/google/android/gms/internal/zzhg:<init>	(Lcom/google/android/gms/ads/internal/request/AdRequestInfoParcel;)V
    //   27: new 468	java/lang/StringBuilder
    //   30: astore 9
    //   32: aload 9
    //   34: invokespecial 469	java/lang/StringBuilder:<init>	()V
    //   37: ldc_w 471
    //   40: astore 12
    //   42: aload 9
    //   44: aload 12
    //   46: invokevirtual 475	java/lang/StringBuilder:append	(Ljava/lang/String;)Ljava/lang/StringBuilder;
    //   49: astore 9
    //   51: aload 9
    //   53: aload_3
    //   54: invokevirtual 475	java/lang/StringBuilder:append	(Ljava/lang/String;)Ljava/lang/StringBuilder;
    //   57: astore 9
    //   59: aload 9
    //   61: invokevirtual 476	java/lang/StringBuilder:toString	()Ljava/lang/String;
    //   64: astore 9
    //   66: aload 9
    //   68: invokestatic 74	com/google/android/gms/internal/zzin:zzaI	(Ljava/lang/String;)V
    //   71: new 478	java/net/URL
    //   74: astore 12
    //   76: aload 12
    //   78: aload_3
    //   79: invokespecial 480	java/net/URL:<init>	(Ljava/lang/String;)V
    //   82: aconst_null
    //   83: astore 9
    //   85: invokestatic 484	com/google/android/gms/ads/internal/zzr:zzbG	()Lcom/google/android/gms/internal/zzmq;
    //   88: astore 13
    //   90: aload 13
    //   92: invokeinterface 489 1 0
    //   97: lstore 14
    //   99: iconst_0
    //   100: istore 16
    //   102: aconst_null
    //   103: astore 17
    //   105: aload 12
    //   107: astore 18
    //   109: aload 8
    //   111: ifnull +17 -> 128
    //   114: aload 8
    //   116: getfield 493	com/google/android/gms/internal/zzhc:zzIO	Lcom/google/android/gms/internal/zzhm;
    //   119: astore 9
    //   121: aload 9
    //   123: invokeinterface 498 1 0
    //   128: aload 18
    //   130: invokevirtual 502	java/net/URL:openConnection	()Ljava/net/URLConnection;
    //   133: astore 9
    //   135: aload 9
    //   137: checkcast 504	java/net/HttpURLConnection
    //   140: astore 9
    //   142: invokestatic 508	com/google/android/gms/ads/internal/zzr:zzbC	()Lcom/google/android/gms/internal/zzir;
    //   145: astore 12
    //   147: iconst_0
    //   148: istore 19
    //   150: aconst_null
    //   151: astore 13
    //   153: aload 12
    //   155: aload_1
    //   156: aload_2
    //   157: iconst_0
    //   158: aload 9
    //   160: invokevirtual 511	com/google/android/gms/internal/zzir:zza	(Landroid/content/Context;Ljava/lang/String;ZLjava/net/HttpURLConnection;)V
    //   163: aload 4
    //   165: invokestatic 517	android/text/TextUtils:isEmpty	(Ljava/lang/CharSequence;)Z
    //   168: istore 20
    //   170: iload 20
    //   172: ifne +17 -> 189
    //   175: ldc_w 519
    //   178: astore 12
    //   180: aload 9
    //   182: aload 12
    //   184: aload 4
    //   186: invokevirtual 522	java/net/HttpURLConnection:addRequestProperty	(Ljava/lang/String;Ljava/lang/String;)V
    //   189: aload 5
    //   191: invokestatic 517	android/text/TextUtils:isEmpty	(Ljava/lang/CharSequence;)Z
    //   194: istore 20
    //   196: iload 20
    //   198: ifne +57 -> 255
    //   201: new 468	java/lang/StringBuilder
    //   204: astore 12
    //   206: aload 12
    //   208: invokespecial 469	java/lang/StringBuilder:<init>	()V
    //   211: ldc_w 524
    //   214: astore 13
    //   216: aload 12
    //   218: aload 13
    //   220: invokevirtual 475	java/lang/StringBuilder:append	(Ljava/lang/String;)Ljava/lang/StringBuilder;
    //   223: astore 12
    //   225: aload 12
    //   227: aload 5
    //   229: invokevirtual 475	java/lang/StringBuilder:append	(Ljava/lang/String;)Ljava/lang/StringBuilder;
    //   232: astore 12
    //   234: aload 12
    //   236: invokevirtual 476	java/lang/StringBuilder:toString	()Ljava/lang/String;
    //   239: astore 12
    //   241: ldc_w 526
    //   244: astore 13
    //   246: aload 9
    //   248: aload 13
    //   250: aload 12
    //   252: invokevirtual 522	java/net/HttpURLConnection:addRequestProperty	(Ljava/lang/String;Ljava/lang/String;)V
    //   255: aload 6
    //   257: ifnull +95 -> 352
    //   260: aload 6
    //   262: invokevirtual 529	com/google/android/gms/internal/zzhi:zzgF	()Ljava/lang/String;
    //   265: astore 12
    //   267: aload 12
    //   269: invokestatic 517	android/text/TextUtils:isEmpty	(Ljava/lang/CharSequence;)Z
    //   272: istore 20
    //   274: iload 20
    //   276: ifne +76 -> 352
    //   279: iconst_1
    //   280: istore 20
    //   282: aload 9
    //   284: iload 20
    //   286: invokevirtual 533	java/net/HttpURLConnection:setDoOutput	(Z)V
    //   289: aload 6
    //   291: invokevirtual 529	com/google/android/gms/internal/zzhi:zzgF	()Ljava/lang/String;
    //   294: astore 12
    //   296: aload 12
    //   298: invokevirtual 537	java/lang/String:getBytes	()[B
    //   301: astore 21
    //   303: aload 21
    //   305: arraylength
    //   306: istore 20
    //   308: aload 9
    //   310: iload 20
    //   312: invokevirtual 540	java/net/HttpURLConnection:setFixedLengthStreamingMode	(I)V
    //   315: iconst_0
    //   316: istore 19
    //   318: aconst_null
    //   319: astore 13
    //   321: new 542	java/io/BufferedOutputStream
    //   324: astore 12
    //   326: aload 9
    //   328: invokevirtual 546	java/net/HttpURLConnection:getOutputStream	()Ljava/io/OutputStream;
    //   331: astore 22
    //   333: aload 12
    //   335: aload 22
    //   337: invokespecial 549	java/io/BufferedOutputStream:<init>	(Ljava/io/OutputStream;)V
    //   340: aload 12
    //   342: aload 21
    //   344: invokevirtual 553	java/io/BufferedOutputStream:write	([B)V
    //   347: aload 12
    //   349: invokestatic 558	com/google/android/gms/internal/zzna:zzb	(Ljava/io/Closeable;)V
    //   352: aload 9
    //   354: invokevirtual 561	java/net/HttpURLConnection:getResponseCode	()I
    //   357: istore 23
    //   359: aload 9
    //   361: invokevirtual 565	java/net/HttpURLConnection:getHeaderFields	()Ljava/util/Map;
    //   364: astore 22
    //   366: sipush 200
    //   369: istore 20
    //   371: iload 23
    //   373: iload 20
    //   375: if_icmplt +307 -> 682
    //   378: sipush 300
    //   381: istore 20
    //   383: iload 23
    //   385: iload 20
    //   387: if_icmpge +295 -> 682
    //   390: aload 18
    //   392: invokevirtual 568	java/net/URL:toString	()Ljava/lang/String;
    //   395: astore 17
    //   397: iconst_0
    //   398: istore 19
    //   400: aconst_null
    //   401: astore 13
    //   403: new 570	java/io/InputStreamReader
    //   406: astore 12
    //   408: aload 9
    //   410: invokevirtual 574	java/net/HttpURLConnection:getInputStream	()Ljava/io/InputStream;
    //   413: astore 18
    //   415: aload 12
    //   417: aload 18
    //   419: invokespecial 577	java/io/InputStreamReader:<init>	(Ljava/io/InputStream;)V
    //   422: invokestatic 508	com/google/android/gms/ads/internal/zzr:zzbC	()Lcom/google/android/gms/internal/zzir;
    //   425: astore 13
    //   427: aload 13
    //   429: aload 12
    //   431: invokevirtual 580	com/google/android/gms/internal/zzir:zza	(Ljava/io/InputStreamReader;)Ljava/lang/String;
    //   434: astore 13
    //   436: aload 12
    //   438: invokestatic 558	com/google/android/gms/internal/zzna:zzb	(Ljava/io/Closeable;)V
    //   441: aload 17
    //   443: aload 22
    //   445: aload 13
    //   447: iload 23
    //   449: invokestatic 583	com/google/android/gms/internal/zzhd:zza	(Ljava/lang/String;Ljava/util/Map;Ljava/lang/String;I)V
    //   452: aload 11
    //   454: aload 17
    //   456: aload 22
    //   458: aload 13
    //   460: invokevirtual 586	com/google/android/gms/internal/zzhg:zzb	(Ljava/lang/String;Ljava/util/Map;Ljava/lang/String;)V
    //   463: aload 7
    //   465: ifnull +40 -> 505
    //   468: iconst_1
    //   469: istore 20
    //   471: iload 20
    //   473: anewarray 130	java/lang/String
    //   476: astore 12
    //   478: iconst_0
    //   479: istore 19
    //   481: aconst_null
    //   482: astore 13
    //   484: ldc_w 588
    //   487: astore 17
    //   489: aload 12
    //   491: iconst_0
    //   492: aload 17
    //   494: aastore
    //   495: aload 7
    //   497: aload 10
    //   499: aload 12
    //   501: invokevirtual 136	com/google/android/gms/internal/zzcb:zza	(Lcom/google/android/gms/internal/zzbz;[Ljava/lang/String;)Z
    //   504: pop
    //   505: aload 11
    //   507: lload 14
    //   509: invokevirtual 592	com/google/android/gms/internal/zzhg:zzj	(J)Lcom/google/android/gms/ads/internal/request/AdResponseParcel;
    //   512: astore 10
    //   514: aload 9
    //   516: invokevirtual 595	java/net/HttpURLConnection:disconnect	()V
    //   519: aload 8
    //   521: ifnull +17 -> 538
    //   524: aload 8
    //   526: getfield 493	com/google/android/gms/internal/zzhc:zzIO	Lcom/google/android/gms/internal/zzhm;
    //   529: astore 9
    //   531: aload 9
    //   533: invokeinterface 598 1 0
    //   538: aload 10
    //   540: astore 9
    //   542: aload 9
    //   544: areturn
    //   545: aconst_null
    //   546: astore 9
    //   548: iconst_0
    //   549: istore 24
    //   551: aconst_null
    //   552: astore 10
    //   554: goto -538 -> 16
    //   557: astore 10
    //   559: iconst_0
    //   560: istore 20
    //   562: aconst_null
    //   563: astore 12
    //   565: aload 12
    //   567: invokestatic 558	com/google/android/gms/internal/zzna:zzb	(Ljava/io/Closeable;)V
    //   570: aload 10
    //   572: athrow
    //   573: astore 10
    //   575: aload 9
    //   577: invokevirtual 595	java/net/HttpURLConnection:disconnect	()V
    //   580: aload 8
    //   582: ifnull +17 -> 599
    //   585: aload 8
    //   587: getfield 493	com/google/android/gms/internal/zzhc:zzIO	Lcom/google/android/gms/internal/zzhm;
    //   590: astore 9
    //   592: aload 9
    //   594: invokeinterface 598 1 0
    //   599: aload 10
    //   601: athrow
    //   602: astore 9
    //   604: new 468	java/lang/StringBuilder
    //   607: astore 10
    //   609: aload 10
    //   611: invokespecial 469	java/lang/StringBuilder:<init>	()V
    //   614: ldc_w 600
    //   617: astore 12
    //   619: aload 10
    //   621: aload 12
    //   623: invokevirtual 475	java/lang/StringBuilder:append	(Ljava/lang/String;)Ljava/lang/StringBuilder;
    //   626: astore 10
    //   628: aload 9
    //   630: invokevirtual 605	java/io/IOException:getMessage	()Ljava/lang/String;
    //   633: astore 9
    //   635: aload 10
    //   637: aload 9
    //   639: invokevirtual 475	java/lang/StringBuilder:append	(Ljava/lang/String;)Ljava/lang/StringBuilder;
    //   642: invokevirtual 476	java/lang/StringBuilder:toString	()Ljava/lang/String;
    //   645: invokestatic 608	com/google/android/gms/internal/zzin:zzaK	(Ljava/lang/String;)V
    //   648: new 205	com/google/android/gms/ads/internal/request/AdResponseParcel
    //   651: astore 9
    //   653: iconst_2
    //   654: istore 24
    //   656: aload 9
    //   658: iload 24
    //   660: invokespecial 209	com/google/android/gms/ads/internal/request/AdResponseParcel:<init>	(I)V
    //   663: goto -121 -> 542
    //   666: astore 10
    //   668: iconst_0
    //   669: istore 20
    //   671: aconst_null
    //   672: astore 12
    //   674: aload 12
    //   676: invokestatic 558	com/google/android/gms/internal/zzna:zzb	(Ljava/io/Closeable;)V
    //   679: aload 10
    //   681: athrow
    //   682: aload 18
    //   684: invokevirtual 568	java/net/URL:toString	()Ljava/lang/String;
    //   687: astore 12
    //   689: iconst_0
    //   690: istore 19
    //   692: aconst_null
    //   693: astore 13
    //   695: aload 12
    //   697: aload 22
    //   699: aconst_null
    //   700: iload 23
    //   702: invokestatic 583	com/google/android/gms/internal/zzhd:zza	(Ljava/lang/String;Ljava/util/Map;Ljava/lang/String;I)V
    //   705: sipush 300
    //   708: istore 20
    //   710: iload 23
    //   712: iload 20
    //   714: if_icmplt +185 -> 899
    //   717: sipush 400
    //   720: istore 20
    //   722: iload 23
    //   724: iload 20
    //   726: if_icmpge +173 -> 899
    //   729: ldc_w 611
    //   732: astore 12
    //   734: aload 9
    //   736: aload 12
    //   738: invokevirtual 614	java/net/HttpURLConnection:getHeaderField	(Ljava/lang/String;)Ljava/lang/String;
    //   741: astore 12
    //   743: aload 12
    //   745: invokestatic 517	android/text/TextUtils:isEmpty	(Ljava/lang/CharSequence;)Z
    //   748: istore 19
    //   750: iload 19
    //   752: ifeq +61 -> 813
    //   755: ldc_w 616
    //   758: astore 10
    //   760: aload 10
    //   762: invokestatic 608	com/google/android/gms/internal/zzin:zzaK	(Ljava/lang/String;)V
    //   765: new 205	com/google/android/gms/ads/internal/request/AdResponseParcel
    //   768: astore 10
    //   770: iconst_0
    //   771: istore 20
    //   773: aconst_null
    //   774: astore 12
    //   776: aload 10
    //   778: iconst_0
    //   779: invokespecial 209	com/google/android/gms/ads/internal/request/AdResponseParcel:<init>	(I)V
    //   782: aload 9
    //   784: invokevirtual 595	java/net/HttpURLConnection:disconnect	()V
    //   787: aload 8
    //   789: ifnull +17 -> 806
    //   792: aload 8
    //   794: getfield 493	com/google/android/gms/internal/zzhc:zzIO	Lcom/google/android/gms/internal/zzhm;
    //   797: astore 9
    //   799: aload 9
    //   801: invokeinterface 598 1 0
    //   806: aload 10
    //   808: astore 9
    //   810: goto -268 -> 542
    //   813: new 478	java/net/URL
    //   816: astore 13
    //   818: aload 13
    //   820: aload 12
    //   822: invokespecial 480	java/net/URL:<init>	(Ljava/lang/String;)V
    //   825: iload 16
    //   827: iconst_1
    //   828: iadd
    //   829: istore 20
    //   831: iconst_5
    //   832: istore 16
    //   834: iload 20
    //   836: iload 16
    //   838: if_icmple +154 -> 992
    //   841: ldc_w 619
    //   844: astore 10
    //   846: aload 10
    //   848: invokestatic 608	com/google/android/gms/internal/zzin:zzaK	(Ljava/lang/String;)V
    //   851: new 205	com/google/android/gms/ads/internal/request/AdResponseParcel
    //   854: astore 10
    //   856: iconst_0
    //   857: istore 20
    //   859: aconst_null
    //   860: astore 12
    //   862: aload 10
    //   864: iconst_0
    //   865: invokespecial 209	com/google/android/gms/ads/internal/request/AdResponseParcel:<init>	(I)V
    //   868: aload 9
    //   870: invokevirtual 595	java/net/HttpURLConnection:disconnect	()V
    //   873: aload 8
    //   875: ifnull +17 -> 892
    //   878: aload 8
    //   880: getfield 493	com/google/android/gms/internal/zzhc:zzIO	Lcom/google/android/gms/internal/zzhm;
    //   883: astore 9
    //   885: aload 9
    //   887: invokeinterface 598 1 0
    //   892: aload 10
    //   894: astore 9
    //   896: goto -354 -> 542
    //   899: new 468	java/lang/StringBuilder
    //   902: astore 10
    //   904: aload 10
    //   906: invokespecial 469	java/lang/StringBuilder:<init>	()V
    //   909: ldc_w 621
    //   912: astore 12
    //   914: aload 10
    //   916: aload 12
    //   918: invokevirtual 475	java/lang/StringBuilder:append	(Ljava/lang/String;)Ljava/lang/StringBuilder;
    //   921: astore 10
    //   923: aload 10
    //   925: iload 23
    //   927: invokevirtual 624	java/lang/StringBuilder:append	(I)Ljava/lang/StringBuilder;
    //   930: astore 10
    //   932: aload 10
    //   934: invokevirtual 476	java/lang/StringBuilder:toString	()Ljava/lang/String;
    //   937: astore 10
    //   939: aload 10
    //   941: invokestatic 608	com/google/android/gms/internal/zzin:zzaK	(Ljava/lang/String;)V
    //   944: new 205	com/google/android/gms/ads/internal/request/AdResponseParcel
    //   947: astore 10
    //   949: iconst_0
    //   950: istore 20
    //   952: aconst_null
    //   953: astore 12
    //   955: aload 10
    //   957: iconst_0
    //   958: invokespecial 209	com/google/android/gms/ads/internal/request/AdResponseParcel:<init>	(I)V
    //   961: aload 9
    //   963: invokevirtual 595	java/net/HttpURLConnection:disconnect	()V
    //   966: aload 8
    //   968: ifnull +17 -> 985
    //   971: aload 8
    //   973: getfield 493	com/google/android/gms/internal/zzhc:zzIO	Lcom/google/android/gms/internal/zzhm;
    //   976: astore 9
    //   978: aload 9
    //   980: invokeinterface 598 1 0
    //   985: aload 10
    //   987: astore 9
    //   989: goto -447 -> 542
    //   992: aload 11
    //   994: aload 22
    //   996: invokevirtual 627	com/google/android/gms/internal/zzhg:zzj	(Ljava/util/Map;)V
    //   999: aload 9
    //   1001: invokevirtual 595	java/net/HttpURLConnection:disconnect	()V
    //   1004: aload 8
    //   1006: ifnull +17 -> 1023
    //   1009: aload 8
    //   1011: getfield 493	com/google/android/gms/internal/zzhc:zzIO	Lcom/google/android/gms/internal/zzhm;
    //   1014: astore 9
    //   1016: aload 9
    //   1018: invokeinterface 598 1 0
    //   1023: iload 20
    //   1025: istore 16
    //   1027: aload 13
    //   1029: astore 18
    //   1031: goto -922 -> 109
    //   1034: astore 10
    //   1036: goto -362 -> 674
    //   1039: astore 10
    //   1041: goto -476 -> 565
    // Local variable table:
    //   start	length	slot	name	signature
    //   0	1044	0	paramAdRequestInfoParcel	AdRequestInfoParcel
    //   0	1044	1	paramContext	Context
    //   0	1044	2	paramString1	String
    //   0	1044	3	paramString2	String
    //   0	1044	4	paramString3	String
    //   0	1044	5	paramString4	String
    //   0	1044	6	paramzzhi	zzhi
    //   0	1044	7	paramzzcb	zzcb
    //   0	1044	8	paramzzhc	zzhc
    //   10	583	9	localObject1	Object
    //   602	27	9	localIOException	java.io.IOException
    //   633	384	9	localObject2	Object
    //   14	539	10	localObject3	Object
    //   557	14	10	localObject4	Object
    //   573	27	10	localObject5	Object
    //   607	29	10	localStringBuilder	StringBuilder
    //   666	14	10	localObject6	Object
    //   758	228	10	localObject7	Object
    //   1034	1	10	localObject8	Object
    //   1039	1	10	localObject9	Object
    //   19	974	11	localzzhg	zzhg
    //   40	914	12	localObject10	Object
    //   88	940	13	localObject11	Object
    //   97	411	14	l	long
    //   100	926	16	i	int
    //   103	390	17	str	String
    //   107	923	18	localObject12	Object
    //   148	603	19	bool1	boolean
    //   168	117	20	bool2	boolean
    //   306	718	20	j	int
    //   301	42	21	arrayOfByte	byte[]
    //   331	664	22	localObject13	Object
    //   357	569	23	k	int
    //   549	110	24	m	int
    // Exception table:
    //   from	to	target	type
    //   321	324	557	finally
    //   326	331	557	finally
    //   335	340	557	finally
    //   142	145	573	finally
    //   158	163	573	finally
    //   163	168	573	finally
    //   184	189	573	finally
    //   189	194	573	finally
    //   201	204	573	finally
    //   206	211	573	finally
    //   218	223	573	finally
    //   227	232	573	finally
    //   234	239	573	finally
    //   250	255	573	finally
    //   260	265	573	finally
    //   267	272	573	finally
    //   284	289	573	finally
    //   289	294	573	finally
    //   296	301	573	finally
    //   303	306	573	finally
    //   310	315	573	finally
    //   347	352	573	finally
    //   352	357	573	finally
    //   359	364	573	finally
    //   390	395	573	finally
    //   436	441	573	finally
    //   447	452	573	finally
    //   458	463	573	finally
    //   471	476	573	finally
    //   492	495	573	finally
    //   499	505	573	finally
    //   507	512	573	finally
    //   565	570	573	finally
    //   570	573	573	finally
    //   674	679	573	finally
    //   679	682	573	finally
    //   682	687	573	finally
    //   700	705	573	finally
    //   736	741	573	finally
    //   743	748	573	finally
    //   760	765	573	finally
    //   765	768	573	finally
    //   778	782	573	finally
    //   813	816	573	finally
    //   820	825	573	finally
    //   846	851	573	finally
    //   851	854	573	finally
    //   864	868	573	finally
    //   899	902	573	finally
    //   904	909	573	finally
    //   916	921	573	finally
    //   925	930	573	finally
    //   932	937	573	finally
    //   939	944	573	finally
    //   944	947	573	finally
    //   957	961	573	finally
    //   994	999	573	finally
    //   16	19	602	java/io/IOException
    //   23	27	602	java/io/IOException
    //   27	30	602	java/io/IOException
    //   32	37	602	java/io/IOException
    //   44	49	602	java/io/IOException
    //   53	57	602	java/io/IOException
    //   59	64	602	java/io/IOException
    //   66	71	602	java/io/IOException
    //   71	74	602	java/io/IOException
    //   78	82	602	java/io/IOException
    //   85	88	602	java/io/IOException
    //   90	97	602	java/io/IOException
    //   114	119	602	java/io/IOException
    //   121	128	602	java/io/IOException
    //   128	133	602	java/io/IOException
    //   135	140	602	java/io/IOException
    //   514	519	602	java/io/IOException
    //   524	529	602	java/io/IOException
    //   531	538	602	java/io/IOException
    //   575	580	602	java/io/IOException
    //   585	590	602	java/io/IOException
    //   592	599	602	java/io/IOException
    //   599	602	602	java/io/IOException
    //   782	787	602	java/io/IOException
    //   792	797	602	java/io/IOException
    //   799	806	602	java/io/IOException
    //   868	873	602	java/io/IOException
    //   878	883	602	java/io/IOException
    //   885	892	602	java/io/IOException
    //   961	966	602	java/io/IOException
    //   971	976	602	java/io/IOException
    //   978	985	602	java/io/IOException
    //   999	1004	602	java/io/IOException
    //   1009	1014	602	java/io/IOException
    //   1016	1023	602	java/io/IOException
    //   403	406	666	finally
    //   408	413	666	finally
    //   417	422	666	finally
    //   422	425	1034	finally
    //   429	434	1034	finally
    //   342	347	1039	finally
  }
  
  public static zzhd zza(Context paramContext, zzbm paramzzbm, zzhc paramzzhc)
  {
    synchronized (zzqy)
    {
      zzhd localzzhd = zzIQ;
      if (localzzhd == null)
      {
        localzzhd = new com/google/android/gms/internal/zzhd;
        Context localContext = paramContext.getApplicationContext();
        if (localContext != null) {
          paramContext = paramContext.getApplicationContext();
        }
        localzzhd.<init>(paramContext, paramzzbm, paramzzhc);
        zzIQ = localzzhd;
      }
      localzzhd = zzIQ;
      return localzzhd;
    }
  }
  
  private static zzjq.zza zza(String paramString, zzcb paramzzcb, zzbz paramzzbz)
  {
    zzhd.5 local5 = new com/google/android/gms/internal/zzhd$5;
    local5.<init>(paramzzcb, paramzzbz, paramString);
    return local5;
  }
  
  private static void zza(String paramString1, Map paramMap, String paramString2, int paramInt)
  {
    int i = zzin.zzQ(2);
    if (i != 0)
    {
      Object localObject1 = new java/lang/StringBuilder;
      ((StringBuilder)localObject1).<init>();
      localObject1 = ((StringBuilder)localObject1).append("Http Response: {\n  URL:\n    ").append(paramString1);
      Object localObject2 = "\n  Headers:";
      localObject1 = (String)localObject2;
      zzin.v((String)localObject1);
      if (paramMap != null)
      {
        localObject1 = paramMap.keySet();
        localObject2 = ((Set)localObject1).iterator();
        i = ((Iterator)localObject2).hasNext();
        if (i != 0)
        {
          localObject1 = (String)((Iterator)localObject2).next();
          Object localObject3 = new java/lang/StringBuilder;
          ((StringBuilder)localObject3).<init>();
          localObject3 = ((StringBuilder)localObject3).append("    ").append((String)localObject1);
          Object localObject4 = ":";
          zzin.v((String)localObject4);
          localObject1 = (List)paramMap.get(localObject1);
          localObject3 = ((List)localObject1).iterator();
          for (;;)
          {
            i = ((Iterator)localObject3).hasNext();
            if (i == 0) {
              break;
            }
            localObject1 = (String)((Iterator)localObject3).next();
            localObject4 = new java/lang/StringBuilder;
            ((StringBuilder)localObject4).<init>();
            String str = "      ";
            localObject4 = ((StringBuilder)localObject4).append(str);
            localObject1 = (String)localObject1;
            zzin.v((String)localObject1);
          }
        }
      }
      localObject1 = "  Body:";
      zzin.v((String)localObject1);
      if (paramString2 != null)
      {
        i = 0;
        localObject1 = null;
        for (;;)
        {
          int k = paramString2.length();
          int n = 100000;
          k = Math.min(k, n);
          if (i >= k) {
            break;
          }
          int m = paramString2.length();
          n = i + 1000;
          m = Math.min(m, n);
          localObject2 = paramString2.substring(i, m);
          zzin.v((String)localObject2);
          int j;
          i += 1000;
        }
      }
      localObject1 = "    null";
      zzin.v((String)localObject1);
      localObject1 = new java/lang/StringBuilder;
      ((StringBuilder)localObject1).<init>();
      localObject1 = ((StringBuilder)localObject1).append("  Response Code:\n    ").append(paramInt);
      localObject2 = "\n}";
      localObject1 = (String)localObject2;
      zzin.v((String)localObject1);
    }
  }
  
  public void zza(AdRequestInfoParcel paramAdRequestInfoParcel, zzk paramzzk)
  {
    Object localObject = zzr.zzbF();
    Context localContext = this.mContext;
    VersionInfoParcel localVersionInfoParcel = paramAdRequestInfoParcel.zzrl;
    ((zzih)localObject).zzb(localContext, localVersionInfoParcel);
    localObject = new com/google/android/gms/internal/zzhd$7;
    ((zzhd.7)localObject).<init>(this, paramAdRequestInfoParcel, paramzzk);
    zziq.zza((Runnable)localObject);
  }
  
  public AdResponseParcel zzd(AdRequestInfoParcel paramAdRequestInfoParcel)
  {
    Context localContext = this.mContext;
    zzeg localzzeg = this.zzIT;
    zzbm localzzbm = this.zzIS;
    zzhc localzzhc = this.zzIR;
    return zza(localContext, localzzeg, localzzbm, localzzhc, paramAdRequestInfoParcel);
  }
}


/* Location:              C:\Users\haryo\Desktop\enjarify-master\presensi-enjarify.jar!\com\google\android\gms\internal\zzhd.class
 * Java compiler version: 5 (49.0)
 * JD-Core Version:       0.7.1
 */