package com.google.android.gms.internal;

import android.content.Context;

public final class zziy
  extends zzim
{
  private final Context mContext;
  private final String zzF;
  private final String zzsy;
  private String zzzN = null;
  
  public zziy(Context paramContext, String paramString1, String paramString2)
  {
    this.mContext = paramContext;
    this.zzsy = paramString1;
    this.zzF = paramString2;
  }
  
  public zziy(Context paramContext, String paramString1, String paramString2, String paramString3)
  {
    this.mContext = paramContext;
    this.zzsy = paramString1;
    this.zzF = paramString2;
    this.zzzN = paramString3;
  }
  
  public void onStop() {}
  
  /* Error */
  public void zzbr()
  {
    // Byte code:
    //   0: new 24	java/lang/StringBuilder
    //   3: astore_1
    //   4: aload_1
    //   5: invokespecial 25	java/lang/StringBuilder:<init>	()V
    //   8: ldc 27
    //   10: astore_2
    //   11: aload_1
    //   12: aload_2
    //   13: invokevirtual 31	java/lang/StringBuilder:append	(Ljava/lang/String;)Ljava/lang/StringBuilder;
    //   16: astore_1
    //   17: aload_0
    //   18: getfield 22	com/google/android/gms/internal/zziy:zzF	Ljava/lang/String;
    //   21: astore_2
    //   22: aload_1
    //   23: aload_2
    //   24: invokevirtual 31	java/lang/StringBuilder:append	(Ljava/lang/String;)Ljava/lang/StringBuilder;
    //   27: astore_1
    //   28: aload_1
    //   29: invokevirtual 35	java/lang/StringBuilder:toString	()Ljava/lang/String;
    //   32: astore_1
    //   33: aload_1
    //   34: invokestatic 41	com/google/android/gms/internal/zzin:v	(Ljava/lang/String;)V
    //   37: new 43	java/net/URL
    //   40: astore_1
    //   41: aload_0
    //   42: getfield 22	com/google/android/gms/internal/zziy:zzF	Ljava/lang/String;
    //   45: astore_2
    //   46: aload_1
    //   47: aload_2
    //   48: invokespecial 45	java/net/URL:<init>	(Ljava/lang/String;)V
    //   51: aload_1
    //   52: invokevirtual 49	java/net/URL:openConnection	()Ljava/net/URLConnection;
    //   55: astore_3
    //   56: aload_3
    //   57: checkcast 51	java/net/HttpURLConnection
    //   60: astore_3
    //   61: aload_0
    //   62: getfield 16	com/google/android/gms/internal/zziy:zzzN	Ljava/lang/String;
    //   65: astore_1
    //   66: aload_1
    //   67: invokestatic 57	android/text/TextUtils:isEmpty	(Ljava/lang/CharSequence;)Z
    //   70: istore 4
    //   72: iload 4
    //   74: ifeq +121 -> 195
    //   77: invokestatic 63	com/google/android/gms/ads/internal/zzr:zzbC	()Lcom/google/android/gms/internal/zzir;
    //   80: astore_1
    //   81: aload_0
    //   82: getfield 18	com/google/android/gms/internal/zziy:mContext	Landroid/content/Context;
    //   85: astore_2
    //   86: aload_0
    //   87: getfield 20	com/google/android/gms/internal/zziy:zzsy	Ljava/lang/String;
    //   90: astore 5
    //   92: iconst_1
    //   93: istore 6
    //   95: aload_1
    //   96: aload_2
    //   97: aload 5
    //   99: iload 6
    //   101: aload_3
    //   102: invokevirtual 70	com/google/android/gms/internal/zzir:zza	(Landroid/content/Context;Ljava/lang/String;ZLjava/net/HttpURLConnection;)V
    //   105: aload_3
    //   106: invokevirtual 74	java/net/HttpURLConnection:getResponseCode	()I
    //   109: istore 4
    //   111: sipush 200
    //   114: istore 7
    //   116: iload 4
    //   118: iload 7
    //   120: if_icmplt +15 -> 135
    //   123: sipush 300
    //   126: istore 7
    //   128: iload 4
    //   130: iload 7
    //   132: if_icmplt +58 -> 190
    //   135: new 24	java/lang/StringBuilder
    //   138: astore_2
    //   139: aload_2
    //   140: invokespecial 25	java/lang/StringBuilder:<init>	()V
    //   143: ldc 78
    //   145: astore 5
    //   147: aload_2
    //   148: aload 5
    //   150: invokevirtual 31	java/lang/StringBuilder:append	(Ljava/lang/String;)Ljava/lang/StringBuilder;
    //   153: astore_2
    //   154: aload_2
    //   155: iload 4
    //   157: invokevirtual 81	java/lang/StringBuilder:append	(I)Ljava/lang/StringBuilder;
    //   160: astore_1
    //   161: ldc 83
    //   163: astore_2
    //   164: aload_1
    //   165: aload_2
    //   166: invokevirtual 31	java/lang/StringBuilder:append	(Ljava/lang/String;)Ljava/lang/StringBuilder;
    //   169: astore_1
    //   170: aload_0
    //   171: getfield 22	com/google/android/gms/internal/zziy:zzF	Ljava/lang/String;
    //   174: astore_2
    //   175: aload_1
    //   176: aload_2
    //   177: invokevirtual 31	java/lang/StringBuilder:append	(Ljava/lang/String;)Ljava/lang/StringBuilder;
    //   180: astore_1
    //   181: aload_1
    //   182: invokevirtual 35	java/lang/StringBuilder:toString	()Ljava/lang/String;
    //   185: astore_1
    //   186: aload_1
    //   187: invokestatic 86	com/google/android/gms/internal/zzin:zzaK	(Ljava/lang/String;)V
    //   190: aload_3
    //   191: invokevirtual 89	java/net/HttpURLConnection:disconnect	()V
    //   194: return
    //   195: invokestatic 63	com/google/android/gms/ads/internal/zzr:zzbC	()Lcom/google/android/gms/internal/zzir;
    //   198: astore_1
    //   199: aload_0
    //   200: getfield 18	com/google/android/gms/internal/zziy:mContext	Landroid/content/Context;
    //   203: astore_2
    //   204: aload_0
    //   205: getfield 20	com/google/android/gms/internal/zziy:zzsy	Ljava/lang/String;
    //   208: astore 5
    //   210: iconst_1
    //   211: istore 6
    //   213: aload_0
    //   214: getfield 16	com/google/android/gms/internal/zziy:zzzN	Ljava/lang/String;
    //   217: astore 8
    //   219: aload_1
    //   220: aload_2
    //   221: aload 5
    //   223: iload 6
    //   225: aload_3
    //   226: aload 8
    //   228: invokevirtual 92	com/google/android/gms/internal/zzir:zza	(Landroid/content/Context;Ljava/lang/String;ZLjava/net/HttpURLConnection;Ljava/lang/String;)V
    //   231: goto -126 -> 105
    //   234: astore_1
    //   235: aload_3
    //   236: invokevirtual 89	java/net/HttpURLConnection:disconnect	()V
    //   239: aload_1
    //   240: athrow
    //   241: astore_1
    //   242: new 24	java/lang/StringBuilder
    //   245: astore_2
    //   246: aload_2
    //   247: invokespecial 25	java/lang/StringBuilder:<init>	()V
    //   250: aload_2
    //   251: ldc 94
    //   253: invokevirtual 31	java/lang/StringBuilder:append	(Ljava/lang/String;)Ljava/lang/StringBuilder;
    //   256: astore_2
    //   257: aload_0
    //   258: getfield 22	com/google/android/gms/internal/zziy:zzF	Ljava/lang/String;
    //   261: astore 5
    //   263: aload_2
    //   264: aload 5
    //   266: invokevirtual 31	java/lang/StringBuilder:append	(Ljava/lang/String;)Ljava/lang/StringBuilder;
    //   269: astore_2
    //   270: ldc 96
    //   272: astore 5
    //   274: aload_2
    //   275: aload 5
    //   277: invokevirtual 31	java/lang/StringBuilder:append	(Ljava/lang/String;)Ljava/lang/StringBuilder;
    //   280: astore_2
    //   281: aload_1
    //   282: invokevirtual 101	java/lang/IndexOutOfBoundsException:getMessage	()Ljava/lang/String;
    //   285: astore_1
    //   286: aload_2
    //   287: aload_1
    //   288: invokevirtual 31	java/lang/StringBuilder:append	(Ljava/lang/String;)Ljava/lang/StringBuilder;
    //   291: invokevirtual 35	java/lang/StringBuilder:toString	()Ljava/lang/String;
    //   294: astore_1
    //   295: aload_1
    //   296: invokestatic 86	com/google/android/gms/internal/zzin:zzaK	(Ljava/lang/String;)V
    //   299: goto -105 -> 194
    //   302: astore_1
    //   303: new 24	java/lang/StringBuilder
    //   306: astore_2
    //   307: aload_2
    //   308: invokespecial 25	java/lang/StringBuilder:<init>	()V
    //   311: aload_2
    //   312: ldc 103
    //   314: invokevirtual 31	java/lang/StringBuilder:append	(Ljava/lang/String;)Ljava/lang/StringBuilder;
    //   317: astore_2
    //   318: aload_0
    //   319: getfield 22	com/google/android/gms/internal/zziy:zzF	Ljava/lang/String;
    //   322: astore 5
    //   324: aload_2
    //   325: aload 5
    //   327: invokevirtual 31	java/lang/StringBuilder:append	(Ljava/lang/String;)Ljava/lang/StringBuilder;
    //   330: astore_2
    //   331: ldc 96
    //   333: astore 5
    //   335: aload_2
    //   336: aload 5
    //   338: invokevirtual 31	java/lang/StringBuilder:append	(Ljava/lang/String;)Ljava/lang/StringBuilder;
    //   341: astore_2
    //   342: aload_1
    //   343: invokevirtual 106	java/io/IOException:getMessage	()Ljava/lang/String;
    //   346: astore_1
    //   347: aload_2
    //   348: aload_1
    //   349: invokevirtual 31	java/lang/StringBuilder:append	(Ljava/lang/String;)Ljava/lang/StringBuilder;
    //   352: invokevirtual 35	java/lang/StringBuilder:toString	()Ljava/lang/String;
    //   355: astore_1
    //   356: aload_1
    //   357: invokestatic 86	com/google/android/gms/internal/zzin:zzaK	(Ljava/lang/String;)V
    //   360: goto -166 -> 194
    //   363: astore_1
    //   364: new 24	java/lang/StringBuilder
    //   367: astore_2
    //   368: aload_2
    //   369: invokespecial 25	java/lang/StringBuilder:<init>	()V
    //   372: aload_2
    //   373: ldc 103
    //   375: invokevirtual 31	java/lang/StringBuilder:append	(Ljava/lang/String;)Ljava/lang/StringBuilder;
    //   378: astore_2
    //   379: aload_0
    //   380: getfield 22	com/google/android/gms/internal/zziy:zzF	Ljava/lang/String;
    //   383: astore 5
    //   385: aload_2
    //   386: aload 5
    //   388: invokevirtual 31	java/lang/StringBuilder:append	(Ljava/lang/String;)Ljava/lang/StringBuilder;
    //   391: astore_2
    //   392: ldc 96
    //   394: astore 5
    //   396: aload_2
    //   397: aload 5
    //   399: invokevirtual 31	java/lang/StringBuilder:append	(Ljava/lang/String;)Ljava/lang/StringBuilder;
    //   402: astore_2
    //   403: aload_1
    //   404: invokevirtual 109	java/lang/RuntimeException:getMessage	()Ljava/lang/String;
    //   407: astore_1
    //   408: aload_2
    //   409: aload_1
    //   410: invokevirtual 31	java/lang/StringBuilder:append	(Ljava/lang/String;)Ljava/lang/StringBuilder;
    //   413: invokevirtual 35	java/lang/StringBuilder:toString	()Ljava/lang/String;
    //   416: astore_1
    //   417: aload_1
    //   418: invokestatic 86	com/google/android/gms/internal/zzin:zzaK	(Ljava/lang/String;)V
    //   421: goto -227 -> 194
    // Local variable table:
    //   start	length	slot	name	signature
    //   0	424	0	this	zziy
    //   3	217	1	localObject1	Object
    //   234	6	1	localObject2	Object
    //   241	41	1	localIndexOutOfBoundsException	IndexOutOfBoundsException
    //   285	11	1	str1	String
    //   302	41	1	localIOException	java.io.IOException
    //   346	11	1	str2	String
    //   363	41	1	localRuntimeException	RuntimeException
    //   407	11	1	str3	String
    //   10	399	2	localObject3	Object
    //   55	181	3	localObject4	Object
    //   70	3	4	bool1	boolean
    //   109	47	4	i	int
    //   90	308	5	str4	String
    //   93	131	6	bool2	boolean
    //   114	19	7	j	int
    //   217	10	8	str5	String
    // Exception table:
    //   from	to	target	type
    //   61	65	234	finally
    //   66	70	234	finally
    //   77	80	234	finally
    //   81	85	234	finally
    //   86	90	234	finally
    //   101	105	234	finally
    //   105	109	234	finally
    //   135	138	234	finally
    //   139	143	234	finally
    //   148	153	234	finally
    //   155	160	234	finally
    //   165	169	234	finally
    //   170	174	234	finally
    //   176	180	234	finally
    //   181	185	234	finally
    //   186	190	234	finally
    //   195	198	234	finally
    //   199	203	234	finally
    //   204	208	234	finally
    //   213	217	234	finally
    //   226	231	234	finally
    //   0	3	241	java/lang/IndexOutOfBoundsException
    //   4	8	241	java/lang/IndexOutOfBoundsException
    //   12	16	241	java/lang/IndexOutOfBoundsException
    //   17	21	241	java/lang/IndexOutOfBoundsException
    //   23	27	241	java/lang/IndexOutOfBoundsException
    //   28	32	241	java/lang/IndexOutOfBoundsException
    //   33	37	241	java/lang/IndexOutOfBoundsException
    //   37	40	241	java/lang/IndexOutOfBoundsException
    //   41	45	241	java/lang/IndexOutOfBoundsException
    //   47	51	241	java/lang/IndexOutOfBoundsException
    //   51	55	241	java/lang/IndexOutOfBoundsException
    //   56	60	241	java/lang/IndexOutOfBoundsException
    //   190	194	241	java/lang/IndexOutOfBoundsException
    //   235	239	241	java/lang/IndexOutOfBoundsException
    //   239	241	241	java/lang/IndexOutOfBoundsException
    //   0	3	302	java/io/IOException
    //   4	8	302	java/io/IOException
    //   12	16	302	java/io/IOException
    //   17	21	302	java/io/IOException
    //   23	27	302	java/io/IOException
    //   28	32	302	java/io/IOException
    //   33	37	302	java/io/IOException
    //   37	40	302	java/io/IOException
    //   41	45	302	java/io/IOException
    //   47	51	302	java/io/IOException
    //   51	55	302	java/io/IOException
    //   56	60	302	java/io/IOException
    //   190	194	302	java/io/IOException
    //   235	239	302	java/io/IOException
    //   239	241	302	java/io/IOException
    //   0	3	363	java/lang/RuntimeException
    //   4	8	363	java/lang/RuntimeException
    //   12	16	363	java/lang/RuntimeException
    //   17	21	363	java/lang/RuntimeException
    //   23	27	363	java/lang/RuntimeException
    //   28	32	363	java/lang/RuntimeException
    //   33	37	363	java/lang/RuntimeException
    //   37	40	363	java/lang/RuntimeException
    //   41	45	363	java/lang/RuntimeException
    //   47	51	363	java/lang/RuntimeException
    //   51	55	363	java/lang/RuntimeException
    //   56	60	363	java/lang/RuntimeException
    //   190	194	363	java/lang/RuntimeException
    //   235	239	363	java/lang/RuntimeException
    //   239	241	363	java/lang/RuntimeException
  }
}


/* Location:              C:\Users\haryo\Desktop\enjarify-master\presensi-enjarify.jar!\com\google\android\gms\internal\zziy.class
 * Java compiler version: 5 (49.0)
 * JD-Core Version:       0.7.1
 */