package com.google.android.gms.internal;

import android.os.Bundle;
import android.os.IBinder;
import android.os.Parcel;
import com.google.android.gms.dynamic.zzd;
import com.google.android.gms.wallet.fragment.WalletFragmentOptions;

class zzrx$zza$zza
  implements zzrx
{
  private IBinder zzoz;
  
  zzrx$zza$zza(IBinder paramIBinder)
  {
    this.zzoz = paramIBinder;
  }
  
  public IBinder asBinder()
  {
    return this.zzoz;
  }
  
  public int getState()
  {
    Parcel localParcel1 = Parcel.obtain();
    Parcel localParcel2 = Parcel.obtain();
    Object localObject1 = "com.google.android.gms.wallet.fragment.internal.IWalletFragmentDelegate";
    try
    {
      localParcel1.writeInterfaceToken((String)localObject1);
      localObject1 = this.zzoz;
      int i = 13;
      ((IBinder)localObject1).transact(i, localParcel1, localParcel2, 0);
      localParcel2.readException();
      int j = localParcel2.readInt();
      return j;
    }
    finally
    {
      localParcel2.recycle();
      localParcel1.recycle();
    }
  }
  
  /* Error */
  public void initialize(com.google.android.gms.wallet.fragment.WalletFragmentInitParams paramWalletFragmentInitParams)
  {
    // Byte code:
    //   0: invokestatic 20	android/os/Parcel:obtain	()Landroid/os/Parcel;
    //   3: astore_2
    //   4: invokestatic 20	android/os/Parcel:obtain	()Landroid/os/Parcel;
    //   7: astore_3
    //   8: ldc 22
    //   10: astore 4
    //   12: aload_2
    //   13: aload 4
    //   15: invokevirtual 26	android/os/Parcel:writeInterfaceToken	(Ljava/lang/String;)V
    //   18: aload_1
    //   19: ifnull +60 -> 79
    //   22: iconst_1
    //   23: istore 5
    //   25: aload_2
    //   26: iload 5
    //   28: invokevirtual 48	android/os/Parcel:writeInt	(I)V
    //   31: iconst_0
    //   32: istore 5
    //   34: aconst_null
    //   35: astore 4
    //   37: aload_1
    //   38: aload_2
    //   39: iconst_0
    //   40: invokevirtual 54	com/google/android/gms/wallet/fragment/WalletFragmentInitParams:writeToParcel	(Landroid/os/Parcel;I)V
    //   43: aload_0
    //   44: getfield 14	com/google/android/gms/internal/zzrx$zza$zza:zzoz	Landroid/os/IBinder;
    //   47: astore 4
    //   49: bipush 10
    //   51: istore 6
    //   53: aload 4
    //   55: iload 6
    //   57: aload_2
    //   58: aload_3
    //   59: iconst_0
    //   60: invokeinterface 33 5 0
    //   65: pop
    //   66: aload_3
    //   67: invokevirtual 36	android/os/Parcel:readException	()V
    //   70: aload_3
    //   71: invokevirtual 43	android/os/Parcel:recycle	()V
    //   74: aload_2
    //   75: invokevirtual 43	android/os/Parcel:recycle	()V
    //   78: return
    //   79: iconst_0
    //   80: istore 5
    //   82: aconst_null
    //   83: astore 4
    //   85: aload_2
    //   86: iconst_0
    //   87: invokevirtual 48	android/os/Parcel:writeInt	(I)V
    //   90: goto -47 -> 43
    //   93: astore 4
    //   95: aload_3
    //   96: invokevirtual 43	android/os/Parcel:recycle	()V
    //   99: aload_2
    //   100: invokevirtual 43	android/os/Parcel:recycle	()V
    //   103: aload 4
    //   105: athrow
    // Local variable table:
    //   start	length	slot	name	signature
    //   0	106	0	this	zza
    //   0	106	1	paramWalletFragmentInitParams	com.google.android.gms.wallet.fragment.WalletFragmentInitParams
    //   3	97	2	localParcel1	Parcel
    //   7	89	3	localParcel2	Parcel
    //   10	74	4	localObject1	Object
    //   93	11	4	localObject2	Object
    //   23	58	5	i	int
    //   51	5	6	j	int
    // Exception table:
    //   from	to	target	type
    //   13	18	93	finally
    //   26	31	93	finally
    //   39	43	93	finally
    //   43	47	93	finally
    //   59	66	93	finally
    //   66	70	93	finally
    //   86	90	93	finally
  }
  
  /* Error */
  public void onActivityResult(int paramInt1, int paramInt2, android.content.Intent paramIntent)
  {
    // Byte code:
    //   0: invokestatic 20	android/os/Parcel:obtain	()Landroid/os/Parcel;
    //   3: astore 4
    //   5: invokestatic 20	android/os/Parcel:obtain	()Landroid/os/Parcel;
    //   8: astore 5
    //   10: ldc 22
    //   12: astore 6
    //   14: aload 4
    //   16: aload 6
    //   18: invokevirtual 26	android/os/Parcel:writeInterfaceToken	(Ljava/lang/String;)V
    //   21: aload 4
    //   23: iload_1
    //   24: invokevirtual 48	android/os/Parcel:writeInt	(I)V
    //   27: aload 4
    //   29: iload_2
    //   30: invokevirtual 48	android/os/Parcel:writeInt	(I)V
    //   33: aload_3
    //   34: ifnull +67 -> 101
    //   37: iconst_1
    //   38: istore 7
    //   40: aload 4
    //   42: iload 7
    //   44: invokevirtual 48	android/os/Parcel:writeInt	(I)V
    //   47: iconst_0
    //   48: istore 7
    //   50: aconst_null
    //   51: astore 6
    //   53: aload_3
    //   54: aload 4
    //   56: iconst_0
    //   57: invokevirtual 58	android/content/Intent:writeToParcel	(Landroid/os/Parcel;I)V
    //   60: aload_0
    //   61: getfield 14	com/google/android/gms/internal/zzrx$zza$zza:zzoz	Landroid/os/IBinder;
    //   64: astore 6
    //   66: bipush 9
    //   68: istore 8
    //   70: aload 6
    //   72: iload 8
    //   74: aload 4
    //   76: aload 5
    //   78: iconst_0
    //   79: invokeinterface 33 5 0
    //   84: pop
    //   85: aload 5
    //   87: invokevirtual 36	android/os/Parcel:readException	()V
    //   90: aload 5
    //   92: invokevirtual 43	android/os/Parcel:recycle	()V
    //   95: aload 4
    //   97: invokevirtual 43	android/os/Parcel:recycle	()V
    //   100: return
    //   101: iconst_0
    //   102: istore 7
    //   104: aconst_null
    //   105: astore 6
    //   107: aload 4
    //   109: iconst_0
    //   110: invokevirtual 48	android/os/Parcel:writeInt	(I)V
    //   113: goto -53 -> 60
    //   116: astore 6
    //   118: aload 5
    //   120: invokevirtual 43	android/os/Parcel:recycle	()V
    //   123: aload 4
    //   125: invokevirtual 43	android/os/Parcel:recycle	()V
    //   128: aload 6
    //   130: athrow
    // Local variable table:
    //   start	length	slot	name	signature
    //   0	131	0	this	zza
    //   0	131	1	paramInt1	int
    //   0	131	2	paramInt2	int
    //   0	131	3	paramIntent	android.content.Intent
    //   3	121	4	localParcel1	Parcel
    //   8	111	5	localParcel2	Parcel
    //   12	94	6	localObject1	Object
    //   116	13	6	localObject2	Object
    //   38	65	7	i	int
    //   68	5	8	j	int
    // Exception table:
    //   from	to	target	type
    //   16	21	116	finally
    //   23	27	116	finally
    //   29	33	116	finally
    //   42	47	116	finally
    //   56	60	116	finally
    //   60	64	116	finally
    //   78	85	116	finally
    //   85	90	116	finally
    //   109	113	116	finally
  }
  
  /* Error */
  public void onCreate(Bundle paramBundle)
  {
    // Byte code:
    //   0: invokestatic 20	android/os/Parcel:obtain	()Landroid/os/Parcel;
    //   3: astore_2
    //   4: invokestatic 20	android/os/Parcel:obtain	()Landroid/os/Parcel;
    //   7: astore_3
    //   8: ldc 22
    //   10: astore 4
    //   12: aload_2
    //   13: aload 4
    //   15: invokevirtual 26	android/os/Parcel:writeInterfaceToken	(Ljava/lang/String;)V
    //   18: aload_1
    //   19: ifnull +59 -> 78
    //   22: iconst_1
    //   23: istore 5
    //   25: aload_2
    //   26: iload 5
    //   28: invokevirtual 48	android/os/Parcel:writeInt	(I)V
    //   31: iconst_0
    //   32: istore 5
    //   34: aconst_null
    //   35: astore 4
    //   37: aload_1
    //   38: aload_2
    //   39: iconst_0
    //   40: invokevirtual 62	android/os/Bundle:writeToParcel	(Landroid/os/Parcel;I)V
    //   43: aload_0
    //   44: getfield 14	com/google/android/gms/internal/zzrx$zza$zza:zzoz	Landroid/os/IBinder;
    //   47: astore 4
    //   49: iconst_2
    //   50: istore 6
    //   52: aload 4
    //   54: iload 6
    //   56: aload_2
    //   57: aload_3
    //   58: iconst_0
    //   59: invokeinterface 33 5 0
    //   64: pop
    //   65: aload_3
    //   66: invokevirtual 36	android/os/Parcel:readException	()V
    //   69: aload_3
    //   70: invokevirtual 43	android/os/Parcel:recycle	()V
    //   73: aload_2
    //   74: invokevirtual 43	android/os/Parcel:recycle	()V
    //   77: return
    //   78: iconst_0
    //   79: istore 5
    //   81: aconst_null
    //   82: astore 4
    //   84: aload_2
    //   85: iconst_0
    //   86: invokevirtual 48	android/os/Parcel:writeInt	(I)V
    //   89: goto -46 -> 43
    //   92: astore 4
    //   94: aload_3
    //   95: invokevirtual 43	android/os/Parcel:recycle	()V
    //   98: aload_2
    //   99: invokevirtual 43	android/os/Parcel:recycle	()V
    //   102: aload 4
    //   104: athrow
    // Local variable table:
    //   start	length	slot	name	signature
    //   0	105	0	this	zza
    //   0	105	1	paramBundle	Bundle
    //   3	96	2	localParcel1	Parcel
    //   7	88	3	localParcel2	Parcel
    //   10	73	4	localObject1	Object
    //   92	11	4	localObject2	Object
    //   23	57	5	i	int
    //   50	5	6	j	int
    // Exception table:
    //   from	to	target	type
    //   13	18	92	finally
    //   26	31	92	finally
    //   39	43	92	finally
    //   43	47	92	finally
    //   58	65	92	finally
    //   65	69	92	finally
    //   85	89	92	finally
  }
  
  /* Error */
  public zzd onCreateView(zzd paramzzd1, zzd paramzzd2, Bundle paramBundle)
  {
    // Byte code:
    //   0: iconst_0
    //   1: istore 4
    //   3: aconst_null
    //   4: astore 5
    //   6: invokestatic 20	android/os/Parcel:obtain	()Landroid/os/Parcel;
    //   9: astore 6
    //   11: invokestatic 20	android/os/Parcel:obtain	()Landroid/os/Parcel;
    //   14: astore 7
    //   16: ldc 22
    //   18: astore 8
    //   20: aload 6
    //   22: aload 8
    //   24: invokevirtual 26	android/os/Parcel:writeInterfaceToken	(Ljava/lang/String;)V
    //   27: aload_1
    //   28: ifnull +120 -> 148
    //   31: aload_1
    //   32: invokeinterface 69 1 0
    //   37: astore 8
    //   39: aload 6
    //   41: aload 8
    //   43: invokevirtual 73	android/os/Parcel:writeStrongBinder	(Landroid/os/IBinder;)V
    //   46: aload_2
    //   47: ifnull +11 -> 58
    //   50: aload_2
    //   51: invokeinterface 69 1 0
    //   56: astore 5
    //   58: aload 6
    //   60: aload 5
    //   62: invokevirtual 73	android/os/Parcel:writeStrongBinder	(Landroid/os/IBinder;)V
    //   65: aload_3
    //   66: ifnull +91 -> 157
    //   69: iconst_1
    //   70: istore 4
    //   72: aload 6
    //   74: iload 4
    //   76: invokevirtual 48	android/os/Parcel:writeInt	(I)V
    //   79: iconst_0
    //   80: istore 4
    //   82: aconst_null
    //   83: astore 5
    //   85: aload_3
    //   86: aload 6
    //   88: iconst_0
    //   89: invokevirtual 62	android/os/Bundle:writeToParcel	(Landroid/os/Parcel;I)V
    //   92: aload_0
    //   93: getfield 14	com/google/android/gms/internal/zzrx$zza$zza:zzoz	Landroid/os/IBinder;
    //   96: astore 5
    //   98: iconst_3
    //   99: istore 9
    //   101: aload 5
    //   103: iload 9
    //   105: aload 6
    //   107: aload 7
    //   109: iconst_0
    //   110: invokeinterface 33 5 0
    //   115: pop
    //   116: aload 7
    //   118: invokevirtual 36	android/os/Parcel:readException	()V
    //   121: aload 7
    //   123: invokevirtual 77	android/os/Parcel:readStrongBinder	()Landroid/os/IBinder;
    //   126: astore 5
    //   128: aload 5
    //   130: invokestatic 83	com/google/android/gms/dynamic/zzd$zza:zzbs	(Landroid/os/IBinder;)Lcom/google/android/gms/dynamic/zzd;
    //   133: astore 5
    //   135: aload 7
    //   137: invokevirtual 43	android/os/Parcel:recycle	()V
    //   140: aload 6
    //   142: invokevirtual 43	android/os/Parcel:recycle	()V
    //   145: aload 5
    //   147: areturn
    //   148: iconst_0
    //   149: istore 9
    //   151: aconst_null
    //   152: astore 8
    //   154: goto -115 -> 39
    //   157: iconst_0
    //   158: istore 4
    //   160: aconst_null
    //   161: astore 5
    //   163: aload 6
    //   165: iconst_0
    //   166: invokevirtual 48	android/os/Parcel:writeInt	(I)V
    //   169: goto -77 -> 92
    //   172: astore 5
    //   174: aload 7
    //   176: invokevirtual 43	android/os/Parcel:recycle	()V
    //   179: aload 6
    //   181: invokevirtual 43	android/os/Parcel:recycle	()V
    //   184: aload 5
    //   186: athrow
    // Local variable table:
    //   start	length	slot	name	signature
    //   0	187	0	this	zza
    //   0	187	1	paramzzd1	zzd
    //   0	187	2	paramzzd2	zzd
    //   0	187	3	paramBundle	Bundle
    //   1	158	4	i	int
    //   4	158	5	localObject1	Object
    //   172	13	5	localObject2	Object
    //   9	171	6	localParcel1	Parcel
    //   14	161	7	localParcel2	Parcel
    //   18	135	8	localObject3	Object
    //   99	51	9	j	int
    // Exception table:
    //   from	to	target	type
    //   22	27	172	finally
    //   31	37	172	finally
    //   41	46	172	finally
    //   50	56	172	finally
    //   60	65	172	finally
    //   74	79	172	finally
    //   88	92	172	finally
    //   92	96	172	finally
    //   109	116	172	finally
    //   116	121	172	finally
    //   121	126	172	finally
    //   128	133	172	finally
    //   165	169	172	finally
  }
  
  public void onPause()
  {
    Parcel localParcel1 = Parcel.obtain();
    Parcel localParcel2 = Parcel.obtain();
    Object localObject1 = "com.google.android.gms.wallet.fragment.internal.IWalletFragmentDelegate";
    try
    {
      localParcel1.writeInterfaceToken((String)localObject1);
      localObject1 = this.zzoz;
      int i = 6;
      ((IBinder)localObject1).transact(i, localParcel1, localParcel2, 0);
      localParcel2.readException();
      return;
    }
    finally
    {
      localParcel2.recycle();
      localParcel1.recycle();
    }
  }
  
  public void onResume()
  {
    Parcel localParcel1 = Parcel.obtain();
    Parcel localParcel2 = Parcel.obtain();
    Object localObject1 = "com.google.android.gms.wallet.fragment.internal.IWalletFragmentDelegate";
    try
    {
      localParcel1.writeInterfaceToken((String)localObject1);
      localObject1 = this.zzoz;
      int i = 5;
      ((IBinder)localObject1).transact(i, localParcel1, localParcel2, 0);
      localParcel2.readException();
      return;
    }
    finally
    {
      localParcel2.recycle();
      localParcel1.recycle();
    }
  }
  
  /* Error */
  public void onSaveInstanceState(Bundle paramBundle)
  {
    // Byte code:
    //   0: invokestatic 20	android/os/Parcel:obtain	()Landroid/os/Parcel;
    //   3: astore_2
    //   4: invokestatic 20	android/os/Parcel:obtain	()Landroid/os/Parcel;
    //   7: astore_3
    //   8: ldc 22
    //   10: astore 4
    //   12: aload_2
    //   13: aload 4
    //   15: invokevirtual 26	android/os/Parcel:writeInterfaceToken	(Ljava/lang/String;)V
    //   18: aload_1
    //   19: ifnull +76 -> 95
    //   22: iconst_1
    //   23: istore 5
    //   25: aload_2
    //   26: iload 5
    //   28: invokevirtual 48	android/os/Parcel:writeInt	(I)V
    //   31: iconst_0
    //   32: istore 5
    //   34: aconst_null
    //   35: astore 4
    //   37: aload_1
    //   38: aload_2
    //   39: iconst_0
    //   40: invokevirtual 62	android/os/Bundle:writeToParcel	(Landroid/os/Parcel;I)V
    //   43: aload_0
    //   44: getfield 14	com/google/android/gms/internal/zzrx$zza$zza:zzoz	Landroid/os/IBinder;
    //   47: astore 4
    //   49: bipush 8
    //   51: istore 6
    //   53: aload 4
    //   55: iload 6
    //   57: aload_2
    //   58: aload_3
    //   59: iconst_0
    //   60: invokeinterface 33 5 0
    //   65: pop
    //   66: aload_3
    //   67: invokevirtual 36	android/os/Parcel:readException	()V
    //   70: aload_3
    //   71: invokevirtual 40	android/os/Parcel:readInt	()I
    //   74: istore 5
    //   76: iload 5
    //   78: ifeq +8 -> 86
    //   81: aload_1
    //   82: aload_3
    //   83: invokevirtual 90	android/os/Bundle:readFromParcel	(Landroid/os/Parcel;)V
    //   86: aload_3
    //   87: invokevirtual 43	android/os/Parcel:recycle	()V
    //   90: aload_2
    //   91: invokevirtual 43	android/os/Parcel:recycle	()V
    //   94: return
    //   95: iconst_0
    //   96: istore 5
    //   98: aconst_null
    //   99: astore 4
    //   101: aload_2
    //   102: iconst_0
    //   103: invokevirtual 48	android/os/Parcel:writeInt	(I)V
    //   106: goto -63 -> 43
    //   109: astore 4
    //   111: aload_3
    //   112: invokevirtual 43	android/os/Parcel:recycle	()V
    //   115: aload_2
    //   116: invokevirtual 43	android/os/Parcel:recycle	()V
    //   119: aload 4
    //   121: athrow
    // Local variable table:
    //   start	length	slot	name	signature
    //   0	122	0	this	zza
    //   0	122	1	paramBundle	Bundle
    //   3	113	2	localParcel1	Parcel
    //   7	105	3	localParcel2	Parcel
    //   10	90	4	localObject1	Object
    //   109	11	4	localObject2	Object
    //   23	74	5	i	int
    //   51	5	6	j	int
    // Exception table:
    //   from	to	target	type
    //   13	18	109	finally
    //   26	31	109	finally
    //   39	43	109	finally
    //   43	47	109	finally
    //   59	66	109	finally
    //   66	70	109	finally
    //   70	74	109	finally
    //   82	86	109	finally
    //   102	106	109	finally
  }
  
  public void onStart()
  {
    Parcel localParcel1 = Parcel.obtain();
    Parcel localParcel2 = Parcel.obtain();
    Object localObject1 = "com.google.android.gms.wallet.fragment.internal.IWalletFragmentDelegate";
    try
    {
      localParcel1.writeInterfaceToken((String)localObject1);
      localObject1 = this.zzoz;
      int i = 4;
      ((IBinder)localObject1).transact(i, localParcel1, localParcel2, 0);
      localParcel2.readException();
      return;
    }
    finally
    {
      localParcel2.recycle();
      localParcel1.recycle();
    }
  }
  
  public void onStop()
  {
    Parcel localParcel1 = Parcel.obtain();
    Parcel localParcel2 = Parcel.obtain();
    Object localObject1 = "com.google.android.gms.wallet.fragment.internal.IWalletFragmentDelegate";
    try
    {
      localParcel1.writeInterfaceToken((String)localObject1);
      localObject1 = this.zzoz;
      int i = 7;
      ((IBinder)localObject1).transact(i, localParcel1, localParcel2, 0);
      localParcel2.readException();
      return;
    }
    finally
    {
      localParcel2.recycle();
      localParcel1.recycle();
    }
  }
  
  public void setEnabled(boolean paramBoolean)
  {
    int i = 0;
    IBinder localIBinder = null;
    Parcel localParcel1 = Parcel.obtain();
    Parcel localParcel2 = Parcel.obtain();
    String str = "com.google.android.gms.wallet.fragment.internal.IWalletFragmentDelegate";
    try
    {
      localParcel1.writeInterfaceToken(str);
      if (paramBoolean) {
        i = 1;
      }
      localParcel1.writeInt(i);
      localIBinder = this.zzoz;
      int j = 12;
      localIBinder.transact(j, localParcel1, localParcel2, 0);
      localParcel2.readException();
      return;
    }
    finally
    {
      localParcel2.recycle();
      localParcel1.recycle();
    }
  }
  
  /* Error */
  public void updateMaskedWallet(com.google.android.gms.wallet.MaskedWallet paramMaskedWallet)
  {
    // Byte code:
    //   0: invokestatic 20	android/os/Parcel:obtain	()Landroid/os/Parcel;
    //   3: astore_2
    //   4: invokestatic 20	android/os/Parcel:obtain	()Landroid/os/Parcel;
    //   7: astore_3
    //   8: ldc 22
    //   10: astore 4
    //   12: aload_2
    //   13: aload 4
    //   15: invokevirtual 26	android/os/Parcel:writeInterfaceToken	(Ljava/lang/String;)V
    //   18: aload_1
    //   19: ifnull +60 -> 79
    //   22: iconst_1
    //   23: istore 5
    //   25: aload_2
    //   26: iload 5
    //   28: invokevirtual 48	android/os/Parcel:writeInt	(I)V
    //   31: iconst_0
    //   32: istore 5
    //   34: aconst_null
    //   35: astore 4
    //   37: aload_1
    //   38: aload_2
    //   39: iconst_0
    //   40: invokevirtual 96	com/google/android/gms/wallet/MaskedWallet:writeToParcel	(Landroid/os/Parcel;I)V
    //   43: aload_0
    //   44: getfield 14	com/google/android/gms/internal/zzrx$zza$zza:zzoz	Landroid/os/IBinder;
    //   47: astore 4
    //   49: bipush 14
    //   51: istore 6
    //   53: aload 4
    //   55: iload 6
    //   57: aload_2
    //   58: aload_3
    //   59: iconst_0
    //   60: invokeinterface 33 5 0
    //   65: pop
    //   66: aload_3
    //   67: invokevirtual 36	android/os/Parcel:readException	()V
    //   70: aload_3
    //   71: invokevirtual 43	android/os/Parcel:recycle	()V
    //   74: aload_2
    //   75: invokevirtual 43	android/os/Parcel:recycle	()V
    //   78: return
    //   79: iconst_0
    //   80: istore 5
    //   82: aconst_null
    //   83: astore 4
    //   85: aload_2
    //   86: iconst_0
    //   87: invokevirtual 48	android/os/Parcel:writeInt	(I)V
    //   90: goto -47 -> 43
    //   93: astore 4
    //   95: aload_3
    //   96: invokevirtual 43	android/os/Parcel:recycle	()V
    //   99: aload_2
    //   100: invokevirtual 43	android/os/Parcel:recycle	()V
    //   103: aload 4
    //   105: athrow
    // Local variable table:
    //   start	length	slot	name	signature
    //   0	106	0	this	zza
    //   0	106	1	paramMaskedWallet	com.google.android.gms.wallet.MaskedWallet
    //   3	97	2	localParcel1	Parcel
    //   7	89	3	localParcel2	Parcel
    //   10	74	4	localObject1	Object
    //   93	11	4	localObject2	Object
    //   23	58	5	i	int
    //   51	5	6	j	int
    // Exception table:
    //   from	to	target	type
    //   13	18	93	finally
    //   26	31	93	finally
    //   39	43	93	finally
    //   43	47	93	finally
    //   59	66	93	finally
    //   66	70	93	finally
    //   86	90	93	finally
  }
  
  /* Error */
  public void updateMaskedWalletRequest(com.google.android.gms.wallet.MaskedWalletRequest paramMaskedWalletRequest)
  {
    // Byte code:
    //   0: invokestatic 20	android/os/Parcel:obtain	()Landroid/os/Parcel;
    //   3: astore_2
    //   4: invokestatic 20	android/os/Parcel:obtain	()Landroid/os/Parcel;
    //   7: astore_3
    //   8: ldc 22
    //   10: astore 4
    //   12: aload_2
    //   13: aload 4
    //   15: invokevirtual 26	android/os/Parcel:writeInterfaceToken	(Ljava/lang/String;)V
    //   18: aload_1
    //   19: ifnull +60 -> 79
    //   22: iconst_1
    //   23: istore 5
    //   25: aload_2
    //   26: iload 5
    //   28: invokevirtual 48	android/os/Parcel:writeInt	(I)V
    //   31: iconst_0
    //   32: istore 5
    //   34: aconst_null
    //   35: astore 4
    //   37: aload_1
    //   38: aload_2
    //   39: iconst_0
    //   40: invokevirtual 100	com/google/android/gms/wallet/MaskedWalletRequest:writeToParcel	(Landroid/os/Parcel;I)V
    //   43: aload_0
    //   44: getfield 14	com/google/android/gms/internal/zzrx$zza$zza:zzoz	Landroid/os/IBinder;
    //   47: astore 4
    //   49: bipush 11
    //   51: istore 6
    //   53: aload 4
    //   55: iload 6
    //   57: aload_2
    //   58: aload_3
    //   59: iconst_0
    //   60: invokeinterface 33 5 0
    //   65: pop
    //   66: aload_3
    //   67: invokevirtual 36	android/os/Parcel:readException	()V
    //   70: aload_3
    //   71: invokevirtual 43	android/os/Parcel:recycle	()V
    //   74: aload_2
    //   75: invokevirtual 43	android/os/Parcel:recycle	()V
    //   78: return
    //   79: iconst_0
    //   80: istore 5
    //   82: aconst_null
    //   83: astore 4
    //   85: aload_2
    //   86: iconst_0
    //   87: invokevirtual 48	android/os/Parcel:writeInt	(I)V
    //   90: goto -47 -> 43
    //   93: astore 4
    //   95: aload_3
    //   96: invokevirtual 43	android/os/Parcel:recycle	()V
    //   99: aload_2
    //   100: invokevirtual 43	android/os/Parcel:recycle	()V
    //   103: aload 4
    //   105: athrow
    // Local variable table:
    //   start	length	slot	name	signature
    //   0	106	0	this	zza
    //   0	106	1	paramMaskedWalletRequest	com.google.android.gms.wallet.MaskedWalletRequest
    //   3	97	2	localParcel1	Parcel
    //   7	89	3	localParcel2	Parcel
    //   10	74	4	localObject1	Object
    //   93	11	4	localObject2	Object
    //   23	58	5	i	int
    //   51	5	6	j	int
    // Exception table:
    //   from	to	target	type
    //   13	18	93	finally
    //   26	31	93	finally
    //   39	43	93	finally
    //   43	47	93	finally
    //   59	66	93	finally
    //   66	70	93	finally
    //   86	90	93	finally
  }
  
  public void zza(zzd paramzzd, WalletFragmentOptions paramWalletFragmentOptions, Bundle paramBundle)
  {
    Parcel localParcel1 = Parcel.obtain();
    Parcel localParcel2 = Parcel.obtain();
    Object localObject1 = "com.google.android.gms.wallet.fragment.internal.IWalletFragmentDelegate";
    for (;;)
    {
      try
      {
        localParcel1.writeInterfaceToken((String)localObject1);
        if (paramzzd != null)
        {
          localObject1 = paramzzd.asBinder();
          localParcel1.writeStrongBinder((IBinder)localObject1);
          if (paramWalletFragmentOptions != null)
          {
            i = 1;
            localParcel1.writeInt(i);
            i = 0;
            localObject1 = null;
            paramWalletFragmentOptions.writeToParcel(localParcel1, 0);
            if (paramBundle == null) {
              break label173;
            }
            i = 1;
            localParcel1.writeInt(i);
            i = 0;
            localObject1 = null;
            paramBundle.writeToParcel(localParcel1, 0);
            localObject1 = this.zzoz;
            int j = 1;
            ((IBinder)localObject1).transact(j, localParcel1, localParcel2, 0);
            localParcel2.readException();
          }
        }
        else
        {
          i = 0;
          localObject1 = null;
          continue;
        }
        int i = 0;
        localObject1 = null;
        localParcel1.writeInt(0);
        continue;
        i = 0;
      }
      finally
      {
        localParcel2.recycle();
        localParcel1.recycle();
      }
      label173:
      Object localObject3 = null;
      localParcel1.writeInt(0);
    }
  }
}


/* Location:              C:\Users\haryo\Desktop\enjarify-master\presensi-enjarify.jar!\com\google\android\gms\internal\zzrx$zza$zza.class
 * Java compiler version: 5 (49.0)
 * JD-Core Version:       0.7.1
 */