package com.google.android.gms.internal;

import android.os.Bundle;
import android.os.IBinder;
import android.os.Parcel;
import com.google.android.gms.wallet.CreateWalletObjectsRequest;
import com.google.android.gms.wallet.FullWalletRequest;
import com.google.android.gms.wallet.IsReadyToPayRequest;
import com.google.android.gms.wallet.MaskedWalletRequest;
import com.google.android.gms.wallet.NotifyTransactionStatusRequest;
import com.google.android.gms.wallet.firstparty.GetBuyFlowInitializationTokenRequest;
import com.google.android.gms.wallet.firstparty.GetInstrumentsRequest;
import com.google.android.gms.wallet.firstparty.InitializeBuyFlowRequest;

class zzrz$zza$zza
  implements zzrz
{
  private IBinder zzoz;
  
  zzrz$zza$zza(IBinder paramIBinder)
  {
    this.zzoz = paramIBinder;
  }
  
  public IBinder asBinder()
  {
    return this.zzoz;
  }
  
  /* Error */
  public void zzK(Bundle paramBundle)
  {
    // Byte code:
    //   0: invokestatic 20	android/os/Parcel:obtain	()Landroid/os/Parcel;
    //   3: astore_2
    //   4: ldc 22
    //   6: astore_3
    //   7: aload_2
    //   8: aload_3
    //   9: invokevirtual 26	android/os/Parcel:writeInterfaceToken	(Ljava/lang/String;)V
    //   12: aload_1
    //   13: ifnull +53 -> 66
    //   16: iconst_1
    //   17: istore 4
    //   19: aload_2
    //   20: iload 4
    //   22: invokevirtual 31	android/os/Parcel:writeInt	(I)V
    //   25: iconst_0
    //   26: istore 4
    //   28: aconst_null
    //   29: astore_3
    //   30: aload_1
    //   31: aload_2
    //   32: iconst_0
    //   33: invokevirtual 37	android/os/Bundle:writeToParcel	(Landroid/os/Parcel;I)V
    //   36: aload_0
    //   37: getfield 14	com/google/android/gms/internal/zzrz$zza$zza:zzoz	Landroid/os/IBinder;
    //   40: astore_3
    //   41: bipush 9
    //   43: istore 5
    //   45: iconst_1
    //   46: istore 6
    //   48: aload_3
    //   49: iload 5
    //   51: aload_2
    //   52: aconst_null
    //   53: iload 6
    //   55: invokeinterface 44 5 0
    //   60: pop
    //   61: aload_2
    //   62: invokevirtual 47	android/os/Parcel:recycle	()V
    //   65: return
    //   66: iconst_0
    //   67: istore 4
    //   69: aconst_null
    //   70: astore_3
    //   71: aload_2
    //   72: iconst_0
    //   73: invokevirtual 31	android/os/Parcel:writeInt	(I)V
    //   76: goto -40 -> 36
    //   79: astore_3
    //   80: aload_2
    //   81: invokevirtual 47	android/os/Parcel:recycle	()V
    //   84: aload_3
    //   85: athrow
    // Local variable table:
    //   start	length	slot	name	signature
    //   0	86	0	this	zza
    //   0	86	1	paramBundle	Bundle
    //   3	78	2	localParcel	Parcel
    //   6	65	3	localObject1	Object
    //   79	6	3	localObject2	Object
    //   17	51	4	i	int
    //   43	7	5	j	int
    //   46	8	6	k	int
    // Exception table:
    //   from	to	target	type
    //   8	12	79	finally
    //   20	25	79	finally
    //   32	36	79	finally
    //   36	40	79	finally
    //   53	61	79	finally
    //   72	76	79	finally
  }
  
  /* Error */
  public void zzL(Bundle paramBundle)
  {
    // Byte code:
    //   0: invokestatic 20	android/os/Parcel:obtain	()Landroid/os/Parcel;
    //   3: astore_2
    //   4: ldc 22
    //   6: astore_3
    //   7: aload_2
    //   8: aload_3
    //   9: invokevirtual 26	android/os/Parcel:writeInterfaceToken	(Ljava/lang/String;)V
    //   12: aload_1
    //   13: ifnull +53 -> 66
    //   16: iconst_1
    //   17: istore 4
    //   19: aload_2
    //   20: iload 4
    //   22: invokevirtual 31	android/os/Parcel:writeInt	(I)V
    //   25: iconst_0
    //   26: istore 4
    //   28: aconst_null
    //   29: astore_3
    //   30: aload_1
    //   31: aload_2
    //   32: iconst_0
    //   33: invokevirtual 37	android/os/Bundle:writeToParcel	(Landroid/os/Parcel;I)V
    //   36: aload_0
    //   37: getfield 14	com/google/android/gms/internal/zzrz$zza$zza:zzoz	Landroid/os/IBinder;
    //   40: astore_3
    //   41: bipush 10
    //   43: istore 5
    //   45: iconst_1
    //   46: istore 6
    //   48: aload_3
    //   49: iload 5
    //   51: aload_2
    //   52: aconst_null
    //   53: iload 6
    //   55: invokeinterface 44 5 0
    //   60: pop
    //   61: aload_2
    //   62: invokevirtual 47	android/os/Parcel:recycle	()V
    //   65: return
    //   66: iconst_0
    //   67: istore 4
    //   69: aconst_null
    //   70: astore_3
    //   71: aload_2
    //   72: iconst_0
    //   73: invokevirtual 31	android/os/Parcel:writeInt	(I)V
    //   76: goto -40 -> 36
    //   79: astore_3
    //   80: aload_2
    //   81: invokevirtual 47	android/os/Parcel:recycle	()V
    //   84: aload_3
    //   85: athrow
    // Local variable table:
    //   start	length	slot	name	signature
    //   0	86	0	this	zza
    //   0	86	1	paramBundle	Bundle
    //   3	78	2	localParcel	Parcel
    //   6	65	3	localObject1	Object
    //   79	6	3	localObject2	Object
    //   17	51	4	i	int
    //   43	7	5	j	int
    //   46	8	6	k	int
    // Exception table:
    //   from	to	target	type
    //   8	12	79	finally
    //   20	25	79	finally
    //   32	36	79	finally
    //   36	40	79	finally
    //   53	61	79	finally
    //   72	76	79	finally
  }
  
  /* Error */
  public void zza(Bundle paramBundle, zzsc paramzzsc)
  {
    // Byte code:
    //   0: aconst_null
    //   1: astore_3
    //   2: invokestatic 20	android/os/Parcel:obtain	()Landroid/os/Parcel;
    //   5: astore 4
    //   7: ldc 22
    //   9: astore 5
    //   11: aload 4
    //   13: aload 5
    //   15: invokevirtual 26	android/os/Parcel:writeInterfaceToken	(Ljava/lang/String;)V
    //   18: aload_1
    //   19: ifnull +74 -> 93
    //   22: iconst_1
    //   23: istore 6
    //   25: aload 4
    //   27: iload 6
    //   29: invokevirtual 31	android/os/Parcel:writeInt	(I)V
    //   32: iconst_0
    //   33: istore 6
    //   35: aconst_null
    //   36: astore 5
    //   38: aload_1
    //   39: aload 4
    //   41: iconst_0
    //   42: invokevirtual 37	android/os/Bundle:writeToParcel	(Landroid/os/Parcel;I)V
    //   45: aload_2
    //   46: ifnull +10 -> 56
    //   49: aload_2
    //   50: invokeinterface 54 1 0
    //   55: astore_3
    //   56: aload 4
    //   58: aload_3
    //   59: invokevirtual 58	android/os/Parcel:writeStrongBinder	(Landroid/os/IBinder;)V
    //   62: aload_0
    //   63: getfield 14	com/google/android/gms/internal/zzrz$zza$zza:zzoz	Landroid/os/IBinder;
    //   66: astore_3
    //   67: iconst_5
    //   68: istore 6
    //   70: iconst_1
    //   71: istore 7
    //   73: aload_3
    //   74: iload 6
    //   76: aload 4
    //   78: aconst_null
    //   79: iload 7
    //   81: invokeinterface 44 5 0
    //   86: pop
    //   87: aload 4
    //   89: invokevirtual 47	android/os/Parcel:recycle	()V
    //   92: return
    //   93: iconst_0
    //   94: istore 6
    //   96: aconst_null
    //   97: astore 5
    //   99: aload 4
    //   101: iconst_0
    //   102: invokevirtual 31	android/os/Parcel:writeInt	(I)V
    //   105: goto -60 -> 45
    //   108: astore_3
    //   109: aload 4
    //   111: invokevirtual 47	android/os/Parcel:recycle	()V
    //   114: aload_3
    //   115: athrow
    // Local variable table:
    //   start	length	slot	name	signature
    //   0	116	0	this	zza
    //   0	116	1	paramBundle	Bundle
    //   0	116	2	paramzzsc	zzsc
    //   1	73	3	localIBinder	IBinder
    //   108	7	3	localObject	Object
    //   5	105	4	localParcel	Parcel
    //   9	89	5	str	String
    //   23	72	6	i	int
    //   71	9	7	j	int
    // Exception table:
    //   from	to	target	type
    //   13	18	108	finally
    //   27	32	108	finally
    //   41	45	108	finally
    //   49	55	108	finally
    //   58	62	108	finally
    //   62	66	108	finally
    //   79	87	108	finally
    //   101	105	108	finally
  }
  
  public void zza(CreateWalletObjectsRequest paramCreateWalletObjectsRequest, Bundle paramBundle, zzsc paramzzsc)
  {
    IBinder localIBinder = null;
    Parcel localParcel = Parcel.obtain();
    String str = "com.google.android.gms.wallet.internal.IOwService";
    for (;;)
    {
      try
      {
        localParcel.writeInterfaceToken(str);
        if (paramCreateWalletObjectsRequest != null)
        {
          i = 1;
          localParcel.writeInt(i);
          i = 0;
          str = null;
          paramCreateWalletObjectsRequest.writeToParcel(localParcel, 0);
          if (paramBundle != null)
          {
            i = 1;
            localParcel.writeInt(i);
            i = 0;
            str = null;
            paramBundle.writeToParcel(localParcel, 0);
            if (paramzzsc != null) {
              localIBinder = paramzzsc.asBinder();
            }
            localParcel.writeStrongBinder(localIBinder);
            localIBinder = this.zzoz;
            i = 6;
            int j = 1;
            localIBinder.transact(i, localParcel, null, j);
          }
        }
        else
        {
          i = 0;
          str = null;
          localParcel.writeInt(0);
          continue;
        }
        int i = 0;
      }
      finally
      {
        localParcel.recycle();
      }
      str = null;
      localParcel.writeInt(0);
    }
  }
  
  public void zza(FullWalletRequest paramFullWalletRequest, Bundle paramBundle, zzsc paramzzsc)
  {
    IBinder localIBinder = null;
    Parcel localParcel = Parcel.obtain();
    String str = "com.google.android.gms.wallet.internal.IOwService";
    for (;;)
    {
      try
      {
        localParcel.writeInterfaceToken(str);
        if (paramFullWalletRequest != null)
        {
          i = 1;
          localParcel.writeInt(i);
          i = 0;
          str = null;
          paramFullWalletRequest.writeToParcel(localParcel, 0);
          if (paramBundle != null)
          {
            i = 1;
            localParcel.writeInt(i);
            i = 0;
            str = null;
            paramBundle.writeToParcel(localParcel, 0);
            if (paramzzsc != null) {
              localIBinder = paramzzsc.asBinder();
            }
            localParcel.writeStrongBinder(localIBinder);
            localIBinder = this.zzoz;
            i = 2;
            int j = 1;
            localIBinder.transact(i, localParcel, null, j);
          }
        }
        else
        {
          i = 0;
          str = null;
          localParcel.writeInt(0);
          continue;
        }
        int i = 0;
      }
      finally
      {
        localParcel.recycle();
      }
      str = null;
      localParcel.writeInt(0);
    }
  }
  
  public void zza(IsReadyToPayRequest paramIsReadyToPayRequest, Bundle paramBundle, zzsc paramzzsc)
  {
    IBinder localIBinder = null;
    Parcel localParcel = Parcel.obtain();
    String str = "com.google.android.gms.wallet.internal.IOwService";
    for (;;)
    {
      try
      {
        localParcel.writeInterfaceToken(str);
        if (paramIsReadyToPayRequest != null)
        {
          i = 1;
          localParcel.writeInt(i);
          i = 0;
          str = null;
          paramIsReadyToPayRequest.writeToParcel(localParcel, 0);
          if (paramBundle != null)
          {
            i = 1;
            localParcel.writeInt(i);
            i = 0;
            str = null;
            paramBundle.writeToParcel(localParcel, 0);
            if (paramzzsc != null) {
              localIBinder = paramzzsc.asBinder();
            }
            localParcel.writeStrongBinder(localIBinder);
            localIBinder = this.zzoz;
            i = 14;
            int j = 1;
            localIBinder.transact(i, localParcel, null, j);
          }
        }
        else
        {
          i = 0;
          str = null;
          localParcel.writeInt(0);
          continue;
        }
        int i = 0;
      }
      finally
      {
        localParcel.recycle();
      }
      str = null;
      localParcel.writeInt(0);
    }
  }
  
  public void zza(MaskedWalletRequest paramMaskedWalletRequest, Bundle paramBundle, zzsb paramzzsb)
  {
    IBinder localIBinder = null;
    Parcel localParcel = Parcel.obtain();
    String str = "com.google.android.gms.wallet.internal.IOwService";
    for (;;)
    {
      try
      {
        localParcel.writeInterfaceToken(str);
        if (paramMaskedWalletRequest != null)
        {
          i = 1;
          localParcel.writeInt(i);
          i = 0;
          str = null;
          paramMaskedWalletRequest.writeToParcel(localParcel, 0);
          if (paramBundle != null)
          {
            i = 1;
            localParcel.writeInt(i);
            i = 0;
            str = null;
            paramBundle.writeToParcel(localParcel, 0);
            if (paramzzsb != null) {
              localIBinder = paramzzsb.asBinder();
            }
            localParcel.writeStrongBinder(localIBinder);
            localIBinder = this.zzoz;
            i = 7;
            int j = 1;
            localIBinder.transact(i, localParcel, null, j);
          }
        }
        else
        {
          i = 0;
          str = null;
          localParcel.writeInt(0);
          continue;
        }
        int i = 0;
      }
      finally
      {
        localParcel.recycle();
      }
      str = null;
      localParcel.writeInt(0);
    }
  }
  
  public void zza(MaskedWalletRequest paramMaskedWalletRequest, Bundle paramBundle, zzsc paramzzsc)
  {
    IBinder localIBinder = null;
    Parcel localParcel = Parcel.obtain();
    String str = "com.google.android.gms.wallet.internal.IOwService";
    for (;;)
    {
      try
      {
        localParcel.writeInterfaceToken(str);
        if (paramMaskedWalletRequest != null)
        {
          i = 1;
          localParcel.writeInt(i);
          i = 0;
          str = null;
          paramMaskedWalletRequest.writeToParcel(localParcel, 0);
          if (paramBundle != null)
          {
            i = 1;
            localParcel.writeInt(i);
            i = 0;
            str = null;
            paramBundle.writeToParcel(localParcel, 0);
            if (paramzzsc != null) {
              localIBinder = paramzzsc.asBinder();
            }
            localParcel.writeStrongBinder(localIBinder);
            localIBinder = this.zzoz;
            i = 1;
            int j = 1;
            localIBinder.transact(i, localParcel, null, j);
          }
        }
        else
        {
          i = 0;
          str = null;
          localParcel.writeInt(0);
          continue;
        }
        int i = 0;
      }
      finally
      {
        localParcel.recycle();
      }
      str = null;
      localParcel.writeInt(0);
    }
  }
  
  public void zza(NotifyTransactionStatusRequest paramNotifyTransactionStatusRequest, Bundle paramBundle)
  {
    Parcel localParcel = Parcel.obtain();
    Object localObject1 = "com.google.android.gms.wallet.internal.IOwService";
    for (;;)
    {
      try
      {
        localParcel.writeInterfaceToken((String)localObject1);
        if (paramNotifyTransactionStatusRequest != null)
        {
          i = 1;
          localParcel.writeInt(i);
          i = 0;
          localObject1 = null;
          paramNotifyTransactionStatusRequest.writeToParcel(localParcel, 0);
          if (paramBundle != null)
          {
            i = 1;
            localParcel.writeInt(i);
            i = 0;
            localObject1 = null;
            paramBundle.writeToParcel(localParcel, 0);
            localObject1 = this.zzoz;
            int j = 4;
            int k = 1;
            ((IBinder)localObject1).transact(j, localParcel, null, k);
          }
        }
        else
        {
          i = 0;
          localObject1 = null;
          localParcel.writeInt(0);
          continue;
        }
        int i = 0;
      }
      finally
      {
        localParcel.recycle();
      }
      Object localObject3 = null;
      localParcel.writeInt(0);
    }
  }
  
  public void zza(GetBuyFlowInitializationTokenRequest paramGetBuyFlowInitializationTokenRequest, Bundle paramBundle, zzsc paramzzsc)
  {
    IBinder localIBinder = null;
    Parcel localParcel = Parcel.obtain();
    String str = "com.google.android.gms.wallet.internal.IOwService";
    for (;;)
    {
      try
      {
        localParcel.writeInterfaceToken(str);
        if (paramGetBuyFlowInitializationTokenRequest != null)
        {
          i = 1;
          localParcel.writeInt(i);
          i = 0;
          str = null;
          paramGetBuyFlowInitializationTokenRequest.writeToParcel(localParcel, 0);
          if (paramBundle != null)
          {
            i = 1;
            localParcel.writeInt(i);
            i = 0;
            str = null;
            paramBundle.writeToParcel(localParcel, 0);
            if (paramzzsc != null) {
              localIBinder = paramzzsc.asBinder();
            }
            localParcel.writeStrongBinder(localIBinder);
            localIBinder = this.zzoz;
            i = 12;
            int j = 1;
            localIBinder.transact(i, localParcel, null, j);
          }
        }
        else
        {
          i = 0;
          str = null;
          localParcel.writeInt(0);
          continue;
        }
        int i = 0;
      }
      finally
      {
        localParcel.recycle();
      }
      str = null;
      localParcel.writeInt(0);
    }
  }
  
  public void zza(GetInstrumentsRequest paramGetInstrumentsRequest, Bundle paramBundle, zzsc paramzzsc)
  {
    IBinder localIBinder = null;
    Parcel localParcel = Parcel.obtain();
    String str = "com.google.android.gms.wallet.internal.IOwService";
    for (;;)
    {
      try
      {
        localParcel.writeInterfaceToken(str);
        if (paramGetInstrumentsRequest != null)
        {
          i = 1;
          localParcel.writeInt(i);
          i = 0;
          str = null;
          paramGetInstrumentsRequest.writeToParcel(localParcel, 0);
          if (paramBundle != null)
          {
            i = 1;
            localParcel.writeInt(i);
            i = 0;
            str = null;
            paramBundle.writeToParcel(localParcel, 0);
            if (paramzzsc != null) {
              localIBinder = paramzzsc.asBinder();
            }
            localParcel.writeStrongBinder(localIBinder);
            localIBinder = this.zzoz;
            i = 8;
            int j = 1;
            localIBinder.transact(i, localParcel, null, j);
          }
        }
        else
        {
          i = 0;
          str = null;
          localParcel.writeInt(0);
          continue;
        }
        int i = 0;
      }
      finally
      {
        localParcel.recycle();
      }
      str = null;
      localParcel.writeInt(0);
    }
  }
  
  public void zza(InitializeBuyFlowRequest paramInitializeBuyFlowRequest, Bundle paramBundle, zzsc paramzzsc)
  {
    IBinder localIBinder = null;
    Parcel localParcel = Parcel.obtain();
    String str = "com.google.android.gms.wallet.internal.IOwService";
    for (;;)
    {
      try
      {
        localParcel.writeInterfaceToken(str);
        if (paramInitializeBuyFlowRequest != null)
        {
          i = 1;
          localParcel.writeInt(i);
          i = 0;
          str = null;
          paramInitializeBuyFlowRequest.writeToParcel(localParcel, 0);
          if (paramBundle != null)
          {
            i = 1;
            localParcel.writeInt(i);
            i = 0;
            str = null;
            paramBundle.writeToParcel(localParcel, 0);
            if (paramzzsc != null) {
              localIBinder = paramzzsc.asBinder();
            }
            localParcel.writeStrongBinder(localIBinder);
            localIBinder = this.zzoz;
            i = 13;
            int j = 1;
            localIBinder.transact(i, localParcel, null, j);
          }
        }
        else
        {
          i = 0;
          str = null;
          localParcel.writeInt(0);
          continue;
        }
        int i = 0;
      }
      finally
      {
        localParcel.recycle();
      }
      str = null;
      localParcel.writeInt(0);
    }
  }
  
  /* Error */
  public void zza(String paramString1, String paramString2, Bundle paramBundle, zzsc paramzzsc)
  {
    // Byte code:
    //   0: aconst_null
    //   1: astore 5
    //   3: invokestatic 20	android/os/Parcel:obtain	()Landroid/os/Parcel;
    //   6: astore 6
    //   8: ldc 22
    //   10: astore 7
    //   12: aload 6
    //   14: aload 7
    //   16: invokevirtual 26	android/os/Parcel:writeInterfaceToken	(Ljava/lang/String;)V
    //   19: aload 6
    //   21: aload_1
    //   22: invokevirtual 97	android/os/Parcel:writeString	(Ljava/lang/String;)V
    //   25: aload 6
    //   27: aload_2
    //   28: invokevirtual 97	android/os/Parcel:writeString	(Ljava/lang/String;)V
    //   31: aload_3
    //   32: ifnull +80 -> 112
    //   35: iconst_1
    //   36: istore 8
    //   38: aload 6
    //   40: iload 8
    //   42: invokevirtual 31	android/os/Parcel:writeInt	(I)V
    //   45: iconst_0
    //   46: istore 8
    //   48: aconst_null
    //   49: astore 7
    //   51: aload_3
    //   52: aload 6
    //   54: iconst_0
    //   55: invokevirtual 37	android/os/Bundle:writeToParcel	(Landroid/os/Parcel;I)V
    //   58: aload 4
    //   60: ifnull +12 -> 72
    //   63: aload 4
    //   65: invokeinterface 54 1 0
    //   70: astore 5
    //   72: aload 6
    //   74: aload 5
    //   76: invokevirtual 58	android/os/Parcel:writeStrongBinder	(Landroid/os/IBinder;)V
    //   79: aload_0
    //   80: getfield 14	com/google/android/gms/internal/zzrz$zza$zza:zzoz	Landroid/os/IBinder;
    //   83: astore 5
    //   85: iconst_3
    //   86: istore 8
    //   88: iconst_1
    //   89: istore 9
    //   91: aload 5
    //   93: iload 8
    //   95: aload 6
    //   97: aconst_null
    //   98: iload 9
    //   100: invokeinterface 44 5 0
    //   105: pop
    //   106: aload 6
    //   108: invokevirtual 47	android/os/Parcel:recycle	()V
    //   111: return
    //   112: iconst_0
    //   113: istore 8
    //   115: aconst_null
    //   116: astore 7
    //   118: aload 6
    //   120: iconst_0
    //   121: invokevirtual 31	android/os/Parcel:writeInt	(I)V
    //   124: goto -66 -> 58
    //   127: astore 5
    //   129: aload 6
    //   131: invokevirtual 47	android/os/Parcel:recycle	()V
    //   134: aload 5
    //   136: athrow
    // Local variable table:
    //   start	length	slot	name	signature
    //   0	137	0	this	zza
    //   0	137	1	paramString1	String
    //   0	137	2	paramString2	String
    //   0	137	3	paramBundle	Bundle
    //   0	137	4	paramzzsc	zzsc
    //   1	91	5	localIBinder	IBinder
    //   127	8	5	localObject	Object
    //   6	124	6	localParcel	Parcel
    //   10	107	7	str	String
    //   36	78	8	i	int
    //   89	10	9	j	int
    // Exception table:
    //   from	to	target	type
    //   14	19	127	finally
    //   21	25	127	finally
    //   27	31	127	finally
    //   40	45	127	finally
    //   54	58	127	finally
    //   63	70	127	finally
    //   74	79	127	finally
    //   79	83	127	finally
    //   98	106	127	finally
    //   120	124	127	finally
  }
  
  /* Error */
  public void zzb(Bundle paramBundle, zzsc paramzzsc)
  {
    // Byte code:
    //   0: aconst_null
    //   1: astore_3
    //   2: invokestatic 20	android/os/Parcel:obtain	()Landroid/os/Parcel;
    //   5: astore 4
    //   7: ldc 22
    //   9: astore 5
    //   11: aload 4
    //   13: aload 5
    //   15: invokevirtual 26	android/os/Parcel:writeInterfaceToken	(Ljava/lang/String;)V
    //   18: aload_1
    //   19: ifnull +75 -> 94
    //   22: iconst_1
    //   23: istore 6
    //   25: aload 4
    //   27: iload 6
    //   29: invokevirtual 31	android/os/Parcel:writeInt	(I)V
    //   32: iconst_0
    //   33: istore 6
    //   35: aconst_null
    //   36: astore 5
    //   38: aload_1
    //   39: aload 4
    //   41: iconst_0
    //   42: invokevirtual 37	android/os/Bundle:writeToParcel	(Landroid/os/Parcel;I)V
    //   45: aload_2
    //   46: ifnull +10 -> 56
    //   49: aload_2
    //   50: invokeinterface 54 1 0
    //   55: astore_3
    //   56: aload 4
    //   58: aload_3
    //   59: invokevirtual 58	android/os/Parcel:writeStrongBinder	(Landroid/os/IBinder;)V
    //   62: aload_0
    //   63: getfield 14	com/google/android/gms/internal/zzrz$zza$zza:zzoz	Landroid/os/IBinder;
    //   66: astore_3
    //   67: bipush 11
    //   69: istore 6
    //   71: iconst_1
    //   72: istore 7
    //   74: aload_3
    //   75: iload 6
    //   77: aload 4
    //   79: aconst_null
    //   80: iload 7
    //   82: invokeinterface 44 5 0
    //   87: pop
    //   88: aload 4
    //   90: invokevirtual 47	android/os/Parcel:recycle	()V
    //   93: return
    //   94: iconst_0
    //   95: istore 6
    //   97: aconst_null
    //   98: astore 5
    //   100: aload 4
    //   102: iconst_0
    //   103: invokevirtual 31	android/os/Parcel:writeInt	(I)V
    //   106: goto -61 -> 45
    //   109: astore_3
    //   110: aload 4
    //   112: invokevirtual 47	android/os/Parcel:recycle	()V
    //   115: aload_3
    //   116: athrow
    // Local variable table:
    //   start	length	slot	name	signature
    //   0	117	0	this	zza
    //   0	117	1	paramBundle	Bundle
    //   0	117	2	paramzzsc	zzsc
    //   1	74	3	localIBinder	IBinder
    //   109	7	3	localObject	Object
    //   5	106	4	localParcel	Parcel
    //   9	90	5	str	String
    //   23	73	6	i	int
    //   72	9	7	j	int
    // Exception table:
    //   from	to	target	type
    //   13	18	109	finally
    //   27	32	109	finally
    //   41	45	109	finally
    //   49	55	109	finally
    //   58	62	109	finally
    //   62	66	109	finally
    //   80	88	109	finally
    //   102	106	109	finally
  }
}


/* Location:              C:\Users\haryo\Desktop\enjarify-master\presensi-enjarify.jar!\com\google\android\gms\internal\zzrz$zza$zza.class
 * Java compiler version: 5 (49.0)
 * JD-Core Version:       0.7.1
 */