package com.google.android.gms.internal;

import java.io.IOException;
import java.io.InputStream;
import java.util.Comparator;
import java.util.Date;
import java.util.Map;
import java.util.TreeMap;
import org.apache.http.Header;
import org.apache.http.HttpEntity;
import org.apache.http.StatusLine;
import org.apache.http.impl.cookie.DateUtils;

public class zzt
  implements zzf
{
  protected static final boolean DEBUG = zzs.DEBUG;
  private static int zzao = 3000;
  private static int zzap = 4096;
  protected final zzy zzaq;
  protected final zzu zzar;
  
  public zzt(zzy paramzzy)
  {
    this(paramzzy, localzzu);
  }
  
  public zzt(zzy paramzzy, zzu paramzzu)
  {
    this.zzaq = paramzzy;
    this.zzar = paramzzu;
  }
  
  protected static Map zza(Header[] paramArrayOfHeader)
  {
    TreeMap localTreeMap = new java/util/TreeMap;
    Comparator localComparator = String.CASE_INSENSITIVE_ORDER;
    localTreeMap.<init>(localComparator);
    int i = 0;
    localComparator = null;
    for (;;)
    {
      int j = paramArrayOfHeader.length;
      if (i >= j) {
        break;
      }
      String str1 = paramArrayOfHeader[i].getName();
      String str2 = paramArrayOfHeader[i].getValue();
      localTreeMap.put(str1, str2);
      i += 1;
    }
    return localTreeMap;
  }
  
  private void zza(long paramLong, zzk paramzzk, byte[] paramArrayOfByte, StatusLine paramStatusLine)
  {
    boolean bool = DEBUG;
    String str;
    Object[] arrayOfObject;
    Object localObject2;
    int j;
    int i;
    if (!bool)
    {
      long l = zzao;
      bool = paramLong < l;
      if (!bool) {}
    }
    else
    {
      str = "HTTP response for request=<%s> [lifetime=%d], [size=%s], [rc=%d], [retryCount=%s]";
      arrayOfObject = new Object[5];
      localObject1 = null;
      arrayOfObject[0] = paramzzk;
      bool = true;
      localObject2 = Long.valueOf(paramLong);
      arrayOfObject[bool] = localObject2;
      j = 2;
      if (paramArrayOfByte == null) {
        break label142;
      }
      i = paramArrayOfByte.length;
    }
    label142:
    for (Object localObject1 = Integer.valueOf(i);; localObject1 = "null")
    {
      arrayOfObject[j] = localObject1;
      localObject2 = Integer.valueOf(paramStatusLine.getStatusCode());
      arrayOfObject[3] = localObject2;
      i = 4;
      j = paramzzk.zzu().zze();
      localObject2 = Integer.valueOf(j);
      arrayOfObject[i] = localObject2;
      zzs.zzb(str, arrayOfObject);
      return;
    }
  }
  
  private static void zza(String paramString, zzk paramzzk, zzr paramzzr)
  {
    int i = 2;
    int j = 1;
    Object localObject1 = paramzzk.zzu();
    int k = paramzzk.zzt();
    try
    {
      ((zzo)localObject1).zza(paramzzr);
      Object[] arrayOfObject1 = new Object[i];
      arrayOfObject1[0] = paramString;
      localObject2 = Integer.valueOf(k);
      arrayOfObject1[j] = localObject2;
      localObject1 = String.format("%s-retry [timeout=%s]", arrayOfObject1);
      paramzzk.zzc((String)localObject1);
      return;
    }
    catch (zzr localzzr)
    {
      Object[] arrayOfObject2 = new Object[i];
      arrayOfObject2[0] = paramString;
      Object localObject2 = Integer.valueOf(k);
      arrayOfObject2[j] = localObject2;
      localObject2 = String.format("%s-timeout-giveup [timeout=%s]", arrayOfObject2);
      paramzzk.zzc((String)localObject2);
      throw localzzr;
    }
  }
  
  private void zza(Map paramMap, zzb.zza paramzza)
  {
    if (paramzza == null) {}
    for (;;)
    {
      return;
      Object localObject = paramzza.zzb;
      String str;
      if (localObject != null)
      {
        localObject = "If-None-Match";
        str = paramzza.zzb;
        paramMap.put(localObject, str);
      }
      long l1 = paramzza.zzd;
      long l2 = 0L;
      boolean bool = l1 < l2;
      if (bool)
      {
        localObject = new java/util/Date;
        l2 = paramzza.zzd;
        ((Date)localObject).<init>(l2);
        str = "If-Modified-Since";
        localObject = DateUtils.formatDate((Date)localObject);
        paramMap.put(str, localObject);
      }
    }
  }
  
  private byte[] zza(HttpEntity paramHttpEntity)
  {
    zzaa localzzaa = new com/google/android/gms/internal/zzaa;
    Object localObject1 = this.zzar;
    long l = paramHttpEntity.getContentLength();
    int i = (int)l;
    localzzaa.<init>((zzu)localObject1, i);
    i = 0;
    byte[] arrayOfByte2 = null;
    try
    {
      localObject1 = paramHttpEntity.getContent();
      if (localObject1 == null)
      {
        localObject1 = new com/google/android/gms/internal/zzp;
        ((zzp)localObject1).<init>();
        throw ((Throwable)localObject1);
      }
    }
    finally {}
    try
    {
      paramHttpEntity.consumeContent();
      this.zzar.zza(arrayOfByte2);
      localzzaa.close();
      throw ((Throwable)localObject2);
      zzu localzzu = this.zzar;
      int j = 1024;
      arrayOfByte2 = localzzu.zzb(j);
      for (;;)
      {
        int k = ((InputStream)localObject2).read(arrayOfByte2);
        j = -1;
        if (k == j) {
          break;
        }
        j = 0;
        arrayOfObject = null;
        localzzaa.write(arrayOfByte2, 0, k);
      }
      byte[] arrayOfByte1 = localzzaa.toByteArray();
      try
      {
        paramHttpEntity.consumeContent();
        this.zzar.zza(arrayOfByte2);
        localzzaa.close();
        return arrayOfByte1;
      }
      catch (IOException localIOException1)
      {
        for (;;)
        {
          String str1 = "Error occured when calling consumingContent";
          arrayOfObject = new Object[0];
          zzs.zza(str1, arrayOfObject);
        }
      }
    }
    catch (IOException localIOException2)
    {
      for (;;)
      {
        String str2 = "Error occured when calling consumingContent";
        Object[] arrayOfObject = new Object[0];
        zzs.zza(str2, arrayOfObject);
      }
    }
  }
  
  /* Error */
  public zzi zza(zzk paramzzk)
  {
    // Byte code:
    //   0: invokestatic 210	android/os/SystemClock:elapsedRealtime	()J
    //   3: lstore_2
    //   4: iconst_0
    //   5: istore 4
    //   7: aconst_null
    //   8: astore 5
    //   10: invokestatic 216	java/util/Collections:emptyMap	()Ljava/util/Map;
    //   13: astore 6
    //   15: new 218	java/util/HashMap
    //   18: astore 7
    //   20: aload 7
    //   22: invokespecial 219	java/util/HashMap:<init>	()V
    //   25: aload_1
    //   26: invokevirtual 223	com/google/android/gms/internal/zzk:zzi	()Lcom/google/android/gms/internal/zzb$zza;
    //   29: astore 8
    //   31: aload_0
    //   32: aload 7
    //   34: aload 8
    //   36: invokespecial 226	com/google/android/gms/internal/zzt:zza	(Ljava/util/Map;Lcom/google/android/gms/internal/zzb$zza;)V
    //   39: aload_0
    //   40: getfield 40	com/google/android/gms/internal/zzt:zzaq	Lcom/google/android/gms/internal/zzy;
    //   43: astore 8
    //   45: aload 8
    //   47: aload_1
    //   48: aload 7
    //   50: invokeinterface 231 3 0
    //   55: astore 9
    //   57: aload 9
    //   59: invokeinterface 237 1 0
    //   64: astore 10
    //   66: aload 10
    //   68: invokeinterface 91 1 0
    //   73: istore 11
    //   75: aload 9
    //   77: invokeinterface 241 1 0
    //   82: astore 7
    //   84: aload 7
    //   86: invokestatic 244	com/google/android/gms/internal/zzt:zza	([Lorg/apache/http/Header;)Ljava/util/Map;
    //   89: astore 6
    //   91: sipush 304
    //   94: istore 12
    //   96: iload 11
    //   98: iload 12
    //   100: if_icmpne +130 -> 230
    //   103: aload_1
    //   104: invokevirtual 223	com/google/android/gms/internal/zzk:zzi	()Lcom/google/android/gms/internal/zzb$zza;
    //   107: astore 7
    //   109: aload 7
    //   111: ifnonnull +43 -> 154
    //   114: new 247	com/google/android/gms/internal/zzi
    //   117: astore 5
    //   119: sipush 304
    //   122: istore 11
    //   124: aconst_null
    //   125: astore 13
    //   127: iconst_1
    //   128: istore 14
    //   130: invokestatic 210	android/os/SystemClock:elapsedRealtime	()J
    //   133: lload_2
    //   134: lsub
    //   135: lstore 15
    //   137: aload 5
    //   139: iload 11
    //   141: aconst_null
    //   142: aload 6
    //   144: iload 14
    //   146: lload 15
    //   148: invokespecial 250	com/google/android/gms/internal/zzi:<init>	(I[BLjava/util/Map;ZJ)V
    //   151: aload 5
    //   153: areturn
    //   154: aload 7
    //   156: getfield 254	com/google/android/gms/internal/zzb$zza:zzg	Ljava/util/Map;
    //   159: astore 5
    //   161: aload 5
    //   163: aload 6
    //   165: invokeinterface 258 2 0
    //   170: new 247	com/google/android/gms/internal/zzi
    //   173: astore 17
    //   175: sipush 304
    //   178: istore 18
    //   180: aload 7
    //   182: getfield 262	com/google/android/gms/internal/zzb$zza:data	[B
    //   185: astore 19
    //   187: aload 7
    //   189: getfield 254	com/google/android/gms/internal/zzb$zza:zzg	Ljava/util/Map;
    //   192: astore 20
    //   194: iconst_1
    //   195: istore 21
    //   197: invokestatic 210	android/os/SystemClock:elapsedRealtime	()J
    //   200: lstore 22
    //   202: lload 22
    //   204: lload_2
    //   205: lsub
    //   206: lstore 24
    //   208: aload 17
    //   210: iload 18
    //   212: aload 19
    //   214: aload 20
    //   216: iload 21
    //   218: lload 24
    //   220: invokespecial 250	com/google/android/gms/internal/zzi:<init>	(I[BLjava/util/Map;ZJ)V
    //   223: aload 17
    //   225: astore 5
    //   227: goto -76 -> 151
    //   230: aload 9
    //   232: invokeinterface 266 1 0
    //   237: astore 7
    //   239: aload 7
    //   241: ifnull +113 -> 354
    //   244: aload 9
    //   246: invokeinterface 266 1 0
    //   251: astore 7
    //   253: aload_0
    //   254: aload 7
    //   256: invokespecial 269	com/google/android/gms/internal/zzt:zza	(Lorg/apache/http/HttpEntity;)[B
    //   259: astore 26
    //   261: invokestatic 210	android/os/SystemClock:elapsedRealtime	()J
    //   264: lstore 22
    //   266: lload 22
    //   268: lload_2
    //   269: lsub
    //   270: lstore 15
    //   272: aload_0
    //   273: astore 17
    //   275: aload_1
    //   276: astore 20
    //   278: aload_0
    //   279: lload 15
    //   281: aload_1
    //   282: aload 26
    //   284: aload 10
    //   286: invokespecial 272	com/google/android/gms/internal/zzt:zza	(JLcom/google/android/gms/internal/zzk;[BLorg/apache/http/StatusLine;)V
    //   289: sipush 200
    //   292: istore 12
    //   294: iload 11
    //   296: iload 12
    //   298: if_icmplt +15 -> 313
    //   301: sipush 299
    //   304: istore 12
    //   306: iload 11
    //   308: iload 12
    //   310: if_icmple +58 -> 368
    //   313: new 205	java/io/IOException
    //   316: astore 7
    //   318: aload 7
    //   320: invokespecial 275	java/io/IOException:<init>	()V
    //   323: aload 7
    //   325: athrow
    //   326: astore 7
    //   328: ldc_w 277
    //   331: astore 7
    //   333: new 279	com/google/android/gms/internal/zzq
    //   336: astore 5
    //   338: aload 5
    //   340: invokespecial 280	com/google/android/gms/internal/zzq:<init>	()V
    //   343: aload 7
    //   345: aload_1
    //   346: aload 5
    //   348: invokestatic 283	com/google/android/gms/internal/zzt:zza	(Ljava/lang/String;Lcom/google/android/gms/internal/zzk;Lcom/google/android/gms/internal/zzr;)V
    //   351: goto -347 -> 4
    //   354: iconst_0
    //   355: istore 12
    //   357: aconst_null
    //   358: astore 7
    //   360: iconst_0
    //   361: newarray <illegal type>
    //   363: astore 26
    //   365: goto -104 -> 261
    //   368: new 247	com/google/android/gms/internal/zzi
    //   371: astore 5
    //   373: iconst_0
    //   374: istore 14
    //   376: aconst_null
    //   377: astore 17
    //   379: invokestatic 210	android/os/SystemClock:elapsedRealtime	()J
    //   382: lload_2
    //   383: lsub
    //   384: lstore 15
    //   386: aload 26
    //   388: astore 13
    //   390: aload 5
    //   392: iload 11
    //   394: aload 26
    //   396: aload 6
    //   398: iconst_0
    //   399: lload 15
    //   401: invokespecial 250	com/google/android/gms/internal/zzi:<init>	(I[BLjava/util/Map;ZJ)V
    //   404: goto -253 -> 151
    //   407: astore 7
    //   409: ldc_w 285
    //   412: astore 7
    //   414: new 279	com/google/android/gms/internal/zzq
    //   417: astore 5
    //   419: aload 5
    //   421: invokespecial 280	com/google/android/gms/internal/zzq:<init>	()V
    //   424: aload 7
    //   426: aload_1
    //   427: aload 5
    //   429: invokestatic 283	com/google/android/gms/internal/zzt:zza	(Ljava/lang/String;Lcom/google/android/gms/internal/zzk;Lcom/google/android/gms/internal/zzr;)V
    //   432: goto -428 -> 4
    //   435: astore 7
    //   437: new 287	java/lang/RuntimeException
    //   440: astore 5
    //   442: new 289	java/lang/StringBuilder
    //   445: astore 8
    //   447: aload 8
    //   449: invokespecial 290	java/lang/StringBuilder:<init>	()V
    //   452: aload 8
    //   454: ldc_w 292
    //   457: invokevirtual 296	java/lang/StringBuilder:append	(Ljava/lang/String;)Ljava/lang/StringBuilder;
    //   460: astore 8
    //   462: aload_1
    //   463: invokevirtual 299	com/google/android/gms/internal/zzk:getUrl	()Ljava/lang/String;
    //   466: astore 13
    //   468: aload 8
    //   470: aload 13
    //   472: invokevirtual 296	java/lang/StringBuilder:append	(Ljava/lang/String;)Ljava/lang/StringBuilder;
    //   475: invokevirtual 302	java/lang/StringBuilder:toString	()Ljava/lang/String;
    //   478: astore 8
    //   480: aload 5
    //   482: aload 8
    //   484: aload 7
    //   486: invokespecial 305	java/lang/RuntimeException:<init>	(Ljava/lang/String;Ljava/lang/Throwable;)V
    //   489: aload 5
    //   491: athrow
    //   492: astore 7
    //   494: aconst_null
    //   495: astore 13
    //   497: iconst_0
    //   498: istore 14
    //   500: aconst_null
    //   501: astore 17
    //   503: aload 5
    //   505: ifnull +157 -> 662
    //   508: aload 5
    //   510: invokeinterface 237 1 0
    //   515: invokeinterface 91 1 0
    //   520: istore 11
    //   522: ldc_w 307
    //   525: astore 7
    //   527: iconst_2
    //   528: istore 4
    //   530: iload 4
    //   532: anewarray 4	java/lang/Object
    //   535: astore 5
    //   537: iload 11
    //   539: invokestatic 84	java/lang/Integer:valueOf	(I)Ljava/lang/Integer;
    //   542: astore 19
    //   544: aload 5
    //   546: iconst_0
    //   547: aload 19
    //   549: aastore
    //   550: iconst_1
    //   551: istore 18
    //   553: aload_1
    //   554: invokevirtual 299	com/google/android/gms/internal/zzk:getUrl	()Ljava/lang/String;
    //   557: astore 19
    //   559: aload 5
    //   561: iload 18
    //   563: aload 19
    //   565: aastore
    //   566: aload 7
    //   568: aload 5
    //   570: invokestatic 309	com/google/android/gms/internal/zzs:zzc	(Ljava/lang/String;[Ljava/lang/Object;)V
    //   573: aload 13
    //   575: ifnull +117 -> 692
    //   578: new 247	com/google/android/gms/internal/zzi
    //   581: astore 5
    //   583: iconst_0
    //   584: istore 14
    //   586: aconst_null
    //   587: astore 17
    //   589: invokestatic 210	android/os/SystemClock:elapsedRealtime	()J
    //   592: lload_2
    //   593: lsub
    //   594: lstore 15
    //   596: aload 5
    //   598: iload 11
    //   600: aload 13
    //   602: aload 6
    //   604: iconst_0
    //   605: lload 15
    //   607: invokespecial 250	com/google/android/gms/internal/zzi:<init>	(I[BLjava/util/Map;ZJ)V
    //   610: sipush 401
    //   613: istore 12
    //   615: iload 11
    //   617: iload 12
    //   619: if_icmpeq +15 -> 634
    //   622: sipush 403
    //   625: istore 12
    //   627: iload 11
    //   629: iload 12
    //   631: if_icmpne +46 -> 677
    //   634: ldc_w 313
    //   637: astore 7
    //   639: new 315	com/google/android/gms/internal/zza
    //   642: astore 8
    //   644: aload 8
    //   646: aload 5
    //   648: invokespecial 318	com/google/android/gms/internal/zza:<init>	(Lcom/google/android/gms/internal/zzi;)V
    //   651: aload 7
    //   653: aload_1
    //   654: aload 8
    //   656: invokestatic 283	com/google/android/gms/internal/zzt:zza	(Ljava/lang/String;Lcom/google/android/gms/internal/zzk;Lcom/google/android/gms/internal/zzr;)V
    //   659: goto -655 -> 4
    //   662: new 320	com/google/android/gms/internal/zzj
    //   665: astore 5
    //   667: aload 5
    //   669: aload 7
    //   671: invokespecial 323	com/google/android/gms/internal/zzj:<init>	(Ljava/lang/Throwable;)V
    //   674: aload 5
    //   676: athrow
    //   677: new 171	com/google/android/gms/internal/zzp
    //   680: astore 7
    //   682: aload 7
    //   684: aload 5
    //   686: invokespecial 324	com/google/android/gms/internal/zzp:<init>	(Lcom/google/android/gms/internal/zzi;)V
    //   689: aload 7
    //   691: athrow
    //   692: new 326	com/google/android/gms/internal/zzh
    //   695: astore 7
    //   697: aload 7
    //   699: aconst_null
    //   700: invokespecial 327	com/google/android/gms/internal/zzh:<init>	(Lcom/google/android/gms/internal/zzi;)V
    //   703: aload 7
    //   705: athrow
    //   706: astore 7
    //   708: aconst_null
    //   709: astore 13
    //   711: aload 9
    //   713: astore 5
    //   715: goto -218 -> 497
    //   718: astore 7
    //   720: aload 26
    //   722: astore 13
    //   724: aload 9
    //   726: astore 5
    //   728: goto -231 -> 497
    // Local variable table:
    //   start	length	slot	name	signature
    //   0	731	0	this	zzt
    //   0	731	1	paramzzk	zzk
    //   3	590	2	l1	long
    //   5	526	4	i	int
    //   8	719	5	localObject1	Object
    //   13	590	6	localMap	Map
    //   18	306	7	localObject2	Object
    //   326	1	7	localSocketTimeoutException	java.net.SocketTimeoutException
    //   331	28	7	str1	String
    //   407	1	7	localConnectTimeoutException	org.apache.http.conn.ConnectTimeoutException
    //   412	13	7	str2	String
    //   435	50	7	localMalformedURLException	java.net.MalformedURLException
    //   492	1	7	localIOException1	IOException
    //   525	179	7	localObject3	Object
    //   706	1	7	localIOException2	IOException
    //   718	1	7	localIOException3	IOException
    //   29	626	8	localObject4	Object
    //   55	670	9	localHttpResponse	org.apache.http.HttpResponse
    //   64	221	10	localStatusLine	StatusLine
    //   73	559	11	j	int
    //   94	538	12	k	int
    //   125	598	13	localObject5	Object
    //   128	457	14	bool1	boolean
    //   135	471	15	l2	long
    //   173	415	17	localObject6	Object
    //   178	384	18	m	int
    //   185	379	19	localObject7	Object
    //   192	85	20	localObject8	Object
    //   195	22	21	bool2	boolean
    //   200	67	22	l3	long
    //   206	13	24	l4	long
    //   259	462	26	arrayOfByte	byte[]
    // Exception table:
    //   from	to	target	type
    //   15	18	326	java/net/SocketTimeoutException
    //   20	25	326	java/net/SocketTimeoutException
    //   25	29	326	java/net/SocketTimeoutException
    //   34	39	326	java/net/SocketTimeoutException
    //   39	43	326	java/net/SocketTimeoutException
    //   48	55	326	java/net/SocketTimeoutException
    //   57	64	326	java/net/SocketTimeoutException
    //   66	73	326	java/net/SocketTimeoutException
    //   75	82	326	java/net/SocketTimeoutException
    //   84	89	326	java/net/SocketTimeoutException
    //   103	107	326	java/net/SocketTimeoutException
    //   114	117	326	java/net/SocketTimeoutException
    //   130	133	326	java/net/SocketTimeoutException
    //   146	151	326	java/net/SocketTimeoutException
    //   154	159	326	java/net/SocketTimeoutException
    //   163	170	326	java/net/SocketTimeoutException
    //   170	173	326	java/net/SocketTimeoutException
    //   180	185	326	java/net/SocketTimeoutException
    //   187	192	326	java/net/SocketTimeoutException
    //   197	200	326	java/net/SocketTimeoutException
    //   218	223	326	java/net/SocketTimeoutException
    //   230	237	326	java/net/SocketTimeoutException
    //   244	251	326	java/net/SocketTimeoutException
    //   254	259	326	java/net/SocketTimeoutException
    //   261	264	326	java/net/SocketTimeoutException
    //   284	289	326	java/net/SocketTimeoutException
    //   313	316	326	java/net/SocketTimeoutException
    //   318	323	326	java/net/SocketTimeoutException
    //   323	326	326	java/net/SocketTimeoutException
    //   360	363	326	java/net/SocketTimeoutException
    //   368	371	326	java/net/SocketTimeoutException
    //   379	382	326	java/net/SocketTimeoutException
    //   399	404	326	java/net/SocketTimeoutException
    //   15	18	407	org/apache/http/conn/ConnectTimeoutException
    //   20	25	407	org/apache/http/conn/ConnectTimeoutException
    //   25	29	407	org/apache/http/conn/ConnectTimeoutException
    //   34	39	407	org/apache/http/conn/ConnectTimeoutException
    //   39	43	407	org/apache/http/conn/ConnectTimeoutException
    //   48	55	407	org/apache/http/conn/ConnectTimeoutException
    //   57	64	407	org/apache/http/conn/ConnectTimeoutException
    //   66	73	407	org/apache/http/conn/ConnectTimeoutException
    //   75	82	407	org/apache/http/conn/ConnectTimeoutException
    //   84	89	407	org/apache/http/conn/ConnectTimeoutException
    //   103	107	407	org/apache/http/conn/ConnectTimeoutException
    //   114	117	407	org/apache/http/conn/ConnectTimeoutException
    //   130	133	407	org/apache/http/conn/ConnectTimeoutException
    //   146	151	407	org/apache/http/conn/ConnectTimeoutException
    //   154	159	407	org/apache/http/conn/ConnectTimeoutException
    //   163	170	407	org/apache/http/conn/ConnectTimeoutException
    //   170	173	407	org/apache/http/conn/ConnectTimeoutException
    //   180	185	407	org/apache/http/conn/ConnectTimeoutException
    //   187	192	407	org/apache/http/conn/ConnectTimeoutException
    //   197	200	407	org/apache/http/conn/ConnectTimeoutException
    //   218	223	407	org/apache/http/conn/ConnectTimeoutException
    //   230	237	407	org/apache/http/conn/ConnectTimeoutException
    //   244	251	407	org/apache/http/conn/ConnectTimeoutException
    //   254	259	407	org/apache/http/conn/ConnectTimeoutException
    //   261	264	407	org/apache/http/conn/ConnectTimeoutException
    //   284	289	407	org/apache/http/conn/ConnectTimeoutException
    //   313	316	407	org/apache/http/conn/ConnectTimeoutException
    //   318	323	407	org/apache/http/conn/ConnectTimeoutException
    //   323	326	407	org/apache/http/conn/ConnectTimeoutException
    //   360	363	407	org/apache/http/conn/ConnectTimeoutException
    //   368	371	407	org/apache/http/conn/ConnectTimeoutException
    //   379	382	407	org/apache/http/conn/ConnectTimeoutException
    //   399	404	407	org/apache/http/conn/ConnectTimeoutException
    //   15	18	435	java/net/MalformedURLException
    //   20	25	435	java/net/MalformedURLException
    //   25	29	435	java/net/MalformedURLException
    //   34	39	435	java/net/MalformedURLException
    //   39	43	435	java/net/MalformedURLException
    //   48	55	435	java/net/MalformedURLException
    //   57	64	435	java/net/MalformedURLException
    //   66	73	435	java/net/MalformedURLException
    //   75	82	435	java/net/MalformedURLException
    //   84	89	435	java/net/MalformedURLException
    //   103	107	435	java/net/MalformedURLException
    //   114	117	435	java/net/MalformedURLException
    //   130	133	435	java/net/MalformedURLException
    //   146	151	435	java/net/MalformedURLException
    //   154	159	435	java/net/MalformedURLException
    //   163	170	435	java/net/MalformedURLException
    //   170	173	435	java/net/MalformedURLException
    //   180	185	435	java/net/MalformedURLException
    //   187	192	435	java/net/MalformedURLException
    //   197	200	435	java/net/MalformedURLException
    //   218	223	435	java/net/MalformedURLException
    //   230	237	435	java/net/MalformedURLException
    //   244	251	435	java/net/MalformedURLException
    //   254	259	435	java/net/MalformedURLException
    //   261	264	435	java/net/MalformedURLException
    //   284	289	435	java/net/MalformedURLException
    //   313	316	435	java/net/MalformedURLException
    //   318	323	435	java/net/MalformedURLException
    //   323	326	435	java/net/MalformedURLException
    //   360	363	435	java/net/MalformedURLException
    //   368	371	435	java/net/MalformedURLException
    //   379	382	435	java/net/MalformedURLException
    //   399	404	435	java/net/MalformedURLException
    //   15	18	492	java/io/IOException
    //   20	25	492	java/io/IOException
    //   25	29	492	java/io/IOException
    //   34	39	492	java/io/IOException
    //   39	43	492	java/io/IOException
    //   48	55	492	java/io/IOException
    //   57	64	706	java/io/IOException
    //   66	73	706	java/io/IOException
    //   75	82	706	java/io/IOException
    //   84	89	706	java/io/IOException
    //   103	107	706	java/io/IOException
    //   114	117	706	java/io/IOException
    //   130	133	706	java/io/IOException
    //   146	151	706	java/io/IOException
    //   154	159	706	java/io/IOException
    //   163	170	706	java/io/IOException
    //   170	173	706	java/io/IOException
    //   180	185	706	java/io/IOException
    //   187	192	706	java/io/IOException
    //   197	200	706	java/io/IOException
    //   218	223	706	java/io/IOException
    //   230	237	706	java/io/IOException
    //   244	251	706	java/io/IOException
    //   254	259	706	java/io/IOException
    //   360	363	706	java/io/IOException
    //   261	264	718	java/io/IOException
    //   284	289	718	java/io/IOException
    //   313	316	718	java/io/IOException
    //   318	323	718	java/io/IOException
    //   323	326	718	java/io/IOException
    //   368	371	718	java/io/IOException
    //   379	382	718	java/io/IOException
    //   399	404	718	java/io/IOException
  }
}


/* Location:              C:\Users\haryo\Desktop\enjarify-master\presensi-enjarify.jar!\com\google\android\gms\internal\zzt.class
 * Java compiler version: 5 (49.0)
 * JD-Core Version:       0.7.1
 */