package com.google.android.gms.tagmanager;

import android.content.ContentValues;
import android.content.Context;
import android.database.Cursor;
import android.database.sqlite.SQLiteDatabase;
import android.database.sqlite.SQLiteException;
import android.text.TextUtils;
import com.google.android.gms.internal.zzmq;
import java.util.ArrayList;
import java.util.Arrays;
import java.util.Collections;
import java.util.Iterator;
import java.util.List;
import java.util.concurrent.Executor;
import java.util.concurrent.ExecutorService;

class zzw
  implements DataLayer.zzc
{
  private static final String zzbiB;
  private final Context mContext;
  private final Executor zzbiC;
  private zzw.zza zzbiD;
  private int zzbiE;
  private zzmq zzqW;
  
  static
  {
    Object[] arrayOfObject = new Object[5];
    arrayOfObject[0] = "datalayer";
    arrayOfObject[1] = "ID";
    arrayOfObject[2] = "key";
    arrayOfObject[3] = "value";
    arrayOfObject[4] = "expires";
    zzbiB = String.format("CREATE TABLE IF NOT EXISTS %s ( '%s' INTEGER PRIMARY KEY AUTOINCREMENT NOT NULL, '%s' STRING NOT NULL, '%s' BLOB NOT NULL, '%s' INTEGER NOT NULL);", arrayOfObject);
  }
  
  public zzw(Context paramContext)
  {
    this(paramContext, localzzmq, "google_tagmanager.db", 2000, localExecutorService);
  }
  
  zzw(Context paramContext, zzmq paramzzmq, String paramString, int paramInt, Executor paramExecutor)
  {
    this.mContext = paramContext;
    this.zzqW = paramzzmq;
    this.zzbiE = paramInt;
    this.zzbiC = paramExecutor;
    zzw.zza localzza = new com/google/android/gms/tagmanager/zzw$zza;
    Context localContext = this.mContext;
    localzza.<init>(this, localContext, paramString);
    this.zzbiD = localzza;
  }
  
  private List zzC(List paramList)
  {
    ArrayList localArrayList = new java/util/ArrayList;
    localArrayList.<init>();
    Iterator localIterator = paramList.iterator();
    for (;;)
    {
      boolean bool = localIterator.hasNext();
      if (!bool) {
        break;
      }
      Object localObject = (zzw.zzb)localIterator.next();
      DataLayer.zza localzza = new com/google/android/gms/tagmanager/DataLayer$zza;
      String str = ((zzw.zzb)localObject).zzvs;
      localObject = ((zzw.zzb)localObject).zzbiK;
      localObject = zzw((byte[])localObject);
      localzza.<init>(str, localObject);
      localArrayList.add(localzza);
    }
    return localArrayList;
  }
  
  private List zzD(List paramList)
  {
    ArrayList localArrayList = new java/util/ArrayList;
    localArrayList.<init>();
    Iterator localIterator = paramList.iterator();
    for (;;)
    {
      boolean bool = localIterator.hasNext();
      if (!bool) {
        break;
      }
      Object localObject = (DataLayer.zza)localIterator.next();
      zzw.zzb localzzb = new com/google/android/gms/tagmanager/zzw$zzb;
      String str = ((DataLayer.zza)localObject).zzvs;
      localObject = ((DataLayer.zza)localObject).zzNc;
      localObject = zzJ(localObject);
      localzzb.<init>(str, (byte[])localObject);
      localArrayList.add(localzzb);
    }
    return localArrayList;
  }
  
  private List zzGr()
  {
    try
    {
      Object localObject1 = this.zzqW;
      long l = ((zzmq)localObject1).currentTimeMillis();
      zzal(l);
      localObject1 = zzGs();
      localObject1 = zzC((List)localObject1);
      return (List)localObject1;
    }
    finally
    {
      zzGu();
    }
  }
  
  private List zzGs()
  {
    int i = 1;
    int j = 0;
    byte[] arrayOfByte = null;
    Object localObject1 = zzgb("Error opening database for loadSerialized.");
    ArrayList localArrayList = new java/util/ArrayList;
    localArrayList.<init>();
    if (localObject1 == null) {}
    Cursor localCursor;
    Object localObject3;
    for (localObject1 = localArrayList;; localObject3 = localArrayList)
    {
      return (List)localObject1;
      int k = 2;
      Object localObject4 = new String[k];
      localObject4[0] = "key";
      localObject4[i] = "value";
      String str = "ID";
      i = 0;
      localCursor = ((SQLiteDatabase)localObject1).query("datalayer", (String[])localObject4, null, null, null, null, str, null);
      try
      {
        for (;;)
        {
          boolean bool = localCursor.moveToNext();
          if (!bool) {
            break;
          }
          localObject1 = new com/google/android/gms/tagmanager/zzw$zzb;
          localObject4 = null;
          localObject4 = localCursor.getString(0);
          j = 1;
          arrayOfByte = localCursor.getBlob(j);
          ((zzw.zzb)localObject1).<init>((String)localObject4, arrayOfByte);
          localArrayList.add(localObject1);
        }
      }
      finally
      {
        localCursor.close();
      }
    }
  }
  
  private int zzGt()
  {
    Cursor localCursor = null;
    int i = 0;
    Object localObject1 = null;
    SQLiteDatabase localSQLiteDatabase = zzgb("Error opening database for getNumStoredEntries.");
    if (localSQLiteDatabase == null) {}
    for (;;)
    {
      return i;
      String str2 = "SELECT COUNT(*) from datalayer";
      try
      {
        localCursor = localSQLiteDatabase.rawQuery(str2, null);
        boolean bool = localCursor.moveToFirst();
        if (bool)
        {
          bool = false;
          localSQLiteDatabase = null;
          long l = localCursor.getLong(0);
          i = (int)l;
        }
        if (localCursor == null) {
          continue;
        }
        localCursor.close();
      }
      catch (SQLiteException localSQLiteException)
      {
        String str1 = "Error getting numStoredEntries";
        zzbg.zzaK(str1);
        if (localCursor == null) {
          continue;
        }
        localCursor.close();
      }
      finally
      {
        if (localCursor != null) {
          localCursor.close();
        }
      }
    }
  }
  
  private void zzGu()
  {
    try
    {
      zzw.zza localzza = this.zzbiD;
      localzza.close();
      return;
    }
    catch (SQLiteException localSQLiteException)
    {
      for (;;) {}
    }
  }
  
  /* Error */
  private byte[] zzJ(Object paramObject)
  {
    // Byte code:
    //   0: aconst_null
    //   1: astore_2
    //   2: new 210	java/io/ByteArrayOutputStream
    //   5: astore_3
    //   6: aload_3
    //   7: invokespecial 211	java/io/ByteArrayOutputStream:<init>	()V
    //   10: new 213	java/io/ObjectOutputStream
    //   13: astore 4
    //   15: aload 4
    //   17: aload_3
    //   18: invokespecial 216	java/io/ObjectOutputStream:<init>	(Ljava/io/OutputStream;)V
    //   21: aload 4
    //   23: aload_1
    //   24: invokevirtual 220	java/io/ObjectOutputStream:writeObject	(Ljava/lang/Object;)V
    //   27: aload_3
    //   28: invokevirtual 224	java/io/ByteArrayOutputStream:toByteArray	()[B
    //   31: astore_2
    //   32: aload 4
    //   34: ifnull +8 -> 42
    //   37: aload 4
    //   39: invokevirtual 225	java/io/ObjectOutputStream:close	()V
    //   42: aload_3
    //   43: invokevirtual 226	java/io/ByteArrayOutputStream:close	()V
    //   46: aload_2
    //   47: areturn
    //   48: astore 4
    //   50: aconst_null
    //   51: astore 4
    //   53: aload 4
    //   55: ifnull +8 -> 63
    //   58: aload 4
    //   60: invokevirtual 225	java/io/ObjectOutputStream:close	()V
    //   63: aload_3
    //   64: invokevirtual 226	java/io/ByteArrayOutputStream:close	()V
    //   67: goto -21 -> 46
    //   70: astore 4
    //   72: goto -26 -> 46
    //   75: astore 5
    //   77: aconst_null
    //   78: astore 4
    //   80: aload 5
    //   82: astore_2
    //   83: aload 4
    //   85: ifnull +8 -> 93
    //   88: aload 4
    //   90: invokevirtual 225	java/io/ObjectOutputStream:close	()V
    //   93: aload_3
    //   94: invokevirtual 226	java/io/ByteArrayOutputStream:close	()V
    //   97: aload_2
    //   98: athrow
    //   99: astore 4
    //   101: goto -4 -> 97
    //   104: astore_2
    //   105: goto -22 -> 83
    //   108: pop
    //   109: goto -56 -> 53
    //   112: astore 4
    //   114: goto -68 -> 46
    // Local variable table:
    //   start	length	slot	name	signature
    //   0	117	0	this	zzw
    //   0	117	1	paramObject	Object
    //   1	97	2	localObject1	Object
    //   104	1	2	localObject2	Object
    //   5	89	3	localByteArrayOutputStream	java.io.ByteArrayOutputStream
    //   13	25	4	localObjectOutputStream	java.io.ObjectOutputStream
    //   48	1	4	localIOException1	java.io.IOException
    //   51	8	4	localObject3	Object
    //   70	1	4	localIOException2	java.io.IOException
    //   78	11	4	localObject4	Object
    //   99	1	4	localIOException3	java.io.IOException
    //   112	1	4	localIOException4	java.io.IOException
    //   75	6	5	localObject5	Object
    //   108	1	13	localIOException5	java.io.IOException
    // Exception table:
    //   from	to	target	type
    //   10	13	48	java/io/IOException
    //   17	21	48	java/io/IOException
    //   58	63	70	java/io/IOException
    //   63	67	70	java/io/IOException
    //   10	13	75	finally
    //   17	21	75	finally
    //   88	93	99	java/io/IOException
    //   93	97	99	java/io/IOException
    //   23	27	104	finally
    //   27	31	104	finally
    //   23	27	108	java/io/IOException
    //   27	31	108	java/io/IOException
    //   37	42	112	java/io/IOException
    //   42	46	112	java/io/IOException
  }
  
  private void zzal(long paramLong)
  {
    Object localObject1 = zzgb("Error opening database for deleteOlderThan.");
    if (localObject1 == null) {}
    for (;;)
    {
      return;
      Object localObject2 = "datalayer";
      String str2 = "expires <= ?";
      int i = 1;
      try
      {
        String[] arrayOfString = new String[i];
        String str3 = Long.toString(paramLong);
        arrayOfString[0] = str3;
        int j = ((SQLiteDatabase)localObject1).delete((String)localObject2, str2, arrayOfString);
        localObject2 = new java/lang/StringBuilder;
        ((StringBuilder)localObject2).<init>();
        str2 = "Deleted ";
        localObject2 = ((StringBuilder)localObject2).append(str2);
        localObject1 = ((StringBuilder)localObject2).append(j);
        localObject2 = " expired items";
        localObject1 = ((StringBuilder)localObject1).append((String)localObject2);
        localObject1 = ((StringBuilder)localObject1).toString();
        zzbg.v((String)localObject1);
      }
      catch (SQLiteException localSQLiteException)
      {
        String str1 = "Error deleting old entries.";
        zzbg.zzaK(str1);
      }
    }
  }
  
  /* Error */
  private void zzb(List paramList, long paramLong)
  {
    // Byte code:
    //   0: aload_0
    //   1: monitorenter
    //   2: aload_0
    //   3: getfield 69	com/google/android/gms/tagmanager/zzw:zzqW	Lcom/google/android/gms/internal/zzmq;
    //   6: astore 4
    //   8: aload 4
    //   10: invokeinterface 139 1 0
    //   15: lstore 5
    //   17: aload_0
    //   18: lload 5
    //   20: invokespecial 143	com/google/android/gms/tagmanager/zzw:zzal	(J)V
    //   23: aload_1
    //   24: invokeinterface 278 1 0
    //   29: istore 7
    //   31: aload_0
    //   32: iload 7
    //   34: invokespecial 282	com/google/android/gms/tagmanager/zzw:zzkf	(I)V
    //   37: lload 5
    //   39: lload_2
    //   40: ladd
    //   41: lstore 5
    //   43: aload_0
    //   44: aload_1
    //   45: lload 5
    //   47: invokespecial 285	com/google/android/gms/tagmanager/zzw:zzc	(Ljava/util/List;J)V
    //   50: aload_0
    //   51: invokespecial 154	com/google/android/gms/tagmanager/zzw:zzGu	()V
    //   54: aload_0
    //   55: monitorexit
    //   56: return
    //   57: astore 4
    //   59: aload_0
    //   60: invokespecial 154	com/google/android/gms/tagmanager/zzw:zzGu	()V
    //   63: aload 4
    //   65: athrow
    //   66: astore 4
    //   68: aload_0
    //   69: monitorexit
    //   70: aload 4
    //   72: athrow
    // Local variable table:
    //   start	length	slot	name	signature
    //   0	73	0	this	zzw
    //   0	73	1	paramList	List
    //   0	73	2	paramLong	long
    //   6	3	4	localzzmq	zzmq
    //   57	7	4	localObject1	Object
    //   66	5	4	localObject2	Object
    //   15	31	5	l	long
    //   29	4	7	i	int
    // Exception table:
    //   from	to	target	type
    //   2	6	57	finally
    //   8	15	57	finally
    //   18	23	57	finally
    //   23	29	57	finally
    //   32	37	57	finally
    //   45	50	57	finally
    //   50	54	66	finally
    //   59	63	66	finally
    //   63	66	66	finally
  }
  
  private void zzc(List paramList, long paramLong)
  {
    Object localObject1 = "Error opening database for writeEntryToDatabase.";
    SQLiteDatabase localSQLiteDatabase = zzgb((String)localObject1);
    if (localSQLiteDatabase == null) {
      return;
    }
    Iterator localIterator = paramList.iterator();
    for (;;)
    {
      boolean bool = localIterator.hasNext();
      if (!bool) {
        break;
      }
      localObject1 = (zzw.zzb)localIterator.next();
      ContentValues localContentValues = new android/content/ContentValues;
      localContentValues.<init>();
      Object localObject2 = Long.valueOf(paramLong);
      localContentValues.put("expires", (Long)localObject2);
      localObject2 = ((zzw.zzb)localObject1).zzvs;
      localContentValues.put("key", (String)localObject2);
      localObject1 = ((zzw.zzb)localObject1).zzbiK;
      localContentValues.put("value", (byte[])localObject1);
      localObject1 = "datalayer";
      localSQLiteDatabase.insert((String)localObject1, null, localContentValues);
    }
  }
  
  private void zze(String[] paramArrayOfString)
  {
    if (paramArrayOfString != null)
    {
      int i = paramArrayOfString.length;
      if (i != 0) {
        break label12;
      }
    }
    for (;;)
    {
      return;
      label12:
      SQLiteDatabase localSQLiteDatabase = zzgb("Error opening database for deleteEntries.");
      if (localSQLiteDatabase != null)
      {
        int j = 2;
        Object localObject2 = new Object[j];
        localObject2[0] = "ID";
        int k = 1;
        int m = paramArrayOfString.length;
        String str1 = "?";
        List localList = Collections.nCopies(m, str1);
        String str2 = TextUtils.join(",", localList);
        localObject2[k] = str2;
        String str3 = String.format("%s in (%s)", (Object[])localObject2);
        localObject2 = "datalayer";
        try
        {
          localSQLiteDatabase.delete((String)localObject2, str3, paramArrayOfString);
        }
        catch (SQLiteException localSQLiteException)
        {
          Object localObject1 = new java/lang/StringBuilder;
          ((StringBuilder)localObject1).<init>();
          localObject1 = ((StringBuilder)localObject1).append("Error deleting entries ");
          str3 = Arrays.toString(paramArrayOfString);
          localObject1 = str3;
          zzbg.zzaK((String)localObject1);
        }
      }
    }
  }
  
  private void zzga(String paramString)
  {
    Object localObject1 = zzgb("Error opening database for clearKeysWithPrefix.");
    if (localObject1 == null) {}
    for (;;)
    {
      return;
      Object localObject4 = "datalayer";
      String str1 = "key = ? OR key LIKE ?";
      int i = 2;
      try
      {
        String[] arrayOfString = new String[i];
        int j = 0;
        arrayOfString[0] = paramString;
        j = 1;
        Object localObject5 = new java/lang/StringBuilder;
        ((StringBuilder)localObject5).<init>();
        localObject5 = ((StringBuilder)localObject5).append(paramString);
        String str2 = ".%";
        localObject5 = ((StringBuilder)localObject5).append(str2);
        localObject5 = ((StringBuilder)localObject5).toString();
        arrayOfString[j] = localObject5;
        int k = ((SQLiteDatabase)localObject1).delete((String)localObject4, str1, arrayOfString);
        localObject4 = new java/lang/StringBuilder;
        ((StringBuilder)localObject4).<init>();
        str1 = "Cleared ";
        localObject4 = ((StringBuilder)localObject4).append(str1);
        localObject1 = ((StringBuilder)localObject4).append(k);
        localObject4 = " items";
        localObject1 = ((StringBuilder)localObject1).append((String)localObject4);
        localObject1 = ((StringBuilder)localObject1).toString();
        zzbg.v((String)localObject1);
        zzGu();
      }
      catch (SQLiteException localSQLiteException)
      {
        localObject4 = new java/lang/StringBuilder;
        ((StringBuilder)localObject4).<init>();
        str1 = "Error deleting entries with key prefix: ";
        localObject4 = ((StringBuilder)localObject4).append(str1);
        localObject4 = ((StringBuilder)localObject4).append(paramString);
        str1 = " (";
        localObject4 = ((StringBuilder)localObject4).append(str1);
        Object localObject2 = ((StringBuilder)localObject4).append(localSQLiteException);
        localObject4 = ").";
        localObject2 = ((StringBuilder)localObject2).append((String)localObject4);
        localObject2 = ((StringBuilder)localObject2).toString();
        zzbg.zzaK((String)localObject2);
        zzGu();
      }
      finally
      {
        zzGu();
      }
    }
  }
  
  private SQLiteDatabase zzgb(String paramString)
  {
    try
    {
      localObject1 = this.zzbiD;
      localObject1 = ((zzw.zza)localObject1).getWritableDatabase();
    }
    catch (SQLiteException localSQLiteException)
    {
      for (;;)
      {
        Object localObject1;
        zzbg.zzaK(paramString);
        Object localObject2 = null;
      }
    }
    return (SQLiteDatabase)localObject1;
  }
  
  private void zzkf(int paramInt)
  {
    int i = zzGt();
    int j = this.zzbiE;
    i = i - j + paramInt;
    if (i > 0)
    {
      Object localObject1 = zzkg(i);
      Object localObject2 = new java/lang/StringBuilder;
      ((StringBuilder)localObject2).<init>();
      localObject2 = ((StringBuilder)localObject2).append("DataLayer store full, deleting ");
      int k = ((List)localObject1).size();
      localObject2 = ((StringBuilder)localObject2).append(k);
      String str = " entries to make room.";
      zzbg.zzaJ(str);
      j = 0;
      localObject2 = new String[0];
      localObject1 = (String[])((List)localObject1).toArray((Object[])localObject2);
      zze((String[])localObject1);
    }
  }
  
  /* Error */
  private List zzkg(int paramInt)
  {
    // Byte code:
    //   0: new 82	java/util/ArrayList
    //   3: astore_2
    //   4: aload_2
    //   5: invokespecial 83	java/util/ArrayList:<init>	()V
    //   8: iload_1
    //   9: ifgt +13 -> 22
    //   12: ldc_w 383
    //   15: invokestatic 205	com/google/android/gms/tagmanager/zzbg:zzaK	(Ljava/lang/String;)V
    //   18: aload_2
    //   19: astore_3
    //   20: aload_3
    //   21: areturn
    //   22: aload_0
    //   23: ldc_w 385
    //   26: invokespecial 160	com/google/android/gms/tagmanager/zzw:zzgb	(Ljava/lang/String;)Landroid/database/sqlite/SQLiteDatabase;
    //   29: astore_3
    //   30: aload_3
    //   31: ifnonnull +8 -> 39
    //   34: aload_2
    //   35: astore_3
    //   36: goto -16 -> 20
    //   39: ldc 23
    //   41: astore 4
    //   43: iconst_1
    //   44: istore 5
    //   46: iload 5
    //   48: anewarray 37	java/lang/String
    //   51: astore 6
    //   53: aconst_null
    //   54: astore 7
    //   56: ldc 26
    //   58: astore 8
    //   60: aload 6
    //   62: iconst_0
    //   63: aload 8
    //   65: aastore
    //   66: aconst_null
    //   67: astore 7
    //   69: aconst_null
    //   70: astore 8
    //   72: ldc_w 387
    //   75: astore 9
    //   77: iconst_1
    //   78: istore 10
    //   80: iload 10
    //   82: anewarray 4	java/lang/Object
    //   85: astore 11
    //   87: ldc 26
    //   89: astore 12
    //   91: aload 11
    //   93: iconst_0
    //   94: aload 12
    //   96: aastore
    //   97: aload 9
    //   99: aload 11
    //   101: invokestatic 41	java/lang/String:format	(Ljava/lang/String;[Ljava/lang/Object;)Ljava/lang/String;
    //   104: astore 9
    //   106: iload_1
    //   107: invokestatic 391	java/lang/Integer:toString	(I)Ljava/lang/String;
    //   110: astore 11
    //   112: aload_3
    //   113: aload 4
    //   115: aload 6
    //   117: aconst_null
    //   118: aconst_null
    //   119: aconst_null
    //   120: aconst_null
    //   121: aload 9
    //   123: aload 11
    //   125: invokevirtual 166	android/database/sqlite/SQLiteDatabase:query	(Ljava/lang/String;[Ljava/lang/String;Ljava/lang/String;[Ljava/lang/String;Ljava/lang/String;Ljava/lang/String;Ljava/lang/String;Ljava/lang/String;)Landroid/database/Cursor;
    //   128: astore 4
    //   130: aload 4
    //   132: invokeinterface 193 1 0
    //   137: istore 13
    //   139: iload 13
    //   141: ifeq +46 -> 187
    //   144: iconst_0
    //   145: istore 13
    //   147: aconst_null
    //   148: astore_3
    //   149: aload 4
    //   151: iconst_0
    //   152: invokeinterface 197 2 0
    //   157: lstore 14
    //   159: lload 14
    //   161: invokestatic 393	java/lang/String:valueOf	(J)Ljava/lang/String;
    //   164: astore_3
    //   165: aload_2
    //   166: aload_3
    //   167: invokeinterface 121 2 0
    //   172: pop
    //   173: aload 4
    //   175: invokeinterface 171 1 0
    //   180: istore 13
    //   182: iload 13
    //   184: ifne -40 -> 144
    //   187: aload 4
    //   189: ifnull +10 -> 199
    //   192: aload 4
    //   194: invokeinterface 182 1 0
    //   199: aload_2
    //   200: astore_3
    //   201: goto -181 -> 20
    //   204: astore_3
    //   205: aconst_null
    //   206: astore 4
    //   208: new 254	java/lang/StringBuilder
    //   211: astore 6
    //   213: aload 6
    //   215: invokespecial 255	java/lang/StringBuilder:<init>	()V
    //   218: ldc_w 395
    //   221: astore 7
    //   223: aload 6
    //   225: aload 7
    //   227: invokevirtual 261	java/lang/StringBuilder:append	(Ljava/lang/String;)Ljava/lang/StringBuilder;
    //   230: astore 6
    //   232: aload_3
    //   233: invokevirtual 398	android/database/sqlite/SQLiteException:getMessage	()Ljava/lang/String;
    //   236: astore_3
    //   237: aload 6
    //   239: aload_3
    //   240: invokevirtual 261	java/lang/StringBuilder:append	(Ljava/lang/String;)Ljava/lang/StringBuilder;
    //   243: astore_3
    //   244: aload_3
    //   245: invokevirtual 269	java/lang/StringBuilder:toString	()Ljava/lang/String;
    //   248: astore_3
    //   249: aload_3
    //   250: invokestatic 205	com/google/android/gms/tagmanager/zzbg:zzaK	(Ljava/lang/String;)V
    //   253: aload 4
    //   255: ifnull -56 -> 199
    //   258: aload 4
    //   260: invokeinterface 182 1 0
    //   265: goto -66 -> 199
    //   268: astore_3
    //   269: aconst_null
    //   270: astore 4
    //   272: aload 4
    //   274: ifnull +10 -> 284
    //   277: aload 4
    //   279: invokeinterface 182 1 0
    //   284: aload_3
    //   285: athrow
    //   286: astore_3
    //   287: goto -15 -> 272
    //   290: astore_3
    //   291: goto -83 -> 208
    // Local variable table:
    //   start	length	slot	name	signature
    //   0	294	0	this	zzw
    //   0	294	1	paramInt	int
    //   3	197	2	localArrayList	ArrayList
    //   19	182	3	localObject1	Object
    //   204	29	3	localSQLiteException1	SQLiteException
    //   236	14	3	localObject2	Object
    //   268	17	3	localObject3	Object
    //   286	1	3	localObject4	Object
    //   290	1	3	localSQLiteException2	SQLiteException
    //   41	237	4	localObject5	Object
    //   44	3	5	i	int
    //   51	187	6	localObject6	Object
    //   54	172	7	str1	String
    //   58	13	8	str2	String
    //   75	47	9	str3	String
    //   78	3	10	j	int
    //   85	39	11	localObject7	Object
    //   89	6	12	str4	String
    //   137	46	13	bool	boolean
    //   157	3	14	l	long
    // Exception table:
    //   from	to	target	type
    //   46	51	204	android/database/sqlite/SQLiteException
    //   63	66	204	android/database/sqlite/SQLiteException
    //   80	85	204	android/database/sqlite/SQLiteException
    //   94	97	204	android/database/sqlite/SQLiteException
    //   99	104	204	android/database/sqlite/SQLiteException
    //   106	110	204	android/database/sqlite/SQLiteException
    //   123	128	204	android/database/sqlite/SQLiteException
    //   46	51	268	finally
    //   63	66	268	finally
    //   80	85	268	finally
    //   94	97	268	finally
    //   99	104	268	finally
    //   106	110	268	finally
    //   123	128	268	finally
    //   130	137	286	finally
    //   151	157	286	finally
    //   159	164	286	finally
    //   166	173	286	finally
    //   173	180	286	finally
    //   208	211	286	finally
    //   213	218	286	finally
    //   225	230	286	finally
    //   232	236	286	finally
    //   239	243	286	finally
    //   244	248	286	finally
    //   249	253	286	finally
    //   130	137	290	android/database/sqlite/SQLiteException
    //   151	157	290	android/database/sqlite/SQLiteException
    //   159	164	290	android/database/sqlite/SQLiteException
    //   166	173	290	android/database/sqlite/SQLiteException
    //   173	180	290	android/database/sqlite/SQLiteException
  }
  
  /* Error */
  private Object zzw(byte[] paramArrayOfByte)
  {
    // Byte code:
    //   0: aconst_null
    //   1: astore_2
    //   2: new 400	java/io/ByteArrayInputStream
    //   5: astore_3
    //   6: aload_3
    //   7: aload_1
    //   8: invokespecial 403	java/io/ByteArrayInputStream:<init>	([B)V
    //   11: new 405	java/io/ObjectInputStream
    //   14: astore 4
    //   16: aload 4
    //   18: aload_3
    //   19: invokespecial 408	java/io/ObjectInputStream:<init>	(Ljava/io/InputStream;)V
    //   22: aload 4
    //   24: invokevirtual 411	java/io/ObjectInputStream:readObject	()Ljava/lang/Object;
    //   27: astore_2
    //   28: aload 4
    //   30: ifnull +8 -> 38
    //   33: aload 4
    //   35: invokevirtual 412	java/io/ObjectInputStream:close	()V
    //   38: aload_3
    //   39: invokevirtual 413	java/io/ByteArrayInputStream:close	()V
    //   42: aload_2
    //   43: areturn
    //   44: astore 4
    //   46: aconst_null
    //   47: astore 4
    //   49: aload 4
    //   51: ifnull +8 -> 59
    //   54: aload 4
    //   56: invokevirtual 412	java/io/ObjectInputStream:close	()V
    //   59: aload_3
    //   60: invokevirtual 413	java/io/ByteArrayInputStream:close	()V
    //   63: goto -21 -> 42
    //   66: astore 4
    //   68: goto -26 -> 42
    //   71: astore 4
    //   73: aconst_null
    //   74: astore 4
    //   76: aload 4
    //   78: ifnull +8 -> 86
    //   81: aload 4
    //   83: invokevirtual 412	java/io/ObjectInputStream:close	()V
    //   86: aload_3
    //   87: invokevirtual 413	java/io/ByteArrayInputStream:close	()V
    //   90: goto -48 -> 42
    //   93: astore 4
    //   95: goto -53 -> 42
    //   98: astore 5
    //   100: aconst_null
    //   101: astore 4
    //   103: aload 5
    //   105: astore_2
    //   106: aload 4
    //   108: ifnull +8 -> 116
    //   111: aload 4
    //   113: invokevirtual 412	java/io/ObjectInputStream:close	()V
    //   116: aload_3
    //   117: invokevirtual 413	java/io/ByteArrayInputStream:close	()V
    //   120: aload_2
    //   121: athrow
    //   122: astore 4
    //   124: goto -4 -> 120
    //   127: astore_2
    //   128: goto -22 -> 106
    //   131: pop
    //   132: goto -56 -> 76
    //   135: pop
    //   136: goto -87 -> 49
    //   139: astore 4
    //   141: goto -99 -> 42
    // Local variable table:
    //   start	length	slot	name	signature
    //   0	144	0	this	zzw
    //   0	144	1	paramArrayOfByte	byte[]
    //   1	120	2	localObject1	Object
    //   127	1	2	localObject2	Object
    //   5	112	3	localByteArrayInputStream	java.io.ByteArrayInputStream
    //   14	20	4	localObjectInputStream	java.io.ObjectInputStream
    //   44	1	4	localIOException1	java.io.IOException
    //   47	8	4	localObject3	Object
    //   66	1	4	localIOException2	java.io.IOException
    //   71	1	4	localClassNotFoundException1	ClassNotFoundException
    //   74	8	4	localObject4	Object
    //   93	1	4	localIOException3	java.io.IOException
    //   101	11	4	localObject5	Object
    //   122	1	4	localIOException4	java.io.IOException
    //   139	1	4	localIOException5	java.io.IOException
    //   98	6	5	localObject6	Object
    //   131	1	16	localClassNotFoundException2	ClassNotFoundException
    //   135	1	17	localIOException6	java.io.IOException
    // Exception table:
    //   from	to	target	type
    //   11	14	44	java/io/IOException
    //   18	22	44	java/io/IOException
    //   54	59	66	java/io/IOException
    //   59	63	66	java/io/IOException
    //   11	14	71	java/lang/ClassNotFoundException
    //   18	22	71	java/lang/ClassNotFoundException
    //   81	86	93	java/io/IOException
    //   86	90	93	java/io/IOException
    //   11	14	98	finally
    //   18	22	98	finally
    //   111	116	122	java/io/IOException
    //   116	120	122	java/io/IOException
    //   22	27	127	finally
    //   22	27	131	java/lang/ClassNotFoundException
    //   22	27	135	java/io/IOException
    //   33	38	139	java/io/IOException
    //   38	42	139	java/io/IOException
  }
  
  public void zza(DataLayer.zzc.zza paramzza)
  {
    Executor localExecutor = this.zzbiC;
    zzw.2 local2 = new com/google/android/gms/tagmanager/zzw$2;
    local2.<init>(this, paramzza);
    localExecutor.execute(local2);
  }
  
  public void zza(List paramList, long paramLong)
  {
    List localList = zzD(paramList);
    Executor localExecutor = this.zzbiC;
    zzw.1 local1 = new com/google/android/gms/tagmanager/zzw$1;
    local1.<init>(this, localList, paramLong);
    localExecutor.execute(local1);
  }
  
  public void zzfZ(String paramString)
  {
    Executor localExecutor = this.zzbiC;
    zzw.3 local3 = new com/google/android/gms/tagmanager/zzw$3;
    local3.<init>(this, paramString);
    localExecutor.execute(local3);
  }
}


/* Location:              C:\Users\haryo\Desktop\enjarify-master\presensi-enjarify.jar!\com\google\android\gms\tagmanager\zzw.class
 * Java compiler version: 5 (49.0)
 * JD-Core Version:       0.7.1
 */