package b.a.a.a.i.c.a;

import b.a.a.a.e.q;
import java.io.IOException;
import java.util.Date;
import java.util.HashMap;
import java.util.Iterator;
import java.util.LinkedList;
import java.util.Map;
import java.util.Queue;
import java.util.Set;
import java.util.concurrent.TimeUnit;
import java.util.concurrent.locks.Condition;
import java.util.concurrent.locks.Lock;

public class d
  extends a
{
  public b.a.a.a.h.b f;
  protected final b.a.a.a.e.d g;
  protected final b.a.a.a.e.a.b h;
  protected final Set i;
  protected final Queue j;
  protected final Queue k;
  protected final Map l;
  protected volatile boolean m;
  protected volatile int n;
  protected volatile int o;
  private final Lock p;
  private final long q;
  private final TimeUnit r;
  
  public d(b.a.a.a.e.d paramd, b.a.a.a.e.a.b paramb, int paramInt)
  {
    this(paramd, paramb, paramInt, -1, localTimeUnit);
  }
  
  public d(b.a.a.a.e.d paramd, b.a.a.a.e.a.b paramb, int paramInt, long paramLong, TimeUnit paramTimeUnit)
  {
    Object localObject = new b/a/a/a/h/b;
    Class localClass = getClass();
    ((b.a.a.a.h.b)localObject).<init>(localClass);
    this.f = ((b.a.a.a.h.b)localObject);
    b.a.a.a.o.a.a(paramd, "Connection operator");
    b.a.a.a.o.a.a(paramb, "Connections per route");
    localObject = this.b;
    this.p = ((Lock)localObject);
    localObject = this.c;
    this.i = ((Set)localObject);
    this.g = paramd;
    this.h = paramb;
    this.n = paramInt;
    localObject = b();
    this.j = ((Queue)localObject);
    localObject = c();
    this.k = ((Queue)localObject);
    localObject = d();
    this.l = ((Map)localObject);
    this.q = paramLong;
    this.r = paramTimeUnit;
  }
  
  public d(b.a.a.a.e.d paramd, b.a.a.a.l.e parame)
  {
    this(paramd, localb, i1);
  }
  
  private void b(b paramb)
  {
    q localq = paramb.c();
    if (localq != null) {}
    try
    {
      localq.close();
      return;
    }
    catch (IOException localIOException)
    {
      for (;;)
      {
        b.a.a.a.h.b localb = this.f;
        String str = "I/O error closing connection";
        localb.a(str, localIOException);
      }
    }
  }
  
  protected b a(b.a.a.a.e.b.b paramb, Object paramObject, long paramLong, TimeUnit paramTimeUnit, i parami)
  {
    localObject1 = null;
    long l1 = 0L;
    boolean bool1 = paramLong < l1;
    if (bool1)
    {
      localObject1 = new java/util/Date;
      l1 = System.currentTimeMillis();
      l2 = paramTimeUnit.toMillis(paramLong);
      l1 += l2;
      ((Date)localObject1).<init>(l1);
    }
    boolean bool2 = false;
    Object localObject4 = null;
    localObject5 = this.p;
    ((Lock)localObject5).lock();
    bool1 = true;
    for (;;)
    {
      try
      {
        localObject6 = a(paramb, bool1);
        bool1 = false;
        localObject5 = null;
      }
      finally
      {
        try
        {
          int i1;
          int i3;
          boolean bool3;
          Object localObject9;
          String str;
          int i4;
          int i2;
          int i5;
          boolean bool5;
          ((f)localObject6).a((h)localObject5);
          Object localObject7 = this.k;
          ((Queue)localObject7).add(localObject5);
          boolean bool4 = ((h)localObject5).a((Date)localObject1);
          ((f)localObject6).b((h)localObject5);
          Object localObject8 = this.k;
          ((Queue)localObject8).remove(localObject5);
          if ((bool4) || (localObject1 == null)) {
            continue;
          }
          l2 = ((Date)localObject1).getTime();
          long l3 = System.currentTimeMillis();
          bool4 = l2 < l3;
          if (bool4) {
            continue;
          }
          localObject1 = new b/a/a/a/e/h;
          localObject5 = "Timeout waiting for connection from pool";
          ((b.a.a.a.e.h)localObject1).<init>((String)localObject5);
          throw ((Throwable)localObject1);
        }
        finally
        {
          ((f)localObject6).b((h)localObject5);
          Object localObject6 = this.k;
          ((Queue)localObject6).remove(localObject5);
        }
        localObject2 = finally;
        this.p.unlock();
      }
      if (localObject4 == null)
      {
        bool2 = this.m;
        if (!bool2)
        {
          bool2 = true;
          localObject7 = "Connection pool shut down";
          b.a.a.a.o.b.a(bool2, (String)localObject7);
          localObject4 = this.f;
          bool2 = ((b.a.a.a.h.b)localObject4).a();
          if (bool2)
          {
            localObject4 = this.f;
            localObject7 = new java/lang/StringBuilder;
            ((StringBuilder)localObject7).<init>();
            localObject8 = "[";
            localObject7 = ((StringBuilder)localObject7).append((String)localObject8);
            localObject7 = ((StringBuilder)localObject7).append(paramb);
            localObject8 = "] total kept alive: ";
            localObject7 = ((StringBuilder)localObject7).append((String)localObject8);
            localObject8 = this.j;
            i1 = ((Queue)localObject8).size();
            localObject7 = ((StringBuilder)localObject7).append(i1);
            localObject8 = ", total issued: ";
            localObject7 = ((StringBuilder)localObject7).append((String)localObject8);
            localObject8 = this.i;
            i1 = ((Set)localObject8).size();
            localObject7 = ((StringBuilder)localObject7).append(i1);
            localObject8 = ", total allocated: ";
            localObject7 = ((StringBuilder)localObject7).append((String)localObject8);
            i1 = this.o;
            localObject7 = ((StringBuilder)localObject7).append(i1);
            localObject8 = " out of ";
            localObject7 = ((StringBuilder)localObject7).append((String)localObject8);
            i1 = this.n;
            localObject7 = ((StringBuilder)localObject7).append(i1);
            localObject7 = ((StringBuilder)localObject7).toString();
            ((b.a.a.a.h.b)localObject4).a(localObject7);
          }
          localObject4 = a((f)localObject6, paramObject);
          if (localObject4 == null) {
            continue;
          }
        }
      }
      else
      {
        this.p.unlock();
        return (b)localObject4;
      }
      bool2 = false;
      localObject4 = null;
      continue;
      i3 = ((f)localObject6).d();
      if (i3 > 0)
      {
        i3 = 1;
        localObject8 = this.f;
        bool3 = ((b.a.a.a.h.b)localObject8).a();
        if (bool3)
        {
          localObject8 = this.f;
          localObject9 = new java/lang/StringBuilder;
          ((StringBuilder)localObject9).<init>();
          str = "Available capacity: ";
          localObject9 = ((StringBuilder)localObject9).append(str);
          i4 = ((f)localObject6).d();
          localObject9 = ((StringBuilder)localObject9).append(i4);
          str = " out of ";
          localObject9 = ((StringBuilder)localObject9).append(str);
          i4 = ((f)localObject6).b();
          localObject9 = ((StringBuilder)localObject9).append(i4);
          str = " [";
          localObject9 = ((StringBuilder)localObject9).append(str);
          localObject9 = ((StringBuilder)localObject9).append(paramb);
          str = "][";
          localObject9 = ((StringBuilder)localObject9).append(str);
          localObject9 = ((StringBuilder)localObject9).append(paramObject);
          str = "]";
          localObject9 = ((StringBuilder)localObject9).append(str);
          localObject9 = ((StringBuilder)localObject9).toString();
          ((b.a.a.a.h.b)localObject8).a(localObject9);
        }
        if (i3 != 0)
        {
          i2 = this.o;
          i5 = this.n;
          if (i2 < i5)
          {
            localObject4 = this.g;
            localObject4 = a((f)localObject6, (b.a.a.a.e.d)localObject4);
          }
        }
      }
      else
      {
        i3 = 0;
        localObject7 = null;
        continue;
      }
      if (i3 == 0) {
        continue;
      }
      localObject7 = this.j;
      bool4 = ((Queue)localObject7).isEmpty();
      if (bool4) {
        continue;
      }
      e();
      bool5 = true;
      localObject6 = a(paramb, bool5);
      localObject4 = this.g;
      localObject4 = a((f)localObject6, (b.a.a.a.e.d)localObject4);
    }
    localObject7 = this.f;
    bool4 = ((b.a.a.a.h.b)localObject7).a();
    if (bool4)
    {
      localObject7 = this.f;
      localObject8 = new java/lang/StringBuilder;
      ((StringBuilder)localObject8).<init>();
      localObject9 = "Need to wait for connection [";
      localObject8 = ((StringBuilder)localObject8).append((String)localObject9);
      localObject8 = ((StringBuilder)localObject8).append(paramb);
      localObject9 = "][";
      localObject8 = ((StringBuilder)localObject8).append((String)localObject9);
      localObject8 = ((StringBuilder)localObject8).append(paramObject);
      localObject9 = "]";
      localObject8 = ((StringBuilder)localObject8).append((String)localObject9);
      localObject8 = ((StringBuilder)localObject8).toString();
      ((b.a.a.a.h.b)localObject7).a(localObject8);
    }
    if (localObject5 == null)
    {
      localObject5 = this.p;
      localObject5 = ((Lock)localObject5).newCondition();
      localObject5 = a((Condition)localObject5, (f)localObject6);
      parami.a((h)localObject5);
    }
  }
  
  protected b a(f paramf, b.a.a.a.e.d paramd)
  {
    Object localObject1 = this.f;
    boolean bool = ((b.a.a.a.h.b)localObject1).a();
    if (bool)
    {
      localObject1 = this.f;
      localObject3 = new java/lang/StringBuilder;
      ((StringBuilder)localObject3).<init>();
      localObject3 = ((StringBuilder)localObject3).append("Creating new connection [");
      localObject4 = paramf.a();
      localObject3 = ((StringBuilder)localObject3).append(localObject4);
      localObject4 = "]";
      localObject3 = (String)localObject4;
      ((b.a.a.a.h.b)localObject1).a(localObject3);
    }
    Object localObject3 = new b/a/a/a/i/c/a/b;
    b.a.a.a.e.b.b localb = paramf.a();
    long l1 = this.q;
    TimeUnit localTimeUnit = this.r;
    Object localObject4 = paramd;
    ((b)localObject3).<init>(paramd, localb, l1, localTimeUnit);
    localObject1 = this.p;
    ((Lock)localObject1).lock();
    try
    {
      paramf.b((b)localObject3);
      int i1 = this.o + 1;
      this.o = i1;
      localObject1 = this.i;
      ((Set)localObject1).add(localObject3);
      return (b)localObject3;
    }
    finally
    {
      this.p.unlock();
    }
  }
  
  protected b a(f paramf, Object paramObject)
  {
    boolean bool1 = true;
    b localb = null;
    this.p.lock();
    boolean bool2 = false;
    Object localObject1 = null;
    for (;;)
    {
      if (!bool2)
      {
        Object localObject4;
        Object localObject5;
        try
        {
          localb = paramf.a(paramObject);
          if (localb == null) {
            break label357;
          }
          localObject4 = this.f;
          boolean bool3 = ((b.a.a.a.h.b)localObject4).a();
          Object localObject6;
          if (bool3)
          {
            localObject4 = this.f;
            localObject5 = new java/lang/StringBuilder;
            ((StringBuilder)localObject5).<init>();
            localObject6 = "Getting free connection [";
            localObject5 = ((StringBuilder)localObject5).append((String)localObject6);
            localObject6 = paramf.a();
            localObject5 = ((StringBuilder)localObject5).append(localObject6);
            localObject6 = "][";
            localObject5 = ((StringBuilder)localObject5).append((String)localObject6);
            localObject5 = ((StringBuilder)localObject5).append(paramObject);
            localObject6 = "]";
            localObject5 = ((StringBuilder)localObject5).append((String)localObject6);
            localObject5 = ((StringBuilder)localObject5).toString();
            ((b.a.a.a.h.b)localObject4).a(localObject5);
          }
          localObject4 = this.j;
          ((Queue)localObject4).remove(localb);
          long l1 = System.currentTimeMillis();
          bool3 = localb.a(l1);
          if (bool3)
          {
            localObject4 = this.f;
            bool3 = ((b.a.a.a.h.b)localObject4).a();
            if (bool3)
            {
              localObject4 = this.f;
              localObject5 = new java/lang/StringBuilder;
              ((StringBuilder)localObject5).<init>();
              localObject6 = "Closing expired free connection [";
              localObject5 = ((StringBuilder)localObject5).append((String)localObject6);
              localObject6 = paramf.a();
              localObject5 = ((StringBuilder)localObject5).append(localObject6);
              localObject6 = "][";
              localObject5 = ((StringBuilder)localObject5).append((String)localObject6);
              localObject5 = ((StringBuilder)localObject5).append(paramObject);
              localObject6 = "]";
              localObject5 = ((StringBuilder)localObject5).append((String)localObject6);
              localObject5 = ((StringBuilder)localObject5).toString();
              ((b.a.a.a.h.b)localObject4).a(localObject5);
            }
            b(localb);
            paramf.e();
            int i1 = this.o + -1;
            this.o = i1;
            continue;
          }
        }
        finally
        {
          this.p.unlock();
        }
        Object localObject3 = this.i;
        ((Set)localObject3).add(localb);
        bool2 = bool1;
        continue;
        label357:
        localObject3 = this.f;
        bool2 = ((b.a.a.a.h.b)localObject3).a();
        if (bool2)
        {
          localObject3 = this.f;
          localObject4 = new java/lang/StringBuilder;
          ((StringBuilder)localObject4).<init>();
          localObject5 = "No free connections [";
          localObject4 = ((StringBuilder)localObject4).append((String)localObject5);
          localObject5 = paramf.a();
          localObject4 = ((StringBuilder)localObject4).append(localObject5);
          localObject5 = "][";
          localObject4 = ((StringBuilder)localObject4).append((String)localObject5);
          localObject4 = ((StringBuilder)localObject4).append(paramObject);
          localObject5 = "]";
          localObject4 = ((StringBuilder)localObject4).append((String)localObject5);
          localObject4 = ((StringBuilder)localObject4).toString();
          ((b.a.a.a.h.b)localObject3).a(localObject4);
          bool2 = bool1;
        }
      }
      else
      {
        this.p.unlock();
        return localb;
      }
      bool2 = bool1;
    }
  }
  
  public e a(b.a.a.a.e.b.b paramb, Object paramObject)
  {
    i locali = new b/a/a/a/i/c/a/i;
    locali.<init>();
    d.1 local1 = new b/a/a/a/i/c/a/d$1;
    local1.<init>(this, locali, paramb, paramObject);
    return local1;
  }
  
  protected f a(b.a.a.a.e.b.b paramb)
  {
    f localf = new b/a/a/a/i/c/a/f;
    b.a.a.a.e.a.b localb = this.h;
    localf.<init>(paramb, localb);
    return localf;
  }
  
  protected f a(b.a.a.a.e.b.b paramb, boolean paramBoolean)
  {
    Object localObject1 = this.p;
    ((Lock)localObject1).lock();
    try
    {
      localObject1 = this.l;
      localObject1 = ((Map)localObject1).get(paramb);
      localObject1 = (f)localObject1;
      if ((localObject1 == null) && (paramBoolean))
      {
        localObject1 = a(paramb);
        Map localMap = this.l;
        localMap.put(paramb, localObject1);
      }
      return (f)localObject1;
    }
    finally
    {
      this.p.unlock();
    }
  }
  
  protected h a(Condition paramCondition, f paramf)
  {
    h localh = new b/a/a/a/i/c/a/h;
    localh.<init>(paramCondition, paramf);
    return localh;
  }
  
  public void a()
  {
    Object localObject1 = this.p;
    ((Lock)localObject1).lock();
    for (;;)
    {
      boolean bool1;
      try
      {
        bool1 = this.m;
        if (bool1)
        {
          localObject1 = this.p;
          ((Lock)localObject1).unlock();
          return;
        }
        bool1 = true;
        this.m = bool1;
        localObject1 = this.i;
        localIterator = ((Set)localObject1).iterator();
        bool1 = localIterator.hasNext();
        if (bool1)
        {
          localObject1 = localIterator.next();
          localObject1 = (b)localObject1;
          localIterator.remove();
          b((b)localObject1);
          continue;
        }
        localObject3 = this.j;
      }
      finally
      {
        this.p.unlock();
      }
      Iterator localIterator = ((Queue)localObject3).iterator();
      for (;;)
      {
        bool1 = localIterator.hasNext();
        if (!bool1) {
          break;
        }
        localObject3 = localIterator.next();
        localObject3 = (b)localObject3;
        localIterator.remove();
        b.a.a.a.h.b localb = this.f;
        boolean bool2 = localb.a();
        if (bool2)
        {
          localb = this.f;
          Object localObject4 = new java/lang/StringBuilder;
          ((StringBuilder)localObject4).<init>();
          Object localObject5 = "Closing connection [";
          localObject4 = ((StringBuilder)localObject4).append((String)localObject5);
          localObject5 = ((b)localObject3).d();
          localObject4 = ((StringBuilder)localObject4).append(localObject5);
          localObject5 = "][";
          localObject4 = ((StringBuilder)localObject4).append((String)localObject5);
          localObject5 = ((b)localObject3).a();
          localObject4 = ((StringBuilder)localObject4).append(localObject5);
          localObject5 = "]";
          localObject4 = ((StringBuilder)localObject4).append((String)localObject5);
          localObject4 = ((StringBuilder)localObject4).toString();
          localb.a(localObject4);
        }
        b((b)localObject3);
      }
      Object localObject3 = this.k;
      localIterator = ((Queue)localObject3).iterator();
      for (;;)
      {
        bool1 = localIterator.hasNext();
        if (!bool1) {
          break;
        }
        localObject3 = localIterator.next();
        localObject3 = (h)localObject3;
        localIterator.remove();
        ((h)localObject3).a();
      }
      localObject3 = this.l;
      ((Map)localObject3).clear();
      localObject3 = this.p;
      ((Lock)localObject3).unlock();
    }
  }
  
  protected void a(b paramb)
  {
    b.a.a.a.e.b.b localb = paramb.d();
    Object localObject2 = this.f;
    boolean bool = ((b.a.a.a.h.b)localObject2).a();
    if (bool)
    {
      localObject2 = this.f;
      Object localObject3 = new java/lang/StringBuilder;
      ((StringBuilder)localObject3).<init>();
      localObject3 = ((StringBuilder)localObject3).append("Deleting connection [").append(localb).append("][");
      Object localObject4 = paramb.a();
      localObject3 = ((StringBuilder)localObject3).append(localObject4);
      localObject4 = "]";
      localObject3 = (String)localObject4;
      ((b.a.a.a.h.b)localObject2).a(localObject3);
    }
    localObject2 = this.p;
    ((Lock)localObject2).lock();
    try
    {
      b(paramb);
      bool = true;
      localObject2 = a(localb, bool);
      ((f)localObject2).c(paramb);
      int i1 = this.o + -1;
      this.o = i1;
      bool = ((f)localObject2).c();
      if (bool)
      {
        localObject2 = this.l;
        ((Map)localObject2).remove(localb);
      }
      return;
    }
    finally
    {
      this.p.unlock();
    }
  }
  
  /* Error */
  public void a(b paramb, boolean paramBoolean, long paramLong, TimeUnit paramTimeUnit)
  {
    // Byte code:
    //   0: aload_1
    //   1: invokevirtual 341	b/a/a/a/i/c/a/b:d	()Lb/a/a/a/e/b/b;
    //   4: astore 6
    //   6: aload_0
    //   7: getfield 53	b/a/a/a/i/c/a/d:f	Lb/a/a/a/h/b;
    //   10: astore 7
    //   12: aload 7
    //   14: invokevirtual 162	b/a/a/a/h/b:a	()Z
    //   17: istore 8
    //   19: iload 8
    //   21: ifeq +77 -> 98
    //   24: aload_0
    //   25: getfield 53	b/a/a/a/i/c/a/d:f	Lb/a/a/a/h/b;
    //   28: astore 7
    //   30: new 164	java/lang/StringBuilder
    //   33: astore 9
    //   35: aload 9
    //   37: invokespecial 165	java/lang/StringBuilder:<init>	()V
    //   40: aload 9
    //   42: ldc_w 359
    //   45: invokevirtual 171	java/lang/StringBuilder:append	(Ljava/lang/String;)Ljava/lang/StringBuilder;
    //   48: aload 6
    //   50: invokevirtual 174	java/lang/StringBuilder:append	(Ljava/lang/Object;)Ljava/lang/StringBuilder;
    //   53: ldc -36
    //   55: invokevirtual 171	java/lang/StringBuilder:append	(Ljava/lang/String;)Ljava/lang/StringBuilder;
    //   58: astore 9
    //   60: aload_1
    //   61: invokevirtual 343	b/a/a/a/i/c/a/b:a	()Ljava/lang/Object;
    //   64: astore 10
    //   66: aload 9
    //   68: aload 10
    //   70: invokevirtual 174	java/lang/StringBuilder:append	(Ljava/lang/Object;)Ljava/lang/StringBuilder;
    //   73: astore 9
    //   75: ldc -34
    //   77: astore 10
    //   79: aload 9
    //   81: aload 10
    //   83: invokevirtual 171	java/lang/StringBuilder:append	(Ljava/lang/String;)Ljava/lang/StringBuilder;
    //   86: invokevirtual 200	java/lang/StringBuilder:toString	()Ljava/lang/String;
    //   89: astore 9
    //   91: aload 7
    //   93: aload 9
    //   95: invokevirtual 202	b/a/a/a/h/b:a	(Ljava/lang/Object;)V
    //   98: aload_0
    //   99: getfield 68	b/a/a/a/i/c/a/d:p	Ljava/util/concurrent/locks/Lock;
    //   102: astore 7
    //   104: aload 7
    //   106: invokeinterface 146 1 0
    //   111: aload_0
    //   112: getfield 152	b/a/a/a/i/c/a/d:m	Z
    //   115: istore 8
    //   117: iload 8
    //   119: ifeq +22 -> 141
    //   122: aload_0
    //   123: aload_1
    //   124: invokespecial 293	b/a/a/a/i/c/a/d:b	(Lb/a/a/a/i/c/a/b;)V
    //   127: aload_0
    //   128: getfield 68	b/a/a/a/i/c/a/d:p	Ljava/util/concurrent/locks/Lock;
    //   131: astore 7
    //   133: aload 7
    //   135: invokeinterface 208 1 0
    //   140: return
    //   141: aload_0
    //   142: getfield 73	b/a/a/a/i/c/a/d:i	Ljava/util/Set;
    //   145: astore 7
    //   147: aload 7
    //   149: aload_1
    //   150: invokeinterface 360 2 0
    //   155: pop
    //   156: iconst_1
    //   157: istore 8
    //   159: aload_0
    //   160: aload 6
    //   162: iload 8
    //   164: invokevirtual 150	b/a/a/a/i/c/a/d:a	(Lb/a/a/a/e/b/b;Z)Lb/a/a/a/i/c/a/f;
    //   167: astore 9
    //   169: iload_2
    //   170: ifeq +271 -> 441
    //   173: aload 9
    //   175: invokevirtual 212	b/a/a/a/i/c/a/f:d	()I
    //   178: istore 8
    //   180: iload 8
    //   182: iflt +259 -> 441
    //   185: aload_0
    //   186: getfield 53	b/a/a/a/i/c/a/d:f	Lb/a/a/a/h/b;
    //   189: astore 7
    //   191: aload 7
    //   193: invokevirtual 162	b/a/a/a/h/b:a	()Z
    //   196: istore 8
    //   198: iload 8
    //   200: ifeq +183 -> 383
    //   203: lconst_0
    //   204: lstore 11
    //   206: lload_3
    //   207: lload 11
    //   209: lcmp
    //   210: istore 8
    //   212: iload 8
    //   214: ifle +219 -> 433
    //   217: new 164	java/lang/StringBuilder
    //   220: astore 7
    //   222: aload 7
    //   224: invokespecial 165	java/lang/StringBuilder:<init>	()V
    //   227: ldc_w 362
    //   230: astore 10
    //   232: aload 7
    //   234: aload 10
    //   236: invokevirtual 171	java/lang/StringBuilder:append	(Ljava/lang/String;)Ljava/lang/StringBuilder;
    //   239: astore 7
    //   241: aload 7
    //   243: lload_3
    //   244: invokevirtual 365	java/lang/StringBuilder:append	(J)Ljava/lang/StringBuilder;
    //   247: astore 7
    //   249: ldc_w 367
    //   252: astore 10
    //   254: aload 7
    //   256: aload 10
    //   258: invokevirtual 171	java/lang/StringBuilder:append	(Ljava/lang/String;)Ljava/lang/StringBuilder;
    //   261: astore 7
    //   263: aload 7
    //   265: aload 5
    //   267: invokevirtual 174	java/lang/StringBuilder:append	(Ljava/lang/Object;)Ljava/lang/StringBuilder;
    //   270: astore 7
    //   272: aload 7
    //   274: invokevirtual 200	java/lang/StringBuilder:toString	()Ljava/lang/String;
    //   277: astore 7
    //   279: aload_0
    //   280: getfield 53	b/a/a/a/i/c/a/d:f	Lb/a/a/a/h/b;
    //   283: astore 10
    //   285: new 164	java/lang/StringBuilder
    //   288: astore 13
    //   290: aload 13
    //   292: invokespecial 165	java/lang/StringBuilder:<init>	()V
    //   295: ldc_w 369
    //   298: astore 14
    //   300: aload 13
    //   302: aload 14
    //   304: invokevirtual 171	java/lang/StringBuilder:append	(Ljava/lang/String;)Ljava/lang/StringBuilder;
    //   307: astore 13
    //   309: aload 13
    //   311: aload 6
    //   313: invokevirtual 174	java/lang/StringBuilder:append	(Ljava/lang/Object;)Ljava/lang/StringBuilder;
    //   316: astore 6
    //   318: ldc -36
    //   320: astore 13
    //   322: aload 6
    //   324: aload 13
    //   326: invokevirtual 171	java/lang/StringBuilder:append	(Ljava/lang/String;)Ljava/lang/StringBuilder;
    //   329: astore 6
    //   331: aload_1
    //   332: invokevirtual 343	b/a/a/a/i/c/a/b:a	()Ljava/lang/Object;
    //   335: astore 13
    //   337: aload 6
    //   339: aload 13
    //   341: invokevirtual 174	java/lang/StringBuilder:append	(Ljava/lang/Object;)Ljava/lang/StringBuilder;
    //   344: astore 6
    //   346: ldc_w 371
    //   349: astore 13
    //   351: aload 6
    //   353: aload 13
    //   355: invokevirtual 171	java/lang/StringBuilder:append	(Ljava/lang/String;)Ljava/lang/StringBuilder;
    //   358: astore 6
    //   360: aload 6
    //   362: aload 7
    //   364: invokevirtual 171	java/lang/StringBuilder:append	(Ljava/lang/String;)Ljava/lang/StringBuilder;
    //   367: astore 7
    //   369: aload 7
    //   371: invokevirtual 200	java/lang/StringBuilder:toString	()Ljava/lang/String;
    //   374: astore 7
    //   376: aload 10
    //   378: aload 7
    //   380: invokevirtual 202	b/a/a/a/h/b:a	(Ljava/lang/Object;)V
    //   383: aload 9
    //   385: aload_1
    //   386: invokevirtual 373	b/a/a/a/i/c/a/f:a	(Lb/a/a/a/i/c/a/b;)V
    //   389: aload_1
    //   390: lload_3
    //   391: aload 5
    //   393: invokevirtual 376	b/a/a/a/i/c/a/b:a	(JLjava/util/concurrent/TimeUnit;)V
    //   396: aload_0
    //   397: getfield 84	b/a/a/a/i/c/a/d:j	Ljava/util/Queue;
    //   400: astore 7
    //   402: aload 7
    //   404: aload_1
    //   405: invokeinterface 250 2 0
    //   410: pop
    //   411: aload_0
    //   412: aload 9
    //   414: invokevirtual 379	b/a/a/a/i/c/a/d:a	(Lb/a/a/a/i/c/a/f;)V
    //   417: aload_0
    //   418: getfield 68	b/a/a/a/i/c/a/d:p	Ljava/util/concurrent/locks/Lock;
    //   421: astore 7
    //   423: aload 7
    //   425: invokeinterface 208 1 0
    //   430: goto -290 -> 140
    //   433: ldc_w 381
    //   436: astore 7
    //   438: goto -159 -> 279
    //   441: aload_0
    //   442: aload_1
    //   443: invokespecial 293	b/a/a/a/i/c/a/d:b	(Lb/a/a/a/i/c/a/b;)V
    //   446: aload 9
    //   448: invokevirtual 294	b/a/a/a/i/c/a/f:e	()V
    //   451: aload_0
    //   452: getfield 194	b/a/a/a/i/c/a/d:o	I
    //   455: iconst_m1
    //   456: iadd
    //   457: istore 8
    //   459: aload_0
    //   460: iload 8
    //   462: putfield 194	b/a/a/a/i/c/a/d:o	I
    //   465: goto -54 -> 411
    //   468: astore 7
    //   470: aload_0
    //   471: getfield 68	b/a/a/a/i/c/a/d:p	Ljava/util/concurrent/locks/Lock;
    //   474: invokeinterface 208 1 0
    //   479: aload 7
    //   481: athrow
    // Local variable table:
    //   start	length	slot	name	signature
    //   0	482	0	this	d
    //   0	482	1	paramb	b
    //   0	482	2	paramBoolean	boolean
    //   0	482	3	paramLong	long
    //   0	482	5	paramTimeUnit	TimeUnit
    //   4	357	6	localObject1	Object
    //   10	427	7	localObject2	Object
    //   468	12	7	localObject3	Object
    //   17	146	8	bool1	boolean
    //   178	3	8	i1	int
    //   196	17	8	bool2	boolean
    //   457	4	8	i2	int
    //   33	414	9	localObject4	Object
    //   64	313	10	localObject5	Object
    //   204	4	11	l1	long
    //   288	66	13	localObject6	Object
    //   298	5	14	str	String
    // Exception table:
    //   from	to	target	type
    //   111	115	468	finally
    //   123	127	468	finally
    //   141	145	468	finally
    //   149	156	468	finally
    //   162	167	468	finally
    //   173	178	468	finally
    //   185	189	468	finally
    //   191	196	468	finally
    //   217	220	468	finally
    //   222	227	468	finally
    //   234	239	468	finally
    //   243	247	468	finally
    //   256	261	468	finally
    //   265	270	468	finally
    //   272	277	468	finally
    //   279	283	468	finally
    //   285	288	468	finally
    //   290	295	468	finally
    //   302	307	468	finally
    //   311	316	468	finally
    //   324	329	468	finally
    //   331	335	468	finally
    //   339	344	468	finally
    //   353	358	468	finally
    //   362	367	468	finally
    //   369	374	468	finally
    //   378	383	468	finally
    //   385	389	468	finally
    //   391	396	468	finally
    //   396	400	468	finally
    //   404	411	468	finally
    //   412	417	468	finally
    //   442	446	468	finally
    //   446	451	468	finally
    //   451	455	468	finally
    //   460	465	468	finally
  }
  
  /* Error */
  protected void a(f paramf)
  {
    // Byte code:
    //   0: iconst_0
    //   1: istore_2
    //   2: aconst_null
    //   3: astore_3
    //   4: aload_0
    //   5: getfield 68	b/a/a/a/i/c/a/d:p	Ljava/util/concurrent/locks/Lock;
    //   8: astore 4
    //   10: aload 4
    //   12: invokeinterface 146 1 0
    //   17: aload_1
    //   18: ifnull +121 -> 139
    //   21: aload_1
    //   22: invokevirtual 383	b/a/a/a/i/c/a/f:f	()Z
    //   25: istore 5
    //   27: iload 5
    //   29: ifeq +110 -> 139
    //   32: aload_0
    //   33: getfield 53	b/a/a/a/i/c/a/d:f	Lb/a/a/a/h/b;
    //   36: astore_3
    //   37: aload_3
    //   38: invokevirtual 162	b/a/a/a/h/b:a	()Z
    //   41: istore_2
    //   42: iload_2
    //   43: ifeq +73 -> 116
    //   46: aload_0
    //   47: getfield 53	b/a/a/a/i/c/a/d:f	Lb/a/a/a/h/b;
    //   50: astore_3
    //   51: new 164	java/lang/StringBuilder
    //   54: astore 4
    //   56: aload 4
    //   58: invokespecial 165	java/lang/StringBuilder:<init>	()V
    //   61: ldc_w 385
    //   64: astore 6
    //   66: aload 4
    //   68: aload 6
    //   70: invokevirtual 171	java/lang/StringBuilder:append	(Ljava/lang/String;)Ljava/lang/StringBuilder;
    //   73: astore 4
    //   75: aload_1
    //   76: invokevirtual 275	b/a/a/a/i/c/a/f:a	()Lb/a/a/a/e/b/b;
    //   79: astore 6
    //   81: aload 4
    //   83: aload 6
    //   85: invokevirtual 174	java/lang/StringBuilder:append	(Ljava/lang/Object;)Ljava/lang/StringBuilder;
    //   88: astore 4
    //   90: ldc -34
    //   92: astore 6
    //   94: aload 4
    //   96: aload 6
    //   98: invokevirtual 171	java/lang/StringBuilder:append	(Ljava/lang/String;)Ljava/lang/StringBuilder;
    //   101: astore 4
    //   103: aload 4
    //   105: invokevirtual 200	java/lang/StringBuilder:toString	()Ljava/lang/String;
    //   108: astore 4
    //   110: aload_3
    //   111: aload 4
    //   113: invokevirtual 202	b/a/a/a/h/b:a	(Ljava/lang/Object;)V
    //   116: aload_1
    //   117: invokevirtual 388	b/a/a/a/i/c/a/f:g	()Lb/a/a/a/i/c/a/h;
    //   120: astore_3
    //   121: aload_3
    //   122: ifnull +7 -> 129
    //   125: aload_3
    //   126: invokevirtual 345	b/a/a/a/i/c/a/h:a	()V
    //   129: aload_0
    //   130: getfield 68	b/a/a/a/i/c/a/d:p	Ljava/util/concurrent/locks/Lock;
    //   133: invokeinterface 208 1 0
    //   138: return
    //   139: aload_0
    //   140: getfield 88	b/a/a/a/i/c/a/d:k	Ljava/util/Queue;
    //   143: astore 4
    //   145: aload 4
    //   147: invokeinterface 228 1 0
    //   152: istore 5
    //   154: iload 5
    //   156: ifne +53 -> 209
    //   159: aload_0
    //   160: getfield 53	b/a/a/a/i/c/a/d:f	Lb/a/a/a/h/b;
    //   163: astore_3
    //   164: aload_3
    //   165: invokevirtual 162	b/a/a/a/h/b:a	()Z
    //   168: istore_2
    //   169: iload_2
    //   170: ifeq +19 -> 189
    //   173: aload_0
    //   174: getfield 53	b/a/a/a/i/c/a/d:f	Lb/a/a/a/h/b;
    //   177: astore_3
    //   178: ldc_w 390
    //   181: astore 4
    //   183: aload_3
    //   184: aload 4
    //   186: invokevirtual 202	b/a/a/a/h/b:a	(Ljava/lang/Object;)V
    //   189: aload_0
    //   190: getfield 88	b/a/a/a/i/c/a/d:k	Ljava/util/Queue;
    //   193: astore_3
    //   194: aload_3
    //   195: invokeinterface 392 1 0
    //   200: astore_3
    //   201: aload_3
    //   202: checkcast 252	b/a/a/a/i/c/a/h
    //   205: astore_3
    //   206: goto -85 -> 121
    //   209: aload_0
    //   210: getfield 53	b/a/a/a/i/c/a/d:f	Lb/a/a/a/h/b;
    //   213: astore 4
    //   215: aload 4
    //   217: invokevirtual 162	b/a/a/a/h/b:a	()Z
    //   220: istore 5
    //   222: iload 5
    //   224: ifeq -103 -> 121
    //   227: aload_0
    //   228: getfield 53	b/a/a/a/i/c/a/d:f	Lb/a/a/a/h/b;
    //   231: astore 4
    //   233: ldc_w 394
    //   236: astore 6
    //   238: aload 4
    //   240: aload 6
    //   242: invokevirtual 202	b/a/a/a/h/b:a	(Ljava/lang/Object;)V
    //   245: goto -124 -> 121
    //   248: astore_3
    //   249: aload_0
    //   250: getfield 68	b/a/a/a/i/c/a/d:p	Ljava/util/concurrent/locks/Lock;
    //   253: invokeinterface 208 1 0
    //   258: aload_3
    //   259: athrow
    // Local variable table:
    //   start	length	slot	name	signature
    //   0	260	0	this	d
    //   0	260	1	paramf	f
    //   1	169	2	bool1	boolean
    //   3	203	3	localObject1	Object
    //   248	11	3	localObject2	Object
    //   8	231	4	localObject3	Object
    //   25	198	5	bool2	boolean
    //   64	177	6	localObject4	Object
    // Exception table:
    //   from	to	target	type
    //   21	25	248	finally
    //   32	36	248	finally
    //   37	41	248	finally
    //   46	50	248	finally
    //   51	54	248	finally
    //   56	61	248	finally
    //   68	73	248	finally
    //   75	79	248	finally
    //   83	88	248	finally
    //   96	101	248	finally
    //   103	108	248	finally
    //   111	116	248	finally
    //   116	120	248	finally
    //   125	129	248	finally
    //   139	143	248	finally
    //   145	152	248	finally
    //   159	163	248	finally
    //   164	168	248	finally
    //   173	177	248	finally
    //   184	189	248	finally
    //   189	193	248	finally
    //   194	200	248	finally
    //   201	205	248	finally
    //   209	213	248	finally
    //   215	220	248	finally
    //   227	231	248	finally
    //   240	245	248	finally
  }
  
  protected Queue b()
  {
    LinkedList localLinkedList = new java/util/LinkedList;
    localLinkedList.<init>();
    return localLinkedList;
  }
  
  protected Queue c()
  {
    LinkedList localLinkedList = new java/util/LinkedList;
    localLinkedList.<init>();
    return localLinkedList;
  }
  
  protected Map d()
  {
    HashMap localHashMap = new java/util/HashMap;
    localHashMap.<init>();
    return localHashMap;
  }
  
  /* Error */
  protected void e()
  {
    // Byte code:
    //   0: aload_0
    //   1: getfield 68	b/a/a/a/i/c/a/d:p	Ljava/util/concurrent/locks/Lock;
    //   4: astore_1
    //   5: aload_1
    //   6: invokeinterface 146 1 0
    //   11: aload_0
    //   12: getfield 84	b/a/a/a/i/c/a/d:j	Ljava/util/Queue;
    //   15: astore_1
    //   16: aload_1
    //   17: invokeinterface 392 1 0
    //   22: astore_1
    //   23: aload_1
    //   24: checkcast 111	b/a/a/a/i/c/a/b
    //   27: astore_1
    //   28: aload_1
    //   29: ifnull +18 -> 47
    //   32: aload_0
    //   33: aload_1
    //   34: invokevirtual 401	b/a/a/a/i/c/a/d:a	(Lb/a/a/a/i/c/a/b;)V
    //   37: aload_0
    //   38: getfield 68	b/a/a/a/i/c/a/d:p	Ljava/util/concurrent/locks/Lock;
    //   41: invokeinterface 208 1 0
    //   46: return
    //   47: aload_0
    //   48: getfield 53	b/a/a/a/i/c/a/d:f	Lb/a/a/a/h/b;
    //   51: astore_1
    //   52: aload_1
    //   53: invokevirtual 162	b/a/a/a/h/b:a	()Z
    //   56: istore_2
    //   57: iload_2
    //   58: ifeq -21 -> 37
    //   61: aload_0
    //   62: getfield 53	b/a/a/a/i/c/a/d:f	Lb/a/a/a/h/b;
    //   65: astore_1
    //   66: ldc_w 403
    //   69: astore_3
    //   70: aload_1
    //   71: aload_3
    //   72: invokevirtual 202	b/a/a/a/h/b:a	(Ljava/lang/Object;)V
    //   75: goto -38 -> 37
    //   78: astore_1
    //   79: aload_0
    //   80: getfield 68	b/a/a/a/i/c/a/d:p	Ljava/util/concurrent/locks/Lock;
    //   83: invokeinterface 208 1 0
    //   88: aload_1
    //   89: athrow
    // Local variable table:
    //   start	length	slot	name	signature
    //   0	90	0	this	d
    //   4	67	1	localObject1	Object
    //   78	11	1	localObject2	Object
    //   56	2	2	bool	boolean
    //   69	3	3	str	String
    // Exception table:
    //   from	to	target	type
    //   11	15	78	finally
    //   16	22	78	finally
    //   23	27	78	finally
    //   33	37	78	finally
    //   47	51	78	finally
    //   52	56	78	finally
    //   61	65	78	finally
    //   71	75	78	finally
  }
}


/* Location:              C:\Users\haryo\Desktop\enjarify-master\presensi-enjarify.jar!\b\a\a\a\i\c\a\d.class
 * Java compiler version: 5 (49.0)
 * JD-Core Version:       0.7.1
 */