package com.google.android.gms.wearable.internal;

import android.os.IBinder;

class zzav$zza$zza
  implements zzav
{
  private IBinder zzoz;
  
  zzav$zza$zza(IBinder paramIBinder)
  {
    this.zzoz = paramIBinder;
  }
  
  public IBinder asBinder()
  {
    return this.zzoz;
  }
  
  /* Error */
  public void zza(com.google.android.gms.common.api.Status paramStatus)
  {
    // Byte code:
    //   0: invokestatic 20	android/os/Parcel:obtain	()Landroid/os/Parcel;
    //   3: astore_2
    //   4: invokestatic 20	android/os/Parcel:obtain	()Landroid/os/Parcel;
    //   7: astore_3
    //   8: ldc 22
    //   10: astore 4
    //   12: aload_2
    //   13: aload 4
    //   15: invokevirtual 26	android/os/Parcel:writeInterfaceToken	(Ljava/lang/String;)V
    //   18: aload_1
    //   19: ifnull +60 -> 79
    //   22: iconst_1
    //   23: istore 5
    //   25: aload_2
    //   26: iload 5
    //   28: invokevirtual 31	android/os/Parcel:writeInt	(I)V
    //   31: iconst_0
    //   32: istore 5
    //   34: aconst_null
    //   35: astore 4
    //   37: aload_1
    //   38: aload_2
    //   39: iconst_0
    //   40: invokevirtual 37	com/google/android/gms/common/api/Status:writeToParcel	(Landroid/os/Parcel;I)V
    //   43: aload_0
    //   44: getfield 14	com/google/android/gms/wearable/internal/zzav$zza$zza:zzoz	Landroid/os/IBinder;
    //   47: astore 4
    //   49: bipush 11
    //   51: istore 6
    //   53: aload 4
    //   55: iload 6
    //   57: aload_2
    //   58: aload_3
    //   59: iconst_0
    //   60: invokeinterface 44 5 0
    //   65: pop
    //   66: aload_3
    //   67: invokevirtual 47	android/os/Parcel:readException	()V
    //   70: aload_3
    //   71: invokevirtual 50	android/os/Parcel:recycle	()V
    //   74: aload_2
    //   75: invokevirtual 50	android/os/Parcel:recycle	()V
    //   78: return
    //   79: iconst_0
    //   80: istore 5
    //   82: aconst_null
    //   83: astore 4
    //   85: aload_2
    //   86: iconst_0
    //   87: invokevirtual 31	android/os/Parcel:writeInt	(I)V
    //   90: goto -47 -> 43
    //   93: astore 4
    //   95: aload_3
    //   96: invokevirtual 50	android/os/Parcel:recycle	()V
    //   99: aload_2
    //   100: invokevirtual 50	android/os/Parcel:recycle	()V
    //   103: aload 4
    //   105: athrow
    // Local variable table:
    //   start	length	slot	name	signature
    //   0	106	0	this	zza
    //   0	106	1	paramStatus	com.google.android.gms.common.api.Status
    //   3	97	2	localParcel1	android.os.Parcel
    //   7	89	3	localParcel2	android.os.Parcel
    //   10	74	4	localObject1	Object
    //   93	11	4	localObject2	Object
    //   23	58	5	i	int
    //   51	5	6	j	int
    // Exception table:
    //   from	to	target	type
    //   13	18	93	finally
    //   26	31	93	finally
    //   39	43	93	finally
    //   43	47	93	finally
    //   59	66	93	finally
    //   66	70	93	finally
    //   86	90	93	finally
  }
  
  /* Error */
  public void zza(AddLocalCapabilityResponse paramAddLocalCapabilityResponse)
  {
    // Byte code:
    //   0: invokestatic 20	android/os/Parcel:obtain	()Landroid/os/Parcel;
    //   3: astore_2
    //   4: invokestatic 20	android/os/Parcel:obtain	()Landroid/os/Parcel;
    //   7: astore_3
    //   8: ldc 22
    //   10: astore 4
    //   12: aload_2
    //   13: aload 4
    //   15: invokevirtual 26	android/os/Parcel:writeInterfaceToken	(Ljava/lang/String;)V
    //   18: aload_1
    //   19: ifnull +60 -> 79
    //   22: iconst_1
    //   23: istore 5
    //   25: aload_2
    //   26: iload 5
    //   28: invokevirtual 31	android/os/Parcel:writeInt	(I)V
    //   31: iconst_0
    //   32: istore 5
    //   34: aconst_null
    //   35: astore 4
    //   37: aload_1
    //   38: aload_2
    //   39: iconst_0
    //   40: invokevirtual 53	com/google/android/gms/wearable/internal/AddLocalCapabilityResponse:writeToParcel	(Landroid/os/Parcel;I)V
    //   43: aload_0
    //   44: getfield 14	com/google/android/gms/wearable/internal/zzav$zza$zza:zzoz	Landroid/os/IBinder;
    //   47: astore 4
    //   49: bipush 26
    //   51: istore 6
    //   53: aload 4
    //   55: iload 6
    //   57: aload_2
    //   58: aload_3
    //   59: iconst_0
    //   60: invokeinterface 44 5 0
    //   65: pop
    //   66: aload_3
    //   67: invokevirtual 47	android/os/Parcel:readException	()V
    //   70: aload_3
    //   71: invokevirtual 50	android/os/Parcel:recycle	()V
    //   74: aload_2
    //   75: invokevirtual 50	android/os/Parcel:recycle	()V
    //   78: return
    //   79: iconst_0
    //   80: istore 5
    //   82: aconst_null
    //   83: astore 4
    //   85: aload_2
    //   86: iconst_0
    //   87: invokevirtual 31	android/os/Parcel:writeInt	(I)V
    //   90: goto -47 -> 43
    //   93: astore 4
    //   95: aload_3
    //   96: invokevirtual 50	android/os/Parcel:recycle	()V
    //   99: aload_2
    //   100: invokevirtual 50	android/os/Parcel:recycle	()V
    //   103: aload 4
    //   105: athrow
    // Local variable table:
    //   start	length	slot	name	signature
    //   0	106	0	this	zza
    //   0	106	1	paramAddLocalCapabilityResponse	AddLocalCapabilityResponse
    //   3	97	2	localParcel1	android.os.Parcel
    //   7	89	3	localParcel2	android.os.Parcel
    //   10	74	4	localObject1	Object
    //   93	11	4	localObject2	Object
    //   23	58	5	i	int
    //   51	5	6	j	int
    // Exception table:
    //   from	to	target	type
    //   13	18	93	finally
    //   26	31	93	finally
    //   39	43	93	finally
    //   43	47	93	finally
    //   59	66	93	finally
    //   66	70	93	finally
    //   86	90	93	finally
  }
  
  /* Error */
  public void zza(ChannelReceiveFileResponse paramChannelReceiveFileResponse)
  {
    // Byte code:
    //   0: invokestatic 20	android/os/Parcel:obtain	()Landroid/os/Parcel;
    //   3: astore_2
    //   4: invokestatic 20	android/os/Parcel:obtain	()Landroid/os/Parcel;
    //   7: astore_3
    //   8: ldc 22
    //   10: astore 4
    //   12: aload_2
    //   13: aload 4
    //   15: invokevirtual 26	android/os/Parcel:writeInterfaceToken	(Ljava/lang/String;)V
    //   18: aload_1
    //   19: ifnull +60 -> 79
    //   22: iconst_1
    //   23: istore 5
    //   25: aload_2
    //   26: iload 5
    //   28: invokevirtual 31	android/os/Parcel:writeInt	(I)V
    //   31: iconst_0
    //   32: istore 5
    //   34: aconst_null
    //   35: astore 4
    //   37: aload_1
    //   38: aload_2
    //   39: iconst_0
    //   40: invokevirtual 57	com/google/android/gms/wearable/internal/ChannelReceiveFileResponse:writeToParcel	(Landroid/os/Parcel;I)V
    //   43: aload_0
    //   44: getfield 14	com/google/android/gms/wearable/internal/zzav$zza$zza:zzoz	Landroid/os/IBinder;
    //   47: astore 4
    //   49: bipush 19
    //   51: istore 6
    //   53: aload 4
    //   55: iload 6
    //   57: aload_2
    //   58: aload_3
    //   59: iconst_0
    //   60: invokeinterface 44 5 0
    //   65: pop
    //   66: aload_3
    //   67: invokevirtual 47	android/os/Parcel:readException	()V
    //   70: aload_3
    //   71: invokevirtual 50	android/os/Parcel:recycle	()V
    //   74: aload_2
    //   75: invokevirtual 50	android/os/Parcel:recycle	()V
    //   78: return
    //   79: iconst_0
    //   80: istore 5
    //   82: aconst_null
    //   83: astore 4
    //   85: aload_2
    //   86: iconst_0
    //   87: invokevirtual 31	android/os/Parcel:writeInt	(I)V
    //   90: goto -47 -> 43
    //   93: astore 4
    //   95: aload_3
    //   96: invokevirtual 50	android/os/Parcel:recycle	()V
    //   99: aload_2
    //   100: invokevirtual 50	android/os/Parcel:recycle	()V
    //   103: aload 4
    //   105: athrow
    // Local variable table:
    //   start	length	slot	name	signature
    //   0	106	0	this	zza
    //   0	106	1	paramChannelReceiveFileResponse	ChannelReceiveFileResponse
    //   3	97	2	localParcel1	android.os.Parcel
    //   7	89	3	localParcel2	android.os.Parcel
    //   10	74	4	localObject1	Object
    //   93	11	4	localObject2	Object
    //   23	58	5	i	int
    //   51	5	6	j	int
    // Exception table:
    //   from	to	target	type
    //   13	18	93	finally
    //   26	31	93	finally
    //   39	43	93	finally
    //   43	47	93	finally
    //   59	66	93	finally
    //   66	70	93	finally
    //   86	90	93	finally
  }
  
  /* Error */
  public void zza(ChannelSendFileResponse paramChannelSendFileResponse)
  {
    // Byte code:
    //   0: invokestatic 20	android/os/Parcel:obtain	()Landroid/os/Parcel;
    //   3: astore_2
    //   4: invokestatic 20	android/os/Parcel:obtain	()Landroid/os/Parcel;
    //   7: astore_3
    //   8: ldc 22
    //   10: astore 4
    //   12: aload_2
    //   13: aload 4
    //   15: invokevirtual 26	android/os/Parcel:writeInterfaceToken	(Ljava/lang/String;)V
    //   18: aload_1
    //   19: ifnull +60 -> 79
    //   22: iconst_1
    //   23: istore 5
    //   25: aload_2
    //   26: iload 5
    //   28: invokevirtual 31	android/os/Parcel:writeInt	(I)V
    //   31: iconst_0
    //   32: istore 5
    //   34: aconst_null
    //   35: astore 4
    //   37: aload_1
    //   38: aload_2
    //   39: iconst_0
    //   40: invokevirtual 61	com/google/android/gms/wearable/internal/ChannelSendFileResponse:writeToParcel	(Landroid/os/Parcel;I)V
    //   43: aload_0
    //   44: getfield 14	com/google/android/gms/wearable/internal/zzav$zza$zza:zzoz	Landroid/os/IBinder;
    //   47: astore 4
    //   49: bipush 20
    //   51: istore 6
    //   53: aload 4
    //   55: iload 6
    //   57: aload_2
    //   58: aload_3
    //   59: iconst_0
    //   60: invokeinterface 44 5 0
    //   65: pop
    //   66: aload_3
    //   67: invokevirtual 47	android/os/Parcel:readException	()V
    //   70: aload_3
    //   71: invokevirtual 50	android/os/Parcel:recycle	()V
    //   74: aload_2
    //   75: invokevirtual 50	android/os/Parcel:recycle	()V
    //   78: return
    //   79: iconst_0
    //   80: istore 5
    //   82: aconst_null
    //   83: astore 4
    //   85: aload_2
    //   86: iconst_0
    //   87: invokevirtual 31	android/os/Parcel:writeInt	(I)V
    //   90: goto -47 -> 43
    //   93: astore 4
    //   95: aload_3
    //   96: invokevirtual 50	android/os/Parcel:recycle	()V
    //   99: aload_2
    //   100: invokevirtual 50	android/os/Parcel:recycle	()V
    //   103: aload 4
    //   105: athrow
    // Local variable table:
    //   start	length	slot	name	signature
    //   0	106	0	this	zza
    //   0	106	1	paramChannelSendFileResponse	ChannelSendFileResponse
    //   3	97	2	localParcel1	android.os.Parcel
    //   7	89	3	localParcel2	android.os.Parcel
    //   10	74	4	localObject1	Object
    //   93	11	4	localObject2	Object
    //   23	58	5	i	int
    //   51	5	6	j	int
    // Exception table:
    //   from	to	target	type
    //   13	18	93	finally
    //   26	31	93	finally
    //   39	43	93	finally
    //   43	47	93	finally
    //   59	66	93	finally
    //   66	70	93	finally
    //   86	90	93	finally
  }
  
  /* Error */
  public void zza(CloseChannelResponse paramCloseChannelResponse)
  {
    // Byte code:
    //   0: invokestatic 20	android/os/Parcel:obtain	()Landroid/os/Parcel;
    //   3: astore_2
    //   4: invokestatic 20	android/os/Parcel:obtain	()Landroid/os/Parcel;
    //   7: astore_3
    //   8: ldc 22
    //   10: astore 4
    //   12: aload_2
    //   13: aload 4
    //   15: invokevirtual 26	android/os/Parcel:writeInterfaceToken	(Ljava/lang/String;)V
    //   18: aload_1
    //   19: ifnull +60 -> 79
    //   22: iconst_1
    //   23: istore 5
    //   25: aload_2
    //   26: iload 5
    //   28: invokevirtual 31	android/os/Parcel:writeInt	(I)V
    //   31: iconst_0
    //   32: istore 5
    //   34: aconst_null
    //   35: astore 4
    //   37: aload_1
    //   38: aload_2
    //   39: iconst_0
    //   40: invokevirtual 65	com/google/android/gms/wearable/internal/CloseChannelResponse:writeToParcel	(Landroid/os/Parcel;I)V
    //   43: aload_0
    //   44: getfield 14	com/google/android/gms/wearable/internal/zzav$zza$zza:zzoz	Landroid/os/IBinder;
    //   47: astore 4
    //   49: bipush 15
    //   51: istore 6
    //   53: aload 4
    //   55: iload 6
    //   57: aload_2
    //   58: aload_3
    //   59: iconst_0
    //   60: invokeinterface 44 5 0
    //   65: pop
    //   66: aload_3
    //   67: invokevirtual 47	android/os/Parcel:readException	()V
    //   70: aload_3
    //   71: invokevirtual 50	android/os/Parcel:recycle	()V
    //   74: aload_2
    //   75: invokevirtual 50	android/os/Parcel:recycle	()V
    //   78: return
    //   79: iconst_0
    //   80: istore 5
    //   82: aconst_null
    //   83: astore 4
    //   85: aload_2
    //   86: iconst_0
    //   87: invokevirtual 31	android/os/Parcel:writeInt	(I)V
    //   90: goto -47 -> 43
    //   93: astore 4
    //   95: aload_3
    //   96: invokevirtual 50	android/os/Parcel:recycle	()V
    //   99: aload_2
    //   100: invokevirtual 50	android/os/Parcel:recycle	()V
    //   103: aload 4
    //   105: athrow
    // Local variable table:
    //   start	length	slot	name	signature
    //   0	106	0	this	zza
    //   0	106	1	paramCloseChannelResponse	CloseChannelResponse
    //   3	97	2	localParcel1	android.os.Parcel
    //   7	89	3	localParcel2	android.os.Parcel
    //   10	74	4	localObject1	Object
    //   93	11	4	localObject2	Object
    //   23	58	5	i	int
    //   51	5	6	j	int
    // Exception table:
    //   from	to	target	type
    //   13	18	93	finally
    //   26	31	93	finally
    //   39	43	93	finally
    //   43	47	93	finally
    //   59	66	93	finally
    //   66	70	93	finally
    //   86	90	93	finally
  }
  
  /* Error */
  public void zza(DeleteDataItemsResponse paramDeleteDataItemsResponse)
  {
    // Byte code:
    //   0: invokestatic 20	android/os/Parcel:obtain	()Landroid/os/Parcel;
    //   3: astore_2
    //   4: invokestatic 20	android/os/Parcel:obtain	()Landroid/os/Parcel;
    //   7: astore_3
    //   8: ldc 22
    //   10: astore 4
    //   12: aload_2
    //   13: aload 4
    //   15: invokevirtual 26	android/os/Parcel:writeInterfaceToken	(Ljava/lang/String;)V
    //   18: aload_1
    //   19: ifnull +60 -> 79
    //   22: iconst_1
    //   23: istore 5
    //   25: aload_2
    //   26: iload 5
    //   28: invokevirtual 31	android/os/Parcel:writeInt	(I)V
    //   31: iconst_0
    //   32: istore 5
    //   34: aconst_null
    //   35: astore 4
    //   37: aload_1
    //   38: aload_2
    //   39: iconst_0
    //   40: invokevirtual 69	com/google/android/gms/wearable/internal/DeleteDataItemsResponse:writeToParcel	(Landroid/os/Parcel;I)V
    //   43: aload_0
    //   44: getfield 14	com/google/android/gms/wearable/internal/zzav$zza$zza:zzoz	Landroid/os/IBinder;
    //   47: astore 4
    //   49: bipush 6
    //   51: istore 6
    //   53: aload 4
    //   55: iload 6
    //   57: aload_2
    //   58: aload_3
    //   59: iconst_0
    //   60: invokeinterface 44 5 0
    //   65: pop
    //   66: aload_3
    //   67: invokevirtual 47	android/os/Parcel:readException	()V
    //   70: aload_3
    //   71: invokevirtual 50	android/os/Parcel:recycle	()V
    //   74: aload_2
    //   75: invokevirtual 50	android/os/Parcel:recycle	()V
    //   78: return
    //   79: iconst_0
    //   80: istore 5
    //   82: aconst_null
    //   83: astore 4
    //   85: aload_2
    //   86: iconst_0
    //   87: invokevirtual 31	android/os/Parcel:writeInt	(I)V
    //   90: goto -47 -> 43
    //   93: astore 4
    //   95: aload_3
    //   96: invokevirtual 50	android/os/Parcel:recycle	()V
    //   99: aload_2
    //   100: invokevirtual 50	android/os/Parcel:recycle	()V
    //   103: aload 4
    //   105: athrow
    // Local variable table:
    //   start	length	slot	name	signature
    //   0	106	0	this	zza
    //   0	106	1	paramDeleteDataItemsResponse	DeleteDataItemsResponse
    //   3	97	2	localParcel1	android.os.Parcel
    //   7	89	3	localParcel2	android.os.Parcel
    //   10	74	4	localObject1	Object
    //   93	11	4	localObject2	Object
    //   23	58	5	i	int
    //   51	5	6	j	int
    // Exception table:
    //   from	to	target	type
    //   13	18	93	finally
    //   26	31	93	finally
    //   39	43	93	finally
    //   43	47	93	finally
    //   59	66	93	finally
    //   66	70	93	finally
    //   86	90	93	finally
  }
  
  /* Error */
  public void zza(GetAllCapabilitiesResponse paramGetAllCapabilitiesResponse)
  {
    // Byte code:
    //   0: invokestatic 20	android/os/Parcel:obtain	()Landroid/os/Parcel;
    //   3: astore_2
    //   4: invokestatic 20	android/os/Parcel:obtain	()Landroid/os/Parcel;
    //   7: astore_3
    //   8: ldc 22
    //   10: astore 4
    //   12: aload_2
    //   13: aload 4
    //   15: invokevirtual 26	android/os/Parcel:writeInterfaceToken	(Ljava/lang/String;)V
    //   18: aload_1
    //   19: ifnull +60 -> 79
    //   22: iconst_1
    //   23: istore 5
    //   25: aload_2
    //   26: iload 5
    //   28: invokevirtual 31	android/os/Parcel:writeInt	(I)V
    //   31: iconst_0
    //   32: istore 5
    //   34: aconst_null
    //   35: astore 4
    //   37: aload_1
    //   38: aload_2
    //   39: iconst_0
    //   40: invokevirtual 73	com/google/android/gms/wearable/internal/GetAllCapabilitiesResponse:writeToParcel	(Landroid/os/Parcel;I)V
    //   43: aload_0
    //   44: getfield 14	com/google/android/gms/wearable/internal/zzav$zza$zza:zzoz	Landroid/os/IBinder;
    //   47: astore 4
    //   49: bipush 23
    //   51: istore 6
    //   53: aload 4
    //   55: iload 6
    //   57: aload_2
    //   58: aload_3
    //   59: iconst_0
    //   60: invokeinterface 44 5 0
    //   65: pop
    //   66: aload_3
    //   67: invokevirtual 47	android/os/Parcel:readException	()V
    //   70: aload_3
    //   71: invokevirtual 50	android/os/Parcel:recycle	()V
    //   74: aload_2
    //   75: invokevirtual 50	android/os/Parcel:recycle	()V
    //   78: return
    //   79: iconst_0
    //   80: istore 5
    //   82: aconst_null
    //   83: astore 4
    //   85: aload_2
    //   86: iconst_0
    //   87: invokevirtual 31	android/os/Parcel:writeInt	(I)V
    //   90: goto -47 -> 43
    //   93: astore 4
    //   95: aload_3
    //   96: invokevirtual 50	android/os/Parcel:recycle	()V
    //   99: aload_2
    //   100: invokevirtual 50	android/os/Parcel:recycle	()V
    //   103: aload 4
    //   105: athrow
    // Local variable table:
    //   start	length	slot	name	signature
    //   0	106	0	this	zza
    //   0	106	1	paramGetAllCapabilitiesResponse	GetAllCapabilitiesResponse
    //   3	97	2	localParcel1	android.os.Parcel
    //   7	89	3	localParcel2	android.os.Parcel
    //   10	74	4	localObject1	Object
    //   93	11	4	localObject2	Object
    //   23	58	5	i	int
    //   51	5	6	j	int
    // Exception table:
    //   from	to	target	type
    //   13	18	93	finally
    //   26	31	93	finally
    //   39	43	93	finally
    //   43	47	93	finally
    //   59	66	93	finally
    //   66	70	93	finally
    //   86	90	93	finally
  }
  
  /* Error */
  public void zza(GetCapabilityResponse paramGetCapabilityResponse)
  {
    // Byte code:
    //   0: invokestatic 20	android/os/Parcel:obtain	()Landroid/os/Parcel;
    //   3: astore_2
    //   4: invokestatic 20	android/os/Parcel:obtain	()Landroid/os/Parcel;
    //   7: astore_3
    //   8: ldc 22
    //   10: astore 4
    //   12: aload_2
    //   13: aload 4
    //   15: invokevirtual 26	android/os/Parcel:writeInterfaceToken	(Ljava/lang/String;)V
    //   18: aload_1
    //   19: ifnull +60 -> 79
    //   22: iconst_1
    //   23: istore 5
    //   25: aload_2
    //   26: iload 5
    //   28: invokevirtual 31	android/os/Parcel:writeInt	(I)V
    //   31: iconst_0
    //   32: istore 5
    //   34: aconst_null
    //   35: astore 4
    //   37: aload_1
    //   38: aload_2
    //   39: iconst_0
    //   40: invokevirtual 77	com/google/android/gms/wearable/internal/GetCapabilityResponse:writeToParcel	(Landroid/os/Parcel;I)V
    //   43: aload_0
    //   44: getfield 14	com/google/android/gms/wearable/internal/zzav$zza$zza:zzoz	Landroid/os/IBinder;
    //   47: astore 4
    //   49: bipush 22
    //   51: istore 6
    //   53: aload 4
    //   55: iload 6
    //   57: aload_2
    //   58: aload_3
    //   59: iconst_0
    //   60: invokeinterface 44 5 0
    //   65: pop
    //   66: aload_3
    //   67: invokevirtual 47	android/os/Parcel:readException	()V
    //   70: aload_3
    //   71: invokevirtual 50	android/os/Parcel:recycle	()V
    //   74: aload_2
    //   75: invokevirtual 50	android/os/Parcel:recycle	()V
    //   78: return
    //   79: iconst_0
    //   80: istore 5
    //   82: aconst_null
    //   83: astore 4
    //   85: aload_2
    //   86: iconst_0
    //   87: invokevirtual 31	android/os/Parcel:writeInt	(I)V
    //   90: goto -47 -> 43
    //   93: astore 4
    //   95: aload_3
    //   96: invokevirtual 50	android/os/Parcel:recycle	()V
    //   99: aload_2
    //   100: invokevirtual 50	android/os/Parcel:recycle	()V
    //   103: aload 4
    //   105: athrow
    // Local variable table:
    //   start	length	slot	name	signature
    //   0	106	0	this	zza
    //   0	106	1	paramGetCapabilityResponse	GetCapabilityResponse
    //   3	97	2	localParcel1	android.os.Parcel
    //   7	89	3	localParcel2	android.os.Parcel
    //   10	74	4	localObject1	Object
    //   93	11	4	localObject2	Object
    //   23	58	5	i	int
    //   51	5	6	j	int
    // Exception table:
    //   from	to	target	type
    //   13	18	93	finally
    //   26	31	93	finally
    //   39	43	93	finally
    //   43	47	93	finally
    //   59	66	93	finally
    //   66	70	93	finally
    //   86	90	93	finally
  }
  
  /* Error */
  public void zza(GetChannelInputStreamResponse paramGetChannelInputStreamResponse)
  {
    // Byte code:
    //   0: invokestatic 20	android/os/Parcel:obtain	()Landroid/os/Parcel;
    //   3: astore_2
    //   4: invokestatic 20	android/os/Parcel:obtain	()Landroid/os/Parcel;
    //   7: astore_3
    //   8: ldc 22
    //   10: astore 4
    //   12: aload_2
    //   13: aload 4
    //   15: invokevirtual 26	android/os/Parcel:writeInterfaceToken	(Ljava/lang/String;)V
    //   18: aload_1
    //   19: ifnull +60 -> 79
    //   22: iconst_1
    //   23: istore 5
    //   25: aload_2
    //   26: iload 5
    //   28: invokevirtual 31	android/os/Parcel:writeInt	(I)V
    //   31: iconst_0
    //   32: istore 5
    //   34: aconst_null
    //   35: astore 4
    //   37: aload_1
    //   38: aload_2
    //   39: iconst_0
    //   40: invokevirtual 81	com/google/android/gms/wearable/internal/GetChannelInputStreamResponse:writeToParcel	(Landroid/os/Parcel;I)V
    //   43: aload_0
    //   44: getfield 14	com/google/android/gms/wearable/internal/zzav$zza$zza:zzoz	Landroid/os/IBinder;
    //   47: astore 4
    //   49: bipush 17
    //   51: istore 6
    //   53: aload 4
    //   55: iload 6
    //   57: aload_2
    //   58: aload_3
    //   59: iconst_0
    //   60: invokeinterface 44 5 0
    //   65: pop
    //   66: aload_3
    //   67: invokevirtual 47	android/os/Parcel:readException	()V
    //   70: aload_3
    //   71: invokevirtual 50	android/os/Parcel:recycle	()V
    //   74: aload_2
    //   75: invokevirtual 50	android/os/Parcel:recycle	()V
    //   78: return
    //   79: iconst_0
    //   80: istore 5
    //   82: aconst_null
    //   83: astore 4
    //   85: aload_2
    //   86: iconst_0
    //   87: invokevirtual 31	android/os/Parcel:writeInt	(I)V
    //   90: goto -47 -> 43
    //   93: astore 4
    //   95: aload_3
    //   96: invokevirtual 50	android/os/Parcel:recycle	()V
    //   99: aload_2
    //   100: invokevirtual 50	android/os/Parcel:recycle	()V
    //   103: aload 4
    //   105: athrow
    // Local variable table:
    //   start	length	slot	name	signature
    //   0	106	0	this	zza
    //   0	106	1	paramGetChannelInputStreamResponse	GetChannelInputStreamResponse
    //   3	97	2	localParcel1	android.os.Parcel
    //   7	89	3	localParcel2	android.os.Parcel
    //   10	74	4	localObject1	Object
    //   93	11	4	localObject2	Object
    //   23	58	5	i	int
    //   51	5	6	j	int
    // Exception table:
    //   from	to	target	type
    //   13	18	93	finally
    //   26	31	93	finally
    //   39	43	93	finally
    //   43	47	93	finally
    //   59	66	93	finally
    //   66	70	93	finally
    //   86	90	93	finally
  }
  
  /* Error */
  public void zza(GetChannelOutputStreamResponse paramGetChannelOutputStreamResponse)
  {
    // Byte code:
    //   0: invokestatic 20	android/os/Parcel:obtain	()Landroid/os/Parcel;
    //   3: astore_2
    //   4: invokestatic 20	android/os/Parcel:obtain	()Landroid/os/Parcel;
    //   7: astore_3
    //   8: ldc 22
    //   10: astore 4
    //   12: aload_2
    //   13: aload 4
    //   15: invokevirtual 26	android/os/Parcel:writeInterfaceToken	(Ljava/lang/String;)V
    //   18: aload_1
    //   19: ifnull +60 -> 79
    //   22: iconst_1
    //   23: istore 5
    //   25: aload_2
    //   26: iload 5
    //   28: invokevirtual 31	android/os/Parcel:writeInt	(I)V
    //   31: iconst_0
    //   32: istore 5
    //   34: aconst_null
    //   35: astore 4
    //   37: aload_1
    //   38: aload_2
    //   39: iconst_0
    //   40: invokevirtual 85	com/google/android/gms/wearable/internal/GetChannelOutputStreamResponse:writeToParcel	(Landroid/os/Parcel;I)V
    //   43: aload_0
    //   44: getfield 14	com/google/android/gms/wearable/internal/zzav$zza$zza:zzoz	Landroid/os/IBinder;
    //   47: astore 4
    //   49: bipush 18
    //   51: istore 6
    //   53: aload 4
    //   55: iload 6
    //   57: aload_2
    //   58: aload_3
    //   59: iconst_0
    //   60: invokeinterface 44 5 0
    //   65: pop
    //   66: aload_3
    //   67: invokevirtual 47	android/os/Parcel:readException	()V
    //   70: aload_3
    //   71: invokevirtual 50	android/os/Parcel:recycle	()V
    //   74: aload_2
    //   75: invokevirtual 50	android/os/Parcel:recycle	()V
    //   78: return
    //   79: iconst_0
    //   80: istore 5
    //   82: aconst_null
    //   83: astore 4
    //   85: aload_2
    //   86: iconst_0
    //   87: invokevirtual 31	android/os/Parcel:writeInt	(I)V
    //   90: goto -47 -> 43
    //   93: astore 4
    //   95: aload_3
    //   96: invokevirtual 50	android/os/Parcel:recycle	()V
    //   99: aload_2
    //   100: invokevirtual 50	android/os/Parcel:recycle	()V
    //   103: aload 4
    //   105: athrow
    // Local variable table:
    //   start	length	slot	name	signature
    //   0	106	0	this	zza
    //   0	106	1	paramGetChannelOutputStreamResponse	GetChannelOutputStreamResponse
    //   3	97	2	localParcel1	android.os.Parcel
    //   7	89	3	localParcel2	android.os.Parcel
    //   10	74	4	localObject1	Object
    //   93	11	4	localObject2	Object
    //   23	58	5	i	int
    //   51	5	6	j	int
    // Exception table:
    //   from	to	target	type
    //   13	18	93	finally
    //   26	31	93	finally
    //   39	43	93	finally
    //   43	47	93	finally
    //   59	66	93	finally
    //   66	70	93	finally
    //   86	90	93	finally
  }
  
  /* Error */
  public void zza(GetCloudSyncOptInOutDoneResponse paramGetCloudSyncOptInOutDoneResponse)
  {
    // Byte code:
    //   0: invokestatic 20	android/os/Parcel:obtain	()Landroid/os/Parcel;
    //   3: astore_2
    //   4: invokestatic 20	android/os/Parcel:obtain	()Landroid/os/Parcel;
    //   7: astore_3
    //   8: ldc 22
    //   10: astore 4
    //   12: aload_2
    //   13: aload 4
    //   15: invokevirtual 26	android/os/Parcel:writeInterfaceToken	(Ljava/lang/String;)V
    //   18: aload_1
    //   19: ifnull +60 -> 79
    //   22: iconst_1
    //   23: istore 5
    //   25: aload_2
    //   26: iload 5
    //   28: invokevirtual 31	android/os/Parcel:writeInt	(I)V
    //   31: iconst_0
    //   32: istore 5
    //   34: aconst_null
    //   35: astore 4
    //   37: aload_1
    //   38: aload_2
    //   39: iconst_0
    //   40: invokevirtual 89	com/google/android/gms/wearable/internal/GetCloudSyncOptInOutDoneResponse:writeToParcel	(Landroid/os/Parcel;I)V
    //   43: aload_0
    //   44: getfield 14	com/google/android/gms/wearable/internal/zzav$zza$zza:zzoz	Landroid/os/IBinder;
    //   47: astore 4
    //   49: bipush 28
    //   51: istore 6
    //   53: aload 4
    //   55: iload 6
    //   57: aload_2
    //   58: aload_3
    //   59: iconst_0
    //   60: invokeinterface 44 5 0
    //   65: pop
    //   66: aload_3
    //   67: invokevirtual 47	android/os/Parcel:readException	()V
    //   70: aload_3
    //   71: invokevirtual 50	android/os/Parcel:recycle	()V
    //   74: aload_2
    //   75: invokevirtual 50	android/os/Parcel:recycle	()V
    //   78: return
    //   79: iconst_0
    //   80: istore 5
    //   82: aconst_null
    //   83: astore 4
    //   85: aload_2
    //   86: iconst_0
    //   87: invokevirtual 31	android/os/Parcel:writeInt	(I)V
    //   90: goto -47 -> 43
    //   93: astore 4
    //   95: aload_3
    //   96: invokevirtual 50	android/os/Parcel:recycle	()V
    //   99: aload_2
    //   100: invokevirtual 50	android/os/Parcel:recycle	()V
    //   103: aload 4
    //   105: athrow
    // Local variable table:
    //   start	length	slot	name	signature
    //   0	106	0	this	zza
    //   0	106	1	paramGetCloudSyncOptInOutDoneResponse	GetCloudSyncOptInOutDoneResponse
    //   3	97	2	localParcel1	android.os.Parcel
    //   7	89	3	localParcel2	android.os.Parcel
    //   10	74	4	localObject1	Object
    //   93	11	4	localObject2	Object
    //   23	58	5	i	int
    //   51	5	6	j	int
    // Exception table:
    //   from	to	target	type
    //   13	18	93	finally
    //   26	31	93	finally
    //   39	43	93	finally
    //   43	47	93	finally
    //   59	66	93	finally
    //   66	70	93	finally
    //   86	90	93	finally
  }
  
  /* Error */
  public void zza(GetCloudSyncOptInStatusResponse paramGetCloudSyncOptInStatusResponse)
  {
    // Byte code:
    //   0: invokestatic 20	android/os/Parcel:obtain	()Landroid/os/Parcel;
    //   3: astore_2
    //   4: invokestatic 20	android/os/Parcel:obtain	()Landroid/os/Parcel;
    //   7: astore_3
    //   8: ldc 22
    //   10: astore 4
    //   12: aload_2
    //   13: aload 4
    //   15: invokevirtual 26	android/os/Parcel:writeInterfaceToken	(Ljava/lang/String;)V
    //   18: aload_1
    //   19: ifnull +60 -> 79
    //   22: iconst_1
    //   23: istore 5
    //   25: aload_2
    //   26: iload 5
    //   28: invokevirtual 31	android/os/Parcel:writeInt	(I)V
    //   31: iconst_0
    //   32: istore 5
    //   34: aconst_null
    //   35: astore 4
    //   37: aload_1
    //   38: aload_2
    //   39: iconst_0
    //   40: invokevirtual 93	com/google/android/gms/wearable/internal/GetCloudSyncOptInStatusResponse:writeToParcel	(Landroid/os/Parcel;I)V
    //   43: aload_0
    //   44: getfield 14	com/google/android/gms/wearable/internal/zzav$zza$zza:zzoz	Landroid/os/IBinder;
    //   47: astore 4
    //   49: bipush 30
    //   51: istore 6
    //   53: aload 4
    //   55: iload 6
    //   57: aload_2
    //   58: aload_3
    //   59: iconst_0
    //   60: invokeinterface 44 5 0
    //   65: pop
    //   66: aload_3
    //   67: invokevirtual 47	android/os/Parcel:readException	()V
    //   70: aload_3
    //   71: invokevirtual 50	android/os/Parcel:recycle	()V
    //   74: aload_2
    //   75: invokevirtual 50	android/os/Parcel:recycle	()V
    //   78: return
    //   79: iconst_0
    //   80: istore 5
    //   82: aconst_null
    //   83: astore 4
    //   85: aload_2
    //   86: iconst_0
    //   87: invokevirtual 31	android/os/Parcel:writeInt	(I)V
    //   90: goto -47 -> 43
    //   93: astore 4
    //   95: aload_3
    //   96: invokevirtual 50	android/os/Parcel:recycle	()V
    //   99: aload_2
    //   100: invokevirtual 50	android/os/Parcel:recycle	()V
    //   103: aload 4
    //   105: athrow
    // Local variable table:
    //   start	length	slot	name	signature
    //   0	106	0	this	zza
    //   0	106	1	paramGetCloudSyncOptInStatusResponse	GetCloudSyncOptInStatusResponse
    //   3	97	2	localParcel1	android.os.Parcel
    //   7	89	3	localParcel2	android.os.Parcel
    //   10	74	4	localObject1	Object
    //   93	11	4	localObject2	Object
    //   23	58	5	i	int
    //   51	5	6	j	int
    // Exception table:
    //   from	to	target	type
    //   13	18	93	finally
    //   26	31	93	finally
    //   39	43	93	finally
    //   43	47	93	finally
    //   59	66	93	finally
    //   66	70	93	finally
    //   86	90	93	finally
  }
  
  /* Error */
  public void zza(GetCloudSyncSettingResponse paramGetCloudSyncSettingResponse)
  {
    // Byte code:
    //   0: invokestatic 20	android/os/Parcel:obtain	()Landroid/os/Parcel;
    //   3: astore_2
    //   4: invokestatic 20	android/os/Parcel:obtain	()Landroid/os/Parcel;
    //   7: astore_3
    //   8: ldc 22
    //   10: astore 4
    //   12: aload_2
    //   13: aload 4
    //   15: invokevirtual 26	android/os/Parcel:writeInterfaceToken	(Ljava/lang/String;)V
    //   18: aload_1
    //   19: ifnull +60 -> 79
    //   22: iconst_1
    //   23: istore 5
    //   25: aload_2
    //   26: iload 5
    //   28: invokevirtual 31	android/os/Parcel:writeInt	(I)V
    //   31: iconst_0
    //   32: istore 5
    //   34: aconst_null
    //   35: astore 4
    //   37: aload_1
    //   38: aload_2
    //   39: iconst_0
    //   40: invokevirtual 97	com/google/android/gms/wearable/internal/GetCloudSyncSettingResponse:writeToParcel	(Landroid/os/Parcel;I)V
    //   43: aload_0
    //   44: getfield 14	com/google/android/gms/wearable/internal/zzav$zza$zza:zzoz	Landroid/os/IBinder;
    //   47: astore 4
    //   49: bipush 29
    //   51: istore 6
    //   53: aload 4
    //   55: iload 6
    //   57: aload_2
    //   58: aload_3
    //   59: iconst_0
    //   60: invokeinterface 44 5 0
    //   65: pop
    //   66: aload_3
    //   67: invokevirtual 47	android/os/Parcel:readException	()V
    //   70: aload_3
    //   71: invokevirtual 50	android/os/Parcel:recycle	()V
    //   74: aload_2
    //   75: invokevirtual 50	android/os/Parcel:recycle	()V
    //   78: return
    //   79: iconst_0
    //   80: istore 5
    //   82: aconst_null
    //   83: astore 4
    //   85: aload_2
    //   86: iconst_0
    //   87: invokevirtual 31	android/os/Parcel:writeInt	(I)V
    //   90: goto -47 -> 43
    //   93: astore 4
    //   95: aload_3
    //   96: invokevirtual 50	android/os/Parcel:recycle	()V
    //   99: aload_2
    //   100: invokevirtual 50	android/os/Parcel:recycle	()V
    //   103: aload 4
    //   105: athrow
    // Local variable table:
    //   start	length	slot	name	signature
    //   0	106	0	this	zza
    //   0	106	1	paramGetCloudSyncSettingResponse	GetCloudSyncSettingResponse
    //   3	97	2	localParcel1	android.os.Parcel
    //   7	89	3	localParcel2	android.os.Parcel
    //   10	74	4	localObject1	Object
    //   93	11	4	localObject2	Object
    //   23	58	5	i	int
    //   51	5	6	j	int
    // Exception table:
    //   from	to	target	type
    //   13	18	93	finally
    //   26	31	93	finally
    //   39	43	93	finally
    //   43	47	93	finally
    //   59	66	93	finally
    //   66	70	93	finally
    //   86	90	93	finally
  }
  
  /* Error */
  public void zza(GetConfigResponse paramGetConfigResponse)
  {
    // Byte code:
    //   0: invokestatic 20	android/os/Parcel:obtain	()Landroid/os/Parcel;
    //   3: astore_2
    //   4: invokestatic 20	android/os/Parcel:obtain	()Landroid/os/Parcel;
    //   7: astore_3
    //   8: ldc 22
    //   10: astore 4
    //   12: aload_2
    //   13: aload 4
    //   15: invokevirtual 26	android/os/Parcel:writeInterfaceToken	(Ljava/lang/String;)V
    //   18: aload_1
    //   19: ifnull +59 -> 78
    //   22: iconst_1
    //   23: istore 5
    //   25: aload_2
    //   26: iload 5
    //   28: invokevirtual 31	android/os/Parcel:writeInt	(I)V
    //   31: iconst_0
    //   32: istore 5
    //   34: aconst_null
    //   35: astore 4
    //   37: aload_1
    //   38: aload_2
    //   39: iconst_0
    //   40: invokevirtual 101	com/google/android/gms/wearable/internal/GetConfigResponse:writeToParcel	(Landroid/os/Parcel;I)V
    //   43: aload_0
    //   44: getfield 14	com/google/android/gms/wearable/internal/zzav$zza$zza:zzoz	Landroid/os/IBinder;
    //   47: astore 4
    //   49: iconst_2
    //   50: istore 6
    //   52: aload 4
    //   54: iload 6
    //   56: aload_2
    //   57: aload_3
    //   58: iconst_0
    //   59: invokeinterface 44 5 0
    //   64: pop
    //   65: aload_3
    //   66: invokevirtual 47	android/os/Parcel:readException	()V
    //   69: aload_3
    //   70: invokevirtual 50	android/os/Parcel:recycle	()V
    //   73: aload_2
    //   74: invokevirtual 50	android/os/Parcel:recycle	()V
    //   77: return
    //   78: iconst_0
    //   79: istore 5
    //   81: aconst_null
    //   82: astore 4
    //   84: aload_2
    //   85: iconst_0
    //   86: invokevirtual 31	android/os/Parcel:writeInt	(I)V
    //   89: goto -46 -> 43
    //   92: astore 4
    //   94: aload_3
    //   95: invokevirtual 50	android/os/Parcel:recycle	()V
    //   98: aload_2
    //   99: invokevirtual 50	android/os/Parcel:recycle	()V
    //   102: aload 4
    //   104: athrow
    // Local variable table:
    //   start	length	slot	name	signature
    //   0	105	0	this	zza
    //   0	105	1	paramGetConfigResponse	GetConfigResponse
    //   3	96	2	localParcel1	android.os.Parcel
    //   7	88	3	localParcel2	android.os.Parcel
    //   10	73	4	localObject1	Object
    //   92	11	4	localObject2	Object
    //   23	57	5	i	int
    //   50	5	6	j	int
    // Exception table:
    //   from	to	target	type
    //   13	18	92	finally
    //   26	31	92	finally
    //   39	43	92	finally
    //   43	47	92	finally
    //   58	65	92	finally
    //   65	69	92	finally
    //   85	89	92	finally
  }
  
  /* Error */
  public void zza(GetConfigsResponse paramGetConfigsResponse)
  {
    // Byte code:
    //   0: invokestatic 20	android/os/Parcel:obtain	()Landroid/os/Parcel;
    //   3: astore_2
    //   4: invokestatic 20	android/os/Parcel:obtain	()Landroid/os/Parcel;
    //   7: astore_3
    //   8: ldc 22
    //   10: astore 4
    //   12: aload_2
    //   13: aload 4
    //   15: invokevirtual 26	android/os/Parcel:writeInterfaceToken	(Ljava/lang/String;)V
    //   18: aload_1
    //   19: ifnull +60 -> 79
    //   22: iconst_1
    //   23: istore 5
    //   25: aload_2
    //   26: iload 5
    //   28: invokevirtual 31	android/os/Parcel:writeInt	(I)V
    //   31: iconst_0
    //   32: istore 5
    //   34: aconst_null
    //   35: astore 4
    //   37: aload_1
    //   38: aload_2
    //   39: iconst_0
    //   40: invokevirtual 105	com/google/android/gms/wearable/internal/GetConfigsResponse:writeToParcel	(Landroid/os/Parcel;I)V
    //   43: aload_0
    //   44: getfield 14	com/google/android/gms/wearable/internal/zzav$zza$zza:zzoz	Landroid/os/IBinder;
    //   47: astore 4
    //   49: bipush 13
    //   51: istore 6
    //   53: aload 4
    //   55: iload 6
    //   57: aload_2
    //   58: aload_3
    //   59: iconst_0
    //   60: invokeinterface 44 5 0
    //   65: pop
    //   66: aload_3
    //   67: invokevirtual 47	android/os/Parcel:readException	()V
    //   70: aload_3
    //   71: invokevirtual 50	android/os/Parcel:recycle	()V
    //   74: aload_2
    //   75: invokevirtual 50	android/os/Parcel:recycle	()V
    //   78: return
    //   79: iconst_0
    //   80: istore 5
    //   82: aconst_null
    //   83: astore 4
    //   85: aload_2
    //   86: iconst_0
    //   87: invokevirtual 31	android/os/Parcel:writeInt	(I)V
    //   90: goto -47 -> 43
    //   93: astore 4
    //   95: aload_3
    //   96: invokevirtual 50	android/os/Parcel:recycle	()V
    //   99: aload_2
    //   100: invokevirtual 50	android/os/Parcel:recycle	()V
    //   103: aload 4
    //   105: athrow
    // Local variable table:
    //   start	length	slot	name	signature
    //   0	106	0	this	zza
    //   0	106	1	paramGetConfigsResponse	GetConfigsResponse
    //   3	97	2	localParcel1	android.os.Parcel
    //   7	89	3	localParcel2	android.os.Parcel
    //   10	74	4	localObject1	Object
    //   93	11	4	localObject2	Object
    //   23	58	5	i	int
    //   51	5	6	j	int
    // Exception table:
    //   from	to	target	type
    //   13	18	93	finally
    //   26	31	93	finally
    //   39	43	93	finally
    //   43	47	93	finally
    //   59	66	93	finally
    //   66	70	93	finally
    //   86	90	93	finally
  }
  
  /* Error */
  public void zza(GetConnectedNodesResponse paramGetConnectedNodesResponse)
  {
    // Byte code:
    //   0: invokestatic 20	android/os/Parcel:obtain	()Landroid/os/Parcel;
    //   3: astore_2
    //   4: invokestatic 20	android/os/Parcel:obtain	()Landroid/os/Parcel;
    //   7: astore_3
    //   8: ldc 22
    //   10: astore 4
    //   12: aload_2
    //   13: aload 4
    //   15: invokevirtual 26	android/os/Parcel:writeInterfaceToken	(Ljava/lang/String;)V
    //   18: aload_1
    //   19: ifnull +60 -> 79
    //   22: iconst_1
    //   23: istore 5
    //   25: aload_2
    //   26: iload 5
    //   28: invokevirtual 31	android/os/Parcel:writeInt	(I)V
    //   31: iconst_0
    //   32: istore 5
    //   34: aconst_null
    //   35: astore 4
    //   37: aload_1
    //   38: aload_2
    //   39: iconst_0
    //   40: invokevirtual 109	com/google/android/gms/wearable/internal/GetConnectedNodesResponse:writeToParcel	(Landroid/os/Parcel;I)V
    //   43: aload_0
    //   44: getfield 14	com/google/android/gms/wearable/internal/zzav$zza$zza:zzoz	Landroid/os/IBinder;
    //   47: astore 4
    //   49: bipush 10
    //   51: istore 6
    //   53: aload 4
    //   55: iload 6
    //   57: aload_2
    //   58: aload_3
    //   59: iconst_0
    //   60: invokeinterface 44 5 0
    //   65: pop
    //   66: aload_3
    //   67: invokevirtual 47	android/os/Parcel:readException	()V
    //   70: aload_3
    //   71: invokevirtual 50	android/os/Parcel:recycle	()V
    //   74: aload_2
    //   75: invokevirtual 50	android/os/Parcel:recycle	()V
    //   78: return
    //   79: iconst_0
    //   80: istore 5
    //   82: aconst_null
    //   83: astore 4
    //   85: aload_2
    //   86: iconst_0
    //   87: invokevirtual 31	android/os/Parcel:writeInt	(I)V
    //   90: goto -47 -> 43
    //   93: astore 4
    //   95: aload_3
    //   96: invokevirtual 50	android/os/Parcel:recycle	()V
    //   99: aload_2
    //   100: invokevirtual 50	android/os/Parcel:recycle	()V
    //   103: aload 4
    //   105: athrow
    // Local variable table:
    //   start	length	slot	name	signature
    //   0	106	0	this	zza
    //   0	106	1	paramGetConnectedNodesResponse	GetConnectedNodesResponse
    //   3	97	2	localParcel1	android.os.Parcel
    //   7	89	3	localParcel2	android.os.Parcel
    //   10	74	4	localObject1	Object
    //   93	11	4	localObject2	Object
    //   23	58	5	i	int
    //   51	5	6	j	int
    // Exception table:
    //   from	to	target	type
    //   13	18	93	finally
    //   26	31	93	finally
    //   39	43	93	finally
    //   43	47	93	finally
    //   59	66	93	finally
    //   66	70	93	finally
    //   86	90	93	finally
  }
  
  /* Error */
  public void zza(GetDataItemResponse paramGetDataItemResponse)
  {
    // Byte code:
    //   0: invokestatic 20	android/os/Parcel:obtain	()Landroid/os/Parcel;
    //   3: astore_2
    //   4: invokestatic 20	android/os/Parcel:obtain	()Landroid/os/Parcel;
    //   7: astore_3
    //   8: ldc 22
    //   10: astore 4
    //   12: aload_2
    //   13: aload 4
    //   15: invokevirtual 26	android/os/Parcel:writeInterfaceToken	(Ljava/lang/String;)V
    //   18: aload_1
    //   19: ifnull +59 -> 78
    //   22: iconst_1
    //   23: istore 5
    //   25: aload_2
    //   26: iload 5
    //   28: invokevirtual 31	android/os/Parcel:writeInt	(I)V
    //   31: iconst_0
    //   32: istore 5
    //   34: aconst_null
    //   35: astore 4
    //   37: aload_1
    //   38: aload_2
    //   39: iconst_0
    //   40: invokevirtual 113	com/google/android/gms/wearable/internal/GetDataItemResponse:writeToParcel	(Landroid/os/Parcel;I)V
    //   43: aload_0
    //   44: getfield 14	com/google/android/gms/wearable/internal/zzav$zza$zza:zzoz	Landroid/os/IBinder;
    //   47: astore 4
    //   49: iconst_4
    //   50: istore 6
    //   52: aload 4
    //   54: iload 6
    //   56: aload_2
    //   57: aload_3
    //   58: iconst_0
    //   59: invokeinterface 44 5 0
    //   64: pop
    //   65: aload_3
    //   66: invokevirtual 47	android/os/Parcel:readException	()V
    //   69: aload_3
    //   70: invokevirtual 50	android/os/Parcel:recycle	()V
    //   73: aload_2
    //   74: invokevirtual 50	android/os/Parcel:recycle	()V
    //   77: return
    //   78: iconst_0
    //   79: istore 5
    //   81: aconst_null
    //   82: astore 4
    //   84: aload_2
    //   85: iconst_0
    //   86: invokevirtual 31	android/os/Parcel:writeInt	(I)V
    //   89: goto -46 -> 43
    //   92: astore 4
    //   94: aload_3
    //   95: invokevirtual 50	android/os/Parcel:recycle	()V
    //   98: aload_2
    //   99: invokevirtual 50	android/os/Parcel:recycle	()V
    //   102: aload 4
    //   104: athrow
    // Local variable table:
    //   start	length	slot	name	signature
    //   0	105	0	this	zza
    //   0	105	1	paramGetDataItemResponse	GetDataItemResponse
    //   3	96	2	localParcel1	android.os.Parcel
    //   7	88	3	localParcel2	android.os.Parcel
    //   10	73	4	localObject1	Object
    //   92	11	4	localObject2	Object
    //   23	57	5	i	int
    //   50	5	6	j	int
    // Exception table:
    //   from	to	target	type
    //   13	18	92	finally
    //   26	31	92	finally
    //   39	43	92	finally
    //   43	47	92	finally
    //   58	65	92	finally
    //   65	69	92	finally
    //   85	89	92	finally
  }
  
  /* Error */
  public void zza(GetFdForAssetResponse paramGetFdForAssetResponse)
  {
    // Byte code:
    //   0: invokestatic 20	android/os/Parcel:obtain	()Landroid/os/Parcel;
    //   3: astore_2
    //   4: invokestatic 20	android/os/Parcel:obtain	()Landroid/os/Parcel;
    //   7: astore_3
    //   8: ldc 22
    //   10: astore 4
    //   12: aload_2
    //   13: aload 4
    //   15: invokevirtual 26	android/os/Parcel:writeInterfaceToken	(Ljava/lang/String;)V
    //   18: aload_1
    //   19: ifnull +60 -> 79
    //   22: iconst_1
    //   23: istore 5
    //   25: aload_2
    //   26: iload 5
    //   28: invokevirtual 31	android/os/Parcel:writeInt	(I)V
    //   31: iconst_0
    //   32: istore 5
    //   34: aconst_null
    //   35: astore 4
    //   37: aload_1
    //   38: aload_2
    //   39: iconst_0
    //   40: invokevirtual 117	com/google/android/gms/wearable/internal/GetFdForAssetResponse:writeToParcel	(Landroid/os/Parcel;I)V
    //   43: aload_0
    //   44: getfield 14	com/google/android/gms/wearable/internal/zzav$zza$zza:zzoz	Landroid/os/IBinder;
    //   47: astore 4
    //   49: bipush 8
    //   51: istore 6
    //   53: aload 4
    //   55: iload 6
    //   57: aload_2
    //   58: aload_3
    //   59: iconst_0
    //   60: invokeinterface 44 5 0
    //   65: pop
    //   66: aload_3
    //   67: invokevirtual 47	android/os/Parcel:readException	()V
    //   70: aload_3
    //   71: invokevirtual 50	android/os/Parcel:recycle	()V
    //   74: aload_2
    //   75: invokevirtual 50	android/os/Parcel:recycle	()V
    //   78: return
    //   79: iconst_0
    //   80: istore 5
    //   82: aconst_null
    //   83: astore 4
    //   85: aload_2
    //   86: iconst_0
    //   87: invokevirtual 31	android/os/Parcel:writeInt	(I)V
    //   90: goto -47 -> 43
    //   93: astore 4
    //   95: aload_3
    //   96: invokevirtual 50	android/os/Parcel:recycle	()V
    //   99: aload_2
    //   100: invokevirtual 50	android/os/Parcel:recycle	()V
    //   103: aload 4
    //   105: athrow
    // Local variable table:
    //   start	length	slot	name	signature
    //   0	106	0	this	zza
    //   0	106	1	paramGetFdForAssetResponse	GetFdForAssetResponse
    //   3	97	2	localParcel1	android.os.Parcel
    //   7	89	3	localParcel2	android.os.Parcel
    //   10	74	4	localObject1	Object
    //   93	11	4	localObject2	Object
    //   23	58	5	i	int
    //   51	5	6	j	int
    // Exception table:
    //   from	to	target	type
    //   13	18	93	finally
    //   26	31	93	finally
    //   39	43	93	finally
    //   43	47	93	finally
    //   59	66	93	finally
    //   66	70	93	finally
    //   86	90	93	finally
  }
  
  /* Error */
  public void zza(GetLocalNodeResponse paramGetLocalNodeResponse)
  {
    // Byte code:
    //   0: invokestatic 20	android/os/Parcel:obtain	()Landroid/os/Parcel;
    //   3: astore_2
    //   4: invokestatic 20	android/os/Parcel:obtain	()Landroid/os/Parcel;
    //   7: astore_3
    //   8: ldc 22
    //   10: astore 4
    //   12: aload_2
    //   13: aload 4
    //   15: invokevirtual 26	android/os/Parcel:writeInterfaceToken	(Ljava/lang/String;)V
    //   18: aload_1
    //   19: ifnull +60 -> 79
    //   22: iconst_1
    //   23: istore 5
    //   25: aload_2
    //   26: iload 5
    //   28: invokevirtual 31	android/os/Parcel:writeInt	(I)V
    //   31: iconst_0
    //   32: istore 5
    //   34: aconst_null
    //   35: astore 4
    //   37: aload_1
    //   38: aload_2
    //   39: iconst_0
    //   40: invokevirtual 121	com/google/android/gms/wearable/internal/GetLocalNodeResponse:writeToParcel	(Landroid/os/Parcel;I)V
    //   43: aload_0
    //   44: getfield 14	com/google/android/gms/wearable/internal/zzav$zza$zza:zzoz	Landroid/os/IBinder;
    //   47: astore 4
    //   49: bipush 9
    //   51: istore 6
    //   53: aload 4
    //   55: iload 6
    //   57: aload_2
    //   58: aload_3
    //   59: iconst_0
    //   60: invokeinterface 44 5 0
    //   65: pop
    //   66: aload_3
    //   67: invokevirtual 47	android/os/Parcel:readException	()V
    //   70: aload_3
    //   71: invokevirtual 50	android/os/Parcel:recycle	()V
    //   74: aload_2
    //   75: invokevirtual 50	android/os/Parcel:recycle	()V
    //   78: return
    //   79: iconst_0
    //   80: istore 5
    //   82: aconst_null
    //   83: astore 4
    //   85: aload_2
    //   86: iconst_0
    //   87: invokevirtual 31	android/os/Parcel:writeInt	(I)V
    //   90: goto -47 -> 43
    //   93: astore 4
    //   95: aload_3
    //   96: invokevirtual 50	android/os/Parcel:recycle	()V
    //   99: aload_2
    //   100: invokevirtual 50	android/os/Parcel:recycle	()V
    //   103: aload 4
    //   105: athrow
    // Local variable table:
    //   start	length	slot	name	signature
    //   0	106	0	this	zza
    //   0	106	1	paramGetLocalNodeResponse	GetLocalNodeResponse
    //   3	97	2	localParcel1	android.os.Parcel
    //   7	89	3	localParcel2	android.os.Parcel
    //   10	74	4	localObject1	Object
    //   93	11	4	localObject2	Object
    //   23	58	5	i	int
    //   51	5	6	j	int
    // Exception table:
    //   from	to	target	type
    //   13	18	93	finally
    //   26	31	93	finally
    //   39	43	93	finally
    //   43	47	93	finally
    //   59	66	93	finally
    //   66	70	93	finally
    //   86	90	93	finally
  }
  
  /* Error */
  public void zza(OpenChannelResponse paramOpenChannelResponse)
  {
    // Byte code:
    //   0: invokestatic 20	android/os/Parcel:obtain	()Landroid/os/Parcel;
    //   3: astore_2
    //   4: invokestatic 20	android/os/Parcel:obtain	()Landroid/os/Parcel;
    //   7: astore_3
    //   8: ldc 22
    //   10: astore 4
    //   12: aload_2
    //   13: aload 4
    //   15: invokevirtual 26	android/os/Parcel:writeInterfaceToken	(Ljava/lang/String;)V
    //   18: aload_1
    //   19: ifnull +60 -> 79
    //   22: iconst_1
    //   23: istore 5
    //   25: aload_2
    //   26: iload 5
    //   28: invokevirtual 31	android/os/Parcel:writeInt	(I)V
    //   31: iconst_0
    //   32: istore 5
    //   34: aconst_null
    //   35: astore 4
    //   37: aload_1
    //   38: aload_2
    //   39: iconst_0
    //   40: invokevirtual 125	com/google/android/gms/wearable/internal/OpenChannelResponse:writeToParcel	(Landroid/os/Parcel;I)V
    //   43: aload_0
    //   44: getfield 14	com/google/android/gms/wearable/internal/zzav$zza$zza:zzoz	Landroid/os/IBinder;
    //   47: astore 4
    //   49: bipush 14
    //   51: istore 6
    //   53: aload 4
    //   55: iload 6
    //   57: aload_2
    //   58: aload_3
    //   59: iconst_0
    //   60: invokeinterface 44 5 0
    //   65: pop
    //   66: aload_3
    //   67: invokevirtual 47	android/os/Parcel:readException	()V
    //   70: aload_3
    //   71: invokevirtual 50	android/os/Parcel:recycle	()V
    //   74: aload_2
    //   75: invokevirtual 50	android/os/Parcel:recycle	()V
    //   78: return
    //   79: iconst_0
    //   80: istore 5
    //   82: aconst_null
    //   83: astore 4
    //   85: aload_2
    //   86: iconst_0
    //   87: invokevirtual 31	android/os/Parcel:writeInt	(I)V
    //   90: goto -47 -> 43
    //   93: astore 4
    //   95: aload_3
    //   96: invokevirtual 50	android/os/Parcel:recycle	()V
    //   99: aload_2
    //   100: invokevirtual 50	android/os/Parcel:recycle	()V
    //   103: aload 4
    //   105: athrow
    // Local variable table:
    //   start	length	slot	name	signature
    //   0	106	0	this	zza
    //   0	106	1	paramOpenChannelResponse	OpenChannelResponse
    //   3	97	2	localParcel1	android.os.Parcel
    //   7	89	3	localParcel2	android.os.Parcel
    //   10	74	4	localObject1	Object
    //   93	11	4	localObject2	Object
    //   23	58	5	i	int
    //   51	5	6	j	int
    // Exception table:
    //   from	to	target	type
    //   13	18	93	finally
    //   26	31	93	finally
    //   39	43	93	finally
    //   43	47	93	finally
    //   59	66	93	finally
    //   66	70	93	finally
    //   86	90	93	finally
  }
  
  /* Error */
  public void zza(PutDataResponse paramPutDataResponse)
  {
    // Byte code:
    //   0: invokestatic 20	android/os/Parcel:obtain	()Landroid/os/Parcel;
    //   3: astore_2
    //   4: invokestatic 20	android/os/Parcel:obtain	()Landroid/os/Parcel;
    //   7: astore_3
    //   8: ldc 22
    //   10: astore 4
    //   12: aload_2
    //   13: aload 4
    //   15: invokevirtual 26	android/os/Parcel:writeInterfaceToken	(Ljava/lang/String;)V
    //   18: aload_1
    //   19: ifnull +59 -> 78
    //   22: iconst_1
    //   23: istore 5
    //   25: aload_2
    //   26: iload 5
    //   28: invokevirtual 31	android/os/Parcel:writeInt	(I)V
    //   31: iconst_0
    //   32: istore 5
    //   34: aconst_null
    //   35: astore 4
    //   37: aload_1
    //   38: aload_2
    //   39: iconst_0
    //   40: invokevirtual 129	com/google/android/gms/wearable/internal/PutDataResponse:writeToParcel	(Landroid/os/Parcel;I)V
    //   43: aload_0
    //   44: getfield 14	com/google/android/gms/wearable/internal/zzav$zza$zza:zzoz	Landroid/os/IBinder;
    //   47: astore 4
    //   49: iconst_3
    //   50: istore 6
    //   52: aload 4
    //   54: iload 6
    //   56: aload_2
    //   57: aload_3
    //   58: iconst_0
    //   59: invokeinterface 44 5 0
    //   64: pop
    //   65: aload_3
    //   66: invokevirtual 47	android/os/Parcel:readException	()V
    //   69: aload_3
    //   70: invokevirtual 50	android/os/Parcel:recycle	()V
    //   73: aload_2
    //   74: invokevirtual 50	android/os/Parcel:recycle	()V
    //   77: return
    //   78: iconst_0
    //   79: istore 5
    //   81: aconst_null
    //   82: astore 4
    //   84: aload_2
    //   85: iconst_0
    //   86: invokevirtual 31	android/os/Parcel:writeInt	(I)V
    //   89: goto -46 -> 43
    //   92: astore 4
    //   94: aload_3
    //   95: invokevirtual 50	android/os/Parcel:recycle	()V
    //   98: aload_2
    //   99: invokevirtual 50	android/os/Parcel:recycle	()V
    //   102: aload 4
    //   104: athrow
    // Local variable table:
    //   start	length	slot	name	signature
    //   0	105	0	this	zza
    //   0	105	1	paramPutDataResponse	PutDataResponse
    //   3	96	2	localParcel1	android.os.Parcel
    //   7	88	3	localParcel2	android.os.Parcel
    //   10	73	4	localObject1	Object
    //   92	11	4	localObject2	Object
    //   23	57	5	i	int
    //   50	5	6	j	int
    // Exception table:
    //   from	to	target	type
    //   13	18	92	finally
    //   26	31	92	finally
    //   39	43	92	finally
    //   43	47	92	finally
    //   58	65	92	finally
    //   65	69	92	finally
    //   85	89	92	finally
  }
  
  /* Error */
  public void zza(RemoveLocalCapabilityResponse paramRemoveLocalCapabilityResponse)
  {
    // Byte code:
    //   0: invokestatic 20	android/os/Parcel:obtain	()Landroid/os/Parcel;
    //   3: astore_2
    //   4: invokestatic 20	android/os/Parcel:obtain	()Landroid/os/Parcel;
    //   7: astore_3
    //   8: ldc 22
    //   10: astore 4
    //   12: aload_2
    //   13: aload 4
    //   15: invokevirtual 26	android/os/Parcel:writeInterfaceToken	(Ljava/lang/String;)V
    //   18: aload_1
    //   19: ifnull +60 -> 79
    //   22: iconst_1
    //   23: istore 5
    //   25: aload_2
    //   26: iload 5
    //   28: invokevirtual 31	android/os/Parcel:writeInt	(I)V
    //   31: iconst_0
    //   32: istore 5
    //   34: aconst_null
    //   35: astore 4
    //   37: aload_1
    //   38: aload_2
    //   39: iconst_0
    //   40: invokevirtual 133	com/google/android/gms/wearable/internal/RemoveLocalCapabilityResponse:writeToParcel	(Landroid/os/Parcel;I)V
    //   43: aload_0
    //   44: getfield 14	com/google/android/gms/wearable/internal/zzav$zza$zza:zzoz	Landroid/os/IBinder;
    //   47: astore 4
    //   49: bipush 27
    //   51: istore 6
    //   53: aload 4
    //   55: iload 6
    //   57: aload_2
    //   58: aload_3
    //   59: iconst_0
    //   60: invokeinterface 44 5 0
    //   65: pop
    //   66: aload_3
    //   67: invokevirtual 47	android/os/Parcel:readException	()V
    //   70: aload_3
    //   71: invokevirtual 50	android/os/Parcel:recycle	()V
    //   74: aload_2
    //   75: invokevirtual 50	android/os/Parcel:recycle	()V
    //   78: return
    //   79: iconst_0
    //   80: istore 5
    //   82: aconst_null
    //   83: astore 4
    //   85: aload_2
    //   86: iconst_0
    //   87: invokevirtual 31	android/os/Parcel:writeInt	(I)V
    //   90: goto -47 -> 43
    //   93: astore 4
    //   95: aload_3
    //   96: invokevirtual 50	android/os/Parcel:recycle	()V
    //   99: aload_2
    //   100: invokevirtual 50	android/os/Parcel:recycle	()V
    //   103: aload 4
    //   105: athrow
    // Local variable table:
    //   start	length	slot	name	signature
    //   0	106	0	this	zza
    //   0	106	1	paramRemoveLocalCapabilityResponse	RemoveLocalCapabilityResponse
    //   3	97	2	localParcel1	android.os.Parcel
    //   7	89	3	localParcel2	android.os.Parcel
    //   10	74	4	localObject1	Object
    //   93	11	4	localObject2	Object
    //   23	58	5	i	int
    //   51	5	6	j	int
    // Exception table:
    //   from	to	target	type
    //   13	18	93	finally
    //   26	31	93	finally
    //   39	43	93	finally
    //   43	47	93	finally
    //   59	66	93	finally
    //   66	70	93	finally
    //   86	90	93	finally
  }
  
  /* Error */
  public void zza(SendMessageResponse paramSendMessageResponse)
  {
    // Byte code:
    //   0: invokestatic 20	android/os/Parcel:obtain	()Landroid/os/Parcel;
    //   3: astore_2
    //   4: invokestatic 20	android/os/Parcel:obtain	()Landroid/os/Parcel;
    //   7: astore_3
    //   8: ldc 22
    //   10: astore 4
    //   12: aload_2
    //   13: aload 4
    //   15: invokevirtual 26	android/os/Parcel:writeInterfaceToken	(Ljava/lang/String;)V
    //   18: aload_1
    //   19: ifnull +60 -> 79
    //   22: iconst_1
    //   23: istore 5
    //   25: aload_2
    //   26: iload 5
    //   28: invokevirtual 31	android/os/Parcel:writeInt	(I)V
    //   31: iconst_0
    //   32: istore 5
    //   34: aconst_null
    //   35: astore 4
    //   37: aload_1
    //   38: aload_2
    //   39: iconst_0
    //   40: invokevirtual 137	com/google/android/gms/wearable/internal/SendMessageResponse:writeToParcel	(Landroid/os/Parcel;I)V
    //   43: aload_0
    //   44: getfield 14	com/google/android/gms/wearable/internal/zzav$zza$zza:zzoz	Landroid/os/IBinder;
    //   47: astore 4
    //   49: bipush 7
    //   51: istore 6
    //   53: aload 4
    //   55: iload 6
    //   57: aload_2
    //   58: aload_3
    //   59: iconst_0
    //   60: invokeinterface 44 5 0
    //   65: pop
    //   66: aload_3
    //   67: invokevirtual 47	android/os/Parcel:readException	()V
    //   70: aload_3
    //   71: invokevirtual 50	android/os/Parcel:recycle	()V
    //   74: aload_2
    //   75: invokevirtual 50	android/os/Parcel:recycle	()V
    //   78: return
    //   79: iconst_0
    //   80: istore 5
    //   82: aconst_null
    //   83: astore 4
    //   85: aload_2
    //   86: iconst_0
    //   87: invokevirtual 31	android/os/Parcel:writeInt	(I)V
    //   90: goto -47 -> 43
    //   93: astore 4
    //   95: aload_3
    //   96: invokevirtual 50	android/os/Parcel:recycle	()V
    //   99: aload_2
    //   100: invokevirtual 50	android/os/Parcel:recycle	()V
    //   103: aload 4
    //   105: athrow
    // Local variable table:
    //   start	length	slot	name	signature
    //   0	106	0	this	zza
    //   0	106	1	paramSendMessageResponse	SendMessageResponse
    //   3	97	2	localParcel1	android.os.Parcel
    //   7	89	3	localParcel2	android.os.Parcel
    //   10	74	4	localObject1	Object
    //   93	11	4	localObject2	Object
    //   23	58	5	i	int
    //   51	5	6	j	int
    // Exception table:
    //   from	to	target	type
    //   13	18	93	finally
    //   26	31	93	finally
    //   39	43	93	finally
    //   43	47	93	finally
    //   59	66	93	finally
    //   66	70	93	finally
    //   86	90	93	finally
  }
  
  /* Error */
  public void zza(StorageInfoResponse paramStorageInfoResponse)
  {
    // Byte code:
    //   0: invokestatic 20	android/os/Parcel:obtain	()Landroid/os/Parcel;
    //   3: astore_2
    //   4: invokestatic 20	android/os/Parcel:obtain	()Landroid/os/Parcel;
    //   7: astore_3
    //   8: ldc 22
    //   10: astore 4
    //   12: aload_2
    //   13: aload 4
    //   15: invokevirtual 26	android/os/Parcel:writeInterfaceToken	(Ljava/lang/String;)V
    //   18: aload_1
    //   19: ifnull +60 -> 79
    //   22: iconst_1
    //   23: istore 5
    //   25: aload_2
    //   26: iload 5
    //   28: invokevirtual 31	android/os/Parcel:writeInt	(I)V
    //   31: iconst_0
    //   32: istore 5
    //   34: aconst_null
    //   35: astore 4
    //   37: aload_1
    //   38: aload_2
    //   39: iconst_0
    //   40: invokevirtual 141	com/google/android/gms/wearable/internal/StorageInfoResponse:writeToParcel	(Landroid/os/Parcel;I)V
    //   43: aload_0
    //   44: getfield 14	com/google/android/gms/wearable/internal/zzav$zza$zza:zzoz	Landroid/os/IBinder;
    //   47: astore 4
    //   49: bipush 12
    //   51: istore 6
    //   53: aload 4
    //   55: iload 6
    //   57: aload_2
    //   58: aload_3
    //   59: iconst_0
    //   60: invokeinterface 44 5 0
    //   65: pop
    //   66: aload_3
    //   67: invokevirtual 47	android/os/Parcel:readException	()V
    //   70: aload_3
    //   71: invokevirtual 50	android/os/Parcel:recycle	()V
    //   74: aload_2
    //   75: invokevirtual 50	android/os/Parcel:recycle	()V
    //   78: return
    //   79: iconst_0
    //   80: istore 5
    //   82: aconst_null
    //   83: astore 4
    //   85: aload_2
    //   86: iconst_0
    //   87: invokevirtual 31	android/os/Parcel:writeInt	(I)V
    //   90: goto -47 -> 43
    //   93: astore 4
    //   95: aload_3
    //   96: invokevirtual 50	android/os/Parcel:recycle	()V
    //   99: aload_2
    //   100: invokevirtual 50	android/os/Parcel:recycle	()V
    //   103: aload 4
    //   105: athrow
    // Local variable table:
    //   start	length	slot	name	signature
    //   0	106	0	this	zza
    //   0	106	1	paramStorageInfoResponse	StorageInfoResponse
    //   3	97	2	localParcel1	android.os.Parcel
    //   7	89	3	localParcel2	android.os.Parcel
    //   10	74	4	localObject1	Object
    //   93	11	4	localObject2	Object
    //   23	58	5	i	int
    //   51	5	6	j	int
    // Exception table:
    //   from	to	target	type
    //   13	18	93	finally
    //   26	31	93	finally
    //   39	43	93	finally
    //   43	47	93	finally
    //   59	66	93	finally
    //   66	70	93	finally
    //   86	90	93	finally
  }
  
  /* Error */
  public void zzah(com.google.android.gms.common.data.DataHolder paramDataHolder)
  {
    // Byte code:
    //   0: invokestatic 20	android/os/Parcel:obtain	()Landroid/os/Parcel;
    //   3: astore_2
    //   4: invokestatic 20	android/os/Parcel:obtain	()Landroid/os/Parcel;
    //   7: astore_3
    //   8: ldc 22
    //   10: astore 4
    //   12: aload_2
    //   13: aload 4
    //   15: invokevirtual 26	android/os/Parcel:writeInterfaceToken	(Ljava/lang/String;)V
    //   18: aload_1
    //   19: ifnull +59 -> 78
    //   22: iconst_1
    //   23: istore 5
    //   25: aload_2
    //   26: iload 5
    //   28: invokevirtual 31	android/os/Parcel:writeInt	(I)V
    //   31: iconst_0
    //   32: istore 5
    //   34: aconst_null
    //   35: astore 4
    //   37: aload_1
    //   38: aload_2
    //   39: iconst_0
    //   40: invokevirtual 145	com/google/android/gms/common/data/DataHolder:writeToParcel	(Landroid/os/Parcel;I)V
    //   43: aload_0
    //   44: getfield 14	com/google/android/gms/wearable/internal/zzav$zza$zza:zzoz	Landroid/os/IBinder;
    //   47: astore 4
    //   49: iconst_5
    //   50: istore 6
    //   52: aload 4
    //   54: iload 6
    //   56: aload_2
    //   57: aload_3
    //   58: iconst_0
    //   59: invokeinterface 44 5 0
    //   64: pop
    //   65: aload_3
    //   66: invokevirtual 47	android/os/Parcel:readException	()V
    //   69: aload_3
    //   70: invokevirtual 50	android/os/Parcel:recycle	()V
    //   73: aload_2
    //   74: invokevirtual 50	android/os/Parcel:recycle	()V
    //   77: return
    //   78: iconst_0
    //   79: istore 5
    //   81: aconst_null
    //   82: astore 4
    //   84: aload_2
    //   85: iconst_0
    //   86: invokevirtual 31	android/os/Parcel:writeInt	(I)V
    //   89: goto -46 -> 43
    //   92: astore 4
    //   94: aload_3
    //   95: invokevirtual 50	android/os/Parcel:recycle	()V
    //   98: aload_2
    //   99: invokevirtual 50	android/os/Parcel:recycle	()V
    //   102: aload 4
    //   104: athrow
    // Local variable table:
    //   start	length	slot	name	signature
    //   0	105	0	this	zza
    //   0	105	1	paramDataHolder	com.google.android.gms.common.data.DataHolder
    //   3	96	2	localParcel1	android.os.Parcel
    //   7	88	3	localParcel2	android.os.Parcel
    //   10	73	4	localObject1	Object
    //   92	11	4	localObject2	Object
    //   23	57	5	i	int
    //   50	5	6	j	int
    // Exception table:
    //   from	to	target	type
    //   13	18	92	finally
    //   26	31	92	finally
    //   39	43	92	finally
    //   43	47	92	finally
    //   58	65	92	finally
    //   65	69	92	finally
    //   85	89	92	finally
  }
  
  /* Error */
  public void zzb(CloseChannelResponse paramCloseChannelResponse)
  {
    // Byte code:
    //   0: invokestatic 20	android/os/Parcel:obtain	()Landroid/os/Parcel;
    //   3: astore_2
    //   4: invokestatic 20	android/os/Parcel:obtain	()Landroid/os/Parcel;
    //   7: astore_3
    //   8: ldc 22
    //   10: astore 4
    //   12: aload_2
    //   13: aload 4
    //   15: invokevirtual 26	android/os/Parcel:writeInterfaceToken	(Ljava/lang/String;)V
    //   18: aload_1
    //   19: ifnull +60 -> 79
    //   22: iconst_1
    //   23: istore 5
    //   25: aload_2
    //   26: iload 5
    //   28: invokevirtual 31	android/os/Parcel:writeInt	(I)V
    //   31: iconst_0
    //   32: istore 5
    //   34: aconst_null
    //   35: astore 4
    //   37: aload_1
    //   38: aload_2
    //   39: iconst_0
    //   40: invokevirtual 65	com/google/android/gms/wearable/internal/CloseChannelResponse:writeToParcel	(Landroid/os/Parcel;I)V
    //   43: aload_0
    //   44: getfield 14	com/google/android/gms/wearable/internal/zzav$zza$zza:zzoz	Landroid/os/IBinder;
    //   47: astore 4
    //   49: bipush 16
    //   51: istore 6
    //   53: aload 4
    //   55: iload 6
    //   57: aload_2
    //   58: aload_3
    //   59: iconst_0
    //   60: invokeinterface 44 5 0
    //   65: pop
    //   66: aload_3
    //   67: invokevirtual 47	android/os/Parcel:readException	()V
    //   70: aload_3
    //   71: invokevirtual 50	android/os/Parcel:recycle	()V
    //   74: aload_2
    //   75: invokevirtual 50	android/os/Parcel:recycle	()V
    //   78: return
    //   79: iconst_0
    //   80: istore 5
    //   82: aconst_null
    //   83: astore 4
    //   85: aload_2
    //   86: iconst_0
    //   87: invokevirtual 31	android/os/Parcel:writeInt	(I)V
    //   90: goto -47 -> 43
    //   93: astore 4
    //   95: aload_3
    //   96: invokevirtual 50	android/os/Parcel:recycle	()V
    //   99: aload_2
    //   100: invokevirtual 50	android/os/Parcel:recycle	()V
    //   103: aload 4
    //   105: athrow
    // Local variable table:
    //   start	length	slot	name	signature
    //   0	106	0	this	zza
    //   0	106	1	paramCloseChannelResponse	CloseChannelResponse
    //   3	97	2	localParcel1	android.os.Parcel
    //   7	89	3	localParcel2	android.os.Parcel
    //   10	74	4	localObject1	Object
    //   93	11	4	localObject2	Object
    //   23	58	5	i	int
    //   51	5	6	j	int
    // Exception table:
    //   from	to	target	type
    //   13	18	93	finally
    //   26	31	93	finally
    //   39	43	93	finally
    //   43	47	93	finally
    //   59	66	93	finally
    //   66	70	93	finally
    //   86	90	93	finally
  }
}


/* Location:              C:\Users\haryo\Desktop\enjarify-master\presensi-enjarify.jar!\com\google\android\gms\wearable\internal\zzav$zza$zza.class
 * Java compiler version: 5 (49.0)
 * JD-Core Version:       0.7.1
 */