package com.google.android.gms.wearable.internal;

import android.os.IBinder;
import android.os.Parcel;
import java.util.List;

class zzaw$zza$zza
  implements zzaw
{
  private IBinder zzoz;
  
  zzaw$zza$zza(IBinder paramIBinder)
  {
    this.zzoz = paramIBinder;
  }
  
  public IBinder asBinder()
  {
    return this.zzoz;
  }
  
  public void onConnectedNodes(List paramList)
  {
    Parcel localParcel = Parcel.obtain();
    Object localObject1 = "com.google.android.gms.wearable.internal.IWearableListener";
    try
    {
      localParcel.writeInterfaceToken((String)localObject1);
      localParcel.writeTypedList(paramList);
      localObject1 = this.zzoz;
      int i = 5;
      int j = 1;
      ((IBinder)localObject1).transact(i, localParcel, null, j);
      return;
    }
    finally
    {
      localParcel.recycle();
    }
  }
  
  /* Error */
  public void zza(AmsEntityUpdateParcelable paramAmsEntityUpdateParcelable)
  {
    // Byte code:
    //   0: invokestatic 20	android/os/Parcel:obtain	()Landroid/os/Parcel;
    //   3: astore_2
    //   4: ldc 22
    //   6: astore_3
    //   7: aload_2
    //   8: aload_3
    //   9: invokevirtual 26	android/os/Parcel:writeInterfaceToken	(Ljava/lang/String;)V
    //   12: aload_1
    //   13: ifnull +53 -> 66
    //   16: iconst_1
    //   17: istore 4
    //   19: aload_2
    //   20: iload 4
    //   22: invokevirtual 45	android/os/Parcel:writeInt	(I)V
    //   25: iconst_0
    //   26: istore 4
    //   28: aconst_null
    //   29: astore_3
    //   30: aload_1
    //   31: aload_2
    //   32: iconst_0
    //   33: invokevirtual 51	com/google/android/gms/wearable/internal/AmsEntityUpdateParcelable:writeToParcel	(Landroid/os/Parcel;I)V
    //   36: aload_0
    //   37: getfield 14	com/google/android/gms/wearable/internal/zzaw$zza$zza:zzoz	Landroid/os/IBinder;
    //   40: astore_3
    //   41: bipush 9
    //   43: istore 5
    //   45: iconst_1
    //   46: istore 6
    //   48: aload_3
    //   49: iload 5
    //   51: aload_2
    //   52: aconst_null
    //   53: iload 6
    //   55: invokeinterface 38 5 0
    //   60: pop
    //   61: aload_2
    //   62: invokevirtual 41	android/os/Parcel:recycle	()V
    //   65: return
    //   66: iconst_0
    //   67: istore 4
    //   69: aconst_null
    //   70: astore_3
    //   71: aload_2
    //   72: iconst_0
    //   73: invokevirtual 45	android/os/Parcel:writeInt	(I)V
    //   76: goto -40 -> 36
    //   79: astore_3
    //   80: aload_2
    //   81: invokevirtual 41	android/os/Parcel:recycle	()V
    //   84: aload_3
    //   85: athrow
    // Local variable table:
    //   start	length	slot	name	signature
    //   0	86	0	this	zza
    //   0	86	1	paramAmsEntityUpdateParcelable	AmsEntityUpdateParcelable
    //   3	78	2	localParcel	Parcel
    //   6	65	3	localObject1	Object
    //   79	6	3	localObject2	Object
    //   17	51	4	i	int
    //   43	7	5	j	int
    //   46	8	6	k	int
    // Exception table:
    //   from	to	target	type
    //   8	12	79	finally
    //   20	25	79	finally
    //   32	36	79	finally
    //   36	40	79	finally
    //   53	61	79	finally
    //   72	76	79	finally
  }
  
  /* Error */
  public void zza(AncsNotificationParcelable paramAncsNotificationParcelable)
  {
    // Byte code:
    //   0: invokestatic 20	android/os/Parcel:obtain	()Landroid/os/Parcel;
    //   3: astore_2
    //   4: ldc 22
    //   6: astore_3
    //   7: aload_2
    //   8: aload_3
    //   9: invokevirtual 26	android/os/Parcel:writeInterfaceToken	(Ljava/lang/String;)V
    //   12: aload_1
    //   13: ifnull +53 -> 66
    //   16: iconst_1
    //   17: istore 4
    //   19: aload_2
    //   20: iload 4
    //   22: invokevirtual 45	android/os/Parcel:writeInt	(I)V
    //   25: iconst_0
    //   26: istore 4
    //   28: aconst_null
    //   29: astore_3
    //   30: aload_1
    //   31: aload_2
    //   32: iconst_0
    //   33: invokevirtual 55	com/google/android/gms/wearable/internal/AncsNotificationParcelable:writeToParcel	(Landroid/os/Parcel;I)V
    //   36: aload_0
    //   37: getfield 14	com/google/android/gms/wearable/internal/zzaw$zza$zza:zzoz	Landroid/os/IBinder;
    //   40: astore_3
    //   41: bipush 6
    //   43: istore 5
    //   45: iconst_1
    //   46: istore 6
    //   48: aload_3
    //   49: iload 5
    //   51: aload_2
    //   52: aconst_null
    //   53: iload 6
    //   55: invokeinterface 38 5 0
    //   60: pop
    //   61: aload_2
    //   62: invokevirtual 41	android/os/Parcel:recycle	()V
    //   65: return
    //   66: iconst_0
    //   67: istore 4
    //   69: aconst_null
    //   70: astore_3
    //   71: aload_2
    //   72: iconst_0
    //   73: invokevirtual 45	android/os/Parcel:writeInt	(I)V
    //   76: goto -40 -> 36
    //   79: astore_3
    //   80: aload_2
    //   81: invokevirtual 41	android/os/Parcel:recycle	()V
    //   84: aload_3
    //   85: athrow
    // Local variable table:
    //   start	length	slot	name	signature
    //   0	86	0	this	zza
    //   0	86	1	paramAncsNotificationParcelable	AncsNotificationParcelable
    //   3	78	2	localParcel	Parcel
    //   6	65	3	localObject1	Object
    //   79	6	3	localObject2	Object
    //   17	51	4	i	int
    //   43	7	5	j	int
    //   46	8	6	k	int
    // Exception table:
    //   from	to	target	type
    //   8	12	79	finally
    //   20	25	79	finally
    //   32	36	79	finally
    //   36	40	79	finally
    //   53	61	79	finally
    //   72	76	79	finally
  }
  
  /* Error */
  public void zza(CapabilityInfoParcelable paramCapabilityInfoParcelable)
  {
    // Byte code:
    //   0: invokestatic 20	android/os/Parcel:obtain	()Landroid/os/Parcel;
    //   3: astore_2
    //   4: ldc 22
    //   6: astore_3
    //   7: aload_2
    //   8: aload_3
    //   9: invokevirtual 26	android/os/Parcel:writeInterfaceToken	(Ljava/lang/String;)V
    //   12: aload_1
    //   13: ifnull +53 -> 66
    //   16: iconst_1
    //   17: istore 4
    //   19: aload_2
    //   20: iload 4
    //   22: invokevirtual 45	android/os/Parcel:writeInt	(I)V
    //   25: iconst_0
    //   26: istore 4
    //   28: aconst_null
    //   29: astore_3
    //   30: aload_1
    //   31: aload_2
    //   32: iconst_0
    //   33: invokevirtual 59	com/google/android/gms/wearable/internal/CapabilityInfoParcelable:writeToParcel	(Landroid/os/Parcel;I)V
    //   36: aload_0
    //   37: getfield 14	com/google/android/gms/wearable/internal/zzaw$zza$zza:zzoz	Landroid/os/IBinder;
    //   40: astore_3
    //   41: bipush 8
    //   43: istore 5
    //   45: iconst_1
    //   46: istore 6
    //   48: aload_3
    //   49: iload 5
    //   51: aload_2
    //   52: aconst_null
    //   53: iload 6
    //   55: invokeinterface 38 5 0
    //   60: pop
    //   61: aload_2
    //   62: invokevirtual 41	android/os/Parcel:recycle	()V
    //   65: return
    //   66: iconst_0
    //   67: istore 4
    //   69: aconst_null
    //   70: astore_3
    //   71: aload_2
    //   72: iconst_0
    //   73: invokevirtual 45	android/os/Parcel:writeInt	(I)V
    //   76: goto -40 -> 36
    //   79: astore_3
    //   80: aload_2
    //   81: invokevirtual 41	android/os/Parcel:recycle	()V
    //   84: aload_3
    //   85: athrow
    // Local variable table:
    //   start	length	slot	name	signature
    //   0	86	0	this	zza
    //   0	86	1	paramCapabilityInfoParcelable	CapabilityInfoParcelable
    //   3	78	2	localParcel	Parcel
    //   6	65	3	localObject1	Object
    //   79	6	3	localObject2	Object
    //   17	51	4	i	int
    //   43	7	5	j	int
    //   46	8	6	k	int
    // Exception table:
    //   from	to	target	type
    //   8	12	79	finally
    //   20	25	79	finally
    //   32	36	79	finally
    //   36	40	79	finally
    //   53	61	79	finally
    //   72	76	79	finally
  }
  
  /* Error */
  public void zza(ChannelEventParcelable paramChannelEventParcelable)
  {
    // Byte code:
    //   0: invokestatic 20	android/os/Parcel:obtain	()Landroid/os/Parcel;
    //   3: astore_2
    //   4: ldc 22
    //   6: astore_3
    //   7: aload_2
    //   8: aload_3
    //   9: invokevirtual 26	android/os/Parcel:writeInterfaceToken	(Ljava/lang/String;)V
    //   12: aload_1
    //   13: ifnull +53 -> 66
    //   16: iconst_1
    //   17: istore 4
    //   19: aload_2
    //   20: iload 4
    //   22: invokevirtual 45	android/os/Parcel:writeInt	(I)V
    //   25: iconst_0
    //   26: istore 4
    //   28: aconst_null
    //   29: astore_3
    //   30: aload_1
    //   31: aload_2
    //   32: iconst_0
    //   33: invokevirtual 63	com/google/android/gms/wearable/internal/ChannelEventParcelable:writeToParcel	(Landroid/os/Parcel;I)V
    //   36: aload_0
    //   37: getfield 14	com/google/android/gms/wearable/internal/zzaw$zza$zza:zzoz	Landroid/os/IBinder;
    //   40: astore_3
    //   41: bipush 7
    //   43: istore 5
    //   45: iconst_1
    //   46: istore 6
    //   48: aload_3
    //   49: iload 5
    //   51: aload_2
    //   52: aconst_null
    //   53: iload 6
    //   55: invokeinterface 38 5 0
    //   60: pop
    //   61: aload_2
    //   62: invokevirtual 41	android/os/Parcel:recycle	()V
    //   65: return
    //   66: iconst_0
    //   67: istore 4
    //   69: aconst_null
    //   70: astore_3
    //   71: aload_2
    //   72: iconst_0
    //   73: invokevirtual 45	android/os/Parcel:writeInt	(I)V
    //   76: goto -40 -> 36
    //   79: astore_3
    //   80: aload_2
    //   81: invokevirtual 41	android/os/Parcel:recycle	()V
    //   84: aload_3
    //   85: athrow
    // Local variable table:
    //   start	length	slot	name	signature
    //   0	86	0	this	zza
    //   0	86	1	paramChannelEventParcelable	ChannelEventParcelable
    //   3	78	2	localParcel	Parcel
    //   6	65	3	localObject1	Object
    //   79	6	3	localObject2	Object
    //   17	51	4	i	int
    //   43	7	5	j	int
    //   46	8	6	k	int
    // Exception table:
    //   from	to	target	type
    //   8	12	79	finally
    //   20	25	79	finally
    //   32	36	79	finally
    //   36	40	79	finally
    //   53	61	79	finally
    //   72	76	79	finally
  }
  
  /* Error */
  public void zza(MessageEventParcelable paramMessageEventParcelable)
  {
    // Byte code:
    //   0: invokestatic 20	android/os/Parcel:obtain	()Landroid/os/Parcel;
    //   3: astore_2
    //   4: ldc 22
    //   6: astore_3
    //   7: aload_2
    //   8: aload_3
    //   9: invokevirtual 26	android/os/Parcel:writeInterfaceToken	(Ljava/lang/String;)V
    //   12: aload_1
    //   13: ifnull +52 -> 65
    //   16: iconst_1
    //   17: istore 4
    //   19: aload_2
    //   20: iload 4
    //   22: invokevirtual 45	android/os/Parcel:writeInt	(I)V
    //   25: iconst_0
    //   26: istore 4
    //   28: aconst_null
    //   29: astore_3
    //   30: aload_1
    //   31: aload_2
    //   32: iconst_0
    //   33: invokevirtual 67	com/google/android/gms/wearable/internal/MessageEventParcelable:writeToParcel	(Landroid/os/Parcel;I)V
    //   36: aload_0
    //   37: getfield 14	com/google/android/gms/wearable/internal/zzaw$zza$zza:zzoz	Landroid/os/IBinder;
    //   40: astore_3
    //   41: iconst_2
    //   42: istore 5
    //   44: iconst_1
    //   45: istore 6
    //   47: aload_3
    //   48: iload 5
    //   50: aload_2
    //   51: aconst_null
    //   52: iload 6
    //   54: invokeinterface 38 5 0
    //   59: pop
    //   60: aload_2
    //   61: invokevirtual 41	android/os/Parcel:recycle	()V
    //   64: return
    //   65: iconst_0
    //   66: istore 4
    //   68: aconst_null
    //   69: astore_3
    //   70: aload_2
    //   71: iconst_0
    //   72: invokevirtual 45	android/os/Parcel:writeInt	(I)V
    //   75: goto -39 -> 36
    //   78: astore_3
    //   79: aload_2
    //   80: invokevirtual 41	android/os/Parcel:recycle	()V
    //   83: aload_3
    //   84: athrow
    // Local variable table:
    //   start	length	slot	name	signature
    //   0	85	0	this	zza
    //   0	85	1	paramMessageEventParcelable	MessageEventParcelable
    //   3	77	2	localParcel	Parcel
    //   6	64	3	localObject1	Object
    //   78	6	3	localObject2	Object
    //   17	50	4	i	int
    //   42	7	5	j	int
    //   45	8	6	k	int
    // Exception table:
    //   from	to	target	type
    //   8	12	78	finally
    //   20	25	78	finally
    //   32	36	78	finally
    //   36	40	78	finally
    //   52	60	78	finally
    //   71	75	78	finally
  }
  
  /* Error */
  public void zza(NodeParcelable paramNodeParcelable)
  {
    // Byte code:
    //   0: invokestatic 20	android/os/Parcel:obtain	()Landroid/os/Parcel;
    //   3: astore_2
    //   4: ldc 22
    //   6: astore_3
    //   7: aload_2
    //   8: aload_3
    //   9: invokevirtual 26	android/os/Parcel:writeInterfaceToken	(Ljava/lang/String;)V
    //   12: aload_1
    //   13: ifnull +52 -> 65
    //   16: iconst_1
    //   17: istore 4
    //   19: aload_2
    //   20: iload 4
    //   22: invokevirtual 45	android/os/Parcel:writeInt	(I)V
    //   25: iconst_0
    //   26: istore 4
    //   28: aconst_null
    //   29: astore_3
    //   30: aload_1
    //   31: aload_2
    //   32: iconst_0
    //   33: invokevirtual 71	com/google/android/gms/wearable/internal/NodeParcelable:writeToParcel	(Landroid/os/Parcel;I)V
    //   36: aload_0
    //   37: getfield 14	com/google/android/gms/wearable/internal/zzaw$zza$zza:zzoz	Landroid/os/IBinder;
    //   40: astore_3
    //   41: iconst_3
    //   42: istore 5
    //   44: iconst_1
    //   45: istore 6
    //   47: aload_3
    //   48: iload 5
    //   50: aload_2
    //   51: aconst_null
    //   52: iload 6
    //   54: invokeinterface 38 5 0
    //   59: pop
    //   60: aload_2
    //   61: invokevirtual 41	android/os/Parcel:recycle	()V
    //   64: return
    //   65: iconst_0
    //   66: istore 4
    //   68: aconst_null
    //   69: astore_3
    //   70: aload_2
    //   71: iconst_0
    //   72: invokevirtual 45	android/os/Parcel:writeInt	(I)V
    //   75: goto -39 -> 36
    //   78: astore_3
    //   79: aload_2
    //   80: invokevirtual 41	android/os/Parcel:recycle	()V
    //   83: aload_3
    //   84: athrow
    // Local variable table:
    //   start	length	slot	name	signature
    //   0	85	0	this	zza
    //   0	85	1	paramNodeParcelable	NodeParcelable
    //   3	77	2	localParcel	Parcel
    //   6	64	3	localObject1	Object
    //   78	6	3	localObject2	Object
    //   17	50	4	i	int
    //   42	7	5	j	int
    //   45	8	6	k	int
    // Exception table:
    //   from	to	target	type
    //   8	12	78	finally
    //   20	25	78	finally
    //   32	36	78	finally
    //   36	40	78	finally
    //   52	60	78	finally
    //   71	75	78	finally
  }
  
  /* Error */
  public void zzag(com.google.android.gms.common.data.DataHolder paramDataHolder)
  {
    // Byte code:
    //   0: invokestatic 20	android/os/Parcel:obtain	()Landroid/os/Parcel;
    //   3: astore_2
    //   4: ldc 22
    //   6: astore_3
    //   7: aload_2
    //   8: aload_3
    //   9: invokevirtual 26	android/os/Parcel:writeInterfaceToken	(Ljava/lang/String;)V
    //   12: aload_1
    //   13: ifnull +52 -> 65
    //   16: iconst_1
    //   17: istore 4
    //   19: aload_2
    //   20: iload 4
    //   22: invokevirtual 45	android/os/Parcel:writeInt	(I)V
    //   25: iconst_0
    //   26: istore 4
    //   28: aconst_null
    //   29: astore_3
    //   30: aload_1
    //   31: aload_2
    //   32: iconst_0
    //   33: invokevirtual 75	com/google/android/gms/common/data/DataHolder:writeToParcel	(Landroid/os/Parcel;I)V
    //   36: aload_0
    //   37: getfield 14	com/google/android/gms/wearable/internal/zzaw$zza$zza:zzoz	Landroid/os/IBinder;
    //   40: astore_3
    //   41: iconst_1
    //   42: istore 5
    //   44: iconst_1
    //   45: istore 6
    //   47: aload_3
    //   48: iload 5
    //   50: aload_2
    //   51: aconst_null
    //   52: iload 6
    //   54: invokeinterface 38 5 0
    //   59: pop
    //   60: aload_2
    //   61: invokevirtual 41	android/os/Parcel:recycle	()V
    //   64: return
    //   65: iconst_0
    //   66: istore 4
    //   68: aconst_null
    //   69: astore_3
    //   70: aload_2
    //   71: iconst_0
    //   72: invokevirtual 45	android/os/Parcel:writeInt	(I)V
    //   75: goto -39 -> 36
    //   78: astore_3
    //   79: aload_2
    //   80: invokevirtual 41	android/os/Parcel:recycle	()V
    //   83: aload_3
    //   84: athrow
    // Local variable table:
    //   start	length	slot	name	signature
    //   0	85	0	this	zza
    //   0	85	1	paramDataHolder	com.google.android.gms.common.data.DataHolder
    //   3	77	2	localParcel	Parcel
    //   6	64	3	localObject1	Object
    //   78	6	3	localObject2	Object
    //   17	50	4	i	int
    //   42	7	5	j	int
    //   45	8	6	k	int
    // Exception table:
    //   from	to	target	type
    //   8	12	78	finally
    //   20	25	78	finally
    //   32	36	78	finally
    //   36	40	78	finally
    //   52	60	78	finally
    //   71	75	78	finally
  }
  
  /* Error */
  public void zzb(NodeParcelable paramNodeParcelable)
  {
    // Byte code:
    //   0: invokestatic 20	android/os/Parcel:obtain	()Landroid/os/Parcel;
    //   3: astore_2
    //   4: ldc 22
    //   6: astore_3
    //   7: aload_2
    //   8: aload_3
    //   9: invokevirtual 26	android/os/Parcel:writeInterfaceToken	(Ljava/lang/String;)V
    //   12: aload_1
    //   13: ifnull +52 -> 65
    //   16: iconst_1
    //   17: istore 4
    //   19: aload_2
    //   20: iload 4
    //   22: invokevirtual 45	android/os/Parcel:writeInt	(I)V
    //   25: iconst_0
    //   26: istore 4
    //   28: aconst_null
    //   29: astore_3
    //   30: aload_1
    //   31: aload_2
    //   32: iconst_0
    //   33: invokevirtual 71	com/google/android/gms/wearable/internal/NodeParcelable:writeToParcel	(Landroid/os/Parcel;I)V
    //   36: aload_0
    //   37: getfield 14	com/google/android/gms/wearable/internal/zzaw$zza$zza:zzoz	Landroid/os/IBinder;
    //   40: astore_3
    //   41: iconst_4
    //   42: istore 5
    //   44: iconst_1
    //   45: istore 6
    //   47: aload_3
    //   48: iload 5
    //   50: aload_2
    //   51: aconst_null
    //   52: iload 6
    //   54: invokeinterface 38 5 0
    //   59: pop
    //   60: aload_2
    //   61: invokevirtual 41	android/os/Parcel:recycle	()V
    //   64: return
    //   65: iconst_0
    //   66: istore 4
    //   68: aconst_null
    //   69: astore_3
    //   70: aload_2
    //   71: iconst_0
    //   72: invokevirtual 45	android/os/Parcel:writeInt	(I)V
    //   75: goto -39 -> 36
    //   78: astore_3
    //   79: aload_2
    //   80: invokevirtual 41	android/os/Parcel:recycle	()V
    //   83: aload_3
    //   84: athrow
    // Local variable table:
    //   start	length	slot	name	signature
    //   0	85	0	this	zza
    //   0	85	1	paramNodeParcelable	NodeParcelable
    //   3	77	2	localParcel	Parcel
    //   6	64	3	localObject1	Object
    //   78	6	3	localObject2	Object
    //   17	50	4	i	int
    //   42	7	5	j	int
    //   45	8	6	k	int
    // Exception table:
    //   from	to	target	type
    //   8	12	78	finally
    //   20	25	78	finally
    //   32	36	78	finally
    //   36	40	78	finally
    //   52	60	78	finally
    //   71	75	78	finally
  }
}


/* Location:              C:\Users\haryo\Desktop\enjarify-master\presensi-enjarify.jar!\com\google\android\gms\wearable\internal\zzaw$zza$zza.class
 * Java compiler version: 5 (49.0)
 * JD-Core Version:       0.7.1
 */