package com.google.android.gms.wearable.internal;

import android.os.IBinder;

class zzax$zza$zza
  implements zzax
{
  private IBinder zzoz;
  
  zzax$zza$zza(IBinder paramIBinder)
  {
    this.zzoz = paramIBinder;
  }
  
  public IBinder asBinder()
  {
    return this.zzoz;
  }
  
  /* Error */
  public void zza(zzav paramzzav)
  {
    // Byte code:
    //   0: invokestatic 20	android/os/Parcel:obtain	()Landroid/os/Parcel;
    //   3: astore_2
    //   4: invokestatic 20	android/os/Parcel:obtain	()Landroid/os/Parcel;
    //   7: astore_3
    //   8: ldc 22
    //   10: astore 4
    //   12: aload_2
    //   13: aload 4
    //   15: invokevirtual 26	android/os/Parcel:writeInterfaceToken	(Ljava/lang/String;)V
    //   18: aload_1
    //   19: ifnull +53 -> 72
    //   22: aload_1
    //   23: invokeinterface 32 1 0
    //   28: astore 4
    //   30: aload_2
    //   31: aload 4
    //   33: invokevirtual 36	android/os/Parcel:writeStrongBinder	(Landroid/os/IBinder;)V
    //   36: aload_0
    //   37: getfield 14	com/google/android/gms/wearable/internal/zzax$zza$zza:zzoz	Landroid/os/IBinder;
    //   40: astore 4
    //   42: bipush 22
    //   44: istore 5
    //   46: aload 4
    //   48: iload 5
    //   50: aload_2
    //   51: aload_3
    //   52: iconst_0
    //   53: invokeinterface 43 5 0
    //   58: pop
    //   59: aload_3
    //   60: invokevirtual 46	android/os/Parcel:readException	()V
    //   63: aload_3
    //   64: invokevirtual 49	android/os/Parcel:recycle	()V
    //   67: aload_2
    //   68: invokevirtual 49	android/os/Parcel:recycle	()V
    //   71: return
    //   72: aconst_null
    //   73: astore 4
    //   75: goto -45 -> 30
    //   78: astore 4
    //   80: aload_3
    //   81: invokevirtual 49	android/os/Parcel:recycle	()V
    //   84: aload_2
    //   85: invokevirtual 49	android/os/Parcel:recycle	()V
    //   88: aload 4
    //   90: athrow
    // Local variable table:
    //   start	length	slot	name	signature
    //   0	91	0	this	zza
    //   0	91	1	paramzzav	zzav
    //   3	82	2	localParcel1	android.os.Parcel
    //   7	74	3	localParcel2	android.os.Parcel
    //   10	64	4	localObject1	Object
    //   78	11	4	localObject2	Object
    //   44	5	5	i	int
    // Exception table:
    //   from	to	target	type
    //   13	18	78	finally
    //   22	28	78	finally
    //   31	36	78	finally
    //   36	40	78	finally
    //   52	59	78	finally
    //   59	63	78	finally
  }
  
  /* Error */
  public void zza(zzav paramzzav, byte paramByte)
  {
    // Byte code:
    //   0: invokestatic 20	android/os/Parcel:obtain	()Landroid/os/Parcel;
    //   3: astore_3
    //   4: invokestatic 20	android/os/Parcel:obtain	()Landroid/os/Parcel;
    //   7: astore 4
    //   9: ldc 22
    //   11: astore 5
    //   13: aload_3
    //   14: aload 5
    //   16: invokevirtual 26	android/os/Parcel:writeInterfaceToken	(Ljava/lang/String;)V
    //   19: aload_1
    //   20: ifnull +61 -> 81
    //   23: aload_1
    //   24: invokeinterface 32 1 0
    //   29: astore 5
    //   31: aload_3
    //   32: aload 5
    //   34: invokevirtual 36	android/os/Parcel:writeStrongBinder	(Landroid/os/IBinder;)V
    //   37: aload_3
    //   38: iload_2
    //   39: invokevirtual 53	android/os/Parcel:writeByte	(B)V
    //   42: aload_0
    //   43: getfield 14	com/google/android/gms/wearable/internal/zzax$zza$zza:zzoz	Landroid/os/IBinder;
    //   46: astore 5
    //   48: bipush 53
    //   50: istore 6
    //   52: aload 5
    //   54: iload 6
    //   56: aload_3
    //   57: aload 4
    //   59: iconst_0
    //   60: invokeinterface 43 5 0
    //   65: pop
    //   66: aload 4
    //   68: invokevirtual 46	android/os/Parcel:readException	()V
    //   71: aload 4
    //   73: invokevirtual 49	android/os/Parcel:recycle	()V
    //   76: aload_3
    //   77: invokevirtual 49	android/os/Parcel:recycle	()V
    //   80: return
    //   81: aconst_null
    //   82: astore 5
    //   84: goto -53 -> 31
    //   87: astore 5
    //   89: aload 4
    //   91: invokevirtual 49	android/os/Parcel:recycle	()V
    //   94: aload_3
    //   95: invokevirtual 49	android/os/Parcel:recycle	()V
    //   98: aload 5
    //   100: athrow
    // Local variable table:
    //   start	length	slot	name	signature
    //   0	101	0	this	zza
    //   0	101	1	paramzzav	zzav
    //   0	101	2	paramByte	byte
    //   3	92	3	localParcel1	android.os.Parcel
    //   7	83	4	localParcel2	android.os.Parcel
    //   11	72	5	localObject1	Object
    //   87	12	5	localObject2	Object
    //   50	5	6	i	int
    // Exception table:
    //   from	to	target	type
    //   14	19	87	finally
    //   23	29	87	finally
    //   32	37	87	finally
    //   38	42	87	finally
    //   42	46	87	finally
    //   59	66	87	finally
    //   66	71	87	finally
  }
  
  /* Error */
  public void zza(zzav paramzzav, int paramInt)
  {
    // Byte code:
    //   0: invokestatic 20	android/os/Parcel:obtain	()Landroid/os/Parcel;
    //   3: astore_3
    //   4: invokestatic 20	android/os/Parcel:obtain	()Landroid/os/Parcel;
    //   7: astore 4
    //   9: ldc 22
    //   11: astore 5
    //   13: aload_3
    //   14: aload 5
    //   16: invokevirtual 26	android/os/Parcel:writeInterfaceToken	(Ljava/lang/String;)V
    //   19: aload_1
    //   20: ifnull +61 -> 81
    //   23: aload_1
    //   24: invokeinterface 32 1 0
    //   29: astore 5
    //   31: aload_3
    //   32: aload 5
    //   34: invokevirtual 36	android/os/Parcel:writeStrongBinder	(Landroid/os/IBinder;)V
    //   37: aload_3
    //   38: iload_2
    //   39: invokevirtual 58	android/os/Parcel:writeInt	(I)V
    //   42: aload_0
    //   43: getfield 14	com/google/android/gms/wearable/internal/zzax$zza$zza:zzoz	Landroid/os/IBinder;
    //   46: astore 5
    //   48: bipush 43
    //   50: istore 6
    //   52: aload 5
    //   54: iload 6
    //   56: aload_3
    //   57: aload 4
    //   59: iconst_0
    //   60: invokeinterface 43 5 0
    //   65: pop
    //   66: aload 4
    //   68: invokevirtual 46	android/os/Parcel:readException	()V
    //   71: aload 4
    //   73: invokevirtual 49	android/os/Parcel:recycle	()V
    //   76: aload_3
    //   77: invokevirtual 49	android/os/Parcel:recycle	()V
    //   80: return
    //   81: aconst_null
    //   82: astore 5
    //   84: goto -53 -> 31
    //   87: astore 5
    //   89: aload 4
    //   91: invokevirtual 49	android/os/Parcel:recycle	()V
    //   94: aload_3
    //   95: invokevirtual 49	android/os/Parcel:recycle	()V
    //   98: aload 5
    //   100: athrow
    // Local variable table:
    //   start	length	slot	name	signature
    //   0	101	0	this	zza
    //   0	101	1	paramzzav	zzav
    //   0	101	2	paramInt	int
    //   3	92	3	localParcel1	android.os.Parcel
    //   7	83	4	localParcel2	android.os.Parcel
    //   11	72	5	localObject1	Object
    //   87	12	5	localObject2	Object
    //   50	5	6	i	int
    // Exception table:
    //   from	to	target	type
    //   14	19	87	finally
    //   23	29	87	finally
    //   32	37	87	finally
    //   38	42	87	finally
    //   42	46	87	finally
    //   59	66	87	finally
    //   66	71	87	finally
  }
  
  /* Error */
  public void zza(zzav paramzzav, android.net.Uri paramUri)
  {
    // Byte code:
    //   0: invokestatic 20	android/os/Parcel:obtain	()Landroid/os/Parcel;
    //   3: astore_3
    //   4: invokestatic 20	android/os/Parcel:obtain	()Landroid/os/Parcel;
    //   7: astore 4
    //   9: ldc 22
    //   11: astore 5
    //   13: aload_3
    //   14: aload 5
    //   16: invokevirtual 26	android/os/Parcel:writeInterfaceToken	(Ljava/lang/String;)V
    //   19: aload_1
    //   20: ifnull +81 -> 101
    //   23: aload_1
    //   24: invokeinterface 32 1 0
    //   29: astore 5
    //   31: aload_3
    //   32: aload 5
    //   34: invokevirtual 36	android/os/Parcel:writeStrongBinder	(Landroid/os/IBinder;)V
    //   37: aload_2
    //   38: ifnull +72 -> 110
    //   41: iconst_1
    //   42: istore 6
    //   44: aload_3
    //   45: iload 6
    //   47: invokevirtual 58	android/os/Parcel:writeInt	(I)V
    //   50: iconst_0
    //   51: istore 6
    //   53: aconst_null
    //   54: astore 5
    //   56: aload_2
    //   57: aload_3
    //   58: iconst_0
    //   59: invokevirtual 66	android/net/Uri:writeToParcel	(Landroid/os/Parcel;I)V
    //   62: aload_0
    //   63: getfield 14	com/google/android/gms/wearable/internal/zzax$zza$zza:zzoz	Landroid/os/IBinder;
    //   66: astore 5
    //   68: bipush 7
    //   70: istore 7
    //   72: aload 5
    //   74: iload 7
    //   76: aload_3
    //   77: aload 4
    //   79: iconst_0
    //   80: invokeinterface 43 5 0
    //   85: pop
    //   86: aload 4
    //   88: invokevirtual 46	android/os/Parcel:readException	()V
    //   91: aload 4
    //   93: invokevirtual 49	android/os/Parcel:recycle	()V
    //   96: aload_3
    //   97: invokevirtual 49	android/os/Parcel:recycle	()V
    //   100: return
    //   101: iconst_0
    //   102: istore 6
    //   104: aconst_null
    //   105: astore 5
    //   107: goto -76 -> 31
    //   110: iconst_0
    //   111: istore 6
    //   113: aconst_null
    //   114: astore 5
    //   116: aload_3
    //   117: iconst_0
    //   118: invokevirtual 58	android/os/Parcel:writeInt	(I)V
    //   121: goto -59 -> 62
    //   124: astore 5
    //   126: aload 4
    //   128: invokevirtual 49	android/os/Parcel:recycle	()V
    //   131: aload_3
    //   132: invokevirtual 49	android/os/Parcel:recycle	()V
    //   135: aload 5
    //   137: athrow
    // Local variable table:
    //   start	length	slot	name	signature
    //   0	138	0	this	zza
    //   0	138	1	paramzzav	zzav
    //   0	138	2	paramUri	android.net.Uri
    //   3	129	3	localParcel1	android.os.Parcel
    //   7	120	4	localParcel2	android.os.Parcel
    //   11	104	5	localObject1	Object
    //   124	12	5	localObject2	Object
    //   42	70	6	i	int
    //   70	5	7	j	int
    // Exception table:
    //   from	to	target	type
    //   14	19	124	finally
    //   23	29	124	finally
    //   32	37	124	finally
    //   45	50	124	finally
    //   58	62	124	finally
    //   62	66	124	finally
    //   79	86	124	finally
    //   86	91	124	finally
    //   117	121	124	finally
  }
  
  /* Error */
  public void zza(zzav paramzzav, android.net.Uri paramUri, int paramInt)
  {
    // Byte code:
    //   0: invokestatic 20	android/os/Parcel:obtain	()Landroid/os/Parcel;
    //   3: astore 4
    //   5: invokestatic 20	android/os/Parcel:obtain	()Landroid/os/Parcel;
    //   8: astore 5
    //   10: ldc 22
    //   12: astore 6
    //   14: aload 4
    //   16: aload 6
    //   18: invokevirtual 26	android/os/Parcel:writeInterfaceToken	(Ljava/lang/String;)V
    //   21: aload_1
    //   22: ifnull +92 -> 114
    //   25: aload_1
    //   26: invokeinterface 32 1 0
    //   31: astore 6
    //   33: aload 4
    //   35: aload 6
    //   37: invokevirtual 36	android/os/Parcel:writeStrongBinder	(Landroid/os/IBinder;)V
    //   40: aload_2
    //   41: ifnull +82 -> 123
    //   44: iconst_1
    //   45: istore 7
    //   47: aload 4
    //   49: iload 7
    //   51: invokevirtual 58	android/os/Parcel:writeInt	(I)V
    //   54: iconst_0
    //   55: istore 7
    //   57: aconst_null
    //   58: astore 6
    //   60: aload_2
    //   61: aload 4
    //   63: iconst_0
    //   64: invokevirtual 66	android/net/Uri:writeToParcel	(Landroid/os/Parcel;I)V
    //   67: aload 4
    //   69: iload_3
    //   70: invokevirtual 58	android/os/Parcel:writeInt	(I)V
    //   73: aload_0
    //   74: getfield 14	com/google/android/gms/wearable/internal/zzax$zza$zza:zzoz	Landroid/os/IBinder;
    //   77: astore 6
    //   79: bipush 40
    //   81: istore 8
    //   83: aload 6
    //   85: iload 8
    //   87: aload 4
    //   89: aload 5
    //   91: iconst_0
    //   92: invokeinterface 43 5 0
    //   97: pop
    //   98: aload 5
    //   100: invokevirtual 46	android/os/Parcel:readException	()V
    //   103: aload 5
    //   105: invokevirtual 49	android/os/Parcel:recycle	()V
    //   108: aload 4
    //   110: invokevirtual 49	android/os/Parcel:recycle	()V
    //   113: return
    //   114: iconst_0
    //   115: istore 7
    //   117: aconst_null
    //   118: astore 6
    //   120: goto -87 -> 33
    //   123: iconst_0
    //   124: istore 7
    //   126: aconst_null
    //   127: astore 6
    //   129: aload 4
    //   131: iconst_0
    //   132: invokevirtual 58	android/os/Parcel:writeInt	(I)V
    //   135: goto -68 -> 67
    //   138: astore 6
    //   140: aload 5
    //   142: invokevirtual 49	android/os/Parcel:recycle	()V
    //   145: aload 4
    //   147: invokevirtual 49	android/os/Parcel:recycle	()V
    //   150: aload 6
    //   152: athrow
    // Local variable table:
    //   start	length	slot	name	signature
    //   0	153	0	this	zza
    //   0	153	1	paramzzav	zzav
    //   0	153	2	paramUri	android.net.Uri
    //   0	153	3	paramInt	int
    //   3	143	4	localParcel1	android.os.Parcel
    //   8	133	5	localParcel2	android.os.Parcel
    //   12	116	6	localObject1	Object
    //   138	13	6	localObject2	Object
    //   45	80	7	i	int
    //   81	5	8	j	int
    // Exception table:
    //   from	to	target	type
    //   16	21	138	finally
    //   25	31	138	finally
    //   35	40	138	finally
    //   49	54	138	finally
    //   63	67	138	finally
    //   69	73	138	finally
    //   73	77	138	finally
    //   91	98	138	finally
    //   98	103	138	finally
    //   131	135	138	finally
  }
  
  /* Error */
  public void zza(zzav paramzzav, com.google.android.gms.wearable.Asset paramAsset)
  {
    // Byte code:
    //   0: invokestatic 20	android/os/Parcel:obtain	()Landroid/os/Parcel;
    //   3: astore_3
    //   4: invokestatic 20	android/os/Parcel:obtain	()Landroid/os/Parcel;
    //   7: astore 4
    //   9: ldc 22
    //   11: astore 5
    //   13: aload_3
    //   14: aload 5
    //   16: invokevirtual 26	android/os/Parcel:writeInterfaceToken	(Ljava/lang/String;)V
    //   19: aload_1
    //   20: ifnull +81 -> 101
    //   23: aload_1
    //   24: invokeinterface 32 1 0
    //   29: astore 5
    //   31: aload_3
    //   32: aload 5
    //   34: invokevirtual 36	android/os/Parcel:writeStrongBinder	(Landroid/os/IBinder;)V
    //   37: aload_2
    //   38: ifnull +72 -> 110
    //   41: iconst_1
    //   42: istore 6
    //   44: aload_3
    //   45: iload 6
    //   47: invokevirtual 58	android/os/Parcel:writeInt	(I)V
    //   50: iconst_0
    //   51: istore 6
    //   53: aconst_null
    //   54: astore 5
    //   56: aload_2
    //   57: aload_3
    //   58: iconst_0
    //   59: invokevirtual 71	com/google/android/gms/wearable/Asset:writeToParcel	(Landroid/os/Parcel;I)V
    //   62: aload_0
    //   63: getfield 14	com/google/android/gms/wearable/internal/zzax$zza$zza:zzoz	Landroid/os/IBinder;
    //   66: astore 5
    //   68: bipush 13
    //   70: istore 7
    //   72: aload 5
    //   74: iload 7
    //   76: aload_3
    //   77: aload 4
    //   79: iconst_0
    //   80: invokeinterface 43 5 0
    //   85: pop
    //   86: aload 4
    //   88: invokevirtual 46	android/os/Parcel:readException	()V
    //   91: aload 4
    //   93: invokevirtual 49	android/os/Parcel:recycle	()V
    //   96: aload_3
    //   97: invokevirtual 49	android/os/Parcel:recycle	()V
    //   100: return
    //   101: iconst_0
    //   102: istore 6
    //   104: aconst_null
    //   105: astore 5
    //   107: goto -76 -> 31
    //   110: iconst_0
    //   111: istore 6
    //   113: aconst_null
    //   114: astore 5
    //   116: aload_3
    //   117: iconst_0
    //   118: invokevirtual 58	android/os/Parcel:writeInt	(I)V
    //   121: goto -59 -> 62
    //   124: astore 5
    //   126: aload 4
    //   128: invokevirtual 49	android/os/Parcel:recycle	()V
    //   131: aload_3
    //   132: invokevirtual 49	android/os/Parcel:recycle	()V
    //   135: aload 5
    //   137: athrow
    // Local variable table:
    //   start	length	slot	name	signature
    //   0	138	0	this	zza
    //   0	138	1	paramzzav	zzav
    //   0	138	2	paramAsset	com.google.android.gms.wearable.Asset
    //   3	129	3	localParcel1	android.os.Parcel
    //   7	120	4	localParcel2	android.os.Parcel
    //   11	104	5	localObject1	Object
    //   124	12	5	localObject2	Object
    //   42	70	6	i	int
    //   70	5	7	j	int
    // Exception table:
    //   from	to	target	type
    //   14	19	124	finally
    //   23	29	124	finally
    //   32	37	124	finally
    //   45	50	124	finally
    //   58	62	124	finally
    //   62	66	124	finally
    //   79	86	124	finally
    //   86	91	124	finally
    //   117	121	124	finally
  }
  
  /* Error */
  public void zza(zzav paramzzav, com.google.android.gms.wearable.ConnectionConfiguration paramConnectionConfiguration)
  {
    // Byte code:
    //   0: invokestatic 20	android/os/Parcel:obtain	()Landroid/os/Parcel;
    //   3: astore_3
    //   4: invokestatic 20	android/os/Parcel:obtain	()Landroid/os/Parcel;
    //   7: astore 4
    //   9: ldc 22
    //   11: astore 5
    //   13: aload_3
    //   14: aload 5
    //   16: invokevirtual 26	android/os/Parcel:writeInterfaceToken	(Ljava/lang/String;)V
    //   19: aload_1
    //   20: ifnull +81 -> 101
    //   23: aload_1
    //   24: invokeinterface 32 1 0
    //   29: astore 5
    //   31: aload_3
    //   32: aload 5
    //   34: invokevirtual 36	android/os/Parcel:writeStrongBinder	(Landroid/os/IBinder;)V
    //   37: aload_2
    //   38: ifnull +72 -> 110
    //   41: iconst_1
    //   42: istore 6
    //   44: aload_3
    //   45: iload 6
    //   47: invokevirtual 58	android/os/Parcel:writeInt	(I)V
    //   50: iconst_0
    //   51: istore 6
    //   53: aconst_null
    //   54: astore 5
    //   56: aload_2
    //   57: aload_3
    //   58: iconst_0
    //   59: invokevirtual 75	com/google/android/gms/wearable/ConnectionConfiguration:writeToParcel	(Landroid/os/Parcel;I)V
    //   62: aload_0
    //   63: getfield 14	com/google/android/gms/wearable/internal/zzax$zza$zza:zzoz	Landroid/os/IBinder;
    //   66: astore 5
    //   68: bipush 20
    //   70: istore 7
    //   72: aload 5
    //   74: iload 7
    //   76: aload_3
    //   77: aload 4
    //   79: iconst_0
    //   80: invokeinterface 43 5 0
    //   85: pop
    //   86: aload 4
    //   88: invokevirtual 46	android/os/Parcel:readException	()V
    //   91: aload 4
    //   93: invokevirtual 49	android/os/Parcel:recycle	()V
    //   96: aload_3
    //   97: invokevirtual 49	android/os/Parcel:recycle	()V
    //   100: return
    //   101: iconst_0
    //   102: istore 6
    //   104: aconst_null
    //   105: astore 5
    //   107: goto -76 -> 31
    //   110: iconst_0
    //   111: istore 6
    //   113: aconst_null
    //   114: astore 5
    //   116: aload_3
    //   117: iconst_0
    //   118: invokevirtual 58	android/os/Parcel:writeInt	(I)V
    //   121: goto -59 -> 62
    //   124: astore 5
    //   126: aload 4
    //   128: invokevirtual 49	android/os/Parcel:recycle	()V
    //   131: aload_3
    //   132: invokevirtual 49	android/os/Parcel:recycle	()V
    //   135: aload 5
    //   137: athrow
    // Local variable table:
    //   start	length	slot	name	signature
    //   0	138	0	this	zza
    //   0	138	1	paramzzav	zzav
    //   0	138	2	paramConnectionConfiguration	com.google.android.gms.wearable.ConnectionConfiguration
    //   3	129	3	localParcel1	android.os.Parcel
    //   7	120	4	localParcel2	android.os.Parcel
    //   11	104	5	localObject1	Object
    //   124	12	5	localObject2	Object
    //   42	70	6	i	int
    //   70	5	7	j	int
    // Exception table:
    //   from	to	target	type
    //   14	19	124	finally
    //   23	29	124	finally
    //   32	37	124	finally
    //   45	50	124	finally
    //   58	62	124	finally
    //   62	66	124	finally
    //   79	86	124	finally
    //   86	91	124	finally
    //   117	121	124	finally
  }
  
  /* Error */
  public void zza(zzav paramzzav, com.google.android.gms.wearable.PutDataRequest paramPutDataRequest)
  {
    // Byte code:
    //   0: invokestatic 20	android/os/Parcel:obtain	()Landroid/os/Parcel;
    //   3: astore_3
    //   4: invokestatic 20	android/os/Parcel:obtain	()Landroid/os/Parcel;
    //   7: astore 4
    //   9: ldc 22
    //   11: astore 5
    //   13: aload_3
    //   14: aload 5
    //   16: invokevirtual 26	android/os/Parcel:writeInterfaceToken	(Ljava/lang/String;)V
    //   19: aload_1
    //   20: ifnull +81 -> 101
    //   23: aload_1
    //   24: invokeinterface 32 1 0
    //   29: astore 5
    //   31: aload_3
    //   32: aload 5
    //   34: invokevirtual 36	android/os/Parcel:writeStrongBinder	(Landroid/os/IBinder;)V
    //   37: aload_2
    //   38: ifnull +72 -> 110
    //   41: iconst_1
    //   42: istore 6
    //   44: aload_3
    //   45: iload 6
    //   47: invokevirtual 58	android/os/Parcel:writeInt	(I)V
    //   50: iconst_0
    //   51: istore 6
    //   53: aconst_null
    //   54: astore 5
    //   56: aload_2
    //   57: aload_3
    //   58: iconst_0
    //   59: invokevirtual 79	com/google/android/gms/wearable/PutDataRequest:writeToParcel	(Landroid/os/Parcel;I)V
    //   62: aload_0
    //   63: getfield 14	com/google/android/gms/wearable/internal/zzax$zza$zza:zzoz	Landroid/os/IBinder;
    //   66: astore 5
    //   68: bipush 6
    //   70: istore 7
    //   72: aload 5
    //   74: iload 7
    //   76: aload_3
    //   77: aload 4
    //   79: iconst_0
    //   80: invokeinterface 43 5 0
    //   85: pop
    //   86: aload 4
    //   88: invokevirtual 46	android/os/Parcel:readException	()V
    //   91: aload 4
    //   93: invokevirtual 49	android/os/Parcel:recycle	()V
    //   96: aload_3
    //   97: invokevirtual 49	android/os/Parcel:recycle	()V
    //   100: return
    //   101: iconst_0
    //   102: istore 6
    //   104: aconst_null
    //   105: astore 5
    //   107: goto -76 -> 31
    //   110: iconst_0
    //   111: istore 6
    //   113: aconst_null
    //   114: astore 5
    //   116: aload_3
    //   117: iconst_0
    //   118: invokevirtual 58	android/os/Parcel:writeInt	(I)V
    //   121: goto -59 -> 62
    //   124: astore 5
    //   126: aload 4
    //   128: invokevirtual 49	android/os/Parcel:recycle	()V
    //   131: aload_3
    //   132: invokevirtual 49	android/os/Parcel:recycle	()V
    //   135: aload 5
    //   137: athrow
    // Local variable table:
    //   start	length	slot	name	signature
    //   0	138	0	this	zza
    //   0	138	1	paramzzav	zzav
    //   0	138	2	paramPutDataRequest	com.google.android.gms.wearable.PutDataRequest
    //   3	129	3	localParcel1	android.os.Parcel
    //   7	120	4	localParcel2	android.os.Parcel
    //   11	104	5	localObject1	Object
    //   124	12	5	localObject2	Object
    //   42	70	6	i	int
    //   70	5	7	j	int
    // Exception table:
    //   from	to	target	type
    //   14	19	124	finally
    //   23	29	124	finally
    //   32	37	124	finally
    //   45	50	124	finally
    //   58	62	124	finally
    //   62	66	124	finally
    //   79	86	124	finally
    //   86	91	124	finally
    //   117	121	124	finally
  }
  
  /* Error */
  public void zza(zzav paramzzav, AddListenerRequest paramAddListenerRequest)
  {
    // Byte code:
    //   0: invokestatic 20	android/os/Parcel:obtain	()Landroid/os/Parcel;
    //   3: astore_3
    //   4: invokestatic 20	android/os/Parcel:obtain	()Landroid/os/Parcel;
    //   7: astore 4
    //   9: ldc 22
    //   11: astore 5
    //   13: aload_3
    //   14: aload 5
    //   16: invokevirtual 26	android/os/Parcel:writeInterfaceToken	(Ljava/lang/String;)V
    //   19: aload_1
    //   20: ifnull +81 -> 101
    //   23: aload_1
    //   24: invokeinterface 32 1 0
    //   29: astore 5
    //   31: aload_3
    //   32: aload 5
    //   34: invokevirtual 36	android/os/Parcel:writeStrongBinder	(Landroid/os/IBinder;)V
    //   37: aload_2
    //   38: ifnull +72 -> 110
    //   41: iconst_1
    //   42: istore 6
    //   44: aload_3
    //   45: iload 6
    //   47: invokevirtual 58	android/os/Parcel:writeInt	(I)V
    //   50: iconst_0
    //   51: istore 6
    //   53: aconst_null
    //   54: astore 5
    //   56: aload_2
    //   57: aload_3
    //   58: iconst_0
    //   59: invokevirtual 83	com/google/android/gms/wearable/internal/AddListenerRequest:writeToParcel	(Landroid/os/Parcel;I)V
    //   62: aload_0
    //   63: getfield 14	com/google/android/gms/wearable/internal/zzax$zza$zza:zzoz	Landroid/os/IBinder;
    //   66: astore 5
    //   68: bipush 16
    //   70: istore 7
    //   72: aload 5
    //   74: iload 7
    //   76: aload_3
    //   77: aload 4
    //   79: iconst_0
    //   80: invokeinterface 43 5 0
    //   85: pop
    //   86: aload 4
    //   88: invokevirtual 46	android/os/Parcel:readException	()V
    //   91: aload 4
    //   93: invokevirtual 49	android/os/Parcel:recycle	()V
    //   96: aload_3
    //   97: invokevirtual 49	android/os/Parcel:recycle	()V
    //   100: return
    //   101: iconst_0
    //   102: istore 6
    //   104: aconst_null
    //   105: astore 5
    //   107: goto -76 -> 31
    //   110: iconst_0
    //   111: istore 6
    //   113: aconst_null
    //   114: astore 5
    //   116: aload_3
    //   117: iconst_0
    //   118: invokevirtual 58	android/os/Parcel:writeInt	(I)V
    //   121: goto -59 -> 62
    //   124: astore 5
    //   126: aload 4
    //   128: invokevirtual 49	android/os/Parcel:recycle	()V
    //   131: aload_3
    //   132: invokevirtual 49	android/os/Parcel:recycle	()V
    //   135: aload 5
    //   137: athrow
    // Local variable table:
    //   start	length	slot	name	signature
    //   0	138	0	this	zza
    //   0	138	1	paramzzav	zzav
    //   0	138	2	paramAddListenerRequest	AddListenerRequest
    //   3	129	3	localParcel1	android.os.Parcel
    //   7	120	4	localParcel2	android.os.Parcel
    //   11	104	5	localObject1	Object
    //   124	12	5	localObject2	Object
    //   42	70	6	i	int
    //   70	5	7	j	int
    // Exception table:
    //   from	to	target	type
    //   14	19	124	finally
    //   23	29	124	finally
    //   32	37	124	finally
    //   45	50	124	finally
    //   58	62	124	finally
    //   62	66	124	finally
    //   79	86	124	finally
    //   86	91	124	finally
    //   117	121	124	finally
  }
  
  /* Error */
  public void zza(zzav paramzzav, AncsNotificationParcelable paramAncsNotificationParcelable)
  {
    // Byte code:
    //   0: invokestatic 20	android/os/Parcel:obtain	()Landroid/os/Parcel;
    //   3: astore_3
    //   4: invokestatic 20	android/os/Parcel:obtain	()Landroid/os/Parcel;
    //   7: astore 4
    //   9: ldc 22
    //   11: astore 5
    //   13: aload_3
    //   14: aload 5
    //   16: invokevirtual 26	android/os/Parcel:writeInterfaceToken	(Ljava/lang/String;)V
    //   19: aload_1
    //   20: ifnull +81 -> 101
    //   23: aload_1
    //   24: invokeinterface 32 1 0
    //   29: astore 5
    //   31: aload_3
    //   32: aload 5
    //   34: invokevirtual 36	android/os/Parcel:writeStrongBinder	(Landroid/os/IBinder;)V
    //   37: aload_2
    //   38: ifnull +72 -> 110
    //   41: iconst_1
    //   42: istore 6
    //   44: aload_3
    //   45: iload 6
    //   47: invokevirtual 58	android/os/Parcel:writeInt	(I)V
    //   50: iconst_0
    //   51: istore 6
    //   53: aconst_null
    //   54: astore 5
    //   56: aload_2
    //   57: aload_3
    //   58: iconst_0
    //   59: invokevirtual 87	com/google/android/gms/wearable/internal/AncsNotificationParcelable:writeToParcel	(Landroid/os/Parcel;I)V
    //   62: aload_0
    //   63: getfield 14	com/google/android/gms/wearable/internal/zzax$zza$zza:zzoz	Landroid/os/IBinder;
    //   66: astore 5
    //   68: bipush 27
    //   70: istore 7
    //   72: aload 5
    //   74: iload 7
    //   76: aload_3
    //   77: aload 4
    //   79: iconst_0
    //   80: invokeinterface 43 5 0
    //   85: pop
    //   86: aload 4
    //   88: invokevirtual 46	android/os/Parcel:readException	()V
    //   91: aload 4
    //   93: invokevirtual 49	android/os/Parcel:recycle	()V
    //   96: aload_3
    //   97: invokevirtual 49	android/os/Parcel:recycle	()V
    //   100: return
    //   101: iconst_0
    //   102: istore 6
    //   104: aconst_null
    //   105: astore 5
    //   107: goto -76 -> 31
    //   110: iconst_0
    //   111: istore 6
    //   113: aconst_null
    //   114: astore 5
    //   116: aload_3
    //   117: iconst_0
    //   118: invokevirtual 58	android/os/Parcel:writeInt	(I)V
    //   121: goto -59 -> 62
    //   124: astore 5
    //   126: aload 4
    //   128: invokevirtual 49	android/os/Parcel:recycle	()V
    //   131: aload_3
    //   132: invokevirtual 49	android/os/Parcel:recycle	()V
    //   135: aload 5
    //   137: athrow
    // Local variable table:
    //   start	length	slot	name	signature
    //   0	138	0	this	zza
    //   0	138	1	paramzzav	zzav
    //   0	138	2	paramAncsNotificationParcelable	AncsNotificationParcelable
    //   3	129	3	localParcel1	android.os.Parcel
    //   7	120	4	localParcel2	android.os.Parcel
    //   11	104	5	localObject1	Object
    //   124	12	5	localObject2	Object
    //   42	70	6	i	int
    //   70	5	7	j	int
    // Exception table:
    //   from	to	target	type
    //   14	19	124	finally
    //   23	29	124	finally
    //   32	37	124	finally
    //   45	50	124	finally
    //   58	62	124	finally
    //   62	66	124	finally
    //   79	86	124	finally
    //   86	91	124	finally
    //   117	121	124	finally
  }
  
  /* Error */
  public void zza(zzav paramzzav, RemoveListenerRequest paramRemoveListenerRequest)
  {
    // Byte code:
    //   0: invokestatic 20	android/os/Parcel:obtain	()Landroid/os/Parcel;
    //   3: astore_3
    //   4: invokestatic 20	android/os/Parcel:obtain	()Landroid/os/Parcel;
    //   7: astore 4
    //   9: ldc 22
    //   11: astore 5
    //   13: aload_3
    //   14: aload 5
    //   16: invokevirtual 26	android/os/Parcel:writeInterfaceToken	(Ljava/lang/String;)V
    //   19: aload_1
    //   20: ifnull +81 -> 101
    //   23: aload_1
    //   24: invokeinterface 32 1 0
    //   29: astore 5
    //   31: aload_3
    //   32: aload 5
    //   34: invokevirtual 36	android/os/Parcel:writeStrongBinder	(Landroid/os/IBinder;)V
    //   37: aload_2
    //   38: ifnull +72 -> 110
    //   41: iconst_1
    //   42: istore 6
    //   44: aload_3
    //   45: iload 6
    //   47: invokevirtual 58	android/os/Parcel:writeInt	(I)V
    //   50: iconst_0
    //   51: istore 6
    //   53: aconst_null
    //   54: astore 5
    //   56: aload_2
    //   57: aload_3
    //   58: iconst_0
    //   59: invokevirtual 91	com/google/android/gms/wearable/internal/RemoveListenerRequest:writeToParcel	(Landroid/os/Parcel;I)V
    //   62: aload_0
    //   63: getfield 14	com/google/android/gms/wearable/internal/zzax$zza$zza:zzoz	Landroid/os/IBinder;
    //   66: astore 5
    //   68: bipush 17
    //   70: istore 7
    //   72: aload 5
    //   74: iload 7
    //   76: aload_3
    //   77: aload 4
    //   79: iconst_0
    //   80: invokeinterface 43 5 0
    //   85: pop
    //   86: aload 4
    //   88: invokevirtual 46	android/os/Parcel:readException	()V
    //   91: aload 4
    //   93: invokevirtual 49	android/os/Parcel:recycle	()V
    //   96: aload_3
    //   97: invokevirtual 49	android/os/Parcel:recycle	()V
    //   100: return
    //   101: iconst_0
    //   102: istore 6
    //   104: aconst_null
    //   105: astore 5
    //   107: goto -76 -> 31
    //   110: iconst_0
    //   111: istore 6
    //   113: aconst_null
    //   114: astore 5
    //   116: aload_3
    //   117: iconst_0
    //   118: invokevirtual 58	android/os/Parcel:writeInt	(I)V
    //   121: goto -59 -> 62
    //   124: astore 5
    //   126: aload 4
    //   128: invokevirtual 49	android/os/Parcel:recycle	()V
    //   131: aload_3
    //   132: invokevirtual 49	android/os/Parcel:recycle	()V
    //   135: aload 5
    //   137: athrow
    // Local variable table:
    //   start	length	slot	name	signature
    //   0	138	0	this	zza
    //   0	138	1	paramzzav	zzav
    //   0	138	2	paramRemoveListenerRequest	RemoveListenerRequest
    //   3	129	3	localParcel1	android.os.Parcel
    //   7	120	4	localParcel2	android.os.Parcel
    //   11	104	5	localObject1	Object
    //   124	12	5	localObject2	Object
    //   42	70	6	i	int
    //   70	5	7	j	int
    // Exception table:
    //   from	to	target	type
    //   14	19	124	finally
    //   23	29	124	finally
    //   32	37	124	finally
    //   45	50	124	finally
    //   58	62	124	finally
    //   62	66	124	finally
    //   79	86	124	finally
    //   86	91	124	finally
    //   117	121	124	finally
  }
  
  /* Error */
  public void zza(zzav paramzzav, zzau paramzzau, String paramString)
  {
    // Byte code:
    //   0: aconst_null
    //   1: astore 4
    //   3: invokestatic 20	android/os/Parcel:obtain	()Landroid/os/Parcel;
    //   6: astore 5
    //   8: invokestatic 20	android/os/Parcel:obtain	()Landroid/os/Parcel;
    //   11: astore 6
    //   13: ldc 22
    //   15: astore 7
    //   17: aload 5
    //   19: aload 7
    //   21: invokevirtual 26	android/os/Parcel:writeInterfaceToken	(Ljava/lang/String;)V
    //   24: aload_1
    //   25: ifnull +84 -> 109
    //   28: aload_1
    //   29: invokeinterface 32 1 0
    //   34: astore 7
    //   36: aload 5
    //   38: aload 7
    //   40: invokevirtual 36	android/os/Parcel:writeStrongBinder	(Landroid/os/IBinder;)V
    //   43: aload_2
    //   44: ifnull +11 -> 55
    //   47: aload_2
    //   48: invokeinterface 95 1 0
    //   53: astore 4
    //   55: aload 5
    //   57: aload 4
    //   59: invokevirtual 36	android/os/Parcel:writeStrongBinder	(Landroid/os/IBinder;)V
    //   62: aload 5
    //   64: aload_3
    //   65: invokevirtual 98	android/os/Parcel:writeString	(Ljava/lang/String;)V
    //   68: aload_0
    //   69: getfield 14	com/google/android/gms/wearable/internal/zzax$zza$zza:zzoz	Landroid/os/IBinder;
    //   72: astore 4
    //   74: bipush 34
    //   76: istore 8
    //   78: aload 4
    //   80: iload 8
    //   82: aload 5
    //   84: aload 6
    //   86: iconst_0
    //   87: invokeinterface 43 5 0
    //   92: pop
    //   93: aload 6
    //   95: invokevirtual 46	android/os/Parcel:readException	()V
    //   98: aload 6
    //   100: invokevirtual 49	android/os/Parcel:recycle	()V
    //   103: aload 5
    //   105: invokevirtual 49	android/os/Parcel:recycle	()V
    //   108: return
    //   109: iconst_0
    //   110: istore 8
    //   112: aconst_null
    //   113: astore 7
    //   115: goto -79 -> 36
    //   118: astore 4
    //   120: aload 6
    //   122: invokevirtual 49	android/os/Parcel:recycle	()V
    //   125: aload 5
    //   127: invokevirtual 49	android/os/Parcel:recycle	()V
    //   130: aload 4
    //   132: athrow
    // Local variable table:
    //   start	length	slot	name	signature
    //   0	133	0	this	zza
    //   0	133	1	paramzzav	zzav
    //   0	133	2	paramzzau	zzau
    //   0	133	3	paramString	String
    //   1	78	4	localIBinder	IBinder
    //   118	13	4	localObject1	Object
    //   6	120	5	localParcel1	android.os.Parcel
    //   11	110	6	localParcel2	android.os.Parcel
    //   15	99	7	localObject2	Object
    //   76	35	8	i	int
    // Exception table:
    //   from	to	target	type
    //   19	24	118	finally
    //   28	34	118	finally
    //   38	43	118	finally
    //   47	53	118	finally
    //   57	62	118	finally
    //   64	68	118	finally
    //   68	72	118	finally
    //   86	93	118	finally
    //   93	98	118	finally
  }
  
  /* Error */
  public void zza(zzav paramzzav, String paramString)
  {
    // Byte code:
    //   0: invokestatic 20	android/os/Parcel:obtain	()Landroid/os/Parcel;
    //   3: astore_3
    //   4: invokestatic 20	android/os/Parcel:obtain	()Landroid/os/Parcel;
    //   7: astore 4
    //   9: ldc 22
    //   11: astore 5
    //   13: aload_3
    //   14: aload 5
    //   16: invokevirtual 26	android/os/Parcel:writeInterfaceToken	(Ljava/lang/String;)V
    //   19: aload_1
    //   20: ifnull +61 -> 81
    //   23: aload_1
    //   24: invokeinterface 32 1 0
    //   29: astore 5
    //   31: aload_3
    //   32: aload 5
    //   34: invokevirtual 36	android/os/Parcel:writeStrongBinder	(Landroid/os/IBinder;)V
    //   37: aload_3
    //   38: aload_2
    //   39: invokevirtual 98	android/os/Parcel:writeString	(Ljava/lang/String;)V
    //   42: aload_0
    //   43: getfield 14	com/google/android/gms/wearable/internal/zzax$zza$zza:zzoz	Landroid/os/IBinder;
    //   46: astore 5
    //   48: bipush 21
    //   50: istore 6
    //   52: aload 5
    //   54: iload 6
    //   56: aload_3
    //   57: aload 4
    //   59: iconst_0
    //   60: invokeinterface 43 5 0
    //   65: pop
    //   66: aload 4
    //   68: invokevirtual 46	android/os/Parcel:readException	()V
    //   71: aload 4
    //   73: invokevirtual 49	android/os/Parcel:recycle	()V
    //   76: aload_3
    //   77: invokevirtual 49	android/os/Parcel:recycle	()V
    //   80: return
    //   81: aconst_null
    //   82: astore 5
    //   84: goto -53 -> 31
    //   87: astore 5
    //   89: aload 4
    //   91: invokevirtual 49	android/os/Parcel:recycle	()V
    //   94: aload_3
    //   95: invokevirtual 49	android/os/Parcel:recycle	()V
    //   98: aload 5
    //   100: athrow
    // Local variable table:
    //   start	length	slot	name	signature
    //   0	101	0	this	zza
    //   0	101	1	paramzzav	zzav
    //   0	101	2	paramString	String
    //   3	92	3	localParcel1	android.os.Parcel
    //   7	83	4	localParcel2	android.os.Parcel
    //   11	72	5	localObject1	Object
    //   87	12	5	localObject2	Object
    //   50	5	6	i	int
    // Exception table:
    //   from	to	target	type
    //   14	19	87	finally
    //   23	29	87	finally
    //   32	37	87	finally
    //   38	42	87	finally
    //   42	46	87	finally
    //   59	66	87	finally
    //   66	71	87	finally
  }
  
  /* Error */
  public void zza(zzav paramzzav, String paramString, int paramInt)
  {
    // Byte code:
    //   0: invokestatic 20	android/os/Parcel:obtain	()Landroid/os/Parcel;
    //   3: astore 4
    //   5: invokestatic 20	android/os/Parcel:obtain	()Landroid/os/Parcel;
    //   8: astore 5
    //   10: ldc 22
    //   12: astore 6
    //   14: aload 4
    //   16: aload 6
    //   18: invokevirtual 26	android/os/Parcel:writeInterfaceToken	(Ljava/lang/String;)V
    //   21: aload_1
    //   22: ifnull +71 -> 93
    //   25: aload_1
    //   26: invokeinterface 32 1 0
    //   31: astore 6
    //   33: aload 4
    //   35: aload 6
    //   37: invokevirtual 36	android/os/Parcel:writeStrongBinder	(Landroid/os/IBinder;)V
    //   40: aload 4
    //   42: aload_2
    //   43: invokevirtual 98	android/os/Parcel:writeString	(Ljava/lang/String;)V
    //   46: aload 4
    //   48: iload_3
    //   49: invokevirtual 58	android/os/Parcel:writeInt	(I)V
    //   52: aload_0
    //   53: getfield 14	com/google/android/gms/wearable/internal/zzax$zza$zza:zzoz	Landroid/os/IBinder;
    //   56: astore 6
    //   58: bipush 42
    //   60: istore 7
    //   62: aload 6
    //   64: iload 7
    //   66: aload 4
    //   68: aload 5
    //   70: iconst_0
    //   71: invokeinterface 43 5 0
    //   76: pop
    //   77: aload 5
    //   79: invokevirtual 46	android/os/Parcel:readException	()V
    //   82: aload 5
    //   84: invokevirtual 49	android/os/Parcel:recycle	()V
    //   87: aload 4
    //   89: invokevirtual 49	android/os/Parcel:recycle	()V
    //   92: return
    //   93: aconst_null
    //   94: astore 6
    //   96: goto -63 -> 33
    //   99: astore 6
    //   101: aload 5
    //   103: invokevirtual 49	android/os/Parcel:recycle	()V
    //   106: aload 4
    //   108: invokevirtual 49	android/os/Parcel:recycle	()V
    //   111: aload 6
    //   113: athrow
    // Local variable table:
    //   start	length	slot	name	signature
    //   0	114	0	this	zza
    //   0	114	1	paramzzav	zzav
    //   0	114	2	paramString	String
    //   0	114	3	paramInt	int
    //   3	104	4	localParcel1	android.os.Parcel
    //   8	94	5	localParcel2	android.os.Parcel
    //   12	83	6	localObject1	Object
    //   99	13	6	localObject2	Object
    //   60	5	7	i	int
    // Exception table:
    //   from	to	target	type
    //   16	21	99	finally
    //   25	31	99	finally
    //   35	40	99	finally
    //   42	46	99	finally
    //   48	52	99	finally
    //   52	56	99	finally
    //   70	77	99	finally
    //   77	82	99	finally
  }
  
  /* Error */
  public void zza(zzav paramzzav, String paramString, android.os.ParcelFileDescriptor paramParcelFileDescriptor)
  {
    // Byte code:
    //   0: invokestatic 20	android/os/Parcel:obtain	()Landroid/os/Parcel;
    //   3: astore 4
    //   5: invokestatic 20	android/os/Parcel:obtain	()Landroid/os/Parcel;
    //   8: astore 5
    //   10: ldc 22
    //   12: astore 6
    //   14: aload 4
    //   16: aload 6
    //   18: invokevirtual 26	android/os/Parcel:writeInterfaceToken	(Ljava/lang/String;)V
    //   21: aload_1
    //   22: ifnull +92 -> 114
    //   25: aload_1
    //   26: invokeinterface 32 1 0
    //   31: astore 6
    //   33: aload 4
    //   35: aload 6
    //   37: invokevirtual 36	android/os/Parcel:writeStrongBinder	(Landroid/os/IBinder;)V
    //   40: aload 4
    //   42: aload_2
    //   43: invokevirtual 98	android/os/Parcel:writeString	(Ljava/lang/String;)V
    //   46: aload_3
    //   47: ifnull +76 -> 123
    //   50: iconst_1
    //   51: istore 7
    //   53: aload 4
    //   55: iload 7
    //   57: invokevirtual 58	android/os/Parcel:writeInt	(I)V
    //   60: iconst_0
    //   61: istore 7
    //   63: aconst_null
    //   64: astore 6
    //   66: aload_3
    //   67: aload 4
    //   69: iconst_0
    //   70: invokevirtual 104	android/os/ParcelFileDescriptor:writeToParcel	(Landroid/os/Parcel;I)V
    //   73: aload_0
    //   74: getfield 14	com/google/android/gms/wearable/internal/zzax$zza$zza:zzoz	Landroid/os/IBinder;
    //   77: astore 6
    //   79: bipush 38
    //   81: istore 8
    //   83: aload 6
    //   85: iload 8
    //   87: aload 4
    //   89: aload 5
    //   91: iconst_0
    //   92: invokeinterface 43 5 0
    //   97: pop
    //   98: aload 5
    //   100: invokevirtual 46	android/os/Parcel:readException	()V
    //   103: aload 5
    //   105: invokevirtual 49	android/os/Parcel:recycle	()V
    //   108: aload 4
    //   110: invokevirtual 49	android/os/Parcel:recycle	()V
    //   113: return
    //   114: iconst_0
    //   115: istore 7
    //   117: aconst_null
    //   118: astore 6
    //   120: goto -87 -> 33
    //   123: iconst_0
    //   124: istore 7
    //   126: aconst_null
    //   127: astore 6
    //   129: aload 4
    //   131: iconst_0
    //   132: invokevirtual 58	android/os/Parcel:writeInt	(I)V
    //   135: goto -62 -> 73
    //   138: astore 6
    //   140: aload 5
    //   142: invokevirtual 49	android/os/Parcel:recycle	()V
    //   145: aload 4
    //   147: invokevirtual 49	android/os/Parcel:recycle	()V
    //   150: aload 6
    //   152: athrow
    // Local variable table:
    //   start	length	slot	name	signature
    //   0	153	0	this	zza
    //   0	153	1	paramzzav	zzav
    //   0	153	2	paramString	String
    //   0	153	3	paramParcelFileDescriptor	android.os.ParcelFileDescriptor
    //   3	143	4	localParcel1	android.os.Parcel
    //   8	133	5	localParcel2	android.os.Parcel
    //   12	116	6	localObject1	Object
    //   138	13	6	localObject2	Object
    //   51	74	7	i	int
    //   81	5	8	j	int
    // Exception table:
    //   from	to	target	type
    //   16	21	138	finally
    //   25	31	138	finally
    //   35	40	138	finally
    //   42	46	138	finally
    //   55	60	138	finally
    //   69	73	138	finally
    //   73	77	138	finally
    //   91	98	138	finally
    //   98	103	138	finally
    //   131	135	138	finally
  }
  
  /* Error */
  public void zza(zzav paramzzav, String paramString, android.os.ParcelFileDescriptor paramParcelFileDescriptor, long paramLong1, long paramLong2)
  {
    // Byte code:
    //   0: invokestatic 20	android/os/Parcel:obtain	()Landroid/os/Parcel;
    //   3: astore 8
    //   5: invokestatic 20	android/os/Parcel:obtain	()Landroid/os/Parcel;
    //   8: astore 9
    //   10: ldc 22
    //   12: astore 10
    //   14: aload 8
    //   16: aload 10
    //   18: invokevirtual 26	android/os/Parcel:writeInterfaceToken	(Ljava/lang/String;)V
    //   21: aload_1
    //   22: ifnull +106 -> 128
    //   25: aload_1
    //   26: invokeinterface 32 1 0
    //   31: astore 10
    //   33: aload 8
    //   35: aload 10
    //   37: invokevirtual 36	android/os/Parcel:writeStrongBinder	(Landroid/os/IBinder;)V
    //   40: aload 8
    //   42: aload_2
    //   43: invokevirtual 98	android/os/Parcel:writeString	(Ljava/lang/String;)V
    //   46: aload_3
    //   47: ifnull +90 -> 137
    //   50: iconst_1
    //   51: istore 11
    //   53: aload 8
    //   55: iload 11
    //   57: invokevirtual 58	android/os/Parcel:writeInt	(I)V
    //   60: iconst_0
    //   61: istore 11
    //   63: aconst_null
    //   64: astore 10
    //   66: aload_3
    //   67: aload 8
    //   69: iconst_0
    //   70: invokevirtual 104	android/os/ParcelFileDescriptor:writeToParcel	(Landroid/os/Parcel;I)V
    //   73: aload 8
    //   75: lload 4
    //   77: invokevirtual 109	android/os/Parcel:writeLong	(J)V
    //   80: aload 8
    //   82: lload 6
    //   84: invokevirtual 109	android/os/Parcel:writeLong	(J)V
    //   87: aload_0
    //   88: getfield 14	com/google/android/gms/wearable/internal/zzax$zza$zza:zzoz	Landroid/os/IBinder;
    //   91: astore 10
    //   93: bipush 39
    //   95: istore 12
    //   97: aload 10
    //   99: iload 12
    //   101: aload 8
    //   103: aload 9
    //   105: iconst_0
    //   106: invokeinterface 43 5 0
    //   111: pop
    //   112: aload 9
    //   114: invokevirtual 46	android/os/Parcel:readException	()V
    //   117: aload 9
    //   119: invokevirtual 49	android/os/Parcel:recycle	()V
    //   122: aload 8
    //   124: invokevirtual 49	android/os/Parcel:recycle	()V
    //   127: return
    //   128: iconst_0
    //   129: istore 11
    //   131: aconst_null
    //   132: astore 10
    //   134: goto -101 -> 33
    //   137: iconst_0
    //   138: istore 11
    //   140: aconst_null
    //   141: astore 10
    //   143: aload 8
    //   145: iconst_0
    //   146: invokevirtual 58	android/os/Parcel:writeInt	(I)V
    //   149: goto -76 -> 73
    //   152: astore 10
    //   154: aload 9
    //   156: invokevirtual 49	android/os/Parcel:recycle	()V
    //   159: aload 8
    //   161: invokevirtual 49	android/os/Parcel:recycle	()V
    //   164: aload 10
    //   166: athrow
    // Local variable table:
    //   start	length	slot	name	signature
    //   0	167	0	this	zza
    //   0	167	1	paramzzav	zzav
    //   0	167	2	paramString	String
    //   0	167	3	paramParcelFileDescriptor	android.os.ParcelFileDescriptor
    //   0	167	4	paramLong1	long
    //   0	167	6	paramLong2	long
    //   3	157	8	localParcel1	android.os.Parcel
    //   8	147	9	localParcel2	android.os.Parcel
    //   12	130	10	localObject1	Object
    //   152	13	10	localObject2	Object
    //   51	88	11	i	int
    //   95	5	12	j	int
    // Exception table:
    //   from	to	target	type
    //   16	21	152	finally
    //   25	31	152	finally
    //   35	40	152	finally
    //   42	46	152	finally
    //   55	60	152	finally
    //   69	73	152	finally
    //   75	80	152	finally
    //   82	87	152	finally
    //   87	91	152	finally
    //   105	112	152	finally
    //   112	117	152	finally
    //   145	149	152	finally
  }
  
  /* Error */
  public void zza(zzav paramzzav, String paramString1, String paramString2)
  {
    // Byte code:
    //   0: invokestatic 20	android/os/Parcel:obtain	()Landroid/os/Parcel;
    //   3: astore 4
    //   5: invokestatic 20	android/os/Parcel:obtain	()Landroid/os/Parcel;
    //   8: astore 5
    //   10: ldc 22
    //   12: astore 6
    //   14: aload 4
    //   16: aload 6
    //   18: invokevirtual 26	android/os/Parcel:writeInterfaceToken	(Ljava/lang/String;)V
    //   21: aload_1
    //   22: ifnull +71 -> 93
    //   25: aload_1
    //   26: invokeinterface 32 1 0
    //   31: astore 6
    //   33: aload 4
    //   35: aload 6
    //   37: invokevirtual 36	android/os/Parcel:writeStrongBinder	(Landroid/os/IBinder;)V
    //   40: aload 4
    //   42: aload_2
    //   43: invokevirtual 98	android/os/Parcel:writeString	(Ljava/lang/String;)V
    //   46: aload 4
    //   48: aload_3
    //   49: invokevirtual 98	android/os/Parcel:writeString	(Ljava/lang/String;)V
    //   52: aload_0
    //   53: getfield 14	com/google/android/gms/wearable/internal/zzax$zza$zza:zzoz	Landroid/os/IBinder;
    //   56: astore 6
    //   58: bipush 31
    //   60: istore 7
    //   62: aload 6
    //   64: iload 7
    //   66: aload 4
    //   68: aload 5
    //   70: iconst_0
    //   71: invokeinterface 43 5 0
    //   76: pop
    //   77: aload 5
    //   79: invokevirtual 46	android/os/Parcel:readException	()V
    //   82: aload 5
    //   84: invokevirtual 49	android/os/Parcel:recycle	()V
    //   87: aload 4
    //   89: invokevirtual 49	android/os/Parcel:recycle	()V
    //   92: return
    //   93: aconst_null
    //   94: astore 6
    //   96: goto -63 -> 33
    //   99: astore 6
    //   101: aload 5
    //   103: invokevirtual 49	android/os/Parcel:recycle	()V
    //   106: aload 4
    //   108: invokevirtual 49	android/os/Parcel:recycle	()V
    //   111: aload 6
    //   113: athrow
    // Local variable table:
    //   start	length	slot	name	signature
    //   0	114	0	this	zza
    //   0	114	1	paramzzav	zzav
    //   0	114	2	paramString1	String
    //   0	114	3	paramString2	String
    //   3	104	4	localParcel1	android.os.Parcel
    //   8	94	5	localParcel2	android.os.Parcel
    //   12	83	6	localObject1	Object
    //   99	13	6	localObject2	Object
    //   60	5	7	i	int
    // Exception table:
    //   from	to	target	type
    //   16	21	99	finally
    //   25	31	99	finally
    //   35	40	99	finally
    //   42	46	99	finally
    //   48	52	99	finally
    //   52	56	99	finally
    //   70	77	99	finally
    //   77	82	99	finally
  }
  
  /* Error */
  public void zza(zzav paramzzav, String paramString1, String paramString2, byte[] paramArrayOfByte)
  {
    // Byte code:
    //   0: invokestatic 20	android/os/Parcel:obtain	()Landroid/os/Parcel;
    //   3: astore 5
    //   5: invokestatic 20	android/os/Parcel:obtain	()Landroid/os/Parcel;
    //   8: astore 6
    //   10: ldc 22
    //   12: astore 7
    //   14: aload 5
    //   16: aload 7
    //   18: invokevirtual 26	android/os/Parcel:writeInterfaceToken	(Ljava/lang/String;)V
    //   21: aload_1
    //   22: ifnull +78 -> 100
    //   25: aload_1
    //   26: invokeinterface 32 1 0
    //   31: astore 7
    //   33: aload 5
    //   35: aload 7
    //   37: invokevirtual 36	android/os/Parcel:writeStrongBinder	(Landroid/os/IBinder;)V
    //   40: aload 5
    //   42: aload_2
    //   43: invokevirtual 98	android/os/Parcel:writeString	(Ljava/lang/String;)V
    //   46: aload 5
    //   48: aload_3
    //   49: invokevirtual 98	android/os/Parcel:writeString	(Ljava/lang/String;)V
    //   52: aload 5
    //   54: aload 4
    //   56: invokevirtual 115	android/os/Parcel:writeByteArray	([B)V
    //   59: aload_0
    //   60: getfield 14	com/google/android/gms/wearable/internal/zzax$zza$zza:zzoz	Landroid/os/IBinder;
    //   63: astore 7
    //   65: bipush 12
    //   67: istore 8
    //   69: aload 7
    //   71: iload 8
    //   73: aload 5
    //   75: aload 6
    //   77: iconst_0
    //   78: invokeinterface 43 5 0
    //   83: pop
    //   84: aload 6
    //   86: invokevirtual 46	android/os/Parcel:readException	()V
    //   89: aload 6
    //   91: invokevirtual 49	android/os/Parcel:recycle	()V
    //   94: aload 5
    //   96: invokevirtual 49	android/os/Parcel:recycle	()V
    //   99: return
    //   100: aconst_null
    //   101: astore 7
    //   103: goto -70 -> 33
    //   106: astore 7
    //   108: aload 6
    //   110: invokevirtual 49	android/os/Parcel:recycle	()V
    //   113: aload 5
    //   115: invokevirtual 49	android/os/Parcel:recycle	()V
    //   118: aload 7
    //   120: athrow
    // Local variable table:
    //   start	length	slot	name	signature
    //   0	121	0	this	zza
    //   0	121	1	paramzzav	zzav
    //   0	121	2	paramString1	String
    //   0	121	3	paramString2	String
    //   0	121	4	paramArrayOfByte	byte[]
    //   3	111	5	localParcel1	android.os.Parcel
    //   8	101	6	localParcel2	android.os.Parcel
    //   12	90	7	localObject1	Object
    //   106	13	7	localObject2	Object
    //   67	5	8	i	int
    // Exception table:
    //   from	to	target	type
    //   16	21	106	finally
    //   25	31	106	finally
    //   35	40	106	finally
    //   42	46	106	finally
    //   48	52	106	finally
    //   54	59	106	finally
    //   59	63	106	finally
    //   77	84	106	finally
    //   84	89	106	finally
  }
  
  /* Error */
  public void zza(zzav paramzzav, boolean paramBoolean)
  {
    // Byte code:
    //   0: iconst_0
    //   1: istore_3
    //   2: aconst_null
    //   3: astore 4
    //   5: invokestatic 20	android/os/Parcel:obtain	()Landroid/os/Parcel;
    //   8: astore 5
    //   10: invokestatic 20	android/os/Parcel:obtain	()Landroid/os/Parcel;
    //   13: astore 6
    //   15: ldc 22
    //   17: astore 7
    //   19: aload 5
    //   21: aload 7
    //   23: invokevirtual 26	android/os/Parcel:writeInterfaceToken	(Ljava/lang/String;)V
    //   26: aload_1
    //   27: ifnull +71 -> 98
    //   30: aload_1
    //   31: invokeinterface 32 1 0
    //   36: astore 7
    //   38: aload 5
    //   40: aload 7
    //   42: invokevirtual 36	android/os/Parcel:writeStrongBinder	(Landroid/os/IBinder;)V
    //   45: iload_2
    //   46: ifeq +5 -> 51
    //   49: iconst_1
    //   50: istore_3
    //   51: aload 5
    //   53: iload_3
    //   54: invokevirtual 58	android/os/Parcel:writeInt	(I)V
    //   57: aload_0
    //   58: getfield 14	com/google/android/gms/wearable/internal/zzax$zza$zza:zzoz	Landroid/os/IBinder;
    //   61: astore 4
    //   63: bipush 48
    //   65: istore 8
    //   67: aload 4
    //   69: iload 8
    //   71: aload 5
    //   73: aload 6
    //   75: iconst_0
    //   76: invokeinterface 43 5 0
    //   81: pop
    //   82: aload 6
    //   84: invokevirtual 46	android/os/Parcel:readException	()V
    //   87: aload 6
    //   89: invokevirtual 49	android/os/Parcel:recycle	()V
    //   92: aload 5
    //   94: invokevirtual 49	android/os/Parcel:recycle	()V
    //   97: return
    //   98: iconst_0
    //   99: istore 8
    //   101: aconst_null
    //   102: astore 7
    //   104: goto -66 -> 38
    //   107: astore 4
    //   109: aload 6
    //   111: invokevirtual 49	android/os/Parcel:recycle	()V
    //   114: aload 5
    //   116: invokevirtual 49	android/os/Parcel:recycle	()V
    //   119: aload 4
    //   121: athrow
    // Local variable table:
    //   start	length	slot	name	signature
    //   0	122	0	this	zza
    //   0	122	1	paramzzav	zzav
    //   0	122	2	paramBoolean	boolean
    //   1	53	3	i	int
    //   3	65	4	localIBinder	IBinder
    //   107	13	4	localObject1	Object
    //   8	107	5	localParcel1	android.os.Parcel
    //   13	97	6	localParcel2	android.os.Parcel
    //   17	86	7	localObject2	Object
    //   65	35	8	j	int
    // Exception table:
    //   from	to	target	type
    //   21	26	107	finally
    //   30	36	107	finally
    //   40	45	107	finally
    //   53	57	107	finally
    //   57	61	107	finally
    //   75	82	107	finally
    //   82	87	107	finally
  }
  
  /* Error */
  public void zzb(zzav paramzzav)
  {
    // Byte code:
    //   0: invokestatic 20	android/os/Parcel:obtain	()Landroid/os/Parcel;
    //   3: astore_2
    //   4: invokestatic 20	android/os/Parcel:obtain	()Landroid/os/Parcel;
    //   7: astore_3
    //   8: ldc 22
    //   10: astore 4
    //   12: aload_2
    //   13: aload 4
    //   15: invokevirtual 26	android/os/Parcel:writeInterfaceToken	(Ljava/lang/String;)V
    //   18: aload_1
    //   19: ifnull +53 -> 72
    //   22: aload_1
    //   23: invokeinterface 32 1 0
    //   28: astore 4
    //   30: aload_2
    //   31: aload 4
    //   33: invokevirtual 36	android/os/Parcel:writeStrongBinder	(Landroid/os/IBinder;)V
    //   36: aload_0
    //   37: getfield 14	com/google/android/gms/wearable/internal/zzax$zza$zza:zzoz	Landroid/os/IBinder;
    //   40: astore 4
    //   42: bipush 8
    //   44: istore 5
    //   46: aload 4
    //   48: iload 5
    //   50: aload_2
    //   51: aload_3
    //   52: iconst_0
    //   53: invokeinterface 43 5 0
    //   58: pop
    //   59: aload_3
    //   60: invokevirtual 46	android/os/Parcel:readException	()V
    //   63: aload_3
    //   64: invokevirtual 49	android/os/Parcel:recycle	()V
    //   67: aload_2
    //   68: invokevirtual 49	android/os/Parcel:recycle	()V
    //   71: return
    //   72: aconst_null
    //   73: astore 4
    //   75: goto -45 -> 30
    //   78: astore 4
    //   80: aload_3
    //   81: invokevirtual 49	android/os/Parcel:recycle	()V
    //   84: aload_2
    //   85: invokevirtual 49	android/os/Parcel:recycle	()V
    //   88: aload 4
    //   90: athrow
    // Local variable table:
    //   start	length	slot	name	signature
    //   0	91	0	this	zza
    //   0	91	1	paramzzav	zzav
    //   3	82	2	localParcel1	android.os.Parcel
    //   7	74	3	localParcel2	android.os.Parcel
    //   10	64	4	localObject1	Object
    //   78	11	4	localObject2	Object
    //   44	5	5	i	int
    // Exception table:
    //   from	to	target	type
    //   13	18	78	finally
    //   22	28	78	finally
    //   31	36	78	finally
    //   36	40	78	finally
    //   52	59	78	finally
    //   59	63	78	finally
  }
  
  /* Error */
  public void zzb(zzav paramzzav, int paramInt)
  {
    // Byte code:
    //   0: invokestatic 20	android/os/Parcel:obtain	()Landroid/os/Parcel;
    //   3: astore_3
    //   4: invokestatic 20	android/os/Parcel:obtain	()Landroid/os/Parcel;
    //   7: astore 4
    //   9: ldc 22
    //   11: astore 5
    //   13: aload_3
    //   14: aload 5
    //   16: invokevirtual 26	android/os/Parcel:writeInterfaceToken	(Ljava/lang/String;)V
    //   19: aload_1
    //   20: ifnull +61 -> 81
    //   23: aload_1
    //   24: invokeinterface 32 1 0
    //   29: astore 5
    //   31: aload_3
    //   32: aload 5
    //   34: invokevirtual 36	android/os/Parcel:writeStrongBinder	(Landroid/os/IBinder;)V
    //   37: aload_3
    //   38: iload_2
    //   39: invokevirtual 58	android/os/Parcel:writeInt	(I)V
    //   42: aload_0
    //   43: getfield 14	com/google/android/gms/wearable/internal/zzax$zza$zza:zzoz	Landroid/os/IBinder;
    //   46: astore 5
    //   48: bipush 28
    //   50: istore 6
    //   52: aload 5
    //   54: iload 6
    //   56: aload_3
    //   57: aload 4
    //   59: iconst_0
    //   60: invokeinterface 43 5 0
    //   65: pop
    //   66: aload 4
    //   68: invokevirtual 46	android/os/Parcel:readException	()V
    //   71: aload 4
    //   73: invokevirtual 49	android/os/Parcel:recycle	()V
    //   76: aload_3
    //   77: invokevirtual 49	android/os/Parcel:recycle	()V
    //   80: return
    //   81: aconst_null
    //   82: astore 5
    //   84: goto -53 -> 31
    //   87: astore 5
    //   89: aload 4
    //   91: invokevirtual 49	android/os/Parcel:recycle	()V
    //   94: aload_3
    //   95: invokevirtual 49	android/os/Parcel:recycle	()V
    //   98: aload 5
    //   100: athrow
    // Local variable table:
    //   start	length	slot	name	signature
    //   0	101	0	this	zza
    //   0	101	1	paramzzav	zzav
    //   0	101	2	paramInt	int
    //   3	92	3	localParcel1	android.os.Parcel
    //   7	83	4	localParcel2	android.os.Parcel
    //   11	72	5	localObject1	Object
    //   87	12	5	localObject2	Object
    //   50	5	6	i	int
    // Exception table:
    //   from	to	target	type
    //   14	19	87	finally
    //   23	29	87	finally
    //   32	37	87	finally
    //   38	42	87	finally
    //   42	46	87	finally
    //   59	66	87	finally
    //   66	71	87	finally
  }
  
  /* Error */
  public void zzb(zzav paramzzav, android.net.Uri paramUri)
  {
    // Byte code:
    //   0: invokestatic 20	android/os/Parcel:obtain	()Landroid/os/Parcel;
    //   3: astore_3
    //   4: invokestatic 20	android/os/Parcel:obtain	()Landroid/os/Parcel;
    //   7: astore 4
    //   9: ldc 22
    //   11: astore 5
    //   13: aload_3
    //   14: aload 5
    //   16: invokevirtual 26	android/os/Parcel:writeInterfaceToken	(Ljava/lang/String;)V
    //   19: aload_1
    //   20: ifnull +81 -> 101
    //   23: aload_1
    //   24: invokeinterface 32 1 0
    //   29: astore 5
    //   31: aload_3
    //   32: aload 5
    //   34: invokevirtual 36	android/os/Parcel:writeStrongBinder	(Landroid/os/IBinder;)V
    //   37: aload_2
    //   38: ifnull +72 -> 110
    //   41: iconst_1
    //   42: istore 6
    //   44: aload_3
    //   45: iload 6
    //   47: invokevirtual 58	android/os/Parcel:writeInt	(I)V
    //   50: iconst_0
    //   51: istore 6
    //   53: aconst_null
    //   54: astore 5
    //   56: aload_2
    //   57: aload_3
    //   58: iconst_0
    //   59: invokevirtual 66	android/net/Uri:writeToParcel	(Landroid/os/Parcel;I)V
    //   62: aload_0
    //   63: getfield 14	com/google/android/gms/wearable/internal/zzax$zza$zza:zzoz	Landroid/os/IBinder;
    //   66: astore 5
    //   68: bipush 9
    //   70: istore 7
    //   72: aload 5
    //   74: iload 7
    //   76: aload_3
    //   77: aload 4
    //   79: iconst_0
    //   80: invokeinterface 43 5 0
    //   85: pop
    //   86: aload 4
    //   88: invokevirtual 46	android/os/Parcel:readException	()V
    //   91: aload 4
    //   93: invokevirtual 49	android/os/Parcel:recycle	()V
    //   96: aload_3
    //   97: invokevirtual 49	android/os/Parcel:recycle	()V
    //   100: return
    //   101: iconst_0
    //   102: istore 6
    //   104: aconst_null
    //   105: astore 5
    //   107: goto -76 -> 31
    //   110: iconst_0
    //   111: istore 6
    //   113: aconst_null
    //   114: astore 5
    //   116: aload_3
    //   117: iconst_0
    //   118: invokevirtual 58	android/os/Parcel:writeInt	(I)V
    //   121: goto -59 -> 62
    //   124: astore 5
    //   126: aload 4
    //   128: invokevirtual 49	android/os/Parcel:recycle	()V
    //   131: aload_3
    //   132: invokevirtual 49	android/os/Parcel:recycle	()V
    //   135: aload 5
    //   137: athrow
    // Local variable table:
    //   start	length	slot	name	signature
    //   0	138	0	this	zza
    //   0	138	1	paramzzav	zzav
    //   0	138	2	paramUri	android.net.Uri
    //   3	129	3	localParcel1	android.os.Parcel
    //   7	120	4	localParcel2	android.os.Parcel
    //   11	104	5	localObject1	Object
    //   124	12	5	localObject2	Object
    //   42	70	6	i	int
    //   70	5	7	j	int
    // Exception table:
    //   from	to	target	type
    //   14	19	124	finally
    //   23	29	124	finally
    //   32	37	124	finally
    //   45	50	124	finally
    //   58	62	124	finally
    //   62	66	124	finally
    //   79	86	124	finally
    //   86	91	124	finally
    //   117	121	124	finally
  }
  
  /* Error */
  public void zzb(zzav paramzzav, android.net.Uri paramUri, int paramInt)
  {
    // Byte code:
    //   0: invokestatic 20	android/os/Parcel:obtain	()Landroid/os/Parcel;
    //   3: astore 4
    //   5: invokestatic 20	android/os/Parcel:obtain	()Landroid/os/Parcel;
    //   8: astore 5
    //   10: ldc 22
    //   12: astore 6
    //   14: aload 4
    //   16: aload 6
    //   18: invokevirtual 26	android/os/Parcel:writeInterfaceToken	(Ljava/lang/String;)V
    //   21: aload_1
    //   22: ifnull +92 -> 114
    //   25: aload_1
    //   26: invokeinterface 32 1 0
    //   31: astore 6
    //   33: aload 4
    //   35: aload 6
    //   37: invokevirtual 36	android/os/Parcel:writeStrongBinder	(Landroid/os/IBinder;)V
    //   40: aload_2
    //   41: ifnull +82 -> 123
    //   44: iconst_1
    //   45: istore 7
    //   47: aload 4
    //   49: iload 7
    //   51: invokevirtual 58	android/os/Parcel:writeInt	(I)V
    //   54: iconst_0
    //   55: istore 7
    //   57: aconst_null
    //   58: astore 6
    //   60: aload_2
    //   61: aload 4
    //   63: iconst_0
    //   64: invokevirtual 66	android/net/Uri:writeToParcel	(Landroid/os/Parcel;I)V
    //   67: aload 4
    //   69: iload_3
    //   70: invokevirtual 58	android/os/Parcel:writeInt	(I)V
    //   73: aload_0
    //   74: getfield 14	com/google/android/gms/wearable/internal/zzax$zza$zza:zzoz	Landroid/os/IBinder;
    //   77: astore 6
    //   79: bipush 41
    //   81: istore 8
    //   83: aload 6
    //   85: iload 8
    //   87: aload 4
    //   89: aload 5
    //   91: iconst_0
    //   92: invokeinterface 43 5 0
    //   97: pop
    //   98: aload 5
    //   100: invokevirtual 46	android/os/Parcel:readException	()V
    //   103: aload 5
    //   105: invokevirtual 49	android/os/Parcel:recycle	()V
    //   108: aload 4
    //   110: invokevirtual 49	android/os/Parcel:recycle	()V
    //   113: return
    //   114: iconst_0
    //   115: istore 7
    //   117: aconst_null
    //   118: astore 6
    //   120: goto -87 -> 33
    //   123: iconst_0
    //   124: istore 7
    //   126: aconst_null
    //   127: astore 6
    //   129: aload 4
    //   131: iconst_0
    //   132: invokevirtual 58	android/os/Parcel:writeInt	(I)V
    //   135: goto -68 -> 67
    //   138: astore 6
    //   140: aload 5
    //   142: invokevirtual 49	android/os/Parcel:recycle	()V
    //   145: aload 4
    //   147: invokevirtual 49	android/os/Parcel:recycle	()V
    //   150: aload 6
    //   152: athrow
    // Local variable table:
    //   start	length	slot	name	signature
    //   0	153	0	this	zza
    //   0	153	1	paramzzav	zzav
    //   0	153	2	paramUri	android.net.Uri
    //   0	153	3	paramInt	int
    //   3	143	4	localParcel1	android.os.Parcel
    //   8	133	5	localParcel2	android.os.Parcel
    //   12	116	6	localObject1	Object
    //   138	13	6	localObject2	Object
    //   45	80	7	i	int
    //   81	5	8	j	int
    // Exception table:
    //   from	to	target	type
    //   16	21	138	finally
    //   25	31	138	finally
    //   35	40	138	finally
    //   49	54	138	finally
    //   63	67	138	finally
    //   69	73	138	finally
    //   73	77	138	finally
    //   91	98	138	finally
    //   98	103	138	finally
    //   131	135	138	finally
  }
  
  /* Error */
  public void zzb(zzav paramzzav, com.google.android.gms.wearable.ConnectionConfiguration paramConnectionConfiguration)
  {
    // Byte code:
    //   0: invokestatic 20	android/os/Parcel:obtain	()Landroid/os/Parcel;
    //   3: astore_3
    //   4: invokestatic 20	android/os/Parcel:obtain	()Landroid/os/Parcel;
    //   7: astore 4
    //   9: ldc 22
    //   11: astore 5
    //   13: aload_3
    //   14: aload 5
    //   16: invokevirtual 26	android/os/Parcel:writeInterfaceToken	(Ljava/lang/String;)V
    //   19: aload_1
    //   20: ifnull +80 -> 100
    //   23: aload_1
    //   24: invokeinterface 32 1 0
    //   29: astore 5
    //   31: aload_3
    //   32: aload 5
    //   34: invokevirtual 36	android/os/Parcel:writeStrongBinder	(Landroid/os/IBinder;)V
    //   37: aload_2
    //   38: ifnull +71 -> 109
    //   41: iconst_1
    //   42: istore 6
    //   44: aload_3
    //   45: iload 6
    //   47: invokevirtual 58	android/os/Parcel:writeInt	(I)V
    //   50: iconst_0
    //   51: istore 6
    //   53: aconst_null
    //   54: astore 5
    //   56: aload_2
    //   57: aload_3
    //   58: iconst_0
    //   59: invokevirtual 75	com/google/android/gms/wearable/ConnectionConfiguration:writeToParcel	(Landroid/os/Parcel;I)V
    //   62: aload_0
    //   63: getfield 14	com/google/android/gms/wearable/internal/zzax$zza$zza:zzoz	Landroid/os/IBinder;
    //   66: astore 5
    //   68: iconst_2
    //   69: istore 7
    //   71: aload 5
    //   73: iload 7
    //   75: aload_3
    //   76: aload 4
    //   78: iconst_0
    //   79: invokeinterface 43 5 0
    //   84: pop
    //   85: aload 4
    //   87: invokevirtual 46	android/os/Parcel:readException	()V
    //   90: aload 4
    //   92: invokevirtual 49	android/os/Parcel:recycle	()V
    //   95: aload_3
    //   96: invokevirtual 49	android/os/Parcel:recycle	()V
    //   99: return
    //   100: iconst_0
    //   101: istore 6
    //   103: aconst_null
    //   104: astore 5
    //   106: goto -75 -> 31
    //   109: iconst_0
    //   110: istore 6
    //   112: aconst_null
    //   113: astore 5
    //   115: aload_3
    //   116: iconst_0
    //   117: invokevirtual 58	android/os/Parcel:writeInt	(I)V
    //   120: goto -58 -> 62
    //   123: astore 5
    //   125: aload 4
    //   127: invokevirtual 49	android/os/Parcel:recycle	()V
    //   130: aload_3
    //   131: invokevirtual 49	android/os/Parcel:recycle	()V
    //   134: aload 5
    //   136: athrow
    // Local variable table:
    //   start	length	slot	name	signature
    //   0	137	0	this	zza
    //   0	137	1	paramzzav	zzav
    //   0	137	2	paramConnectionConfiguration	com.google.android.gms.wearable.ConnectionConfiguration
    //   3	128	3	localParcel1	android.os.Parcel
    //   7	119	4	localParcel2	android.os.Parcel
    //   11	103	5	localObject1	Object
    //   123	12	5	localObject2	Object
    //   42	69	6	i	int
    //   69	5	7	j	int
    // Exception table:
    //   from	to	target	type
    //   14	19	123	finally
    //   23	29	123	finally
    //   32	37	123	finally
    //   45	50	123	finally
    //   58	62	123	finally
    //   62	66	123	finally
    //   78	85	123	finally
    //   85	90	123	finally
    //   116	120	123	finally
  }
  
  /* Error */
  public void zzb(zzav paramzzav, zzau paramzzau, String paramString)
  {
    // Byte code:
    //   0: aconst_null
    //   1: astore 4
    //   3: invokestatic 20	android/os/Parcel:obtain	()Landroid/os/Parcel;
    //   6: astore 5
    //   8: invokestatic 20	android/os/Parcel:obtain	()Landroid/os/Parcel;
    //   11: astore 6
    //   13: ldc 22
    //   15: astore 7
    //   17: aload 5
    //   19: aload 7
    //   21: invokevirtual 26	android/os/Parcel:writeInterfaceToken	(Ljava/lang/String;)V
    //   24: aload_1
    //   25: ifnull +84 -> 109
    //   28: aload_1
    //   29: invokeinterface 32 1 0
    //   34: astore 7
    //   36: aload 5
    //   38: aload 7
    //   40: invokevirtual 36	android/os/Parcel:writeStrongBinder	(Landroid/os/IBinder;)V
    //   43: aload_2
    //   44: ifnull +11 -> 55
    //   47: aload_2
    //   48: invokeinterface 95 1 0
    //   53: astore 4
    //   55: aload 5
    //   57: aload 4
    //   59: invokevirtual 36	android/os/Parcel:writeStrongBinder	(Landroid/os/IBinder;)V
    //   62: aload 5
    //   64: aload_3
    //   65: invokevirtual 98	android/os/Parcel:writeString	(Ljava/lang/String;)V
    //   68: aload_0
    //   69: getfield 14	com/google/android/gms/wearable/internal/zzax$zza$zza:zzoz	Landroid/os/IBinder;
    //   72: astore 4
    //   74: bipush 35
    //   76: istore 8
    //   78: aload 4
    //   80: iload 8
    //   82: aload 5
    //   84: aload 6
    //   86: iconst_0
    //   87: invokeinterface 43 5 0
    //   92: pop
    //   93: aload 6
    //   95: invokevirtual 46	android/os/Parcel:readException	()V
    //   98: aload 6
    //   100: invokevirtual 49	android/os/Parcel:recycle	()V
    //   103: aload 5
    //   105: invokevirtual 49	android/os/Parcel:recycle	()V
    //   108: return
    //   109: iconst_0
    //   110: istore 8
    //   112: aconst_null
    //   113: astore 7
    //   115: goto -79 -> 36
    //   118: astore 4
    //   120: aload 6
    //   122: invokevirtual 49	android/os/Parcel:recycle	()V
    //   125: aload 5
    //   127: invokevirtual 49	android/os/Parcel:recycle	()V
    //   130: aload 4
    //   132: athrow
    // Local variable table:
    //   start	length	slot	name	signature
    //   0	133	0	this	zza
    //   0	133	1	paramzzav	zzav
    //   0	133	2	paramzzau	zzau
    //   0	133	3	paramString	String
    //   1	78	4	localIBinder	IBinder
    //   118	13	4	localObject1	Object
    //   6	120	5	localParcel1	android.os.Parcel
    //   11	110	6	localParcel2	android.os.Parcel
    //   15	99	7	localObject2	Object
    //   76	35	8	i	int
    // Exception table:
    //   from	to	target	type
    //   19	24	118	finally
    //   28	34	118	finally
    //   38	43	118	finally
    //   47	53	118	finally
    //   57	62	118	finally
    //   64	68	118	finally
    //   68	72	118	finally
    //   86	93	118	finally
    //   93	98	118	finally
  }
  
  /* Error */
  public void zzb(zzav paramzzav, String paramString)
  {
    // Byte code:
    //   0: invokestatic 20	android/os/Parcel:obtain	()Landroid/os/Parcel;
    //   3: astore_3
    //   4: invokestatic 20	android/os/Parcel:obtain	()Landroid/os/Parcel;
    //   7: astore 4
    //   9: ldc 22
    //   11: astore 5
    //   13: aload_3
    //   14: aload 5
    //   16: invokevirtual 26	android/os/Parcel:writeInterfaceToken	(Ljava/lang/String;)V
    //   19: aload_1
    //   20: ifnull +61 -> 81
    //   23: aload_1
    //   24: invokeinterface 32 1 0
    //   29: astore 5
    //   31: aload_3
    //   32: aload 5
    //   34: invokevirtual 36	android/os/Parcel:writeStrongBinder	(Landroid/os/IBinder;)V
    //   37: aload_3
    //   38: aload_2
    //   39: invokevirtual 98	android/os/Parcel:writeString	(Ljava/lang/String;)V
    //   42: aload_0
    //   43: getfield 14	com/google/android/gms/wearable/internal/zzax$zza$zza:zzoz	Landroid/os/IBinder;
    //   46: astore 5
    //   48: bipush 23
    //   50: istore 6
    //   52: aload 5
    //   54: iload 6
    //   56: aload_3
    //   57: aload 4
    //   59: iconst_0
    //   60: invokeinterface 43 5 0
    //   65: pop
    //   66: aload 4
    //   68: invokevirtual 46	android/os/Parcel:readException	()V
    //   71: aload 4
    //   73: invokevirtual 49	android/os/Parcel:recycle	()V
    //   76: aload_3
    //   77: invokevirtual 49	android/os/Parcel:recycle	()V
    //   80: return
    //   81: aconst_null
    //   82: astore 5
    //   84: goto -53 -> 31
    //   87: astore 5
    //   89: aload 4
    //   91: invokevirtual 49	android/os/Parcel:recycle	()V
    //   94: aload_3
    //   95: invokevirtual 49	android/os/Parcel:recycle	()V
    //   98: aload 5
    //   100: athrow
    // Local variable table:
    //   start	length	slot	name	signature
    //   0	101	0	this	zza
    //   0	101	1	paramzzav	zzav
    //   0	101	2	paramString	String
    //   3	92	3	localParcel1	android.os.Parcel
    //   7	83	4	localParcel2	android.os.Parcel
    //   11	72	5	localObject1	Object
    //   87	12	5	localObject2	Object
    //   50	5	6	i	int
    // Exception table:
    //   from	to	target	type
    //   14	19	87	finally
    //   23	29	87	finally
    //   32	37	87	finally
    //   38	42	87	finally
    //   42	46	87	finally
    //   59	66	87	finally
    //   66	71	87	finally
  }
  
  /* Error */
  public void zzb(zzav paramzzav, String paramString, int paramInt)
  {
    // Byte code:
    //   0: invokestatic 20	android/os/Parcel:obtain	()Landroid/os/Parcel;
    //   3: astore 4
    //   5: invokestatic 20	android/os/Parcel:obtain	()Landroid/os/Parcel;
    //   8: astore 5
    //   10: ldc 22
    //   12: astore 6
    //   14: aload 4
    //   16: aload 6
    //   18: invokevirtual 26	android/os/Parcel:writeInterfaceToken	(Ljava/lang/String;)V
    //   21: aload_1
    //   22: ifnull +71 -> 93
    //   25: aload_1
    //   26: invokeinterface 32 1 0
    //   31: astore 6
    //   33: aload 4
    //   35: aload 6
    //   37: invokevirtual 36	android/os/Parcel:writeStrongBinder	(Landroid/os/IBinder;)V
    //   40: aload 4
    //   42: aload_2
    //   43: invokevirtual 98	android/os/Parcel:writeString	(Ljava/lang/String;)V
    //   46: aload 4
    //   48: iload_3
    //   49: invokevirtual 58	android/os/Parcel:writeInt	(I)V
    //   52: aload_0
    //   53: getfield 14	com/google/android/gms/wearable/internal/zzax$zza$zza:zzoz	Landroid/os/IBinder;
    //   56: astore 6
    //   58: bipush 33
    //   60: istore 7
    //   62: aload 6
    //   64: iload 7
    //   66: aload 4
    //   68: aload 5
    //   70: iconst_0
    //   71: invokeinterface 43 5 0
    //   76: pop
    //   77: aload 5
    //   79: invokevirtual 46	android/os/Parcel:readException	()V
    //   82: aload 5
    //   84: invokevirtual 49	android/os/Parcel:recycle	()V
    //   87: aload 4
    //   89: invokevirtual 49	android/os/Parcel:recycle	()V
    //   92: return
    //   93: aconst_null
    //   94: astore 6
    //   96: goto -63 -> 33
    //   99: astore 6
    //   101: aload 5
    //   103: invokevirtual 49	android/os/Parcel:recycle	()V
    //   106: aload 4
    //   108: invokevirtual 49	android/os/Parcel:recycle	()V
    //   111: aload 6
    //   113: athrow
    // Local variable table:
    //   start	length	slot	name	signature
    //   0	114	0	this	zza
    //   0	114	1	paramzzav	zzav
    //   0	114	2	paramString	String
    //   0	114	3	paramInt	int
    //   3	104	4	localParcel1	android.os.Parcel
    //   8	94	5	localParcel2	android.os.Parcel
    //   12	83	6	localObject1	Object
    //   99	13	6	localObject2	Object
    //   60	5	7	i	int
    // Exception table:
    //   from	to	target	type
    //   16	21	99	finally
    //   25	31	99	finally
    //   35	40	99	finally
    //   42	46	99	finally
    //   48	52	99	finally
    //   52	56	99	finally
    //   70	77	99	finally
    //   77	82	99	finally
  }
  
  /* Error */
  public void zzb(zzav paramzzav, boolean paramBoolean)
  {
    // Byte code:
    //   0: iconst_0
    //   1: istore_3
    //   2: aconst_null
    //   3: astore 4
    //   5: invokestatic 20	android/os/Parcel:obtain	()Landroid/os/Parcel;
    //   8: astore 5
    //   10: invokestatic 20	android/os/Parcel:obtain	()Landroid/os/Parcel;
    //   13: astore 6
    //   15: ldc 22
    //   17: astore 7
    //   19: aload 5
    //   21: aload 7
    //   23: invokevirtual 26	android/os/Parcel:writeInterfaceToken	(Ljava/lang/String;)V
    //   26: aload_1
    //   27: ifnull +71 -> 98
    //   30: aload_1
    //   31: invokeinterface 32 1 0
    //   36: astore 7
    //   38: aload 5
    //   40: aload 7
    //   42: invokevirtual 36	android/os/Parcel:writeStrongBinder	(Landroid/os/IBinder;)V
    //   45: iload_2
    //   46: ifeq +5 -> 51
    //   49: iconst_1
    //   50: istore_3
    //   51: aload 5
    //   53: iload_3
    //   54: invokevirtual 58	android/os/Parcel:writeInt	(I)V
    //   57: aload_0
    //   58: getfield 14	com/google/android/gms/wearable/internal/zzax$zza$zza:zzoz	Landroid/os/IBinder;
    //   61: astore 4
    //   63: bipush 50
    //   65: istore 8
    //   67: aload 4
    //   69: iload 8
    //   71: aload 5
    //   73: aload 6
    //   75: iconst_0
    //   76: invokeinterface 43 5 0
    //   81: pop
    //   82: aload 6
    //   84: invokevirtual 46	android/os/Parcel:readException	()V
    //   87: aload 6
    //   89: invokevirtual 49	android/os/Parcel:recycle	()V
    //   92: aload 5
    //   94: invokevirtual 49	android/os/Parcel:recycle	()V
    //   97: return
    //   98: iconst_0
    //   99: istore 8
    //   101: aconst_null
    //   102: astore 7
    //   104: goto -66 -> 38
    //   107: astore 4
    //   109: aload 6
    //   111: invokevirtual 49	android/os/Parcel:recycle	()V
    //   114: aload 5
    //   116: invokevirtual 49	android/os/Parcel:recycle	()V
    //   119: aload 4
    //   121: athrow
    // Local variable table:
    //   start	length	slot	name	signature
    //   0	122	0	this	zza
    //   0	122	1	paramzzav	zzav
    //   0	122	2	paramBoolean	boolean
    //   1	53	3	i	int
    //   3	65	4	localIBinder	IBinder
    //   107	13	4	localObject1	Object
    //   8	107	5	localParcel1	android.os.Parcel
    //   13	97	6	localParcel2	android.os.Parcel
    //   17	86	7	localObject2	Object
    //   65	35	8	j	int
    // Exception table:
    //   from	to	target	type
    //   21	26	107	finally
    //   30	36	107	finally
    //   40	45	107	finally
    //   53	57	107	finally
    //   57	61	107	finally
    //   75	82	107	finally
    //   82	87	107	finally
  }
  
  /* Error */
  public void zzc(zzav paramzzav)
  {
    // Byte code:
    //   0: invokestatic 20	android/os/Parcel:obtain	()Landroid/os/Parcel;
    //   3: astore_2
    //   4: invokestatic 20	android/os/Parcel:obtain	()Landroid/os/Parcel;
    //   7: astore_3
    //   8: ldc 22
    //   10: astore 4
    //   12: aload_2
    //   13: aload 4
    //   15: invokevirtual 26	android/os/Parcel:writeInterfaceToken	(Ljava/lang/String;)V
    //   18: aload_1
    //   19: ifnull +53 -> 72
    //   22: aload_1
    //   23: invokeinterface 32 1 0
    //   28: astore 4
    //   30: aload_2
    //   31: aload 4
    //   33: invokevirtual 36	android/os/Parcel:writeStrongBinder	(Landroid/os/IBinder;)V
    //   36: aload_0
    //   37: getfield 14	com/google/android/gms/wearable/internal/zzax$zza$zza:zzoz	Landroid/os/IBinder;
    //   40: astore 4
    //   42: bipush 14
    //   44: istore 5
    //   46: aload 4
    //   48: iload 5
    //   50: aload_2
    //   51: aload_3
    //   52: iconst_0
    //   53: invokeinterface 43 5 0
    //   58: pop
    //   59: aload_3
    //   60: invokevirtual 46	android/os/Parcel:readException	()V
    //   63: aload_3
    //   64: invokevirtual 49	android/os/Parcel:recycle	()V
    //   67: aload_2
    //   68: invokevirtual 49	android/os/Parcel:recycle	()V
    //   71: return
    //   72: aconst_null
    //   73: astore 4
    //   75: goto -45 -> 30
    //   78: astore 4
    //   80: aload_3
    //   81: invokevirtual 49	android/os/Parcel:recycle	()V
    //   84: aload_2
    //   85: invokevirtual 49	android/os/Parcel:recycle	()V
    //   88: aload 4
    //   90: athrow
    // Local variable table:
    //   start	length	slot	name	signature
    //   0	91	0	this	zza
    //   0	91	1	paramzzav	zzav
    //   3	82	2	localParcel1	android.os.Parcel
    //   7	74	3	localParcel2	android.os.Parcel
    //   10	64	4	localObject1	Object
    //   78	11	4	localObject2	Object
    //   44	5	5	i	int
    // Exception table:
    //   from	to	target	type
    //   13	18	78	finally
    //   22	28	78	finally
    //   31	36	78	finally
    //   36	40	78	finally
    //   52	59	78	finally
    //   59	63	78	finally
  }
  
  /* Error */
  public void zzc(zzav paramzzav, int paramInt)
  {
    // Byte code:
    //   0: invokestatic 20	android/os/Parcel:obtain	()Landroid/os/Parcel;
    //   3: astore_3
    //   4: invokestatic 20	android/os/Parcel:obtain	()Landroid/os/Parcel;
    //   7: astore 4
    //   9: ldc 22
    //   11: astore 5
    //   13: aload_3
    //   14: aload 5
    //   16: invokevirtual 26	android/os/Parcel:writeInterfaceToken	(Ljava/lang/String;)V
    //   19: aload_1
    //   20: ifnull +61 -> 81
    //   23: aload_1
    //   24: invokeinterface 32 1 0
    //   29: astore 5
    //   31: aload_3
    //   32: aload 5
    //   34: invokevirtual 36	android/os/Parcel:writeStrongBinder	(Landroid/os/IBinder;)V
    //   37: aload_3
    //   38: iload_2
    //   39: invokevirtual 58	android/os/Parcel:writeInt	(I)V
    //   42: aload_0
    //   43: getfield 14	com/google/android/gms/wearable/internal/zzax$zza$zza:zzoz	Landroid/os/IBinder;
    //   46: astore 5
    //   48: bipush 29
    //   50: istore 6
    //   52: aload 5
    //   54: iload 6
    //   56: aload_3
    //   57: aload 4
    //   59: iconst_0
    //   60: invokeinterface 43 5 0
    //   65: pop
    //   66: aload 4
    //   68: invokevirtual 46	android/os/Parcel:readException	()V
    //   71: aload 4
    //   73: invokevirtual 49	android/os/Parcel:recycle	()V
    //   76: aload_3
    //   77: invokevirtual 49	android/os/Parcel:recycle	()V
    //   80: return
    //   81: aconst_null
    //   82: astore 5
    //   84: goto -53 -> 31
    //   87: astore 5
    //   89: aload 4
    //   91: invokevirtual 49	android/os/Parcel:recycle	()V
    //   94: aload_3
    //   95: invokevirtual 49	android/os/Parcel:recycle	()V
    //   98: aload 5
    //   100: athrow
    // Local variable table:
    //   start	length	slot	name	signature
    //   0	101	0	this	zza
    //   0	101	1	paramzzav	zzav
    //   0	101	2	paramInt	int
    //   3	92	3	localParcel1	android.os.Parcel
    //   7	83	4	localParcel2	android.os.Parcel
    //   11	72	5	localObject1	Object
    //   87	12	5	localObject2	Object
    //   50	5	6	i	int
    // Exception table:
    //   from	to	target	type
    //   14	19	87	finally
    //   23	29	87	finally
    //   32	37	87	finally
    //   38	42	87	finally
    //   42	46	87	finally
    //   59	66	87	finally
    //   66	71	87	finally
  }
  
  /* Error */
  public void zzc(zzav paramzzav, android.net.Uri paramUri)
  {
    // Byte code:
    //   0: invokestatic 20	android/os/Parcel:obtain	()Landroid/os/Parcel;
    //   3: astore_3
    //   4: invokestatic 20	android/os/Parcel:obtain	()Landroid/os/Parcel;
    //   7: astore 4
    //   9: ldc 22
    //   11: astore 5
    //   13: aload_3
    //   14: aload 5
    //   16: invokevirtual 26	android/os/Parcel:writeInterfaceToken	(Ljava/lang/String;)V
    //   19: aload_1
    //   20: ifnull +81 -> 101
    //   23: aload_1
    //   24: invokeinterface 32 1 0
    //   29: astore 5
    //   31: aload_3
    //   32: aload 5
    //   34: invokevirtual 36	android/os/Parcel:writeStrongBinder	(Landroid/os/IBinder;)V
    //   37: aload_2
    //   38: ifnull +72 -> 110
    //   41: iconst_1
    //   42: istore 6
    //   44: aload_3
    //   45: iload 6
    //   47: invokevirtual 58	android/os/Parcel:writeInt	(I)V
    //   50: iconst_0
    //   51: istore 6
    //   53: aconst_null
    //   54: astore 5
    //   56: aload_2
    //   57: aload_3
    //   58: iconst_0
    //   59: invokevirtual 66	android/net/Uri:writeToParcel	(Landroid/os/Parcel;I)V
    //   62: aload_0
    //   63: getfield 14	com/google/android/gms/wearable/internal/zzax$zza$zza:zzoz	Landroid/os/IBinder;
    //   66: astore 5
    //   68: bipush 11
    //   70: istore 7
    //   72: aload 5
    //   74: iload 7
    //   76: aload_3
    //   77: aload 4
    //   79: iconst_0
    //   80: invokeinterface 43 5 0
    //   85: pop
    //   86: aload 4
    //   88: invokevirtual 46	android/os/Parcel:readException	()V
    //   91: aload 4
    //   93: invokevirtual 49	android/os/Parcel:recycle	()V
    //   96: aload_3
    //   97: invokevirtual 49	android/os/Parcel:recycle	()V
    //   100: return
    //   101: iconst_0
    //   102: istore 6
    //   104: aconst_null
    //   105: astore 5
    //   107: goto -76 -> 31
    //   110: iconst_0
    //   111: istore 6
    //   113: aconst_null
    //   114: astore 5
    //   116: aload_3
    //   117: iconst_0
    //   118: invokevirtual 58	android/os/Parcel:writeInt	(I)V
    //   121: goto -59 -> 62
    //   124: astore 5
    //   126: aload 4
    //   128: invokevirtual 49	android/os/Parcel:recycle	()V
    //   131: aload_3
    //   132: invokevirtual 49	android/os/Parcel:recycle	()V
    //   135: aload 5
    //   137: athrow
    // Local variable table:
    //   start	length	slot	name	signature
    //   0	138	0	this	zza
    //   0	138	1	paramzzav	zzav
    //   0	138	2	paramUri	android.net.Uri
    //   3	129	3	localParcel1	android.os.Parcel
    //   7	120	4	localParcel2	android.os.Parcel
    //   11	104	5	localObject1	Object
    //   124	12	5	localObject2	Object
    //   42	70	6	i	int
    //   70	5	7	j	int
    // Exception table:
    //   from	to	target	type
    //   14	19	124	finally
    //   23	29	124	finally
    //   32	37	124	finally
    //   45	50	124	finally
    //   58	62	124	finally
    //   62	66	124	finally
    //   79	86	124	finally
    //   86	91	124	finally
    //   117	121	124	finally
  }
  
  /* Error */
  public void zzc(zzav paramzzav, String paramString)
  {
    // Byte code:
    //   0: invokestatic 20	android/os/Parcel:obtain	()Landroid/os/Parcel;
    //   3: astore_3
    //   4: invokestatic 20	android/os/Parcel:obtain	()Landroid/os/Parcel;
    //   7: astore 4
    //   9: ldc 22
    //   11: astore 5
    //   13: aload_3
    //   14: aload 5
    //   16: invokevirtual 26	android/os/Parcel:writeInterfaceToken	(Ljava/lang/String;)V
    //   19: aload_1
    //   20: ifnull +61 -> 81
    //   23: aload_1
    //   24: invokeinterface 32 1 0
    //   29: astore 5
    //   31: aload_3
    //   32: aload 5
    //   34: invokevirtual 36	android/os/Parcel:writeStrongBinder	(Landroid/os/IBinder;)V
    //   37: aload_3
    //   38: aload_2
    //   39: invokevirtual 98	android/os/Parcel:writeString	(Ljava/lang/String;)V
    //   42: aload_0
    //   43: getfield 14	com/google/android/gms/wearable/internal/zzax$zza$zza:zzoz	Landroid/os/IBinder;
    //   46: astore 5
    //   48: bipush 24
    //   50: istore 6
    //   52: aload 5
    //   54: iload 6
    //   56: aload_3
    //   57: aload 4
    //   59: iconst_0
    //   60: invokeinterface 43 5 0
    //   65: pop
    //   66: aload 4
    //   68: invokevirtual 46	android/os/Parcel:readException	()V
    //   71: aload 4
    //   73: invokevirtual 49	android/os/Parcel:recycle	()V
    //   76: aload_3
    //   77: invokevirtual 49	android/os/Parcel:recycle	()V
    //   80: return
    //   81: aconst_null
    //   82: astore 5
    //   84: goto -53 -> 31
    //   87: astore 5
    //   89: aload 4
    //   91: invokevirtual 49	android/os/Parcel:recycle	()V
    //   94: aload_3
    //   95: invokevirtual 49	android/os/Parcel:recycle	()V
    //   98: aload 5
    //   100: athrow
    // Local variable table:
    //   start	length	slot	name	signature
    //   0	101	0	this	zza
    //   0	101	1	paramzzav	zzav
    //   0	101	2	paramString	String
    //   3	92	3	localParcel1	android.os.Parcel
    //   7	83	4	localParcel2	android.os.Parcel
    //   11	72	5	localObject1	Object
    //   87	12	5	localObject2	Object
    //   50	5	6	i	int
    // Exception table:
    //   from	to	target	type
    //   14	19	87	finally
    //   23	29	87	finally
    //   32	37	87	finally
    //   38	42	87	finally
    //   42	46	87	finally
    //   59	66	87	finally
    //   66	71	87	finally
  }
  
  /* Error */
  public void zzd(zzav paramzzav)
  {
    // Byte code:
    //   0: invokestatic 20	android/os/Parcel:obtain	()Landroid/os/Parcel;
    //   3: astore_2
    //   4: invokestatic 20	android/os/Parcel:obtain	()Landroid/os/Parcel;
    //   7: astore_3
    //   8: ldc 22
    //   10: astore 4
    //   12: aload_2
    //   13: aload 4
    //   15: invokevirtual 26	android/os/Parcel:writeInterfaceToken	(Ljava/lang/String;)V
    //   18: aload_1
    //   19: ifnull +53 -> 72
    //   22: aload_1
    //   23: invokeinterface 32 1 0
    //   28: astore 4
    //   30: aload_2
    //   31: aload 4
    //   33: invokevirtual 36	android/os/Parcel:writeStrongBinder	(Landroid/os/IBinder;)V
    //   36: aload_0
    //   37: getfield 14	com/google/android/gms/wearable/internal/zzax$zza$zza:zzoz	Landroid/os/IBinder;
    //   40: astore 4
    //   42: bipush 15
    //   44: istore 5
    //   46: aload 4
    //   48: iload 5
    //   50: aload_2
    //   51: aload_3
    //   52: iconst_0
    //   53: invokeinterface 43 5 0
    //   58: pop
    //   59: aload_3
    //   60: invokevirtual 46	android/os/Parcel:readException	()V
    //   63: aload_3
    //   64: invokevirtual 49	android/os/Parcel:recycle	()V
    //   67: aload_2
    //   68: invokevirtual 49	android/os/Parcel:recycle	()V
    //   71: return
    //   72: aconst_null
    //   73: astore 4
    //   75: goto -45 -> 30
    //   78: astore 4
    //   80: aload_3
    //   81: invokevirtual 49	android/os/Parcel:recycle	()V
    //   84: aload_2
    //   85: invokevirtual 49	android/os/Parcel:recycle	()V
    //   88: aload 4
    //   90: athrow
    // Local variable table:
    //   start	length	slot	name	signature
    //   0	91	0	this	zza
    //   0	91	1	paramzzav	zzav
    //   3	82	2	localParcel1	android.os.Parcel
    //   7	74	3	localParcel2	android.os.Parcel
    //   10	64	4	localObject1	Object
    //   78	11	4	localObject2	Object
    //   44	5	5	i	int
    // Exception table:
    //   from	to	target	type
    //   13	18	78	finally
    //   22	28	78	finally
    //   31	36	78	finally
    //   36	40	78	finally
    //   52	59	78	finally
    //   59	63	78	finally
  }
  
  /* Error */
  public void zzd(zzav paramzzav, String paramString)
  {
    // Byte code:
    //   0: invokestatic 20	android/os/Parcel:obtain	()Landroid/os/Parcel;
    //   3: astore_3
    //   4: invokestatic 20	android/os/Parcel:obtain	()Landroid/os/Parcel;
    //   7: astore 4
    //   9: ldc 22
    //   11: astore 5
    //   13: aload_3
    //   14: aload 5
    //   16: invokevirtual 26	android/os/Parcel:writeInterfaceToken	(Ljava/lang/String;)V
    //   19: aload_1
    //   20: ifnull +61 -> 81
    //   23: aload_1
    //   24: invokeinterface 32 1 0
    //   29: astore 5
    //   31: aload_3
    //   32: aload 5
    //   34: invokevirtual 36	android/os/Parcel:writeStrongBinder	(Landroid/os/IBinder;)V
    //   37: aload_3
    //   38: aload_2
    //   39: invokevirtual 98	android/os/Parcel:writeString	(Ljava/lang/String;)V
    //   42: aload_0
    //   43: getfield 14	com/google/android/gms/wearable/internal/zzax$zza$zza:zzoz	Landroid/os/IBinder;
    //   46: astore 5
    //   48: bipush 46
    //   50: istore 6
    //   52: aload 5
    //   54: iload 6
    //   56: aload_3
    //   57: aload 4
    //   59: iconst_0
    //   60: invokeinterface 43 5 0
    //   65: pop
    //   66: aload 4
    //   68: invokevirtual 46	android/os/Parcel:readException	()V
    //   71: aload 4
    //   73: invokevirtual 49	android/os/Parcel:recycle	()V
    //   76: aload_3
    //   77: invokevirtual 49	android/os/Parcel:recycle	()V
    //   80: return
    //   81: aconst_null
    //   82: astore 5
    //   84: goto -53 -> 31
    //   87: astore 5
    //   89: aload 4
    //   91: invokevirtual 49	android/os/Parcel:recycle	()V
    //   94: aload_3
    //   95: invokevirtual 49	android/os/Parcel:recycle	()V
    //   98: aload 5
    //   100: athrow
    // Local variable table:
    //   start	length	slot	name	signature
    //   0	101	0	this	zza
    //   0	101	1	paramzzav	zzav
    //   0	101	2	paramString	String
    //   3	92	3	localParcel1	android.os.Parcel
    //   7	83	4	localParcel2	android.os.Parcel
    //   11	72	5	localObject1	Object
    //   87	12	5	localObject2	Object
    //   50	5	6	i	int
    // Exception table:
    //   from	to	target	type
    //   14	19	87	finally
    //   23	29	87	finally
    //   32	37	87	finally
    //   38	42	87	finally
    //   42	46	87	finally
    //   59	66	87	finally
    //   66	71	87	finally
  }
  
  /* Error */
  public void zze(zzav paramzzav)
  {
    // Byte code:
    //   0: invokestatic 20	android/os/Parcel:obtain	()Landroid/os/Parcel;
    //   3: astore_2
    //   4: invokestatic 20	android/os/Parcel:obtain	()Landroid/os/Parcel;
    //   7: astore_3
    //   8: ldc 22
    //   10: astore 4
    //   12: aload_2
    //   13: aload 4
    //   15: invokevirtual 26	android/os/Parcel:writeInterfaceToken	(Ljava/lang/String;)V
    //   18: aload_1
    //   19: ifnull +53 -> 72
    //   22: aload_1
    //   23: invokeinterface 32 1 0
    //   28: astore 4
    //   30: aload_2
    //   31: aload 4
    //   33: invokevirtual 36	android/os/Parcel:writeStrongBinder	(Landroid/os/IBinder;)V
    //   36: aload_0
    //   37: getfield 14	com/google/android/gms/wearable/internal/zzax$zza$zza:zzoz	Landroid/os/IBinder;
    //   40: astore 4
    //   42: bipush 18
    //   44: istore 5
    //   46: aload 4
    //   48: iload 5
    //   50: aload_2
    //   51: aload_3
    //   52: iconst_0
    //   53: invokeinterface 43 5 0
    //   58: pop
    //   59: aload_3
    //   60: invokevirtual 46	android/os/Parcel:readException	()V
    //   63: aload_3
    //   64: invokevirtual 49	android/os/Parcel:recycle	()V
    //   67: aload_2
    //   68: invokevirtual 49	android/os/Parcel:recycle	()V
    //   71: return
    //   72: aconst_null
    //   73: astore 4
    //   75: goto -45 -> 30
    //   78: astore 4
    //   80: aload_3
    //   81: invokevirtual 49	android/os/Parcel:recycle	()V
    //   84: aload_2
    //   85: invokevirtual 49	android/os/Parcel:recycle	()V
    //   88: aload 4
    //   90: athrow
    // Local variable table:
    //   start	length	slot	name	signature
    //   0	91	0	this	zza
    //   0	91	1	paramzzav	zzav
    //   3	82	2	localParcel1	android.os.Parcel
    //   7	74	3	localParcel2	android.os.Parcel
    //   10	64	4	localObject1	Object
    //   78	11	4	localObject2	Object
    //   44	5	5	i	int
    // Exception table:
    //   from	to	target	type
    //   13	18	78	finally
    //   22	28	78	finally
    //   31	36	78	finally
    //   36	40	78	finally
    //   52	59	78	finally
    //   59	63	78	finally
  }
  
  /* Error */
  public void zze(zzav paramzzav, String paramString)
  {
    // Byte code:
    //   0: invokestatic 20	android/os/Parcel:obtain	()Landroid/os/Parcel;
    //   3: astore_3
    //   4: invokestatic 20	android/os/Parcel:obtain	()Landroid/os/Parcel;
    //   7: astore 4
    //   9: ldc 22
    //   11: astore 5
    //   13: aload_3
    //   14: aload 5
    //   16: invokevirtual 26	android/os/Parcel:writeInterfaceToken	(Ljava/lang/String;)V
    //   19: aload_1
    //   20: ifnull +61 -> 81
    //   23: aload_1
    //   24: invokeinterface 32 1 0
    //   29: astore 5
    //   31: aload_3
    //   32: aload 5
    //   34: invokevirtual 36	android/os/Parcel:writeStrongBinder	(Landroid/os/IBinder;)V
    //   37: aload_3
    //   38: aload_2
    //   39: invokevirtual 98	android/os/Parcel:writeString	(Ljava/lang/String;)V
    //   42: aload_0
    //   43: getfield 14	com/google/android/gms/wearable/internal/zzax$zza$zza:zzoz	Landroid/os/IBinder;
    //   46: astore 5
    //   48: bipush 47
    //   50: istore 6
    //   52: aload 5
    //   54: iload 6
    //   56: aload_3
    //   57: aload 4
    //   59: iconst_0
    //   60: invokeinterface 43 5 0
    //   65: pop
    //   66: aload 4
    //   68: invokevirtual 46	android/os/Parcel:readException	()V
    //   71: aload 4
    //   73: invokevirtual 49	android/os/Parcel:recycle	()V
    //   76: aload_3
    //   77: invokevirtual 49	android/os/Parcel:recycle	()V
    //   80: return
    //   81: aconst_null
    //   82: astore 5
    //   84: goto -53 -> 31
    //   87: astore 5
    //   89: aload 4
    //   91: invokevirtual 49	android/os/Parcel:recycle	()V
    //   94: aload_3
    //   95: invokevirtual 49	android/os/Parcel:recycle	()V
    //   98: aload 5
    //   100: athrow
    // Local variable table:
    //   start	length	slot	name	signature
    //   0	101	0	this	zza
    //   0	101	1	paramzzav	zzav
    //   0	101	2	paramString	String
    //   3	92	3	localParcel1	android.os.Parcel
    //   7	83	4	localParcel2	android.os.Parcel
    //   11	72	5	localObject1	Object
    //   87	12	5	localObject2	Object
    //   50	5	6	i	int
    // Exception table:
    //   from	to	target	type
    //   14	19	87	finally
    //   23	29	87	finally
    //   32	37	87	finally
    //   38	42	87	finally
    //   42	46	87	finally
    //   59	66	87	finally
    //   66	71	87	finally
  }
  
  /* Error */
  public void zzf(zzav paramzzav)
  {
    // Byte code:
    //   0: invokestatic 20	android/os/Parcel:obtain	()Landroid/os/Parcel;
    //   3: astore_2
    //   4: invokestatic 20	android/os/Parcel:obtain	()Landroid/os/Parcel;
    //   7: astore_3
    //   8: ldc 22
    //   10: astore 4
    //   12: aload_2
    //   13: aload 4
    //   15: invokevirtual 26	android/os/Parcel:writeInterfaceToken	(Ljava/lang/String;)V
    //   18: aload_1
    //   19: ifnull +53 -> 72
    //   22: aload_1
    //   23: invokeinterface 32 1 0
    //   28: astore 4
    //   30: aload_2
    //   31: aload 4
    //   33: invokevirtual 36	android/os/Parcel:writeStrongBinder	(Landroid/os/IBinder;)V
    //   36: aload_0
    //   37: getfield 14	com/google/android/gms/wearable/internal/zzax$zza$zza:zzoz	Landroid/os/IBinder;
    //   40: astore 4
    //   42: bipush 19
    //   44: istore 5
    //   46: aload 4
    //   48: iload 5
    //   50: aload_2
    //   51: aload_3
    //   52: iconst_0
    //   53: invokeinterface 43 5 0
    //   58: pop
    //   59: aload_3
    //   60: invokevirtual 46	android/os/Parcel:readException	()V
    //   63: aload_3
    //   64: invokevirtual 49	android/os/Parcel:recycle	()V
    //   67: aload_2
    //   68: invokevirtual 49	android/os/Parcel:recycle	()V
    //   71: return
    //   72: aconst_null
    //   73: astore 4
    //   75: goto -45 -> 30
    //   78: astore 4
    //   80: aload_3
    //   81: invokevirtual 49	android/os/Parcel:recycle	()V
    //   84: aload_2
    //   85: invokevirtual 49	android/os/Parcel:recycle	()V
    //   88: aload 4
    //   90: athrow
    // Local variable table:
    //   start	length	slot	name	signature
    //   0	91	0	this	zza
    //   0	91	1	paramzzav	zzav
    //   3	82	2	localParcel1	android.os.Parcel
    //   7	74	3	localParcel2	android.os.Parcel
    //   10	64	4	localObject1	Object
    //   78	11	4	localObject2	Object
    //   44	5	5	i	int
    // Exception table:
    //   from	to	target	type
    //   13	18	78	finally
    //   22	28	78	finally
    //   31	36	78	finally
    //   36	40	78	finally
    //   52	59	78	finally
    //   59	63	78	finally
  }
  
  /* Error */
  public void zzf(zzav paramzzav, String paramString)
  {
    // Byte code:
    //   0: invokestatic 20	android/os/Parcel:obtain	()Landroid/os/Parcel;
    //   3: astore_3
    //   4: invokestatic 20	android/os/Parcel:obtain	()Landroid/os/Parcel;
    //   7: astore 4
    //   9: ldc 22
    //   11: astore 5
    //   13: aload_3
    //   14: aload 5
    //   16: invokevirtual 26	android/os/Parcel:writeInterfaceToken	(Ljava/lang/String;)V
    //   19: aload_1
    //   20: ifnull +61 -> 81
    //   23: aload_1
    //   24: invokeinterface 32 1 0
    //   29: astore 5
    //   31: aload_3
    //   32: aload 5
    //   34: invokevirtual 36	android/os/Parcel:writeStrongBinder	(Landroid/os/IBinder;)V
    //   37: aload_3
    //   38: aload_2
    //   39: invokevirtual 98	android/os/Parcel:writeString	(Ljava/lang/String;)V
    //   42: aload_0
    //   43: getfield 14	com/google/android/gms/wearable/internal/zzax$zza$zza:zzoz	Landroid/os/IBinder;
    //   46: astore 5
    //   48: bipush 32
    //   50: istore 6
    //   52: aload 5
    //   54: iload 6
    //   56: aload_3
    //   57: aload 4
    //   59: iconst_0
    //   60: invokeinterface 43 5 0
    //   65: pop
    //   66: aload 4
    //   68: invokevirtual 46	android/os/Parcel:readException	()V
    //   71: aload 4
    //   73: invokevirtual 49	android/os/Parcel:recycle	()V
    //   76: aload_3
    //   77: invokevirtual 49	android/os/Parcel:recycle	()V
    //   80: return
    //   81: aconst_null
    //   82: astore 5
    //   84: goto -53 -> 31
    //   87: astore 5
    //   89: aload 4
    //   91: invokevirtual 49	android/os/Parcel:recycle	()V
    //   94: aload_3
    //   95: invokevirtual 49	android/os/Parcel:recycle	()V
    //   98: aload 5
    //   100: athrow
    // Local variable table:
    //   start	length	slot	name	signature
    //   0	101	0	this	zza
    //   0	101	1	paramzzav	zzav
    //   0	101	2	paramString	String
    //   3	92	3	localParcel1	android.os.Parcel
    //   7	83	4	localParcel2	android.os.Parcel
    //   11	72	5	localObject1	Object
    //   87	12	5	localObject2	Object
    //   50	5	6	i	int
    // Exception table:
    //   from	to	target	type
    //   14	19	87	finally
    //   23	29	87	finally
    //   32	37	87	finally
    //   38	42	87	finally
    //   42	46	87	finally
    //   59	66	87	finally
    //   66	71	87	finally
  }
  
  /* Error */
  public void zzg(zzav paramzzav)
  {
    // Byte code:
    //   0: invokestatic 20	android/os/Parcel:obtain	()Landroid/os/Parcel;
    //   3: astore_2
    //   4: invokestatic 20	android/os/Parcel:obtain	()Landroid/os/Parcel;
    //   7: astore_3
    //   8: ldc 22
    //   10: astore 4
    //   12: aload_2
    //   13: aload 4
    //   15: invokevirtual 26	android/os/Parcel:writeInterfaceToken	(Ljava/lang/String;)V
    //   18: aload_1
    //   19: ifnull +53 -> 72
    //   22: aload_1
    //   23: invokeinterface 32 1 0
    //   28: astore 4
    //   30: aload_2
    //   31: aload 4
    //   33: invokevirtual 36	android/os/Parcel:writeStrongBinder	(Landroid/os/IBinder;)V
    //   36: aload_0
    //   37: getfield 14	com/google/android/gms/wearable/internal/zzax$zza$zza:zzoz	Landroid/os/IBinder;
    //   40: astore 4
    //   42: bipush 25
    //   44: istore 5
    //   46: aload 4
    //   48: iload 5
    //   50: aload_2
    //   51: aload_3
    //   52: iconst_0
    //   53: invokeinterface 43 5 0
    //   58: pop
    //   59: aload_3
    //   60: invokevirtual 46	android/os/Parcel:readException	()V
    //   63: aload_3
    //   64: invokevirtual 49	android/os/Parcel:recycle	()V
    //   67: aload_2
    //   68: invokevirtual 49	android/os/Parcel:recycle	()V
    //   71: return
    //   72: aconst_null
    //   73: astore 4
    //   75: goto -45 -> 30
    //   78: astore 4
    //   80: aload_3
    //   81: invokevirtual 49	android/os/Parcel:recycle	()V
    //   84: aload_2
    //   85: invokevirtual 49	android/os/Parcel:recycle	()V
    //   88: aload 4
    //   90: athrow
    // Local variable table:
    //   start	length	slot	name	signature
    //   0	91	0	this	zza
    //   0	91	1	paramzzav	zzav
    //   3	82	2	localParcel1	android.os.Parcel
    //   7	74	3	localParcel2	android.os.Parcel
    //   10	64	4	localObject1	Object
    //   78	11	4	localObject2	Object
    //   44	5	5	i	int
    // Exception table:
    //   from	to	target	type
    //   13	18	78	finally
    //   22	28	78	finally
    //   31	36	78	finally
    //   36	40	78	finally
    //   52	59	78	finally
    //   59	63	78	finally
  }
  
  /* Error */
  public void zzh(zzav paramzzav)
  {
    // Byte code:
    //   0: invokestatic 20	android/os/Parcel:obtain	()Landroid/os/Parcel;
    //   3: astore_2
    //   4: invokestatic 20	android/os/Parcel:obtain	()Landroid/os/Parcel;
    //   7: astore_3
    //   8: ldc 22
    //   10: astore 4
    //   12: aload_2
    //   13: aload 4
    //   15: invokevirtual 26	android/os/Parcel:writeInterfaceToken	(Ljava/lang/String;)V
    //   18: aload_1
    //   19: ifnull +53 -> 72
    //   22: aload_1
    //   23: invokeinterface 32 1 0
    //   28: astore 4
    //   30: aload_2
    //   31: aload 4
    //   33: invokevirtual 36	android/os/Parcel:writeStrongBinder	(Landroid/os/IBinder;)V
    //   36: aload_0
    //   37: getfield 14	com/google/android/gms/wearable/internal/zzax$zza$zza:zzoz	Landroid/os/IBinder;
    //   40: astore 4
    //   42: bipush 26
    //   44: istore 5
    //   46: aload 4
    //   48: iload 5
    //   50: aload_2
    //   51: aload_3
    //   52: iconst_0
    //   53: invokeinterface 43 5 0
    //   58: pop
    //   59: aload_3
    //   60: invokevirtual 46	android/os/Parcel:readException	()V
    //   63: aload_3
    //   64: invokevirtual 49	android/os/Parcel:recycle	()V
    //   67: aload_2
    //   68: invokevirtual 49	android/os/Parcel:recycle	()V
    //   71: return
    //   72: aconst_null
    //   73: astore 4
    //   75: goto -45 -> 30
    //   78: astore 4
    //   80: aload_3
    //   81: invokevirtual 49	android/os/Parcel:recycle	()V
    //   84: aload_2
    //   85: invokevirtual 49	android/os/Parcel:recycle	()V
    //   88: aload 4
    //   90: athrow
    // Local variable table:
    //   start	length	slot	name	signature
    //   0	91	0	this	zza
    //   0	91	1	paramzzav	zzav
    //   3	82	2	localParcel1	android.os.Parcel
    //   7	74	3	localParcel2	android.os.Parcel
    //   10	64	4	localObject1	Object
    //   78	11	4	localObject2	Object
    //   44	5	5	i	int
    // Exception table:
    //   from	to	target	type
    //   13	18	78	finally
    //   22	28	78	finally
    //   31	36	78	finally
    //   36	40	78	finally
    //   52	59	78	finally
    //   59	63	78	finally
  }
  
  /* Error */
  public void zzi(zzav paramzzav)
  {
    // Byte code:
    //   0: invokestatic 20	android/os/Parcel:obtain	()Landroid/os/Parcel;
    //   3: astore_2
    //   4: invokestatic 20	android/os/Parcel:obtain	()Landroid/os/Parcel;
    //   7: astore_3
    //   8: ldc 22
    //   10: astore 4
    //   12: aload_2
    //   13: aload 4
    //   15: invokevirtual 26	android/os/Parcel:writeInterfaceToken	(Ljava/lang/String;)V
    //   18: aload_1
    //   19: ifnull +53 -> 72
    //   22: aload_1
    //   23: invokeinterface 32 1 0
    //   28: astore 4
    //   30: aload_2
    //   31: aload 4
    //   33: invokevirtual 36	android/os/Parcel:writeStrongBinder	(Landroid/os/IBinder;)V
    //   36: aload_0
    //   37: getfield 14	com/google/android/gms/wearable/internal/zzax$zza$zza:zzoz	Landroid/os/IBinder;
    //   40: astore 4
    //   42: bipush 30
    //   44: istore 5
    //   46: aload 4
    //   48: iload 5
    //   50: aload_2
    //   51: aload_3
    //   52: iconst_0
    //   53: invokeinterface 43 5 0
    //   58: pop
    //   59: aload_3
    //   60: invokevirtual 46	android/os/Parcel:readException	()V
    //   63: aload_3
    //   64: invokevirtual 49	android/os/Parcel:recycle	()V
    //   67: aload_2
    //   68: invokevirtual 49	android/os/Parcel:recycle	()V
    //   71: return
    //   72: aconst_null
    //   73: astore 4
    //   75: goto -45 -> 30
    //   78: astore 4
    //   80: aload_3
    //   81: invokevirtual 49	android/os/Parcel:recycle	()V
    //   84: aload_2
    //   85: invokevirtual 49	android/os/Parcel:recycle	()V
    //   88: aload 4
    //   90: athrow
    // Local variable table:
    //   start	length	slot	name	signature
    //   0	91	0	this	zza
    //   0	91	1	paramzzav	zzav
    //   3	82	2	localParcel1	android.os.Parcel
    //   7	74	3	localParcel2	android.os.Parcel
    //   10	64	4	localObject1	Object
    //   78	11	4	localObject2	Object
    //   44	5	5	i	int
    // Exception table:
    //   from	to	target	type
    //   13	18	78	finally
    //   22	28	78	finally
    //   31	36	78	finally
    //   36	40	78	finally
    //   52	59	78	finally
    //   59	63	78	finally
  }
  
  /* Error */
  public void zzj(zzav paramzzav)
  {
    // Byte code:
    //   0: invokestatic 20	android/os/Parcel:obtain	()Landroid/os/Parcel;
    //   3: astore_2
    //   4: invokestatic 20	android/os/Parcel:obtain	()Landroid/os/Parcel;
    //   7: astore_3
    //   8: ldc 22
    //   10: astore 4
    //   12: aload_2
    //   13: aload 4
    //   15: invokevirtual 26	android/os/Parcel:writeInterfaceToken	(Ljava/lang/String;)V
    //   18: aload_1
    //   19: ifnull +53 -> 72
    //   22: aload_1
    //   23: invokeinterface 32 1 0
    //   28: astore 4
    //   30: aload_2
    //   31: aload 4
    //   33: invokevirtual 36	android/os/Parcel:writeStrongBinder	(Landroid/os/IBinder;)V
    //   36: aload_0
    //   37: getfield 14	com/google/android/gms/wearable/internal/zzax$zza$zza:zzoz	Landroid/os/IBinder;
    //   40: astore 4
    //   42: bipush 37
    //   44: istore 5
    //   46: aload 4
    //   48: iload 5
    //   50: aload_2
    //   51: aload_3
    //   52: iconst_0
    //   53: invokeinterface 43 5 0
    //   58: pop
    //   59: aload_3
    //   60: invokevirtual 46	android/os/Parcel:readException	()V
    //   63: aload_3
    //   64: invokevirtual 49	android/os/Parcel:recycle	()V
    //   67: aload_2
    //   68: invokevirtual 49	android/os/Parcel:recycle	()V
    //   71: return
    //   72: aconst_null
    //   73: astore 4
    //   75: goto -45 -> 30
    //   78: astore 4
    //   80: aload_3
    //   81: invokevirtual 49	android/os/Parcel:recycle	()V
    //   84: aload_2
    //   85: invokevirtual 49	android/os/Parcel:recycle	()V
    //   88: aload 4
    //   90: athrow
    // Local variable table:
    //   start	length	slot	name	signature
    //   0	91	0	this	zza
    //   0	91	1	paramzzav	zzav
    //   3	82	2	localParcel1	android.os.Parcel
    //   7	74	3	localParcel2	android.os.Parcel
    //   10	64	4	localObject1	Object
    //   78	11	4	localObject2	Object
    //   44	5	5	i	int
    // Exception table:
    //   from	to	target	type
    //   13	18	78	finally
    //   22	28	78	finally
    //   31	36	78	finally
    //   36	40	78	finally
    //   52	59	78	finally
    //   59	63	78	finally
  }
  
  /* Error */
  public void zzk(zzav paramzzav)
  {
    // Byte code:
    //   0: invokestatic 20	android/os/Parcel:obtain	()Landroid/os/Parcel;
    //   3: astore_2
    //   4: invokestatic 20	android/os/Parcel:obtain	()Landroid/os/Parcel;
    //   7: astore_3
    //   8: ldc 22
    //   10: astore 4
    //   12: aload_2
    //   13: aload 4
    //   15: invokevirtual 26	android/os/Parcel:writeInterfaceToken	(Ljava/lang/String;)V
    //   18: aload_1
    //   19: ifnull +53 -> 72
    //   22: aload_1
    //   23: invokeinterface 32 1 0
    //   28: astore 4
    //   30: aload_2
    //   31: aload 4
    //   33: invokevirtual 36	android/os/Parcel:writeStrongBinder	(Landroid/os/IBinder;)V
    //   36: aload_0
    //   37: getfield 14	com/google/android/gms/wearable/internal/zzax$zza$zza:zzoz	Landroid/os/IBinder;
    //   40: astore 4
    //   42: bipush 49
    //   44: istore 5
    //   46: aload 4
    //   48: iload 5
    //   50: aload_2
    //   51: aload_3
    //   52: iconst_0
    //   53: invokeinterface 43 5 0
    //   58: pop
    //   59: aload_3
    //   60: invokevirtual 46	android/os/Parcel:readException	()V
    //   63: aload_3
    //   64: invokevirtual 49	android/os/Parcel:recycle	()V
    //   67: aload_2
    //   68: invokevirtual 49	android/os/Parcel:recycle	()V
    //   71: return
    //   72: aconst_null
    //   73: astore 4
    //   75: goto -45 -> 30
    //   78: astore 4
    //   80: aload_3
    //   81: invokevirtual 49	android/os/Parcel:recycle	()V
    //   84: aload_2
    //   85: invokevirtual 49	android/os/Parcel:recycle	()V
    //   88: aload 4
    //   90: athrow
    // Local variable table:
    //   start	length	slot	name	signature
    //   0	91	0	this	zza
    //   0	91	1	paramzzav	zzav
    //   3	82	2	localParcel1	android.os.Parcel
    //   7	74	3	localParcel2	android.os.Parcel
    //   10	64	4	localObject1	Object
    //   78	11	4	localObject2	Object
    //   44	5	5	i	int
    // Exception table:
    //   from	to	target	type
    //   13	18	78	finally
    //   22	28	78	finally
    //   31	36	78	finally
    //   36	40	78	finally
    //   52	59	78	finally
    //   59	63	78	finally
  }
  
  /* Error */
  public void zzl(zzav paramzzav)
  {
    // Byte code:
    //   0: invokestatic 20	android/os/Parcel:obtain	()Landroid/os/Parcel;
    //   3: astore_2
    //   4: invokestatic 20	android/os/Parcel:obtain	()Landroid/os/Parcel;
    //   7: astore_3
    //   8: ldc 22
    //   10: astore 4
    //   12: aload_2
    //   13: aload 4
    //   15: invokevirtual 26	android/os/Parcel:writeInterfaceToken	(Ljava/lang/String;)V
    //   18: aload_1
    //   19: ifnull +53 -> 72
    //   22: aload_1
    //   23: invokeinterface 32 1 0
    //   28: astore 4
    //   30: aload_2
    //   31: aload 4
    //   33: invokevirtual 36	android/os/Parcel:writeStrongBinder	(Landroid/os/IBinder;)V
    //   36: aload_0
    //   37: getfield 14	com/google/android/gms/wearable/internal/zzax$zza$zza:zzoz	Landroid/os/IBinder;
    //   40: astore 4
    //   42: bipush 51
    //   44: istore 5
    //   46: aload 4
    //   48: iload 5
    //   50: aload_2
    //   51: aload_3
    //   52: iconst_0
    //   53: invokeinterface 43 5 0
    //   58: pop
    //   59: aload_3
    //   60: invokevirtual 46	android/os/Parcel:readException	()V
    //   63: aload_3
    //   64: invokevirtual 49	android/os/Parcel:recycle	()V
    //   67: aload_2
    //   68: invokevirtual 49	android/os/Parcel:recycle	()V
    //   71: return
    //   72: aconst_null
    //   73: astore 4
    //   75: goto -45 -> 30
    //   78: astore 4
    //   80: aload_3
    //   81: invokevirtual 49	android/os/Parcel:recycle	()V
    //   84: aload_2
    //   85: invokevirtual 49	android/os/Parcel:recycle	()V
    //   88: aload 4
    //   90: athrow
    // Local variable table:
    //   start	length	slot	name	signature
    //   0	91	0	this	zza
    //   0	91	1	paramzzav	zzav
    //   3	82	2	localParcel1	android.os.Parcel
    //   7	74	3	localParcel2	android.os.Parcel
    //   10	64	4	localObject1	Object
    //   78	11	4	localObject2	Object
    //   44	5	5	i	int
    // Exception table:
    //   from	to	target	type
    //   13	18	78	finally
    //   22	28	78	finally
    //   31	36	78	finally
    //   36	40	78	finally
    //   52	59	78	finally
    //   59	63	78	finally
  }
  
  /* Error */
  public void zzm(zzav paramzzav)
  {
    // Byte code:
    //   0: invokestatic 20	android/os/Parcel:obtain	()Landroid/os/Parcel;
    //   3: astore_2
    //   4: invokestatic 20	android/os/Parcel:obtain	()Landroid/os/Parcel;
    //   7: astore_3
    //   8: ldc 22
    //   10: astore 4
    //   12: aload_2
    //   13: aload 4
    //   15: invokevirtual 26	android/os/Parcel:writeInterfaceToken	(Ljava/lang/String;)V
    //   18: aload_1
    //   19: ifnull +53 -> 72
    //   22: aload_1
    //   23: invokeinterface 32 1 0
    //   28: astore 4
    //   30: aload_2
    //   31: aload 4
    //   33: invokevirtual 36	android/os/Parcel:writeStrongBinder	(Landroid/os/IBinder;)V
    //   36: aload_0
    //   37: getfield 14	com/google/android/gms/wearable/internal/zzax$zza$zza:zzoz	Landroid/os/IBinder;
    //   40: astore 4
    //   42: bipush 52
    //   44: istore 5
    //   46: aload 4
    //   48: iload 5
    //   50: aload_2
    //   51: aload_3
    //   52: iconst_0
    //   53: invokeinterface 43 5 0
    //   58: pop
    //   59: aload_3
    //   60: invokevirtual 46	android/os/Parcel:readException	()V
    //   63: aload_3
    //   64: invokevirtual 49	android/os/Parcel:recycle	()V
    //   67: aload_2
    //   68: invokevirtual 49	android/os/Parcel:recycle	()V
    //   71: return
    //   72: aconst_null
    //   73: astore 4
    //   75: goto -45 -> 30
    //   78: astore 4
    //   80: aload_3
    //   81: invokevirtual 49	android/os/Parcel:recycle	()V
    //   84: aload_2
    //   85: invokevirtual 49	android/os/Parcel:recycle	()V
    //   88: aload 4
    //   90: athrow
    // Local variable table:
    //   start	length	slot	name	signature
    //   0	91	0	this	zza
    //   0	91	1	paramzzav	zzav
    //   3	82	2	localParcel1	android.os.Parcel
    //   7	74	3	localParcel2	android.os.Parcel
    //   10	64	4	localObject1	Object
    //   78	11	4	localObject2	Object
    //   44	5	5	i	int
    // Exception table:
    //   from	to	target	type
    //   13	18	78	finally
    //   22	28	78	finally
    //   31	36	78	finally
    //   36	40	78	finally
    //   52	59	78	finally
    //   59	63	78	finally
  }
  
  /* Error */
  public void zzn(zzav paramzzav)
  {
    // Byte code:
    //   0: invokestatic 20	android/os/Parcel:obtain	()Landroid/os/Parcel;
    //   3: astore_2
    //   4: invokestatic 20	android/os/Parcel:obtain	()Landroid/os/Parcel;
    //   7: astore_3
    //   8: ldc 22
    //   10: astore 4
    //   12: aload_2
    //   13: aload 4
    //   15: invokevirtual 26	android/os/Parcel:writeInterfaceToken	(Ljava/lang/String;)V
    //   18: aload_1
    //   19: ifnull +52 -> 71
    //   22: aload_1
    //   23: invokeinterface 32 1 0
    //   28: astore 4
    //   30: aload_2
    //   31: aload 4
    //   33: invokevirtual 36	android/os/Parcel:writeStrongBinder	(Landroid/os/IBinder;)V
    //   36: aload_0
    //   37: getfield 14	com/google/android/gms/wearable/internal/zzax$zza$zza:zzoz	Landroid/os/IBinder;
    //   40: astore 4
    //   42: iconst_3
    //   43: istore 5
    //   45: aload 4
    //   47: iload 5
    //   49: aload_2
    //   50: aload_3
    //   51: iconst_0
    //   52: invokeinterface 43 5 0
    //   57: pop
    //   58: aload_3
    //   59: invokevirtual 46	android/os/Parcel:readException	()V
    //   62: aload_3
    //   63: invokevirtual 49	android/os/Parcel:recycle	()V
    //   66: aload_2
    //   67: invokevirtual 49	android/os/Parcel:recycle	()V
    //   70: return
    //   71: aconst_null
    //   72: astore 4
    //   74: goto -44 -> 30
    //   77: astore 4
    //   79: aload_3
    //   80: invokevirtual 49	android/os/Parcel:recycle	()V
    //   83: aload_2
    //   84: invokevirtual 49	android/os/Parcel:recycle	()V
    //   87: aload 4
    //   89: athrow
    // Local variable table:
    //   start	length	slot	name	signature
    //   0	90	0	this	zza
    //   0	90	1	paramzzav	zzav
    //   3	81	2	localParcel1	android.os.Parcel
    //   7	73	3	localParcel2	android.os.Parcel
    //   10	63	4	localObject1	Object
    //   77	11	4	localObject2	Object
    //   43	5	5	i	int
    // Exception table:
    //   from	to	target	type
    //   13	18	77	finally
    //   22	28	77	finally
    //   31	36	77	finally
    //   36	40	77	finally
    //   51	58	77	finally
    //   58	62	77	finally
  }
  
  /* Error */
  public void zzo(zzav paramzzav)
  {
    // Byte code:
    //   0: invokestatic 20	android/os/Parcel:obtain	()Landroid/os/Parcel;
    //   3: astore_2
    //   4: invokestatic 20	android/os/Parcel:obtain	()Landroid/os/Parcel;
    //   7: astore_3
    //   8: ldc 22
    //   10: astore 4
    //   12: aload_2
    //   13: aload 4
    //   15: invokevirtual 26	android/os/Parcel:writeInterfaceToken	(Ljava/lang/String;)V
    //   18: aload_1
    //   19: ifnull +52 -> 71
    //   22: aload_1
    //   23: invokeinterface 32 1 0
    //   28: astore 4
    //   30: aload_2
    //   31: aload 4
    //   33: invokevirtual 36	android/os/Parcel:writeStrongBinder	(Landroid/os/IBinder;)V
    //   36: aload_0
    //   37: getfield 14	com/google/android/gms/wearable/internal/zzax$zza$zza:zzoz	Landroid/os/IBinder;
    //   40: astore 4
    //   42: iconst_4
    //   43: istore 5
    //   45: aload 4
    //   47: iload 5
    //   49: aload_2
    //   50: aload_3
    //   51: iconst_0
    //   52: invokeinterface 43 5 0
    //   57: pop
    //   58: aload_3
    //   59: invokevirtual 46	android/os/Parcel:readException	()V
    //   62: aload_3
    //   63: invokevirtual 49	android/os/Parcel:recycle	()V
    //   66: aload_2
    //   67: invokevirtual 49	android/os/Parcel:recycle	()V
    //   70: return
    //   71: aconst_null
    //   72: astore 4
    //   74: goto -44 -> 30
    //   77: astore 4
    //   79: aload_3
    //   80: invokevirtual 49	android/os/Parcel:recycle	()V
    //   83: aload_2
    //   84: invokevirtual 49	android/os/Parcel:recycle	()V
    //   87: aload 4
    //   89: athrow
    // Local variable table:
    //   start	length	slot	name	signature
    //   0	90	0	this	zza
    //   0	90	1	paramzzav	zzav
    //   3	81	2	localParcel1	android.os.Parcel
    //   7	73	3	localParcel2	android.os.Parcel
    //   10	63	4	localObject1	Object
    //   77	11	4	localObject2	Object
    //   43	5	5	i	int
    // Exception table:
    //   from	to	target	type
    //   13	18	77	finally
    //   22	28	77	finally
    //   31	36	77	finally
    //   36	40	77	finally
    //   51	58	77	finally
    //   58	62	77	finally
  }
  
  /* Error */
  public void zzp(zzav paramzzav)
  {
    // Byte code:
    //   0: invokestatic 20	android/os/Parcel:obtain	()Landroid/os/Parcel;
    //   3: astore_2
    //   4: invokestatic 20	android/os/Parcel:obtain	()Landroid/os/Parcel;
    //   7: astore_3
    //   8: ldc 22
    //   10: astore 4
    //   12: aload_2
    //   13: aload 4
    //   15: invokevirtual 26	android/os/Parcel:writeInterfaceToken	(Ljava/lang/String;)V
    //   18: aload_1
    //   19: ifnull +52 -> 71
    //   22: aload_1
    //   23: invokeinterface 32 1 0
    //   28: astore 4
    //   30: aload_2
    //   31: aload 4
    //   33: invokevirtual 36	android/os/Parcel:writeStrongBinder	(Landroid/os/IBinder;)V
    //   36: aload_0
    //   37: getfield 14	com/google/android/gms/wearable/internal/zzax$zza$zza:zzoz	Landroid/os/IBinder;
    //   40: astore 4
    //   42: iconst_5
    //   43: istore 5
    //   45: aload 4
    //   47: iload 5
    //   49: aload_2
    //   50: aload_3
    //   51: iconst_0
    //   52: invokeinterface 43 5 0
    //   57: pop
    //   58: aload_3
    //   59: invokevirtual 46	android/os/Parcel:readException	()V
    //   62: aload_3
    //   63: invokevirtual 49	android/os/Parcel:recycle	()V
    //   66: aload_2
    //   67: invokevirtual 49	android/os/Parcel:recycle	()V
    //   70: return
    //   71: aconst_null
    //   72: astore 4
    //   74: goto -44 -> 30
    //   77: astore 4
    //   79: aload_3
    //   80: invokevirtual 49	android/os/Parcel:recycle	()V
    //   83: aload_2
    //   84: invokevirtual 49	android/os/Parcel:recycle	()V
    //   87: aload 4
    //   89: athrow
    // Local variable table:
    //   start	length	slot	name	signature
    //   0	90	0	this	zza
    //   0	90	1	paramzzav	zzav
    //   3	81	2	localParcel1	android.os.Parcel
    //   7	73	3	localParcel2	android.os.Parcel
    //   10	63	4	localObject1	Object
    //   77	11	4	localObject2	Object
    //   43	5	5	i	int
    // Exception table:
    //   from	to	target	type
    //   13	18	77	finally
    //   22	28	77	finally
    //   31	36	77	finally
    //   36	40	77	finally
    //   51	58	77	finally
    //   58	62	77	finally
  }
}


/* Location:              C:\Users\haryo\Desktop\enjarify-master\presensi-enjarify.jar!\com\google\android\gms\wearable\internal\zzax$zza$zza.class
 * Java compiler version: 5 (49.0)
 * JD-Core Version:       0.7.1
 */