package com.google.android.gms.wearable.internal;

import android.net.Uri;
import com.google.android.gms.common.api.internal.zza.zzb;

class zzbp$3
  implements Runnable
{
  zzbp$3(zzbp paramzzbp, Uri paramUri, zza.zzb paramzzb, String paramString, long paramLong1, long paramLong2) {}
  
  /* Error */
  public void run()
  {
    // Byte code:
    //   0: ldc 35
    //   2: astore_1
    //   3: iconst_2
    //   4: istore_2
    //   5: aload_1
    //   6: iload_2
    //   7: invokestatic 42	android/util/Log:isLoggable	(Ljava/lang/String;I)Z
    //   10: istore_3
    //   11: iload_3
    //   12: ifeq +17 -> 29
    //   15: ldc 35
    //   17: astore_1
    //   18: ldc 44
    //   20: astore 4
    //   22: aload_1
    //   23: aload 4
    //   25: invokestatic 48	android/util/Log:v	(Ljava/lang/String;Ljava/lang/String;)I
    //   28: pop
    //   29: ldc 50
    //   31: astore_1
    //   32: aload_0
    //   33: getfield 21	com/google/android/gms/wearable/internal/zzbp$3:zzbds	Landroid/net/Uri;
    //   36: invokevirtual 56	android/net/Uri:getScheme	()Ljava/lang/String;
    //   39: astore 4
    //   41: aload_1
    //   42: aload 4
    //   44: invokevirtual 62	java/lang/String:equals	(Ljava/lang/Object;)Z
    //   47: istore_3
    //   48: iload_3
    //   49: ifne +47 -> 96
    //   52: ldc 35
    //   54: ldc 64
    //   56: invokestatic 67	android/util/Log:w	(Ljava/lang/String;Ljava/lang/String;)I
    //   59: pop
    //   60: aload_0
    //   61: getfield 23	com/google/android/gms/wearable/internal/zzbp$3:zzbto	Lcom/google/android/gms/common/api/internal/zza$zzb;
    //   64: astore_1
    //   65: new 69	com/google/android/gms/common/api/Status
    //   68: astore 4
    //   70: bipush 10
    //   72: istore 5
    //   74: ldc 64
    //   76: astore 6
    //   78: aload 4
    //   80: iload 5
    //   82: aload 6
    //   84: invokespecial 73	com/google/android/gms/common/api/Status:<init>	(ILjava/lang/String;)V
    //   87: aload_1
    //   88: aload 4
    //   90: invokeinterface 79 2 0
    //   95: return
    //   96: new 81	java/io/File
    //   99: astore_1
    //   100: aload_0
    //   101: getfield 21	com/google/android/gms/wearable/internal/zzbp$3:zzbds	Landroid/net/Uri;
    //   104: invokevirtual 84	android/net/Uri:getPath	()Ljava/lang/String;
    //   107: astore 4
    //   109: aload_1
    //   110: aload 4
    //   112: invokespecial 87	java/io/File:<init>	(Ljava/lang/String;)V
    //   115: ldc 88
    //   117: istore_2
    //   118: aload_1
    //   119: iload_2
    //   120: invokestatic 95	android/os/ParcelFileDescriptor:open	(Ljava/io/File;I)Landroid/os/ParcelFileDescriptor;
    //   123: astore 6
    //   125: aload_0
    //   126: getfield 19	com/google/android/gms/wearable/internal/zzbp$3:zzbtn	Lcom/google/android/gms/wearable/internal/zzbp;
    //   129: astore_1
    //   130: aload_1
    //   131: invokevirtual 101	com/google/android/gms/wearable/internal/zzbp:zzqJ	()Landroid/os/IInterface;
    //   134: astore_1
    //   135: aload_1
    //   136: checkcast 103	com/google/android/gms/wearable/internal/zzax
    //   139: astore_1
    //   140: new 105	com/google/android/gms/wearable/internal/zzbo$zzr
    //   143: astore 4
    //   145: aload_0
    //   146: getfield 23	com/google/android/gms/wearable/internal/zzbp$3:zzbto	Lcom/google/android/gms/common/api/internal/zza$zzb;
    //   149: astore 7
    //   151: aload 4
    //   153: aload 7
    //   155: invokespecial 108	com/google/android/gms/wearable/internal/zzbo$zzr:<init>	(Lcom/google/android/gms/common/api/internal/zza$zzb;)V
    //   158: aload_0
    //   159: getfield 25	com/google/android/gms/wearable/internal/zzbp$3:zzVj	Ljava/lang/String;
    //   162: astore 7
    //   164: aload_0
    //   165: getfield 27	com/google/android/gms/wearable/internal/zzbp$3:zzbsf	J
    //   168: lstore 8
    //   170: aload_0
    //   171: getfield 29	com/google/android/gms/wearable/internal/zzbp$3:zzbsg	J
    //   174: lstore 10
    //   176: aload_1
    //   177: aload 4
    //   179: aload 7
    //   181: aload 6
    //   183: lload 8
    //   185: lload 10
    //   187: invokeinterface 112 8 0
    //   192: aload 6
    //   194: invokevirtual 115	android/os/ParcelFileDescriptor:close	()V
    //   197: goto -102 -> 95
    //   200: astore_1
    //   201: ldc 35
    //   203: astore 4
    //   205: ldc 117
    //   207: astore 7
    //   209: aload 4
    //   211: aload 7
    //   213: aload_1
    //   214: invokestatic 120	android/util/Log:w	(Ljava/lang/String;Ljava/lang/String;Ljava/lang/Throwable;)I
    //   217: pop
    //   218: goto -123 -> 95
    //   221: astore 4
    //   223: new 122	java/lang/StringBuilder
    //   226: astore 7
    //   228: aload 7
    //   230: invokespecial 123	java/lang/StringBuilder:<init>	()V
    //   233: ldc 125
    //   235: astore 6
    //   237: aload 7
    //   239: aload 6
    //   241: invokevirtual 129	java/lang/StringBuilder:append	(Ljava/lang/String;)Ljava/lang/StringBuilder;
    //   244: astore 7
    //   246: aload 7
    //   248: aload_1
    //   249: invokevirtual 132	java/lang/StringBuilder:append	(Ljava/lang/Object;)Ljava/lang/StringBuilder;
    //   252: invokevirtual 135	java/lang/StringBuilder:toString	()Ljava/lang/String;
    //   255: astore_1
    //   256: ldc 35
    //   258: aload_1
    //   259: invokestatic 67	android/util/Log:w	(Ljava/lang/String;Ljava/lang/String;)I
    //   262: pop
    //   263: aload_0
    //   264: getfield 23	com/google/android/gms/wearable/internal/zzbp$3:zzbto	Lcom/google/android/gms/common/api/internal/zza$zzb;
    //   267: astore_1
    //   268: new 69	com/google/android/gms/common/api/Status
    //   271: astore 4
    //   273: bipush 13
    //   275: istore 5
    //   277: aload 4
    //   279: iload 5
    //   281: invokespecial 139	com/google/android/gms/common/api/Status:<init>	(I)V
    //   284: aload_1
    //   285: aload 4
    //   287: invokeinterface 79 2 0
    //   292: goto -197 -> 95
    //   295: astore_1
    //   296: ldc 35
    //   298: astore 4
    //   300: ldc -115
    //   302: astore 7
    //   304: aload 4
    //   306: aload 7
    //   308: aload_1
    //   309: invokestatic 120	android/util/Log:w	(Ljava/lang/String;Ljava/lang/String;Ljava/lang/Throwable;)I
    //   312: pop
    //   313: aload_0
    //   314: getfield 23	com/google/android/gms/wearable/internal/zzbp$3:zzbto	Lcom/google/android/gms/common/api/internal/zza$zzb;
    //   317: astore_1
    //   318: new 69	com/google/android/gms/common/api/Status
    //   321: astore 4
    //   323: bipush 8
    //   325: istore 5
    //   327: aload 4
    //   329: iload 5
    //   331: invokespecial 139	com/google/android/gms/common/api/Status:<init>	(I)V
    //   334: aload_1
    //   335: aload 4
    //   337: invokeinterface 79 2 0
    //   342: aload 6
    //   344: invokevirtual 115	android/os/ParcelFileDescriptor:close	()V
    //   347: goto -252 -> 95
    //   350: astore_1
    //   351: ldc 35
    //   353: astore 4
    //   355: ldc 117
    //   357: astore 7
    //   359: aload 4
    //   361: aload 7
    //   363: aload_1
    //   364: invokestatic 120	android/util/Log:w	(Ljava/lang/String;Ljava/lang/String;Ljava/lang/Throwable;)I
    //   367: pop
    //   368: goto -273 -> 95
    //   371: astore_1
    //   372: aload 6
    //   374: invokevirtual 115	android/os/ParcelFileDescriptor:close	()V
    //   377: aload_1
    //   378: athrow
    //   379: astore 4
    //   381: ldc 35
    //   383: astore 7
    //   385: ldc 117
    //   387: astore 6
    //   389: aload 7
    //   391: aload 6
    //   393: aload 4
    //   395: invokestatic 120	android/util/Log:w	(Ljava/lang/String;Ljava/lang/String;Ljava/lang/Throwable;)I
    //   398: pop
    //   399: goto -22 -> 377
    // Local variable table:
    //   start	length	slot	name	signature
    //   0	402	0	this	3
    //   2	175	1	localObject1	Object
    //   200	49	1	localIOException1	java.io.IOException
    //   255	30	1	localObject2	Object
    //   295	14	1	localRemoteException	android.os.RemoteException
    //   317	18	1	localzzb	zza.zzb
    //   350	14	1	localIOException2	java.io.IOException
    //   371	7	1	localObject3	Object
    //   4	116	2	i	int
    //   10	39	3	bool	boolean
    //   20	190	4	localObject4	Object
    //   221	1	4	localFileNotFoundException	java.io.FileNotFoundException
    //   271	89	4	localObject5	Object
    //   379	15	4	localIOException3	java.io.IOException
    //   72	258	5	j	int
    //   76	316	6	localObject6	Object
    //   149	241	7	localObject7	Object
    //   168	16	8	l1	long
    //   174	12	10	l2	long
    // Exception table:
    //   from	to	target	type
    //   192	197	200	java/io/IOException
    //   119	123	221	java/io/FileNotFoundException
    //   125	129	295	android/os/RemoteException
    //   130	134	295	android/os/RemoteException
    //   135	139	295	android/os/RemoteException
    //   140	143	295	android/os/RemoteException
    //   145	149	295	android/os/RemoteException
    //   153	158	295	android/os/RemoteException
    //   158	162	295	android/os/RemoteException
    //   164	168	295	android/os/RemoteException
    //   170	174	295	android/os/RemoteException
    //   185	192	295	android/os/RemoteException
    //   342	347	350	java/io/IOException
    //   125	129	371	finally
    //   130	134	371	finally
    //   135	139	371	finally
    //   140	143	371	finally
    //   145	149	371	finally
    //   153	158	371	finally
    //   158	162	371	finally
    //   164	168	371	finally
    //   170	174	371	finally
    //   185	192	371	finally
    //   308	313	371	finally
    //   313	317	371	finally
    //   318	321	371	finally
    //   329	334	371	finally
    //   335	342	371	finally
    //   372	377	379	java/io/IOException
  }
}


/* Location:              C:\Users\haryo\Desktop\enjarify-master\presensi-enjarify.jar!\com\google\android\gms\wearable\internal\zzbp$3.class
 * Java compiler version: 5 (49.0)
 * JD-Core Version:       0.7.1
 */