package com.google.android.gms.maps.model.internal;

import android.os.IBinder;
import android.os.Parcel;

class zzc$zza$zza
  implements zzc
{
  private IBinder zzoz;
  
  zzc$zza$zza(IBinder paramIBinder)
  {
    this.zzoz = paramIBinder;
  }
  
  public IBinder asBinder()
  {
    return this.zzoz;
  }
  
  public float getBearing()
  {
    Parcel localParcel1 = Parcel.obtain();
    Parcel localParcel2 = Parcel.obtain();
    Object localObject1 = "com.google.android.gms.maps.model.internal.IGroundOverlayDelegate";
    try
    {
      localParcel1.writeInterfaceToken((String)localObject1);
      localObject1 = this.zzoz;
      int i = 12;
      ((IBinder)localObject1).transact(i, localParcel1, localParcel2, 0);
      localParcel2.readException();
      float f = localParcel2.readFloat();
      return f;
    }
    finally
    {
      localParcel2.recycle();
      localParcel1.recycle();
    }
  }
  
  /* Error */
  public com.google.android.gms.maps.model.LatLngBounds getBounds()
  {
    // Byte code:
    //   0: invokestatic 20	android/os/Parcel:obtain	()Landroid/os/Parcel;
    //   3: astore_1
    //   4: invokestatic 20	android/os/Parcel:obtain	()Landroid/os/Parcel;
    //   7: astore_2
    //   8: ldc 22
    //   10: astore_3
    //   11: aload_1
    //   12: aload_3
    //   13: invokevirtual 26	android/os/Parcel:writeInterfaceToken	(Ljava/lang/String;)V
    //   16: aload_0
    //   17: getfield 14	com/google/android/gms/maps/model/internal/zzc$zza$zza:zzoz	Landroid/os/IBinder;
    //   20: astore_3
    //   21: bipush 10
    //   23: istore 4
    //   25: aload_3
    //   26: iload 4
    //   28: aload_1
    //   29: aload_2
    //   30: iconst_0
    //   31: invokeinterface 33 5 0
    //   36: pop
    //   37: aload_2
    //   38: invokevirtual 36	android/os/Parcel:readException	()V
    //   41: aload_2
    //   42: invokevirtual 48	android/os/Parcel:readInt	()I
    //   45: istore 5
    //   47: iload 5
    //   49: ifeq +23 -> 72
    //   52: getstatic 54	com/google/android/gms/maps/model/LatLngBounds:CREATOR	Lcom/google/android/gms/maps/model/zzd;
    //   55: astore_3
    //   56: aload_3
    //   57: aload_2
    //   58: invokevirtual 60	com/google/android/gms/maps/model/zzd:zzfy	(Landroid/os/Parcel;)Lcom/google/android/gms/maps/model/LatLngBounds;
    //   61: astore_3
    //   62: aload_2
    //   63: invokevirtual 43	android/os/Parcel:recycle	()V
    //   66: aload_1
    //   67: invokevirtual 43	android/os/Parcel:recycle	()V
    //   70: aload_3
    //   71: areturn
    //   72: iconst_0
    //   73: istore 5
    //   75: aconst_null
    //   76: astore_3
    //   77: goto -15 -> 62
    //   80: astore_3
    //   81: aload_2
    //   82: invokevirtual 43	android/os/Parcel:recycle	()V
    //   85: aload_1
    //   86: invokevirtual 43	android/os/Parcel:recycle	()V
    //   89: aload_3
    //   90: athrow
    // Local variable table:
    //   start	length	slot	name	signature
    //   0	91	0	this	zza
    //   3	83	1	localParcel1	Parcel
    //   7	75	2	localParcel2	Parcel
    //   10	67	3	localObject1	Object
    //   80	10	3	localObject2	Object
    //   23	4	4	i	int
    //   45	29	5	j	int
    // Exception table:
    //   from	to	target	type
    //   12	16	80	finally
    //   16	20	80	finally
    //   30	37	80	finally
    //   37	41	80	finally
    //   41	45	80	finally
    //   52	55	80	finally
    //   57	61	80	finally
  }
  
  public float getHeight()
  {
    Parcel localParcel1 = Parcel.obtain();
    Parcel localParcel2 = Parcel.obtain();
    Object localObject1 = "com.google.android.gms.maps.model.internal.IGroundOverlayDelegate";
    try
    {
      localParcel1.writeInterfaceToken((String)localObject1);
      localObject1 = this.zzoz;
      int i = 8;
      ((IBinder)localObject1).transact(i, localParcel1, localParcel2, 0);
      localParcel2.readException();
      float f = localParcel2.readFloat();
      return f;
    }
    finally
    {
      localParcel2.recycle();
      localParcel1.recycle();
    }
  }
  
  public String getId()
  {
    Parcel localParcel1 = Parcel.obtain();
    Parcel localParcel2 = Parcel.obtain();
    Object localObject1 = "com.google.android.gms.maps.model.internal.IGroundOverlayDelegate";
    try
    {
      localParcel1.writeInterfaceToken((String)localObject1);
      localObject1 = this.zzoz;
      int i = 2;
      ((IBinder)localObject1).transact(i, localParcel1, localParcel2, 0);
      localParcel2.readException();
      localObject1 = localParcel2.readString();
      return (String)localObject1;
    }
    finally
    {
      localParcel2.recycle();
      localParcel1.recycle();
    }
  }
  
  /* Error */
  public com.google.android.gms.maps.model.LatLng getPosition()
  {
    // Byte code:
    //   0: invokestatic 20	android/os/Parcel:obtain	()Landroid/os/Parcel;
    //   3: astore_1
    //   4: invokestatic 20	android/os/Parcel:obtain	()Landroid/os/Parcel;
    //   7: astore_2
    //   8: ldc 22
    //   10: astore_3
    //   11: aload_1
    //   12: aload_3
    //   13: invokevirtual 26	android/os/Parcel:writeInterfaceToken	(Ljava/lang/String;)V
    //   16: aload_0
    //   17: getfield 14	com/google/android/gms/maps/model/internal/zzc$zza$zza:zzoz	Landroid/os/IBinder;
    //   20: astore_3
    //   21: iconst_4
    //   22: istore 4
    //   24: aload_3
    //   25: iload 4
    //   27: aload_1
    //   28: aload_2
    //   29: iconst_0
    //   30: invokeinterface 33 5 0
    //   35: pop
    //   36: aload_2
    //   37: invokevirtual 36	android/os/Parcel:readException	()V
    //   40: aload_2
    //   41: invokevirtual 48	android/os/Parcel:readInt	()I
    //   44: istore 5
    //   46: iload 5
    //   48: ifeq +23 -> 71
    //   51: getstatic 72	com/google/android/gms/maps/model/LatLng:CREATOR	Lcom/google/android/gms/maps/model/zze;
    //   54: astore_3
    //   55: aload_3
    //   56: aload_2
    //   57: invokevirtual 78	com/google/android/gms/maps/model/zze:zzfz	(Landroid/os/Parcel;)Lcom/google/android/gms/maps/model/LatLng;
    //   60: astore_3
    //   61: aload_2
    //   62: invokevirtual 43	android/os/Parcel:recycle	()V
    //   65: aload_1
    //   66: invokevirtual 43	android/os/Parcel:recycle	()V
    //   69: aload_3
    //   70: areturn
    //   71: iconst_0
    //   72: istore 5
    //   74: aconst_null
    //   75: astore_3
    //   76: goto -15 -> 61
    //   79: astore_3
    //   80: aload_2
    //   81: invokevirtual 43	android/os/Parcel:recycle	()V
    //   84: aload_1
    //   85: invokevirtual 43	android/os/Parcel:recycle	()V
    //   88: aload_3
    //   89: athrow
    // Local variable table:
    //   start	length	slot	name	signature
    //   0	90	0	this	zza
    //   3	82	1	localParcel1	Parcel
    //   7	74	2	localParcel2	Parcel
    //   10	66	3	localObject1	Object
    //   79	10	3	localObject2	Object
    //   22	4	4	i	int
    //   44	29	5	j	int
    // Exception table:
    //   from	to	target	type
    //   12	16	79	finally
    //   16	20	79	finally
    //   29	36	79	finally
    //   36	40	79	finally
    //   40	44	79	finally
    //   51	54	79	finally
    //   56	60	79	finally
  }
  
  public float getTransparency()
  {
    Parcel localParcel1 = Parcel.obtain();
    Parcel localParcel2 = Parcel.obtain();
    Object localObject1 = "com.google.android.gms.maps.model.internal.IGroundOverlayDelegate";
    try
    {
      localParcel1.writeInterfaceToken((String)localObject1);
      localObject1 = this.zzoz;
      int i = 18;
      ((IBinder)localObject1).transact(i, localParcel1, localParcel2, 0);
      localParcel2.readException();
      float f = localParcel2.readFloat();
      return f;
    }
    finally
    {
      localParcel2.recycle();
      localParcel1.recycle();
    }
  }
  
  public float getWidth()
  {
    Parcel localParcel1 = Parcel.obtain();
    Parcel localParcel2 = Parcel.obtain();
    Object localObject1 = "com.google.android.gms.maps.model.internal.IGroundOverlayDelegate";
    try
    {
      localParcel1.writeInterfaceToken((String)localObject1);
      localObject1 = this.zzoz;
      int i = 7;
      ((IBinder)localObject1).transact(i, localParcel1, localParcel2, 0);
      localParcel2.readException();
      float f = localParcel2.readFloat();
      return f;
    }
    finally
    {
      localParcel2.recycle();
      localParcel1.recycle();
    }
  }
  
  public float getZIndex()
  {
    Parcel localParcel1 = Parcel.obtain();
    Parcel localParcel2 = Parcel.obtain();
    Object localObject1 = "com.google.android.gms.maps.model.internal.IGroundOverlayDelegate";
    try
    {
      localParcel1.writeInterfaceToken((String)localObject1);
      localObject1 = this.zzoz;
      int i = 14;
      ((IBinder)localObject1).transact(i, localParcel1, localParcel2, 0);
      localParcel2.readException();
      float f = localParcel2.readFloat();
      return f;
    }
    finally
    {
      localParcel2.recycle();
      localParcel1.recycle();
    }
  }
  
  public int hashCodeRemote()
  {
    Parcel localParcel1 = Parcel.obtain();
    Parcel localParcel2 = Parcel.obtain();
    Object localObject1 = "com.google.android.gms.maps.model.internal.IGroundOverlayDelegate";
    try
    {
      localParcel1.writeInterfaceToken((String)localObject1);
      localObject1 = this.zzoz;
      int i = 20;
      ((IBinder)localObject1).transact(i, localParcel1, localParcel2, 0);
      localParcel2.readException();
      int j = localParcel2.readInt();
      return j;
    }
    finally
    {
      localParcel2.recycle();
      localParcel1.recycle();
    }
  }
  
  public boolean isClickable()
  {
    boolean bool = false;
    Object localObject1 = null;
    Parcel localParcel1 = Parcel.obtain();
    Parcel localParcel2 = Parcel.obtain();
    Object localObject3 = "com.google.android.gms.maps.model.internal.IGroundOverlayDelegate";
    try
    {
      localParcel1.writeInterfaceToken((String)localObject3);
      localObject3 = this.zzoz;
      int i = 23;
      ((IBinder)localObject3).transact(i, localParcel1, localParcel2, 0);
      localParcel2.readException();
      int j = localParcel2.readInt();
      if (j != 0) {
        bool = true;
      }
      return bool;
    }
    finally
    {
      localParcel2.recycle();
      localParcel1.recycle();
    }
  }
  
  public boolean isVisible()
  {
    boolean bool = false;
    Object localObject1 = null;
    Parcel localParcel1 = Parcel.obtain();
    Parcel localParcel2 = Parcel.obtain();
    Object localObject3 = "com.google.android.gms.maps.model.internal.IGroundOverlayDelegate";
    try
    {
      localParcel1.writeInterfaceToken((String)localObject3);
      localObject3 = this.zzoz;
      int i = 16;
      ((IBinder)localObject3).transact(i, localParcel1, localParcel2, 0);
      localParcel2.readException();
      int j = localParcel2.readInt();
      if (j != 0) {
        bool = true;
      }
      return bool;
    }
    finally
    {
      localParcel2.recycle();
      localParcel1.recycle();
    }
  }
  
  public void remove()
  {
    Parcel localParcel1 = Parcel.obtain();
    Parcel localParcel2 = Parcel.obtain();
    Object localObject1 = "com.google.android.gms.maps.model.internal.IGroundOverlayDelegate";
    try
    {
      localParcel1.writeInterfaceToken((String)localObject1);
      localObject1 = this.zzoz;
      int i = 1;
      ((IBinder)localObject1).transact(i, localParcel1, localParcel2, 0);
      localParcel2.readException();
      return;
    }
    finally
    {
      localParcel2.recycle();
      localParcel1.recycle();
    }
  }
  
  public void setBearing(float paramFloat)
  {
    Parcel localParcel1 = Parcel.obtain();
    Parcel localParcel2 = Parcel.obtain();
    Object localObject1 = "com.google.android.gms.maps.model.internal.IGroundOverlayDelegate";
    try
    {
      localParcel1.writeInterfaceToken((String)localObject1);
      localParcel1.writeFloat(paramFloat);
      localObject1 = this.zzoz;
      int i = 11;
      ((IBinder)localObject1).transact(i, localParcel1, localParcel2, 0);
      localParcel2.readException();
      return;
    }
    finally
    {
      localParcel2.recycle();
      localParcel1.recycle();
    }
  }
  
  public void setClickable(boolean paramBoolean)
  {
    int i = 0;
    IBinder localIBinder = null;
    Parcel localParcel1 = Parcel.obtain();
    Parcel localParcel2 = Parcel.obtain();
    String str = "com.google.android.gms.maps.model.internal.IGroundOverlayDelegate";
    try
    {
      localParcel1.writeInterfaceToken(str);
      if (paramBoolean) {
        i = 1;
      }
      localParcel1.writeInt(i);
      localIBinder = this.zzoz;
      int j = 22;
      localIBinder.transact(j, localParcel1, localParcel2, 0);
      localParcel2.readException();
      return;
    }
    finally
    {
      localParcel2.recycle();
      localParcel1.recycle();
    }
  }
  
  public void setDimensions(float paramFloat)
  {
    Parcel localParcel1 = Parcel.obtain();
    Parcel localParcel2 = Parcel.obtain();
    Object localObject1 = "com.google.android.gms.maps.model.internal.IGroundOverlayDelegate";
    try
    {
      localParcel1.writeInterfaceToken((String)localObject1);
      localParcel1.writeFloat(paramFloat);
      localObject1 = this.zzoz;
      int i = 5;
      ((IBinder)localObject1).transact(i, localParcel1, localParcel2, 0);
      localParcel2.readException();
      return;
    }
    finally
    {
      localParcel2.recycle();
      localParcel1.recycle();
    }
  }
  
  /* Error */
  public void setPosition(com.google.android.gms.maps.model.LatLng paramLatLng)
  {
    // Byte code:
    //   0: invokestatic 20	android/os/Parcel:obtain	()Landroid/os/Parcel;
    //   3: astore_2
    //   4: invokestatic 20	android/os/Parcel:obtain	()Landroid/os/Parcel;
    //   7: astore_3
    //   8: ldc 22
    //   10: astore 4
    //   12: aload_2
    //   13: aload 4
    //   15: invokevirtual 26	android/os/Parcel:writeInterfaceToken	(Ljava/lang/String;)V
    //   18: aload_1
    //   19: ifnull +59 -> 78
    //   22: iconst_1
    //   23: istore 5
    //   25: aload_2
    //   26: iload 5
    //   28: invokevirtual 94	android/os/Parcel:writeInt	(I)V
    //   31: iconst_0
    //   32: istore 5
    //   34: aconst_null
    //   35: astore 4
    //   37: aload_1
    //   38: aload_2
    //   39: iconst_0
    //   40: invokevirtual 100	com/google/android/gms/maps/model/LatLng:writeToParcel	(Landroid/os/Parcel;I)V
    //   43: aload_0
    //   44: getfield 14	com/google/android/gms/maps/model/internal/zzc$zza$zza:zzoz	Landroid/os/IBinder;
    //   47: astore 4
    //   49: iconst_3
    //   50: istore 6
    //   52: aload 4
    //   54: iload 6
    //   56: aload_2
    //   57: aload_3
    //   58: iconst_0
    //   59: invokeinterface 33 5 0
    //   64: pop
    //   65: aload_3
    //   66: invokevirtual 36	android/os/Parcel:readException	()V
    //   69: aload_3
    //   70: invokevirtual 43	android/os/Parcel:recycle	()V
    //   73: aload_2
    //   74: invokevirtual 43	android/os/Parcel:recycle	()V
    //   77: return
    //   78: iconst_0
    //   79: istore 5
    //   81: aconst_null
    //   82: astore 4
    //   84: aload_2
    //   85: iconst_0
    //   86: invokevirtual 94	android/os/Parcel:writeInt	(I)V
    //   89: goto -46 -> 43
    //   92: astore 4
    //   94: aload_3
    //   95: invokevirtual 43	android/os/Parcel:recycle	()V
    //   98: aload_2
    //   99: invokevirtual 43	android/os/Parcel:recycle	()V
    //   102: aload 4
    //   104: athrow
    // Local variable table:
    //   start	length	slot	name	signature
    //   0	105	0	this	zza
    //   0	105	1	paramLatLng	com.google.android.gms.maps.model.LatLng
    //   3	96	2	localParcel1	Parcel
    //   7	88	3	localParcel2	Parcel
    //   10	73	4	localObject1	Object
    //   92	11	4	localObject2	Object
    //   23	57	5	i	int
    //   50	5	6	j	int
    // Exception table:
    //   from	to	target	type
    //   13	18	92	finally
    //   26	31	92	finally
    //   39	43	92	finally
    //   43	47	92	finally
    //   58	65	92	finally
    //   65	69	92	finally
    //   85	89	92	finally
  }
  
  /* Error */
  public void setPositionFromBounds(com.google.android.gms.maps.model.LatLngBounds paramLatLngBounds)
  {
    // Byte code:
    //   0: invokestatic 20	android/os/Parcel:obtain	()Landroid/os/Parcel;
    //   3: astore_2
    //   4: invokestatic 20	android/os/Parcel:obtain	()Landroid/os/Parcel;
    //   7: astore_3
    //   8: ldc 22
    //   10: astore 4
    //   12: aload_2
    //   13: aload 4
    //   15: invokevirtual 26	android/os/Parcel:writeInterfaceToken	(Ljava/lang/String;)V
    //   18: aload_1
    //   19: ifnull +60 -> 79
    //   22: iconst_1
    //   23: istore 5
    //   25: aload_2
    //   26: iload 5
    //   28: invokevirtual 94	android/os/Parcel:writeInt	(I)V
    //   31: iconst_0
    //   32: istore 5
    //   34: aconst_null
    //   35: astore 4
    //   37: aload_1
    //   38: aload_2
    //   39: iconst_0
    //   40: invokevirtual 102	com/google/android/gms/maps/model/LatLngBounds:writeToParcel	(Landroid/os/Parcel;I)V
    //   43: aload_0
    //   44: getfield 14	com/google/android/gms/maps/model/internal/zzc$zza$zza:zzoz	Landroid/os/IBinder;
    //   47: astore 4
    //   49: bipush 9
    //   51: istore 6
    //   53: aload 4
    //   55: iload 6
    //   57: aload_2
    //   58: aload_3
    //   59: iconst_0
    //   60: invokeinterface 33 5 0
    //   65: pop
    //   66: aload_3
    //   67: invokevirtual 36	android/os/Parcel:readException	()V
    //   70: aload_3
    //   71: invokevirtual 43	android/os/Parcel:recycle	()V
    //   74: aload_2
    //   75: invokevirtual 43	android/os/Parcel:recycle	()V
    //   78: return
    //   79: iconst_0
    //   80: istore 5
    //   82: aconst_null
    //   83: astore 4
    //   85: aload_2
    //   86: iconst_0
    //   87: invokevirtual 94	android/os/Parcel:writeInt	(I)V
    //   90: goto -47 -> 43
    //   93: astore 4
    //   95: aload_3
    //   96: invokevirtual 43	android/os/Parcel:recycle	()V
    //   99: aload_2
    //   100: invokevirtual 43	android/os/Parcel:recycle	()V
    //   103: aload 4
    //   105: athrow
    // Local variable table:
    //   start	length	slot	name	signature
    //   0	106	0	this	zza
    //   0	106	1	paramLatLngBounds	com.google.android.gms.maps.model.LatLngBounds
    //   3	97	2	localParcel1	Parcel
    //   7	89	3	localParcel2	Parcel
    //   10	74	4	localObject1	Object
    //   93	11	4	localObject2	Object
    //   23	58	5	i	int
    //   51	5	6	j	int
    // Exception table:
    //   from	to	target	type
    //   13	18	93	finally
    //   26	31	93	finally
    //   39	43	93	finally
    //   43	47	93	finally
    //   59	66	93	finally
    //   66	70	93	finally
    //   86	90	93	finally
  }
  
  public void setTransparency(float paramFloat)
  {
    Parcel localParcel1 = Parcel.obtain();
    Parcel localParcel2 = Parcel.obtain();
    Object localObject1 = "com.google.android.gms.maps.model.internal.IGroundOverlayDelegate";
    try
    {
      localParcel1.writeInterfaceToken((String)localObject1);
      localParcel1.writeFloat(paramFloat);
      localObject1 = this.zzoz;
      int i = 17;
      ((IBinder)localObject1).transact(i, localParcel1, localParcel2, 0);
      localParcel2.readException();
      return;
    }
    finally
    {
      localParcel2.recycle();
      localParcel1.recycle();
    }
  }
  
  public void setVisible(boolean paramBoolean)
  {
    int i = 0;
    IBinder localIBinder = null;
    Parcel localParcel1 = Parcel.obtain();
    Parcel localParcel2 = Parcel.obtain();
    String str = "com.google.android.gms.maps.model.internal.IGroundOverlayDelegate";
    try
    {
      localParcel1.writeInterfaceToken(str);
      if (paramBoolean) {
        i = 1;
      }
      localParcel1.writeInt(i);
      localIBinder = this.zzoz;
      int j = 15;
      localIBinder.transact(j, localParcel1, localParcel2, 0);
      localParcel2.readException();
      return;
    }
    finally
    {
      localParcel2.recycle();
      localParcel1.recycle();
    }
  }
  
  public void setZIndex(float paramFloat)
  {
    Parcel localParcel1 = Parcel.obtain();
    Parcel localParcel2 = Parcel.obtain();
    Object localObject1 = "com.google.android.gms.maps.model.internal.IGroundOverlayDelegate";
    try
    {
      localParcel1.writeInterfaceToken((String)localObject1);
      localParcel1.writeFloat(paramFloat);
      localObject1 = this.zzoz;
      int i = 13;
      ((IBinder)localObject1).transact(i, localParcel1, localParcel2, 0);
      localParcel2.readException();
      return;
    }
    finally
    {
      localParcel2.recycle();
      localParcel1.recycle();
    }
  }
  
  public void zza(float paramFloat1, float paramFloat2)
  {
    Parcel localParcel1 = Parcel.obtain();
    Parcel localParcel2 = Parcel.obtain();
    Object localObject1 = "com.google.android.gms.maps.model.internal.IGroundOverlayDelegate";
    try
    {
      localParcel1.writeInterfaceToken((String)localObject1);
      localParcel1.writeFloat(paramFloat1);
      localParcel1.writeFloat(paramFloat2);
      localObject1 = this.zzoz;
      int i = 6;
      ((IBinder)localObject1).transact(i, localParcel1, localParcel2, 0);
      localParcel2.readException();
      return;
    }
    finally
    {
      localParcel2.recycle();
      localParcel1.recycle();
    }
  }
  
  /* Error */
  public boolean zzb(zzc paramzzc)
  {
    // Byte code:
    //   0: iconst_0
    //   1: istore_2
    //   2: aconst_null
    //   3: astore_3
    //   4: invokestatic 20	android/os/Parcel:obtain	()Landroid/os/Parcel;
    //   7: astore 4
    //   9: invokestatic 20	android/os/Parcel:obtain	()Landroid/os/Parcel;
    //   12: astore 5
    //   14: ldc 22
    //   16: astore 6
    //   18: aload 4
    //   20: aload 6
    //   22: invokevirtual 26	android/os/Parcel:writeInterfaceToken	(Ljava/lang/String;)V
    //   25: aload_1
    //   26: ifnull +74 -> 100
    //   29: aload_1
    //   30: invokeinterface 111 1 0
    //   35: astore 6
    //   37: aload 4
    //   39: aload 6
    //   41: invokevirtual 115	android/os/Parcel:writeStrongBinder	(Landroid/os/IBinder;)V
    //   44: aload_0
    //   45: getfield 14	com/google/android/gms/maps/model/internal/zzc$zza$zza:zzoz	Landroid/os/IBinder;
    //   48: astore 6
    //   50: bipush 19
    //   52: istore 7
    //   54: aload 6
    //   56: iload 7
    //   58: aload 4
    //   60: aload 5
    //   62: iconst_0
    //   63: invokeinterface 33 5 0
    //   68: pop
    //   69: aload 5
    //   71: invokevirtual 36	android/os/Parcel:readException	()V
    //   74: aload 5
    //   76: invokevirtual 48	android/os/Parcel:readInt	()I
    //   79: istore 8
    //   81: iload 8
    //   83: ifeq +5 -> 88
    //   86: iconst_1
    //   87: istore_2
    //   88: aload 5
    //   90: invokevirtual 43	android/os/Parcel:recycle	()V
    //   93: aload 4
    //   95: invokevirtual 43	android/os/Parcel:recycle	()V
    //   98: iload_2
    //   99: ireturn
    //   100: iconst_0
    //   101: istore 8
    //   103: aconst_null
    //   104: astore 6
    //   106: goto -69 -> 37
    //   109: astore_3
    //   110: aload 5
    //   112: invokevirtual 43	android/os/Parcel:recycle	()V
    //   115: aload 4
    //   117: invokevirtual 43	android/os/Parcel:recycle	()V
    //   120: aload_3
    //   121: athrow
    // Local variable table:
    //   start	length	slot	name	signature
    //   0	122	0	this	zza
    //   0	122	1	paramzzc	zzc
    //   1	98	2	bool	boolean
    //   3	1	3	localObject1	Object
    //   109	12	3	localObject2	Object
    //   7	109	4	localParcel1	Parcel
    //   12	99	5	localParcel2	Parcel
    //   16	89	6	localObject3	Object
    //   52	5	7	i	int
    //   79	23	8	j	int
    // Exception table:
    //   from	to	target	type
    //   20	25	109	finally
    //   29	35	109	finally
    //   39	44	109	finally
    //   44	48	109	finally
    //   62	69	109	finally
    //   69	74	109	finally
    //   74	79	109	finally
  }
  
  /* Error */
  public void zzv(com.google.android.gms.dynamic.zzd paramzzd)
  {
    // Byte code:
    //   0: invokestatic 20	android/os/Parcel:obtain	()Landroid/os/Parcel;
    //   3: astore_2
    //   4: invokestatic 20	android/os/Parcel:obtain	()Landroid/os/Parcel;
    //   7: astore_3
    //   8: ldc 22
    //   10: astore 4
    //   12: aload_2
    //   13: aload 4
    //   15: invokevirtual 26	android/os/Parcel:writeInterfaceToken	(Ljava/lang/String;)V
    //   18: aload_1
    //   19: ifnull +53 -> 72
    //   22: aload_1
    //   23: invokeinterface 119 1 0
    //   28: astore 4
    //   30: aload_2
    //   31: aload 4
    //   33: invokevirtual 115	android/os/Parcel:writeStrongBinder	(Landroid/os/IBinder;)V
    //   36: aload_0
    //   37: getfield 14	com/google/android/gms/maps/model/internal/zzc$zza$zza:zzoz	Landroid/os/IBinder;
    //   40: astore 4
    //   42: bipush 21
    //   44: istore 5
    //   46: aload 4
    //   48: iload 5
    //   50: aload_2
    //   51: aload_3
    //   52: iconst_0
    //   53: invokeinterface 33 5 0
    //   58: pop
    //   59: aload_3
    //   60: invokevirtual 36	android/os/Parcel:readException	()V
    //   63: aload_3
    //   64: invokevirtual 43	android/os/Parcel:recycle	()V
    //   67: aload_2
    //   68: invokevirtual 43	android/os/Parcel:recycle	()V
    //   71: return
    //   72: aconst_null
    //   73: astore 4
    //   75: goto -45 -> 30
    //   78: astore 4
    //   80: aload_3
    //   81: invokevirtual 43	android/os/Parcel:recycle	()V
    //   84: aload_2
    //   85: invokevirtual 43	android/os/Parcel:recycle	()V
    //   88: aload 4
    //   90: athrow
    // Local variable table:
    //   start	length	slot	name	signature
    //   0	91	0	this	zza
    //   0	91	1	paramzzd	com.google.android.gms.dynamic.zzd
    //   3	82	2	localParcel1	Parcel
    //   7	74	3	localParcel2	Parcel
    //   10	64	4	localObject1	Object
    //   78	11	4	localObject2	Object
    //   44	5	5	i	int
    // Exception table:
    //   from	to	target	type
    //   13	18	78	finally
    //   22	28	78	finally
    //   31	36	78	finally
    //   36	40	78	finally
    //   52	59	78	finally
    //   59	63	78	finally
  }
}


/* Location:              C:\Users\haryo\Desktop\enjarify-master\presensi-enjarify.jar!\com\google\android\gms\maps\model\internal\zzc$zza$zza.class
 * Java compiler version: 5 (49.0)
 * JD-Core Version:       0.7.1
 */