package com.google.android.gms.drive.realtime.internal;

import android.os.IBinder;
import android.os.Parcel;
import com.google.android.gms.common.data.DataHolder;
import com.google.android.gms.drive.DriveId;

class zzm$zza$zza
  implements zzm
{
  private IBinder zzoz;
  
  zzm$zza$zza(IBinder paramIBinder)
  {
    this.zzoz = paramIBinder;
  }
  
  public IBinder asBinder()
  {
    return this.zzoz;
  }
  
  /* Error */
  public void zza(int paramInt, zzj paramzzj)
  {
    // Byte code:
    //   0: invokestatic 20	android/os/Parcel:obtain	()Landroid/os/Parcel;
    //   3: astore_3
    //   4: invokestatic 20	android/os/Parcel:obtain	()Landroid/os/Parcel;
    //   7: astore 4
    //   9: ldc 22
    //   11: astore 5
    //   13: aload_3
    //   14: aload 5
    //   16: invokevirtual 26	android/os/Parcel:writeInterfaceToken	(Ljava/lang/String;)V
    //   19: aload_3
    //   20: iload_1
    //   21: invokevirtual 30	android/os/Parcel:writeInt	(I)V
    //   24: aload_2
    //   25: ifnull +56 -> 81
    //   28: aload_2
    //   29: invokeinterface 36 1 0
    //   34: astore 5
    //   36: aload_3
    //   37: aload 5
    //   39: invokevirtual 40	android/os/Parcel:writeStrongBinder	(Landroid/os/IBinder;)V
    //   42: aload_0
    //   43: getfield 14	com/google/android/gms/drive/realtime/internal/zzm$zza$zza:zzoz	Landroid/os/IBinder;
    //   46: astore 5
    //   48: bipush 30
    //   50: istore 6
    //   52: aload 5
    //   54: iload 6
    //   56: aload_3
    //   57: aload 4
    //   59: iconst_0
    //   60: invokeinterface 47 5 0
    //   65: pop
    //   66: aload 4
    //   68: invokevirtual 50	android/os/Parcel:readException	()V
    //   71: aload 4
    //   73: invokevirtual 53	android/os/Parcel:recycle	()V
    //   76: aload_3
    //   77: invokevirtual 53	android/os/Parcel:recycle	()V
    //   80: return
    //   81: aconst_null
    //   82: astore 5
    //   84: goto -48 -> 36
    //   87: astore 5
    //   89: aload 4
    //   91: invokevirtual 53	android/os/Parcel:recycle	()V
    //   94: aload_3
    //   95: invokevirtual 53	android/os/Parcel:recycle	()V
    //   98: aload 5
    //   100: athrow
    // Local variable table:
    //   start	length	slot	name	signature
    //   0	101	0	this	zza
    //   0	101	1	paramInt	int
    //   0	101	2	paramzzj	zzj
    //   3	92	3	localParcel1	Parcel
    //   7	83	4	localParcel2	Parcel
    //   11	72	5	localObject1	Object
    //   87	12	5	localObject2	Object
    //   50	5	6	i	int
    // Exception table:
    //   from	to	target	type
    //   14	19	87	finally
    //   20	24	87	finally
    //   28	34	87	finally
    //   37	42	87	finally
    //   42	46	87	finally
    //   59	66	87	finally
    //   66	71	87	finally
  }
  
  /* Error */
  public void zza(int paramInt, zzo paramzzo)
  {
    // Byte code:
    //   0: invokestatic 20	android/os/Parcel:obtain	()Landroid/os/Parcel;
    //   3: astore_3
    //   4: invokestatic 20	android/os/Parcel:obtain	()Landroid/os/Parcel;
    //   7: astore 4
    //   9: ldc 22
    //   11: astore 5
    //   13: aload_3
    //   14: aload 5
    //   16: invokevirtual 26	android/os/Parcel:writeInterfaceToken	(Ljava/lang/String;)V
    //   19: aload_3
    //   20: iload_1
    //   21: invokevirtual 30	android/os/Parcel:writeInt	(I)V
    //   24: aload_2
    //   25: ifnull +56 -> 81
    //   28: aload_2
    //   29: invokeinterface 56 1 0
    //   34: astore 5
    //   36: aload_3
    //   37: aload 5
    //   39: invokevirtual 40	android/os/Parcel:writeStrongBinder	(Landroid/os/IBinder;)V
    //   42: aload_0
    //   43: getfield 14	com/google/android/gms/drive/realtime/internal/zzm$zza$zza:zzoz	Landroid/os/IBinder;
    //   46: astore 5
    //   48: bipush 50
    //   50: istore 6
    //   52: aload 5
    //   54: iload 6
    //   56: aload_3
    //   57: aload 4
    //   59: iconst_0
    //   60: invokeinterface 47 5 0
    //   65: pop
    //   66: aload 4
    //   68: invokevirtual 50	android/os/Parcel:readException	()V
    //   71: aload 4
    //   73: invokevirtual 53	android/os/Parcel:recycle	()V
    //   76: aload_3
    //   77: invokevirtual 53	android/os/Parcel:recycle	()V
    //   80: return
    //   81: aconst_null
    //   82: astore 5
    //   84: goto -48 -> 36
    //   87: astore 5
    //   89: aload 4
    //   91: invokevirtual 53	android/os/Parcel:recycle	()V
    //   94: aload_3
    //   95: invokevirtual 53	android/os/Parcel:recycle	()V
    //   98: aload 5
    //   100: athrow
    // Local variable table:
    //   start	length	slot	name	signature
    //   0	101	0	this	zza
    //   0	101	1	paramInt	int
    //   0	101	2	paramzzo	zzo
    //   3	92	3	localParcel1	Parcel
    //   7	83	4	localParcel2	Parcel
    //   11	72	5	localObject1	Object
    //   87	12	5	localObject2	Object
    //   50	5	6	i	int
    // Exception table:
    //   from	to	target	type
    //   14	19	87	finally
    //   20	24	87	finally
    //   28	34	87	finally
    //   37	42	87	finally
    //   42	46	87	finally
    //   59	66	87	finally
    //   66	71	87	finally
  }
  
  public void zza(DriveId paramDriveId, zzo paramzzo)
  {
    Parcel localParcel1 = Parcel.obtain();
    Parcel localParcel2 = Parcel.obtain();
    Object localObject3;
    for (Object localObject1 = "com.google.android.gms.drive.realtime.internal.IRealtimeService";; localObject3 = null) {
      try
      {
        localParcel1.writeInterfaceToken((String)localObject1);
        if (paramDriveId != null)
        {
          i = 1;
          localParcel1.writeInt(i);
          i = 0;
          localObject1 = null;
          paramDriveId.writeToParcel(localParcel1, 0);
        }
        while (paramzzo != null)
        {
          localObject1 = paramzzo.asBinder();
          localParcel1.writeStrongBinder((IBinder)localObject1);
          localObject1 = this.zzoz;
          int j = 48;
          ((IBinder)localObject1).transact(j, localParcel1, localParcel2, 0);
          localParcel2.readException();
          return;
          i = 0;
          localObject1 = null;
          localParcel1.writeInt(0);
        }
        int i = 0;
      }
      finally
      {
        localParcel2.recycle();
        localParcel1.recycle();
      }
    }
  }
  
  public void zza(BeginCompoundOperationRequest paramBeginCompoundOperationRequest, zzo paramzzo)
  {
    Parcel localParcel1 = Parcel.obtain();
    Parcel localParcel2 = Parcel.obtain();
    Object localObject3;
    for (Object localObject1 = "com.google.android.gms.drive.realtime.internal.IRealtimeService";; localObject3 = null) {
      try
      {
        localParcel1.writeInterfaceToken((String)localObject1);
        if (paramBeginCompoundOperationRequest != null)
        {
          i = 1;
          localParcel1.writeInt(i);
          i = 0;
          localObject1 = null;
          paramBeginCompoundOperationRequest.writeToParcel(localParcel1, 0);
        }
        while (paramzzo != null)
        {
          localObject1 = paramzzo.asBinder();
          localParcel1.writeStrongBinder((IBinder)localObject1);
          localObject1 = this.zzoz;
          int j = 18;
          ((IBinder)localObject1).transact(j, localParcel1, localParcel2, 0);
          localParcel2.readException();
          return;
          i = 0;
          localObject1 = null;
          localParcel1.writeInt(0);
        }
        int i = 0;
      }
      finally
      {
        localParcel2.recycle();
        localParcel1.recycle();
      }
    }
  }
  
  public void zza(EndCompoundOperationRequest paramEndCompoundOperationRequest, zzj paramzzj)
  {
    Parcel localParcel1 = Parcel.obtain();
    Parcel localParcel2 = Parcel.obtain();
    Object localObject3;
    for (Object localObject1 = "com.google.android.gms.drive.realtime.internal.IRealtimeService";; localObject3 = null) {
      try
      {
        localParcel1.writeInterfaceToken((String)localObject1);
        if (paramEndCompoundOperationRequest != null)
        {
          i = 1;
          localParcel1.writeInt(i);
          i = 0;
          localObject1 = null;
          paramEndCompoundOperationRequest.writeToParcel(localParcel1, 0);
        }
        while (paramzzj != null)
        {
          localObject1 = paramzzj.asBinder();
          localParcel1.writeStrongBinder((IBinder)localObject1);
          localObject1 = this.zzoz;
          int j = 41;
          ((IBinder)localObject1).transact(j, localParcel1, localParcel2, 0);
          localParcel2.readException();
          return;
          i = 0;
          localObject1 = null;
          localParcel1.writeInt(0);
        }
        int i = 0;
      }
      finally
      {
        localParcel2.recycle();
        localParcel1.recycle();
      }
    }
  }
  
  public void zza(EndCompoundOperationRequest paramEndCompoundOperationRequest, zzo paramzzo)
  {
    Parcel localParcel1 = Parcel.obtain();
    Parcel localParcel2 = Parcel.obtain();
    Object localObject3;
    for (Object localObject1 = "com.google.android.gms.drive.realtime.internal.IRealtimeService";; localObject3 = null) {
      try
      {
        localParcel1.writeInterfaceToken((String)localObject1);
        if (paramEndCompoundOperationRequest != null)
        {
          i = 1;
          localParcel1.writeInt(i);
          i = 0;
          localObject1 = null;
          paramEndCompoundOperationRequest.writeToParcel(localParcel1, 0);
        }
        while (paramzzo != null)
        {
          localObject1 = paramzzo.asBinder();
          localParcel1.writeStrongBinder((IBinder)localObject1);
          localObject1 = this.zzoz;
          int j = 19;
          ((IBinder)localObject1).transact(j, localParcel1, localParcel2, 0);
          localParcel2.readException();
          return;
          i = 0;
          localObject1 = null;
          localParcel1.writeInt(0);
        }
        int i = 0;
      }
      finally
      {
        localParcel2.recycle();
        localParcel1.recycle();
      }
    }
  }
  
  public void zza(ParcelableIndexReference paramParcelableIndexReference, zzn paramzzn)
  {
    Parcel localParcel1 = Parcel.obtain();
    Parcel localParcel2 = Parcel.obtain();
    Object localObject3;
    for (Object localObject1 = "com.google.android.gms.drive.realtime.internal.IRealtimeService";; localObject3 = null) {
      try
      {
        localParcel1.writeInterfaceToken((String)localObject1);
        if (paramParcelableIndexReference != null)
        {
          i = 1;
          localParcel1.writeInt(i);
          i = 0;
          localObject1 = null;
          paramParcelableIndexReference.writeToParcel(localParcel1, 0);
        }
        while (paramzzn != null)
        {
          localObject1 = paramzzn.asBinder();
          localParcel1.writeStrongBinder((IBinder)localObject1);
          localObject1 = this.zzoz;
          int j = 26;
          ((IBinder)localObject1).transact(j, localParcel1, localParcel2, 0);
          localParcel2.readException();
          return;
          i = 0;
          localObject1 = null;
          localParcel1.writeInt(0);
        }
        int i = 0;
      }
      finally
      {
        localParcel2.recycle();
        localParcel1.recycle();
      }
    }
  }
  
  /* Error */
  public void zza(zzc paramzzc)
  {
    // Byte code:
    //   0: invokestatic 20	android/os/Parcel:obtain	()Landroid/os/Parcel;
    //   3: astore_2
    //   4: invokestatic 20	android/os/Parcel:obtain	()Landroid/os/Parcel;
    //   7: astore_3
    //   8: ldc 22
    //   10: astore 4
    //   12: aload_2
    //   13: aload 4
    //   15: invokevirtual 26	android/os/Parcel:writeInterfaceToken	(Ljava/lang/String;)V
    //   18: aload_1
    //   19: ifnull +52 -> 71
    //   22: aload_1
    //   23: invokeinterface 84 1 0
    //   28: astore 4
    //   30: aload_2
    //   31: aload 4
    //   33: invokevirtual 40	android/os/Parcel:writeStrongBinder	(Landroid/os/IBinder;)V
    //   36: aload_0
    //   37: getfield 14	com/google/android/gms/drive/realtime/internal/zzm$zza$zza:zzoz	Landroid/os/IBinder;
    //   40: astore 4
    //   42: iconst_2
    //   43: istore 5
    //   45: aload 4
    //   47: iload 5
    //   49: aload_2
    //   50: aload_3
    //   51: iconst_0
    //   52: invokeinterface 47 5 0
    //   57: pop
    //   58: aload_3
    //   59: invokevirtual 50	android/os/Parcel:readException	()V
    //   62: aload_3
    //   63: invokevirtual 53	android/os/Parcel:recycle	()V
    //   66: aload_2
    //   67: invokevirtual 53	android/os/Parcel:recycle	()V
    //   70: return
    //   71: aconst_null
    //   72: astore 4
    //   74: goto -44 -> 30
    //   77: astore 4
    //   79: aload_3
    //   80: invokevirtual 53	android/os/Parcel:recycle	()V
    //   83: aload_2
    //   84: invokevirtual 53	android/os/Parcel:recycle	()V
    //   87: aload 4
    //   89: athrow
    // Local variable table:
    //   start	length	slot	name	signature
    //   0	90	0	this	zza
    //   0	90	1	paramzzc	zzc
    //   3	81	2	localParcel1	Parcel
    //   7	73	3	localParcel2	Parcel
    //   10	63	4	localObject1	Object
    //   77	11	4	localObject2	Object
    //   43	5	5	i	int
    // Exception table:
    //   from	to	target	type
    //   13	18	77	finally
    //   22	28	77	finally
    //   31	36	77	finally
    //   36	40	77	finally
    //   51	58	77	finally
    //   58	62	77	finally
  }
  
  /* Error */
  public void zza(zzd paramzzd)
  {
    // Byte code:
    //   0: invokestatic 20	android/os/Parcel:obtain	()Landroid/os/Parcel;
    //   3: astore_2
    //   4: invokestatic 20	android/os/Parcel:obtain	()Landroid/os/Parcel;
    //   7: astore_3
    //   8: ldc 22
    //   10: astore 4
    //   12: aload_2
    //   13: aload 4
    //   15: invokevirtual 26	android/os/Parcel:writeInterfaceToken	(Ljava/lang/String;)V
    //   18: aload_1
    //   19: ifnull +53 -> 72
    //   22: aload_1
    //   23: invokeinterface 88 1 0
    //   28: astore 4
    //   30: aload_2
    //   31: aload 4
    //   33: invokevirtual 40	android/os/Parcel:writeStrongBinder	(Landroid/os/IBinder;)V
    //   36: aload_0
    //   37: getfield 14	com/google/android/gms/drive/realtime/internal/zzm$zza$zza:zzoz	Landroid/os/IBinder;
    //   40: astore 4
    //   42: bipush 32
    //   44: istore 5
    //   46: aload 4
    //   48: iload 5
    //   50: aload_2
    //   51: aload_3
    //   52: iconst_0
    //   53: invokeinterface 47 5 0
    //   58: pop
    //   59: aload_3
    //   60: invokevirtual 50	android/os/Parcel:readException	()V
    //   63: aload_3
    //   64: invokevirtual 53	android/os/Parcel:recycle	()V
    //   67: aload_2
    //   68: invokevirtual 53	android/os/Parcel:recycle	()V
    //   71: return
    //   72: aconst_null
    //   73: astore 4
    //   75: goto -45 -> 30
    //   78: astore 4
    //   80: aload_3
    //   81: invokevirtual 53	android/os/Parcel:recycle	()V
    //   84: aload_2
    //   85: invokevirtual 53	android/os/Parcel:recycle	()V
    //   88: aload 4
    //   90: athrow
    // Local variable table:
    //   start	length	slot	name	signature
    //   0	91	0	this	zza
    //   0	91	1	paramzzd	zzd
    //   3	82	2	localParcel1	Parcel
    //   7	74	3	localParcel2	Parcel
    //   10	64	4	localObject1	Object
    //   78	11	4	localObject2	Object
    //   44	5	5	i	int
    // Exception table:
    //   from	to	target	type
    //   13	18	78	finally
    //   22	28	78	finally
    //   31	36	78	finally
    //   36	40	78	finally
    //   52	59	78	finally
    //   59	63	78	finally
  }
  
  /* Error */
  public void zza(zze paramzze)
  {
    // Byte code:
    //   0: invokestatic 20	android/os/Parcel:obtain	()Landroid/os/Parcel;
    //   3: astore_2
    //   4: invokestatic 20	android/os/Parcel:obtain	()Landroid/os/Parcel;
    //   7: astore_3
    //   8: ldc 22
    //   10: astore 4
    //   12: aload_2
    //   13: aload 4
    //   15: invokevirtual 26	android/os/Parcel:writeInterfaceToken	(Ljava/lang/String;)V
    //   18: aload_1
    //   19: ifnull +53 -> 72
    //   22: aload_1
    //   23: invokeinterface 92 1 0
    //   28: astore 4
    //   30: aload_2
    //   31: aload 4
    //   33: invokevirtual 40	android/os/Parcel:writeStrongBinder	(Landroid/os/IBinder;)V
    //   36: aload_0
    //   37: getfield 14	com/google/android/gms/drive/realtime/internal/zzm$zza$zza:zzoz	Landroid/os/IBinder;
    //   40: astore 4
    //   42: bipush 31
    //   44: istore 5
    //   46: aload 4
    //   48: iload 5
    //   50: aload_2
    //   51: aload_3
    //   52: iconst_0
    //   53: invokeinterface 47 5 0
    //   58: pop
    //   59: aload_3
    //   60: invokevirtual 50	android/os/Parcel:readException	()V
    //   63: aload_3
    //   64: invokevirtual 53	android/os/Parcel:recycle	()V
    //   67: aload_2
    //   68: invokevirtual 53	android/os/Parcel:recycle	()V
    //   71: return
    //   72: aconst_null
    //   73: astore 4
    //   75: goto -45 -> 30
    //   78: astore 4
    //   80: aload_3
    //   81: invokevirtual 53	android/os/Parcel:recycle	()V
    //   84: aload_2
    //   85: invokevirtual 53	android/os/Parcel:recycle	()V
    //   88: aload 4
    //   90: athrow
    // Local variable table:
    //   start	length	slot	name	signature
    //   0	91	0	this	zza
    //   0	91	1	paramzze	zze
    //   3	82	2	localParcel1	Parcel
    //   7	74	3	localParcel2	Parcel
    //   10	64	4	localObject1	Object
    //   78	11	4	localObject2	Object
    //   44	5	5	i	int
    // Exception table:
    //   from	to	target	type
    //   13	18	78	finally
    //   22	28	78	finally
    //   31	36	78	finally
    //   36	40	78	finally
    //   52	59	78	finally
    //   59	63	78	finally
  }
  
  /* Error */
  public void zza(zzh paramzzh)
  {
    // Byte code:
    //   0: invokestatic 20	android/os/Parcel:obtain	()Landroid/os/Parcel;
    //   3: astore_2
    //   4: invokestatic 20	android/os/Parcel:obtain	()Landroid/os/Parcel;
    //   7: astore_3
    //   8: ldc 22
    //   10: astore 4
    //   12: aload_2
    //   13: aload 4
    //   15: invokevirtual 26	android/os/Parcel:writeInterfaceToken	(Ljava/lang/String;)V
    //   18: aload_1
    //   19: ifnull +53 -> 72
    //   22: aload_1
    //   23: invokeinterface 96 1 0
    //   28: astore 4
    //   30: aload_2
    //   31: aload 4
    //   33: invokevirtual 40	android/os/Parcel:writeStrongBinder	(Landroid/os/IBinder;)V
    //   36: aload_0
    //   37: getfield 14	com/google/android/gms/drive/realtime/internal/zzm$zza$zza:zzoz	Landroid/os/IBinder;
    //   40: astore 4
    //   42: bipush 36
    //   44: istore 5
    //   46: aload 4
    //   48: iload 5
    //   50: aload_2
    //   51: aload_3
    //   52: iconst_0
    //   53: invokeinterface 47 5 0
    //   58: pop
    //   59: aload_3
    //   60: invokevirtual 50	android/os/Parcel:readException	()V
    //   63: aload_3
    //   64: invokevirtual 53	android/os/Parcel:recycle	()V
    //   67: aload_2
    //   68: invokevirtual 53	android/os/Parcel:recycle	()V
    //   71: return
    //   72: aconst_null
    //   73: astore 4
    //   75: goto -45 -> 30
    //   78: astore 4
    //   80: aload_3
    //   81: invokevirtual 53	android/os/Parcel:recycle	()V
    //   84: aload_2
    //   85: invokevirtual 53	android/os/Parcel:recycle	()V
    //   88: aload 4
    //   90: athrow
    // Local variable table:
    //   start	length	slot	name	signature
    //   0	91	0	this	zza
    //   0	91	1	paramzzh	zzh
    //   3	82	2	localParcel1	Parcel
    //   7	74	3	localParcel2	Parcel
    //   10	64	4	localObject1	Object
    //   78	11	4	localObject2	Object
    //   44	5	5	i	int
    // Exception table:
    //   from	to	target	type
    //   13	18	78	finally
    //   22	28	78	finally
    //   31	36	78	finally
    //   36	40	78	finally
    //   52	59	78	finally
    //   59	63	78	finally
  }
  
  /* Error */
  public void zza(zzi paramzzi)
  {
    // Byte code:
    //   0: invokestatic 20	android/os/Parcel:obtain	()Landroid/os/Parcel;
    //   3: astore_2
    //   4: invokestatic 20	android/os/Parcel:obtain	()Landroid/os/Parcel;
    //   7: astore_3
    //   8: ldc 22
    //   10: astore 4
    //   12: aload_2
    //   13: aload 4
    //   15: invokevirtual 26	android/os/Parcel:writeInterfaceToken	(Ljava/lang/String;)V
    //   18: aload_1
    //   19: ifnull +53 -> 72
    //   22: aload_1
    //   23: invokeinterface 100 1 0
    //   28: astore 4
    //   30: aload_2
    //   31: aload 4
    //   33: invokevirtual 40	android/os/Parcel:writeStrongBinder	(Landroid/os/IBinder;)V
    //   36: aload_0
    //   37: getfield 14	com/google/android/gms/drive/realtime/internal/zzm$zza$zza:zzoz	Landroid/os/IBinder;
    //   40: astore 4
    //   42: bipush 34
    //   44: istore 5
    //   46: aload 4
    //   48: iload 5
    //   50: aload_2
    //   51: aload_3
    //   52: iconst_0
    //   53: invokeinterface 47 5 0
    //   58: pop
    //   59: aload_3
    //   60: invokevirtual 50	android/os/Parcel:readException	()V
    //   63: aload_3
    //   64: invokevirtual 53	android/os/Parcel:recycle	()V
    //   67: aload_2
    //   68: invokevirtual 53	android/os/Parcel:recycle	()V
    //   71: return
    //   72: aconst_null
    //   73: astore 4
    //   75: goto -45 -> 30
    //   78: astore 4
    //   80: aload_3
    //   81: invokevirtual 53	android/os/Parcel:recycle	()V
    //   84: aload_2
    //   85: invokevirtual 53	android/os/Parcel:recycle	()V
    //   88: aload 4
    //   90: athrow
    // Local variable table:
    //   start	length	slot	name	signature
    //   0	91	0	this	zza
    //   0	91	1	paramzzi	zzi
    //   3	82	2	localParcel1	Parcel
    //   7	74	3	localParcel2	Parcel
    //   10	64	4	localObject1	Object
    //   78	11	4	localObject2	Object
    //   44	5	5	i	int
    // Exception table:
    //   from	to	target	type
    //   13	18	78	finally
    //   22	28	78	finally
    //   31	36	78	finally
    //   36	40	78	finally
    //   52	59	78	finally
    //   59	63	78	finally
  }
  
  /* Error */
  public void zza(zzj paramzzj)
  {
    // Byte code:
    //   0: invokestatic 20	android/os/Parcel:obtain	()Landroid/os/Parcel;
    //   3: astore_2
    //   4: invokestatic 20	android/os/Parcel:obtain	()Landroid/os/Parcel;
    //   7: astore_3
    //   8: ldc 22
    //   10: astore 4
    //   12: aload_2
    //   13: aload 4
    //   15: invokevirtual 26	android/os/Parcel:writeInterfaceToken	(Ljava/lang/String;)V
    //   18: aload_1
    //   19: ifnull +53 -> 72
    //   22: aload_1
    //   23: invokeinterface 36 1 0
    //   28: astore 4
    //   30: aload_2
    //   31: aload 4
    //   33: invokevirtual 40	android/os/Parcel:writeStrongBinder	(Landroid/os/IBinder;)V
    //   36: aload_0
    //   37: getfield 14	com/google/android/gms/drive/realtime/internal/zzm$zza$zza:zzoz	Landroid/os/IBinder;
    //   40: astore 4
    //   42: bipush 22
    //   44: istore 5
    //   46: aload 4
    //   48: iload 5
    //   50: aload_2
    //   51: aload_3
    //   52: iconst_0
    //   53: invokeinterface 47 5 0
    //   58: pop
    //   59: aload_3
    //   60: invokevirtual 50	android/os/Parcel:readException	()V
    //   63: aload_3
    //   64: invokevirtual 53	android/os/Parcel:recycle	()V
    //   67: aload_2
    //   68: invokevirtual 53	android/os/Parcel:recycle	()V
    //   71: return
    //   72: aconst_null
    //   73: astore 4
    //   75: goto -45 -> 30
    //   78: astore 4
    //   80: aload_3
    //   81: invokevirtual 53	android/os/Parcel:recycle	()V
    //   84: aload_2
    //   85: invokevirtual 53	android/os/Parcel:recycle	()V
    //   88: aload 4
    //   90: athrow
    // Local variable table:
    //   start	length	slot	name	signature
    //   0	91	0	this	zza
    //   0	91	1	paramzzj	zzj
    //   3	82	2	localParcel1	Parcel
    //   7	74	3	localParcel2	Parcel
    //   10	64	4	localObject1	Object
    //   78	11	4	localObject2	Object
    //   44	5	5	i	int
    // Exception table:
    //   from	to	target	type
    //   13	18	78	finally
    //   22	28	78	finally
    //   31	36	78	finally
    //   36	40	78	finally
    //   52	59	78	finally
    //   59	63	78	finally
  }
  
  /* Error */
  public void zza(zzl paramzzl)
  {
    // Byte code:
    //   0: invokestatic 20	android/os/Parcel:obtain	()Landroid/os/Parcel;
    //   3: astore_2
    //   4: invokestatic 20	android/os/Parcel:obtain	()Landroid/os/Parcel;
    //   7: astore_3
    //   8: ldc 22
    //   10: astore 4
    //   12: aload_2
    //   13: aload 4
    //   15: invokevirtual 26	android/os/Parcel:writeInterfaceToken	(Ljava/lang/String;)V
    //   18: aload_1
    //   19: ifnull +53 -> 72
    //   22: aload_1
    //   23: invokeinterface 105 1 0
    //   28: astore 4
    //   30: aload_2
    //   31: aload 4
    //   33: invokevirtual 40	android/os/Parcel:writeStrongBinder	(Landroid/os/IBinder;)V
    //   36: aload_0
    //   37: getfield 14	com/google/android/gms/drive/realtime/internal/zzm$zza$zza:zzoz	Landroid/os/IBinder;
    //   40: astore 4
    //   42: bipush 40
    //   44: istore 5
    //   46: aload 4
    //   48: iload 5
    //   50: aload_2
    //   51: aload_3
    //   52: iconst_0
    //   53: invokeinterface 47 5 0
    //   58: pop
    //   59: aload_3
    //   60: invokevirtual 50	android/os/Parcel:readException	()V
    //   63: aload_3
    //   64: invokevirtual 53	android/os/Parcel:recycle	()V
    //   67: aload_2
    //   68: invokevirtual 53	android/os/Parcel:recycle	()V
    //   71: return
    //   72: aconst_null
    //   73: astore 4
    //   75: goto -45 -> 30
    //   78: astore 4
    //   80: aload_3
    //   81: invokevirtual 53	android/os/Parcel:recycle	()V
    //   84: aload_2
    //   85: invokevirtual 53	android/os/Parcel:recycle	()V
    //   88: aload 4
    //   90: athrow
    // Local variable table:
    //   start	length	slot	name	signature
    //   0	91	0	this	zza
    //   0	91	1	paramzzl	zzl
    //   3	82	2	localParcel1	Parcel
    //   7	74	3	localParcel2	Parcel
    //   10	64	4	localObject1	Object
    //   78	11	4	localObject2	Object
    //   44	5	5	i	int
    // Exception table:
    //   from	to	target	type
    //   13	18	78	finally
    //   22	28	78	finally
    //   31	36	78	finally
    //   36	40	78	finally
    //   52	59	78	finally
    //   59	63	78	finally
  }
  
  /* Error */
  public void zza(zzo paramzzo)
  {
    // Byte code:
    //   0: invokestatic 20	android/os/Parcel:obtain	()Landroid/os/Parcel;
    //   3: astore_2
    //   4: invokestatic 20	android/os/Parcel:obtain	()Landroid/os/Parcel;
    //   7: astore_3
    //   8: ldc 22
    //   10: astore 4
    //   12: aload_2
    //   13: aload 4
    //   15: invokevirtual 26	android/os/Parcel:writeInterfaceToken	(Ljava/lang/String;)V
    //   18: aload_1
    //   19: ifnull +52 -> 71
    //   22: aload_1
    //   23: invokeinterface 56 1 0
    //   28: astore 4
    //   30: aload_2
    //   31: aload 4
    //   33: invokevirtual 40	android/os/Parcel:writeStrongBinder	(Landroid/os/IBinder;)V
    //   36: aload_0
    //   37: getfield 14	com/google/android/gms/drive/realtime/internal/zzm$zza$zza:zzoz	Landroid/os/IBinder;
    //   40: astore 4
    //   42: iconst_3
    //   43: istore 5
    //   45: aload 4
    //   47: iload 5
    //   49: aload_2
    //   50: aload_3
    //   51: iconst_0
    //   52: invokeinterface 47 5 0
    //   57: pop
    //   58: aload_3
    //   59: invokevirtual 50	android/os/Parcel:readException	()V
    //   62: aload_3
    //   63: invokevirtual 53	android/os/Parcel:recycle	()V
    //   66: aload_2
    //   67: invokevirtual 53	android/os/Parcel:recycle	()V
    //   70: return
    //   71: aconst_null
    //   72: astore 4
    //   74: goto -44 -> 30
    //   77: astore 4
    //   79: aload_3
    //   80: invokevirtual 53	android/os/Parcel:recycle	()V
    //   83: aload_2
    //   84: invokevirtual 53	android/os/Parcel:recycle	()V
    //   87: aload 4
    //   89: athrow
    // Local variable table:
    //   start	length	slot	name	signature
    //   0	90	0	this	zza
    //   0	90	1	paramzzo	zzo
    //   3	81	2	localParcel1	Parcel
    //   7	73	3	localParcel2	Parcel
    //   10	63	4	localObject1	Object
    //   77	11	4	localObject2	Object
    //   43	5	5	i	int
    // Exception table:
    //   from	to	target	type
    //   13	18	77	finally
    //   22	28	77	finally
    //   31	36	77	finally
    //   36	40	77	finally
    //   51	58	77	finally
    //   58	62	77	finally
  }
  
  /* Error */
  public void zza(String paramString, int paramInt1, int paramInt2, zzg paramzzg)
  {
    // Byte code:
    //   0: invokestatic 20	android/os/Parcel:obtain	()Landroid/os/Parcel;
    //   3: astore 5
    //   5: invokestatic 20	android/os/Parcel:obtain	()Landroid/os/Parcel;
    //   8: astore 6
    //   10: ldc 22
    //   12: astore 7
    //   14: aload 5
    //   16: aload 7
    //   18: invokevirtual 26	android/os/Parcel:writeInterfaceToken	(Ljava/lang/String;)V
    //   21: aload 5
    //   23: aload_1
    //   24: invokevirtual 110	android/os/Parcel:writeString	(Ljava/lang/String;)V
    //   27: aload 5
    //   29: iload_2
    //   30: invokevirtual 30	android/os/Parcel:writeInt	(I)V
    //   33: aload 5
    //   35: iload_3
    //   36: invokevirtual 30	android/os/Parcel:writeInt	(I)V
    //   39: aload 4
    //   41: ifnull +60 -> 101
    //   44: aload 4
    //   46: invokeinterface 113 1 0
    //   51: astore 7
    //   53: aload 5
    //   55: aload 7
    //   57: invokevirtual 40	android/os/Parcel:writeStrongBinder	(Landroid/os/IBinder;)V
    //   60: aload_0
    //   61: getfield 14	com/google/android/gms/drive/realtime/internal/zzm$zza$zza:zzoz	Landroid/os/IBinder;
    //   64: astore 7
    //   66: bipush 17
    //   68: istore 8
    //   70: aload 7
    //   72: iload 8
    //   74: aload 5
    //   76: aload 6
    //   78: iconst_0
    //   79: invokeinterface 47 5 0
    //   84: pop
    //   85: aload 6
    //   87: invokevirtual 50	android/os/Parcel:readException	()V
    //   90: aload 6
    //   92: invokevirtual 53	android/os/Parcel:recycle	()V
    //   95: aload 5
    //   97: invokevirtual 53	android/os/Parcel:recycle	()V
    //   100: return
    //   101: aconst_null
    //   102: astore 7
    //   104: goto -51 -> 53
    //   107: astore 7
    //   109: aload 6
    //   111: invokevirtual 53	android/os/Parcel:recycle	()V
    //   114: aload 5
    //   116: invokevirtual 53	android/os/Parcel:recycle	()V
    //   119: aload 7
    //   121: athrow
    // Local variable table:
    //   start	length	slot	name	signature
    //   0	122	0	this	zza
    //   0	122	1	paramString	String
    //   0	122	2	paramInt1	int
    //   0	122	3	paramInt2	int
    //   0	122	4	paramzzg	zzg
    //   3	112	5	localParcel1	Parcel
    //   8	102	6	localParcel2	Parcel
    //   12	91	7	localObject1	Object
    //   107	13	7	localObject2	Object
    //   68	5	8	i	int
    // Exception table:
    //   from	to	target	type
    //   16	21	107	finally
    //   23	27	107	finally
    //   29	33	107	finally
    //   35	39	107	finally
    //   44	51	107	finally
    //   55	60	107	finally
    //   60	64	107	finally
    //   78	85	107	finally
    //   85	90	107	finally
  }
  
  /* Error */
  public void zza(String paramString, int paramInt1, int paramInt2, zzj paramzzj)
  {
    // Byte code:
    //   0: invokestatic 20	android/os/Parcel:obtain	()Landroid/os/Parcel;
    //   3: astore 5
    //   5: invokestatic 20	android/os/Parcel:obtain	()Landroid/os/Parcel;
    //   8: astore 6
    //   10: ldc 22
    //   12: astore 7
    //   14: aload 5
    //   16: aload 7
    //   18: invokevirtual 26	android/os/Parcel:writeInterfaceToken	(Ljava/lang/String;)V
    //   21: aload 5
    //   23: aload_1
    //   24: invokevirtual 110	android/os/Parcel:writeString	(Ljava/lang/String;)V
    //   27: aload 5
    //   29: iload_2
    //   30: invokevirtual 30	android/os/Parcel:writeInt	(I)V
    //   33: aload 5
    //   35: iload_3
    //   36: invokevirtual 30	android/os/Parcel:writeInt	(I)V
    //   39: aload 4
    //   41: ifnull +60 -> 101
    //   44: aload 4
    //   46: invokeinterface 36 1 0
    //   51: astore 7
    //   53: aload 5
    //   55: aload 7
    //   57: invokevirtual 40	android/os/Parcel:writeStrongBinder	(Landroid/os/IBinder;)V
    //   60: aload_0
    //   61: getfield 14	com/google/android/gms/drive/realtime/internal/zzm$zza$zza:zzoz	Landroid/os/IBinder;
    //   64: astore 7
    //   66: bipush 11
    //   68: istore 8
    //   70: aload 7
    //   72: iload 8
    //   74: aload 5
    //   76: aload 6
    //   78: iconst_0
    //   79: invokeinterface 47 5 0
    //   84: pop
    //   85: aload 6
    //   87: invokevirtual 50	android/os/Parcel:readException	()V
    //   90: aload 6
    //   92: invokevirtual 53	android/os/Parcel:recycle	()V
    //   95: aload 5
    //   97: invokevirtual 53	android/os/Parcel:recycle	()V
    //   100: return
    //   101: aconst_null
    //   102: astore 7
    //   104: goto -51 -> 53
    //   107: astore 7
    //   109: aload 6
    //   111: invokevirtual 53	android/os/Parcel:recycle	()V
    //   114: aload 5
    //   116: invokevirtual 53	android/os/Parcel:recycle	()V
    //   119: aload 7
    //   121: athrow
    // Local variable table:
    //   start	length	slot	name	signature
    //   0	122	0	this	zza
    //   0	122	1	paramString	String
    //   0	122	2	paramInt1	int
    //   0	122	3	paramInt2	int
    //   0	122	4	paramzzj	zzj
    //   3	112	5	localParcel1	Parcel
    //   8	102	6	localParcel2	Parcel
    //   12	91	7	localObject1	Object
    //   107	13	7	localObject2	Object
    //   68	5	8	i	int
    // Exception table:
    //   from	to	target	type
    //   16	21	107	finally
    //   23	27	107	finally
    //   29	33	107	finally
    //   35	39	107	finally
    //   44	51	107	finally
    //   55	60	107	finally
    //   60	64	107	finally
    //   78	85	107	finally
    //   85	90	107	finally
  }
  
  public void zza(String paramString, int paramInt, DataHolder paramDataHolder, zzg paramzzg)
  {
    Parcel localParcel1 = Parcel.obtain();
    Parcel localParcel2 = Parcel.obtain();
    Object localObject3;
    for (Object localObject1 = "com.google.android.gms.drive.realtime.internal.IRealtimeService";; localObject3 = null) {
      try
      {
        localParcel1.writeInterfaceToken((String)localObject1);
        localParcel1.writeString(paramString);
        localParcel1.writeInt(paramInt);
        if (paramDataHolder != null)
        {
          i = 1;
          localParcel1.writeInt(i);
          i = 0;
          localObject1 = null;
          paramDataHolder.writeToParcel(localParcel1, 0);
        }
        while (paramzzg != null)
        {
          localObject1 = paramzzg.asBinder();
          localParcel1.writeStrongBinder((IBinder)localObject1);
          localObject1 = this.zzoz;
          int j = 16;
          ((IBinder)localObject1).transact(j, localParcel1, localParcel2, 0);
          localParcel2.readException();
          return;
          i = 0;
          localObject1 = null;
          localParcel1.writeInt(0);
        }
        int i = 0;
      }
      finally
      {
        localParcel2.recycle();
        localParcel1.recycle();
      }
    }
  }
  
  public void zza(String paramString, int paramInt, DataHolder paramDataHolder, zzj paramzzj)
  {
    Parcel localParcel1 = Parcel.obtain();
    Parcel localParcel2 = Parcel.obtain();
    Object localObject3;
    for (Object localObject1 = "com.google.android.gms.drive.realtime.internal.IRealtimeService";; localObject3 = null) {
      try
      {
        localParcel1.writeInterfaceToken((String)localObject1);
        localParcel1.writeString(paramString);
        localParcel1.writeInt(paramInt);
        if (paramDataHolder != null)
        {
          i = 1;
          localParcel1.writeInt(i);
          i = 0;
          localObject1 = null;
          paramDataHolder.writeToParcel(localParcel1, 0);
        }
        while (paramzzj != null)
        {
          localObject1 = paramzzj.asBinder();
          localParcel1.writeStrongBinder((IBinder)localObject1);
          localObject1 = this.zzoz;
          int j = 15;
          ((IBinder)localObject1).transact(j, localParcel1, localParcel2, 0);
          localParcel2.readException();
          return;
          i = 0;
          localObject1 = null;
          localParcel1.writeInt(0);
        }
        int i = 0;
      }
      finally
      {
        localParcel2.recycle();
        localParcel1.recycle();
      }
    }
  }
  
  /* Error */
  public void zza(String paramString, int paramInt, zzn paramzzn)
  {
    // Byte code:
    //   0: invokestatic 20	android/os/Parcel:obtain	()Landroid/os/Parcel;
    //   3: astore 4
    //   5: invokestatic 20	android/os/Parcel:obtain	()Landroid/os/Parcel;
    //   8: astore 5
    //   10: ldc 22
    //   12: astore 6
    //   14: aload 4
    //   16: aload 6
    //   18: invokevirtual 26	android/os/Parcel:writeInterfaceToken	(Ljava/lang/String;)V
    //   21: aload 4
    //   23: aload_1
    //   24: invokevirtual 110	android/os/Parcel:writeString	(Ljava/lang/String;)V
    //   27: aload 4
    //   29: iload_2
    //   30: invokevirtual 30	android/os/Parcel:writeInt	(I)V
    //   33: aload_3
    //   34: ifnull +59 -> 93
    //   37: aload_3
    //   38: invokeinterface 80 1 0
    //   43: astore 6
    //   45: aload 4
    //   47: aload 6
    //   49: invokevirtual 40	android/os/Parcel:writeStrongBinder	(Landroid/os/IBinder;)V
    //   52: aload_0
    //   53: getfield 14	com/google/android/gms/drive/realtime/internal/zzm$zza$zza:zzoz	Landroid/os/IBinder;
    //   56: astore 6
    //   58: bipush 46
    //   60: istore 7
    //   62: aload 6
    //   64: iload 7
    //   66: aload 4
    //   68: aload 5
    //   70: iconst_0
    //   71: invokeinterface 47 5 0
    //   76: pop
    //   77: aload 5
    //   79: invokevirtual 50	android/os/Parcel:readException	()V
    //   82: aload 5
    //   84: invokevirtual 53	android/os/Parcel:recycle	()V
    //   87: aload 4
    //   89: invokevirtual 53	android/os/Parcel:recycle	()V
    //   92: return
    //   93: aconst_null
    //   94: astore 6
    //   96: goto -51 -> 45
    //   99: astore 6
    //   101: aload 5
    //   103: invokevirtual 53	android/os/Parcel:recycle	()V
    //   106: aload 4
    //   108: invokevirtual 53	android/os/Parcel:recycle	()V
    //   111: aload 6
    //   113: athrow
    // Local variable table:
    //   start	length	slot	name	signature
    //   0	114	0	this	zza
    //   0	114	1	paramString	String
    //   0	114	2	paramInt	int
    //   0	114	3	paramzzn	zzn
    //   3	104	4	localParcel1	Parcel
    //   8	94	5	localParcel2	Parcel
    //   12	83	6	localObject1	Object
    //   99	13	6	localObject2	Object
    //   60	5	7	i	int
    // Exception table:
    //   from	to	target	type
    //   16	21	99	finally
    //   23	27	99	finally
    //   29	33	99	finally
    //   37	43	99	finally
    //   47	52	99	finally
    //   52	56	99	finally
    //   70	77	99	finally
    //   77	82	99	finally
  }
  
  /* Error */
  public void zza(String paramString, int paramInt, zzo paramzzo)
  {
    // Byte code:
    //   0: invokestatic 20	android/os/Parcel:obtain	()Landroid/os/Parcel;
    //   3: astore 4
    //   5: invokestatic 20	android/os/Parcel:obtain	()Landroid/os/Parcel;
    //   8: astore 5
    //   10: ldc 22
    //   12: astore 6
    //   14: aload 4
    //   16: aload 6
    //   18: invokevirtual 26	android/os/Parcel:writeInterfaceToken	(Ljava/lang/String;)V
    //   21: aload 4
    //   23: aload_1
    //   24: invokevirtual 110	android/os/Parcel:writeString	(Ljava/lang/String;)V
    //   27: aload 4
    //   29: iload_2
    //   30: invokevirtual 30	android/os/Parcel:writeInt	(I)V
    //   33: aload_3
    //   34: ifnull +59 -> 93
    //   37: aload_3
    //   38: invokeinterface 56 1 0
    //   43: astore 6
    //   45: aload 4
    //   47: aload 6
    //   49: invokevirtual 40	android/os/Parcel:writeStrongBinder	(Landroid/os/IBinder;)V
    //   52: aload_0
    //   53: getfield 14	com/google/android/gms/drive/realtime/internal/zzm$zza$zza:zzoz	Landroid/os/IBinder;
    //   56: astore 6
    //   58: bipush 28
    //   60: istore 7
    //   62: aload 6
    //   64: iload 7
    //   66: aload 4
    //   68: aload 5
    //   70: iconst_0
    //   71: invokeinterface 47 5 0
    //   76: pop
    //   77: aload 5
    //   79: invokevirtual 50	android/os/Parcel:readException	()V
    //   82: aload 5
    //   84: invokevirtual 53	android/os/Parcel:recycle	()V
    //   87: aload 4
    //   89: invokevirtual 53	android/os/Parcel:recycle	()V
    //   92: return
    //   93: aconst_null
    //   94: astore 6
    //   96: goto -51 -> 45
    //   99: astore 6
    //   101: aload 5
    //   103: invokevirtual 53	android/os/Parcel:recycle	()V
    //   106: aload 4
    //   108: invokevirtual 53	android/os/Parcel:recycle	()V
    //   111: aload 6
    //   113: athrow
    // Local variable table:
    //   start	length	slot	name	signature
    //   0	114	0	this	zza
    //   0	114	1	paramString	String
    //   0	114	2	paramInt	int
    //   0	114	3	paramzzo	zzo
    //   3	104	4	localParcel1	Parcel
    //   8	94	5	localParcel2	Parcel
    //   12	83	6	localObject1	Object
    //   99	13	6	localObject2	Object
    //   60	5	7	i	int
    // Exception table:
    //   from	to	target	type
    //   16	21	99	finally
    //   23	27	99	finally
    //   29	33	99	finally
    //   37	43	99	finally
    //   47	52	99	finally
    //   52	56	99	finally
    //   70	77	99	finally
    //   77	82	99	finally
  }
  
  /* Error */
  public void zza(String paramString1, int paramInt1, String paramString2, int paramInt2, zzj paramzzj)
  {
    // Byte code:
    //   0: invokestatic 20	android/os/Parcel:obtain	()Landroid/os/Parcel;
    //   3: astore 6
    //   5: invokestatic 20	android/os/Parcel:obtain	()Landroid/os/Parcel;
    //   8: astore 7
    //   10: ldc 22
    //   12: astore 8
    //   14: aload 6
    //   16: aload 8
    //   18: invokevirtual 26	android/os/Parcel:writeInterfaceToken	(Ljava/lang/String;)V
    //   21: aload 6
    //   23: aload_1
    //   24: invokevirtual 110	android/os/Parcel:writeString	(Ljava/lang/String;)V
    //   27: aload 6
    //   29: iload_2
    //   30: invokevirtual 30	android/os/Parcel:writeInt	(I)V
    //   33: aload 6
    //   35: aload_3
    //   36: invokevirtual 110	android/os/Parcel:writeString	(Ljava/lang/String;)V
    //   39: aload 6
    //   41: iload 4
    //   43: invokevirtual 30	android/os/Parcel:writeInt	(I)V
    //   46: aload 5
    //   48: ifnull +60 -> 108
    //   51: aload 5
    //   53: invokeinterface 36 1 0
    //   58: astore 8
    //   60: aload 6
    //   62: aload 8
    //   64: invokevirtual 40	android/os/Parcel:writeStrongBinder	(Landroid/os/IBinder;)V
    //   67: aload_0
    //   68: getfield 14	com/google/android/gms/drive/realtime/internal/zzm$zza$zza:zzoz	Landroid/os/IBinder;
    //   71: astore 8
    //   73: bipush 37
    //   75: istore 9
    //   77: aload 8
    //   79: iload 9
    //   81: aload 6
    //   83: aload 7
    //   85: iconst_0
    //   86: invokeinterface 47 5 0
    //   91: pop
    //   92: aload 7
    //   94: invokevirtual 50	android/os/Parcel:readException	()V
    //   97: aload 7
    //   99: invokevirtual 53	android/os/Parcel:recycle	()V
    //   102: aload 6
    //   104: invokevirtual 53	android/os/Parcel:recycle	()V
    //   107: return
    //   108: aconst_null
    //   109: astore 8
    //   111: goto -51 -> 60
    //   114: astore 8
    //   116: aload 7
    //   118: invokevirtual 53	android/os/Parcel:recycle	()V
    //   121: aload 6
    //   123: invokevirtual 53	android/os/Parcel:recycle	()V
    //   126: aload 8
    //   128: athrow
    // Local variable table:
    //   start	length	slot	name	signature
    //   0	129	0	this	zza
    //   0	129	1	paramString1	String
    //   0	129	2	paramInt1	int
    //   0	129	3	paramString2	String
    //   0	129	4	paramInt2	int
    //   0	129	5	paramzzj	zzj
    //   3	119	6	localParcel1	Parcel
    //   8	109	7	localParcel2	Parcel
    //   12	98	8	localObject1	Object
    //   114	13	8	localObject2	Object
    //   75	5	9	i	int
    // Exception table:
    //   from	to	target	type
    //   16	21	114	finally
    //   23	27	114	finally
    //   29	33	114	finally
    //   35	39	114	finally
    //   41	46	114	finally
    //   51	58	114	finally
    //   62	67	114	finally
    //   67	71	114	finally
    //   85	92	114	finally
    //   92	97	114	finally
  }
  
  /* Error */
  public void zza(String paramString1, int paramInt, String paramString2, zzj paramzzj)
  {
    // Byte code:
    //   0: invokestatic 20	android/os/Parcel:obtain	()Landroid/os/Parcel;
    //   3: astore 5
    //   5: invokestatic 20	android/os/Parcel:obtain	()Landroid/os/Parcel;
    //   8: astore 6
    //   10: ldc 22
    //   12: astore 7
    //   14: aload 5
    //   16: aload 7
    //   18: invokevirtual 26	android/os/Parcel:writeInterfaceToken	(Ljava/lang/String;)V
    //   21: aload 5
    //   23: aload_1
    //   24: invokevirtual 110	android/os/Parcel:writeString	(Ljava/lang/String;)V
    //   27: aload 5
    //   29: iload_2
    //   30: invokevirtual 30	android/os/Parcel:writeInt	(I)V
    //   33: aload 5
    //   35: aload_3
    //   36: invokevirtual 110	android/os/Parcel:writeString	(Ljava/lang/String;)V
    //   39: aload 4
    //   41: ifnull +60 -> 101
    //   44: aload 4
    //   46: invokeinterface 36 1 0
    //   51: astore 7
    //   53: aload 5
    //   55: aload 7
    //   57: invokevirtual 40	android/os/Parcel:writeStrongBinder	(Landroid/os/IBinder;)V
    //   60: aload_0
    //   61: getfield 14	com/google/android/gms/drive/realtime/internal/zzm$zza$zza:zzoz	Landroid/os/IBinder;
    //   64: astore 7
    //   66: bipush 10
    //   68: istore 8
    //   70: aload 7
    //   72: iload 8
    //   74: aload 5
    //   76: aload 6
    //   78: iconst_0
    //   79: invokeinterface 47 5 0
    //   84: pop
    //   85: aload 6
    //   87: invokevirtual 50	android/os/Parcel:readException	()V
    //   90: aload 6
    //   92: invokevirtual 53	android/os/Parcel:recycle	()V
    //   95: aload 5
    //   97: invokevirtual 53	android/os/Parcel:recycle	()V
    //   100: return
    //   101: aconst_null
    //   102: astore 7
    //   104: goto -51 -> 53
    //   107: astore 7
    //   109: aload 6
    //   111: invokevirtual 53	android/os/Parcel:recycle	()V
    //   114: aload 5
    //   116: invokevirtual 53	android/os/Parcel:recycle	()V
    //   119: aload 7
    //   121: athrow
    // Local variable table:
    //   start	length	slot	name	signature
    //   0	122	0	this	zza
    //   0	122	1	paramString1	String
    //   0	122	2	paramInt	int
    //   0	122	3	paramString2	String
    //   0	122	4	paramzzj	zzj
    //   3	112	5	localParcel1	Parcel
    //   8	102	6	localParcel2	Parcel
    //   12	91	7	localObject1	Object
    //   107	13	7	localObject2	Object
    //   68	5	8	i	int
    // Exception table:
    //   from	to	target	type
    //   16	21	107	finally
    //   23	27	107	finally
    //   29	33	107	finally
    //   35	39	107	finally
    //   44	51	107	finally
    //   55	60	107	finally
    //   60	64	107	finally
    //   78	85	107	finally
    //   85	90	107	finally
  }
  
  public void zza(String paramString, DataHolder paramDataHolder, zzj paramzzj)
  {
    Parcel localParcel1 = Parcel.obtain();
    Parcel localParcel2 = Parcel.obtain();
    Object localObject3;
    for (Object localObject1 = "com.google.android.gms.drive.realtime.internal.IRealtimeService";; localObject3 = null) {
      try
      {
        localParcel1.writeInterfaceToken((String)localObject1);
        localParcel1.writeString(paramString);
        if (paramDataHolder != null)
        {
          i = 1;
          localParcel1.writeInt(i);
          i = 0;
          localObject1 = null;
          paramDataHolder.writeToParcel(localParcel1, 0);
        }
        while (paramzzj != null)
        {
          localObject1 = paramzzj.asBinder();
          localParcel1.writeStrongBinder((IBinder)localObject1);
          localObject1 = this.zzoz;
          int j = 6;
          ((IBinder)localObject1).transact(j, localParcel1, localParcel2, 0);
          localParcel2.readException();
          return;
          i = 0;
          localObject1 = null;
          localParcel1.writeInt(0);
        }
        int i = 0;
      }
      finally
      {
        localParcel2.recycle();
        localParcel1.recycle();
      }
    }
  }
  
  /* Error */
  public void zza(String paramString, zzf paramzzf)
  {
    // Byte code:
    //   0: invokestatic 20	android/os/Parcel:obtain	()Landroid/os/Parcel;
    //   3: astore_3
    //   4: invokestatic 20	android/os/Parcel:obtain	()Landroid/os/Parcel;
    //   7: astore 4
    //   9: ldc 22
    //   11: astore 5
    //   13: aload_3
    //   14: aload 5
    //   16: invokevirtual 26	android/os/Parcel:writeInterfaceToken	(Ljava/lang/String;)V
    //   19: aload_3
    //   20: aload_1
    //   21: invokevirtual 110	android/os/Parcel:writeString	(Ljava/lang/String;)V
    //   24: aload_2
    //   25: ifnull +56 -> 81
    //   28: aload_2
    //   29: invokeinterface 128 1 0
    //   34: astore 5
    //   36: aload_3
    //   37: aload 5
    //   39: invokevirtual 40	android/os/Parcel:writeStrongBinder	(Landroid/os/IBinder;)V
    //   42: aload_0
    //   43: getfield 14	com/google/android/gms/drive/realtime/internal/zzm$zza$zza:zzoz	Landroid/os/IBinder;
    //   46: astore 5
    //   48: bipush 20
    //   50: istore 6
    //   52: aload 5
    //   54: iload 6
    //   56: aload_3
    //   57: aload 4
    //   59: iconst_0
    //   60: invokeinterface 47 5 0
    //   65: pop
    //   66: aload 4
    //   68: invokevirtual 50	android/os/Parcel:readException	()V
    //   71: aload 4
    //   73: invokevirtual 53	android/os/Parcel:recycle	()V
    //   76: aload_3
    //   77: invokevirtual 53	android/os/Parcel:recycle	()V
    //   80: return
    //   81: aconst_null
    //   82: astore 5
    //   84: goto -48 -> 36
    //   87: astore 5
    //   89: aload 4
    //   91: invokevirtual 53	android/os/Parcel:recycle	()V
    //   94: aload_3
    //   95: invokevirtual 53	android/os/Parcel:recycle	()V
    //   98: aload 5
    //   100: athrow
    // Local variable table:
    //   start	length	slot	name	signature
    //   0	101	0	this	zza
    //   0	101	1	paramString	String
    //   0	101	2	paramzzf	zzf
    //   3	92	3	localParcel1	Parcel
    //   7	83	4	localParcel2	Parcel
    //   11	72	5	localObject1	Object
    //   87	12	5	localObject2	Object
    //   50	5	6	i	int
    // Exception table:
    //   from	to	target	type
    //   14	19	87	finally
    //   20	24	87	finally
    //   28	34	87	finally
    //   37	42	87	finally
    //   42	46	87	finally
    //   59	66	87	finally
    //   66	71	87	finally
  }
  
  /* Error */
  public void zza(String paramString, zzj paramzzj)
  {
    // Byte code:
    //   0: invokestatic 20	android/os/Parcel:obtain	()Landroid/os/Parcel;
    //   3: astore_3
    //   4: invokestatic 20	android/os/Parcel:obtain	()Landroid/os/Parcel;
    //   7: astore 4
    //   9: ldc 22
    //   11: astore 5
    //   13: aload_3
    //   14: aload 5
    //   16: invokevirtual 26	android/os/Parcel:writeInterfaceToken	(Ljava/lang/String;)V
    //   19: aload_3
    //   20: aload_1
    //   21: invokevirtual 110	android/os/Parcel:writeString	(Ljava/lang/String;)V
    //   24: aload_2
    //   25: ifnull +56 -> 81
    //   28: aload_2
    //   29: invokeinterface 36 1 0
    //   34: astore 5
    //   36: aload_3
    //   37: aload 5
    //   39: invokevirtual 40	android/os/Parcel:writeStrongBinder	(Landroid/os/IBinder;)V
    //   42: aload_0
    //   43: getfield 14	com/google/android/gms/drive/realtime/internal/zzm$zza$zza:zzoz	Landroid/os/IBinder;
    //   46: astore 5
    //   48: bipush 7
    //   50: istore 6
    //   52: aload 5
    //   54: iload 6
    //   56: aload_3
    //   57: aload 4
    //   59: iconst_0
    //   60: invokeinterface 47 5 0
    //   65: pop
    //   66: aload 4
    //   68: invokevirtual 50	android/os/Parcel:readException	()V
    //   71: aload 4
    //   73: invokevirtual 53	android/os/Parcel:recycle	()V
    //   76: aload_3
    //   77: invokevirtual 53	android/os/Parcel:recycle	()V
    //   80: return
    //   81: aconst_null
    //   82: astore 5
    //   84: goto -48 -> 36
    //   87: astore 5
    //   89: aload 4
    //   91: invokevirtual 53	android/os/Parcel:recycle	()V
    //   94: aload_3
    //   95: invokevirtual 53	android/os/Parcel:recycle	()V
    //   98: aload 5
    //   100: athrow
    // Local variable table:
    //   start	length	slot	name	signature
    //   0	101	0	this	zza
    //   0	101	1	paramString	String
    //   0	101	2	paramzzj	zzj
    //   3	92	3	localParcel1	Parcel
    //   7	83	4	localParcel2	Parcel
    //   11	72	5	localObject1	Object
    //   87	12	5	localObject2	Object
    //   50	5	6	i	int
    // Exception table:
    //   from	to	target	type
    //   14	19	87	finally
    //   20	24	87	finally
    //   28	34	87	finally
    //   37	42	87	finally
    //   42	46	87	finally
    //   59	66	87	finally
    //   66	71	87	finally
  }
  
  /* Error */
  public void zza(String paramString, zzk paramzzk)
  {
    // Byte code:
    //   0: invokestatic 20	android/os/Parcel:obtain	()Landroid/os/Parcel;
    //   3: astore_3
    //   4: invokestatic 20	android/os/Parcel:obtain	()Landroid/os/Parcel;
    //   7: astore 4
    //   9: ldc 22
    //   11: astore 5
    //   13: aload_3
    //   14: aload 5
    //   16: invokevirtual 26	android/os/Parcel:writeInterfaceToken	(Ljava/lang/String;)V
    //   19: aload_3
    //   20: aload_1
    //   21: invokevirtual 110	android/os/Parcel:writeString	(Ljava/lang/String;)V
    //   24: aload_2
    //   25: ifnull +56 -> 81
    //   28: aload_2
    //   29: invokeinterface 133 1 0
    //   34: astore 5
    //   36: aload_3
    //   37: aload 5
    //   39: invokevirtual 40	android/os/Parcel:writeStrongBinder	(Landroid/os/IBinder;)V
    //   42: aload_0
    //   43: getfield 14	com/google/android/gms/drive/realtime/internal/zzm$zza$zza:zzoz	Landroid/os/IBinder;
    //   46: astore 5
    //   48: bipush 27
    //   50: istore 6
    //   52: aload 5
    //   54: iload 6
    //   56: aload_3
    //   57: aload 4
    //   59: iconst_0
    //   60: invokeinterface 47 5 0
    //   65: pop
    //   66: aload 4
    //   68: invokevirtual 50	android/os/Parcel:readException	()V
    //   71: aload 4
    //   73: invokevirtual 53	android/os/Parcel:recycle	()V
    //   76: aload_3
    //   77: invokevirtual 53	android/os/Parcel:recycle	()V
    //   80: return
    //   81: aconst_null
    //   82: astore 5
    //   84: goto -48 -> 36
    //   87: astore 5
    //   89: aload 4
    //   91: invokevirtual 53	android/os/Parcel:recycle	()V
    //   94: aload_3
    //   95: invokevirtual 53	android/os/Parcel:recycle	()V
    //   98: aload 5
    //   100: athrow
    // Local variable table:
    //   start	length	slot	name	signature
    //   0	101	0	this	zza
    //   0	101	1	paramString	String
    //   0	101	2	paramzzk	zzk
    //   3	92	3	localParcel1	Parcel
    //   7	83	4	localParcel2	Parcel
    //   11	72	5	localObject1	Object
    //   87	12	5	localObject2	Object
    //   50	5	6	i	int
    // Exception table:
    //   from	to	target	type
    //   14	19	87	finally
    //   20	24	87	finally
    //   28	34	87	finally
    //   37	42	87	finally
    //   42	46	87	finally
    //   59	66	87	finally
    //   66	71	87	finally
  }
  
  /* Error */
  public void zza(String paramString, zzl paramzzl)
  {
    // Byte code:
    //   0: invokestatic 20	android/os/Parcel:obtain	()Landroid/os/Parcel;
    //   3: astore_3
    //   4: invokestatic 20	android/os/Parcel:obtain	()Landroid/os/Parcel;
    //   7: astore 4
    //   9: ldc 22
    //   11: astore 5
    //   13: aload_3
    //   14: aload 5
    //   16: invokevirtual 26	android/os/Parcel:writeInterfaceToken	(Ljava/lang/String;)V
    //   19: aload_3
    //   20: aload_1
    //   21: invokevirtual 110	android/os/Parcel:writeString	(Ljava/lang/String;)V
    //   24: aload_2
    //   25: ifnull +55 -> 80
    //   28: aload_2
    //   29: invokeinterface 105 1 0
    //   34: astore 5
    //   36: aload_3
    //   37: aload 5
    //   39: invokevirtual 40	android/os/Parcel:writeStrongBinder	(Landroid/os/IBinder;)V
    //   42: aload_0
    //   43: getfield 14	com/google/android/gms/drive/realtime/internal/zzm$zza$zza:zzoz	Landroid/os/IBinder;
    //   46: astore 5
    //   48: iconst_5
    //   49: istore 6
    //   51: aload 5
    //   53: iload 6
    //   55: aload_3
    //   56: aload 4
    //   58: iconst_0
    //   59: invokeinterface 47 5 0
    //   64: pop
    //   65: aload 4
    //   67: invokevirtual 50	android/os/Parcel:readException	()V
    //   70: aload 4
    //   72: invokevirtual 53	android/os/Parcel:recycle	()V
    //   75: aload_3
    //   76: invokevirtual 53	android/os/Parcel:recycle	()V
    //   79: return
    //   80: aconst_null
    //   81: astore 5
    //   83: goto -47 -> 36
    //   86: astore 5
    //   88: aload 4
    //   90: invokevirtual 53	android/os/Parcel:recycle	()V
    //   93: aload_3
    //   94: invokevirtual 53	android/os/Parcel:recycle	()V
    //   97: aload 5
    //   99: athrow
    // Local variable table:
    //   start	length	slot	name	signature
    //   0	100	0	this	zza
    //   0	100	1	paramString	String
    //   0	100	2	paramzzl	zzl
    //   3	91	3	localParcel1	Parcel
    //   7	82	4	localParcel2	Parcel
    //   11	71	5	localObject1	Object
    //   86	12	5	localObject2	Object
    //   49	5	6	i	int
    // Exception table:
    //   from	to	target	type
    //   14	19	86	finally
    //   20	24	86	finally
    //   28	34	86	finally
    //   37	42	86	finally
    //   42	46	86	finally
    //   58	65	86	finally
    //   65	70	86	finally
  }
  
  /* Error */
  public void zza(String paramString, zzn paramzzn)
  {
    // Byte code:
    //   0: invokestatic 20	android/os/Parcel:obtain	()Landroid/os/Parcel;
    //   3: astore_3
    //   4: invokestatic 20	android/os/Parcel:obtain	()Landroid/os/Parcel;
    //   7: astore 4
    //   9: ldc 22
    //   11: astore 5
    //   13: aload_3
    //   14: aload 5
    //   16: invokevirtual 26	android/os/Parcel:writeInterfaceToken	(Ljava/lang/String;)V
    //   19: aload_3
    //   20: aload_1
    //   21: invokevirtual 110	android/os/Parcel:writeString	(Ljava/lang/String;)V
    //   24: aload_2
    //   25: ifnull +55 -> 80
    //   28: aload_2
    //   29: invokeinterface 80 1 0
    //   34: astore 5
    //   36: aload_3
    //   37: aload 5
    //   39: invokevirtual 40	android/os/Parcel:writeStrongBinder	(Landroid/os/IBinder;)V
    //   42: aload_0
    //   43: getfield 14	com/google/android/gms/drive/realtime/internal/zzm$zza$zza:zzoz	Landroid/os/IBinder;
    //   46: astore 5
    //   48: iconst_1
    //   49: istore 6
    //   51: aload 5
    //   53: iload 6
    //   55: aload_3
    //   56: aload 4
    //   58: iconst_0
    //   59: invokeinterface 47 5 0
    //   64: pop
    //   65: aload 4
    //   67: invokevirtual 50	android/os/Parcel:readException	()V
    //   70: aload 4
    //   72: invokevirtual 53	android/os/Parcel:recycle	()V
    //   75: aload_3
    //   76: invokevirtual 53	android/os/Parcel:recycle	()V
    //   79: return
    //   80: aconst_null
    //   81: astore 5
    //   83: goto -47 -> 36
    //   86: astore 5
    //   88: aload 4
    //   90: invokevirtual 53	android/os/Parcel:recycle	()V
    //   93: aload_3
    //   94: invokevirtual 53	android/os/Parcel:recycle	()V
    //   97: aload 5
    //   99: athrow
    // Local variable table:
    //   start	length	slot	name	signature
    //   0	100	0	this	zza
    //   0	100	1	paramString	String
    //   0	100	2	paramzzn	zzn
    //   3	91	3	localParcel1	Parcel
    //   7	82	4	localParcel2	Parcel
    //   11	71	5	localObject1	Object
    //   86	12	5	localObject2	Object
    //   49	5	6	i	int
    // Exception table:
    //   from	to	target	type
    //   14	19	86	finally
    //   20	24	86	finally
    //   28	34	86	finally
    //   37	42	86	finally
    //   42	46	86	finally
    //   58	65	86	finally
    //   65	70	86	finally
  }
  
  /* Error */
  public void zza(String paramString, zzo paramzzo)
  {
    // Byte code:
    //   0: invokestatic 20	android/os/Parcel:obtain	()Landroid/os/Parcel;
    //   3: astore_3
    //   4: invokestatic 20	android/os/Parcel:obtain	()Landroid/os/Parcel;
    //   7: astore 4
    //   9: ldc 22
    //   11: astore 5
    //   13: aload_3
    //   14: aload 5
    //   16: invokevirtual 26	android/os/Parcel:writeInterfaceToken	(Ljava/lang/String;)V
    //   19: aload_3
    //   20: aload_1
    //   21: invokevirtual 110	android/os/Parcel:writeString	(Ljava/lang/String;)V
    //   24: aload_2
    //   25: ifnull +56 -> 81
    //   28: aload_2
    //   29: invokeinterface 56 1 0
    //   34: astore 5
    //   36: aload_3
    //   37: aload 5
    //   39: invokevirtual 40	android/os/Parcel:writeStrongBinder	(Landroid/os/IBinder;)V
    //   42: aload_0
    //   43: getfield 14	com/google/android/gms/drive/realtime/internal/zzm$zza$zza:zzoz	Landroid/os/IBinder;
    //   46: astore 5
    //   48: bipush 38
    //   50: istore 6
    //   52: aload 5
    //   54: iload 6
    //   56: aload_3
    //   57: aload 4
    //   59: iconst_0
    //   60: invokeinterface 47 5 0
    //   65: pop
    //   66: aload 4
    //   68: invokevirtual 50	android/os/Parcel:readException	()V
    //   71: aload 4
    //   73: invokevirtual 53	android/os/Parcel:recycle	()V
    //   76: aload_3
    //   77: invokevirtual 53	android/os/Parcel:recycle	()V
    //   80: return
    //   81: aconst_null
    //   82: astore 5
    //   84: goto -48 -> 36
    //   87: astore 5
    //   89: aload 4
    //   91: invokevirtual 53	android/os/Parcel:recycle	()V
    //   94: aload_3
    //   95: invokevirtual 53	android/os/Parcel:recycle	()V
    //   98: aload 5
    //   100: athrow
    // Local variable table:
    //   start	length	slot	name	signature
    //   0	101	0	this	zza
    //   0	101	1	paramString	String
    //   0	101	2	paramzzo	zzo
    //   3	92	3	localParcel1	Parcel
    //   7	83	4	localParcel2	Parcel
    //   11	72	5	localObject1	Object
    //   87	12	5	localObject2	Object
    //   50	5	6	i	int
    // Exception table:
    //   from	to	target	type
    //   14	19	87	finally
    //   20	24	87	finally
    //   28	34	87	finally
    //   37	42	87	finally
    //   42	46	87	finally
    //   59	66	87	finally
    //   66	71	87	finally
  }
  
  public void zza(String paramString1, String paramString2, DataHolder paramDataHolder, zzj paramzzj)
  {
    Parcel localParcel1 = Parcel.obtain();
    Parcel localParcel2 = Parcel.obtain();
    Object localObject3;
    for (Object localObject1 = "com.google.android.gms.drive.realtime.internal.IRealtimeService";; localObject3 = null) {
      try
      {
        localParcel1.writeInterfaceToken((String)localObject1);
        localParcel1.writeString(paramString1);
        localParcel1.writeString(paramString2);
        if (paramDataHolder != null)
        {
          i = 1;
          localParcel1.writeInt(i);
          i = 0;
          localObject1 = null;
          paramDataHolder.writeToParcel(localParcel1, 0);
        }
        while (paramzzj != null)
        {
          localObject1 = paramzzj.asBinder();
          localParcel1.writeStrongBinder((IBinder)localObject1);
          localObject1 = this.zzoz;
          int j = 43;
          ((IBinder)localObject1).transact(j, localParcel1, localParcel2, 0);
          localParcel2.readException();
          return;
          i = 0;
          localObject1 = null;
          localParcel1.writeInt(0);
        }
        int i = 0;
      }
      finally
      {
        localParcel2.recycle();
        localParcel1.recycle();
      }
    }
  }
  
  /* Error */
  public void zza(String paramString1, String paramString2, zzf paramzzf)
  {
    // Byte code:
    //   0: invokestatic 20	android/os/Parcel:obtain	()Landroid/os/Parcel;
    //   3: astore 4
    //   5: invokestatic 20	android/os/Parcel:obtain	()Landroid/os/Parcel;
    //   8: astore 5
    //   10: ldc 22
    //   12: astore 6
    //   14: aload 4
    //   16: aload 6
    //   18: invokevirtual 26	android/os/Parcel:writeInterfaceToken	(Ljava/lang/String;)V
    //   21: aload 4
    //   23: aload_1
    //   24: invokevirtual 110	android/os/Parcel:writeString	(Ljava/lang/String;)V
    //   27: aload 4
    //   29: aload_2
    //   30: invokevirtual 110	android/os/Parcel:writeString	(Ljava/lang/String;)V
    //   33: aload_3
    //   34: ifnull +58 -> 92
    //   37: aload_3
    //   38: invokeinterface 128 1 0
    //   43: astore 6
    //   45: aload 4
    //   47: aload 6
    //   49: invokevirtual 40	android/os/Parcel:writeStrongBinder	(Landroid/os/IBinder;)V
    //   52: aload_0
    //   53: getfield 14	com/google/android/gms/drive/realtime/internal/zzm$zza$zza:zzoz	Landroid/os/IBinder;
    //   56: astore 6
    //   58: iconst_4
    //   59: istore 7
    //   61: aload 6
    //   63: iload 7
    //   65: aload 4
    //   67: aload 5
    //   69: iconst_0
    //   70: invokeinterface 47 5 0
    //   75: pop
    //   76: aload 5
    //   78: invokevirtual 50	android/os/Parcel:readException	()V
    //   81: aload 5
    //   83: invokevirtual 53	android/os/Parcel:recycle	()V
    //   86: aload 4
    //   88: invokevirtual 53	android/os/Parcel:recycle	()V
    //   91: return
    //   92: aconst_null
    //   93: astore 6
    //   95: goto -50 -> 45
    //   98: astore 6
    //   100: aload 5
    //   102: invokevirtual 53	android/os/Parcel:recycle	()V
    //   105: aload 4
    //   107: invokevirtual 53	android/os/Parcel:recycle	()V
    //   110: aload 6
    //   112: athrow
    // Local variable table:
    //   start	length	slot	name	signature
    //   0	113	0	this	zza
    //   0	113	1	paramString1	String
    //   0	113	2	paramString2	String
    //   0	113	3	paramzzf	zzf
    //   3	103	4	localParcel1	Parcel
    //   8	93	5	localParcel2	Parcel
    //   12	82	6	localObject1	Object
    //   98	13	6	localObject2	Object
    //   59	5	7	i	int
    // Exception table:
    //   from	to	target	type
    //   16	21	98	finally
    //   23	27	98	finally
    //   29	33	98	finally
    //   37	43	98	finally
    //   47	52	98	finally
    //   52	56	98	finally
    //   69	76	98	finally
    //   76	81	98	finally
  }
  
  /* Error */
  public void zza(String paramString1, String paramString2, zzg paramzzg)
  {
    // Byte code:
    //   0: invokestatic 20	android/os/Parcel:obtain	()Landroid/os/Parcel;
    //   3: astore 4
    //   5: invokestatic 20	android/os/Parcel:obtain	()Landroid/os/Parcel;
    //   8: astore 5
    //   10: ldc 22
    //   12: astore 6
    //   14: aload 4
    //   16: aload 6
    //   18: invokevirtual 26	android/os/Parcel:writeInterfaceToken	(Ljava/lang/String;)V
    //   21: aload 4
    //   23: aload_1
    //   24: invokevirtual 110	android/os/Parcel:writeString	(Ljava/lang/String;)V
    //   27: aload 4
    //   29: aload_2
    //   30: invokevirtual 110	android/os/Parcel:writeString	(Ljava/lang/String;)V
    //   33: aload_3
    //   34: ifnull +59 -> 93
    //   37: aload_3
    //   38: invokeinterface 113 1 0
    //   43: astore 6
    //   45: aload 4
    //   47: aload 6
    //   49: invokevirtual 40	android/os/Parcel:writeStrongBinder	(Landroid/os/IBinder;)V
    //   52: aload_0
    //   53: getfield 14	com/google/android/gms/drive/realtime/internal/zzm$zza$zza:zzoz	Landroid/os/IBinder;
    //   56: astore 6
    //   58: bipush 21
    //   60: istore 7
    //   62: aload 6
    //   64: iload 7
    //   66: aload 4
    //   68: aload 5
    //   70: iconst_0
    //   71: invokeinterface 47 5 0
    //   76: pop
    //   77: aload 5
    //   79: invokevirtual 50	android/os/Parcel:readException	()V
    //   82: aload 5
    //   84: invokevirtual 53	android/os/Parcel:recycle	()V
    //   87: aload 4
    //   89: invokevirtual 53	android/os/Parcel:recycle	()V
    //   92: return
    //   93: aconst_null
    //   94: astore 6
    //   96: goto -51 -> 45
    //   99: astore 6
    //   101: aload 5
    //   103: invokevirtual 53	android/os/Parcel:recycle	()V
    //   106: aload 4
    //   108: invokevirtual 53	android/os/Parcel:recycle	()V
    //   111: aload 6
    //   113: athrow
    // Local variable table:
    //   start	length	slot	name	signature
    //   0	114	0	this	zza
    //   0	114	1	paramString1	String
    //   0	114	2	paramString2	String
    //   0	114	3	paramzzg	zzg
    //   3	104	4	localParcel1	Parcel
    //   8	94	5	localParcel2	Parcel
    //   12	83	6	localObject1	Object
    //   99	13	6	localObject2	Object
    //   60	5	7	i	int
    // Exception table:
    //   from	to	target	type
    //   16	21	99	finally
    //   23	27	99	finally
    //   29	33	99	finally
    //   37	43	99	finally
    //   47	52	99	finally
    //   52	56	99	finally
    //   70	77	99	finally
    //   77	82	99	finally
  }
  
  /* Error */
  public void zza(String paramString1, String paramString2, zzj paramzzj)
  {
    // Byte code:
    //   0: invokestatic 20	android/os/Parcel:obtain	()Landroid/os/Parcel;
    //   3: astore 4
    //   5: invokestatic 20	android/os/Parcel:obtain	()Landroid/os/Parcel;
    //   8: astore 5
    //   10: ldc 22
    //   12: astore 6
    //   14: aload 4
    //   16: aload 6
    //   18: invokevirtual 26	android/os/Parcel:writeInterfaceToken	(Ljava/lang/String;)V
    //   21: aload 4
    //   23: aload_1
    //   24: invokevirtual 110	android/os/Parcel:writeString	(Ljava/lang/String;)V
    //   27: aload 4
    //   29: aload_2
    //   30: invokevirtual 110	android/os/Parcel:writeString	(Ljava/lang/String;)V
    //   33: aload_3
    //   34: ifnull +59 -> 93
    //   37: aload_3
    //   38: invokeinterface 36 1 0
    //   43: astore 6
    //   45: aload 4
    //   47: aload 6
    //   49: invokevirtual 40	android/os/Parcel:writeStrongBinder	(Landroid/os/IBinder;)V
    //   52: aload_0
    //   53: getfield 14	com/google/android/gms/drive/realtime/internal/zzm$zza$zza:zzoz	Landroid/os/IBinder;
    //   56: astore 6
    //   58: bipush 12
    //   60: istore 7
    //   62: aload 6
    //   64: iload 7
    //   66: aload 4
    //   68: aload 5
    //   70: iconst_0
    //   71: invokeinterface 47 5 0
    //   76: pop
    //   77: aload 5
    //   79: invokevirtual 50	android/os/Parcel:readException	()V
    //   82: aload 5
    //   84: invokevirtual 53	android/os/Parcel:recycle	()V
    //   87: aload 4
    //   89: invokevirtual 53	android/os/Parcel:recycle	()V
    //   92: return
    //   93: aconst_null
    //   94: astore 6
    //   96: goto -51 -> 45
    //   99: astore 6
    //   101: aload 5
    //   103: invokevirtual 53	android/os/Parcel:recycle	()V
    //   106: aload 4
    //   108: invokevirtual 53	android/os/Parcel:recycle	()V
    //   111: aload 6
    //   113: athrow
    // Local variable table:
    //   start	length	slot	name	signature
    //   0	114	0	this	zza
    //   0	114	1	paramString1	String
    //   0	114	2	paramString2	String
    //   0	114	3	paramzzj	zzj
    //   3	104	4	localParcel1	Parcel
    //   8	94	5	localParcel2	Parcel
    //   12	83	6	localObject1	Object
    //   99	13	6	localObject2	Object
    //   60	5	7	i	int
    // Exception table:
    //   from	to	target	type
    //   16	21	99	finally
    //   23	27	99	finally
    //   29	33	99	finally
    //   37	43	99	finally
    //   47	52	99	finally
    //   52	56	99	finally
    //   70	77	99	finally
    //   77	82	99	finally
  }
  
  /* Error */
  public void zza(boolean paramBoolean, zzo paramzzo)
  {
    // Byte code:
    //   0: iconst_0
    //   1: istore_3
    //   2: aconst_null
    //   3: astore 4
    //   5: invokestatic 20	android/os/Parcel:obtain	()Landroid/os/Parcel;
    //   8: astore 5
    //   10: invokestatic 20	android/os/Parcel:obtain	()Landroid/os/Parcel;
    //   13: astore 6
    //   15: ldc 22
    //   17: astore 7
    //   19: aload 5
    //   21: aload 7
    //   23: invokevirtual 26	android/os/Parcel:writeInterfaceToken	(Ljava/lang/String;)V
    //   26: iload_1
    //   27: ifeq +5 -> 32
    //   30: iconst_1
    //   31: istore_3
    //   32: aload 5
    //   34: iload_3
    //   35: invokevirtual 30	android/os/Parcel:writeInt	(I)V
    //   38: aload_2
    //   39: ifnull +59 -> 98
    //   42: aload_2
    //   43: invokeinterface 56 1 0
    //   48: astore 4
    //   50: aload 5
    //   52: aload 4
    //   54: invokevirtual 40	android/os/Parcel:writeStrongBinder	(Landroid/os/IBinder;)V
    //   57: aload_0
    //   58: getfield 14	com/google/android/gms/drive/realtime/internal/zzm$zza$zza:zzoz	Landroid/os/IBinder;
    //   61: astore 4
    //   63: bipush 47
    //   65: istore 8
    //   67: aload 4
    //   69: iload 8
    //   71: aload 5
    //   73: aload 6
    //   75: iconst_0
    //   76: invokeinterface 47 5 0
    //   81: pop
    //   82: aload 6
    //   84: invokevirtual 50	android/os/Parcel:readException	()V
    //   87: aload 6
    //   89: invokevirtual 53	android/os/Parcel:recycle	()V
    //   92: aload 5
    //   94: invokevirtual 53	android/os/Parcel:recycle	()V
    //   97: return
    //   98: iconst_0
    //   99: istore_3
    //   100: aconst_null
    //   101: astore 4
    //   103: goto -53 -> 50
    //   106: astore 4
    //   108: aload 6
    //   110: invokevirtual 53	android/os/Parcel:recycle	()V
    //   113: aload 5
    //   115: invokevirtual 53	android/os/Parcel:recycle	()V
    //   118: aload 4
    //   120: athrow
    // Local variable table:
    //   start	length	slot	name	signature
    //   0	121	0	this	zza
    //   0	121	1	paramBoolean	boolean
    //   0	121	2	paramzzo	zzo
    //   1	99	3	i	int
    //   3	99	4	localIBinder	IBinder
    //   106	13	4	localObject	Object
    //   8	106	5	localParcel1	Parcel
    //   13	96	6	localParcel2	Parcel
    //   17	5	7	str	String
    //   65	5	8	j	int
    // Exception table:
    //   from	to	target	type
    //   21	26	106	finally
    //   34	38	106	finally
    //   42	48	106	finally
    //   52	57	106	finally
    //   57	61	106	finally
    //   75	82	106	finally
    //   82	87	106	finally
  }
  
  /* Error */
  public void zzb(zzc paramzzc)
  {
    // Byte code:
    //   0: invokestatic 20	android/os/Parcel:obtain	()Landroid/os/Parcel;
    //   3: astore_2
    //   4: invokestatic 20	android/os/Parcel:obtain	()Landroid/os/Parcel;
    //   7: astore_3
    //   8: ldc 22
    //   10: astore 4
    //   12: aload_2
    //   13: aload 4
    //   15: invokevirtual 26	android/os/Parcel:writeInterfaceToken	(Ljava/lang/String;)V
    //   18: aload_1
    //   19: ifnull +53 -> 72
    //   22: aload_1
    //   23: invokeinterface 84 1 0
    //   28: astore 4
    //   30: aload_2
    //   31: aload 4
    //   33: invokevirtual 40	android/os/Parcel:writeStrongBinder	(Landroid/os/IBinder;)V
    //   36: aload_0
    //   37: getfield 14	com/google/android/gms/drive/realtime/internal/zzm$zza$zza:zzoz	Landroid/os/IBinder;
    //   40: astore 4
    //   42: bipush 33
    //   44: istore 5
    //   46: aload 4
    //   48: iload 5
    //   50: aload_2
    //   51: aload_3
    //   52: iconst_0
    //   53: invokeinterface 47 5 0
    //   58: pop
    //   59: aload_3
    //   60: invokevirtual 50	android/os/Parcel:readException	()V
    //   63: aload_3
    //   64: invokevirtual 53	android/os/Parcel:recycle	()V
    //   67: aload_2
    //   68: invokevirtual 53	android/os/Parcel:recycle	()V
    //   71: return
    //   72: aconst_null
    //   73: astore 4
    //   75: goto -45 -> 30
    //   78: astore 4
    //   80: aload_3
    //   81: invokevirtual 53	android/os/Parcel:recycle	()V
    //   84: aload_2
    //   85: invokevirtual 53	android/os/Parcel:recycle	()V
    //   88: aload 4
    //   90: athrow
    // Local variable table:
    //   start	length	slot	name	signature
    //   0	91	0	this	zza
    //   0	91	1	paramzzc	zzc
    //   3	82	2	localParcel1	Parcel
    //   7	74	3	localParcel2	Parcel
    //   10	64	4	localObject1	Object
    //   78	11	4	localObject2	Object
    //   44	5	5	i	int
    // Exception table:
    //   from	to	target	type
    //   13	18	78	finally
    //   22	28	78	finally
    //   31	36	78	finally
    //   36	40	78	finally
    //   52	59	78	finally
    //   59	63	78	finally
  }
  
  /* Error */
  public void zzb(zzj paramzzj)
  {
    // Byte code:
    //   0: invokestatic 20	android/os/Parcel:obtain	()Landroid/os/Parcel;
    //   3: astore_2
    //   4: invokestatic 20	android/os/Parcel:obtain	()Landroid/os/Parcel;
    //   7: astore_3
    //   8: ldc 22
    //   10: astore 4
    //   12: aload_2
    //   13: aload 4
    //   15: invokevirtual 26	android/os/Parcel:writeInterfaceToken	(Ljava/lang/String;)V
    //   18: aload_1
    //   19: ifnull +53 -> 72
    //   22: aload_1
    //   23: invokeinterface 36 1 0
    //   28: astore 4
    //   30: aload_2
    //   31: aload 4
    //   33: invokevirtual 40	android/os/Parcel:writeStrongBinder	(Landroid/os/IBinder;)V
    //   36: aload_0
    //   37: getfield 14	com/google/android/gms/drive/realtime/internal/zzm$zza$zza:zzoz	Landroid/os/IBinder;
    //   40: astore 4
    //   42: bipush 23
    //   44: istore 5
    //   46: aload 4
    //   48: iload 5
    //   50: aload_2
    //   51: aload_3
    //   52: iconst_0
    //   53: invokeinterface 47 5 0
    //   58: pop
    //   59: aload_3
    //   60: invokevirtual 50	android/os/Parcel:readException	()V
    //   63: aload_3
    //   64: invokevirtual 53	android/os/Parcel:recycle	()V
    //   67: aload_2
    //   68: invokevirtual 53	android/os/Parcel:recycle	()V
    //   71: return
    //   72: aconst_null
    //   73: astore 4
    //   75: goto -45 -> 30
    //   78: astore 4
    //   80: aload_3
    //   81: invokevirtual 53	android/os/Parcel:recycle	()V
    //   84: aload_2
    //   85: invokevirtual 53	android/os/Parcel:recycle	()V
    //   88: aload 4
    //   90: athrow
    // Local variable table:
    //   start	length	slot	name	signature
    //   0	91	0	this	zza
    //   0	91	1	paramzzj	zzj
    //   3	82	2	localParcel1	Parcel
    //   7	74	3	localParcel2	Parcel
    //   10	64	4	localObject1	Object
    //   78	11	4	localObject2	Object
    //   44	5	5	i	int
    // Exception table:
    //   from	to	target	type
    //   13	18	78	finally
    //   22	28	78	finally
    //   31	36	78	finally
    //   36	40	78	finally
    //   52	59	78	finally
    //   59	63	78	finally
  }
  
  /* Error */
  public void zzb(zzl paramzzl)
  {
    // Byte code:
    //   0: invokestatic 20	android/os/Parcel:obtain	()Landroid/os/Parcel;
    //   3: astore_2
    //   4: invokestatic 20	android/os/Parcel:obtain	()Landroid/os/Parcel;
    //   7: astore_3
    //   8: ldc 22
    //   10: astore 4
    //   12: aload_2
    //   13: aload 4
    //   15: invokevirtual 26	android/os/Parcel:writeInterfaceToken	(Ljava/lang/String;)V
    //   18: aload_1
    //   19: ifnull +53 -> 72
    //   22: aload_1
    //   23: invokeinterface 105 1 0
    //   28: astore 4
    //   30: aload_2
    //   31: aload 4
    //   33: invokevirtual 40	android/os/Parcel:writeStrongBinder	(Landroid/os/IBinder;)V
    //   36: aload_0
    //   37: getfield 14	com/google/android/gms/drive/realtime/internal/zzm$zza$zza:zzoz	Landroid/os/IBinder;
    //   40: astore 4
    //   42: bipush 29
    //   44: istore 5
    //   46: aload 4
    //   48: iload 5
    //   50: aload_2
    //   51: aload_3
    //   52: iconst_0
    //   53: invokeinterface 47 5 0
    //   58: pop
    //   59: aload_3
    //   60: invokevirtual 50	android/os/Parcel:readException	()V
    //   63: aload_3
    //   64: invokevirtual 53	android/os/Parcel:recycle	()V
    //   67: aload_2
    //   68: invokevirtual 53	android/os/Parcel:recycle	()V
    //   71: return
    //   72: aconst_null
    //   73: astore 4
    //   75: goto -45 -> 30
    //   78: astore 4
    //   80: aload_3
    //   81: invokevirtual 53	android/os/Parcel:recycle	()V
    //   84: aload_2
    //   85: invokevirtual 53	android/os/Parcel:recycle	()V
    //   88: aload 4
    //   90: athrow
    // Local variable table:
    //   start	length	slot	name	signature
    //   0	91	0	this	zza
    //   0	91	1	paramzzl	zzl
    //   3	82	2	localParcel1	Parcel
    //   7	74	3	localParcel2	Parcel
    //   10	64	4	localObject1	Object
    //   78	11	4	localObject2	Object
    //   44	5	5	i	int
    // Exception table:
    //   from	to	target	type
    //   13	18	78	finally
    //   22	28	78	finally
    //   31	36	78	finally
    //   36	40	78	finally
    //   52	59	78	finally
    //   59	63	78	finally
  }
  
  /* Error */
  public void zzb(zzo paramzzo)
  {
    // Byte code:
    //   0: invokestatic 20	android/os/Parcel:obtain	()Landroid/os/Parcel;
    //   3: astore_2
    //   4: invokestatic 20	android/os/Parcel:obtain	()Landroid/os/Parcel;
    //   7: astore_3
    //   8: ldc 22
    //   10: astore 4
    //   12: aload_2
    //   13: aload 4
    //   15: invokevirtual 26	android/os/Parcel:writeInterfaceToken	(Ljava/lang/String;)V
    //   18: aload_1
    //   19: ifnull +53 -> 72
    //   22: aload_1
    //   23: invokeinterface 56 1 0
    //   28: astore 4
    //   30: aload_2
    //   31: aload 4
    //   33: invokevirtual 40	android/os/Parcel:writeStrongBinder	(Landroid/os/IBinder;)V
    //   36: aload_0
    //   37: getfield 14	com/google/android/gms/drive/realtime/internal/zzm$zza$zza:zzoz	Landroid/os/IBinder;
    //   40: astore 4
    //   42: bipush 35
    //   44: istore 5
    //   46: aload 4
    //   48: iload 5
    //   50: aload_2
    //   51: aload_3
    //   52: iconst_0
    //   53: invokeinterface 47 5 0
    //   58: pop
    //   59: aload_3
    //   60: invokevirtual 50	android/os/Parcel:readException	()V
    //   63: aload_3
    //   64: invokevirtual 53	android/os/Parcel:recycle	()V
    //   67: aload_2
    //   68: invokevirtual 53	android/os/Parcel:recycle	()V
    //   71: return
    //   72: aconst_null
    //   73: astore 4
    //   75: goto -45 -> 30
    //   78: astore 4
    //   80: aload_3
    //   81: invokevirtual 53	android/os/Parcel:recycle	()V
    //   84: aload_2
    //   85: invokevirtual 53	android/os/Parcel:recycle	()V
    //   88: aload 4
    //   90: athrow
    // Local variable table:
    //   start	length	slot	name	signature
    //   0	91	0	this	zza
    //   0	91	1	paramzzo	zzo
    //   3	82	2	localParcel1	Parcel
    //   7	74	3	localParcel2	Parcel
    //   10	64	4	localObject1	Object
    //   78	11	4	localObject2	Object
    //   44	5	5	i	int
    // Exception table:
    //   from	to	target	type
    //   13	18	78	finally
    //   22	28	78	finally
    //   31	36	78	finally
    //   36	40	78	finally
    //   52	59	78	finally
    //   59	63	78	finally
  }
  
  /* Error */
  public void zzb(String paramString, zzf paramzzf)
  {
    // Byte code:
    //   0: invokestatic 20	android/os/Parcel:obtain	()Landroid/os/Parcel;
    //   3: astore_3
    //   4: invokestatic 20	android/os/Parcel:obtain	()Landroid/os/Parcel;
    //   7: astore 4
    //   9: ldc 22
    //   11: astore 5
    //   13: aload_3
    //   14: aload 5
    //   16: invokevirtual 26	android/os/Parcel:writeInterfaceToken	(Ljava/lang/String;)V
    //   19: aload_3
    //   20: aload_1
    //   21: invokevirtual 110	android/os/Parcel:writeString	(Ljava/lang/String;)V
    //   24: aload_2
    //   25: ifnull +56 -> 81
    //   28: aload_2
    //   29: invokeinterface 128 1 0
    //   34: astore 5
    //   36: aload_3
    //   37: aload 5
    //   39: invokevirtual 40	android/os/Parcel:writeStrongBinder	(Landroid/os/IBinder;)V
    //   42: aload_0
    //   43: getfield 14	com/google/android/gms/drive/realtime/internal/zzm$zza$zza:zzoz	Landroid/os/IBinder;
    //   46: astore 5
    //   48: bipush 13
    //   50: istore 6
    //   52: aload 5
    //   54: iload 6
    //   56: aload_3
    //   57: aload 4
    //   59: iconst_0
    //   60: invokeinterface 47 5 0
    //   65: pop
    //   66: aload 4
    //   68: invokevirtual 50	android/os/Parcel:readException	()V
    //   71: aload 4
    //   73: invokevirtual 53	android/os/Parcel:recycle	()V
    //   76: aload_3
    //   77: invokevirtual 53	android/os/Parcel:recycle	()V
    //   80: return
    //   81: aconst_null
    //   82: astore 5
    //   84: goto -48 -> 36
    //   87: astore 5
    //   89: aload 4
    //   91: invokevirtual 53	android/os/Parcel:recycle	()V
    //   94: aload_3
    //   95: invokevirtual 53	android/os/Parcel:recycle	()V
    //   98: aload 5
    //   100: athrow
    // Local variable table:
    //   start	length	slot	name	signature
    //   0	101	0	this	zza
    //   0	101	1	paramString	String
    //   0	101	2	paramzzf	zzf
    //   3	92	3	localParcel1	Parcel
    //   7	83	4	localParcel2	Parcel
    //   11	72	5	localObject1	Object
    //   87	12	5	localObject2	Object
    //   50	5	6	i	int
    // Exception table:
    //   from	to	target	type
    //   14	19	87	finally
    //   20	24	87	finally
    //   28	34	87	finally
    //   37	42	87	finally
    //   42	46	87	finally
    //   59	66	87	finally
    //   66	71	87	finally
  }
  
  /* Error */
  public void zzb(String paramString, zzl paramzzl)
  {
    // Byte code:
    //   0: invokestatic 20	android/os/Parcel:obtain	()Landroid/os/Parcel;
    //   3: astore_3
    //   4: invokestatic 20	android/os/Parcel:obtain	()Landroid/os/Parcel;
    //   7: astore 4
    //   9: ldc 22
    //   11: astore 5
    //   13: aload_3
    //   14: aload 5
    //   16: invokevirtual 26	android/os/Parcel:writeInterfaceToken	(Ljava/lang/String;)V
    //   19: aload_3
    //   20: aload_1
    //   21: invokevirtual 110	android/os/Parcel:writeString	(Ljava/lang/String;)V
    //   24: aload_2
    //   25: ifnull +56 -> 81
    //   28: aload_2
    //   29: invokeinterface 105 1 0
    //   34: astore 5
    //   36: aload_3
    //   37: aload 5
    //   39: invokevirtual 40	android/os/Parcel:writeStrongBinder	(Landroid/os/IBinder;)V
    //   42: aload_0
    //   43: getfield 14	com/google/android/gms/drive/realtime/internal/zzm$zza$zza:zzoz	Landroid/os/IBinder;
    //   46: astore 5
    //   48: bipush 8
    //   50: istore 6
    //   52: aload 5
    //   54: iload 6
    //   56: aload_3
    //   57: aload 4
    //   59: iconst_0
    //   60: invokeinterface 47 5 0
    //   65: pop
    //   66: aload 4
    //   68: invokevirtual 50	android/os/Parcel:readException	()V
    //   71: aload 4
    //   73: invokevirtual 53	android/os/Parcel:recycle	()V
    //   76: aload_3
    //   77: invokevirtual 53	android/os/Parcel:recycle	()V
    //   80: return
    //   81: aconst_null
    //   82: astore 5
    //   84: goto -48 -> 36
    //   87: astore 5
    //   89: aload 4
    //   91: invokevirtual 53	android/os/Parcel:recycle	()V
    //   94: aload_3
    //   95: invokevirtual 53	android/os/Parcel:recycle	()V
    //   98: aload 5
    //   100: athrow
    // Local variable table:
    //   start	length	slot	name	signature
    //   0	101	0	this	zza
    //   0	101	1	paramString	String
    //   0	101	2	paramzzl	zzl
    //   3	92	3	localParcel1	Parcel
    //   7	83	4	localParcel2	Parcel
    //   11	72	5	localObject1	Object
    //   87	12	5	localObject2	Object
    //   50	5	6	i	int
    // Exception table:
    //   from	to	target	type
    //   14	19	87	finally
    //   20	24	87	finally
    //   28	34	87	finally
    //   37	42	87	finally
    //   42	46	87	finally
    //   59	66	87	finally
    //   66	71	87	finally
  }
  
  /* Error */
  public void zzb(String paramString, zzn paramzzn)
  {
    // Byte code:
    //   0: invokestatic 20	android/os/Parcel:obtain	()Landroid/os/Parcel;
    //   3: astore_3
    //   4: invokestatic 20	android/os/Parcel:obtain	()Landroid/os/Parcel;
    //   7: astore 4
    //   9: ldc 22
    //   11: astore 5
    //   13: aload_3
    //   14: aload 5
    //   16: invokevirtual 26	android/os/Parcel:writeInterfaceToken	(Ljava/lang/String;)V
    //   19: aload_3
    //   20: aload_1
    //   21: invokevirtual 110	android/os/Parcel:writeString	(Ljava/lang/String;)V
    //   24: aload_2
    //   25: ifnull +56 -> 81
    //   28: aload_2
    //   29: invokeinterface 80 1 0
    //   34: astore 5
    //   36: aload_3
    //   37: aload 5
    //   39: invokevirtual 40	android/os/Parcel:writeStrongBinder	(Landroid/os/IBinder;)V
    //   42: aload_0
    //   43: getfield 14	com/google/android/gms/drive/realtime/internal/zzm$zza$zza:zzoz	Landroid/os/IBinder;
    //   46: astore 5
    //   48: bipush 9
    //   50: istore 6
    //   52: aload 5
    //   54: iload 6
    //   56: aload_3
    //   57: aload 4
    //   59: iconst_0
    //   60: invokeinterface 47 5 0
    //   65: pop
    //   66: aload 4
    //   68: invokevirtual 50	android/os/Parcel:readException	()V
    //   71: aload 4
    //   73: invokevirtual 53	android/os/Parcel:recycle	()V
    //   76: aload_3
    //   77: invokevirtual 53	android/os/Parcel:recycle	()V
    //   80: return
    //   81: aconst_null
    //   82: astore 5
    //   84: goto -48 -> 36
    //   87: astore 5
    //   89: aload 4
    //   91: invokevirtual 53	android/os/Parcel:recycle	()V
    //   94: aload_3
    //   95: invokevirtual 53	android/os/Parcel:recycle	()V
    //   98: aload 5
    //   100: athrow
    // Local variable table:
    //   start	length	slot	name	signature
    //   0	101	0	this	zza
    //   0	101	1	paramString	String
    //   0	101	2	paramzzn	zzn
    //   3	92	3	localParcel1	Parcel
    //   7	83	4	localParcel2	Parcel
    //   11	72	5	localObject1	Object
    //   87	12	5	localObject2	Object
    //   50	5	6	i	int
    // Exception table:
    //   from	to	target	type
    //   14	19	87	finally
    //   20	24	87	finally
    //   28	34	87	finally
    //   37	42	87	finally
    //   42	46	87	finally
    //   59	66	87	finally
    //   66	71	87	finally
  }
  
  /* Error */
  public void zzb(String paramString, zzo paramzzo)
  {
    // Byte code:
    //   0: invokestatic 20	android/os/Parcel:obtain	()Landroid/os/Parcel;
    //   3: astore_3
    //   4: invokestatic 20	android/os/Parcel:obtain	()Landroid/os/Parcel;
    //   7: astore 4
    //   9: ldc 22
    //   11: astore 5
    //   13: aload_3
    //   14: aload 5
    //   16: invokevirtual 26	android/os/Parcel:writeInterfaceToken	(Ljava/lang/String;)V
    //   19: aload_3
    //   20: aload_1
    //   21: invokevirtual 110	android/os/Parcel:writeString	(Ljava/lang/String;)V
    //   24: aload_2
    //   25: ifnull +56 -> 81
    //   28: aload_2
    //   29: invokeinterface 56 1 0
    //   34: astore 5
    //   36: aload_3
    //   37: aload 5
    //   39: invokevirtual 40	android/os/Parcel:writeStrongBinder	(Landroid/os/IBinder;)V
    //   42: aload_0
    //   43: getfield 14	com/google/android/gms/drive/realtime/internal/zzm$zza$zza:zzoz	Landroid/os/IBinder;
    //   46: astore 5
    //   48: bipush 39
    //   50: istore 6
    //   52: aload 5
    //   54: iload 6
    //   56: aload_3
    //   57: aload 4
    //   59: iconst_0
    //   60: invokeinterface 47 5 0
    //   65: pop
    //   66: aload 4
    //   68: invokevirtual 50	android/os/Parcel:readException	()V
    //   71: aload 4
    //   73: invokevirtual 53	android/os/Parcel:recycle	()V
    //   76: aload_3
    //   77: invokevirtual 53	android/os/Parcel:recycle	()V
    //   80: return
    //   81: aconst_null
    //   82: astore 5
    //   84: goto -48 -> 36
    //   87: astore 5
    //   89: aload 4
    //   91: invokevirtual 53	android/os/Parcel:recycle	()V
    //   94: aload_3
    //   95: invokevirtual 53	android/os/Parcel:recycle	()V
    //   98: aload 5
    //   100: athrow
    // Local variable table:
    //   start	length	slot	name	signature
    //   0	101	0	this	zza
    //   0	101	1	paramString	String
    //   0	101	2	paramzzo	zzo
    //   3	92	3	localParcel1	Parcel
    //   7	83	4	localParcel2	Parcel
    //   11	72	5	localObject1	Object
    //   87	12	5	localObject2	Object
    //   50	5	6	i	int
    // Exception table:
    //   from	to	target	type
    //   14	19	87	finally
    //   20	24	87	finally
    //   28	34	87	finally
    //   37	42	87	finally
    //   42	46	87	finally
    //   59	66	87	finally
    //   66	71	87	finally
  }
  
  /* Error */
  public void zzb(String paramString1, String paramString2, zzf paramzzf)
  {
    // Byte code:
    //   0: invokestatic 20	android/os/Parcel:obtain	()Landroid/os/Parcel;
    //   3: astore 4
    //   5: invokestatic 20	android/os/Parcel:obtain	()Landroid/os/Parcel;
    //   8: astore 5
    //   10: ldc 22
    //   12: astore 6
    //   14: aload 4
    //   16: aload 6
    //   18: invokevirtual 26	android/os/Parcel:writeInterfaceToken	(Ljava/lang/String;)V
    //   21: aload 4
    //   23: aload_1
    //   24: invokevirtual 110	android/os/Parcel:writeString	(Ljava/lang/String;)V
    //   27: aload 4
    //   29: aload_2
    //   30: invokevirtual 110	android/os/Parcel:writeString	(Ljava/lang/String;)V
    //   33: aload_3
    //   34: ifnull +59 -> 93
    //   37: aload_3
    //   38: invokeinterface 128 1 0
    //   43: astore 6
    //   45: aload 4
    //   47: aload 6
    //   49: invokevirtual 40	android/os/Parcel:writeStrongBinder	(Landroid/os/IBinder;)V
    //   52: aload_0
    //   53: getfield 14	com/google/android/gms/drive/realtime/internal/zzm$zza$zza:zzoz	Landroid/os/IBinder;
    //   56: astore 6
    //   58: bipush 42
    //   60: istore 7
    //   62: aload 6
    //   64: iload 7
    //   66: aload 4
    //   68: aload 5
    //   70: iconst_0
    //   71: invokeinterface 47 5 0
    //   76: pop
    //   77: aload 5
    //   79: invokevirtual 50	android/os/Parcel:readException	()V
    //   82: aload 5
    //   84: invokevirtual 53	android/os/Parcel:recycle	()V
    //   87: aload 4
    //   89: invokevirtual 53	android/os/Parcel:recycle	()V
    //   92: return
    //   93: aconst_null
    //   94: astore 6
    //   96: goto -51 -> 45
    //   99: astore 6
    //   101: aload 5
    //   103: invokevirtual 53	android/os/Parcel:recycle	()V
    //   106: aload 4
    //   108: invokevirtual 53	android/os/Parcel:recycle	()V
    //   111: aload 6
    //   113: athrow
    // Local variable table:
    //   start	length	slot	name	signature
    //   0	114	0	this	zza
    //   0	114	1	paramString1	String
    //   0	114	2	paramString2	String
    //   0	114	3	paramzzf	zzf
    //   3	104	4	localParcel1	Parcel
    //   8	94	5	localParcel2	Parcel
    //   12	83	6	localObject1	Object
    //   99	13	6	localObject2	Object
    //   60	5	7	i	int
    // Exception table:
    //   from	to	target	type
    //   16	21	99	finally
    //   23	27	99	finally
    //   29	33	99	finally
    //   37	43	99	finally
    //   47	52	99	finally
    //   52	56	99	finally
    //   70	77	99	finally
    //   77	82	99	finally
  }
  
  /* Error */
  public void zzc(zzc paramzzc)
  {
    // Byte code:
    //   0: invokestatic 20	android/os/Parcel:obtain	()Landroid/os/Parcel;
    //   3: astore_2
    //   4: invokestatic 20	android/os/Parcel:obtain	()Landroid/os/Parcel;
    //   7: astore_3
    //   8: ldc 22
    //   10: astore 4
    //   12: aload_2
    //   13: aload 4
    //   15: invokevirtual 26	android/os/Parcel:writeInterfaceToken	(Ljava/lang/String;)V
    //   18: aload_1
    //   19: ifnull +53 -> 72
    //   22: aload_1
    //   23: invokeinterface 84 1 0
    //   28: astore 4
    //   30: aload_2
    //   31: aload 4
    //   33: invokevirtual 40	android/os/Parcel:writeStrongBinder	(Landroid/os/IBinder;)V
    //   36: aload_0
    //   37: getfield 14	com/google/android/gms/drive/realtime/internal/zzm$zza$zza:zzoz	Landroid/os/IBinder;
    //   40: astore 4
    //   42: bipush 45
    //   44: istore 5
    //   46: aload 4
    //   48: iload 5
    //   50: aload_2
    //   51: aload_3
    //   52: iconst_0
    //   53: invokeinterface 47 5 0
    //   58: pop
    //   59: aload_3
    //   60: invokevirtual 50	android/os/Parcel:readException	()V
    //   63: aload_3
    //   64: invokevirtual 53	android/os/Parcel:recycle	()V
    //   67: aload_2
    //   68: invokevirtual 53	android/os/Parcel:recycle	()V
    //   71: return
    //   72: aconst_null
    //   73: astore 4
    //   75: goto -45 -> 30
    //   78: astore 4
    //   80: aload_3
    //   81: invokevirtual 53	android/os/Parcel:recycle	()V
    //   84: aload_2
    //   85: invokevirtual 53	android/os/Parcel:recycle	()V
    //   88: aload 4
    //   90: athrow
    // Local variable table:
    //   start	length	slot	name	signature
    //   0	91	0	this	zza
    //   0	91	1	paramzzc	zzc
    //   3	82	2	localParcel1	Parcel
    //   7	74	3	localParcel2	Parcel
    //   10	64	4	localObject1	Object
    //   78	11	4	localObject2	Object
    //   44	5	5	i	int
    // Exception table:
    //   from	to	target	type
    //   13	18	78	finally
    //   22	28	78	finally
    //   31	36	78	finally
    //   36	40	78	finally
    //   52	59	78	finally
    //   59	63	78	finally
  }
  
  /* Error */
  public void zzc(zzo paramzzo)
  {
    // Byte code:
    //   0: invokestatic 20	android/os/Parcel:obtain	()Landroid/os/Parcel;
    //   3: astore_2
    //   4: invokestatic 20	android/os/Parcel:obtain	()Landroid/os/Parcel;
    //   7: astore_3
    //   8: ldc 22
    //   10: astore 4
    //   12: aload_2
    //   13: aload 4
    //   15: invokevirtual 26	android/os/Parcel:writeInterfaceToken	(Ljava/lang/String;)V
    //   18: aload_1
    //   19: ifnull +53 -> 72
    //   22: aload_1
    //   23: invokeinterface 56 1 0
    //   28: astore 4
    //   30: aload_2
    //   31: aload 4
    //   33: invokevirtual 40	android/os/Parcel:writeStrongBinder	(Landroid/os/IBinder;)V
    //   36: aload_0
    //   37: getfield 14	com/google/android/gms/drive/realtime/internal/zzm$zza$zza:zzoz	Landroid/os/IBinder;
    //   40: astore 4
    //   42: bipush 49
    //   44: istore 5
    //   46: aload 4
    //   48: iload 5
    //   50: aload_2
    //   51: aload_3
    //   52: iconst_0
    //   53: invokeinterface 47 5 0
    //   58: pop
    //   59: aload_3
    //   60: invokevirtual 50	android/os/Parcel:readException	()V
    //   63: aload_3
    //   64: invokevirtual 53	android/os/Parcel:recycle	()V
    //   67: aload_2
    //   68: invokevirtual 53	android/os/Parcel:recycle	()V
    //   71: return
    //   72: aconst_null
    //   73: astore 4
    //   75: goto -45 -> 30
    //   78: astore 4
    //   80: aload_3
    //   81: invokevirtual 53	android/os/Parcel:recycle	()V
    //   84: aload_2
    //   85: invokevirtual 53	android/os/Parcel:recycle	()V
    //   88: aload 4
    //   90: athrow
    // Local variable table:
    //   start	length	slot	name	signature
    //   0	91	0	this	zza
    //   0	91	1	paramzzo	zzo
    //   3	82	2	localParcel1	Parcel
    //   7	74	3	localParcel2	Parcel
    //   10	64	4	localObject1	Object
    //   78	11	4	localObject2	Object
    //   44	5	5	i	int
    // Exception table:
    //   from	to	target	type
    //   13	18	78	finally
    //   22	28	78	finally
    //   31	36	78	finally
    //   36	40	78	finally
    //   52	59	78	finally
    //   59	63	78	finally
  }
  
  /* Error */
  public void zzc(String paramString, zzl paramzzl)
  {
    // Byte code:
    //   0: invokestatic 20	android/os/Parcel:obtain	()Landroid/os/Parcel;
    //   3: astore_3
    //   4: invokestatic 20	android/os/Parcel:obtain	()Landroid/os/Parcel;
    //   7: astore 4
    //   9: ldc 22
    //   11: astore 5
    //   13: aload_3
    //   14: aload 5
    //   16: invokevirtual 26	android/os/Parcel:writeInterfaceToken	(Ljava/lang/String;)V
    //   19: aload_3
    //   20: aload_1
    //   21: invokevirtual 110	android/os/Parcel:writeString	(Ljava/lang/String;)V
    //   24: aload_2
    //   25: ifnull +56 -> 81
    //   28: aload_2
    //   29: invokeinterface 105 1 0
    //   34: astore 5
    //   36: aload_3
    //   37: aload 5
    //   39: invokevirtual 40	android/os/Parcel:writeStrongBinder	(Landroid/os/IBinder;)V
    //   42: aload_0
    //   43: getfield 14	com/google/android/gms/drive/realtime/internal/zzm$zza$zza:zzoz	Landroid/os/IBinder;
    //   46: astore 5
    //   48: bipush 14
    //   50: istore 6
    //   52: aload 5
    //   54: iload 6
    //   56: aload_3
    //   57: aload 4
    //   59: iconst_0
    //   60: invokeinterface 47 5 0
    //   65: pop
    //   66: aload 4
    //   68: invokevirtual 50	android/os/Parcel:readException	()V
    //   71: aload 4
    //   73: invokevirtual 53	android/os/Parcel:recycle	()V
    //   76: aload_3
    //   77: invokevirtual 53	android/os/Parcel:recycle	()V
    //   80: return
    //   81: aconst_null
    //   82: astore 5
    //   84: goto -48 -> 36
    //   87: astore 5
    //   89: aload 4
    //   91: invokevirtual 53	android/os/Parcel:recycle	()V
    //   94: aload_3
    //   95: invokevirtual 53	android/os/Parcel:recycle	()V
    //   98: aload 5
    //   100: athrow
    // Local variable table:
    //   start	length	slot	name	signature
    //   0	101	0	this	zza
    //   0	101	1	paramString	String
    //   0	101	2	paramzzl	zzl
    //   3	92	3	localParcel1	Parcel
    //   7	83	4	localParcel2	Parcel
    //   11	72	5	localObject1	Object
    //   87	12	5	localObject2	Object
    //   50	5	6	i	int
    // Exception table:
    //   from	to	target	type
    //   14	19	87	finally
    //   20	24	87	finally
    //   28	34	87	finally
    //   37	42	87	finally
    //   42	46	87	finally
    //   59	66	87	finally
    //   66	71	87	finally
  }
  
  /* Error */
  public void zzd(zzc paramzzc)
  {
    // Byte code:
    //   0: invokestatic 20	android/os/Parcel:obtain	()Landroid/os/Parcel;
    //   3: astore_2
    //   4: invokestatic 20	android/os/Parcel:obtain	()Landroid/os/Parcel;
    //   7: astore_3
    //   8: ldc 22
    //   10: astore 4
    //   12: aload_2
    //   13: aload 4
    //   15: invokevirtual 26	android/os/Parcel:writeInterfaceToken	(Ljava/lang/String;)V
    //   18: aload_1
    //   19: ifnull +53 -> 72
    //   22: aload_1
    //   23: invokeinterface 84 1 0
    //   28: astore 4
    //   30: aload_2
    //   31: aload 4
    //   33: invokevirtual 40	android/os/Parcel:writeStrongBinder	(Landroid/os/IBinder;)V
    //   36: aload_0
    //   37: getfield 14	com/google/android/gms/drive/realtime/internal/zzm$zza$zza:zzoz	Landroid/os/IBinder;
    //   40: astore 4
    //   42: bipush 24
    //   44: istore 5
    //   46: aload 4
    //   48: iload 5
    //   50: aload_2
    //   51: aload_3
    //   52: iconst_0
    //   53: invokeinterface 47 5 0
    //   58: pop
    //   59: aload_3
    //   60: invokevirtual 50	android/os/Parcel:readException	()V
    //   63: aload_3
    //   64: invokevirtual 53	android/os/Parcel:recycle	()V
    //   67: aload_2
    //   68: invokevirtual 53	android/os/Parcel:recycle	()V
    //   71: return
    //   72: aconst_null
    //   73: astore 4
    //   75: goto -45 -> 30
    //   78: astore 4
    //   80: aload_3
    //   81: invokevirtual 53	android/os/Parcel:recycle	()V
    //   84: aload_2
    //   85: invokevirtual 53	android/os/Parcel:recycle	()V
    //   88: aload 4
    //   90: athrow
    // Local variable table:
    //   start	length	slot	name	signature
    //   0	91	0	this	zza
    //   0	91	1	paramzzc	zzc
    //   3	82	2	localParcel1	Parcel
    //   7	74	3	localParcel2	Parcel
    //   10	64	4	localObject1	Object
    //   78	11	4	localObject2	Object
    //   44	5	5	i	int
    // Exception table:
    //   from	to	target	type
    //   13	18	78	finally
    //   22	28	78	finally
    //   31	36	78	finally
    //   36	40	78	finally
    //   52	59	78	finally
    //   59	63	78	finally
  }
  
  /* Error */
  public void zze(zzc paramzzc)
  {
    // Byte code:
    //   0: invokestatic 20	android/os/Parcel:obtain	()Landroid/os/Parcel;
    //   3: astore_2
    //   4: invokestatic 20	android/os/Parcel:obtain	()Landroid/os/Parcel;
    //   7: astore_3
    //   8: ldc 22
    //   10: astore 4
    //   12: aload_2
    //   13: aload 4
    //   15: invokevirtual 26	android/os/Parcel:writeInterfaceToken	(Ljava/lang/String;)V
    //   18: aload_1
    //   19: ifnull +53 -> 72
    //   22: aload_1
    //   23: invokeinterface 84 1 0
    //   28: astore 4
    //   30: aload_2
    //   31: aload 4
    //   33: invokevirtual 40	android/os/Parcel:writeStrongBinder	(Landroid/os/IBinder;)V
    //   36: aload_0
    //   37: getfield 14	com/google/android/gms/drive/realtime/internal/zzm$zza$zza:zzoz	Landroid/os/IBinder;
    //   40: astore 4
    //   42: bipush 25
    //   44: istore 5
    //   46: aload 4
    //   48: iload 5
    //   50: aload_2
    //   51: aload_3
    //   52: iconst_0
    //   53: invokeinterface 47 5 0
    //   58: pop
    //   59: aload_3
    //   60: invokevirtual 50	android/os/Parcel:readException	()V
    //   63: aload_3
    //   64: invokevirtual 53	android/os/Parcel:recycle	()V
    //   67: aload_2
    //   68: invokevirtual 53	android/os/Parcel:recycle	()V
    //   71: return
    //   72: aconst_null
    //   73: astore 4
    //   75: goto -45 -> 30
    //   78: astore 4
    //   80: aload_3
    //   81: invokevirtual 53	android/os/Parcel:recycle	()V
    //   84: aload_2
    //   85: invokevirtual 53	android/os/Parcel:recycle	()V
    //   88: aload 4
    //   90: athrow
    // Local variable table:
    //   start	length	slot	name	signature
    //   0	91	0	this	zza
    //   0	91	1	paramzzc	zzc
    //   3	82	2	localParcel1	Parcel
    //   7	74	3	localParcel2	Parcel
    //   10	64	4	localObject1	Object
    //   78	11	4	localObject2	Object
    //   44	5	5	i	int
    // Exception table:
    //   from	to	target	type
    //   13	18	78	finally
    //   22	28	78	finally
    //   31	36	78	finally
    //   36	40	78	finally
    //   52	59	78	finally
    //   59	63	78	finally
  }
  
  /* Error */
  public com.google.android.gms.drive.realtime.internal.event.ParcelableEventList zzf(String paramString1, String paramString2, String paramString3)
  {
    // Byte code:
    //   0: invokestatic 20	android/os/Parcel:obtain	()Landroid/os/Parcel;
    //   3: astore 4
    //   5: invokestatic 20	android/os/Parcel:obtain	()Landroid/os/Parcel;
    //   8: astore 5
    //   10: ldc 22
    //   12: astore 6
    //   14: aload 4
    //   16: aload 6
    //   18: invokevirtual 26	android/os/Parcel:writeInterfaceToken	(Ljava/lang/String;)V
    //   21: aload 4
    //   23: aload_1
    //   24: invokevirtual 110	android/os/Parcel:writeString	(Ljava/lang/String;)V
    //   27: aload 4
    //   29: aload_2
    //   30: invokevirtual 110	android/os/Parcel:writeString	(Ljava/lang/String;)V
    //   33: aload 4
    //   35: aload_3
    //   36: invokevirtual 110	android/os/Parcel:writeString	(Ljava/lang/String;)V
    //   39: aload_0
    //   40: getfield 14	com/google/android/gms/drive/realtime/internal/zzm$zza$zza:zzoz	Landroid/os/IBinder;
    //   43: astore 6
    //   45: bipush 51
    //   47: istore 7
    //   49: aload 6
    //   51: iload 7
    //   53: aload 4
    //   55: aload 5
    //   57: iconst_0
    //   58: invokeinterface 47 5 0
    //   63: pop
    //   64: aload 5
    //   66: invokevirtual 50	android/os/Parcel:readException	()V
    //   69: aload 5
    //   71: invokevirtual 160	android/os/Parcel:readInt	()I
    //   74: istore 8
    //   76: iload 8
    //   78: ifeq +39 -> 117
    //   81: getstatic 166	com/google/android/gms/drive/realtime/internal/event/ParcelableEventList:CREATOR	Landroid/os/Parcelable$Creator;
    //   84: astore 6
    //   86: aload 6
    //   88: aload 5
    //   90: invokeinterface 172 2 0
    //   95: astore 6
    //   97: aload 6
    //   99: checkcast 162	com/google/android/gms/drive/realtime/internal/event/ParcelableEventList
    //   102: astore 6
    //   104: aload 5
    //   106: invokevirtual 53	android/os/Parcel:recycle	()V
    //   109: aload 4
    //   111: invokevirtual 53	android/os/Parcel:recycle	()V
    //   114: aload 6
    //   116: areturn
    //   117: iconst_0
    //   118: istore 8
    //   120: aconst_null
    //   121: astore 6
    //   123: goto -19 -> 104
    //   126: astore 6
    //   128: aload 5
    //   130: invokevirtual 53	android/os/Parcel:recycle	()V
    //   133: aload 4
    //   135: invokevirtual 53	android/os/Parcel:recycle	()V
    //   138: aload 6
    //   140: athrow
    // Local variable table:
    //   start	length	slot	name	signature
    //   0	141	0	this	zza
    //   0	141	1	paramString1	String
    //   0	141	2	paramString2	String
    //   0	141	3	paramString3	String
    //   3	131	4	localParcel1	Parcel
    //   8	121	5	localParcel2	Parcel
    //   12	110	6	localObject1	Object
    //   126	13	6	localObject2	Object
    //   47	5	7	i	int
    //   74	45	8	j	int
    // Exception table:
    //   from	to	target	type
    //   16	21	126	finally
    //   23	27	126	finally
    //   29	33	126	finally
    //   35	39	126	finally
    //   39	43	126	finally
    //   57	64	126	finally
    //   64	69	126	finally
    //   69	74	126	finally
    //   81	84	126	finally
    //   88	95	126	finally
    //   97	102	126	finally
  }
  
  public void zztT()
  {
    Parcel localParcel1 = Parcel.obtain();
    Parcel localParcel2 = Parcel.obtain();
    Object localObject1 = "com.google.android.gms.drive.realtime.internal.IRealtimeService";
    try
    {
      localParcel1.writeInterfaceToken((String)localObject1);
      localObject1 = this.zzoz;
      int i = 44;
      ((IBinder)localObject1).transact(i, localParcel1, localParcel2, 0);
      localParcel2.readException();
      return;
    }
    finally
    {
      localParcel2.recycle();
      localParcel1.recycle();
    }
  }
}


/* Location:              C:\Users\haryo\Desktop\enjarify-master\presensi-enjarify.jar!\com\google\android\gms\drive\realtime\internal\zzm$zza$zza.class
 * Java compiler version: 5 (49.0)
 * JD-Core Version:       0.7.1
 */