package b.a.a.a.i.c;

import b.a.a.a.e.e;
import b.a.a.a.o.a;
import java.io.IOException;
import java.util.concurrent.atomic.AtomicLong;

public class d
  implements b.a.a.a.e.b
{
  private static final AtomicLong b;
  public b.a.a.a.h.b a;
  private final b.a.a.a.e.c.i c;
  private final b.a.a.a.e.d d;
  private k e;
  private o f;
  private volatile boolean g;
  
  static
  {
    AtomicLong localAtomicLong = new java/util/concurrent/atomic/AtomicLong;
    localAtomicLong.<init>();
    b = localAtomicLong;
  }
  
  public d()
  {
    this(locali);
  }
  
  public d(b.a.a.a.e.c.i parami)
  {
    Object localObject = new b/a/a/a/h/b;
    Class localClass = getClass();
    ((b.a.a.a.h.b)localObject).<init>(localClass);
    this.a = ((b.a.a.a.h.b)localObject);
    a.a(parami, "Scheme registry");
    this.c = parami;
    localObject = a(parami);
    this.d = ((b.a.a.a.e.d)localObject);
  }
  
  private void a(b.a.a.a.i parami)
  {
    try
    {
      parami.e();
      return;
    }
    catch (IOException localIOException)
    {
      for (;;)
      {
        b.a.a.a.h.b localb = this.a;
        boolean bool = localb.a();
        if (bool)
        {
          localb = this.a;
          String str = "I/O exception shutting down connection";
          localb.a(str, localIOException);
        }
      }
    }
  }
  
  private void c()
  {
    boolean bool = this.g;
    if (!bool) {}
    for (bool = true;; bool = false)
    {
      b.a.a.a.o.b.a(bool, "Connection manager has been shut down");
      return;
    }
  }
  
  public b.a.a.a.e.c.i a()
  {
    return this.c;
  }
  
  protected b.a.a.a.e.d a(b.a.a.a.e.c.i parami)
  {
    g localg = new b/a/a/a/i/c/g;
    localg.<init>(parami);
    return localg;
  }
  
  public final e a(b.a.a.a.e.b.b paramb, Object paramObject)
  {
    d.1 local1 = new b/a/a/a/i/c/d$1;
    local1.<init>(this, paramb, paramObject);
    return local1;
  }
  
  /* Error */
  public void a(b.a.a.a.e.o paramo, long paramLong, java.util.concurrent.TimeUnit paramTimeUnit)
  {
    // Byte code:
    //   0: aload_1
    //   1: instanceof 96
    //   4: istore 5
    //   6: ldc 98
    //   8: astore 6
    //   10: iload 5
    //   12: aload 6
    //   14: invokestatic 99	b/a/a/a/o/a:a	(ZLjava/lang/String;)V
    //   17: aload_1
    //   18: astore 7
    //   20: aload_1
    //   21: checkcast 96	b/a/a/a/i/c/o
    //   24: astore 7
    //   26: aload 7
    //   28: monitorenter
    //   29: aload_0
    //   30: getfield 48	b/a/a/a/i/c/d:a	Lb/a/a/a/h/b;
    //   33: astore 6
    //   35: aload 6
    //   37: invokevirtual 69	b/a/a/a/h/b:a	()Z
    //   40: istore 8
    //   42: iload 8
    //   44: ifeq +54 -> 98
    //   47: aload_0
    //   48: getfield 48	b/a/a/a/i/c/d:a	Lb/a/a/a/h/b;
    //   51: astore 6
    //   53: new 101	java/lang/StringBuilder
    //   56: astore 9
    //   58: aload 9
    //   60: invokespecial 102	java/lang/StringBuilder:<init>	()V
    //   63: ldc 104
    //   65: astore 10
    //   67: aload 9
    //   69: aload 10
    //   71: invokevirtual 108	java/lang/StringBuilder:append	(Ljava/lang/String;)Ljava/lang/StringBuilder;
    //   74: astore 9
    //   76: aload 9
    //   78: aload_1
    //   79: invokevirtual 111	java/lang/StringBuilder:append	(Ljava/lang/Object;)Ljava/lang/StringBuilder;
    //   82: astore 9
    //   84: aload 9
    //   86: invokevirtual 115	java/lang/StringBuilder:toString	()Ljava/lang/String;
    //   89: astore 9
    //   91: aload 6
    //   93: aload 9
    //   95: invokevirtual 117	b/a/a/a/h/b:a	(Ljava/lang/Object;)V
    //   98: aload 7
    //   100: invokevirtual 121	b/a/a/a/i/c/o:l	()Lb/a/a/a/i/c/k;
    //   103: astore 6
    //   105: aload 6
    //   107: ifnonnull +7 -> 114
    //   110: aload 7
    //   112: monitorexit
    //   113: return
    //   114: aload 7
    //   116: invokevirtual 125	b/a/a/a/i/c/o:n	()Lb/a/a/a/e/b;
    //   119: astore 6
    //   121: aload 6
    //   123: aload_0
    //   124: if_acmpne +52 -> 176
    //   127: iconst_1
    //   128: istore 8
    //   130: ldc 127
    //   132: astore 9
    //   134: iload 8
    //   136: aload 9
    //   138: invokestatic 86	b/a/a/a/o/b:a	(ZLjava/lang/String;)V
    //   141: aload_0
    //   142: monitorenter
    //   143: aload_0
    //   144: getfield 78	b/a/a/a/i/c/d:g	Z
    //   147: istore 8
    //   149: iload 8
    //   151: ifeq +34 -> 185
    //   154: aload_0
    //   155: aload 7
    //   157: invokespecial 130	b/a/a/a/i/c/d:a	(Lb/a/a/a/i;)V
    //   160: aload_0
    //   161: monitorexit
    //   162: aload 7
    //   164: monitorexit
    //   165: goto -52 -> 113
    //   168: astore 6
    //   170: aload 7
    //   172: monitorexit
    //   173: aload 6
    //   175: athrow
    //   176: iconst_0
    //   177: istore 8
    //   179: aconst_null
    //   180: astore 6
    //   182: goto -52 -> 130
    //   185: aload 7
    //   187: invokevirtual 132	b/a/a/a/i/c/o:c	()Z
    //   190: istore 8
    //   192: iload 8
    //   194: ifeq +21 -> 215
    //   197: aload 7
    //   199: invokevirtual 135	b/a/a/a/i/c/o:o	()Z
    //   202: istore 8
    //   204: iload 8
    //   206: ifne +9 -> 215
    //   209: aload_0
    //   210: aload 7
    //   212: invokespecial 130	b/a/a/a/i/c/d:a	(Lb/a/a/a/i;)V
    //   215: aload 7
    //   217: invokevirtual 135	b/a/a/a/i/c/o:o	()Z
    //   220: istore 8
    //   222: iload 8
    //   224: ifeq +170 -> 394
    //   227: aload_0
    //   228: getfield 137	b/a/a/a/i/c/d:e	Lb/a/a/a/i/c/k;
    //   231: astore 9
    //   233: aload 4
    //   235: ifnull +213 -> 448
    //   238: aload 4
    //   240: astore 6
    //   242: aload 9
    //   244: lload_2
    //   245: aload 6
    //   247: invokevirtual 142	b/a/a/a/i/c/k:a	(JLjava/util/concurrent/TimeUnit;)V
    //   250: aload_0
    //   251: getfield 48	b/a/a/a/i/c/d:a	Lb/a/a/a/h/b;
    //   254: astore 6
    //   256: aload 6
    //   258: invokevirtual 69	b/a/a/a/h/b:a	()Z
    //   261: istore 8
    //   263: iload 8
    //   265: ifeq +129 -> 394
    //   268: lconst_0
    //   269: lstore 11
    //   271: lload_2
    //   272: lload 11
    //   274: lcmp
    //   275: istore 8
    //   277: iload 8
    //   279: ifle +177 -> 456
    //   282: new 101	java/lang/StringBuilder
    //   285: astore 6
    //   287: aload 6
    //   289: invokespecial 102	java/lang/StringBuilder:<init>	()V
    //   292: ldc -112
    //   294: astore 9
    //   296: aload 6
    //   298: aload 9
    //   300: invokevirtual 108	java/lang/StringBuilder:append	(Ljava/lang/String;)Ljava/lang/StringBuilder;
    //   303: astore 6
    //   305: aload 6
    //   307: lload_2
    //   308: invokevirtual 147	java/lang/StringBuilder:append	(J)Ljava/lang/StringBuilder;
    //   311: astore 6
    //   313: ldc -107
    //   315: astore 9
    //   317: aload 6
    //   319: aload 9
    //   321: invokevirtual 108	java/lang/StringBuilder:append	(Ljava/lang/String;)Ljava/lang/StringBuilder;
    //   324: astore 6
    //   326: aload 6
    //   328: aload 4
    //   330: invokevirtual 111	java/lang/StringBuilder:append	(Ljava/lang/Object;)Ljava/lang/StringBuilder;
    //   333: astore 6
    //   335: aload 6
    //   337: invokevirtual 115	java/lang/StringBuilder:toString	()Ljava/lang/String;
    //   340: astore 6
    //   342: aload_0
    //   343: getfield 48	b/a/a/a/i/c/d:a	Lb/a/a/a/h/b;
    //   346: astore 9
    //   348: new 101	java/lang/StringBuilder
    //   351: astore 10
    //   353: aload 10
    //   355: invokespecial 102	java/lang/StringBuilder:<init>	()V
    //   358: ldc -105
    //   360: astore 13
    //   362: aload 10
    //   364: aload 13
    //   366: invokevirtual 108	java/lang/StringBuilder:append	(Ljava/lang/String;)Ljava/lang/StringBuilder;
    //   369: astore 10
    //   371: aload 10
    //   373: aload 6
    //   375: invokevirtual 108	java/lang/StringBuilder:append	(Ljava/lang/String;)Ljava/lang/StringBuilder;
    //   378: astore 6
    //   380: aload 6
    //   382: invokevirtual 115	java/lang/StringBuilder:toString	()Ljava/lang/String;
    //   385: astore 6
    //   387: aload 9
    //   389: aload 6
    //   391: invokevirtual 117	b/a/a/a/h/b:a	(Ljava/lang/Object;)V
    //   394: aload 7
    //   396: invokevirtual 154	b/a/a/a/i/c/o:m	()Lb/a/a/a/i/c/k;
    //   399: pop
    //   400: iconst_0
    //   401: istore 8
    //   403: aconst_null
    //   404: astore 6
    //   406: aload_0
    //   407: aconst_null
    //   408: putfield 156	b/a/a/a/i/c/d:f	Lb/a/a/a/i/c/o;
    //   411: aload_0
    //   412: getfield 137	b/a/a/a/i/c/d:e	Lb/a/a/a/i/c/k;
    //   415: astore 6
    //   417: aload 6
    //   419: invokevirtual 158	b/a/a/a/i/c/k:d	()Z
    //   422: istore 8
    //   424: iload 8
    //   426: ifeq +14 -> 440
    //   429: iconst_0
    //   430: istore 8
    //   432: aconst_null
    //   433: astore 6
    //   435: aload_0
    //   436: aconst_null
    //   437: putfield 137	b/a/a/a/i/c/d:e	Lb/a/a/a/i/c/k;
    //   440: aload_0
    //   441: monitorexit
    //   442: aload 7
    //   444: monitorexit
    //   445: goto -332 -> 113
    //   448: getstatic 164	java/util/concurrent/TimeUnit:MILLISECONDS	Ljava/util/concurrent/TimeUnit;
    //   451: astore 6
    //   453: goto -211 -> 242
    //   456: ldc -90
    //   458: astore 6
    //   460: goto -118 -> 342
    //   463: astore 6
    //   465: aload 7
    //   467: invokevirtual 154	b/a/a/a/i/c/o:m	()Lb/a/a/a/i/c/k;
    //   470: pop
    //   471: iconst_0
    //   472: istore 14
    //   474: aconst_null
    //   475: astore 9
    //   477: aload_0
    //   478: aconst_null
    //   479: putfield 156	b/a/a/a/i/c/d:f	Lb/a/a/a/i/c/o;
    //   482: aload_0
    //   483: getfield 137	b/a/a/a/i/c/d:e	Lb/a/a/a/i/c/k;
    //   486: astore 9
    //   488: aload 9
    //   490: invokevirtual 158	b/a/a/a/i/c/k:d	()Z
    //   493: istore 14
    //   495: iload 14
    //   497: ifeq +14 -> 511
    //   500: iconst_0
    //   501: istore 14
    //   503: aconst_null
    //   504: astore 9
    //   506: aload_0
    //   507: aconst_null
    //   508: putfield 137	b/a/a/a/i/c/d:e	Lb/a/a/a/i/c/k;
    //   511: aload 6
    //   513: athrow
    //   514: astore 6
    //   516: aload_0
    //   517: monitorexit
    //   518: aload 6
    //   520: athrow
    // Local variable table:
    //   start	length	slot	name	signature
    //   0	521	0	this	d
    //   0	521	1	paramo	b.a.a.a.e.o
    //   0	521	2	paramLong	long
    //   0	521	4	paramTimeUnit	java.util.concurrent.TimeUnit
    //   4	7	5	bool1	boolean
    //   8	114	6	localObject1	Object
    //   168	6	6	localObject2	Object
    //   180	279	6	localObject3	Object
    //   463	49	6	localObject4	Object
    //   514	5	6	localObject5	Object
    //   18	448	7	localObject6	Object
    //   40	391	8	bool2	boolean
    //   56	449	9	localObject7	Object
    //   65	307	10	localObject8	Object
    //   269	4	11	l	long
    //   360	5	13	str	String
    //   472	30	14	bool3	boolean
    // Exception table:
    //   from	to	target	type
    //   29	33	168	finally
    //   35	40	168	finally
    //   47	51	168	finally
    //   53	56	168	finally
    //   58	63	168	finally
    //   69	74	168	finally
    //   78	82	168	finally
    //   84	89	168	finally
    //   93	98	168	finally
    //   98	103	168	finally
    //   110	113	168	finally
    //   114	119	168	finally
    //   136	141	168	finally
    //   141	143	168	finally
    //   162	165	168	finally
    //   170	173	168	finally
    //   442	445	168	finally
    //   518	521	168	finally
    //   185	190	463	finally
    //   197	202	463	finally
    //   210	215	463	finally
    //   215	220	463	finally
    //   227	231	463	finally
    //   245	250	463	finally
    //   250	254	463	finally
    //   256	261	463	finally
    //   282	285	463	finally
    //   287	292	463	finally
    //   298	303	463	finally
    //   307	311	463	finally
    //   319	324	463	finally
    //   328	333	463	finally
    //   335	340	463	finally
    //   342	346	463	finally
    //   348	351	463	finally
    //   353	358	463	finally
    //   364	369	463	finally
    //   373	378	463	finally
    //   380	385	463	finally
    //   389	394	463	finally
    //   448	451	463	finally
    //   143	147	514	finally
    //   155	160	514	finally
    //   160	162	514	finally
    //   394	400	514	finally
    //   407	411	514	finally
    //   411	415	514	finally
    //   417	422	514	finally
    //   436	440	514	finally
    //   440	442	514	finally
    //   465	471	514	finally
    //   478	482	514	finally
    //   482	486	514	finally
    //   488	493	514	finally
    //   507	511	514	finally
    //   511	514	514	finally
    //   516	518	514	finally
  }
  
  /* Error */
  b.a.a.a.e.o b(b.a.a.a.e.b.b paramb, Object paramObject)
  {
    // Byte code:
    //   0: ldc -88
    //   2: astore_3
    //   3: aload_1
    //   4: aload_3
    //   5: invokestatic 55	b/a/a/a/o/a:a	(Ljava/lang/Object;Ljava/lang/String;)Ljava/lang/Object;
    //   8: pop
    //   9: aload_0
    //   10: monitorenter
    //   11: aload_0
    //   12: invokespecial 170	b/a/a/a/i/c/d:c	()V
    //   15: aload_0
    //   16: getfield 48	b/a/a/a/i/c/d:a	Lb/a/a/a/h/b;
    //   19: astore_3
    //   20: aload_3
    //   21: invokevirtual 69	b/a/a/a/h/b:a	()Z
    //   24: istore 4
    //   26: iload 4
    //   28: ifeq +52 -> 80
    //   31: aload_0
    //   32: getfield 48	b/a/a/a/i/c/d:a	Lb/a/a/a/h/b;
    //   35: astore_3
    //   36: new 101	java/lang/StringBuilder
    //   39: astore 5
    //   41: aload 5
    //   43: invokespecial 102	java/lang/StringBuilder:<init>	()V
    //   46: ldc -84
    //   48: astore 6
    //   50: aload 5
    //   52: aload 6
    //   54: invokevirtual 108	java/lang/StringBuilder:append	(Ljava/lang/String;)Ljava/lang/StringBuilder;
    //   57: astore 5
    //   59: aload 5
    //   61: aload_1
    //   62: invokevirtual 111	java/lang/StringBuilder:append	(Ljava/lang/Object;)Ljava/lang/StringBuilder;
    //   65: astore 5
    //   67: aload 5
    //   69: invokevirtual 115	java/lang/StringBuilder:toString	()Ljava/lang/String;
    //   72: astore 5
    //   74: aload_3
    //   75: aload 5
    //   77: invokevirtual 117	b/a/a/a/h/b:a	(Ljava/lang/Object;)V
    //   80: aload_0
    //   81: getfield 156	b/a/a/a/i/c/d:f	Lb/a/a/a/i/c/o;
    //   84: astore_3
    //   85: aload_3
    //   86: ifnonnull +234 -> 320
    //   89: iconst_1
    //   90: istore 4
    //   92: ldc -82
    //   94: astore 5
    //   96: iload 4
    //   98: aload 5
    //   100: invokestatic 86	b/a/a/a/o/b:a	(ZLjava/lang/String;)V
    //   103: aload_0
    //   104: getfield 137	b/a/a/a/i/c/d:e	Lb/a/a/a/i/c/k;
    //   107: astore_3
    //   108: aload_3
    //   109: ifnull +44 -> 153
    //   112: aload_0
    //   113: getfield 137	b/a/a/a/i/c/d:e	Lb/a/a/a/i/c/k;
    //   116: astore_3
    //   117: aload_3
    //   118: invokevirtual 177	b/a/a/a/i/c/k:b	()Lb/a/a/a/e/b/b;
    //   121: astore_3
    //   122: aload_3
    //   123: aload_1
    //   124: invokevirtual 183	b/a/a/a/e/b/b:equals	(Ljava/lang/Object;)Z
    //   127: istore 4
    //   129: iload 4
    //   131: ifne +22 -> 153
    //   134: aload_0
    //   135: getfield 137	b/a/a/a/i/c/d:e	Lb/a/a/a/i/c/k;
    //   138: astore_3
    //   139: aload_3
    //   140: invokevirtual 184	b/a/a/a/i/c/k:e	()V
    //   143: iconst_0
    //   144: istore 4
    //   146: aconst_null
    //   147: astore_3
    //   148: aload_0
    //   149: aconst_null
    //   150: putfield 137	b/a/a/a/i/c/d:e	Lb/a/a/a/i/c/k;
    //   153: aload_0
    //   154: getfield 137	b/a/a/a/i/c/d:e	Lb/a/a/a/i/c/k;
    //   157: astore_3
    //   158: aload_3
    //   159: ifnonnull +74 -> 233
    //   162: getstatic 28	b/a/a/a/i/c/d:b	Ljava/util/concurrent/atomic/AtomicLong;
    //   165: astore_3
    //   166: aload_3
    //   167: invokevirtual 188	java/util/concurrent/atomic/AtomicLong:getAndIncrement	()J
    //   170: lstore 7
    //   172: lload 7
    //   174: invokestatic 193	java/lang/Long:toString	(J)Ljava/lang/String;
    //   177: astore 9
    //   179: aload_0
    //   180: getfield 62	b/a/a/a/i/c/d:d	Lb/a/a/a/e/d;
    //   183: astore_3
    //   184: aload_3
    //   185: invokeinterface 198 1 0
    //   190: astore 10
    //   192: new 139	b/a/a/a/i/c/k
    //   195: astore 5
    //   197: aload_0
    //   198: getfield 48	b/a/a/a/i/c/d:a	Lb/a/a/a/h/b;
    //   201: astore 6
    //   203: lconst_0
    //   204: lstore 11
    //   206: getstatic 164	java/util/concurrent/TimeUnit:MILLISECONDS	Ljava/util/concurrent/TimeUnit;
    //   209: astore 13
    //   211: aload 5
    //   213: aload 6
    //   215: aload 9
    //   217: aload_1
    //   218: aload 10
    //   220: lload 11
    //   222: aload 13
    //   224: invokespecial 201	b/a/a/a/i/c/k:<init>	(Lb/a/a/a/h/b;Ljava/lang/String;Lb/a/a/a/e/b/b;Lb/a/a/a/e/q;JLjava/util/concurrent/TimeUnit;)V
    //   227: aload_0
    //   228: aload 5
    //   230: putfield 137	b/a/a/a/i/c/d:e	Lb/a/a/a/i/c/k;
    //   233: invokestatic 206	java/lang/System:currentTimeMillis	()J
    //   236: lstore 7
    //   238: aload_0
    //   239: getfield 137	b/a/a/a/i/c/d:e	Lb/a/a/a/i/c/k;
    //   242: astore 6
    //   244: aload 6
    //   246: lload 7
    //   248: invokevirtual 209	b/a/a/a/i/c/k:a	(J)Z
    //   251: istore 4
    //   253: iload 4
    //   255: ifeq +26 -> 281
    //   258: aload_0
    //   259: getfield 137	b/a/a/a/i/c/d:e	Lb/a/a/a/i/c/k;
    //   262: astore_3
    //   263: aload_3
    //   264: invokevirtual 184	b/a/a/a/i/c/k:e	()V
    //   267: aload_0
    //   268: getfield 137	b/a/a/a/i/c/d:e	Lb/a/a/a/i/c/k;
    //   271: astore_3
    //   272: aload_3
    //   273: invokevirtual 212	b/a/a/a/i/c/k:a	()Lb/a/a/a/e/b/f;
    //   276: astore_3
    //   277: aload_3
    //   278: invokevirtual 217	b/a/a/a/e/b/f:h	()V
    //   281: new 96	b/a/a/a/i/c/o
    //   284: astore_3
    //   285: aload_0
    //   286: getfield 62	b/a/a/a/i/c/d:d	Lb/a/a/a/e/d;
    //   289: astore 5
    //   291: aload_0
    //   292: getfield 137	b/a/a/a/i/c/d:e	Lb/a/a/a/i/c/k;
    //   295: astore 6
    //   297: aload_3
    //   298: aload_0
    //   299: aload 5
    //   301: aload 6
    //   303: invokespecial 220	b/a/a/a/i/c/o:<init>	(Lb/a/a/a/e/b;Lb/a/a/a/e/d;Lb/a/a/a/i/c/k;)V
    //   306: aload_0
    //   307: aload_3
    //   308: putfield 156	b/a/a/a/i/c/d:f	Lb/a/a/a/i/c/o;
    //   311: aload_0
    //   312: getfield 156	b/a/a/a/i/c/d:f	Lb/a/a/a/i/c/o;
    //   315: astore_3
    //   316: aload_0
    //   317: monitorexit
    //   318: aload_3
    //   319: areturn
    //   320: iconst_0
    //   321: istore 4
    //   323: aconst_null
    //   324: astore_3
    //   325: goto -233 -> 92
    //   328: astore_3
    //   329: aload_0
    //   330: monitorexit
    //   331: aload_3
    //   332: athrow
    // Local variable table:
    //   start	length	slot	name	signature
    //   0	333	0	this	d
    //   0	333	1	paramb	b.a.a.a.e.b.b
    //   0	333	2	paramObject	Object
    //   2	323	3	localObject1	Object
    //   328	4	3	localObject2	Object
    //   24	298	4	bool	boolean
    //   39	261	5	localObject3	Object
    //   48	254	6	localObject4	Object
    //   170	77	7	l1	long
    //   177	39	9	str	String
    //   190	29	10	localq	b.a.a.a.e.q
    //   204	17	11	l2	long
    //   209	14	13	localTimeUnit	java.util.concurrent.TimeUnit
    // Exception table:
    //   from	to	target	type
    //   11	15	328	finally
    //   15	19	328	finally
    //   20	24	328	finally
    //   31	35	328	finally
    //   36	39	328	finally
    //   41	46	328	finally
    //   52	57	328	finally
    //   61	65	328	finally
    //   67	72	328	finally
    //   75	80	328	finally
    //   80	84	328	finally
    //   98	103	328	finally
    //   103	107	328	finally
    //   112	116	328	finally
    //   117	121	328	finally
    //   123	127	328	finally
    //   134	138	328	finally
    //   139	143	328	finally
    //   149	153	328	finally
    //   153	157	328	finally
    //   162	165	328	finally
    //   166	170	328	finally
    //   172	177	328	finally
    //   179	183	328	finally
    //   184	190	328	finally
    //   192	195	328	finally
    //   197	201	328	finally
    //   206	209	328	finally
    //   222	227	328	finally
    //   228	233	328	finally
    //   233	236	328	finally
    //   238	242	328	finally
    //   246	251	328	finally
    //   258	262	328	finally
    //   263	267	328	finally
    //   267	271	328	finally
    //   272	276	328	finally
    //   277	281	328	finally
    //   281	284	328	finally
    //   285	289	328	finally
    //   291	295	328	finally
    //   301	306	328	finally
    //   307	311	328	finally
    //   311	315	328	finally
    //   316	318	328	finally
    //   329	331	328	finally
  }
  
  /* Error */
  public void b()
  {
    // Byte code:
    //   0: aload_0
    //   1: monitorenter
    //   2: iconst_1
    //   3: istore_1
    //   4: aload_0
    //   5: iload_1
    //   6: putfield 78	b/a/a/a/i/c/d:g	Z
    //   9: aload_0
    //   10: getfield 137	b/a/a/a/i/c/d:e	Lb/a/a/a/i/c/k;
    //   13: astore_2
    //   14: aload_2
    //   15: ifnull +12 -> 27
    //   18: aload_0
    //   19: getfield 137	b/a/a/a/i/c/d:e	Lb/a/a/a/i/c/k;
    //   22: astore_2
    //   23: aload_2
    //   24: invokevirtual 184	b/a/a/a/i/c/k:e	()V
    //   27: iconst_0
    //   28: istore_1
    //   29: aconst_null
    //   30: astore_2
    //   31: aload_0
    //   32: aconst_null
    //   33: putfield 137	b/a/a/a/i/c/d:e	Lb/a/a/a/i/c/k;
    //   36: iconst_0
    //   37: istore_1
    //   38: aconst_null
    //   39: astore_2
    //   40: aload_0
    //   41: aconst_null
    //   42: putfield 156	b/a/a/a/i/c/d:f	Lb/a/a/a/i/c/o;
    //   45: aload_0
    //   46: monitorexit
    //   47: return
    //   48: astore_2
    //   49: aload_0
    //   50: aconst_null
    //   51: putfield 137	b/a/a/a/i/c/d:e	Lb/a/a/a/i/c/k;
    //   54: aload_0
    //   55: aconst_null
    //   56: putfield 156	b/a/a/a/i/c/d:f	Lb/a/a/a/i/c/o;
    //   59: aload_2
    //   60: athrow
    //   61: astore_2
    //   62: aload_0
    //   63: monitorexit
    //   64: aload_2
    //   65: athrow
    // Local variable table:
    //   start	length	slot	name	signature
    //   0	66	0	this	d
    //   3	35	1	bool	boolean
    //   13	27	2	localk	k
    //   48	12	2	localObject1	Object
    //   61	4	2	localObject2	Object
    // Exception table:
    //   from	to	target	type
    //   9	13	48	finally
    //   18	22	48	finally
    //   23	27	48	finally
    //   5	9	61	finally
    //   32	36	61	finally
    //   41	45	61	finally
    //   45	47	61	finally
    //   50	54	61	finally
    //   55	59	61	finally
    //   59	61	61	finally
    //   62	64	61	finally
  }
  
  protected void finalize()
  {
    try
    {
      b();
      return;
    }
    finally
    {
      super.finalize();
    }
  }
}


/* Location:              C:\Users\haryo\Desktop\enjarify-master\presensi-enjarify.jar!\b\a\a\a\i\c\d.class
 * Java compiler version: 5 (49.0)
 * JD-Core Version:       0.7.1
 */