package com.google.android.gms.common.internal;

import android.os.IBinder;
import android.os.Parcel;

class zzs$zza$zza
  implements zzs
{
  private IBinder zzoz;
  
  zzs$zza$zza(IBinder paramIBinder)
  {
    this.zzoz = paramIBinder;
  }
  
  public IBinder asBinder()
  {
    return this.zzoz;
  }
  
  /* Error */
  public void zza(zzr paramzzr, int paramInt)
  {
    // Byte code:
    //   0: invokestatic 20	android/os/Parcel:obtain	()Landroid/os/Parcel;
    //   3: astore_3
    //   4: invokestatic 20	android/os/Parcel:obtain	()Landroid/os/Parcel;
    //   7: astore 4
    //   9: ldc 22
    //   11: astore 5
    //   13: aload_3
    //   14: aload 5
    //   16: invokevirtual 26	android/os/Parcel:writeInterfaceToken	(Ljava/lang/String;)V
    //   19: aload_1
    //   20: ifnull +60 -> 80
    //   23: aload_1
    //   24: invokeinterface 32 1 0
    //   29: astore 5
    //   31: aload_3
    //   32: aload 5
    //   34: invokevirtual 36	android/os/Parcel:writeStrongBinder	(Landroid/os/IBinder;)V
    //   37: aload_3
    //   38: iload_2
    //   39: invokevirtual 40	android/os/Parcel:writeInt	(I)V
    //   42: aload_0
    //   43: getfield 14	com/google/android/gms/common/internal/zzs$zza$zza:zzoz	Landroid/os/IBinder;
    //   46: astore 5
    //   48: iconst_4
    //   49: istore 6
    //   51: aload 5
    //   53: iload 6
    //   55: aload_3
    //   56: aload 4
    //   58: iconst_0
    //   59: invokeinterface 47 5 0
    //   64: pop
    //   65: aload 4
    //   67: invokevirtual 50	android/os/Parcel:readException	()V
    //   70: aload 4
    //   72: invokevirtual 53	android/os/Parcel:recycle	()V
    //   75: aload_3
    //   76: invokevirtual 53	android/os/Parcel:recycle	()V
    //   79: return
    //   80: aconst_null
    //   81: astore 5
    //   83: goto -52 -> 31
    //   86: astore 5
    //   88: aload 4
    //   90: invokevirtual 53	android/os/Parcel:recycle	()V
    //   93: aload_3
    //   94: invokevirtual 53	android/os/Parcel:recycle	()V
    //   97: aload 5
    //   99: athrow
    // Local variable table:
    //   start	length	slot	name	signature
    //   0	100	0	this	zza
    //   0	100	1	paramzzr	zzr
    //   0	100	2	paramInt	int
    //   3	91	3	localParcel1	Parcel
    //   7	82	4	localParcel2	Parcel
    //   11	71	5	localObject1	Object
    //   86	12	5	localObject2	Object
    //   49	5	6	i	int
    // Exception table:
    //   from	to	target	type
    //   14	19	86	finally
    //   23	29	86	finally
    //   32	37	86	finally
    //   38	42	86	finally
    //   42	46	86	finally
    //   58	65	86	finally
    //   65	70	86	finally
  }
  
  /* Error */
  public void zza(zzr paramzzr, int paramInt, String paramString)
  {
    // Byte code:
    //   0: invokestatic 20	android/os/Parcel:obtain	()Landroid/os/Parcel;
    //   3: astore 4
    //   5: invokestatic 20	android/os/Parcel:obtain	()Landroid/os/Parcel;
    //   8: astore 5
    //   10: ldc 22
    //   12: astore 6
    //   14: aload 4
    //   16: aload 6
    //   18: invokevirtual 26	android/os/Parcel:writeInterfaceToken	(Ljava/lang/String;)V
    //   21: aload_1
    //   22: ifnull +70 -> 92
    //   25: aload_1
    //   26: invokeinterface 32 1 0
    //   31: astore 6
    //   33: aload 4
    //   35: aload 6
    //   37: invokevirtual 36	android/os/Parcel:writeStrongBinder	(Landroid/os/IBinder;)V
    //   40: aload 4
    //   42: iload_2
    //   43: invokevirtual 40	android/os/Parcel:writeInt	(I)V
    //   46: aload 4
    //   48: aload_3
    //   49: invokevirtual 56	android/os/Parcel:writeString	(Ljava/lang/String;)V
    //   52: aload_0
    //   53: getfield 14	com/google/android/gms/common/internal/zzs$zza$zza:zzoz	Landroid/os/IBinder;
    //   56: astore 6
    //   58: iconst_3
    //   59: istore 7
    //   61: aload 6
    //   63: iload 7
    //   65: aload 4
    //   67: aload 5
    //   69: iconst_0
    //   70: invokeinterface 47 5 0
    //   75: pop
    //   76: aload 5
    //   78: invokevirtual 50	android/os/Parcel:readException	()V
    //   81: aload 5
    //   83: invokevirtual 53	android/os/Parcel:recycle	()V
    //   86: aload 4
    //   88: invokevirtual 53	android/os/Parcel:recycle	()V
    //   91: return
    //   92: aconst_null
    //   93: astore 6
    //   95: goto -62 -> 33
    //   98: astore 6
    //   100: aload 5
    //   102: invokevirtual 53	android/os/Parcel:recycle	()V
    //   105: aload 4
    //   107: invokevirtual 53	android/os/Parcel:recycle	()V
    //   110: aload 6
    //   112: athrow
    // Local variable table:
    //   start	length	slot	name	signature
    //   0	113	0	this	zza
    //   0	113	1	paramzzr	zzr
    //   0	113	2	paramInt	int
    //   0	113	3	paramString	String
    //   3	103	4	localParcel1	Parcel
    //   8	93	5	localParcel2	Parcel
    //   12	82	6	localObject1	Object
    //   98	13	6	localObject2	Object
    //   59	5	7	i	int
    // Exception table:
    //   from	to	target	type
    //   16	21	98	finally
    //   25	31	98	finally
    //   35	40	98	finally
    //   42	46	98	finally
    //   48	52	98	finally
    //   52	56	98	finally
    //   69	76	98	finally
    //   76	81	98	finally
  }
  
  /* Error */
  public void zza(zzr paramzzr, int paramInt, String paramString, android.os.Bundle paramBundle)
  {
    // Byte code:
    //   0: invokestatic 20	android/os/Parcel:obtain	()Landroid/os/Parcel;
    //   3: astore 5
    //   5: invokestatic 20	android/os/Parcel:obtain	()Landroid/os/Parcel;
    //   8: astore 6
    //   10: ldc 22
    //   12: astore 7
    //   14: aload 5
    //   16: aload 7
    //   18: invokevirtual 26	android/os/Parcel:writeInterfaceToken	(Ljava/lang/String;)V
    //   21: aload_1
    //   22: ifnull +99 -> 121
    //   25: aload_1
    //   26: invokeinterface 32 1 0
    //   31: astore 7
    //   33: aload 5
    //   35: aload 7
    //   37: invokevirtual 36	android/os/Parcel:writeStrongBinder	(Landroid/os/IBinder;)V
    //   40: aload 5
    //   42: iload_2
    //   43: invokevirtual 40	android/os/Parcel:writeInt	(I)V
    //   46: aload 5
    //   48: aload_3
    //   49: invokevirtual 56	android/os/Parcel:writeString	(Ljava/lang/String;)V
    //   52: aload 4
    //   54: ifnull +76 -> 130
    //   57: iconst_1
    //   58: istore 8
    //   60: aload 5
    //   62: iload 8
    //   64: invokevirtual 40	android/os/Parcel:writeInt	(I)V
    //   67: iconst_0
    //   68: istore 8
    //   70: aconst_null
    //   71: astore 7
    //   73: aload 4
    //   75: aload 5
    //   77: iconst_0
    //   78: invokevirtual 64	android/os/Bundle:writeToParcel	(Landroid/os/Parcel;I)V
    //   81: aload_0
    //   82: getfield 14	com/google/android/gms/common/internal/zzs$zza$zza:zzoz	Landroid/os/IBinder;
    //   85: astore 7
    //   87: iconst_2
    //   88: istore 9
    //   90: aload 7
    //   92: iload 9
    //   94: aload 5
    //   96: aload 6
    //   98: iconst_0
    //   99: invokeinterface 47 5 0
    //   104: pop
    //   105: aload 6
    //   107: invokevirtual 50	android/os/Parcel:readException	()V
    //   110: aload 6
    //   112: invokevirtual 53	android/os/Parcel:recycle	()V
    //   115: aload 5
    //   117: invokevirtual 53	android/os/Parcel:recycle	()V
    //   120: return
    //   121: iconst_0
    //   122: istore 8
    //   124: aconst_null
    //   125: astore 7
    //   127: goto -94 -> 33
    //   130: iconst_0
    //   131: istore 8
    //   133: aconst_null
    //   134: astore 7
    //   136: aload 5
    //   138: iconst_0
    //   139: invokevirtual 40	android/os/Parcel:writeInt	(I)V
    //   142: goto -61 -> 81
    //   145: astore 7
    //   147: aload 6
    //   149: invokevirtual 53	android/os/Parcel:recycle	()V
    //   152: aload 5
    //   154: invokevirtual 53	android/os/Parcel:recycle	()V
    //   157: aload 7
    //   159: athrow
    // Local variable table:
    //   start	length	slot	name	signature
    //   0	160	0	this	zza
    //   0	160	1	paramzzr	zzr
    //   0	160	2	paramInt	int
    //   0	160	3	paramString	String
    //   0	160	4	paramBundle	android.os.Bundle
    //   3	150	5	localParcel1	Parcel
    //   8	140	6	localParcel2	Parcel
    //   12	123	7	localObject1	Object
    //   145	13	7	localObject2	Object
    //   58	74	8	i	int
    //   88	5	9	j	int
    // Exception table:
    //   from	to	target	type
    //   16	21	145	finally
    //   25	31	145	finally
    //   35	40	145	finally
    //   42	46	145	finally
    //   48	52	145	finally
    //   62	67	145	finally
    //   77	81	145	finally
    //   81	85	145	finally
    //   98	105	145	finally
    //   105	110	145	finally
    //   138	142	145	finally
  }
  
  /* Error */
  public void zza(zzr paramzzr, int paramInt, String paramString, IBinder paramIBinder, android.os.Bundle paramBundle)
  {
    // Byte code:
    //   0: invokestatic 20	android/os/Parcel:obtain	()Landroid/os/Parcel;
    //   3: astore 6
    //   5: invokestatic 20	android/os/Parcel:obtain	()Landroid/os/Parcel;
    //   8: astore 7
    //   10: ldc 22
    //   12: astore 8
    //   14: aload 6
    //   16: aload 8
    //   18: invokevirtual 26	android/os/Parcel:writeInterfaceToken	(Ljava/lang/String;)V
    //   21: aload_1
    //   22: ifnull +107 -> 129
    //   25: aload_1
    //   26: invokeinterface 32 1 0
    //   31: astore 8
    //   33: aload 6
    //   35: aload 8
    //   37: invokevirtual 36	android/os/Parcel:writeStrongBinder	(Landroid/os/IBinder;)V
    //   40: aload 6
    //   42: iload_2
    //   43: invokevirtual 40	android/os/Parcel:writeInt	(I)V
    //   46: aload 6
    //   48: aload_3
    //   49: invokevirtual 56	android/os/Parcel:writeString	(Ljava/lang/String;)V
    //   52: aload 6
    //   54: aload 4
    //   56: invokevirtual 36	android/os/Parcel:writeStrongBinder	(Landroid/os/IBinder;)V
    //   59: aload 5
    //   61: ifnull +77 -> 138
    //   64: iconst_1
    //   65: istore 9
    //   67: aload 6
    //   69: iload 9
    //   71: invokevirtual 40	android/os/Parcel:writeInt	(I)V
    //   74: iconst_0
    //   75: istore 9
    //   77: aconst_null
    //   78: astore 8
    //   80: aload 5
    //   82: aload 6
    //   84: iconst_0
    //   85: invokevirtual 64	android/os/Bundle:writeToParcel	(Landroid/os/Parcel;I)V
    //   88: aload_0
    //   89: getfield 14	com/google/android/gms/common/internal/zzs$zza$zza:zzoz	Landroid/os/IBinder;
    //   92: astore 8
    //   94: bipush 19
    //   96: istore 10
    //   98: aload 8
    //   100: iload 10
    //   102: aload 6
    //   104: aload 7
    //   106: iconst_0
    //   107: invokeinterface 47 5 0
    //   112: pop
    //   113: aload 7
    //   115: invokevirtual 50	android/os/Parcel:readException	()V
    //   118: aload 7
    //   120: invokevirtual 53	android/os/Parcel:recycle	()V
    //   123: aload 6
    //   125: invokevirtual 53	android/os/Parcel:recycle	()V
    //   128: return
    //   129: iconst_0
    //   130: istore 9
    //   132: aconst_null
    //   133: astore 8
    //   135: goto -102 -> 33
    //   138: iconst_0
    //   139: istore 9
    //   141: aconst_null
    //   142: astore 8
    //   144: aload 6
    //   146: iconst_0
    //   147: invokevirtual 40	android/os/Parcel:writeInt	(I)V
    //   150: goto -62 -> 88
    //   153: astore 8
    //   155: aload 7
    //   157: invokevirtual 53	android/os/Parcel:recycle	()V
    //   160: aload 6
    //   162: invokevirtual 53	android/os/Parcel:recycle	()V
    //   165: aload 8
    //   167: athrow
    // Local variable table:
    //   start	length	slot	name	signature
    //   0	168	0	this	zza
    //   0	168	1	paramzzr	zzr
    //   0	168	2	paramInt	int
    //   0	168	3	paramString	String
    //   0	168	4	paramIBinder	IBinder
    //   0	168	5	paramBundle	android.os.Bundle
    //   3	158	6	localParcel1	Parcel
    //   8	148	7	localParcel2	Parcel
    //   12	131	8	localObject1	Object
    //   153	13	8	localObject2	Object
    //   65	75	9	i	int
    //   96	5	10	j	int
    // Exception table:
    //   from	to	target	type
    //   16	21	153	finally
    //   25	31	153	finally
    //   35	40	153	finally
    //   42	46	153	finally
    //   48	52	153	finally
    //   54	59	153	finally
    //   69	74	153	finally
    //   84	88	153	finally
    //   88	92	153	finally
    //   106	113	153	finally
    //   113	118	153	finally
    //   146	150	153	finally
  }
  
  /* Error */
  public void zza(zzr paramzzr, int paramInt, String paramString1, String paramString2)
  {
    // Byte code:
    //   0: invokestatic 20	android/os/Parcel:obtain	()Landroid/os/Parcel;
    //   3: astore 5
    //   5: invokestatic 20	android/os/Parcel:obtain	()Landroid/os/Parcel;
    //   8: astore 6
    //   10: ldc 22
    //   12: astore 7
    //   14: aload 5
    //   16: aload 7
    //   18: invokevirtual 26	android/os/Parcel:writeInterfaceToken	(Ljava/lang/String;)V
    //   21: aload_1
    //   22: ifnull +78 -> 100
    //   25: aload_1
    //   26: invokeinterface 32 1 0
    //   31: astore 7
    //   33: aload 5
    //   35: aload 7
    //   37: invokevirtual 36	android/os/Parcel:writeStrongBinder	(Landroid/os/IBinder;)V
    //   40: aload 5
    //   42: iload_2
    //   43: invokevirtual 40	android/os/Parcel:writeInt	(I)V
    //   46: aload 5
    //   48: aload_3
    //   49: invokevirtual 56	android/os/Parcel:writeString	(Ljava/lang/String;)V
    //   52: aload 5
    //   54: aload 4
    //   56: invokevirtual 56	android/os/Parcel:writeString	(Ljava/lang/String;)V
    //   59: aload_0
    //   60: getfield 14	com/google/android/gms/common/internal/zzs$zza$zza:zzoz	Landroid/os/IBinder;
    //   63: astore 7
    //   65: bipush 34
    //   67: istore 8
    //   69: aload 7
    //   71: iload 8
    //   73: aload 5
    //   75: aload 6
    //   77: iconst_0
    //   78: invokeinterface 47 5 0
    //   83: pop
    //   84: aload 6
    //   86: invokevirtual 50	android/os/Parcel:readException	()V
    //   89: aload 6
    //   91: invokevirtual 53	android/os/Parcel:recycle	()V
    //   94: aload 5
    //   96: invokevirtual 53	android/os/Parcel:recycle	()V
    //   99: return
    //   100: aconst_null
    //   101: astore 7
    //   103: goto -70 -> 33
    //   106: astore 7
    //   108: aload 6
    //   110: invokevirtual 53	android/os/Parcel:recycle	()V
    //   113: aload 5
    //   115: invokevirtual 53	android/os/Parcel:recycle	()V
    //   118: aload 7
    //   120: athrow
    // Local variable table:
    //   start	length	slot	name	signature
    //   0	121	0	this	zza
    //   0	121	1	paramzzr	zzr
    //   0	121	2	paramInt	int
    //   0	121	3	paramString1	String
    //   0	121	4	paramString2	String
    //   3	111	5	localParcel1	Parcel
    //   8	101	6	localParcel2	Parcel
    //   12	90	7	localObject1	Object
    //   106	13	7	localObject2	Object
    //   67	5	8	i	int
    // Exception table:
    //   from	to	target	type
    //   16	21	106	finally
    //   25	31	106	finally
    //   35	40	106	finally
    //   42	46	106	finally
    //   48	52	106	finally
    //   54	59	106	finally
    //   59	63	106	finally
    //   77	84	106	finally
    //   84	89	106	finally
  }
  
  /* Error */
  public void zza(zzr paramzzr, int paramInt, String paramString1, String paramString2, String paramString3, String[] paramArrayOfString)
  {
    // Byte code:
    //   0: invokestatic 20	android/os/Parcel:obtain	()Landroid/os/Parcel;
    //   3: astore 7
    //   5: invokestatic 20	android/os/Parcel:obtain	()Landroid/os/Parcel;
    //   8: astore 8
    //   10: ldc 22
    //   12: astore 9
    //   14: aload 7
    //   16: aload 9
    //   18: invokevirtual 26	android/os/Parcel:writeInterfaceToken	(Ljava/lang/String;)V
    //   21: aload_1
    //   22: ifnull +92 -> 114
    //   25: aload_1
    //   26: invokeinterface 32 1 0
    //   31: astore 9
    //   33: aload 7
    //   35: aload 9
    //   37: invokevirtual 36	android/os/Parcel:writeStrongBinder	(Landroid/os/IBinder;)V
    //   40: aload 7
    //   42: iload_2
    //   43: invokevirtual 40	android/os/Parcel:writeInt	(I)V
    //   46: aload 7
    //   48: aload_3
    //   49: invokevirtual 56	android/os/Parcel:writeString	(Ljava/lang/String;)V
    //   52: aload 7
    //   54: aload 4
    //   56: invokevirtual 56	android/os/Parcel:writeString	(Ljava/lang/String;)V
    //   59: aload 7
    //   61: aload 5
    //   63: invokevirtual 56	android/os/Parcel:writeString	(Ljava/lang/String;)V
    //   66: aload 7
    //   68: aload 6
    //   70: invokevirtual 71	android/os/Parcel:writeStringArray	([Ljava/lang/String;)V
    //   73: aload_0
    //   74: getfield 14	com/google/android/gms/common/internal/zzs$zza$zza:zzoz	Landroid/os/IBinder;
    //   77: astore 9
    //   79: bipush 33
    //   81: istore 10
    //   83: aload 9
    //   85: iload 10
    //   87: aload 7
    //   89: aload 8
    //   91: iconst_0
    //   92: invokeinterface 47 5 0
    //   97: pop
    //   98: aload 8
    //   100: invokevirtual 50	android/os/Parcel:readException	()V
    //   103: aload 8
    //   105: invokevirtual 53	android/os/Parcel:recycle	()V
    //   108: aload 7
    //   110: invokevirtual 53	android/os/Parcel:recycle	()V
    //   113: return
    //   114: aconst_null
    //   115: astore 9
    //   117: goto -84 -> 33
    //   120: astore 9
    //   122: aload 8
    //   124: invokevirtual 53	android/os/Parcel:recycle	()V
    //   127: aload 7
    //   129: invokevirtual 53	android/os/Parcel:recycle	()V
    //   132: aload 9
    //   134: athrow
    // Local variable table:
    //   start	length	slot	name	signature
    //   0	135	0	this	zza
    //   0	135	1	paramzzr	zzr
    //   0	135	2	paramInt	int
    //   0	135	3	paramString1	String
    //   0	135	4	paramString2	String
    //   0	135	5	paramString3	String
    //   0	135	6	paramArrayOfString	String[]
    //   3	125	7	localParcel1	Parcel
    //   8	115	8	localParcel2	Parcel
    //   12	104	9	localObject1	Object
    //   120	13	9	localObject2	Object
    //   81	5	10	i	int
    // Exception table:
    //   from	to	target	type
    //   16	21	120	finally
    //   25	31	120	finally
    //   35	40	120	finally
    //   42	46	120	finally
    //   48	52	120	finally
    //   54	59	120	finally
    //   61	66	120	finally
    //   68	73	120	finally
    //   73	77	120	finally
    //   91	98	120	finally
    //   98	103	120	finally
  }
  
  /* Error */
  public void zza(zzr paramzzr, int paramInt, String paramString1, String paramString2, String[] paramArrayOfString)
  {
    // Byte code:
    //   0: invokestatic 20	android/os/Parcel:obtain	()Landroid/os/Parcel;
    //   3: astore 6
    //   5: invokestatic 20	android/os/Parcel:obtain	()Landroid/os/Parcel;
    //   8: astore 7
    //   10: ldc 22
    //   12: astore 8
    //   14: aload 6
    //   16: aload 8
    //   18: invokevirtual 26	android/os/Parcel:writeInterfaceToken	(Ljava/lang/String;)V
    //   21: aload_1
    //   22: ifnull +85 -> 107
    //   25: aload_1
    //   26: invokeinterface 32 1 0
    //   31: astore 8
    //   33: aload 6
    //   35: aload 8
    //   37: invokevirtual 36	android/os/Parcel:writeStrongBinder	(Landroid/os/IBinder;)V
    //   40: aload 6
    //   42: iload_2
    //   43: invokevirtual 40	android/os/Parcel:writeInt	(I)V
    //   46: aload 6
    //   48: aload_3
    //   49: invokevirtual 56	android/os/Parcel:writeString	(Ljava/lang/String;)V
    //   52: aload 6
    //   54: aload 4
    //   56: invokevirtual 56	android/os/Parcel:writeString	(Ljava/lang/String;)V
    //   59: aload 6
    //   61: aload 5
    //   63: invokevirtual 71	android/os/Parcel:writeStringArray	([Ljava/lang/String;)V
    //   66: aload_0
    //   67: getfield 14	com/google/android/gms/common/internal/zzs$zza$zza:zzoz	Landroid/os/IBinder;
    //   70: astore 8
    //   72: bipush 10
    //   74: istore 9
    //   76: aload 8
    //   78: iload 9
    //   80: aload 6
    //   82: aload 7
    //   84: iconst_0
    //   85: invokeinterface 47 5 0
    //   90: pop
    //   91: aload 7
    //   93: invokevirtual 50	android/os/Parcel:readException	()V
    //   96: aload 7
    //   98: invokevirtual 53	android/os/Parcel:recycle	()V
    //   101: aload 6
    //   103: invokevirtual 53	android/os/Parcel:recycle	()V
    //   106: return
    //   107: aconst_null
    //   108: astore 8
    //   110: goto -77 -> 33
    //   113: astore 8
    //   115: aload 7
    //   117: invokevirtual 53	android/os/Parcel:recycle	()V
    //   120: aload 6
    //   122: invokevirtual 53	android/os/Parcel:recycle	()V
    //   125: aload 8
    //   127: athrow
    // Local variable table:
    //   start	length	slot	name	signature
    //   0	128	0	this	zza
    //   0	128	1	paramzzr	zzr
    //   0	128	2	paramInt	int
    //   0	128	3	paramString1	String
    //   0	128	4	paramString2	String
    //   0	128	5	paramArrayOfString	String[]
    //   3	118	6	localParcel1	Parcel
    //   8	108	7	localParcel2	Parcel
    //   12	97	8	localObject1	Object
    //   113	13	8	localObject2	Object
    //   74	5	9	i	int
    // Exception table:
    //   from	to	target	type
    //   16	21	113	finally
    //   25	31	113	finally
    //   35	40	113	finally
    //   42	46	113	finally
    //   48	52	113	finally
    //   54	59	113	finally
    //   61	66	113	finally
    //   66	70	113	finally
    //   84	91	113	finally
    //   91	96	113	finally
  }
  
  /* Error */
  public void zza(zzr paramzzr, int paramInt, String paramString1, String paramString2, String[] paramArrayOfString, android.os.Bundle paramBundle)
  {
    // Byte code:
    //   0: invokestatic 20	android/os/Parcel:obtain	()Landroid/os/Parcel;
    //   3: astore 7
    //   5: invokestatic 20	android/os/Parcel:obtain	()Landroid/os/Parcel;
    //   8: astore 8
    //   10: ldc 22
    //   12: astore 9
    //   14: aload 7
    //   16: aload 9
    //   18: invokevirtual 26	android/os/Parcel:writeInterfaceToken	(Ljava/lang/String;)V
    //   21: aload_1
    //   22: ifnull +114 -> 136
    //   25: aload_1
    //   26: invokeinterface 32 1 0
    //   31: astore 9
    //   33: aload 7
    //   35: aload 9
    //   37: invokevirtual 36	android/os/Parcel:writeStrongBinder	(Landroid/os/IBinder;)V
    //   40: aload 7
    //   42: iload_2
    //   43: invokevirtual 40	android/os/Parcel:writeInt	(I)V
    //   46: aload 7
    //   48: aload_3
    //   49: invokevirtual 56	android/os/Parcel:writeString	(Ljava/lang/String;)V
    //   52: aload 7
    //   54: aload 4
    //   56: invokevirtual 56	android/os/Parcel:writeString	(Ljava/lang/String;)V
    //   59: aload 7
    //   61: aload 5
    //   63: invokevirtual 71	android/os/Parcel:writeStringArray	([Ljava/lang/String;)V
    //   66: aload 6
    //   68: ifnull +77 -> 145
    //   71: iconst_1
    //   72: istore 10
    //   74: aload 7
    //   76: iload 10
    //   78: invokevirtual 40	android/os/Parcel:writeInt	(I)V
    //   81: iconst_0
    //   82: istore 10
    //   84: aconst_null
    //   85: astore 9
    //   87: aload 6
    //   89: aload 7
    //   91: iconst_0
    //   92: invokevirtual 64	android/os/Bundle:writeToParcel	(Landroid/os/Parcel;I)V
    //   95: aload_0
    //   96: getfield 14	com/google/android/gms/common/internal/zzs$zza$zza:zzoz	Landroid/os/IBinder;
    //   99: astore 9
    //   101: bipush 30
    //   103: istore 11
    //   105: aload 9
    //   107: iload 11
    //   109: aload 7
    //   111: aload 8
    //   113: iconst_0
    //   114: invokeinterface 47 5 0
    //   119: pop
    //   120: aload 8
    //   122: invokevirtual 50	android/os/Parcel:readException	()V
    //   125: aload 8
    //   127: invokevirtual 53	android/os/Parcel:recycle	()V
    //   130: aload 7
    //   132: invokevirtual 53	android/os/Parcel:recycle	()V
    //   135: return
    //   136: iconst_0
    //   137: istore 10
    //   139: aconst_null
    //   140: astore 9
    //   142: goto -109 -> 33
    //   145: iconst_0
    //   146: istore 10
    //   148: aconst_null
    //   149: astore 9
    //   151: aload 7
    //   153: iconst_0
    //   154: invokevirtual 40	android/os/Parcel:writeInt	(I)V
    //   157: goto -62 -> 95
    //   160: astore 9
    //   162: aload 8
    //   164: invokevirtual 53	android/os/Parcel:recycle	()V
    //   167: aload 7
    //   169: invokevirtual 53	android/os/Parcel:recycle	()V
    //   172: aload 9
    //   174: athrow
    // Local variable table:
    //   start	length	slot	name	signature
    //   0	175	0	this	zza
    //   0	175	1	paramzzr	zzr
    //   0	175	2	paramInt	int
    //   0	175	3	paramString1	String
    //   0	175	4	paramString2	String
    //   0	175	5	paramArrayOfString	String[]
    //   0	175	6	paramBundle	android.os.Bundle
    //   3	165	7	localParcel1	Parcel
    //   8	155	8	localParcel2	Parcel
    //   12	138	9	localObject1	Object
    //   160	13	9	localObject2	Object
    //   72	75	10	i	int
    //   103	5	11	j	int
    // Exception table:
    //   from	to	target	type
    //   16	21	160	finally
    //   25	31	160	finally
    //   35	40	160	finally
    //   42	46	160	finally
    //   48	52	160	finally
    //   54	59	160	finally
    //   61	66	160	finally
    //   76	81	160	finally
    //   91	95	160	finally
    //   95	99	160	finally
    //   113	120	160	finally
    //   120	125	160	finally
    //   153	157	160	finally
  }
  
  /* Error */
  public void zza(zzr paramzzr, int paramInt, String paramString1, String paramString2, String[] paramArrayOfString, String paramString3, android.os.Bundle paramBundle)
  {
    // Byte code:
    //   0: invokestatic 20	android/os/Parcel:obtain	()Landroid/os/Parcel;
    //   3: astore 8
    //   5: invokestatic 20	android/os/Parcel:obtain	()Landroid/os/Parcel;
    //   8: astore 9
    //   10: ldc 22
    //   12: astore 10
    //   14: aload 8
    //   16: aload 10
    //   18: invokevirtual 26	android/os/Parcel:writeInterfaceToken	(Ljava/lang/String;)V
    //   21: aload_1
    //   22: ifnull +120 -> 142
    //   25: aload_1
    //   26: invokeinterface 32 1 0
    //   31: astore 10
    //   33: aload 8
    //   35: aload 10
    //   37: invokevirtual 36	android/os/Parcel:writeStrongBinder	(Landroid/os/IBinder;)V
    //   40: aload 8
    //   42: iload_2
    //   43: invokevirtual 40	android/os/Parcel:writeInt	(I)V
    //   46: aload 8
    //   48: aload_3
    //   49: invokevirtual 56	android/os/Parcel:writeString	(Ljava/lang/String;)V
    //   52: aload 8
    //   54: aload 4
    //   56: invokevirtual 56	android/os/Parcel:writeString	(Ljava/lang/String;)V
    //   59: aload 8
    //   61: aload 5
    //   63: invokevirtual 71	android/os/Parcel:writeStringArray	([Ljava/lang/String;)V
    //   66: aload 8
    //   68: aload 6
    //   70: invokevirtual 56	android/os/Parcel:writeString	(Ljava/lang/String;)V
    //   73: aload 7
    //   75: ifnull +76 -> 151
    //   78: iconst_1
    //   79: istore 11
    //   81: aload 8
    //   83: iload 11
    //   85: invokevirtual 40	android/os/Parcel:writeInt	(I)V
    //   88: iconst_0
    //   89: istore 11
    //   91: aconst_null
    //   92: astore 10
    //   94: aload 7
    //   96: aload 8
    //   98: iconst_0
    //   99: invokevirtual 64	android/os/Bundle:writeToParcel	(Landroid/os/Parcel;I)V
    //   102: aload_0
    //   103: getfield 14	com/google/android/gms/common/internal/zzs$zza$zza:zzoz	Landroid/os/IBinder;
    //   106: astore 10
    //   108: iconst_1
    //   109: istore 12
    //   111: aload 10
    //   113: iload 12
    //   115: aload 8
    //   117: aload 9
    //   119: iconst_0
    //   120: invokeinterface 47 5 0
    //   125: pop
    //   126: aload 9
    //   128: invokevirtual 50	android/os/Parcel:readException	()V
    //   131: aload 9
    //   133: invokevirtual 53	android/os/Parcel:recycle	()V
    //   136: aload 8
    //   138: invokevirtual 53	android/os/Parcel:recycle	()V
    //   141: return
    //   142: iconst_0
    //   143: istore 11
    //   145: aconst_null
    //   146: astore 10
    //   148: goto -115 -> 33
    //   151: iconst_0
    //   152: istore 11
    //   154: aconst_null
    //   155: astore 10
    //   157: aload 8
    //   159: iconst_0
    //   160: invokevirtual 40	android/os/Parcel:writeInt	(I)V
    //   163: goto -61 -> 102
    //   166: astore 10
    //   168: aload 9
    //   170: invokevirtual 53	android/os/Parcel:recycle	()V
    //   173: aload 8
    //   175: invokevirtual 53	android/os/Parcel:recycle	()V
    //   178: aload 10
    //   180: athrow
    // Local variable table:
    //   start	length	slot	name	signature
    //   0	181	0	this	zza
    //   0	181	1	paramzzr	zzr
    //   0	181	2	paramInt	int
    //   0	181	3	paramString1	String
    //   0	181	4	paramString2	String
    //   0	181	5	paramArrayOfString	String[]
    //   0	181	6	paramString3	String
    //   0	181	7	paramBundle	android.os.Bundle
    //   3	171	8	localParcel1	Parcel
    //   8	161	9	localParcel2	Parcel
    //   12	144	10	localObject1	Object
    //   166	13	10	localObject2	Object
    //   79	74	11	i	int
    //   109	5	12	j	int
    // Exception table:
    //   from	to	target	type
    //   16	21	166	finally
    //   25	31	166	finally
    //   35	40	166	finally
    //   42	46	166	finally
    //   48	52	166	finally
    //   54	59	166	finally
    //   61	66	166	finally
    //   68	73	166	finally
    //   83	88	166	finally
    //   98	102	166	finally
    //   102	106	166	finally
    //   119	126	166	finally
    //   126	131	166	finally
    //   159	163	166	finally
  }
  
  /* Error */
  public void zza(zzr paramzzr, int paramInt, String paramString1, String paramString2, String[] paramArrayOfString, String paramString3, IBinder paramIBinder, String paramString4, android.os.Bundle paramBundle)
  {
    // Byte code:
    //   0: invokestatic 20	android/os/Parcel:obtain	()Landroid/os/Parcel;
    //   3: astore 10
    //   5: invokestatic 20	android/os/Parcel:obtain	()Landroid/os/Parcel;
    //   8: astore 11
    //   10: ldc 22
    //   12: astore 12
    //   14: aload 10
    //   16: aload 12
    //   18: invokevirtual 26	android/os/Parcel:writeInterfaceToken	(Ljava/lang/String;)V
    //   21: aload_1
    //   22: ifnull +135 -> 157
    //   25: aload_1
    //   26: invokeinterface 32 1 0
    //   31: astore 12
    //   33: aload 10
    //   35: aload 12
    //   37: invokevirtual 36	android/os/Parcel:writeStrongBinder	(Landroid/os/IBinder;)V
    //   40: aload 10
    //   42: iload_2
    //   43: invokevirtual 40	android/os/Parcel:writeInt	(I)V
    //   46: aload 10
    //   48: aload_3
    //   49: invokevirtual 56	android/os/Parcel:writeString	(Ljava/lang/String;)V
    //   52: aload 10
    //   54: aload 4
    //   56: invokevirtual 56	android/os/Parcel:writeString	(Ljava/lang/String;)V
    //   59: aload 10
    //   61: aload 5
    //   63: invokevirtual 71	android/os/Parcel:writeStringArray	([Ljava/lang/String;)V
    //   66: aload 10
    //   68: aload 6
    //   70: invokevirtual 56	android/os/Parcel:writeString	(Ljava/lang/String;)V
    //   73: aload 10
    //   75: aload 7
    //   77: invokevirtual 36	android/os/Parcel:writeStrongBinder	(Landroid/os/IBinder;)V
    //   80: aload 10
    //   82: aload 8
    //   84: invokevirtual 56	android/os/Parcel:writeString	(Ljava/lang/String;)V
    //   87: aload 9
    //   89: ifnull +77 -> 166
    //   92: iconst_1
    //   93: istore 13
    //   95: aload 10
    //   97: iload 13
    //   99: invokevirtual 40	android/os/Parcel:writeInt	(I)V
    //   102: iconst_0
    //   103: istore 13
    //   105: aconst_null
    //   106: astore 12
    //   108: aload 9
    //   110: aload 10
    //   112: iconst_0
    //   113: invokevirtual 64	android/os/Bundle:writeToParcel	(Landroid/os/Parcel;I)V
    //   116: aload_0
    //   117: getfield 14	com/google/android/gms/common/internal/zzs$zza$zza:zzoz	Landroid/os/IBinder;
    //   120: astore 12
    //   122: bipush 9
    //   124: istore 14
    //   126: aload 12
    //   128: iload 14
    //   130: aload 10
    //   132: aload 11
    //   134: iconst_0
    //   135: invokeinterface 47 5 0
    //   140: pop
    //   141: aload 11
    //   143: invokevirtual 50	android/os/Parcel:readException	()V
    //   146: aload 11
    //   148: invokevirtual 53	android/os/Parcel:recycle	()V
    //   151: aload 10
    //   153: invokevirtual 53	android/os/Parcel:recycle	()V
    //   156: return
    //   157: iconst_0
    //   158: istore 13
    //   160: aconst_null
    //   161: astore 12
    //   163: goto -130 -> 33
    //   166: iconst_0
    //   167: istore 13
    //   169: aconst_null
    //   170: astore 12
    //   172: aload 10
    //   174: iconst_0
    //   175: invokevirtual 40	android/os/Parcel:writeInt	(I)V
    //   178: goto -62 -> 116
    //   181: astore 12
    //   183: aload 11
    //   185: invokevirtual 53	android/os/Parcel:recycle	()V
    //   188: aload 10
    //   190: invokevirtual 53	android/os/Parcel:recycle	()V
    //   193: aload 12
    //   195: athrow
    // Local variable table:
    //   start	length	slot	name	signature
    //   0	196	0	this	zza
    //   0	196	1	paramzzr	zzr
    //   0	196	2	paramInt	int
    //   0	196	3	paramString1	String
    //   0	196	4	paramString2	String
    //   0	196	5	paramArrayOfString	String[]
    //   0	196	6	paramString3	String
    //   0	196	7	paramIBinder	IBinder
    //   0	196	8	paramString4	String
    //   0	196	9	paramBundle	android.os.Bundle
    //   3	186	10	localParcel1	Parcel
    //   8	176	11	localParcel2	Parcel
    //   12	159	12	localObject1	Object
    //   181	13	12	localObject2	Object
    //   93	75	13	i	int
    //   124	5	14	j	int
    // Exception table:
    //   from	to	target	type
    //   16	21	181	finally
    //   25	31	181	finally
    //   35	40	181	finally
    //   42	46	181	finally
    //   48	52	181	finally
    //   54	59	181	finally
    //   61	66	181	finally
    //   68	73	181	finally
    //   75	80	181	finally
    //   82	87	181	finally
    //   97	102	181	finally
    //   112	116	181	finally
    //   116	120	181	finally
    //   134	141	181	finally
    //   141	146	181	finally
    //   174	178	181	finally
  }
  
  /* Error */
  public void zza(zzr paramzzr, int paramInt, String paramString1, String[] paramArrayOfString, String paramString2, android.os.Bundle paramBundle)
  {
    // Byte code:
    //   0: invokestatic 20	android/os/Parcel:obtain	()Landroid/os/Parcel;
    //   3: astore 7
    //   5: invokestatic 20	android/os/Parcel:obtain	()Landroid/os/Parcel;
    //   8: astore 8
    //   10: ldc 22
    //   12: astore 9
    //   14: aload 7
    //   16: aload 9
    //   18: invokevirtual 26	android/os/Parcel:writeInterfaceToken	(Ljava/lang/String;)V
    //   21: aload_1
    //   22: ifnull +114 -> 136
    //   25: aload_1
    //   26: invokeinterface 32 1 0
    //   31: astore 9
    //   33: aload 7
    //   35: aload 9
    //   37: invokevirtual 36	android/os/Parcel:writeStrongBinder	(Landroid/os/IBinder;)V
    //   40: aload 7
    //   42: iload_2
    //   43: invokevirtual 40	android/os/Parcel:writeInt	(I)V
    //   46: aload 7
    //   48: aload_3
    //   49: invokevirtual 56	android/os/Parcel:writeString	(Ljava/lang/String;)V
    //   52: aload 7
    //   54: aload 4
    //   56: invokevirtual 71	android/os/Parcel:writeStringArray	([Ljava/lang/String;)V
    //   59: aload 7
    //   61: aload 5
    //   63: invokevirtual 56	android/os/Parcel:writeString	(Ljava/lang/String;)V
    //   66: aload 6
    //   68: ifnull +77 -> 145
    //   71: iconst_1
    //   72: istore 10
    //   74: aload 7
    //   76: iload 10
    //   78: invokevirtual 40	android/os/Parcel:writeInt	(I)V
    //   81: iconst_0
    //   82: istore 10
    //   84: aconst_null
    //   85: astore 9
    //   87: aload 6
    //   89: aload 7
    //   91: iconst_0
    //   92: invokevirtual 64	android/os/Bundle:writeToParcel	(Landroid/os/Parcel;I)V
    //   95: aload_0
    //   96: getfield 14	com/google/android/gms/common/internal/zzs$zza$zza:zzoz	Landroid/os/IBinder;
    //   99: astore 9
    //   101: bipush 20
    //   103: istore 11
    //   105: aload 9
    //   107: iload 11
    //   109: aload 7
    //   111: aload 8
    //   113: iconst_0
    //   114: invokeinterface 47 5 0
    //   119: pop
    //   120: aload 8
    //   122: invokevirtual 50	android/os/Parcel:readException	()V
    //   125: aload 8
    //   127: invokevirtual 53	android/os/Parcel:recycle	()V
    //   130: aload 7
    //   132: invokevirtual 53	android/os/Parcel:recycle	()V
    //   135: return
    //   136: iconst_0
    //   137: istore 10
    //   139: aconst_null
    //   140: astore 9
    //   142: goto -109 -> 33
    //   145: iconst_0
    //   146: istore 10
    //   148: aconst_null
    //   149: astore 9
    //   151: aload 7
    //   153: iconst_0
    //   154: invokevirtual 40	android/os/Parcel:writeInt	(I)V
    //   157: goto -62 -> 95
    //   160: astore 9
    //   162: aload 8
    //   164: invokevirtual 53	android/os/Parcel:recycle	()V
    //   167: aload 7
    //   169: invokevirtual 53	android/os/Parcel:recycle	()V
    //   172: aload 9
    //   174: athrow
    // Local variable table:
    //   start	length	slot	name	signature
    //   0	175	0	this	zza
    //   0	175	1	paramzzr	zzr
    //   0	175	2	paramInt	int
    //   0	175	3	paramString1	String
    //   0	175	4	paramArrayOfString	String[]
    //   0	175	5	paramString2	String
    //   0	175	6	paramBundle	android.os.Bundle
    //   3	165	7	localParcel1	Parcel
    //   8	155	8	localParcel2	Parcel
    //   12	138	9	localObject1	Object
    //   160	13	9	localObject2	Object
    //   72	75	10	i	int
    //   103	5	11	j	int
    // Exception table:
    //   from	to	target	type
    //   16	21	160	finally
    //   25	31	160	finally
    //   35	40	160	finally
    //   42	46	160	finally
    //   48	52	160	finally
    //   54	59	160	finally
    //   61	66	160	finally
    //   76	81	160	finally
    //   91	95	160	finally
    //   95	99	160	finally
    //   113	120	160	finally
    //   120	125	160	finally
    //   153	157	160	finally
  }
  
  /* Error */
  public void zza(zzr paramzzr, GetServiceRequest paramGetServiceRequest)
  {
    // Byte code:
    //   0: invokestatic 20	android/os/Parcel:obtain	()Landroid/os/Parcel;
    //   3: astore_3
    //   4: invokestatic 20	android/os/Parcel:obtain	()Landroid/os/Parcel;
    //   7: astore 4
    //   9: ldc 22
    //   11: astore 5
    //   13: aload_3
    //   14: aload 5
    //   16: invokevirtual 26	android/os/Parcel:writeInterfaceToken	(Ljava/lang/String;)V
    //   19: aload_1
    //   20: ifnull +81 -> 101
    //   23: aload_1
    //   24: invokeinterface 32 1 0
    //   29: astore 5
    //   31: aload_3
    //   32: aload 5
    //   34: invokevirtual 36	android/os/Parcel:writeStrongBinder	(Landroid/os/IBinder;)V
    //   37: aload_2
    //   38: ifnull +72 -> 110
    //   41: iconst_1
    //   42: istore 6
    //   44: aload_3
    //   45: iload 6
    //   47: invokevirtual 40	android/os/Parcel:writeInt	(I)V
    //   50: iconst_0
    //   51: istore 6
    //   53: aconst_null
    //   54: astore 5
    //   56: aload_2
    //   57: aload_3
    //   58: iconst_0
    //   59: invokevirtual 79	com/google/android/gms/common/internal/GetServiceRequest:writeToParcel	(Landroid/os/Parcel;I)V
    //   62: aload_0
    //   63: getfield 14	com/google/android/gms/common/internal/zzs$zza$zza:zzoz	Landroid/os/IBinder;
    //   66: astore 5
    //   68: bipush 46
    //   70: istore 7
    //   72: aload 5
    //   74: iload 7
    //   76: aload_3
    //   77: aload 4
    //   79: iconst_0
    //   80: invokeinterface 47 5 0
    //   85: pop
    //   86: aload 4
    //   88: invokevirtual 50	android/os/Parcel:readException	()V
    //   91: aload 4
    //   93: invokevirtual 53	android/os/Parcel:recycle	()V
    //   96: aload_3
    //   97: invokevirtual 53	android/os/Parcel:recycle	()V
    //   100: return
    //   101: iconst_0
    //   102: istore 6
    //   104: aconst_null
    //   105: astore 5
    //   107: goto -76 -> 31
    //   110: iconst_0
    //   111: istore 6
    //   113: aconst_null
    //   114: astore 5
    //   116: aload_3
    //   117: iconst_0
    //   118: invokevirtual 40	android/os/Parcel:writeInt	(I)V
    //   121: goto -59 -> 62
    //   124: astore 5
    //   126: aload 4
    //   128: invokevirtual 53	android/os/Parcel:recycle	()V
    //   131: aload_3
    //   132: invokevirtual 53	android/os/Parcel:recycle	()V
    //   135: aload 5
    //   137: athrow
    // Local variable table:
    //   start	length	slot	name	signature
    //   0	138	0	this	zza
    //   0	138	1	paramzzr	zzr
    //   0	138	2	paramGetServiceRequest	GetServiceRequest
    //   3	129	3	localParcel1	Parcel
    //   7	120	4	localParcel2	Parcel
    //   11	104	5	localObject1	Object
    //   124	12	5	localObject2	Object
    //   42	70	6	i	int
    //   70	5	7	j	int
    // Exception table:
    //   from	to	target	type
    //   14	19	124	finally
    //   23	29	124	finally
    //   32	37	124	finally
    //   45	50	124	finally
    //   58	62	124	finally
    //   62	66	124	finally
    //   79	86	124	finally
    //   86	91	124	finally
    //   117	121	124	finally
  }
  
  /* Error */
  public void zza(zzr paramzzr, ValidateAccountRequest paramValidateAccountRequest)
  {
    // Byte code:
    //   0: invokestatic 20	android/os/Parcel:obtain	()Landroid/os/Parcel;
    //   3: astore_3
    //   4: invokestatic 20	android/os/Parcel:obtain	()Landroid/os/Parcel;
    //   7: astore 4
    //   9: ldc 22
    //   11: astore 5
    //   13: aload_3
    //   14: aload 5
    //   16: invokevirtual 26	android/os/Parcel:writeInterfaceToken	(Ljava/lang/String;)V
    //   19: aload_1
    //   20: ifnull +81 -> 101
    //   23: aload_1
    //   24: invokeinterface 32 1 0
    //   29: astore 5
    //   31: aload_3
    //   32: aload 5
    //   34: invokevirtual 36	android/os/Parcel:writeStrongBinder	(Landroid/os/IBinder;)V
    //   37: aload_2
    //   38: ifnull +72 -> 110
    //   41: iconst_1
    //   42: istore 6
    //   44: aload_3
    //   45: iload 6
    //   47: invokevirtual 40	android/os/Parcel:writeInt	(I)V
    //   50: iconst_0
    //   51: istore 6
    //   53: aconst_null
    //   54: astore 5
    //   56: aload_2
    //   57: aload_3
    //   58: iconst_0
    //   59: invokevirtual 83	com/google/android/gms/common/internal/ValidateAccountRequest:writeToParcel	(Landroid/os/Parcel;I)V
    //   62: aload_0
    //   63: getfield 14	com/google/android/gms/common/internal/zzs$zza$zza:zzoz	Landroid/os/IBinder;
    //   66: astore 5
    //   68: bipush 47
    //   70: istore 7
    //   72: aload 5
    //   74: iload 7
    //   76: aload_3
    //   77: aload 4
    //   79: iconst_0
    //   80: invokeinterface 47 5 0
    //   85: pop
    //   86: aload 4
    //   88: invokevirtual 50	android/os/Parcel:readException	()V
    //   91: aload 4
    //   93: invokevirtual 53	android/os/Parcel:recycle	()V
    //   96: aload_3
    //   97: invokevirtual 53	android/os/Parcel:recycle	()V
    //   100: return
    //   101: iconst_0
    //   102: istore 6
    //   104: aconst_null
    //   105: astore 5
    //   107: goto -76 -> 31
    //   110: iconst_0
    //   111: istore 6
    //   113: aconst_null
    //   114: astore 5
    //   116: aload_3
    //   117: iconst_0
    //   118: invokevirtual 40	android/os/Parcel:writeInt	(I)V
    //   121: goto -59 -> 62
    //   124: astore 5
    //   126: aload 4
    //   128: invokevirtual 53	android/os/Parcel:recycle	()V
    //   131: aload_3
    //   132: invokevirtual 53	android/os/Parcel:recycle	()V
    //   135: aload 5
    //   137: athrow
    // Local variable table:
    //   start	length	slot	name	signature
    //   0	138	0	this	zza
    //   0	138	1	paramzzr	zzr
    //   0	138	2	paramValidateAccountRequest	ValidateAccountRequest
    //   3	129	3	localParcel1	Parcel
    //   7	120	4	localParcel2	Parcel
    //   11	104	5	localObject1	Object
    //   124	12	5	localObject2	Object
    //   42	70	6	i	int
    //   70	5	7	j	int
    // Exception table:
    //   from	to	target	type
    //   14	19	124	finally
    //   23	29	124	finally
    //   32	37	124	finally
    //   45	50	124	finally
    //   58	62	124	finally
    //   62	66	124	finally
    //   79	86	124	finally
    //   86	91	124	finally
    //   117	121	124	finally
  }
  
  /* Error */
  public void zzb(zzr paramzzr, int paramInt, String paramString)
  {
    // Byte code:
    //   0: invokestatic 20	android/os/Parcel:obtain	()Landroid/os/Parcel;
    //   3: astore 4
    //   5: invokestatic 20	android/os/Parcel:obtain	()Landroid/os/Parcel;
    //   8: astore 5
    //   10: ldc 22
    //   12: astore 6
    //   14: aload 4
    //   16: aload 6
    //   18: invokevirtual 26	android/os/Parcel:writeInterfaceToken	(Ljava/lang/String;)V
    //   21: aload_1
    //   22: ifnull +71 -> 93
    //   25: aload_1
    //   26: invokeinterface 32 1 0
    //   31: astore 6
    //   33: aload 4
    //   35: aload 6
    //   37: invokevirtual 36	android/os/Parcel:writeStrongBinder	(Landroid/os/IBinder;)V
    //   40: aload 4
    //   42: iload_2
    //   43: invokevirtual 40	android/os/Parcel:writeInt	(I)V
    //   46: aload 4
    //   48: aload_3
    //   49: invokevirtual 56	android/os/Parcel:writeString	(Ljava/lang/String;)V
    //   52: aload_0
    //   53: getfield 14	com/google/android/gms/common/internal/zzs$zza$zza:zzoz	Landroid/os/IBinder;
    //   56: astore 6
    //   58: bipush 21
    //   60: istore 7
    //   62: aload 6
    //   64: iload 7
    //   66: aload 4
    //   68: aload 5
    //   70: iconst_0
    //   71: invokeinterface 47 5 0
    //   76: pop
    //   77: aload 5
    //   79: invokevirtual 50	android/os/Parcel:readException	()V
    //   82: aload 5
    //   84: invokevirtual 53	android/os/Parcel:recycle	()V
    //   87: aload 4
    //   89: invokevirtual 53	android/os/Parcel:recycle	()V
    //   92: return
    //   93: aconst_null
    //   94: astore 6
    //   96: goto -63 -> 33
    //   99: astore 6
    //   101: aload 5
    //   103: invokevirtual 53	android/os/Parcel:recycle	()V
    //   106: aload 4
    //   108: invokevirtual 53	android/os/Parcel:recycle	()V
    //   111: aload 6
    //   113: athrow
    // Local variable table:
    //   start	length	slot	name	signature
    //   0	114	0	this	zza
    //   0	114	1	paramzzr	zzr
    //   0	114	2	paramInt	int
    //   0	114	3	paramString	String
    //   3	104	4	localParcel1	Parcel
    //   8	94	5	localParcel2	Parcel
    //   12	83	6	localObject1	Object
    //   99	13	6	localObject2	Object
    //   60	5	7	i	int
    // Exception table:
    //   from	to	target	type
    //   16	21	99	finally
    //   25	31	99	finally
    //   35	40	99	finally
    //   42	46	99	finally
    //   48	52	99	finally
    //   52	56	99	finally
    //   70	77	99	finally
    //   77	82	99	finally
  }
  
  /* Error */
  public void zzb(zzr paramzzr, int paramInt, String paramString, android.os.Bundle paramBundle)
  {
    // Byte code:
    //   0: invokestatic 20	android/os/Parcel:obtain	()Landroid/os/Parcel;
    //   3: astore 5
    //   5: invokestatic 20	android/os/Parcel:obtain	()Landroid/os/Parcel;
    //   8: astore 6
    //   10: ldc 22
    //   12: astore 7
    //   14: aload 5
    //   16: aload 7
    //   18: invokevirtual 26	android/os/Parcel:writeInterfaceToken	(Ljava/lang/String;)V
    //   21: aload_1
    //   22: ifnull +99 -> 121
    //   25: aload_1
    //   26: invokeinterface 32 1 0
    //   31: astore 7
    //   33: aload 5
    //   35: aload 7
    //   37: invokevirtual 36	android/os/Parcel:writeStrongBinder	(Landroid/os/IBinder;)V
    //   40: aload 5
    //   42: iload_2
    //   43: invokevirtual 40	android/os/Parcel:writeInt	(I)V
    //   46: aload 5
    //   48: aload_3
    //   49: invokevirtual 56	android/os/Parcel:writeString	(Ljava/lang/String;)V
    //   52: aload 4
    //   54: ifnull +76 -> 130
    //   57: iconst_1
    //   58: istore 8
    //   60: aload 5
    //   62: iload 8
    //   64: invokevirtual 40	android/os/Parcel:writeInt	(I)V
    //   67: iconst_0
    //   68: istore 8
    //   70: aconst_null
    //   71: astore 7
    //   73: aload 4
    //   75: aload 5
    //   77: iconst_0
    //   78: invokevirtual 64	android/os/Bundle:writeToParcel	(Landroid/os/Parcel;I)V
    //   81: aload_0
    //   82: getfield 14	com/google/android/gms/common/internal/zzs$zza$zza:zzoz	Landroid/os/IBinder;
    //   85: astore 7
    //   87: iconst_5
    //   88: istore 9
    //   90: aload 7
    //   92: iload 9
    //   94: aload 5
    //   96: aload 6
    //   98: iconst_0
    //   99: invokeinterface 47 5 0
    //   104: pop
    //   105: aload 6
    //   107: invokevirtual 50	android/os/Parcel:readException	()V
    //   110: aload 6
    //   112: invokevirtual 53	android/os/Parcel:recycle	()V
    //   115: aload 5
    //   117: invokevirtual 53	android/os/Parcel:recycle	()V
    //   120: return
    //   121: iconst_0
    //   122: istore 8
    //   124: aconst_null
    //   125: astore 7
    //   127: goto -94 -> 33
    //   130: iconst_0
    //   131: istore 8
    //   133: aconst_null
    //   134: astore 7
    //   136: aload 5
    //   138: iconst_0
    //   139: invokevirtual 40	android/os/Parcel:writeInt	(I)V
    //   142: goto -61 -> 81
    //   145: astore 7
    //   147: aload 6
    //   149: invokevirtual 53	android/os/Parcel:recycle	()V
    //   152: aload 5
    //   154: invokevirtual 53	android/os/Parcel:recycle	()V
    //   157: aload 7
    //   159: athrow
    // Local variable table:
    //   start	length	slot	name	signature
    //   0	160	0	this	zza
    //   0	160	1	paramzzr	zzr
    //   0	160	2	paramInt	int
    //   0	160	3	paramString	String
    //   0	160	4	paramBundle	android.os.Bundle
    //   3	150	5	localParcel1	Parcel
    //   8	140	6	localParcel2	Parcel
    //   12	123	7	localObject1	Object
    //   145	13	7	localObject2	Object
    //   58	74	8	i	int
    //   88	5	9	j	int
    // Exception table:
    //   from	to	target	type
    //   16	21	145	finally
    //   25	31	145	finally
    //   35	40	145	finally
    //   42	46	145	finally
    //   48	52	145	finally
    //   62	67	145	finally
    //   77	81	145	finally
    //   81	85	145	finally
    //   98	105	145	finally
    //   105	110	145	finally
    //   138	142	145	finally
  }
  
  /* Error */
  public void zzc(zzr paramzzr, int paramInt, String paramString)
  {
    // Byte code:
    //   0: invokestatic 20	android/os/Parcel:obtain	()Landroid/os/Parcel;
    //   3: astore 4
    //   5: invokestatic 20	android/os/Parcel:obtain	()Landroid/os/Parcel;
    //   8: astore 5
    //   10: ldc 22
    //   12: astore 6
    //   14: aload 4
    //   16: aload 6
    //   18: invokevirtual 26	android/os/Parcel:writeInterfaceToken	(Ljava/lang/String;)V
    //   21: aload_1
    //   22: ifnull +71 -> 93
    //   25: aload_1
    //   26: invokeinterface 32 1 0
    //   31: astore 6
    //   33: aload 4
    //   35: aload 6
    //   37: invokevirtual 36	android/os/Parcel:writeStrongBinder	(Landroid/os/IBinder;)V
    //   40: aload 4
    //   42: iload_2
    //   43: invokevirtual 40	android/os/Parcel:writeInt	(I)V
    //   46: aload 4
    //   48: aload_3
    //   49: invokevirtual 56	android/os/Parcel:writeString	(Ljava/lang/String;)V
    //   52: aload_0
    //   53: getfield 14	com/google/android/gms/common/internal/zzs$zza$zza:zzoz	Landroid/os/IBinder;
    //   56: astore 6
    //   58: bipush 22
    //   60: istore 7
    //   62: aload 6
    //   64: iload 7
    //   66: aload 4
    //   68: aload 5
    //   70: iconst_0
    //   71: invokeinterface 47 5 0
    //   76: pop
    //   77: aload 5
    //   79: invokevirtual 50	android/os/Parcel:readException	()V
    //   82: aload 5
    //   84: invokevirtual 53	android/os/Parcel:recycle	()V
    //   87: aload 4
    //   89: invokevirtual 53	android/os/Parcel:recycle	()V
    //   92: return
    //   93: aconst_null
    //   94: astore 6
    //   96: goto -63 -> 33
    //   99: astore 6
    //   101: aload 5
    //   103: invokevirtual 53	android/os/Parcel:recycle	()V
    //   106: aload 4
    //   108: invokevirtual 53	android/os/Parcel:recycle	()V
    //   111: aload 6
    //   113: athrow
    // Local variable table:
    //   start	length	slot	name	signature
    //   0	114	0	this	zza
    //   0	114	1	paramzzr	zzr
    //   0	114	2	paramInt	int
    //   0	114	3	paramString	String
    //   3	104	4	localParcel1	Parcel
    //   8	94	5	localParcel2	Parcel
    //   12	83	6	localObject1	Object
    //   99	13	6	localObject2	Object
    //   60	5	7	i	int
    // Exception table:
    //   from	to	target	type
    //   16	21	99	finally
    //   25	31	99	finally
    //   35	40	99	finally
    //   42	46	99	finally
    //   48	52	99	finally
    //   52	56	99	finally
    //   70	77	99	finally
    //   77	82	99	finally
  }
  
  /* Error */
  public void zzc(zzr paramzzr, int paramInt, String paramString, android.os.Bundle paramBundle)
  {
    // Byte code:
    //   0: invokestatic 20	android/os/Parcel:obtain	()Landroid/os/Parcel;
    //   3: astore 5
    //   5: invokestatic 20	android/os/Parcel:obtain	()Landroid/os/Parcel;
    //   8: astore 6
    //   10: ldc 22
    //   12: astore 7
    //   14: aload 5
    //   16: aload 7
    //   18: invokevirtual 26	android/os/Parcel:writeInterfaceToken	(Ljava/lang/String;)V
    //   21: aload_1
    //   22: ifnull +100 -> 122
    //   25: aload_1
    //   26: invokeinterface 32 1 0
    //   31: astore 7
    //   33: aload 5
    //   35: aload 7
    //   37: invokevirtual 36	android/os/Parcel:writeStrongBinder	(Landroid/os/IBinder;)V
    //   40: aload 5
    //   42: iload_2
    //   43: invokevirtual 40	android/os/Parcel:writeInt	(I)V
    //   46: aload 5
    //   48: aload_3
    //   49: invokevirtual 56	android/os/Parcel:writeString	(Ljava/lang/String;)V
    //   52: aload 4
    //   54: ifnull +77 -> 131
    //   57: iconst_1
    //   58: istore 8
    //   60: aload 5
    //   62: iload 8
    //   64: invokevirtual 40	android/os/Parcel:writeInt	(I)V
    //   67: iconst_0
    //   68: istore 8
    //   70: aconst_null
    //   71: astore 7
    //   73: aload 4
    //   75: aload 5
    //   77: iconst_0
    //   78: invokevirtual 64	android/os/Bundle:writeToParcel	(Landroid/os/Parcel;I)V
    //   81: aload_0
    //   82: getfield 14	com/google/android/gms/common/internal/zzs$zza$zza:zzoz	Landroid/os/IBinder;
    //   85: astore 7
    //   87: bipush 6
    //   89: istore 9
    //   91: aload 7
    //   93: iload 9
    //   95: aload 5
    //   97: aload 6
    //   99: iconst_0
    //   100: invokeinterface 47 5 0
    //   105: pop
    //   106: aload 6
    //   108: invokevirtual 50	android/os/Parcel:readException	()V
    //   111: aload 6
    //   113: invokevirtual 53	android/os/Parcel:recycle	()V
    //   116: aload 5
    //   118: invokevirtual 53	android/os/Parcel:recycle	()V
    //   121: return
    //   122: iconst_0
    //   123: istore 8
    //   125: aconst_null
    //   126: astore 7
    //   128: goto -95 -> 33
    //   131: iconst_0
    //   132: istore 8
    //   134: aconst_null
    //   135: astore 7
    //   137: aload 5
    //   139: iconst_0
    //   140: invokevirtual 40	android/os/Parcel:writeInt	(I)V
    //   143: goto -62 -> 81
    //   146: astore 7
    //   148: aload 6
    //   150: invokevirtual 53	android/os/Parcel:recycle	()V
    //   153: aload 5
    //   155: invokevirtual 53	android/os/Parcel:recycle	()V
    //   158: aload 7
    //   160: athrow
    // Local variable table:
    //   start	length	slot	name	signature
    //   0	161	0	this	zza
    //   0	161	1	paramzzr	zzr
    //   0	161	2	paramInt	int
    //   0	161	3	paramString	String
    //   0	161	4	paramBundle	android.os.Bundle
    //   3	151	5	localParcel1	Parcel
    //   8	141	6	localParcel2	Parcel
    //   12	124	7	localObject1	Object
    //   146	13	7	localObject2	Object
    //   58	75	8	i	int
    //   89	5	9	j	int
    // Exception table:
    //   from	to	target	type
    //   16	21	146	finally
    //   25	31	146	finally
    //   35	40	146	finally
    //   42	46	146	finally
    //   48	52	146	finally
    //   62	67	146	finally
    //   77	81	146	finally
    //   81	85	146	finally
    //   99	106	146	finally
    //   106	111	146	finally
    //   139	143	146	finally
  }
  
  /* Error */
  public void zzd(zzr paramzzr, int paramInt, String paramString)
  {
    // Byte code:
    //   0: invokestatic 20	android/os/Parcel:obtain	()Landroid/os/Parcel;
    //   3: astore 4
    //   5: invokestatic 20	android/os/Parcel:obtain	()Landroid/os/Parcel;
    //   8: astore 5
    //   10: ldc 22
    //   12: astore 6
    //   14: aload 4
    //   16: aload 6
    //   18: invokevirtual 26	android/os/Parcel:writeInterfaceToken	(Ljava/lang/String;)V
    //   21: aload_1
    //   22: ifnull +71 -> 93
    //   25: aload_1
    //   26: invokeinterface 32 1 0
    //   31: astore 6
    //   33: aload 4
    //   35: aload 6
    //   37: invokevirtual 36	android/os/Parcel:writeStrongBinder	(Landroid/os/IBinder;)V
    //   40: aload 4
    //   42: iload_2
    //   43: invokevirtual 40	android/os/Parcel:writeInt	(I)V
    //   46: aload 4
    //   48: aload_3
    //   49: invokevirtual 56	android/os/Parcel:writeString	(Ljava/lang/String;)V
    //   52: aload_0
    //   53: getfield 14	com/google/android/gms/common/internal/zzs$zza$zza:zzoz	Landroid/os/IBinder;
    //   56: astore 6
    //   58: bipush 24
    //   60: istore 7
    //   62: aload 6
    //   64: iload 7
    //   66: aload 4
    //   68: aload 5
    //   70: iconst_0
    //   71: invokeinterface 47 5 0
    //   76: pop
    //   77: aload 5
    //   79: invokevirtual 50	android/os/Parcel:readException	()V
    //   82: aload 5
    //   84: invokevirtual 53	android/os/Parcel:recycle	()V
    //   87: aload 4
    //   89: invokevirtual 53	android/os/Parcel:recycle	()V
    //   92: return
    //   93: aconst_null
    //   94: astore 6
    //   96: goto -63 -> 33
    //   99: astore 6
    //   101: aload 5
    //   103: invokevirtual 53	android/os/Parcel:recycle	()V
    //   106: aload 4
    //   108: invokevirtual 53	android/os/Parcel:recycle	()V
    //   111: aload 6
    //   113: athrow
    // Local variable table:
    //   start	length	slot	name	signature
    //   0	114	0	this	zza
    //   0	114	1	paramzzr	zzr
    //   0	114	2	paramInt	int
    //   0	114	3	paramString	String
    //   3	104	4	localParcel1	Parcel
    //   8	94	5	localParcel2	Parcel
    //   12	83	6	localObject1	Object
    //   99	13	6	localObject2	Object
    //   60	5	7	i	int
    // Exception table:
    //   from	to	target	type
    //   16	21	99	finally
    //   25	31	99	finally
    //   35	40	99	finally
    //   42	46	99	finally
    //   48	52	99	finally
    //   52	56	99	finally
    //   70	77	99	finally
    //   77	82	99	finally
  }
  
  /* Error */
  public void zzd(zzr paramzzr, int paramInt, String paramString, android.os.Bundle paramBundle)
  {
    // Byte code:
    //   0: invokestatic 20	android/os/Parcel:obtain	()Landroid/os/Parcel;
    //   3: astore 5
    //   5: invokestatic 20	android/os/Parcel:obtain	()Landroid/os/Parcel;
    //   8: astore 6
    //   10: ldc 22
    //   12: astore 7
    //   14: aload 5
    //   16: aload 7
    //   18: invokevirtual 26	android/os/Parcel:writeInterfaceToken	(Ljava/lang/String;)V
    //   21: aload_1
    //   22: ifnull +100 -> 122
    //   25: aload_1
    //   26: invokeinterface 32 1 0
    //   31: astore 7
    //   33: aload 5
    //   35: aload 7
    //   37: invokevirtual 36	android/os/Parcel:writeStrongBinder	(Landroid/os/IBinder;)V
    //   40: aload 5
    //   42: iload_2
    //   43: invokevirtual 40	android/os/Parcel:writeInt	(I)V
    //   46: aload 5
    //   48: aload_3
    //   49: invokevirtual 56	android/os/Parcel:writeString	(Ljava/lang/String;)V
    //   52: aload 4
    //   54: ifnull +77 -> 131
    //   57: iconst_1
    //   58: istore 8
    //   60: aload 5
    //   62: iload 8
    //   64: invokevirtual 40	android/os/Parcel:writeInt	(I)V
    //   67: iconst_0
    //   68: istore 8
    //   70: aconst_null
    //   71: astore 7
    //   73: aload 4
    //   75: aload 5
    //   77: iconst_0
    //   78: invokevirtual 64	android/os/Bundle:writeToParcel	(Landroid/os/Parcel;I)V
    //   81: aload_0
    //   82: getfield 14	com/google/android/gms/common/internal/zzs$zza$zza:zzoz	Landroid/os/IBinder;
    //   85: astore 7
    //   87: bipush 7
    //   89: istore 9
    //   91: aload 7
    //   93: iload 9
    //   95: aload 5
    //   97: aload 6
    //   99: iconst_0
    //   100: invokeinterface 47 5 0
    //   105: pop
    //   106: aload 6
    //   108: invokevirtual 50	android/os/Parcel:readException	()V
    //   111: aload 6
    //   113: invokevirtual 53	android/os/Parcel:recycle	()V
    //   116: aload 5
    //   118: invokevirtual 53	android/os/Parcel:recycle	()V
    //   121: return
    //   122: iconst_0
    //   123: istore 8
    //   125: aconst_null
    //   126: astore 7
    //   128: goto -95 -> 33
    //   131: iconst_0
    //   132: istore 8
    //   134: aconst_null
    //   135: astore 7
    //   137: aload 5
    //   139: iconst_0
    //   140: invokevirtual 40	android/os/Parcel:writeInt	(I)V
    //   143: goto -62 -> 81
    //   146: astore 7
    //   148: aload 6
    //   150: invokevirtual 53	android/os/Parcel:recycle	()V
    //   153: aload 5
    //   155: invokevirtual 53	android/os/Parcel:recycle	()V
    //   158: aload 7
    //   160: athrow
    // Local variable table:
    //   start	length	slot	name	signature
    //   0	161	0	this	zza
    //   0	161	1	paramzzr	zzr
    //   0	161	2	paramInt	int
    //   0	161	3	paramString	String
    //   0	161	4	paramBundle	android.os.Bundle
    //   3	151	5	localParcel1	Parcel
    //   8	141	6	localParcel2	Parcel
    //   12	124	7	localObject1	Object
    //   146	13	7	localObject2	Object
    //   58	75	8	i	int
    //   89	5	9	j	int
    // Exception table:
    //   from	to	target	type
    //   16	21	146	finally
    //   25	31	146	finally
    //   35	40	146	finally
    //   42	46	146	finally
    //   48	52	146	finally
    //   62	67	146	finally
    //   77	81	146	finally
    //   81	85	146	finally
    //   99	106	146	finally
    //   106	111	146	finally
    //   139	143	146	finally
  }
  
  /* Error */
  public void zze(zzr paramzzr, int paramInt, String paramString)
  {
    // Byte code:
    //   0: invokestatic 20	android/os/Parcel:obtain	()Landroid/os/Parcel;
    //   3: astore 4
    //   5: invokestatic 20	android/os/Parcel:obtain	()Landroid/os/Parcel;
    //   8: astore 5
    //   10: ldc 22
    //   12: astore 6
    //   14: aload 4
    //   16: aload 6
    //   18: invokevirtual 26	android/os/Parcel:writeInterfaceToken	(Ljava/lang/String;)V
    //   21: aload_1
    //   22: ifnull +71 -> 93
    //   25: aload_1
    //   26: invokeinterface 32 1 0
    //   31: astore 6
    //   33: aload 4
    //   35: aload 6
    //   37: invokevirtual 36	android/os/Parcel:writeStrongBinder	(Landroid/os/IBinder;)V
    //   40: aload 4
    //   42: iload_2
    //   43: invokevirtual 40	android/os/Parcel:writeInt	(I)V
    //   46: aload 4
    //   48: aload_3
    //   49: invokevirtual 56	android/os/Parcel:writeString	(Ljava/lang/String;)V
    //   52: aload_0
    //   53: getfield 14	com/google/android/gms/common/internal/zzs$zza$zza:zzoz	Landroid/os/IBinder;
    //   56: astore 6
    //   58: bipush 26
    //   60: istore 7
    //   62: aload 6
    //   64: iload 7
    //   66: aload 4
    //   68: aload 5
    //   70: iconst_0
    //   71: invokeinterface 47 5 0
    //   76: pop
    //   77: aload 5
    //   79: invokevirtual 50	android/os/Parcel:readException	()V
    //   82: aload 5
    //   84: invokevirtual 53	android/os/Parcel:recycle	()V
    //   87: aload 4
    //   89: invokevirtual 53	android/os/Parcel:recycle	()V
    //   92: return
    //   93: aconst_null
    //   94: astore 6
    //   96: goto -63 -> 33
    //   99: astore 6
    //   101: aload 5
    //   103: invokevirtual 53	android/os/Parcel:recycle	()V
    //   106: aload 4
    //   108: invokevirtual 53	android/os/Parcel:recycle	()V
    //   111: aload 6
    //   113: athrow
    // Local variable table:
    //   start	length	slot	name	signature
    //   0	114	0	this	zza
    //   0	114	1	paramzzr	zzr
    //   0	114	2	paramInt	int
    //   0	114	3	paramString	String
    //   3	104	4	localParcel1	Parcel
    //   8	94	5	localParcel2	Parcel
    //   12	83	6	localObject1	Object
    //   99	13	6	localObject2	Object
    //   60	5	7	i	int
    // Exception table:
    //   from	to	target	type
    //   16	21	99	finally
    //   25	31	99	finally
    //   35	40	99	finally
    //   42	46	99	finally
    //   48	52	99	finally
    //   52	56	99	finally
    //   70	77	99	finally
    //   77	82	99	finally
  }
  
  /* Error */
  public void zze(zzr paramzzr, int paramInt, String paramString, android.os.Bundle paramBundle)
  {
    // Byte code:
    //   0: invokestatic 20	android/os/Parcel:obtain	()Landroid/os/Parcel;
    //   3: astore 5
    //   5: invokestatic 20	android/os/Parcel:obtain	()Landroid/os/Parcel;
    //   8: astore 6
    //   10: ldc 22
    //   12: astore 7
    //   14: aload 5
    //   16: aload 7
    //   18: invokevirtual 26	android/os/Parcel:writeInterfaceToken	(Ljava/lang/String;)V
    //   21: aload_1
    //   22: ifnull +100 -> 122
    //   25: aload_1
    //   26: invokeinterface 32 1 0
    //   31: astore 7
    //   33: aload 5
    //   35: aload 7
    //   37: invokevirtual 36	android/os/Parcel:writeStrongBinder	(Landroid/os/IBinder;)V
    //   40: aload 5
    //   42: iload_2
    //   43: invokevirtual 40	android/os/Parcel:writeInt	(I)V
    //   46: aload 5
    //   48: aload_3
    //   49: invokevirtual 56	android/os/Parcel:writeString	(Ljava/lang/String;)V
    //   52: aload 4
    //   54: ifnull +77 -> 131
    //   57: iconst_1
    //   58: istore 8
    //   60: aload 5
    //   62: iload 8
    //   64: invokevirtual 40	android/os/Parcel:writeInt	(I)V
    //   67: iconst_0
    //   68: istore 8
    //   70: aconst_null
    //   71: astore 7
    //   73: aload 4
    //   75: aload 5
    //   77: iconst_0
    //   78: invokevirtual 64	android/os/Bundle:writeToParcel	(Landroid/os/Parcel;I)V
    //   81: aload_0
    //   82: getfield 14	com/google/android/gms/common/internal/zzs$zza$zza:zzoz	Landroid/os/IBinder;
    //   85: astore 7
    //   87: bipush 8
    //   89: istore 9
    //   91: aload 7
    //   93: iload 9
    //   95: aload 5
    //   97: aload 6
    //   99: iconst_0
    //   100: invokeinterface 47 5 0
    //   105: pop
    //   106: aload 6
    //   108: invokevirtual 50	android/os/Parcel:readException	()V
    //   111: aload 6
    //   113: invokevirtual 53	android/os/Parcel:recycle	()V
    //   116: aload 5
    //   118: invokevirtual 53	android/os/Parcel:recycle	()V
    //   121: return
    //   122: iconst_0
    //   123: istore 8
    //   125: aconst_null
    //   126: astore 7
    //   128: goto -95 -> 33
    //   131: iconst_0
    //   132: istore 8
    //   134: aconst_null
    //   135: astore 7
    //   137: aload 5
    //   139: iconst_0
    //   140: invokevirtual 40	android/os/Parcel:writeInt	(I)V
    //   143: goto -62 -> 81
    //   146: astore 7
    //   148: aload 6
    //   150: invokevirtual 53	android/os/Parcel:recycle	()V
    //   153: aload 5
    //   155: invokevirtual 53	android/os/Parcel:recycle	()V
    //   158: aload 7
    //   160: athrow
    // Local variable table:
    //   start	length	slot	name	signature
    //   0	161	0	this	zza
    //   0	161	1	paramzzr	zzr
    //   0	161	2	paramInt	int
    //   0	161	3	paramString	String
    //   0	161	4	paramBundle	android.os.Bundle
    //   3	151	5	localParcel1	Parcel
    //   8	141	6	localParcel2	Parcel
    //   12	124	7	localObject1	Object
    //   146	13	7	localObject2	Object
    //   58	75	8	i	int
    //   89	5	9	j	int
    // Exception table:
    //   from	to	target	type
    //   16	21	146	finally
    //   25	31	146	finally
    //   35	40	146	finally
    //   42	46	146	finally
    //   48	52	146	finally
    //   62	67	146	finally
    //   77	81	146	finally
    //   81	85	146	finally
    //   99	106	146	finally
    //   106	111	146	finally
    //   139	143	146	finally
  }
  
  /* Error */
  public void zzf(zzr paramzzr, int paramInt, String paramString)
  {
    // Byte code:
    //   0: invokestatic 20	android/os/Parcel:obtain	()Landroid/os/Parcel;
    //   3: astore 4
    //   5: invokestatic 20	android/os/Parcel:obtain	()Landroid/os/Parcel;
    //   8: astore 5
    //   10: ldc 22
    //   12: astore 6
    //   14: aload 4
    //   16: aload 6
    //   18: invokevirtual 26	android/os/Parcel:writeInterfaceToken	(Ljava/lang/String;)V
    //   21: aload_1
    //   22: ifnull +71 -> 93
    //   25: aload_1
    //   26: invokeinterface 32 1 0
    //   31: astore 6
    //   33: aload 4
    //   35: aload 6
    //   37: invokevirtual 36	android/os/Parcel:writeStrongBinder	(Landroid/os/IBinder;)V
    //   40: aload 4
    //   42: iload_2
    //   43: invokevirtual 40	android/os/Parcel:writeInt	(I)V
    //   46: aload 4
    //   48: aload_3
    //   49: invokevirtual 56	android/os/Parcel:writeString	(Ljava/lang/String;)V
    //   52: aload_0
    //   53: getfield 14	com/google/android/gms/common/internal/zzs$zza$zza:zzoz	Landroid/os/IBinder;
    //   56: astore 6
    //   58: bipush 31
    //   60: istore 7
    //   62: aload 6
    //   64: iload 7
    //   66: aload 4
    //   68: aload 5
    //   70: iconst_0
    //   71: invokeinterface 47 5 0
    //   76: pop
    //   77: aload 5
    //   79: invokevirtual 50	android/os/Parcel:readException	()V
    //   82: aload 5
    //   84: invokevirtual 53	android/os/Parcel:recycle	()V
    //   87: aload 4
    //   89: invokevirtual 53	android/os/Parcel:recycle	()V
    //   92: return
    //   93: aconst_null
    //   94: astore 6
    //   96: goto -63 -> 33
    //   99: astore 6
    //   101: aload 5
    //   103: invokevirtual 53	android/os/Parcel:recycle	()V
    //   106: aload 4
    //   108: invokevirtual 53	android/os/Parcel:recycle	()V
    //   111: aload 6
    //   113: athrow
    // Local variable table:
    //   start	length	slot	name	signature
    //   0	114	0	this	zza
    //   0	114	1	paramzzr	zzr
    //   0	114	2	paramInt	int
    //   0	114	3	paramString	String
    //   3	104	4	localParcel1	Parcel
    //   8	94	5	localParcel2	Parcel
    //   12	83	6	localObject1	Object
    //   99	13	6	localObject2	Object
    //   60	5	7	i	int
    // Exception table:
    //   from	to	target	type
    //   16	21	99	finally
    //   25	31	99	finally
    //   35	40	99	finally
    //   42	46	99	finally
    //   48	52	99	finally
    //   52	56	99	finally
    //   70	77	99	finally
    //   77	82	99	finally
  }
  
  /* Error */
  public void zzf(zzr paramzzr, int paramInt, String paramString, android.os.Bundle paramBundle)
  {
    // Byte code:
    //   0: invokestatic 20	android/os/Parcel:obtain	()Landroid/os/Parcel;
    //   3: astore 5
    //   5: invokestatic 20	android/os/Parcel:obtain	()Landroid/os/Parcel;
    //   8: astore 6
    //   10: ldc 22
    //   12: astore 7
    //   14: aload 5
    //   16: aload 7
    //   18: invokevirtual 26	android/os/Parcel:writeInterfaceToken	(Ljava/lang/String;)V
    //   21: aload_1
    //   22: ifnull +100 -> 122
    //   25: aload_1
    //   26: invokeinterface 32 1 0
    //   31: astore 7
    //   33: aload 5
    //   35: aload 7
    //   37: invokevirtual 36	android/os/Parcel:writeStrongBinder	(Landroid/os/IBinder;)V
    //   40: aload 5
    //   42: iload_2
    //   43: invokevirtual 40	android/os/Parcel:writeInt	(I)V
    //   46: aload 5
    //   48: aload_3
    //   49: invokevirtual 56	android/os/Parcel:writeString	(Ljava/lang/String;)V
    //   52: aload 4
    //   54: ifnull +77 -> 131
    //   57: iconst_1
    //   58: istore 8
    //   60: aload 5
    //   62: iload 8
    //   64: invokevirtual 40	android/os/Parcel:writeInt	(I)V
    //   67: iconst_0
    //   68: istore 8
    //   70: aconst_null
    //   71: astore 7
    //   73: aload 4
    //   75: aload 5
    //   77: iconst_0
    //   78: invokevirtual 64	android/os/Bundle:writeToParcel	(Landroid/os/Parcel;I)V
    //   81: aload_0
    //   82: getfield 14	com/google/android/gms/common/internal/zzs$zza$zza:zzoz	Landroid/os/IBinder;
    //   85: astore 7
    //   87: bipush 11
    //   89: istore 9
    //   91: aload 7
    //   93: iload 9
    //   95: aload 5
    //   97: aload 6
    //   99: iconst_0
    //   100: invokeinterface 47 5 0
    //   105: pop
    //   106: aload 6
    //   108: invokevirtual 50	android/os/Parcel:readException	()V
    //   111: aload 6
    //   113: invokevirtual 53	android/os/Parcel:recycle	()V
    //   116: aload 5
    //   118: invokevirtual 53	android/os/Parcel:recycle	()V
    //   121: return
    //   122: iconst_0
    //   123: istore 8
    //   125: aconst_null
    //   126: astore 7
    //   128: goto -95 -> 33
    //   131: iconst_0
    //   132: istore 8
    //   134: aconst_null
    //   135: astore 7
    //   137: aload 5
    //   139: iconst_0
    //   140: invokevirtual 40	android/os/Parcel:writeInt	(I)V
    //   143: goto -62 -> 81
    //   146: astore 7
    //   148: aload 6
    //   150: invokevirtual 53	android/os/Parcel:recycle	()V
    //   153: aload 5
    //   155: invokevirtual 53	android/os/Parcel:recycle	()V
    //   158: aload 7
    //   160: athrow
    // Local variable table:
    //   start	length	slot	name	signature
    //   0	161	0	this	zza
    //   0	161	1	paramzzr	zzr
    //   0	161	2	paramInt	int
    //   0	161	3	paramString	String
    //   0	161	4	paramBundle	android.os.Bundle
    //   3	151	5	localParcel1	Parcel
    //   8	141	6	localParcel2	Parcel
    //   12	124	7	localObject1	Object
    //   146	13	7	localObject2	Object
    //   58	75	8	i	int
    //   89	5	9	j	int
    // Exception table:
    //   from	to	target	type
    //   16	21	146	finally
    //   25	31	146	finally
    //   35	40	146	finally
    //   42	46	146	finally
    //   48	52	146	finally
    //   62	67	146	finally
    //   77	81	146	finally
    //   81	85	146	finally
    //   99	106	146	finally
    //   106	111	146	finally
    //   139	143	146	finally
  }
  
  /* Error */
  public void zzg(zzr paramzzr, int paramInt, String paramString)
  {
    // Byte code:
    //   0: invokestatic 20	android/os/Parcel:obtain	()Landroid/os/Parcel;
    //   3: astore 4
    //   5: invokestatic 20	android/os/Parcel:obtain	()Landroid/os/Parcel;
    //   8: astore 5
    //   10: ldc 22
    //   12: astore 6
    //   14: aload 4
    //   16: aload 6
    //   18: invokevirtual 26	android/os/Parcel:writeInterfaceToken	(Ljava/lang/String;)V
    //   21: aload_1
    //   22: ifnull +71 -> 93
    //   25: aload_1
    //   26: invokeinterface 32 1 0
    //   31: astore 6
    //   33: aload 4
    //   35: aload 6
    //   37: invokevirtual 36	android/os/Parcel:writeStrongBinder	(Landroid/os/IBinder;)V
    //   40: aload 4
    //   42: iload_2
    //   43: invokevirtual 40	android/os/Parcel:writeInt	(I)V
    //   46: aload 4
    //   48: aload_3
    //   49: invokevirtual 56	android/os/Parcel:writeString	(Ljava/lang/String;)V
    //   52: aload_0
    //   53: getfield 14	com/google/android/gms/common/internal/zzs$zza$zza:zzoz	Landroid/os/IBinder;
    //   56: astore 6
    //   58: bipush 32
    //   60: istore 7
    //   62: aload 6
    //   64: iload 7
    //   66: aload 4
    //   68: aload 5
    //   70: iconst_0
    //   71: invokeinterface 47 5 0
    //   76: pop
    //   77: aload 5
    //   79: invokevirtual 50	android/os/Parcel:readException	()V
    //   82: aload 5
    //   84: invokevirtual 53	android/os/Parcel:recycle	()V
    //   87: aload 4
    //   89: invokevirtual 53	android/os/Parcel:recycle	()V
    //   92: return
    //   93: aconst_null
    //   94: astore 6
    //   96: goto -63 -> 33
    //   99: astore 6
    //   101: aload 5
    //   103: invokevirtual 53	android/os/Parcel:recycle	()V
    //   106: aload 4
    //   108: invokevirtual 53	android/os/Parcel:recycle	()V
    //   111: aload 6
    //   113: athrow
    // Local variable table:
    //   start	length	slot	name	signature
    //   0	114	0	this	zza
    //   0	114	1	paramzzr	zzr
    //   0	114	2	paramInt	int
    //   0	114	3	paramString	String
    //   3	104	4	localParcel1	Parcel
    //   8	94	5	localParcel2	Parcel
    //   12	83	6	localObject1	Object
    //   99	13	6	localObject2	Object
    //   60	5	7	i	int
    // Exception table:
    //   from	to	target	type
    //   16	21	99	finally
    //   25	31	99	finally
    //   35	40	99	finally
    //   42	46	99	finally
    //   48	52	99	finally
    //   52	56	99	finally
    //   70	77	99	finally
    //   77	82	99	finally
  }
  
  /* Error */
  public void zzg(zzr paramzzr, int paramInt, String paramString, android.os.Bundle paramBundle)
  {
    // Byte code:
    //   0: invokestatic 20	android/os/Parcel:obtain	()Landroid/os/Parcel;
    //   3: astore 5
    //   5: invokestatic 20	android/os/Parcel:obtain	()Landroid/os/Parcel;
    //   8: astore 6
    //   10: ldc 22
    //   12: astore 7
    //   14: aload 5
    //   16: aload 7
    //   18: invokevirtual 26	android/os/Parcel:writeInterfaceToken	(Ljava/lang/String;)V
    //   21: aload_1
    //   22: ifnull +100 -> 122
    //   25: aload_1
    //   26: invokeinterface 32 1 0
    //   31: astore 7
    //   33: aload 5
    //   35: aload 7
    //   37: invokevirtual 36	android/os/Parcel:writeStrongBinder	(Landroid/os/IBinder;)V
    //   40: aload 5
    //   42: iload_2
    //   43: invokevirtual 40	android/os/Parcel:writeInt	(I)V
    //   46: aload 5
    //   48: aload_3
    //   49: invokevirtual 56	android/os/Parcel:writeString	(Ljava/lang/String;)V
    //   52: aload 4
    //   54: ifnull +77 -> 131
    //   57: iconst_1
    //   58: istore 8
    //   60: aload 5
    //   62: iload 8
    //   64: invokevirtual 40	android/os/Parcel:writeInt	(I)V
    //   67: iconst_0
    //   68: istore 8
    //   70: aconst_null
    //   71: astore 7
    //   73: aload 4
    //   75: aload 5
    //   77: iconst_0
    //   78: invokevirtual 64	android/os/Bundle:writeToParcel	(Landroid/os/Parcel;I)V
    //   81: aload_0
    //   82: getfield 14	com/google/android/gms/common/internal/zzs$zza$zza:zzoz	Landroid/os/IBinder;
    //   85: astore 7
    //   87: bipush 12
    //   89: istore 9
    //   91: aload 7
    //   93: iload 9
    //   95: aload 5
    //   97: aload 6
    //   99: iconst_0
    //   100: invokeinterface 47 5 0
    //   105: pop
    //   106: aload 6
    //   108: invokevirtual 50	android/os/Parcel:readException	()V
    //   111: aload 6
    //   113: invokevirtual 53	android/os/Parcel:recycle	()V
    //   116: aload 5
    //   118: invokevirtual 53	android/os/Parcel:recycle	()V
    //   121: return
    //   122: iconst_0
    //   123: istore 8
    //   125: aconst_null
    //   126: astore 7
    //   128: goto -95 -> 33
    //   131: iconst_0
    //   132: istore 8
    //   134: aconst_null
    //   135: astore 7
    //   137: aload 5
    //   139: iconst_0
    //   140: invokevirtual 40	android/os/Parcel:writeInt	(I)V
    //   143: goto -62 -> 81
    //   146: astore 7
    //   148: aload 6
    //   150: invokevirtual 53	android/os/Parcel:recycle	()V
    //   153: aload 5
    //   155: invokevirtual 53	android/os/Parcel:recycle	()V
    //   158: aload 7
    //   160: athrow
    // Local variable table:
    //   start	length	slot	name	signature
    //   0	161	0	this	zza
    //   0	161	1	paramzzr	zzr
    //   0	161	2	paramInt	int
    //   0	161	3	paramString	String
    //   0	161	4	paramBundle	android.os.Bundle
    //   3	151	5	localParcel1	Parcel
    //   8	141	6	localParcel2	Parcel
    //   12	124	7	localObject1	Object
    //   146	13	7	localObject2	Object
    //   58	75	8	i	int
    //   89	5	9	j	int
    // Exception table:
    //   from	to	target	type
    //   16	21	146	finally
    //   25	31	146	finally
    //   35	40	146	finally
    //   42	46	146	finally
    //   48	52	146	finally
    //   62	67	146	finally
    //   77	81	146	finally
    //   81	85	146	finally
    //   99	106	146	finally
    //   106	111	146	finally
    //   139	143	146	finally
  }
  
  /* Error */
  public void zzh(zzr paramzzr, int paramInt, String paramString)
  {
    // Byte code:
    //   0: invokestatic 20	android/os/Parcel:obtain	()Landroid/os/Parcel;
    //   3: astore 4
    //   5: invokestatic 20	android/os/Parcel:obtain	()Landroid/os/Parcel;
    //   8: astore 5
    //   10: ldc 22
    //   12: astore 6
    //   14: aload 4
    //   16: aload 6
    //   18: invokevirtual 26	android/os/Parcel:writeInterfaceToken	(Ljava/lang/String;)V
    //   21: aload_1
    //   22: ifnull +71 -> 93
    //   25: aload_1
    //   26: invokeinterface 32 1 0
    //   31: astore 6
    //   33: aload 4
    //   35: aload 6
    //   37: invokevirtual 36	android/os/Parcel:writeStrongBinder	(Landroid/os/IBinder;)V
    //   40: aload 4
    //   42: iload_2
    //   43: invokevirtual 40	android/os/Parcel:writeInt	(I)V
    //   46: aload 4
    //   48: aload_3
    //   49: invokevirtual 56	android/os/Parcel:writeString	(Ljava/lang/String;)V
    //   52: aload_0
    //   53: getfield 14	com/google/android/gms/common/internal/zzs$zza$zza:zzoz	Landroid/os/IBinder;
    //   56: astore 6
    //   58: bipush 35
    //   60: istore 7
    //   62: aload 6
    //   64: iload 7
    //   66: aload 4
    //   68: aload 5
    //   70: iconst_0
    //   71: invokeinterface 47 5 0
    //   76: pop
    //   77: aload 5
    //   79: invokevirtual 50	android/os/Parcel:readException	()V
    //   82: aload 5
    //   84: invokevirtual 53	android/os/Parcel:recycle	()V
    //   87: aload 4
    //   89: invokevirtual 53	android/os/Parcel:recycle	()V
    //   92: return
    //   93: aconst_null
    //   94: astore 6
    //   96: goto -63 -> 33
    //   99: astore 6
    //   101: aload 5
    //   103: invokevirtual 53	android/os/Parcel:recycle	()V
    //   106: aload 4
    //   108: invokevirtual 53	android/os/Parcel:recycle	()V
    //   111: aload 6
    //   113: athrow
    // Local variable table:
    //   start	length	slot	name	signature
    //   0	114	0	this	zza
    //   0	114	1	paramzzr	zzr
    //   0	114	2	paramInt	int
    //   0	114	3	paramString	String
    //   3	104	4	localParcel1	Parcel
    //   8	94	5	localParcel2	Parcel
    //   12	83	6	localObject1	Object
    //   99	13	6	localObject2	Object
    //   60	5	7	i	int
    // Exception table:
    //   from	to	target	type
    //   16	21	99	finally
    //   25	31	99	finally
    //   35	40	99	finally
    //   42	46	99	finally
    //   48	52	99	finally
    //   52	56	99	finally
    //   70	77	99	finally
    //   77	82	99	finally
  }
  
  /* Error */
  public void zzh(zzr paramzzr, int paramInt, String paramString, android.os.Bundle paramBundle)
  {
    // Byte code:
    //   0: invokestatic 20	android/os/Parcel:obtain	()Landroid/os/Parcel;
    //   3: astore 5
    //   5: invokestatic 20	android/os/Parcel:obtain	()Landroid/os/Parcel;
    //   8: astore 6
    //   10: ldc 22
    //   12: astore 7
    //   14: aload 5
    //   16: aload 7
    //   18: invokevirtual 26	android/os/Parcel:writeInterfaceToken	(Ljava/lang/String;)V
    //   21: aload_1
    //   22: ifnull +100 -> 122
    //   25: aload_1
    //   26: invokeinterface 32 1 0
    //   31: astore 7
    //   33: aload 5
    //   35: aload 7
    //   37: invokevirtual 36	android/os/Parcel:writeStrongBinder	(Landroid/os/IBinder;)V
    //   40: aload 5
    //   42: iload_2
    //   43: invokevirtual 40	android/os/Parcel:writeInt	(I)V
    //   46: aload 5
    //   48: aload_3
    //   49: invokevirtual 56	android/os/Parcel:writeString	(Ljava/lang/String;)V
    //   52: aload 4
    //   54: ifnull +77 -> 131
    //   57: iconst_1
    //   58: istore 8
    //   60: aload 5
    //   62: iload 8
    //   64: invokevirtual 40	android/os/Parcel:writeInt	(I)V
    //   67: iconst_0
    //   68: istore 8
    //   70: aconst_null
    //   71: astore 7
    //   73: aload 4
    //   75: aload 5
    //   77: iconst_0
    //   78: invokevirtual 64	android/os/Bundle:writeToParcel	(Landroid/os/Parcel;I)V
    //   81: aload_0
    //   82: getfield 14	com/google/android/gms/common/internal/zzs$zza$zza:zzoz	Landroid/os/IBinder;
    //   85: astore 7
    //   87: bipush 13
    //   89: istore 9
    //   91: aload 7
    //   93: iload 9
    //   95: aload 5
    //   97: aload 6
    //   99: iconst_0
    //   100: invokeinterface 47 5 0
    //   105: pop
    //   106: aload 6
    //   108: invokevirtual 50	android/os/Parcel:readException	()V
    //   111: aload 6
    //   113: invokevirtual 53	android/os/Parcel:recycle	()V
    //   116: aload 5
    //   118: invokevirtual 53	android/os/Parcel:recycle	()V
    //   121: return
    //   122: iconst_0
    //   123: istore 8
    //   125: aconst_null
    //   126: astore 7
    //   128: goto -95 -> 33
    //   131: iconst_0
    //   132: istore 8
    //   134: aconst_null
    //   135: astore 7
    //   137: aload 5
    //   139: iconst_0
    //   140: invokevirtual 40	android/os/Parcel:writeInt	(I)V
    //   143: goto -62 -> 81
    //   146: astore 7
    //   148: aload 6
    //   150: invokevirtual 53	android/os/Parcel:recycle	()V
    //   153: aload 5
    //   155: invokevirtual 53	android/os/Parcel:recycle	()V
    //   158: aload 7
    //   160: athrow
    // Local variable table:
    //   start	length	slot	name	signature
    //   0	161	0	this	zza
    //   0	161	1	paramzzr	zzr
    //   0	161	2	paramInt	int
    //   0	161	3	paramString	String
    //   0	161	4	paramBundle	android.os.Bundle
    //   3	151	5	localParcel1	Parcel
    //   8	141	6	localParcel2	Parcel
    //   12	124	7	localObject1	Object
    //   146	13	7	localObject2	Object
    //   58	75	8	i	int
    //   89	5	9	j	int
    // Exception table:
    //   from	to	target	type
    //   16	21	146	finally
    //   25	31	146	finally
    //   35	40	146	finally
    //   42	46	146	finally
    //   48	52	146	finally
    //   62	67	146	finally
    //   77	81	146	finally
    //   81	85	146	finally
    //   99	106	146	finally
    //   106	111	146	finally
    //   139	143	146	finally
  }
  
  /* Error */
  public void zzi(zzr paramzzr, int paramInt, String paramString)
  {
    // Byte code:
    //   0: invokestatic 20	android/os/Parcel:obtain	()Landroid/os/Parcel;
    //   3: astore 4
    //   5: invokestatic 20	android/os/Parcel:obtain	()Landroid/os/Parcel;
    //   8: astore 5
    //   10: ldc 22
    //   12: astore 6
    //   14: aload 4
    //   16: aload 6
    //   18: invokevirtual 26	android/os/Parcel:writeInterfaceToken	(Ljava/lang/String;)V
    //   21: aload_1
    //   22: ifnull +71 -> 93
    //   25: aload_1
    //   26: invokeinterface 32 1 0
    //   31: astore 6
    //   33: aload 4
    //   35: aload 6
    //   37: invokevirtual 36	android/os/Parcel:writeStrongBinder	(Landroid/os/IBinder;)V
    //   40: aload 4
    //   42: iload_2
    //   43: invokevirtual 40	android/os/Parcel:writeInt	(I)V
    //   46: aload 4
    //   48: aload_3
    //   49: invokevirtual 56	android/os/Parcel:writeString	(Ljava/lang/String;)V
    //   52: aload_0
    //   53: getfield 14	com/google/android/gms/common/internal/zzs$zza$zza:zzoz	Landroid/os/IBinder;
    //   56: astore 6
    //   58: bipush 36
    //   60: istore 7
    //   62: aload 6
    //   64: iload 7
    //   66: aload 4
    //   68: aload 5
    //   70: iconst_0
    //   71: invokeinterface 47 5 0
    //   76: pop
    //   77: aload 5
    //   79: invokevirtual 50	android/os/Parcel:readException	()V
    //   82: aload 5
    //   84: invokevirtual 53	android/os/Parcel:recycle	()V
    //   87: aload 4
    //   89: invokevirtual 53	android/os/Parcel:recycle	()V
    //   92: return
    //   93: aconst_null
    //   94: astore 6
    //   96: goto -63 -> 33
    //   99: astore 6
    //   101: aload 5
    //   103: invokevirtual 53	android/os/Parcel:recycle	()V
    //   106: aload 4
    //   108: invokevirtual 53	android/os/Parcel:recycle	()V
    //   111: aload 6
    //   113: athrow
    // Local variable table:
    //   start	length	slot	name	signature
    //   0	114	0	this	zza
    //   0	114	1	paramzzr	zzr
    //   0	114	2	paramInt	int
    //   0	114	3	paramString	String
    //   3	104	4	localParcel1	Parcel
    //   8	94	5	localParcel2	Parcel
    //   12	83	6	localObject1	Object
    //   99	13	6	localObject2	Object
    //   60	5	7	i	int
    // Exception table:
    //   from	to	target	type
    //   16	21	99	finally
    //   25	31	99	finally
    //   35	40	99	finally
    //   42	46	99	finally
    //   48	52	99	finally
    //   52	56	99	finally
    //   70	77	99	finally
    //   77	82	99	finally
  }
  
  /* Error */
  public void zzi(zzr paramzzr, int paramInt, String paramString, android.os.Bundle paramBundle)
  {
    // Byte code:
    //   0: invokestatic 20	android/os/Parcel:obtain	()Landroid/os/Parcel;
    //   3: astore 5
    //   5: invokestatic 20	android/os/Parcel:obtain	()Landroid/os/Parcel;
    //   8: astore 6
    //   10: ldc 22
    //   12: astore 7
    //   14: aload 5
    //   16: aload 7
    //   18: invokevirtual 26	android/os/Parcel:writeInterfaceToken	(Ljava/lang/String;)V
    //   21: aload_1
    //   22: ifnull +100 -> 122
    //   25: aload_1
    //   26: invokeinterface 32 1 0
    //   31: astore 7
    //   33: aload 5
    //   35: aload 7
    //   37: invokevirtual 36	android/os/Parcel:writeStrongBinder	(Landroid/os/IBinder;)V
    //   40: aload 5
    //   42: iload_2
    //   43: invokevirtual 40	android/os/Parcel:writeInt	(I)V
    //   46: aload 5
    //   48: aload_3
    //   49: invokevirtual 56	android/os/Parcel:writeString	(Ljava/lang/String;)V
    //   52: aload 4
    //   54: ifnull +77 -> 131
    //   57: iconst_1
    //   58: istore 8
    //   60: aload 5
    //   62: iload 8
    //   64: invokevirtual 40	android/os/Parcel:writeInt	(I)V
    //   67: iconst_0
    //   68: istore 8
    //   70: aconst_null
    //   71: astore 7
    //   73: aload 4
    //   75: aload 5
    //   77: iconst_0
    //   78: invokevirtual 64	android/os/Bundle:writeToParcel	(Landroid/os/Parcel;I)V
    //   81: aload_0
    //   82: getfield 14	com/google/android/gms/common/internal/zzs$zza$zza:zzoz	Landroid/os/IBinder;
    //   85: astore 7
    //   87: bipush 14
    //   89: istore 9
    //   91: aload 7
    //   93: iload 9
    //   95: aload 5
    //   97: aload 6
    //   99: iconst_0
    //   100: invokeinterface 47 5 0
    //   105: pop
    //   106: aload 6
    //   108: invokevirtual 50	android/os/Parcel:readException	()V
    //   111: aload 6
    //   113: invokevirtual 53	android/os/Parcel:recycle	()V
    //   116: aload 5
    //   118: invokevirtual 53	android/os/Parcel:recycle	()V
    //   121: return
    //   122: iconst_0
    //   123: istore 8
    //   125: aconst_null
    //   126: astore 7
    //   128: goto -95 -> 33
    //   131: iconst_0
    //   132: istore 8
    //   134: aconst_null
    //   135: astore 7
    //   137: aload 5
    //   139: iconst_0
    //   140: invokevirtual 40	android/os/Parcel:writeInt	(I)V
    //   143: goto -62 -> 81
    //   146: astore 7
    //   148: aload 6
    //   150: invokevirtual 53	android/os/Parcel:recycle	()V
    //   153: aload 5
    //   155: invokevirtual 53	android/os/Parcel:recycle	()V
    //   158: aload 7
    //   160: athrow
    // Local variable table:
    //   start	length	slot	name	signature
    //   0	161	0	this	zza
    //   0	161	1	paramzzr	zzr
    //   0	161	2	paramInt	int
    //   0	161	3	paramString	String
    //   0	161	4	paramBundle	android.os.Bundle
    //   3	151	5	localParcel1	Parcel
    //   8	141	6	localParcel2	Parcel
    //   12	124	7	localObject1	Object
    //   146	13	7	localObject2	Object
    //   58	75	8	i	int
    //   89	5	9	j	int
    // Exception table:
    //   from	to	target	type
    //   16	21	146	finally
    //   25	31	146	finally
    //   35	40	146	finally
    //   42	46	146	finally
    //   48	52	146	finally
    //   62	67	146	finally
    //   77	81	146	finally
    //   81	85	146	finally
    //   99	106	146	finally
    //   106	111	146	finally
    //   139	143	146	finally
  }
  
  /* Error */
  public void zzj(zzr paramzzr, int paramInt, String paramString)
  {
    // Byte code:
    //   0: invokestatic 20	android/os/Parcel:obtain	()Landroid/os/Parcel;
    //   3: astore 4
    //   5: invokestatic 20	android/os/Parcel:obtain	()Landroid/os/Parcel;
    //   8: astore 5
    //   10: ldc 22
    //   12: astore 6
    //   14: aload 4
    //   16: aload 6
    //   18: invokevirtual 26	android/os/Parcel:writeInterfaceToken	(Ljava/lang/String;)V
    //   21: aload_1
    //   22: ifnull +71 -> 93
    //   25: aload_1
    //   26: invokeinterface 32 1 0
    //   31: astore 6
    //   33: aload 4
    //   35: aload 6
    //   37: invokevirtual 36	android/os/Parcel:writeStrongBinder	(Landroid/os/IBinder;)V
    //   40: aload 4
    //   42: iload_2
    //   43: invokevirtual 40	android/os/Parcel:writeInt	(I)V
    //   46: aload 4
    //   48: aload_3
    //   49: invokevirtual 56	android/os/Parcel:writeString	(Ljava/lang/String;)V
    //   52: aload_0
    //   53: getfield 14	com/google/android/gms/common/internal/zzs$zza$zza:zzoz	Landroid/os/IBinder;
    //   56: astore 6
    //   58: bipush 40
    //   60: istore 7
    //   62: aload 6
    //   64: iload 7
    //   66: aload 4
    //   68: aload 5
    //   70: iconst_0
    //   71: invokeinterface 47 5 0
    //   76: pop
    //   77: aload 5
    //   79: invokevirtual 50	android/os/Parcel:readException	()V
    //   82: aload 5
    //   84: invokevirtual 53	android/os/Parcel:recycle	()V
    //   87: aload 4
    //   89: invokevirtual 53	android/os/Parcel:recycle	()V
    //   92: return
    //   93: aconst_null
    //   94: astore 6
    //   96: goto -63 -> 33
    //   99: astore 6
    //   101: aload 5
    //   103: invokevirtual 53	android/os/Parcel:recycle	()V
    //   106: aload 4
    //   108: invokevirtual 53	android/os/Parcel:recycle	()V
    //   111: aload 6
    //   113: athrow
    // Local variable table:
    //   start	length	slot	name	signature
    //   0	114	0	this	zza
    //   0	114	1	paramzzr	zzr
    //   0	114	2	paramInt	int
    //   0	114	3	paramString	String
    //   3	104	4	localParcel1	Parcel
    //   8	94	5	localParcel2	Parcel
    //   12	83	6	localObject1	Object
    //   99	13	6	localObject2	Object
    //   60	5	7	i	int
    // Exception table:
    //   from	to	target	type
    //   16	21	99	finally
    //   25	31	99	finally
    //   35	40	99	finally
    //   42	46	99	finally
    //   48	52	99	finally
    //   52	56	99	finally
    //   70	77	99	finally
    //   77	82	99	finally
  }
  
  /* Error */
  public void zzj(zzr paramzzr, int paramInt, String paramString, android.os.Bundle paramBundle)
  {
    // Byte code:
    //   0: invokestatic 20	android/os/Parcel:obtain	()Landroid/os/Parcel;
    //   3: astore 5
    //   5: invokestatic 20	android/os/Parcel:obtain	()Landroid/os/Parcel;
    //   8: astore 6
    //   10: ldc 22
    //   12: astore 7
    //   14: aload 5
    //   16: aload 7
    //   18: invokevirtual 26	android/os/Parcel:writeInterfaceToken	(Ljava/lang/String;)V
    //   21: aload_1
    //   22: ifnull +100 -> 122
    //   25: aload_1
    //   26: invokeinterface 32 1 0
    //   31: astore 7
    //   33: aload 5
    //   35: aload 7
    //   37: invokevirtual 36	android/os/Parcel:writeStrongBinder	(Landroid/os/IBinder;)V
    //   40: aload 5
    //   42: iload_2
    //   43: invokevirtual 40	android/os/Parcel:writeInt	(I)V
    //   46: aload 5
    //   48: aload_3
    //   49: invokevirtual 56	android/os/Parcel:writeString	(Ljava/lang/String;)V
    //   52: aload 4
    //   54: ifnull +77 -> 131
    //   57: iconst_1
    //   58: istore 8
    //   60: aload 5
    //   62: iload 8
    //   64: invokevirtual 40	android/os/Parcel:writeInt	(I)V
    //   67: iconst_0
    //   68: istore 8
    //   70: aconst_null
    //   71: astore 7
    //   73: aload 4
    //   75: aload 5
    //   77: iconst_0
    //   78: invokevirtual 64	android/os/Bundle:writeToParcel	(Landroid/os/Parcel;I)V
    //   81: aload_0
    //   82: getfield 14	com/google/android/gms/common/internal/zzs$zza$zza:zzoz	Landroid/os/IBinder;
    //   85: astore 7
    //   87: bipush 15
    //   89: istore 9
    //   91: aload 7
    //   93: iload 9
    //   95: aload 5
    //   97: aload 6
    //   99: iconst_0
    //   100: invokeinterface 47 5 0
    //   105: pop
    //   106: aload 6
    //   108: invokevirtual 50	android/os/Parcel:readException	()V
    //   111: aload 6
    //   113: invokevirtual 53	android/os/Parcel:recycle	()V
    //   116: aload 5
    //   118: invokevirtual 53	android/os/Parcel:recycle	()V
    //   121: return
    //   122: iconst_0
    //   123: istore 8
    //   125: aconst_null
    //   126: astore 7
    //   128: goto -95 -> 33
    //   131: iconst_0
    //   132: istore 8
    //   134: aconst_null
    //   135: astore 7
    //   137: aload 5
    //   139: iconst_0
    //   140: invokevirtual 40	android/os/Parcel:writeInt	(I)V
    //   143: goto -62 -> 81
    //   146: astore 7
    //   148: aload 6
    //   150: invokevirtual 53	android/os/Parcel:recycle	()V
    //   153: aload 5
    //   155: invokevirtual 53	android/os/Parcel:recycle	()V
    //   158: aload 7
    //   160: athrow
    // Local variable table:
    //   start	length	slot	name	signature
    //   0	161	0	this	zza
    //   0	161	1	paramzzr	zzr
    //   0	161	2	paramInt	int
    //   0	161	3	paramString	String
    //   0	161	4	paramBundle	android.os.Bundle
    //   3	151	5	localParcel1	Parcel
    //   8	141	6	localParcel2	Parcel
    //   12	124	7	localObject1	Object
    //   146	13	7	localObject2	Object
    //   58	75	8	i	int
    //   89	5	9	j	int
    // Exception table:
    //   from	to	target	type
    //   16	21	146	finally
    //   25	31	146	finally
    //   35	40	146	finally
    //   42	46	146	finally
    //   48	52	146	finally
    //   62	67	146	finally
    //   77	81	146	finally
    //   81	85	146	finally
    //   99	106	146	finally
    //   106	111	146	finally
    //   139	143	146	finally
  }
  
  /* Error */
  public void zzk(zzr paramzzr, int paramInt, String paramString)
  {
    // Byte code:
    //   0: invokestatic 20	android/os/Parcel:obtain	()Landroid/os/Parcel;
    //   3: astore 4
    //   5: invokestatic 20	android/os/Parcel:obtain	()Landroid/os/Parcel;
    //   8: astore 5
    //   10: ldc 22
    //   12: astore 6
    //   14: aload 4
    //   16: aload 6
    //   18: invokevirtual 26	android/os/Parcel:writeInterfaceToken	(Ljava/lang/String;)V
    //   21: aload_1
    //   22: ifnull +71 -> 93
    //   25: aload_1
    //   26: invokeinterface 32 1 0
    //   31: astore 6
    //   33: aload 4
    //   35: aload 6
    //   37: invokevirtual 36	android/os/Parcel:writeStrongBinder	(Landroid/os/IBinder;)V
    //   40: aload 4
    //   42: iload_2
    //   43: invokevirtual 40	android/os/Parcel:writeInt	(I)V
    //   46: aload 4
    //   48: aload_3
    //   49: invokevirtual 56	android/os/Parcel:writeString	(Ljava/lang/String;)V
    //   52: aload_0
    //   53: getfield 14	com/google/android/gms/common/internal/zzs$zza$zza:zzoz	Landroid/os/IBinder;
    //   56: astore 6
    //   58: bipush 42
    //   60: istore 7
    //   62: aload 6
    //   64: iload 7
    //   66: aload 4
    //   68: aload 5
    //   70: iconst_0
    //   71: invokeinterface 47 5 0
    //   76: pop
    //   77: aload 5
    //   79: invokevirtual 50	android/os/Parcel:readException	()V
    //   82: aload 5
    //   84: invokevirtual 53	android/os/Parcel:recycle	()V
    //   87: aload 4
    //   89: invokevirtual 53	android/os/Parcel:recycle	()V
    //   92: return
    //   93: aconst_null
    //   94: astore 6
    //   96: goto -63 -> 33
    //   99: astore 6
    //   101: aload 5
    //   103: invokevirtual 53	android/os/Parcel:recycle	()V
    //   106: aload 4
    //   108: invokevirtual 53	android/os/Parcel:recycle	()V
    //   111: aload 6
    //   113: athrow
    // Local variable table:
    //   start	length	slot	name	signature
    //   0	114	0	this	zza
    //   0	114	1	paramzzr	zzr
    //   0	114	2	paramInt	int
    //   0	114	3	paramString	String
    //   3	104	4	localParcel1	Parcel
    //   8	94	5	localParcel2	Parcel
    //   12	83	6	localObject1	Object
    //   99	13	6	localObject2	Object
    //   60	5	7	i	int
    // Exception table:
    //   from	to	target	type
    //   16	21	99	finally
    //   25	31	99	finally
    //   35	40	99	finally
    //   42	46	99	finally
    //   48	52	99	finally
    //   52	56	99	finally
    //   70	77	99	finally
    //   77	82	99	finally
  }
  
  /* Error */
  public void zzk(zzr paramzzr, int paramInt, String paramString, android.os.Bundle paramBundle)
  {
    // Byte code:
    //   0: invokestatic 20	android/os/Parcel:obtain	()Landroid/os/Parcel;
    //   3: astore 5
    //   5: invokestatic 20	android/os/Parcel:obtain	()Landroid/os/Parcel;
    //   8: astore 6
    //   10: ldc 22
    //   12: astore 7
    //   14: aload 5
    //   16: aload 7
    //   18: invokevirtual 26	android/os/Parcel:writeInterfaceToken	(Ljava/lang/String;)V
    //   21: aload_1
    //   22: ifnull +100 -> 122
    //   25: aload_1
    //   26: invokeinterface 32 1 0
    //   31: astore 7
    //   33: aload 5
    //   35: aload 7
    //   37: invokevirtual 36	android/os/Parcel:writeStrongBinder	(Landroid/os/IBinder;)V
    //   40: aload 5
    //   42: iload_2
    //   43: invokevirtual 40	android/os/Parcel:writeInt	(I)V
    //   46: aload 5
    //   48: aload_3
    //   49: invokevirtual 56	android/os/Parcel:writeString	(Ljava/lang/String;)V
    //   52: aload 4
    //   54: ifnull +77 -> 131
    //   57: iconst_1
    //   58: istore 8
    //   60: aload 5
    //   62: iload 8
    //   64: invokevirtual 40	android/os/Parcel:writeInt	(I)V
    //   67: iconst_0
    //   68: istore 8
    //   70: aconst_null
    //   71: astore 7
    //   73: aload 4
    //   75: aload 5
    //   77: iconst_0
    //   78: invokevirtual 64	android/os/Bundle:writeToParcel	(Landroid/os/Parcel;I)V
    //   81: aload_0
    //   82: getfield 14	com/google/android/gms/common/internal/zzs$zza$zza:zzoz	Landroid/os/IBinder;
    //   85: astore 7
    //   87: bipush 16
    //   89: istore 9
    //   91: aload 7
    //   93: iload 9
    //   95: aload 5
    //   97: aload 6
    //   99: iconst_0
    //   100: invokeinterface 47 5 0
    //   105: pop
    //   106: aload 6
    //   108: invokevirtual 50	android/os/Parcel:readException	()V
    //   111: aload 6
    //   113: invokevirtual 53	android/os/Parcel:recycle	()V
    //   116: aload 5
    //   118: invokevirtual 53	android/os/Parcel:recycle	()V
    //   121: return
    //   122: iconst_0
    //   123: istore 8
    //   125: aconst_null
    //   126: astore 7
    //   128: goto -95 -> 33
    //   131: iconst_0
    //   132: istore 8
    //   134: aconst_null
    //   135: astore 7
    //   137: aload 5
    //   139: iconst_0
    //   140: invokevirtual 40	android/os/Parcel:writeInt	(I)V
    //   143: goto -62 -> 81
    //   146: astore 7
    //   148: aload 6
    //   150: invokevirtual 53	android/os/Parcel:recycle	()V
    //   153: aload 5
    //   155: invokevirtual 53	android/os/Parcel:recycle	()V
    //   158: aload 7
    //   160: athrow
    // Local variable table:
    //   start	length	slot	name	signature
    //   0	161	0	this	zza
    //   0	161	1	paramzzr	zzr
    //   0	161	2	paramInt	int
    //   0	161	3	paramString	String
    //   0	161	4	paramBundle	android.os.Bundle
    //   3	151	5	localParcel1	Parcel
    //   8	141	6	localParcel2	Parcel
    //   12	124	7	localObject1	Object
    //   146	13	7	localObject2	Object
    //   58	75	8	i	int
    //   89	5	9	j	int
    // Exception table:
    //   from	to	target	type
    //   16	21	146	finally
    //   25	31	146	finally
    //   35	40	146	finally
    //   42	46	146	finally
    //   48	52	146	finally
    //   62	67	146	finally
    //   77	81	146	finally
    //   81	85	146	finally
    //   99	106	146	finally
    //   106	111	146	finally
    //   139	143	146	finally
  }
  
  /* Error */
  public void zzl(zzr paramzzr, int paramInt, String paramString)
  {
    // Byte code:
    //   0: invokestatic 20	android/os/Parcel:obtain	()Landroid/os/Parcel;
    //   3: astore 4
    //   5: invokestatic 20	android/os/Parcel:obtain	()Landroid/os/Parcel;
    //   8: astore 5
    //   10: ldc 22
    //   12: astore 6
    //   14: aload 4
    //   16: aload 6
    //   18: invokevirtual 26	android/os/Parcel:writeInterfaceToken	(Ljava/lang/String;)V
    //   21: aload_1
    //   22: ifnull +71 -> 93
    //   25: aload_1
    //   26: invokeinterface 32 1 0
    //   31: astore 6
    //   33: aload 4
    //   35: aload 6
    //   37: invokevirtual 36	android/os/Parcel:writeStrongBinder	(Landroid/os/IBinder;)V
    //   40: aload 4
    //   42: iload_2
    //   43: invokevirtual 40	android/os/Parcel:writeInt	(I)V
    //   46: aload 4
    //   48: aload_3
    //   49: invokevirtual 56	android/os/Parcel:writeString	(Ljava/lang/String;)V
    //   52: aload_0
    //   53: getfield 14	com/google/android/gms/common/internal/zzs$zza$zza:zzoz	Landroid/os/IBinder;
    //   56: astore 6
    //   58: bipush 44
    //   60: istore 7
    //   62: aload 6
    //   64: iload 7
    //   66: aload 4
    //   68: aload 5
    //   70: iconst_0
    //   71: invokeinterface 47 5 0
    //   76: pop
    //   77: aload 5
    //   79: invokevirtual 50	android/os/Parcel:readException	()V
    //   82: aload 5
    //   84: invokevirtual 53	android/os/Parcel:recycle	()V
    //   87: aload 4
    //   89: invokevirtual 53	android/os/Parcel:recycle	()V
    //   92: return
    //   93: aconst_null
    //   94: astore 6
    //   96: goto -63 -> 33
    //   99: astore 6
    //   101: aload 5
    //   103: invokevirtual 53	android/os/Parcel:recycle	()V
    //   106: aload 4
    //   108: invokevirtual 53	android/os/Parcel:recycle	()V
    //   111: aload 6
    //   113: athrow
    // Local variable table:
    //   start	length	slot	name	signature
    //   0	114	0	this	zza
    //   0	114	1	paramzzr	zzr
    //   0	114	2	paramInt	int
    //   0	114	3	paramString	String
    //   3	104	4	localParcel1	Parcel
    //   8	94	5	localParcel2	Parcel
    //   12	83	6	localObject1	Object
    //   99	13	6	localObject2	Object
    //   60	5	7	i	int
    // Exception table:
    //   from	to	target	type
    //   16	21	99	finally
    //   25	31	99	finally
    //   35	40	99	finally
    //   42	46	99	finally
    //   48	52	99	finally
    //   52	56	99	finally
    //   70	77	99	finally
    //   77	82	99	finally
  }
  
  /* Error */
  public void zzl(zzr paramzzr, int paramInt, String paramString, android.os.Bundle paramBundle)
  {
    // Byte code:
    //   0: invokestatic 20	android/os/Parcel:obtain	()Landroid/os/Parcel;
    //   3: astore 5
    //   5: invokestatic 20	android/os/Parcel:obtain	()Landroid/os/Parcel;
    //   8: astore 6
    //   10: ldc 22
    //   12: astore 7
    //   14: aload 5
    //   16: aload 7
    //   18: invokevirtual 26	android/os/Parcel:writeInterfaceToken	(Ljava/lang/String;)V
    //   21: aload_1
    //   22: ifnull +100 -> 122
    //   25: aload_1
    //   26: invokeinterface 32 1 0
    //   31: astore 7
    //   33: aload 5
    //   35: aload 7
    //   37: invokevirtual 36	android/os/Parcel:writeStrongBinder	(Landroid/os/IBinder;)V
    //   40: aload 5
    //   42: iload_2
    //   43: invokevirtual 40	android/os/Parcel:writeInt	(I)V
    //   46: aload 5
    //   48: aload_3
    //   49: invokevirtual 56	android/os/Parcel:writeString	(Ljava/lang/String;)V
    //   52: aload 4
    //   54: ifnull +77 -> 131
    //   57: iconst_1
    //   58: istore 8
    //   60: aload 5
    //   62: iload 8
    //   64: invokevirtual 40	android/os/Parcel:writeInt	(I)V
    //   67: iconst_0
    //   68: istore 8
    //   70: aconst_null
    //   71: astore 7
    //   73: aload 4
    //   75: aload 5
    //   77: iconst_0
    //   78: invokevirtual 64	android/os/Bundle:writeToParcel	(Landroid/os/Parcel;I)V
    //   81: aload_0
    //   82: getfield 14	com/google/android/gms/common/internal/zzs$zza$zza:zzoz	Landroid/os/IBinder;
    //   85: astore 7
    //   87: bipush 17
    //   89: istore 9
    //   91: aload 7
    //   93: iload 9
    //   95: aload 5
    //   97: aload 6
    //   99: iconst_0
    //   100: invokeinterface 47 5 0
    //   105: pop
    //   106: aload 6
    //   108: invokevirtual 50	android/os/Parcel:readException	()V
    //   111: aload 6
    //   113: invokevirtual 53	android/os/Parcel:recycle	()V
    //   116: aload 5
    //   118: invokevirtual 53	android/os/Parcel:recycle	()V
    //   121: return
    //   122: iconst_0
    //   123: istore 8
    //   125: aconst_null
    //   126: astore 7
    //   128: goto -95 -> 33
    //   131: iconst_0
    //   132: istore 8
    //   134: aconst_null
    //   135: astore 7
    //   137: aload 5
    //   139: iconst_0
    //   140: invokevirtual 40	android/os/Parcel:writeInt	(I)V
    //   143: goto -62 -> 81
    //   146: astore 7
    //   148: aload 6
    //   150: invokevirtual 53	android/os/Parcel:recycle	()V
    //   153: aload 5
    //   155: invokevirtual 53	android/os/Parcel:recycle	()V
    //   158: aload 7
    //   160: athrow
    // Local variable table:
    //   start	length	slot	name	signature
    //   0	161	0	this	zza
    //   0	161	1	paramzzr	zzr
    //   0	161	2	paramInt	int
    //   0	161	3	paramString	String
    //   0	161	4	paramBundle	android.os.Bundle
    //   3	151	5	localParcel1	Parcel
    //   8	141	6	localParcel2	Parcel
    //   12	124	7	localObject1	Object
    //   146	13	7	localObject2	Object
    //   58	75	8	i	int
    //   89	5	9	j	int
    // Exception table:
    //   from	to	target	type
    //   16	21	146	finally
    //   25	31	146	finally
    //   35	40	146	finally
    //   42	46	146	finally
    //   48	52	146	finally
    //   62	67	146	finally
    //   77	81	146	finally
    //   81	85	146	finally
    //   99	106	146	finally
    //   106	111	146	finally
    //   139	143	146	finally
  }
  
  /* Error */
  public void zzm(zzr paramzzr, int paramInt, String paramString)
  {
    // Byte code:
    //   0: invokestatic 20	android/os/Parcel:obtain	()Landroid/os/Parcel;
    //   3: astore 4
    //   5: invokestatic 20	android/os/Parcel:obtain	()Landroid/os/Parcel;
    //   8: astore 5
    //   10: ldc 22
    //   12: astore 6
    //   14: aload 4
    //   16: aload 6
    //   18: invokevirtual 26	android/os/Parcel:writeInterfaceToken	(Ljava/lang/String;)V
    //   21: aload_1
    //   22: ifnull +71 -> 93
    //   25: aload_1
    //   26: invokeinterface 32 1 0
    //   31: astore 6
    //   33: aload 4
    //   35: aload 6
    //   37: invokevirtual 36	android/os/Parcel:writeStrongBinder	(Landroid/os/IBinder;)V
    //   40: aload 4
    //   42: iload_2
    //   43: invokevirtual 40	android/os/Parcel:writeInt	(I)V
    //   46: aload 4
    //   48: aload_3
    //   49: invokevirtual 56	android/os/Parcel:writeString	(Ljava/lang/String;)V
    //   52: aload_0
    //   53: getfield 14	com/google/android/gms/common/internal/zzs$zza$zza:zzoz	Landroid/os/IBinder;
    //   56: astore 6
    //   58: bipush 45
    //   60: istore 7
    //   62: aload 6
    //   64: iload 7
    //   66: aload 4
    //   68: aload 5
    //   70: iconst_0
    //   71: invokeinterface 47 5 0
    //   76: pop
    //   77: aload 5
    //   79: invokevirtual 50	android/os/Parcel:readException	()V
    //   82: aload 5
    //   84: invokevirtual 53	android/os/Parcel:recycle	()V
    //   87: aload 4
    //   89: invokevirtual 53	android/os/Parcel:recycle	()V
    //   92: return
    //   93: aconst_null
    //   94: astore 6
    //   96: goto -63 -> 33
    //   99: astore 6
    //   101: aload 5
    //   103: invokevirtual 53	android/os/Parcel:recycle	()V
    //   106: aload 4
    //   108: invokevirtual 53	android/os/Parcel:recycle	()V
    //   111: aload 6
    //   113: athrow
    // Local variable table:
    //   start	length	slot	name	signature
    //   0	114	0	this	zza
    //   0	114	1	paramzzr	zzr
    //   0	114	2	paramInt	int
    //   0	114	3	paramString	String
    //   3	104	4	localParcel1	Parcel
    //   8	94	5	localParcel2	Parcel
    //   12	83	6	localObject1	Object
    //   99	13	6	localObject2	Object
    //   60	5	7	i	int
    // Exception table:
    //   from	to	target	type
    //   16	21	99	finally
    //   25	31	99	finally
    //   35	40	99	finally
    //   42	46	99	finally
    //   48	52	99	finally
    //   52	56	99	finally
    //   70	77	99	finally
    //   77	82	99	finally
  }
  
  /* Error */
  public void zzm(zzr paramzzr, int paramInt, String paramString, android.os.Bundle paramBundle)
  {
    // Byte code:
    //   0: invokestatic 20	android/os/Parcel:obtain	()Landroid/os/Parcel;
    //   3: astore 5
    //   5: invokestatic 20	android/os/Parcel:obtain	()Landroid/os/Parcel;
    //   8: astore 6
    //   10: ldc 22
    //   12: astore 7
    //   14: aload 5
    //   16: aload 7
    //   18: invokevirtual 26	android/os/Parcel:writeInterfaceToken	(Ljava/lang/String;)V
    //   21: aload_1
    //   22: ifnull +100 -> 122
    //   25: aload_1
    //   26: invokeinterface 32 1 0
    //   31: astore 7
    //   33: aload 5
    //   35: aload 7
    //   37: invokevirtual 36	android/os/Parcel:writeStrongBinder	(Landroid/os/IBinder;)V
    //   40: aload 5
    //   42: iload_2
    //   43: invokevirtual 40	android/os/Parcel:writeInt	(I)V
    //   46: aload 5
    //   48: aload_3
    //   49: invokevirtual 56	android/os/Parcel:writeString	(Ljava/lang/String;)V
    //   52: aload 4
    //   54: ifnull +77 -> 131
    //   57: iconst_1
    //   58: istore 8
    //   60: aload 5
    //   62: iload 8
    //   64: invokevirtual 40	android/os/Parcel:writeInt	(I)V
    //   67: iconst_0
    //   68: istore 8
    //   70: aconst_null
    //   71: astore 7
    //   73: aload 4
    //   75: aload 5
    //   77: iconst_0
    //   78: invokevirtual 64	android/os/Bundle:writeToParcel	(Landroid/os/Parcel;I)V
    //   81: aload_0
    //   82: getfield 14	com/google/android/gms/common/internal/zzs$zza$zza:zzoz	Landroid/os/IBinder;
    //   85: astore 7
    //   87: bipush 18
    //   89: istore 9
    //   91: aload 7
    //   93: iload 9
    //   95: aload 5
    //   97: aload 6
    //   99: iconst_0
    //   100: invokeinterface 47 5 0
    //   105: pop
    //   106: aload 6
    //   108: invokevirtual 50	android/os/Parcel:readException	()V
    //   111: aload 6
    //   113: invokevirtual 53	android/os/Parcel:recycle	()V
    //   116: aload 5
    //   118: invokevirtual 53	android/os/Parcel:recycle	()V
    //   121: return
    //   122: iconst_0
    //   123: istore 8
    //   125: aconst_null
    //   126: astore 7
    //   128: goto -95 -> 33
    //   131: iconst_0
    //   132: istore 8
    //   134: aconst_null
    //   135: astore 7
    //   137: aload 5
    //   139: iconst_0
    //   140: invokevirtual 40	android/os/Parcel:writeInt	(I)V
    //   143: goto -62 -> 81
    //   146: astore 7
    //   148: aload 6
    //   150: invokevirtual 53	android/os/Parcel:recycle	()V
    //   153: aload 5
    //   155: invokevirtual 53	android/os/Parcel:recycle	()V
    //   158: aload 7
    //   160: athrow
    // Local variable table:
    //   start	length	slot	name	signature
    //   0	161	0	this	zza
    //   0	161	1	paramzzr	zzr
    //   0	161	2	paramInt	int
    //   0	161	3	paramString	String
    //   0	161	4	paramBundle	android.os.Bundle
    //   3	151	5	localParcel1	Parcel
    //   8	141	6	localParcel2	Parcel
    //   12	124	7	localObject1	Object
    //   146	13	7	localObject2	Object
    //   58	75	8	i	int
    //   89	5	9	j	int
    // Exception table:
    //   from	to	target	type
    //   16	21	146	finally
    //   25	31	146	finally
    //   35	40	146	finally
    //   42	46	146	finally
    //   48	52	146	finally
    //   62	67	146	finally
    //   77	81	146	finally
    //   81	85	146	finally
    //   99	106	146	finally
    //   106	111	146	finally
    //   139	143	146	finally
  }
  
  /* Error */
  public void zzn(zzr paramzzr, int paramInt, String paramString, android.os.Bundle paramBundle)
  {
    // Byte code:
    //   0: invokestatic 20	android/os/Parcel:obtain	()Landroid/os/Parcel;
    //   3: astore 5
    //   5: invokestatic 20	android/os/Parcel:obtain	()Landroid/os/Parcel;
    //   8: astore 6
    //   10: ldc 22
    //   12: astore 7
    //   14: aload 5
    //   16: aload 7
    //   18: invokevirtual 26	android/os/Parcel:writeInterfaceToken	(Ljava/lang/String;)V
    //   21: aload_1
    //   22: ifnull +100 -> 122
    //   25: aload_1
    //   26: invokeinterface 32 1 0
    //   31: astore 7
    //   33: aload 5
    //   35: aload 7
    //   37: invokevirtual 36	android/os/Parcel:writeStrongBinder	(Landroid/os/IBinder;)V
    //   40: aload 5
    //   42: iload_2
    //   43: invokevirtual 40	android/os/Parcel:writeInt	(I)V
    //   46: aload 5
    //   48: aload_3
    //   49: invokevirtual 56	android/os/Parcel:writeString	(Ljava/lang/String;)V
    //   52: aload 4
    //   54: ifnull +77 -> 131
    //   57: iconst_1
    //   58: istore 8
    //   60: aload 5
    //   62: iload 8
    //   64: invokevirtual 40	android/os/Parcel:writeInt	(I)V
    //   67: iconst_0
    //   68: istore 8
    //   70: aconst_null
    //   71: astore 7
    //   73: aload 4
    //   75: aload 5
    //   77: iconst_0
    //   78: invokevirtual 64	android/os/Bundle:writeToParcel	(Landroid/os/Parcel;I)V
    //   81: aload_0
    //   82: getfield 14	com/google/android/gms/common/internal/zzs$zza$zza:zzoz	Landroid/os/IBinder;
    //   85: astore 7
    //   87: bipush 23
    //   89: istore 9
    //   91: aload 7
    //   93: iload 9
    //   95: aload 5
    //   97: aload 6
    //   99: iconst_0
    //   100: invokeinterface 47 5 0
    //   105: pop
    //   106: aload 6
    //   108: invokevirtual 50	android/os/Parcel:readException	()V
    //   111: aload 6
    //   113: invokevirtual 53	android/os/Parcel:recycle	()V
    //   116: aload 5
    //   118: invokevirtual 53	android/os/Parcel:recycle	()V
    //   121: return
    //   122: iconst_0
    //   123: istore 8
    //   125: aconst_null
    //   126: astore 7
    //   128: goto -95 -> 33
    //   131: iconst_0
    //   132: istore 8
    //   134: aconst_null
    //   135: astore 7
    //   137: aload 5
    //   139: iconst_0
    //   140: invokevirtual 40	android/os/Parcel:writeInt	(I)V
    //   143: goto -62 -> 81
    //   146: astore 7
    //   148: aload 6
    //   150: invokevirtual 53	android/os/Parcel:recycle	()V
    //   153: aload 5
    //   155: invokevirtual 53	android/os/Parcel:recycle	()V
    //   158: aload 7
    //   160: athrow
    // Local variable table:
    //   start	length	slot	name	signature
    //   0	161	0	this	zza
    //   0	161	1	paramzzr	zzr
    //   0	161	2	paramInt	int
    //   0	161	3	paramString	String
    //   0	161	4	paramBundle	android.os.Bundle
    //   3	151	5	localParcel1	Parcel
    //   8	141	6	localParcel2	Parcel
    //   12	124	7	localObject1	Object
    //   146	13	7	localObject2	Object
    //   58	75	8	i	int
    //   89	5	9	j	int
    // Exception table:
    //   from	to	target	type
    //   16	21	146	finally
    //   25	31	146	finally
    //   35	40	146	finally
    //   42	46	146	finally
    //   48	52	146	finally
    //   62	67	146	finally
    //   77	81	146	finally
    //   81	85	146	finally
    //   99	106	146	finally
    //   106	111	146	finally
    //   139	143	146	finally
  }
  
  /* Error */
  public void zzo(zzr paramzzr, int paramInt, String paramString, android.os.Bundle paramBundle)
  {
    // Byte code:
    //   0: invokestatic 20	android/os/Parcel:obtain	()Landroid/os/Parcel;
    //   3: astore 5
    //   5: invokestatic 20	android/os/Parcel:obtain	()Landroid/os/Parcel;
    //   8: astore 6
    //   10: ldc 22
    //   12: astore 7
    //   14: aload 5
    //   16: aload 7
    //   18: invokevirtual 26	android/os/Parcel:writeInterfaceToken	(Ljava/lang/String;)V
    //   21: aload_1
    //   22: ifnull +100 -> 122
    //   25: aload_1
    //   26: invokeinterface 32 1 0
    //   31: astore 7
    //   33: aload 5
    //   35: aload 7
    //   37: invokevirtual 36	android/os/Parcel:writeStrongBinder	(Landroid/os/IBinder;)V
    //   40: aload 5
    //   42: iload_2
    //   43: invokevirtual 40	android/os/Parcel:writeInt	(I)V
    //   46: aload 5
    //   48: aload_3
    //   49: invokevirtual 56	android/os/Parcel:writeString	(Ljava/lang/String;)V
    //   52: aload 4
    //   54: ifnull +77 -> 131
    //   57: iconst_1
    //   58: istore 8
    //   60: aload 5
    //   62: iload 8
    //   64: invokevirtual 40	android/os/Parcel:writeInt	(I)V
    //   67: iconst_0
    //   68: istore 8
    //   70: aconst_null
    //   71: astore 7
    //   73: aload 4
    //   75: aload 5
    //   77: iconst_0
    //   78: invokevirtual 64	android/os/Bundle:writeToParcel	(Landroid/os/Parcel;I)V
    //   81: aload_0
    //   82: getfield 14	com/google/android/gms/common/internal/zzs$zza$zza:zzoz	Landroid/os/IBinder;
    //   85: astore 7
    //   87: bipush 25
    //   89: istore 9
    //   91: aload 7
    //   93: iload 9
    //   95: aload 5
    //   97: aload 6
    //   99: iconst_0
    //   100: invokeinterface 47 5 0
    //   105: pop
    //   106: aload 6
    //   108: invokevirtual 50	android/os/Parcel:readException	()V
    //   111: aload 6
    //   113: invokevirtual 53	android/os/Parcel:recycle	()V
    //   116: aload 5
    //   118: invokevirtual 53	android/os/Parcel:recycle	()V
    //   121: return
    //   122: iconst_0
    //   123: istore 8
    //   125: aconst_null
    //   126: astore 7
    //   128: goto -95 -> 33
    //   131: iconst_0
    //   132: istore 8
    //   134: aconst_null
    //   135: astore 7
    //   137: aload 5
    //   139: iconst_0
    //   140: invokevirtual 40	android/os/Parcel:writeInt	(I)V
    //   143: goto -62 -> 81
    //   146: astore 7
    //   148: aload 6
    //   150: invokevirtual 53	android/os/Parcel:recycle	()V
    //   153: aload 5
    //   155: invokevirtual 53	android/os/Parcel:recycle	()V
    //   158: aload 7
    //   160: athrow
    // Local variable table:
    //   start	length	slot	name	signature
    //   0	161	0	this	zza
    //   0	161	1	paramzzr	zzr
    //   0	161	2	paramInt	int
    //   0	161	3	paramString	String
    //   0	161	4	paramBundle	android.os.Bundle
    //   3	151	5	localParcel1	Parcel
    //   8	141	6	localParcel2	Parcel
    //   12	124	7	localObject1	Object
    //   146	13	7	localObject2	Object
    //   58	75	8	i	int
    //   89	5	9	j	int
    // Exception table:
    //   from	to	target	type
    //   16	21	146	finally
    //   25	31	146	finally
    //   35	40	146	finally
    //   42	46	146	finally
    //   48	52	146	finally
    //   62	67	146	finally
    //   77	81	146	finally
    //   81	85	146	finally
    //   99	106	146	finally
    //   106	111	146	finally
    //   139	143	146	finally
  }
  
  /* Error */
  public void zzp(zzr paramzzr, int paramInt, String paramString, android.os.Bundle paramBundle)
  {
    // Byte code:
    //   0: invokestatic 20	android/os/Parcel:obtain	()Landroid/os/Parcel;
    //   3: astore 5
    //   5: invokestatic 20	android/os/Parcel:obtain	()Landroid/os/Parcel;
    //   8: astore 6
    //   10: ldc 22
    //   12: astore 7
    //   14: aload 5
    //   16: aload 7
    //   18: invokevirtual 26	android/os/Parcel:writeInterfaceToken	(Ljava/lang/String;)V
    //   21: aload_1
    //   22: ifnull +100 -> 122
    //   25: aload_1
    //   26: invokeinterface 32 1 0
    //   31: astore 7
    //   33: aload 5
    //   35: aload 7
    //   37: invokevirtual 36	android/os/Parcel:writeStrongBinder	(Landroid/os/IBinder;)V
    //   40: aload 5
    //   42: iload_2
    //   43: invokevirtual 40	android/os/Parcel:writeInt	(I)V
    //   46: aload 5
    //   48: aload_3
    //   49: invokevirtual 56	android/os/Parcel:writeString	(Ljava/lang/String;)V
    //   52: aload 4
    //   54: ifnull +77 -> 131
    //   57: iconst_1
    //   58: istore 8
    //   60: aload 5
    //   62: iload 8
    //   64: invokevirtual 40	android/os/Parcel:writeInt	(I)V
    //   67: iconst_0
    //   68: istore 8
    //   70: aconst_null
    //   71: astore 7
    //   73: aload 4
    //   75: aload 5
    //   77: iconst_0
    //   78: invokevirtual 64	android/os/Bundle:writeToParcel	(Landroid/os/Parcel;I)V
    //   81: aload_0
    //   82: getfield 14	com/google/android/gms/common/internal/zzs$zza$zza:zzoz	Landroid/os/IBinder;
    //   85: astore 7
    //   87: bipush 27
    //   89: istore 9
    //   91: aload 7
    //   93: iload 9
    //   95: aload 5
    //   97: aload 6
    //   99: iconst_0
    //   100: invokeinterface 47 5 0
    //   105: pop
    //   106: aload 6
    //   108: invokevirtual 50	android/os/Parcel:readException	()V
    //   111: aload 6
    //   113: invokevirtual 53	android/os/Parcel:recycle	()V
    //   116: aload 5
    //   118: invokevirtual 53	android/os/Parcel:recycle	()V
    //   121: return
    //   122: iconst_0
    //   123: istore 8
    //   125: aconst_null
    //   126: astore 7
    //   128: goto -95 -> 33
    //   131: iconst_0
    //   132: istore 8
    //   134: aconst_null
    //   135: astore 7
    //   137: aload 5
    //   139: iconst_0
    //   140: invokevirtual 40	android/os/Parcel:writeInt	(I)V
    //   143: goto -62 -> 81
    //   146: astore 7
    //   148: aload 6
    //   150: invokevirtual 53	android/os/Parcel:recycle	()V
    //   153: aload 5
    //   155: invokevirtual 53	android/os/Parcel:recycle	()V
    //   158: aload 7
    //   160: athrow
    // Local variable table:
    //   start	length	slot	name	signature
    //   0	161	0	this	zza
    //   0	161	1	paramzzr	zzr
    //   0	161	2	paramInt	int
    //   0	161	3	paramString	String
    //   0	161	4	paramBundle	android.os.Bundle
    //   3	151	5	localParcel1	Parcel
    //   8	141	6	localParcel2	Parcel
    //   12	124	7	localObject1	Object
    //   146	13	7	localObject2	Object
    //   58	75	8	i	int
    //   89	5	9	j	int
    // Exception table:
    //   from	to	target	type
    //   16	21	146	finally
    //   25	31	146	finally
    //   35	40	146	finally
    //   42	46	146	finally
    //   48	52	146	finally
    //   62	67	146	finally
    //   77	81	146	finally
    //   81	85	146	finally
    //   99	106	146	finally
    //   106	111	146	finally
    //   139	143	146	finally
  }
  
  /* Error */
  public void zzq(zzr paramzzr, int paramInt, String paramString, android.os.Bundle paramBundle)
  {
    // Byte code:
    //   0: invokestatic 20	android/os/Parcel:obtain	()Landroid/os/Parcel;
    //   3: astore 5
    //   5: invokestatic 20	android/os/Parcel:obtain	()Landroid/os/Parcel;
    //   8: astore 6
    //   10: ldc 22
    //   12: astore 7
    //   14: aload 5
    //   16: aload 7
    //   18: invokevirtual 26	android/os/Parcel:writeInterfaceToken	(Ljava/lang/String;)V
    //   21: aload_1
    //   22: ifnull +100 -> 122
    //   25: aload_1
    //   26: invokeinterface 32 1 0
    //   31: astore 7
    //   33: aload 5
    //   35: aload 7
    //   37: invokevirtual 36	android/os/Parcel:writeStrongBinder	(Landroid/os/IBinder;)V
    //   40: aload 5
    //   42: iload_2
    //   43: invokevirtual 40	android/os/Parcel:writeInt	(I)V
    //   46: aload 5
    //   48: aload_3
    //   49: invokevirtual 56	android/os/Parcel:writeString	(Ljava/lang/String;)V
    //   52: aload 4
    //   54: ifnull +77 -> 131
    //   57: iconst_1
    //   58: istore 8
    //   60: aload 5
    //   62: iload 8
    //   64: invokevirtual 40	android/os/Parcel:writeInt	(I)V
    //   67: iconst_0
    //   68: istore 8
    //   70: aconst_null
    //   71: astore 7
    //   73: aload 4
    //   75: aload 5
    //   77: iconst_0
    //   78: invokevirtual 64	android/os/Bundle:writeToParcel	(Landroid/os/Parcel;I)V
    //   81: aload_0
    //   82: getfield 14	com/google/android/gms/common/internal/zzs$zza$zza:zzoz	Landroid/os/IBinder;
    //   85: astore 7
    //   87: bipush 37
    //   89: istore 9
    //   91: aload 7
    //   93: iload 9
    //   95: aload 5
    //   97: aload 6
    //   99: iconst_0
    //   100: invokeinterface 47 5 0
    //   105: pop
    //   106: aload 6
    //   108: invokevirtual 50	android/os/Parcel:readException	()V
    //   111: aload 6
    //   113: invokevirtual 53	android/os/Parcel:recycle	()V
    //   116: aload 5
    //   118: invokevirtual 53	android/os/Parcel:recycle	()V
    //   121: return
    //   122: iconst_0
    //   123: istore 8
    //   125: aconst_null
    //   126: astore 7
    //   128: goto -95 -> 33
    //   131: iconst_0
    //   132: istore 8
    //   134: aconst_null
    //   135: astore 7
    //   137: aload 5
    //   139: iconst_0
    //   140: invokevirtual 40	android/os/Parcel:writeInt	(I)V
    //   143: goto -62 -> 81
    //   146: astore 7
    //   148: aload 6
    //   150: invokevirtual 53	android/os/Parcel:recycle	()V
    //   153: aload 5
    //   155: invokevirtual 53	android/os/Parcel:recycle	()V
    //   158: aload 7
    //   160: athrow
    // Local variable table:
    //   start	length	slot	name	signature
    //   0	161	0	this	zza
    //   0	161	1	paramzzr	zzr
    //   0	161	2	paramInt	int
    //   0	161	3	paramString	String
    //   0	161	4	paramBundle	android.os.Bundle
    //   3	151	5	localParcel1	Parcel
    //   8	141	6	localParcel2	Parcel
    //   12	124	7	localObject1	Object
    //   146	13	7	localObject2	Object
    //   58	75	8	i	int
    //   89	5	9	j	int
    // Exception table:
    //   from	to	target	type
    //   16	21	146	finally
    //   25	31	146	finally
    //   35	40	146	finally
    //   42	46	146	finally
    //   48	52	146	finally
    //   62	67	146	finally
    //   77	81	146	finally
    //   81	85	146	finally
    //   99	106	146	finally
    //   106	111	146	finally
    //   139	143	146	finally
  }
  
  public void zzqV()
  {
    Parcel localParcel1 = Parcel.obtain();
    Parcel localParcel2 = Parcel.obtain();
    Object localObject1 = "com.google.android.gms.common.internal.IGmsServiceBroker";
    try
    {
      localParcel1.writeInterfaceToken((String)localObject1);
      localObject1 = this.zzoz;
      int i = 28;
      ((IBinder)localObject1).transact(i, localParcel1, localParcel2, 0);
      localParcel2.readException();
      return;
    }
    finally
    {
      localParcel2.recycle();
      localParcel1.recycle();
    }
  }
  
  /* Error */
  public void zzr(zzr paramzzr, int paramInt, String paramString, android.os.Bundle paramBundle)
  {
    // Byte code:
    //   0: invokestatic 20	android/os/Parcel:obtain	()Landroid/os/Parcel;
    //   3: astore 5
    //   5: invokestatic 20	android/os/Parcel:obtain	()Landroid/os/Parcel;
    //   8: astore 6
    //   10: ldc 22
    //   12: astore 7
    //   14: aload 5
    //   16: aload 7
    //   18: invokevirtual 26	android/os/Parcel:writeInterfaceToken	(Ljava/lang/String;)V
    //   21: aload_1
    //   22: ifnull +100 -> 122
    //   25: aload_1
    //   26: invokeinterface 32 1 0
    //   31: astore 7
    //   33: aload 5
    //   35: aload 7
    //   37: invokevirtual 36	android/os/Parcel:writeStrongBinder	(Landroid/os/IBinder;)V
    //   40: aload 5
    //   42: iload_2
    //   43: invokevirtual 40	android/os/Parcel:writeInt	(I)V
    //   46: aload 5
    //   48: aload_3
    //   49: invokevirtual 56	android/os/Parcel:writeString	(Ljava/lang/String;)V
    //   52: aload 4
    //   54: ifnull +77 -> 131
    //   57: iconst_1
    //   58: istore 8
    //   60: aload 5
    //   62: iload 8
    //   64: invokevirtual 40	android/os/Parcel:writeInt	(I)V
    //   67: iconst_0
    //   68: istore 8
    //   70: aconst_null
    //   71: astore 7
    //   73: aload 4
    //   75: aload 5
    //   77: iconst_0
    //   78: invokevirtual 64	android/os/Bundle:writeToParcel	(Landroid/os/Parcel;I)V
    //   81: aload_0
    //   82: getfield 14	com/google/android/gms/common/internal/zzs$zza$zza:zzoz	Landroid/os/IBinder;
    //   85: astore 7
    //   87: bipush 38
    //   89: istore 9
    //   91: aload 7
    //   93: iload 9
    //   95: aload 5
    //   97: aload 6
    //   99: iconst_0
    //   100: invokeinterface 47 5 0
    //   105: pop
    //   106: aload 6
    //   108: invokevirtual 50	android/os/Parcel:readException	()V
    //   111: aload 6
    //   113: invokevirtual 53	android/os/Parcel:recycle	()V
    //   116: aload 5
    //   118: invokevirtual 53	android/os/Parcel:recycle	()V
    //   121: return
    //   122: iconst_0
    //   123: istore 8
    //   125: aconst_null
    //   126: astore 7
    //   128: goto -95 -> 33
    //   131: iconst_0
    //   132: istore 8
    //   134: aconst_null
    //   135: astore 7
    //   137: aload 5
    //   139: iconst_0
    //   140: invokevirtual 40	android/os/Parcel:writeInt	(I)V
    //   143: goto -62 -> 81
    //   146: astore 7
    //   148: aload 6
    //   150: invokevirtual 53	android/os/Parcel:recycle	()V
    //   153: aload 5
    //   155: invokevirtual 53	android/os/Parcel:recycle	()V
    //   158: aload 7
    //   160: athrow
    // Local variable table:
    //   start	length	slot	name	signature
    //   0	161	0	this	zza
    //   0	161	1	paramzzr	zzr
    //   0	161	2	paramInt	int
    //   0	161	3	paramString	String
    //   0	161	4	paramBundle	android.os.Bundle
    //   3	151	5	localParcel1	Parcel
    //   8	141	6	localParcel2	Parcel
    //   12	124	7	localObject1	Object
    //   146	13	7	localObject2	Object
    //   58	75	8	i	int
    //   89	5	9	j	int
    // Exception table:
    //   from	to	target	type
    //   16	21	146	finally
    //   25	31	146	finally
    //   35	40	146	finally
    //   42	46	146	finally
    //   48	52	146	finally
    //   62	67	146	finally
    //   77	81	146	finally
    //   81	85	146	finally
    //   99	106	146	finally
    //   106	111	146	finally
    //   139	143	146	finally
  }
  
  /* Error */
  public void zzs(zzr paramzzr, int paramInt, String paramString, android.os.Bundle paramBundle)
  {
    // Byte code:
    //   0: invokestatic 20	android/os/Parcel:obtain	()Landroid/os/Parcel;
    //   3: astore 5
    //   5: invokestatic 20	android/os/Parcel:obtain	()Landroid/os/Parcel;
    //   8: astore 6
    //   10: ldc 22
    //   12: astore 7
    //   14: aload 5
    //   16: aload 7
    //   18: invokevirtual 26	android/os/Parcel:writeInterfaceToken	(Ljava/lang/String;)V
    //   21: aload_1
    //   22: ifnull +100 -> 122
    //   25: aload_1
    //   26: invokeinterface 32 1 0
    //   31: astore 7
    //   33: aload 5
    //   35: aload 7
    //   37: invokevirtual 36	android/os/Parcel:writeStrongBinder	(Landroid/os/IBinder;)V
    //   40: aload 5
    //   42: iload_2
    //   43: invokevirtual 40	android/os/Parcel:writeInt	(I)V
    //   46: aload 5
    //   48: aload_3
    //   49: invokevirtual 56	android/os/Parcel:writeString	(Ljava/lang/String;)V
    //   52: aload 4
    //   54: ifnull +77 -> 131
    //   57: iconst_1
    //   58: istore 8
    //   60: aload 5
    //   62: iload 8
    //   64: invokevirtual 40	android/os/Parcel:writeInt	(I)V
    //   67: iconst_0
    //   68: istore 8
    //   70: aconst_null
    //   71: astore 7
    //   73: aload 4
    //   75: aload 5
    //   77: iconst_0
    //   78: invokevirtual 64	android/os/Bundle:writeToParcel	(Landroid/os/Parcel;I)V
    //   81: aload_0
    //   82: getfield 14	com/google/android/gms/common/internal/zzs$zza$zza:zzoz	Landroid/os/IBinder;
    //   85: astore 7
    //   87: bipush 41
    //   89: istore 9
    //   91: aload 7
    //   93: iload 9
    //   95: aload 5
    //   97: aload 6
    //   99: iconst_0
    //   100: invokeinterface 47 5 0
    //   105: pop
    //   106: aload 6
    //   108: invokevirtual 50	android/os/Parcel:readException	()V
    //   111: aload 6
    //   113: invokevirtual 53	android/os/Parcel:recycle	()V
    //   116: aload 5
    //   118: invokevirtual 53	android/os/Parcel:recycle	()V
    //   121: return
    //   122: iconst_0
    //   123: istore 8
    //   125: aconst_null
    //   126: astore 7
    //   128: goto -95 -> 33
    //   131: iconst_0
    //   132: istore 8
    //   134: aconst_null
    //   135: astore 7
    //   137: aload 5
    //   139: iconst_0
    //   140: invokevirtual 40	android/os/Parcel:writeInt	(I)V
    //   143: goto -62 -> 81
    //   146: astore 7
    //   148: aload 6
    //   150: invokevirtual 53	android/os/Parcel:recycle	()V
    //   153: aload 5
    //   155: invokevirtual 53	android/os/Parcel:recycle	()V
    //   158: aload 7
    //   160: athrow
    // Local variable table:
    //   start	length	slot	name	signature
    //   0	161	0	this	zza
    //   0	161	1	paramzzr	zzr
    //   0	161	2	paramInt	int
    //   0	161	3	paramString	String
    //   0	161	4	paramBundle	android.os.Bundle
    //   3	151	5	localParcel1	Parcel
    //   8	141	6	localParcel2	Parcel
    //   12	124	7	localObject1	Object
    //   146	13	7	localObject2	Object
    //   58	75	8	i	int
    //   89	5	9	j	int
    // Exception table:
    //   from	to	target	type
    //   16	21	146	finally
    //   25	31	146	finally
    //   35	40	146	finally
    //   42	46	146	finally
    //   48	52	146	finally
    //   62	67	146	finally
    //   77	81	146	finally
    //   81	85	146	finally
    //   99	106	146	finally
    //   106	111	146	finally
    //   139	143	146	finally
  }
  
  /* Error */
  public void zzt(zzr paramzzr, int paramInt, String paramString, android.os.Bundle paramBundle)
  {
    // Byte code:
    //   0: invokestatic 20	android/os/Parcel:obtain	()Landroid/os/Parcel;
    //   3: astore 5
    //   5: invokestatic 20	android/os/Parcel:obtain	()Landroid/os/Parcel;
    //   8: astore 6
    //   10: ldc 22
    //   12: astore 7
    //   14: aload 5
    //   16: aload 7
    //   18: invokevirtual 26	android/os/Parcel:writeInterfaceToken	(Ljava/lang/String;)V
    //   21: aload_1
    //   22: ifnull +100 -> 122
    //   25: aload_1
    //   26: invokeinterface 32 1 0
    //   31: astore 7
    //   33: aload 5
    //   35: aload 7
    //   37: invokevirtual 36	android/os/Parcel:writeStrongBinder	(Landroid/os/IBinder;)V
    //   40: aload 5
    //   42: iload_2
    //   43: invokevirtual 40	android/os/Parcel:writeInt	(I)V
    //   46: aload 5
    //   48: aload_3
    //   49: invokevirtual 56	android/os/Parcel:writeString	(Ljava/lang/String;)V
    //   52: aload 4
    //   54: ifnull +77 -> 131
    //   57: iconst_1
    //   58: istore 8
    //   60: aload 5
    //   62: iload 8
    //   64: invokevirtual 40	android/os/Parcel:writeInt	(I)V
    //   67: iconst_0
    //   68: istore 8
    //   70: aconst_null
    //   71: astore 7
    //   73: aload 4
    //   75: aload 5
    //   77: iconst_0
    //   78: invokevirtual 64	android/os/Bundle:writeToParcel	(Landroid/os/Parcel;I)V
    //   81: aload_0
    //   82: getfield 14	com/google/android/gms/common/internal/zzs$zza$zza:zzoz	Landroid/os/IBinder;
    //   85: astore 7
    //   87: bipush 43
    //   89: istore 9
    //   91: aload 7
    //   93: iload 9
    //   95: aload 5
    //   97: aload 6
    //   99: iconst_0
    //   100: invokeinterface 47 5 0
    //   105: pop
    //   106: aload 6
    //   108: invokevirtual 50	android/os/Parcel:readException	()V
    //   111: aload 6
    //   113: invokevirtual 53	android/os/Parcel:recycle	()V
    //   116: aload 5
    //   118: invokevirtual 53	android/os/Parcel:recycle	()V
    //   121: return
    //   122: iconst_0
    //   123: istore 8
    //   125: aconst_null
    //   126: astore 7
    //   128: goto -95 -> 33
    //   131: iconst_0
    //   132: istore 8
    //   134: aconst_null
    //   135: astore 7
    //   137: aload 5
    //   139: iconst_0
    //   140: invokevirtual 40	android/os/Parcel:writeInt	(I)V
    //   143: goto -62 -> 81
    //   146: astore 7
    //   148: aload 6
    //   150: invokevirtual 53	android/os/Parcel:recycle	()V
    //   153: aload 5
    //   155: invokevirtual 53	android/os/Parcel:recycle	()V
    //   158: aload 7
    //   160: athrow
    // Local variable table:
    //   start	length	slot	name	signature
    //   0	161	0	this	zza
    //   0	161	1	paramzzr	zzr
    //   0	161	2	paramInt	int
    //   0	161	3	paramString	String
    //   0	161	4	paramBundle	android.os.Bundle
    //   3	151	5	localParcel1	Parcel
    //   8	141	6	localParcel2	Parcel
    //   12	124	7	localObject1	Object
    //   146	13	7	localObject2	Object
    //   58	75	8	i	int
    //   89	5	9	j	int
    // Exception table:
    //   from	to	target	type
    //   16	21	146	finally
    //   25	31	146	finally
    //   35	40	146	finally
    //   42	46	146	finally
    //   48	52	146	finally
    //   62	67	146	finally
    //   77	81	146	finally
    //   81	85	146	finally
    //   99	106	146	finally
    //   106	111	146	finally
    //   139	143	146	finally
  }
}


/* Location:              C:\Users\haryo\Desktop\enjarify-master\presensi-enjarify.jar!\com\google\android\gms\common\internal\zzs$zza$zza.class
 * Java compiler version: 5 (49.0)
 * JD-Core Version:       0.7.1
 */