package com.google.android.gms.location.internal;

import android.app.PendingIntent;
import android.os.IBinder;
import android.os.Parcel;
import com.google.android.gms.common.api.internal.zzo;
import com.google.android.gms.location.GeofencingRequest;
import com.google.android.gms.location.GestureRequest;
import com.google.android.gms.location.LocationRequest;
import com.google.android.gms.location.LocationSettingsRequest;
import com.google.android.gms.location.zzd;
import java.util.List;

class zzi$zza$zza
  implements zzi
{
  private IBinder zzoz;
  
  zzi$zza$zza(IBinder paramIBinder)
  {
    this.zzoz = paramIBinder;
  }
  
  public IBinder asBinder()
  {
    return this.zzoz;
  }
  
  /* Error */
  public void zza(long paramLong, boolean paramBoolean, PendingIntent paramPendingIntent)
  {
    // Byte code:
    //   0: iconst_1
    //   1: istore 5
    //   3: iconst_0
    //   4: istore 6
    //   6: invokestatic 21	android/os/Parcel:obtain	()Landroid/os/Parcel;
    //   9: astore 7
    //   11: invokestatic 21	android/os/Parcel:obtain	()Landroid/os/Parcel;
    //   14: astore 8
    //   16: ldc 23
    //   18: astore 9
    //   20: aload 7
    //   22: aload 9
    //   24: invokevirtual 27	android/os/Parcel:writeInterfaceToken	(Ljava/lang/String;)V
    //   27: aload 7
    //   29: lload_1
    //   30: invokevirtual 31	android/os/Parcel:writeLong	(J)V
    //   33: iload_3
    //   34: ifeq +82 -> 116
    //   37: aload 7
    //   39: iload 5
    //   41: invokevirtual 35	android/os/Parcel:writeInt	(I)V
    //   44: aload 4
    //   46: ifnull +79 -> 125
    //   49: iconst_1
    //   50: istore 5
    //   52: aload 7
    //   54: iload 5
    //   56: invokevirtual 35	android/os/Parcel:writeInt	(I)V
    //   59: iconst_0
    //   60: istore 5
    //   62: aconst_null
    //   63: astore 10
    //   65: aload 4
    //   67: aload 7
    //   69: iconst_0
    //   70: invokevirtual 41	android/app/PendingIntent:writeToParcel	(Landroid/os/Parcel;I)V
    //   73: aload_0
    //   74: getfield 14	com/google/android/gms/location/internal/zzi$zza$zza:zzoz	Landroid/os/IBinder;
    //   77: astore 10
    //   79: iconst_5
    //   80: istore 6
    //   82: aconst_null
    //   83: astore 9
    //   85: aload 10
    //   87: iload 6
    //   89: aload 7
    //   91: aload 8
    //   93: iconst_0
    //   94: invokeinterface 48 5 0
    //   99: pop
    //   100: aload 8
    //   102: invokevirtual 51	android/os/Parcel:readException	()V
    //   105: aload 8
    //   107: invokevirtual 54	android/os/Parcel:recycle	()V
    //   110: aload 7
    //   112: invokevirtual 54	android/os/Parcel:recycle	()V
    //   115: return
    //   116: iconst_0
    //   117: istore 5
    //   119: aconst_null
    //   120: astore 10
    //   122: goto -85 -> 37
    //   125: iconst_0
    //   126: istore 5
    //   128: aconst_null
    //   129: astore 10
    //   131: aload 7
    //   133: iconst_0
    //   134: invokevirtual 35	android/os/Parcel:writeInt	(I)V
    //   137: goto -64 -> 73
    //   140: astore 10
    //   142: aload 8
    //   144: invokevirtual 54	android/os/Parcel:recycle	()V
    //   147: aload 7
    //   149: invokevirtual 54	android/os/Parcel:recycle	()V
    //   152: aload 10
    //   154: athrow
    // Local variable table:
    //   start	length	slot	name	signature
    //   0	155	0	this	zza
    //   0	155	1	paramLong	long
    //   0	155	3	paramBoolean	boolean
    //   0	155	4	paramPendingIntent	PendingIntent
    //   1	126	5	i	int
    //   4	84	6	j	int
    //   9	139	7	localParcel1	Parcel
    //   14	129	8	localParcel2	Parcel
    //   18	66	9	str	String
    //   63	67	10	localIBinder	IBinder
    //   140	13	10	localObject	Object
    // Exception table:
    //   from	to	target	type
    //   22	27	140	finally
    //   29	33	140	finally
    //   39	44	140	finally
    //   54	59	140	finally
    //   69	73	140	finally
    //   73	77	140	finally
    //   93	100	140	finally
    //   100	105	140	finally
    //   133	137	140	finally
  }
  
  /* Error */
  public void zza(PendingIntent paramPendingIntent)
  {
    // Byte code:
    //   0: invokestatic 21	android/os/Parcel:obtain	()Landroid/os/Parcel;
    //   3: astore_2
    //   4: invokestatic 21	android/os/Parcel:obtain	()Landroid/os/Parcel;
    //   7: astore_3
    //   8: ldc 23
    //   10: astore 4
    //   12: aload_2
    //   13: aload 4
    //   15: invokevirtual 27	android/os/Parcel:writeInterfaceToken	(Ljava/lang/String;)V
    //   18: aload_1
    //   19: ifnull +60 -> 79
    //   22: iconst_1
    //   23: istore 5
    //   25: aload_2
    //   26: iload 5
    //   28: invokevirtual 35	android/os/Parcel:writeInt	(I)V
    //   31: iconst_0
    //   32: istore 5
    //   34: aconst_null
    //   35: astore 4
    //   37: aload_1
    //   38: aload_2
    //   39: iconst_0
    //   40: invokevirtual 41	android/app/PendingIntent:writeToParcel	(Landroid/os/Parcel;I)V
    //   43: aload_0
    //   44: getfield 14	com/google/android/gms/location/internal/zzi$zza$zza:zzoz	Landroid/os/IBinder;
    //   47: astore 4
    //   49: bipush 6
    //   51: istore 6
    //   53: aload 4
    //   55: iload 6
    //   57: aload_2
    //   58: aload_3
    //   59: iconst_0
    //   60: invokeinterface 48 5 0
    //   65: pop
    //   66: aload_3
    //   67: invokevirtual 51	android/os/Parcel:readException	()V
    //   70: aload_3
    //   71: invokevirtual 54	android/os/Parcel:recycle	()V
    //   74: aload_2
    //   75: invokevirtual 54	android/os/Parcel:recycle	()V
    //   78: return
    //   79: iconst_0
    //   80: istore 5
    //   82: aconst_null
    //   83: astore 4
    //   85: aload_2
    //   86: iconst_0
    //   87: invokevirtual 35	android/os/Parcel:writeInt	(I)V
    //   90: goto -47 -> 43
    //   93: astore 4
    //   95: aload_3
    //   96: invokevirtual 54	android/os/Parcel:recycle	()V
    //   99: aload_2
    //   100: invokevirtual 54	android/os/Parcel:recycle	()V
    //   103: aload 4
    //   105: athrow
    // Local variable table:
    //   start	length	slot	name	signature
    //   0	106	0	this	zza
    //   0	106	1	paramPendingIntent	PendingIntent
    //   3	97	2	localParcel1	Parcel
    //   7	89	3	localParcel2	Parcel
    //   10	74	4	localObject1	Object
    //   93	11	4	localObject2	Object
    //   23	58	5	i	int
    //   51	5	6	j	int
    // Exception table:
    //   from	to	target	type
    //   13	18	93	finally
    //   26	31	93	finally
    //   39	43	93	finally
    //   43	47	93	finally
    //   59	66	93	finally
    //   66	70	93	finally
    //   86	90	93	finally
  }
  
  public void zza(PendingIntent paramPendingIntent, zzo paramzzo)
  {
    Parcel localParcel1 = Parcel.obtain();
    Parcel localParcel2 = Parcel.obtain();
    Object localObject3;
    for (Object localObject1 = "com.google.android.gms.location.internal.IGoogleLocationManagerService";; localObject3 = null) {
      try
      {
        localParcel1.writeInterfaceToken((String)localObject1);
        if (paramPendingIntent != null)
        {
          i = 1;
          localParcel1.writeInt(i);
          i = 0;
          localObject1 = null;
          paramPendingIntent.writeToParcel(localParcel1, 0);
        }
        while (paramzzo != null)
        {
          localObject1 = paramzzo.asBinder();
          localParcel1.writeStrongBinder((IBinder)localObject1);
          localObject1 = this.zzoz;
          int j = 65;
          ((IBinder)localObject1).transact(j, localParcel1, localParcel2, 0);
          localParcel2.readException();
          return;
          i = 0;
          localObject1 = null;
          localParcel1.writeInt(0);
        }
        int i = 0;
      }
      finally
      {
        localParcel2.recycle();
        localParcel1.recycle();
      }
    }
  }
  
  public void zza(PendingIntent paramPendingIntent, zzh paramzzh, String paramString)
  {
    Parcel localParcel1 = Parcel.obtain();
    Parcel localParcel2 = Parcel.obtain();
    Object localObject3;
    for (Object localObject1 = "com.google.android.gms.location.internal.IGoogleLocationManagerService";; localObject3 = null) {
      try
      {
        localParcel1.writeInterfaceToken((String)localObject1);
        if (paramPendingIntent != null)
        {
          i = 1;
          localParcel1.writeInt(i);
          i = 0;
          localObject1 = null;
          paramPendingIntent.writeToParcel(localParcel1, 0);
        }
        while (paramzzh != null)
        {
          localObject1 = paramzzh.asBinder();
          localParcel1.writeStrongBinder((IBinder)localObject1);
          localParcel1.writeString(paramString);
          localObject1 = this.zzoz;
          int j = 2;
          ((IBinder)localObject1).transact(j, localParcel1, localParcel2, 0);
          localParcel2.readException();
          return;
          i = 0;
          localObject1 = null;
          localParcel1.writeInt(0);
        }
        int i = 0;
      }
      finally
      {
        localParcel2.recycle();
        localParcel1.recycle();
      }
    }
  }
  
  /* Error */
  public void zza(android.location.Location paramLocation, int paramInt)
  {
    // Byte code:
    //   0: invokestatic 21	android/os/Parcel:obtain	()Landroid/os/Parcel;
    //   3: astore_3
    //   4: invokestatic 21	android/os/Parcel:obtain	()Landroid/os/Parcel;
    //   7: astore 4
    //   9: ldc 23
    //   11: astore 5
    //   13: aload_3
    //   14: aload 5
    //   16: invokevirtual 27	android/os/Parcel:writeInterfaceToken	(Ljava/lang/String;)V
    //   19: aload_1
    //   20: ifnull +68 -> 88
    //   23: iconst_1
    //   24: istore 6
    //   26: aload_3
    //   27: iload 6
    //   29: invokevirtual 35	android/os/Parcel:writeInt	(I)V
    //   32: iconst_0
    //   33: istore 6
    //   35: aconst_null
    //   36: astore 5
    //   38: aload_1
    //   39: aload_3
    //   40: iconst_0
    //   41: invokevirtual 76	android/location/Location:writeToParcel	(Landroid/os/Parcel;I)V
    //   44: aload_3
    //   45: iload_2
    //   46: invokevirtual 35	android/os/Parcel:writeInt	(I)V
    //   49: aload_0
    //   50: getfield 14	com/google/android/gms/location/internal/zzi$zza$zza:zzoz	Landroid/os/IBinder;
    //   53: astore 5
    //   55: bipush 26
    //   57: istore 7
    //   59: aload 5
    //   61: iload 7
    //   63: aload_3
    //   64: aload 4
    //   66: iconst_0
    //   67: invokeinterface 48 5 0
    //   72: pop
    //   73: aload 4
    //   75: invokevirtual 51	android/os/Parcel:readException	()V
    //   78: aload 4
    //   80: invokevirtual 54	android/os/Parcel:recycle	()V
    //   83: aload_3
    //   84: invokevirtual 54	android/os/Parcel:recycle	()V
    //   87: return
    //   88: iconst_0
    //   89: istore 6
    //   91: aconst_null
    //   92: astore 5
    //   94: aload_3
    //   95: iconst_0
    //   96: invokevirtual 35	android/os/Parcel:writeInt	(I)V
    //   99: goto -55 -> 44
    //   102: astore 5
    //   104: aload 4
    //   106: invokevirtual 54	android/os/Parcel:recycle	()V
    //   109: aload_3
    //   110: invokevirtual 54	android/os/Parcel:recycle	()V
    //   113: aload 5
    //   115: athrow
    // Local variable table:
    //   start	length	slot	name	signature
    //   0	116	0	this	zza
    //   0	116	1	paramLocation	android.location.Location
    //   0	116	2	paramInt	int
    //   3	107	3	localParcel1	Parcel
    //   7	98	4	localParcel2	Parcel
    //   11	82	5	localObject1	Object
    //   102	12	5	localObject2	Object
    //   24	66	6	i	int
    //   57	5	7	j	int
    // Exception table:
    //   from	to	target	type
    //   14	19	102	finally
    //   27	32	102	finally
    //   40	44	102	finally
    //   45	49	102	finally
    //   49	53	102	finally
    //   66	73	102	finally
    //   73	78	102	finally
    //   95	99	102	finally
  }
  
  public void zza(GeofencingRequest paramGeofencingRequest, PendingIntent paramPendingIntent, zzh paramzzh)
  {
    Parcel localParcel1 = Parcel.obtain();
    Parcel localParcel2 = Parcel.obtain();
    Object localObject1 = "com.google.android.gms.location.internal.IGoogleLocationManagerService";
    for (;;)
    {
      try
      {
        localParcel1.writeInterfaceToken((String)localObject1);
        if (paramGeofencingRequest != null)
        {
          i = 1;
          localParcel1.writeInt(i);
          i = 0;
          localObject1 = null;
          paramGeofencingRequest.writeToParcel(localParcel1, 0);
          if (paramPendingIntent != null)
          {
            i = 1;
            localParcel1.writeInt(i);
            i = 0;
            localObject1 = null;
            paramPendingIntent.writeToParcel(localParcel1, 0);
            if (paramzzh == null) {
              break label180;
            }
            localObject1 = paramzzh.asBinder();
            localParcel1.writeStrongBinder((IBinder)localObject1);
            localObject1 = this.zzoz;
            int j = 57;
            ((IBinder)localObject1).transact(j, localParcel1, localParcel2, 0);
            localParcel2.readException();
          }
        }
        else
        {
          i = 0;
          localObject1 = null;
          localParcel1.writeInt(0);
          continue;
        }
        i = 0;
      }
      finally
      {
        localParcel2.recycle();
        localParcel1.recycle();
      }
      Object localObject3 = null;
      localParcel1.writeInt(0);
      continue;
      label180:
      int i = 0;
      localObject3 = null;
    }
  }
  
  public void zza(GestureRequest paramGestureRequest, PendingIntent paramPendingIntent, zzo paramzzo)
  {
    Parcel localParcel1 = Parcel.obtain();
    Parcel localParcel2 = Parcel.obtain();
    Object localObject1 = "com.google.android.gms.location.internal.IGoogleLocationManagerService";
    for (;;)
    {
      try
      {
        localParcel1.writeInterfaceToken((String)localObject1);
        if (paramGestureRequest != null)
        {
          i = 1;
          localParcel1.writeInt(i);
          i = 0;
          localObject1 = null;
          paramGestureRequest.writeToParcel(localParcel1, 0);
          if (paramPendingIntent != null)
          {
            i = 1;
            localParcel1.writeInt(i);
            i = 0;
            localObject1 = null;
            paramPendingIntent.writeToParcel(localParcel1, 0);
            if (paramzzo == null) {
              break label180;
            }
            localObject1 = paramzzo.asBinder();
            localParcel1.writeStrongBinder((IBinder)localObject1);
            localObject1 = this.zzoz;
            int j = 60;
            ((IBinder)localObject1).transact(j, localParcel1, localParcel2, 0);
            localParcel2.readException();
          }
        }
        else
        {
          i = 0;
          localObject1 = null;
          localParcel1.writeInt(0);
          continue;
        }
        i = 0;
      }
      finally
      {
        localParcel2.recycle();
        localParcel1.recycle();
      }
      Object localObject3 = null;
      localParcel1.writeInt(0);
      continue;
      label180:
      int i = 0;
      localObject3 = null;
    }
  }
  
  public void zza(LocationRequest paramLocationRequest, PendingIntent paramPendingIntent)
  {
    Parcel localParcel1 = Parcel.obtain();
    Parcel localParcel2 = Parcel.obtain();
    Object localObject1 = "com.google.android.gms.location.internal.IGoogleLocationManagerService";
    for (;;)
    {
      try
      {
        localParcel1.writeInterfaceToken((String)localObject1);
        if (paramLocationRequest != null)
        {
          i = 1;
          localParcel1.writeInt(i);
          i = 0;
          localObject1 = null;
          paramLocationRequest.writeToParcel(localParcel1, 0);
          if (paramPendingIntent != null)
          {
            i = 1;
            localParcel1.writeInt(i);
            i = 0;
            localObject1 = null;
            paramPendingIntent.writeToParcel(localParcel1, 0);
            localObject1 = this.zzoz;
            int j = 9;
            ((IBinder)localObject1).transact(j, localParcel1, localParcel2, 0);
            localParcel2.readException();
          }
        }
        else
        {
          i = 0;
          localObject1 = null;
          localParcel1.writeInt(0);
          continue;
        }
        int i = 0;
      }
      finally
      {
        localParcel2.recycle();
        localParcel1.recycle();
      }
      Object localObject3 = null;
      localParcel1.writeInt(0);
    }
  }
  
  public void zza(LocationRequest paramLocationRequest, zzd paramzzd)
  {
    Parcel localParcel1 = Parcel.obtain();
    Parcel localParcel2 = Parcel.obtain();
    Object localObject3;
    for (Object localObject1 = "com.google.android.gms.location.internal.IGoogleLocationManagerService";; localObject3 = null) {
      try
      {
        localParcel1.writeInterfaceToken((String)localObject1);
        if (paramLocationRequest != null)
        {
          i = 1;
          localParcel1.writeInt(i);
          i = 0;
          localObject1 = null;
          paramLocationRequest.writeToParcel(localParcel1, 0);
        }
        while (paramzzd != null)
        {
          localObject1 = paramzzd.asBinder();
          localParcel1.writeStrongBinder((IBinder)localObject1);
          localObject1 = this.zzoz;
          int j = 8;
          ((IBinder)localObject1).transact(j, localParcel1, localParcel2, 0);
          localParcel2.readException();
          return;
          i = 0;
          localObject1 = null;
          localParcel1.writeInt(0);
        }
        int i = 0;
      }
      finally
      {
        localParcel2.recycle();
        localParcel1.recycle();
      }
    }
  }
  
  public void zza(LocationRequest paramLocationRequest, zzd paramzzd, String paramString)
  {
    Parcel localParcel1 = Parcel.obtain();
    Parcel localParcel2 = Parcel.obtain();
    Object localObject3;
    for (Object localObject1 = "com.google.android.gms.location.internal.IGoogleLocationManagerService";; localObject3 = null) {
      try
      {
        localParcel1.writeInterfaceToken((String)localObject1);
        if (paramLocationRequest != null)
        {
          i = 1;
          localParcel1.writeInt(i);
          i = 0;
          localObject1 = null;
          paramLocationRequest.writeToParcel(localParcel1, 0);
        }
        while (paramzzd != null)
        {
          localObject1 = paramzzd.asBinder();
          localParcel1.writeStrongBinder((IBinder)localObject1);
          localParcel1.writeString(paramString);
          localObject1 = this.zzoz;
          int j = 20;
          ((IBinder)localObject1).transact(j, localParcel1, localParcel2, 0);
          localParcel2.readException();
          return;
          i = 0;
          localObject1 = null;
          localParcel1.writeInt(0);
        }
        int i = 0;
      }
      finally
      {
        localParcel2.recycle();
        localParcel1.recycle();
      }
    }
  }
  
  public void zza(LocationSettingsRequest paramLocationSettingsRequest, zzj paramzzj, String paramString)
  {
    Parcel localParcel1 = Parcel.obtain();
    Parcel localParcel2 = Parcel.obtain();
    Object localObject3;
    for (Object localObject1 = "com.google.android.gms.location.internal.IGoogleLocationManagerService";; localObject3 = null) {
      try
      {
        localParcel1.writeInterfaceToken((String)localObject1);
        if (paramLocationSettingsRequest != null)
        {
          i = 1;
          localParcel1.writeInt(i);
          i = 0;
          localObject1 = null;
          paramLocationSettingsRequest.writeToParcel(localParcel1, 0);
        }
        while (paramzzj != null)
        {
          localObject1 = paramzzj.asBinder();
          localParcel1.writeStrongBinder((IBinder)localObject1);
          localParcel1.writeString(paramString);
          localObject1 = this.zzoz;
          int j = 63;
          ((IBinder)localObject1).transact(j, localParcel1, localParcel2, 0);
          localParcel2.readException();
          return;
          i = 0;
          localObject1 = null;
          localParcel1.writeInt(0);
        }
        int i = 0;
      }
      finally
      {
        localParcel2.recycle();
        localParcel1.recycle();
      }
    }
  }
  
  public void zza(LocationRequestInternal paramLocationRequestInternal, PendingIntent paramPendingIntent)
  {
    Parcel localParcel1 = Parcel.obtain();
    Parcel localParcel2 = Parcel.obtain();
    Object localObject1 = "com.google.android.gms.location.internal.IGoogleLocationManagerService";
    for (;;)
    {
      try
      {
        localParcel1.writeInterfaceToken((String)localObject1);
        if (paramLocationRequestInternal != null)
        {
          i = 1;
          localParcel1.writeInt(i);
          i = 0;
          localObject1 = null;
          paramLocationRequestInternal.writeToParcel(localParcel1, 0);
          if (paramPendingIntent != null)
          {
            i = 1;
            localParcel1.writeInt(i);
            i = 0;
            localObject1 = null;
            paramPendingIntent.writeToParcel(localParcel1, 0);
            localObject1 = this.zzoz;
            int j = 53;
            ((IBinder)localObject1).transact(j, localParcel1, localParcel2, 0);
            localParcel2.readException();
          }
        }
        else
        {
          i = 0;
          localObject1 = null;
          localParcel1.writeInt(0);
          continue;
        }
        int i = 0;
      }
      finally
      {
        localParcel2.recycle();
        localParcel1.recycle();
      }
      Object localObject3 = null;
      localParcel1.writeInt(0);
    }
  }
  
  public void zza(LocationRequestInternal paramLocationRequestInternal, zzd paramzzd)
  {
    Parcel localParcel1 = Parcel.obtain();
    Parcel localParcel2 = Parcel.obtain();
    Object localObject3;
    for (Object localObject1 = "com.google.android.gms.location.internal.IGoogleLocationManagerService";; localObject3 = null) {
      try
      {
        localParcel1.writeInterfaceToken((String)localObject1);
        if (paramLocationRequestInternal != null)
        {
          i = 1;
          localParcel1.writeInt(i);
          i = 0;
          localObject1 = null;
          paramLocationRequestInternal.writeToParcel(localParcel1, 0);
        }
        while (paramzzd != null)
        {
          localObject1 = paramzzd.asBinder();
          localParcel1.writeStrongBinder((IBinder)localObject1);
          localObject1 = this.zzoz;
          int j = 52;
          ((IBinder)localObject1).transact(j, localParcel1, localParcel2, 0);
          localParcel2.readException();
          return;
          i = 0;
          localObject1 = null;
          localParcel1.writeInt(0);
        }
        int i = 0;
      }
      finally
      {
        localParcel2.recycle();
        localParcel1.recycle();
      }
    }
  }
  
  /* Error */
  public void zza(LocationRequestUpdateData paramLocationRequestUpdateData)
  {
    // Byte code:
    //   0: invokestatic 21	android/os/Parcel:obtain	()Landroid/os/Parcel;
    //   3: astore_2
    //   4: invokestatic 21	android/os/Parcel:obtain	()Landroid/os/Parcel;
    //   7: astore_3
    //   8: ldc 23
    //   10: astore 4
    //   12: aload_2
    //   13: aload 4
    //   15: invokevirtual 27	android/os/Parcel:writeInterfaceToken	(Ljava/lang/String;)V
    //   18: aload_1
    //   19: ifnull +60 -> 79
    //   22: iconst_1
    //   23: istore 5
    //   25: aload_2
    //   26: iload 5
    //   28: invokevirtual 35	android/os/Parcel:writeInt	(I)V
    //   31: iconst_0
    //   32: istore 5
    //   34: aconst_null
    //   35: astore 4
    //   37: aload_1
    //   38: aload_2
    //   39: iconst_0
    //   40: invokevirtual 109	com/google/android/gms/location/internal/LocationRequestUpdateData:writeToParcel	(Landroid/os/Parcel;I)V
    //   43: aload_0
    //   44: getfield 14	com/google/android/gms/location/internal/zzi$zza$zza:zzoz	Landroid/os/IBinder;
    //   47: astore 4
    //   49: bipush 59
    //   51: istore 6
    //   53: aload 4
    //   55: iload 6
    //   57: aload_2
    //   58: aload_3
    //   59: iconst_0
    //   60: invokeinterface 48 5 0
    //   65: pop
    //   66: aload_3
    //   67: invokevirtual 51	android/os/Parcel:readException	()V
    //   70: aload_3
    //   71: invokevirtual 54	android/os/Parcel:recycle	()V
    //   74: aload_2
    //   75: invokevirtual 54	android/os/Parcel:recycle	()V
    //   78: return
    //   79: iconst_0
    //   80: istore 5
    //   82: aconst_null
    //   83: astore 4
    //   85: aload_2
    //   86: iconst_0
    //   87: invokevirtual 35	android/os/Parcel:writeInt	(I)V
    //   90: goto -47 -> 43
    //   93: astore 4
    //   95: aload_3
    //   96: invokevirtual 54	android/os/Parcel:recycle	()V
    //   99: aload_2
    //   100: invokevirtual 54	android/os/Parcel:recycle	()V
    //   103: aload 4
    //   105: athrow
    // Local variable table:
    //   start	length	slot	name	signature
    //   0	106	0	this	zza
    //   0	106	1	paramLocationRequestUpdateData	LocationRequestUpdateData
    //   3	97	2	localParcel1	Parcel
    //   7	89	3	localParcel2	Parcel
    //   10	74	4	localObject1	Object
    //   93	11	4	localObject2	Object
    //   23	58	5	i	int
    //   51	5	6	j	int
    // Exception table:
    //   from	to	target	type
    //   13	18	93	finally
    //   26	31	93	finally
    //   39	43	93	finally
    //   43	47	93	finally
    //   59	66	93	finally
    //   66	70	93	finally
    //   86	90	93	finally
  }
  
  /* Error */
  public void zza(zzg paramzzg)
  {
    // Byte code:
    //   0: invokestatic 21	android/os/Parcel:obtain	()Landroid/os/Parcel;
    //   3: astore_2
    //   4: invokestatic 21	android/os/Parcel:obtain	()Landroid/os/Parcel;
    //   7: astore_3
    //   8: ldc 23
    //   10: astore 4
    //   12: aload_2
    //   13: aload 4
    //   15: invokevirtual 27	android/os/Parcel:writeInterfaceToken	(Ljava/lang/String;)V
    //   18: aload_1
    //   19: ifnull +53 -> 72
    //   22: aload_1
    //   23: invokeinterface 113 1 0
    //   28: astore 4
    //   30: aload_2
    //   31: aload 4
    //   33: invokevirtual 65	android/os/Parcel:writeStrongBinder	(Landroid/os/IBinder;)V
    //   36: aload_0
    //   37: getfield 14	com/google/android/gms/location/internal/zzi$zza$zza:zzoz	Landroid/os/IBinder;
    //   40: astore 4
    //   42: bipush 67
    //   44: istore 5
    //   46: aload 4
    //   48: iload 5
    //   50: aload_2
    //   51: aload_3
    //   52: iconst_0
    //   53: invokeinterface 48 5 0
    //   58: pop
    //   59: aload_3
    //   60: invokevirtual 51	android/os/Parcel:readException	()V
    //   63: aload_3
    //   64: invokevirtual 54	android/os/Parcel:recycle	()V
    //   67: aload_2
    //   68: invokevirtual 54	android/os/Parcel:recycle	()V
    //   71: return
    //   72: aconst_null
    //   73: astore 4
    //   75: goto -45 -> 30
    //   78: astore 4
    //   80: aload_3
    //   81: invokevirtual 54	android/os/Parcel:recycle	()V
    //   84: aload_2
    //   85: invokevirtual 54	android/os/Parcel:recycle	()V
    //   88: aload 4
    //   90: athrow
    // Local variable table:
    //   start	length	slot	name	signature
    //   0	91	0	this	zza
    //   0	91	1	paramzzg	zzg
    //   3	82	2	localParcel1	Parcel
    //   7	74	3	localParcel2	Parcel
    //   10	64	4	localObject1	Object
    //   78	11	4	localObject2	Object
    //   44	5	5	i	int
    // Exception table:
    //   from	to	target	type
    //   13	18	78	finally
    //   22	28	78	finally
    //   31	36	78	finally
    //   36	40	78	finally
    //   52	59	78	finally
    //   59	63	78	finally
  }
  
  /* Error */
  public void zza(zzh paramzzh, String paramString)
  {
    // Byte code:
    //   0: invokestatic 21	android/os/Parcel:obtain	()Landroid/os/Parcel;
    //   3: astore_3
    //   4: invokestatic 21	android/os/Parcel:obtain	()Landroid/os/Parcel;
    //   7: astore 4
    //   9: ldc 23
    //   11: astore 5
    //   13: aload_3
    //   14: aload 5
    //   16: invokevirtual 27	android/os/Parcel:writeInterfaceToken	(Ljava/lang/String;)V
    //   19: aload_1
    //   20: ifnull +60 -> 80
    //   23: aload_1
    //   24: invokeinterface 69 1 0
    //   29: astore 5
    //   31: aload_3
    //   32: aload 5
    //   34: invokevirtual 65	android/os/Parcel:writeStrongBinder	(Landroid/os/IBinder;)V
    //   37: aload_3
    //   38: aload_2
    //   39: invokevirtual 72	android/os/Parcel:writeString	(Ljava/lang/String;)V
    //   42: aload_0
    //   43: getfield 14	com/google/android/gms/location/internal/zzi$zza$zza:zzoz	Landroid/os/IBinder;
    //   46: astore 5
    //   48: iconst_4
    //   49: istore 6
    //   51: aload 5
    //   53: iload 6
    //   55: aload_3
    //   56: aload 4
    //   58: iconst_0
    //   59: invokeinterface 48 5 0
    //   64: pop
    //   65: aload 4
    //   67: invokevirtual 51	android/os/Parcel:readException	()V
    //   70: aload 4
    //   72: invokevirtual 54	android/os/Parcel:recycle	()V
    //   75: aload_3
    //   76: invokevirtual 54	android/os/Parcel:recycle	()V
    //   79: return
    //   80: aconst_null
    //   81: astore 5
    //   83: goto -52 -> 31
    //   86: astore 5
    //   88: aload 4
    //   90: invokevirtual 54	android/os/Parcel:recycle	()V
    //   93: aload_3
    //   94: invokevirtual 54	android/os/Parcel:recycle	()V
    //   97: aload 5
    //   99: athrow
    // Local variable table:
    //   start	length	slot	name	signature
    //   0	100	0	this	zza
    //   0	100	1	paramzzh	zzh
    //   0	100	2	paramString	String
    //   3	91	3	localParcel1	Parcel
    //   7	82	4	localParcel2	Parcel
    //   11	71	5	localObject1	Object
    //   86	12	5	localObject2	Object
    //   49	5	6	i	int
    // Exception table:
    //   from	to	target	type
    //   14	19	86	finally
    //   23	29	86	finally
    //   32	37	86	finally
    //   38	42	86	finally
    //   42	46	86	finally
    //   58	65	86	finally
    //   65	70	86	finally
  }
  
  /* Error */
  public void zza(zzd paramzzd)
  {
    // Byte code:
    //   0: invokestatic 21	android/os/Parcel:obtain	()Landroid/os/Parcel;
    //   3: astore_2
    //   4: invokestatic 21	android/os/Parcel:obtain	()Landroid/os/Parcel;
    //   7: astore_3
    //   8: ldc 23
    //   10: astore 4
    //   12: aload_2
    //   13: aload 4
    //   15: invokevirtual 27	android/os/Parcel:writeInterfaceToken	(Ljava/lang/String;)V
    //   18: aload_1
    //   19: ifnull +53 -> 72
    //   22: aload_1
    //   23: invokeinterface 92 1 0
    //   28: astore 4
    //   30: aload_2
    //   31: aload 4
    //   33: invokevirtual 65	android/os/Parcel:writeStrongBinder	(Landroid/os/IBinder;)V
    //   36: aload_0
    //   37: getfield 14	com/google/android/gms/location/internal/zzi$zza$zza:zzoz	Landroid/os/IBinder;
    //   40: astore 4
    //   42: bipush 10
    //   44: istore 5
    //   46: aload 4
    //   48: iload 5
    //   50: aload_2
    //   51: aload_3
    //   52: iconst_0
    //   53: invokeinterface 48 5 0
    //   58: pop
    //   59: aload_3
    //   60: invokevirtual 51	android/os/Parcel:readException	()V
    //   63: aload_3
    //   64: invokevirtual 54	android/os/Parcel:recycle	()V
    //   67: aload_2
    //   68: invokevirtual 54	android/os/Parcel:recycle	()V
    //   71: return
    //   72: aconst_null
    //   73: astore 4
    //   75: goto -45 -> 30
    //   78: astore 4
    //   80: aload_3
    //   81: invokevirtual 54	android/os/Parcel:recycle	()V
    //   84: aload_2
    //   85: invokevirtual 54	android/os/Parcel:recycle	()V
    //   88: aload 4
    //   90: athrow
    // Local variable table:
    //   start	length	slot	name	signature
    //   0	91	0	this	zza
    //   0	91	1	paramzzd	zzd
    //   3	82	2	localParcel1	Parcel
    //   7	74	3	localParcel2	Parcel
    //   10	64	4	localObject1	Object
    //   78	11	4	localObject2	Object
    //   44	5	5	i	int
    // Exception table:
    //   from	to	target	type
    //   13	18	78	finally
    //   22	28	78	finally
    //   31	36	78	finally
    //   36	40	78	finally
    //   52	59	78	finally
    //   59	63	78	finally
  }
  
  public void zza(List paramList, PendingIntent paramPendingIntent, zzh paramzzh, String paramString)
  {
    Parcel localParcel1 = Parcel.obtain();
    Parcel localParcel2 = Parcel.obtain();
    Object localObject3;
    for (Object localObject1 = "com.google.android.gms.location.internal.IGoogleLocationManagerService";; localObject3 = null) {
      try
      {
        localParcel1.writeInterfaceToken((String)localObject1);
        localParcel1.writeTypedList(paramList);
        if (paramPendingIntent != null)
        {
          i = 1;
          localParcel1.writeInt(i);
          i = 0;
          localObject1 = null;
          paramPendingIntent.writeToParcel(localParcel1, 0);
        }
        while (paramzzh != null)
        {
          localObject1 = paramzzh.asBinder();
          localParcel1.writeStrongBinder((IBinder)localObject1);
          localParcel1.writeString(paramString);
          localObject1 = this.zzoz;
          int j = 1;
          ((IBinder)localObject1).transact(j, localParcel1, localParcel2, 0);
          localParcel2.readException();
          return;
          i = 0;
          localObject1 = null;
          localParcel1.writeInt(0);
        }
        int i = 0;
      }
      finally
      {
        localParcel2.recycle();
        localParcel1.recycle();
      }
    }
  }
  
  /* Error */
  public void zza(String[] paramArrayOfString, zzh paramzzh, String paramString)
  {
    // Byte code:
    //   0: invokestatic 21	android/os/Parcel:obtain	()Landroid/os/Parcel;
    //   3: astore 4
    //   5: invokestatic 21	android/os/Parcel:obtain	()Landroid/os/Parcel;
    //   8: astore 5
    //   10: ldc 23
    //   12: astore 6
    //   14: aload 4
    //   16: aload 6
    //   18: invokevirtual 27	android/os/Parcel:writeInterfaceToken	(Ljava/lang/String;)V
    //   21: aload 4
    //   23: aload_1
    //   24: invokevirtual 124	android/os/Parcel:writeStringArray	([Ljava/lang/String;)V
    //   27: aload_2
    //   28: ifnull +64 -> 92
    //   31: aload_2
    //   32: invokeinterface 69 1 0
    //   37: astore 6
    //   39: aload 4
    //   41: aload 6
    //   43: invokevirtual 65	android/os/Parcel:writeStrongBinder	(Landroid/os/IBinder;)V
    //   46: aload 4
    //   48: aload_3
    //   49: invokevirtual 72	android/os/Parcel:writeString	(Ljava/lang/String;)V
    //   52: aload_0
    //   53: getfield 14	com/google/android/gms/location/internal/zzi$zza$zza:zzoz	Landroid/os/IBinder;
    //   56: astore 6
    //   58: iconst_3
    //   59: istore 7
    //   61: aload 6
    //   63: iload 7
    //   65: aload 4
    //   67: aload 5
    //   69: iconst_0
    //   70: invokeinterface 48 5 0
    //   75: pop
    //   76: aload 5
    //   78: invokevirtual 51	android/os/Parcel:readException	()V
    //   81: aload 5
    //   83: invokevirtual 54	android/os/Parcel:recycle	()V
    //   86: aload 4
    //   88: invokevirtual 54	android/os/Parcel:recycle	()V
    //   91: return
    //   92: aconst_null
    //   93: astore 6
    //   95: goto -56 -> 39
    //   98: astore 6
    //   100: aload 5
    //   102: invokevirtual 54	android/os/Parcel:recycle	()V
    //   105: aload 4
    //   107: invokevirtual 54	android/os/Parcel:recycle	()V
    //   110: aload 6
    //   112: athrow
    // Local variable table:
    //   start	length	slot	name	signature
    //   0	113	0	this	zza
    //   0	113	1	paramArrayOfString	String[]
    //   0	113	2	paramzzh	zzh
    //   0	113	3	paramString	String
    //   3	103	4	localParcel1	Parcel
    //   8	93	5	localParcel2	Parcel
    //   12	82	6	localObject1	Object
    //   98	13	6	localObject2	Object
    //   59	5	7	i	int
    // Exception table:
    //   from	to	target	type
    //   16	21	98	finally
    //   23	27	98	finally
    //   31	37	98	finally
    //   41	46	98	finally
    //   48	52	98	finally
    //   52	56	98	finally
    //   69	76	98	finally
    //   76	81	98	finally
  }
  
  public void zzam(boolean paramBoolean)
  {
    int i = 0;
    IBinder localIBinder = null;
    Parcel localParcel1 = Parcel.obtain();
    Parcel localParcel2 = Parcel.obtain();
    String str = "com.google.android.gms.location.internal.IGoogleLocationManagerService";
    try
    {
      localParcel1.writeInterfaceToken(str);
      if (paramBoolean) {
        i = 1;
      }
      localParcel1.writeInt(i);
      localIBinder = this.zzoz;
      int j = 12;
      localIBinder.transact(j, localParcel1, localParcel2, 0);
      localParcel2.readException();
      return;
    }
    finally
    {
      localParcel2.recycle();
      localParcel1.recycle();
    }
  }
  
  /* Error */
  public void zzb(PendingIntent paramPendingIntent)
  {
    // Byte code:
    //   0: invokestatic 21	android/os/Parcel:obtain	()Landroid/os/Parcel;
    //   3: astore_2
    //   4: invokestatic 21	android/os/Parcel:obtain	()Landroid/os/Parcel;
    //   7: astore_3
    //   8: ldc 23
    //   10: astore 4
    //   12: aload_2
    //   13: aload 4
    //   15: invokevirtual 27	android/os/Parcel:writeInterfaceToken	(Ljava/lang/String;)V
    //   18: aload_1
    //   19: ifnull +60 -> 79
    //   22: iconst_1
    //   23: istore 5
    //   25: aload_2
    //   26: iload 5
    //   28: invokevirtual 35	android/os/Parcel:writeInt	(I)V
    //   31: iconst_0
    //   32: istore 5
    //   34: aconst_null
    //   35: astore 4
    //   37: aload_1
    //   38: aload_2
    //   39: iconst_0
    //   40: invokevirtual 41	android/app/PendingIntent:writeToParcel	(Landroid/os/Parcel;I)V
    //   43: aload_0
    //   44: getfield 14	com/google/android/gms/location/internal/zzi$zza$zza:zzoz	Landroid/os/IBinder;
    //   47: astore 4
    //   49: bipush 11
    //   51: istore 6
    //   53: aload 4
    //   55: iload 6
    //   57: aload_2
    //   58: aload_3
    //   59: iconst_0
    //   60: invokeinterface 48 5 0
    //   65: pop
    //   66: aload_3
    //   67: invokevirtual 51	android/os/Parcel:readException	()V
    //   70: aload_3
    //   71: invokevirtual 54	android/os/Parcel:recycle	()V
    //   74: aload_2
    //   75: invokevirtual 54	android/os/Parcel:recycle	()V
    //   78: return
    //   79: iconst_0
    //   80: istore 5
    //   82: aconst_null
    //   83: astore 4
    //   85: aload_2
    //   86: iconst_0
    //   87: invokevirtual 35	android/os/Parcel:writeInt	(I)V
    //   90: goto -47 -> 43
    //   93: astore 4
    //   95: aload_3
    //   96: invokevirtual 54	android/os/Parcel:recycle	()V
    //   99: aload_2
    //   100: invokevirtual 54	android/os/Parcel:recycle	()V
    //   103: aload 4
    //   105: athrow
    // Local variable table:
    //   start	length	slot	name	signature
    //   0	106	0	this	zza
    //   0	106	1	paramPendingIntent	PendingIntent
    //   3	97	2	localParcel1	Parcel
    //   7	89	3	localParcel2	Parcel
    //   10	74	4	localObject1	Object
    //   93	11	4	localObject2	Object
    //   23	58	5	i	int
    //   51	5	6	j	int
    // Exception table:
    //   from	to	target	type
    //   13	18	93	finally
    //   26	31	93	finally
    //   39	43	93	finally
    //   43	47	93	finally
    //   59	66	93	finally
    //   66	70	93	finally
    //   86	90	93	finally
  }
  
  public void zzb(PendingIntent paramPendingIntent, zzo paramzzo)
  {
    Parcel localParcel1 = Parcel.obtain();
    Parcel localParcel2 = Parcel.obtain();
    Object localObject3;
    for (Object localObject1 = "com.google.android.gms.location.internal.IGoogleLocationManagerService";; localObject3 = null) {
      try
      {
        localParcel1.writeInterfaceToken((String)localObject1);
        if (paramPendingIntent != null)
        {
          i = 1;
          localParcel1.writeInt(i);
          i = 0;
          localObject1 = null;
          paramPendingIntent.writeToParcel(localParcel1, 0);
        }
        while (paramzzo != null)
        {
          localObject1 = paramzzo.asBinder();
          localParcel1.writeStrongBinder((IBinder)localObject1);
          localObject1 = this.zzoz;
          int j = 66;
          ((IBinder)localObject1).transact(j, localParcel1, localParcel2, 0);
          localParcel2.readException();
          return;
          i = 0;
          localObject1 = null;
          localParcel1.writeInt(0);
        }
        int i = 0;
      }
      finally
      {
        localParcel2.recycle();
        localParcel1.recycle();
      }
    }
  }
  
  public void zzc(PendingIntent paramPendingIntent, zzo paramzzo)
  {
    Parcel localParcel1 = Parcel.obtain();
    Parcel localParcel2 = Parcel.obtain();
    Object localObject3;
    for (Object localObject1 = "com.google.android.gms.location.internal.IGoogleLocationManagerService";; localObject3 = null) {
      try
      {
        localParcel1.writeInterfaceToken((String)localObject1);
        if (paramPendingIntent != null)
        {
          i = 1;
          localParcel1.writeInt(i);
          i = 0;
          localObject1 = null;
          paramPendingIntent.writeToParcel(localParcel1, 0);
        }
        while (paramzzo != null)
        {
          localObject1 = paramzzo.asBinder();
          localParcel1.writeStrongBinder((IBinder)localObject1);
          localObject1 = this.zzoz;
          int j = 61;
          ((IBinder)localObject1).transact(j, localParcel1, localParcel2, 0);
          localParcel2.readException();
          return;
          i = 0;
          localObject1 = null;
          localParcel1.writeInt(0);
        }
        int i = 0;
      }
      finally
      {
        localParcel2.recycle();
        localParcel1.recycle();
      }
    }
  }
  
  /* Error */
  public void zzc(android.location.Location paramLocation)
  {
    // Byte code:
    //   0: invokestatic 21	android/os/Parcel:obtain	()Landroid/os/Parcel;
    //   3: astore_2
    //   4: invokestatic 21	android/os/Parcel:obtain	()Landroid/os/Parcel;
    //   7: astore_3
    //   8: ldc 23
    //   10: astore 4
    //   12: aload_2
    //   13: aload 4
    //   15: invokevirtual 27	android/os/Parcel:writeInterfaceToken	(Ljava/lang/String;)V
    //   18: aload_1
    //   19: ifnull +60 -> 79
    //   22: iconst_1
    //   23: istore 5
    //   25: aload_2
    //   26: iload 5
    //   28: invokevirtual 35	android/os/Parcel:writeInt	(I)V
    //   31: iconst_0
    //   32: istore 5
    //   34: aconst_null
    //   35: astore 4
    //   37: aload_1
    //   38: aload_2
    //   39: iconst_0
    //   40: invokevirtual 76	android/location/Location:writeToParcel	(Landroid/os/Parcel;I)V
    //   43: aload_0
    //   44: getfield 14	com/google/android/gms/location/internal/zzi$zza$zza:zzoz	Landroid/os/IBinder;
    //   47: astore 4
    //   49: bipush 13
    //   51: istore 6
    //   53: aload 4
    //   55: iload 6
    //   57: aload_2
    //   58: aload_3
    //   59: iconst_0
    //   60: invokeinterface 48 5 0
    //   65: pop
    //   66: aload_3
    //   67: invokevirtual 51	android/os/Parcel:readException	()V
    //   70: aload_3
    //   71: invokevirtual 54	android/os/Parcel:recycle	()V
    //   74: aload_2
    //   75: invokevirtual 54	android/os/Parcel:recycle	()V
    //   78: return
    //   79: iconst_0
    //   80: istore 5
    //   82: aconst_null
    //   83: astore 4
    //   85: aload_2
    //   86: iconst_0
    //   87: invokevirtual 35	android/os/Parcel:writeInt	(I)V
    //   90: goto -47 -> 43
    //   93: astore 4
    //   95: aload_3
    //   96: invokevirtual 54	android/os/Parcel:recycle	()V
    //   99: aload_2
    //   100: invokevirtual 54	android/os/Parcel:recycle	()V
    //   103: aload 4
    //   105: athrow
    // Local variable table:
    //   start	length	slot	name	signature
    //   0	106	0	this	zza
    //   0	106	1	paramLocation	android.location.Location
    //   3	97	2	localParcel1	Parcel
    //   7	89	3	localParcel2	Parcel
    //   10	74	4	localObject1	Object
    //   93	11	4	localObject2	Object
    //   23	58	5	i	int
    //   51	5	6	j	int
    // Exception table:
    //   from	to	target	type
    //   13	18	93	finally
    //   26	31	93	finally
    //   39	43	93	finally
    //   43	47	93	finally
    //   59	66	93	finally
    //   66	70	93	finally
    //   86	90	93	finally
  }
  
  public void zzd(PendingIntent paramPendingIntent, zzo paramzzo)
  {
    Parcel localParcel1 = Parcel.obtain();
    Parcel localParcel2 = Parcel.obtain();
    Object localObject3;
    for (Object localObject1 = "com.google.android.gms.location.internal.IGoogleLocationManagerService";; localObject3 = null) {
      try
      {
        localParcel1.writeInterfaceToken((String)localObject1);
        if (paramPendingIntent != null)
        {
          i = 1;
          localParcel1.writeInt(i);
          i = 0;
          localObject1 = null;
          paramPendingIntent.writeToParcel(localParcel1, 0);
        }
        while (paramzzo != null)
        {
          localObject1 = paramzzo.asBinder();
          localParcel1.writeStrongBinder((IBinder)localObject1);
          localObject1 = this.zzoz;
          int j = 68;
          ((IBinder)localObject1).transact(j, localParcel1, localParcel2, 0);
          localParcel2.readException();
          return;
          i = 0;
          localObject1 = null;
          localParcel1.writeInt(0);
        }
        int i = 0;
      }
      finally
      {
        localParcel2.recycle();
        localParcel1.recycle();
      }
    }
  }
  
  public void zze(PendingIntent paramPendingIntent, zzo paramzzo)
  {
    Parcel localParcel1 = Parcel.obtain();
    Parcel localParcel2 = Parcel.obtain();
    Object localObject3;
    for (Object localObject1 = "com.google.android.gms.location.internal.IGoogleLocationManagerService";; localObject3 = null) {
      try
      {
        localParcel1.writeInterfaceToken((String)localObject1);
        if (paramPendingIntent != null)
        {
          i = 1;
          localParcel1.writeInt(i);
          i = 0;
          localObject1 = null;
          paramPendingIntent.writeToParcel(localParcel1, 0);
        }
        while (paramzzo != null)
        {
          localObject1 = paramzzo.asBinder();
          localParcel1.writeStrongBinder((IBinder)localObject1);
          localObject1 = this.zzoz;
          int j = 69;
          ((IBinder)localObject1).transact(j, localParcel1, localParcel2, 0);
          localParcel2.readException();
          return;
          i = 0;
          localObject1 = null;
          localParcel1.writeInt(0);
        }
        int i = 0;
      }
      finally
      {
        localParcel2.recycle();
        localParcel1.recycle();
      }
    }
  }
  
  /* Error */
  public com.google.android.gms.location.ActivityRecognitionResult zzeh(String paramString)
  {
    // Byte code:
    //   0: invokestatic 21	android/os/Parcel:obtain	()Landroid/os/Parcel;
    //   3: astore_2
    //   4: invokestatic 21	android/os/Parcel:obtain	()Landroid/os/Parcel;
    //   7: astore_3
    //   8: ldc 23
    //   10: astore 4
    //   12: aload_2
    //   13: aload 4
    //   15: invokevirtual 27	android/os/Parcel:writeInterfaceToken	(Ljava/lang/String;)V
    //   18: aload_2
    //   19: aload_1
    //   20: invokevirtual 72	android/os/Parcel:writeString	(Ljava/lang/String;)V
    //   23: aload_0
    //   24: getfield 14	com/google/android/gms/location/internal/zzi$zza$zza:zzoz	Landroid/os/IBinder;
    //   27: astore 4
    //   29: bipush 64
    //   31: istore 5
    //   33: aload 4
    //   35: iload 5
    //   37: aload_2
    //   38: aload_3
    //   39: iconst_0
    //   40: invokeinterface 48 5 0
    //   45: pop
    //   46: aload_3
    //   47: invokevirtual 51	android/os/Parcel:readException	()V
    //   50: aload_3
    //   51: invokevirtual 137	android/os/Parcel:readInt	()I
    //   54: istore 6
    //   56: iload 6
    //   58: ifeq +27 -> 85
    //   61: getstatic 143	com/google/android/gms/location/ActivityRecognitionResult:CREATOR	Lcom/google/android/gms/location/ActivityRecognitionResultCreator;
    //   64: astore 4
    //   66: aload 4
    //   68: aload_3
    //   69: invokevirtual 149	com/google/android/gms/location/ActivityRecognitionResultCreator:createFromParcel	(Landroid/os/Parcel;)Lcom/google/android/gms/location/ActivityRecognitionResult;
    //   72: astore 4
    //   74: aload_3
    //   75: invokevirtual 54	android/os/Parcel:recycle	()V
    //   78: aload_2
    //   79: invokevirtual 54	android/os/Parcel:recycle	()V
    //   82: aload 4
    //   84: areturn
    //   85: iconst_0
    //   86: istore 6
    //   88: aconst_null
    //   89: astore 4
    //   91: goto -17 -> 74
    //   94: astore 4
    //   96: aload_3
    //   97: invokevirtual 54	android/os/Parcel:recycle	()V
    //   100: aload_2
    //   101: invokevirtual 54	android/os/Parcel:recycle	()V
    //   104: aload 4
    //   106: athrow
    // Local variable table:
    //   start	length	slot	name	signature
    //   0	107	0	this	zza
    //   0	107	1	paramString	String
    //   3	98	2	localParcel1	Parcel
    //   7	90	3	localParcel2	Parcel
    //   10	80	4	localObject1	Object
    //   94	11	4	localObject2	Object
    //   31	5	5	i	int
    //   54	33	6	j	int
    // Exception table:
    //   from	to	target	type
    //   13	18	94	finally
    //   19	23	94	finally
    //   23	27	94	finally
    //   39	46	94	finally
    //   46	50	94	finally
    //   50	54	94	finally
    //   61	64	94	finally
    //   68	72	94	finally
  }
  
  /* Error */
  public android.location.Location zzei(String paramString)
  {
    // Byte code:
    //   0: invokestatic 21	android/os/Parcel:obtain	()Landroid/os/Parcel;
    //   3: astore_2
    //   4: invokestatic 21	android/os/Parcel:obtain	()Landroid/os/Parcel;
    //   7: astore_3
    //   8: ldc 23
    //   10: astore 4
    //   12: aload_2
    //   13: aload 4
    //   15: invokevirtual 27	android/os/Parcel:writeInterfaceToken	(Ljava/lang/String;)V
    //   18: aload_2
    //   19: aload_1
    //   20: invokevirtual 72	android/os/Parcel:writeString	(Ljava/lang/String;)V
    //   23: aload_0
    //   24: getfield 14	com/google/android/gms/location/internal/zzi$zza$zza:zzoz	Landroid/os/IBinder;
    //   27: astore 4
    //   29: bipush 21
    //   31: istore 5
    //   33: aload 4
    //   35: iload 5
    //   37: aload_2
    //   38: aload_3
    //   39: iconst_0
    //   40: invokeinterface 48 5 0
    //   45: pop
    //   46: aload_3
    //   47: invokevirtual 51	android/os/Parcel:readException	()V
    //   50: aload_3
    //   51: invokevirtual 137	android/os/Parcel:readInt	()I
    //   54: istore 6
    //   56: iload 6
    //   58: ifeq +36 -> 94
    //   61: getstatic 153	android/location/Location:CREATOR	Landroid/os/Parcelable$Creator;
    //   64: astore 4
    //   66: aload 4
    //   68: aload_3
    //   69: invokeinterface 158 2 0
    //   74: astore 4
    //   76: aload 4
    //   78: checkcast 75	android/location/Location
    //   81: astore 4
    //   83: aload_3
    //   84: invokevirtual 54	android/os/Parcel:recycle	()V
    //   87: aload_2
    //   88: invokevirtual 54	android/os/Parcel:recycle	()V
    //   91: aload 4
    //   93: areturn
    //   94: iconst_0
    //   95: istore 6
    //   97: aconst_null
    //   98: astore 4
    //   100: goto -17 -> 83
    //   103: astore 4
    //   105: aload_3
    //   106: invokevirtual 54	android/os/Parcel:recycle	()V
    //   109: aload_2
    //   110: invokevirtual 54	android/os/Parcel:recycle	()V
    //   113: aload 4
    //   115: athrow
    // Local variable table:
    //   start	length	slot	name	signature
    //   0	116	0	this	zza
    //   0	116	1	paramString	String
    //   3	107	2	localParcel1	Parcel
    //   7	99	3	localParcel2	Parcel
    //   10	89	4	localObject1	Object
    //   103	11	4	localObject2	Object
    //   31	5	5	i	int
    //   54	42	6	j	int
    // Exception table:
    //   from	to	target	type
    //   13	18	103	finally
    //   19	23	103	finally
    //   23	27	103	finally
    //   39	46	103	finally
    //   46	50	103	finally
    //   50	54	103	finally
    //   61	64	103	finally
    //   68	74	103	finally
    //   76	81	103	finally
  }
  
  /* Error */
  public com.google.android.gms.location.LocationAvailability zzej(String paramString)
  {
    // Byte code:
    //   0: invokestatic 21	android/os/Parcel:obtain	()Landroid/os/Parcel;
    //   3: astore_2
    //   4: invokestatic 21	android/os/Parcel:obtain	()Landroid/os/Parcel;
    //   7: astore_3
    //   8: ldc 23
    //   10: astore 4
    //   12: aload_2
    //   13: aload 4
    //   15: invokevirtual 27	android/os/Parcel:writeInterfaceToken	(Ljava/lang/String;)V
    //   18: aload_2
    //   19: aload_1
    //   20: invokevirtual 72	android/os/Parcel:writeString	(Ljava/lang/String;)V
    //   23: aload_0
    //   24: getfield 14	com/google/android/gms/location/internal/zzi$zza$zza:zzoz	Landroid/os/IBinder;
    //   27: astore 4
    //   29: bipush 34
    //   31: istore 5
    //   33: aload 4
    //   35: iload 5
    //   37: aload_2
    //   38: aload_3
    //   39: iconst_0
    //   40: invokeinterface 48 5 0
    //   45: pop
    //   46: aload_3
    //   47: invokevirtual 51	android/os/Parcel:readException	()V
    //   50: aload_3
    //   51: invokevirtual 137	android/os/Parcel:readInt	()I
    //   54: istore 6
    //   56: iload 6
    //   58: ifeq +27 -> 85
    //   61: getstatic 164	com/google/android/gms/location/LocationAvailability:CREATOR	Lcom/google/android/gms/location/LocationAvailabilityCreator;
    //   64: astore 4
    //   66: aload 4
    //   68: aload_3
    //   69: invokevirtual 169	com/google/android/gms/location/LocationAvailabilityCreator:createFromParcel	(Landroid/os/Parcel;)Lcom/google/android/gms/location/LocationAvailability;
    //   72: astore 4
    //   74: aload_3
    //   75: invokevirtual 54	android/os/Parcel:recycle	()V
    //   78: aload_2
    //   79: invokevirtual 54	android/os/Parcel:recycle	()V
    //   82: aload 4
    //   84: areturn
    //   85: iconst_0
    //   86: istore 6
    //   88: aconst_null
    //   89: astore 4
    //   91: goto -17 -> 74
    //   94: astore 4
    //   96: aload_3
    //   97: invokevirtual 54	android/os/Parcel:recycle	()V
    //   100: aload_2
    //   101: invokevirtual 54	android/os/Parcel:recycle	()V
    //   104: aload 4
    //   106: athrow
    // Local variable table:
    //   start	length	slot	name	signature
    //   0	107	0	this	zza
    //   0	107	1	paramString	String
    //   3	98	2	localParcel1	Parcel
    //   7	90	3	localParcel2	Parcel
    //   10	80	4	localObject1	Object
    //   94	11	4	localObject2	Object
    //   31	5	5	i	int
    //   54	33	6	j	int
    // Exception table:
    //   from	to	target	type
    //   13	18	94	finally
    //   19	23	94	finally
    //   23	27	94	finally
    //   39	46	94	finally
    //   46	50	94	finally
    //   50	54	94	finally
    //   61	64	94	finally
    //   68	72	94	finally
  }
  
  /* Error */
  public android.location.Location zzyN()
  {
    // Byte code:
    //   0: invokestatic 21	android/os/Parcel:obtain	()Landroid/os/Parcel;
    //   3: astore_1
    //   4: invokestatic 21	android/os/Parcel:obtain	()Landroid/os/Parcel;
    //   7: astore_2
    //   8: ldc 23
    //   10: astore_3
    //   11: aload_1
    //   12: aload_3
    //   13: invokevirtual 27	android/os/Parcel:writeInterfaceToken	(Ljava/lang/String;)V
    //   16: aload_0
    //   17: getfield 14	com/google/android/gms/location/internal/zzi$zza$zza:zzoz	Landroid/os/IBinder;
    //   20: astore_3
    //   21: bipush 7
    //   23: istore 4
    //   25: aload_3
    //   26: iload 4
    //   28: aload_1
    //   29: aload_2
    //   30: iconst_0
    //   31: invokeinterface 48 5 0
    //   36: pop
    //   37: aload_2
    //   38: invokevirtual 51	android/os/Parcel:readException	()V
    //   41: aload_2
    //   42: invokevirtual 137	android/os/Parcel:readInt	()I
    //   45: istore 5
    //   47: iload 5
    //   49: ifeq +30 -> 79
    //   52: getstatic 153	android/location/Location:CREATOR	Landroid/os/Parcelable$Creator;
    //   55: astore_3
    //   56: aload_3
    //   57: aload_2
    //   58: invokeinterface 158 2 0
    //   63: astore_3
    //   64: aload_3
    //   65: checkcast 75	android/location/Location
    //   68: astore_3
    //   69: aload_2
    //   70: invokevirtual 54	android/os/Parcel:recycle	()V
    //   73: aload_1
    //   74: invokevirtual 54	android/os/Parcel:recycle	()V
    //   77: aload_3
    //   78: areturn
    //   79: iconst_0
    //   80: istore 5
    //   82: aconst_null
    //   83: astore_3
    //   84: goto -15 -> 69
    //   87: astore_3
    //   88: aload_2
    //   89: invokevirtual 54	android/os/Parcel:recycle	()V
    //   92: aload_1
    //   93: invokevirtual 54	android/os/Parcel:recycle	()V
    //   96: aload_3
    //   97: athrow
    // Local variable table:
    //   start	length	slot	name	signature
    //   0	98	0	this	zza
    //   3	90	1	localParcel1	Parcel
    //   7	82	2	localParcel2	Parcel
    //   10	74	3	localObject1	Object
    //   87	10	3	localObject2	Object
    //   23	4	4	i	int
    //   45	36	5	j	int
    // Exception table:
    //   from	to	target	type
    //   12	16	87	finally
    //   16	20	87	finally
    //   30	37	87	finally
    //   37	41	87	finally
    //   41	45	87	finally
    //   52	55	87	finally
    //   57	63	87	finally
    //   64	68	87	finally
  }
}


/* Location:              C:\Users\haryo\Desktop\enjarify-master\presensi-enjarify.jar!\com\google\android\gms\location\internal\zzi$zza$zza.class
 * Java compiler version: 5 (49.0)
 * JD-Core Version:       0.7.1
 */