package b.a.a.a.i.b;

import b.a.a.a.i.d.af;
import b.a.a.a.i.d.v;

public abstract class a
  extends h
{
  public b.a.a.a.h.b a;
  private b.a.a.a.l.e c;
  private b.a.a.a.n.h d;
  private b.a.a.a.e.b e;
  private b.a.a.a.b f;
  private b.a.a.a.e.g g;
  private b.a.a.a.f.k h;
  private b.a.a.a.a.f i;
  private b.a.a.a.n.b j;
  private b.a.a.a.n.i k;
  private b.a.a.a.b.k l;
  private b.a.a.a.b.p m;
  private b.a.a.a.b.c n;
  private b.a.a.a.b.c o;
  private b.a.a.a.b.h p;
  private b.a.a.a.b.i q;
  private b.a.a.a.e.b.d r;
  private b.a.a.a.b.r s;
  private b.a.a.a.b.g t;
  private b.a.a.a.b.d u;
  
  protected a(b.a.a.a.e.b paramb, b.a.a.a.l.e parame)
  {
    b.a.a.a.h.b localb = new b/a/a/a/h/b;
    Class localClass = getClass();
    localb.<init>(localClass);
    this.a = localb;
    this.c = parame;
    this.e = paramb;
  }
  
  private b.a.a.a.n.g I()
  {
    int i1 = 0;
    b.a.a.a.n.i locali1 = null;
    try
    {
      b.a.a.a.n.i locali2 = this.k;
      if (locali2 == null)
      {
        b.a.a.a.n.b localb = H();
        int i2 = localb.a();
        b.a.a.a.r[] arrayOfr = new b.a.a.a.r[i2];
        int i3 = 0;
        locali2 = null;
        Object localObject2;
        while (i3 < i2)
        {
          localObject2 = localb.a(i3);
          arrayOfr[i3] = localObject2;
          i3 += 1;
        }
        i3 = localb.b();
        b.a.a.a.u[] arrayOfu = new b.a.a.a.u[i3];
        while (i1 < i3)
        {
          localObject2 = localb.b(i1);
          arrayOfu[i1] = localObject2;
          i1 += 1;
        }
        locali1 = new b/a/a/a/n/i;
        locali1.<init>(arrayOfr, arrayOfu);
        this.k = locali1;
      }
      locali1 = this.k;
      return locali1;
    }
    finally {}
  }
  
  public final b.a.a.a.b.p A()
  {
    try
    {
      Object localObject1 = this.m;
      if (localObject1 == null)
      {
        localObject1 = new b/a/a/a/i/b/n;
        ((n)localObject1).<init>();
        this.m = ((b.a.a.a.b.p)localObject1);
      }
      localObject1 = this.m;
      return (b.a.a.a.b.p)localObject1;
    }
    finally {}
  }
  
  public final b.a.a.a.b.c B()
  {
    try
    {
      b.a.a.a.b.c localc = this.n;
      if (localc == null)
      {
        localc = k();
        this.n = localc;
      }
      localc = this.n;
      return localc;
    }
    finally {}
  }
  
  public final b.a.a.a.b.c C()
  {
    try
    {
      b.a.a.a.b.c localc = this.o;
      if (localc == null)
      {
        localc = l();
        this.o = localc;
      }
      localc = this.o;
      return localc;
    }
    finally {}
  }
  
  public final b.a.a.a.b.h D()
  {
    try
    {
      b.a.a.a.b.h localh = this.p;
      if (localh == null)
      {
        localh = m();
        this.p = localh;
      }
      localh = this.p;
      return localh;
    }
    finally {}
  }
  
  public final b.a.a.a.b.i E()
  {
    try
    {
      b.a.a.a.b.i locali = this.q;
      if (locali == null)
      {
        locali = n();
        this.q = locali;
      }
      locali = this.q;
      return locali;
    }
    finally {}
  }
  
  public final b.a.a.a.e.b.d F()
  {
    try
    {
      b.a.a.a.e.b.d locald = this.r;
      if (locald == null)
      {
        locald = o();
        this.r = locald;
      }
      locald = this.r;
      return locald;
    }
    finally {}
  }
  
  public final b.a.a.a.b.r G()
  {
    try
    {
      b.a.a.a.b.r localr = this.s;
      if (localr == null)
      {
        localr = p();
        this.s = localr;
      }
      localr = this.s;
      return localr;
    }
    finally {}
  }
  
  protected final b.a.a.a.n.b H()
  {
    try
    {
      b.a.a.a.n.b localb = this.j;
      if (localb == null)
      {
        localb = b();
        this.j = localb;
      }
      localb = this.j;
      return localb;
    }
    finally {}
  }
  
  /* Error */
  protected final b.a.a.a.b.c.c a(b.a.a.a.n paramn, b.a.a.a.q paramq, b.a.a.a.n.e parame)
  {
    // Byte code:
    //   0: ldc -123
    //   2: astore 4
    //   4: aload_2
    //   5: aload 4
    //   7: invokestatic 138	b/a/a/a/o/a:a	(Ljava/lang/Object;Ljava/lang/String;)Ljava/lang/Object;
    //   10: pop
    //   11: aload_0
    //   12: monitorenter
    //   13: aload_0
    //   14: invokevirtual 141	b/a/a/a/i/b/a:c	()Lb/a/a/a/n/e;
    //   17: astore 4
    //   19: aload_3
    //   20: ifnonnull +234 -> 254
    //   23: aload 4
    //   25: astore 5
    //   27: aload_0
    //   28: aload_2
    //   29: invokevirtual 144	b/a/a/a/i/b/a:a	(Lb/a/a/a/q;)Lb/a/a/a/l/e;
    //   32: astore 6
    //   34: aload 6
    //   36: invokestatic 149	b/a/a/a/b/d/a:a	(Lb/a/a/a/l/e;)Lb/a/a/a/b/a/a;
    //   39: astore 4
    //   41: ldc -105
    //   43: astore 7
    //   45: aload 5
    //   47: aload 7
    //   49: aload 4
    //   51: invokeinterface 156 3 0
    //   56: aload_0
    //   57: invokevirtual 159	b/a/a/a/i/b/a:s	()Lb/a/a/a/n/h;
    //   60: astore 7
    //   62: aload_0
    //   63: invokevirtual 162	b/a/a/a/i/b/a:r	()Lb/a/a/a/e/b;
    //   66: astore 8
    //   68: aload_0
    //   69: invokevirtual 166	b/a/a/a/i/b/a:x	()Lb/a/a/a/b;
    //   72: astore 9
    //   74: aload_0
    //   75: invokevirtual 170	b/a/a/a/i/b/a:y	()Lb/a/a/a/e/g;
    //   78: astore 10
    //   80: aload_0
    //   81: invokevirtual 173	b/a/a/a/i/b/a:F	()Lb/a/a/a/e/b/d;
    //   84: astore 11
    //   86: aload_0
    //   87: invokespecial 177	b/a/a/a/i/b/a:I	()Lb/a/a/a/n/g;
    //   90: astore 12
    //   92: aload_0
    //   93: invokevirtual 181	b/a/a/a/i/b/a:z	()Lb/a/a/a/b/k;
    //   96: astore 13
    //   98: aload_0
    //   99: invokevirtual 185	b/a/a/a/i/b/a:A	()Lb/a/a/a/b/p;
    //   102: astore 14
    //   104: aload_0
    //   105: invokevirtual 188	b/a/a/a/i/b/a:B	()Lb/a/a/a/b/c;
    //   108: astore 15
    //   110: aload_0
    //   111: invokevirtual 191	b/a/a/a/i/b/a:C	()Lb/a/a/a/b/c;
    //   114: astore 16
    //   116: aload_0
    //   117: invokevirtual 194	b/a/a/a/i/b/a:G	()Lb/a/a/a/b/r;
    //   120: astore 17
    //   122: aload_0
    //   123: astore 4
    //   125: aload_0
    //   126: aload 7
    //   128: aload 8
    //   130: aload 9
    //   132: aload 10
    //   134: aload 11
    //   136: aload 12
    //   138: aload 13
    //   140: aload 14
    //   142: aload 15
    //   144: aload 16
    //   146: aload 17
    //   148: aload 6
    //   150: invokevirtual 197	b/a/a/a/i/b/a:a	(Lb/a/a/a/n/h;Lb/a/a/a/e/b;Lb/a/a/a/b;Lb/a/a/a/e/g;Lb/a/a/a/e/b/d;Lb/a/a/a/n/g;Lb/a/a/a/b/k;Lb/a/a/a/b/p;Lb/a/a/a/b/c;Lb/a/a/a/b/c;Lb/a/a/a/b/r;Lb/a/a/a/l/e;)Lb/a/a/a/b/q;
    //   153: astore 7
    //   155: aload_0
    //   156: invokevirtual 173	b/a/a/a/i/b/a:F	()Lb/a/a/a/e/b/d;
    //   159: astore 8
    //   161: aload_0
    //   162: invokevirtual 200	b/a/a/a/i/b/a:u	()Lb/a/a/a/b/g;
    //   165: astore 9
    //   167: aload_0
    //   168: invokevirtual 204	b/a/a/a/i/b/a:w	()Lb/a/a/a/b/d;
    //   171: astore 10
    //   173: aload_0
    //   174: monitorexit
    //   175: aload 9
    //   177: ifnull +281 -> 458
    //   180: aload 10
    //   182: ifnull +276 -> 458
    //   185: aload_1
    //   186: ifnull +95 -> 281
    //   189: aload_1
    //   190: astore 4
    //   192: aload 8
    //   194: aload 4
    //   196: aload_2
    //   197: aload 5
    //   199: invokeinterface 209 4 0
    //   204: astore 8
    //   206: aload 7
    //   208: aload_1
    //   209: aload_2
    //   210: aload 5
    //   212: invokeinterface 214 4 0
    //   217: astore 4
    //   219: aload 4
    //   221: invokestatic 219	b/a/a/a/i/b/i:a	(Lb/a/a/a/s;)Lb/a/a/a/b/c/c;
    //   224: astore 4
    //   226: aload 9
    //   228: aload 4
    //   230: invokeinterface 224 2 0
    //   235: istore 18
    //   237: iload 18
    //   239: ifeq +207 -> 446
    //   242: aload 10
    //   244: aload 8
    //   246: invokeinterface 229 2 0
    //   251: aload 4
    //   253: areturn
    //   254: new 231	b/a/a/a/n/c
    //   257: astore 7
    //   259: aload 7
    //   261: aload_3
    //   262: aload 4
    //   264: invokespecial 234	b/a/a/a/n/c:<init>	(Lb/a/a/a/n/e;Lb/a/a/a/n/e;)V
    //   267: aload 7
    //   269: astore 5
    //   271: goto -244 -> 27
    //   274: astore 4
    //   276: aload_0
    //   277: monitorexit
    //   278: aload 4
    //   280: athrow
    //   281: aload_0
    //   282: aload_2
    //   283: invokevirtual 144	b/a/a/a/i/b/a:a	(Lb/a/a/a/q;)Lb/a/a/a/l/e;
    //   286: astore 4
    //   288: ldc -20
    //   290: astore 11
    //   292: aload 4
    //   294: aload 11
    //   296: invokeinterface 241 2 0
    //   301: astore 4
    //   303: aload 4
    //   305: checkcast 243	b/a/a/a/n
    //   308: astore 4
    //   310: goto -118 -> 192
    //   313: astore 4
    //   315: aload 9
    //   317: aload 4
    //   319: invokeinterface 246 2 0
    //   324: istore 18
    //   326: iload 18
    //   328: ifeq +12 -> 340
    //   331: aload 10
    //   333: aload 8
    //   335: invokeinterface 229 2 0
    //   340: aload 4
    //   342: athrow
    //   343: astore 4
    //   345: new 248	b/a/a/a/b/f
    //   348: astore 7
    //   350: aload 7
    //   352: aload 4
    //   354: invokespecial 251	b/a/a/a/b/f:<init>	(Ljava/lang/Throwable;)V
    //   357: aload 7
    //   359: athrow
    //   360: astore 4
    //   362: aload 9
    //   364: aload 4
    //   366: invokeinterface 246 2 0
    //   371: istore 18
    //   373: iload 18
    //   375: ifeq +12 -> 387
    //   378: aload 10
    //   380: aload 8
    //   382: invokeinterface 229 2 0
    //   387: aload 4
    //   389: instanceof 253
    //   392: istore 18
    //   394: iload 18
    //   396: ifeq +13 -> 409
    //   399: aload 4
    //   401: checkcast 253	b/a/a/a/m
    //   404: astore 4
    //   406: aload 4
    //   408: athrow
    //   409: aload 4
    //   411: instanceof 255
    //   414: istore 18
    //   416: iload 18
    //   418: ifeq +13 -> 431
    //   421: aload 4
    //   423: checkcast 255	java/io/IOException
    //   426: astore 4
    //   428: aload 4
    //   430: athrow
    //   431: new 257	java/lang/reflect/UndeclaredThrowableException
    //   434: astore 7
    //   436: aload 7
    //   438: aload 4
    //   440: invokespecial 258	java/lang/reflect/UndeclaredThrowableException:<init>	(Ljava/lang/Throwable;)V
    //   443: aload 7
    //   445: athrow
    //   446: aload 10
    //   448: aload 8
    //   450: invokeinterface 260 2 0
    //   455: goto -204 -> 251
    //   458: aload 7
    //   460: aload_1
    //   461: aload_2
    //   462: aload 5
    //   464: invokeinterface 214 4 0
    //   469: astore 4
    //   471: aload 4
    //   473: invokestatic 219	b/a/a/a/i/b/i:a	(Lb/a/a/a/s;)Lb/a/a/a/b/c/c;
    //   476: astore 4
    //   478: goto -227 -> 251
    // Local variable table:
    //   start	length	slot	name	signature
    //   0	481	0	this	a
    //   0	481	1	paramn	b.a.a.a.n
    //   0	481	2	paramq	b.a.a.a.q
    //   0	481	3	parame	b.a.a.a.n.e
    //   2	261	4	localObject1	Object
    //   274	5	4	localObject2	Object
    //   286	23	4	localObject3	Object
    //   313	28	4	localRuntimeException	RuntimeException
    //   343	10	4	localm	b.a.a.a.m
    //   360	40	4	localException	Exception
    //   404	73	4	localObject4	Object
    //   25	438	5	localObject5	Object
    //   32	117	6	locale	b.a.a.a.l.e
    //   43	416	7	localObject6	Object
    //   66	383	8	localObject7	Object
    //   72	291	9	localObject8	Object
    //   78	369	10	localObject9	Object
    //   84	211	11	localObject10	Object
    //   90	47	12	localg	b.a.a.a.n.g
    //   96	43	13	localk	b.a.a.a.b.k
    //   102	39	14	localp	b.a.a.a.b.p
    //   108	35	15	localc1	b.a.a.a.b.c
    //   114	31	16	localc2	b.a.a.a.b.c
    //   120	27	17	localr	b.a.a.a.b.r
    //   235	182	18	bool	boolean
    // Exception table:
    //   from	to	target	type
    //   13	17	274	finally
    //   28	32	274	finally
    //   34	39	274	finally
    //   49	56	274	finally
    //   56	60	274	finally
    //   62	66	274	finally
    //   68	72	274	finally
    //   74	78	274	finally
    //   80	84	274	finally
    //   86	90	274	finally
    //   92	96	274	finally
    //   98	102	274	finally
    //   104	108	274	finally
    //   110	114	274	finally
    //   116	120	274	finally
    //   148	153	274	finally
    //   155	159	274	finally
    //   161	165	274	finally
    //   167	171	274	finally
    //   173	175	274	finally
    //   254	257	274	finally
    //   262	267	274	finally
    //   276	278	274	finally
    //   210	217	313	java/lang/RuntimeException
    //   219	224	313	java/lang/RuntimeException
    //   197	204	343	b/a/a/a/m
    //   210	217	343	b/a/a/a/m
    //   219	224	343	b/a/a/a/m
    //   228	235	343	b/a/a/a/m
    //   244	251	343	b/a/a/a/m
    //   282	286	343	b/a/a/a/m
    //   294	301	343	b/a/a/a/m
    //   303	308	343	b/a/a/a/m
    //   317	324	343	b/a/a/a/m
    //   333	340	343	b/a/a/a/m
    //   340	343	343	b/a/a/a/m
    //   364	371	343	b/a/a/a/m
    //   380	387	343	b/a/a/a/m
    //   399	404	343	b/a/a/a/m
    //   406	409	343	b/a/a/a/m
    //   421	426	343	b/a/a/a/m
    //   428	431	343	b/a/a/a/m
    //   431	434	343	b/a/a/a/m
    //   438	443	343	b/a/a/a/m
    //   443	446	343	b/a/a/a/m
    //   448	455	343	b/a/a/a/m
    //   462	469	343	b/a/a/a/m
    //   471	476	343	b/a/a/a/m
    //   210	217	360	java/lang/Exception
    //   219	224	360	java/lang/Exception
  }
  
  protected b.a.a.a.b.q a(b.a.a.a.n.h paramh, b.a.a.a.e.b paramb, b.a.a.a.b paramb1, b.a.a.a.e.g paramg, b.a.a.a.e.b.d paramd, b.a.a.a.n.g paramg1, b.a.a.a.b.k paramk, b.a.a.a.b.p paramp, b.a.a.a.b.c paramc1, b.a.a.a.b.c paramc2, b.a.a.a.b.r paramr, b.a.a.a.l.e parame)
  {
    p localp = new b/a/a/a/i/b/p;
    b.a.a.a.h.b localb = this.a;
    localp.<init>(localb, paramh, paramb, paramb1, paramg, paramd, paramg1, paramk, paramp, paramc1, paramc2, paramr, parame);
    return localp;
  }
  
  protected abstract b.a.a.a.l.e a();
  
  protected b.a.a.a.l.e a(b.a.a.a.q paramq)
  {
    g localg = new b/a/a/a/i/b/g;
    b.a.a.a.l.e locale1 = q();
    b.a.a.a.l.e locale2 = paramq.getParams();
    localg.<init>(null, locale1, locale2, null);
    return localg;
  }
  
  public void a(b.a.a.a.b.k paramk)
  {
    try
    {
      this.l = paramk;
      return;
    }
    finally
    {
      localObject = finally;
      throw ((Throwable)localObject);
    }
  }
  
  public void a(b.a.a.a.b.o paramo)
  {
    try
    {
      o localo = new b/a/a/a/i/b/o;
      localo.<init>(paramo);
      this.m = localo;
      return;
    }
    finally {}
  }
  
  public void a(b.a.a.a.r paramr)
  {
    try
    {
      b.a.a.a.n.b localb = H();
      localb.b(paramr);
      localb = null;
      this.k = null;
      return;
    }
    finally {}
  }
  
  public void a(b.a.a.a.r paramr, int paramInt)
  {
    try
    {
      b.a.a.a.n.b localb = H();
      localb.b(paramr, paramInt);
      localb = null;
      this.k = null;
      return;
    }
    finally {}
  }
  
  public void a(b.a.a.a.u paramu)
  {
    try
    {
      b.a.a.a.n.b localb = H();
      localb.b(paramu);
      localb = null;
      this.k = null;
      return;
    }
    finally {}
  }
  
  public void a(Class paramClass)
  {
    try
    {
      b.a.a.a.n.b localb = H();
      localb.a(paramClass);
      localb = null;
      this.k = null;
      return;
    }
    finally {}
  }
  
  protected abstract b.a.a.a.n.b b();
  
  protected b.a.a.a.n.e c()
  {
    b.a.a.a.n.a locala = new b/a/a/a/n/a;
    locala.<init>();
    Object localObject = r().a();
    locala.a("http.scheme-registry", localObject);
    localObject = t();
    locala.a("http.authscheme-registry", localObject);
    localObject = v();
    locala.a("http.cookiespec-registry", localObject);
    localObject = D();
    locala.a("http.cookie-store", localObject);
    localObject = E();
    locala.a("http.auth.credentials-provider", localObject);
    return locala;
  }
  
  public void close()
  {
    r().b();
  }
  
  protected b.a.a.a.e.b d()
  {
    Object localObject1 = b.a.a.a.i.c.p.a();
    b.a.a.a.l.e locale = q();
    Object localObject2 = null;
    Object localObject4 = (String)locale.a("http.connection-manager.factory-class-name");
    if (localObject4 != null) {}
    for (;;)
    {
      try
      {
        localObject2 = Class.forName((String)localObject4);
        localObject2 = ((Class)localObject2).newInstance();
        Object localObject6 = localObject2;
        localObject6 = (b.a.a.a.e.c)localObject2;
        localObject4 = localObject6;
        if (localObject4 != null)
        {
          localObject4 = ((b.a.a.a.e.c)localObject4).a(locale, (b.a.a.a.e.c.i)localObject1);
          return (b.a.a.a.e.b)localObject4;
        }
      }
      catch (ClassNotFoundException localClassNotFoundException)
      {
        localObject3 = new java/lang/IllegalStateException;
        localObject1 = new java/lang/StringBuilder;
        ((StringBuilder)localObject1).<init>();
        localObject4 = "Invalid class name: " + (String)localObject4;
        ((IllegalStateException)localObject3).<init>((String)localObject4);
        throw ((Throwable)localObject3);
      }
      catch (IllegalAccessException localIllegalAccessException)
      {
        localObject3 = new java/lang/IllegalAccessError;
        String str = localIllegalAccessException.getMessage();
        ((IllegalAccessError)localObject3).<init>(str);
        throw ((Throwable)localObject3);
      }
      catch (InstantiationException localInstantiationException)
      {
        Object localObject3 = new java/lang/InstantiationError;
        localObject5 = localInstantiationException.getMessage();
        ((InstantiationError)localObject3).<init>((String)localObject5);
        throw ((Throwable)localObject3);
      }
      Object localObject5 = new b/a/a/a/i/c/d;
      ((b.a.a.a.i.c.d)localObject5).<init>((b.a.a.a.e.c.i)localObject1);
      continue;
      localObject5 = null;
    }
  }
  
  protected b.a.a.a.a.f e()
  {
    b.a.a.a.a.f localf = new b/a/a/a/a/f;
    localf.<init>();
    Object localObject = new b/a/a/a/i/a/c;
    ((b.a.a.a.i.a.c)localObject).<init>();
    localf.a("Basic", (b.a.a.a.a.d)localObject);
    localObject = new b/a/a/a/i/a/e;
    ((b.a.a.a.i.a.e)localObject).<init>();
    localf.a("Digest", (b.a.a.a.a.d)localObject);
    localObject = new b/a/a/a/i/a/l;
    ((b.a.a.a.i.a.l)localObject).<init>();
    localf.a("NTLM", (b.a.a.a.a.d)localObject);
    return localf;
  }
  
  protected b.a.a.a.f.k f()
  {
    b.a.a.a.f.k localk = new b/a/a/a/f/k;
    localk.<init>();
    Object localObject = new b/a/a/a/i/d/l;
    ((b.a.a.a.i.d.l)localObject).<init>();
    localk.a("best-match", (b.a.a.a.f.i)localObject);
    localObject = new b/a/a/a/i/d/n;
    ((b.a.a.a.i.d.n)localObject).<init>();
    localk.a("compatibility", (b.a.a.a.f.i)localObject);
    localObject = new b/a/a/a/i/d/v;
    ((v)localObject).<init>();
    localk.a("netscape", (b.a.a.a.f.i)localObject);
    localObject = new b/a/a/a/i/d/y;
    ((b.a.a.a.i.d.y)localObject).<init>();
    localk.a("rfc2109", (b.a.a.a.f.i)localObject);
    localObject = new b/a/a/a/i/d/af;
    ((af)localObject).<init>();
    localk.a("rfc2965", (b.a.a.a.f.i)localObject);
    localObject = new b/a/a/a/i/d/r;
    ((b.a.a.a.i.d.r)localObject).<init>();
    localk.a("ignoreCookies", (b.a.a.a.f.i)localObject);
    return localk;
  }
  
  protected b.a.a.a.n.h g()
  {
    b.a.a.a.n.h localh = new b/a/a/a/n/h;
    localh.<init>();
    return localh;
  }
  
  protected b.a.a.a.b h()
  {
    b.a.a.a.i.b localb = new b/a/a/a/i/b;
    localb.<init>();
    return localb;
  }
  
  protected b.a.a.a.e.g i()
  {
    j localj = new b/a/a/a/i/b/j;
    localj.<init>();
    return localj;
  }
  
  protected b.a.a.a.b.k j()
  {
    l locall = new b/a/a/a/i/b/l;
    locall.<init>();
    return locall;
  }
  
  protected b.a.a.a.b.c k()
  {
    y localy = new b/a/a/a/i/b/y;
    localy.<init>();
    return localy;
  }
  
  protected b.a.a.a.b.c l()
  {
    u localu = new b/a/a/a/i/b/u;
    localu.<init>();
    return localu;
  }
  
  protected b.a.a.a.b.h m()
  {
    e locale = new b/a/a/a/i/b/e;
    locale.<init>();
    return locale;
  }
  
  protected b.a.a.a.b.i n()
  {
    f localf = new b/a/a/a/i/b/f;
    localf.<init>();
    return localf;
  }
  
  protected b.a.a.a.e.b.d o()
  {
    b.a.a.a.i.c.i locali = new b/a/a/a/i/c/i;
    b.a.a.a.e.c.i locali1 = r().a();
    locali.<init>(locali1);
    return locali;
  }
  
  protected b.a.a.a.b.r p()
  {
    q localq = new b/a/a/a/i/b/q;
    localq.<init>();
    return localq;
  }
  
  public final b.a.a.a.l.e q()
  {
    try
    {
      b.a.a.a.l.e locale = this.c;
      if (locale == null)
      {
        locale = a();
        this.c = locale;
      }
      locale = this.c;
      return locale;
    }
    finally {}
  }
  
  public final b.a.a.a.e.b r()
  {
    try
    {
      b.a.a.a.e.b localb = this.e;
      if (localb == null)
      {
        localb = d();
        this.e = localb;
      }
      localb = this.e;
      return localb;
    }
    finally {}
  }
  
  public final b.a.a.a.n.h s()
  {
    try
    {
      b.a.a.a.n.h localh = this.d;
      if (localh == null)
      {
        localh = g();
        this.d = localh;
      }
      localh = this.d;
      return localh;
    }
    finally {}
  }
  
  public final b.a.a.a.a.f t()
  {
    try
    {
      b.a.a.a.a.f localf = this.i;
      if (localf == null)
      {
        localf = e();
        this.i = localf;
      }
      localf = this.i;
      return localf;
    }
    finally {}
  }
  
  public final b.a.a.a.b.g u()
  {
    try
    {
      b.a.a.a.b.g localg = this.t;
      return localg;
    }
    finally
    {
      localObject = finally;
      throw ((Throwable)localObject);
    }
  }
  
  public final b.a.a.a.f.k v()
  {
    try
    {
      b.a.a.a.f.k localk = this.h;
      if (localk == null)
      {
        localk = f();
        this.h = localk;
      }
      localk = this.h;
      return localk;
    }
    finally {}
  }
  
  public final b.a.a.a.b.d w()
  {
    try
    {
      b.a.a.a.b.d locald = this.u;
      return locald;
    }
    finally
    {
      localObject = finally;
      throw ((Throwable)localObject);
    }
  }
  
  public final b.a.a.a.b x()
  {
    try
    {
      b.a.a.a.b localb = this.f;
      if (localb == null)
      {
        localb = h();
        this.f = localb;
      }
      localb = this.f;
      return localb;
    }
    finally {}
  }
  
  public final b.a.a.a.e.g y()
  {
    try
    {
      b.a.a.a.e.g localg = this.g;
      if (localg == null)
      {
        localg = i();
        this.g = localg;
      }
      localg = this.g;
      return localg;
    }
    finally {}
  }
  
  public final b.a.a.a.b.k z()
  {
    try
    {
      b.a.a.a.b.k localk = this.l;
      if (localk == null)
      {
        localk = j();
        this.l = localk;
      }
      localk = this.l;
      return localk;
    }
    finally {}
  }
}


/* Location:              C:\Users\haryo\Desktop\enjarify-master\presensi-enjarify.jar!\b\a\a\a\i\b\a.class
 * Java compiler version: 5 (49.0)
 * JD-Core Version:       0.7.1
 */