package com.google.android.gms.measurement.internal;

import android.content.ContentValues;
import android.content.Context;
import android.database.Cursor;
import android.database.CursorWindow;
import android.database.sqlite.SQLiteCursor;
import android.database.sqlite.SQLiteDatabase;
import android.database.sqlite.SQLiteException;
import android.os.Build.VERSION;
import android.support.v4.h.a;
import android.text.TextUtils;
import com.google.android.gms.common.internal.zzx;
import com.google.android.gms.internal.zzmq;
import com.google.android.gms.internal.zzpz.zza;
import com.google.android.gms.internal.zzpz.zzb;
import com.google.android.gms.internal.zzpz.zze;
import com.google.android.gms.internal.zzsn;
import java.io.File;
import java.io.IOException;
import java.util.List;
import java.util.Map;

class zze
  extends zzz
{
  private static final Map zzaVB;
  private final zze.zzc zzaVC;
  private final zzaf zzaVD;
  
  static
  {
    a locala = new android/support/v4/h/a;
    locala.<init>(13);
    zzaVB = locala;
    zzaVB.put("app_version", "ALTER TABLE apps ADD COLUMN app_version TEXT;");
    zzaVB.put("app_store", "ALTER TABLE apps ADD COLUMN app_store TEXT;");
    zzaVB.put("gmp_version", "ALTER TABLE apps ADD COLUMN gmp_version INTEGER;");
    zzaVB.put("dev_cert_hash", "ALTER TABLE apps ADD COLUMN dev_cert_hash INTEGER;");
    zzaVB.put("measurement_enabled", "ALTER TABLE apps ADD COLUMN measurement_enabled INTEGER;");
    zzaVB.put("last_bundle_start_timestamp", "ALTER TABLE apps ADD COLUMN last_bundle_start_timestamp INTEGER;");
    zzaVB.put("day", "ALTER TABLE apps ADD COLUMN day INTEGER;");
    zzaVB.put("daily_public_events_count", "ALTER TABLE apps ADD COLUMN daily_public_events_count INTEGER;");
    zzaVB.put("daily_events_count", "ALTER TABLE apps ADD COLUMN daily_events_count INTEGER;");
    zzaVB.put("daily_conversions_count", "ALTER TABLE apps ADD COLUMN daily_conversions_count INTEGER;");
    zzaVB.put("remote_config", "ALTER TABLE apps ADD COLUMN remote_config BLOB;");
    zzaVB.put("config_fetched_time", "ALTER TABLE apps ADD COLUMN config_fetched_time INTEGER;");
    zzaVB.put("failed_config_fetch_time", "ALTER TABLE apps ADD COLUMN failed_config_fetch_time INTEGER;");
  }
  
  zze(zzw paramzzw)
  {
    super(paramzzw);
    Object localObject1 = new com/google/android/gms/measurement/internal/zzaf;
    Object localObject2 = zzjl();
    ((zzaf)localObject1).<init>((zzmq)localObject2);
    this.zzaVD = ((zzaf)localObject1);
    localObject1 = zzjQ();
    localObject2 = new com/google/android/gms/measurement/internal/zze$zzc;
    Context localContext = getContext();
    ((zze.zzc)localObject2).<init>(this, localContext, (String)localObject1);
    this.zzaVC = ((zze.zzc)localObject2);
  }
  
  private boolean zzCw()
  {
    Context localContext = getContext();
    String str = zzjQ();
    return localContext.getDatabasePath(str).exists();
  }
  
  static int zza(Cursor paramCursor, int paramInt)
  {
    int i = Build.VERSION.SDK_INT;
    int k = 11;
    if (i >= k) {
      i = paramCursor.getType(paramInt);
    }
    for (;;)
    {
      return i;
      Object localObject = paramCursor;
      localObject = ((SQLiteCursor)paramCursor).getWindow();
      k = paramCursor.getPosition();
      boolean bool2 = ((CursorWindow)localObject).isNull(k, paramInt);
      if (bool2)
      {
        i = 0;
        localObject = null;
      }
      else
      {
        bool2 = ((CursorWindow)localObject).isLong(k, paramInt);
        if (bool2)
        {
          i = 1;
        }
        else
        {
          bool2 = ((CursorWindow)localObject).isFloat(k, paramInt);
          if (bool2)
          {
            i = 2;
          }
          else
          {
            bool2 = ((CursorWindow)localObject).isString(k, paramInt);
            if (bool2)
            {
              i = 3;
            }
            else
            {
              boolean bool1 = ((CursorWindow)localObject).isBlob(k, paramInt);
              int j;
              if (bool1) {
                j = 4;
              } else {
                j = -1;
              }
            }
          }
        }
      }
    }
  }
  
  /* Error */
  private long zza(String paramString, String[] paramArrayOfString, long paramLong)
  {
    // Byte code:
    //   0: aload_0
    //   1: invokevirtual 167	com/google/android/gms/measurement/internal/zze:getWritableDatabase	()Landroid/database/sqlite/SQLiteDatabase;
    //   4: astore 5
    //   6: aconst_null
    //   7: astore 6
    //   9: aload 5
    //   11: aload_1
    //   12: aload_2
    //   13: invokevirtual 173	android/database/sqlite/SQLiteDatabase:rawQuery	(Ljava/lang/String;[Ljava/lang/String;)Landroid/database/Cursor;
    //   16: astore 6
    //   18: aload 6
    //   20: invokeinterface 176 1 0
    //   25: istore 7
    //   27: iload 7
    //   29: ifeq +32 -> 61
    //   32: iconst_0
    //   33: istore 7
    //   35: aconst_null
    //   36: astore 5
    //   38: aload 6
    //   40: iconst_0
    //   41: invokeinterface 180 2 0
    //   46: lstore_3
    //   47: aload 6
    //   49: ifnull +10 -> 59
    //   52: aload 6
    //   54: invokeinterface 184 1 0
    //   59: lload_3
    //   60: lreturn
    //   61: aload 6
    //   63: ifnull -4 -> 59
    //   66: aload 6
    //   68: invokeinterface 184 1 0
    //   73: goto -14 -> 59
    //   76: astore 5
    //   78: aload_0
    //   79: invokevirtual 188	com/google/android/gms/measurement/internal/zze:zzAo	()Lcom/google/android/gms/measurement/internal/zzp;
    //   82: astore 8
    //   84: aload 8
    //   86: invokevirtual 194	com/google/android/gms/measurement/internal/zzp:zzCE	()Lcom/google/android/gms/measurement/internal/zzp$zza;
    //   89: astore 8
    //   91: ldc -60
    //   93: astore 9
    //   95: aload 8
    //   97: aload 9
    //   99: aload_1
    //   100: aload 5
    //   102: invokevirtual 202	com/google/android/gms/measurement/internal/zzp$zza:zze	(Ljava/lang/String;Ljava/lang/Object;Ljava/lang/Object;)V
    //   105: aload 5
    //   107: athrow
    //   108: astore 5
    //   110: aload 6
    //   112: ifnull +10 -> 122
    //   115: aload 6
    //   117: invokeinterface 184 1 0
    //   122: aload 5
    //   124: athrow
    // Local variable table:
    //   start	length	slot	name	signature
    //   0	125	0	this	zze
    //   0	125	1	paramString	String
    //   0	125	2	paramArrayOfString	String[]
    //   0	125	3	paramLong	long
    //   4	33	5	localSQLiteDatabase	SQLiteDatabase
    //   76	30	5	localSQLiteException	SQLiteException
    //   108	15	5	localObject1	Object
    //   7	109	6	localCursor	Cursor
    //   25	9	7	bool	boolean
    //   82	14	8	localObject2	Object
    //   93	5	9	str	String
    // Exception table:
    //   from	to	target	type
    //   12	16	76	android/database/sqlite/SQLiteException
    //   18	25	76	android/database/sqlite/SQLiteException
    //   40	46	76	android/database/sqlite/SQLiteException
    //   12	16	108	finally
    //   18	25	108	finally
    //   40	46	108	finally
    //   78	82	108	finally
    //   84	89	108	finally
    //   100	105	108	finally
    //   105	108	108	finally
  }
  
  private void zza(String paramString, zzpz.zza paramzza)
  {
    int i = 0;
    zzp.zza localzza = null;
    zzjv();
    zzjk();
    zzx.zzcM(paramString);
    zzx.zzz(paramzza);
    zzx.zzz(paramzza.zzaZt);
    zzx.zzz(paramzza.zzaZs);
    Object localObject1 = paramzza.zzaZr;
    if (localObject1 == null)
    {
      localzza = zzAo().zzCF();
      localObject1 = "Audience with no ID";
      localzza.zzfg((String)localObject1);
    }
    label160:
    label241:
    label261:
    label319:
    label372:
    label381:
    label385:
    for (;;)
    {
      return;
      int j = paramzza.zzaZr.intValue();
      Object localObject2 = paramzza.zzaZt;
      int k = localObject2.length;
      int m = 0;
      localObject1 = null;
      Integer localInteger;
      for (;;)
      {
        if (m >= k) {
          break label160;
        }
        localInteger = localObject2[m].zzaZv;
        if (localInteger == null)
        {
          localzza = zzAo().zzCF();
          localObject1 = "Event filter with no ID. Audience definition ignored. appId, audienceId";
          localObject2 = paramzza.zzaZr;
          localzza.zze((String)localObject1, paramString, localObject2);
          break;
        }
        m += 1;
      }
      localObject2 = paramzza.zzaZs;
      k = localObject2.length;
      m = 0;
      localObject1 = null;
      for (;;)
      {
        if (m >= k) {
          break label241;
        }
        localInteger = localObject2[m].zzaZv;
        if (localInteger == null)
        {
          localzza = zzAo().zzCF();
          localObject1 = "Property filter with no ID. Audience definition ignored. appId, audienceId";
          localObject2 = paramzza.zzaZr;
          localzza.zze((String)localObject1, paramString, localObject2);
          break;
        }
        m += 1;
      }
      m = 1;
      Object localObject3 = paramzza.zzaZt;
      int n = localObject3.length;
      int i1 = 0;
      localObject2 = null;
      zzpz.zzb localzzb;
      boolean bool;
      if (i1 < n)
      {
        localzzb = localObject3[i1];
        bool = zza(paramString, j, localzzb);
        if (!bool)
        {
          m = 0;
          localObject1 = null;
        }
      }
      else
      {
        if (m == 0) {
          break label381;
        }
        localObject3 = paramzza.zzaZs;
        n = localObject3.length;
        i1 = 0;
        localObject2 = null;
        if (i1 >= n) {
          break label381;
        }
        localzzb = localObject3[i1];
        bool = zza(paramString, j, localzzb);
        if (bool) {
          break label372;
        }
      }
      for (;;)
      {
        if (i != 0) {
          break label385;
        }
        zzB(paramString, j);
        break;
        i1 += 1;
        break label261;
        i1 += 1;
        break label319;
        i = m;
      }
    }
  }
  
  private boolean zza(String paramString, int paramInt, zzpz.zzb paramzzb)
  {
    boolean bool1 = false;
    zzjv();
    zzjk();
    zzx.zzcM(paramString);
    zzx.zzz(paramzzb);
    Object localObject1 = paramzzb.zzaZw;
    boolean bool2 = TextUtils.isEmpty((CharSequence)localObject1);
    Object localObject2;
    Object localObject3;
    Object localObject4;
    if (bool2)
    {
      localObject1 = zzAo().zzCF();
      localObject2 = "Event filter had no event name. Audience definition ignored. audienceId, filterId";
      localObject3 = Integer.valueOf(paramInt);
      localObject4 = String.valueOf(paramzzb.zzaZv);
      ((zzp.zza)localObject1).zze((String)localObject2, localObject3, localObject4);
    }
    for (;;)
    {
      return bool1;
      try
      {
        int i = paramzzb.getSerializedSize();
        localObject1 = new byte[i];
        localObject2 = zzsn.zzE((byte[])localObject1);
        paramzzb.writeTo((zzsn)localObject2);
        ((zzsn)localObject2).zzJo();
        localObject2 = new android/content/ContentValues;
        ((ContentValues)localObject2).<init>();
        ((ContentValues)localObject2).put("app_id", paramString);
        localObject4 = Integer.valueOf(paramInt);
        ((ContentValues)localObject2).put("audience_id", (Integer)localObject4);
        localObject4 = paramzzb.zzaZv;
        ((ContentValues)localObject2).put("filter_id", (Integer)localObject4);
        localObject4 = paramzzb.zzaZw;
        ((ContentValues)localObject2).put("event_name", (String)localObject4);
        localObject3 = "data";
        ((ContentValues)localObject2).put((String)localObject3, (byte[])localObject1);
      }
      catch (IOException localIOException)
      {
        try
        {
          localObject1 = getWritableDatabase();
          localObject3 = "event_filters";
          localObject4 = null;
          int j = 5;
          long l1 = ((SQLiteDatabase)localObject1).insertWithOnConflict((String)localObject3, null, (ContentValues)localObject2, j);
          long l2 = -1;
          boolean bool3 = l1 < l2;
          if (!bool3)
          {
            localObject1 = zzAo();
            localObject1 = ((zzp)localObject1).zzCE();
            localObject2 = "Failed to insert event filter (got -1)";
            ((zzp.zza)localObject1).zzfg((String)localObject2);
          }
          bool1 = true;
        }
        catch (SQLiteException localSQLiteException)
        {
          localObject2 = zzAo().zzCE();
          localObject3 = "Error storing event filter";
          ((zzp.zza)localObject2).zzj((String)localObject3, localSQLiteException);
        }
        localIOException = localIOException;
        localObject2 = zzAo().zzCE();
        localObject3 = "Configuration loss. Failed to serialize event filter";
        ((zzp.zza)localObject2).zzj((String)localObject3, localIOException);
      }
    }
  }
  
  private boolean zza(String paramString, int paramInt, zzpz.zze paramzze)
  {
    boolean bool1 = false;
    zzjv();
    zzjk();
    zzx.zzcM(paramString);
    zzx.zzz(paramzze);
    Object localObject1 = paramzze.zzaZL;
    boolean bool2 = TextUtils.isEmpty((CharSequence)localObject1);
    Object localObject2;
    Object localObject3;
    Object localObject4;
    if (bool2)
    {
      localObject1 = zzAo().zzCF();
      localObject2 = "Property filter had no property name. Audience definition ignored. audienceId, filterId";
      localObject3 = Integer.valueOf(paramInt);
      localObject4 = String.valueOf(paramzze.zzaZv);
      ((zzp.zza)localObject1).zze((String)localObject2, localObject3, localObject4);
    }
    for (;;)
    {
      return bool1;
      try
      {
        int i = paramzze.getSerializedSize();
        localObject1 = new byte[i];
        localObject2 = zzsn.zzE((byte[])localObject1);
        paramzze.writeTo((zzsn)localObject2);
        ((zzsn)localObject2).zzJo();
        localObject2 = new android/content/ContentValues;
        ((ContentValues)localObject2).<init>();
        ((ContentValues)localObject2).put("app_id", paramString);
        localObject4 = Integer.valueOf(paramInt);
        ((ContentValues)localObject2).put("audience_id", (Integer)localObject4);
        localObject4 = paramzze.zzaZv;
        ((ContentValues)localObject2).put("filter_id", (Integer)localObject4);
        localObject4 = paramzze.zzaZL;
        ((ContentValues)localObject2).put("property_name", (String)localObject4);
        localObject3 = "data";
        ((ContentValues)localObject2).put((String)localObject3, (byte[])localObject1);
        try
        {
          localObject1 = getWritableDatabase();
          localObject3 = "property_filters";
          localObject4 = null;
          int j = 5;
          long l1 = ((SQLiteDatabase)localObject1).insertWithOnConflict((String)localObject3, null, (ContentValues)localObject2, j);
          long l2 = -1;
          boolean bool3 = l1 < l2;
          if (bool3) {
            break label324;
          }
          localObject1 = zzAo();
          localObject1 = ((zzp)localObject1).zzCE();
          localObject2 = "Failed to insert property filter (got -1)";
          ((zzp.zza)localObject1).zzfg((String)localObject2);
        }
        catch (SQLiteException localSQLiteException)
        {
          localObject2 = zzAo().zzCE();
          localObject3 = "Error storing property filter";
          ((zzp.zza)localObject2).zzj((String)localObject3, localSQLiteException);
        }
      }
      catch (IOException localIOException)
      {
        localObject2 = zzAo().zzCE();
        localObject3 = "Configuration loss. Failed to serialize property filter";
        ((zzp.zza)localObject2).zzj((String)localObject3, localIOException);
      }
      continue;
      label324:
      bool1 = true;
    }
  }
  
  private long zzb(String paramString, String[] paramArrayOfString)
  {
    Object localObject1 = getWritableDatabase();
    Cursor localCursor = null;
    try
    {
      localCursor = ((SQLiteDatabase)localObject1).rawQuery(paramString, paramArrayOfString);
      boolean bool = localCursor.moveToFirst();
      if (bool)
      {
        bool = false;
        localObject1 = null;
        long l = localCursor.getLong(0);
        return l;
      }
      localObject1 = new android/database/sqlite/SQLiteException;
      localObject3 = "Database returned empty set";
      ((SQLiteException)localObject1).<init>((String)localObject3);
      throw ((Throwable)localObject1);
    }
    catch (SQLiteException localSQLiteException)
    {
      Object localObject3 = zzAo();
      localObject3 = ((zzp)localObject3).zzCE();
      String str = "Database error";
      ((zzp.zza)localObject3).zze(str, paramString, localSQLiteException);
      throw localSQLiteException;
    }
    finally
    {
      if (localCursor != null) {
        localCursor.close();
      }
    }
  }
  
  private String zzjQ()
  {
    Object localObject = zzCp();
    boolean bool = ((zzd)localObject).zzkr();
    if (!bool) {
      localObject = zzCp().zzkR();
    }
    for (;;)
    {
      return (String)localObject;
      localObject = zzCp();
      bool = ((zzd)localObject).zzks();
      if (bool)
      {
        localObject = zzCp().zzkR();
      }
      else
      {
        localObject = zzAo().zzCG();
        String str = "Using secondary database";
        ((zzp.zza)localObject).zzfg(str);
        localObject = zzCp().zzkS();
      }
    }
  }
  
  public void beginTransaction()
  {
    zzjv();
    getWritableDatabase().beginTransaction();
  }
  
  public void endTransaction()
  {
    zzjv();
    getWritableDatabase().endTransaction();
  }
  
  SQLiteDatabase getWritableDatabase()
  {
    zzjk();
    try
    {
      zze.zzc localzzc = this.zzaVC;
      return localzzc.getWritableDatabase();
    }
    catch (SQLiteException localSQLiteException)
    {
      zzAo().zzCF().zzj("Error opening database", localSQLiteException);
      throw localSQLiteException;
    }
  }
  
  public void setTransactionSuccessful()
  {
    zzjv();
    getWritableDatabase().setTransactionSuccessful();
  }
  
  public void zzA(String paramString, int paramInt)
  {
    zzx.zzcM(paramString);
    zzjk();
    zzjv();
    try
    {
      SQLiteDatabase localSQLiteDatabase = getWritableDatabase();
      localObject1 = "delete from user_attributes where app_id=? and name in (select name from user_attributes where app_id=? and name like '_ltv_%' order by set_timestamp desc limit ?,10);";
      int i = 3;
      localObject2 = new String[i];
      int j = 0;
      localObject2[0] = paramString;
      j = 1;
      localObject2[j] = paramString;
      j = 2;
      String str = String.valueOf(paramInt);
      localObject2[j] = str;
      localSQLiteDatabase.execSQL((String)localObject1, (Object[])localObject2);
      return;
    }
    catch (SQLiteException localSQLiteException)
    {
      for (;;)
      {
        Object localObject1 = zzAo().zzCE();
        Object localObject2 = "Error pruning currencies";
        ((zzp.zza)localObject1).zze((String)localObject2, paramString, localSQLiteException);
      }
    }
  }
  
  void zzB(String paramString, int paramInt)
  {
    int i = 2;
    int j = 1;
    zzjv();
    zzjk();
    zzx.zzcM(paramString);
    SQLiteDatabase localSQLiteDatabase = getWritableDatabase();
    String[] arrayOfString = new String[i];
    arrayOfString[0] = paramString;
    String str = String.valueOf(paramInt);
    arrayOfString[j] = str;
    localSQLiteDatabase.delete("property_filters", "app_id=? and audience_id=?", arrayOfString);
    arrayOfString = new String[i];
    arrayOfString[0] = paramString;
    str = String.valueOf(paramInt);
    arrayOfString[j] = str;
    localSQLiteDatabase.delete("event_filters", "app_id=? and audience_id=?", arrayOfString);
  }
  
  /* Error */
  com.google.android.gms.internal.zzqb.zzf zzC(String paramString, int paramInt)
  {
    // Byte code:
    //   0: aload_0
    //   1: invokevirtual 207	com/google/android/gms/measurement/internal/zze:zzjv	()V
    //   4: aload_0
    //   5: invokevirtual 210	com/google/android/gms/measurement/internal/zze:zzjk	()V
    //   8: aload_1
    //   9: invokestatic 216	com/google/android/gms/common/internal/zzx:zzcM	(Ljava/lang/String;)Ljava/lang/String;
    //   12: pop
    //   13: aload_0
    //   14: invokevirtual 167	com/google/android/gms/measurement/internal/zze:getWritableDatabase	()Landroid/database/sqlite/SQLiteDatabase;
    //   17: astore_3
    //   18: ldc_w 425
    //   21: astore 4
    //   23: iconst_1
    //   24: istore 5
    //   26: iload 5
    //   28: anewarray 289	java/lang/String
    //   31: astore 6
    //   33: aconst_null
    //   34: astore 7
    //   36: ldc_w 427
    //   39: astore 8
    //   41: aload 6
    //   43: iconst_0
    //   44: aload 8
    //   46: aastore
    //   47: ldc_w 429
    //   50: astore 7
    //   52: iconst_2
    //   53: istore 9
    //   55: iload 9
    //   57: anewarray 289	java/lang/String
    //   60: astore 8
    //   62: iconst_0
    //   63: istore 10
    //   65: aload 8
    //   67: iconst_0
    //   68: aload_1
    //   69: aastore
    //   70: iconst_1
    //   71: istore 10
    //   73: iload_2
    //   74: invokestatic 411	java/lang/String:valueOf	(I)Ljava/lang/String;
    //   77: astore 11
    //   79: aload 8
    //   81: iload 10
    //   83: aload 11
    //   85: aastore
    //   86: iconst_0
    //   87: istore 10
    //   89: aconst_null
    //   90: astore 11
    //   92: aload_3
    //   93: aload 4
    //   95: aload 6
    //   97: aload 7
    //   99: aload 8
    //   101: aconst_null
    //   102: aconst_null
    //   103: aconst_null
    //   104: invokevirtual 433	android/database/sqlite/SQLiteDatabase:query	(Ljava/lang/String;[Ljava/lang/String;Ljava/lang/String;[Ljava/lang/String;Ljava/lang/String;Ljava/lang/String;Ljava/lang/String;)Landroid/database/Cursor;
    //   107: astore 4
    //   109: aload 4
    //   111: invokeinterface 176 1 0
    //   116: istore 12
    //   118: iload 12
    //   120: ifne +22 -> 142
    //   123: aload 4
    //   125: ifnull +10 -> 135
    //   128: aload 4
    //   130: invokeinterface 184 1 0
    //   135: iconst_0
    //   136: istore 12
    //   138: aconst_null
    //   139: astore_3
    //   140: aload_3
    //   141: areturn
    //   142: iconst_0
    //   143: istore 12
    //   145: aconst_null
    //   146: astore_3
    //   147: aload 4
    //   149: iconst_0
    //   150: invokeinterface 437 2 0
    //   155: astore_3
    //   156: aload_3
    //   157: invokestatic 443	com/google/android/gms/internal/zzsm:zzD	([B)Lcom/google/android/gms/internal/zzsm;
    //   160: astore 6
    //   162: new 445	com/google/android/gms/internal/zzqb$zzf
    //   165: astore_3
    //   166: aload_3
    //   167: invokespecial 446	com/google/android/gms/internal/zzqb$zzf:<init>	()V
    //   170: aload_3
    //   171: aload 6
    //   173: invokevirtual 450	com/google/android/gms/internal/zzqb$zzf:zzH	(Lcom/google/android/gms/internal/zzsm;)Lcom/google/android/gms/internal/zzqb$zzf;
    //   176: pop
    //   177: aload 4
    //   179: ifnull -39 -> 140
    //   182: aload 4
    //   184: invokeinterface 184 1 0
    //   189: goto -49 -> 140
    //   192: astore 6
    //   194: aload_0
    //   195: invokevirtual 188	com/google/android/gms/measurement/internal/zze:zzAo	()Lcom/google/android/gms/measurement/internal/zzp;
    //   198: astore 7
    //   200: aload 7
    //   202: invokevirtual 194	com/google/android/gms/measurement/internal/zzp:zzCE	()Lcom/google/android/gms/measurement/internal/zzp$zza;
    //   205: astore 7
    //   207: ldc_w 452
    //   210: astore 8
    //   212: aload 7
    //   214: aload 8
    //   216: aload_1
    //   217: aload 6
    //   219: invokevirtual 202	com/google/android/gms/measurement/internal/zzp$zza:zze	(Ljava/lang/String;Ljava/lang/Object;Ljava/lang/Object;)V
    //   222: goto -45 -> 177
    //   225: astore_3
    //   226: aload_0
    //   227: invokevirtual 188	com/google/android/gms/measurement/internal/zze:zzAo	()Lcom/google/android/gms/measurement/internal/zzp;
    //   230: astore 6
    //   232: aload 6
    //   234: invokevirtual 194	com/google/android/gms/measurement/internal/zzp:zzCE	()Lcom/google/android/gms/measurement/internal/zzp$zza;
    //   237: astore 6
    //   239: ldc_w 454
    //   242: astore 7
    //   244: aload 6
    //   246: aload 7
    //   248: aload_3
    //   249: invokevirtual 346	com/google/android/gms/measurement/internal/zzp$zza:zzj	(Ljava/lang/String;Ljava/lang/Object;)V
    //   252: aload 4
    //   254: ifnull +10 -> 264
    //   257: aload 4
    //   259: invokeinterface 184 1 0
    //   264: iconst_0
    //   265: istore 12
    //   267: aconst_null
    //   268: astore_3
    //   269: goto -129 -> 140
    //   272: astore_3
    //   273: aconst_null
    //   274: astore 4
    //   276: aload 4
    //   278: ifnull +10 -> 288
    //   281: aload 4
    //   283: invokeinterface 184 1 0
    //   288: aload_3
    //   289: athrow
    //   290: astore_3
    //   291: goto -15 -> 276
    //   294: astore_3
    //   295: aconst_null
    //   296: astore 4
    //   298: goto -72 -> 226
    // Local variable table:
    //   start	length	slot	name	signature
    //   0	301	0	this	zze
    //   0	301	1	paramString	String
    //   0	301	2	paramInt	int
    //   17	154	3	localObject1	Object
    //   225	24	3	localSQLiteException1	SQLiteException
    //   268	1	3	localObject2	Object
    //   272	17	3	localObject3	Object
    //   290	1	3	localObject4	Object
    //   294	1	3	localSQLiteException2	SQLiteException
    //   21	276	4	localObject5	Object
    //   24	3	5	i	int
    //   31	141	6	localObject6	Object
    //   192	26	6	localIOException	IOException
    //   230	15	6	localObject7	Object
    //   34	213	7	localObject8	Object
    //   39	176	8	localObject9	Object
    //   53	3	9	j	int
    //   63	25	10	k	int
    //   77	14	11	str	String
    //   116	150	12	bool	boolean
    // Exception table:
    //   from	to	target	type
    //   171	177	192	java/io/IOException
    //   109	116	225	android/database/sqlite/SQLiteException
    //   149	155	225	android/database/sqlite/SQLiteException
    //   156	160	225	android/database/sqlite/SQLiteException
    //   162	165	225	android/database/sqlite/SQLiteException
    //   166	170	225	android/database/sqlite/SQLiteException
    //   171	177	225	android/database/sqlite/SQLiteException
    //   194	198	225	android/database/sqlite/SQLiteException
    //   200	205	225	android/database/sqlite/SQLiteException
    //   217	222	225	android/database/sqlite/SQLiteException
    //   26	31	272	finally
    //   44	47	272	finally
    //   55	60	272	finally
    //   68	70	272	finally
    //   73	77	272	finally
    //   83	86	272	finally
    //   103	107	272	finally
    //   109	116	290	finally
    //   149	155	290	finally
    //   156	160	290	finally
    //   162	165	290	finally
    //   166	170	290	finally
    //   171	177	290	finally
    //   194	198	290	finally
    //   200	205	290	finally
    //   217	222	290	finally
    //   226	230	290	finally
    //   232	237	290	finally
    //   248	252	290	finally
    //   26	31	294	android/database/sqlite/SQLiteException
    //   44	47	294	android/database/sqlite/SQLiteException
    //   55	60	294	android/database/sqlite/SQLiteException
    //   68	70	294	android/database/sqlite/SQLiteException
    //   73	77	294	android/database/sqlite/SQLiteException
    //   83	86	294	android/database/sqlite/SQLiteException
    //   103	107	294	android/database/sqlite/SQLiteException
  }
  
  /* Error */
  public String zzCq()
  {
    // Byte code:
    //   0: aconst_null
    //   1: astore_1
    //   2: aload_0
    //   3: invokevirtual 167	com/google/android/gms/measurement/internal/zze:getWritableDatabase	()Landroid/database/sqlite/SQLiteDatabase;
    //   6: astore_2
    //   7: ldc_w 456
    //   10: astore_3
    //   11: aconst_null
    //   12: astore 4
    //   14: aload_2
    //   15: aload_3
    //   16: aconst_null
    //   17: invokevirtual 173	android/database/sqlite/SQLiteDatabase:rawQuery	(Ljava/lang/String;[Ljava/lang/String;)Landroid/database/Cursor;
    //   20: astore_3
    //   21: aload_3
    //   22: invokeinterface 176 1 0
    //   27: istore 5
    //   29: iload 5
    //   31: ifeq +28 -> 59
    //   34: iconst_0
    //   35: istore 5
    //   37: aconst_null
    //   38: astore_2
    //   39: aload_3
    //   40: iconst_0
    //   41: invokeinterface 459 2 0
    //   46: astore_1
    //   47: aload_3
    //   48: ifnull +9 -> 57
    //   51: aload_3
    //   52: invokeinterface 184 1 0
    //   57: aload_1
    //   58: areturn
    //   59: aload_3
    //   60: ifnull -3 -> 57
    //   63: aload_3
    //   64: invokeinterface 184 1 0
    //   69: goto -12 -> 57
    //   72: astore_2
    //   73: aconst_null
    //   74: astore_3
    //   75: aload_0
    //   76: invokevirtual 188	com/google/android/gms/measurement/internal/zze:zzAo	()Lcom/google/android/gms/measurement/internal/zzp;
    //   79: astore 4
    //   81: aload 4
    //   83: invokevirtual 194	com/google/android/gms/measurement/internal/zzp:zzCE	()Lcom/google/android/gms/measurement/internal/zzp$zza;
    //   86: astore 4
    //   88: ldc_w 461
    //   91: astore 6
    //   93: aload 4
    //   95: aload 6
    //   97: aload_2
    //   98: invokevirtual 346	com/google/android/gms/measurement/internal/zzp$zza:zzj	(Ljava/lang/String;Ljava/lang/Object;)V
    //   101: aload_3
    //   102: ifnull -45 -> 57
    //   105: aload_3
    //   106: invokeinterface 184 1 0
    //   111: goto -54 -> 57
    //   114: astore_2
    //   115: aconst_null
    //   116: astore_3
    //   117: aload_2
    //   118: astore_1
    //   119: aload_3
    //   120: ifnull +9 -> 129
    //   123: aload_3
    //   124: invokeinterface 184 1 0
    //   129: aload_1
    //   130: athrow
    //   131: astore_1
    //   132: goto -13 -> 119
    //   135: astore_2
    //   136: goto -61 -> 75
    // Local variable table:
    //   start	length	slot	name	signature
    //   0	139	0	this	zze
    //   1	129	1	localObject1	Object
    //   131	1	1	localObject2	Object
    //   6	33	2	localSQLiteDatabase	SQLiteDatabase
    //   72	26	2	localSQLiteException1	SQLiteException
    //   114	4	2	localObject3	Object
    //   135	1	2	localSQLiteException2	SQLiteException
    //   10	114	3	localObject4	Object
    //   12	82	4	localObject5	Object
    //   27	9	5	bool	boolean
    //   91	5	6	str	String
    // Exception table:
    //   from	to	target	type
    //   16	20	72	android/database/sqlite/SQLiteException
    //   16	20	114	finally
    //   21	27	131	finally
    //   40	46	131	finally
    //   75	79	131	finally
    //   81	86	131	finally
    //   97	101	131	finally
    //   21	27	135	android/database/sqlite/SQLiteException
    //   40	46	135	android/database/sqlite/SQLiteException
  }
  
  void zzCr()
  {
    zzjk();
    zzjv();
    boolean bool = zzCw();
    if (!bool) {}
    for (;;)
    {
      return;
      zzt.zzb localzzb = zzCo().zzaXm;
      long l1 = localzzb.get();
      zzmq localzzmq = zzjl();
      long l2 = localzzmq.elapsedRealtime();
      l1 = Math.abs(l2 - l1);
      zzd localzzd = zzCp();
      long l3 = localzzd.zzBR();
      bool = l1 < l3;
      if (bool)
      {
        localzzb = zzCo().zzaXm;
        localzzb.set(l2);
        zzCs();
      }
    }
  }
  
  void zzCs()
  {
    zzjk();
    zzjv();
    boolean bool = zzCw();
    if (!bool) {}
    for (;;)
    {
      return;
      Object localObject1 = getWritableDatabase();
      int j = 2;
      Object localObject2 = new String[j];
      String str1 = String.valueOf(zzjl().currentTimeMillis());
      localObject2[0] = str1;
      int k = 1;
      long l = zzCp().zzBQ();
      str1 = String.valueOf(l);
      localObject2[k] = str1;
      String str2 = "queue";
      str1 = "abs(bundle_end_timestamp - ?) > cast(? as integer)";
      int i = ((SQLiteDatabase)localObject1).delete(str2, str1, (String[])localObject2);
      if (i > 0)
      {
        localObject2 = zzAo().zzCK();
        str2 = "Deleted stale rows. rowsDeleted";
        localObject1 = Integer.valueOf(i);
        ((zzp.zza)localObject2).zzj(str2, localObject1);
      }
    }
  }
  
  public long zzCt()
  {
    return zza("select max(bundle_end_timestamp) from queue", null, 0L);
  }
  
  public long zzCu()
  {
    return zza("select max(timestamp) from raw_events", null, 0L);
  }
  
  public boolean zzCv()
  {
    String str = "select count(1) > 0 from raw_events";
    long l1 = zzb(str, null);
    long l2 = 0L;
    boolean bool = l1 < l2;
    if (bool) {
      bool = true;
    }
    for (;;)
    {
      return bool;
      bool = false;
      str = null;
    }
  }
  
  /* Error */
  public zzi zzI(String paramString1, String paramString2)
  {
    // Byte code:
    //   0: aconst_null
    //   1: astore_3
    //   2: aload_1
    //   3: invokestatic 216	com/google/android/gms/common/internal/zzx:zzcM	(Ljava/lang/String;)Ljava/lang/String;
    //   6: pop
    //   7: aload_2
    //   8: invokestatic 216	com/google/android/gms/common/internal/zzx:zzcM	(Ljava/lang/String;)Ljava/lang/String;
    //   11: pop
    //   12: aload_0
    //   13: invokevirtual 210	com/google/android/gms/measurement/internal/zze:zzjk	()V
    //   16: aload_0
    //   17: invokevirtual 207	com/google/android/gms/measurement/internal/zze:zzjv	()V
    //   20: aload_0
    //   21: invokevirtual 167	com/google/android/gms/measurement/internal/zze:getWritableDatabase	()Landroid/database/sqlite/SQLiteDatabase;
    //   24: astore 4
    //   26: ldc_w 534
    //   29: astore 5
    //   31: iconst_3
    //   32: istore 6
    //   34: iload 6
    //   36: anewarray 289	java/lang/String
    //   39: astore 7
    //   41: iconst_0
    //   42: istore 8
    //   44: aconst_null
    //   45: astore 9
    //   47: ldc_w 536
    //   50: astore 10
    //   52: aload 7
    //   54: iconst_0
    //   55: aload 10
    //   57: aastore
    //   58: iconst_1
    //   59: istore 8
    //   61: ldc_w 538
    //   64: astore 10
    //   66: aload 7
    //   68: iload 8
    //   70: aload 10
    //   72: aastore
    //   73: iconst_2
    //   74: istore 8
    //   76: ldc_w 540
    //   79: astore 10
    //   81: aload 7
    //   83: iload 8
    //   85: aload 10
    //   87: aastore
    //   88: ldc_w 542
    //   91: astore 9
    //   93: iconst_2
    //   94: istore 11
    //   96: iload 11
    //   98: anewarray 289	java/lang/String
    //   101: astore 10
    //   103: iconst_0
    //   104: istore 12
    //   106: aload 10
    //   108: iconst_0
    //   109: aload_1
    //   110: aastore
    //   111: iconst_1
    //   112: istore 12
    //   114: aload 10
    //   116: iload 12
    //   118: aload_2
    //   119: aastore
    //   120: iconst_0
    //   121: istore 12
    //   123: aload 4
    //   125: aload 5
    //   127: aload 7
    //   129: aload 9
    //   131: aload 10
    //   133: aconst_null
    //   134: aconst_null
    //   135: aconst_null
    //   136: invokevirtual 433	android/database/sqlite/SQLiteDatabase:query	(Ljava/lang/String;[Ljava/lang/String;Ljava/lang/String;[Ljava/lang/String;Ljava/lang/String;Ljava/lang/String;Ljava/lang/String;)Landroid/database/Cursor;
    //   139: astore 13
    //   141: aload 13
    //   143: invokeinterface 176 1 0
    //   148: istore 14
    //   150: iload 14
    //   152: ifne +21 -> 173
    //   155: aload 13
    //   157: ifnull +10 -> 167
    //   160: aload 13
    //   162: invokeinterface 184 1 0
    //   167: aconst_null
    //   168: astore 5
    //   170: aload 5
    //   172: areturn
    //   173: iconst_0
    //   174: istore 14
    //   176: aconst_null
    //   177: astore 4
    //   179: aload 13
    //   181: iconst_0
    //   182: invokeinterface 180 2 0
    //   187: lstore 15
    //   189: iconst_1
    //   190: istore 14
    //   192: aload 13
    //   194: iload 14
    //   196: invokeinterface 180 2 0
    //   201: lstore 17
    //   203: iconst_2
    //   204: istore 14
    //   206: aload 13
    //   208: iload 14
    //   210: invokeinterface 180 2 0
    //   215: lstore 19
    //   217: new 544	com/google/android/gms/measurement/internal/zzi
    //   220: astore 5
    //   222: aload_1
    //   223: astore 7
    //   225: aload_2
    //   226: astore 9
    //   228: aload 5
    //   230: aload_1
    //   231: aload_2
    //   232: lload 15
    //   234: lload 17
    //   236: lload 19
    //   238: invokespecial 547	com/google/android/gms/measurement/internal/zzi:<init>	(Ljava/lang/String;Ljava/lang/String;JJJ)V
    //   241: aload 13
    //   243: invokeinterface 550 1 0
    //   248: istore 14
    //   250: iload 14
    //   252: ifeq +28 -> 280
    //   255: aload_0
    //   256: invokevirtual 188	com/google/android/gms/measurement/internal/zze:zzAo	()Lcom/google/android/gms/measurement/internal/zzp;
    //   259: astore 4
    //   261: aload 4
    //   263: invokevirtual 194	com/google/android/gms/measurement/internal/zzp:zzCE	()Lcom/google/android/gms/measurement/internal/zzp$zza;
    //   266: astore 4
    //   268: ldc_w 552
    //   271: astore 7
    //   273: aload 4
    //   275: aload 7
    //   277: invokevirtual 243	com/google/android/gms/measurement/internal/zzp$zza:zzfg	(Ljava/lang/String;)V
    //   280: aload 13
    //   282: ifnull -112 -> 170
    //   285: aload 13
    //   287: invokeinterface 184 1 0
    //   292: goto -122 -> 170
    //   295: astore 4
    //   297: aconst_null
    //   298: astore 5
    //   300: aload_0
    //   301: invokevirtual 188	com/google/android/gms/measurement/internal/zze:zzAo	()Lcom/google/android/gms/measurement/internal/zzp;
    //   304: astore 7
    //   306: aload 7
    //   308: invokevirtual 194	com/google/android/gms/measurement/internal/zzp:zzCE	()Lcom/google/android/gms/measurement/internal/zzp$zza;
    //   311: astore 7
    //   313: ldc_w 554
    //   316: astore 9
    //   318: aload 7
    //   320: aload 9
    //   322: aload_1
    //   323: aload_2
    //   324: aload 4
    //   326: invokevirtual 558	com/google/android/gms/measurement/internal/zzp$zza:zzd	(Ljava/lang/String;Ljava/lang/Object;Ljava/lang/Object;Ljava/lang/Object;)V
    //   329: aload 5
    //   331: ifnull +10 -> 341
    //   334: aload 5
    //   336: invokeinterface 184 1 0
    //   341: aconst_null
    //   342: astore 5
    //   344: goto -174 -> 170
    //   347: astore 4
    //   349: aload_3
    //   350: ifnull +9 -> 359
    //   353: aload_3
    //   354: invokeinterface 184 1 0
    //   359: aload 4
    //   361: athrow
    //   362: astore 4
    //   364: aload 13
    //   366: astore_3
    //   367: goto -18 -> 349
    //   370: astore 4
    //   372: aload 5
    //   374: astore_3
    //   375: goto -26 -> 349
    //   378: astore 4
    //   380: aload 13
    //   382: astore 5
    //   384: goto -84 -> 300
    // Local variable table:
    //   start	length	slot	name	signature
    //   0	387	0	this	zze
    //   0	387	1	paramString1	String
    //   0	387	2	paramString2	String
    //   1	374	3	localObject1	Object
    //   24	250	4	localObject2	Object
    //   295	30	4	localSQLiteException1	SQLiteException
    //   347	13	4	localObject3	Object
    //   362	1	4	localObject4	Object
    //   370	1	4	localObject5	Object
    //   378	1	4	localSQLiteException2	SQLiteException
    //   29	354	5	localObject6	Object
    //   32	3	6	i	int
    //   39	280	7	localObject7	Object
    //   42	42	8	j	int
    //   45	276	9	str	String
    //   50	82	10	localObject8	Object
    //   94	3	11	k	int
    //   104	18	12	m	int
    //   139	242	13	localCursor	Cursor
    //   148	47	14	n	int
    //   204	5	14	i1	int
    //   248	3	14	bool	boolean
    //   187	46	15	l1	long
    //   201	34	17	l2	long
    //   215	22	19	l3	long
    // Exception table:
    //   from	to	target	type
    //   20	24	295	android/database/sqlite/SQLiteException
    //   34	39	295	android/database/sqlite/SQLiteException
    //   55	58	295	android/database/sqlite/SQLiteException
    //   70	73	295	android/database/sqlite/SQLiteException
    //   85	88	295	android/database/sqlite/SQLiteException
    //   96	101	295	android/database/sqlite/SQLiteException
    //   109	111	295	android/database/sqlite/SQLiteException
    //   118	120	295	android/database/sqlite/SQLiteException
    //   135	139	295	android/database/sqlite/SQLiteException
    //   20	24	347	finally
    //   34	39	347	finally
    //   55	58	347	finally
    //   70	73	347	finally
    //   85	88	347	finally
    //   96	101	347	finally
    //   109	111	347	finally
    //   118	120	347	finally
    //   135	139	347	finally
    //   141	148	362	finally
    //   181	187	362	finally
    //   194	201	362	finally
    //   208	215	362	finally
    //   217	220	362	finally
    //   236	241	362	finally
    //   241	248	362	finally
    //   255	259	362	finally
    //   261	266	362	finally
    //   275	280	362	finally
    //   300	304	370	finally
    //   306	311	370	finally
    //   324	329	370	finally
    //   141	148	378	android/database/sqlite/SQLiteException
    //   181	187	378	android/database/sqlite/SQLiteException
    //   194	201	378	android/database/sqlite/SQLiteException
    //   208	215	378	android/database/sqlite/SQLiteException
    //   217	220	378	android/database/sqlite/SQLiteException
    //   236	241	378	android/database/sqlite/SQLiteException
    //   241	248	378	android/database/sqlite/SQLiteException
    //   255	259	378	android/database/sqlite/SQLiteException
    //   261	266	378	android/database/sqlite/SQLiteException
    //   275	280	378	android/database/sqlite/SQLiteException
  }
  
  public void zzJ(String paramString1, String paramString2)
  {
    zzx.zzcM(paramString1);
    zzx.zzcM(paramString2);
    zzjk();
    zzjv();
    try
    {
      Object localObject1 = getWritableDatabase();
      localObject2 = "user_attributes";
      str = "app_id=? and name=?";
      int i = 2;
      String[] arrayOfString = new String[i];
      int j = 0;
      arrayOfString[0] = paramString1;
      j = 1;
      arrayOfString[j] = paramString2;
      int k = ((SQLiteDatabase)localObject1).delete((String)localObject2, str, arrayOfString);
      localObject2 = zzAo();
      localObject2 = ((zzp)localObject2).zzCK();
      str = "Deleted user attribute rows:";
      localObject1 = Integer.valueOf(k);
      ((zzp.zza)localObject2).zzj(str, localObject1);
      return;
    }
    catch (SQLiteException localSQLiteException)
    {
      for (;;)
      {
        Object localObject2 = zzAo().zzCE();
        String str = "Error deleting user attribute";
        ((zzp.zza)localObject2).zzd(str, paramString1, paramString2, localSQLiteException);
      }
    }
  }
  
  /* Error */
  public zzai zzK(String paramString1, String paramString2)
  {
    // Byte code:
    //   0: aconst_null
    //   1: astore_3
    //   2: aload_1
    //   3: invokestatic 216	com/google/android/gms/common/internal/zzx:zzcM	(Ljava/lang/String;)Ljava/lang/String;
    //   6: pop
    //   7: aload_2
    //   8: invokestatic 216	com/google/android/gms/common/internal/zzx:zzcM	(Ljava/lang/String;)Ljava/lang/String;
    //   11: pop
    //   12: aload_0
    //   13: invokevirtual 210	com/google/android/gms/measurement/internal/zze:zzjk	()V
    //   16: aload_0
    //   17: invokevirtual 207	com/google/android/gms/measurement/internal/zze:zzjv	()V
    //   20: aload_0
    //   21: invokevirtual 167	com/google/android/gms/measurement/internal/zze:getWritableDatabase	()Landroid/database/sqlite/SQLiteDatabase;
    //   24: astore 4
    //   26: ldc_w 560
    //   29: astore 5
    //   31: iconst_2
    //   32: istore 6
    //   34: iload 6
    //   36: anewarray 289	java/lang/String
    //   39: astore 7
    //   41: iconst_0
    //   42: istore 8
    //   44: aconst_null
    //   45: astore 9
    //   47: ldc_w 566
    //   50: astore 10
    //   52: aload 7
    //   54: iconst_0
    //   55: aload 10
    //   57: aastore
    //   58: iconst_1
    //   59: istore 8
    //   61: ldc_w 568
    //   64: astore 10
    //   66: aload 7
    //   68: iload 8
    //   70: aload 10
    //   72: aastore
    //   73: ldc_w 542
    //   76: astore 9
    //   78: iconst_2
    //   79: istore 11
    //   81: iload 11
    //   83: anewarray 289	java/lang/String
    //   86: astore 10
    //   88: iconst_0
    //   89: istore 12
    //   91: aload 10
    //   93: iconst_0
    //   94: aload_1
    //   95: aastore
    //   96: iconst_1
    //   97: istore 12
    //   99: aload 10
    //   101: iload 12
    //   103: aload_2
    //   104: aastore
    //   105: iconst_0
    //   106: istore 12
    //   108: aconst_null
    //   109: astore 13
    //   111: aconst_null
    //   112: astore 14
    //   114: aload 4
    //   116: aload 5
    //   118: aload 7
    //   120: aload 9
    //   122: aload 10
    //   124: aconst_null
    //   125: aconst_null
    //   126: aconst_null
    //   127: invokevirtual 433	android/database/sqlite/SQLiteDatabase:query	(Ljava/lang/String;[Ljava/lang/String;Ljava/lang/String;[Ljava/lang/String;Ljava/lang/String;Ljava/lang/String;Ljava/lang/String;)Landroid/database/Cursor;
    //   130: astore 14
    //   132: aload 14
    //   134: invokeinterface 176 1 0
    //   139: istore 15
    //   141: iload 15
    //   143: ifne +21 -> 164
    //   146: aload 14
    //   148: ifnull +10 -> 158
    //   151: aload 14
    //   153: invokeinterface 184 1 0
    //   158: aconst_null
    //   159: astore 5
    //   161: aload 5
    //   163: areturn
    //   164: iconst_0
    //   165: istore 15
    //   167: aconst_null
    //   168: astore 4
    //   170: aload 14
    //   172: iconst_0
    //   173: invokeinterface 180 2 0
    //   178: lstore 16
    //   180: iconst_1
    //   181: istore 15
    //   183: aload_0
    //   184: aload 14
    //   186: iload 15
    //   188: invokevirtual 571	com/google/android/gms/measurement/internal/zze:zzb	(Landroid/database/Cursor;I)Ljava/lang/Object;
    //   191: astore 13
    //   193: new 573	com/google/android/gms/measurement/internal/zzai
    //   196: astore 5
    //   198: aload_1
    //   199: astore 7
    //   201: aload_2
    //   202: astore 9
    //   204: aload 5
    //   206: aload_1
    //   207: aload_2
    //   208: lload 16
    //   210: aload 13
    //   212: invokespecial 576	com/google/android/gms/measurement/internal/zzai:<init>	(Ljava/lang/String;Ljava/lang/String;JLjava/lang/Object;)V
    //   215: aload 14
    //   217: invokeinterface 550 1 0
    //   222: istore 15
    //   224: iload 15
    //   226: ifeq +28 -> 254
    //   229: aload_0
    //   230: invokevirtual 188	com/google/android/gms/measurement/internal/zze:zzAo	()Lcom/google/android/gms/measurement/internal/zzp;
    //   233: astore 4
    //   235: aload 4
    //   237: invokevirtual 194	com/google/android/gms/measurement/internal/zzp:zzCE	()Lcom/google/android/gms/measurement/internal/zzp$zza;
    //   240: astore 4
    //   242: ldc_w 578
    //   245: astore 7
    //   247: aload 4
    //   249: aload 7
    //   251: invokevirtual 243	com/google/android/gms/measurement/internal/zzp$zza:zzfg	(Ljava/lang/String;)V
    //   254: aload 14
    //   256: ifnull -95 -> 161
    //   259: aload 14
    //   261: invokeinterface 184 1 0
    //   266: goto -105 -> 161
    //   269: astore 4
    //   271: aconst_null
    //   272: astore 5
    //   274: aload_0
    //   275: invokevirtual 188	com/google/android/gms/measurement/internal/zze:zzAo	()Lcom/google/android/gms/measurement/internal/zzp;
    //   278: astore 7
    //   280: aload 7
    //   282: invokevirtual 194	com/google/android/gms/measurement/internal/zzp:zzCE	()Lcom/google/android/gms/measurement/internal/zzp$zza;
    //   285: astore 7
    //   287: ldc_w 580
    //   290: astore 9
    //   292: aload 7
    //   294: aload 9
    //   296: aload_1
    //   297: aload_2
    //   298: aload 4
    //   300: invokevirtual 558	com/google/android/gms/measurement/internal/zzp$zza:zzd	(Ljava/lang/String;Ljava/lang/Object;Ljava/lang/Object;Ljava/lang/Object;)V
    //   303: aload 5
    //   305: ifnull +10 -> 315
    //   308: aload 5
    //   310: invokeinterface 184 1 0
    //   315: aconst_null
    //   316: astore 5
    //   318: goto -157 -> 161
    //   321: astore 4
    //   323: aload_3
    //   324: ifnull +9 -> 333
    //   327: aload_3
    //   328: invokeinterface 184 1 0
    //   333: aload 4
    //   335: athrow
    //   336: astore 4
    //   338: aload 14
    //   340: astore_3
    //   341: goto -18 -> 323
    //   344: astore 4
    //   346: aload 5
    //   348: astore_3
    //   349: goto -26 -> 323
    //   352: astore 4
    //   354: aload 14
    //   356: astore 5
    //   358: goto -84 -> 274
    // Local variable table:
    //   start	length	slot	name	signature
    //   0	361	0	this	zze
    //   0	361	1	paramString1	String
    //   0	361	2	paramString2	String
    //   1	348	3	localObject1	Object
    //   24	224	4	localObject2	Object
    //   269	30	4	localSQLiteException1	SQLiteException
    //   321	13	4	localObject3	Object
    //   336	1	4	localObject4	Object
    //   344	1	4	localObject5	Object
    //   352	1	4	localSQLiteException2	SQLiteException
    //   29	328	5	localObject6	Object
    //   32	3	6	i	int
    //   39	254	7	localObject7	Object
    //   42	27	8	j	int
    //   45	250	9	str	String
    //   50	73	10	localObject8	Object
    //   79	3	11	k	int
    //   89	18	12	m	int
    //   109	102	13	localObject9	Object
    //   112	243	14	localCursor	Cursor
    //   139	48	15	n	int
    //   222	3	15	bool	boolean
    //   178	31	16	l	long
    // Exception table:
    //   from	to	target	type
    //   20	24	269	android/database/sqlite/SQLiteException
    //   34	39	269	android/database/sqlite/SQLiteException
    //   55	58	269	android/database/sqlite/SQLiteException
    //   70	73	269	android/database/sqlite/SQLiteException
    //   81	86	269	android/database/sqlite/SQLiteException
    //   94	96	269	android/database/sqlite/SQLiteException
    //   103	105	269	android/database/sqlite/SQLiteException
    //   126	130	269	android/database/sqlite/SQLiteException
    //   20	24	321	finally
    //   34	39	321	finally
    //   55	58	321	finally
    //   70	73	321	finally
    //   81	86	321	finally
    //   94	96	321	finally
    //   103	105	321	finally
    //   126	130	321	finally
    //   132	139	336	finally
    //   172	178	336	finally
    //   186	191	336	finally
    //   193	196	336	finally
    //   210	215	336	finally
    //   215	222	336	finally
    //   229	233	336	finally
    //   235	240	336	finally
    //   249	254	336	finally
    //   274	278	344	finally
    //   280	285	344	finally
    //   298	303	344	finally
    //   132	139	352	android/database/sqlite/SQLiteException
    //   172	178	352	android/database/sqlite/SQLiteException
    //   186	191	352	android/database/sqlite/SQLiteException
    //   193	196	352	android/database/sqlite/SQLiteException
    //   210	215	352	android/database/sqlite/SQLiteException
    //   215	222	352	android/database/sqlite/SQLiteException
    //   229	233	352	android/database/sqlite/SQLiteException
    //   235	240	352	android/database/sqlite/SQLiteException
    //   249	254	352	android/database/sqlite/SQLiteException
  }
  
  /* Error */
  Map zzL(String paramString1, String paramString2)
  {
    // Byte code:
    //   0: aload_0
    //   1: invokevirtual 207	com/google/android/gms/measurement/internal/zze:zzjv	()V
    //   4: aload_0
    //   5: invokevirtual 210	com/google/android/gms/measurement/internal/zze:zzjk	()V
    //   8: aload_1
    //   9: invokestatic 216	com/google/android/gms/common/internal/zzx:zzcM	(Ljava/lang/String;)Ljava/lang/String;
    //   12: pop
    //   13: aload_2
    //   14: invokestatic 216	com/google/android/gms/common/internal/zzx:zzcM	(Ljava/lang/String;)Ljava/lang/String;
    //   17: pop
    //   18: new 12	android/support/v4/h/a
    //   21: astore_3
    //   22: aload_3
    //   23: invokespecial 581	android/support/v4/h/a:<init>	()V
    //   26: aload_0
    //   27: invokevirtual 167	com/google/android/gms/measurement/internal/zze:getWritableDatabase	()Landroid/database/sqlite/SQLiteDatabase;
    //   30: astore 4
    //   32: ldc_w 333
    //   35: astore 5
    //   37: iconst_2
    //   38: istore 6
    //   40: iload 6
    //   42: anewarray 289	java/lang/String
    //   45: astore 7
    //   47: iconst_0
    //   48: istore 8
    //   50: aconst_null
    //   51: astore 9
    //   53: ldc_w 319
    //   56: astore 10
    //   58: aload 7
    //   60: iconst_0
    //   61: aload 10
    //   63: aastore
    //   64: iconst_1
    //   65: istore 8
    //   67: ldc_w 328
    //   70: astore 10
    //   72: aload 7
    //   74: iload 8
    //   76: aload 10
    //   78: aastore
    //   79: ldc_w 583
    //   82: astore 9
    //   84: iconst_2
    //   85: istore 11
    //   87: iload 11
    //   89: anewarray 289	java/lang/String
    //   92: astore 10
    //   94: iconst_0
    //   95: istore 12
    //   97: aload 10
    //   99: iconst_0
    //   100: aload_1
    //   101: aastore
    //   102: iconst_1
    //   103: istore 12
    //   105: aload 10
    //   107: iload 12
    //   109: aload_2
    //   110: aastore
    //   111: iconst_0
    //   112: istore 12
    //   114: aload 4
    //   116: aload 5
    //   118: aload 7
    //   120: aload 9
    //   122: aload 10
    //   124: aconst_null
    //   125: aconst_null
    //   126: aconst_null
    //   127: invokevirtual 433	android/database/sqlite/SQLiteDatabase:query	(Ljava/lang/String;[Ljava/lang/String;Ljava/lang/String;[Ljava/lang/String;Ljava/lang/String;Ljava/lang/String;Ljava/lang/String;)Landroid/database/Cursor;
    //   130: astore 5
    //   132: aload 5
    //   134: invokeinterface 176 1 0
    //   139: istore 13
    //   141: iload 13
    //   143: ifne +23 -> 166
    //   146: invokestatic 589	java/util/Collections:emptyMap	()Ljava/util/Map;
    //   149: astore 4
    //   151: aload 5
    //   153: ifnull +10 -> 163
    //   156: aload 5
    //   158: invokeinterface 184 1 0
    //   163: aload 4
    //   165: areturn
    //   166: iconst_1
    //   167: istore 13
    //   169: aload 5
    //   171: iload 13
    //   173: invokeinterface 437 2 0
    //   178: astore 4
    //   180: aload 4
    //   182: invokestatic 443	com/google/android/gms/internal/zzsm:zzD	([B)Lcom/google/android/gms/internal/zzsm;
    //   185: astore 4
    //   187: new 250	com/google/android/gms/internal/zzpz$zzb
    //   190: astore 7
    //   192: aload 7
    //   194: invokespecial 590	com/google/android/gms/internal/zzpz$zzb:<init>	()V
    //   197: aload 7
    //   199: aload 4
    //   201: invokevirtual 594	com/google/android/gms/internal/zzpz$zzb:zzu	(Lcom/google/android/gms/internal/zzsm;)Lcom/google/android/gms/internal/zzpz$zzb;
    //   204: pop
    //   205: iconst_0
    //   206: istore 13
    //   208: aconst_null
    //   209: astore 4
    //   211: aload 5
    //   213: iconst_0
    //   214: invokeinterface 597 2 0
    //   219: istore 8
    //   221: iload 8
    //   223: invokestatic 287	java/lang/Integer:valueOf	(I)Ljava/lang/Integer;
    //   226: astore 4
    //   228: aload_3
    //   229: aload 4
    //   231: invokeinterface 599 2 0
    //   236: astore 4
    //   238: aload 4
    //   240: checkcast 601	java/util/List
    //   243: astore 4
    //   245: aload 4
    //   247: ifnonnull +31 -> 278
    //   250: new 603	java/util/ArrayList
    //   253: astore 4
    //   255: aload 4
    //   257: invokespecial 604	java/util/ArrayList:<init>	()V
    //   260: iload 8
    //   262: invokestatic 287	java/lang/Integer:valueOf	(I)Ljava/lang/Integer;
    //   265: astore 9
    //   267: aload_3
    //   268: aload 9
    //   270: aload 4
    //   272: invokeinterface 29 3 0
    //   277: pop
    //   278: aload 4
    //   280: aload 7
    //   282: invokeinterface 608 2 0
    //   287: pop
    //   288: aload 5
    //   290: invokeinterface 550 1 0
    //   295: istore 13
    //   297: iload 13
    //   299: ifne -133 -> 166
    //   302: aload 5
    //   304: ifnull +10 -> 314
    //   307: aload 5
    //   309: invokeinterface 184 1 0
    //   314: aload_3
    //   315: astore 4
    //   317: goto -154 -> 163
    //   320: astore 4
    //   322: aload_0
    //   323: invokevirtual 188	com/google/android/gms/measurement/internal/zze:zzAo	()Lcom/google/android/gms/measurement/internal/zzp;
    //   326: astore 7
    //   328: aload 7
    //   330: invokevirtual 194	com/google/android/gms/measurement/internal/zzp:zzCE	()Lcom/google/android/gms/measurement/internal/zzp$zza;
    //   333: astore 7
    //   335: ldc_w 610
    //   338: astore 9
    //   340: aload 7
    //   342: aload 9
    //   344: aload_1
    //   345: aload 4
    //   347: invokevirtual 202	com/google/android/gms/measurement/internal/zzp$zza:zze	(Ljava/lang/String;Ljava/lang/Object;Ljava/lang/Object;)V
    //   350: goto -62 -> 288
    //   353: astore 4
    //   355: aload_0
    //   356: invokevirtual 188	com/google/android/gms/measurement/internal/zze:zzAo	()Lcom/google/android/gms/measurement/internal/zzp;
    //   359: astore 7
    //   361: aload 7
    //   363: invokevirtual 194	com/google/android/gms/measurement/internal/zzp:zzCE	()Lcom/google/android/gms/measurement/internal/zzp$zza;
    //   366: astore 7
    //   368: ldc_w 612
    //   371: astore 9
    //   373: aload 7
    //   375: aload 9
    //   377: aload 4
    //   379: invokevirtual 346	com/google/android/gms/measurement/internal/zzp$zza:zzj	(Ljava/lang/String;Ljava/lang/Object;)V
    //   382: aload 5
    //   384: ifnull +10 -> 394
    //   387: aload 5
    //   389: invokeinterface 184 1 0
    //   394: iconst_0
    //   395: istore 13
    //   397: aconst_null
    //   398: astore 4
    //   400: goto -237 -> 163
    //   403: astore 4
    //   405: aconst_null
    //   406: astore 5
    //   408: aload 5
    //   410: ifnull +10 -> 420
    //   413: aload 5
    //   415: invokeinterface 184 1 0
    //   420: aload 4
    //   422: athrow
    //   423: astore 4
    //   425: goto -17 -> 408
    //   428: astore 4
    //   430: aconst_null
    //   431: astore 5
    //   433: goto -78 -> 355
    // Local variable table:
    //   start	length	slot	name	signature
    //   0	436	0	this	zze
    //   0	436	1	paramString1	String
    //   0	436	2	paramString2	String
    //   21	294	3	locala	a
    //   30	286	4	localObject1	Object
    //   320	26	4	localIOException	IOException
    //   353	25	4	localSQLiteException1	SQLiteException
    //   398	1	4	localObject2	Object
    //   403	18	4	localObject3	Object
    //   423	1	4	localObject4	Object
    //   428	1	4	localSQLiteException2	SQLiteException
    //   35	397	5	localObject5	Object
    //   38	3	6	i	int
    //   45	329	7	localObject6	Object
    //   48	213	8	j	int
    //   51	325	9	localObject7	Object
    //   56	67	10	localObject8	Object
    //   85	3	11	k	int
    //   95	18	12	m	int
    //   139	33	13	n	int
    //   206	190	13	bool	boolean
    // Exception table:
    //   from	to	target	type
    //   199	205	320	java/io/IOException
    //   132	139	353	android/database/sqlite/SQLiteException
    //   146	149	353	android/database/sqlite/SQLiteException
    //   171	178	353	android/database/sqlite/SQLiteException
    //   180	185	353	android/database/sqlite/SQLiteException
    //   187	190	353	android/database/sqlite/SQLiteException
    //   192	197	353	android/database/sqlite/SQLiteException
    //   199	205	353	android/database/sqlite/SQLiteException
    //   213	219	353	android/database/sqlite/SQLiteException
    //   221	226	353	android/database/sqlite/SQLiteException
    //   229	236	353	android/database/sqlite/SQLiteException
    //   238	243	353	android/database/sqlite/SQLiteException
    //   250	253	353	android/database/sqlite/SQLiteException
    //   255	260	353	android/database/sqlite/SQLiteException
    //   260	265	353	android/database/sqlite/SQLiteException
    //   270	278	353	android/database/sqlite/SQLiteException
    //   280	288	353	android/database/sqlite/SQLiteException
    //   288	295	353	android/database/sqlite/SQLiteException
    //   322	326	353	android/database/sqlite/SQLiteException
    //   328	333	353	android/database/sqlite/SQLiteException
    //   345	350	353	android/database/sqlite/SQLiteException
    //   40	45	403	finally
    //   61	64	403	finally
    //   76	79	403	finally
    //   87	92	403	finally
    //   100	102	403	finally
    //   109	111	403	finally
    //   126	130	403	finally
    //   132	139	423	finally
    //   146	149	423	finally
    //   171	178	423	finally
    //   180	185	423	finally
    //   187	190	423	finally
    //   192	197	423	finally
    //   199	205	423	finally
    //   213	219	423	finally
    //   221	226	423	finally
    //   229	236	423	finally
    //   238	243	423	finally
    //   250	253	423	finally
    //   255	260	423	finally
    //   260	265	423	finally
    //   270	278	423	finally
    //   280	288	423	finally
    //   288	295	423	finally
    //   322	326	423	finally
    //   328	333	423	finally
    //   345	350	423	finally
    //   355	359	423	finally
    //   361	366	423	finally
    //   377	382	423	finally
    //   40	45	428	android/database/sqlite/SQLiteException
    //   61	64	428	android/database/sqlite/SQLiteException
    //   76	79	428	android/database/sqlite/SQLiteException
    //   87	92	428	android/database/sqlite/SQLiteException
    //   100	102	428	android/database/sqlite/SQLiteException
    //   109	111	428	android/database/sqlite/SQLiteException
    //   126	130	428	android/database/sqlite/SQLiteException
  }
  
  /* Error */
  Map zzM(String paramString1, String paramString2)
  {
    // Byte code:
    //   0: aload_0
    //   1: invokevirtual 207	com/google/android/gms/measurement/internal/zze:zzjv	()V
    //   4: aload_0
    //   5: invokevirtual 210	com/google/android/gms/measurement/internal/zze:zzjk	()V
    //   8: aload_1
    //   9: invokestatic 216	com/google/android/gms/common/internal/zzx:zzcM	(Ljava/lang/String;)Ljava/lang/String;
    //   12: pop
    //   13: aload_2
    //   14: invokestatic 216	com/google/android/gms/common/internal/zzx:zzcM	(Ljava/lang/String;)Ljava/lang/String;
    //   17: pop
    //   18: new 12	android/support/v4/h/a
    //   21: astore_3
    //   22: aload_3
    //   23: invokespecial 581	android/support/v4/h/a:<init>	()V
    //   26: aload_0
    //   27: invokevirtual 167	com/google/android/gms/measurement/internal/zze:getWritableDatabase	()Landroid/database/sqlite/SQLiteDatabase;
    //   30: astore 4
    //   32: ldc_w 361
    //   35: astore 5
    //   37: iconst_2
    //   38: istore 6
    //   40: iload 6
    //   42: anewarray 289	java/lang/String
    //   45: astore 7
    //   47: iconst_0
    //   48: istore 8
    //   50: aconst_null
    //   51: astore 9
    //   53: ldc_w 319
    //   56: astore 10
    //   58: aload 7
    //   60: iconst_0
    //   61: aload 10
    //   63: aastore
    //   64: iconst_1
    //   65: istore 8
    //   67: ldc_w 328
    //   70: astore 10
    //   72: aload 7
    //   74: iload 8
    //   76: aload 10
    //   78: aastore
    //   79: ldc_w 614
    //   82: astore 9
    //   84: iconst_2
    //   85: istore 11
    //   87: iload 11
    //   89: anewarray 289	java/lang/String
    //   92: astore 10
    //   94: iconst_0
    //   95: istore 12
    //   97: aload 10
    //   99: iconst_0
    //   100: aload_1
    //   101: aastore
    //   102: iconst_1
    //   103: istore 12
    //   105: aload 10
    //   107: iload 12
    //   109: aload_2
    //   110: aastore
    //   111: iconst_0
    //   112: istore 12
    //   114: aload 4
    //   116: aload 5
    //   118: aload 7
    //   120: aload 9
    //   122: aload 10
    //   124: aconst_null
    //   125: aconst_null
    //   126: aconst_null
    //   127: invokevirtual 433	android/database/sqlite/SQLiteDatabase:query	(Ljava/lang/String;[Ljava/lang/String;Ljava/lang/String;[Ljava/lang/String;Ljava/lang/String;Ljava/lang/String;Ljava/lang/String;)Landroid/database/Cursor;
    //   130: astore 5
    //   132: aload 5
    //   134: invokeinterface 176 1 0
    //   139: istore 13
    //   141: iload 13
    //   143: ifne +23 -> 166
    //   146: invokestatic 589	java/util/Collections:emptyMap	()Ljava/util/Map;
    //   149: astore 4
    //   151: aload 5
    //   153: ifnull +10 -> 163
    //   156: aload 5
    //   158: invokeinterface 184 1 0
    //   163: aload 4
    //   165: areturn
    //   166: iconst_1
    //   167: istore 13
    //   169: aload 5
    //   171: iload 13
    //   173: invokeinterface 437 2 0
    //   178: astore 4
    //   180: aload 4
    //   182: invokestatic 443	com/google/android/gms/internal/zzsm:zzD	([B)Lcom/google/android/gms/internal/zzsm;
    //   185: astore 4
    //   187: new 257	com/google/android/gms/internal/zzpz$zze
    //   190: astore 7
    //   192: aload 7
    //   194: invokespecial 615	com/google/android/gms/internal/zzpz$zze:<init>	()V
    //   197: aload 7
    //   199: aload 4
    //   201: invokevirtual 619	com/google/android/gms/internal/zzpz$zze:zzx	(Lcom/google/android/gms/internal/zzsm;)Lcom/google/android/gms/internal/zzpz$zze;
    //   204: pop
    //   205: iconst_0
    //   206: istore 13
    //   208: aconst_null
    //   209: astore 4
    //   211: aload 5
    //   213: iconst_0
    //   214: invokeinterface 597 2 0
    //   219: istore 8
    //   221: iload 8
    //   223: invokestatic 287	java/lang/Integer:valueOf	(I)Ljava/lang/Integer;
    //   226: astore 4
    //   228: aload_3
    //   229: aload 4
    //   231: invokeinterface 599 2 0
    //   236: astore 4
    //   238: aload 4
    //   240: checkcast 601	java/util/List
    //   243: astore 4
    //   245: aload 4
    //   247: ifnonnull +31 -> 278
    //   250: new 603	java/util/ArrayList
    //   253: astore 4
    //   255: aload 4
    //   257: invokespecial 604	java/util/ArrayList:<init>	()V
    //   260: iload 8
    //   262: invokestatic 287	java/lang/Integer:valueOf	(I)Ljava/lang/Integer;
    //   265: astore 9
    //   267: aload_3
    //   268: aload 9
    //   270: aload 4
    //   272: invokeinterface 29 3 0
    //   277: pop
    //   278: aload 4
    //   280: aload 7
    //   282: invokeinterface 608 2 0
    //   287: pop
    //   288: aload 5
    //   290: invokeinterface 550 1 0
    //   295: istore 13
    //   297: iload 13
    //   299: ifne -133 -> 166
    //   302: aload 5
    //   304: ifnull +10 -> 314
    //   307: aload 5
    //   309: invokeinterface 184 1 0
    //   314: aload_3
    //   315: astore 4
    //   317: goto -154 -> 163
    //   320: astore 4
    //   322: aload_0
    //   323: invokevirtual 188	com/google/android/gms/measurement/internal/zze:zzAo	()Lcom/google/android/gms/measurement/internal/zzp;
    //   326: astore 7
    //   328: aload 7
    //   330: invokevirtual 194	com/google/android/gms/measurement/internal/zzp:zzCE	()Lcom/google/android/gms/measurement/internal/zzp$zza;
    //   333: astore 7
    //   335: ldc_w 610
    //   338: astore 9
    //   340: aload 7
    //   342: aload 9
    //   344: aload_1
    //   345: aload 4
    //   347: invokevirtual 202	com/google/android/gms/measurement/internal/zzp$zza:zze	(Ljava/lang/String;Ljava/lang/Object;Ljava/lang/Object;)V
    //   350: goto -62 -> 288
    //   353: astore 4
    //   355: aload_0
    //   356: invokevirtual 188	com/google/android/gms/measurement/internal/zze:zzAo	()Lcom/google/android/gms/measurement/internal/zzp;
    //   359: astore 7
    //   361: aload 7
    //   363: invokevirtual 194	com/google/android/gms/measurement/internal/zzp:zzCE	()Lcom/google/android/gms/measurement/internal/zzp$zza;
    //   366: astore 7
    //   368: ldc_w 612
    //   371: astore 9
    //   373: aload 7
    //   375: aload 9
    //   377: aload 4
    //   379: invokevirtual 346	com/google/android/gms/measurement/internal/zzp$zza:zzj	(Ljava/lang/String;Ljava/lang/Object;)V
    //   382: aload 5
    //   384: ifnull +10 -> 394
    //   387: aload 5
    //   389: invokeinterface 184 1 0
    //   394: iconst_0
    //   395: istore 13
    //   397: aconst_null
    //   398: astore 4
    //   400: goto -237 -> 163
    //   403: astore 4
    //   405: aconst_null
    //   406: astore 5
    //   408: aload 5
    //   410: ifnull +10 -> 420
    //   413: aload 5
    //   415: invokeinterface 184 1 0
    //   420: aload 4
    //   422: athrow
    //   423: astore 4
    //   425: goto -17 -> 408
    //   428: astore 4
    //   430: aconst_null
    //   431: astore 5
    //   433: goto -78 -> 355
    // Local variable table:
    //   start	length	slot	name	signature
    //   0	436	0	this	zze
    //   0	436	1	paramString1	String
    //   0	436	2	paramString2	String
    //   21	294	3	locala	a
    //   30	286	4	localObject1	Object
    //   320	26	4	localIOException	IOException
    //   353	25	4	localSQLiteException1	SQLiteException
    //   398	1	4	localObject2	Object
    //   403	18	4	localObject3	Object
    //   423	1	4	localObject4	Object
    //   428	1	4	localSQLiteException2	SQLiteException
    //   35	397	5	localObject5	Object
    //   38	3	6	i	int
    //   45	329	7	localObject6	Object
    //   48	213	8	j	int
    //   51	325	9	localObject7	Object
    //   56	67	10	localObject8	Object
    //   85	3	11	k	int
    //   95	18	12	m	int
    //   139	33	13	n	int
    //   206	190	13	bool	boolean
    // Exception table:
    //   from	to	target	type
    //   199	205	320	java/io/IOException
    //   132	139	353	android/database/sqlite/SQLiteException
    //   146	149	353	android/database/sqlite/SQLiteException
    //   171	178	353	android/database/sqlite/SQLiteException
    //   180	185	353	android/database/sqlite/SQLiteException
    //   187	190	353	android/database/sqlite/SQLiteException
    //   192	197	353	android/database/sqlite/SQLiteException
    //   199	205	353	android/database/sqlite/SQLiteException
    //   213	219	353	android/database/sqlite/SQLiteException
    //   221	226	353	android/database/sqlite/SQLiteException
    //   229	236	353	android/database/sqlite/SQLiteException
    //   238	243	353	android/database/sqlite/SQLiteException
    //   250	253	353	android/database/sqlite/SQLiteException
    //   255	260	353	android/database/sqlite/SQLiteException
    //   260	265	353	android/database/sqlite/SQLiteException
    //   270	278	353	android/database/sqlite/SQLiteException
    //   280	288	353	android/database/sqlite/SQLiteException
    //   288	295	353	android/database/sqlite/SQLiteException
    //   322	326	353	android/database/sqlite/SQLiteException
    //   328	333	353	android/database/sqlite/SQLiteException
    //   345	350	353	android/database/sqlite/SQLiteException
    //   40	45	403	finally
    //   61	64	403	finally
    //   76	79	403	finally
    //   87	92	403	finally
    //   100	102	403	finally
    //   109	111	403	finally
    //   126	130	403	finally
    //   132	139	423	finally
    //   146	149	423	finally
    //   171	178	423	finally
    //   180	185	423	finally
    //   187	190	423	finally
    //   192	197	423	finally
    //   199	205	423	finally
    //   213	219	423	finally
    //   221	226	423	finally
    //   229	236	423	finally
    //   238	243	423	finally
    //   250	253	423	finally
    //   255	260	423	finally
    //   260	265	423	finally
    //   270	278	423	finally
    //   280	288	423	finally
    //   288	295	423	finally
    //   322	326	423	finally
    //   328	333	423	finally
    //   345	350	423	finally
    //   355	359	423	finally
    //   361	366	423	finally
    //   377	382	423	finally
    //   40	45	428	android/database/sqlite/SQLiteException
    //   61	64	428	android/database/sqlite/SQLiteException
    //   76	79	428	android/database/sqlite/SQLiteException
    //   87	92	428	android/database/sqlite/SQLiteException
    //   100	102	428	android/database/sqlite/SQLiteException
    //   109	111	428	android/database/sqlite/SQLiteException
    //   126	130	428	android/database/sqlite/SQLiteException
  }
  
  public void zzZ(long paramLong)
  {
    int i = 1;
    zzjk();
    zzjv();
    Object localObject1 = getWritableDatabase();
    Object localObject2 = new String[i];
    String str1 = String.valueOf(paramLong);
    localObject2[0] = str1;
    String str2 = "queue";
    str1 = "rowid=?";
    int j = ((SQLiteDatabase)localObject1).delete(str2, str1, (String[])localObject2);
    if (j != i)
    {
      localObject1 = zzAo().zzCE();
      localObject2 = "Deleted fewer rows from queue than expected";
      ((zzp.zza)localObject1).zzfg((String)localObject2);
    }
  }
  
  /* Error */
  public zze.zza zza(long paramLong, String paramString, boolean paramBoolean1, boolean paramBoolean2)
  {
    // Byte code:
    //   0: aload_3
    //   1: invokestatic 216	com/google/android/gms/common/internal/zzx:zzcM	(Ljava/lang/String;)Ljava/lang/String;
    //   4: pop
    //   5: aload_0
    //   6: invokevirtual 210	com/google/android/gms/measurement/internal/zze:zzjk	()V
    //   9: aload_0
    //   10: invokevirtual 207	com/google/android/gms/measurement/internal/zze:zzjv	()V
    //   13: iconst_1
    //   14: anewarray 289	java/lang/String
    //   17: astore 6
    //   19: aconst_null
    //   20: astore 7
    //   22: aload 6
    //   24: iconst_0
    //   25: aload_3
    //   26: aastore
    //   27: new 625	com/google/android/gms/measurement/internal/zze$zza
    //   30: astore 8
    //   32: aload 8
    //   34: invokespecial 626	com/google/android/gms/measurement/internal/zze$zza:<init>	()V
    //   37: aload_0
    //   38: invokevirtual 167	com/google/android/gms/measurement/internal/zze:getWritableDatabase	()Landroid/database/sqlite/SQLiteDatabase;
    //   41: astore 7
    //   43: ldc_w 628
    //   46: astore 9
    //   48: iconst_4
    //   49: istore 10
    //   51: iload 10
    //   53: anewarray 289	java/lang/String
    //   56: astore 11
    //   58: iconst_0
    //   59: istore 12
    //   61: aconst_null
    //   62: astore 13
    //   64: ldc 51
    //   66: astore 14
    //   68: aload 11
    //   70: iconst_0
    //   71: aload 14
    //   73: aastore
    //   74: iconst_1
    //   75: istore 12
    //   77: ldc 59
    //   79: astore 14
    //   81: aload 11
    //   83: iload 12
    //   85: aload 14
    //   87: aastore
    //   88: iconst_2
    //   89: istore 12
    //   91: ldc 55
    //   93: astore 14
    //   95: aload 11
    //   97: iload 12
    //   99: aload 14
    //   101: aastore
    //   102: iconst_3
    //   103: istore 12
    //   105: ldc 63
    //   107: astore 14
    //   109: aload 11
    //   111: iload 12
    //   113: aload 14
    //   115: aastore
    //   116: ldc_w 630
    //   119: astore 13
    //   121: iconst_1
    //   122: istore 15
    //   124: iload 15
    //   126: anewarray 289	java/lang/String
    //   129: astore 14
    //   131: aload 14
    //   133: iconst_0
    //   134: aload_3
    //   135: aastore
    //   136: aload 7
    //   138: aload 9
    //   140: aload 11
    //   142: aload 13
    //   144: aload 14
    //   146: aconst_null
    //   147: aconst_null
    //   148: aconst_null
    //   149: invokevirtual 433	android/database/sqlite/SQLiteDatabase:query	(Ljava/lang/String;[Ljava/lang/String;Ljava/lang/String;[Ljava/lang/String;Ljava/lang/String;Ljava/lang/String;Ljava/lang/String;)Landroid/database/Cursor;
    //   152: astore 9
    //   154: aload 9
    //   156: invokeinterface 176 1 0
    //   161: istore 10
    //   163: iload 10
    //   165: ifne +48 -> 213
    //   168: aload_0
    //   169: invokevirtual 188	com/google/android/gms/measurement/internal/zze:zzAo	()Lcom/google/android/gms/measurement/internal/zzp;
    //   172: astore 7
    //   174: aload 7
    //   176: invokevirtual 237	com/google/android/gms/measurement/internal/zzp:zzCF	()Lcom/google/android/gms/measurement/internal/zzp$zza;
    //   179: astore 7
    //   181: ldc_w 632
    //   184: astore 11
    //   186: aload 7
    //   188: aload 11
    //   190: aload_3
    //   191: invokevirtual 346	com/google/android/gms/measurement/internal/zzp$zza:zzj	(Ljava/lang/String;Ljava/lang/Object;)V
    //   194: aload 9
    //   196: ifnull +10 -> 206
    //   199: aload 9
    //   201: invokeinterface 184 1 0
    //   206: aload 8
    //   208: astore 7
    //   210: aload 7
    //   212: areturn
    //   213: iconst_0
    //   214: istore 10
    //   216: aconst_null
    //   217: astore 11
    //   219: aload 9
    //   221: iconst_0
    //   222: invokeinterface 180 2 0
    //   227: lstore 16
    //   229: lload 16
    //   231: lload_1
    //   232: lcmp
    //   233: istore 10
    //   235: iload 10
    //   237: ifne +66 -> 303
    //   240: iconst_1
    //   241: istore 10
    //   243: aload 9
    //   245: iload 10
    //   247: invokeinterface 180 2 0
    //   252: lstore 16
    //   254: aload 8
    //   256: lload 16
    //   258: putfield 636	com/google/android/gms/measurement/internal/zze$zza:zzaVF	J
    //   261: iconst_2
    //   262: istore 10
    //   264: aload 9
    //   266: iload 10
    //   268: invokeinterface 180 2 0
    //   273: lstore 16
    //   275: aload 8
    //   277: lload 16
    //   279: putfield 639	com/google/android/gms/measurement/internal/zze$zza:zzaVE	J
    //   282: iconst_3
    //   283: istore 10
    //   285: aload 9
    //   287: iload 10
    //   289: invokeinterface 180 2 0
    //   294: lstore 16
    //   296: aload 8
    //   298: lload 16
    //   300: putfield 642	com/google/android/gms/measurement/internal/zze$zza:zzaVG	J
    //   303: aload 8
    //   305: getfield 636	com/google/android/gms/measurement/internal/zze$zza:zzaVF	J
    //   308: lstore 16
    //   310: lconst_1
    //   311: lstore 18
    //   313: lload 16
    //   315: lload 18
    //   317: ladd
    //   318: lstore 16
    //   320: aload 8
    //   322: lload 16
    //   324: putfield 636	com/google/android/gms/measurement/internal/zze$zza:zzaVF	J
    //   327: iload 4
    //   329: ifeq +27 -> 356
    //   332: aload 8
    //   334: getfield 639	com/google/android/gms/measurement/internal/zze$zza:zzaVE	J
    //   337: lstore 16
    //   339: lconst_1
    //   340: lstore 18
    //   342: lload 16
    //   344: lload 18
    //   346: ladd
    //   347: lstore 16
    //   349: aload 8
    //   351: lload 16
    //   353: putfield 639	com/google/android/gms/measurement/internal/zze$zza:zzaVE	J
    //   356: iload 5
    //   358: ifeq +27 -> 385
    //   361: aload 8
    //   363: getfield 642	com/google/android/gms/measurement/internal/zze$zza:zzaVG	J
    //   366: lstore 16
    //   368: lconst_1
    //   369: lstore 18
    //   371: lload 16
    //   373: lload 18
    //   375: ladd
    //   376: lstore 16
    //   378: aload 8
    //   380: lload 16
    //   382: putfield 642	com/google/android/gms/measurement/internal/zze$zza:zzaVG	J
    //   385: new 310	android/content/ContentValues
    //   388: astore 11
    //   390: aload 11
    //   392: invokespecial 312	android/content/ContentValues:<init>	()V
    //   395: ldc 51
    //   397: astore 13
    //   399: lload_1
    //   400: invokestatic 649	java/lang/Long:valueOf	(J)Ljava/lang/Long;
    //   403: astore 14
    //   405: aload 11
    //   407: aload 13
    //   409: aload 14
    //   411: invokevirtual 652	android/content/ContentValues:put	(Ljava/lang/String;Ljava/lang/Long;)V
    //   414: ldc 55
    //   416: astore 13
    //   418: aload 8
    //   420: getfield 639	com/google/android/gms/measurement/internal/zze$zza:zzaVE	J
    //   423: lstore 18
    //   425: lload 18
    //   427: invokestatic 649	java/lang/Long:valueOf	(J)Ljava/lang/Long;
    //   430: astore 14
    //   432: aload 11
    //   434: aload 13
    //   436: aload 14
    //   438: invokevirtual 652	android/content/ContentValues:put	(Ljava/lang/String;Ljava/lang/Long;)V
    //   441: ldc 59
    //   443: astore 13
    //   445: aload 8
    //   447: getfield 636	com/google/android/gms/measurement/internal/zze$zza:zzaVF	J
    //   450: lstore 18
    //   452: lload 18
    //   454: invokestatic 649	java/lang/Long:valueOf	(J)Ljava/lang/Long;
    //   457: astore 14
    //   459: aload 11
    //   461: aload 13
    //   463: aload 14
    //   465: invokevirtual 652	android/content/ContentValues:put	(Ljava/lang/String;Ljava/lang/Long;)V
    //   468: ldc 63
    //   470: astore 13
    //   472: aload 8
    //   474: getfield 642	com/google/android/gms/measurement/internal/zze$zza:zzaVG	J
    //   477: lstore 18
    //   479: lload 18
    //   481: invokestatic 649	java/lang/Long:valueOf	(J)Ljava/lang/Long;
    //   484: astore 14
    //   486: aload 11
    //   488: aload 13
    //   490: aload 14
    //   492: invokevirtual 652	android/content/ContentValues:put	(Ljava/lang/String;Ljava/lang/Long;)V
    //   495: ldc_w 628
    //   498: astore 13
    //   500: ldc_w 630
    //   503: astore 14
    //   505: aload 7
    //   507: aload 13
    //   509: aload 11
    //   511: aload 14
    //   513: aload 6
    //   515: invokevirtual 656	android/database/sqlite/SQLiteDatabase:update	(Ljava/lang/String;Landroid/content/ContentValues;Ljava/lang/String;[Ljava/lang/String;)I
    //   518: pop
    //   519: aload 9
    //   521: ifnull +10 -> 531
    //   524: aload 9
    //   526: invokeinterface 184 1 0
    //   531: aload 8
    //   533: astore 7
    //   535: goto -325 -> 210
    //   538: astore 7
    //   540: aconst_null
    //   541: astore 9
    //   543: aload_0
    //   544: invokevirtual 188	com/google/android/gms/measurement/internal/zze:zzAo	()Lcom/google/android/gms/measurement/internal/zzp;
    //   547: astore 11
    //   549: aload 11
    //   551: invokevirtual 194	com/google/android/gms/measurement/internal/zzp:zzCE	()Lcom/google/android/gms/measurement/internal/zzp$zza;
    //   554: astore 11
    //   556: ldc_w 658
    //   559: astore 13
    //   561: aload 11
    //   563: aload 13
    //   565: aload 7
    //   567: invokevirtual 346	com/google/android/gms/measurement/internal/zzp$zza:zzj	(Ljava/lang/String;Ljava/lang/Object;)V
    //   570: aload 9
    //   572: ifnull +10 -> 582
    //   575: aload 9
    //   577: invokeinterface 184 1 0
    //   582: aload 8
    //   584: astore 7
    //   586: goto -376 -> 210
    //   589: astore 7
    //   591: aconst_null
    //   592: astore 9
    //   594: aload 9
    //   596: ifnull +10 -> 606
    //   599: aload 9
    //   601: invokeinterface 184 1 0
    //   606: aload 7
    //   608: athrow
    //   609: astore 7
    //   611: goto -17 -> 594
    //   614: astore 7
    //   616: goto -73 -> 543
    // Local variable table:
    //   start	length	slot	name	signature
    //   0	619	0	this	zze
    //   0	619	1	paramLong	long
    //   0	619	3	paramString	String
    //   0	619	4	paramBoolean1	boolean
    //   0	619	5	paramBoolean2	boolean
    //   17	497	6	arrayOfString	String[]
    //   20	514	7	localObject1	Object
    //   538	28	7	localSQLiteException1	SQLiteException
    //   584	1	7	localObject2	Object
    //   589	18	7	localObject3	Object
    //   609	1	7	localObject4	Object
    //   614	1	7	localSQLiteException2	SQLiteException
    //   30	553	8	localzza	zze.zza
    //   46	554	9	localObject5	Object
    //   49	3	10	i	int
    //   161	85	10	j	int
    //   262	26	10	k	int
    //   56	506	11	localObject6	Object
    //   59	53	12	m	int
    //   62	502	13	str	String
    //   66	446	14	localObject7	Object
    //   122	3	15	n	int
    //   227	154	16	l1	long
    //   311	169	18	l2	long
    // Exception table:
    //   from	to	target	type
    //   37	41	538	android/database/sqlite/SQLiteException
    //   51	56	538	android/database/sqlite/SQLiteException
    //   71	74	538	android/database/sqlite/SQLiteException
    //   85	88	538	android/database/sqlite/SQLiteException
    //   99	102	538	android/database/sqlite/SQLiteException
    //   113	116	538	android/database/sqlite/SQLiteException
    //   124	129	538	android/database/sqlite/SQLiteException
    //   134	136	538	android/database/sqlite/SQLiteException
    //   148	152	538	android/database/sqlite/SQLiteException
    //   37	41	589	finally
    //   51	56	589	finally
    //   71	74	589	finally
    //   85	88	589	finally
    //   99	102	589	finally
    //   113	116	589	finally
    //   124	129	589	finally
    //   134	136	589	finally
    //   148	152	589	finally
    //   154	161	609	finally
    //   168	172	609	finally
    //   174	179	609	finally
    //   190	194	609	finally
    //   221	227	609	finally
    //   245	252	609	finally
    //   256	261	609	finally
    //   266	273	609	finally
    //   277	282	609	finally
    //   287	294	609	finally
    //   298	303	609	finally
    //   303	308	609	finally
    //   322	327	609	finally
    //   332	337	609	finally
    //   351	356	609	finally
    //   361	366	609	finally
    //   380	385	609	finally
    //   385	388	609	finally
    //   390	395	609	finally
    //   399	403	609	finally
    //   409	414	609	finally
    //   418	423	609	finally
    //   425	430	609	finally
    //   436	441	609	finally
    //   445	450	609	finally
    //   452	457	609	finally
    //   463	468	609	finally
    //   472	477	609	finally
    //   479	484	609	finally
    //   490	495	609	finally
    //   513	519	609	finally
    //   543	547	609	finally
    //   549	554	609	finally
    //   565	570	609	finally
    //   154	161	614	android/database/sqlite/SQLiteException
    //   168	172	614	android/database/sqlite/SQLiteException
    //   174	179	614	android/database/sqlite/SQLiteException
    //   190	194	614	android/database/sqlite/SQLiteException
    //   221	227	614	android/database/sqlite/SQLiteException
    //   245	252	614	android/database/sqlite/SQLiteException
    //   256	261	614	android/database/sqlite/SQLiteException
    //   266	273	614	android/database/sqlite/SQLiteException
    //   277	282	614	android/database/sqlite/SQLiteException
    //   287	294	614	android/database/sqlite/SQLiteException
    //   298	303	614	android/database/sqlite/SQLiteException
    //   303	308	614	android/database/sqlite/SQLiteException
    //   322	327	614	android/database/sqlite/SQLiteException
    //   332	337	614	android/database/sqlite/SQLiteException
    //   351	356	614	android/database/sqlite/SQLiteException
    //   361	366	614	android/database/sqlite/SQLiteException
    //   380	385	614	android/database/sqlite/SQLiteException
    //   385	388	614	android/database/sqlite/SQLiteException
    //   390	395	614	android/database/sqlite/SQLiteException
    //   399	403	614	android/database/sqlite/SQLiteException
    //   409	414	614	android/database/sqlite/SQLiteException
    //   418	423	614	android/database/sqlite/SQLiteException
    //   425	430	614	android/database/sqlite/SQLiteException
    //   436	441	614	android/database/sqlite/SQLiteException
    //   445	450	614	android/database/sqlite/SQLiteException
    //   452	457	614	android/database/sqlite/SQLiteException
    //   463	468	614	android/database/sqlite/SQLiteException
    //   472	477	614	android/database/sqlite/SQLiteException
    //   479	484	614	android/database/sqlite/SQLiteException
    //   490	495	614	android/database/sqlite/SQLiteException
    //   513	519	614	android/database/sqlite/SQLiteException
  }
  
  void zza(ContentValues paramContentValues, String paramString, Object paramObject)
  {
    zzx.zzcM(paramString);
    zzx.zzz(paramObject);
    boolean bool = paramObject instanceof String;
    if (bool)
    {
      paramObject = (String)paramObject;
      paramContentValues.put(paramString, (String)paramObject);
    }
    for (;;)
    {
      return;
      bool = paramObject instanceof Long;
      if (bool)
      {
        paramObject = (Long)paramObject;
        paramContentValues.put(paramString, (Long)paramObject);
      }
      else
      {
        bool = paramObject instanceof Float;
        if (!bool) {
          break;
        }
        paramObject = (Float)paramObject;
        paramContentValues.put(paramString, (Float)paramObject);
      }
    }
    IllegalArgumentException localIllegalArgumentException = new java/lang/IllegalArgumentException;
    localIllegalArgumentException.<init>("Invalid value type");
    throw localIllegalArgumentException;
  }
  
  /* Error */
  public void zza(com.google.android.gms.internal.zzqb.zze paramzze)
  {
    // Byte code:
    //   0: aload_0
    //   1: invokevirtual 210	com/google/android/gms/measurement/internal/zze:zzjk	()V
    //   4: aload_0
    //   5: invokevirtual 207	com/google/android/gms/measurement/internal/zze:zzjv	()V
    //   8: aload_1
    //   9: invokestatic 220	com/google/android/gms/common/internal/zzx:zzz	(Ljava/lang/Object;)Ljava/lang/Object;
    //   12: pop
    //   13: aload_1
    //   14: getfield 673	com/google/android/gms/internal/zzqb$zze:appId	Ljava/lang/String;
    //   17: invokestatic 216	com/google/android/gms/common/internal/zzx:zzcM	(Ljava/lang/String;)Ljava/lang/String;
    //   20: pop
    //   21: aload_1
    //   22: getfield 677	com/google/android/gms/internal/zzqb$zze:zzbaq	Ljava/lang/Long;
    //   25: invokestatic 220	com/google/android/gms/common/internal/zzx:zzz	(Ljava/lang/Object;)Ljava/lang/Object;
    //   28: pop
    //   29: aload_0
    //   30: invokevirtual 680	com/google/android/gms/measurement/internal/zze:zzCr	()V
    //   33: aload_0
    //   34: invokevirtual 86	com/google/android/gms/measurement/internal/zze:zzjl	()Lcom/google/android/gms/internal/zzmq;
    //   37: astore_2
    //   38: aload_2
    //   39: invokeinterface 504 1 0
    //   44: lstore_3
    //   45: aload_1
    //   46: getfield 677	com/google/android/gms/internal/zzqb$zze:zzbaq	Ljava/lang/Long;
    //   49: astore 5
    //   51: aload 5
    //   53: invokevirtual 683	java/lang/Long:longValue	()J
    //   56: lstore 6
    //   58: aload_0
    //   59: invokevirtual 375	com/google/android/gms/measurement/internal/zze:zzCp	()Lcom/google/android/gms/measurement/internal/zzd;
    //   62: astore 8
    //   64: aload 8
    //   66: invokevirtual 510	com/google/android/gms/measurement/internal/zzd:zzBQ	()J
    //   69: lstore 9
    //   71: lload_3
    //   72: lload 9
    //   74: lsub
    //   75: lstore 9
    //   77: lload 6
    //   79: lload 9
    //   81: lcmp
    //   82: istore 11
    //   84: iload 11
    //   86: iflt +43 -> 129
    //   89: aload_1
    //   90: getfield 677	com/google/android/gms/internal/zzqb$zze:zzbaq	Ljava/lang/Long;
    //   93: astore 5
    //   95: aload 5
    //   97: invokevirtual 683	java/lang/Long:longValue	()J
    //   100: lstore 6
    //   102: aload_0
    //   103: invokevirtual 375	com/google/android/gms/measurement/internal/zze:zzCp	()Lcom/google/android/gms/measurement/internal/zzd;
    //   106: astore 8
    //   108: aload 8
    //   110: invokevirtual 510	com/google/android/gms/measurement/internal/zzd:zzBQ	()J
    //   113: lload_3
    //   114: ladd
    //   115: lstore 9
    //   117: lload 6
    //   119: lload 9
    //   121: lcmp
    //   122: istore 11
    //   124: iload 11
    //   126: ifle +38 -> 164
    //   129: aload_0
    //   130: invokevirtual 188	com/google/android/gms/measurement/internal/zze:zzAo	()Lcom/google/android/gms/measurement/internal/zzp;
    //   133: invokevirtual 237	com/google/android/gms/measurement/internal/zzp:zzCF	()Lcom/google/android/gms/measurement/internal/zzp$zza;
    //   136: astore 5
    //   138: ldc_w 685
    //   141: astore 12
    //   143: lload_3
    //   144: invokestatic 649	java/lang/Long:valueOf	(J)Ljava/lang/Long;
    //   147: astore_2
    //   148: aload_1
    //   149: getfield 677	com/google/android/gms/internal/zzqb$zze:zzbaq	Ljava/lang/Long;
    //   152: astore 13
    //   154: aload 5
    //   156: aload 12
    //   158: aload_2
    //   159: aload 13
    //   161: invokevirtual 202	com/google/android/gms/measurement/internal/zzp$zza:zze	(Ljava/lang/String;Ljava/lang/Object;Ljava/lang/Object;)V
    //   164: aload_1
    //   165: invokevirtual 686	com/google/android/gms/internal/zzqb$zze:getSerializedSize	()I
    //   168: istore 14
    //   170: iload 14
    //   172: newarray <illegal type>
    //   174: astore_2
    //   175: aload_2
    //   176: invokestatic 301	com/google/android/gms/internal/zzsn:zzE	([B)Lcom/google/android/gms/internal/zzsn;
    //   179: astore 13
    //   181: aload_1
    //   182: aload 13
    //   184: invokevirtual 687	com/google/android/gms/internal/zzqb$zze:writeTo	(Lcom/google/android/gms/internal/zzsn;)V
    //   187: aload 13
    //   189: invokevirtual 308	com/google/android/gms/internal/zzsn:zzJo	()V
    //   192: aload_0
    //   193: invokevirtual 691	com/google/android/gms/measurement/internal/zze:zzCk	()Lcom/google/android/gms/measurement/internal/zzaj;
    //   196: astore 13
    //   198: aload 13
    //   200: aload_2
    //   201: invokevirtual 697	com/google/android/gms/measurement/internal/zzaj:zzg	([B)[B
    //   204: astore_2
    //   205: aload_0
    //   206: invokevirtual 188	com/google/android/gms/measurement/internal/zze:zzAo	()Lcom/google/android/gms/measurement/internal/zzp;
    //   209: invokevirtual 517	com/google/android/gms/measurement/internal/zzp:zzCK	()Lcom/google/android/gms/measurement/internal/zzp$zza;
    //   212: astore 13
    //   214: aload_2
    //   215: arraylength
    //   216: istore 15
    //   218: iload 15
    //   220: invokestatic 287	java/lang/Integer:valueOf	(I)Ljava/lang/Integer;
    //   223: astore 12
    //   225: aload 13
    //   227: ldc_w 699
    //   230: aload 12
    //   232: invokevirtual 346	com/google/android/gms/measurement/internal/zzp$zza:zzj	(Ljava/lang/String;Ljava/lang/Object;)V
    //   235: new 310	android/content/ContentValues
    //   238: astore 13
    //   240: aload 13
    //   242: invokespecial 312	android/content/ContentValues:<init>	()V
    //   245: aload_1
    //   246: getfield 673	com/google/android/gms/internal/zzqb$zze:appId	Ljava/lang/String;
    //   249: astore 12
    //   251: aload 13
    //   253: ldc_w 314
    //   256: aload 12
    //   258: invokevirtual 317	android/content/ContentValues:put	(Ljava/lang/String;Ljava/lang/String;)V
    //   261: aload_1
    //   262: getfield 677	com/google/android/gms/internal/zzqb$zze:zzbaq	Ljava/lang/Long;
    //   265: astore 12
    //   267: aload 13
    //   269: ldc_w 701
    //   272: aload 12
    //   274: invokevirtual 652	android/content/ContentValues:put	(Ljava/lang/String;Ljava/lang/Long;)V
    //   277: ldc_w 328
    //   280: astore 5
    //   282: aload 13
    //   284: aload 5
    //   286: aload_2
    //   287: invokevirtual 331	android/content/ContentValues:put	(Ljava/lang/String;[B)V
    //   290: aload_0
    //   291: invokevirtual 167	com/google/android/gms/measurement/internal/zze:getWritableDatabase	()Landroid/database/sqlite/SQLiteDatabase;
    //   294: astore_2
    //   295: ldc_w 512
    //   298: astore 5
    //   300: iconst_0
    //   301: istore 15
    //   303: aconst_null
    //   304: astore 12
    //   306: aload_2
    //   307: aload 5
    //   309: aconst_null
    //   310: aload 13
    //   312: invokevirtual 705	android/database/sqlite/SQLiteDatabase:insert	(Ljava/lang/String;Ljava/lang/String;Landroid/content/ContentValues;)J
    //   315: lstore_3
    //   316: iconst_m1
    //   317: i2l
    //   318: lstore 6
    //   320: lload_3
    //   321: lload 6
    //   323: lcmp
    //   324: istore 14
    //   326: iload 14
    //   328: ifne +24 -> 352
    //   331: aload_0
    //   332: invokevirtual 188	com/google/android/gms/measurement/internal/zze:zzAo	()Lcom/google/android/gms/measurement/internal/zzp;
    //   335: astore_2
    //   336: aload_2
    //   337: invokevirtual 194	com/google/android/gms/measurement/internal/zzp:zzCE	()Lcom/google/android/gms/measurement/internal/zzp$zza;
    //   340: astore_2
    //   341: ldc_w 707
    //   344: astore 13
    //   346: aload_2
    //   347: aload 13
    //   349: invokevirtual 243	com/google/android/gms/measurement/internal/zzp$zza:zzfg	(Ljava/lang/String;)V
    //   352: return
    //   353: astore_2
    //   354: aload_0
    //   355: invokevirtual 188	com/google/android/gms/measurement/internal/zze:zzAo	()Lcom/google/android/gms/measurement/internal/zzp;
    //   358: invokevirtual 194	com/google/android/gms/measurement/internal/zzp:zzCE	()Lcom/google/android/gms/measurement/internal/zzp$zza;
    //   361: astore 13
    //   363: ldc_w 709
    //   366: astore 5
    //   368: aload 13
    //   370: aload 5
    //   372: aload_2
    //   373: invokevirtual 346	com/google/android/gms/measurement/internal/zzp$zza:zzj	(Ljava/lang/String;Ljava/lang/Object;)V
    //   376: goto -24 -> 352
    //   379: astore_2
    //   380: aload_0
    //   381: invokevirtual 188	com/google/android/gms/measurement/internal/zze:zzAo	()Lcom/google/android/gms/measurement/internal/zzp;
    //   384: invokevirtual 194	com/google/android/gms/measurement/internal/zzp:zzCE	()Lcom/google/android/gms/measurement/internal/zzp$zza;
    //   387: astore 13
    //   389: ldc_w 711
    //   392: astore 5
    //   394: aload 13
    //   396: aload 5
    //   398: aload_2
    //   399: invokevirtual 346	com/google/android/gms/measurement/internal/zzp$zza:zzj	(Ljava/lang/String;Ljava/lang/Object;)V
    //   402: goto -50 -> 352
    // Local variable table:
    //   start	length	slot	name	signature
    //   0	405	0	this	zze
    //   0	405	1	paramzze	com.google.android.gms.internal.zzqb.zze
    //   37	310	2	localObject1	Object
    //   353	20	2	localIOException	IOException
    //   379	20	2	localSQLiteException	SQLiteException
    //   44	277	3	l1	long
    //   49	348	5	localObject2	Object
    //   56	266	6	l2	long
    //   62	47	8	localzzd	zzd
    //   69	51	9	l3	long
    //   82	43	11	bool1	boolean
    //   141	164	12	localObject3	Object
    //   152	243	13	localObject4	Object
    //   168	3	14	i	int
    //   324	3	14	bool2	boolean
    //   216	86	15	j	int
    // Exception table:
    //   from	to	target	type
    //   164	168	353	java/io/IOException
    //   170	174	353	java/io/IOException
    //   175	179	353	java/io/IOException
    //   182	187	353	java/io/IOException
    //   187	192	353	java/io/IOException
    //   192	196	353	java/io/IOException
    //   200	204	353	java/io/IOException
    //   290	294	379	android/database/sqlite/SQLiteException
    //   310	315	379	android/database/sqlite/SQLiteException
    //   331	335	379	android/database/sqlite/SQLiteException
    //   336	340	379	android/database/sqlite/SQLiteException
    //   347	352	379	android/database/sqlite/SQLiteException
  }
  
  public void zza(zza paramzza)
  {
    zzx.zzz(paramzza);
    zzjk();
    zzjv();
    Object localObject1 = new android/content/ContentValues;
    ((ContentValues)localObject1).<init>();
    Object localObject2 = paramzza.zzwK();
    ((ContentValues)localObject1).put("app_id", (String)localObject2);
    localObject2 = paramzza.zzBj();
    ((ContentValues)localObject1).put("app_instance_id", (String)localObject2);
    localObject2 = paramzza.zzBk();
    ((ContentValues)localObject1).put("gmp_app_id", (String)localObject2);
    localObject2 = paramzza.zzBl();
    ((ContentValues)localObject1).put("resettable_device_id_hash", (String)localObject2);
    localObject2 = Long.valueOf(paramzza.zzBr());
    ((ContentValues)localObject1).put("last_bundle_index", (Long)localObject2);
    localObject2 = Long.valueOf(paramzza.zzBm());
    ((ContentValues)localObject1).put("last_bundle_start_timestamp", (Long)localObject2);
    localObject2 = Long.valueOf(paramzza.zzBn());
    ((ContentValues)localObject1).put("last_bundle_end_timestamp", (Long)localObject2);
    localObject2 = paramzza.zzli();
    ((ContentValues)localObject1).put("app_version", (String)localObject2);
    localObject2 = paramzza.zzBo();
    ((ContentValues)localObject1).put("app_store", (String)localObject2);
    localObject2 = Long.valueOf(paramzza.zzBp());
    ((ContentValues)localObject1).put("gmp_version", (Long)localObject2);
    localObject2 = Long.valueOf(paramzza.zzBq());
    ((ContentValues)localObject1).put("dev_cert_hash", (Long)localObject2);
    boolean bool1 = paramzza.zzAr();
    localObject2 = Boolean.valueOf(bool1);
    ((ContentValues)localObject1).put("measurement_enabled", (Boolean)localObject2);
    localObject2 = Long.valueOf(paramzza.zzBv());
    ((ContentValues)localObject1).put("day", (Long)localObject2);
    localObject2 = Long.valueOf(paramzza.zzBw());
    ((ContentValues)localObject1).put("daily_public_events_count", (Long)localObject2);
    localObject2 = Long.valueOf(paramzza.zzBx());
    ((ContentValues)localObject1).put("daily_events_count", (Long)localObject2);
    localObject2 = Long.valueOf(paramzza.zzBy());
    ((ContentValues)localObject1).put("daily_conversions_count", (Long)localObject2);
    localObject2 = Long.valueOf(paramzza.zzBs());
    ((ContentValues)localObject1).put("config_fetched_time", (Long)localObject2);
    Object localObject3 = "failed_config_fetch_time";
    long l1 = paramzza.zzBt();
    localObject2 = Long.valueOf(l1);
    ((ContentValues)localObject1).put((String)localObject3, (Long)localObject2);
    try
    {
      localObject3 = getWritableDatabase();
      localObject2 = "apps";
      int i = 5;
      long l2 = ((SQLiteDatabase)localObject3).insertWithOnConflict((String)localObject2, null, (ContentValues)localObject1, i);
      l1 = -1;
      boolean bool2 = l2 < l1;
      if (!bool2)
      {
        localObject1 = zzAo();
        localObject1 = ((zzp)localObject1).zzCE();
        localObject3 = "Failed to insert/update app (got -1)";
        ((zzp.zza)localObject1).zzfg((String)localObject3);
      }
      return;
    }
    catch (SQLiteException localSQLiteException)
    {
      for (;;)
      {
        localObject3 = zzAo().zzCE();
        localObject2 = "Error storing app";
        ((zzp.zza)localObject3).zzj((String)localObject2, localSQLiteException);
      }
    }
  }
  
  /* Error */
  public void zza(zzh paramzzh, long paramLong)
  {
    // Byte code:
    //   0: aload_0
    //   1: invokevirtual 210	com/google/android/gms/measurement/internal/zze:zzjk	()V
    //   4: aload_0
    //   5: invokevirtual 207	com/google/android/gms/measurement/internal/zze:zzjv	()V
    //   8: aload_1
    //   9: invokestatic 220	com/google/android/gms/common/internal/zzx:zzz	(Ljava/lang/Object;)Ljava/lang/Object;
    //   12: pop
    //   13: aload_1
    //   14: getfield 794	com/google/android/gms/measurement/internal/zzh:zzaUa	Ljava/lang/String;
    //   17: invokestatic 216	com/google/android/gms/common/internal/zzx:zzcM	(Ljava/lang/String;)Ljava/lang/String;
    //   20: pop
    //   21: new 796	com/google/android/gms/internal/zzqb$zzb
    //   24: astore 4
    //   26: aload 4
    //   28: invokespecial 797	com/google/android/gms/internal/zzqb$zzb:<init>	()V
    //   31: aload_1
    //   32: getfield 800	com/google/android/gms/measurement/internal/zzh:zzaVN	J
    //   35: lstore 5
    //   37: lload 5
    //   39: invokestatic 649	java/lang/Long:valueOf	(J)Ljava/lang/Long;
    //   42: astore 7
    //   44: aload 4
    //   46: aload 7
    //   48: putfield 803	com/google/android/gms/internal/zzqb$zzb:zzbag	Ljava/lang/Long;
    //   51: aload_1
    //   52: getfield 807	com/google/android/gms/measurement/internal/zzh:zzaVO	Lcom/google/android/gms/measurement/internal/EventParams;
    //   55: invokevirtual 812	com/google/android/gms/measurement/internal/EventParams:size	()I
    //   58: anewarray 814	com/google/android/gms/internal/zzqb$zzc
    //   61: astore 7
    //   63: aload 4
    //   65: aload 7
    //   67: putfield 818	com/google/android/gms/internal/zzqb$zzb:zzbae	[Lcom/google/android/gms/internal/zzqb$zzc;
    //   70: iconst_0
    //   71: istore 8
    //   73: aconst_null
    //   74: astore 7
    //   76: aload_1
    //   77: getfield 807	com/google/android/gms/measurement/internal/zzh:zzaVO	Lcom/google/android/gms/measurement/internal/EventParams;
    //   80: invokevirtual 822	com/google/android/gms/measurement/internal/EventParams:iterator	()Ljava/util/Iterator;
    //   83: astore 9
    //   85: iconst_0
    //   86: istore 10
    //   88: aconst_null
    //   89: astore 11
    //   91: aload 9
    //   93: invokeinterface 827 1 0
    //   98: istore 8
    //   100: iload 8
    //   102: ifeq +85 -> 187
    //   105: aload 9
    //   107: invokeinterface 831 1 0
    //   112: checkcast 289	java/lang/String
    //   115: astore 7
    //   117: new 814	com/google/android/gms/internal/zzqb$zzc
    //   120: astore 12
    //   122: aload 12
    //   124: invokespecial 832	com/google/android/gms/internal/zzqb$zzc:<init>	()V
    //   127: aload 4
    //   129: getfield 818	com/google/android/gms/internal/zzqb$zzb:zzbae	[Lcom/google/android/gms/internal/zzqb$zzc;
    //   132: astore 13
    //   134: iload 10
    //   136: iconst_1
    //   137: iadd
    //   138: istore 14
    //   140: aload 13
    //   142: iload 10
    //   144: aload 12
    //   146: aastore
    //   147: aload 12
    //   149: aload 7
    //   151: putfield 835	com/google/android/gms/internal/zzqb$zzc:name	Ljava/lang/String;
    //   154: aload_1
    //   155: getfield 807	com/google/android/gms/measurement/internal/zzh:zzaVO	Lcom/google/android/gms/measurement/internal/EventParams;
    //   158: aload 7
    //   160: invokevirtual 838	com/google/android/gms/measurement/internal/EventParams:get	(Ljava/lang/String;)Ljava/lang/Object;
    //   163: astore 7
    //   165: aload_0
    //   166: invokevirtual 691	com/google/android/gms/measurement/internal/zze:zzCk	()Lcom/google/android/gms/measurement/internal/zzaj;
    //   169: astore 11
    //   171: aload 11
    //   173: aload 12
    //   175: aload 7
    //   177: invokevirtual 841	com/google/android/gms/measurement/internal/zzaj:zza	(Lcom/google/android/gms/internal/zzqb$zzc;Ljava/lang/Object;)V
    //   180: iload 14
    //   182: istore 10
    //   184: goto -93 -> 91
    //   187: aload 4
    //   189: invokevirtual 842	com/google/android/gms/internal/zzqb$zzb:getSerializedSize	()I
    //   192: istore 8
    //   194: iload 8
    //   196: newarray <illegal type>
    //   198: astore 7
    //   200: aload 7
    //   202: invokestatic 301	com/google/android/gms/internal/zzsn:zzE	([B)Lcom/google/android/gms/internal/zzsn;
    //   205: astore 11
    //   207: aload 4
    //   209: aload 11
    //   211: invokevirtual 843	com/google/android/gms/internal/zzqb$zzb:writeTo	(Lcom/google/android/gms/internal/zzsn;)V
    //   214: aload 11
    //   216: invokevirtual 308	com/google/android/gms/internal/zzsn:zzJo	()V
    //   219: aload_0
    //   220: invokevirtual 188	com/google/android/gms/measurement/internal/zze:zzAo	()Lcom/google/android/gms/measurement/internal/zzp;
    //   223: invokevirtual 517	com/google/android/gms/measurement/internal/zzp:zzCK	()Lcom/google/android/gms/measurement/internal/zzp$zza;
    //   226: astore 11
    //   228: aload_1
    //   229: getfield 848	com/google/android/gms/measurement/internal/zzh:mName	Ljava/lang/String;
    //   232: astore 4
    //   234: aload 7
    //   236: arraylength
    //   237: istore 15
    //   239: iload 15
    //   241: invokestatic 287	java/lang/Integer:valueOf	(I)Ljava/lang/Integer;
    //   244: astore 9
    //   246: aload 11
    //   248: ldc_w 845
    //   251: aload 4
    //   253: aload 9
    //   255: invokevirtual 202	com/google/android/gms/measurement/internal/zzp$zza:zze	(Ljava/lang/String;Ljava/lang/Object;Ljava/lang/Object;)V
    //   258: new 310	android/content/ContentValues
    //   261: astore 11
    //   263: aload 11
    //   265: invokespecial 312	android/content/ContentValues:<init>	()V
    //   268: aload_1
    //   269: getfield 794	com/google/android/gms/measurement/internal/zzh:zzaUa	Ljava/lang/String;
    //   272: astore 4
    //   274: aload 11
    //   276: ldc_w 314
    //   279: aload 4
    //   281: invokevirtual 317	android/content/ContentValues:put	(Ljava/lang/String;Ljava/lang/String;)V
    //   284: aload_1
    //   285: getfield 848	com/google/android/gms/measurement/internal/zzh:mName	Ljava/lang/String;
    //   288: astore 4
    //   290: aload 11
    //   292: ldc_w 849
    //   295: aload 4
    //   297: invokevirtual 317	android/content/ContentValues:put	(Ljava/lang/String;Ljava/lang/String;)V
    //   300: aload_1
    //   301: getfield 854	com/google/android/gms/measurement/internal/zzh:zzaez	J
    //   304: lstore 16
    //   306: lload 16
    //   308: invokestatic 649	java/lang/Long:valueOf	(J)Ljava/lang/Long;
    //   311: astore 4
    //   313: aload 11
    //   315: ldc_w 851
    //   318: aload 4
    //   320: invokevirtual 652	android/content/ContentValues:put	(Ljava/lang/String;Ljava/lang/Long;)V
    //   323: lload_2
    //   324: invokestatic 649	java/lang/Long:valueOf	(J)Ljava/lang/Long;
    //   327: astore 4
    //   329: aload 11
    //   331: ldc_w 856
    //   334: aload 4
    //   336: invokevirtual 652	android/content/ContentValues:put	(Ljava/lang/String;Ljava/lang/Long;)V
    //   339: ldc_w 328
    //   342: astore 18
    //   344: aload 11
    //   346: aload 18
    //   348: aload 7
    //   350: invokevirtual 331	android/content/ContentValues:put	(Ljava/lang/String;[B)V
    //   353: aload_0
    //   354: invokevirtual 167	com/google/android/gms/measurement/internal/zze:getWritableDatabase	()Landroid/database/sqlite/SQLiteDatabase;
    //   357: astore 7
    //   359: ldc_w 858
    //   362: astore 18
    //   364: aconst_null
    //   365: astore 4
    //   367: aload 7
    //   369: aload 18
    //   371: aconst_null
    //   372: aload 11
    //   374: invokevirtual 705	android/database/sqlite/SQLiteDatabase:insert	(Ljava/lang/String;Ljava/lang/String;Landroid/content/ContentValues;)J
    //   377: lstore 5
    //   379: iconst_m1
    //   380: i2l
    //   381: lstore 19
    //   383: lload 5
    //   385: lload 19
    //   387: lcmp
    //   388: istore 8
    //   390: iload 8
    //   392: ifne +28 -> 420
    //   395: aload_0
    //   396: invokevirtual 188	com/google/android/gms/measurement/internal/zze:zzAo	()Lcom/google/android/gms/measurement/internal/zzp;
    //   399: astore 7
    //   401: aload 7
    //   403: invokevirtual 194	com/google/android/gms/measurement/internal/zzp:zzCE	()Lcom/google/android/gms/measurement/internal/zzp$zza;
    //   406: astore 7
    //   408: ldc_w 860
    //   411: astore 11
    //   413: aload 7
    //   415: aload 11
    //   417: invokevirtual 243	com/google/android/gms/measurement/internal/zzp$zza:zzfg	(Ljava/lang/String;)V
    //   420: return
    //   421: astore 7
    //   423: aload_0
    //   424: invokevirtual 188	com/google/android/gms/measurement/internal/zze:zzAo	()Lcom/google/android/gms/measurement/internal/zzp;
    //   427: invokevirtual 194	com/google/android/gms/measurement/internal/zzp:zzCE	()Lcom/google/android/gms/measurement/internal/zzp$zza;
    //   430: astore 11
    //   432: ldc_w 862
    //   435: astore 18
    //   437: aload 11
    //   439: aload 18
    //   441: aload 7
    //   443: invokevirtual 346	com/google/android/gms/measurement/internal/zzp$zza:zzj	(Ljava/lang/String;Ljava/lang/Object;)V
    //   446: goto -26 -> 420
    //   449: astore 7
    //   451: aload_0
    //   452: invokevirtual 188	com/google/android/gms/measurement/internal/zze:zzAo	()Lcom/google/android/gms/measurement/internal/zzp;
    //   455: invokevirtual 194	com/google/android/gms/measurement/internal/zzp:zzCE	()Lcom/google/android/gms/measurement/internal/zzp$zza;
    //   458: astore 11
    //   460: ldc_w 864
    //   463: astore 18
    //   465: aload 11
    //   467: aload 18
    //   469: aload 7
    //   471: invokevirtual 346	com/google/android/gms/measurement/internal/zzp$zza:zzj	(Ljava/lang/String;Ljava/lang/Object;)V
    //   474: goto -54 -> 420
    // Local variable table:
    //   start	length	slot	name	signature
    //   0	477	0	this	zze
    //   0	477	1	paramzzh	zzh
    //   0	477	2	paramLong	long
    //   24	342	4	localObject1	Object
    //   35	349	5	l1	long
    //   42	372	7	localObject2	Object
    //   421	21	7	localIOException	IOException
    //   449	21	7	localSQLiteException	SQLiteException
    //   71	30	8	bool1	boolean
    //   192	3	8	i	int
    //   388	3	8	bool2	boolean
    //   83	171	9	localObject3	Object
    //   86	97	10	j	int
    //   89	377	11	localObject4	Object
    //   120	54	12	localzzc	com.google.android.gms.internal.zzqb.zzc
    //   132	9	13	arrayOfzzc	com.google.android.gms.internal.zzqb.zzc[]
    //   138	43	14	k	int
    //   237	3	15	m	int
    //   304	3	16	l2	long
    //   342	126	18	str	String
    //   381	5	19	l3	long
    // Exception table:
    //   from	to	target	type
    //   187	192	421	java/io/IOException
    //   194	198	421	java/io/IOException
    //   200	205	421	java/io/IOException
    //   209	214	421	java/io/IOException
    //   214	219	421	java/io/IOException
    //   353	357	449	android/database/sqlite/SQLiteException
    //   372	377	449	android/database/sqlite/SQLiteException
    //   395	399	449	android/database/sqlite/SQLiteException
    //   401	406	449	android/database/sqlite/SQLiteException
    //   415	420	449	android/database/sqlite/SQLiteException
  }
  
  public void zza(zzi paramzzi)
  {
    zzx.zzz(paramzzi);
    zzjk();
    zzjv();
    Object localObject1 = new android/content/ContentValues;
    ((ContentValues)localObject1).<init>();
    Object localObject2 = paramzzi.zzaUa;
    ((ContentValues)localObject1).put("app_id", (String)localObject2);
    localObject2 = paramzzi.mName;
    ((ContentValues)localObject1).put("name", (String)localObject2);
    localObject2 = Long.valueOf(paramzzi.zzaVP);
    ((ContentValues)localObject1).put("lifetime_count", (Long)localObject2);
    localObject2 = Long.valueOf(paramzzi.zzaVQ);
    ((ContentValues)localObject1).put("current_bundle_count", (Long)localObject2);
    Object localObject3 = "last_fire_timestamp";
    long l1 = paramzzi.zzaVR;
    localObject2 = Long.valueOf(l1);
    ((ContentValues)localObject1).put((String)localObject3, (Long)localObject2);
    try
    {
      localObject3 = getWritableDatabase();
      localObject2 = "events";
      int i = 5;
      long l2 = ((SQLiteDatabase)localObject3).insertWithOnConflict((String)localObject2, null, (ContentValues)localObject1, i);
      l1 = -1;
      boolean bool = l2 < l1;
      if (!bool)
      {
        localObject1 = zzAo();
        localObject1 = ((zzp)localObject1).zzCE();
        localObject3 = "Failed to insert/update event aggregates (got -1)";
        ((zzp.zza)localObject1).zzfg((String)localObject3);
      }
      return;
    }
    catch (SQLiteException localSQLiteException)
    {
      for (;;)
      {
        localObject3 = zzAo().zzCE();
        localObject2 = "Error storing event aggregates";
        ((zzp.zza)localObject3).zzj((String)localObject2, localSQLiteException);
      }
    }
  }
  
  /* Error */
  void zza(String paramString, int paramInt, com.google.android.gms.internal.zzqb.zzf paramzzf)
  {
    // Byte code:
    //   0: aload_0
    //   1: invokevirtual 207	com/google/android/gms/measurement/internal/zze:zzjv	()V
    //   4: aload_0
    //   5: invokevirtual 210	com/google/android/gms/measurement/internal/zze:zzjk	()V
    //   8: aload_1
    //   9: invokestatic 216	com/google/android/gms/common/internal/zzx:zzcM	(Ljava/lang/String;)Ljava/lang/String;
    //   12: pop
    //   13: aload_3
    //   14: invokestatic 220	com/google/android/gms/common/internal/zzx:zzz	(Ljava/lang/Object;)Ljava/lang/Object;
    //   17: pop
    //   18: aload_3
    //   19: invokevirtual 880	com/google/android/gms/internal/zzqb$zzf:getSerializedSize	()I
    //   22: istore 4
    //   24: iload 4
    //   26: newarray <illegal type>
    //   28: astore 5
    //   30: aload 5
    //   32: invokestatic 301	com/google/android/gms/internal/zzsn:zzE	([B)Lcom/google/android/gms/internal/zzsn;
    //   35: astore 6
    //   37: aload_3
    //   38: aload 6
    //   40: invokevirtual 881	com/google/android/gms/internal/zzqb$zzf:writeTo	(Lcom/google/android/gms/internal/zzsn;)V
    //   43: aload 6
    //   45: invokevirtual 308	com/google/android/gms/internal/zzsn:zzJo	()V
    //   48: new 310	android/content/ContentValues
    //   51: astore 6
    //   53: aload 6
    //   55: invokespecial 312	android/content/ContentValues:<init>	()V
    //   58: aload 6
    //   60: ldc_w 314
    //   63: aload_1
    //   64: invokevirtual 317	android/content/ContentValues:put	(Ljava/lang/String;Ljava/lang/String;)V
    //   67: iload_2
    //   68: invokestatic 287	java/lang/Integer:valueOf	(I)Ljava/lang/Integer;
    //   71: astore 7
    //   73: aload 6
    //   75: ldc_w 319
    //   78: aload 7
    //   80: invokevirtual 322	android/content/ContentValues:put	(Ljava/lang/String;Ljava/lang/Integer;)V
    //   83: ldc_w 427
    //   86: astore 8
    //   88: aload 6
    //   90: aload 8
    //   92: aload 5
    //   94: invokevirtual 331	android/content/ContentValues:put	(Ljava/lang/String;[B)V
    //   97: aload_0
    //   98: invokevirtual 167	com/google/android/gms/measurement/internal/zze:getWritableDatabase	()Landroid/database/sqlite/SQLiteDatabase;
    //   101: astore 5
    //   103: ldc_w 425
    //   106: astore 8
    //   108: aconst_null
    //   109: astore 7
    //   111: iconst_5
    //   112: istore 9
    //   114: aload 5
    //   116: aload 8
    //   118: aconst_null
    //   119: aload 6
    //   121: iload 9
    //   123: invokevirtual 338	android/database/sqlite/SQLiteDatabase:insertWithOnConflict	(Ljava/lang/String;Ljava/lang/String;Landroid/content/ContentValues;I)J
    //   126: lstore 10
    //   128: iconst_m1
    //   129: i2l
    //   130: lstore 12
    //   132: lload 10
    //   134: lload 12
    //   136: lcmp
    //   137: istore 4
    //   139: iload 4
    //   141: ifne +28 -> 169
    //   144: aload_0
    //   145: invokevirtual 188	com/google/android/gms/measurement/internal/zze:zzAo	()Lcom/google/android/gms/measurement/internal/zzp;
    //   148: astore 5
    //   150: aload 5
    //   152: invokevirtual 194	com/google/android/gms/measurement/internal/zzp:zzCE	()Lcom/google/android/gms/measurement/internal/zzp$zza;
    //   155: astore 5
    //   157: ldc_w 883
    //   160: astore 6
    //   162: aload 5
    //   164: aload 6
    //   166: invokevirtual 243	com/google/android/gms/measurement/internal/zzp$zza:zzfg	(Ljava/lang/String;)V
    //   169: return
    //   170: astore 5
    //   172: aload_0
    //   173: invokevirtual 188	com/google/android/gms/measurement/internal/zze:zzAo	()Lcom/google/android/gms/measurement/internal/zzp;
    //   176: invokevirtual 194	com/google/android/gms/measurement/internal/zzp:zzCE	()Lcom/google/android/gms/measurement/internal/zzp$zza;
    //   179: astore 6
    //   181: ldc_w 885
    //   184: astore 8
    //   186: aload 6
    //   188: aload 8
    //   190: aload 5
    //   192: invokevirtual 346	com/google/android/gms/measurement/internal/zzp$zza:zzj	(Ljava/lang/String;Ljava/lang/Object;)V
    //   195: goto -26 -> 169
    //   198: astore 5
    //   200: aload_0
    //   201: invokevirtual 188	com/google/android/gms/measurement/internal/zze:zzAo	()Lcom/google/android/gms/measurement/internal/zzp;
    //   204: invokevirtual 194	com/google/android/gms/measurement/internal/zzp:zzCE	()Lcom/google/android/gms/measurement/internal/zzp$zza;
    //   207: astore 6
    //   209: ldc_w 887
    //   212: astore 8
    //   214: aload 6
    //   216: aload 8
    //   218: aload 5
    //   220: invokevirtual 346	com/google/android/gms/measurement/internal/zzp$zza:zzj	(Ljava/lang/String;Ljava/lang/Object;)V
    //   223: goto -54 -> 169
    // Local variable table:
    //   start	length	slot	name	signature
    //   0	226	0	this	zze
    //   0	226	1	paramString	String
    //   0	226	2	paramInt	int
    //   0	226	3	paramzzf	com.google.android.gms.internal.zzqb.zzf
    //   22	3	4	i	int
    //   137	3	4	bool	boolean
    //   28	135	5	localObject1	Object
    //   170	21	5	localIOException	IOException
    //   198	21	5	localSQLiteException	SQLiteException
    //   35	180	6	localObject2	Object
    //   71	39	7	localInteger	Integer
    //   86	131	8	str	String
    //   112	10	9	j	int
    //   126	7	10	l1	long
    //   130	5	12	l2	long
    // Exception table:
    //   from	to	target	type
    //   18	22	170	java/io/IOException
    //   24	28	170	java/io/IOException
    //   30	35	170	java/io/IOException
    //   38	43	170	java/io/IOException
    //   43	48	170	java/io/IOException
    //   97	101	198	android/database/sqlite/SQLiteException
    //   121	126	198	android/database/sqlite/SQLiteException
    //   144	148	198	android/database/sqlite/SQLiteException
    //   150	155	198	android/database/sqlite/SQLiteException
    //   164	169	198	android/database/sqlite/SQLiteException
  }
  
  /* Error */
  public void zza(String paramString, long paramLong, zze.zzb paramzzb)
  {
    // Byte code:
    //   0: iconst_0
    //   1: istore 5
    //   3: aconst_null
    //   4: astore 6
    //   6: aload 4
    //   8: invokestatic 220	com/google/android/gms/common/internal/zzx:zzz	(Ljava/lang/Object;)Ljava/lang/Object;
    //   11: pop
    //   12: aload_0
    //   13: invokevirtual 210	com/google/android/gms/measurement/internal/zze:zzjk	()V
    //   16: aload_0
    //   17: invokevirtual 207	com/google/android/gms/measurement/internal/zze:zzjv	()V
    //   20: aload_0
    //   21: invokevirtual 167	com/google/android/gms/measurement/internal/zze:getWritableDatabase	()Landroid/database/sqlite/SQLiteDatabase;
    //   24: astore 7
    //   26: aload_1
    //   27: invokestatic 281	android/text/TextUtils:isEmpty	(Ljava/lang/CharSequence;)Z
    //   30: istore 8
    //   32: iload 8
    //   34: ifeq +277 -> 311
    //   37: ldc_w 889
    //   40: astore 9
    //   42: iconst_1
    //   43: istore 10
    //   45: iload 10
    //   47: anewarray 289	java/lang/String
    //   50: astore 11
    //   52: iconst_0
    //   53: istore 12
    //   55: aconst_null
    //   56: astore 13
    //   58: lload_2
    //   59: invokestatic 507	java/lang/String:valueOf	(J)Ljava/lang/String;
    //   62: astore 14
    //   64: aload 11
    //   66: iconst_0
    //   67: aload 14
    //   69: aastore
    //   70: aload 7
    //   72: aload 9
    //   74: aload 11
    //   76: invokevirtual 173	android/database/sqlite/SQLiteDatabase:rawQuery	(Ljava/lang/String;[Ljava/lang/String;)Landroid/database/Cursor;
    //   79: astore 6
    //   81: aload 6
    //   83: invokeinterface 176 1 0
    //   88: istore 8
    //   90: iload 8
    //   92: ifne +16 -> 108
    //   95: aload 6
    //   97: ifnull +10 -> 107
    //   100: aload 6
    //   102: invokeinterface 184 1 0
    //   107: return
    //   108: iconst_0
    //   109: istore 8
    //   111: aconst_null
    //   112: astore 9
    //   114: aload 6
    //   116: iconst_0
    //   117: invokeinterface 459 2 0
    //   122: astore_1
    //   123: iconst_1
    //   124: istore 8
    //   126: aload 6
    //   128: iload 8
    //   130: invokeinterface 459 2 0
    //   135: astore 9
    //   137: aload 6
    //   139: invokeinterface 184 1 0
    //   144: aload 9
    //   146: astore 15
    //   148: aload 6
    //   150: astore 16
    //   152: ldc_w 891
    //   155: astore 6
    //   157: iconst_1
    //   158: istore 8
    //   160: iload 8
    //   162: anewarray 289	java/lang/String
    //   165: astore 9
    //   167: iconst_0
    //   168: istore 10
    //   170: aconst_null
    //   171: astore 11
    //   173: ldc_w 893
    //   176: astore 13
    //   178: aload 9
    //   180: iconst_0
    //   181: aload 13
    //   183: aastore
    //   184: ldc_w 895
    //   187: astore 11
    //   189: iconst_2
    //   190: istore 12
    //   192: iload 12
    //   194: anewarray 289	java/lang/String
    //   197: astore 13
    //   199: iconst_0
    //   200: istore 17
    //   202: aconst_null
    //   203: astore 14
    //   205: aload 13
    //   207: iconst_0
    //   208: aload_1
    //   209: aastore
    //   210: iconst_1
    //   211: istore 17
    //   213: aload 13
    //   215: iload 17
    //   217: aload 15
    //   219: aastore
    //   220: iconst_0
    //   221: istore 17
    //   223: aconst_null
    //   224: astore 14
    //   226: ldc_w 897
    //   229: astore 18
    //   231: ldc_w 899
    //   234: astore 19
    //   236: aload 7
    //   238: aload 6
    //   240: aload 9
    //   242: aload 11
    //   244: aload 13
    //   246: aconst_null
    //   247: aconst_null
    //   248: aload 18
    //   250: aload 19
    //   252: invokevirtual 902	android/database/sqlite/SQLiteDatabase:query	(Ljava/lang/String;[Ljava/lang/String;Ljava/lang/String;[Ljava/lang/String;Ljava/lang/String;Ljava/lang/String;Ljava/lang/String;Ljava/lang/String;)Landroid/database/Cursor;
    //   255: astore 16
    //   257: aload 16
    //   259: invokeinterface 176 1 0
    //   264: istore 5
    //   266: iload 5
    //   268: ifne +143 -> 411
    //   271: aload_0
    //   272: invokevirtual 188	com/google/android/gms/measurement/internal/zze:zzAo	()Lcom/google/android/gms/measurement/internal/zzp;
    //   275: astore 7
    //   277: aload 7
    //   279: invokevirtual 194	com/google/android/gms/measurement/internal/zzp:zzCE	()Lcom/google/android/gms/measurement/internal/zzp$zza;
    //   282: astore 7
    //   284: ldc_w 904
    //   287: astore 6
    //   289: aload 7
    //   291: aload 6
    //   293: invokevirtual 243	com/google/android/gms/measurement/internal/zzp$zza:zzfg	(Ljava/lang/String;)V
    //   296: aload 16
    //   298: ifnull -191 -> 107
    //   301: aload 16
    //   303: invokeinterface 184 1 0
    //   308: goto -201 -> 107
    //   311: ldc_w 906
    //   314: astore 9
    //   316: iconst_1
    //   317: istore 10
    //   319: iload 10
    //   321: anewarray 289	java/lang/String
    //   324: astore 11
    //   326: iconst_0
    //   327: istore 12
    //   329: aconst_null
    //   330: astore 13
    //   332: aload 11
    //   334: iconst_0
    //   335: aload_1
    //   336: aastore
    //   337: aload 7
    //   339: aload 9
    //   341: aload 11
    //   343: invokevirtual 173	android/database/sqlite/SQLiteDatabase:rawQuery	(Ljava/lang/String;[Ljava/lang/String;)Landroid/database/Cursor;
    //   346: astore 6
    //   348: aload 6
    //   350: invokeinterface 176 1 0
    //   355: istore 8
    //   357: iload 8
    //   359: ifne +18 -> 377
    //   362: aload 6
    //   364: ifnull -257 -> 107
    //   367: aload 6
    //   369: invokeinterface 184 1 0
    //   374: goto -267 -> 107
    //   377: iconst_0
    //   378: istore 8
    //   380: aconst_null
    //   381: astore 9
    //   383: aload 6
    //   385: iconst_0
    //   386: invokeinterface 459 2 0
    //   391: astore 9
    //   393: aload 6
    //   395: invokeinterface 184 1 0
    //   400: aload 9
    //   402: astore 15
    //   404: aload 6
    //   406: astore 16
    //   408: goto -256 -> 152
    //   411: iconst_0
    //   412: istore 5
    //   414: aconst_null
    //   415: astore 6
    //   417: aload 16
    //   419: iconst_0
    //   420: invokeinterface 437 2 0
    //   425: astore 6
    //   427: aload 6
    //   429: invokestatic 443	com/google/android/gms/internal/zzsm:zzD	([B)Lcom/google/android/gms/internal/zzsm;
    //   432: astore 6
    //   434: new 670	com/google/android/gms/internal/zzqb$zze
    //   437: astore 9
    //   439: aload 9
    //   441: invokespecial 907	com/google/android/gms/internal/zzqb$zze:<init>	()V
    //   444: aload 9
    //   446: aload 6
    //   448: invokevirtual 911	com/google/android/gms/internal/zzqb$zze:zzG	(Lcom/google/android/gms/internal/zzsm;)Lcom/google/android/gms/internal/zzqb$zze;
    //   451: pop
    //   452: aload 16
    //   454: invokeinterface 550 1 0
    //   459: istore 5
    //   461: iload 5
    //   463: ifeq +28 -> 491
    //   466: aload_0
    //   467: invokevirtual 188	com/google/android/gms/measurement/internal/zze:zzAo	()Lcom/google/android/gms/measurement/internal/zzp;
    //   470: astore 6
    //   472: aload 6
    //   474: invokevirtual 237	com/google/android/gms/measurement/internal/zzp:zzCF	()Lcom/google/android/gms/measurement/internal/zzp$zza;
    //   477: astore 6
    //   479: ldc_w 913
    //   482: astore 11
    //   484: aload 6
    //   486: aload 11
    //   488: invokevirtual 243	com/google/android/gms/measurement/internal/zzp$zza:zzfg	(Ljava/lang/String;)V
    //   491: aload 16
    //   493: invokeinterface 184 1 0
    //   498: aload 4
    //   500: aload 9
    //   502: invokeinterface 919 2 0
    //   507: ldc_w 858
    //   510: astore 6
    //   512: iconst_4
    //   513: istore 8
    //   515: iload 8
    //   517: anewarray 289	java/lang/String
    //   520: astore 9
    //   522: iconst_0
    //   523: istore 10
    //   525: aconst_null
    //   526: astore 11
    //   528: ldc_w 897
    //   531: astore 13
    //   533: aload 9
    //   535: iconst_0
    //   536: aload 13
    //   538: aastore
    //   539: iconst_1
    //   540: istore 10
    //   542: ldc_w 849
    //   545: astore 13
    //   547: aload 9
    //   549: iload 10
    //   551: aload 13
    //   553: aastore
    //   554: iconst_2
    //   555: istore 10
    //   557: ldc_w 851
    //   560: astore 13
    //   562: aload 9
    //   564: iload 10
    //   566: aload 13
    //   568: aastore
    //   569: iconst_3
    //   570: istore 10
    //   572: ldc_w 328
    //   575: astore 13
    //   577: aload 9
    //   579: iload 10
    //   581: aload 13
    //   583: aastore
    //   584: ldc_w 895
    //   587: astore 11
    //   589: iconst_2
    //   590: istore 12
    //   592: iload 12
    //   594: anewarray 289	java/lang/String
    //   597: astore 13
    //   599: iconst_0
    //   600: istore 17
    //   602: aconst_null
    //   603: astore 14
    //   605: aload 13
    //   607: iconst_0
    //   608: aload_1
    //   609: aastore
    //   610: iconst_1
    //   611: istore 17
    //   613: aload 13
    //   615: iload 17
    //   617: aload 15
    //   619: aastore
    //   620: iconst_0
    //   621: istore 17
    //   623: aconst_null
    //   624: astore 14
    //   626: ldc_w 897
    //   629: astore 18
    //   631: aconst_null
    //   632: astore 19
    //   634: aload 7
    //   636: aload 6
    //   638: aload 9
    //   640: aload 11
    //   642: aload 13
    //   644: aconst_null
    //   645: aconst_null
    //   646: aload 18
    //   648: aconst_null
    //   649: invokevirtual 902	android/database/sqlite/SQLiteDatabase:query	(Ljava/lang/String;[Ljava/lang/String;Ljava/lang/String;[Ljava/lang/String;Ljava/lang/String;Ljava/lang/String;Ljava/lang/String;Ljava/lang/String;)Landroid/database/Cursor;
    //   652: astore 6
    //   654: aload 6
    //   656: invokeinterface 176 1 0
    //   661: istore 20
    //   663: iload 20
    //   665: ifne +88 -> 753
    //   668: aload_0
    //   669: invokevirtual 188	com/google/android/gms/measurement/internal/zze:zzAo	()Lcom/google/android/gms/measurement/internal/zzp;
    //   672: astore 7
    //   674: aload 7
    //   676: invokevirtual 237	com/google/android/gms/measurement/internal/zzp:zzCF	()Lcom/google/android/gms/measurement/internal/zzp$zza;
    //   679: astore 7
    //   681: ldc_w 921
    //   684: astore 9
    //   686: aload 7
    //   688: aload 9
    //   690: invokevirtual 243	com/google/android/gms/measurement/internal/zzp$zza:zzfg	(Ljava/lang/String;)V
    //   693: aload 6
    //   695: ifnull -588 -> 107
    //   698: aload 6
    //   700: invokeinterface 184 1 0
    //   705: goto -598 -> 107
    //   708: astore 7
    //   710: aload_0
    //   711: invokevirtual 188	com/google/android/gms/measurement/internal/zze:zzAo	()Lcom/google/android/gms/measurement/internal/zzp;
    //   714: astore 6
    //   716: aload 6
    //   718: invokevirtual 194	com/google/android/gms/measurement/internal/zzp:zzCE	()Lcom/google/android/gms/measurement/internal/zzp$zza;
    //   721: astore 6
    //   723: ldc_w 923
    //   726: astore 9
    //   728: aload 6
    //   730: aload 9
    //   732: aload_1
    //   733: aload 7
    //   735: invokevirtual 202	com/google/android/gms/measurement/internal/zzp$zza:zze	(Ljava/lang/String;Ljava/lang/Object;Ljava/lang/Object;)V
    //   738: aload 16
    //   740: ifnull -633 -> 107
    //   743: aload 16
    //   745: invokeinterface 184 1 0
    //   750: goto -643 -> 107
    //   753: iconst_0
    //   754: istore 20
    //   756: aconst_null
    //   757: astore 7
    //   759: aload 6
    //   761: iconst_0
    //   762: invokeinterface 180 2 0
    //   767: lstore 21
    //   769: iconst_3
    //   770: istore 20
    //   772: aload 6
    //   774: iload 20
    //   776: invokeinterface 437 2 0
    //   781: astore 7
    //   783: aload 7
    //   785: invokestatic 443	com/google/android/gms/internal/zzsm:zzD	([B)Lcom/google/android/gms/internal/zzsm;
    //   788: astore 7
    //   790: new 796	com/google/android/gms/internal/zzqb$zzb
    //   793: astore 13
    //   795: aload 13
    //   797: invokespecial 797	com/google/android/gms/internal/zzqb$zzb:<init>	()V
    //   800: aload 13
    //   802: aload 7
    //   804: invokevirtual 926	com/google/android/gms/internal/zzqb$zzb:zzD	(Lcom/google/android/gms/internal/zzsm;)Lcom/google/android/gms/internal/zzqb$zzb;
    //   807: pop
    //   808: iconst_1
    //   809: istore 20
    //   811: aload 6
    //   813: iload 20
    //   815: invokeinterface 459 2 0
    //   820: astore 7
    //   822: aload 13
    //   824: aload 7
    //   826: putfield 927	com/google/android/gms/internal/zzqb$zzb:name	Ljava/lang/String;
    //   829: iconst_2
    //   830: istore 20
    //   832: aload 6
    //   834: iload 20
    //   836: invokeinterface 180 2 0
    //   841: lstore 23
    //   843: lload 23
    //   845: invokestatic 649	java/lang/Long:valueOf	(J)Ljava/lang/Long;
    //   848: astore 7
    //   850: aload 13
    //   852: aload 7
    //   854: putfield 930	com/google/android/gms/internal/zzqb$zzb:zzbaf	Ljava/lang/Long;
    //   857: aload 4
    //   859: lload 21
    //   861: aload 13
    //   863: invokeinterface 933 4 0
    //   868: istore 20
    //   870: iload 20
    //   872: ifne +48 -> 920
    //   875: aload 6
    //   877: ifnull -770 -> 107
    //   880: aload 6
    //   882: invokeinterface 184 1 0
    //   887: goto -780 -> 107
    //   890: astore 7
    //   892: aload_0
    //   893: invokevirtual 188	com/google/android/gms/measurement/internal/zze:zzAo	()Lcom/google/android/gms/measurement/internal/zzp;
    //   896: astore 9
    //   898: aload 9
    //   900: invokevirtual 194	com/google/android/gms/measurement/internal/zzp:zzCE	()Lcom/google/android/gms/measurement/internal/zzp$zza;
    //   903: astore 9
    //   905: ldc_w 935
    //   908: astore 11
    //   910: aload 9
    //   912: aload 11
    //   914: aload_1
    //   915: aload 7
    //   917: invokevirtual 202	com/google/android/gms/measurement/internal/zzp$zza:zze	(Ljava/lang/String;Ljava/lang/Object;Ljava/lang/Object;)V
    //   920: aload 6
    //   922: invokeinterface 550 1 0
    //   927: istore 20
    //   929: iload 20
    //   931: ifne -178 -> 753
    //   934: aload 6
    //   936: ifnull -829 -> 107
    //   939: aload 6
    //   941: invokeinterface 184 1 0
    //   946: goto -839 -> 107
    //   949: astore 7
    //   951: aload_0
    //   952: invokevirtual 188	com/google/android/gms/measurement/internal/zze:zzAo	()Lcom/google/android/gms/measurement/internal/zzp;
    //   955: astore 9
    //   957: aload 9
    //   959: invokevirtual 194	com/google/android/gms/measurement/internal/zzp:zzCE	()Lcom/google/android/gms/measurement/internal/zzp$zza;
    //   962: astore 9
    //   964: ldc_w 937
    //   967: astore 11
    //   969: aload 9
    //   971: aload 11
    //   973: aload 7
    //   975: invokevirtual 346	com/google/android/gms/measurement/internal/zzp$zza:zzj	(Ljava/lang/String;Ljava/lang/Object;)V
    //   978: aload 6
    //   980: ifnull -873 -> 107
    //   983: aload 6
    //   985: invokeinterface 184 1 0
    //   990: goto -883 -> 107
    //   993: astore 7
    //   995: aconst_null
    //   996: astore 16
    //   998: aload 16
    //   1000: ifnull +10 -> 1010
    //   1003: aload 16
    //   1005: invokeinterface 184 1 0
    //   1010: aload 7
    //   1012: athrow
    //   1013: astore 7
    //   1015: aload 6
    //   1017: astore 16
    //   1019: goto -21 -> 998
    //   1022: astore 7
    //   1024: goto -26 -> 998
    //   1027: astore 7
    //   1029: aload 16
    //   1031: astore 6
    //   1033: goto -82 -> 951
    // Local variable table:
    //   start	length	slot	name	signature
    //   0	1036	0	this	zze
    //   0	1036	1	paramString	String
    //   0	1036	2	paramLong	long
    //   0	1036	4	paramzzb	zze.zzb
    //   1	461	5	bool1	boolean
    //   4	1028	6	localObject1	Object
    //   24	663	7	localObject2	Object
    //   708	26	7	localIOException1	IOException
    //   757	96	7	localObject3	Object
    //   890	26	7	localIOException2	IOException
    //   949	25	7	localSQLiteException1	SQLiteException
    //   993	18	7	localObject4	Object
    //   1013	1	7	localObject5	Object
    //   1022	1	7	localObject6	Object
    //   1027	1	7	localSQLiteException2	SQLiteException
    //   30	99	8	i	int
    //   158	221	8	bool2	boolean
    //   513	3	8	j	int
    //   40	930	9	localObject7	Object
    //   43	537	10	k	int
    //   50	922	11	localObject8	Object
    //   53	540	12	m	int
    //   56	806	13	localObject9	Object
    //   62	563	14	str1	String
    //   146	472	15	localObject10	Object
    //   150	880	16	localObject11	Object
    //   200	422	17	n	int
    //   229	418	18	str2	String
    //   234	399	19	str3	String
    //   661	94	20	bool3	boolean
    //   770	65	20	i1	int
    //   868	62	20	bool4	boolean
    //   767	93	21	l1	long
    //   841	3	23	l2	long
    // Exception table:
    //   from	to	target	type
    //   446	452	708	java/io/IOException
    //   802	808	890	java/io/IOException
    //   20	24	949	android/database/sqlite/SQLiteException
    //   26	30	949	android/database/sqlite/SQLiteException
    //   45	50	949	android/database/sqlite/SQLiteException
    //   58	62	949	android/database/sqlite/SQLiteException
    //   67	70	949	android/database/sqlite/SQLiteException
    //   74	79	949	android/database/sqlite/SQLiteException
    //   81	88	949	android/database/sqlite/SQLiteException
    //   116	122	949	android/database/sqlite/SQLiteException
    //   128	135	949	android/database/sqlite/SQLiteException
    //   137	144	949	android/database/sqlite/SQLiteException
    //   319	324	949	android/database/sqlite/SQLiteException
    //   335	337	949	android/database/sqlite/SQLiteException
    //   341	346	949	android/database/sqlite/SQLiteException
    //   348	355	949	android/database/sqlite/SQLiteException
    //   385	391	949	android/database/sqlite/SQLiteException
    //   393	400	949	android/database/sqlite/SQLiteException
    //   654	661	949	android/database/sqlite/SQLiteException
    //   668	672	949	android/database/sqlite/SQLiteException
    //   674	679	949	android/database/sqlite/SQLiteException
    //   688	693	949	android/database/sqlite/SQLiteException
    //   761	767	949	android/database/sqlite/SQLiteException
    //   774	781	949	android/database/sqlite/SQLiteException
    //   783	788	949	android/database/sqlite/SQLiteException
    //   790	793	949	android/database/sqlite/SQLiteException
    //   795	800	949	android/database/sqlite/SQLiteException
    //   802	808	949	android/database/sqlite/SQLiteException
    //   813	820	949	android/database/sqlite/SQLiteException
    //   824	829	949	android/database/sqlite/SQLiteException
    //   834	841	949	android/database/sqlite/SQLiteException
    //   843	848	949	android/database/sqlite/SQLiteException
    //   852	857	949	android/database/sqlite/SQLiteException
    //   861	868	949	android/database/sqlite/SQLiteException
    //   892	896	949	android/database/sqlite/SQLiteException
    //   898	903	949	android/database/sqlite/SQLiteException
    //   915	920	949	android/database/sqlite/SQLiteException
    //   920	927	949	android/database/sqlite/SQLiteException
    //   20	24	993	finally
    //   26	30	993	finally
    //   45	50	993	finally
    //   58	62	993	finally
    //   67	70	993	finally
    //   74	79	993	finally
    //   319	324	993	finally
    //   335	337	993	finally
    //   341	346	993	finally
    //   81	88	1013	finally
    //   116	122	1013	finally
    //   128	135	1013	finally
    //   137	144	1013	finally
    //   348	355	1013	finally
    //   385	391	1013	finally
    //   393	400	1013	finally
    //   654	661	1013	finally
    //   668	672	1013	finally
    //   674	679	1013	finally
    //   688	693	1013	finally
    //   761	767	1013	finally
    //   774	781	1013	finally
    //   783	788	1013	finally
    //   790	793	1013	finally
    //   795	800	1013	finally
    //   802	808	1013	finally
    //   813	820	1013	finally
    //   824	829	1013	finally
    //   834	841	1013	finally
    //   843	848	1013	finally
    //   852	857	1013	finally
    //   861	868	1013	finally
    //   892	896	1013	finally
    //   898	903	1013	finally
    //   915	920	1013	finally
    //   920	927	1013	finally
    //   951	955	1013	finally
    //   957	962	1013	finally
    //   973	978	1013	finally
    //   160	165	1022	finally
    //   181	184	1022	finally
    //   192	197	1022	finally
    //   208	210	1022	finally
    //   217	220	1022	finally
    //   250	255	1022	finally
    //   257	264	1022	finally
    //   271	275	1022	finally
    //   277	282	1022	finally
    //   291	296	1022	finally
    //   419	425	1022	finally
    //   427	432	1022	finally
    //   434	437	1022	finally
    //   439	444	1022	finally
    //   446	452	1022	finally
    //   452	459	1022	finally
    //   466	470	1022	finally
    //   472	477	1022	finally
    //   486	491	1022	finally
    //   491	498	1022	finally
    //   500	507	1022	finally
    //   515	520	1022	finally
    //   536	539	1022	finally
    //   551	554	1022	finally
    //   566	569	1022	finally
    //   581	584	1022	finally
    //   592	597	1022	finally
    //   608	610	1022	finally
    //   617	620	1022	finally
    //   648	652	1022	finally
    //   710	714	1022	finally
    //   716	721	1022	finally
    //   733	738	1022	finally
    //   160	165	1027	android/database/sqlite/SQLiteException
    //   181	184	1027	android/database/sqlite/SQLiteException
    //   192	197	1027	android/database/sqlite/SQLiteException
    //   208	210	1027	android/database/sqlite/SQLiteException
    //   217	220	1027	android/database/sqlite/SQLiteException
    //   250	255	1027	android/database/sqlite/SQLiteException
    //   257	264	1027	android/database/sqlite/SQLiteException
    //   271	275	1027	android/database/sqlite/SQLiteException
    //   277	282	1027	android/database/sqlite/SQLiteException
    //   291	296	1027	android/database/sqlite/SQLiteException
    //   419	425	1027	android/database/sqlite/SQLiteException
    //   427	432	1027	android/database/sqlite/SQLiteException
    //   434	437	1027	android/database/sqlite/SQLiteException
    //   439	444	1027	android/database/sqlite/SQLiteException
    //   446	452	1027	android/database/sqlite/SQLiteException
    //   452	459	1027	android/database/sqlite/SQLiteException
    //   466	470	1027	android/database/sqlite/SQLiteException
    //   472	477	1027	android/database/sqlite/SQLiteException
    //   486	491	1027	android/database/sqlite/SQLiteException
    //   491	498	1027	android/database/sqlite/SQLiteException
    //   500	507	1027	android/database/sqlite/SQLiteException
    //   515	520	1027	android/database/sqlite/SQLiteException
    //   536	539	1027	android/database/sqlite/SQLiteException
    //   551	554	1027	android/database/sqlite/SQLiteException
    //   566	569	1027	android/database/sqlite/SQLiteException
    //   581	584	1027	android/database/sqlite/SQLiteException
    //   592	597	1027	android/database/sqlite/SQLiteException
    //   608	610	1027	android/database/sqlite/SQLiteException
    //   617	620	1027	android/database/sqlite/SQLiteException
    //   648	652	1027	android/database/sqlite/SQLiteException
    //   710	714	1027	android/database/sqlite/SQLiteException
    //   716	721	1027	android/database/sqlite/SQLiteException
    //   733	738	1027	android/database/sqlite/SQLiteException
  }
  
  public boolean zza(zzai paramzzai)
  {
    boolean bool1 = true;
    boolean bool2 = false;
    Object localObject1 = null;
    zzx.zzz(paramzzai);
    zzjk();
    zzjv();
    localObject2 = paramzzai.zzaUa;
    localObject3 = paramzzai.mName;
    localObject2 = zzK((String)localObject2, (String)localObject3);
    boolean bool3;
    Object localObject4;
    long l1;
    int i;
    long l2;
    if (localObject2 == null)
    {
      localObject2 = paramzzai.mName;
      bool3 = zzaj.zzfq((String)localObject2);
      if (bool3)
      {
        localObject2 = "select count(1) from user_attributes where app_id=? and name not like '!_%' escape '!'";
        localObject3 = new String[bool1];
        localObject4 = paramzzai.zzaUa;
        localObject3[0] = localObject4;
        l1 = zzb((String)localObject2, (String[])localObject3);
        localObject4 = zzCp();
        i = ((zzd)localObject4).zzBL();
        l2 = i;
        bool3 = l1 < l2;
        if (bool3) {
          break label193;
        }
      }
    }
    for (;;)
    {
      return bool2;
      localObject2 = "select count(1) from user_attributes where app_id=?";
      localObject3 = new String[bool1];
      localObject4 = paramzzai.zzaUa;
      localObject3[0] = localObject4;
      l1 = zzb((String)localObject2, (String[])localObject3);
      localObject4 = zzCp();
      i = ((zzd)localObject4).zzBM();
      l2 = i;
      bool3 = l1 < l2;
      if (bool3)
      {
        label193:
        localObject1 = new android/content/ContentValues;
        ((ContentValues)localObject1).<init>();
        localObject3 = paramzzai.zzaUa;
        ((ContentValues)localObject1).put("app_id", (String)localObject3);
        localObject3 = paramzzai.mName;
        ((ContentValues)localObject1).put("name", (String)localObject3);
        l2 = paramzzai.zzaZp;
        localObject3 = Long.valueOf(l2);
        ((ContentValues)localObject1).put("set_timestamp", (Long)localObject3);
        localObject2 = "value";
        localObject3 = paramzzai.zzNc;
        zza((ContentValues)localObject1, (String)localObject2, localObject3);
      }
      try
      {
        localObject2 = getWritableDatabase();
        localObject3 = "user_attributes";
        i = 0;
        localObject4 = null;
        int j = 5;
        l1 = ((SQLiteDatabase)localObject2).insertWithOnConflict((String)localObject3, null, (ContentValues)localObject1, j);
        l2 = -1;
        bool2 = l1 < l2;
        if (!bool2)
        {
          localObject1 = zzAo();
          localObject1 = ((zzp)localObject1).zzCE();
          localObject2 = "Failed to insert/update user property (got -1)";
          ((zzp.zza)localObject1).zzfg((String)localObject2);
        }
      }
      catch (SQLiteException localSQLiteException)
      {
        for (;;)
        {
          localObject2 = zzAo().zzCE();
          localObject3 = "Error storing user property";
          ((zzp.zza)localObject2).zzj((String)localObject3, localSQLiteException);
        }
      }
      bool2 = bool1;
    }
  }
  
  /* Error */
  public String zzaa(long paramLong)
  {
    // Byte code:
    //   0: aconst_null
    //   1: astore_3
    //   2: aload_0
    //   3: invokevirtual 210	com/google/android/gms/measurement/internal/zze:zzjk	()V
    //   6: aload_0
    //   7: invokevirtual 207	com/google/android/gms/measurement/internal/zze:zzjv	()V
    //   10: aload_0
    //   11: invokevirtual 167	com/google/android/gms/measurement/internal/zze:getWritableDatabase	()Landroid/database/sqlite/SQLiteDatabase;
    //   14: astore 4
    //   16: ldc_w 973
    //   19: astore 5
    //   21: iconst_1
    //   22: istore 6
    //   24: iload 6
    //   26: anewarray 289	java/lang/String
    //   29: astore 7
    //   31: aconst_null
    //   32: astore 8
    //   34: lload_1
    //   35: invokestatic 507	java/lang/String:valueOf	(J)Ljava/lang/String;
    //   38: astore 9
    //   40: aload 7
    //   42: iconst_0
    //   43: aload 9
    //   45: aastore
    //   46: aload 4
    //   48: aload 5
    //   50: aload 7
    //   52: invokevirtual 173	android/database/sqlite/SQLiteDatabase:rawQuery	(Ljava/lang/String;[Ljava/lang/String;)Landroid/database/Cursor;
    //   55: astore 5
    //   57: aload 5
    //   59: invokeinterface 176 1 0
    //   64: istore 10
    //   66: iload 10
    //   68: ifne +42 -> 110
    //   71: aload_0
    //   72: invokevirtual 188	com/google/android/gms/measurement/internal/zze:zzAo	()Lcom/google/android/gms/measurement/internal/zzp;
    //   75: astore 4
    //   77: aload 4
    //   79: invokevirtual 517	com/google/android/gms/measurement/internal/zzp:zzCK	()Lcom/google/android/gms/measurement/internal/zzp$zza;
    //   82: astore 4
    //   84: ldc_w 975
    //   87: astore 7
    //   89: aload 4
    //   91: aload 7
    //   93: invokevirtual 243	com/google/android/gms/measurement/internal/zzp$zza:zzfg	(Ljava/lang/String;)V
    //   96: aload 5
    //   98: ifnull +10 -> 108
    //   101: aload 5
    //   103: invokeinterface 184 1 0
    //   108: aload_3
    //   109: areturn
    //   110: iconst_0
    //   111: istore 10
    //   113: aconst_null
    //   114: astore 4
    //   116: aload 5
    //   118: iconst_0
    //   119: invokeinterface 459 2 0
    //   124: astore_3
    //   125: aload 5
    //   127: ifnull -19 -> 108
    //   130: aload 5
    //   132: invokeinterface 184 1 0
    //   137: goto -29 -> 108
    //   140: astore 4
    //   142: aconst_null
    //   143: astore 5
    //   145: aload_0
    //   146: invokevirtual 188	com/google/android/gms/measurement/internal/zze:zzAo	()Lcom/google/android/gms/measurement/internal/zzp;
    //   149: astore 7
    //   151: aload 7
    //   153: invokevirtual 194	com/google/android/gms/measurement/internal/zzp:zzCE	()Lcom/google/android/gms/measurement/internal/zzp$zza;
    //   156: astore 7
    //   158: ldc_w 977
    //   161: astore 8
    //   163: aload 7
    //   165: aload 8
    //   167: aload 4
    //   169: invokevirtual 346	com/google/android/gms/measurement/internal/zzp$zza:zzj	(Ljava/lang/String;Ljava/lang/Object;)V
    //   172: aload 5
    //   174: ifnull -66 -> 108
    //   177: aload 5
    //   179: invokeinterface 184 1 0
    //   184: goto -76 -> 108
    //   187: astore 4
    //   189: aconst_null
    //   190: astore 5
    //   192: aload 4
    //   194: astore_3
    //   195: aload 5
    //   197: ifnull +10 -> 207
    //   200: aload 5
    //   202: invokeinterface 184 1 0
    //   207: aload_3
    //   208: athrow
    //   209: astore_3
    //   210: goto -15 -> 195
    //   213: astore 4
    //   215: goto -70 -> 145
    // Local variable table:
    //   start	length	slot	name	signature
    //   0	218	0	this	zze
    //   0	218	1	paramLong	long
    //   1	207	3	localObject1	Object
    //   209	1	3	localObject2	Object
    //   14	101	4	localObject3	Object
    //   140	28	4	localSQLiteException1	SQLiteException
    //   187	6	4	localObject4	Object
    //   213	1	4	localSQLiteException2	SQLiteException
    //   19	182	5	localObject5	Object
    //   22	3	6	i	int
    //   29	135	7	localObject6	Object
    //   32	134	8	str1	String
    //   38	6	9	str2	String
    //   64	48	10	bool	boolean
    // Exception table:
    //   from	to	target	type
    //   10	14	140	android/database/sqlite/SQLiteException
    //   24	29	140	android/database/sqlite/SQLiteException
    //   34	38	140	android/database/sqlite/SQLiteException
    //   43	46	140	android/database/sqlite/SQLiteException
    //   50	55	140	android/database/sqlite/SQLiteException
    //   10	14	187	finally
    //   24	29	187	finally
    //   34	38	187	finally
    //   43	46	187	finally
    //   50	55	187	finally
    //   57	64	209	finally
    //   71	75	209	finally
    //   77	82	209	finally
    //   91	96	209	finally
    //   118	124	209	finally
    //   145	149	209	finally
    //   151	156	209	finally
    //   167	172	209	finally
    //   57	64	213	android/database/sqlite/SQLiteException
    //   71	75	213	android/database/sqlite/SQLiteException
    //   77	82	213	android/database/sqlite/SQLiteException
    //   91	96	213	android/database/sqlite/SQLiteException
    //   118	124	213	android/database/sqlite/SQLiteException
  }
  
  /* Error */
  public long zzb(com.google.android.gms.internal.zzqb.zze paramzze)
  {
    // Byte code:
    //   0: aload_0
    //   1: invokevirtual 210	com/google/android/gms/measurement/internal/zze:zzjk	()V
    //   4: aload_0
    //   5: invokevirtual 207	com/google/android/gms/measurement/internal/zze:zzjv	()V
    //   8: aload_1
    //   9: invokestatic 220	com/google/android/gms/common/internal/zzx:zzz	(Ljava/lang/Object;)Ljava/lang/Object;
    //   12: pop
    //   13: aload_1
    //   14: getfield 673	com/google/android/gms/internal/zzqb$zze:appId	Ljava/lang/String;
    //   17: astore_2
    //   18: aload_2
    //   19: invokestatic 216	com/google/android/gms/common/internal/zzx:zzcM	(Ljava/lang/String;)Ljava/lang/String;
    //   22: pop
    //   23: aload_1
    //   24: invokevirtual 686	com/google/android/gms/internal/zzqb$zze:getSerializedSize	()I
    //   27: istore_3
    //   28: iload_3
    //   29: newarray <illegal type>
    //   31: astore_2
    //   32: aload_2
    //   33: invokestatic 301	com/google/android/gms/internal/zzsn:zzE	([B)Lcom/google/android/gms/internal/zzsn;
    //   36: astore 4
    //   38: aload_1
    //   39: aload 4
    //   41: invokevirtual 687	com/google/android/gms/internal/zzqb$zze:writeTo	(Lcom/google/android/gms/internal/zzsn;)V
    //   44: aload 4
    //   46: invokevirtual 308	com/google/android/gms/internal/zzsn:zzJo	()V
    //   49: aload_0
    //   50: invokevirtual 691	com/google/android/gms/measurement/internal/zze:zzCk	()Lcom/google/android/gms/measurement/internal/zzaj;
    //   53: aload_2
    //   54: invokevirtual 981	com/google/android/gms/measurement/internal/zzaj:zzr	([B)J
    //   57: lstore 5
    //   59: new 310	android/content/ContentValues
    //   62: astore 4
    //   64: aload 4
    //   66: invokespecial 312	android/content/ContentValues:<init>	()V
    //   69: aload_1
    //   70: getfield 673	com/google/android/gms/internal/zzqb$zze:appId	Ljava/lang/String;
    //   73: astore 7
    //   75: aload 4
    //   77: ldc_w 314
    //   80: aload 7
    //   82: invokevirtual 317	android/content/ContentValues:put	(Ljava/lang/String;Ljava/lang/String;)V
    //   85: lload 5
    //   87: invokestatic 649	java/lang/Long:valueOf	(J)Ljava/lang/Long;
    //   90: astore 7
    //   92: aload 4
    //   94: ldc_w 856
    //   97: aload 7
    //   99: invokevirtual 652	android/content/ContentValues:put	(Ljava/lang/String;Ljava/lang/Long;)V
    //   102: ldc_w 893
    //   105: astore 8
    //   107: aload 4
    //   109: aload 8
    //   111: aload_2
    //   112: invokevirtual 331	android/content/ContentValues:put	(Ljava/lang/String;[B)V
    //   115: aload_0
    //   116: invokevirtual 167	com/google/android/gms/measurement/internal/zze:getWritableDatabase	()Landroid/database/sqlite/SQLiteDatabase;
    //   119: astore_2
    //   120: ldc_w 891
    //   123: astore 8
    //   125: aconst_null
    //   126: astore 7
    //   128: iconst_4
    //   129: istore 9
    //   131: aload_2
    //   132: aload 8
    //   134: aconst_null
    //   135: aload 4
    //   137: iload 9
    //   139: invokevirtual 338	android/database/sqlite/SQLiteDatabase:insertWithOnConflict	(Ljava/lang/String;Ljava/lang/String;Landroid/content/ContentValues;I)J
    //   142: pop2
    //   143: lload 5
    //   145: lreturn
    //   146: astore_2
    //   147: aload_0
    //   148: invokevirtual 188	com/google/android/gms/measurement/internal/zze:zzAo	()Lcom/google/android/gms/measurement/internal/zzp;
    //   151: invokevirtual 194	com/google/android/gms/measurement/internal/zzp:zzCE	()Lcom/google/android/gms/measurement/internal/zzp$zza;
    //   154: ldc_w 983
    //   157: aload_2
    //   158: invokevirtual 346	com/google/android/gms/measurement/internal/zzp$zza:zzj	(Ljava/lang/String;Ljava/lang/Object;)V
    //   161: aload_2
    //   162: athrow
    //   163: astore_2
    //   164: aload_0
    //   165: invokevirtual 188	com/google/android/gms/measurement/internal/zze:zzAo	()Lcom/google/android/gms/measurement/internal/zzp;
    //   168: invokevirtual 194	com/google/android/gms/measurement/internal/zzp:zzCE	()Lcom/google/android/gms/measurement/internal/zzp$zza;
    //   171: ldc_w 985
    //   174: aload_2
    //   175: invokevirtual 346	com/google/android/gms/measurement/internal/zzp$zza:zzj	(Ljava/lang/String;Ljava/lang/Object;)V
    //   178: aload_2
    //   179: athrow
    // Local variable table:
    //   start	length	slot	name	signature
    //   0	180	0	this	zze
    //   0	180	1	paramzze	com.google.android.gms.internal.zzqb.zze
    //   17	115	2	localObject1	Object
    //   146	16	2	localIOException	IOException
    //   163	16	2	localSQLiteException	SQLiteException
    //   27	2	3	i	int
    //   36	100	4	localObject2	Object
    //   57	87	5	l	long
    //   73	54	7	localObject3	Object
    //   105	28	8	str	String
    //   129	9	9	j	int
    // Exception table:
    //   from	to	target	type
    //   23	27	146	java/io/IOException
    //   28	31	146	java/io/IOException
    //   32	36	146	java/io/IOException
    //   39	44	146	java/io/IOException
    //   44	49	146	java/io/IOException
    //   115	119	163	android/database/sqlite/SQLiteException
    //   137	143	163	android/database/sqlite/SQLiteException
  }
  
  Object zzb(Cursor paramCursor, int paramInt)
  {
    float f = 0.0F;
    Object localObject1 = null;
    int i = zza(paramCursor, paramInt);
    Object localObject2;
    Object localObject3;
    switch (i)
    {
    default: 
      localObject2 = zzAo().zzCE();
      String str = "Loaded invalid unknown value type, ignoring it";
      localObject3 = Integer.valueOf(i);
      ((zzp.zza)localObject2).zzj(str, localObject3);
    }
    for (;;)
    {
      return localObject1;
      localObject3 = zzAo().zzCE();
      localObject2 = "Loaded invalid null value from database";
      ((zzp.zza)localObject3).zzfg((String)localObject2);
      continue;
      long l = paramCursor.getLong(paramInt);
      localObject1 = Long.valueOf(l);
      continue;
      f = paramCursor.getFloat(paramInt);
      localObject1 = Float.valueOf(f);
      continue;
      localObject1 = paramCursor.getString(paramInt);
      continue;
      localObject3 = zzAo().zzCE();
      localObject2 = "Loaded invalid blob type value, ignoring it";
      ((zzp.zza)localObject3).zzfg((String)localObject2);
    }
  }
  
  void zzb(String paramString, zzpz.zza[] paramArrayOfzza)
  {
    zzjv();
    zzjk();
    zzx.zzcM(paramString);
    zzx.zzz(paramArrayOfzza);
    SQLiteDatabase localSQLiteDatabase = getWritableDatabase();
    localSQLiteDatabase.beginTransaction();
    try
    {
      zzfb(paramString);
      int i = paramArrayOfzza.length;
      int j = 0;
      Object localObject1 = null;
      while (j < i)
      {
        zzpz.zza localzza = paramArrayOfzza[j];
        zza(paramString, localzza);
        j += 1;
      }
      localSQLiteDatabase.setTransactionSuccessful();
      return;
    }
    finally
    {
      localSQLiteDatabase.endTransaction();
    }
  }
  
  public void zzd(String paramString, byte[] paramArrayOfByte)
  {
    zzx.zzcM(paramString);
    zzjk();
    zzjv();
    Object localObject1 = new android/content/ContentValues;
    ((ContentValues)localObject1).<init>();
    Object localObject2 = "remote_config";
    ((ContentValues)localObject1).put((String)localObject2, paramArrayOfByte);
    try
    {
      localObject2 = getWritableDatabase();
      str1 = "apps";
      String str2 = "app_id = ?";
      int i = 1;
      String[] arrayOfString = new String[i];
      arrayOfString[0] = paramString;
      long l1 = ((SQLiteDatabase)localObject2).update(str1, (ContentValues)localObject1, str2, arrayOfString);
      long l2 = 0L;
      boolean bool = l1 < l2;
      if (!bool)
      {
        localObject1 = zzAo();
        localObject1 = ((zzp)localObject1).zzCE();
        localObject2 = "Failed to update remote config (got 0)";
        ((zzp.zza)localObject1).zzfg((String)localObject2);
      }
      return;
    }
    catch (SQLiteException localSQLiteException)
    {
      for (;;)
      {
        localObject2 = zzAo().zzCE();
        String str1 = "Error storing remote config";
        ((zzp.zza)localObject2).zzj(str1, localSQLiteException);
      }
    }
  }
  
  /* Error */
  public List zzeX(String paramString)
  {
    // Byte code:
    //   0: aconst_null
    //   1: astore_2
    //   2: aload_1
    //   3: invokestatic 216	com/google/android/gms/common/internal/zzx:zzcM	(Ljava/lang/String;)Ljava/lang/String;
    //   6: pop
    //   7: aload_0
    //   8: invokevirtual 210	com/google/android/gms/measurement/internal/zze:zzjk	()V
    //   11: aload_0
    //   12: invokevirtual 207	com/google/android/gms/measurement/internal/zze:zzjv	()V
    //   15: new 603	java/util/ArrayList
    //   18: astore_3
    //   19: aload_3
    //   20: invokespecial 604	java/util/ArrayList:<init>	()V
    //   23: aload_0
    //   24: invokevirtual 167	com/google/android/gms/measurement/internal/zze:getWritableDatabase	()Landroid/database/sqlite/SQLiteDatabase;
    //   27: astore 4
    //   29: ldc_w 560
    //   32: astore 5
    //   34: iconst_3
    //   35: istore 6
    //   37: iload 6
    //   39: anewarray 289	java/lang/String
    //   42: astore 7
    //   44: iconst_0
    //   45: istore 8
    //   47: aconst_null
    //   48: astore 9
    //   50: ldc_w 849
    //   53: astore 10
    //   55: aload 7
    //   57: iconst_0
    //   58: aload 10
    //   60: aastore
    //   61: iconst_1
    //   62: istore 8
    //   64: ldc_w 566
    //   67: astore 10
    //   69: aload 7
    //   71: iload 8
    //   73: aload 10
    //   75: aastore
    //   76: iconst_2
    //   77: istore 8
    //   79: ldc_w 568
    //   82: astore 10
    //   84: aload 7
    //   86: iload 8
    //   88: aload 10
    //   90: aastore
    //   91: ldc_w 630
    //   94: astore 9
    //   96: iconst_1
    //   97: istore 11
    //   99: iload 11
    //   101: anewarray 289	java/lang/String
    //   104: astore 10
    //   106: aload 10
    //   108: iconst_0
    //   109: aload_1
    //   110: aastore
    //   111: aconst_null
    //   112: astore 12
    //   114: ldc_w 897
    //   117: astore 13
    //   119: aload_0
    //   120: invokevirtual 375	com/google/android/gms/measurement/internal/zze:zzCp	()Lcom/google/android/gms/measurement/internal/zzd;
    //   123: astore 14
    //   125: aload 14
    //   127: invokevirtual 957	com/google/android/gms/measurement/internal/zzd:zzBM	()I
    //   130: istore 15
    //   132: iload 15
    //   134: invokestatic 411	java/lang/String:valueOf	(I)Ljava/lang/String;
    //   137: astore 14
    //   139: aload 4
    //   141: aload 5
    //   143: aload 7
    //   145: aload 9
    //   147: aload 10
    //   149: aconst_null
    //   150: aconst_null
    //   151: aload 13
    //   153: aload 14
    //   155: invokevirtual 902	android/database/sqlite/SQLiteDatabase:query	(Ljava/lang/String;[Ljava/lang/String;Ljava/lang/String;[Ljava/lang/String;Ljava/lang/String;Ljava/lang/String;Ljava/lang/String;Ljava/lang/String;)Landroid/database/Cursor;
    //   158: astore 13
    //   160: aload 13
    //   162: invokeinterface 176 1 0
    //   167: istore 16
    //   169: iload 16
    //   171: ifne +21 -> 192
    //   174: aload 13
    //   176: ifnull +10 -> 186
    //   179: aload 13
    //   181: invokeinterface 184 1 0
    //   186: aload_3
    //   187: astore 4
    //   189: aload 4
    //   191: areturn
    //   192: iconst_0
    //   193: istore 16
    //   195: aconst_null
    //   196: astore 4
    //   198: aload 13
    //   200: iconst_0
    //   201: invokeinterface 459 2 0
    //   206: astore 9
    //   208: iconst_1
    //   209: istore 16
    //   211: aload 13
    //   213: iload 16
    //   215: invokeinterface 180 2 0
    //   220: lstore 17
    //   222: iconst_2
    //   223: istore 16
    //   225: aload_0
    //   226: aload 13
    //   228: iload 16
    //   230: invokevirtual 571	com/google/android/gms/measurement/internal/zze:zzb	(Landroid/database/Cursor;I)Ljava/lang/Object;
    //   233: astore 12
    //   235: aload 12
    //   237: ifnonnull +60 -> 297
    //   240: aload_0
    //   241: invokevirtual 188	com/google/android/gms/measurement/internal/zze:zzAo	()Lcom/google/android/gms/measurement/internal/zzp;
    //   244: astore 4
    //   246: aload 4
    //   248: invokevirtual 194	com/google/android/gms/measurement/internal/zzp:zzCE	()Lcom/google/android/gms/measurement/internal/zzp$zza;
    //   251: astore 4
    //   253: ldc_w 1015
    //   256: astore 5
    //   258: aload 4
    //   260: aload 5
    //   262: invokevirtual 243	com/google/android/gms/measurement/internal/zzp$zza:zzfg	(Ljava/lang/String;)V
    //   265: aload 13
    //   267: invokeinterface 550 1 0
    //   272: istore 16
    //   274: iload 16
    //   276: ifne -84 -> 192
    //   279: aload 13
    //   281: ifnull +10 -> 291
    //   284: aload 13
    //   286: invokeinterface 184 1 0
    //   291: aload_3
    //   292: astore 4
    //   294: goto -105 -> 189
    //   297: new 573	com/google/android/gms/measurement/internal/zzai
    //   300: astore 5
    //   302: aload_1
    //   303: astore 7
    //   305: aload 5
    //   307: aload_1
    //   308: aload 9
    //   310: lload 17
    //   312: aload 12
    //   314: invokespecial 576	com/google/android/gms/measurement/internal/zzai:<init>	(Ljava/lang/String;Ljava/lang/String;JLjava/lang/Object;)V
    //   317: aload_3
    //   318: aload 5
    //   320: invokeinterface 608 2 0
    //   325: pop
    //   326: goto -61 -> 265
    //   329: astore 4
    //   331: aload 13
    //   333: astore 5
    //   335: aload_0
    //   336: invokevirtual 188	com/google/android/gms/measurement/internal/zze:zzAo	()Lcom/google/android/gms/measurement/internal/zzp;
    //   339: astore 7
    //   341: aload 7
    //   343: invokevirtual 194	com/google/android/gms/measurement/internal/zzp:zzCE	()Lcom/google/android/gms/measurement/internal/zzp$zza;
    //   346: astore 7
    //   348: ldc_w 1017
    //   351: astore 9
    //   353: aload 7
    //   355: aload 9
    //   357: aload_1
    //   358: aload 4
    //   360: invokevirtual 202	com/google/android/gms/measurement/internal/zzp$zza:zze	(Ljava/lang/String;Ljava/lang/Object;Ljava/lang/Object;)V
    //   363: aload 5
    //   365: ifnull +10 -> 375
    //   368: aload 5
    //   370: invokeinterface 184 1 0
    //   375: iconst_0
    //   376: istore 16
    //   378: aconst_null
    //   379: astore 4
    //   381: goto -192 -> 189
    //   384: astore 4
    //   386: aload_2
    //   387: ifnull +9 -> 396
    //   390: aload_2
    //   391: invokeinterface 184 1 0
    //   396: aload 4
    //   398: athrow
    //   399: astore 4
    //   401: aload 13
    //   403: astore_2
    //   404: goto -18 -> 386
    //   407: astore 4
    //   409: aload 5
    //   411: astore_2
    //   412: goto -26 -> 386
    //   415: astore 4
    //   417: aconst_null
    //   418: astore 5
    //   420: goto -85 -> 335
    // Local variable table:
    //   start	length	slot	name	signature
    //   0	423	0	this	zze
    //   0	423	1	paramString	String
    //   1	411	2	localObject1	Object
    //   18	300	3	localArrayList	java.util.ArrayList
    //   27	266	4	localObject2	Object
    //   329	30	4	localSQLiteException1	SQLiteException
    //   379	1	4	localObject3	Object
    //   384	13	4	localObject4	Object
    //   399	1	4	localObject5	Object
    //   407	1	4	localObject6	Object
    //   415	1	4	localSQLiteException2	SQLiteException
    //   32	387	5	localObject7	Object
    //   35	3	6	i	int
    //   42	312	7	localObject8	Object
    //   45	42	8	j	int
    //   48	308	9	str	String
    //   53	95	10	localObject9	Object
    //   97	3	11	k	int
    //   112	201	12	localObject10	Object
    //   117	285	13	localObject11	Object
    //   123	31	14	localObject12	Object
    //   130	3	15	m	int
    //   167	47	16	n	int
    //   223	6	16	i1	int
    //   272	105	16	bool	boolean
    //   220	91	17	l	long
    // Exception table:
    //   from	to	target	type
    //   160	167	329	android/database/sqlite/SQLiteException
    //   200	206	329	android/database/sqlite/SQLiteException
    //   213	220	329	android/database/sqlite/SQLiteException
    //   228	233	329	android/database/sqlite/SQLiteException
    //   240	244	329	android/database/sqlite/SQLiteException
    //   246	251	329	android/database/sqlite/SQLiteException
    //   260	265	329	android/database/sqlite/SQLiteException
    //   265	272	329	android/database/sqlite/SQLiteException
    //   297	300	329	android/database/sqlite/SQLiteException
    //   312	317	329	android/database/sqlite/SQLiteException
    //   318	326	329	android/database/sqlite/SQLiteException
    //   23	27	384	finally
    //   37	42	384	finally
    //   58	61	384	finally
    //   73	76	384	finally
    //   88	91	384	finally
    //   99	104	384	finally
    //   109	111	384	finally
    //   119	123	384	finally
    //   125	130	384	finally
    //   132	137	384	finally
    //   153	158	384	finally
    //   160	167	399	finally
    //   200	206	399	finally
    //   213	220	399	finally
    //   228	233	399	finally
    //   240	244	399	finally
    //   246	251	399	finally
    //   260	265	399	finally
    //   265	272	399	finally
    //   297	300	399	finally
    //   312	317	399	finally
    //   318	326	399	finally
    //   335	339	407	finally
    //   341	346	407	finally
    //   358	363	407	finally
    //   23	27	415	android/database/sqlite/SQLiteException
    //   37	42	415	android/database/sqlite/SQLiteException
    //   58	61	415	android/database/sqlite/SQLiteException
    //   73	76	415	android/database/sqlite/SQLiteException
    //   88	91	415	android/database/sqlite/SQLiteException
    //   99	104	415	android/database/sqlite/SQLiteException
    //   109	111	415	android/database/sqlite/SQLiteException
    //   119	123	415	android/database/sqlite/SQLiteException
    //   125	130	415	android/database/sqlite/SQLiteException
    //   132	137	415	android/database/sqlite/SQLiteException
    //   153	158	415	android/database/sqlite/SQLiteException
  }
  
  /* Error */
  public zza zzeY(String paramString)
  {
    // Byte code:
    //   0: iconst_1
    //   1: istore_2
    //   2: aload_1
    //   3: invokestatic 216	com/google/android/gms/common/internal/zzx:zzcM	(Ljava/lang/String;)Ljava/lang/String;
    //   6: pop
    //   7: aload_0
    //   8: invokevirtual 210	com/google/android/gms/measurement/internal/zze:zzjk	()V
    //   11: aload_0
    //   12: invokevirtual 207	com/google/android/gms/measurement/internal/zze:zzjv	()V
    //   15: aload_0
    //   16: invokevirtual 167	com/google/android/gms/measurement/internal/zze:getWritableDatabase	()Landroid/database/sqlite/SQLiteDatabase;
    //   19: astore_3
    //   20: ldc_w 628
    //   23: astore 4
    //   25: bipush 17
    //   27: istore 5
    //   29: iload 5
    //   31: anewarray 289	java/lang/String
    //   34: astore 6
    //   36: iconst_0
    //   37: istore 7
    //   39: aconst_null
    //   40: astore 8
    //   42: ldc_w 718
    //   45: astore 9
    //   47: aload 6
    //   49: iconst_0
    //   50: aload 9
    //   52: aastore
    //   53: iconst_1
    //   54: istore 7
    //   56: ldc_w 723
    //   59: astore 9
    //   61: aload 6
    //   63: iload 7
    //   65: aload 9
    //   67: aastore
    //   68: iconst_2
    //   69: istore 7
    //   71: ldc_w 728
    //   74: astore 9
    //   76: aload 6
    //   78: iload 7
    //   80: aload 9
    //   82: aastore
    //   83: iconst_3
    //   84: istore 7
    //   86: ldc_w 733
    //   89: astore 9
    //   91: aload 6
    //   93: iload 7
    //   95: aload 9
    //   97: aastore
    //   98: iconst_4
    //   99: istore 7
    //   101: ldc 47
    //   103: astore 9
    //   105: aload 6
    //   107: iload 7
    //   109: aload 9
    //   111: aastore
    //   112: iconst_5
    //   113: istore 7
    //   115: ldc_w 741
    //   118: astore 9
    //   120: aload 6
    //   122: iload 7
    //   124: aload 9
    //   126: aastore
    //   127: bipush 6
    //   129: istore 7
    //   131: ldc 21
    //   133: astore 9
    //   135: aload 6
    //   137: iload 7
    //   139: aload 9
    //   141: aastore
    //   142: bipush 7
    //   144: istore 7
    //   146: ldc 31
    //   148: astore 9
    //   150: aload 6
    //   152: iload 7
    //   154: aload 9
    //   156: aastore
    //   157: bipush 8
    //   159: istore 7
    //   161: ldc 35
    //   163: astore 9
    //   165: aload 6
    //   167: iload 7
    //   169: aload 9
    //   171: aastore
    //   172: bipush 9
    //   174: istore 7
    //   176: ldc 39
    //   178: astore 9
    //   180: aload 6
    //   182: iload 7
    //   184: aload 9
    //   186: aastore
    //   187: bipush 10
    //   189: istore 7
    //   191: ldc 43
    //   193: astore 9
    //   195: aload 6
    //   197: iload 7
    //   199: aload 9
    //   201: aastore
    //   202: bipush 11
    //   204: istore 7
    //   206: ldc 51
    //   208: astore 9
    //   210: aload 6
    //   212: iload 7
    //   214: aload 9
    //   216: aastore
    //   217: bipush 12
    //   219: istore 7
    //   221: ldc 55
    //   223: astore 9
    //   225: aload 6
    //   227: iload 7
    //   229: aload 9
    //   231: aastore
    //   232: bipush 13
    //   234: istore 7
    //   236: ldc 59
    //   238: astore 9
    //   240: aload 6
    //   242: iload 7
    //   244: aload 9
    //   246: aastore
    //   247: bipush 14
    //   249: istore 7
    //   251: ldc 63
    //   253: astore 9
    //   255: aload 6
    //   257: iload 7
    //   259: aload 9
    //   261: aastore
    //   262: bipush 15
    //   264: istore 7
    //   266: ldc 71
    //   268: astore 9
    //   270: aload 6
    //   272: iload 7
    //   274: aload 9
    //   276: aastore
    //   277: bipush 16
    //   279: istore 7
    //   281: ldc 75
    //   283: astore 9
    //   285: aload 6
    //   287: iload 7
    //   289: aload 9
    //   291: aastore
    //   292: ldc_w 630
    //   295: astore 8
    //   297: iconst_1
    //   298: istore 10
    //   300: iload 10
    //   302: anewarray 289	java/lang/String
    //   305: astore 9
    //   307: aload 9
    //   309: iconst_0
    //   310: aload_1
    //   311: aastore
    //   312: aload_3
    //   313: aload 4
    //   315: aload 6
    //   317: aload 8
    //   319: aload 9
    //   321: aconst_null
    //   322: aconst_null
    //   323: aconst_null
    //   324: invokevirtual 433	android/database/sqlite/SQLiteDatabase:query	(Ljava/lang/String;[Ljava/lang/String;Ljava/lang/String;[Ljava/lang/String;Ljava/lang/String;Ljava/lang/String;Ljava/lang/String;)Landroid/database/Cursor;
    //   327: astore 4
    //   329: aload 4
    //   331: invokeinterface 176 1 0
    //   336: istore 11
    //   338: iload 11
    //   340: ifne +22 -> 362
    //   343: aload 4
    //   345: ifnull +10 -> 355
    //   348: aload 4
    //   350: invokeinterface 184 1 0
    //   355: iconst_0
    //   356: istore 11
    //   358: aconst_null
    //   359: astore_3
    //   360: aload_3
    //   361: areturn
    //   362: new 713	com/google/android/gms/measurement/internal/zza
    //   365: astore_3
    //   366: aload_0
    //   367: getfield 1031	com/google/android/gms/measurement/internal/zze:zzaTV	Lcom/google/android/gms/measurement/internal/zzw;
    //   370: astore 6
    //   372: aload_3
    //   373: aload 6
    //   375: aload_1
    //   376: invokespecial 1034	com/google/android/gms/measurement/internal/zza:<init>	(Lcom/google/android/gms/measurement/internal/zzw;Ljava/lang/String;)V
    //   379: iconst_0
    //   380: istore 5
    //   382: aconst_null
    //   383: astore 6
    //   385: aload 4
    //   387: iconst_0
    //   388: invokeinterface 459 2 0
    //   393: astore 6
    //   395: aload_3
    //   396: aload 6
    //   398: invokevirtual 1037	com/google/android/gms/measurement/internal/zza:zzeM	(Ljava/lang/String;)V
    //   401: iconst_1
    //   402: istore 5
    //   404: aload 4
    //   406: iload 5
    //   408: invokeinterface 459 2 0
    //   413: astore 6
    //   415: aload_3
    //   416: aload 6
    //   418: invokevirtual 1040	com/google/android/gms/measurement/internal/zza:zzeN	(Ljava/lang/String;)V
    //   421: iconst_2
    //   422: istore 5
    //   424: aload 4
    //   426: iload 5
    //   428: invokeinterface 459 2 0
    //   433: astore 6
    //   435: aload_3
    //   436: aload 6
    //   438: invokevirtual 1043	com/google/android/gms/measurement/internal/zza:zzeO	(Ljava/lang/String;)V
    //   441: iconst_3
    //   442: istore 5
    //   444: aload 4
    //   446: iload 5
    //   448: invokeinterface 180 2 0
    //   453: lstore 12
    //   455: aload_3
    //   456: lload 12
    //   458: invokevirtual 1046	com/google/android/gms/measurement/internal/zza:zzS	(J)V
    //   461: iconst_4
    //   462: istore 5
    //   464: aload 4
    //   466: iload 5
    //   468: invokeinterface 180 2 0
    //   473: lstore 12
    //   475: aload_3
    //   476: lload 12
    //   478: invokevirtual 1049	com/google/android/gms/measurement/internal/zza:zzO	(J)V
    //   481: iconst_5
    //   482: istore 5
    //   484: aload 4
    //   486: iload 5
    //   488: invokeinterface 180 2 0
    //   493: lstore 12
    //   495: aload_3
    //   496: lload 12
    //   498: invokevirtual 1052	com/google/android/gms/measurement/internal/zza:zzP	(J)V
    //   501: bipush 6
    //   503: istore 5
    //   505: aload 4
    //   507: iload 5
    //   509: invokeinterface 459 2 0
    //   514: astore 6
    //   516: aload_3
    //   517: aload 6
    //   519: invokevirtual 1055	com/google/android/gms/measurement/internal/zza:setAppVersion	(Ljava/lang/String;)V
    //   522: bipush 7
    //   524: istore 5
    //   526: aload 4
    //   528: iload 5
    //   530: invokeinterface 459 2 0
    //   535: astore 6
    //   537: aload_3
    //   538: aload 6
    //   540: invokevirtual 1058	com/google/android/gms/measurement/internal/zza:zzeP	(Ljava/lang/String;)V
    //   543: bipush 8
    //   545: istore 5
    //   547: aload 4
    //   549: iload 5
    //   551: invokeinterface 180 2 0
    //   556: lstore 12
    //   558: aload_3
    //   559: lload 12
    //   561: invokevirtual 1061	com/google/android/gms/measurement/internal/zza:zzQ	(J)V
    //   564: bipush 9
    //   566: istore 5
    //   568: aload 4
    //   570: iload 5
    //   572: invokeinterface 180 2 0
    //   577: lstore 12
    //   579: aload_3
    //   580: lload 12
    //   582: invokevirtual 1064	com/google/android/gms/measurement/internal/zza:zzR	(J)V
    //   585: bipush 10
    //   587: istore 5
    //   589: aload 4
    //   591: iload 5
    //   593: invokeinterface 1067 2 0
    //   598: istore 5
    //   600: iload 5
    //   602: ifeq +204 -> 806
    //   605: iload_2
    //   606: istore 5
    //   608: iload 5
    //   610: ifeq +214 -> 824
    //   613: iload_2
    //   614: istore 5
    //   616: aload_3
    //   617: iload 5
    //   619: invokevirtual 1071	com/google/android/gms/measurement/internal/zza:setMeasurementEnabled	(Z)V
    //   622: bipush 11
    //   624: istore 5
    //   626: aload 4
    //   628: iload 5
    //   630: invokeinterface 180 2 0
    //   635: lstore 12
    //   637: aload_3
    //   638: lload 12
    //   640: invokevirtual 1074	com/google/android/gms/measurement/internal/zza:zzV	(J)V
    //   643: bipush 12
    //   645: istore 5
    //   647: aload 4
    //   649: iload 5
    //   651: invokeinterface 180 2 0
    //   656: lstore 12
    //   658: aload_3
    //   659: lload 12
    //   661: invokevirtual 1077	com/google/android/gms/measurement/internal/zza:zzW	(J)V
    //   664: bipush 13
    //   666: istore 5
    //   668: aload 4
    //   670: iload 5
    //   672: invokeinterface 180 2 0
    //   677: lstore 12
    //   679: aload_3
    //   680: lload 12
    //   682: invokevirtual 1080	com/google/android/gms/measurement/internal/zza:zzX	(J)V
    //   685: bipush 14
    //   687: istore 5
    //   689: aload 4
    //   691: iload 5
    //   693: invokeinterface 180 2 0
    //   698: lstore 12
    //   700: aload_3
    //   701: lload 12
    //   703: invokevirtual 1083	com/google/android/gms/measurement/internal/zza:zzY	(J)V
    //   706: bipush 15
    //   708: istore 5
    //   710: aload 4
    //   712: iload 5
    //   714: invokeinterface 180 2 0
    //   719: lstore 12
    //   721: aload_3
    //   722: lload 12
    //   724: invokevirtual 1086	com/google/android/gms/measurement/internal/zza:zzT	(J)V
    //   727: bipush 16
    //   729: istore 5
    //   731: aload 4
    //   733: iload 5
    //   735: invokeinterface 180 2 0
    //   740: lstore 12
    //   742: aload_3
    //   743: lload 12
    //   745: invokevirtual 1089	com/google/android/gms/measurement/internal/zza:zzU	(J)V
    //   748: aload_3
    //   749: invokevirtual 1092	com/google/android/gms/measurement/internal/zza:zzBi	()V
    //   752: aload 4
    //   754: invokeinterface 550 1 0
    //   759: istore 5
    //   761: iload 5
    //   763: ifeq +28 -> 791
    //   766: aload_0
    //   767: invokevirtual 188	com/google/android/gms/measurement/internal/zze:zzAo	()Lcom/google/android/gms/measurement/internal/zzp;
    //   770: astore 6
    //   772: aload 6
    //   774: invokevirtual 194	com/google/android/gms/measurement/internal/zzp:zzCE	()Lcom/google/android/gms/measurement/internal/zzp$zza;
    //   777: astore 6
    //   779: ldc_w 1094
    //   782: astore 8
    //   784: aload 6
    //   786: aload 8
    //   788: invokevirtual 243	com/google/android/gms/measurement/internal/zzp$zza:zzfg	(Ljava/lang/String;)V
    //   791: aload 4
    //   793: ifnull -433 -> 360
    //   796: aload 4
    //   798: invokeinterface 184 1 0
    //   803: goto -443 -> 360
    //   806: bipush 10
    //   808: istore 5
    //   810: aload 4
    //   812: iload 5
    //   814: invokeinterface 597 2 0
    //   819: istore 5
    //   821: goto -213 -> 608
    //   824: iconst_0
    //   825: istore 5
    //   827: aconst_null
    //   828: astore 6
    //   830: goto -214 -> 616
    //   833: astore_3
    //   834: aconst_null
    //   835: astore 4
    //   837: aload_0
    //   838: invokevirtual 188	com/google/android/gms/measurement/internal/zze:zzAo	()Lcom/google/android/gms/measurement/internal/zzp;
    //   841: astore 6
    //   843: aload 6
    //   845: invokevirtual 194	com/google/android/gms/measurement/internal/zzp:zzCE	()Lcom/google/android/gms/measurement/internal/zzp$zza;
    //   848: astore 6
    //   850: ldc_w 1096
    //   853: astore 8
    //   855: aload 6
    //   857: aload 8
    //   859: aload_1
    //   860: aload_3
    //   861: invokevirtual 202	com/google/android/gms/measurement/internal/zzp$zza:zze	(Ljava/lang/String;Ljava/lang/Object;Ljava/lang/Object;)V
    //   864: aload 4
    //   866: ifnull +10 -> 876
    //   869: aload 4
    //   871: invokeinterface 184 1 0
    //   876: iconst_0
    //   877: istore 11
    //   879: aconst_null
    //   880: astore_3
    //   881: goto -521 -> 360
    //   884: astore_3
    //   885: aconst_null
    //   886: astore 4
    //   888: aload 4
    //   890: ifnull +10 -> 900
    //   893: aload 4
    //   895: invokeinterface 184 1 0
    //   900: aload_3
    //   901: athrow
    //   902: astore_3
    //   903: goto -15 -> 888
    //   906: astore_3
    //   907: goto -70 -> 837
    // Local variable table:
    //   start	length	slot	name	signature
    //   0	910	0	this	zze
    //   0	910	1	paramString	String
    //   1	613	2	bool1	boolean
    //   19	730	3	localObject1	Object
    //   833	28	3	localSQLiteException1	SQLiteException
    //   880	1	3	localObject2	Object
    //   884	17	3	localObject3	Object
    //   902	1	3	localObject4	Object
    //   906	1	3	localSQLiteException2	SQLiteException
    //   23	871	4	localObject5	Object
    //   27	565	5	i	int
    //   598	20	5	bool2	boolean
    //   624	110	5	j	int
    //   759	3	5	bool3	boolean
    //   808	18	5	k	int
    //   34	822	6	localObject6	Object
    //   37	251	7	m	int
    //   40	818	8	str	String
    //   45	275	9	localObject7	Object
    //   298	3	10	n	int
    //   336	542	11	bool4	boolean
    //   453	291	12	l	long
    // Exception table:
    //   from	to	target	type
    //   15	19	833	android/database/sqlite/SQLiteException
    //   29	34	833	android/database/sqlite/SQLiteException
    //   50	53	833	android/database/sqlite/SQLiteException
    //   65	68	833	android/database/sqlite/SQLiteException
    //   80	83	833	android/database/sqlite/SQLiteException
    //   95	98	833	android/database/sqlite/SQLiteException
    //   109	112	833	android/database/sqlite/SQLiteException
    //   124	127	833	android/database/sqlite/SQLiteException
    //   139	142	833	android/database/sqlite/SQLiteException
    //   154	157	833	android/database/sqlite/SQLiteException
    //   169	172	833	android/database/sqlite/SQLiteException
    //   184	187	833	android/database/sqlite/SQLiteException
    //   199	202	833	android/database/sqlite/SQLiteException
    //   214	217	833	android/database/sqlite/SQLiteException
    //   229	232	833	android/database/sqlite/SQLiteException
    //   244	247	833	android/database/sqlite/SQLiteException
    //   259	262	833	android/database/sqlite/SQLiteException
    //   274	277	833	android/database/sqlite/SQLiteException
    //   289	292	833	android/database/sqlite/SQLiteException
    //   300	305	833	android/database/sqlite/SQLiteException
    //   310	312	833	android/database/sqlite/SQLiteException
    //   323	327	833	android/database/sqlite/SQLiteException
    //   15	19	884	finally
    //   29	34	884	finally
    //   50	53	884	finally
    //   65	68	884	finally
    //   80	83	884	finally
    //   95	98	884	finally
    //   109	112	884	finally
    //   124	127	884	finally
    //   139	142	884	finally
    //   154	157	884	finally
    //   169	172	884	finally
    //   184	187	884	finally
    //   199	202	884	finally
    //   214	217	884	finally
    //   229	232	884	finally
    //   244	247	884	finally
    //   259	262	884	finally
    //   274	277	884	finally
    //   289	292	884	finally
    //   300	305	884	finally
    //   310	312	884	finally
    //   323	327	884	finally
    //   329	336	902	finally
    //   362	365	902	finally
    //   366	370	902	finally
    //   375	379	902	finally
    //   387	393	902	finally
    //   396	401	902	finally
    //   406	413	902	finally
    //   416	421	902	finally
    //   426	433	902	finally
    //   436	441	902	finally
    //   446	453	902	finally
    //   456	461	902	finally
    //   466	473	902	finally
    //   476	481	902	finally
    //   486	493	902	finally
    //   496	501	902	finally
    //   507	514	902	finally
    //   517	522	902	finally
    //   528	535	902	finally
    //   538	543	902	finally
    //   549	556	902	finally
    //   559	564	902	finally
    //   570	577	902	finally
    //   580	585	902	finally
    //   591	598	902	finally
    //   617	622	902	finally
    //   628	635	902	finally
    //   638	643	902	finally
    //   649	656	902	finally
    //   659	664	902	finally
    //   670	677	902	finally
    //   680	685	902	finally
    //   691	698	902	finally
    //   701	706	902	finally
    //   712	719	902	finally
    //   722	727	902	finally
    //   733	740	902	finally
    //   743	748	902	finally
    //   748	752	902	finally
    //   752	759	902	finally
    //   766	770	902	finally
    //   772	777	902	finally
    //   786	791	902	finally
    //   812	819	902	finally
    //   837	841	902	finally
    //   843	848	902	finally
    //   860	864	902	finally
    //   329	336	906	android/database/sqlite/SQLiteException
    //   362	365	906	android/database/sqlite/SQLiteException
    //   366	370	906	android/database/sqlite/SQLiteException
    //   375	379	906	android/database/sqlite/SQLiteException
    //   387	393	906	android/database/sqlite/SQLiteException
    //   396	401	906	android/database/sqlite/SQLiteException
    //   406	413	906	android/database/sqlite/SQLiteException
    //   416	421	906	android/database/sqlite/SQLiteException
    //   426	433	906	android/database/sqlite/SQLiteException
    //   436	441	906	android/database/sqlite/SQLiteException
    //   446	453	906	android/database/sqlite/SQLiteException
    //   456	461	906	android/database/sqlite/SQLiteException
    //   466	473	906	android/database/sqlite/SQLiteException
    //   476	481	906	android/database/sqlite/SQLiteException
    //   486	493	906	android/database/sqlite/SQLiteException
    //   496	501	906	android/database/sqlite/SQLiteException
    //   507	514	906	android/database/sqlite/SQLiteException
    //   517	522	906	android/database/sqlite/SQLiteException
    //   528	535	906	android/database/sqlite/SQLiteException
    //   538	543	906	android/database/sqlite/SQLiteException
    //   549	556	906	android/database/sqlite/SQLiteException
    //   559	564	906	android/database/sqlite/SQLiteException
    //   570	577	906	android/database/sqlite/SQLiteException
    //   580	585	906	android/database/sqlite/SQLiteException
    //   591	598	906	android/database/sqlite/SQLiteException
    //   617	622	906	android/database/sqlite/SQLiteException
    //   628	635	906	android/database/sqlite/SQLiteException
    //   638	643	906	android/database/sqlite/SQLiteException
    //   649	656	906	android/database/sqlite/SQLiteException
    //   659	664	906	android/database/sqlite/SQLiteException
    //   670	677	906	android/database/sqlite/SQLiteException
    //   680	685	906	android/database/sqlite/SQLiteException
    //   691	698	906	android/database/sqlite/SQLiteException
    //   701	706	906	android/database/sqlite/SQLiteException
    //   712	719	906	android/database/sqlite/SQLiteException
    //   722	727	906	android/database/sqlite/SQLiteException
    //   733	740	906	android/database/sqlite/SQLiteException
    //   743	748	906	android/database/sqlite/SQLiteException
    //   748	752	906	android/database/sqlite/SQLiteException
    //   752	759	906	android/database/sqlite/SQLiteException
    //   766	770	906	android/database/sqlite/SQLiteException
    //   772	777	906	android/database/sqlite/SQLiteException
    //   786	791	906	android/database/sqlite/SQLiteException
    //   812	819	906	android/database/sqlite/SQLiteException
  }
  
  public long zzeZ(String paramString)
  {
    zzx.zzcM(paramString);
    zzjk();
    zzjv();
    try
    {
      SQLiteDatabase localSQLiteDatabase = getWritableDatabase();
      localObject = zzCp();
      int i = ((zzd)localObject).zzeW(paramString);
      localObject = String.valueOf(i);
      str1 = "raw_events";
      String str2 = "rowid in (select rowid from raw_events where app_id=? order by rowid desc limit -1 offset ?)";
      int j = 2;
      String[] arrayOfString = new String[j];
      int k = 0;
      arrayOfString[0] = paramString;
      k = 1;
      arrayOfString[k] = localObject;
      int m = localSQLiteDatabase.delete(str1, str2, arrayOfString);
      l = m;
    }
    catch (SQLiteException localSQLiteException)
    {
      for (;;)
      {
        Object localObject = zzAo().zzCE();
        String str1 = "Error deleting over the limit events";
        ((zzp.zza)localObject).zzj(str1, localSQLiteException);
        long l = 0L;
      }
    }
    return l;
  }
  
  /* Error */
  public byte[] zzfa(String paramString)
  {
    // Byte code:
    //   0: aload_1
    //   1: invokestatic 216	com/google/android/gms/common/internal/zzx:zzcM	(Ljava/lang/String;)Ljava/lang/String;
    //   4: pop
    //   5: aload_0
    //   6: invokevirtual 210	com/google/android/gms/measurement/internal/zze:zzjk	()V
    //   9: aload_0
    //   10: invokevirtual 207	com/google/android/gms/measurement/internal/zze:zzjv	()V
    //   13: aload_0
    //   14: invokevirtual 167	com/google/android/gms/measurement/internal/zze:getWritableDatabase	()Landroid/database/sqlite/SQLiteDatabase;
    //   17: astore_2
    //   18: ldc_w 628
    //   21: astore_3
    //   22: iconst_1
    //   23: istore 4
    //   25: iload 4
    //   27: anewarray 289	java/lang/String
    //   30: astore 5
    //   32: aconst_null
    //   33: astore 6
    //   35: ldc 67
    //   37: astore 7
    //   39: aload 5
    //   41: iconst_0
    //   42: aload 7
    //   44: aastore
    //   45: ldc_w 630
    //   48: astore 6
    //   50: iconst_1
    //   51: istore 8
    //   53: iload 8
    //   55: anewarray 289	java/lang/String
    //   58: astore 7
    //   60: aload 7
    //   62: iconst_0
    //   63: aload_1
    //   64: aastore
    //   65: aload_2
    //   66: aload_3
    //   67: aload 5
    //   69: aload 6
    //   71: aload 7
    //   73: aconst_null
    //   74: aconst_null
    //   75: aconst_null
    //   76: invokevirtual 433	android/database/sqlite/SQLiteDatabase:query	(Ljava/lang/String;[Ljava/lang/String;Ljava/lang/String;[Ljava/lang/String;Ljava/lang/String;Ljava/lang/String;Ljava/lang/String;)Landroid/database/Cursor;
    //   79: astore_3
    //   80: aload_3
    //   81: invokeinterface 176 1 0
    //   86: istore 9
    //   88: iload 9
    //   90: ifne +20 -> 110
    //   93: aload_3
    //   94: ifnull +9 -> 103
    //   97: aload_3
    //   98: invokeinterface 184 1 0
    //   103: iconst_0
    //   104: istore 9
    //   106: aconst_null
    //   107: astore_2
    //   108: aload_2
    //   109: areturn
    //   110: iconst_0
    //   111: istore 9
    //   113: aconst_null
    //   114: astore_2
    //   115: aload_3
    //   116: iconst_0
    //   117: invokeinterface 437 2 0
    //   122: astore_2
    //   123: aload_3
    //   124: invokeinterface 550 1 0
    //   129: istore 4
    //   131: iload 4
    //   133: ifeq +28 -> 161
    //   136: aload_0
    //   137: invokevirtual 188	com/google/android/gms/measurement/internal/zze:zzAo	()Lcom/google/android/gms/measurement/internal/zzp;
    //   140: astore 5
    //   142: aload 5
    //   144: invokevirtual 194	com/google/android/gms/measurement/internal/zzp:zzCE	()Lcom/google/android/gms/measurement/internal/zzp$zza;
    //   147: astore 5
    //   149: ldc_w 1106
    //   152: astore 6
    //   154: aload 5
    //   156: aload 6
    //   158: invokevirtual 243	com/google/android/gms/measurement/internal/zzp$zza:zzfg	(Ljava/lang/String;)V
    //   161: aload_3
    //   162: ifnull -54 -> 108
    //   165: aload_3
    //   166: invokeinterface 184 1 0
    //   171: goto -63 -> 108
    //   174: astore_2
    //   175: aconst_null
    //   176: astore_3
    //   177: aload_0
    //   178: invokevirtual 188	com/google/android/gms/measurement/internal/zze:zzAo	()Lcom/google/android/gms/measurement/internal/zzp;
    //   181: astore 5
    //   183: aload 5
    //   185: invokevirtual 194	com/google/android/gms/measurement/internal/zzp:zzCE	()Lcom/google/android/gms/measurement/internal/zzp$zza;
    //   188: astore 5
    //   190: ldc_w 1108
    //   193: astore 6
    //   195: aload 5
    //   197: aload 6
    //   199: aload_1
    //   200: aload_2
    //   201: invokevirtual 202	com/google/android/gms/measurement/internal/zzp$zza:zze	(Ljava/lang/String;Ljava/lang/Object;Ljava/lang/Object;)V
    //   204: aload_3
    //   205: ifnull +9 -> 214
    //   208: aload_3
    //   209: invokeinterface 184 1 0
    //   214: iconst_0
    //   215: istore 9
    //   217: aconst_null
    //   218: astore_2
    //   219: goto -111 -> 108
    //   222: astore_2
    //   223: aconst_null
    //   224: astore_3
    //   225: aload_3
    //   226: ifnull +9 -> 235
    //   229: aload_3
    //   230: invokeinterface 184 1 0
    //   235: aload_2
    //   236: athrow
    //   237: astore_2
    //   238: goto -13 -> 225
    //   241: astore_2
    //   242: goto -65 -> 177
    // Local variable table:
    //   start	length	slot	name	signature
    //   0	245	0	this	zze
    //   0	245	1	paramString	String
    //   17	106	2	localObject1	Object
    //   174	27	2	localSQLiteException1	SQLiteException
    //   218	1	2	localObject2	Object
    //   222	14	2	localObject3	Object
    //   237	1	2	localObject4	Object
    //   241	1	2	localSQLiteException2	SQLiteException
    //   21	209	3	localObject5	Object
    //   23	109	4	bool1	boolean
    //   30	166	5	localObject6	Object
    //   33	165	6	str	String
    //   37	35	7	localObject7	Object
    //   51	3	8	i	int
    //   86	130	9	bool2	boolean
    // Exception table:
    //   from	to	target	type
    //   13	17	174	android/database/sqlite/SQLiteException
    //   25	30	174	android/database/sqlite/SQLiteException
    //   42	45	174	android/database/sqlite/SQLiteException
    //   53	58	174	android/database/sqlite/SQLiteException
    //   63	65	174	android/database/sqlite/SQLiteException
    //   75	79	174	android/database/sqlite/SQLiteException
    //   13	17	222	finally
    //   25	30	222	finally
    //   42	45	222	finally
    //   53	58	222	finally
    //   63	65	222	finally
    //   75	79	222	finally
    //   80	86	237	finally
    //   116	122	237	finally
    //   123	129	237	finally
    //   136	140	237	finally
    //   142	147	237	finally
    //   156	161	237	finally
    //   177	181	237	finally
    //   183	188	237	finally
    //   200	204	237	finally
    //   80	86	241	android/database/sqlite/SQLiteException
    //   116	122	241	android/database/sqlite/SQLiteException
    //   123	129	241	android/database/sqlite/SQLiteException
    //   136	140	241	android/database/sqlite/SQLiteException
    //   142	147	241	android/database/sqlite/SQLiteException
    //   156	161	241	android/database/sqlite/SQLiteException
  }
  
  void zzfb(String paramString)
  {
    int i = 1;
    zzjv();
    zzjk();
    zzx.zzcM(paramString);
    SQLiteDatabase localSQLiteDatabase = getWritableDatabase();
    String[] arrayOfString = new String[i];
    arrayOfString[0] = paramString;
    localSQLiteDatabase.delete("property_filters", "app_id=?", arrayOfString);
    arrayOfString = new String[i];
    arrayOfString[0] = paramString;
    localSQLiteDatabase.delete("event_filters", "app_id=?", arrayOfString);
  }
  
  public void zzfc(String paramString)
  {
    SQLiteDatabase localSQLiteDatabase = getWritableDatabase();
    Object localObject1 = "delete from raw_events_metadata where app_id=? and metadata_fingerprint not in (select distinct metadata_fingerprint from raw_events where app_id=?)";
    int i = 2;
    try
    {
      localObject2 = new String[i];
      int j = 0;
      localObject2[0] = paramString;
      j = 1;
      localObject2[j] = paramString;
      localSQLiteDatabase.execSQL((String)localObject1, (Object[])localObject2);
      return;
    }
    catch (SQLiteException localSQLiteException)
    {
      for (;;)
      {
        localObject1 = zzAo().zzCE();
        Object localObject2 = "Failed to remove unused event metadata";
        ((zzp.zza)localObject1).zzj((String)localObject2, localSQLiteException);
      }
    }
  }
  
  public long zzfd(String paramString)
  {
    zzx.zzcM(paramString);
    String[] arrayOfString = new String[1];
    arrayOfString[0] = paramString;
    return zza("select count(1) from events where app_id=? and name not like '!_%' escape '!'", arrayOfString, 0L);
  }
  
  protected void zziJ() {}
  
  /* Error */
  public List zzn(String paramString, int paramInt1, int paramInt2)
  {
    // Byte code:
    //   0: iconst_1
    //   1: istore 4
    //   3: aload_0
    //   4: invokevirtual 210	com/google/android/gms/measurement/internal/zze:zzjk	()V
    //   7: aload_0
    //   8: invokevirtual 207	com/google/android/gms/measurement/internal/zze:zzjv	()V
    //   11: iload_2
    //   12: ifle +177 -> 189
    //   15: iload 4
    //   17: istore 5
    //   19: iload 5
    //   21: invokestatic 1117	com/google/android/gms/common/internal/zzx:zzac	(Z)V
    //   24: iload_3
    //   25: ifle +173 -> 198
    //   28: iload 4
    //   30: invokestatic 1117	com/google/android/gms/common/internal/zzx:zzac	(Z)V
    //   33: aload_1
    //   34: invokestatic 216	com/google/android/gms/common/internal/zzx:zzcM	(Ljava/lang/String;)Ljava/lang/String;
    //   37: pop
    //   38: aload_0
    //   39: invokevirtual 167	com/google/android/gms/measurement/internal/zze:getWritableDatabase	()Landroid/database/sqlite/SQLiteDatabase;
    //   42: astore 6
    //   44: ldc_w 512
    //   47: astore 7
    //   49: iconst_2
    //   50: istore 8
    //   52: iload 8
    //   54: anewarray 289	java/lang/String
    //   57: astore 9
    //   59: iconst_0
    //   60: istore 10
    //   62: aconst_null
    //   63: astore 11
    //   65: ldc_w 897
    //   68: astore 12
    //   70: aload 9
    //   72: iconst_0
    //   73: aload 12
    //   75: aastore
    //   76: iconst_1
    //   77: istore 10
    //   79: ldc_w 328
    //   82: astore 12
    //   84: aload 9
    //   86: iload 10
    //   88: aload 12
    //   90: aastore
    //   91: ldc_w 630
    //   94: astore 11
    //   96: iconst_1
    //   97: istore 13
    //   99: iload 13
    //   101: anewarray 289	java/lang/String
    //   104: astore 12
    //   106: aconst_null
    //   107: astore 14
    //   109: aload 12
    //   111: iconst_0
    //   112: aload_1
    //   113: aastore
    //   114: aconst_null
    //   115: astore 14
    //   117: iconst_0
    //   118: istore 15
    //   120: aconst_null
    //   121: astore 16
    //   123: ldc_w 897
    //   126: astore 17
    //   128: iload_2
    //   129: invokestatic 411	java/lang/String:valueOf	(I)Ljava/lang/String;
    //   132: astore 18
    //   134: aload 6
    //   136: aload 7
    //   138: aload 9
    //   140: aload 11
    //   142: aload 12
    //   144: aconst_null
    //   145: aconst_null
    //   146: aload 17
    //   148: aload 18
    //   150: invokevirtual 902	android/database/sqlite/SQLiteDatabase:query	(Ljava/lang/String;[Ljava/lang/String;Ljava/lang/String;[Ljava/lang/String;Ljava/lang/String;Ljava/lang/String;Ljava/lang/String;Ljava/lang/String;)Landroid/database/Cursor;
    //   153: astore 9
    //   155: aload 9
    //   157: invokeinterface 176 1 0
    //   162: istore 5
    //   164: iload 5
    //   166: ifne +41 -> 207
    //   169: invokestatic 1121	java/util/Collections:emptyList	()Ljava/util/List;
    //   172: astore 6
    //   174: aload 9
    //   176: ifnull +10 -> 186
    //   179: aload 9
    //   181: invokeinterface 184 1 0
    //   186: aload 6
    //   188: areturn
    //   189: iconst_0
    //   190: istore 5
    //   192: aconst_null
    //   193: astore 6
    //   195: goto -176 -> 19
    //   198: iconst_0
    //   199: istore 4
    //   201: aconst_null
    //   202: astore 7
    //   204: goto -176 -> 28
    //   207: new 603	java/util/ArrayList
    //   210: astore 6
    //   212: aload 6
    //   214: invokespecial 604	java/util/ArrayList:<init>	()V
    //   217: iconst_0
    //   218: istore 10
    //   220: aconst_null
    //   221: astore 11
    //   223: iconst_0
    //   224: istore 4
    //   226: aconst_null
    //   227: astore 7
    //   229: aload 9
    //   231: iconst_0
    //   232: invokeinterface 180 2 0
    //   237: lstore 19
    //   239: iconst_1
    //   240: istore 4
    //   242: aload 9
    //   244: iload 4
    //   246: invokeinterface 437 2 0
    //   251: astore 7
    //   253: aload_0
    //   254: invokevirtual 691	com/google/android/gms/measurement/internal/zze:zzCk	()Lcom/google/android/gms/measurement/internal/zzaj;
    //   257: astore 16
    //   259: aload 16
    //   261: aload 7
    //   263: invokevirtual 1124	com/google/android/gms/measurement/internal/zzaj:zzp	([B)[B
    //   266: astore 7
    //   268: aload 6
    //   270: invokeinterface 1126 1 0
    //   275: istore 15
    //   277: iload 15
    //   279: ifne +93 -> 372
    //   282: aload 7
    //   284: arraylength
    //   285: iload 10
    //   287: iadd
    //   288: istore 15
    //   290: iload 15
    //   292: iload_3
    //   293: if_icmple +79 -> 372
    //   296: aload 9
    //   298: ifnull -112 -> 186
    //   301: aload 9
    //   303: invokeinterface 184 1 0
    //   308: goto -122 -> 186
    //   311: astore 7
    //   313: aload_0
    //   314: invokevirtual 188	com/google/android/gms/measurement/internal/zze:zzAo	()Lcom/google/android/gms/measurement/internal/zzp;
    //   317: astore 12
    //   319: aload 12
    //   321: invokevirtual 194	com/google/android/gms/measurement/internal/zzp:zzCE	()Lcom/google/android/gms/measurement/internal/zzp$zza;
    //   324: astore 12
    //   326: ldc_w 1128
    //   329: astore 14
    //   331: aload 12
    //   333: aload 14
    //   335: aload_1
    //   336: aload 7
    //   338: invokevirtual 202	com/google/android/gms/measurement/internal/zzp$zza:zze	(Ljava/lang/String;Ljava/lang/Object;Ljava/lang/Object;)V
    //   341: iload 10
    //   343: istore 4
    //   345: aload 9
    //   347: invokeinterface 550 1 0
    //   352: istore 10
    //   354: iload 10
    //   356: ifeq -60 -> 296
    //   359: iload 4
    //   361: iload_3
    //   362: if_icmpgt -66 -> 296
    //   365: iload 4
    //   367: istore 10
    //   369: goto -146 -> 223
    //   372: aload 7
    //   374: invokestatic 443	com/google/android/gms/internal/zzsm:zzD	([B)Lcom/google/android/gms/internal/zzsm;
    //   377: astore 16
    //   379: new 670	com/google/android/gms/internal/zzqb$zze
    //   382: astore 17
    //   384: aload 17
    //   386: invokespecial 907	com/google/android/gms/internal/zzqb$zze:<init>	()V
    //   389: aload 17
    //   391: aload 16
    //   393: invokevirtual 911	com/google/android/gms/internal/zzqb$zze:zzG	(Lcom/google/android/gms/internal/zzsm;)Lcom/google/android/gms/internal/zzqb$zze;
    //   396: pop
    //   397: aload 7
    //   399: arraylength
    //   400: iload 10
    //   402: iadd
    //   403: istore 4
    //   405: lload 19
    //   407: invokestatic 649	java/lang/Long:valueOf	(J)Ljava/lang/Long;
    //   410: astore 11
    //   412: aload 17
    //   414: aload 11
    //   416: invokestatic 1134	android/util/Pair:create	(Ljava/lang/Object;Ljava/lang/Object;)Landroid/util/Pair;
    //   419: astore 11
    //   421: aload 6
    //   423: aload 11
    //   425: invokeinterface 608 2 0
    //   430: pop
    //   431: goto -86 -> 345
    //   434: astore 6
    //   436: aload 9
    //   438: astore 7
    //   440: aload_0
    //   441: invokevirtual 188	com/google/android/gms/measurement/internal/zze:zzAo	()Lcom/google/android/gms/measurement/internal/zzp;
    //   444: astore 9
    //   446: aload 9
    //   448: invokevirtual 194	com/google/android/gms/measurement/internal/zzp:zzCE	()Lcom/google/android/gms/measurement/internal/zzp$zza;
    //   451: astore 9
    //   453: ldc_w 1136
    //   456: astore 11
    //   458: aload 9
    //   460: aload 11
    //   462: aload_1
    //   463: aload 6
    //   465: invokevirtual 202	com/google/android/gms/measurement/internal/zzp$zza:zze	(Ljava/lang/String;Ljava/lang/Object;Ljava/lang/Object;)V
    //   468: invokestatic 1121	java/util/Collections:emptyList	()Ljava/util/List;
    //   471: astore 6
    //   473: aload 7
    //   475: ifnull -289 -> 186
    //   478: aload 7
    //   480: invokeinterface 184 1 0
    //   485: goto -299 -> 186
    //   488: astore 7
    //   490: aload_0
    //   491: invokevirtual 188	com/google/android/gms/measurement/internal/zze:zzAo	()Lcom/google/android/gms/measurement/internal/zzp;
    //   494: astore 12
    //   496: aload 12
    //   498: invokevirtual 194	com/google/android/gms/measurement/internal/zzp:zzCE	()Lcom/google/android/gms/measurement/internal/zzp$zza;
    //   501: astore 12
    //   503: ldc_w 1138
    //   506: astore 14
    //   508: aload 12
    //   510: aload 14
    //   512: aload_1
    //   513: aload 7
    //   515: invokevirtual 202	com/google/android/gms/measurement/internal/zzp$zza:zze	(Ljava/lang/String;Ljava/lang/Object;Ljava/lang/Object;)V
    //   518: iload 10
    //   520: istore 4
    //   522: goto -177 -> 345
    //   525: astore 6
    //   527: iconst_0
    //   528: istore 8
    //   530: aconst_null
    //   531: astore 9
    //   533: aload 9
    //   535: ifnull +10 -> 545
    //   538: aload 9
    //   540: invokeinterface 184 1 0
    //   545: aload 6
    //   547: athrow
    //   548: astore 6
    //   550: goto -17 -> 533
    //   553: astore 6
    //   555: aload 7
    //   557: astore 9
    //   559: goto -26 -> 533
    //   562: astore 6
    //   564: iconst_0
    //   565: istore 4
    //   567: aconst_null
    //   568: astore 7
    //   570: goto -130 -> 440
    // Local variable table:
    //   start	length	slot	name	signature
    //   0	573	0	this	zze
    //   0	573	1	paramString	String
    //   0	573	2	paramInt1	int
    //   0	573	3	paramInt2	int
    //   1	565	4	i	int
    //   17	3	5	j	int
    //   162	29	5	bool1	boolean
    //   42	380	6	localObject1	Object
    //   434	30	6	localSQLiteException1	SQLiteException
    //   471	1	6	localList	List
    //   525	21	6	localObject2	Object
    //   548	1	6	localObject3	Object
    //   553	1	6	localObject4	Object
    //   562	1	6	localSQLiteException2	SQLiteException
    //   47	236	7	localObject5	Object
    //   311	87	7	localIOException1	IOException
    //   438	41	7	localObject6	Object
    //   488	68	7	localIOException2	IOException
    //   568	1	7	localObject7	Object
    //   50	479	8	k	int
    //   57	501	9	localObject8	Object
    //   60	282	10	m	int
    //   352	3	10	bool2	boolean
    //   367	152	10	n	int
    //   63	398	11	localObject9	Object
    //   68	441	12	localObject10	Object
    //   97	3	13	i1	int
    //   107	404	14	str1	String
    //   118	160	15	bool3	boolean
    //   288	6	15	i2	int
    //   121	271	16	localObject11	Object
    //   126	287	17	localObject12	Object
    //   132	17	18	str2	String
    //   237	169	19	l	long
    // Exception table:
    //   from	to	target	type
    //   244	251	311	java/io/IOException
    //   253	257	311	java/io/IOException
    //   261	266	311	java/io/IOException
    //   155	162	434	android/database/sqlite/SQLiteException
    //   169	172	434	android/database/sqlite/SQLiteException
    //   207	210	434	android/database/sqlite/SQLiteException
    //   212	217	434	android/database/sqlite/SQLiteException
    //   231	237	434	android/database/sqlite/SQLiteException
    //   244	251	434	android/database/sqlite/SQLiteException
    //   253	257	434	android/database/sqlite/SQLiteException
    //   261	266	434	android/database/sqlite/SQLiteException
    //   268	275	434	android/database/sqlite/SQLiteException
    //   282	285	434	android/database/sqlite/SQLiteException
    //   313	317	434	android/database/sqlite/SQLiteException
    //   319	324	434	android/database/sqlite/SQLiteException
    //   336	341	434	android/database/sqlite/SQLiteException
    //   345	352	434	android/database/sqlite/SQLiteException
    //   372	377	434	android/database/sqlite/SQLiteException
    //   379	382	434	android/database/sqlite/SQLiteException
    //   384	389	434	android/database/sqlite/SQLiteException
    //   391	397	434	android/database/sqlite/SQLiteException
    //   397	400	434	android/database/sqlite/SQLiteException
    //   405	410	434	android/database/sqlite/SQLiteException
    //   414	419	434	android/database/sqlite/SQLiteException
    //   423	431	434	android/database/sqlite/SQLiteException
    //   490	494	434	android/database/sqlite/SQLiteException
    //   496	501	434	android/database/sqlite/SQLiteException
    //   513	518	434	android/database/sqlite/SQLiteException
    //   391	397	488	java/io/IOException
    //   38	42	525	finally
    //   52	57	525	finally
    //   73	76	525	finally
    //   88	91	525	finally
    //   99	104	525	finally
    //   112	114	525	finally
    //   128	132	525	finally
    //   148	153	525	finally
    //   155	162	548	finally
    //   169	172	548	finally
    //   207	210	548	finally
    //   212	217	548	finally
    //   231	237	548	finally
    //   244	251	548	finally
    //   253	257	548	finally
    //   261	266	548	finally
    //   268	275	548	finally
    //   282	285	548	finally
    //   313	317	548	finally
    //   319	324	548	finally
    //   336	341	548	finally
    //   345	352	548	finally
    //   372	377	548	finally
    //   379	382	548	finally
    //   384	389	548	finally
    //   391	397	548	finally
    //   397	400	548	finally
    //   405	410	548	finally
    //   414	419	548	finally
    //   423	431	548	finally
    //   490	494	548	finally
    //   496	501	548	finally
    //   513	518	548	finally
    //   440	444	553	finally
    //   446	451	553	finally
    //   463	468	553	finally
    //   468	471	553	finally
    //   38	42	562	android/database/sqlite/SQLiteException
    //   52	57	562	android/database/sqlite/SQLiteException
    //   73	76	562	android/database/sqlite/SQLiteException
    //   88	91	562	android/database/sqlite/SQLiteException
    //   99	104	562	android/database/sqlite/SQLiteException
    //   112	114	562	android/database/sqlite/SQLiteException
    //   128	132	562	android/database/sqlite/SQLiteException
    //   148	153	562	android/database/sqlite/SQLiteException
  }
  
  public void zzz(List paramList)
  {
    zzx.zzz(paramList);
    zzjk();
    zzjv();
    Object localObject1 = new java/lang/StringBuilder;
    ((StringBuilder)localObject1).<init>("rowid in (");
    int i = 0;
    Object localObject2 = null;
    int j = 0;
    Object localObject3 = null;
    for (;;)
    {
      i = paramList.size();
      if (j >= i) {
        break;
      }
      if (j != 0)
      {
        localObject2 = ",";
        ((StringBuilder)localObject1).append((String)localObject2);
      }
      localObject2 = (Long)paramList.get(j);
      long l = ((Long)localObject2).longValue();
      ((StringBuilder)localObject1).append(l);
      i = j + 1;
      j = i;
    }
    ((StringBuilder)localObject1).append(")");
    localObject2 = getWritableDatabase();
    localObject3 = "raw_events";
    localObject1 = ((StringBuilder)localObject1).toString();
    int k = 0;
    Integer localInteger = null;
    i = ((SQLiteDatabase)localObject2).delete((String)localObject3, (String)localObject1, null);
    j = paramList.size();
    if (i != j)
    {
      localObject3 = zzAo().zzCE();
      localObject1 = "Deleted fewer rows from raw events table than expected";
      localObject2 = Integer.valueOf(i);
      k = paramList.size();
      localInteger = Integer.valueOf(k);
      ((zzp.zza)localObject3).zze((String)localObject1, localObject2, localInteger);
    }
  }
}


/* Location:              C:\Users\haryo\Desktop\enjarify-master\presensi-enjarify.jar!\com\google\android\gms\measurement\internal\zze.class
 * Java compiler version: 5 (49.0)
 * JD-Core Version:       0.7.1
 */