package com.google.android.gms.measurement.internal;

import com.google.android.gms.common.internal.zzx;
import java.net.URL;
import java.util.Map;

class zzq$zzc
  implements Runnable
{
  private final String zzTJ;
  private final byte[] zzaWS;
  private final zzq.zza zzaWT;
  private final Map zzaWU;
  private final URL zzzq;
  
  public zzq$zzc(zzq paramzzq, String paramString, URL paramURL, byte[] paramArrayOfByte, Map paramMap, zzq.zza paramzza)
  {
    zzx.zzcM(paramString);
    zzx.zzz(paramURL);
    zzx.zzz(paramzza);
    this.zzzq = paramURL;
    this.zzaWS = paramArrayOfByte;
    this.zzaWT = paramzza;
    this.zzTJ = paramString;
    this.zzaWU = paramMap;
  }
  
  /* Error */
  public void run()
  {
    // Byte code:
    //   0: aload_0
    //   1: getfield 20	com/google/android/gms/measurement/internal/zzq$zzc:zzaWV	Lcom/google/android/gms/measurement/internal/zzq;
    //   4: astore_1
    //   5: aload_1
    //   6: invokevirtual 49	com/google/android/gms/measurement/internal/zzq:zzCd	()V
    //   9: iconst_0
    //   10: istore_2
    //   11: aconst_null
    //   12: astore_3
    //   13: aload_0
    //   14: getfield 20	com/google/android/gms/measurement/internal/zzq$zzc:zzaWV	Lcom/google/android/gms/measurement/internal/zzq;
    //   17: astore_1
    //   18: aload_0
    //   19: getfield 36	com/google/android/gms/measurement/internal/zzq$zzc:zzzq	Ljava/net/URL;
    //   22: astore 4
    //   24: aload_1
    //   25: aload 4
    //   27: invokevirtual 53	com/google/android/gms/measurement/internal/zzq:zzc	(Ljava/net/URL;)Ljava/net/HttpURLConnection;
    //   30: astore 5
    //   32: aload_0
    //   33: getfield 44	com/google/android/gms/measurement/internal/zzq$zzc:zzaWU	Ljava/util/Map;
    //   36: astore_1
    //   37: aload_1
    //   38: ifnull +167 -> 205
    //   41: aload_0
    //   42: getfield 44	com/google/android/gms/measurement/internal/zzq$zzc:zzaWU	Ljava/util/Map;
    //   45: astore_1
    //   46: aload_1
    //   47: invokeinterface 59 1 0
    //   52: astore_1
    //   53: aload_1
    //   54: invokeinterface 65 1 0
    //   59: astore 6
    //   61: aload 6
    //   63: invokeinterface 71 1 0
    //   68: istore 7
    //   70: iload 7
    //   72: ifeq +133 -> 205
    //   75: aload 6
    //   77: invokeinterface 75 1 0
    //   82: astore_1
    //   83: aload_1
    //   84: checkcast 77	java/util/Map$Entry
    //   87: astore_1
    //   88: aload_1
    //   89: invokeinterface 80 1 0
    //   94: astore 4
    //   96: aload 4
    //   98: checkcast 82	java/lang/String
    //   101: astore 4
    //   103: aload_1
    //   104: invokeinterface 85 1 0
    //   109: astore_1
    //   110: aload_1
    //   111: checkcast 82	java/lang/String
    //   114: astore_1
    //   115: aload 5
    //   117: aload 4
    //   119: aload_1
    //   120: invokevirtual 91	java/net/HttpURLConnection:addRequestProperty	(Ljava/lang/String;Ljava/lang/String;)V
    //   123: goto -62 -> 61
    //   126: astore 8
    //   128: iload_2
    //   129: istore 9
    //   131: iconst_0
    //   132: istore 7
    //   134: aconst_null
    //   135: astore_1
    //   136: aload 5
    //   138: astore 4
    //   140: aload_1
    //   141: ifnull +7 -> 148
    //   144: aload_1
    //   145: invokevirtual 96	java/io/OutputStream:close	()V
    //   148: aload 4
    //   150: ifnull +8 -> 158
    //   153: aload 4
    //   155: invokevirtual 99	java/net/HttpURLConnection:disconnect	()V
    //   158: aload_0
    //   159: getfield 20	com/google/android/gms/measurement/internal/zzq$zzc:zzaWV	Lcom/google/android/gms/measurement/internal/zzq;
    //   162: invokevirtual 103	com/google/android/gms/measurement/internal/zzq:zzCn	()Lcom/google/android/gms/measurement/internal/zzv;
    //   165: astore_1
    //   166: new 105	com/google/android/gms/measurement/internal/zzq$zzb
    //   169: astore 6
    //   171: aload_0
    //   172: getfield 42	com/google/android/gms/measurement/internal/zzq$zzc:zzTJ	Ljava/lang/String;
    //   175: astore 10
    //   177: aload_0
    //   178: getfield 40	com/google/android/gms/measurement/internal/zzq$zzc:zzaWT	Lcom/google/android/gms/measurement/internal/zzq$zza;
    //   181: astore 11
    //   183: aload 6
    //   185: aload 10
    //   187: aload 11
    //   189: iload 9
    //   191: aload 8
    //   193: aconst_null
    //   194: aconst_null
    //   195: invokespecial 108	com/google/android/gms/measurement/internal/zzq$zzb:<init>	(Ljava/lang/String;Lcom/google/android/gms/measurement/internal/zzq$zza;ILjava/lang/Throwable;[BLcom/google/android/gms/measurement/internal/zzq$1;)V
    //   198: aload_1
    //   199: aload 6
    //   201: invokevirtual 114	com/google/android/gms/measurement/internal/zzv:zzg	(Ljava/lang/Runnable;)V
    //   204: return
    //   205: aload_0
    //   206: getfield 38	com/google/android/gms/measurement/internal/zzq$zzc:zzaWS	[B
    //   209: astore_1
    //   210: aload_1
    //   211: ifnull +430 -> 641
    //   214: aload_0
    //   215: getfield 20	com/google/android/gms/measurement/internal/zzq$zzc:zzaWV	Lcom/google/android/gms/measurement/internal/zzq;
    //   218: astore_1
    //   219: aload_1
    //   220: invokevirtual 118	com/google/android/gms/measurement/internal/zzq:zzCk	()Lcom/google/android/gms/measurement/internal/zzaj;
    //   223: astore_1
    //   224: aload_0
    //   225: getfield 38	com/google/android/gms/measurement/internal/zzq$zzc:zzaWS	[B
    //   228: astore 4
    //   230: aload_1
    //   231: aload 4
    //   233: invokevirtual 123	com/google/android/gms/measurement/internal/zzaj:zzg	([B)[B
    //   236: astore 4
    //   238: aload_0
    //   239: getfield 20	com/google/android/gms/measurement/internal/zzq$zzc:zzaWV	Lcom/google/android/gms/measurement/internal/zzq;
    //   242: astore_1
    //   243: aload_1
    //   244: invokevirtual 127	com/google/android/gms/measurement/internal/zzq:zzAo	()Lcom/google/android/gms/measurement/internal/zzp;
    //   247: astore_1
    //   248: aload_1
    //   249: invokevirtual 133	com/google/android/gms/measurement/internal/zzp:zzCK	()Lcom/google/android/gms/measurement/internal/zzp$zza;
    //   252: astore_1
    //   253: ldc -121
    //   255: astore 6
    //   257: aload 4
    //   259: arraylength
    //   260: istore 12
    //   262: iload 12
    //   264: invokestatic 141	java/lang/Integer:valueOf	(I)Ljava/lang/Integer;
    //   267: astore 10
    //   269: aload_1
    //   270: aload 6
    //   272: aload 10
    //   274: invokevirtual 147	com/google/android/gms/measurement/internal/zzp$zza:zzj	(Ljava/lang/String;Ljava/lang/Object;)V
    //   277: iconst_1
    //   278: istore 7
    //   280: aload 5
    //   282: iload 7
    //   284: invokevirtual 152	java/net/HttpURLConnection:setDoOutput	(Z)V
    //   287: ldc -102
    //   289: astore_1
    //   290: ldc -100
    //   292: astore 6
    //   294: aload 5
    //   296: aload_1
    //   297: aload 6
    //   299: invokevirtual 91	java/net/HttpURLConnection:addRequestProperty	(Ljava/lang/String;Ljava/lang/String;)V
    //   302: aload 4
    //   304: arraylength
    //   305: istore 7
    //   307: aload 5
    //   309: iload 7
    //   311: invokevirtual 160	java/net/HttpURLConnection:setFixedLengthStreamingMode	(I)V
    //   314: aload 5
    //   316: invokevirtual 163	java/net/HttpURLConnection:connect	()V
    //   319: aload 5
    //   321: invokevirtual 167	java/net/HttpURLConnection:getOutputStream	()Ljava/io/OutputStream;
    //   324: astore_1
    //   325: aload_1
    //   326: aload 4
    //   328: invokevirtual 171	java/io/OutputStream:write	([B)V
    //   331: aload_1
    //   332: invokevirtual 96	java/io/OutputStream:close	()V
    //   335: iconst_0
    //   336: istore 7
    //   338: aconst_null
    //   339: astore_1
    //   340: aload 5
    //   342: invokevirtual 175	java/net/HttpURLConnection:getResponseCode	()I
    //   345: istore_2
    //   346: aload_0
    //   347: getfield 20	com/google/android/gms/measurement/internal/zzq$zzc:zzaWV	Lcom/google/android/gms/measurement/internal/zzq;
    //   350: astore 4
    //   352: aload 4
    //   354: aload 5
    //   356: invokestatic 179	com/google/android/gms/measurement/internal/zzq:zza	(Lcom/google/android/gms/measurement/internal/zzq;Ljava/net/HttpURLConnection;)[B
    //   359: astore 6
    //   361: iconst_0
    //   362: ifeq +7 -> 369
    //   365: aconst_null
    //   366: invokevirtual 96	java/io/OutputStream:close	()V
    //   369: aload 5
    //   371: ifnull +8 -> 379
    //   374: aload 5
    //   376: invokevirtual 99	java/net/HttpURLConnection:disconnect	()V
    //   379: aload_0
    //   380: getfield 20	com/google/android/gms/measurement/internal/zzq$zzc:zzaWV	Lcom/google/android/gms/measurement/internal/zzq;
    //   383: invokevirtual 103	com/google/android/gms/measurement/internal/zzq:zzCn	()Lcom/google/android/gms/measurement/internal/zzv;
    //   386: astore 11
    //   388: new 105	com/google/android/gms/measurement/internal/zzq$zzb
    //   391: astore_1
    //   392: aload_0
    //   393: getfield 42	com/google/android/gms/measurement/internal/zzq$zzc:zzTJ	Ljava/lang/String;
    //   396: astore 4
    //   398: aload_0
    //   399: getfield 40	com/google/android/gms/measurement/internal/zzq$zzc:zzaWT	Lcom/google/android/gms/measurement/internal/zzq$zza;
    //   402: astore 5
    //   404: iconst_0
    //   405: istore 12
    //   407: aconst_null
    //   408: astore 10
    //   410: aload_1
    //   411: aload 4
    //   413: aload 5
    //   415: iload_2
    //   416: aconst_null
    //   417: aload 6
    //   419: aconst_null
    //   420: invokespecial 108	com/google/android/gms/measurement/internal/zzq$zzb:<init>	(Ljava/lang/String;Lcom/google/android/gms/measurement/internal/zzq$zza;ILjava/lang/Throwable;[BLcom/google/android/gms/measurement/internal/zzq$1;)V
    //   423: aload 11
    //   425: aload_1
    //   426: invokevirtual 114	com/google/android/gms/measurement/internal/zzv:zzg	(Ljava/lang/Runnable;)V
    //   429: goto -225 -> 204
    //   432: astore_1
    //   433: aload_0
    //   434: getfield 20	com/google/android/gms/measurement/internal/zzq$zzc:zzaWV	Lcom/google/android/gms/measurement/internal/zzq;
    //   437: invokevirtual 127	com/google/android/gms/measurement/internal/zzq:zzAo	()Lcom/google/android/gms/measurement/internal/zzp;
    //   440: invokevirtual 182	com/google/android/gms/measurement/internal/zzp:zzCE	()Lcom/google/android/gms/measurement/internal/zzp$zza;
    //   443: astore 4
    //   445: ldc -72
    //   447: astore 10
    //   449: aload 4
    //   451: aload 10
    //   453: aload_1
    //   454: invokevirtual 147	com/google/android/gms/measurement/internal/zzp$zza:zzj	(Ljava/lang/String;Ljava/lang/Object;)V
    //   457: goto -88 -> 369
    //   460: astore_1
    //   461: aload_0
    //   462: getfield 20	com/google/android/gms/measurement/internal/zzq$zzc:zzaWV	Lcom/google/android/gms/measurement/internal/zzq;
    //   465: invokevirtual 127	com/google/android/gms/measurement/internal/zzq:zzAo	()Lcom/google/android/gms/measurement/internal/zzp;
    //   468: invokevirtual 182	com/google/android/gms/measurement/internal/zzp:zzCE	()Lcom/google/android/gms/measurement/internal/zzp$zza;
    //   471: astore 5
    //   473: ldc -72
    //   475: astore_3
    //   476: aload 5
    //   478: aload_3
    //   479: aload_1
    //   480: invokevirtual 147	com/google/android/gms/measurement/internal/zzp$zza:zzj	(Ljava/lang/String;Ljava/lang/Object;)V
    //   483: goto -335 -> 148
    //   486: astore 11
    //   488: aconst_null
    //   489: astore 5
    //   491: iconst_0
    //   492: istore 7
    //   494: aconst_null
    //   495: astore_1
    //   496: aload_1
    //   497: ifnull +7 -> 504
    //   500: aload_1
    //   501: invokevirtual 96	java/io/OutputStream:close	()V
    //   504: aload 5
    //   506: ifnull +8 -> 514
    //   509: aload 5
    //   511: invokevirtual 99	java/net/HttpURLConnection:disconnect	()V
    //   514: aload_0
    //   515: getfield 20	com/google/android/gms/measurement/internal/zzq$zzc:zzaWV	Lcom/google/android/gms/measurement/internal/zzq;
    //   518: invokevirtual 103	com/google/android/gms/measurement/internal/zzq:zzCn	()Lcom/google/android/gms/measurement/internal/zzv;
    //   521: astore 13
    //   523: new 105	com/google/android/gms/measurement/internal/zzq$zzb
    //   526: astore_1
    //   527: aload_0
    //   528: getfield 42	com/google/android/gms/measurement/internal/zzq$zzc:zzTJ	Ljava/lang/String;
    //   531: astore 4
    //   533: aload_0
    //   534: getfield 40	com/google/android/gms/measurement/internal/zzq$zzc:zzaWT	Lcom/google/android/gms/measurement/internal/zzq$zza;
    //   537: astore 5
    //   539: aload_1
    //   540: aload 4
    //   542: aload 5
    //   544: iload_2
    //   545: aconst_null
    //   546: aconst_null
    //   547: aconst_null
    //   548: invokespecial 108	com/google/android/gms/measurement/internal/zzq$zzb:<init>	(Ljava/lang/String;Lcom/google/android/gms/measurement/internal/zzq$zza;ILjava/lang/Throwable;[BLcom/google/android/gms/measurement/internal/zzq$1;)V
    //   551: aload 13
    //   553: aload_1
    //   554: invokevirtual 114	com/google/android/gms/measurement/internal/zzv:zzg	(Ljava/lang/Runnable;)V
    //   557: aload 11
    //   559: athrow
    //   560: astore_1
    //   561: aload_0
    //   562: getfield 20	com/google/android/gms/measurement/internal/zzq$zzc:zzaWV	Lcom/google/android/gms/measurement/internal/zzq;
    //   565: invokevirtual 127	com/google/android/gms/measurement/internal/zzq:zzAo	()Lcom/google/android/gms/measurement/internal/zzp;
    //   568: invokevirtual 182	com/google/android/gms/measurement/internal/zzp:zzCE	()Lcom/google/android/gms/measurement/internal/zzp$zza;
    //   571: astore 4
    //   573: ldc -72
    //   575: astore 6
    //   577: aload 4
    //   579: aload 6
    //   581: aload_1
    //   582: invokevirtual 147	com/google/android/gms/measurement/internal/zzp$zza:zzj	(Ljava/lang/String;Ljava/lang/Object;)V
    //   585: goto -81 -> 504
    //   588: astore 11
    //   590: iconst_0
    //   591: istore 7
    //   593: aconst_null
    //   594: astore_1
    //   595: goto -99 -> 496
    //   598: astore 4
    //   600: aload 4
    //   602: astore 11
    //   604: goto -108 -> 496
    //   607: astore 8
    //   609: iconst_0
    //   610: istore 9
    //   612: aconst_null
    //   613: astore 13
    //   615: iconst_0
    //   616: istore 7
    //   618: aconst_null
    //   619: astore_1
    //   620: aconst_null
    //   621: astore 4
    //   623: goto -483 -> 140
    //   626: astore 8
    //   628: iconst_0
    //   629: istore 9
    //   631: aconst_null
    //   632: astore 13
    //   634: aload 5
    //   636: astore 4
    //   638: goto -498 -> 140
    //   641: iconst_0
    //   642: istore 7
    //   644: aconst_null
    //   645: astore_1
    //   646: goto -306 -> 340
    // Local variable table:
    //   start	length	slot	name	signature
    //   0	649	0	this	zzc
    //   4	422	1	localObject1	Object
    //   432	22	1	localIOException1	java.io.IOException
    //   460	20	1	localIOException2	java.io.IOException
    //   495	59	1	localzzb	zzq.zzb
    //   560	22	1	localIOException3	java.io.IOException
    //   594	52	1	localObject2	Object
    //   10	535	2	i	int
    //   12	467	3	str	String
    //   22	556	4	localObject3	Object
    //   598	3	4	localObject4	Object
    //   621	16	4	localObject5	Object
    //   30	605	5	localObject6	Object
    //   59	521	6	localObject7	Object
    //   68	215	7	bool	boolean
    //   305	338	7	j	int
    //   126	66	8	localIOException4	java.io.IOException
    //   607	1	8	localIOException5	java.io.IOException
    //   626	1	8	localIOException6	java.io.IOException
    //   129	501	9	k	int
    //   175	277	10	localObject8	Object
    //   181	243	11	localObject9	Object
    //   486	72	11	localObject10	Object
    //   588	1	11	localObject11	Object
    //   602	1	11	localObject12	Object
    //   260	146	12	m	int
    //   521	112	13	localzzv	zzv
    // Exception table:
    //   from	to	target	type
    //   32	36	126	java/io/IOException
    //   41	45	126	java/io/IOException
    //   46	52	126	java/io/IOException
    //   53	59	126	java/io/IOException
    //   61	68	126	java/io/IOException
    //   75	82	126	java/io/IOException
    //   83	87	126	java/io/IOException
    //   88	94	126	java/io/IOException
    //   96	101	126	java/io/IOException
    //   103	109	126	java/io/IOException
    //   110	114	126	java/io/IOException
    //   119	123	126	java/io/IOException
    //   205	209	126	java/io/IOException
    //   214	218	126	java/io/IOException
    //   219	223	126	java/io/IOException
    //   224	228	126	java/io/IOException
    //   231	236	126	java/io/IOException
    //   238	242	126	java/io/IOException
    //   243	247	126	java/io/IOException
    //   248	252	126	java/io/IOException
    //   257	260	126	java/io/IOException
    //   262	267	126	java/io/IOException
    //   272	277	126	java/io/IOException
    //   282	287	126	java/io/IOException
    //   297	302	126	java/io/IOException
    //   302	305	126	java/io/IOException
    //   309	314	126	java/io/IOException
    //   314	319	126	java/io/IOException
    //   319	324	126	java/io/IOException
    //   340	345	126	java/io/IOException
    //   346	350	126	java/io/IOException
    //   354	359	126	java/io/IOException
    //   365	369	432	java/io/IOException
    //   144	148	460	java/io/IOException
    //   13	17	486	finally
    //   18	22	486	finally
    //   25	30	486	finally
    //   500	504	560	java/io/IOException
    //   32	36	588	finally
    //   41	45	588	finally
    //   46	52	588	finally
    //   53	59	588	finally
    //   61	68	588	finally
    //   75	82	588	finally
    //   83	87	588	finally
    //   88	94	588	finally
    //   96	101	588	finally
    //   103	109	588	finally
    //   110	114	588	finally
    //   119	123	588	finally
    //   205	209	588	finally
    //   214	218	588	finally
    //   219	223	588	finally
    //   224	228	588	finally
    //   231	236	588	finally
    //   238	242	588	finally
    //   243	247	588	finally
    //   248	252	588	finally
    //   257	260	588	finally
    //   262	267	588	finally
    //   272	277	588	finally
    //   282	287	588	finally
    //   297	302	588	finally
    //   302	305	588	finally
    //   309	314	588	finally
    //   314	319	588	finally
    //   319	324	588	finally
    //   340	345	588	finally
    //   346	350	588	finally
    //   354	359	588	finally
    //   326	331	598	finally
    //   331	335	598	finally
    //   13	17	607	java/io/IOException
    //   18	22	607	java/io/IOException
    //   25	30	607	java/io/IOException
    //   326	331	626	java/io/IOException
    //   331	335	626	java/io/IOException
  }
}


/* Location:              C:\Users\haryo\Desktop\enjarify-master\presensi-enjarify.jar!\com\google\android\gms\measurement\internal\zzq$zzc.class
 * Java compiler version: 5 (49.0)
 * JD-Core Version:       0.7.1
 */