package com.google.android.gms.measurement.internal;

import com.google.android.gms.common.internal.zzx;
import java.util.concurrent.BlockingQueue;

final class zzv$zzc
  extends Thread
{
  private final Object zzaXT;
  private final BlockingQueue zzaXU;
  
  public zzv$zzc(zzv paramzzv, String paramString, BlockingQueue paramBlockingQueue)
  {
    zzx.zzz(paramString);
    Object localObject = new java/lang/Object;
    localObject.<init>();
    this.zzaXT = localObject;
    this.zzaXU = paramBlockingQueue;
    setName(paramString);
  }
  
  private void zza(InterruptedException paramInterruptedException)
  {
    zzp.zza localzza = this.zzaXS.zzAo().zzCF();
    Object localObject = new java/lang/StringBuilder;
    ((StringBuilder)localObject).<init>();
    String str = getName();
    localObject = str + " was interrupted";
    localzza.zzj((String)localObject, paramInterruptedException);
  }
  
  /* Error */
  public void run()
  {
    // Byte code:
    //   0: iconst_0
    //   1: istore_1
    //   2: aconst_null
    //   3: astore_2
    //   4: iconst_0
    //   5: istore_3
    //   6: aconst_null
    //   7: astore 4
    //   9: iload_3
    //   10: ifne +33 -> 43
    //   13: aload_0
    //   14: getfield 12	com/google/android/gms/measurement/internal/zzv$zzc:zzaXS	Lcom/google/android/gms/measurement/internal/zzv;
    //   17: astore_2
    //   18: aload_2
    //   19: invokestatic 71	com/google/android/gms/measurement/internal/zzv:zza	(Lcom/google/android/gms/measurement/internal/zzv;)Ljava/util/concurrent/Semaphore;
    //   22: astore_2
    //   23: aload_2
    //   24: invokevirtual 76	java/util/concurrent/Semaphore:acquire	()V
    //   27: iconst_1
    //   28: istore_1
    //   29: iload_1
    //   30: istore_3
    //   31: goto -22 -> 9
    //   34: astore_2
    //   35: aload_0
    //   36: aload_2
    //   37: invokespecial 80	com/google/android/gms/measurement/internal/zzv$zzc:zza	(Ljava/lang/InterruptedException;)V
    //   40: goto -31 -> 9
    //   43: aload_0
    //   44: getfield 29	com/google/android/gms/measurement/internal/zzv$zzc:zzaXU	Ljava/util/concurrent/BlockingQueue;
    //   47: astore_2
    //   48: aload_2
    //   49: invokeinterface 86 1 0
    //   54: astore_2
    //   55: aload_2
    //   56: checkcast 88	java/util/concurrent/FutureTask
    //   59: astore_2
    //   60: aload_2
    //   61: ifnull +99 -> 160
    //   64: aload_2
    //   65: invokevirtual 91	java/util/concurrent/FutureTask:run	()V
    //   68: goto -25 -> 43
    //   71: astore_2
    //   72: aload_0
    //   73: getfield 12	com/google/android/gms/measurement/internal/zzv$zzc:zzaXS	Lcom/google/android/gms/measurement/internal/zzv;
    //   76: invokestatic 95	com/google/android/gms/measurement/internal/zzv:zzc	(Lcom/google/android/gms/measurement/internal/zzv;)Ljava/lang/Object;
    //   79: astore 4
    //   81: aload 4
    //   83: monitorenter
    //   84: aload_0
    //   85: getfield 12	com/google/android/gms/measurement/internal/zzv$zzc:zzaXS	Lcom/google/android/gms/measurement/internal/zzv;
    //   88: astore 5
    //   90: aload 5
    //   92: invokestatic 71	com/google/android/gms/measurement/internal/zzv:zza	(Lcom/google/android/gms/measurement/internal/zzv;)Ljava/util/concurrent/Semaphore;
    //   95: astore 5
    //   97: aload 5
    //   99: invokevirtual 98	java/util/concurrent/Semaphore:release	()V
    //   102: aload_0
    //   103: getfield 12	com/google/android/gms/measurement/internal/zzv$zzc:zzaXS	Lcom/google/android/gms/measurement/internal/zzv;
    //   106: astore 5
    //   108: aload 5
    //   110: invokestatic 95	com/google/android/gms/measurement/internal/zzv:zzc	(Lcom/google/android/gms/measurement/internal/zzv;)Ljava/lang/Object;
    //   113: astore 5
    //   115: aload 5
    //   117: invokevirtual 101	java/lang/Object:notifyAll	()V
    //   120: aload_0
    //   121: getfield 12	com/google/android/gms/measurement/internal/zzv$zzc:zzaXS	Lcom/google/android/gms/measurement/internal/zzv;
    //   124: astore 5
    //   126: aload 5
    //   128: invokestatic 105	com/google/android/gms/measurement/internal/zzv:zzd	(Lcom/google/android/gms/measurement/internal/zzv;)Lcom/google/android/gms/measurement/internal/zzv$zzc;
    //   131: astore 5
    //   133: aload_0
    //   134: aload 5
    //   136: if_acmpne +283 -> 419
    //   139: aload_0
    //   140: getfield 12	com/google/android/gms/measurement/internal/zzv$zzc:zzaXS	Lcom/google/android/gms/measurement/internal/zzv;
    //   143: astore 5
    //   145: aconst_null
    //   146: astore 6
    //   148: aload 5
    //   150: aconst_null
    //   151: invokestatic 108	com/google/android/gms/measurement/internal/zzv:zza	(Lcom/google/android/gms/measurement/internal/zzv;Lcom/google/android/gms/measurement/internal/zzv$zzc;)Lcom/google/android/gms/measurement/internal/zzv$zzc;
    //   154: pop
    //   155: aload 4
    //   157: monitorexit
    //   158: aload_2
    //   159: athrow
    //   160: aload_0
    //   161: getfield 27	com/google/android/gms/measurement/internal/zzv$zzc:zzaXT	Ljava/lang/Object;
    //   164: astore 4
    //   166: aload 4
    //   168: monitorenter
    //   169: aload_0
    //   170: getfield 29	com/google/android/gms/measurement/internal/zzv$zzc:zzaXU	Ljava/util/concurrent/BlockingQueue;
    //   173: astore_2
    //   174: aload_2
    //   175: invokeinterface 111 1 0
    //   180: astore_2
    //   181: aload_2
    //   182: ifnonnull +33 -> 215
    //   185: aload_0
    //   186: getfield 12	com/google/android/gms/measurement/internal/zzv$zzc:zzaXS	Lcom/google/android/gms/measurement/internal/zzv;
    //   189: astore_2
    //   190: aload_2
    //   191: invokestatic 115	com/google/android/gms/measurement/internal/zzv:zzb	(Lcom/google/android/gms/measurement/internal/zzv;)Z
    //   194: istore_1
    //   195: iload_1
    //   196: ifne +19 -> 215
    //   199: aload_0
    //   200: getfield 27	com/google/android/gms/measurement/internal/zzv$zzc:zzaXT	Ljava/lang/Object;
    //   203: astore_2
    //   204: ldc2_w 116
    //   207: lstore 7
    //   209: aload_2
    //   210: lload 7
    //   212: invokevirtual 123	java/lang/Object:wait	(J)V
    //   215: aload 4
    //   217: monitorexit
    //   218: aload_0
    //   219: getfield 12	com/google/android/gms/measurement/internal/zzv$zzc:zzaXS	Lcom/google/android/gms/measurement/internal/zzv;
    //   222: astore_2
    //   223: aload_2
    //   224: invokestatic 95	com/google/android/gms/measurement/internal/zzv:zzc	(Lcom/google/android/gms/measurement/internal/zzv;)Ljava/lang/Object;
    //   227: astore 4
    //   229: aload 4
    //   231: monitorenter
    //   232: aload_0
    //   233: getfield 29	com/google/android/gms/measurement/internal/zzv$zzc:zzaXU	Ljava/util/concurrent/BlockingQueue;
    //   236: astore_2
    //   237: aload_2
    //   238: invokeinterface 111 1 0
    //   243: astore_2
    //   244: aload_2
    //   245: ifnonnull +162 -> 407
    //   248: aload 4
    //   250: monitorexit
    //   251: aload_0
    //   252: getfield 12	com/google/android/gms/measurement/internal/zzv$zzc:zzaXS	Lcom/google/android/gms/measurement/internal/zzv;
    //   255: astore_2
    //   256: aload_2
    //   257: invokestatic 95	com/google/android/gms/measurement/internal/zzv:zzc	(Lcom/google/android/gms/measurement/internal/zzv;)Ljava/lang/Object;
    //   260: astore 4
    //   262: aload 4
    //   264: monitorenter
    //   265: aload_0
    //   266: getfield 12	com/google/android/gms/measurement/internal/zzv$zzc:zzaXS	Lcom/google/android/gms/measurement/internal/zzv;
    //   269: astore_2
    //   270: aload_2
    //   271: invokestatic 71	com/google/android/gms/measurement/internal/zzv:zza	(Lcom/google/android/gms/measurement/internal/zzv;)Ljava/util/concurrent/Semaphore;
    //   274: astore_2
    //   275: aload_2
    //   276: invokevirtual 98	java/util/concurrent/Semaphore:release	()V
    //   279: aload_0
    //   280: getfield 12	com/google/android/gms/measurement/internal/zzv$zzc:zzaXS	Lcom/google/android/gms/measurement/internal/zzv;
    //   283: astore_2
    //   284: aload_2
    //   285: invokestatic 95	com/google/android/gms/measurement/internal/zzv:zzc	(Lcom/google/android/gms/measurement/internal/zzv;)Ljava/lang/Object;
    //   288: astore_2
    //   289: aload_2
    //   290: invokevirtual 101	java/lang/Object:notifyAll	()V
    //   293: aload_0
    //   294: getfield 12	com/google/android/gms/measurement/internal/zzv$zzc:zzaXS	Lcom/google/android/gms/measurement/internal/zzv;
    //   297: astore_2
    //   298: aload_2
    //   299: invokestatic 105	com/google/android/gms/measurement/internal/zzv:zzd	(Lcom/google/android/gms/measurement/internal/zzv;)Lcom/google/android/gms/measurement/internal/zzv$zzc;
    //   302: astore_2
    //   303: aload_0
    //   304: aload_2
    //   305: if_acmpne +36 -> 341
    //   308: aload_0
    //   309: getfield 12	com/google/android/gms/measurement/internal/zzv$zzc:zzaXS	Lcom/google/android/gms/measurement/internal/zzv;
    //   312: astore_2
    //   313: aconst_null
    //   314: astore 5
    //   316: aload_2
    //   317: aconst_null
    //   318: invokestatic 108	com/google/android/gms/measurement/internal/zzv:zza	(Lcom/google/android/gms/measurement/internal/zzv;Lcom/google/android/gms/measurement/internal/zzv$zzc;)Lcom/google/android/gms/measurement/internal/zzv$zzc;
    //   321: pop
    //   322: aload 4
    //   324: monitorexit
    //   325: return
    //   326: astore_2
    //   327: aload_0
    //   328: aload_2
    //   329: invokespecial 80	com/google/android/gms/measurement/internal/zzv$zzc:zza	(Ljava/lang/InterruptedException;)V
    //   332: goto -117 -> 215
    //   335: astore_2
    //   336: aload 4
    //   338: monitorexit
    //   339: aload_2
    //   340: athrow
    //   341: aload_0
    //   342: getfield 12	com/google/android/gms/measurement/internal/zzv$zzc:zzaXS	Lcom/google/android/gms/measurement/internal/zzv;
    //   345: astore_2
    //   346: aload_2
    //   347: invokestatic 126	com/google/android/gms/measurement/internal/zzv:zze	(Lcom/google/android/gms/measurement/internal/zzv;)Lcom/google/android/gms/measurement/internal/zzv$zzc;
    //   350: astore_2
    //   351: aload_0
    //   352: aload_2
    //   353: if_acmpne +26 -> 379
    //   356: aload_0
    //   357: getfield 12	com/google/android/gms/measurement/internal/zzv$zzc:zzaXS	Lcom/google/android/gms/measurement/internal/zzv;
    //   360: astore_2
    //   361: aconst_null
    //   362: astore 5
    //   364: aload_2
    //   365: aconst_null
    //   366: invokestatic 128	com/google/android/gms/measurement/internal/zzv:zzb	(Lcom/google/android/gms/measurement/internal/zzv;Lcom/google/android/gms/measurement/internal/zzv$zzc;)Lcom/google/android/gms/measurement/internal/zzv$zzc;
    //   369: pop
    //   370: goto -48 -> 322
    //   373: astore_2
    //   374: aload 4
    //   376: monitorexit
    //   377: aload_2
    //   378: athrow
    //   379: aload_0
    //   380: getfield 12	com/google/android/gms/measurement/internal/zzv$zzc:zzaXS	Lcom/google/android/gms/measurement/internal/zzv;
    //   383: astore_2
    //   384: aload_2
    //   385: invokevirtual 39	com/google/android/gms/measurement/internal/zzv:zzAo	()Lcom/google/android/gms/measurement/internal/zzp;
    //   388: astore_2
    //   389: aload_2
    //   390: invokevirtual 131	com/google/android/gms/measurement/internal/zzp:zzCE	()Lcom/google/android/gms/measurement/internal/zzp$zza;
    //   393: astore_2
    //   394: ldc -123
    //   396: astore 5
    //   398: aload_2
    //   399: aload 5
    //   401: invokevirtual 136	com/google/android/gms/measurement/internal/zzp$zza:zzfg	(Ljava/lang/String;)V
    //   404: goto -82 -> 322
    //   407: aload 4
    //   409: monitorexit
    //   410: goto -367 -> 43
    //   413: astore_2
    //   414: aload 4
    //   416: monitorexit
    //   417: aload_2
    //   418: athrow
    //   419: aload_0
    //   420: getfield 12	com/google/android/gms/measurement/internal/zzv$zzc:zzaXS	Lcom/google/android/gms/measurement/internal/zzv;
    //   423: astore 5
    //   425: aload 5
    //   427: invokestatic 126	com/google/android/gms/measurement/internal/zzv:zze	(Lcom/google/android/gms/measurement/internal/zzv;)Lcom/google/android/gms/measurement/internal/zzv$zzc;
    //   430: astore 5
    //   432: aload_0
    //   433: aload 5
    //   435: if_acmpne +28 -> 463
    //   438: aload_0
    //   439: getfield 12	com/google/android/gms/measurement/internal/zzv$zzc:zzaXS	Lcom/google/android/gms/measurement/internal/zzv;
    //   442: astore 5
    //   444: aconst_null
    //   445: astore 6
    //   447: aload 5
    //   449: aconst_null
    //   450: invokestatic 128	com/google/android/gms/measurement/internal/zzv:zzb	(Lcom/google/android/gms/measurement/internal/zzv;Lcom/google/android/gms/measurement/internal/zzv$zzc;)Lcom/google/android/gms/measurement/internal/zzv$zzc;
    //   453: pop
    //   454: goto -299 -> 155
    //   457: astore_2
    //   458: aload 4
    //   460: monitorexit
    //   461: aload_2
    //   462: athrow
    //   463: aload_0
    //   464: getfield 12	com/google/android/gms/measurement/internal/zzv$zzc:zzaXS	Lcom/google/android/gms/measurement/internal/zzv;
    //   467: astore 5
    //   469: aload 5
    //   471: invokevirtual 39	com/google/android/gms/measurement/internal/zzv:zzAo	()Lcom/google/android/gms/measurement/internal/zzp;
    //   474: astore 5
    //   476: aload 5
    //   478: invokevirtual 131	com/google/android/gms/measurement/internal/zzp:zzCE	()Lcom/google/android/gms/measurement/internal/zzp$zza;
    //   481: astore 5
    //   483: ldc -123
    //   485: astore 6
    //   487: aload 5
    //   489: aload 6
    //   491: invokevirtual 136	com/google/android/gms/measurement/internal/zzp$zza:zzfg	(Ljava/lang/String;)V
    //   494: goto -339 -> 155
    // Local variable table:
    //   start	length	slot	name	signature
    //   0	497	0	this	zzc
    //   1	195	1	bool	boolean
    //   3	21	2	localObject1	Object
    //   34	3	2	localInterruptedException1	InterruptedException
    //   47	18	2	localObject2	Object
    //   71	88	2	localObject3	Object
    //   173	144	2	localObject4	Object
    //   326	3	2	localInterruptedException2	InterruptedException
    //   335	5	2	localObject5	Object
    //   345	20	2	localObject6	Object
    //   373	5	2	localObject7	Object
    //   383	16	2	localObject8	Object
    //   413	5	2	localObject9	Object
    //   457	5	2	localObject10	Object
    //   5	26	3	i	int
    //   88	400	5	localObject12	Object
    //   146	344	6	str	String
    //   207	4	7	l	long
    // Exception table:
    //   from	to	target	type
    //   13	17	34	java/lang/InterruptedException
    //   18	22	34	java/lang/InterruptedException
    //   23	27	34	java/lang/InterruptedException
    //   43	47	71	finally
    //   48	54	71	finally
    //   55	59	71	finally
    //   64	68	71	finally
    //   160	164	71	finally
    //   166	169	71	finally
    //   218	222	71	finally
    //   223	227	71	finally
    //   229	232	71	finally
    //   339	341	71	finally
    //   417	419	71	finally
    //   199	203	326	java/lang/InterruptedException
    //   210	215	326	java/lang/InterruptedException
    //   169	173	335	finally
    //   174	180	335	finally
    //   185	189	335	finally
    //   190	194	335	finally
    //   199	203	335	finally
    //   210	215	335	finally
    //   215	218	335	finally
    //   328	332	335	finally
    //   336	339	335	finally
    //   265	269	373	finally
    //   270	274	373	finally
    //   275	279	373	finally
    //   279	283	373	finally
    //   284	288	373	finally
    //   289	293	373	finally
    //   293	297	373	finally
    //   298	302	373	finally
    //   308	312	373	finally
    //   317	322	373	finally
    //   322	325	373	finally
    //   341	345	373	finally
    //   346	350	373	finally
    //   356	360	373	finally
    //   365	370	373	finally
    //   374	377	373	finally
    //   379	383	373	finally
    //   384	388	373	finally
    //   389	393	373	finally
    //   399	404	373	finally
    //   232	236	413	finally
    //   237	243	413	finally
    //   248	251	413	finally
    //   407	410	413	finally
    //   414	417	413	finally
    //   84	88	457	finally
    //   90	95	457	finally
    //   97	102	457	finally
    //   102	106	457	finally
    //   108	113	457	finally
    //   115	120	457	finally
    //   120	124	457	finally
    //   126	131	457	finally
    //   139	143	457	finally
    //   150	155	457	finally
    //   155	158	457	finally
    //   419	423	457	finally
    //   425	430	457	finally
    //   438	442	457	finally
    //   449	454	457	finally
    //   458	461	457	finally
    //   463	467	457	finally
    //   469	474	457	finally
    //   476	481	457	finally
    //   489	494	457	finally
  }
  
  public void zzfb()
  {
    synchronized (this.zzaXT)
    {
      Object localObject2 = this.zzaXT;
      localObject2.notifyAll();
      return;
    }
  }
}


/* Location:              C:\Users\haryo\Desktop\enjarify-master\presensi-enjarify.jar!\com\google\android\gms\measurement\internal\zzv$zzc.class
 * Java compiler version: 5 (49.0)
 * JD-Core Version:       0.7.1
 */