package org.apache.http.impl.execchain;

import org.apache.commons.logging.Log;
import org.apache.commons.logging.LogFactory;
import org.apache.http.ConnectionReuseStrategy;
import org.apache.http.HttpClientConnection;
import org.apache.http.HttpEntity;
import org.apache.http.HttpException;
import org.apache.http.HttpHost;
import org.apache.http.HttpRequest;
import org.apache.http.HttpRequestInterceptor;
import org.apache.http.HttpResponse;
import org.apache.http.ProtocolVersion;
import org.apache.http.StatusLine;
import org.apache.http.auth.AuthState;
import org.apache.http.client.AuthenticationStrategy;
import org.apache.http.client.UserTokenHandler;
import org.apache.http.client.config.RequestConfig;
import org.apache.http.client.protocol.HttpClientContext;
import org.apache.http.client.protocol.RequestClientConnControl;
import org.apache.http.conn.ConnectionKeepAliveStrategy;
import org.apache.http.conn.HttpClientConnectionManager;
import org.apache.http.conn.routing.BasicRouteDirector;
import org.apache.http.conn.routing.HttpRoute;
import org.apache.http.conn.routing.HttpRouteDirector;
import org.apache.http.conn.routing.RouteInfo;
import org.apache.http.conn.routing.RouteTracker;
import org.apache.http.entity.BufferedHttpEntity;
import org.apache.http.impl.auth.HttpAuthenticator;
import org.apache.http.message.BasicHttpRequest;
import org.apache.http.protocol.HttpProcessor;
import org.apache.http.protocol.HttpRequestExecutor;
import org.apache.http.protocol.ImmutableHttpProcessor;
import org.apache.http.protocol.RequestTargetHost;
import org.apache.http.util.Args;
import org.apache.http.util.EntityUtils;

public class MainClientExec
  implements ClientExecChain
{
  private final HttpAuthenticator authenticator;
  private final HttpClientConnectionManager connManager;
  private final ConnectionKeepAliveStrategy keepAliveStrategy;
  private final Log log;
  private final AuthenticationStrategy proxyAuthStrategy;
  private final HttpProcessor proxyHttpProcessor;
  private final HttpRequestExecutor requestExecutor;
  private final ConnectionReuseStrategy reuseStrategy;
  private final HttpRouteDirector routeDirector;
  private final AuthenticationStrategy targetAuthStrategy;
  private final UserTokenHandler userTokenHandler;
  
  public MainClientExec(HttpRequestExecutor paramHttpRequestExecutor, HttpClientConnectionManager paramHttpClientConnectionManager, ConnectionReuseStrategy paramConnectionReuseStrategy, ConnectionKeepAliveStrategy paramConnectionKeepAliveStrategy, AuthenticationStrategy paramAuthenticationStrategy1, AuthenticationStrategy paramAuthenticationStrategy2, UserTokenHandler paramUserTokenHandler)
  {
    Object localObject1 = LogFactory.getLog(getClass());
    this.log = ((Log)localObject1);
    Args.notNull(paramHttpRequestExecutor, "HTTP request executor");
    Args.notNull(paramHttpClientConnectionManager, "Client connection manager");
    Args.notNull(paramConnectionReuseStrategy, "Connection reuse strategy");
    Args.notNull(paramConnectionKeepAliveStrategy, "Connection keep alive strategy");
    Args.notNull(paramAuthenticationStrategy1, "Target authentication strategy");
    Args.notNull(paramAuthenticationStrategy2, "Proxy authentication strategy");
    Args.notNull(paramUserTokenHandler, "User token handler");
    localObject1 = new org/apache/http/impl/auth/HttpAuthenticator;
    ((HttpAuthenticator)localObject1).<init>();
    this.authenticator = ((HttpAuthenticator)localObject1);
    localObject1 = new org/apache/http/protocol/ImmutableHttpProcessor;
    HttpRequestInterceptor[] arrayOfHttpRequestInterceptor = new HttpRequestInterceptor[2];
    Object localObject2 = new org/apache/http/protocol/RequestTargetHost;
    ((RequestTargetHost)localObject2).<init>();
    arrayOfHttpRequestInterceptor[0] = localObject2;
    localObject2 = new org/apache/http/client/protocol/RequestClientConnControl;
    ((RequestClientConnControl)localObject2).<init>();
    arrayOfHttpRequestInterceptor[1] = localObject2;
    ((ImmutableHttpProcessor)localObject1).<init>(arrayOfHttpRequestInterceptor);
    this.proxyHttpProcessor = ((HttpProcessor)localObject1);
    localObject1 = new org/apache/http/conn/routing/BasicRouteDirector;
    ((BasicRouteDirector)localObject1).<init>();
    this.routeDirector = ((HttpRouteDirector)localObject1);
    this.requestExecutor = paramHttpRequestExecutor;
    this.connManager = paramHttpClientConnectionManager;
    this.reuseStrategy = paramConnectionReuseStrategy;
    this.keepAliveStrategy = paramConnectionKeepAliveStrategy;
    this.targetAuthStrategy = paramAuthenticationStrategy1;
    this.proxyAuthStrategy = paramAuthenticationStrategy2;
    this.userTokenHandler = paramUserTokenHandler;
  }
  
  private boolean createTunnelToProxy(HttpRoute paramHttpRoute, int paramInt, HttpClientContext paramHttpClientContext)
  {
    HttpException localHttpException = new org/apache/http/HttpException;
    localHttpException.<init>("Proxy chains are not supported.");
    throw localHttpException;
  }
  
  private boolean createTunnelToTarget(AuthState paramAuthState, HttpClientConnection paramHttpClientConnection, HttpRoute paramHttpRoute, HttpRequest paramHttpRequest, HttpClientContext paramHttpClientContext)
  {
    RequestConfig localRequestConfig = paramHttpClientContext.getRequestConfig();
    int i = localRequestConfig.getConnectTimeout();
    Object localObject1 = paramHttpRoute.getTargetHost();
    Object localObject2 = paramHttpRoute.getProxyHost();
    Object localObject3 = null;
    localObject1 = ((HttpHost)localObject1).toHostString();
    BasicHttpRequest localBasicHttpRequest = new org/apache/http/message/BasicHttpRequest;
    Object localObject4 = paramHttpRequest.getProtocolVersion();
    localBasicHttpRequest.<init>("CONNECT", (String)localObject1, (ProtocolVersion)localObject4);
    localObject1 = this.requestExecutor;
    Object localObject5 = this.proxyHttpProcessor;
    ((HttpRequestExecutor)localObject1).preProcess(localBasicHttpRequest, (HttpProcessor)localObject5, paramHttpClientContext);
    while (localObject3 == null)
    {
      int j = paramHttpClientConnection.isOpen();
      if (j == 0)
      {
        localObject3 = this.connManager;
        if (i <= 0) {
          break label250;
        }
        j = i;
      }
      for (;;)
      {
        ((HttpClientConnectionManager)localObject3).connect(paramHttpClientConnection, paramHttpRoute, j, paramHttpClientContext);
        localBasicHttpRequest.removeHeaders("Proxy-Authorization");
        this.authenticator.generateAuthResponse(localBasicHttpRequest, paramAuthState, paramHttpClientContext);
        localObject3 = this.requestExecutor.execute(localBasicHttpRequest, paramHttpClientConnection, paramHttpClientContext);
        localObject1 = ((HttpResponse)localObject3).getStatusLine();
        int k = ((StatusLine)localObject1).getStatusCode();
        int n = 200;
        if (k >= n) {
          break;
        }
        localObject1 = new org/apache/http/HttpException;
        localObject2 = new java/lang/StringBuilder;
        ((StringBuilder)localObject2).<init>();
        localObject2 = ((StringBuilder)localObject2).append("Unexpected response to CONNECT request: ");
        localObject3 = ((HttpResponse)localObject3).getStatusLine();
        localObject2 = localObject3;
        ((HttpException)localObject1).<init>((String)localObject2);
        throw ((Throwable)localObject1);
        label250:
        k = 0;
        localObject1 = null;
      }
      boolean bool = localRequestConfig.isAuthenticationEnabled();
      if (bool)
      {
        localObject1 = this.authenticator;
        localObject5 = this.proxyAuthStrategy;
        localObject4 = paramAuthState;
        bool = ((HttpAuthenticator)localObject1).isAuthenticationRequested((HttpHost)localObject2, (HttpResponse)localObject3, (AuthenticationStrategy)localObject5, paramAuthState, paramHttpClientContext);
        if (bool)
        {
          localObject1 = this.authenticator;
          localObject5 = this.proxyAuthStrategy;
          bool = ((HttpAuthenticator)localObject1).handleAuthChallenge((HttpHost)localObject2, (HttpResponse)localObject3, (AuthenticationStrategy)localObject5, paramAuthState, paramHttpClientContext);
          if (bool)
          {
            localObject1 = this.reuseStrategy;
            bool = ((ConnectionReuseStrategy)localObject1).keepAlive((HttpResponse)localObject3, paramHttpClientContext);
            if (bool)
            {
              localObject1 = this.log;
              localObject5 = "Connection kept alive";
              ((Log)localObject1).debug(localObject5);
              localObject1 = ((HttpResponse)localObject3).getEntity();
              EntityUtils.consume((HttpEntity)localObject1);
            }
            for (;;)
            {
              localObject3 = null;
              break;
              paramHttpClientConnection.close();
            }
          }
        }
      }
    }
    localObject1 = ((HttpResponse)localObject3).getStatusLine();
    int m = ((StatusLine)localObject1).getStatusCode();
    int i1 = 299;
    if (m > i1)
    {
      localObject1 = ((HttpResponse)localObject3).getEntity();
      if (localObject1 != null)
      {
        localObject2 = new org/apache/http/entity/BufferedHttpEntity;
        ((BufferedHttpEntity)localObject2).<init>((HttpEntity)localObject1);
        ((HttpResponse)localObject3).setEntity((HttpEntity)localObject2);
      }
      paramHttpClientConnection.close();
      localObject1 = new org/apache/http/impl/execchain/TunnelRefusedException;
      localObject2 = new java/lang/StringBuilder;
      ((StringBuilder)localObject2).<init>();
      localObject2 = ((StringBuilder)localObject2).append("CONNECT refused by proxy: ");
      localObject5 = ((HttpResponse)localObject3).getStatusLine();
      localObject2 = localObject5;
      ((TunnelRefusedException)localObject1).<init>((String)localObject2, (HttpResponse)localObject3);
      throw ((Throwable)localObject1);
    }
    return false;
  }
  
  private boolean needAuthentication(AuthState paramAuthState1, AuthState paramAuthState2, HttpRoute paramHttpRoute, HttpResponse paramHttpResponse, HttpClientContext paramHttpClientContext)
  {
    Object localObject1 = paramHttpClientContext.getRequestConfig();
    boolean bool1 = ((RequestConfig)localObject1).isAuthenticationEnabled();
    Object localObject2;
    Object localObject3;
    Object localObject4;
    if (bool1)
    {
      localObject1 = paramHttpClientContext.getTargetHost();
      if (localObject1 == null) {
        localObject1 = paramHttpRoute.getTargetHost();
      }
      int i = ((HttpHost)localObject1).getPort();
      if (i >= 0) {
        break label262;
      }
      localObject2 = new org/apache/http/HttpHost;
      localObject3 = ((HttpHost)localObject1).getHostName();
      localObject4 = paramHttpRoute.getTargetHost();
      int j = ((HttpHost)localObject4).getPort();
      localObject1 = ((HttpHost)localObject1).getSchemeName();
      ((HttpHost)localObject2).<init>((String)localObject3, j, (String)localObject1);
    }
    for (;;)
    {
      localObject1 = this.authenticator;
      localObject4 = this.targetAuthStrategy;
      localObject3 = paramHttpResponse;
      Object localObject5 = paramHttpClientContext;
      bool1 = ((HttpAuthenticator)localObject1).isAuthenticationRequested((HttpHost)localObject2, paramHttpResponse, (AuthenticationStrategy)localObject4, paramAuthState1, paramHttpClientContext);
      localObject4 = paramHttpRoute.getProxyHost();
      if (localObject4 == null) {
        localObject4 = paramHttpRoute.getTargetHost();
      }
      localObject3 = this.authenticator;
      localObject5 = this.proxyAuthStrategy;
      boolean bool2 = ((HttpAuthenticator)localObject3).isAuthenticationRequested((HttpHost)localObject4, paramHttpResponse, (AuthenticationStrategy)localObject5, paramAuthState2, paramHttpClientContext);
      if (bool1)
      {
        localObject1 = this.authenticator;
        localObject4 = this.targetAuthStrategy;
        localObject3 = paramHttpResponse;
        localObject5 = paramHttpClientContext;
        bool1 = ((HttpAuthenticator)localObject1).handleAuthChallenge((HttpHost)localObject2, paramHttpResponse, (AuthenticationStrategy)localObject4, paramAuthState1, paramHttpClientContext);
      }
      for (;;)
      {
        return bool1;
        if (bool2)
        {
          localObject3 = this.authenticator;
          localObject5 = this.proxyAuthStrategy;
          bool1 = ((HttpAuthenticator)localObject3).handleAuthChallenge((HttpHost)localObject4, paramHttpResponse, (AuthenticationStrategy)localObject5, paramAuthState2, paramHttpClientContext);
        }
        else
        {
          bool1 = false;
          localObject1 = null;
        }
      }
      label262:
      localObject2 = localObject1;
    }
  }
  
  void establishRoute(AuthState paramAuthState, HttpClientConnection paramHttpClientConnection, HttpRoute paramHttpRoute, HttpRequest paramHttpRequest, HttpClientContext paramHttpClientContext)
  {
    StringBuilder localStringBuilder = null;
    Object localObject1 = paramHttpClientContext.getRequestConfig();
    int i = ((RequestConfig)localObject1).getConnectTimeout();
    RouteTracker localRouteTracker = new org/apache/http/conn/routing/RouteTracker;
    localRouteTracker.<init>(paramHttpRoute);
    localObject1 = localRouteTracker.toRoute();
    HttpRouteDirector localHttpRouteDirector = this.routeDirector;
    int j = localHttpRouteDirector.nextStep(paramHttpRoute, (RouteInfo)localObject1);
    Object localObject2;
    Object localObject3;
    label160:
    int m;
    switch (j)
    {
    default: 
      localObject1 = new java/lang/IllegalStateException;
      localObject2 = new java/lang/StringBuilder;
      ((StringBuilder)localObject2).<init>();
      localObject2 = "Unknown step indicator " + j + " from RouteDirector.";
      ((IllegalStateException)localObject1).<init>((String)localObject2);
      throw ((Throwable)localObject1);
    case 1: 
      localObject3 = this.connManager;
      if (i > 0)
      {
        int k = i;
        ((HttpClientConnectionManager)localObject3).connect(paramHttpClientConnection, paramHttpRoute, k, paramHttpClientContext);
        m = paramHttpRoute.isSecure();
        localRouteTracker.connectTarget(m);
      }
      break;
    }
    while (j <= 0)
    {
      return;
      m = 0;
      localObject1 = null;
      break label160;
      localObject3 = this.connManager;
      if (i > 0) {
        m = i;
      }
      for (;;)
      {
        ((HttpClientConnectionManager)localObject3).connect(paramHttpClientConnection, paramHttpRoute, m, paramHttpClientContext);
        localObject1 = paramHttpRoute.getProxyHost();
        localRouteTracker.connectProxy((HttpHost)localObject1, false);
        break;
        bool1 = false;
        localObject1 = null;
      }
      boolean bool1 = createTunnelToTarget(paramAuthState, paramHttpClientConnection, paramHttpRoute, paramHttpRequest, paramHttpClientContext);
      localObject3 = this.log;
      Object localObject4 = "Tunnel to target created.";
      ((Log)localObject3).debug(localObject4);
      localRouteTracker.tunnelTarget(bool1);
      continue;
      int n = ((HttpRoute)localObject1).getHopCount() + -1;
      boolean bool3 = createTunnelToProxy(paramHttpRoute, n, paramHttpClientContext);
      localObject4 = this.log;
      String str = "Tunnel to proxy created.";
      ((Log)localObject4).debug(str);
      localObject1 = paramHttpRoute.getHopTarget(n);
      localRouteTracker.tunnelProxy((HttpHost)localObject1, bool3);
      continue;
      localObject1 = this.connManager;
      ((HttpClientConnectionManager)localObject1).upgrade(paramHttpClientConnection, paramHttpRoute, paramHttpClientContext);
      boolean bool2 = paramHttpRoute.isSecure();
      localRouteTracker.layerProtocol(bool2);
      continue;
      localObject2 = new org/apache/http/HttpException;
      localStringBuilder = new java/lang/StringBuilder;
      localStringBuilder.<init>();
      localObject1 = "Unable to establish route: planned = " + paramHttpRoute + "; current = " + localObject1;
      ((HttpException)localObject2).<init>((String)localObject1);
      throw ((Throwable)localObject2);
      localObject1 = this.connManager;
      ((HttpClientConnectionManager)localObject1).routeComplete(paramHttpClientConnection, paramHttpRoute, paramHttpClientContext);
    }
  }
  
  /* Error */
  public org.apache.http.client.methods.CloseableHttpResponse execute(HttpRoute paramHttpRoute, org.apache.http.client.methods.HttpRequestWrapper paramHttpRequestWrapper, HttpClientContext paramHttpClientContext, org.apache.http.client.methods.HttpExecutionAware paramHttpExecutionAware)
  {
    // Byte code:
    //   0: aload_1
    //   1: ldc_w 351
    //   4: invokestatic 51	org/apache/http/util/Args:notNull	(Ljava/lang/Object;Ljava/lang/String;)Ljava/lang/Object;
    //   7: pop
    //   8: aload_2
    //   9: ldc_w 353
    //   12: invokestatic 51	org/apache/http/util/Args:notNull	(Ljava/lang/Object;Ljava/lang/String;)Ljava/lang/Object;
    //   15: pop
    //   16: aload_3
    //   17: ldc_w 355
    //   20: invokestatic 51	org/apache/http/util/Args:notNull	(Ljava/lang/Object;Ljava/lang/String;)Ljava/lang/Object;
    //   23: pop
    //   24: aload_3
    //   25: invokevirtual 359	org/apache/http/client/protocol/HttpClientContext:getTargetAuthState	()Lorg/apache/http/auth/AuthState;
    //   28: astore 5
    //   30: aload 5
    //   32: ifnonnull +1790 -> 1822
    //   35: new 361	org/apache/http/auth/AuthState
    //   38: astore 5
    //   40: aload 5
    //   42: invokespecial 362	org/apache/http/auth/AuthState:<init>	()V
    //   45: ldc_w 364
    //   48: astore 6
    //   50: aload_3
    //   51: aload 6
    //   53: aload 5
    //   55: invokevirtual 368	org/apache/http/client/protocol/HttpClientContext:setAttribute	(Ljava/lang/String;Ljava/lang/Object;)V
    //   58: aload 5
    //   60: astore 7
    //   62: aload_3
    //   63: invokevirtual 371	org/apache/http/client/protocol/HttpClientContext:getProxyAuthState	()Lorg/apache/http/auth/AuthState;
    //   66: astore 6
    //   68: aload 6
    //   70: ifnonnull +26 -> 96
    //   73: new 361	org/apache/http/auth/AuthState
    //   76: astore 6
    //   78: aload 6
    //   80: invokespecial 362	org/apache/http/auth/AuthState:<init>	()V
    //   83: ldc_w 373
    //   86: astore 5
    //   88: aload_3
    //   89: aload 5
    //   91: aload 6
    //   93: invokevirtual 368	org/apache/http/client/protocol/HttpClientContext:setAttribute	(Ljava/lang/String;Ljava/lang/Object;)V
    //   96: aload_2
    //   97: instanceof 375
    //   100: istore 8
    //   102: iload 8
    //   104: ifeq +17 -> 121
    //   107: aload_2
    //   108: astore 5
    //   110: aload_2
    //   111: checkcast 375	org/apache/http/HttpEntityEnclosingRequest
    //   114: astore 5
    //   116: aload 5
    //   118: invokestatic 381	org/apache/http/impl/execchain/RequestEntityProxy:enhance	(Lorg/apache/http/HttpEntityEnclosingRequest;)V
    //   121: aload_3
    //   122: invokevirtual 385	org/apache/http/client/protocol/HttpClientContext:getUserToken	()Ljava/lang/Object;
    //   125: astore 9
    //   127: aload_0
    //   128: getfield 94	org/apache/http/impl/execchain/MainClientExec:connManager	Lorg/apache/http/conn/HttpClientConnectionManager;
    //   131: aload_1
    //   132: aload 9
    //   134: invokeinterface 389 3 0
    //   139: astore 5
    //   141: aload 4
    //   143: ifnull +50 -> 193
    //   146: aload 4
    //   148: invokeinterface 394 1 0
    //   153: istore 10
    //   155: iload 10
    //   157: ifeq +27 -> 184
    //   160: aload 5
    //   162: invokeinterface 399 1 0
    //   167: pop
    //   168: new 401	org/apache/http/impl/execchain/RequestAbortedException
    //   171: astore 5
    //   173: aload 5
    //   175: ldc_w 403
    //   178: invokespecial 404	org/apache/http/impl/execchain/RequestAbortedException:<init>	(Ljava/lang/String;)V
    //   181: aload 5
    //   183: athrow
    //   184: aload 4
    //   186: aload 5
    //   188: invokeinterface 408 2 0
    //   193: aload_3
    //   194: invokevirtual 117	org/apache/http/client/protocol/HttpClientContext:getRequestConfig	()Lorg/apache/http/client/config/RequestConfig;
    //   197: astore 11
    //   199: aload 11
    //   201: invokevirtual 411	org/apache/http/client/config/RequestConfig:getConnectionRequestTimeout	()I
    //   204: istore 10
    //   206: iload 10
    //   208: ifle +245 -> 453
    //   211: iload 10
    //   213: i2l
    //   214: lstore 12
    //   216: getstatic 417	java/util/concurrent/TimeUnit:MILLISECONDS	Ljava/util/concurrent/TimeUnit;
    //   219: astore 14
    //   221: aload 5
    //   223: lload 12
    //   225: aload 14
    //   227: invokeinterface 421 4 0
    //   232: astore 15
    //   234: ldc_w 423
    //   237: astore 5
    //   239: aload_3
    //   240: aload 5
    //   242: aload 15
    //   244: invokevirtual 368	org/apache/http/client/protocol/HttpClientContext:setAttribute	(Ljava/lang/String;Ljava/lang/Object;)V
    //   247: aload 11
    //   249: invokevirtual 426	org/apache/http/client/config/RequestConfig:isStaleConnectionCheckEnabled	()Z
    //   252: istore 8
    //   254: iload 8
    //   256: ifeq +78 -> 334
    //   259: aload 15
    //   261: invokeinterface 163 1 0
    //   266: istore 8
    //   268: iload 8
    //   270: ifeq +64 -> 334
    //   273: aload_0
    //   274: getfield 43	org/apache/http/impl/execchain/MainClientExec:log	Lorg/apache/commons/logging/Log;
    //   277: astore 5
    //   279: ldc_w 428
    //   282: astore 16
    //   284: aload 5
    //   286: aload 16
    //   288: invokeinterface 233 2 0
    //   293: aload 15
    //   295: invokeinterface 431 1 0
    //   300: istore 8
    //   302: iload 8
    //   304: ifeq +30 -> 334
    //   307: aload_0
    //   308: getfield 43	org/apache/http/impl/execchain/MainClientExec:log	Lorg/apache/commons/logging/Log;
    //   311: astore 5
    //   313: ldc_w 433
    //   316: astore 16
    //   318: aload 5
    //   320: aload 16
    //   322: invokeinterface 233 2 0
    //   327: aload 15
    //   329: invokeinterface 246 1 0
    //   334: new 435	org/apache/http/impl/execchain/ConnectionHolder
    //   337: astore 17
    //   339: aload_0
    //   340: getfield 43	org/apache/http/impl/execchain/MainClientExec:log	Lorg/apache/commons/logging/Log;
    //   343: astore 5
    //   345: aload_0
    //   346: getfield 94	org/apache/http/impl/execchain/MainClientExec:connManager	Lorg/apache/http/conn/HttpClientConnectionManager;
    //   349: astore 16
    //   351: aload 17
    //   353: aload 5
    //   355: aload 16
    //   357: aload 15
    //   359: invokespecial 438	org/apache/http/impl/execchain/ConnectionHolder:<init>	(Lorg/apache/commons/logging/Log;Lorg/apache/http/conn/HttpClientConnectionManager;Lorg/apache/http/HttpClientConnection;)V
    //   362: aload 4
    //   364: ifnull +12 -> 376
    //   367: aload 4
    //   369: aload 17
    //   371: invokeinterface 408 2 0
    //   376: iconst_1
    //   377: istore 8
    //   379: iload 8
    //   381: istore 18
    //   383: iconst_1
    //   384: istore 8
    //   386: iload 18
    //   388: iload 8
    //   390: if_icmple +127 -> 517
    //   393: aload_2
    //   394: checkcast 144	org/apache/http/HttpRequest
    //   397: invokestatic 442	org/apache/http/impl/execchain/RequestEntityProxy:isRepeatable	(Lorg/apache/http/HttpRequest;)Z
    //   400: istore 8
    //   402: iload 8
    //   404: ifne +113 -> 517
    //   407: new 444	org/apache/http/client/NonRepeatableRequestException
    //   410: astore 5
    //   412: ldc_w 446
    //   415: astore 6
    //   417: aload 5
    //   419: aload 6
    //   421: invokespecial 447	org/apache/http/client/NonRepeatableRequestException:<init>	(Ljava/lang/String;)V
    //   424: aload 5
    //   426: athrow
    //   427: astore 5
    //   429: new 449	java/io/InterruptedIOException
    //   432: astore 6
    //   434: aload 6
    //   436: ldc_w 451
    //   439: invokespecial 452	java/io/InterruptedIOException:<init>	(Ljava/lang/String;)V
    //   442: aload 6
    //   444: aload 5
    //   446: invokevirtual 456	java/io/InterruptedIOException:initCause	(Ljava/lang/Throwable;)Ljava/lang/Throwable;
    //   449: pop
    //   450: aload 6
    //   452: athrow
    //   453: lconst_0
    //   454: lstore 12
    //   456: goto -240 -> 216
    //   459: astore 5
    //   461: invokestatic 462	java/lang/Thread:currentThread	()Ljava/lang/Thread;
    //   464: invokevirtual 465	java/lang/Thread:interrupt	()V
    //   467: new 401	org/apache/http/impl/execchain/RequestAbortedException
    //   470: astore 6
    //   472: aload 6
    //   474: ldc_w 403
    //   477: aload 5
    //   479: invokespecial 468	org/apache/http/impl/execchain/RequestAbortedException:<init>	(Ljava/lang/String;Ljava/lang/Throwable;)V
    //   482: aload 6
    //   484: athrow
    //   485: astore 5
    //   487: aload 5
    //   489: invokevirtual 474	java/util/concurrent/ExecutionException:getCause	()Ljava/lang/Throwable;
    //   492: astore 6
    //   494: aload 6
    //   496: ifnonnull +1319 -> 1815
    //   499: new 401	org/apache/http/impl/execchain/RequestAbortedException
    //   502: astore 6
    //   504: aload 6
    //   506: ldc_w 476
    //   509: aload 5
    //   511: invokespecial 468	org/apache/http/impl/execchain/RequestAbortedException:<init>	(Ljava/lang/String;Ljava/lang/Throwable;)V
    //   514: aload 6
    //   516: athrow
    //   517: aload 4
    //   519: ifnull +47 -> 566
    //   522: aload 4
    //   524: invokeinterface 394 1 0
    //   529: istore 8
    //   531: iload 8
    //   533: ifeq +33 -> 566
    //   536: new 401	org/apache/http/impl/execchain/RequestAbortedException
    //   539: astore 5
    //   541: ldc_w 403
    //   544: astore 6
    //   546: aload 5
    //   548: aload 6
    //   550: invokespecial 404	org/apache/http/impl/execchain/RequestAbortedException:<init>	(Ljava/lang/String;)V
    //   553: aload 5
    //   555: athrow
    //   556: astore 5
    //   558: aload 17
    //   560: invokevirtual 479	org/apache/http/impl/execchain/ConnectionHolder:abortConnection	()V
    //   563: aload 5
    //   565: athrow
    //   566: aload 15
    //   568: invokeinterface 163 1 0
    //   573: istore 8
    //   575: iload 8
    //   577: ifne +80 -> 657
    //   580: aload_0
    //   581: getfield 43	org/apache/http/impl/execchain/MainClientExec:log	Lorg/apache/commons/logging/Log;
    //   584: astore 5
    //   586: new 196	java/lang/StringBuilder
    //   589: astore 16
    //   591: aload 16
    //   593: invokespecial 197	java/lang/StringBuilder:<init>	()V
    //   596: ldc_w 481
    //   599: astore 14
    //   601: aload 16
    //   603: aload 14
    //   605: invokevirtual 203	java/lang/StringBuilder:append	(Ljava/lang/String;)Ljava/lang/StringBuilder;
    //   608: astore 16
    //   610: aload 16
    //   612: aload_1
    //   613: invokevirtual 206	java/lang/StringBuilder:append	(Ljava/lang/Object;)Ljava/lang/StringBuilder;
    //   616: astore 16
    //   618: aload 16
    //   620: invokevirtual 209	java/lang/StringBuilder:toString	()Ljava/lang/String;
    //   623: astore 16
    //   625: aload 5
    //   627: aload 16
    //   629: invokeinterface 233 2 0
    //   634: aload_0
    //   635: astore 5
    //   637: aload_1
    //   638: astore 16
    //   640: aload_2
    //   641: astore 14
    //   643: aload_0
    //   644: aload 6
    //   646: aload 15
    //   648: aload_1
    //   649: aload_2
    //   650: checkcast 144	org/apache/http/HttpRequest
    //   653: aload_3
    //   654: invokevirtual 485	org/apache/http/impl/execchain/MainClientExec:establishRoute	(Lorg/apache/http/auth/AuthState;Lorg/apache/http/HttpClientConnection;Lorg/apache/http/conn/routing/HttpRoute;Lorg/apache/http/HttpRequest;Lorg/apache/http/client/protocol/HttpClientContext;)V
    //   657: aload 11
    //   659: invokevirtual 488	org/apache/http/client/config/RequestConfig:getSocketTimeout	()I
    //   662: istore 8
    //   664: iload 8
    //   666: iflt +12 -> 678
    //   669: aload 15
    //   671: iload 8
    //   673: invokeinterface 492 2 0
    //   678: aload 4
    //   680: ifnull +199 -> 879
    //   683: aload 4
    //   685: invokeinterface 394 1 0
    //   690: istore 8
    //   692: iload 8
    //   694: ifeq +185 -> 879
    //   697: new 401	org/apache/http/impl/execchain/RequestAbortedException
    //   700: astore 5
    //   702: ldc_w 403
    //   705: astore 6
    //   707: aload 5
    //   709: aload 6
    //   711: invokespecial 404	org/apache/http/impl/execchain/RequestAbortedException:<init>	(Ljava/lang/String;)V
    //   714: aload 5
    //   716: athrow
    //   717: astore 5
    //   719: aload 17
    //   721: invokevirtual 479	org/apache/http/impl/execchain/ConnectionHolder:abortConnection	()V
    //   724: aload 5
    //   726: athrow
    //   727: astore 5
    //   729: aload_0
    //   730: getfield 43	org/apache/http/impl/execchain/MainClientExec:log	Lorg/apache/commons/logging/Log;
    //   733: astore 6
    //   735: aload 6
    //   737: invokeinterface 495 1 0
    //   742: istore 19
    //   744: iload 19
    //   746: ifeq +25 -> 771
    //   749: aload_0
    //   750: getfield 43	org/apache/http/impl/execchain/MainClientExec:log	Lorg/apache/commons/logging/Log;
    //   753: astore 6
    //   755: aload 5
    //   757: invokevirtual 498	org/apache/http/impl/execchain/TunnelRefusedException:getMessage	()Ljava/lang/String;
    //   760: astore 15
    //   762: aload 6
    //   764: aload 15
    //   766: invokeinterface 233 2 0
    //   771: aload 5
    //   773: invokevirtual 502	org/apache/http/impl/execchain/TunnelRefusedException:getResponse	()Lorg/apache/http/HttpResponse;
    //   776: astore 20
    //   778: aload 9
    //   780: ifnonnull +1028 -> 1808
    //   783: aload_0
    //   784: getfield 104	org/apache/http/impl/execchain/MainClientExec:userTokenHandler	Lorg/apache/http/client/UserTokenHandler;
    //   787: astore 5
    //   789: aload 5
    //   791: aload_3
    //   792: invokeinterface 507 2 0
    //   797: astore 5
    //   799: ldc_w 509
    //   802: astore 6
    //   804: aload_3
    //   805: aload 6
    //   807: aload 5
    //   809: invokevirtual 368	org/apache/http/client/protocol/HttpClientContext:setAttribute	(Ljava/lang/String;Ljava/lang/Object;)V
    //   812: aload 5
    //   814: ifnull +10 -> 824
    //   817: aload 17
    //   819: aload 5
    //   821: invokevirtual 512	org/apache/http/impl/execchain/ConnectionHolder:setState	(Ljava/lang/Object;)V
    //   824: aload 20
    //   826: invokeinterface 237 1 0
    //   831: astore 5
    //   833: aload 5
    //   835: ifnull +17 -> 852
    //   838: aload 5
    //   840: invokeinterface 517 1 0
    //   845: istore 8
    //   847: iload 8
    //   849: ifne +942 -> 1791
    //   852: aload 17
    //   854: invokevirtual 520	org/apache/http/impl/execchain/ConnectionHolder:releaseConnection	()V
    //   857: new 522	org/apache/http/impl/execchain/HttpResponseProxy
    //   860: astore 5
    //   862: iconst_0
    //   863: istore 19
    //   865: aconst_null
    //   866: astore 6
    //   868: aload 5
    //   870: aload 20
    //   872: aconst_null
    //   873: invokespecial 525	org/apache/http/impl/execchain/HttpResponseProxy:<init>	(Lorg/apache/http/HttpResponse;Lorg/apache/http/impl/execchain/ConnectionHolder;)V
    //   876: aload 5
    //   878: areturn
    //   879: aload_0
    //   880: getfield 43	org/apache/http/impl/execchain/MainClientExec:log	Lorg/apache/commons/logging/Log;
    //   883: astore 5
    //   885: aload 5
    //   887: invokeinterface 495 1 0
    //   892: istore 8
    //   894: iload 8
    //   896: ifeq +67 -> 963
    //   899: aload_0
    //   900: getfield 43	org/apache/http/impl/execchain/MainClientExec:log	Lorg/apache/commons/logging/Log;
    //   903: astore 5
    //   905: new 196	java/lang/StringBuilder
    //   908: astore 16
    //   910: aload 16
    //   912: invokespecial 197	java/lang/StringBuilder:<init>	()V
    //   915: ldc_w 527
    //   918: astore 14
    //   920: aload 16
    //   922: aload 14
    //   924: invokevirtual 203	java/lang/StringBuilder:append	(Ljava/lang/String;)Ljava/lang/StringBuilder;
    //   927: astore 16
    //   929: aload_2
    //   930: checkcast 529	org/apache/http/client/methods/HttpRequestWrapper
    //   933: invokevirtual 533	org/apache/http/client/methods/HttpRequestWrapper:getRequestLine	()Lorg/apache/http/RequestLine;
    //   936: astore 14
    //   938: aload 16
    //   940: aload 14
    //   942: invokevirtual 206	java/lang/StringBuilder:append	(Ljava/lang/Object;)Ljava/lang/StringBuilder;
    //   945: astore 16
    //   947: aload 16
    //   949: invokevirtual 209	java/lang/StringBuilder:toString	()Ljava/lang/String;
    //   952: astore 16
    //   954: aload 5
    //   956: aload 16
    //   958: invokeinterface 233 2 0
    //   963: ldc_w 535
    //   966: astore 5
    //   968: aload_2
    //   969: checkcast 529	org/apache/http/client/methods/HttpRequestWrapper
    //   972: aload 5
    //   974: invokevirtual 539	org/apache/http/client/methods/HttpRequestWrapper:containsHeader	(Ljava/lang/String;)Z
    //   977: istore 8
    //   979: iload 8
    //   981: ifne +103 -> 1084
    //   984: aload_0
    //   985: getfield 43	org/apache/http/impl/execchain/MainClientExec:log	Lorg/apache/commons/logging/Log;
    //   988: astore 5
    //   990: aload 5
    //   992: invokeinterface 495 1 0
    //   997: istore 8
    //   999: iload 8
    //   1001: ifeq +65 -> 1066
    //   1004: aload_0
    //   1005: getfield 43	org/apache/http/impl/execchain/MainClientExec:log	Lorg/apache/commons/logging/Log;
    //   1008: astore 5
    //   1010: new 196	java/lang/StringBuilder
    //   1013: astore 16
    //   1015: aload 16
    //   1017: invokespecial 197	java/lang/StringBuilder:<init>	()V
    //   1020: ldc_w 541
    //   1023: astore 14
    //   1025: aload 16
    //   1027: aload 14
    //   1029: invokevirtual 203	java/lang/StringBuilder:append	(Ljava/lang/String;)Ljava/lang/StringBuilder;
    //   1032: astore 16
    //   1034: aload 7
    //   1036: invokevirtual 545	org/apache/http/auth/AuthState:getState	()Lorg/apache/http/auth/AuthProtocolState;
    //   1039: astore 14
    //   1041: aload 16
    //   1043: aload 14
    //   1045: invokevirtual 206	java/lang/StringBuilder:append	(Ljava/lang/Object;)Ljava/lang/StringBuilder;
    //   1048: astore 16
    //   1050: aload 16
    //   1052: invokevirtual 209	java/lang/StringBuilder:toString	()Ljava/lang/String;
    //   1055: astore 16
    //   1057: aload 5
    //   1059: aload 16
    //   1061: invokeinterface 233 2 0
    //   1066: aload_0
    //   1067: getfield 68	org/apache/http/impl/execchain/MainClientExec:authenticator	Lorg/apache/http/impl/auth/HttpAuthenticator;
    //   1070: astore 5
    //   1072: aload 5
    //   1074: aload_2
    //   1075: checkcast 144	org/apache/http/HttpRequest
    //   1078: aload 7
    //   1080: aload_3
    //   1081: invokevirtual 178	org/apache/http/impl/auth/HttpAuthenticator:generateAuthResponse	(Lorg/apache/http/HttpRequest;Lorg/apache/http/auth/AuthState;Lorg/apache/http/protocol/HttpContext;)V
    //   1084: ldc -85
    //   1086: astore 5
    //   1088: aload_2
    //   1089: checkcast 529	org/apache/http/client/methods/HttpRequestWrapper
    //   1092: aload 5
    //   1094: invokevirtual 539	org/apache/http/client/methods/HttpRequestWrapper:containsHeader	(Ljava/lang/String;)Z
    //   1097: istore 8
    //   1099: iload 8
    //   1101: ifne +114 -> 1215
    //   1104: aload_1
    //   1105: invokevirtual 548	org/apache/http/conn/routing/HttpRoute:isTunnelled	()Z
    //   1108: istore 8
    //   1110: iload 8
    //   1112: ifne +103 -> 1215
    //   1115: aload_0
    //   1116: getfield 43	org/apache/http/impl/execchain/MainClientExec:log	Lorg/apache/commons/logging/Log;
    //   1119: astore 5
    //   1121: aload 5
    //   1123: invokeinterface 495 1 0
    //   1128: istore 8
    //   1130: iload 8
    //   1132: ifeq +65 -> 1197
    //   1135: aload_0
    //   1136: getfield 43	org/apache/http/impl/execchain/MainClientExec:log	Lorg/apache/commons/logging/Log;
    //   1139: astore 5
    //   1141: new 196	java/lang/StringBuilder
    //   1144: astore 16
    //   1146: aload 16
    //   1148: invokespecial 197	java/lang/StringBuilder:<init>	()V
    //   1151: ldc_w 550
    //   1154: astore 14
    //   1156: aload 16
    //   1158: aload 14
    //   1160: invokevirtual 203	java/lang/StringBuilder:append	(Ljava/lang/String;)Ljava/lang/StringBuilder;
    //   1163: astore 16
    //   1165: aload 6
    //   1167: invokevirtual 545	org/apache/http/auth/AuthState:getState	()Lorg/apache/http/auth/AuthProtocolState;
    //   1170: astore 14
    //   1172: aload 16
    //   1174: aload 14
    //   1176: invokevirtual 206	java/lang/StringBuilder:append	(Ljava/lang/Object;)Ljava/lang/StringBuilder;
    //   1179: astore 16
    //   1181: aload 16
    //   1183: invokevirtual 209	java/lang/StringBuilder:toString	()Ljava/lang/String;
    //   1186: astore 16
    //   1188: aload 5
    //   1190: aload 16
    //   1192: invokeinterface 233 2 0
    //   1197: aload_0
    //   1198: getfield 68	org/apache/http/impl/execchain/MainClientExec:authenticator	Lorg/apache/http/impl/auth/HttpAuthenticator;
    //   1201: astore 5
    //   1203: aload 5
    //   1205: aload_2
    //   1206: checkcast 144	org/apache/http/HttpRequest
    //   1209: aload 6
    //   1211: aload_3
    //   1212: invokevirtual 178	org/apache/http/impl/auth/HttpAuthenticator:generateAuthResponse	(Lorg/apache/http/HttpRequest;Lorg/apache/http/auth/AuthState;Lorg/apache/http/protocol/HttpContext;)V
    //   1215: aload_0
    //   1216: getfield 92	org/apache/http/impl/execchain/MainClientExec:requestExecutor	Lorg/apache/http/protocol/HttpRequestExecutor;
    //   1219: astore 5
    //   1221: aload 5
    //   1223: aload_2
    //   1224: checkcast 144	org/apache/http/HttpRequest
    //   1227: aload 15
    //   1229: aload_3
    //   1230: invokevirtual 182	org/apache/http/protocol/HttpRequestExecutor:execute	(Lorg/apache/http/HttpRequest;Lorg/apache/http/HttpClientConnection;Lorg/apache/http/protocol/HttpContext;)Lorg/apache/http/HttpResponse;
    //   1233: astore 20
    //   1235: aload_0
    //   1236: getfield 96	org/apache/http/impl/execchain/MainClientExec:reuseStrategy	Lorg/apache/http/ConnectionReuseStrategy;
    //   1239: astore 5
    //   1241: aload 5
    //   1243: aload 20
    //   1245: aload_3
    //   1246: invokeinterface 225 3 0
    //   1251: istore 8
    //   1253: iload 8
    //   1255: ifeq +354 -> 1609
    //   1258: aload_0
    //   1259: getfield 98	org/apache/http/impl/execchain/MainClientExec:keepAliveStrategy	Lorg/apache/http/conn/ConnectionKeepAliveStrategy;
    //   1262: astore 5
    //   1264: aload 5
    //   1266: aload 20
    //   1268: aload_3
    //   1269: invokeinterface 556 3 0
    //   1274: lstore 21
    //   1276: aload_0
    //   1277: getfield 43	org/apache/http/impl/execchain/MainClientExec:log	Lorg/apache/commons/logging/Log;
    //   1280: astore 5
    //   1282: aload 5
    //   1284: invokeinterface 495 1 0
    //   1289: istore 8
    //   1291: iload 8
    //   1293: ifeq +141 -> 1434
    //   1296: lconst_0
    //   1297: lstore 23
    //   1299: lload 21
    //   1301: lload 23
    //   1303: lcmp
    //   1304: istore 8
    //   1306: iload 8
    //   1308: ifle +293 -> 1601
    //   1311: new 196	java/lang/StringBuilder
    //   1314: astore 5
    //   1316: aload 5
    //   1318: invokespecial 197	java/lang/StringBuilder:<init>	()V
    //   1321: ldc_w 558
    //   1324: astore 16
    //   1326: aload 5
    //   1328: aload 16
    //   1330: invokevirtual 203	java/lang/StringBuilder:append	(Ljava/lang/String;)Ljava/lang/StringBuilder;
    //   1333: astore 5
    //   1335: aload 5
    //   1337: lload 21
    //   1339: invokevirtual 561	java/lang/StringBuilder:append	(J)Ljava/lang/StringBuilder;
    //   1342: astore 5
    //   1344: ldc_w 563
    //   1347: astore 16
    //   1349: aload 5
    //   1351: aload 16
    //   1353: invokevirtual 203	java/lang/StringBuilder:append	(Ljava/lang/String;)Ljava/lang/StringBuilder;
    //   1356: astore 5
    //   1358: getstatic 417	java/util/concurrent/TimeUnit:MILLISECONDS	Ljava/util/concurrent/TimeUnit;
    //   1361: astore 16
    //   1363: aload 5
    //   1365: aload 16
    //   1367: invokevirtual 206	java/lang/StringBuilder:append	(Ljava/lang/Object;)Ljava/lang/StringBuilder;
    //   1370: astore 5
    //   1372: aload 5
    //   1374: invokevirtual 209	java/lang/StringBuilder:toString	()Ljava/lang/String;
    //   1377: astore 5
    //   1379: aload_0
    //   1380: getfield 43	org/apache/http/impl/execchain/MainClientExec:log	Lorg/apache/commons/logging/Log;
    //   1383: astore 16
    //   1385: new 196	java/lang/StringBuilder
    //   1388: astore 25
    //   1390: aload 25
    //   1392: invokespecial 197	java/lang/StringBuilder:<init>	()V
    //   1395: ldc_w 565
    //   1398: astore 26
    //   1400: aload 25
    //   1402: aload 26
    //   1404: invokevirtual 203	java/lang/StringBuilder:append	(Ljava/lang/String;)Ljava/lang/StringBuilder;
    //   1407: astore 25
    //   1409: aload 25
    //   1411: aload 5
    //   1413: invokevirtual 203	java/lang/StringBuilder:append	(Ljava/lang/String;)Ljava/lang/StringBuilder;
    //   1416: astore 5
    //   1418: aload 5
    //   1420: invokevirtual 209	java/lang/StringBuilder:toString	()Ljava/lang/String;
    //   1423: astore 5
    //   1425: aload 16
    //   1427: aload 5
    //   1429: invokeinterface 233 2 0
    //   1434: getstatic 417	java/util/concurrent/TimeUnit:MILLISECONDS	Ljava/util/concurrent/TimeUnit;
    //   1437: astore 5
    //   1439: aload 17
    //   1441: lload 21
    //   1443: aload 5
    //   1445: invokevirtual 569	org/apache/http/impl/execchain/ConnectionHolder:setValidFor	(JLjava/util/concurrent/TimeUnit;)V
    //   1448: aload 17
    //   1450: invokevirtual 572	org/apache/http/impl/execchain/ConnectionHolder:markReusable	()V
    //   1453: aload_0
    //   1454: astore 16
    //   1456: aload 7
    //   1458: astore 14
    //   1460: aload_1
    //   1461: astore 25
    //   1463: aload_3
    //   1464: astore 26
    //   1466: aload_0
    //   1467: aload 7
    //   1469: aload 6
    //   1471: aload_1
    //   1472: aload 20
    //   1474: aload_3
    //   1475: invokespecial 576	org/apache/http/impl/execchain/MainClientExec:needAuthentication	(Lorg/apache/http/auth/AuthState;Lorg/apache/http/auth/AuthState;Lorg/apache/http/conn/routing/HttpRoute;Lorg/apache/http/HttpResponse;Lorg/apache/http/client/protocol/HttpClientContext;)Z
    //   1478: istore 8
    //   1480: iload 8
    //   1482: ifeq -704 -> 778
    //   1485: aload 20
    //   1487: invokeinterface 237 1 0
    //   1492: astore 5
    //   1494: aload 17
    //   1496: invokevirtual 579	org/apache/http/impl/execchain/ConnectionHolder:isReusable	()Z
    //   1499: istore 27
    //   1501: iload 27
    //   1503: ifeq +124 -> 1627
    //   1506: aload 5
    //   1508: invokestatic 243	org/apache/http/util/EntityUtils:consume	(Lorg/apache/http/HttpEntity;)V
    //   1511: aload_2
    //   1512: checkcast 529	org/apache/http/client/methods/HttpRequestWrapper
    //   1515: invokevirtual 583	org/apache/http/client/methods/HttpRequestWrapper:getOriginal	()Lorg/apache/http/HttpRequest;
    //   1518: astore 5
    //   1520: ldc_w 535
    //   1523: astore 16
    //   1525: aload 5
    //   1527: aload 16
    //   1529: invokeinterface 584 2 0
    //   1534: istore 27
    //   1536: iload 27
    //   1538: ifne +17 -> 1555
    //   1541: ldc_w 535
    //   1544: astore 16
    //   1546: aload_2
    //   1547: checkcast 529	org/apache/http/client/methods/HttpRequestWrapper
    //   1550: aload 16
    //   1552: invokevirtual 585	org/apache/http/client/methods/HttpRequestWrapper:removeHeaders	(Ljava/lang/String;)V
    //   1555: ldc -85
    //   1557: astore 16
    //   1559: aload 5
    //   1561: aload 16
    //   1563: invokeinterface 584 2 0
    //   1568: istore 8
    //   1570: iload 8
    //   1572: ifne +16 -> 1588
    //   1575: ldc -85
    //   1577: astore 5
    //   1579: aload_2
    //   1580: checkcast 529	org/apache/http/client/methods/HttpRequestWrapper
    //   1583: aload 5
    //   1585: invokevirtual 585	org/apache/http/client/methods/HttpRequestWrapper:removeHeaders	(Ljava/lang/String;)V
    //   1588: iload 18
    //   1590: iconst_1
    //   1591: iadd
    //   1592: istore 8
    //   1594: iload 8
    //   1596: istore 18
    //   1598: goto -1215 -> 383
    //   1601: ldc_w 587
    //   1604: astore 5
    //   1606: goto -227 -> 1379
    //   1609: aload 17
    //   1611: invokevirtual 590	org/apache/http/impl/execchain/ConnectionHolder:markNonReusable	()V
    //   1614: goto -161 -> 1453
    //   1617: astore 5
    //   1619: aload 17
    //   1621: invokevirtual 479	org/apache/http/impl/execchain/ConnectionHolder:abortConnection	()V
    //   1624: aload 5
    //   1626: athrow
    //   1627: aload 15
    //   1629: invokeinterface 246 1 0
    //   1634: aload 6
    //   1636: invokevirtual 545	org/apache/http/auth/AuthState:getState	()Lorg/apache/http/auth/AuthProtocolState;
    //   1639: astore 5
    //   1641: getstatic 596	org/apache/http/auth/AuthProtocolState:SUCCESS	Lorg/apache/http/auth/AuthProtocolState;
    //   1644: astore 16
    //   1646: aload 5
    //   1648: aload 16
    //   1650: if_acmpne +61 -> 1711
    //   1653: aload 6
    //   1655: invokevirtual 600	org/apache/http/auth/AuthState:getAuthScheme	()Lorg/apache/http/auth/AuthScheme;
    //   1658: astore 5
    //   1660: aload 5
    //   1662: ifnull +49 -> 1711
    //   1665: aload 6
    //   1667: invokevirtual 600	org/apache/http/auth/AuthState:getAuthScheme	()Lorg/apache/http/auth/AuthScheme;
    //   1670: astore 5
    //   1672: aload 5
    //   1674: invokeinterface 605 1 0
    //   1679: istore 8
    //   1681: iload 8
    //   1683: ifeq +28 -> 1711
    //   1686: aload_0
    //   1687: getfield 43	org/apache/http/impl/execchain/MainClientExec:log	Lorg/apache/commons/logging/Log;
    //   1690: astore 5
    //   1692: ldc_w 607
    //   1695: astore 16
    //   1697: aload 5
    //   1699: aload 16
    //   1701: invokeinterface 233 2 0
    //   1706: aload 6
    //   1708: invokevirtual 610	org/apache/http/auth/AuthState:reset	()V
    //   1711: aload 7
    //   1713: invokevirtual 545	org/apache/http/auth/AuthState:getState	()Lorg/apache/http/auth/AuthProtocolState;
    //   1716: astore 5
    //   1718: getstatic 596	org/apache/http/auth/AuthProtocolState:SUCCESS	Lorg/apache/http/auth/AuthProtocolState;
    //   1721: astore 16
    //   1723: aload 5
    //   1725: aload 16
    //   1727: if_acmpne -216 -> 1511
    //   1730: aload 7
    //   1732: invokevirtual 600	org/apache/http/auth/AuthState:getAuthScheme	()Lorg/apache/http/auth/AuthScheme;
    //   1735: astore 5
    //   1737: aload 5
    //   1739: ifnull -228 -> 1511
    //   1742: aload 7
    //   1744: invokevirtual 600	org/apache/http/auth/AuthState:getAuthScheme	()Lorg/apache/http/auth/AuthScheme;
    //   1747: astore 5
    //   1749: aload 5
    //   1751: invokeinterface 605 1 0
    //   1756: istore 8
    //   1758: iload 8
    //   1760: ifeq -249 -> 1511
    //   1763: aload_0
    //   1764: getfield 43	org/apache/http/impl/execchain/MainClientExec:log	Lorg/apache/commons/logging/Log;
    //   1767: astore 5
    //   1769: ldc_w 612
    //   1772: astore 16
    //   1774: aload 5
    //   1776: aload 16
    //   1778: invokeinterface 233 2 0
    //   1783: aload 7
    //   1785: invokevirtual 610	org/apache/http/auth/AuthState:reset	()V
    //   1788: goto -277 -> 1511
    //   1791: new 522	org/apache/http/impl/execchain/HttpResponseProxy
    //   1794: astore 5
    //   1796: aload 5
    //   1798: aload 20
    //   1800: aload 17
    //   1802: invokespecial 525	org/apache/http/impl/execchain/HttpResponseProxy:<init>	(Lorg/apache/http/HttpResponse;Lorg/apache/http/impl/execchain/ConnectionHolder;)V
    //   1805: goto -929 -> 876
    //   1808: aload 9
    //   1810: astore 5
    //   1812: goto -1000 -> 812
    //   1815: aload 6
    //   1817: astore 5
    //   1819: goto -1320 -> 499
    //   1822: aload 5
    //   1824: astore 7
    //   1826: goto -1764 -> 62
    // Local variable table:
    //   start	length	slot	name	signature
    //   0	1829	0	this	MainClientExec
    //   0	1829	1	paramHttpRoute	HttpRoute
    //   0	1829	2	paramHttpRequestWrapper	org.apache.http.client.methods.HttpRequestWrapper
    //   0	1829	3	paramHttpClientContext	HttpClientContext
    //   0	1829	4	paramHttpExecutionAware	org.apache.http.client.methods.HttpExecutionAware
    //   28	397	5	localObject1	Object
    //   427	18	5	localConnectionShutdownException	org.apache.http.impl.conn.ConnectionShutdownException
    //   459	19	5	localInterruptedException	InterruptedException
    //   485	25	5	localExecutionException	java.util.concurrent.ExecutionException
    //   539	15	5	localRequestAbortedException	RequestAbortedException
    //   556	8	5	localHttpException	HttpException
    //   584	131	5	localObject2	Object
    //   717	8	5	localIOException	java.io.IOException
    //   727	45	5	localTunnelRefusedException	TunnelRefusedException
    //   787	818	5	localObject3	Object
    //   1617	8	5	localRuntimeException	RuntimeException
    //   1639	184	5	localObject4	Object
    //   48	1768	6	localObject5	Object
    //   60	1765	7	localObject6	Object
    //   100	476	8	bool1	boolean
    //   662	10	8	i	int
    //   690	881	8	bool2	boolean
    //   1592	3	8	j	int
    //   1679	80	8	bool3	boolean
    //   125	1684	9	localObject7	Object
    //   153	3	10	bool4	boolean
    //   204	8	10	k	int
    //   197	461	11	localRequestConfig	RequestConfig
    //   214	241	12	l1	long
    //   219	1240	14	localObject8	Object
    //   232	1396	15	localObject9	Object
    //   282	1495	16	localObject10	Object
    //   337	1464	17	localConnectionHolder	ConnectionHolder
    //   381	1216	18	bool5	boolean
    //   742	122	19	bool6	boolean
    //   776	1023	20	localHttpResponse	HttpResponse
    //   1274	168	21	l2	long
    //   1297	5	23	l3	long
    //   1388	74	25	localObject11	Object
    //   1398	67	26	localObject12	Object
    //   1499	38	27	bool7	boolean
    // Exception table:
    //   from	to	target	type
    //   369	376	427	org/apache/http/impl/conn/ConnectionShutdownException
    //   393	400	427	org/apache/http/impl/conn/ConnectionShutdownException
    //   407	410	427	org/apache/http/impl/conn/ConnectionShutdownException
    //   419	424	427	org/apache/http/impl/conn/ConnectionShutdownException
    //   424	427	427	org/apache/http/impl/conn/ConnectionShutdownException
    //   522	529	427	org/apache/http/impl/conn/ConnectionShutdownException
    //   536	539	427	org/apache/http/impl/conn/ConnectionShutdownException
    //   548	553	427	org/apache/http/impl/conn/ConnectionShutdownException
    //   553	556	427	org/apache/http/impl/conn/ConnectionShutdownException
    //   566	573	427	org/apache/http/impl/conn/ConnectionShutdownException
    //   580	584	427	org/apache/http/impl/conn/ConnectionShutdownException
    //   586	589	427	org/apache/http/impl/conn/ConnectionShutdownException
    //   591	596	427	org/apache/http/impl/conn/ConnectionShutdownException
    //   603	608	427	org/apache/http/impl/conn/ConnectionShutdownException
    //   612	616	427	org/apache/http/impl/conn/ConnectionShutdownException
    //   618	623	427	org/apache/http/impl/conn/ConnectionShutdownException
    //   627	634	427	org/apache/http/impl/conn/ConnectionShutdownException
    //   649	657	427	org/apache/http/impl/conn/ConnectionShutdownException
    //   657	662	427	org/apache/http/impl/conn/ConnectionShutdownException
    //   671	678	427	org/apache/http/impl/conn/ConnectionShutdownException
    //   683	690	427	org/apache/http/impl/conn/ConnectionShutdownException
    //   697	700	427	org/apache/http/impl/conn/ConnectionShutdownException
    //   709	714	427	org/apache/http/impl/conn/ConnectionShutdownException
    //   714	717	427	org/apache/http/impl/conn/ConnectionShutdownException
    //   729	733	427	org/apache/http/impl/conn/ConnectionShutdownException
    //   735	742	427	org/apache/http/impl/conn/ConnectionShutdownException
    //   749	753	427	org/apache/http/impl/conn/ConnectionShutdownException
    //   755	760	427	org/apache/http/impl/conn/ConnectionShutdownException
    //   764	771	427	org/apache/http/impl/conn/ConnectionShutdownException
    //   771	776	427	org/apache/http/impl/conn/ConnectionShutdownException
    //   783	787	427	org/apache/http/impl/conn/ConnectionShutdownException
    //   791	797	427	org/apache/http/impl/conn/ConnectionShutdownException
    //   807	812	427	org/apache/http/impl/conn/ConnectionShutdownException
    //   819	824	427	org/apache/http/impl/conn/ConnectionShutdownException
    //   824	831	427	org/apache/http/impl/conn/ConnectionShutdownException
    //   838	845	427	org/apache/http/impl/conn/ConnectionShutdownException
    //   852	857	427	org/apache/http/impl/conn/ConnectionShutdownException
    //   857	860	427	org/apache/http/impl/conn/ConnectionShutdownException
    //   872	876	427	org/apache/http/impl/conn/ConnectionShutdownException
    //   879	883	427	org/apache/http/impl/conn/ConnectionShutdownException
    //   885	892	427	org/apache/http/impl/conn/ConnectionShutdownException
    //   899	903	427	org/apache/http/impl/conn/ConnectionShutdownException
    //   905	908	427	org/apache/http/impl/conn/ConnectionShutdownException
    //   910	915	427	org/apache/http/impl/conn/ConnectionShutdownException
    //   922	927	427	org/apache/http/impl/conn/ConnectionShutdownException
    //   929	936	427	org/apache/http/impl/conn/ConnectionShutdownException
    //   940	945	427	org/apache/http/impl/conn/ConnectionShutdownException
    //   947	952	427	org/apache/http/impl/conn/ConnectionShutdownException
    //   956	963	427	org/apache/http/impl/conn/ConnectionShutdownException
    //   968	977	427	org/apache/http/impl/conn/ConnectionShutdownException
    //   984	988	427	org/apache/http/impl/conn/ConnectionShutdownException
    //   990	997	427	org/apache/http/impl/conn/ConnectionShutdownException
    //   1004	1008	427	org/apache/http/impl/conn/ConnectionShutdownException
    //   1010	1013	427	org/apache/http/impl/conn/ConnectionShutdownException
    //   1015	1020	427	org/apache/http/impl/conn/ConnectionShutdownException
    //   1027	1032	427	org/apache/http/impl/conn/ConnectionShutdownException
    //   1034	1039	427	org/apache/http/impl/conn/ConnectionShutdownException
    //   1043	1048	427	org/apache/http/impl/conn/ConnectionShutdownException
    //   1050	1055	427	org/apache/http/impl/conn/ConnectionShutdownException
    //   1059	1066	427	org/apache/http/impl/conn/ConnectionShutdownException
    //   1066	1070	427	org/apache/http/impl/conn/ConnectionShutdownException
    //   1074	1084	427	org/apache/http/impl/conn/ConnectionShutdownException
    //   1088	1097	427	org/apache/http/impl/conn/ConnectionShutdownException
    //   1104	1108	427	org/apache/http/impl/conn/ConnectionShutdownException
    //   1115	1119	427	org/apache/http/impl/conn/ConnectionShutdownException
    //   1121	1128	427	org/apache/http/impl/conn/ConnectionShutdownException
    //   1135	1139	427	org/apache/http/impl/conn/ConnectionShutdownException
    //   1141	1144	427	org/apache/http/impl/conn/ConnectionShutdownException
    //   1146	1151	427	org/apache/http/impl/conn/ConnectionShutdownException
    //   1158	1163	427	org/apache/http/impl/conn/ConnectionShutdownException
    //   1165	1170	427	org/apache/http/impl/conn/ConnectionShutdownException
    //   1174	1179	427	org/apache/http/impl/conn/ConnectionShutdownException
    //   1181	1186	427	org/apache/http/impl/conn/ConnectionShutdownException
    //   1190	1197	427	org/apache/http/impl/conn/ConnectionShutdownException
    //   1197	1201	427	org/apache/http/impl/conn/ConnectionShutdownException
    //   1205	1215	427	org/apache/http/impl/conn/ConnectionShutdownException
    //   1215	1219	427	org/apache/http/impl/conn/ConnectionShutdownException
    //   1223	1233	427	org/apache/http/impl/conn/ConnectionShutdownException
    //   1235	1239	427	org/apache/http/impl/conn/ConnectionShutdownException
    //   1245	1251	427	org/apache/http/impl/conn/ConnectionShutdownException
    //   1258	1262	427	org/apache/http/impl/conn/ConnectionShutdownException
    //   1268	1274	427	org/apache/http/impl/conn/ConnectionShutdownException
    //   1276	1280	427	org/apache/http/impl/conn/ConnectionShutdownException
    //   1282	1289	427	org/apache/http/impl/conn/ConnectionShutdownException
    //   1311	1314	427	org/apache/http/impl/conn/ConnectionShutdownException
    //   1316	1321	427	org/apache/http/impl/conn/ConnectionShutdownException
    //   1328	1333	427	org/apache/http/impl/conn/ConnectionShutdownException
    //   1337	1342	427	org/apache/http/impl/conn/ConnectionShutdownException
    //   1351	1356	427	org/apache/http/impl/conn/ConnectionShutdownException
    //   1358	1361	427	org/apache/http/impl/conn/ConnectionShutdownException
    //   1365	1370	427	org/apache/http/impl/conn/ConnectionShutdownException
    //   1372	1377	427	org/apache/http/impl/conn/ConnectionShutdownException
    //   1379	1383	427	org/apache/http/impl/conn/ConnectionShutdownException
    //   1385	1388	427	org/apache/http/impl/conn/ConnectionShutdownException
    //   1390	1395	427	org/apache/http/impl/conn/ConnectionShutdownException
    //   1402	1407	427	org/apache/http/impl/conn/ConnectionShutdownException
    //   1411	1416	427	org/apache/http/impl/conn/ConnectionShutdownException
    //   1418	1423	427	org/apache/http/impl/conn/ConnectionShutdownException
    //   1427	1434	427	org/apache/http/impl/conn/ConnectionShutdownException
    //   1434	1437	427	org/apache/http/impl/conn/ConnectionShutdownException
    //   1443	1448	427	org/apache/http/impl/conn/ConnectionShutdownException
    //   1448	1453	427	org/apache/http/impl/conn/ConnectionShutdownException
    //   1474	1478	427	org/apache/http/impl/conn/ConnectionShutdownException
    //   1485	1492	427	org/apache/http/impl/conn/ConnectionShutdownException
    //   1494	1499	427	org/apache/http/impl/conn/ConnectionShutdownException
    //   1506	1511	427	org/apache/http/impl/conn/ConnectionShutdownException
    //   1511	1518	427	org/apache/http/impl/conn/ConnectionShutdownException
    //   1527	1534	427	org/apache/http/impl/conn/ConnectionShutdownException
    //   1546	1555	427	org/apache/http/impl/conn/ConnectionShutdownException
    //   1561	1568	427	org/apache/http/impl/conn/ConnectionShutdownException
    //   1579	1588	427	org/apache/http/impl/conn/ConnectionShutdownException
    //   1609	1614	427	org/apache/http/impl/conn/ConnectionShutdownException
    //   1627	1634	427	org/apache/http/impl/conn/ConnectionShutdownException
    //   1634	1639	427	org/apache/http/impl/conn/ConnectionShutdownException
    //   1641	1644	427	org/apache/http/impl/conn/ConnectionShutdownException
    //   1653	1658	427	org/apache/http/impl/conn/ConnectionShutdownException
    //   1665	1670	427	org/apache/http/impl/conn/ConnectionShutdownException
    //   1672	1679	427	org/apache/http/impl/conn/ConnectionShutdownException
    //   1686	1690	427	org/apache/http/impl/conn/ConnectionShutdownException
    //   1699	1706	427	org/apache/http/impl/conn/ConnectionShutdownException
    //   1706	1711	427	org/apache/http/impl/conn/ConnectionShutdownException
    //   1711	1716	427	org/apache/http/impl/conn/ConnectionShutdownException
    //   1718	1721	427	org/apache/http/impl/conn/ConnectionShutdownException
    //   1730	1735	427	org/apache/http/impl/conn/ConnectionShutdownException
    //   1742	1747	427	org/apache/http/impl/conn/ConnectionShutdownException
    //   1749	1756	427	org/apache/http/impl/conn/ConnectionShutdownException
    //   1763	1767	427	org/apache/http/impl/conn/ConnectionShutdownException
    //   1776	1783	427	org/apache/http/impl/conn/ConnectionShutdownException
    //   1783	1788	427	org/apache/http/impl/conn/ConnectionShutdownException
    //   1791	1794	427	org/apache/http/impl/conn/ConnectionShutdownException
    //   1800	1805	427	org/apache/http/impl/conn/ConnectionShutdownException
    //   199	204	459	java/lang/InterruptedException
    //   216	219	459	java/lang/InterruptedException
    //   225	232	459	java/lang/InterruptedException
    //   199	204	485	java/util/concurrent/ExecutionException
    //   216	219	485	java/util/concurrent/ExecutionException
    //   225	232	485	java/util/concurrent/ExecutionException
    //   369	376	556	org/apache/http/HttpException
    //   393	400	556	org/apache/http/HttpException
    //   407	410	556	org/apache/http/HttpException
    //   419	424	556	org/apache/http/HttpException
    //   424	427	556	org/apache/http/HttpException
    //   522	529	556	org/apache/http/HttpException
    //   536	539	556	org/apache/http/HttpException
    //   548	553	556	org/apache/http/HttpException
    //   553	556	556	org/apache/http/HttpException
    //   566	573	556	org/apache/http/HttpException
    //   580	584	556	org/apache/http/HttpException
    //   586	589	556	org/apache/http/HttpException
    //   591	596	556	org/apache/http/HttpException
    //   603	608	556	org/apache/http/HttpException
    //   612	616	556	org/apache/http/HttpException
    //   618	623	556	org/apache/http/HttpException
    //   627	634	556	org/apache/http/HttpException
    //   649	657	556	org/apache/http/HttpException
    //   657	662	556	org/apache/http/HttpException
    //   671	678	556	org/apache/http/HttpException
    //   683	690	556	org/apache/http/HttpException
    //   697	700	556	org/apache/http/HttpException
    //   709	714	556	org/apache/http/HttpException
    //   714	717	556	org/apache/http/HttpException
    //   729	733	556	org/apache/http/HttpException
    //   735	742	556	org/apache/http/HttpException
    //   749	753	556	org/apache/http/HttpException
    //   755	760	556	org/apache/http/HttpException
    //   764	771	556	org/apache/http/HttpException
    //   771	776	556	org/apache/http/HttpException
    //   783	787	556	org/apache/http/HttpException
    //   791	797	556	org/apache/http/HttpException
    //   807	812	556	org/apache/http/HttpException
    //   819	824	556	org/apache/http/HttpException
    //   824	831	556	org/apache/http/HttpException
    //   838	845	556	org/apache/http/HttpException
    //   852	857	556	org/apache/http/HttpException
    //   857	860	556	org/apache/http/HttpException
    //   872	876	556	org/apache/http/HttpException
    //   879	883	556	org/apache/http/HttpException
    //   885	892	556	org/apache/http/HttpException
    //   899	903	556	org/apache/http/HttpException
    //   905	908	556	org/apache/http/HttpException
    //   910	915	556	org/apache/http/HttpException
    //   922	927	556	org/apache/http/HttpException
    //   929	936	556	org/apache/http/HttpException
    //   940	945	556	org/apache/http/HttpException
    //   947	952	556	org/apache/http/HttpException
    //   956	963	556	org/apache/http/HttpException
    //   968	977	556	org/apache/http/HttpException
    //   984	988	556	org/apache/http/HttpException
    //   990	997	556	org/apache/http/HttpException
    //   1004	1008	556	org/apache/http/HttpException
    //   1010	1013	556	org/apache/http/HttpException
    //   1015	1020	556	org/apache/http/HttpException
    //   1027	1032	556	org/apache/http/HttpException
    //   1034	1039	556	org/apache/http/HttpException
    //   1043	1048	556	org/apache/http/HttpException
    //   1050	1055	556	org/apache/http/HttpException
    //   1059	1066	556	org/apache/http/HttpException
    //   1066	1070	556	org/apache/http/HttpException
    //   1074	1084	556	org/apache/http/HttpException
    //   1088	1097	556	org/apache/http/HttpException
    //   1104	1108	556	org/apache/http/HttpException
    //   1115	1119	556	org/apache/http/HttpException
    //   1121	1128	556	org/apache/http/HttpException
    //   1135	1139	556	org/apache/http/HttpException
    //   1141	1144	556	org/apache/http/HttpException
    //   1146	1151	556	org/apache/http/HttpException
    //   1158	1163	556	org/apache/http/HttpException
    //   1165	1170	556	org/apache/http/HttpException
    //   1174	1179	556	org/apache/http/HttpException
    //   1181	1186	556	org/apache/http/HttpException
    //   1190	1197	556	org/apache/http/HttpException
    //   1197	1201	556	org/apache/http/HttpException
    //   1205	1215	556	org/apache/http/HttpException
    //   1215	1219	556	org/apache/http/HttpException
    //   1223	1233	556	org/apache/http/HttpException
    //   1235	1239	556	org/apache/http/HttpException
    //   1245	1251	556	org/apache/http/HttpException
    //   1258	1262	556	org/apache/http/HttpException
    //   1268	1274	556	org/apache/http/HttpException
    //   1276	1280	556	org/apache/http/HttpException
    //   1282	1289	556	org/apache/http/HttpException
    //   1311	1314	556	org/apache/http/HttpException
    //   1316	1321	556	org/apache/http/HttpException
    //   1328	1333	556	org/apache/http/HttpException
    //   1337	1342	556	org/apache/http/HttpException
    //   1351	1356	556	org/apache/http/HttpException
    //   1358	1361	556	org/apache/http/HttpException
    //   1365	1370	556	org/apache/http/HttpException
    //   1372	1377	556	org/apache/http/HttpException
    //   1379	1383	556	org/apache/http/HttpException
    //   1385	1388	556	org/apache/http/HttpException
    //   1390	1395	556	org/apache/http/HttpException
    //   1402	1407	556	org/apache/http/HttpException
    //   1411	1416	556	org/apache/http/HttpException
    //   1418	1423	556	org/apache/http/HttpException
    //   1427	1434	556	org/apache/http/HttpException
    //   1434	1437	556	org/apache/http/HttpException
    //   1443	1448	556	org/apache/http/HttpException
    //   1448	1453	556	org/apache/http/HttpException
    //   1474	1478	556	org/apache/http/HttpException
    //   1485	1492	556	org/apache/http/HttpException
    //   1494	1499	556	org/apache/http/HttpException
    //   1506	1511	556	org/apache/http/HttpException
    //   1511	1518	556	org/apache/http/HttpException
    //   1527	1534	556	org/apache/http/HttpException
    //   1546	1555	556	org/apache/http/HttpException
    //   1561	1568	556	org/apache/http/HttpException
    //   1579	1588	556	org/apache/http/HttpException
    //   1609	1614	556	org/apache/http/HttpException
    //   1627	1634	556	org/apache/http/HttpException
    //   1634	1639	556	org/apache/http/HttpException
    //   1641	1644	556	org/apache/http/HttpException
    //   1653	1658	556	org/apache/http/HttpException
    //   1665	1670	556	org/apache/http/HttpException
    //   1672	1679	556	org/apache/http/HttpException
    //   1686	1690	556	org/apache/http/HttpException
    //   1699	1706	556	org/apache/http/HttpException
    //   1706	1711	556	org/apache/http/HttpException
    //   1711	1716	556	org/apache/http/HttpException
    //   1718	1721	556	org/apache/http/HttpException
    //   1730	1735	556	org/apache/http/HttpException
    //   1742	1747	556	org/apache/http/HttpException
    //   1749	1756	556	org/apache/http/HttpException
    //   1763	1767	556	org/apache/http/HttpException
    //   1776	1783	556	org/apache/http/HttpException
    //   1783	1788	556	org/apache/http/HttpException
    //   1791	1794	556	org/apache/http/HttpException
    //   1800	1805	556	org/apache/http/HttpException
    //   369	376	717	java/io/IOException
    //   393	400	717	java/io/IOException
    //   407	410	717	java/io/IOException
    //   419	424	717	java/io/IOException
    //   424	427	717	java/io/IOException
    //   522	529	717	java/io/IOException
    //   536	539	717	java/io/IOException
    //   548	553	717	java/io/IOException
    //   553	556	717	java/io/IOException
    //   566	573	717	java/io/IOException
    //   580	584	717	java/io/IOException
    //   586	589	717	java/io/IOException
    //   591	596	717	java/io/IOException
    //   603	608	717	java/io/IOException
    //   612	616	717	java/io/IOException
    //   618	623	717	java/io/IOException
    //   627	634	717	java/io/IOException
    //   649	657	717	java/io/IOException
    //   657	662	717	java/io/IOException
    //   671	678	717	java/io/IOException
    //   683	690	717	java/io/IOException
    //   697	700	717	java/io/IOException
    //   709	714	717	java/io/IOException
    //   714	717	717	java/io/IOException
    //   729	733	717	java/io/IOException
    //   735	742	717	java/io/IOException
    //   749	753	717	java/io/IOException
    //   755	760	717	java/io/IOException
    //   764	771	717	java/io/IOException
    //   771	776	717	java/io/IOException
    //   783	787	717	java/io/IOException
    //   791	797	717	java/io/IOException
    //   807	812	717	java/io/IOException
    //   819	824	717	java/io/IOException
    //   824	831	717	java/io/IOException
    //   838	845	717	java/io/IOException
    //   852	857	717	java/io/IOException
    //   857	860	717	java/io/IOException
    //   872	876	717	java/io/IOException
    //   879	883	717	java/io/IOException
    //   885	892	717	java/io/IOException
    //   899	903	717	java/io/IOException
    //   905	908	717	java/io/IOException
    //   910	915	717	java/io/IOException
    //   922	927	717	java/io/IOException
    //   929	936	717	java/io/IOException
    //   940	945	717	java/io/IOException
    //   947	952	717	java/io/IOException
    //   956	963	717	java/io/IOException
    //   968	977	717	java/io/IOException
    //   984	988	717	java/io/IOException
    //   990	997	717	java/io/IOException
    //   1004	1008	717	java/io/IOException
    //   1010	1013	717	java/io/IOException
    //   1015	1020	717	java/io/IOException
    //   1027	1032	717	java/io/IOException
    //   1034	1039	717	java/io/IOException
    //   1043	1048	717	java/io/IOException
    //   1050	1055	717	java/io/IOException
    //   1059	1066	717	java/io/IOException
    //   1066	1070	717	java/io/IOException
    //   1074	1084	717	java/io/IOException
    //   1088	1097	717	java/io/IOException
    //   1104	1108	717	java/io/IOException
    //   1115	1119	717	java/io/IOException
    //   1121	1128	717	java/io/IOException
    //   1135	1139	717	java/io/IOException
    //   1141	1144	717	java/io/IOException
    //   1146	1151	717	java/io/IOException
    //   1158	1163	717	java/io/IOException
    //   1165	1170	717	java/io/IOException
    //   1174	1179	717	java/io/IOException
    //   1181	1186	717	java/io/IOException
    //   1190	1197	717	java/io/IOException
    //   1197	1201	717	java/io/IOException
    //   1205	1215	717	java/io/IOException
    //   1215	1219	717	java/io/IOException
    //   1223	1233	717	java/io/IOException
    //   1235	1239	717	java/io/IOException
    //   1245	1251	717	java/io/IOException
    //   1258	1262	717	java/io/IOException
    //   1268	1274	717	java/io/IOException
    //   1276	1280	717	java/io/IOException
    //   1282	1289	717	java/io/IOException
    //   1311	1314	717	java/io/IOException
    //   1316	1321	717	java/io/IOException
    //   1328	1333	717	java/io/IOException
    //   1337	1342	717	java/io/IOException
    //   1351	1356	717	java/io/IOException
    //   1358	1361	717	java/io/IOException
    //   1365	1370	717	java/io/IOException
    //   1372	1377	717	java/io/IOException
    //   1379	1383	717	java/io/IOException
    //   1385	1388	717	java/io/IOException
    //   1390	1395	717	java/io/IOException
    //   1402	1407	717	java/io/IOException
    //   1411	1416	717	java/io/IOException
    //   1418	1423	717	java/io/IOException
    //   1427	1434	717	java/io/IOException
    //   1434	1437	717	java/io/IOException
    //   1443	1448	717	java/io/IOException
    //   1448	1453	717	java/io/IOException
    //   1474	1478	717	java/io/IOException
    //   1485	1492	717	java/io/IOException
    //   1494	1499	717	java/io/IOException
    //   1506	1511	717	java/io/IOException
    //   1511	1518	717	java/io/IOException
    //   1527	1534	717	java/io/IOException
    //   1546	1555	717	java/io/IOException
    //   1561	1568	717	java/io/IOException
    //   1579	1588	717	java/io/IOException
    //   1609	1614	717	java/io/IOException
    //   1627	1634	717	java/io/IOException
    //   1634	1639	717	java/io/IOException
    //   1641	1644	717	java/io/IOException
    //   1653	1658	717	java/io/IOException
    //   1665	1670	717	java/io/IOException
    //   1672	1679	717	java/io/IOException
    //   1686	1690	717	java/io/IOException
    //   1699	1706	717	java/io/IOException
    //   1706	1711	717	java/io/IOException
    //   1711	1716	717	java/io/IOException
    //   1718	1721	717	java/io/IOException
    //   1730	1735	717	java/io/IOException
    //   1742	1747	717	java/io/IOException
    //   1749	1756	717	java/io/IOException
    //   1763	1767	717	java/io/IOException
    //   1776	1783	717	java/io/IOException
    //   1783	1788	717	java/io/IOException
    //   1791	1794	717	java/io/IOException
    //   1800	1805	717	java/io/IOException
    //   649	657	727	org/apache/http/impl/execchain/TunnelRefusedException
    //   369	376	1617	java/lang/RuntimeException
    //   393	400	1617	java/lang/RuntimeException
    //   407	410	1617	java/lang/RuntimeException
    //   419	424	1617	java/lang/RuntimeException
    //   424	427	1617	java/lang/RuntimeException
    //   522	529	1617	java/lang/RuntimeException
    //   536	539	1617	java/lang/RuntimeException
    //   548	553	1617	java/lang/RuntimeException
    //   553	556	1617	java/lang/RuntimeException
    //   566	573	1617	java/lang/RuntimeException
    //   580	584	1617	java/lang/RuntimeException
    //   586	589	1617	java/lang/RuntimeException
    //   591	596	1617	java/lang/RuntimeException
    //   603	608	1617	java/lang/RuntimeException
    //   612	616	1617	java/lang/RuntimeException
    //   618	623	1617	java/lang/RuntimeException
    //   627	634	1617	java/lang/RuntimeException
    //   649	657	1617	java/lang/RuntimeException
    //   657	662	1617	java/lang/RuntimeException
    //   671	678	1617	java/lang/RuntimeException
    //   683	690	1617	java/lang/RuntimeException
    //   697	700	1617	java/lang/RuntimeException
    //   709	714	1617	java/lang/RuntimeException
    //   714	717	1617	java/lang/RuntimeException
    //   729	733	1617	java/lang/RuntimeException
    //   735	742	1617	java/lang/RuntimeException
    //   749	753	1617	java/lang/RuntimeException
    //   755	760	1617	java/lang/RuntimeException
    //   764	771	1617	java/lang/RuntimeException
    //   771	776	1617	java/lang/RuntimeException
    //   783	787	1617	java/lang/RuntimeException
    //   791	797	1617	java/lang/RuntimeException
    //   807	812	1617	java/lang/RuntimeException
    //   819	824	1617	java/lang/RuntimeException
    //   824	831	1617	java/lang/RuntimeException
    //   838	845	1617	java/lang/RuntimeException
    //   852	857	1617	java/lang/RuntimeException
    //   857	860	1617	java/lang/RuntimeException
    //   872	876	1617	java/lang/RuntimeException
    //   879	883	1617	java/lang/RuntimeException
    //   885	892	1617	java/lang/RuntimeException
    //   899	903	1617	java/lang/RuntimeException
    //   905	908	1617	java/lang/RuntimeException
    //   910	915	1617	java/lang/RuntimeException
    //   922	927	1617	java/lang/RuntimeException
    //   929	936	1617	java/lang/RuntimeException
    //   940	945	1617	java/lang/RuntimeException
    //   947	952	1617	java/lang/RuntimeException
    //   956	963	1617	java/lang/RuntimeException
    //   968	977	1617	java/lang/RuntimeException
    //   984	988	1617	java/lang/RuntimeException
    //   990	997	1617	java/lang/RuntimeException
    //   1004	1008	1617	java/lang/RuntimeException
    //   1010	1013	1617	java/lang/RuntimeException
    //   1015	1020	1617	java/lang/RuntimeException
    //   1027	1032	1617	java/lang/RuntimeException
    //   1034	1039	1617	java/lang/RuntimeException
    //   1043	1048	1617	java/lang/RuntimeException
    //   1050	1055	1617	java/lang/RuntimeException
    //   1059	1066	1617	java/lang/RuntimeException
    //   1066	1070	1617	java/lang/RuntimeException
    //   1074	1084	1617	java/lang/RuntimeException
    //   1088	1097	1617	java/lang/RuntimeException
    //   1104	1108	1617	java/lang/RuntimeException
    //   1115	1119	1617	java/lang/RuntimeException
    //   1121	1128	1617	java/lang/RuntimeException
    //   1135	1139	1617	java/lang/RuntimeException
    //   1141	1144	1617	java/lang/RuntimeException
    //   1146	1151	1617	java/lang/RuntimeException
    //   1158	1163	1617	java/lang/RuntimeException
    //   1165	1170	1617	java/lang/RuntimeException
    //   1174	1179	1617	java/lang/RuntimeException
    //   1181	1186	1617	java/lang/RuntimeException
    //   1190	1197	1617	java/lang/RuntimeException
    //   1197	1201	1617	java/lang/RuntimeException
    //   1205	1215	1617	java/lang/RuntimeException
    //   1215	1219	1617	java/lang/RuntimeException
    //   1223	1233	1617	java/lang/RuntimeException
    //   1235	1239	1617	java/lang/RuntimeException
    //   1245	1251	1617	java/lang/RuntimeException
    //   1258	1262	1617	java/lang/RuntimeException
    //   1268	1274	1617	java/lang/RuntimeException
    //   1276	1280	1617	java/lang/RuntimeException
    //   1282	1289	1617	java/lang/RuntimeException
    //   1311	1314	1617	java/lang/RuntimeException
    //   1316	1321	1617	java/lang/RuntimeException
    //   1328	1333	1617	java/lang/RuntimeException
    //   1337	1342	1617	java/lang/RuntimeException
    //   1351	1356	1617	java/lang/RuntimeException
    //   1358	1361	1617	java/lang/RuntimeException
    //   1365	1370	1617	java/lang/RuntimeException
    //   1372	1377	1617	java/lang/RuntimeException
    //   1379	1383	1617	java/lang/RuntimeException
    //   1385	1388	1617	java/lang/RuntimeException
    //   1390	1395	1617	java/lang/RuntimeException
    //   1402	1407	1617	java/lang/RuntimeException
    //   1411	1416	1617	java/lang/RuntimeException
    //   1418	1423	1617	java/lang/RuntimeException
    //   1427	1434	1617	java/lang/RuntimeException
    //   1434	1437	1617	java/lang/RuntimeException
    //   1443	1448	1617	java/lang/RuntimeException
    //   1448	1453	1617	java/lang/RuntimeException
    //   1474	1478	1617	java/lang/RuntimeException
    //   1485	1492	1617	java/lang/RuntimeException
    //   1494	1499	1617	java/lang/RuntimeException
    //   1506	1511	1617	java/lang/RuntimeException
    //   1511	1518	1617	java/lang/RuntimeException
    //   1527	1534	1617	java/lang/RuntimeException
    //   1546	1555	1617	java/lang/RuntimeException
    //   1561	1568	1617	java/lang/RuntimeException
    //   1579	1588	1617	java/lang/RuntimeException
    //   1609	1614	1617	java/lang/RuntimeException
    //   1627	1634	1617	java/lang/RuntimeException
    //   1634	1639	1617	java/lang/RuntimeException
    //   1641	1644	1617	java/lang/RuntimeException
    //   1653	1658	1617	java/lang/RuntimeException
    //   1665	1670	1617	java/lang/RuntimeException
    //   1672	1679	1617	java/lang/RuntimeException
    //   1686	1690	1617	java/lang/RuntimeException
    //   1699	1706	1617	java/lang/RuntimeException
    //   1706	1711	1617	java/lang/RuntimeException
    //   1711	1716	1617	java/lang/RuntimeException
    //   1718	1721	1617	java/lang/RuntimeException
    //   1730	1735	1617	java/lang/RuntimeException
    //   1742	1747	1617	java/lang/RuntimeException
    //   1749	1756	1617	java/lang/RuntimeException
    //   1763	1767	1617	java/lang/RuntimeException
    //   1776	1783	1617	java/lang/RuntimeException
    //   1783	1788	1617	java/lang/RuntimeException
    //   1791	1794	1617	java/lang/RuntimeException
    //   1800	1805	1617	java/lang/RuntimeException
  }
}


/* Location:              C:\Users\haryo\Desktop\enjarify-master\presensi-enjarify.jar!\org\apache\http\impl\execchain\MainClientExec.class
 * Java compiler version: 5 (49.0)
 * JD-Core Version:       0.7.1
 */