package com.google.android.gms.cast;

import com.google.android.gms.common.api.GoogleApiClient;
import org.json.JSONObject;

class RemoteMediaPlayer$22
  extends RemoteMediaPlayer.zzb
{
  RemoteMediaPlayer$22(RemoteMediaPlayer paramRemoteMediaPlayer, GoogleApiClient paramGoogleApiClient1, GoogleApiClient paramGoogleApiClient2, boolean paramBoolean, JSONObject paramJSONObject)
  {
    super(paramGoogleApiClient1);
  }
  
  /* Error */
  protected void zza(com.google.android.gms.cast.internal.zze paramzze)
  {
    // Byte code:
    //   0: aload_0
    //   1: getfield 14	com/google/android/gms/cast/RemoteMediaPlayer$22:zzabK	Lcom/google/android/gms/cast/RemoteMediaPlayer;
    //   4: astore_2
    //   5: aload_2
    //   6: invokestatic 30	com/google/android/gms/cast/RemoteMediaPlayer:zze	(Lcom/google/android/gms/cast/RemoteMediaPlayer;)Ljava/lang/Object;
    //   9: astore_3
    //   10: aload_3
    //   11: monitorenter
    //   12: aload_0
    //   13: getfield 14	com/google/android/gms/cast/RemoteMediaPlayer$22:zzabK	Lcom/google/android/gms/cast/RemoteMediaPlayer;
    //   16: astore_2
    //   17: aload_2
    //   18: invokestatic 34	com/google/android/gms/cast/RemoteMediaPlayer:zzf	(Lcom/google/android/gms/cast/RemoteMediaPlayer;)Lcom/google/android/gms/cast/RemoteMediaPlayer$zza;
    //   21: astore_2
    //   22: aload_0
    //   23: getfield 16	com/google/android/gms/cast/RemoteMediaPlayer$22:zzabL	Lcom/google/android/gms/common/api/GoogleApiClient;
    //   26: astore 4
    //   28: aload_2
    //   29: aload 4
    //   31: invokevirtual 39	com/google/android/gms/cast/RemoteMediaPlayer$zza:zzc	(Lcom/google/android/gms/common/api/GoogleApiClient;)V
    //   34: aload_0
    //   35: getfield 14	com/google/android/gms/cast/RemoteMediaPlayer$22:zzabK	Lcom/google/android/gms/cast/RemoteMediaPlayer;
    //   38: astore_2
    //   39: aload_2
    //   40: invokestatic 43	com/google/android/gms/cast/RemoteMediaPlayer:zzg	(Lcom/google/android/gms/cast/RemoteMediaPlayer;)Lcom/google/android/gms/cast/internal/zzm;
    //   43: astore_2
    //   44: aload_0
    //   45: getfield 47	com/google/android/gms/cast/RemoteMediaPlayer$22:zzacm	Lcom/google/android/gms/cast/internal/zzo;
    //   48: astore 4
    //   50: aload_0
    //   51: getfield 18	com/google/android/gms/cast/RemoteMediaPlayer$22:zzach	Z
    //   54: istore 5
    //   56: aload_0
    //   57: getfield 20	com/google/android/gms/cast/RemoteMediaPlayer$22:zzabS	Lorg/json/JSONObject;
    //   60: astore 6
    //   62: aload_2
    //   63: aload 4
    //   65: iload 5
    //   67: aload 6
    //   69: invokevirtual 53	com/google/android/gms/cast/internal/zzm:zza	(Lcom/google/android/gms/cast/internal/zzo;ZLorg/json/JSONObject;)J
    //   72: pop2
    //   73: aload_0
    //   74: getfield 14	com/google/android/gms/cast/RemoteMediaPlayer$22:zzabK	Lcom/google/android/gms/cast/RemoteMediaPlayer;
    //   77: astore_2
    //   78: aload_2
    //   79: invokestatic 34	com/google/android/gms/cast/RemoteMediaPlayer:zzf	(Lcom/google/android/gms/cast/RemoteMediaPlayer;)Lcom/google/android/gms/cast/RemoteMediaPlayer$zza;
    //   82: astore_2
    //   83: iconst_0
    //   84: istore 7
    //   86: aconst_null
    //   87: astore 4
    //   89: aload_2
    //   90: aconst_null
    //   91: invokevirtual 39	com/google/android/gms/cast/RemoteMediaPlayer$zza:zzc	(Lcom/google/android/gms/common/api/GoogleApiClient;)V
    //   94: aload_3
    //   95: monitorexit
    //   96: return
    //   97: astore_2
    //   98: new 55	com/google/android/gms/common/api/Status
    //   101: astore_2
    //   102: sipush 2100
    //   105: istore 7
    //   107: aload_2
    //   108: iload 7
    //   110: invokespecial 59	com/google/android/gms/common/api/Status:<init>	(I)V
    //   113: aload_0
    //   114: aload_2
    //   115: invokevirtual 63	com/google/android/gms/cast/RemoteMediaPlayer$22:zzq	(Lcom/google/android/gms/common/api/Status;)Lcom/google/android/gms/cast/RemoteMediaPlayer$MediaChannelResult;
    //   118: astore_2
    //   119: aload_0
    //   120: aload_2
    //   121: invokevirtual 66	com/google/android/gms/cast/RemoteMediaPlayer$22:zza	(Lcom/google/android/gms/common/api/Result;)V
    //   124: aload_0
    //   125: getfield 14	com/google/android/gms/cast/RemoteMediaPlayer$22:zzabK	Lcom/google/android/gms/cast/RemoteMediaPlayer;
    //   128: astore_2
    //   129: aload_2
    //   130: invokestatic 34	com/google/android/gms/cast/RemoteMediaPlayer:zzf	(Lcom/google/android/gms/cast/RemoteMediaPlayer;)Lcom/google/android/gms/cast/RemoteMediaPlayer$zza;
    //   133: astore_2
    //   134: iconst_0
    //   135: istore 7
    //   137: aconst_null
    //   138: astore 4
    //   140: aload_2
    //   141: aconst_null
    //   142: invokevirtual 39	com/google/android/gms/cast/RemoteMediaPlayer$zza:zzc	(Lcom/google/android/gms/common/api/GoogleApiClient;)V
    //   145: goto -51 -> 94
    //   148: astore_2
    //   149: aload_3
    //   150: monitorexit
    //   151: aload_2
    //   152: athrow
    //   153: astore_2
    //   154: aload_0
    //   155: getfield 14	com/google/android/gms/cast/RemoteMediaPlayer$22:zzabK	Lcom/google/android/gms/cast/RemoteMediaPlayer;
    //   158: astore 4
    //   160: aload 4
    //   162: invokestatic 34	com/google/android/gms/cast/RemoteMediaPlayer:zzf	(Lcom/google/android/gms/cast/RemoteMediaPlayer;)Lcom/google/android/gms/cast/RemoteMediaPlayer$zza;
    //   165: astore 4
    //   167: iconst_0
    //   168: istore 5
    //   170: aload 4
    //   172: aconst_null
    //   173: invokevirtual 39	com/google/android/gms/cast/RemoteMediaPlayer$zza:zzc	(Lcom/google/android/gms/common/api/GoogleApiClient;)V
    //   176: aload_2
    //   177: athrow
    //   178: astore_2
    //   179: goto -81 -> 98
    // Local variable table:
    //   start	length	slot	name	signature
    //   0	182	0	this	22
    //   0	182	1	paramzze	com.google.android.gms.cast.internal.zze
    //   4	86	2	localObject1	Object
    //   97	1	2	localIllegalStateException	IllegalStateException
    //   101	40	2	localObject2	Object
    //   148	4	2	localObject3	Object
    //   153	24	2	localObject4	Object
    //   178	1	2	localIOException	java.io.IOException
    //   9	141	3	localObject5	Object
    //   26	145	4	localObject6	Object
    //   54	115	5	bool	boolean
    //   60	8	6	localJSONObject	JSONObject
    //   84	52	7	i	int
    // Exception table:
    //   from	to	target	type
    //   34	38	97	java/lang/IllegalStateException
    //   39	43	97	java/lang/IllegalStateException
    //   44	48	97	java/lang/IllegalStateException
    //   50	54	97	java/lang/IllegalStateException
    //   56	60	97	java/lang/IllegalStateException
    //   67	73	97	java/lang/IllegalStateException
    //   12	16	148	finally
    //   17	21	148	finally
    //   22	26	148	finally
    //   29	34	148	finally
    //   73	77	148	finally
    //   78	82	148	finally
    //   90	94	148	finally
    //   94	96	148	finally
    //   124	128	148	finally
    //   129	133	148	finally
    //   141	145	148	finally
    //   149	151	148	finally
    //   154	158	148	finally
    //   160	165	148	finally
    //   172	176	148	finally
    //   176	178	148	finally
    //   34	38	153	finally
    //   39	43	153	finally
    //   44	48	153	finally
    //   50	54	153	finally
    //   56	60	153	finally
    //   67	73	153	finally
    //   98	101	153	finally
    //   108	113	153	finally
    //   114	118	153	finally
    //   120	124	153	finally
    //   34	38	178	java/io/IOException
    //   39	43	178	java/io/IOException
    //   44	48	178	java/io/IOException
    //   50	54	178	java/io/IOException
    //   56	60	178	java/io/IOException
    //   67	73	178	java/io/IOException
  }
}


/* Location:              C:\Users\haryo\Desktop\enjarify-master\presensi-enjarify.jar!\com\google\android\gms\cast\RemoteMediaPlayer$22.class
 * Java compiler version: 5 (49.0)
 * JD-Core Version:       0.7.1
 */