package com.google.android.gms.games.internal;

import android.os.IBinder;
import android.os.Parcel;
import com.google.android.gms.common.data.DataHolder;
import com.google.android.gms.drive.Contents;

class IGamesCallbacks$Stub$Proxy
  implements IGamesCallbacks
{
  private IBinder zzoz;
  
  IGamesCallbacks$Stub$Proxy(IBinder paramIBinder)
  {
    this.zzoz = paramIBinder;
  }
  
  public IBinder asBinder()
  {
    return this.zzoz;
  }
  
  public void onInvitationRemoved(String paramString)
  {
    Parcel localParcel1 = Parcel.obtain();
    Parcel localParcel2 = Parcel.obtain();
    Object localObject1 = "com.google.android.gms.games.internal.IGamesCallbacks";
    try
    {
      localParcel1.writeInterfaceToken((String)localObject1);
      localParcel1.writeString(paramString);
      localObject1 = this.zzoz;
      int i = 8010;
      ((IBinder)localObject1).transact(i, localParcel1, localParcel2, 0);
      localParcel2.readException();
      return;
    }
    finally
    {
      localParcel2.recycle();
      localParcel1.recycle();
    }
  }
  
  public void onLeftRoom(int paramInt, String paramString)
  {
    Parcel localParcel1 = Parcel.obtain();
    Parcel localParcel2 = Parcel.obtain();
    Object localObject1 = "com.google.android.gms.games.internal.IGamesCallbacks";
    try
    {
      localParcel1.writeInterfaceToken((String)localObject1);
      localParcel1.writeInt(paramInt);
      localParcel1.writeString(paramString);
      localObject1 = this.zzoz;
      int i = 5020;
      ((IBinder)localObject1).transact(i, localParcel1, localParcel2, 0);
      localParcel2.readException();
      return;
    }
    finally
    {
      localParcel2.recycle();
      localParcel1.recycle();
    }
  }
  
  public void onP2PConnected(String paramString)
  {
    Parcel localParcel1 = Parcel.obtain();
    Parcel localParcel2 = Parcel.obtain();
    Object localObject1 = "com.google.android.gms.games.internal.IGamesCallbacks";
    try
    {
      localParcel1.writeInterfaceToken((String)localObject1);
      localParcel1.writeString(paramString);
      localObject1 = this.zzoz;
      int i = 6001;
      ((IBinder)localObject1).transact(i, localParcel1, localParcel2, 0);
      localParcel2.readException();
      return;
    }
    finally
    {
      localParcel2.recycle();
      localParcel1.recycle();
    }
  }
  
  public void onP2PDisconnected(String paramString)
  {
    Parcel localParcel1 = Parcel.obtain();
    Parcel localParcel2 = Parcel.obtain();
    Object localObject1 = "com.google.android.gms.games.internal.IGamesCallbacks";
    try
    {
      localParcel1.writeInterfaceToken((String)localObject1);
      localParcel1.writeString(paramString);
      localObject1 = this.zzoz;
      int i = 6002;
      ((IBinder)localObject1).transact(i, localParcel1, localParcel2, 0);
      localParcel2.readException();
      return;
    }
    finally
    {
      localParcel2.recycle();
      localParcel1.recycle();
    }
  }
  
  /* Error */
  public void onRealTimeMessageReceived(com.google.android.gms.games.multiplayer.realtime.RealTimeMessage paramRealTimeMessage)
  {
    // Byte code:
    //   0: invokestatic 20	android/os/Parcel:obtain	()Landroid/os/Parcel;
    //   3: astore_2
    //   4: invokestatic 20	android/os/Parcel:obtain	()Landroid/os/Parcel;
    //   7: astore_3
    //   8: ldc 22
    //   10: astore 4
    //   12: aload_2
    //   13: aload 4
    //   15: invokevirtual 26	android/os/Parcel:writeInterfaceToken	(Ljava/lang/String;)V
    //   18: aload_1
    //   19: ifnull +61 -> 80
    //   22: iconst_1
    //   23: istore 5
    //   25: aload_2
    //   26: iload 5
    //   28: invokevirtual 46	android/os/Parcel:writeInt	(I)V
    //   31: iconst_0
    //   32: istore 5
    //   34: aconst_null
    //   35: astore 4
    //   37: aload_1
    //   38: aload_2
    //   39: iconst_0
    //   40: invokevirtual 56	com/google/android/gms/games/multiplayer/realtime/RealTimeMessage:writeToParcel	(Landroid/os/Parcel;I)V
    //   43: aload_0
    //   44: getfield 14	com/google/android/gms/games/internal/IGamesCallbacks$Stub$Proxy:zzoz	Landroid/os/IBinder;
    //   47: astore 4
    //   49: sipush 5032
    //   52: istore 6
    //   54: aload 4
    //   56: iload 6
    //   58: aload_2
    //   59: aload_3
    //   60: iconst_0
    //   61: invokeinterface 36 5 0
    //   66: pop
    //   67: aload_3
    //   68: invokevirtual 39	android/os/Parcel:readException	()V
    //   71: aload_3
    //   72: invokevirtual 42	android/os/Parcel:recycle	()V
    //   75: aload_2
    //   76: invokevirtual 42	android/os/Parcel:recycle	()V
    //   79: return
    //   80: iconst_0
    //   81: istore 5
    //   83: aconst_null
    //   84: astore 4
    //   86: aload_2
    //   87: iconst_0
    //   88: invokevirtual 46	android/os/Parcel:writeInt	(I)V
    //   91: goto -48 -> 43
    //   94: astore 4
    //   96: aload_3
    //   97: invokevirtual 42	android/os/Parcel:recycle	()V
    //   100: aload_2
    //   101: invokevirtual 42	android/os/Parcel:recycle	()V
    //   104: aload 4
    //   106: athrow
    // Local variable table:
    //   start	length	slot	name	signature
    //   0	107	0	this	Proxy
    //   0	107	1	paramRealTimeMessage	com.google.android.gms.games.multiplayer.realtime.RealTimeMessage
    //   3	98	2	localParcel1	Parcel
    //   7	90	3	localParcel2	Parcel
    //   10	75	4	localObject1	Object
    //   94	11	4	localObject2	Object
    //   23	59	5	i	int
    //   52	5	6	j	int
    // Exception table:
    //   from	to	target	type
    //   13	18	94	finally
    //   26	31	94	finally
    //   39	43	94	finally
    //   43	47	94	finally
    //   60	67	94	finally
    //   67	71	94	finally
    //   87	91	94	finally
  }
  
  public void onRequestRemoved(String paramString)
  {
    Parcel localParcel1 = Parcel.obtain();
    Parcel localParcel2 = Parcel.obtain();
    Object localObject1 = "com.google.android.gms.games.internal.IGamesCallbacks";
    try
    {
      localParcel1.writeInterfaceToken((String)localObject1);
      localParcel1.writeString(paramString);
      localObject1 = this.zzoz;
      int i = 10002;
      ((IBinder)localObject1).transact(i, localParcel1, localParcel2, 0);
      localParcel2.readException();
      return;
    }
    finally
    {
      localParcel2.recycle();
      localParcel1.recycle();
    }
  }
  
  public void onTurnBasedMatchRemoved(String paramString)
  {
    Parcel localParcel1 = Parcel.obtain();
    Parcel localParcel2 = Parcel.obtain();
    Object localObject1 = "com.google.android.gms.games.internal.IGamesCallbacks";
    try
    {
      localParcel1.writeInterfaceToken((String)localObject1);
      localParcel1.writeString(paramString);
      localObject1 = this.zzoz;
      int i = 8009;
      ((IBinder)localObject1).transact(i, localParcel1, localParcel2, 0);
      localParcel2.readException();
      return;
    }
    finally
    {
      localParcel2.recycle();
      localParcel1.recycle();
    }
  }
  
  /* Error */
  public void zzA(DataHolder paramDataHolder)
  {
    // Byte code:
    //   0: invokestatic 20	android/os/Parcel:obtain	()Landroid/os/Parcel;
    //   3: astore_2
    //   4: invokestatic 20	android/os/Parcel:obtain	()Landroid/os/Parcel;
    //   7: astore_3
    //   8: ldc 22
    //   10: astore 4
    //   12: aload_2
    //   13: aload 4
    //   15: invokevirtual 26	android/os/Parcel:writeInterfaceToken	(Ljava/lang/String;)V
    //   18: aload_1
    //   19: ifnull +61 -> 80
    //   22: iconst_1
    //   23: istore 5
    //   25: aload_2
    //   26: iload 5
    //   28: invokevirtual 46	android/os/Parcel:writeInt	(I)V
    //   31: iconst_0
    //   32: istore 5
    //   34: aconst_null
    //   35: astore 4
    //   37: aload_1
    //   38: aload_2
    //   39: iconst_0
    //   40: invokevirtual 62	com/google/android/gms/common/data/DataHolder:writeToParcel	(Landroid/os/Parcel;I)V
    //   43: aload_0
    //   44: getfield 14	com/google/android/gms/games/internal/IGamesCallbacks$Stub$Proxy:zzoz	Landroid/os/IBinder;
    //   47: astore 4
    //   49: sipush 5019
    //   52: istore 6
    //   54: aload 4
    //   56: iload 6
    //   58: aload_2
    //   59: aload_3
    //   60: iconst_0
    //   61: invokeinterface 36 5 0
    //   66: pop
    //   67: aload_3
    //   68: invokevirtual 39	android/os/Parcel:readException	()V
    //   71: aload_3
    //   72: invokevirtual 42	android/os/Parcel:recycle	()V
    //   75: aload_2
    //   76: invokevirtual 42	android/os/Parcel:recycle	()V
    //   79: return
    //   80: iconst_0
    //   81: istore 5
    //   83: aconst_null
    //   84: astore 4
    //   86: aload_2
    //   87: iconst_0
    //   88: invokevirtual 46	android/os/Parcel:writeInt	(I)V
    //   91: goto -48 -> 43
    //   94: astore 4
    //   96: aload_3
    //   97: invokevirtual 42	android/os/Parcel:recycle	()V
    //   100: aload_2
    //   101: invokevirtual 42	android/os/Parcel:recycle	()V
    //   104: aload 4
    //   106: athrow
    // Local variable table:
    //   start	length	slot	name	signature
    //   0	107	0	this	Proxy
    //   0	107	1	paramDataHolder	DataHolder
    //   3	98	2	localParcel1	Parcel
    //   7	90	3	localParcel2	Parcel
    //   10	75	4	localObject1	Object
    //   94	11	4	localObject2	Object
    //   23	59	5	i	int
    //   52	5	6	j	int
    // Exception table:
    //   from	to	target	type
    //   13	18	94	finally
    //   26	31	94	finally
    //   39	43	94	finally
    //   43	47	94	finally
    //   60	67	94	finally
    //   67	71	94	finally
    //   87	91	94	finally
  }
  
  /* Error */
  public void zzB(DataHolder paramDataHolder)
  {
    // Byte code:
    //   0: invokestatic 20	android/os/Parcel:obtain	()Landroid/os/Parcel;
    //   3: astore_2
    //   4: invokestatic 20	android/os/Parcel:obtain	()Landroid/os/Parcel;
    //   7: astore_3
    //   8: ldc 22
    //   10: astore 4
    //   12: aload_2
    //   13: aload 4
    //   15: invokevirtual 26	android/os/Parcel:writeInterfaceToken	(Ljava/lang/String;)V
    //   18: aload_1
    //   19: ifnull +61 -> 80
    //   22: iconst_1
    //   23: istore 5
    //   25: aload_2
    //   26: iload 5
    //   28: invokevirtual 46	android/os/Parcel:writeInt	(I)V
    //   31: iconst_0
    //   32: istore 5
    //   34: aconst_null
    //   35: astore 4
    //   37: aload_1
    //   38: aload_2
    //   39: iconst_0
    //   40: invokevirtual 62	com/google/android/gms/common/data/DataHolder:writeToParcel	(Landroid/os/Parcel;I)V
    //   43: aload_0
    //   44: getfield 14	com/google/android/gms/games/internal/IGamesCallbacks$Stub$Proxy:zzoz	Landroid/os/IBinder;
    //   47: astore 4
    //   49: sipush 5021
    //   52: istore 6
    //   54: aload 4
    //   56: iload 6
    //   58: aload_2
    //   59: aload_3
    //   60: iconst_0
    //   61: invokeinterface 36 5 0
    //   66: pop
    //   67: aload_3
    //   68: invokevirtual 39	android/os/Parcel:readException	()V
    //   71: aload_3
    //   72: invokevirtual 42	android/os/Parcel:recycle	()V
    //   75: aload_2
    //   76: invokevirtual 42	android/os/Parcel:recycle	()V
    //   79: return
    //   80: iconst_0
    //   81: istore 5
    //   83: aconst_null
    //   84: astore 4
    //   86: aload_2
    //   87: iconst_0
    //   88: invokevirtual 46	android/os/Parcel:writeInt	(I)V
    //   91: goto -48 -> 43
    //   94: astore 4
    //   96: aload_3
    //   97: invokevirtual 42	android/os/Parcel:recycle	()V
    //   100: aload_2
    //   101: invokevirtual 42	android/os/Parcel:recycle	()V
    //   104: aload 4
    //   106: athrow
    // Local variable table:
    //   start	length	slot	name	signature
    //   0	107	0	this	Proxy
    //   0	107	1	paramDataHolder	DataHolder
    //   3	98	2	localParcel1	Parcel
    //   7	90	3	localParcel2	Parcel
    //   10	75	4	localObject1	Object
    //   94	11	4	localObject2	Object
    //   23	59	5	i	int
    //   52	5	6	j	int
    // Exception table:
    //   from	to	target	type
    //   13	18	94	finally
    //   26	31	94	finally
    //   39	43	94	finally
    //   43	47	94	finally
    //   60	67	94	finally
    //   67	71	94	finally
    //   87	91	94	finally
  }
  
  /* Error */
  public void zzC(DataHolder paramDataHolder)
  {
    // Byte code:
    //   0: invokestatic 20	android/os/Parcel:obtain	()Landroid/os/Parcel;
    //   3: astore_2
    //   4: invokestatic 20	android/os/Parcel:obtain	()Landroid/os/Parcel;
    //   7: astore_3
    //   8: ldc 22
    //   10: astore 4
    //   12: aload_2
    //   13: aload 4
    //   15: invokevirtual 26	android/os/Parcel:writeInterfaceToken	(Ljava/lang/String;)V
    //   18: aload_1
    //   19: ifnull +61 -> 80
    //   22: iconst_1
    //   23: istore 5
    //   25: aload_2
    //   26: iload 5
    //   28: invokevirtual 46	android/os/Parcel:writeInt	(I)V
    //   31: iconst_0
    //   32: istore 5
    //   34: aconst_null
    //   35: astore 4
    //   37: aload_1
    //   38: aload_2
    //   39: iconst_0
    //   40: invokevirtual 62	com/google/android/gms/common/data/DataHolder:writeToParcel	(Landroid/os/Parcel;I)V
    //   43: aload_0
    //   44: getfield 14	com/google/android/gms/games/internal/IGamesCallbacks$Stub$Proxy:zzoz	Landroid/os/IBinder;
    //   47: astore 4
    //   49: sipush 5022
    //   52: istore 6
    //   54: aload 4
    //   56: iload 6
    //   58: aload_2
    //   59: aload_3
    //   60: iconst_0
    //   61: invokeinterface 36 5 0
    //   66: pop
    //   67: aload_3
    //   68: invokevirtual 39	android/os/Parcel:readException	()V
    //   71: aload_3
    //   72: invokevirtual 42	android/os/Parcel:recycle	()V
    //   75: aload_2
    //   76: invokevirtual 42	android/os/Parcel:recycle	()V
    //   79: return
    //   80: iconst_0
    //   81: istore 5
    //   83: aconst_null
    //   84: astore 4
    //   86: aload_2
    //   87: iconst_0
    //   88: invokevirtual 46	android/os/Parcel:writeInt	(I)V
    //   91: goto -48 -> 43
    //   94: astore 4
    //   96: aload_3
    //   97: invokevirtual 42	android/os/Parcel:recycle	()V
    //   100: aload_2
    //   101: invokevirtual 42	android/os/Parcel:recycle	()V
    //   104: aload 4
    //   106: athrow
    // Local variable table:
    //   start	length	slot	name	signature
    //   0	107	0	this	Proxy
    //   0	107	1	paramDataHolder	DataHolder
    //   3	98	2	localParcel1	Parcel
    //   7	90	3	localParcel2	Parcel
    //   10	75	4	localObject1	Object
    //   94	11	4	localObject2	Object
    //   23	59	5	i	int
    //   52	5	6	j	int
    // Exception table:
    //   from	to	target	type
    //   13	18	94	finally
    //   26	31	94	finally
    //   39	43	94	finally
    //   43	47	94	finally
    //   60	67	94	finally
    //   67	71	94	finally
    //   87	91	94	finally
  }
  
  /* Error */
  public void zzD(DataHolder paramDataHolder)
  {
    // Byte code:
    //   0: invokestatic 20	android/os/Parcel:obtain	()Landroid/os/Parcel;
    //   3: astore_2
    //   4: invokestatic 20	android/os/Parcel:obtain	()Landroid/os/Parcel;
    //   7: astore_3
    //   8: ldc 22
    //   10: astore 4
    //   12: aload_2
    //   13: aload 4
    //   15: invokevirtual 26	android/os/Parcel:writeInterfaceToken	(Ljava/lang/String;)V
    //   18: aload_1
    //   19: ifnull +61 -> 80
    //   22: iconst_1
    //   23: istore 5
    //   25: aload_2
    //   26: iload 5
    //   28: invokevirtual 46	android/os/Parcel:writeInt	(I)V
    //   31: iconst_0
    //   32: istore 5
    //   34: aconst_null
    //   35: astore 4
    //   37: aload_1
    //   38: aload_2
    //   39: iconst_0
    //   40: invokevirtual 62	com/google/android/gms/common/data/DataHolder:writeToParcel	(Landroid/os/Parcel;I)V
    //   43: aload_0
    //   44: getfield 14	com/google/android/gms/games/internal/IGamesCallbacks$Stub$Proxy:zzoz	Landroid/os/IBinder;
    //   47: astore 4
    //   49: sipush 5023
    //   52: istore 6
    //   54: aload 4
    //   56: iload 6
    //   58: aload_2
    //   59: aload_3
    //   60: iconst_0
    //   61: invokeinterface 36 5 0
    //   66: pop
    //   67: aload_3
    //   68: invokevirtual 39	android/os/Parcel:readException	()V
    //   71: aload_3
    //   72: invokevirtual 42	android/os/Parcel:recycle	()V
    //   75: aload_2
    //   76: invokevirtual 42	android/os/Parcel:recycle	()V
    //   79: return
    //   80: iconst_0
    //   81: istore 5
    //   83: aconst_null
    //   84: astore 4
    //   86: aload_2
    //   87: iconst_0
    //   88: invokevirtual 46	android/os/Parcel:writeInt	(I)V
    //   91: goto -48 -> 43
    //   94: astore 4
    //   96: aload_3
    //   97: invokevirtual 42	android/os/Parcel:recycle	()V
    //   100: aload_2
    //   101: invokevirtual 42	android/os/Parcel:recycle	()V
    //   104: aload 4
    //   106: athrow
    // Local variable table:
    //   start	length	slot	name	signature
    //   0	107	0	this	Proxy
    //   0	107	1	paramDataHolder	DataHolder
    //   3	98	2	localParcel1	Parcel
    //   7	90	3	localParcel2	Parcel
    //   10	75	4	localObject1	Object
    //   94	11	4	localObject2	Object
    //   23	59	5	i	int
    //   52	5	6	j	int
    // Exception table:
    //   from	to	target	type
    //   13	18	94	finally
    //   26	31	94	finally
    //   39	43	94	finally
    //   43	47	94	finally
    //   60	67	94	finally
    //   67	71	94	finally
    //   87	91	94	finally
  }
  
  /* Error */
  public void zzE(DataHolder paramDataHolder)
  {
    // Byte code:
    //   0: invokestatic 20	android/os/Parcel:obtain	()Landroid/os/Parcel;
    //   3: astore_2
    //   4: invokestatic 20	android/os/Parcel:obtain	()Landroid/os/Parcel;
    //   7: astore_3
    //   8: ldc 22
    //   10: astore 4
    //   12: aload_2
    //   13: aload 4
    //   15: invokevirtual 26	android/os/Parcel:writeInterfaceToken	(Ljava/lang/String;)V
    //   18: aload_1
    //   19: ifnull +61 -> 80
    //   22: iconst_1
    //   23: istore 5
    //   25: aload_2
    //   26: iload 5
    //   28: invokevirtual 46	android/os/Parcel:writeInt	(I)V
    //   31: iconst_0
    //   32: istore 5
    //   34: aconst_null
    //   35: astore 4
    //   37: aload_1
    //   38: aload_2
    //   39: iconst_0
    //   40: invokevirtual 62	com/google/android/gms/common/data/DataHolder:writeToParcel	(Landroid/os/Parcel;I)V
    //   43: aload_0
    //   44: getfield 14	com/google/android/gms/games/internal/IGamesCallbacks$Stub$Proxy:zzoz	Landroid/os/IBinder;
    //   47: astore 4
    //   49: sipush 5024
    //   52: istore 6
    //   54: aload 4
    //   56: iload 6
    //   58: aload_2
    //   59: aload_3
    //   60: iconst_0
    //   61: invokeinterface 36 5 0
    //   66: pop
    //   67: aload_3
    //   68: invokevirtual 39	android/os/Parcel:readException	()V
    //   71: aload_3
    //   72: invokevirtual 42	android/os/Parcel:recycle	()V
    //   75: aload_2
    //   76: invokevirtual 42	android/os/Parcel:recycle	()V
    //   79: return
    //   80: iconst_0
    //   81: istore 5
    //   83: aconst_null
    //   84: astore 4
    //   86: aload_2
    //   87: iconst_0
    //   88: invokevirtual 46	android/os/Parcel:writeInt	(I)V
    //   91: goto -48 -> 43
    //   94: astore 4
    //   96: aload_3
    //   97: invokevirtual 42	android/os/Parcel:recycle	()V
    //   100: aload_2
    //   101: invokevirtual 42	android/os/Parcel:recycle	()V
    //   104: aload 4
    //   106: athrow
    // Local variable table:
    //   start	length	slot	name	signature
    //   0	107	0	this	Proxy
    //   0	107	1	paramDataHolder	DataHolder
    //   3	98	2	localParcel1	Parcel
    //   7	90	3	localParcel2	Parcel
    //   10	75	4	localObject1	Object
    //   94	11	4	localObject2	Object
    //   23	59	5	i	int
    //   52	5	6	j	int
    // Exception table:
    //   from	to	target	type
    //   13	18	94	finally
    //   26	31	94	finally
    //   39	43	94	finally
    //   43	47	94	finally
    //   60	67	94	finally
    //   67	71	94	finally
    //   87	91	94	finally
  }
  
  /* Error */
  public void zzF(DataHolder paramDataHolder)
  {
    // Byte code:
    //   0: invokestatic 20	android/os/Parcel:obtain	()Landroid/os/Parcel;
    //   3: astore_2
    //   4: invokestatic 20	android/os/Parcel:obtain	()Landroid/os/Parcel;
    //   7: astore_3
    //   8: ldc 22
    //   10: astore 4
    //   12: aload_2
    //   13: aload 4
    //   15: invokevirtual 26	android/os/Parcel:writeInterfaceToken	(Ljava/lang/String;)V
    //   18: aload_1
    //   19: ifnull +61 -> 80
    //   22: iconst_1
    //   23: istore 5
    //   25: aload_2
    //   26: iload 5
    //   28: invokevirtual 46	android/os/Parcel:writeInt	(I)V
    //   31: iconst_0
    //   32: istore 5
    //   34: aconst_null
    //   35: astore 4
    //   37: aload_1
    //   38: aload_2
    //   39: iconst_0
    //   40: invokevirtual 62	com/google/android/gms/common/data/DataHolder:writeToParcel	(Landroid/os/Parcel;I)V
    //   43: aload_0
    //   44: getfield 14	com/google/android/gms/games/internal/IGamesCallbacks$Stub$Proxy:zzoz	Landroid/os/IBinder;
    //   47: astore 4
    //   49: sipush 5025
    //   52: istore 6
    //   54: aload 4
    //   56: iload 6
    //   58: aload_2
    //   59: aload_3
    //   60: iconst_0
    //   61: invokeinterface 36 5 0
    //   66: pop
    //   67: aload_3
    //   68: invokevirtual 39	android/os/Parcel:readException	()V
    //   71: aload_3
    //   72: invokevirtual 42	android/os/Parcel:recycle	()V
    //   75: aload_2
    //   76: invokevirtual 42	android/os/Parcel:recycle	()V
    //   79: return
    //   80: iconst_0
    //   81: istore 5
    //   83: aconst_null
    //   84: astore 4
    //   86: aload_2
    //   87: iconst_0
    //   88: invokevirtual 46	android/os/Parcel:writeInt	(I)V
    //   91: goto -48 -> 43
    //   94: astore 4
    //   96: aload_3
    //   97: invokevirtual 42	android/os/Parcel:recycle	()V
    //   100: aload_2
    //   101: invokevirtual 42	android/os/Parcel:recycle	()V
    //   104: aload 4
    //   106: athrow
    // Local variable table:
    //   start	length	slot	name	signature
    //   0	107	0	this	Proxy
    //   0	107	1	paramDataHolder	DataHolder
    //   3	98	2	localParcel1	Parcel
    //   7	90	3	localParcel2	Parcel
    //   10	75	4	localObject1	Object
    //   94	11	4	localObject2	Object
    //   23	59	5	i	int
    //   52	5	6	j	int
    // Exception table:
    //   from	to	target	type
    //   13	18	94	finally
    //   26	31	94	finally
    //   39	43	94	finally
    //   43	47	94	finally
    //   60	67	94	finally
    //   67	71	94	finally
    //   87	91	94	finally
  }
  
  /* Error */
  public void zzG(DataHolder paramDataHolder)
  {
    // Byte code:
    //   0: invokestatic 20	android/os/Parcel:obtain	()Landroid/os/Parcel;
    //   3: astore_2
    //   4: invokestatic 20	android/os/Parcel:obtain	()Landroid/os/Parcel;
    //   7: astore_3
    //   8: ldc 22
    //   10: astore 4
    //   12: aload_2
    //   13: aload 4
    //   15: invokevirtual 26	android/os/Parcel:writeInterfaceToken	(Ljava/lang/String;)V
    //   18: aload_1
    //   19: ifnull +61 -> 80
    //   22: iconst_1
    //   23: istore 5
    //   25: aload_2
    //   26: iload 5
    //   28: invokevirtual 46	android/os/Parcel:writeInt	(I)V
    //   31: iconst_0
    //   32: istore 5
    //   34: aconst_null
    //   35: astore 4
    //   37: aload_1
    //   38: aload_2
    //   39: iconst_0
    //   40: invokevirtual 62	com/google/android/gms/common/data/DataHolder:writeToParcel	(Landroid/os/Parcel;I)V
    //   43: aload_0
    //   44: getfield 14	com/google/android/gms/games/internal/IGamesCallbacks$Stub$Proxy:zzoz	Landroid/os/IBinder;
    //   47: astore 4
    //   49: sipush 5038
    //   52: istore 6
    //   54: aload 4
    //   56: iload 6
    //   58: aload_2
    //   59: aload_3
    //   60: iconst_0
    //   61: invokeinterface 36 5 0
    //   66: pop
    //   67: aload_3
    //   68: invokevirtual 39	android/os/Parcel:readException	()V
    //   71: aload_3
    //   72: invokevirtual 42	android/os/Parcel:recycle	()V
    //   75: aload_2
    //   76: invokevirtual 42	android/os/Parcel:recycle	()V
    //   79: return
    //   80: iconst_0
    //   81: istore 5
    //   83: aconst_null
    //   84: astore 4
    //   86: aload_2
    //   87: iconst_0
    //   88: invokevirtual 46	android/os/Parcel:writeInt	(I)V
    //   91: goto -48 -> 43
    //   94: astore 4
    //   96: aload_3
    //   97: invokevirtual 42	android/os/Parcel:recycle	()V
    //   100: aload_2
    //   101: invokevirtual 42	android/os/Parcel:recycle	()V
    //   104: aload 4
    //   106: athrow
    // Local variable table:
    //   start	length	slot	name	signature
    //   0	107	0	this	Proxy
    //   0	107	1	paramDataHolder	DataHolder
    //   3	98	2	localParcel1	Parcel
    //   7	90	3	localParcel2	Parcel
    //   10	75	4	localObject1	Object
    //   94	11	4	localObject2	Object
    //   23	59	5	i	int
    //   52	5	6	j	int
    // Exception table:
    //   from	to	target	type
    //   13	18	94	finally
    //   26	31	94	finally
    //   39	43	94	finally
    //   43	47	94	finally
    //   60	67	94	finally
    //   67	71	94	finally
    //   87	91	94	finally
  }
  
  /* Error */
  public void zzH(DataHolder paramDataHolder)
  {
    // Byte code:
    //   0: invokestatic 20	android/os/Parcel:obtain	()Landroid/os/Parcel;
    //   3: astore_2
    //   4: invokestatic 20	android/os/Parcel:obtain	()Landroid/os/Parcel;
    //   7: astore_3
    //   8: ldc 22
    //   10: astore 4
    //   12: aload_2
    //   13: aload 4
    //   15: invokevirtual 26	android/os/Parcel:writeInterfaceToken	(Ljava/lang/String;)V
    //   18: aload_1
    //   19: ifnull +61 -> 80
    //   22: iconst_1
    //   23: istore 5
    //   25: aload_2
    //   26: iload 5
    //   28: invokevirtual 46	android/os/Parcel:writeInt	(I)V
    //   31: iconst_0
    //   32: istore 5
    //   34: aconst_null
    //   35: astore 4
    //   37: aload_1
    //   38: aload_2
    //   39: iconst_0
    //   40: invokevirtual 62	com/google/android/gms/common/data/DataHolder:writeToParcel	(Landroid/os/Parcel;I)V
    //   43: aload_0
    //   44: getfield 14	com/google/android/gms/games/internal/IGamesCallbacks$Stub$Proxy:zzoz	Landroid/os/IBinder;
    //   47: astore 4
    //   49: sipush 5035
    //   52: istore 6
    //   54: aload 4
    //   56: iload 6
    //   58: aload_2
    //   59: aload_3
    //   60: iconst_0
    //   61: invokeinterface 36 5 0
    //   66: pop
    //   67: aload_3
    //   68: invokevirtual 39	android/os/Parcel:readException	()V
    //   71: aload_3
    //   72: invokevirtual 42	android/os/Parcel:recycle	()V
    //   75: aload_2
    //   76: invokevirtual 42	android/os/Parcel:recycle	()V
    //   79: return
    //   80: iconst_0
    //   81: istore 5
    //   83: aconst_null
    //   84: astore 4
    //   86: aload_2
    //   87: iconst_0
    //   88: invokevirtual 46	android/os/Parcel:writeInt	(I)V
    //   91: goto -48 -> 43
    //   94: astore 4
    //   96: aload_3
    //   97: invokevirtual 42	android/os/Parcel:recycle	()V
    //   100: aload_2
    //   101: invokevirtual 42	android/os/Parcel:recycle	()V
    //   104: aload 4
    //   106: athrow
    // Local variable table:
    //   start	length	slot	name	signature
    //   0	107	0	this	Proxy
    //   0	107	1	paramDataHolder	DataHolder
    //   3	98	2	localParcel1	Parcel
    //   7	90	3	localParcel2	Parcel
    //   10	75	4	localObject1	Object
    //   94	11	4	localObject2	Object
    //   23	59	5	i	int
    //   52	5	6	j	int
    // Exception table:
    //   from	to	target	type
    //   13	18	94	finally
    //   26	31	94	finally
    //   39	43	94	finally
    //   43	47	94	finally
    //   60	67	94	finally
    //   67	71	94	finally
    //   87	91	94	finally
  }
  
  /* Error */
  public void zzI(DataHolder paramDataHolder)
  {
    // Byte code:
    //   0: invokestatic 20	android/os/Parcel:obtain	()Landroid/os/Parcel;
    //   3: astore_2
    //   4: invokestatic 20	android/os/Parcel:obtain	()Landroid/os/Parcel;
    //   7: astore_3
    //   8: ldc 22
    //   10: astore 4
    //   12: aload_2
    //   13: aload 4
    //   15: invokevirtual 26	android/os/Parcel:writeInterfaceToken	(Ljava/lang/String;)V
    //   18: aload_1
    //   19: ifnull +61 -> 80
    //   22: iconst_1
    //   23: istore 5
    //   25: aload_2
    //   26: iload 5
    //   28: invokevirtual 46	android/os/Parcel:writeInt	(I)V
    //   31: iconst_0
    //   32: istore 5
    //   34: aconst_null
    //   35: astore 4
    //   37: aload_1
    //   38: aload_2
    //   39: iconst_0
    //   40: invokevirtual 62	com/google/android/gms/common/data/DataHolder:writeToParcel	(Landroid/os/Parcel;I)V
    //   43: aload_0
    //   44: getfield 14	com/google/android/gms/games/internal/IGamesCallbacks$Stub$Proxy:zzoz	Landroid/os/IBinder;
    //   47: astore 4
    //   49: sipush 5039
    //   52: istore 6
    //   54: aload 4
    //   56: iload 6
    //   58: aload_2
    //   59: aload_3
    //   60: iconst_0
    //   61: invokeinterface 36 5 0
    //   66: pop
    //   67: aload_3
    //   68: invokevirtual 39	android/os/Parcel:readException	()V
    //   71: aload_3
    //   72: invokevirtual 42	android/os/Parcel:recycle	()V
    //   75: aload_2
    //   76: invokevirtual 42	android/os/Parcel:recycle	()V
    //   79: return
    //   80: iconst_0
    //   81: istore 5
    //   83: aconst_null
    //   84: astore 4
    //   86: aload_2
    //   87: iconst_0
    //   88: invokevirtual 46	android/os/Parcel:writeInt	(I)V
    //   91: goto -48 -> 43
    //   94: astore 4
    //   96: aload_3
    //   97: invokevirtual 42	android/os/Parcel:recycle	()V
    //   100: aload_2
    //   101: invokevirtual 42	android/os/Parcel:recycle	()V
    //   104: aload 4
    //   106: athrow
    // Local variable table:
    //   start	length	slot	name	signature
    //   0	107	0	this	Proxy
    //   0	107	1	paramDataHolder	DataHolder
    //   3	98	2	localParcel1	Parcel
    //   7	90	3	localParcel2	Parcel
    //   10	75	4	localObject1	Object
    //   94	11	4	localObject2	Object
    //   23	59	5	i	int
    //   52	5	6	j	int
    // Exception table:
    //   from	to	target	type
    //   13	18	94	finally
    //   26	31	94	finally
    //   39	43	94	finally
    //   43	47	94	finally
    //   60	67	94	finally
    //   67	71	94	finally
    //   87	91	94	finally
  }
  
  /* Error */
  public void zzJ(DataHolder paramDataHolder)
  {
    // Byte code:
    //   0: invokestatic 20	android/os/Parcel:obtain	()Landroid/os/Parcel;
    //   3: astore_2
    //   4: invokestatic 20	android/os/Parcel:obtain	()Landroid/os/Parcel;
    //   7: astore_3
    //   8: ldc 22
    //   10: astore 4
    //   12: aload_2
    //   13: aload 4
    //   15: invokevirtual 26	android/os/Parcel:writeInterfaceToken	(Ljava/lang/String;)V
    //   18: aload_1
    //   19: ifnull +61 -> 80
    //   22: iconst_1
    //   23: istore 5
    //   25: aload_2
    //   26: iload 5
    //   28: invokevirtual 46	android/os/Parcel:writeInt	(I)V
    //   31: iconst_0
    //   32: istore 5
    //   34: aconst_null
    //   35: astore 4
    //   37: aload_1
    //   38: aload_2
    //   39: iconst_0
    //   40: invokevirtual 62	com/google/android/gms/common/data/DataHolder:writeToParcel	(Landroid/os/Parcel;I)V
    //   43: aload_0
    //   44: getfield 14	com/google/android/gms/games/internal/IGamesCallbacks$Stub$Proxy:zzoz	Landroid/os/IBinder;
    //   47: astore 4
    //   49: sipush 8001
    //   52: istore 6
    //   54: aload 4
    //   56: iload 6
    //   58: aload_2
    //   59: aload_3
    //   60: iconst_0
    //   61: invokeinterface 36 5 0
    //   66: pop
    //   67: aload_3
    //   68: invokevirtual 39	android/os/Parcel:readException	()V
    //   71: aload_3
    //   72: invokevirtual 42	android/os/Parcel:recycle	()V
    //   75: aload_2
    //   76: invokevirtual 42	android/os/Parcel:recycle	()V
    //   79: return
    //   80: iconst_0
    //   81: istore 5
    //   83: aconst_null
    //   84: astore 4
    //   86: aload_2
    //   87: iconst_0
    //   88: invokevirtual 46	android/os/Parcel:writeInt	(I)V
    //   91: goto -48 -> 43
    //   94: astore 4
    //   96: aload_3
    //   97: invokevirtual 42	android/os/Parcel:recycle	()V
    //   100: aload_2
    //   101: invokevirtual 42	android/os/Parcel:recycle	()V
    //   104: aload 4
    //   106: athrow
    // Local variable table:
    //   start	length	slot	name	signature
    //   0	107	0	this	Proxy
    //   0	107	1	paramDataHolder	DataHolder
    //   3	98	2	localParcel1	Parcel
    //   7	90	3	localParcel2	Parcel
    //   10	75	4	localObject1	Object
    //   94	11	4	localObject2	Object
    //   23	59	5	i	int
    //   52	5	6	j	int
    // Exception table:
    //   from	to	target	type
    //   13	18	94	finally
    //   26	31	94	finally
    //   39	43	94	finally
    //   43	47	94	finally
    //   60	67	94	finally
    //   67	71	94	finally
    //   87	91	94	finally
  }
  
  /* Error */
  public void zzK(DataHolder paramDataHolder)
  {
    // Byte code:
    //   0: invokestatic 20	android/os/Parcel:obtain	()Landroid/os/Parcel;
    //   3: astore_2
    //   4: invokestatic 20	android/os/Parcel:obtain	()Landroid/os/Parcel;
    //   7: astore_3
    //   8: ldc 22
    //   10: astore 4
    //   12: aload_2
    //   13: aload 4
    //   15: invokevirtual 26	android/os/Parcel:writeInterfaceToken	(Ljava/lang/String;)V
    //   18: aload_1
    //   19: ifnull +61 -> 80
    //   22: iconst_1
    //   23: istore 5
    //   25: aload_2
    //   26: iload 5
    //   28: invokevirtual 46	android/os/Parcel:writeInt	(I)V
    //   31: iconst_0
    //   32: istore 5
    //   34: aconst_null
    //   35: astore 4
    //   37: aload_1
    //   38: aload_2
    //   39: iconst_0
    //   40: invokevirtual 62	com/google/android/gms/common/data/DataHolder:writeToParcel	(Landroid/os/Parcel;I)V
    //   43: aload_0
    //   44: getfield 14	com/google/android/gms/games/internal/IGamesCallbacks$Stub$Proxy:zzoz	Landroid/os/IBinder;
    //   47: astore 4
    //   49: sipush 10003
    //   52: istore 6
    //   54: aload 4
    //   56: iload 6
    //   58: aload_2
    //   59: aload_3
    //   60: iconst_0
    //   61: invokeinterface 36 5 0
    //   66: pop
    //   67: aload_3
    //   68: invokevirtual 39	android/os/Parcel:readException	()V
    //   71: aload_3
    //   72: invokevirtual 42	android/os/Parcel:recycle	()V
    //   75: aload_2
    //   76: invokevirtual 42	android/os/Parcel:recycle	()V
    //   79: return
    //   80: iconst_0
    //   81: istore 5
    //   83: aconst_null
    //   84: astore 4
    //   86: aload_2
    //   87: iconst_0
    //   88: invokevirtual 46	android/os/Parcel:writeInt	(I)V
    //   91: goto -48 -> 43
    //   94: astore 4
    //   96: aload_3
    //   97: invokevirtual 42	android/os/Parcel:recycle	()V
    //   100: aload_2
    //   101: invokevirtual 42	android/os/Parcel:recycle	()V
    //   104: aload 4
    //   106: athrow
    // Local variable table:
    //   start	length	slot	name	signature
    //   0	107	0	this	Proxy
    //   0	107	1	paramDataHolder	DataHolder
    //   3	98	2	localParcel1	Parcel
    //   7	90	3	localParcel2	Parcel
    //   10	75	4	localObject1	Object
    //   94	11	4	localObject2	Object
    //   23	59	5	i	int
    //   52	5	6	j	int
    // Exception table:
    //   from	to	target	type
    //   13	18	94	finally
    //   26	31	94	finally
    //   39	43	94	finally
    //   43	47	94	finally
    //   60	67	94	finally
    //   67	71	94	finally
    //   87	91	94	finally
  }
  
  /* Error */
  public void zzL(DataHolder paramDataHolder)
  {
    // Byte code:
    //   0: invokestatic 20	android/os/Parcel:obtain	()Landroid/os/Parcel;
    //   3: astore_2
    //   4: invokestatic 20	android/os/Parcel:obtain	()Landroid/os/Parcel;
    //   7: astore_3
    //   8: ldc 22
    //   10: astore 4
    //   12: aload_2
    //   13: aload 4
    //   15: invokevirtual 26	android/os/Parcel:writeInterfaceToken	(Ljava/lang/String;)V
    //   18: aload_1
    //   19: ifnull +61 -> 80
    //   22: iconst_1
    //   23: istore 5
    //   25: aload_2
    //   26: iload 5
    //   28: invokevirtual 46	android/os/Parcel:writeInt	(I)V
    //   31: iconst_0
    //   32: istore 5
    //   34: aconst_null
    //   35: astore 4
    //   37: aload_1
    //   38: aload_2
    //   39: iconst_0
    //   40: invokevirtual 62	com/google/android/gms/common/data/DataHolder:writeToParcel	(Landroid/os/Parcel;I)V
    //   43: aload_0
    //   44: getfield 14	com/google/android/gms/games/internal/IGamesCallbacks$Stub$Proxy:zzoz	Landroid/os/IBinder;
    //   47: astore 4
    //   49: sipush 10004
    //   52: istore 6
    //   54: aload 4
    //   56: iload 6
    //   58: aload_2
    //   59: aload_3
    //   60: iconst_0
    //   61: invokeinterface 36 5 0
    //   66: pop
    //   67: aload_3
    //   68: invokevirtual 39	android/os/Parcel:readException	()V
    //   71: aload_3
    //   72: invokevirtual 42	android/os/Parcel:recycle	()V
    //   75: aload_2
    //   76: invokevirtual 42	android/os/Parcel:recycle	()V
    //   79: return
    //   80: iconst_0
    //   81: istore 5
    //   83: aconst_null
    //   84: astore 4
    //   86: aload_2
    //   87: iconst_0
    //   88: invokevirtual 46	android/os/Parcel:writeInt	(I)V
    //   91: goto -48 -> 43
    //   94: astore 4
    //   96: aload_3
    //   97: invokevirtual 42	android/os/Parcel:recycle	()V
    //   100: aload_2
    //   101: invokevirtual 42	android/os/Parcel:recycle	()V
    //   104: aload 4
    //   106: athrow
    // Local variable table:
    //   start	length	slot	name	signature
    //   0	107	0	this	Proxy
    //   0	107	1	paramDataHolder	DataHolder
    //   3	98	2	localParcel1	Parcel
    //   7	90	3	localParcel2	Parcel
    //   10	75	4	localObject1	Object
    //   94	11	4	localObject2	Object
    //   23	59	5	i	int
    //   52	5	6	j	int
    // Exception table:
    //   from	to	target	type
    //   13	18	94	finally
    //   26	31	94	finally
    //   39	43	94	finally
    //   43	47	94	finally
    //   60	67	94	finally
    //   67	71	94	finally
    //   87	91	94	finally
  }
  
  /* Error */
  public void zzM(DataHolder paramDataHolder)
  {
    // Byte code:
    //   0: invokestatic 20	android/os/Parcel:obtain	()Landroid/os/Parcel;
    //   3: astore_2
    //   4: invokestatic 20	android/os/Parcel:obtain	()Landroid/os/Parcel;
    //   7: astore_3
    //   8: ldc 22
    //   10: astore 4
    //   12: aload_2
    //   13: aload 4
    //   15: invokevirtual 26	android/os/Parcel:writeInterfaceToken	(Ljava/lang/String;)V
    //   18: aload_1
    //   19: ifnull +61 -> 80
    //   22: iconst_1
    //   23: istore 5
    //   25: aload_2
    //   26: iload 5
    //   28: invokevirtual 46	android/os/Parcel:writeInt	(I)V
    //   31: iconst_0
    //   32: istore 5
    //   34: aconst_null
    //   35: astore 4
    //   37: aload_1
    //   38: aload_2
    //   39: iconst_0
    //   40: invokevirtual 62	com/google/android/gms/common/data/DataHolder:writeToParcel	(Landroid/os/Parcel;I)V
    //   43: aload_0
    //   44: getfield 14	com/google/android/gms/games/internal/IGamesCallbacks$Stub$Proxy:zzoz	Landroid/os/IBinder;
    //   47: astore 4
    //   49: sipush 10006
    //   52: istore 6
    //   54: aload 4
    //   56: iload 6
    //   58: aload_2
    //   59: aload_3
    //   60: iconst_0
    //   61: invokeinterface 36 5 0
    //   66: pop
    //   67: aload_3
    //   68: invokevirtual 39	android/os/Parcel:readException	()V
    //   71: aload_3
    //   72: invokevirtual 42	android/os/Parcel:recycle	()V
    //   75: aload_2
    //   76: invokevirtual 42	android/os/Parcel:recycle	()V
    //   79: return
    //   80: iconst_0
    //   81: istore 5
    //   83: aconst_null
    //   84: astore 4
    //   86: aload_2
    //   87: iconst_0
    //   88: invokevirtual 46	android/os/Parcel:writeInt	(I)V
    //   91: goto -48 -> 43
    //   94: astore 4
    //   96: aload_3
    //   97: invokevirtual 42	android/os/Parcel:recycle	()V
    //   100: aload_2
    //   101: invokevirtual 42	android/os/Parcel:recycle	()V
    //   104: aload 4
    //   106: athrow
    // Local variable table:
    //   start	length	slot	name	signature
    //   0	107	0	this	Proxy
    //   0	107	1	paramDataHolder	DataHolder
    //   3	98	2	localParcel1	Parcel
    //   7	90	3	localParcel2	Parcel
    //   10	75	4	localObject1	Object
    //   94	11	4	localObject2	Object
    //   23	59	5	i	int
    //   52	5	6	j	int
    // Exception table:
    //   from	to	target	type
    //   13	18	94	finally
    //   26	31	94	finally
    //   39	43	94	finally
    //   43	47	94	finally
    //   60	67	94	finally
    //   67	71	94	finally
    //   87	91	94	finally
  }
  
  /* Error */
  public void zzN(DataHolder paramDataHolder)
  {
    // Byte code:
    //   0: invokestatic 20	android/os/Parcel:obtain	()Landroid/os/Parcel;
    //   3: astore_2
    //   4: invokestatic 20	android/os/Parcel:obtain	()Landroid/os/Parcel;
    //   7: astore_3
    //   8: ldc 22
    //   10: astore 4
    //   12: aload_2
    //   13: aload 4
    //   15: invokevirtual 26	android/os/Parcel:writeInterfaceToken	(Ljava/lang/String;)V
    //   18: aload_1
    //   19: ifnull +61 -> 80
    //   22: iconst_1
    //   23: istore 5
    //   25: aload_2
    //   26: iload 5
    //   28: invokevirtual 46	android/os/Parcel:writeInt	(I)V
    //   31: iconst_0
    //   32: istore 5
    //   34: aconst_null
    //   35: astore 4
    //   37: aload_1
    //   38: aload_2
    //   39: iconst_0
    //   40: invokevirtual 62	com/google/android/gms/common/data/DataHolder:writeToParcel	(Landroid/os/Parcel;I)V
    //   43: aload_0
    //   44: getfield 14	com/google/android/gms/games/internal/IGamesCallbacks$Stub$Proxy:zzoz	Landroid/os/IBinder;
    //   47: astore 4
    //   49: sipush 12001
    //   52: istore 6
    //   54: aload 4
    //   56: iload 6
    //   58: aload_2
    //   59: aload_3
    //   60: iconst_0
    //   61: invokeinterface 36 5 0
    //   66: pop
    //   67: aload_3
    //   68: invokevirtual 39	android/os/Parcel:readException	()V
    //   71: aload_3
    //   72: invokevirtual 42	android/os/Parcel:recycle	()V
    //   75: aload_2
    //   76: invokevirtual 42	android/os/Parcel:recycle	()V
    //   79: return
    //   80: iconst_0
    //   81: istore 5
    //   83: aconst_null
    //   84: astore 4
    //   86: aload_2
    //   87: iconst_0
    //   88: invokevirtual 46	android/os/Parcel:writeInt	(I)V
    //   91: goto -48 -> 43
    //   94: astore 4
    //   96: aload_3
    //   97: invokevirtual 42	android/os/Parcel:recycle	()V
    //   100: aload_2
    //   101: invokevirtual 42	android/os/Parcel:recycle	()V
    //   104: aload 4
    //   106: athrow
    // Local variable table:
    //   start	length	slot	name	signature
    //   0	107	0	this	Proxy
    //   0	107	1	paramDataHolder	DataHolder
    //   3	98	2	localParcel1	Parcel
    //   7	90	3	localParcel2	Parcel
    //   10	75	4	localObject1	Object
    //   94	11	4	localObject2	Object
    //   23	59	5	i	int
    //   52	5	6	j	int
    // Exception table:
    //   from	to	target	type
    //   13	18	94	finally
    //   26	31	94	finally
    //   39	43	94	finally
    //   43	47	94	finally
    //   60	67	94	finally
    //   67	71	94	finally
    //   87	91	94	finally
  }
  
  /* Error */
  public void zzO(DataHolder paramDataHolder)
  {
    // Byte code:
    //   0: invokestatic 20	android/os/Parcel:obtain	()Landroid/os/Parcel;
    //   3: astore_2
    //   4: invokestatic 20	android/os/Parcel:obtain	()Landroid/os/Parcel;
    //   7: astore_3
    //   8: ldc 22
    //   10: astore 4
    //   12: aload_2
    //   13: aload 4
    //   15: invokevirtual 26	android/os/Parcel:writeInterfaceToken	(Ljava/lang/String;)V
    //   18: aload_1
    //   19: ifnull +61 -> 80
    //   22: iconst_1
    //   23: istore 5
    //   25: aload_2
    //   26: iload 5
    //   28: invokevirtual 46	android/os/Parcel:writeInt	(I)V
    //   31: iconst_0
    //   32: istore 5
    //   34: aconst_null
    //   35: astore 4
    //   37: aload_1
    //   38: aload_2
    //   39: iconst_0
    //   40: invokevirtual 62	com/google/android/gms/common/data/DataHolder:writeToParcel	(Landroid/os/Parcel;I)V
    //   43: aload_0
    //   44: getfield 14	com/google/android/gms/games/internal/IGamesCallbacks$Stub$Proxy:zzoz	Landroid/os/IBinder;
    //   47: astore 4
    //   49: sipush 12005
    //   52: istore 6
    //   54: aload 4
    //   56: iload 6
    //   58: aload_2
    //   59: aload_3
    //   60: iconst_0
    //   61: invokeinterface 36 5 0
    //   66: pop
    //   67: aload_3
    //   68: invokevirtual 39	android/os/Parcel:readException	()V
    //   71: aload_3
    //   72: invokevirtual 42	android/os/Parcel:recycle	()V
    //   75: aload_2
    //   76: invokevirtual 42	android/os/Parcel:recycle	()V
    //   79: return
    //   80: iconst_0
    //   81: istore 5
    //   83: aconst_null
    //   84: astore 4
    //   86: aload_2
    //   87: iconst_0
    //   88: invokevirtual 46	android/os/Parcel:writeInt	(I)V
    //   91: goto -48 -> 43
    //   94: astore 4
    //   96: aload_3
    //   97: invokevirtual 42	android/os/Parcel:recycle	()V
    //   100: aload_2
    //   101: invokevirtual 42	android/os/Parcel:recycle	()V
    //   104: aload 4
    //   106: athrow
    // Local variable table:
    //   start	length	slot	name	signature
    //   0	107	0	this	Proxy
    //   0	107	1	paramDataHolder	DataHolder
    //   3	98	2	localParcel1	Parcel
    //   7	90	3	localParcel2	Parcel
    //   10	75	4	localObject1	Object
    //   94	11	4	localObject2	Object
    //   23	59	5	i	int
    //   52	5	6	j	int
    // Exception table:
    //   from	to	target	type
    //   13	18	94	finally
    //   26	31	94	finally
    //   39	43	94	finally
    //   43	47	94	finally
    //   60	67	94	finally
    //   67	71	94	finally
    //   87	91	94	finally
  }
  
  /* Error */
  public void zzP(DataHolder paramDataHolder)
  {
    // Byte code:
    //   0: invokestatic 20	android/os/Parcel:obtain	()Landroid/os/Parcel;
    //   3: astore_2
    //   4: invokestatic 20	android/os/Parcel:obtain	()Landroid/os/Parcel;
    //   7: astore_3
    //   8: ldc 22
    //   10: astore 4
    //   12: aload_2
    //   13: aload 4
    //   15: invokevirtual 26	android/os/Parcel:writeInterfaceToken	(Ljava/lang/String;)V
    //   18: aload_1
    //   19: ifnull +61 -> 80
    //   22: iconst_1
    //   23: istore 5
    //   25: aload_2
    //   26: iload 5
    //   28: invokevirtual 46	android/os/Parcel:writeInt	(I)V
    //   31: iconst_0
    //   32: istore 5
    //   34: aconst_null
    //   35: astore 4
    //   37: aload_1
    //   38: aload_2
    //   39: iconst_0
    //   40: invokevirtual 62	com/google/android/gms/common/data/DataHolder:writeToParcel	(Landroid/os/Parcel;I)V
    //   43: aload_0
    //   44: getfield 14	com/google/android/gms/games/internal/IGamesCallbacks$Stub$Proxy:zzoz	Landroid/os/IBinder;
    //   47: astore 4
    //   49: sipush 12006
    //   52: istore 6
    //   54: aload 4
    //   56: iload 6
    //   58: aload_2
    //   59: aload_3
    //   60: iconst_0
    //   61: invokeinterface 36 5 0
    //   66: pop
    //   67: aload_3
    //   68: invokevirtual 39	android/os/Parcel:readException	()V
    //   71: aload_3
    //   72: invokevirtual 42	android/os/Parcel:recycle	()V
    //   75: aload_2
    //   76: invokevirtual 42	android/os/Parcel:recycle	()V
    //   79: return
    //   80: iconst_0
    //   81: istore 5
    //   83: aconst_null
    //   84: astore 4
    //   86: aload_2
    //   87: iconst_0
    //   88: invokevirtual 46	android/os/Parcel:writeInt	(I)V
    //   91: goto -48 -> 43
    //   94: astore 4
    //   96: aload_3
    //   97: invokevirtual 42	android/os/Parcel:recycle	()V
    //   100: aload_2
    //   101: invokevirtual 42	android/os/Parcel:recycle	()V
    //   104: aload 4
    //   106: athrow
    // Local variable table:
    //   start	length	slot	name	signature
    //   0	107	0	this	Proxy
    //   0	107	1	paramDataHolder	DataHolder
    //   3	98	2	localParcel1	Parcel
    //   7	90	3	localParcel2	Parcel
    //   10	75	4	localObject1	Object
    //   94	11	4	localObject2	Object
    //   23	59	5	i	int
    //   52	5	6	j	int
    // Exception table:
    //   from	to	target	type
    //   13	18	94	finally
    //   26	31	94	finally
    //   39	43	94	finally
    //   43	47	94	finally
    //   60	67	94	finally
    //   67	71	94	finally
    //   87	91	94	finally
  }
  
  /* Error */
  public void zzQ(DataHolder paramDataHolder)
  {
    // Byte code:
    //   0: invokestatic 20	android/os/Parcel:obtain	()Landroid/os/Parcel;
    //   3: astore_2
    //   4: invokestatic 20	android/os/Parcel:obtain	()Landroid/os/Parcel;
    //   7: astore_3
    //   8: ldc 22
    //   10: astore 4
    //   12: aload_2
    //   13: aload 4
    //   15: invokevirtual 26	android/os/Parcel:writeInterfaceToken	(Ljava/lang/String;)V
    //   18: aload_1
    //   19: ifnull +61 -> 80
    //   22: iconst_1
    //   23: istore 5
    //   25: aload_2
    //   26: iload 5
    //   28: invokevirtual 46	android/os/Parcel:writeInt	(I)V
    //   31: iconst_0
    //   32: istore 5
    //   34: aconst_null
    //   35: astore 4
    //   37: aload_1
    //   38: aload_2
    //   39: iconst_0
    //   40: invokevirtual 62	com/google/android/gms/common/data/DataHolder:writeToParcel	(Landroid/os/Parcel;I)V
    //   43: aload_0
    //   44: getfield 14	com/google/android/gms/games/internal/IGamesCallbacks$Stub$Proxy:zzoz	Landroid/os/IBinder;
    //   47: astore 4
    //   49: sipush 12007
    //   52: istore 6
    //   54: aload 4
    //   56: iload 6
    //   58: aload_2
    //   59: aload_3
    //   60: iconst_0
    //   61: invokeinterface 36 5 0
    //   66: pop
    //   67: aload_3
    //   68: invokevirtual 39	android/os/Parcel:readException	()V
    //   71: aload_3
    //   72: invokevirtual 42	android/os/Parcel:recycle	()V
    //   75: aload_2
    //   76: invokevirtual 42	android/os/Parcel:recycle	()V
    //   79: return
    //   80: iconst_0
    //   81: istore 5
    //   83: aconst_null
    //   84: astore 4
    //   86: aload_2
    //   87: iconst_0
    //   88: invokevirtual 46	android/os/Parcel:writeInt	(I)V
    //   91: goto -48 -> 43
    //   94: astore 4
    //   96: aload_3
    //   97: invokevirtual 42	android/os/Parcel:recycle	()V
    //   100: aload_2
    //   101: invokevirtual 42	android/os/Parcel:recycle	()V
    //   104: aload 4
    //   106: athrow
    // Local variable table:
    //   start	length	slot	name	signature
    //   0	107	0	this	Proxy
    //   0	107	1	paramDataHolder	DataHolder
    //   3	98	2	localParcel1	Parcel
    //   7	90	3	localParcel2	Parcel
    //   10	75	4	localObject1	Object
    //   94	11	4	localObject2	Object
    //   23	59	5	i	int
    //   52	5	6	j	int
    // Exception table:
    //   from	to	target	type
    //   13	18	94	finally
    //   26	31	94	finally
    //   39	43	94	finally
    //   43	47	94	finally
    //   60	67	94	finally
    //   67	71	94	finally
    //   87	91	94	finally
  }
  
  /* Error */
  public void zzR(DataHolder paramDataHolder)
  {
    // Byte code:
    //   0: invokestatic 20	android/os/Parcel:obtain	()Landroid/os/Parcel;
    //   3: astore_2
    //   4: invokestatic 20	android/os/Parcel:obtain	()Landroid/os/Parcel;
    //   7: astore_3
    //   8: ldc 22
    //   10: astore 4
    //   12: aload_2
    //   13: aload 4
    //   15: invokevirtual 26	android/os/Parcel:writeInterfaceToken	(Ljava/lang/String;)V
    //   18: aload_1
    //   19: ifnull +61 -> 80
    //   22: iconst_1
    //   23: istore 5
    //   25: aload_2
    //   26: iload 5
    //   28: invokevirtual 46	android/os/Parcel:writeInt	(I)V
    //   31: iconst_0
    //   32: istore 5
    //   34: aconst_null
    //   35: astore 4
    //   37: aload_1
    //   38: aload_2
    //   39: iconst_0
    //   40: invokevirtual 62	com/google/android/gms/common/data/DataHolder:writeToParcel	(Landroid/os/Parcel;I)V
    //   43: aload_0
    //   44: getfield 14	com/google/android/gms/games/internal/IGamesCallbacks$Stub$Proxy:zzoz	Landroid/os/IBinder;
    //   47: astore 4
    //   49: sipush 12014
    //   52: istore 6
    //   54: aload 4
    //   56: iload 6
    //   58: aload_2
    //   59: aload_3
    //   60: iconst_0
    //   61: invokeinterface 36 5 0
    //   66: pop
    //   67: aload_3
    //   68: invokevirtual 39	android/os/Parcel:readException	()V
    //   71: aload_3
    //   72: invokevirtual 42	android/os/Parcel:recycle	()V
    //   75: aload_2
    //   76: invokevirtual 42	android/os/Parcel:recycle	()V
    //   79: return
    //   80: iconst_0
    //   81: istore 5
    //   83: aconst_null
    //   84: astore 4
    //   86: aload_2
    //   87: iconst_0
    //   88: invokevirtual 46	android/os/Parcel:writeInt	(I)V
    //   91: goto -48 -> 43
    //   94: astore 4
    //   96: aload_3
    //   97: invokevirtual 42	android/os/Parcel:recycle	()V
    //   100: aload_2
    //   101: invokevirtual 42	android/os/Parcel:recycle	()V
    //   104: aload 4
    //   106: athrow
    // Local variable table:
    //   start	length	slot	name	signature
    //   0	107	0	this	Proxy
    //   0	107	1	paramDataHolder	DataHolder
    //   3	98	2	localParcel1	Parcel
    //   7	90	3	localParcel2	Parcel
    //   10	75	4	localObject1	Object
    //   94	11	4	localObject2	Object
    //   23	59	5	i	int
    //   52	5	6	j	int
    // Exception table:
    //   from	to	target	type
    //   13	18	94	finally
    //   26	31	94	finally
    //   39	43	94	finally
    //   43	47	94	finally
    //   60	67	94	finally
    //   67	71	94	finally
    //   87	91	94	finally
  }
  
  /* Error */
  public void zzS(DataHolder paramDataHolder)
  {
    // Byte code:
    //   0: invokestatic 20	android/os/Parcel:obtain	()Landroid/os/Parcel;
    //   3: astore_2
    //   4: invokestatic 20	android/os/Parcel:obtain	()Landroid/os/Parcel;
    //   7: astore_3
    //   8: ldc 22
    //   10: astore 4
    //   12: aload_2
    //   13: aload 4
    //   15: invokevirtual 26	android/os/Parcel:writeInterfaceToken	(Ljava/lang/String;)V
    //   18: aload_1
    //   19: ifnull +61 -> 80
    //   22: iconst_1
    //   23: istore 5
    //   25: aload_2
    //   26: iload 5
    //   28: invokevirtual 46	android/os/Parcel:writeInt	(I)V
    //   31: iconst_0
    //   32: istore 5
    //   34: aconst_null
    //   35: astore 4
    //   37: aload_1
    //   38: aload_2
    //   39: iconst_0
    //   40: invokevirtual 62	com/google/android/gms/common/data/DataHolder:writeToParcel	(Landroid/os/Parcel;I)V
    //   43: aload_0
    //   44: getfield 14	com/google/android/gms/games/internal/IGamesCallbacks$Stub$Proxy:zzoz	Landroid/os/IBinder;
    //   47: astore 4
    //   49: sipush 12016
    //   52: istore 6
    //   54: aload 4
    //   56: iload 6
    //   58: aload_2
    //   59: aload_3
    //   60: iconst_0
    //   61: invokeinterface 36 5 0
    //   66: pop
    //   67: aload_3
    //   68: invokevirtual 39	android/os/Parcel:readException	()V
    //   71: aload_3
    //   72: invokevirtual 42	android/os/Parcel:recycle	()V
    //   75: aload_2
    //   76: invokevirtual 42	android/os/Parcel:recycle	()V
    //   79: return
    //   80: iconst_0
    //   81: istore 5
    //   83: aconst_null
    //   84: astore 4
    //   86: aload_2
    //   87: iconst_0
    //   88: invokevirtual 46	android/os/Parcel:writeInt	(I)V
    //   91: goto -48 -> 43
    //   94: astore 4
    //   96: aload_3
    //   97: invokevirtual 42	android/os/Parcel:recycle	()V
    //   100: aload_2
    //   101: invokevirtual 42	android/os/Parcel:recycle	()V
    //   104: aload 4
    //   106: athrow
    // Local variable table:
    //   start	length	slot	name	signature
    //   0	107	0	this	Proxy
    //   0	107	1	paramDataHolder	DataHolder
    //   3	98	2	localParcel1	Parcel
    //   7	90	3	localParcel2	Parcel
    //   10	75	4	localObject1	Object
    //   94	11	4	localObject2	Object
    //   23	59	5	i	int
    //   52	5	6	j	int
    // Exception table:
    //   from	to	target	type
    //   13	18	94	finally
    //   26	31	94	finally
    //   39	43	94	finally
    //   43	47	94	finally
    //   60	67	94	finally
    //   67	71	94	finally
    //   87	91	94	finally
  }
  
  /* Error */
  public void zzT(DataHolder paramDataHolder)
  {
    // Byte code:
    //   0: invokestatic 20	android/os/Parcel:obtain	()Landroid/os/Parcel;
    //   3: astore_2
    //   4: invokestatic 20	android/os/Parcel:obtain	()Landroid/os/Parcel;
    //   7: astore_3
    //   8: ldc 22
    //   10: astore 4
    //   12: aload_2
    //   13: aload 4
    //   15: invokevirtual 26	android/os/Parcel:writeInterfaceToken	(Ljava/lang/String;)V
    //   18: aload_1
    //   19: ifnull +61 -> 80
    //   22: iconst_1
    //   23: istore 5
    //   25: aload_2
    //   26: iload 5
    //   28: invokevirtual 46	android/os/Parcel:writeInt	(I)V
    //   31: iconst_0
    //   32: istore 5
    //   34: aconst_null
    //   35: astore 4
    //   37: aload_1
    //   38: aload_2
    //   39: iconst_0
    //   40: invokevirtual 62	com/google/android/gms/common/data/DataHolder:writeToParcel	(Landroid/os/Parcel;I)V
    //   43: aload_0
    //   44: getfield 14	com/google/android/gms/games/internal/IGamesCallbacks$Stub$Proxy:zzoz	Landroid/os/IBinder;
    //   47: astore 4
    //   49: sipush 12008
    //   52: istore 6
    //   54: aload 4
    //   56: iload 6
    //   58: aload_2
    //   59: aload_3
    //   60: iconst_0
    //   61: invokeinterface 36 5 0
    //   66: pop
    //   67: aload_3
    //   68: invokevirtual 39	android/os/Parcel:readException	()V
    //   71: aload_3
    //   72: invokevirtual 42	android/os/Parcel:recycle	()V
    //   75: aload_2
    //   76: invokevirtual 42	android/os/Parcel:recycle	()V
    //   79: return
    //   80: iconst_0
    //   81: istore 5
    //   83: aconst_null
    //   84: astore 4
    //   86: aload_2
    //   87: iconst_0
    //   88: invokevirtual 46	android/os/Parcel:writeInt	(I)V
    //   91: goto -48 -> 43
    //   94: astore 4
    //   96: aload_3
    //   97: invokevirtual 42	android/os/Parcel:recycle	()V
    //   100: aload_2
    //   101: invokevirtual 42	android/os/Parcel:recycle	()V
    //   104: aload 4
    //   106: athrow
    // Local variable table:
    //   start	length	slot	name	signature
    //   0	107	0	this	Proxy
    //   0	107	1	paramDataHolder	DataHolder
    //   3	98	2	localParcel1	Parcel
    //   7	90	3	localParcel2	Parcel
    //   10	75	4	localObject1	Object
    //   94	11	4	localObject2	Object
    //   23	59	5	i	int
    //   52	5	6	j	int
    // Exception table:
    //   from	to	target	type
    //   13	18	94	finally
    //   26	31	94	finally
    //   39	43	94	finally
    //   43	47	94	finally
    //   60	67	94	finally
    //   67	71	94	finally
    //   87	91	94	finally
  }
  
  /* Error */
  public void zzU(DataHolder paramDataHolder)
  {
    // Byte code:
    //   0: invokestatic 20	android/os/Parcel:obtain	()Landroid/os/Parcel;
    //   3: astore_2
    //   4: invokestatic 20	android/os/Parcel:obtain	()Landroid/os/Parcel;
    //   7: astore_3
    //   8: ldc 22
    //   10: astore 4
    //   12: aload_2
    //   13: aload 4
    //   15: invokevirtual 26	android/os/Parcel:writeInterfaceToken	(Ljava/lang/String;)V
    //   18: aload_1
    //   19: ifnull +61 -> 80
    //   22: iconst_1
    //   23: istore 5
    //   25: aload_2
    //   26: iload 5
    //   28: invokevirtual 46	android/os/Parcel:writeInt	(I)V
    //   31: iconst_0
    //   32: istore 5
    //   34: aconst_null
    //   35: astore 4
    //   37: aload_1
    //   38: aload_2
    //   39: iconst_0
    //   40: invokevirtual 62	com/google/android/gms/common/data/DataHolder:writeToParcel	(Landroid/os/Parcel;I)V
    //   43: aload_0
    //   44: getfield 14	com/google/android/gms/games/internal/IGamesCallbacks$Stub$Proxy:zzoz	Landroid/os/IBinder;
    //   47: astore 4
    //   49: sipush 12013
    //   52: istore 6
    //   54: aload 4
    //   56: iload 6
    //   58: aload_2
    //   59: aload_3
    //   60: iconst_0
    //   61: invokeinterface 36 5 0
    //   66: pop
    //   67: aload_3
    //   68: invokevirtual 39	android/os/Parcel:readException	()V
    //   71: aload_3
    //   72: invokevirtual 42	android/os/Parcel:recycle	()V
    //   75: aload_2
    //   76: invokevirtual 42	android/os/Parcel:recycle	()V
    //   79: return
    //   80: iconst_0
    //   81: istore 5
    //   83: aconst_null
    //   84: astore 4
    //   86: aload_2
    //   87: iconst_0
    //   88: invokevirtual 46	android/os/Parcel:writeInt	(I)V
    //   91: goto -48 -> 43
    //   94: astore 4
    //   96: aload_3
    //   97: invokevirtual 42	android/os/Parcel:recycle	()V
    //   100: aload_2
    //   101: invokevirtual 42	android/os/Parcel:recycle	()V
    //   104: aload 4
    //   106: athrow
    // Local variable table:
    //   start	length	slot	name	signature
    //   0	107	0	this	Proxy
    //   0	107	1	paramDataHolder	DataHolder
    //   3	98	2	localParcel1	Parcel
    //   7	90	3	localParcel2	Parcel
    //   10	75	4	localObject1	Object
    //   94	11	4	localObject2	Object
    //   23	59	5	i	int
    //   52	5	6	j	int
    // Exception table:
    //   from	to	target	type
    //   13	18	94	finally
    //   26	31	94	finally
    //   39	43	94	finally
    //   43	47	94	finally
    //   60	67	94	finally
    //   67	71	94	finally
    //   87	91	94	finally
  }
  
  /* Error */
  public void zzV(DataHolder paramDataHolder)
  {
    // Byte code:
    //   0: invokestatic 20	android/os/Parcel:obtain	()Landroid/os/Parcel;
    //   3: astore_2
    //   4: invokestatic 20	android/os/Parcel:obtain	()Landroid/os/Parcel;
    //   7: astore_3
    //   8: ldc 22
    //   10: astore 4
    //   12: aload_2
    //   13: aload 4
    //   15: invokevirtual 26	android/os/Parcel:writeInterfaceToken	(Ljava/lang/String;)V
    //   18: aload_1
    //   19: ifnull +61 -> 80
    //   22: iconst_1
    //   23: istore 5
    //   25: aload_2
    //   26: iload 5
    //   28: invokevirtual 46	android/os/Parcel:writeInt	(I)V
    //   31: iconst_0
    //   32: istore 5
    //   34: aconst_null
    //   35: astore 4
    //   37: aload_1
    //   38: aload_2
    //   39: iconst_0
    //   40: invokevirtual 62	com/google/android/gms/common/data/DataHolder:writeToParcel	(Landroid/os/Parcel;I)V
    //   43: aload_0
    //   44: getfield 14	com/google/android/gms/games/internal/IGamesCallbacks$Stub$Proxy:zzoz	Landroid/os/IBinder;
    //   47: astore 4
    //   49: sipush 13001
    //   52: istore 6
    //   54: aload 4
    //   56: iload 6
    //   58: aload_2
    //   59: aload_3
    //   60: iconst_0
    //   61: invokeinterface 36 5 0
    //   66: pop
    //   67: aload_3
    //   68: invokevirtual 39	android/os/Parcel:readException	()V
    //   71: aload_3
    //   72: invokevirtual 42	android/os/Parcel:recycle	()V
    //   75: aload_2
    //   76: invokevirtual 42	android/os/Parcel:recycle	()V
    //   79: return
    //   80: iconst_0
    //   81: istore 5
    //   83: aconst_null
    //   84: astore 4
    //   86: aload_2
    //   87: iconst_0
    //   88: invokevirtual 46	android/os/Parcel:writeInt	(I)V
    //   91: goto -48 -> 43
    //   94: astore 4
    //   96: aload_3
    //   97: invokevirtual 42	android/os/Parcel:recycle	()V
    //   100: aload_2
    //   101: invokevirtual 42	android/os/Parcel:recycle	()V
    //   104: aload 4
    //   106: athrow
    // Local variable table:
    //   start	length	slot	name	signature
    //   0	107	0	this	Proxy
    //   0	107	1	paramDataHolder	DataHolder
    //   3	98	2	localParcel1	Parcel
    //   7	90	3	localParcel2	Parcel
    //   10	75	4	localObject1	Object
    //   94	11	4	localObject2	Object
    //   23	59	5	i	int
    //   52	5	6	j	int
    // Exception table:
    //   from	to	target	type
    //   13	18	94	finally
    //   26	31	94	finally
    //   39	43	94	finally
    //   43	47	94	finally
    //   60	67	94	finally
    //   67	71	94	finally
    //   87	91	94	finally
  }
  
  /* Error */
  public void zzW(DataHolder paramDataHolder)
  {
    // Byte code:
    //   0: invokestatic 20	android/os/Parcel:obtain	()Landroid/os/Parcel;
    //   3: astore_2
    //   4: invokestatic 20	android/os/Parcel:obtain	()Landroid/os/Parcel;
    //   7: astore_3
    //   8: ldc 22
    //   10: astore 4
    //   12: aload_2
    //   13: aload 4
    //   15: invokevirtual 26	android/os/Parcel:writeInterfaceToken	(Ljava/lang/String;)V
    //   18: aload_1
    //   19: ifnull +61 -> 80
    //   22: iconst_1
    //   23: istore 5
    //   25: aload_2
    //   26: iload 5
    //   28: invokevirtual 46	android/os/Parcel:writeInt	(I)V
    //   31: iconst_0
    //   32: istore 5
    //   34: aconst_null
    //   35: astore 4
    //   37: aload_1
    //   38: aload_2
    //   39: iconst_0
    //   40: invokevirtual 62	com/google/android/gms/common/data/DataHolder:writeToParcel	(Landroid/os/Parcel;I)V
    //   43: aload_0
    //   44: getfield 14	com/google/android/gms/games/internal/IGamesCallbacks$Stub$Proxy:zzoz	Landroid/os/IBinder;
    //   47: astore 4
    //   49: sipush 15001
    //   52: istore 6
    //   54: aload 4
    //   56: iload 6
    //   58: aload_2
    //   59: aload_3
    //   60: iconst_0
    //   61: invokeinterface 36 5 0
    //   66: pop
    //   67: aload_3
    //   68: invokevirtual 39	android/os/Parcel:readException	()V
    //   71: aload_3
    //   72: invokevirtual 42	android/os/Parcel:recycle	()V
    //   75: aload_2
    //   76: invokevirtual 42	android/os/Parcel:recycle	()V
    //   79: return
    //   80: iconst_0
    //   81: istore 5
    //   83: aconst_null
    //   84: astore 4
    //   86: aload_2
    //   87: iconst_0
    //   88: invokevirtual 46	android/os/Parcel:writeInt	(I)V
    //   91: goto -48 -> 43
    //   94: astore 4
    //   96: aload_3
    //   97: invokevirtual 42	android/os/Parcel:recycle	()V
    //   100: aload_2
    //   101: invokevirtual 42	android/os/Parcel:recycle	()V
    //   104: aload 4
    //   106: athrow
    // Local variable table:
    //   start	length	slot	name	signature
    //   0	107	0	this	Proxy
    //   0	107	1	paramDataHolder	DataHolder
    //   3	98	2	localParcel1	Parcel
    //   7	90	3	localParcel2	Parcel
    //   10	75	4	localObject1	Object
    //   94	11	4	localObject2	Object
    //   23	59	5	i	int
    //   52	5	6	j	int
    // Exception table:
    //   from	to	target	type
    //   13	18	94	finally
    //   26	31	94	finally
    //   39	43	94	finally
    //   43	47	94	finally
    //   60	67	94	finally
    //   67	71	94	finally
    //   87	91	94	finally
  }
  
  /* Error */
  public void zzX(DataHolder paramDataHolder)
  {
    // Byte code:
    //   0: invokestatic 20	android/os/Parcel:obtain	()Landroid/os/Parcel;
    //   3: astore_2
    //   4: invokestatic 20	android/os/Parcel:obtain	()Landroid/os/Parcel;
    //   7: astore_3
    //   8: ldc 22
    //   10: astore 4
    //   12: aload_2
    //   13: aload 4
    //   15: invokevirtual 26	android/os/Parcel:writeInterfaceToken	(Ljava/lang/String;)V
    //   18: aload_1
    //   19: ifnull +61 -> 80
    //   22: iconst_1
    //   23: istore 5
    //   25: aload_2
    //   26: iload 5
    //   28: invokevirtual 46	android/os/Parcel:writeInt	(I)V
    //   31: iconst_0
    //   32: istore 5
    //   34: aconst_null
    //   35: astore 4
    //   37: aload_1
    //   38: aload_2
    //   39: iconst_0
    //   40: invokevirtual 62	com/google/android/gms/common/data/DataHolder:writeToParcel	(Landroid/os/Parcel;I)V
    //   43: aload_0
    //   44: getfield 14	com/google/android/gms/games/internal/IGamesCallbacks$Stub$Proxy:zzoz	Landroid/os/IBinder;
    //   47: astore 4
    //   49: sipush 17001
    //   52: istore 6
    //   54: aload 4
    //   56: iload 6
    //   58: aload_2
    //   59: aload_3
    //   60: iconst_0
    //   61: invokeinterface 36 5 0
    //   66: pop
    //   67: aload_3
    //   68: invokevirtual 39	android/os/Parcel:readException	()V
    //   71: aload_3
    //   72: invokevirtual 42	android/os/Parcel:recycle	()V
    //   75: aload_2
    //   76: invokevirtual 42	android/os/Parcel:recycle	()V
    //   79: return
    //   80: iconst_0
    //   81: istore 5
    //   83: aconst_null
    //   84: astore 4
    //   86: aload_2
    //   87: iconst_0
    //   88: invokevirtual 46	android/os/Parcel:writeInt	(I)V
    //   91: goto -48 -> 43
    //   94: astore 4
    //   96: aload_3
    //   97: invokevirtual 42	android/os/Parcel:recycle	()V
    //   100: aload_2
    //   101: invokevirtual 42	android/os/Parcel:recycle	()V
    //   104: aload 4
    //   106: athrow
    // Local variable table:
    //   start	length	slot	name	signature
    //   0	107	0	this	Proxy
    //   0	107	1	paramDataHolder	DataHolder
    //   3	98	2	localParcel1	Parcel
    //   7	90	3	localParcel2	Parcel
    //   10	75	4	localObject1	Object
    //   94	11	4	localObject2	Object
    //   23	59	5	i	int
    //   52	5	6	j	int
    // Exception table:
    //   from	to	target	type
    //   13	18	94	finally
    //   26	31	94	finally
    //   39	43	94	finally
    //   43	47	94	finally
    //   60	67	94	finally
    //   67	71	94	finally
    //   87	91	94	finally
  }
  
  /* Error */
  public void zza(int paramInt, com.google.android.gms.games.video.VideoCapabilities paramVideoCapabilities)
  {
    // Byte code:
    //   0: invokestatic 20	android/os/Parcel:obtain	()Landroid/os/Parcel;
    //   3: astore_3
    //   4: invokestatic 20	android/os/Parcel:obtain	()Landroid/os/Parcel;
    //   7: astore 4
    //   9: ldc 22
    //   11: astore 5
    //   13: aload_3
    //   14: aload 5
    //   16: invokevirtual 26	android/os/Parcel:writeInterfaceToken	(Ljava/lang/String;)V
    //   19: aload_3
    //   20: iload_1
    //   21: invokevirtual 46	android/os/Parcel:writeInt	(I)V
    //   24: aload_2
    //   25: ifnull +64 -> 89
    //   28: iconst_1
    //   29: istore 6
    //   31: aload_3
    //   32: iload 6
    //   34: invokevirtual 46	android/os/Parcel:writeInt	(I)V
    //   37: iconst_0
    //   38: istore 6
    //   40: aconst_null
    //   41: astore 5
    //   43: aload_2
    //   44: aload_3
    //   45: iconst_0
    //   46: invokevirtual 89	com/google/android/gms/games/video/VideoCapabilities:writeToParcel	(Landroid/os/Parcel;I)V
    //   49: aload_0
    //   50: getfield 14	com/google/android/gms/games/internal/IGamesCallbacks$Stub$Proxy:zzoz	Landroid/os/IBinder;
    //   53: astore 5
    //   55: sipush 19001
    //   58: istore 7
    //   60: aload 5
    //   62: iload 7
    //   64: aload_3
    //   65: aload 4
    //   67: iconst_0
    //   68: invokeinterface 36 5 0
    //   73: pop
    //   74: aload 4
    //   76: invokevirtual 39	android/os/Parcel:readException	()V
    //   79: aload 4
    //   81: invokevirtual 42	android/os/Parcel:recycle	()V
    //   84: aload_3
    //   85: invokevirtual 42	android/os/Parcel:recycle	()V
    //   88: return
    //   89: iconst_0
    //   90: istore 6
    //   92: aconst_null
    //   93: astore 5
    //   95: aload_3
    //   96: iconst_0
    //   97: invokevirtual 46	android/os/Parcel:writeInt	(I)V
    //   100: goto -51 -> 49
    //   103: astore 5
    //   105: aload 4
    //   107: invokevirtual 42	android/os/Parcel:recycle	()V
    //   110: aload_3
    //   111: invokevirtual 42	android/os/Parcel:recycle	()V
    //   114: aload 5
    //   116: athrow
    // Local variable table:
    //   start	length	slot	name	signature
    //   0	117	0	this	Proxy
    //   0	117	1	paramInt	int
    //   0	117	2	paramVideoCapabilities	com.google.android.gms.games.video.VideoCapabilities
    //   3	108	3	localParcel1	Parcel
    //   7	99	4	localParcel2	Parcel
    //   11	83	5	localObject1	Object
    //   103	12	5	localObject2	Object
    //   29	62	6	i	int
    //   58	5	7	j	int
    // Exception table:
    //   from	to	target	type
    //   14	19	103	finally
    //   20	24	103	finally
    //   32	37	103	finally
    //   45	49	103	finally
    //   49	53	103	finally
    //   67	74	103	finally
    //   74	79	103	finally
    //   96	100	103	finally
  }
  
  public void zza(int paramInt, String paramString, boolean paramBoolean)
  {
    int i = 0;
    IBinder localIBinder = null;
    Parcel localParcel1 = Parcel.obtain();
    Parcel localParcel2 = Parcel.obtain();
    String str = "com.google.android.gms.games.internal.IGamesCallbacks";
    try
    {
      localParcel1.writeInterfaceToken(str);
      localParcel1.writeInt(paramInt);
      localParcel1.writeString(paramString);
      if (paramBoolean) {
        i = 1;
      }
      localParcel1.writeInt(i);
      localIBinder = this.zzoz;
      int j = 5034;
      localIBinder.transact(j, localParcel1, localParcel2, 0);
      localParcel2.readException();
      return;
    }
    finally
    {
      localParcel2.recycle();
      localParcel1.recycle();
    }
  }
  
  public void zza(int paramInt, long[] paramArrayOfLong)
  {
    Parcel localParcel1 = Parcel.obtain();
    Parcel localParcel2 = Parcel.obtain();
    Object localObject1 = "com.google.android.gms.games.internal.IGamesCallbacks";
    try
    {
      localParcel1.writeInterfaceToken((String)localObject1);
      localParcel1.writeInt(paramInt);
      localParcel1.writeLongArray(paramArrayOfLong);
      localObject1 = this.zzoz;
      int i = 19003;
      ((IBinder)localObject1).transact(i, localParcel1, localParcel2, 0);
      localParcel2.readException();
      return;
    }
    finally
    {
      localParcel2.recycle();
      localParcel1.recycle();
    }
  }
  
  public void zza(DataHolder paramDataHolder1, DataHolder paramDataHolder2)
  {
    Parcel localParcel1 = Parcel.obtain();
    Parcel localParcel2 = Parcel.obtain();
    Object localObject1 = "com.google.android.gms.games.internal.IGamesCallbacks";
    for (;;)
    {
      try
      {
        localParcel1.writeInterfaceToken((String)localObject1);
        if (paramDataHolder1 != null)
        {
          i = 1;
          localParcel1.writeInt(i);
          i = 0;
          localObject1 = null;
          paramDataHolder1.writeToParcel(localParcel1, 0);
          if (paramDataHolder2 != null)
          {
            i = 1;
            localParcel1.writeInt(i);
            i = 0;
            localObject1 = null;
            paramDataHolder2.writeToParcel(localParcel1, 0);
            localObject1 = this.zzoz;
            int j = 5005;
            ((IBinder)localObject1).transact(j, localParcel1, localParcel2, 0);
            localParcel2.readException();
          }
        }
        else
        {
          i = 0;
          localObject1 = null;
          localParcel1.writeInt(0);
          continue;
        }
        int i = 0;
      }
      finally
      {
        localParcel2.recycle();
        localParcel1.recycle();
      }
      Object localObject3 = null;
      localParcel1.writeInt(0);
    }
  }
  
  public void zza(DataHolder paramDataHolder, Contents paramContents)
  {
    Parcel localParcel1 = Parcel.obtain();
    Parcel localParcel2 = Parcel.obtain();
    Object localObject1 = "com.google.android.gms.games.internal.IGamesCallbacks";
    for (;;)
    {
      try
      {
        localParcel1.writeInterfaceToken((String)localObject1);
        if (paramDataHolder != null)
        {
          i = 1;
          localParcel1.writeInt(i);
          i = 0;
          localObject1 = null;
          paramDataHolder.writeToParcel(localParcel1, 0);
          if (paramContents != null)
          {
            i = 1;
            localParcel1.writeInt(i);
            i = 0;
            localObject1 = null;
            paramContents.writeToParcel(localParcel1, 0);
            localObject1 = this.zzoz;
            int j = 12004;
            ((IBinder)localObject1).transact(j, localParcel1, localParcel2, 0);
            localParcel2.readException();
          }
        }
        else
        {
          i = 0;
          localObject1 = null;
          localParcel1.writeInt(0);
          continue;
        }
        int i = 0;
      }
      finally
      {
        localParcel2.recycle();
        localParcel1.recycle();
      }
      Object localObject3 = null;
      localParcel1.writeInt(0);
    }
  }
  
  public void zza(DataHolder paramDataHolder, String paramString, Contents paramContents1, Contents paramContents2, Contents paramContents3)
  {
    Parcel localParcel1 = Parcel.obtain();
    Parcel localParcel2 = Parcel.obtain();
    Object localObject1 = "com.google.android.gms.games.internal.IGamesCallbacks";
    for (;;)
    {
      try
      {
        localParcel1.writeInterfaceToken((String)localObject1);
        if (paramDataHolder != null)
        {
          i = 1;
          localParcel1.writeInt(i);
          i = 0;
          localObject1 = null;
          paramDataHolder.writeToParcel(localParcel1, 0);
          localParcel1.writeString(paramString);
          if (paramContents1 != null)
          {
            i = 1;
            localParcel1.writeInt(i);
            i = 0;
            localObject1 = null;
            paramContents1.writeToParcel(localParcel1, 0);
            if (paramContents2 == null) {
              break label226;
            }
            i = 1;
            localParcel1.writeInt(i);
            i = 0;
            localObject1 = null;
            paramContents2.writeToParcel(localParcel1, 0);
            if (paramContents3 == null) {
              break label241;
            }
            i = 1;
            localParcel1.writeInt(i);
            i = 0;
            localObject1 = null;
            paramContents3.writeToParcel(localParcel1, 0);
            localObject1 = this.zzoz;
            int j = 12017;
            ((IBinder)localObject1).transact(j, localParcel1, localParcel2, 0);
            localParcel2.readException();
          }
        }
        else
        {
          i = 0;
          localObject1 = null;
          localParcel1.writeInt(0);
          continue;
        }
        i = 0;
      }
      finally
      {
        localParcel2.recycle();
        localParcel1.recycle();
      }
      Object localObject3 = null;
      localParcel1.writeInt(0);
      continue;
      label226:
      int i = 0;
      localObject3 = null;
      localParcel1.writeInt(0);
      continue;
      label241:
      i = 0;
      localObject3 = null;
      localParcel1.writeInt(0);
    }
  }
  
  /* Error */
  public void zza(DataHolder paramDataHolder, String[] paramArrayOfString)
  {
    // Byte code:
    //   0: invokestatic 20	android/os/Parcel:obtain	()Landroid/os/Parcel;
    //   3: astore_3
    //   4: invokestatic 20	android/os/Parcel:obtain	()Landroid/os/Parcel;
    //   7: astore 4
    //   9: ldc 22
    //   11: astore 5
    //   13: aload_3
    //   14: aload 5
    //   16: invokevirtual 26	android/os/Parcel:writeInterfaceToken	(Ljava/lang/String;)V
    //   19: aload_1
    //   20: ifnull +69 -> 89
    //   23: iconst_1
    //   24: istore 6
    //   26: aload_3
    //   27: iload 6
    //   29: invokevirtual 46	android/os/Parcel:writeInt	(I)V
    //   32: iconst_0
    //   33: istore 6
    //   35: aconst_null
    //   36: astore 5
    //   38: aload_1
    //   39: aload_3
    //   40: iconst_0
    //   41: invokevirtual 62	com/google/android/gms/common/data/DataHolder:writeToParcel	(Landroid/os/Parcel;I)V
    //   44: aload_3
    //   45: aload_2
    //   46: invokevirtual 106	android/os/Parcel:writeStringArray	([Ljava/lang/String;)V
    //   49: aload_0
    //   50: getfield 14	com/google/android/gms/games/internal/IGamesCallbacks$Stub$Proxy:zzoz	Landroid/os/IBinder;
    //   53: astore 5
    //   55: sipush 5026
    //   58: istore 7
    //   60: aload 5
    //   62: iload 7
    //   64: aload_3
    //   65: aload 4
    //   67: iconst_0
    //   68: invokeinterface 36 5 0
    //   73: pop
    //   74: aload 4
    //   76: invokevirtual 39	android/os/Parcel:readException	()V
    //   79: aload 4
    //   81: invokevirtual 42	android/os/Parcel:recycle	()V
    //   84: aload_3
    //   85: invokevirtual 42	android/os/Parcel:recycle	()V
    //   88: return
    //   89: iconst_0
    //   90: istore 6
    //   92: aconst_null
    //   93: astore 5
    //   95: aload_3
    //   96: iconst_0
    //   97: invokevirtual 46	android/os/Parcel:writeInt	(I)V
    //   100: goto -56 -> 44
    //   103: astore 5
    //   105: aload 4
    //   107: invokevirtual 42	android/os/Parcel:recycle	()V
    //   110: aload_3
    //   111: invokevirtual 42	android/os/Parcel:recycle	()V
    //   114: aload 5
    //   116: athrow
    // Local variable table:
    //   start	length	slot	name	signature
    //   0	117	0	this	Proxy
    //   0	117	1	paramDataHolder	DataHolder
    //   0	117	2	paramArrayOfString	String[]
    //   3	108	3	localParcel1	Parcel
    //   7	99	4	localParcel2	Parcel
    //   11	83	5	localObject1	Object
    //   103	12	5	localObject2	Object
    //   24	67	6	i	int
    //   58	5	7	j	int
    // Exception table:
    //   from	to	target	type
    //   14	19	103	finally
    //   27	32	103	finally
    //   40	44	103	finally
    //   45	49	103	finally
    //   49	53	103	finally
    //   67	74	103	finally
    //   74	79	103	finally
    //   96	100	103	finally
  }
  
  public void zza(DataHolder[] paramArrayOfDataHolder)
  {
    Parcel localParcel1 = Parcel.obtain();
    Parcel localParcel2 = Parcel.obtain();
    Object localObject1 = "com.google.android.gms.games.internal.IGamesCallbacks";
    try
    {
      localParcel1.writeInterfaceToken((String)localObject1);
      localObject1 = null;
      localParcel1.writeTypedArray(paramArrayOfDataHolder, 0);
      localObject1 = this.zzoz;
      int i = 14001;
      ((IBinder)localObject1).transact(i, localParcel1, localParcel2, 0);
      localParcel2.readException();
      return;
    }
    finally
    {
      localParcel2.recycle();
      localParcel1.recycle();
    }
  }
  
  public void zzb(int paramInt1, int paramInt2, String paramString)
  {
    Parcel localParcel1 = Parcel.obtain();
    Parcel localParcel2 = Parcel.obtain();
    Object localObject1 = "com.google.android.gms.games.internal.IGamesCallbacks";
    try
    {
      localParcel1.writeInterfaceToken((String)localObject1);
      localParcel1.writeInt(paramInt1);
      localParcel1.writeInt(paramInt2);
      localParcel1.writeString(paramString);
      localObject1 = this.zzoz;
      int i = 5033;
      ((IBinder)localObject1).transact(i, localParcel1, localParcel2, 0);
      localParcel2.readException();
      return;
    }
    finally
    {
      localParcel2.recycle();
      localParcel1.recycle();
    }
  }
  
  /* Error */
  public void zzb(DataHolder paramDataHolder, String[] paramArrayOfString)
  {
    // Byte code:
    //   0: invokestatic 20	android/os/Parcel:obtain	()Landroid/os/Parcel;
    //   3: astore_3
    //   4: invokestatic 20	android/os/Parcel:obtain	()Landroid/os/Parcel;
    //   7: astore 4
    //   9: ldc 22
    //   11: astore 5
    //   13: aload_3
    //   14: aload 5
    //   16: invokevirtual 26	android/os/Parcel:writeInterfaceToken	(Ljava/lang/String;)V
    //   19: aload_1
    //   20: ifnull +69 -> 89
    //   23: iconst_1
    //   24: istore 6
    //   26: aload_3
    //   27: iload 6
    //   29: invokevirtual 46	android/os/Parcel:writeInt	(I)V
    //   32: iconst_0
    //   33: istore 6
    //   35: aconst_null
    //   36: astore 5
    //   38: aload_1
    //   39: aload_3
    //   40: iconst_0
    //   41: invokevirtual 62	com/google/android/gms/common/data/DataHolder:writeToParcel	(Landroid/os/Parcel;I)V
    //   44: aload_3
    //   45: aload_2
    //   46: invokevirtual 106	android/os/Parcel:writeStringArray	([Ljava/lang/String;)V
    //   49: aload_0
    //   50: getfield 14	com/google/android/gms/games/internal/IGamesCallbacks$Stub$Proxy:zzoz	Landroid/os/IBinder;
    //   53: astore 5
    //   55: sipush 5027
    //   58: istore 7
    //   60: aload 5
    //   62: iload 7
    //   64: aload_3
    //   65: aload 4
    //   67: iconst_0
    //   68: invokeinterface 36 5 0
    //   73: pop
    //   74: aload 4
    //   76: invokevirtual 39	android/os/Parcel:readException	()V
    //   79: aload 4
    //   81: invokevirtual 42	android/os/Parcel:recycle	()V
    //   84: aload_3
    //   85: invokevirtual 42	android/os/Parcel:recycle	()V
    //   88: return
    //   89: iconst_0
    //   90: istore 6
    //   92: aconst_null
    //   93: astore 5
    //   95: aload_3
    //   96: iconst_0
    //   97: invokevirtual 46	android/os/Parcel:writeInt	(I)V
    //   100: goto -56 -> 44
    //   103: astore 5
    //   105: aload 4
    //   107: invokevirtual 42	android/os/Parcel:recycle	()V
    //   110: aload_3
    //   111: invokevirtual 42	android/os/Parcel:recycle	()V
    //   114: aload 5
    //   116: athrow
    // Local variable table:
    //   start	length	slot	name	signature
    //   0	117	0	this	Proxy
    //   0	117	1	paramDataHolder	DataHolder
    //   0	117	2	paramArrayOfString	String[]
    //   3	108	3	localParcel1	Parcel
    //   7	99	4	localParcel2	Parcel
    //   11	83	5	localObject1	Object
    //   103	12	5	localObject2	Object
    //   24	67	6	i	int
    //   58	5	7	j	int
    // Exception table:
    //   from	to	target	type
    //   14	19	103	finally
    //   27	32	103	finally
    //   40	44	103	finally
    //   45	49	103	finally
    //   49	53	103	finally
    //   67	74	103	finally
    //   74	79	103	finally
    //   96	100	103	finally
  }
  
  /* Error */
  public void zzc(int paramInt, android.os.Bundle paramBundle)
  {
    // Byte code:
    //   0: invokestatic 20	android/os/Parcel:obtain	()Landroid/os/Parcel;
    //   3: astore_3
    //   4: invokestatic 20	android/os/Parcel:obtain	()Landroid/os/Parcel;
    //   7: astore 4
    //   9: ldc 22
    //   11: astore 5
    //   13: aload_3
    //   14: aload 5
    //   16: invokevirtual 26	android/os/Parcel:writeInterfaceToken	(Ljava/lang/String;)V
    //   19: aload_3
    //   20: iload_1
    //   21: invokevirtual 46	android/os/Parcel:writeInt	(I)V
    //   24: aload_2
    //   25: ifnull +64 -> 89
    //   28: iconst_1
    //   29: istore 6
    //   31: aload_3
    //   32: iload 6
    //   34: invokevirtual 46	android/os/Parcel:writeInt	(I)V
    //   37: iconst_0
    //   38: istore 6
    //   40: aconst_null
    //   41: astore 5
    //   43: aload_2
    //   44: aload_3
    //   45: iconst_0
    //   46: invokevirtual 117	android/os/Bundle:writeToParcel	(Landroid/os/Parcel;I)V
    //   49: aload_0
    //   50: getfield 14	com/google/android/gms/games/internal/IGamesCallbacks$Stub$Proxy:zzoz	Landroid/os/IBinder;
    //   53: astore 5
    //   55: sipush 8002
    //   58: istore 7
    //   60: aload 5
    //   62: iload 7
    //   64: aload_3
    //   65: aload 4
    //   67: iconst_0
    //   68: invokeinterface 36 5 0
    //   73: pop
    //   74: aload 4
    //   76: invokevirtual 39	android/os/Parcel:readException	()V
    //   79: aload 4
    //   81: invokevirtual 42	android/os/Parcel:recycle	()V
    //   84: aload_3
    //   85: invokevirtual 42	android/os/Parcel:recycle	()V
    //   88: return
    //   89: iconst_0
    //   90: istore 6
    //   92: aconst_null
    //   93: astore 5
    //   95: aload_3
    //   96: iconst_0
    //   97: invokevirtual 46	android/os/Parcel:writeInt	(I)V
    //   100: goto -51 -> 49
    //   103: astore 5
    //   105: aload 4
    //   107: invokevirtual 42	android/os/Parcel:recycle	()V
    //   110: aload_3
    //   111: invokevirtual 42	android/os/Parcel:recycle	()V
    //   114: aload 5
    //   116: athrow
    // Local variable table:
    //   start	length	slot	name	signature
    //   0	117	0	this	Proxy
    //   0	117	1	paramInt	int
    //   0	117	2	paramBundle	android.os.Bundle
    //   3	108	3	localParcel1	Parcel
    //   7	99	4	localParcel2	Parcel
    //   11	83	5	localObject1	Object
    //   103	12	5	localObject2	Object
    //   29	62	6	i	int
    //   58	5	7	j	int
    // Exception table:
    //   from	to	target	type
    //   14	19	103	finally
    //   20	24	103	finally
    //   32	37	103	finally
    //   45	49	103	finally
    //   49	53	103	finally
    //   67	74	103	finally
    //   74	79	103	finally
    //   96	100	103	finally
  }
  
  /* Error */
  public void zzc(DataHolder paramDataHolder, String[] paramArrayOfString)
  {
    // Byte code:
    //   0: invokestatic 20	android/os/Parcel:obtain	()Landroid/os/Parcel;
    //   3: astore_3
    //   4: invokestatic 20	android/os/Parcel:obtain	()Landroid/os/Parcel;
    //   7: astore 4
    //   9: ldc 22
    //   11: astore 5
    //   13: aload_3
    //   14: aload 5
    //   16: invokevirtual 26	android/os/Parcel:writeInterfaceToken	(Ljava/lang/String;)V
    //   19: aload_1
    //   20: ifnull +69 -> 89
    //   23: iconst_1
    //   24: istore 6
    //   26: aload_3
    //   27: iload 6
    //   29: invokevirtual 46	android/os/Parcel:writeInt	(I)V
    //   32: iconst_0
    //   33: istore 6
    //   35: aconst_null
    //   36: astore 5
    //   38: aload_1
    //   39: aload_3
    //   40: iconst_0
    //   41: invokevirtual 62	com/google/android/gms/common/data/DataHolder:writeToParcel	(Landroid/os/Parcel;I)V
    //   44: aload_3
    //   45: aload_2
    //   46: invokevirtual 106	android/os/Parcel:writeStringArray	([Ljava/lang/String;)V
    //   49: aload_0
    //   50: getfield 14	com/google/android/gms/games/internal/IGamesCallbacks$Stub$Proxy:zzoz	Landroid/os/IBinder;
    //   53: astore 5
    //   55: sipush 5028
    //   58: istore 7
    //   60: aload 5
    //   62: iload 7
    //   64: aload_3
    //   65: aload 4
    //   67: iconst_0
    //   68: invokeinterface 36 5 0
    //   73: pop
    //   74: aload 4
    //   76: invokevirtual 39	android/os/Parcel:readException	()V
    //   79: aload 4
    //   81: invokevirtual 42	android/os/Parcel:recycle	()V
    //   84: aload_3
    //   85: invokevirtual 42	android/os/Parcel:recycle	()V
    //   88: return
    //   89: iconst_0
    //   90: istore 6
    //   92: aconst_null
    //   93: astore 5
    //   95: aload_3
    //   96: iconst_0
    //   97: invokevirtual 46	android/os/Parcel:writeInt	(I)V
    //   100: goto -56 -> 44
    //   103: astore 5
    //   105: aload 4
    //   107: invokevirtual 42	android/os/Parcel:recycle	()V
    //   110: aload_3
    //   111: invokevirtual 42	android/os/Parcel:recycle	()V
    //   114: aload 5
    //   116: athrow
    // Local variable table:
    //   start	length	slot	name	signature
    //   0	117	0	this	Proxy
    //   0	117	1	paramDataHolder	DataHolder
    //   0	117	2	paramArrayOfString	String[]
    //   3	108	3	localParcel1	Parcel
    //   7	99	4	localParcel2	Parcel
    //   11	83	5	localObject1	Object
    //   103	12	5	localObject2	Object
    //   24	67	6	i	int
    //   58	5	7	j	int
    // Exception table:
    //   from	to	target	type
    //   14	19	103	finally
    //   27	32	103	finally
    //   40	44	103	finally
    //   45	49	103	finally
    //   49	53	103	finally
    //   67	74	103	finally
    //   74	79	103	finally
    //   96	100	103	finally
  }
  
  /* Error */
  public void zzd(int paramInt, android.os.Bundle paramBundle)
  {
    // Byte code:
    //   0: invokestatic 20	android/os/Parcel:obtain	()Landroid/os/Parcel;
    //   3: astore_3
    //   4: invokestatic 20	android/os/Parcel:obtain	()Landroid/os/Parcel;
    //   7: astore 4
    //   9: ldc 22
    //   11: astore 5
    //   13: aload_3
    //   14: aload 5
    //   16: invokevirtual 26	android/os/Parcel:writeInterfaceToken	(Ljava/lang/String;)V
    //   19: aload_3
    //   20: iload_1
    //   21: invokevirtual 46	android/os/Parcel:writeInt	(I)V
    //   24: aload_2
    //   25: ifnull +64 -> 89
    //   28: iconst_1
    //   29: istore 6
    //   31: aload_3
    //   32: iload 6
    //   34: invokevirtual 46	android/os/Parcel:writeInt	(I)V
    //   37: iconst_0
    //   38: istore 6
    //   40: aconst_null
    //   41: astore 5
    //   43: aload_2
    //   44: aload_3
    //   45: iconst_0
    //   46: invokevirtual 117	android/os/Bundle:writeToParcel	(Landroid/os/Parcel;I)V
    //   49: aload_0
    //   50: getfield 14	com/google/android/gms/games/internal/IGamesCallbacks$Stub$Proxy:zzoz	Landroid/os/IBinder;
    //   53: astore 5
    //   55: sipush 10005
    //   58: istore 7
    //   60: aload 5
    //   62: iload 7
    //   64: aload_3
    //   65: aload 4
    //   67: iconst_0
    //   68: invokeinterface 36 5 0
    //   73: pop
    //   74: aload 4
    //   76: invokevirtual 39	android/os/Parcel:readException	()V
    //   79: aload 4
    //   81: invokevirtual 42	android/os/Parcel:recycle	()V
    //   84: aload_3
    //   85: invokevirtual 42	android/os/Parcel:recycle	()V
    //   88: return
    //   89: iconst_0
    //   90: istore 6
    //   92: aconst_null
    //   93: astore 5
    //   95: aload_3
    //   96: iconst_0
    //   97: invokevirtual 46	android/os/Parcel:writeInt	(I)V
    //   100: goto -51 -> 49
    //   103: astore 5
    //   105: aload 4
    //   107: invokevirtual 42	android/os/Parcel:recycle	()V
    //   110: aload_3
    //   111: invokevirtual 42	android/os/Parcel:recycle	()V
    //   114: aload 5
    //   116: athrow
    // Local variable table:
    //   start	length	slot	name	signature
    //   0	117	0	this	Proxy
    //   0	117	1	paramInt	int
    //   0	117	2	paramBundle	android.os.Bundle
    //   3	108	3	localParcel1	Parcel
    //   7	99	4	localParcel2	Parcel
    //   11	83	5	localObject1	Object
    //   103	12	5	localObject2	Object
    //   29	62	6	i	int
    //   58	5	7	j	int
    // Exception table:
    //   from	to	target	type
    //   14	19	103	finally
    //   20	24	103	finally
    //   32	37	103	finally
    //   45	49	103	finally
    //   49	53	103	finally
    //   67	74	103	finally
    //   74	79	103	finally
    //   96	100	103	finally
  }
  
  public void zzd(int paramInt, boolean paramBoolean)
  {
    int i = 0;
    IBinder localIBinder = null;
    Parcel localParcel1 = Parcel.obtain();
    Parcel localParcel2 = Parcel.obtain();
    String str = "com.google.android.gms.games.internal.IGamesCallbacks";
    try
    {
      localParcel1.writeInterfaceToken(str);
      localParcel1.writeInt(paramInt);
      if (paramBoolean) {
        i = 1;
      }
      localParcel1.writeInt(i);
      localIBinder = this.zzoz;
      int j = 19002;
      localIBinder.transact(j, localParcel1, localParcel2, 0);
      localParcel2.readException();
      return;
    }
    finally
    {
      localParcel2.recycle();
      localParcel1.recycle();
    }
  }
  
  /* Error */
  public void zzd(DataHolder paramDataHolder, String[] paramArrayOfString)
  {
    // Byte code:
    //   0: invokestatic 20	android/os/Parcel:obtain	()Landroid/os/Parcel;
    //   3: astore_3
    //   4: invokestatic 20	android/os/Parcel:obtain	()Landroid/os/Parcel;
    //   7: astore 4
    //   9: ldc 22
    //   11: astore 5
    //   13: aload_3
    //   14: aload 5
    //   16: invokevirtual 26	android/os/Parcel:writeInterfaceToken	(Ljava/lang/String;)V
    //   19: aload_1
    //   20: ifnull +69 -> 89
    //   23: iconst_1
    //   24: istore 6
    //   26: aload_3
    //   27: iload 6
    //   29: invokevirtual 46	android/os/Parcel:writeInt	(I)V
    //   32: iconst_0
    //   33: istore 6
    //   35: aconst_null
    //   36: astore 5
    //   38: aload_1
    //   39: aload_3
    //   40: iconst_0
    //   41: invokevirtual 62	com/google/android/gms/common/data/DataHolder:writeToParcel	(Landroid/os/Parcel;I)V
    //   44: aload_3
    //   45: aload_2
    //   46: invokevirtual 106	android/os/Parcel:writeStringArray	([Ljava/lang/String;)V
    //   49: aload_0
    //   50: getfield 14	com/google/android/gms/games/internal/IGamesCallbacks$Stub$Proxy:zzoz	Landroid/os/IBinder;
    //   53: astore 5
    //   55: sipush 5029
    //   58: istore 7
    //   60: aload 5
    //   62: iload 7
    //   64: aload_3
    //   65: aload 4
    //   67: iconst_0
    //   68: invokeinterface 36 5 0
    //   73: pop
    //   74: aload 4
    //   76: invokevirtual 39	android/os/Parcel:readException	()V
    //   79: aload 4
    //   81: invokevirtual 42	android/os/Parcel:recycle	()V
    //   84: aload_3
    //   85: invokevirtual 42	android/os/Parcel:recycle	()V
    //   88: return
    //   89: iconst_0
    //   90: istore 6
    //   92: aconst_null
    //   93: astore 5
    //   95: aload_3
    //   96: iconst_0
    //   97: invokevirtual 46	android/os/Parcel:writeInt	(I)V
    //   100: goto -56 -> 44
    //   103: astore 5
    //   105: aload 4
    //   107: invokevirtual 42	android/os/Parcel:recycle	()V
    //   110: aload_3
    //   111: invokevirtual 42	android/os/Parcel:recycle	()V
    //   114: aload 5
    //   116: athrow
    // Local variable table:
    //   start	length	slot	name	signature
    //   0	117	0	this	Proxy
    //   0	117	1	paramDataHolder	DataHolder
    //   0	117	2	paramArrayOfString	String[]
    //   3	108	3	localParcel1	Parcel
    //   7	99	4	localParcel2	Parcel
    //   11	83	5	localObject1	Object
    //   103	12	5	localObject2	Object
    //   24	67	6	i	int
    //   58	5	7	j	int
    // Exception table:
    //   from	to	target	type
    //   14	19	103	finally
    //   27	32	103	finally
    //   40	44	103	finally
    //   45	49	103	finally
    //   49	53	103	finally
    //   67	74	103	finally
    //   74	79	103	finally
    //   96	100	103	finally
  }
  
  /* Error */
  public void zze(int paramInt, android.os.Bundle paramBundle)
  {
    // Byte code:
    //   0: invokestatic 20	android/os/Parcel:obtain	()Landroid/os/Parcel;
    //   3: astore_3
    //   4: invokestatic 20	android/os/Parcel:obtain	()Landroid/os/Parcel;
    //   7: astore 4
    //   9: ldc 22
    //   11: astore 5
    //   13: aload_3
    //   14: aload 5
    //   16: invokevirtual 26	android/os/Parcel:writeInterfaceToken	(Ljava/lang/String;)V
    //   19: aload_3
    //   20: iload_1
    //   21: invokevirtual 46	android/os/Parcel:writeInt	(I)V
    //   24: aload_2
    //   25: ifnull +64 -> 89
    //   28: iconst_1
    //   29: istore 6
    //   31: aload_3
    //   32: iload 6
    //   34: invokevirtual 46	android/os/Parcel:writeInt	(I)V
    //   37: iconst_0
    //   38: istore 6
    //   40: aconst_null
    //   41: astore 5
    //   43: aload_2
    //   44: aload_3
    //   45: iconst_0
    //   46: invokevirtual 117	android/os/Bundle:writeToParcel	(Landroid/os/Parcel;I)V
    //   49: aload_0
    //   50: getfield 14	com/google/android/gms/games/internal/IGamesCallbacks$Stub$Proxy:zzoz	Landroid/os/IBinder;
    //   53: astore 5
    //   55: sipush 11001
    //   58: istore 7
    //   60: aload 5
    //   62: iload 7
    //   64: aload_3
    //   65: aload 4
    //   67: iconst_0
    //   68: invokeinterface 36 5 0
    //   73: pop
    //   74: aload 4
    //   76: invokevirtual 39	android/os/Parcel:readException	()V
    //   79: aload 4
    //   81: invokevirtual 42	android/os/Parcel:recycle	()V
    //   84: aload_3
    //   85: invokevirtual 42	android/os/Parcel:recycle	()V
    //   88: return
    //   89: iconst_0
    //   90: istore 6
    //   92: aconst_null
    //   93: astore 5
    //   95: aload_3
    //   96: iconst_0
    //   97: invokevirtual 46	android/os/Parcel:writeInt	(I)V
    //   100: goto -51 -> 49
    //   103: astore 5
    //   105: aload 4
    //   107: invokevirtual 42	android/os/Parcel:recycle	()V
    //   110: aload_3
    //   111: invokevirtual 42	android/os/Parcel:recycle	()V
    //   114: aload 5
    //   116: athrow
    // Local variable table:
    //   start	length	slot	name	signature
    //   0	117	0	this	Proxy
    //   0	117	1	paramInt	int
    //   0	117	2	paramBundle	android.os.Bundle
    //   3	108	3	localParcel1	Parcel
    //   7	99	4	localParcel2	Parcel
    //   11	83	5	localObject1	Object
    //   103	12	5	localObject2	Object
    //   29	62	6	i	int
    //   58	5	7	j	int
    // Exception table:
    //   from	to	target	type
    //   14	19	103	finally
    //   20	24	103	finally
    //   32	37	103	finally
    //   45	49	103	finally
    //   49	53	103	finally
    //   67	74	103	finally
    //   74	79	103	finally
    //   96	100	103	finally
  }
  
  /* Error */
  public void zze(DataHolder paramDataHolder, String[] paramArrayOfString)
  {
    // Byte code:
    //   0: invokestatic 20	android/os/Parcel:obtain	()Landroid/os/Parcel;
    //   3: astore_3
    //   4: invokestatic 20	android/os/Parcel:obtain	()Landroid/os/Parcel;
    //   7: astore 4
    //   9: ldc 22
    //   11: astore 5
    //   13: aload_3
    //   14: aload 5
    //   16: invokevirtual 26	android/os/Parcel:writeInterfaceToken	(Ljava/lang/String;)V
    //   19: aload_1
    //   20: ifnull +69 -> 89
    //   23: iconst_1
    //   24: istore 6
    //   26: aload_3
    //   27: iload 6
    //   29: invokevirtual 46	android/os/Parcel:writeInt	(I)V
    //   32: iconst_0
    //   33: istore 6
    //   35: aconst_null
    //   36: astore 5
    //   38: aload_1
    //   39: aload_3
    //   40: iconst_0
    //   41: invokevirtual 62	com/google/android/gms/common/data/DataHolder:writeToParcel	(Landroid/os/Parcel;I)V
    //   44: aload_3
    //   45: aload_2
    //   46: invokevirtual 106	android/os/Parcel:writeStringArray	([Ljava/lang/String;)V
    //   49: aload_0
    //   50: getfield 14	com/google/android/gms/games/internal/IGamesCallbacks$Stub$Proxy:zzoz	Landroid/os/IBinder;
    //   53: astore 5
    //   55: sipush 5030
    //   58: istore 7
    //   60: aload 5
    //   62: iload 7
    //   64: aload_3
    //   65: aload 4
    //   67: iconst_0
    //   68: invokeinterface 36 5 0
    //   73: pop
    //   74: aload 4
    //   76: invokevirtual 39	android/os/Parcel:readException	()V
    //   79: aload 4
    //   81: invokevirtual 42	android/os/Parcel:recycle	()V
    //   84: aload_3
    //   85: invokevirtual 42	android/os/Parcel:recycle	()V
    //   88: return
    //   89: iconst_0
    //   90: istore 6
    //   92: aconst_null
    //   93: astore 5
    //   95: aload_3
    //   96: iconst_0
    //   97: invokevirtual 46	android/os/Parcel:writeInt	(I)V
    //   100: goto -56 -> 44
    //   103: astore 5
    //   105: aload 4
    //   107: invokevirtual 42	android/os/Parcel:recycle	()V
    //   110: aload_3
    //   111: invokevirtual 42	android/os/Parcel:recycle	()V
    //   114: aload 5
    //   116: athrow
    // Local variable table:
    //   start	length	slot	name	signature
    //   0	117	0	this	Proxy
    //   0	117	1	paramDataHolder	DataHolder
    //   0	117	2	paramArrayOfString	String[]
    //   3	108	3	localParcel1	Parcel
    //   7	99	4	localParcel2	Parcel
    //   11	83	5	localObject1	Object
    //   103	12	5	localObject2	Object
    //   24	67	6	i	int
    //   58	5	7	j	int
    // Exception table:
    //   from	to	target	type
    //   14	19	103	finally
    //   27	32	103	finally
    //   40	44	103	finally
    //   45	49	103	finally
    //   49	53	103	finally
    //   67	74	103	finally
    //   74	79	103	finally
    //   96	100	103	finally
  }
  
  /* Error */
  public void zzf(int paramInt, android.os.Bundle paramBundle)
  {
    // Byte code:
    //   0: invokestatic 20	android/os/Parcel:obtain	()Landroid/os/Parcel;
    //   3: astore_3
    //   4: invokestatic 20	android/os/Parcel:obtain	()Landroid/os/Parcel;
    //   7: astore 4
    //   9: ldc 22
    //   11: astore 5
    //   13: aload_3
    //   14: aload 5
    //   16: invokevirtual 26	android/os/Parcel:writeInterfaceToken	(Ljava/lang/String;)V
    //   19: aload_3
    //   20: iload_1
    //   21: invokevirtual 46	android/os/Parcel:writeInt	(I)V
    //   24: aload_2
    //   25: ifnull +64 -> 89
    //   28: iconst_1
    //   29: istore 6
    //   31: aload_3
    //   32: iload 6
    //   34: invokevirtual 46	android/os/Parcel:writeInt	(I)V
    //   37: iconst_0
    //   38: istore 6
    //   40: aconst_null
    //   41: astore 5
    //   43: aload_2
    //   44: aload_3
    //   45: iconst_0
    //   46: invokevirtual 117	android/os/Bundle:writeToParcel	(Landroid/os/Parcel;I)V
    //   49: aload_0
    //   50: getfield 14	com/google/android/gms/games/internal/IGamesCallbacks$Stub$Proxy:zzoz	Landroid/os/IBinder;
    //   53: astore 5
    //   55: sipush 12003
    //   58: istore 7
    //   60: aload 5
    //   62: iload 7
    //   64: aload_3
    //   65: aload 4
    //   67: iconst_0
    //   68: invokeinterface 36 5 0
    //   73: pop
    //   74: aload 4
    //   76: invokevirtual 39	android/os/Parcel:readException	()V
    //   79: aload 4
    //   81: invokevirtual 42	android/os/Parcel:recycle	()V
    //   84: aload_3
    //   85: invokevirtual 42	android/os/Parcel:recycle	()V
    //   88: return
    //   89: iconst_0
    //   90: istore 6
    //   92: aconst_null
    //   93: astore 5
    //   95: aload_3
    //   96: iconst_0
    //   97: invokevirtual 46	android/os/Parcel:writeInt	(I)V
    //   100: goto -51 -> 49
    //   103: astore 5
    //   105: aload 4
    //   107: invokevirtual 42	android/os/Parcel:recycle	()V
    //   110: aload_3
    //   111: invokevirtual 42	android/os/Parcel:recycle	()V
    //   114: aload 5
    //   116: athrow
    // Local variable table:
    //   start	length	slot	name	signature
    //   0	117	0	this	Proxy
    //   0	117	1	paramInt	int
    //   0	117	2	paramBundle	android.os.Bundle
    //   3	108	3	localParcel1	Parcel
    //   7	99	4	localParcel2	Parcel
    //   11	83	5	localObject1	Object
    //   103	12	5	localObject2	Object
    //   29	62	6	i	int
    //   58	5	7	j	int
    // Exception table:
    //   from	to	target	type
    //   14	19	103	finally
    //   20	24	103	finally
    //   32	37	103	finally
    //   45	49	103	finally
    //   49	53	103	finally
    //   67	74	103	finally
    //   74	79	103	finally
    //   96	100	103	finally
  }
  
  /* Error */
  public void zzf(DataHolder paramDataHolder, String[] paramArrayOfString)
  {
    // Byte code:
    //   0: invokestatic 20	android/os/Parcel:obtain	()Landroid/os/Parcel;
    //   3: astore_3
    //   4: invokestatic 20	android/os/Parcel:obtain	()Landroid/os/Parcel;
    //   7: astore 4
    //   9: ldc 22
    //   11: astore 5
    //   13: aload_3
    //   14: aload 5
    //   16: invokevirtual 26	android/os/Parcel:writeInterfaceToken	(Ljava/lang/String;)V
    //   19: aload_1
    //   20: ifnull +69 -> 89
    //   23: iconst_1
    //   24: istore 6
    //   26: aload_3
    //   27: iload 6
    //   29: invokevirtual 46	android/os/Parcel:writeInt	(I)V
    //   32: iconst_0
    //   33: istore 6
    //   35: aconst_null
    //   36: astore 5
    //   38: aload_1
    //   39: aload_3
    //   40: iconst_0
    //   41: invokevirtual 62	com/google/android/gms/common/data/DataHolder:writeToParcel	(Landroid/os/Parcel;I)V
    //   44: aload_3
    //   45: aload_2
    //   46: invokevirtual 106	android/os/Parcel:writeStringArray	([Ljava/lang/String;)V
    //   49: aload_0
    //   50: getfield 14	com/google/android/gms/games/internal/IGamesCallbacks$Stub$Proxy:zzoz	Landroid/os/IBinder;
    //   53: astore 5
    //   55: sipush 5031
    //   58: istore 7
    //   60: aload 5
    //   62: iload 7
    //   64: aload_3
    //   65: aload 4
    //   67: iconst_0
    //   68: invokeinterface 36 5 0
    //   73: pop
    //   74: aload 4
    //   76: invokevirtual 39	android/os/Parcel:readException	()V
    //   79: aload 4
    //   81: invokevirtual 42	android/os/Parcel:recycle	()V
    //   84: aload_3
    //   85: invokevirtual 42	android/os/Parcel:recycle	()V
    //   88: return
    //   89: iconst_0
    //   90: istore 6
    //   92: aconst_null
    //   93: astore 5
    //   95: aload_3
    //   96: iconst_0
    //   97: invokevirtual 46	android/os/Parcel:writeInt	(I)V
    //   100: goto -56 -> 44
    //   103: astore 5
    //   105: aload 4
    //   107: invokevirtual 42	android/os/Parcel:recycle	()V
    //   110: aload_3
    //   111: invokevirtual 42	android/os/Parcel:recycle	()V
    //   114: aload 5
    //   116: athrow
    // Local variable table:
    //   start	length	slot	name	signature
    //   0	117	0	this	Proxy
    //   0	117	1	paramDataHolder	DataHolder
    //   0	117	2	paramArrayOfString	String[]
    //   3	108	3	localParcel1	Parcel
    //   7	99	4	localParcel2	Parcel
    //   11	83	5	localObject1	Object
    //   103	12	5	localObject2	Object
    //   24	67	6	i	int
    //   58	5	7	j	int
    // Exception table:
    //   from	to	target	type
    //   14	19	103	finally
    //   27	32	103	finally
    //   40	44	103	finally
    //   45	49	103	finally
    //   49	53	103	finally
    //   67	74	103	finally
    //   74	79	103	finally
    //   96	100	103	finally
  }
  
  /* Error */
  public void zzg(int paramInt, android.os.Bundle paramBundle)
  {
    // Byte code:
    //   0: invokestatic 20	android/os/Parcel:obtain	()Landroid/os/Parcel;
    //   3: astore_3
    //   4: invokestatic 20	android/os/Parcel:obtain	()Landroid/os/Parcel;
    //   7: astore 4
    //   9: ldc 22
    //   11: astore 5
    //   13: aload_3
    //   14: aload 5
    //   16: invokevirtual 26	android/os/Parcel:writeInterfaceToken	(Ljava/lang/String;)V
    //   19: aload_3
    //   20: iload_1
    //   21: invokevirtual 46	android/os/Parcel:writeInt	(I)V
    //   24: aload_2
    //   25: ifnull +64 -> 89
    //   28: iconst_1
    //   29: istore 6
    //   31: aload_3
    //   32: iload 6
    //   34: invokevirtual 46	android/os/Parcel:writeInt	(I)V
    //   37: iconst_0
    //   38: istore 6
    //   40: aconst_null
    //   41: astore 5
    //   43: aload_2
    //   44: aload_3
    //   45: iconst_0
    //   46: invokevirtual 117	android/os/Bundle:writeToParcel	(Landroid/os/Parcel;I)V
    //   49: aload_0
    //   50: getfield 14	com/google/android/gms/games/internal/IGamesCallbacks$Stub$Proxy:zzoz	Landroid/os/IBinder;
    //   53: astore 5
    //   55: sipush 12015
    //   58: istore 7
    //   60: aload 5
    //   62: iload 7
    //   64: aload_3
    //   65: aload 4
    //   67: iconst_0
    //   68: invokeinterface 36 5 0
    //   73: pop
    //   74: aload 4
    //   76: invokevirtual 39	android/os/Parcel:readException	()V
    //   79: aload 4
    //   81: invokevirtual 42	android/os/Parcel:recycle	()V
    //   84: aload_3
    //   85: invokevirtual 42	android/os/Parcel:recycle	()V
    //   88: return
    //   89: iconst_0
    //   90: istore 6
    //   92: aconst_null
    //   93: astore 5
    //   95: aload_3
    //   96: iconst_0
    //   97: invokevirtual 46	android/os/Parcel:writeInt	(I)V
    //   100: goto -51 -> 49
    //   103: astore 5
    //   105: aload 4
    //   107: invokevirtual 42	android/os/Parcel:recycle	()V
    //   110: aload_3
    //   111: invokevirtual 42	android/os/Parcel:recycle	()V
    //   114: aload 5
    //   116: athrow
    // Local variable table:
    //   start	length	slot	name	signature
    //   0	117	0	this	Proxy
    //   0	117	1	paramInt	int
    //   0	117	2	paramBundle	android.os.Bundle
    //   3	108	3	localParcel1	Parcel
    //   7	99	4	localParcel2	Parcel
    //   11	83	5	localObject1	Object
    //   103	12	5	localObject2	Object
    //   29	62	6	i	int
    //   58	5	7	j	int
    // Exception table:
    //   from	to	target	type
    //   14	19	103	finally
    //   20	24	103	finally
    //   32	37	103	finally
    //   45	49	103	finally
    //   49	53	103	finally
    //   67	74	103	finally
    //   74	79	103	finally
    //   96	100	103	finally
  }
  
  public void zzg(int paramInt, String paramString)
  {
    Parcel localParcel1 = Parcel.obtain();
    Parcel localParcel2 = Parcel.obtain();
    Object localObject1 = "com.google.android.gms.games.internal.IGamesCallbacks";
    try
    {
      localParcel1.writeInterfaceToken((String)localObject1);
      localParcel1.writeInt(paramInt);
      localParcel1.writeString(paramString);
      localObject1 = this.zzoz;
      int i = 5001;
      ((IBinder)localObject1).transact(i, localParcel1, localParcel2, 0);
      localParcel2.readException();
      return;
    }
    finally
    {
      localParcel2.recycle();
      localParcel1.recycle();
    }
  }
  
  public void zzgn(int paramInt)
  {
    Parcel localParcel1 = Parcel.obtain();
    Parcel localParcel2 = Parcel.obtain();
    Object localObject1 = "com.google.android.gms.games.internal.IGamesCallbacks";
    try
    {
      localParcel1.writeInterfaceToken((String)localObject1);
      localParcel1.writeInt(paramInt);
      localObject1 = this.zzoz;
      int i = 5036;
      ((IBinder)localObject1).transact(i, localParcel1, localParcel2, 0);
      localParcel2.readException();
      return;
    }
    finally
    {
      localParcel2.recycle();
      localParcel1.recycle();
    }
  }
  
  public void zzgo(int paramInt)
  {
    Parcel localParcel1 = Parcel.obtain();
    Parcel localParcel2 = Parcel.obtain();
    Object localObject1 = "com.google.android.gms.games.internal.IGamesCallbacks";
    try
    {
      localParcel1.writeInterfaceToken((String)localObject1);
      localParcel1.writeInt(paramInt);
      localObject1 = this.zzoz;
      int i = 5040;
      ((IBinder)localObject1).transact(i, localParcel1, localParcel2, 0);
      localParcel2.readException();
      return;
    }
    finally
    {
      localParcel2.recycle();
      localParcel1.recycle();
    }
  }
  
  public void zzgp(int paramInt)
  {
    Parcel localParcel1 = Parcel.obtain();
    Parcel localParcel2 = Parcel.obtain();
    Object localObject1 = "com.google.android.gms.games.internal.IGamesCallbacks";
    try
    {
      localParcel1.writeInterfaceToken((String)localObject1);
      localParcel1.writeInt(paramInt);
      localObject1 = this.zzoz;
      int i = 13002;
      ((IBinder)localObject1).transact(i, localParcel1, localParcel2, 0);
      localParcel2.readException();
      return;
    }
    finally
    {
      localParcel2.recycle();
      localParcel1.recycle();
    }
  }
  
  public void zzgq(int paramInt)
  {
    Parcel localParcel1 = Parcel.obtain();
    Parcel localParcel2 = Parcel.obtain();
    Object localObject1 = "com.google.android.gms.games.internal.IGamesCallbacks";
    try
    {
      localParcel1.writeInterfaceToken((String)localObject1);
      localParcel1.writeInt(paramInt);
      localObject1 = this.zzoz;
      int i = 17002;
      ((IBinder)localObject1).transact(i, localParcel1, localParcel2, 0);
      localParcel2.readException();
      return;
    }
    finally
    {
      localParcel2.recycle();
      localParcel1.recycle();
    }
  }
  
  public void zzh(int paramInt, String paramString)
  {
    Parcel localParcel1 = Parcel.obtain();
    Parcel localParcel2 = Parcel.obtain();
    Object localObject1 = "com.google.android.gms.games.internal.IGamesCallbacks";
    try
    {
      localParcel1.writeInterfaceToken((String)localObject1);
      localParcel1.writeInt(paramInt);
      localParcel1.writeString(paramString);
      localObject1 = this.zzoz;
      int i = 5003;
      ((IBinder)localObject1).transact(i, localParcel1, localParcel2, 0);
      localParcel2.readException();
      return;
    }
    finally
    {
      localParcel2.recycle();
      localParcel1.recycle();
    }
  }
  
  /* Error */
  public void zzh(DataHolder paramDataHolder)
  {
    // Byte code:
    //   0: invokestatic 20	android/os/Parcel:obtain	()Landroid/os/Parcel;
    //   3: astore_2
    //   4: invokestatic 20	android/os/Parcel:obtain	()Landroid/os/Parcel;
    //   7: astore_3
    //   8: ldc 22
    //   10: astore 4
    //   12: aload_2
    //   13: aload 4
    //   15: invokevirtual 26	android/os/Parcel:writeInterfaceToken	(Ljava/lang/String;)V
    //   18: aload_1
    //   19: ifnull +61 -> 80
    //   22: iconst_1
    //   23: istore 5
    //   25: aload_2
    //   26: iload 5
    //   28: invokevirtual 46	android/os/Parcel:writeInt	(I)V
    //   31: iconst_0
    //   32: istore 5
    //   34: aconst_null
    //   35: astore 4
    //   37: aload_1
    //   38: aload_2
    //   39: iconst_0
    //   40: invokevirtual 62	com/google/android/gms/common/data/DataHolder:writeToParcel	(Landroid/os/Parcel;I)V
    //   43: aload_0
    //   44: getfield 14	com/google/android/gms/games/internal/IGamesCallbacks$Stub$Proxy:zzoz	Landroid/os/IBinder;
    //   47: astore 4
    //   49: sipush 5002
    //   52: istore 6
    //   54: aload 4
    //   56: iload 6
    //   58: aload_2
    //   59: aload_3
    //   60: iconst_0
    //   61: invokeinterface 36 5 0
    //   66: pop
    //   67: aload_3
    //   68: invokevirtual 39	android/os/Parcel:readException	()V
    //   71: aload_3
    //   72: invokevirtual 42	android/os/Parcel:recycle	()V
    //   75: aload_2
    //   76: invokevirtual 42	android/os/Parcel:recycle	()V
    //   79: return
    //   80: iconst_0
    //   81: istore 5
    //   83: aconst_null
    //   84: astore 4
    //   86: aload_2
    //   87: iconst_0
    //   88: invokevirtual 46	android/os/Parcel:writeInt	(I)V
    //   91: goto -48 -> 43
    //   94: astore 4
    //   96: aload_3
    //   97: invokevirtual 42	android/os/Parcel:recycle	()V
    //   100: aload_2
    //   101: invokevirtual 42	android/os/Parcel:recycle	()V
    //   104: aload 4
    //   106: athrow
    // Local variable table:
    //   start	length	slot	name	signature
    //   0	107	0	this	Proxy
    //   0	107	1	paramDataHolder	DataHolder
    //   3	98	2	localParcel1	Parcel
    //   7	90	3	localParcel2	Parcel
    //   10	75	4	localObject1	Object
    //   94	11	4	localObject2	Object
    //   23	59	5	i	int
    //   52	5	6	j	int
    // Exception table:
    //   from	to	target	type
    //   13	18	94	finally
    //   26	31	94	finally
    //   39	43	94	finally
    //   43	47	94	finally
    //   60	67	94	finally
    //   67	71	94	finally
    //   87	91	94	finally
  }
  
  public void zzi(int paramInt, String paramString)
  {
    Parcel localParcel1 = Parcel.obtain();
    Parcel localParcel2 = Parcel.obtain();
    Object localObject1 = "com.google.android.gms.games.internal.IGamesCallbacks";
    try
    {
      localParcel1.writeInterfaceToken((String)localObject1);
      localParcel1.writeInt(paramInt);
      localParcel1.writeString(paramString);
      localObject1 = this.zzoz;
      int i = 8007;
      ((IBinder)localObject1).transact(i, localParcel1, localParcel2, 0);
      localParcel2.readException();
      return;
    }
    finally
    {
      localParcel2.recycle();
      localParcel1.recycle();
    }
  }
  
  /* Error */
  public void zzi(DataHolder paramDataHolder)
  {
    // Byte code:
    //   0: invokestatic 20	android/os/Parcel:obtain	()Landroid/os/Parcel;
    //   3: astore_2
    //   4: invokestatic 20	android/os/Parcel:obtain	()Landroid/os/Parcel;
    //   7: astore_3
    //   8: ldc 22
    //   10: astore 4
    //   12: aload_2
    //   13: aload 4
    //   15: invokevirtual 26	android/os/Parcel:writeInterfaceToken	(Ljava/lang/String;)V
    //   18: aload_1
    //   19: ifnull +61 -> 80
    //   22: iconst_1
    //   23: istore 5
    //   25: aload_2
    //   26: iload 5
    //   28: invokevirtual 46	android/os/Parcel:writeInt	(I)V
    //   31: iconst_0
    //   32: istore 5
    //   34: aconst_null
    //   35: astore 4
    //   37: aload_1
    //   38: aload_2
    //   39: iconst_0
    //   40: invokevirtual 62	com/google/android/gms/common/data/DataHolder:writeToParcel	(Landroid/os/Parcel;I)V
    //   43: aload_0
    //   44: getfield 14	com/google/android/gms/games/internal/IGamesCallbacks$Stub$Proxy:zzoz	Landroid/os/IBinder;
    //   47: astore 4
    //   49: sipush 12011
    //   52: istore 6
    //   54: aload 4
    //   56: iload 6
    //   58: aload_2
    //   59: aload_3
    //   60: iconst_0
    //   61: invokeinterface 36 5 0
    //   66: pop
    //   67: aload_3
    //   68: invokevirtual 39	android/os/Parcel:readException	()V
    //   71: aload_3
    //   72: invokevirtual 42	android/os/Parcel:recycle	()V
    //   75: aload_2
    //   76: invokevirtual 42	android/os/Parcel:recycle	()V
    //   79: return
    //   80: iconst_0
    //   81: istore 5
    //   83: aconst_null
    //   84: astore 4
    //   86: aload_2
    //   87: iconst_0
    //   88: invokevirtual 46	android/os/Parcel:writeInt	(I)V
    //   91: goto -48 -> 43
    //   94: astore 4
    //   96: aload_3
    //   97: invokevirtual 42	android/os/Parcel:recycle	()V
    //   100: aload_2
    //   101: invokevirtual 42	android/os/Parcel:recycle	()V
    //   104: aload 4
    //   106: athrow
    // Local variable table:
    //   start	length	slot	name	signature
    //   0	107	0	this	Proxy
    //   0	107	1	paramDataHolder	DataHolder
    //   3	98	2	localParcel1	Parcel
    //   7	90	3	localParcel2	Parcel
    //   10	75	4	localObject1	Object
    //   94	11	4	localObject2	Object
    //   23	59	5	i	int
    //   52	5	6	j	int
    // Exception table:
    //   from	to	target	type
    //   13	18	94	finally
    //   26	31	94	finally
    //   39	43	94	finally
    //   43	47	94	finally
    //   60	67	94	finally
    //   67	71	94	finally
    //   87	91	94	finally
  }
  
  public void zzj(int paramInt, String paramString)
  {
    Parcel localParcel1 = Parcel.obtain();
    Parcel localParcel2 = Parcel.obtain();
    Object localObject1 = "com.google.android.gms.games.internal.IGamesCallbacks";
    try
    {
      localParcel1.writeInterfaceToken((String)localObject1);
      localParcel1.writeInt(paramInt);
      localParcel1.writeString(paramString);
      localObject1 = this.zzoz;
      int i = 12012;
      ((IBinder)localObject1).transact(i, localParcel1, localParcel2, 0);
      localParcel2.readException();
      return;
    }
    finally
    {
      localParcel2.recycle();
      localParcel1.recycle();
    }
  }
  
  /* Error */
  public void zzj(DataHolder paramDataHolder)
  {
    // Byte code:
    //   0: invokestatic 20	android/os/Parcel:obtain	()Landroid/os/Parcel;
    //   3: astore_2
    //   4: invokestatic 20	android/os/Parcel:obtain	()Landroid/os/Parcel;
    //   7: astore_3
    //   8: ldc 22
    //   10: astore 4
    //   12: aload_2
    //   13: aload 4
    //   15: invokevirtual 26	android/os/Parcel:writeInterfaceToken	(Ljava/lang/String;)V
    //   18: aload_1
    //   19: ifnull +61 -> 80
    //   22: iconst_1
    //   23: istore 5
    //   25: aload_2
    //   26: iload 5
    //   28: invokevirtual 46	android/os/Parcel:writeInt	(I)V
    //   31: iconst_0
    //   32: istore 5
    //   34: aconst_null
    //   35: astore 4
    //   37: aload_1
    //   38: aload_2
    //   39: iconst_0
    //   40: invokevirtual 62	com/google/android/gms/common/data/DataHolder:writeToParcel	(Landroid/os/Parcel;I)V
    //   43: aload_0
    //   44: getfield 14	com/google/android/gms/games/internal/IGamesCallbacks$Stub$Proxy:zzoz	Landroid/os/IBinder;
    //   47: astore 4
    //   49: sipush 5004
    //   52: istore 6
    //   54: aload 4
    //   56: iload 6
    //   58: aload_2
    //   59: aload_3
    //   60: iconst_0
    //   61: invokeinterface 36 5 0
    //   66: pop
    //   67: aload_3
    //   68: invokevirtual 39	android/os/Parcel:readException	()V
    //   71: aload_3
    //   72: invokevirtual 42	android/os/Parcel:recycle	()V
    //   75: aload_2
    //   76: invokevirtual 42	android/os/Parcel:recycle	()V
    //   79: return
    //   80: iconst_0
    //   81: istore 5
    //   83: aconst_null
    //   84: astore 4
    //   86: aload_2
    //   87: iconst_0
    //   88: invokevirtual 46	android/os/Parcel:writeInt	(I)V
    //   91: goto -48 -> 43
    //   94: astore 4
    //   96: aload_3
    //   97: invokevirtual 42	android/os/Parcel:recycle	()V
    //   100: aload_2
    //   101: invokevirtual 42	android/os/Parcel:recycle	()V
    //   104: aload 4
    //   106: athrow
    // Local variable table:
    //   start	length	slot	name	signature
    //   0	107	0	this	Proxy
    //   0	107	1	paramDataHolder	DataHolder
    //   3	98	2	localParcel1	Parcel
    //   7	90	3	localParcel2	Parcel
    //   10	75	4	localObject1	Object
    //   94	11	4	localObject2	Object
    //   23	59	5	i	int
    //   52	5	6	j	int
    // Exception table:
    //   from	to	target	type
    //   13	18	94	finally
    //   26	31	94	finally
    //   39	43	94	finally
    //   43	47	94	finally
    //   60	67	94	finally
    //   67	71	94	finally
    //   87	91	94	finally
  }
  
  /* Error */
  public void zzk(DataHolder paramDataHolder)
  {
    // Byte code:
    //   0: invokestatic 20	android/os/Parcel:obtain	()Landroid/os/Parcel;
    //   3: astore_2
    //   4: invokestatic 20	android/os/Parcel:obtain	()Landroid/os/Parcel;
    //   7: astore_3
    //   8: ldc 22
    //   10: astore 4
    //   12: aload_2
    //   13: aload 4
    //   15: invokevirtual 26	android/os/Parcel:writeInterfaceToken	(Ljava/lang/String;)V
    //   18: aload_1
    //   19: ifnull +61 -> 80
    //   22: iconst_1
    //   23: istore 5
    //   25: aload_2
    //   26: iload 5
    //   28: invokevirtual 46	android/os/Parcel:writeInt	(I)V
    //   31: iconst_0
    //   32: istore 5
    //   34: aconst_null
    //   35: astore 4
    //   37: aload_1
    //   38: aload_2
    //   39: iconst_0
    //   40: invokevirtual 62	com/google/android/gms/common/data/DataHolder:writeToParcel	(Landroid/os/Parcel;I)V
    //   43: aload_0
    //   44: getfield 14	com/google/android/gms/games/internal/IGamesCallbacks$Stub$Proxy:zzoz	Landroid/os/IBinder;
    //   47: astore 4
    //   49: sipush 5006
    //   52: istore 6
    //   54: aload 4
    //   56: iload 6
    //   58: aload_2
    //   59: aload_3
    //   60: iconst_0
    //   61: invokeinterface 36 5 0
    //   66: pop
    //   67: aload_3
    //   68: invokevirtual 39	android/os/Parcel:readException	()V
    //   71: aload_3
    //   72: invokevirtual 42	android/os/Parcel:recycle	()V
    //   75: aload_2
    //   76: invokevirtual 42	android/os/Parcel:recycle	()V
    //   79: return
    //   80: iconst_0
    //   81: istore 5
    //   83: aconst_null
    //   84: astore 4
    //   86: aload_2
    //   87: iconst_0
    //   88: invokevirtual 46	android/os/Parcel:writeInt	(I)V
    //   91: goto -48 -> 43
    //   94: astore 4
    //   96: aload_3
    //   97: invokevirtual 42	android/os/Parcel:recycle	()V
    //   100: aload_2
    //   101: invokevirtual 42	android/os/Parcel:recycle	()V
    //   104: aload 4
    //   106: athrow
    // Local variable table:
    //   start	length	slot	name	signature
    //   0	107	0	this	Proxy
    //   0	107	1	paramDataHolder	DataHolder
    //   3	98	2	localParcel1	Parcel
    //   7	90	3	localParcel2	Parcel
    //   10	75	4	localObject1	Object
    //   94	11	4	localObject2	Object
    //   23	59	5	i	int
    //   52	5	6	j	int
    // Exception table:
    //   from	to	target	type
    //   13	18	94	finally
    //   26	31	94	finally
    //   39	43	94	finally
    //   43	47	94	finally
    //   60	67	94	finally
    //   67	71	94	finally
    //   87	91	94	finally
  }
  
  /* Error */
  public void zzl(DataHolder paramDataHolder)
  {
    // Byte code:
    //   0: invokestatic 20	android/os/Parcel:obtain	()Landroid/os/Parcel;
    //   3: astore_2
    //   4: invokestatic 20	android/os/Parcel:obtain	()Landroid/os/Parcel;
    //   7: astore_3
    //   8: ldc 22
    //   10: astore 4
    //   12: aload_2
    //   13: aload 4
    //   15: invokevirtual 26	android/os/Parcel:writeInterfaceToken	(Ljava/lang/String;)V
    //   18: aload_1
    //   19: ifnull +61 -> 80
    //   22: iconst_1
    //   23: istore 5
    //   25: aload_2
    //   26: iload 5
    //   28: invokevirtual 46	android/os/Parcel:writeInt	(I)V
    //   31: iconst_0
    //   32: istore 5
    //   34: aconst_null
    //   35: astore 4
    //   37: aload_1
    //   38: aload_2
    //   39: iconst_0
    //   40: invokevirtual 62	com/google/android/gms/common/data/DataHolder:writeToParcel	(Landroid/os/Parcel;I)V
    //   43: aload_0
    //   44: getfield 14	com/google/android/gms/games/internal/IGamesCallbacks$Stub$Proxy:zzoz	Landroid/os/IBinder;
    //   47: astore 4
    //   49: sipush 5007
    //   52: istore 6
    //   54: aload 4
    //   56: iload 6
    //   58: aload_2
    //   59: aload_3
    //   60: iconst_0
    //   61: invokeinterface 36 5 0
    //   66: pop
    //   67: aload_3
    //   68: invokevirtual 39	android/os/Parcel:readException	()V
    //   71: aload_3
    //   72: invokevirtual 42	android/os/Parcel:recycle	()V
    //   75: aload_2
    //   76: invokevirtual 42	android/os/Parcel:recycle	()V
    //   79: return
    //   80: iconst_0
    //   81: istore 5
    //   83: aconst_null
    //   84: astore 4
    //   86: aload_2
    //   87: iconst_0
    //   88: invokevirtual 46	android/os/Parcel:writeInt	(I)V
    //   91: goto -48 -> 43
    //   94: astore 4
    //   96: aload_3
    //   97: invokevirtual 42	android/os/Parcel:recycle	()V
    //   100: aload_2
    //   101: invokevirtual 42	android/os/Parcel:recycle	()V
    //   104: aload 4
    //   106: athrow
    // Local variable table:
    //   start	length	slot	name	signature
    //   0	107	0	this	Proxy
    //   0	107	1	paramDataHolder	DataHolder
    //   3	98	2	localParcel1	Parcel
    //   7	90	3	localParcel2	Parcel
    //   10	75	4	localObject1	Object
    //   94	11	4	localObject2	Object
    //   23	59	5	i	int
    //   52	5	6	j	int
    // Exception table:
    //   from	to	target	type
    //   13	18	94	finally
    //   26	31	94	finally
    //   39	43	94	finally
    //   43	47	94	finally
    //   60	67	94	finally
    //   67	71	94	finally
    //   87	91	94	finally
  }
  
  /* Error */
  public void zzm(DataHolder paramDataHolder)
  {
    // Byte code:
    //   0: invokestatic 20	android/os/Parcel:obtain	()Landroid/os/Parcel;
    //   3: astore_2
    //   4: invokestatic 20	android/os/Parcel:obtain	()Landroid/os/Parcel;
    //   7: astore_3
    //   8: ldc 22
    //   10: astore 4
    //   12: aload_2
    //   13: aload 4
    //   15: invokevirtual 26	android/os/Parcel:writeInterfaceToken	(Ljava/lang/String;)V
    //   18: aload_1
    //   19: ifnull +61 -> 80
    //   22: iconst_1
    //   23: istore 5
    //   25: aload_2
    //   26: iload 5
    //   28: invokevirtual 46	android/os/Parcel:writeInt	(I)V
    //   31: iconst_0
    //   32: istore 5
    //   34: aconst_null
    //   35: astore 4
    //   37: aload_1
    //   38: aload_2
    //   39: iconst_0
    //   40: invokevirtual 62	com/google/android/gms/common/data/DataHolder:writeToParcel	(Landroid/os/Parcel;I)V
    //   43: aload_0
    //   44: getfield 14	com/google/android/gms/games/internal/IGamesCallbacks$Stub$Proxy:zzoz	Landroid/os/IBinder;
    //   47: astore 4
    //   49: sipush 5008
    //   52: istore 6
    //   54: aload 4
    //   56: iload 6
    //   58: aload_2
    //   59: aload_3
    //   60: iconst_0
    //   61: invokeinterface 36 5 0
    //   66: pop
    //   67: aload_3
    //   68: invokevirtual 39	android/os/Parcel:readException	()V
    //   71: aload_3
    //   72: invokevirtual 42	android/os/Parcel:recycle	()V
    //   75: aload_2
    //   76: invokevirtual 42	android/os/Parcel:recycle	()V
    //   79: return
    //   80: iconst_0
    //   81: istore 5
    //   83: aconst_null
    //   84: astore 4
    //   86: aload_2
    //   87: iconst_0
    //   88: invokevirtual 46	android/os/Parcel:writeInt	(I)V
    //   91: goto -48 -> 43
    //   94: astore 4
    //   96: aload_3
    //   97: invokevirtual 42	android/os/Parcel:recycle	()V
    //   100: aload_2
    //   101: invokevirtual 42	android/os/Parcel:recycle	()V
    //   104: aload 4
    //   106: athrow
    // Local variable table:
    //   start	length	slot	name	signature
    //   0	107	0	this	Proxy
    //   0	107	1	paramDataHolder	DataHolder
    //   3	98	2	localParcel1	Parcel
    //   7	90	3	localParcel2	Parcel
    //   10	75	4	localObject1	Object
    //   94	11	4	localObject2	Object
    //   23	59	5	i	int
    //   52	5	6	j	int
    // Exception table:
    //   from	to	target	type
    //   13	18	94	finally
    //   26	31	94	finally
    //   39	43	94	finally
    //   43	47	94	finally
    //   60	67	94	finally
    //   67	71	94	finally
    //   87	91	94	finally
  }
  
  /* Error */
  public void zzn(DataHolder paramDataHolder)
  {
    // Byte code:
    //   0: invokestatic 20	android/os/Parcel:obtain	()Landroid/os/Parcel;
    //   3: astore_2
    //   4: invokestatic 20	android/os/Parcel:obtain	()Landroid/os/Parcel;
    //   7: astore_3
    //   8: ldc 22
    //   10: astore 4
    //   12: aload_2
    //   13: aload 4
    //   15: invokevirtual 26	android/os/Parcel:writeInterfaceToken	(Ljava/lang/String;)V
    //   18: aload_1
    //   19: ifnull +61 -> 80
    //   22: iconst_1
    //   23: istore 5
    //   25: aload_2
    //   26: iload 5
    //   28: invokevirtual 46	android/os/Parcel:writeInt	(I)V
    //   31: iconst_0
    //   32: istore 5
    //   34: aconst_null
    //   35: astore 4
    //   37: aload_1
    //   38: aload_2
    //   39: iconst_0
    //   40: invokevirtual 62	com/google/android/gms/common/data/DataHolder:writeToParcel	(Landroid/os/Parcel;I)V
    //   43: aload_0
    //   44: getfield 14	com/google/android/gms/games/internal/IGamesCallbacks$Stub$Proxy:zzoz	Landroid/os/IBinder;
    //   47: astore 4
    //   49: sipush 5009
    //   52: istore 6
    //   54: aload 4
    //   56: iload 6
    //   58: aload_2
    //   59: aload_3
    //   60: iconst_0
    //   61: invokeinterface 36 5 0
    //   66: pop
    //   67: aload_3
    //   68: invokevirtual 39	android/os/Parcel:readException	()V
    //   71: aload_3
    //   72: invokevirtual 42	android/os/Parcel:recycle	()V
    //   75: aload_2
    //   76: invokevirtual 42	android/os/Parcel:recycle	()V
    //   79: return
    //   80: iconst_0
    //   81: istore 5
    //   83: aconst_null
    //   84: astore 4
    //   86: aload_2
    //   87: iconst_0
    //   88: invokevirtual 46	android/os/Parcel:writeInt	(I)V
    //   91: goto -48 -> 43
    //   94: astore 4
    //   96: aload_3
    //   97: invokevirtual 42	android/os/Parcel:recycle	()V
    //   100: aload_2
    //   101: invokevirtual 42	android/os/Parcel:recycle	()V
    //   104: aload 4
    //   106: athrow
    // Local variable table:
    //   start	length	slot	name	signature
    //   0	107	0	this	Proxy
    //   0	107	1	paramDataHolder	DataHolder
    //   3	98	2	localParcel1	Parcel
    //   7	90	3	localParcel2	Parcel
    //   10	75	4	localObject1	Object
    //   94	11	4	localObject2	Object
    //   23	59	5	i	int
    //   52	5	6	j	int
    // Exception table:
    //   from	to	target	type
    //   13	18	94	finally
    //   26	31	94	finally
    //   39	43	94	finally
    //   43	47	94	finally
    //   60	67	94	finally
    //   67	71	94	finally
    //   87	91	94	finally
  }
  
  /* Error */
  public void zzo(DataHolder paramDataHolder)
  {
    // Byte code:
    //   0: invokestatic 20	android/os/Parcel:obtain	()Landroid/os/Parcel;
    //   3: astore_2
    //   4: invokestatic 20	android/os/Parcel:obtain	()Landroid/os/Parcel;
    //   7: astore_3
    //   8: ldc 22
    //   10: astore 4
    //   12: aload_2
    //   13: aload 4
    //   15: invokevirtual 26	android/os/Parcel:writeInterfaceToken	(Ljava/lang/String;)V
    //   18: aload_1
    //   19: ifnull +61 -> 80
    //   22: iconst_1
    //   23: istore 5
    //   25: aload_2
    //   26: iload 5
    //   28: invokevirtual 46	android/os/Parcel:writeInt	(I)V
    //   31: iconst_0
    //   32: istore 5
    //   34: aconst_null
    //   35: astore 4
    //   37: aload_1
    //   38: aload_2
    //   39: iconst_0
    //   40: invokevirtual 62	com/google/android/gms/common/data/DataHolder:writeToParcel	(Landroid/os/Parcel;I)V
    //   43: aload_0
    //   44: getfield 14	com/google/android/gms/games/internal/IGamesCallbacks$Stub$Proxy:zzoz	Landroid/os/IBinder;
    //   47: astore 4
    //   49: sipush 5010
    //   52: istore 6
    //   54: aload 4
    //   56: iload 6
    //   58: aload_2
    //   59: aload_3
    //   60: iconst_0
    //   61: invokeinterface 36 5 0
    //   66: pop
    //   67: aload_3
    //   68: invokevirtual 39	android/os/Parcel:readException	()V
    //   71: aload_3
    //   72: invokevirtual 42	android/os/Parcel:recycle	()V
    //   75: aload_2
    //   76: invokevirtual 42	android/os/Parcel:recycle	()V
    //   79: return
    //   80: iconst_0
    //   81: istore 5
    //   83: aconst_null
    //   84: astore 4
    //   86: aload_2
    //   87: iconst_0
    //   88: invokevirtual 46	android/os/Parcel:writeInt	(I)V
    //   91: goto -48 -> 43
    //   94: astore 4
    //   96: aload_3
    //   97: invokevirtual 42	android/os/Parcel:recycle	()V
    //   100: aload_2
    //   101: invokevirtual 42	android/os/Parcel:recycle	()V
    //   104: aload 4
    //   106: athrow
    // Local variable table:
    //   start	length	slot	name	signature
    //   0	107	0	this	Proxy
    //   0	107	1	paramDataHolder	DataHolder
    //   3	98	2	localParcel1	Parcel
    //   7	90	3	localParcel2	Parcel
    //   10	75	4	localObject1	Object
    //   94	11	4	localObject2	Object
    //   23	59	5	i	int
    //   52	5	6	j	int
    // Exception table:
    //   from	to	target	type
    //   13	18	94	finally
    //   26	31	94	finally
    //   39	43	94	finally
    //   43	47	94	finally
    //   60	67	94	finally
    //   67	71	94	finally
    //   87	91	94	finally
  }
  
  /* Error */
  public void zzp(DataHolder paramDataHolder)
  {
    // Byte code:
    //   0: invokestatic 20	android/os/Parcel:obtain	()Landroid/os/Parcel;
    //   3: astore_2
    //   4: invokestatic 20	android/os/Parcel:obtain	()Landroid/os/Parcel;
    //   7: astore_3
    //   8: ldc 22
    //   10: astore 4
    //   12: aload_2
    //   13: aload 4
    //   15: invokevirtual 26	android/os/Parcel:writeInterfaceToken	(Ljava/lang/String;)V
    //   18: aload_1
    //   19: ifnull +61 -> 80
    //   22: iconst_1
    //   23: istore 5
    //   25: aload_2
    //   26: iload 5
    //   28: invokevirtual 46	android/os/Parcel:writeInt	(I)V
    //   31: iconst_0
    //   32: istore 5
    //   34: aconst_null
    //   35: astore 4
    //   37: aload_1
    //   38: aload_2
    //   39: iconst_0
    //   40: invokevirtual 62	com/google/android/gms/common/data/DataHolder:writeToParcel	(Landroid/os/Parcel;I)V
    //   43: aload_0
    //   44: getfield 14	com/google/android/gms/games/internal/IGamesCallbacks$Stub$Proxy:zzoz	Landroid/os/IBinder;
    //   47: astore 4
    //   49: sipush 5011
    //   52: istore 6
    //   54: aload 4
    //   56: iload 6
    //   58: aload_2
    //   59: aload_3
    //   60: iconst_0
    //   61: invokeinterface 36 5 0
    //   66: pop
    //   67: aload_3
    //   68: invokevirtual 39	android/os/Parcel:readException	()V
    //   71: aload_3
    //   72: invokevirtual 42	android/os/Parcel:recycle	()V
    //   75: aload_2
    //   76: invokevirtual 42	android/os/Parcel:recycle	()V
    //   79: return
    //   80: iconst_0
    //   81: istore 5
    //   83: aconst_null
    //   84: astore 4
    //   86: aload_2
    //   87: iconst_0
    //   88: invokevirtual 46	android/os/Parcel:writeInt	(I)V
    //   91: goto -48 -> 43
    //   94: astore 4
    //   96: aload_3
    //   97: invokevirtual 42	android/os/Parcel:recycle	()V
    //   100: aload_2
    //   101: invokevirtual 42	android/os/Parcel:recycle	()V
    //   104: aload 4
    //   106: athrow
    // Local variable table:
    //   start	length	slot	name	signature
    //   0	107	0	this	Proxy
    //   0	107	1	paramDataHolder	DataHolder
    //   3	98	2	localParcel1	Parcel
    //   7	90	3	localParcel2	Parcel
    //   10	75	4	localObject1	Object
    //   94	11	4	localObject2	Object
    //   23	59	5	i	int
    //   52	5	6	j	int
    // Exception table:
    //   from	to	target	type
    //   13	18	94	finally
    //   26	31	94	finally
    //   39	43	94	finally
    //   43	47	94	finally
    //   60	67	94	finally
    //   67	71	94	finally
    //   87	91	94	finally
  }
  
  /* Error */
  public void zzq(DataHolder paramDataHolder)
  {
    // Byte code:
    //   0: invokestatic 20	android/os/Parcel:obtain	()Landroid/os/Parcel;
    //   3: astore_2
    //   4: invokestatic 20	android/os/Parcel:obtain	()Landroid/os/Parcel;
    //   7: astore_3
    //   8: ldc 22
    //   10: astore 4
    //   12: aload_2
    //   13: aload 4
    //   15: invokevirtual 26	android/os/Parcel:writeInterfaceToken	(Ljava/lang/String;)V
    //   18: aload_1
    //   19: ifnull +61 -> 80
    //   22: iconst_1
    //   23: istore 5
    //   25: aload_2
    //   26: iload 5
    //   28: invokevirtual 46	android/os/Parcel:writeInt	(I)V
    //   31: iconst_0
    //   32: istore 5
    //   34: aconst_null
    //   35: astore 4
    //   37: aload_1
    //   38: aload_2
    //   39: iconst_0
    //   40: invokevirtual 62	com/google/android/gms/common/data/DataHolder:writeToParcel	(Landroid/os/Parcel;I)V
    //   43: aload_0
    //   44: getfield 14	com/google/android/gms/games/internal/IGamesCallbacks$Stub$Proxy:zzoz	Landroid/os/IBinder;
    //   47: astore 4
    //   49: sipush 9001
    //   52: istore 6
    //   54: aload 4
    //   56: iload 6
    //   58: aload_2
    //   59: aload_3
    //   60: iconst_0
    //   61: invokeinterface 36 5 0
    //   66: pop
    //   67: aload_3
    //   68: invokevirtual 39	android/os/Parcel:readException	()V
    //   71: aload_3
    //   72: invokevirtual 42	android/os/Parcel:recycle	()V
    //   75: aload_2
    //   76: invokevirtual 42	android/os/Parcel:recycle	()V
    //   79: return
    //   80: iconst_0
    //   81: istore 5
    //   83: aconst_null
    //   84: astore 4
    //   86: aload_2
    //   87: iconst_0
    //   88: invokevirtual 46	android/os/Parcel:writeInt	(I)V
    //   91: goto -48 -> 43
    //   94: astore 4
    //   96: aload_3
    //   97: invokevirtual 42	android/os/Parcel:recycle	()V
    //   100: aload_2
    //   101: invokevirtual 42	android/os/Parcel:recycle	()V
    //   104: aload 4
    //   106: athrow
    // Local variable table:
    //   start	length	slot	name	signature
    //   0	107	0	this	Proxy
    //   0	107	1	paramDataHolder	DataHolder
    //   3	98	2	localParcel1	Parcel
    //   7	90	3	localParcel2	Parcel
    //   10	75	4	localObject1	Object
    //   94	11	4	localObject2	Object
    //   23	59	5	i	int
    //   52	5	6	j	int
    // Exception table:
    //   from	to	target	type
    //   13	18	94	finally
    //   26	31	94	finally
    //   39	43	94	finally
    //   43	47	94	finally
    //   60	67	94	finally
    //   67	71	94	finally
    //   87	91	94	finally
  }
  
  /* Error */
  public void zzr(DataHolder paramDataHolder)
  {
    // Byte code:
    //   0: invokestatic 20	android/os/Parcel:obtain	()Landroid/os/Parcel;
    //   3: astore_2
    //   4: invokestatic 20	android/os/Parcel:obtain	()Landroid/os/Parcel;
    //   7: astore_3
    //   8: ldc 22
    //   10: astore 4
    //   12: aload_2
    //   13: aload 4
    //   15: invokevirtual 26	android/os/Parcel:writeInterfaceToken	(Ljava/lang/String;)V
    //   18: aload_1
    //   19: ifnull +61 -> 80
    //   22: iconst_1
    //   23: istore 5
    //   25: aload_2
    //   26: iload 5
    //   28: invokevirtual 46	android/os/Parcel:writeInt	(I)V
    //   31: iconst_0
    //   32: istore 5
    //   34: aconst_null
    //   35: astore 4
    //   37: aload_1
    //   38: aload_2
    //   39: iconst_0
    //   40: invokevirtual 62	com/google/android/gms/common/data/DataHolder:writeToParcel	(Landroid/os/Parcel;I)V
    //   43: aload_0
    //   44: getfield 14	com/google/android/gms/games/internal/IGamesCallbacks$Stub$Proxy:zzoz	Landroid/os/IBinder;
    //   47: astore 4
    //   49: sipush 5017
    //   52: istore 6
    //   54: aload 4
    //   56: iload 6
    //   58: aload_2
    //   59: aload_3
    //   60: iconst_0
    //   61: invokeinterface 36 5 0
    //   66: pop
    //   67: aload_3
    //   68: invokevirtual 39	android/os/Parcel:readException	()V
    //   71: aload_3
    //   72: invokevirtual 42	android/os/Parcel:recycle	()V
    //   75: aload_2
    //   76: invokevirtual 42	android/os/Parcel:recycle	()V
    //   79: return
    //   80: iconst_0
    //   81: istore 5
    //   83: aconst_null
    //   84: astore 4
    //   86: aload_2
    //   87: iconst_0
    //   88: invokevirtual 46	android/os/Parcel:writeInt	(I)V
    //   91: goto -48 -> 43
    //   94: astore 4
    //   96: aload_3
    //   97: invokevirtual 42	android/os/Parcel:recycle	()V
    //   100: aload_2
    //   101: invokevirtual 42	android/os/Parcel:recycle	()V
    //   104: aload 4
    //   106: athrow
    // Local variable table:
    //   start	length	slot	name	signature
    //   0	107	0	this	Proxy
    //   0	107	1	paramDataHolder	DataHolder
    //   3	98	2	localParcel1	Parcel
    //   7	90	3	localParcel2	Parcel
    //   10	75	4	localObject1	Object
    //   94	11	4	localObject2	Object
    //   23	59	5	i	int
    //   52	5	6	j	int
    // Exception table:
    //   from	to	target	type
    //   13	18	94	finally
    //   26	31	94	finally
    //   39	43	94	finally
    //   43	47	94	finally
    //   60	67	94	finally
    //   67	71	94	finally
    //   87	91	94	finally
  }
  
  /* Error */
  public void zzs(DataHolder paramDataHolder)
  {
    // Byte code:
    //   0: invokestatic 20	android/os/Parcel:obtain	()Landroid/os/Parcel;
    //   3: astore_2
    //   4: invokestatic 20	android/os/Parcel:obtain	()Landroid/os/Parcel;
    //   7: astore_3
    //   8: ldc 22
    //   10: astore 4
    //   12: aload_2
    //   13: aload 4
    //   15: invokevirtual 26	android/os/Parcel:writeInterfaceToken	(Ljava/lang/String;)V
    //   18: aload_1
    //   19: ifnull +61 -> 80
    //   22: iconst_1
    //   23: istore 5
    //   25: aload_2
    //   26: iload 5
    //   28: invokevirtual 46	android/os/Parcel:writeInt	(I)V
    //   31: iconst_0
    //   32: istore 5
    //   34: aconst_null
    //   35: astore 4
    //   37: aload_1
    //   38: aload_2
    //   39: iconst_0
    //   40: invokevirtual 62	com/google/android/gms/common/data/DataHolder:writeToParcel	(Landroid/os/Parcel;I)V
    //   43: aload_0
    //   44: getfield 14	com/google/android/gms/games/internal/IGamesCallbacks$Stub$Proxy:zzoz	Landroid/os/IBinder;
    //   47: astore 4
    //   49: sipush 5037
    //   52: istore 6
    //   54: aload 4
    //   56: iload 6
    //   58: aload_2
    //   59: aload_3
    //   60: iconst_0
    //   61: invokeinterface 36 5 0
    //   66: pop
    //   67: aload_3
    //   68: invokevirtual 39	android/os/Parcel:readException	()V
    //   71: aload_3
    //   72: invokevirtual 42	android/os/Parcel:recycle	()V
    //   75: aload_2
    //   76: invokevirtual 42	android/os/Parcel:recycle	()V
    //   79: return
    //   80: iconst_0
    //   81: istore 5
    //   83: aconst_null
    //   84: astore 4
    //   86: aload_2
    //   87: iconst_0
    //   88: invokevirtual 46	android/os/Parcel:writeInt	(I)V
    //   91: goto -48 -> 43
    //   94: astore 4
    //   96: aload_3
    //   97: invokevirtual 42	android/os/Parcel:recycle	()V
    //   100: aload_2
    //   101: invokevirtual 42	android/os/Parcel:recycle	()V
    //   104: aload 4
    //   106: athrow
    // Local variable table:
    //   start	length	slot	name	signature
    //   0	107	0	this	Proxy
    //   0	107	1	paramDataHolder	DataHolder
    //   3	98	2	localParcel1	Parcel
    //   7	90	3	localParcel2	Parcel
    //   10	75	4	localObject1	Object
    //   94	11	4	localObject2	Object
    //   23	59	5	i	int
    //   52	5	6	j	int
    // Exception table:
    //   from	to	target	type
    //   13	18	94	finally
    //   26	31	94	finally
    //   39	43	94	finally
    //   43	47	94	finally
    //   60	67	94	finally
    //   67	71	94	finally
    //   87	91	94	finally
  }
  
  /* Error */
  public void zzt(DataHolder paramDataHolder)
  {
    // Byte code:
    //   0: invokestatic 20	android/os/Parcel:obtain	()Landroid/os/Parcel;
    //   3: astore_2
    //   4: invokestatic 20	android/os/Parcel:obtain	()Landroid/os/Parcel;
    //   7: astore_3
    //   8: ldc 22
    //   10: astore 4
    //   12: aload_2
    //   13: aload 4
    //   15: invokevirtual 26	android/os/Parcel:writeInterfaceToken	(Ljava/lang/String;)V
    //   18: aload_1
    //   19: ifnull +61 -> 80
    //   22: iconst_1
    //   23: istore 5
    //   25: aload_2
    //   26: iload 5
    //   28: invokevirtual 46	android/os/Parcel:writeInt	(I)V
    //   31: iconst_0
    //   32: istore 5
    //   34: aconst_null
    //   35: astore 4
    //   37: aload_1
    //   38: aload_2
    //   39: iconst_0
    //   40: invokevirtual 62	com/google/android/gms/common/data/DataHolder:writeToParcel	(Landroid/os/Parcel;I)V
    //   43: aload_0
    //   44: getfield 14	com/google/android/gms/games/internal/IGamesCallbacks$Stub$Proxy:zzoz	Landroid/os/IBinder;
    //   47: astore 4
    //   49: sipush 10001
    //   52: istore 6
    //   54: aload 4
    //   56: iload 6
    //   58: aload_2
    //   59: aload_3
    //   60: iconst_0
    //   61: invokeinterface 36 5 0
    //   66: pop
    //   67: aload_3
    //   68: invokevirtual 39	android/os/Parcel:readException	()V
    //   71: aload_3
    //   72: invokevirtual 42	android/os/Parcel:recycle	()V
    //   75: aload_2
    //   76: invokevirtual 42	android/os/Parcel:recycle	()V
    //   79: return
    //   80: iconst_0
    //   81: istore 5
    //   83: aconst_null
    //   84: astore 4
    //   86: aload_2
    //   87: iconst_0
    //   88: invokevirtual 46	android/os/Parcel:writeInt	(I)V
    //   91: goto -48 -> 43
    //   94: astore 4
    //   96: aload_3
    //   97: invokevirtual 42	android/os/Parcel:recycle	()V
    //   100: aload_2
    //   101: invokevirtual 42	android/os/Parcel:recycle	()V
    //   104: aload 4
    //   106: athrow
    // Local variable table:
    //   start	length	slot	name	signature
    //   0	107	0	this	Proxy
    //   0	107	1	paramDataHolder	DataHolder
    //   3	98	2	localParcel1	Parcel
    //   7	90	3	localParcel2	Parcel
    //   10	75	4	localObject1	Object
    //   94	11	4	localObject2	Object
    //   23	59	5	i	int
    //   52	5	6	j	int
    // Exception table:
    //   from	to	target	type
    //   13	18	94	finally
    //   26	31	94	finally
    //   39	43	94	finally
    //   43	47	94	finally
    //   60	67	94	finally
    //   67	71	94	finally
    //   87	91	94	finally
  }
  
  /* Error */
  public void zzu(DataHolder paramDataHolder)
  {
    // Byte code:
    //   0: invokestatic 20	android/os/Parcel:obtain	()Landroid/os/Parcel;
    //   3: astore_2
    //   4: invokestatic 20	android/os/Parcel:obtain	()Landroid/os/Parcel;
    //   7: astore_3
    //   8: ldc 22
    //   10: astore 4
    //   12: aload_2
    //   13: aload 4
    //   15: invokevirtual 26	android/os/Parcel:writeInterfaceToken	(Ljava/lang/String;)V
    //   18: aload_1
    //   19: ifnull +61 -> 80
    //   22: iconst_1
    //   23: istore 5
    //   25: aload_2
    //   26: iload 5
    //   28: invokevirtual 46	android/os/Parcel:writeInt	(I)V
    //   31: iconst_0
    //   32: istore 5
    //   34: aconst_null
    //   35: astore 4
    //   37: aload_1
    //   38: aload_2
    //   39: iconst_0
    //   40: invokevirtual 62	com/google/android/gms/common/data/DataHolder:writeToParcel	(Landroid/os/Parcel;I)V
    //   43: aload_0
    //   44: getfield 14	com/google/android/gms/games/internal/IGamesCallbacks$Stub$Proxy:zzoz	Landroid/os/IBinder;
    //   47: astore 4
    //   49: sipush 8003
    //   52: istore 6
    //   54: aload 4
    //   56: iload 6
    //   58: aload_2
    //   59: aload_3
    //   60: iconst_0
    //   61: invokeinterface 36 5 0
    //   66: pop
    //   67: aload_3
    //   68: invokevirtual 39	android/os/Parcel:readException	()V
    //   71: aload_3
    //   72: invokevirtual 42	android/os/Parcel:recycle	()V
    //   75: aload_2
    //   76: invokevirtual 42	android/os/Parcel:recycle	()V
    //   79: return
    //   80: iconst_0
    //   81: istore 5
    //   83: aconst_null
    //   84: astore 4
    //   86: aload_2
    //   87: iconst_0
    //   88: invokevirtual 46	android/os/Parcel:writeInt	(I)V
    //   91: goto -48 -> 43
    //   94: astore 4
    //   96: aload_3
    //   97: invokevirtual 42	android/os/Parcel:recycle	()V
    //   100: aload_2
    //   101: invokevirtual 42	android/os/Parcel:recycle	()V
    //   104: aload 4
    //   106: athrow
    // Local variable table:
    //   start	length	slot	name	signature
    //   0	107	0	this	Proxy
    //   0	107	1	paramDataHolder	DataHolder
    //   3	98	2	localParcel1	Parcel
    //   7	90	3	localParcel2	Parcel
    //   10	75	4	localObject1	Object
    //   94	11	4	localObject2	Object
    //   23	59	5	i	int
    //   52	5	6	j	int
    // Exception table:
    //   from	to	target	type
    //   13	18	94	finally
    //   26	31	94	finally
    //   39	43	94	finally
    //   43	47	94	finally
    //   60	67	94	finally
    //   67	71	94	finally
    //   87	91	94	finally
  }
  
  /* Error */
  public void zzv(DataHolder paramDataHolder)
  {
    // Byte code:
    //   0: invokestatic 20	android/os/Parcel:obtain	()Landroid/os/Parcel;
    //   3: astore_2
    //   4: invokestatic 20	android/os/Parcel:obtain	()Landroid/os/Parcel;
    //   7: astore_3
    //   8: ldc 22
    //   10: astore 4
    //   12: aload_2
    //   13: aload 4
    //   15: invokevirtual 26	android/os/Parcel:writeInterfaceToken	(Ljava/lang/String;)V
    //   18: aload_1
    //   19: ifnull +61 -> 80
    //   22: iconst_1
    //   23: istore 5
    //   25: aload_2
    //   26: iload 5
    //   28: invokevirtual 46	android/os/Parcel:writeInt	(I)V
    //   31: iconst_0
    //   32: istore 5
    //   34: aconst_null
    //   35: astore 4
    //   37: aload_1
    //   38: aload_2
    //   39: iconst_0
    //   40: invokevirtual 62	com/google/android/gms/common/data/DataHolder:writeToParcel	(Landroid/os/Parcel;I)V
    //   43: aload_0
    //   44: getfield 14	com/google/android/gms/games/internal/IGamesCallbacks$Stub$Proxy:zzoz	Landroid/os/IBinder;
    //   47: astore 4
    //   49: sipush 8004
    //   52: istore 6
    //   54: aload 4
    //   56: iload 6
    //   58: aload_2
    //   59: aload_3
    //   60: iconst_0
    //   61: invokeinterface 36 5 0
    //   66: pop
    //   67: aload_3
    //   68: invokevirtual 39	android/os/Parcel:readException	()V
    //   71: aload_3
    //   72: invokevirtual 42	android/os/Parcel:recycle	()V
    //   75: aload_2
    //   76: invokevirtual 42	android/os/Parcel:recycle	()V
    //   79: return
    //   80: iconst_0
    //   81: istore 5
    //   83: aconst_null
    //   84: astore 4
    //   86: aload_2
    //   87: iconst_0
    //   88: invokevirtual 46	android/os/Parcel:writeInt	(I)V
    //   91: goto -48 -> 43
    //   94: astore 4
    //   96: aload_3
    //   97: invokevirtual 42	android/os/Parcel:recycle	()V
    //   100: aload_2
    //   101: invokevirtual 42	android/os/Parcel:recycle	()V
    //   104: aload 4
    //   106: athrow
    // Local variable table:
    //   start	length	slot	name	signature
    //   0	107	0	this	Proxy
    //   0	107	1	paramDataHolder	DataHolder
    //   3	98	2	localParcel1	Parcel
    //   7	90	3	localParcel2	Parcel
    //   10	75	4	localObject1	Object
    //   94	11	4	localObject2	Object
    //   23	59	5	i	int
    //   52	5	6	j	int
    // Exception table:
    //   from	to	target	type
    //   13	18	94	finally
    //   26	31	94	finally
    //   39	43	94	finally
    //   43	47	94	finally
    //   60	67	94	finally
    //   67	71	94	finally
    //   87	91	94	finally
  }
  
  /* Error */
  public void zzw(DataHolder paramDataHolder)
  {
    // Byte code:
    //   0: invokestatic 20	android/os/Parcel:obtain	()Landroid/os/Parcel;
    //   3: astore_2
    //   4: invokestatic 20	android/os/Parcel:obtain	()Landroid/os/Parcel;
    //   7: astore_3
    //   8: ldc 22
    //   10: astore 4
    //   12: aload_2
    //   13: aload 4
    //   15: invokevirtual 26	android/os/Parcel:writeInterfaceToken	(Ljava/lang/String;)V
    //   18: aload_1
    //   19: ifnull +61 -> 80
    //   22: iconst_1
    //   23: istore 5
    //   25: aload_2
    //   26: iload 5
    //   28: invokevirtual 46	android/os/Parcel:writeInt	(I)V
    //   31: iconst_0
    //   32: istore 5
    //   34: aconst_null
    //   35: astore 4
    //   37: aload_1
    //   38: aload_2
    //   39: iconst_0
    //   40: invokevirtual 62	com/google/android/gms/common/data/DataHolder:writeToParcel	(Landroid/os/Parcel;I)V
    //   43: aload_0
    //   44: getfield 14	com/google/android/gms/games/internal/IGamesCallbacks$Stub$Proxy:zzoz	Landroid/os/IBinder;
    //   47: astore 4
    //   49: sipush 8005
    //   52: istore 6
    //   54: aload 4
    //   56: iload 6
    //   58: aload_2
    //   59: aload_3
    //   60: iconst_0
    //   61: invokeinterface 36 5 0
    //   66: pop
    //   67: aload_3
    //   68: invokevirtual 39	android/os/Parcel:readException	()V
    //   71: aload_3
    //   72: invokevirtual 42	android/os/Parcel:recycle	()V
    //   75: aload_2
    //   76: invokevirtual 42	android/os/Parcel:recycle	()V
    //   79: return
    //   80: iconst_0
    //   81: istore 5
    //   83: aconst_null
    //   84: astore 4
    //   86: aload_2
    //   87: iconst_0
    //   88: invokevirtual 46	android/os/Parcel:writeInt	(I)V
    //   91: goto -48 -> 43
    //   94: astore 4
    //   96: aload_3
    //   97: invokevirtual 42	android/os/Parcel:recycle	()V
    //   100: aload_2
    //   101: invokevirtual 42	android/os/Parcel:recycle	()V
    //   104: aload 4
    //   106: athrow
    // Local variable table:
    //   start	length	slot	name	signature
    //   0	107	0	this	Proxy
    //   0	107	1	paramDataHolder	DataHolder
    //   3	98	2	localParcel1	Parcel
    //   7	90	3	localParcel2	Parcel
    //   10	75	4	localObject1	Object
    //   94	11	4	localObject2	Object
    //   23	59	5	i	int
    //   52	5	6	j	int
    // Exception table:
    //   from	to	target	type
    //   13	18	94	finally
    //   26	31	94	finally
    //   39	43	94	finally
    //   43	47	94	finally
    //   60	67	94	finally
    //   67	71	94	finally
    //   87	91	94	finally
  }
  
  public void zzwr()
  {
    Parcel localParcel1 = Parcel.obtain();
    Parcel localParcel2 = Parcel.obtain();
    Object localObject1 = "com.google.android.gms.games.internal.IGamesCallbacks";
    try
    {
      localParcel1.writeInterfaceToken((String)localObject1);
      localObject1 = this.zzoz;
      int i = 5016;
      ((IBinder)localObject1).transact(i, localParcel1, localParcel2, 0);
      localParcel2.readException();
      return;
    }
    finally
    {
      localParcel2.recycle();
      localParcel1.recycle();
    }
  }
  
  /* Error */
  public void zzx(DataHolder paramDataHolder)
  {
    // Byte code:
    //   0: invokestatic 20	android/os/Parcel:obtain	()Landroid/os/Parcel;
    //   3: astore_2
    //   4: invokestatic 20	android/os/Parcel:obtain	()Landroid/os/Parcel;
    //   7: astore_3
    //   8: ldc 22
    //   10: astore 4
    //   12: aload_2
    //   13: aload 4
    //   15: invokevirtual 26	android/os/Parcel:writeInterfaceToken	(Ljava/lang/String;)V
    //   18: aload_1
    //   19: ifnull +61 -> 80
    //   22: iconst_1
    //   23: istore 5
    //   25: aload_2
    //   26: iload 5
    //   28: invokevirtual 46	android/os/Parcel:writeInt	(I)V
    //   31: iconst_0
    //   32: istore 5
    //   34: aconst_null
    //   35: astore 4
    //   37: aload_1
    //   38: aload_2
    //   39: iconst_0
    //   40: invokevirtual 62	com/google/android/gms/common/data/DataHolder:writeToParcel	(Landroid/os/Parcel;I)V
    //   43: aload_0
    //   44: getfield 14	com/google/android/gms/games/internal/IGamesCallbacks$Stub$Proxy:zzoz	Landroid/os/IBinder;
    //   47: astore 4
    //   49: sipush 8006
    //   52: istore 6
    //   54: aload 4
    //   56: iload 6
    //   58: aload_2
    //   59: aload_3
    //   60: iconst_0
    //   61: invokeinterface 36 5 0
    //   66: pop
    //   67: aload_3
    //   68: invokevirtual 39	android/os/Parcel:readException	()V
    //   71: aload_3
    //   72: invokevirtual 42	android/os/Parcel:recycle	()V
    //   75: aload_2
    //   76: invokevirtual 42	android/os/Parcel:recycle	()V
    //   79: return
    //   80: iconst_0
    //   81: istore 5
    //   83: aconst_null
    //   84: astore 4
    //   86: aload_2
    //   87: iconst_0
    //   88: invokevirtual 46	android/os/Parcel:writeInt	(I)V
    //   91: goto -48 -> 43
    //   94: astore 4
    //   96: aload_3
    //   97: invokevirtual 42	android/os/Parcel:recycle	()V
    //   100: aload_2
    //   101: invokevirtual 42	android/os/Parcel:recycle	()V
    //   104: aload 4
    //   106: athrow
    // Local variable table:
    //   start	length	slot	name	signature
    //   0	107	0	this	Proxy
    //   0	107	1	paramDataHolder	DataHolder
    //   3	98	2	localParcel1	Parcel
    //   7	90	3	localParcel2	Parcel
    //   10	75	4	localObject1	Object
    //   94	11	4	localObject2	Object
    //   23	59	5	i	int
    //   52	5	6	j	int
    // Exception table:
    //   from	to	target	type
    //   13	18	94	finally
    //   26	31	94	finally
    //   39	43	94	finally
    //   43	47	94	finally
    //   60	67	94	finally
    //   67	71	94	finally
    //   87	91	94	finally
  }
  
  /* Error */
  public void zzy(DataHolder paramDataHolder)
  {
    // Byte code:
    //   0: invokestatic 20	android/os/Parcel:obtain	()Landroid/os/Parcel;
    //   3: astore_2
    //   4: invokestatic 20	android/os/Parcel:obtain	()Landroid/os/Parcel;
    //   7: astore_3
    //   8: ldc 22
    //   10: astore 4
    //   12: aload_2
    //   13: aload 4
    //   15: invokevirtual 26	android/os/Parcel:writeInterfaceToken	(Ljava/lang/String;)V
    //   18: aload_1
    //   19: ifnull +61 -> 80
    //   22: iconst_1
    //   23: istore 5
    //   25: aload_2
    //   26: iload 5
    //   28: invokevirtual 46	android/os/Parcel:writeInt	(I)V
    //   31: iconst_0
    //   32: istore 5
    //   34: aconst_null
    //   35: astore 4
    //   37: aload_1
    //   38: aload_2
    //   39: iconst_0
    //   40: invokevirtual 62	com/google/android/gms/common/data/DataHolder:writeToParcel	(Landroid/os/Parcel;I)V
    //   43: aload_0
    //   44: getfield 14	com/google/android/gms/games/internal/IGamesCallbacks$Stub$Proxy:zzoz	Landroid/os/IBinder;
    //   47: astore 4
    //   49: sipush 8008
    //   52: istore 6
    //   54: aload 4
    //   56: iload 6
    //   58: aload_2
    //   59: aload_3
    //   60: iconst_0
    //   61: invokeinterface 36 5 0
    //   66: pop
    //   67: aload_3
    //   68: invokevirtual 39	android/os/Parcel:readException	()V
    //   71: aload_3
    //   72: invokevirtual 42	android/os/Parcel:recycle	()V
    //   75: aload_2
    //   76: invokevirtual 42	android/os/Parcel:recycle	()V
    //   79: return
    //   80: iconst_0
    //   81: istore 5
    //   83: aconst_null
    //   84: astore 4
    //   86: aload_2
    //   87: iconst_0
    //   88: invokevirtual 46	android/os/Parcel:writeInt	(I)V
    //   91: goto -48 -> 43
    //   94: astore 4
    //   96: aload_3
    //   97: invokevirtual 42	android/os/Parcel:recycle	()V
    //   100: aload_2
    //   101: invokevirtual 42	android/os/Parcel:recycle	()V
    //   104: aload 4
    //   106: athrow
    // Local variable table:
    //   start	length	slot	name	signature
    //   0	107	0	this	Proxy
    //   0	107	1	paramDataHolder	DataHolder
    //   3	98	2	localParcel1	Parcel
    //   7	90	3	localParcel2	Parcel
    //   10	75	4	localObject1	Object
    //   94	11	4	localObject2	Object
    //   23	59	5	i	int
    //   52	5	6	j	int
    // Exception table:
    //   from	to	target	type
    //   13	18	94	finally
    //   26	31	94	finally
    //   39	43	94	finally
    //   43	47	94	finally
    //   60	67	94	finally
    //   67	71	94	finally
    //   87	91	94	finally
  }
  
  /* Error */
  public void zzz(DataHolder paramDataHolder)
  {
    // Byte code:
    //   0: invokestatic 20	android/os/Parcel:obtain	()Landroid/os/Parcel;
    //   3: astore_2
    //   4: invokestatic 20	android/os/Parcel:obtain	()Landroid/os/Parcel;
    //   7: astore_3
    //   8: ldc 22
    //   10: astore 4
    //   12: aload_2
    //   13: aload 4
    //   15: invokevirtual 26	android/os/Parcel:writeInterfaceToken	(Ljava/lang/String;)V
    //   18: aload_1
    //   19: ifnull +61 -> 80
    //   22: iconst_1
    //   23: istore 5
    //   25: aload_2
    //   26: iload 5
    //   28: invokevirtual 46	android/os/Parcel:writeInt	(I)V
    //   31: iconst_0
    //   32: istore 5
    //   34: aconst_null
    //   35: astore 4
    //   37: aload_1
    //   38: aload_2
    //   39: iconst_0
    //   40: invokevirtual 62	com/google/android/gms/common/data/DataHolder:writeToParcel	(Landroid/os/Parcel;I)V
    //   43: aload_0
    //   44: getfield 14	com/google/android/gms/games/internal/IGamesCallbacks$Stub$Proxy:zzoz	Landroid/os/IBinder;
    //   47: astore 4
    //   49: sipush 5018
    //   52: istore 6
    //   54: aload 4
    //   56: iload 6
    //   58: aload_2
    //   59: aload_3
    //   60: iconst_0
    //   61: invokeinterface 36 5 0
    //   66: pop
    //   67: aload_3
    //   68: invokevirtual 39	android/os/Parcel:readException	()V
    //   71: aload_3
    //   72: invokevirtual 42	android/os/Parcel:recycle	()V
    //   75: aload_2
    //   76: invokevirtual 42	android/os/Parcel:recycle	()V
    //   79: return
    //   80: iconst_0
    //   81: istore 5
    //   83: aconst_null
    //   84: astore 4
    //   86: aload_2
    //   87: iconst_0
    //   88: invokevirtual 46	android/os/Parcel:writeInt	(I)V
    //   91: goto -48 -> 43
    //   94: astore 4
    //   96: aload_3
    //   97: invokevirtual 42	android/os/Parcel:recycle	()V
    //   100: aload_2
    //   101: invokevirtual 42	android/os/Parcel:recycle	()V
    //   104: aload 4
    //   106: athrow
    // Local variable table:
    //   start	length	slot	name	signature
    //   0	107	0	this	Proxy
    //   0	107	1	paramDataHolder	DataHolder
    //   3	98	2	localParcel1	Parcel
    //   7	90	3	localParcel2	Parcel
    //   10	75	4	localObject1	Object
    //   94	11	4	localObject2	Object
    //   23	59	5	i	int
    //   52	5	6	j	int
    // Exception table:
    //   from	to	target	type
    //   13	18	94	finally
    //   26	31	94	finally
    //   39	43	94	finally
    //   43	47	94	finally
    //   60	67	94	finally
    //   67	71	94	finally
    //   87	91	94	finally
  }
}


/* Location:              C:\Users\haryo\Desktop\enjarify-master\presensi-enjarify.jar!\com\google\android\gms\games\internal\IGamesCallbacks$Stub$Proxy.class
 * Java compiler version: 5 (49.0)
 * JD-Core Version:       0.7.1
 */