package com.google.android.gms.drive.events;

import com.google.android.gms.drive.internal.zzao.zza;

final class DriveEventService$zzb
  extends zzao.zza
{
  DriveEventService$zzb(DriveEventService paramDriveEventService) {}
  
  /* Error */
  public void zzc(com.google.android.gms.drive.internal.OnEventResponse paramOnEventResponse)
  {
    // Byte code:
    //   0: aload_0
    //   1: getfield 8	com/google/android/gms/drive/events/DriveEventService$zzb:zzapP	Lcom/google/android/gms/drive/events/DriveEventService;
    //   4: astore_2
    //   5: aload_2
    //   6: monitorenter
    //   7: ldc 14
    //   9: astore_3
    //   10: new 16	java/lang/StringBuilder
    //   13: astore 4
    //   15: aload 4
    //   17: invokespecial 17	java/lang/StringBuilder:<init>	()V
    //   20: ldc 19
    //   22: astore 5
    //   24: aload 4
    //   26: aload 5
    //   28: invokevirtual 23	java/lang/StringBuilder:append	(Ljava/lang/String;)Ljava/lang/StringBuilder;
    //   31: astore 4
    //   33: aload 4
    //   35: aload_1
    //   36: invokevirtual 26	java/lang/StringBuilder:append	(Ljava/lang/Object;)Ljava/lang/StringBuilder;
    //   39: astore 4
    //   41: aload 4
    //   43: invokevirtual 30	java/lang/StringBuilder:toString	()Ljava/lang/String;
    //   46: astore 4
    //   48: aload_3
    //   49: aload 4
    //   51: invokestatic 36	com/google/android/gms/drive/internal/zzz:zzy	(Ljava/lang/String;Ljava/lang/String;)V
    //   54: aload_0
    //   55: getfield 8	com/google/android/gms/drive/events/DriveEventService$zzb:zzapP	Lcom/google/android/gms/drive/events/DriveEventService;
    //   58: astore_3
    //   59: aload_3
    //   60: invokestatic 42	com/google/android/gms/drive/events/DriveEventService:zza	(Lcom/google/android/gms/drive/events/DriveEventService;)V
    //   63: aload_0
    //   64: getfield 8	com/google/android/gms/drive/events/DriveEventService$zzb:zzapP	Lcom/google/android/gms/drive/events/DriveEventService;
    //   67: astore_3
    //   68: aload_3
    //   69: getfield 46	com/google/android/gms/drive/events/DriveEventService:zzapM	Lcom/google/android/gms/drive/events/DriveEventService$zza;
    //   72: astore_3
    //   73: aload_3
    //   74: ifnull +42 -> 116
    //   77: aload_0
    //   78: getfield 8	com/google/android/gms/drive/events/DriveEventService$zzb:zzapP	Lcom/google/android/gms/drive/events/DriveEventService;
    //   81: astore_3
    //   82: aload_3
    //   83: getfield 46	com/google/android/gms/drive/events/DriveEventService:zzapM	Lcom/google/android/gms/drive/events/DriveEventService$zza;
    //   86: astore_3
    //   87: aload_3
    //   88: aload_1
    //   89: invokestatic 51	com/google/android/gms/drive/events/DriveEventService$zza:zza	(Lcom/google/android/gms/drive/events/DriveEventService$zza;Lcom/google/android/gms/drive/internal/OnEventResponse;)Landroid/os/Message;
    //   92: astore_3
    //   93: aload_0
    //   94: getfield 8	com/google/android/gms/drive/events/DriveEventService$zzb:zzapP	Lcom/google/android/gms/drive/events/DriveEventService;
    //   97: astore 4
    //   99: aload 4
    //   101: getfield 46	com/google/android/gms/drive/events/DriveEventService:zzapM	Lcom/google/android/gms/drive/events/DriveEventService$zza;
    //   104: astore 4
    //   106: aload 4
    //   108: aload_3
    //   109: invokevirtual 55	com/google/android/gms/drive/events/DriveEventService$zza:sendMessage	(Landroid/os/Message;)Z
    //   112: pop
    //   113: aload_2
    //   114: monitorexit
    //   115: return
    //   116: ldc 14
    //   118: astore_3
    //   119: ldc 57
    //   121: astore 4
    //   123: aload_3
    //   124: aload 4
    //   126: invokestatic 60	com/google/android/gms/drive/internal/zzz:zzA	(Ljava/lang/String;Ljava/lang/String;)V
    //   129: goto -16 -> 113
    //   132: astore_3
    //   133: aload_2
    //   134: monitorexit
    //   135: aload_3
    //   136: athrow
    // Local variable table:
    //   start	length	slot	name	signature
    //   0	137	0	this	zzb
    //   0	137	1	paramOnEventResponse	com.google.android.gms.drive.internal.OnEventResponse
    //   4	130	2	localDriveEventService	DriveEventService
    //   9	115	3	localObject1	Object
    //   132	4	3	localObject2	Object
    //   13	112	4	localObject3	Object
    //   22	5	5	str	String
    // Exception table:
    //   from	to	target	type
    //   10	13	132	finally
    //   15	20	132	finally
    //   26	31	132	finally
    //   35	39	132	finally
    //   41	46	132	finally
    //   49	54	132	finally
    //   54	58	132	finally
    //   59	63	132	finally
    //   63	67	132	finally
    //   68	72	132	finally
    //   77	81	132	finally
    //   82	86	132	finally
    //   88	92	132	finally
    //   93	97	132	finally
    //   99	104	132	finally
    //   108	113	132	finally
    //   113	115	132	finally
    //   124	129	132	finally
    //   133	135	132	finally
  }
}


/* Location:              C:\Users\haryo\Desktop\enjarify-master\presensi-enjarify.jar!\com\google\android\gms\drive\events\DriveEventService$zzb.class
 * Java compiler version: 5 (49.0)
 * JD-Core Version:       0.7.1
 */