package com.google.android.gms.drive.internal;

import android.content.IntentSender;
import android.os.IBinder;
import android.os.Parcel;
import android.os.Parcelable.Creator;
import com.google.android.gms.drive.RealtimeDocumentSyncRequest;

class zzam$zza$zza
  implements zzam
{
  private IBinder zzoz;
  
  zzam$zza$zza(IBinder paramIBinder)
  {
    this.zzoz = paramIBinder;
  }
  
  public IBinder asBinder()
  {
    return this.zzoz;
  }
  
  public IntentSender zza(CreateFileIntentSenderRequest paramCreateFileIntentSenderRequest)
  {
    Parcel localParcel1 = Parcel.obtain();
    Parcel localParcel2 = Parcel.obtain();
    Object localObject3;
    for (Object localObject1 = "com.google.android.gms.drive.internal.IDriveService";; localObject3 = null) {
      try
      {
        localParcel1.writeInterfaceToken((String)localObject1);
        if (paramCreateFileIntentSenderRequest != null)
        {
          i = 1;
          localParcel1.writeInt(i);
          i = 0;
          localObject1 = null;
          paramCreateFileIntentSenderRequest.writeToParcel(localParcel1, 0);
        }
        for (;;)
        {
          localObject1 = this.zzoz;
          int j = 11;
          ((IBinder)localObject1).transact(j, localParcel1, localParcel2, 0);
          localParcel2.readException();
          i = localParcel2.readInt();
          if (i == 0) {
            break;
          }
          localObject1 = IntentSender.CREATOR;
          localObject1 = ((Parcelable.Creator)localObject1).createFromParcel(localParcel2);
          localObject1 = (IntentSender)localObject1;
          return (IntentSender)localObject1;
          i = 0;
          localObject1 = null;
          localParcel1.writeInt(0);
        }
        int i = 0;
      }
      finally
      {
        localParcel2.recycle();
        localParcel1.recycle();
      }
    }
  }
  
  public IntentSender zza(OpenFileIntentSenderRequest paramOpenFileIntentSenderRequest)
  {
    Parcel localParcel1 = Parcel.obtain();
    Parcel localParcel2 = Parcel.obtain();
    Object localObject3;
    for (Object localObject1 = "com.google.android.gms.drive.internal.IDriveService";; localObject3 = null) {
      try
      {
        localParcel1.writeInterfaceToken((String)localObject1);
        if (paramOpenFileIntentSenderRequest != null)
        {
          i = 1;
          localParcel1.writeInt(i);
          i = 0;
          localObject1 = null;
          paramOpenFileIntentSenderRequest.writeToParcel(localParcel1, 0);
        }
        for (;;)
        {
          localObject1 = this.zzoz;
          int j = 10;
          ((IBinder)localObject1).transact(j, localParcel1, localParcel2, 0);
          localParcel2.readException();
          i = localParcel2.readInt();
          if (i == 0) {
            break;
          }
          localObject1 = IntentSender.CREATOR;
          localObject1 = ((Parcelable.Creator)localObject1).createFromParcel(localParcel2);
          localObject1 = (IntentSender)localObject1;
          return (IntentSender)localObject1;
          i = 0;
          localObject1 = null;
          localParcel1.writeInt(0);
        }
        int i = 0;
      }
      finally
      {
        localParcel2.recycle();
        localParcel1.recycle();
      }
    }
  }
  
  public DriveServiceResponse zza(OpenContentsRequest paramOpenContentsRequest, zzan paramzzan)
  {
    Object localObject1 = null;
    Parcel localParcel1 = Parcel.obtain();
    Parcel localParcel2 = Parcel.obtain();
    for (Object localObject3 = "com.google.android.gms.drive.internal.IDriveService";; localObject3 = null) {
      try
      {
        localParcel1.writeInterfaceToken((String)localObject3);
        if (paramOpenContentsRequest != null)
        {
          i = 1;
          localParcel1.writeInt(i);
          i = 0;
          localObject3 = null;
          paramOpenContentsRequest.writeToParcel(localParcel1, 0);
        }
        while (paramzzan != null)
        {
          localObject3 = paramzzan.asBinder();
          localParcel1.writeStrongBinder((IBinder)localObject3);
          localObject3 = this.zzoz;
          int j = 7;
          ((IBinder)localObject3).transact(j, localParcel1, localParcel2, 0);
          localParcel2.readException();
          i = localParcel2.readInt();
          if (i != 0)
          {
            localObject1 = DriveServiceResponse.CREATOR;
            localObject1 = ((Parcelable.Creator)localObject1).createFromParcel(localParcel2);
            localObject1 = (DriveServiceResponse)localObject1;
          }
          return (DriveServiceResponse)localObject1;
          i = 0;
          localObject3 = null;
          localParcel1.writeInt(0);
        }
        int i = 0;
      }
      finally
      {
        localParcel2.recycle();
        localParcel1.recycle();
      }
    }
  }
  
  public DriveServiceResponse zza(StreamContentsRequest paramStreamContentsRequest, zzan paramzzan)
  {
    Object localObject1 = null;
    Parcel localParcel1 = Parcel.obtain();
    Parcel localParcel2 = Parcel.obtain();
    for (Object localObject3 = "com.google.android.gms.drive.internal.IDriveService";; localObject3 = null) {
      try
      {
        localParcel1.writeInterfaceToken((String)localObject3);
        if (paramStreamContentsRequest != null)
        {
          i = 1;
          localParcel1.writeInt(i);
          i = 0;
          localObject3 = null;
          paramStreamContentsRequest.writeToParcel(localParcel1, 0);
        }
        while (paramzzan != null)
        {
          localObject3 = paramzzan.asBinder();
          localParcel1.writeStrongBinder((IBinder)localObject3);
          localObject3 = this.zzoz;
          int j = 56;
          ((IBinder)localObject3).transact(j, localParcel1, localParcel2, 0);
          localParcel2.readException();
          i = localParcel2.readInt();
          if (i != 0)
          {
            localObject1 = DriveServiceResponse.CREATOR;
            localObject1 = ((Parcelable.Creator)localObject1).createFromParcel(localParcel2);
            localObject1 = (DriveServiceResponse)localObject1;
          }
          return (DriveServiceResponse)localObject1;
          i = 0;
          localObject3 = null;
          localParcel1.writeInt(0);
        }
        int i = 0;
      }
      finally
      {
        localParcel2.recycle();
        localParcel1.recycle();
      }
    }
  }
  
  public void zza(RealtimeDocumentSyncRequest paramRealtimeDocumentSyncRequest, zzan paramzzan)
  {
    Parcel localParcel1 = Parcel.obtain();
    Parcel localParcel2 = Parcel.obtain();
    Object localObject3;
    for (Object localObject1 = "com.google.android.gms.drive.internal.IDriveService";; localObject3 = null) {
      try
      {
        localParcel1.writeInterfaceToken((String)localObject1);
        if (paramRealtimeDocumentSyncRequest != null)
        {
          i = 1;
          localParcel1.writeInt(i);
          i = 0;
          localObject1 = null;
          paramRealtimeDocumentSyncRequest.writeToParcel(localParcel1, 0);
        }
        while (paramzzan != null)
        {
          localObject1 = paramzzan.asBinder();
          localParcel1.writeStrongBinder((IBinder)localObject1);
          localObject1 = this.zzoz;
          int j = 34;
          ((IBinder)localObject1).transact(j, localParcel1, localParcel2, 0);
          localParcel2.readException();
          return;
          i = 0;
          localObject1 = null;
          localParcel1.writeInt(0);
        }
        int i = 0;
      }
      finally
      {
        localParcel2.recycle();
        localParcel1.recycle();
      }
    }
  }
  
  public void zza(AddEventListenerRequest paramAddEventListenerRequest, zzao paramzzao, String paramString, zzan paramzzan)
  {
    IBinder localIBinder = null;
    Parcel localParcel1 = Parcel.obtain();
    Parcel localParcel2 = Parcel.obtain();
    for (Object localObject2 = "com.google.android.gms.drive.internal.IDriveService";; localObject2 = null) {
      try
      {
        localParcel1.writeInterfaceToken((String)localObject2);
        if (paramAddEventListenerRequest != null)
        {
          i = 1;
          localParcel1.writeInt(i);
          i = 0;
          localObject2 = null;
          paramAddEventListenerRequest.writeToParcel(localParcel1, 0);
        }
        while (paramzzao != null)
        {
          localObject2 = paramzzao.asBinder();
          localParcel1.writeStrongBinder((IBinder)localObject2);
          localParcel1.writeString(paramString);
          if (paramzzan != null) {
            localIBinder = paramzzan.asBinder();
          }
          localParcel1.writeStrongBinder(localIBinder);
          localIBinder = this.zzoz;
          i = 14;
          localIBinder.transact(i, localParcel1, localParcel2, 0);
          localParcel2.readException();
          return;
          i = 0;
          localObject2 = null;
          localParcel1.writeInt(0);
        }
        int i = 0;
      }
      finally
      {
        localParcel2.recycle();
        localParcel1.recycle();
      }
    }
  }
  
  public void zza(AddPermissionRequest paramAddPermissionRequest, zzan paramzzan)
  {
    Parcel localParcel1 = Parcel.obtain();
    Parcel localParcel2 = Parcel.obtain();
    Object localObject3;
    for (Object localObject1 = "com.google.android.gms.drive.internal.IDriveService";; localObject3 = null) {
      try
      {
        localParcel1.writeInterfaceToken((String)localObject1);
        if (paramAddPermissionRequest != null)
        {
          i = 1;
          localParcel1.writeInt(i);
          i = 0;
          localObject1 = null;
          paramAddPermissionRequest.writeToParcel(localParcel1, 0);
        }
        while (paramzzan != null)
        {
          localObject1 = paramzzan.asBinder();
          localParcel1.writeStrongBinder((IBinder)localObject1);
          localObject1 = this.zzoz;
          int j = 48;
          ((IBinder)localObject1).transact(j, localParcel1, localParcel2, 0);
          localParcel2.readException();
          return;
          i = 0;
          localObject1 = null;
          localParcel1.writeInt(0);
        }
        int i = 0;
      }
      finally
      {
        localParcel2.recycle();
        localParcel1.recycle();
      }
    }
  }
  
  public void zza(AuthorizeAccessRequest paramAuthorizeAccessRequest, zzan paramzzan)
  {
    Parcel localParcel1 = Parcel.obtain();
    Parcel localParcel2 = Parcel.obtain();
    Object localObject3;
    for (Object localObject1 = "com.google.android.gms.drive.internal.IDriveService";; localObject3 = null) {
      try
      {
        localParcel1.writeInterfaceToken((String)localObject1);
        if (paramAuthorizeAccessRequest != null)
        {
          i = 1;
          localParcel1.writeInt(i);
          i = 0;
          localObject1 = null;
          paramAuthorizeAccessRequest.writeToParcel(localParcel1, 0);
        }
        while (paramzzan != null)
        {
          localObject1 = paramzzan.asBinder();
          localParcel1.writeStrongBinder((IBinder)localObject1);
          localObject1 = this.zzoz;
          int j = 12;
          ((IBinder)localObject1).transact(j, localParcel1, localParcel2, 0);
          localParcel2.readException();
          return;
          i = 0;
          localObject1 = null;
          localParcel1.writeInt(0);
        }
        int i = 0;
      }
      finally
      {
        localParcel2.recycle();
        localParcel1.recycle();
      }
    }
  }
  
  public void zza(CancelPendingActionsRequest paramCancelPendingActionsRequest, zzan paramzzan)
  {
    Parcel localParcel1 = Parcel.obtain();
    Parcel localParcel2 = Parcel.obtain();
    Object localObject3;
    for (Object localObject1 = "com.google.android.gms.drive.internal.IDriveService";; localObject3 = null) {
      try
      {
        localParcel1.writeInterfaceToken((String)localObject1);
        if (paramCancelPendingActionsRequest != null)
        {
          i = 1;
          localParcel1.writeInt(i);
          i = 0;
          localObject1 = null;
          paramCancelPendingActionsRequest.writeToParcel(localParcel1, 0);
        }
        while (paramzzan != null)
        {
          localObject1 = paramzzan.asBinder();
          localParcel1.writeStrongBinder((IBinder)localObject1);
          localObject1 = this.zzoz;
          int j = 37;
          ((IBinder)localObject1).transact(j, localParcel1, localParcel2, 0);
          localParcel2.readException();
          return;
          i = 0;
          localObject1 = null;
          localParcel1.writeInt(0);
        }
        int i = 0;
      }
      finally
      {
        localParcel2.recycle();
        localParcel1.recycle();
      }
    }
  }
  
  public void zza(ChangeResourceParentsRequest paramChangeResourceParentsRequest, zzan paramzzan)
  {
    Parcel localParcel1 = Parcel.obtain();
    Parcel localParcel2 = Parcel.obtain();
    Object localObject3;
    for (Object localObject1 = "com.google.android.gms.drive.internal.IDriveService";; localObject3 = null) {
      try
      {
        localParcel1.writeInterfaceToken((String)localObject1);
        if (paramChangeResourceParentsRequest != null)
        {
          i = 1;
          localParcel1.writeInt(i);
          i = 0;
          localObject1 = null;
          paramChangeResourceParentsRequest.writeToParcel(localParcel1, 0);
        }
        while (paramzzan != null)
        {
          localObject1 = paramzzan.asBinder();
          localParcel1.writeStrongBinder((IBinder)localObject1);
          localObject1 = this.zzoz;
          int j = 55;
          ((IBinder)localObject1).transact(j, localParcel1, localParcel2, 0);
          localParcel2.readException();
          return;
          i = 0;
          localObject1 = null;
          localParcel1.writeInt(0);
        }
        int i = 0;
      }
      finally
      {
        localParcel2.recycle();
        localParcel1.recycle();
      }
    }
  }
  
  public void zza(CheckResourceIdsExistRequest paramCheckResourceIdsExistRequest, zzan paramzzan)
  {
    Parcel localParcel1 = Parcel.obtain();
    Parcel localParcel2 = Parcel.obtain();
    Object localObject3;
    for (Object localObject1 = "com.google.android.gms.drive.internal.IDriveService";; localObject3 = null) {
      try
      {
        localParcel1.writeInterfaceToken((String)localObject1);
        if (paramCheckResourceIdsExistRequest != null)
        {
          i = 1;
          localParcel1.writeInt(i);
          i = 0;
          localObject1 = null;
          paramCheckResourceIdsExistRequest.writeToParcel(localParcel1, 0);
        }
        while (paramzzan != null)
        {
          localObject1 = paramzzan.asBinder();
          localParcel1.writeStrongBinder((IBinder)localObject1);
          localObject1 = this.zzoz;
          int j = 30;
          ((IBinder)localObject1).transact(j, localParcel1, localParcel2, 0);
          localParcel2.readException();
          return;
          i = 0;
          localObject1 = null;
          localParcel1.writeInt(0);
        }
        int i = 0;
      }
      finally
      {
        localParcel2.recycle();
        localParcel1.recycle();
      }
    }
  }
  
  public void zza(CloseContentsAndUpdateMetadataRequest paramCloseContentsAndUpdateMetadataRequest, zzan paramzzan)
  {
    Parcel localParcel1 = Parcel.obtain();
    Parcel localParcel2 = Parcel.obtain();
    Object localObject3;
    for (Object localObject1 = "com.google.android.gms.drive.internal.IDriveService";; localObject3 = null) {
      try
      {
        localParcel1.writeInterfaceToken((String)localObject1);
        if (paramCloseContentsAndUpdateMetadataRequest != null)
        {
          i = 1;
          localParcel1.writeInt(i);
          i = 0;
          localObject1 = null;
          paramCloseContentsAndUpdateMetadataRequest.writeToParcel(localParcel1, 0);
        }
        while (paramzzan != null)
        {
          localObject1 = paramzzan.asBinder();
          localParcel1.writeStrongBinder((IBinder)localObject1);
          localObject1 = this.zzoz;
          int j = 18;
          ((IBinder)localObject1).transact(j, localParcel1, localParcel2, 0);
          localParcel2.readException();
          return;
          i = 0;
          localObject1 = null;
          localParcel1.writeInt(0);
        }
        int i = 0;
      }
      finally
      {
        localParcel2.recycle();
        localParcel1.recycle();
      }
    }
  }
  
  public void zza(CloseContentsRequest paramCloseContentsRequest, zzan paramzzan)
  {
    Parcel localParcel1 = Parcel.obtain();
    Parcel localParcel2 = Parcel.obtain();
    Object localObject3;
    for (Object localObject1 = "com.google.android.gms.drive.internal.IDriveService";; localObject3 = null) {
      try
      {
        localParcel1.writeInterfaceToken((String)localObject1);
        if (paramCloseContentsRequest != null)
        {
          i = 1;
          localParcel1.writeInt(i);
          i = 0;
          localObject1 = null;
          paramCloseContentsRequest.writeToParcel(localParcel1, 0);
        }
        while (paramzzan != null)
        {
          localObject1 = paramzzan.asBinder();
          localParcel1.writeStrongBinder((IBinder)localObject1);
          localObject1 = this.zzoz;
          int j = 8;
          ((IBinder)localObject1).transact(j, localParcel1, localParcel2, 0);
          localParcel2.readException();
          return;
          i = 0;
          localObject1 = null;
          localParcel1.writeInt(0);
        }
        int i = 0;
      }
      finally
      {
        localParcel2.recycle();
        localParcel1.recycle();
      }
    }
  }
  
  public void zza(ControlProgressRequest paramControlProgressRequest, zzan paramzzan)
  {
    Parcel localParcel1 = Parcel.obtain();
    Parcel localParcel2 = Parcel.obtain();
    Object localObject3;
    for (Object localObject1 = "com.google.android.gms.drive.internal.IDriveService";; localObject3 = null) {
      try
      {
        localParcel1.writeInterfaceToken((String)localObject1);
        if (paramControlProgressRequest != null)
        {
          i = 1;
          localParcel1.writeInt(i);
          i = 0;
          localObject1 = null;
          paramControlProgressRequest.writeToParcel(localParcel1, 0);
        }
        while (paramzzan != null)
        {
          localObject1 = paramzzan.asBinder();
          localParcel1.writeStrongBinder((IBinder)localObject1);
          localObject1 = this.zzoz;
          int j = 53;
          ((IBinder)localObject1).transact(j, localParcel1, localParcel2, 0);
          localParcel2.readException();
          return;
          i = 0;
          localObject1 = null;
          localParcel1.writeInt(0);
        }
        int i = 0;
      }
      finally
      {
        localParcel2.recycle();
        localParcel1.recycle();
      }
    }
  }
  
  public void zza(CreateContentsRequest paramCreateContentsRequest, zzan paramzzan)
  {
    Parcel localParcel1 = Parcel.obtain();
    Parcel localParcel2 = Parcel.obtain();
    Object localObject3;
    for (Object localObject1 = "com.google.android.gms.drive.internal.IDriveService";; localObject3 = null) {
      try
      {
        localParcel1.writeInterfaceToken((String)localObject1);
        if (paramCreateContentsRequest != null)
        {
          i = 1;
          localParcel1.writeInt(i);
          i = 0;
          localObject1 = null;
          paramCreateContentsRequest.writeToParcel(localParcel1, 0);
        }
        while (paramzzan != null)
        {
          localObject1 = paramzzan.asBinder();
          localParcel1.writeStrongBinder((IBinder)localObject1);
          localObject1 = this.zzoz;
          int j = 4;
          ((IBinder)localObject1).transact(j, localParcel1, localParcel2, 0);
          localParcel2.readException();
          return;
          i = 0;
          localObject1 = null;
          localParcel1.writeInt(0);
        }
        int i = 0;
      }
      finally
      {
        localParcel2.recycle();
        localParcel1.recycle();
      }
    }
  }
  
  public void zza(CreateFileRequest paramCreateFileRequest, zzan paramzzan)
  {
    Parcel localParcel1 = Parcel.obtain();
    Parcel localParcel2 = Parcel.obtain();
    Object localObject3;
    for (Object localObject1 = "com.google.android.gms.drive.internal.IDriveService";; localObject3 = null) {
      try
      {
        localParcel1.writeInterfaceToken((String)localObject1);
        if (paramCreateFileRequest != null)
        {
          i = 1;
          localParcel1.writeInt(i);
          i = 0;
          localObject1 = null;
          paramCreateFileRequest.writeToParcel(localParcel1, 0);
        }
        while (paramzzan != null)
        {
          localObject1 = paramzzan.asBinder();
          localParcel1.writeStrongBinder((IBinder)localObject1);
          localObject1 = this.zzoz;
          int j = 5;
          ((IBinder)localObject1).transact(j, localParcel1, localParcel2, 0);
          localParcel2.readException();
          return;
          i = 0;
          localObject1 = null;
          localParcel1.writeInt(0);
        }
        int i = 0;
      }
      finally
      {
        localParcel2.recycle();
        localParcel1.recycle();
      }
    }
  }
  
  public void zza(CreateFolderRequest paramCreateFolderRequest, zzan paramzzan)
  {
    Parcel localParcel1 = Parcel.obtain();
    Parcel localParcel2 = Parcel.obtain();
    Object localObject3;
    for (Object localObject1 = "com.google.android.gms.drive.internal.IDriveService";; localObject3 = null) {
      try
      {
        localParcel1.writeInterfaceToken((String)localObject1);
        if (paramCreateFolderRequest != null)
        {
          i = 1;
          localParcel1.writeInt(i);
          i = 0;
          localObject1 = null;
          paramCreateFolderRequest.writeToParcel(localParcel1, 0);
        }
        while (paramzzan != null)
        {
          localObject1 = paramzzan.asBinder();
          localParcel1.writeStrongBinder((IBinder)localObject1);
          localObject1 = this.zzoz;
          int j = 6;
          ((IBinder)localObject1).transact(j, localParcel1, localParcel2, 0);
          localParcel2.readException();
          return;
          i = 0;
          localObject1 = null;
          localParcel1.writeInt(0);
        }
        int i = 0;
      }
      finally
      {
        localParcel2.recycle();
        localParcel1.recycle();
      }
    }
  }
  
  public void zza(DeleteResourceRequest paramDeleteResourceRequest, zzan paramzzan)
  {
    Parcel localParcel1 = Parcel.obtain();
    Parcel localParcel2 = Parcel.obtain();
    Object localObject3;
    for (Object localObject1 = "com.google.android.gms.drive.internal.IDriveService";; localObject3 = null) {
      try
      {
        localParcel1.writeInterfaceToken((String)localObject1);
        if (paramDeleteResourceRequest != null)
        {
          i = 1;
          localParcel1.writeInt(i);
          i = 0;
          localObject1 = null;
          paramDeleteResourceRequest.writeToParcel(localParcel1, 0);
        }
        while (paramzzan != null)
        {
          localObject1 = paramzzan.asBinder();
          localParcel1.writeStrongBinder((IBinder)localObject1);
          localObject1 = this.zzoz;
          int j = 24;
          ((IBinder)localObject1).transact(j, localParcel1, localParcel2, 0);
          localParcel2.readException();
          return;
          i = 0;
          localObject1 = null;
          localParcel1.writeInt(0);
        }
        int i = 0;
      }
      finally
      {
        localParcel2.recycle();
        localParcel1.recycle();
      }
    }
  }
  
  /* Error */
  public void zza(DisconnectRequest paramDisconnectRequest)
  {
    // Byte code:
    //   0: invokestatic 20	android/os/Parcel:obtain	()Landroid/os/Parcel;
    //   3: astore_2
    //   4: invokestatic 20	android/os/Parcel:obtain	()Landroid/os/Parcel;
    //   7: astore_3
    //   8: ldc 22
    //   10: astore 4
    //   12: aload_2
    //   13: aload 4
    //   15: invokevirtual 26	android/os/Parcel:writeInterfaceToken	(Ljava/lang/String;)V
    //   18: aload_1
    //   19: ifnull +60 -> 79
    //   22: iconst_1
    //   23: istore 5
    //   25: aload_2
    //   26: iload 5
    //   28: invokevirtual 31	android/os/Parcel:writeInt	(I)V
    //   31: iconst_0
    //   32: istore 5
    //   34: aconst_null
    //   35: astore 4
    //   37: aload_1
    //   38: aload_2
    //   39: iconst_0
    //   40: invokevirtual 156	com/google/android/gms/drive/internal/DisconnectRequest:writeToParcel	(Landroid/os/Parcel;I)V
    //   43: aload_0
    //   44: getfield 14	com/google/android/gms/drive/internal/zzam$zza$zza:zzoz	Landroid/os/IBinder;
    //   47: astore 4
    //   49: bipush 16
    //   51: istore 6
    //   53: aload 4
    //   55: iload 6
    //   57: aload_2
    //   58: aload_3
    //   59: iconst_0
    //   60: invokeinterface 44 5 0
    //   65: pop
    //   66: aload_3
    //   67: invokevirtual 47	android/os/Parcel:readException	()V
    //   70: aload_3
    //   71: invokevirtual 66	android/os/Parcel:recycle	()V
    //   74: aload_2
    //   75: invokevirtual 66	android/os/Parcel:recycle	()V
    //   78: return
    //   79: iconst_0
    //   80: istore 5
    //   82: aconst_null
    //   83: astore 4
    //   85: aload_2
    //   86: iconst_0
    //   87: invokevirtual 31	android/os/Parcel:writeInt	(I)V
    //   90: goto -47 -> 43
    //   93: astore 4
    //   95: aload_3
    //   96: invokevirtual 66	android/os/Parcel:recycle	()V
    //   99: aload_2
    //   100: invokevirtual 66	android/os/Parcel:recycle	()V
    //   103: aload 4
    //   105: athrow
    // Local variable table:
    //   start	length	slot	name	signature
    //   0	106	0	this	zza
    //   0	106	1	paramDisconnectRequest	DisconnectRequest
    //   3	97	2	localParcel1	Parcel
    //   7	89	3	localParcel2	Parcel
    //   10	74	4	localObject1	Object
    //   93	11	4	localObject2	Object
    //   23	58	5	i	int
    //   51	5	6	j	int
    // Exception table:
    //   from	to	target	type
    //   13	18	93	finally
    //   26	31	93	finally
    //   39	43	93	finally
    //   43	47	93	finally
    //   59	66	93	finally
    //   66	70	93	finally
    //   86	90	93	finally
  }
  
  public void zza(FetchThumbnailRequest paramFetchThumbnailRequest, zzan paramzzan)
  {
    Parcel localParcel1 = Parcel.obtain();
    Parcel localParcel2 = Parcel.obtain();
    Object localObject3;
    for (Object localObject1 = "com.google.android.gms.drive.internal.IDriveService";; localObject3 = null) {
      try
      {
        localParcel1.writeInterfaceToken((String)localObject1);
        if (paramFetchThumbnailRequest != null)
        {
          i = 1;
          localParcel1.writeInt(i);
          i = 0;
          localObject1 = null;
          paramFetchThumbnailRequest.writeToParcel(localParcel1, 0);
        }
        while (paramzzan != null)
        {
          localObject1 = paramzzan.asBinder();
          localParcel1.writeStrongBinder((IBinder)localObject1);
          localObject1 = this.zzoz;
          int j = 42;
          ((IBinder)localObject1).transact(j, localParcel1, localParcel2, 0);
          localParcel2.readException();
          return;
          i = 0;
          localObject1 = null;
          localParcel1.writeInt(0);
        }
        int i = 0;
      }
      finally
      {
        localParcel2.recycle();
        localParcel1.recycle();
      }
    }
  }
  
  public void zza(GetChangesRequest paramGetChangesRequest, zzan paramzzan)
  {
    Parcel localParcel1 = Parcel.obtain();
    Parcel localParcel2 = Parcel.obtain();
    Object localObject3;
    for (Object localObject1 = "com.google.android.gms.drive.internal.IDriveService";; localObject3 = null) {
      try
      {
        localParcel1.writeInterfaceToken((String)localObject1);
        if (paramGetChangesRequest != null)
        {
          i = 1;
          localParcel1.writeInt(i);
          i = 0;
          localObject1 = null;
          paramGetChangesRequest.writeToParcel(localParcel1, 0);
        }
        while (paramzzan != null)
        {
          localObject1 = paramzzan.asBinder();
          localParcel1.writeStrongBinder((IBinder)localObject1);
          localObject1 = this.zzoz;
          int j = 44;
          ((IBinder)localObject1).transact(j, localParcel1, localParcel2, 0);
          localParcel2.readException();
          return;
          i = 0;
          localObject1 = null;
          localParcel1.writeInt(0);
        }
        int i = 0;
      }
      finally
      {
        localParcel2.recycle();
        localParcel1.recycle();
      }
    }
  }
  
  public void zza(GetDriveIdFromUniqueIdentifierRequest paramGetDriveIdFromUniqueIdentifierRequest, zzan paramzzan)
  {
    Parcel localParcel1 = Parcel.obtain();
    Parcel localParcel2 = Parcel.obtain();
    Object localObject3;
    for (Object localObject1 = "com.google.android.gms.drive.internal.IDriveService";; localObject3 = null) {
      try
      {
        localParcel1.writeInterfaceToken((String)localObject1);
        if (paramGetDriveIdFromUniqueIdentifierRequest != null)
        {
          i = 1;
          localParcel1.writeInt(i);
          i = 0;
          localObject1 = null;
          paramGetDriveIdFromUniqueIdentifierRequest.writeToParcel(localParcel1, 0);
        }
        while (paramzzan != null)
        {
          localObject1 = paramzzan.asBinder();
          localParcel1.writeStrongBinder((IBinder)localObject1);
          localObject1 = this.zzoz;
          int j = 29;
          ((IBinder)localObject1).transact(j, localParcel1, localParcel2, 0);
          localParcel2.readException();
          return;
          i = 0;
          localObject1 = null;
          localParcel1.writeInt(0);
        }
        int i = 0;
      }
      finally
      {
        localParcel2.recycle();
        localParcel1.recycle();
      }
    }
  }
  
  public void zza(GetMetadataRequest paramGetMetadataRequest, zzan paramzzan)
  {
    Parcel localParcel1 = Parcel.obtain();
    Parcel localParcel2 = Parcel.obtain();
    Object localObject3;
    for (Object localObject1 = "com.google.android.gms.drive.internal.IDriveService";; localObject3 = null) {
      try
      {
        localParcel1.writeInterfaceToken((String)localObject1);
        if (paramGetMetadataRequest != null)
        {
          i = 1;
          localParcel1.writeInt(i);
          i = 0;
          localObject1 = null;
          paramGetMetadataRequest.writeToParcel(localParcel1, 0);
        }
        while (paramzzan != null)
        {
          localObject1 = paramzzan.asBinder();
          localParcel1.writeStrongBinder((IBinder)localObject1);
          localObject1 = this.zzoz;
          int j = 1;
          ((IBinder)localObject1).transact(j, localParcel1, localParcel2, 0);
          localParcel2.readException();
          return;
          i = 0;
          localObject1 = null;
          localParcel1.writeInt(0);
        }
        int i = 0;
      }
      finally
      {
        localParcel2.recycle();
        localParcel1.recycle();
      }
    }
  }
  
  public void zza(GetPermissionsRequest paramGetPermissionsRequest, zzan paramzzan)
  {
    Parcel localParcel1 = Parcel.obtain();
    Parcel localParcel2 = Parcel.obtain();
    Object localObject3;
    for (Object localObject1 = "com.google.android.gms.drive.internal.IDriveService";; localObject3 = null) {
      try
      {
        localParcel1.writeInterfaceToken((String)localObject1);
        if (paramGetPermissionsRequest != null)
        {
          i = 1;
          localParcel1.writeInt(i);
          i = 0;
          localObject1 = null;
          paramGetPermissionsRequest.writeToParcel(localParcel1, 0);
        }
        while (paramzzan != null)
        {
          localObject1 = paramzzan.asBinder();
          localParcel1.writeStrongBinder((IBinder)localObject1);
          localObject1 = this.zzoz;
          int j = 47;
          ((IBinder)localObject1).transact(j, localParcel1, localParcel2, 0);
          localParcel2.readException();
          return;
          i = 0;
          localObject1 = null;
          localParcel1.writeInt(0);
        }
        int i = 0;
      }
      finally
      {
        localParcel2.recycle();
        localParcel1.recycle();
      }
    }
  }
  
  public void zza(ListParentsRequest paramListParentsRequest, zzan paramzzan)
  {
    Parcel localParcel1 = Parcel.obtain();
    Parcel localParcel2 = Parcel.obtain();
    Object localObject3;
    for (Object localObject1 = "com.google.android.gms.drive.internal.IDriveService";; localObject3 = null) {
      try
      {
        localParcel1.writeInterfaceToken((String)localObject1);
        if (paramListParentsRequest != null)
        {
          i = 1;
          localParcel1.writeInt(i);
          i = 0;
          localObject1 = null;
          paramListParentsRequest.writeToParcel(localParcel1, 0);
        }
        while (paramzzan != null)
        {
          localObject1 = paramzzan.asBinder();
          localParcel1.writeStrongBinder((IBinder)localObject1);
          localObject1 = this.zzoz;
          int j = 13;
          ((IBinder)localObject1).transact(j, localParcel1, localParcel2, 0);
          localParcel2.readException();
          return;
          i = 0;
          localObject1 = null;
          localParcel1.writeInt(0);
        }
        int i = 0;
      }
      finally
      {
        localParcel2.recycle();
        localParcel1.recycle();
      }
    }
  }
  
  public void zza(LoadRealtimeRequest paramLoadRealtimeRequest, zzan paramzzan)
  {
    Parcel localParcel1 = Parcel.obtain();
    Parcel localParcel2 = Parcel.obtain();
    Object localObject3;
    for (Object localObject1 = "com.google.android.gms.drive.internal.IDriveService";; localObject3 = null) {
      try
      {
        localParcel1.writeInterfaceToken((String)localObject1);
        if (paramLoadRealtimeRequest != null)
        {
          i = 1;
          localParcel1.writeInt(i);
          i = 0;
          localObject1 = null;
          paramLoadRealtimeRequest.writeToParcel(localParcel1, 0);
        }
        while (paramzzan != null)
        {
          localObject1 = paramzzan.asBinder();
          localParcel1.writeStrongBinder((IBinder)localObject1);
          localObject1 = this.zzoz;
          int j = 27;
          ((IBinder)localObject1).transact(j, localParcel1, localParcel2, 0);
          localParcel2.readException();
          return;
          i = 0;
          localObject1 = null;
          localParcel1.writeInt(0);
        }
        int i = 0;
      }
      finally
      {
        localParcel2.recycle();
        localParcel1.recycle();
      }
    }
  }
  
  public void zza(QueryRequest paramQueryRequest, zzan paramzzan)
  {
    Parcel localParcel1 = Parcel.obtain();
    Parcel localParcel2 = Parcel.obtain();
    Object localObject3;
    for (Object localObject1 = "com.google.android.gms.drive.internal.IDriveService";; localObject3 = null) {
      try
      {
        localParcel1.writeInterfaceToken((String)localObject1);
        if (paramQueryRequest != null)
        {
          i = 1;
          localParcel1.writeInt(i);
          i = 0;
          localObject1 = null;
          paramQueryRequest.writeToParcel(localParcel1, 0);
        }
        while (paramzzan != null)
        {
          localObject1 = paramzzan.asBinder();
          localParcel1.writeStrongBinder((IBinder)localObject1);
          localObject1 = this.zzoz;
          int j = 2;
          ((IBinder)localObject1).transact(j, localParcel1, localParcel2, 0);
          localParcel2.readException();
          return;
          i = 0;
          localObject1 = null;
          localParcel1.writeInt(0);
        }
        int i = 0;
      }
      finally
      {
        localParcel2.recycle();
        localParcel1.recycle();
      }
    }
  }
  
  public void zza(QueryRequest paramQueryRequest, zzao paramzzao, zzan paramzzan)
  {
    IBinder localIBinder = null;
    Parcel localParcel1 = Parcel.obtain();
    Parcel localParcel2 = Parcel.obtain();
    for (Object localObject2 = "com.google.android.gms.drive.internal.IDriveService";; localObject2 = null) {
      try
      {
        localParcel1.writeInterfaceToken((String)localObject2);
        if (paramQueryRequest != null)
        {
          i = 1;
          localParcel1.writeInt(i);
          i = 0;
          localObject2 = null;
          paramQueryRequest.writeToParcel(localParcel1, 0);
        }
        while (paramzzao != null)
        {
          localObject2 = paramzzao.asBinder();
          localParcel1.writeStrongBinder((IBinder)localObject2);
          if (paramzzan != null) {
            localIBinder = paramzzan.asBinder();
          }
          localParcel1.writeStrongBinder(localIBinder);
          localIBinder = this.zzoz;
          i = 51;
          localIBinder.transact(i, localParcel1, localParcel2, 0);
          localParcel2.readException();
          return;
          i = 0;
          localObject2 = null;
          localParcel1.writeInt(0);
        }
        int i = 0;
      }
      finally
      {
        localParcel2.recycle();
        localParcel1.recycle();
      }
    }
  }
  
  public void zza(RemoveEventListenerRequest paramRemoveEventListenerRequest, zzao paramzzao, String paramString, zzan paramzzan)
  {
    IBinder localIBinder = null;
    Parcel localParcel1 = Parcel.obtain();
    Parcel localParcel2 = Parcel.obtain();
    for (Object localObject2 = "com.google.android.gms.drive.internal.IDriveService";; localObject2 = null) {
      try
      {
        localParcel1.writeInterfaceToken((String)localObject2);
        if (paramRemoveEventListenerRequest != null)
        {
          i = 1;
          localParcel1.writeInt(i);
          i = 0;
          localObject2 = null;
          paramRemoveEventListenerRequest.writeToParcel(localParcel1, 0);
        }
        while (paramzzao != null)
        {
          localObject2 = paramzzao.asBinder();
          localParcel1.writeStrongBinder((IBinder)localObject2);
          localParcel1.writeString(paramString);
          if (paramzzan != null) {
            localIBinder = paramzzan.asBinder();
          }
          localParcel1.writeStrongBinder(localIBinder);
          localIBinder = this.zzoz;
          i = 15;
          localIBinder.transact(i, localParcel1, localParcel2, 0);
          localParcel2.readException();
          return;
          i = 0;
          localObject2 = null;
          localParcel1.writeInt(0);
        }
        int i = 0;
      }
      finally
      {
        localParcel2.recycle();
        localParcel1.recycle();
      }
    }
  }
  
  public void zza(RemovePermissionRequest paramRemovePermissionRequest, zzan paramzzan)
  {
    Parcel localParcel1 = Parcel.obtain();
    Parcel localParcel2 = Parcel.obtain();
    Object localObject3;
    for (Object localObject1 = "com.google.android.gms.drive.internal.IDriveService";; localObject3 = null) {
      try
      {
        localParcel1.writeInterfaceToken((String)localObject1);
        if (paramRemovePermissionRequest != null)
        {
          i = 1;
          localParcel1.writeInt(i);
          i = 0;
          localObject1 = null;
          paramRemovePermissionRequest.writeToParcel(localParcel1, 0);
        }
        while (paramzzan != null)
        {
          localObject1 = paramzzan.asBinder();
          localParcel1.writeStrongBinder((IBinder)localObject1);
          localObject1 = this.zzoz;
          int j = 50;
          ((IBinder)localObject1).transact(j, localParcel1, localParcel2, 0);
          localParcel2.readException();
          return;
          i = 0;
          localObject1 = null;
          localParcel1.writeInt(0);
        }
        int i = 0;
      }
      finally
      {
        localParcel2.recycle();
        localParcel1.recycle();
      }
    }
  }
  
  public void zza(SetFileUploadPreferencesRequest paramSetFileUploadPreferencesRequest, zzan paramzzan)
  {
    Parcel localParcel1 = Parcel.obtain();
    Parcel localParcel2 = Parcel.obtain();
    Object localObject3;
    for (Object localObject1 = "com.google.android.gms.drive.internal.IDriveService";; localObject3 = null) {
      try
      {
        localParcel1.writeInterfaceToken((String)localObject1);
        if (paramSetFileUploadPreferencesRequest != null)
        {
          i = 1;
          localParcel1.writeInt(i);
          i = 0;
          localObject1 = null;
          paramSetFileUploadPreferencesRequest.writeToParcel(localParcel1, 0);
        }
        while (paramzzan != null)
        {
          localObject1 = paramzzan.asBinder();
          localParcel1.writeStrongBinder((IBinder)localObject1);
          localObject1 = this.zzoz;
          int j = 36;
          ((IBinder)localObject1).transact(j, localParcel1, localParcel2, 0);
          localParcel2.readException();
          return;
          i = 0;
          localObject1 = null;
          localParcel1.writeInt(0);
        }
        int i = 0;
      }
      finally
      {
        localParcel2.recycle();
        localParcel1.recycle();
      }
    }
  }
  
  public void zza(SetPinnedDownloadPreferencesRequest paramSetPinnedDownloadPreferencesRequest, zzan paramzzan)
  {
    Parcel localParcel1 = Parcel.obtain();
    Parcel localParcel2 = Parcel.obtain();
    Object localObject3;
    for (Object localObject1 = "com.google.android.gms.drive.internal.IDriveService";; localObject3 = null) {
      try
      {
        localParcel1.writeInterfaceToken((String)localObject1);
        if (paramSetPinnedDownloadPreferencesRequest != null)
        {
          i = 1;
          localParcel1.writeInt(i);
          i = 0;
          localObject1 = null;
          paramSetPinnedDownloadPreferencesRequest.writeToParcel(localParcel1, 0);
        }
        while (paramzzan != null)
        {
          localObject1 = paramzzan.asBinder();
          localParcel1.writeStrongBinder((IBinder)localObject1);
          localObject1 = this.zzoz;
          int j = 33;
          ((IBinder)localObject1).transact(j, localParcel1, localParcel2, 0);
          localParcel2.readException();
          return;
          i = 0;
          localObject1 = null;
          localParcel1.writeInt(0);
        }
        int i = 0;
      }
      finally
      {
        localParcel2.recycle();
        localParcel1.recycle();
      }
    }
  }
  
  public void zza(SetResourceParentsRequest paramSetResourceParentsRequest, zzan paramzzan)
  {
    Parcel localParcel1 = Parcel.obtain();
    Parcel localParcel2 = Parcel.obtain();
    Object localObject3;
    for (Object localObject1 = "com.google.android.gms.drive.internal.IDriveService";; localObject3 = null) {
      try
      {
        localParcel1.writeInterfaceToken((String)localObject1);
        if (paramSetResourceParentsRequest != null)
        {
          i = 1;
          localParcel1.writeInt(i);
          i = 0;
          localObject1 = null;
          paramSetResourceParentsRequest.writeToParcel(localParcel1, 0);
        }
        while (paramzzan != null)
        {
          localObject1 = paramzzan.asBinder();
          localParcel1.writeStrongBinder((IBinder)localObject1);
          localObject1 = this.zzoz;
          int j = 28;
          ((IBinder)localObject1).transact(j, localParcel1, localParcel2, 0);
          localParcel2.readException();
          return;
          i = 0;
          localObject1 = null;
          localParcel1.writeInt(0);
        }
        int i = 0;
      }
      finally
      {
        localParcel2.recycle();
        localParcel1.recycle();
      }
    }
  }
  
  public void zza(TrashResourceRequest paramTrashResourceRequest, zzan paramzzan)
  {
    Parcel localParcel1 = Parcel.obtain();
    Parcel localParcel2 = Parcel.obtain();
    Object localObject3;
    for (Object localObject1 = "com.google.android.gms.drive.internal.IDriveService";; localObject3 = null) {
      try
      {
        localParcel1.writeInterfaceToken((String)localObject1);
        if (paramTrashResourceRequest != null)
        {
          i = 1;
          localParcel1.writeInt(i);
          i = 0;
          localObject1 = null;
          paramTrashResourceRequest.writeToParcel(localParcel1, 0);
        }
        while (paramzzan != null)
        {
          localObject1 = paramzzan.asBinder();
          localParcel1.writeStrongBinder((IBinder)localObject1);
          localObject1 = this.zzoz;
          int j = 17;
          ((IBinder)localObject1).transact(j, localParcel1, localParcel2, 0);
          localParcel2.readException();
          return;
          i = 0;
          localObject1 = null;
          localParcel1.writeInt(0);
        }
        int i = 0;
      }
      finally
      {
        localParcel2.recycle();
        localParcel1.recycle();
      }
    }
  }
  
  public void zza(UnsubscribeResourceRequest paramUnsubscribeResourceRequest, zzan paramzzan)
  {
    Parcel localParcel1 = Parcel.obtain();
    Parcel localParcel2 = Parcel.obtain();
    Object localObject3;
    for (Object localObject1 = "com.google.android.gms.drive.internal.IDriveService";; localObject3 = null) {
      try
      {
        localParcel1.writeInterfaceToken((String)localObject1);
        if (paramUnsubscribeResourceRequest != null)
        {
          i = 1;
          localParcel1.writeInt(i);
          i = 0;
          localObject1 = null;
          paramUnsubscribeResourceRequest.writeToParcel(localParcel1, 0);
        }
        while (paramzzan != null)
        {
          localObject1 = paramzzan.asBinder();
          localParcel1.writeStrongBinder((IBinder)localObject1);
          localObject1 = this.zzoz;
          int j = 46;
          ((IBinder)localObject1).transact(j, localParcel1, localParcel2, 0);
          localParcel2.readException();
          return;
          i = 0;
          localObject1 = null;
          localParcel1.writeInt(0);
        }
        int i = 0;
      }
      finally
      {
        localParcel2.recycle();
        localParcel1.recycle();
      }
    }
  }
  
  public void zza(UntrashResourceRequest paramUntrashResourceRequest, zzan paramzzan)
  {
    Parcel localParcel1 = Parcel.obtain();
    Parcel localParcel2 = Parcel.obtain();
    Object localObject3;
    for (Object localObject1 = "com.google.android.gms.drive.internal.IDriveService";; localObject3 = null) {
      try
      {
        localParcel1.writeInterfaceToken((String)localObject1);
        if (paramUntrashResourceRequest != null)
        {
          i = 1;
          localParcel1.writeInt(i);
          i = 0;
          localObject1 = null;
          paramUntrashResourceRequest.writeToParcel(localParcel1, 0);
        }
        while (paramzzan != null)
        {
          localObject1 = paramzzan.asBinder();
          localParcel1.writeStrongBinder((IBinder)localObject1);
          localObject1 = this.zzoz;
          int j = 38;
          ((IBinder)localObject1).transact(j, localParcel1, localParcel2, 0);
          localParcel2.readException();
          return;
          i = 0;
          localObject1 = null;
          localParcel1.writeInt(0);
        }
        int i = 0;
      }
      finally
      {
        localParcel2.recycle();
        localParcel1.recycle();
      }
    }
  }
  
  public void zza(UpdateMetadataRequest paramUpdateMetadataRequest, zzan paramzzan)
  {
    Parcel localParcel1 = Parcel.obtain();
    Parcel localParcel2 = Parcel.obtain();
    Object localObject3;
    for (Object localObject1 = "com.google.android.gms.drive.internal.IDriveService";; localObject3 = null) {
      try
      {
        localParcel1.writeInterfaceToken((String)localObject1);
        if (paramUpdateMetadataRequest != null)
        {
          i = 1;
          localParcel1.writeInt(i);
          i = 0;
          localObject1 = null;
          paramUpdateMetadataRequest.writeToParcel(localParcel1, 0);
        }
        while (paramzzan != null)
        {
          localObject1 = paramzzan.asBinder();
          localParcel1.writeStrongBinder((IBinder)localObject1);
          localObject1 = this.zzoz;
          int j = 3;
          ((IBinder)localObject1).transact(j, localParcel1, localParcel2, 0);
          localParcel2.readException();
          return;
          i = 0;
          localObject1 = null;
          localParcel1.writeInt(0);
        }
        int i = 0;
      }
      finally
      {
        localParcel2.recycle();
        localParcel1.recycle();
      }
    }
  }
  
  public void zza(UpdatePermissionRequest paramUpdatePermissionRequest, zzan paramzzan)
  {
    Parcel localParcel1 = Parcel.obtain();
    Parcel localParcel2 = Parcel.obtain();
    Object localObject3;
    for (Object localObject1 = "com.google.android.gms.drive.internal.IDriveService";; localObject3 = null) {
      try
      {
        localParcel1.writeInterfaceToken((String)localObject1);
        if (paramUpdatePermissionRequest != null)
        {
          i = 1;
          localParcel1.writeInt(i);
          i = 0;
          localObject1 = null;
          paramUpdatePermissionRequest.writeToParcel(localParcel1, 0);
        }
        while (paramzzan != null)
        {
          localObject1 = paramzzan.asBinder();
          localParcel1.writeStrongBinder((IBinder)localObject1);
          localObject1 = this.zzoz;
          int j = 49;
          ((IBinder)localObject1).transact(j, localParcel1, localParcel2, 0);
          localParcel2.readException();
          return;
          i = 0;
          localObject1 = null;
          localParcel1.writeInt(0);
        }
        int i = 0;
      }
      finally
      {
        localParcel2.recycle();
        localParcel1.recycle();
      }
    }
  }
  
  /* Error */
  public void zza(zzan paramzzan)
  {
    // Byte code:
    //   0: invokestatic 20	android/os/Parcel:obtain	()Landroid/os/Parcel;
    //   3: astore_2
    //   4: invokestatic 20	android/os/Parcel:obtain	()Landroid/os/Parcel;
    //   7: astore_3
    //   8: ldc 22
    //   10: astore 4
    //   12: aload_2
    //   13: aload 4
    //   15: invokevirtual 26	android/os/Parcel:writeInterfaceToken	(Ljava/lang/String;)V
    //   18: aload_1
    //   19: ifnull +53 -> 72
    //   22: aload_1
    //   23: invokeinterface 79 1 0
    //   28: astore 4
    //   30: aload_2
    //   31: aload 4
    //   33: invokevirtual 83	android/os/Parcel:writeStrongBinder	(Landroid/os/IBinder;)V
    //   36: aload_0
    //   37: getfield 14	com/google/android/gms/drive/internal/zzam$zza$zza:zzoz	Landroid/os/IBinder;
    //   40: astore 4
    //   42: bipush 9
    //   44: istore 5
    //   46: aload 4
    //   48: iload 5
    //   50: aload_2
    //   51: aload_3
    //   52: iconst_0
    //   53: invokeinterface 44 5 0
    //   58: pop
    //   59: aload_3
    //   60: invokevirtual 47	android/os/Parcel:readException	()V
    //   63: aload_3
    //   64: invokevirtual 66	android/os/Parcel:recycle	()V
    //   67: aload_2
    //   68: invokevirtual 66	android/os/Parcel:recycle	()V
    //   71: return
    //   72: aconst_null
    //   73: astore 4
    //   75: goto -45 -> 30
    //   78: astore 4
    //   80: aload_3
    //   81: invokevirtual 66	android/os/Parcel:recycle	()V
    //   84: aload_2
    //   85: invokevirtual 66	android/os/Parcel:recycle	()V
    //   88: aload 4
    //   90: athrow
    // Local variable table:
    //   start	length	slot	name	signature
    //   0	91	0	this	zza
    //   0	91	1	paramzzan	zzan
    //   3	82	2	localParcel1	Parcel
    //   7	74	3	localParcel2	Parcel
    //   10	64	4	localObject1	Object
    //   78	11	4	localObject2	Object
    //   44	5	5	i	int
    // Exception table:
    //   from	to	target	type
    //   13	18	78	finally
    //   22	28	78	finally
    //   31	36	78	finally
    //   36	40	78	finally
    //   52	59	78	finally
    //   59	63	78	finally
  }
  
  /* Error */
  public void zza(zzao paramzzao, zzan paramzzan)
  {
    // Byte code:
    //   0: aconst_null
    //   1: astore_3
    //   2: invokestatic 20	android/os/Parcel:obtain	()Landroid/os/Parcel;
    //   5: astore 4
    //   7: invokestatic 20	android/os/Parcel:obtain	()Landroid/os/Parcel;
    //   10: astore 5
    //   12: ldc 22
    //   14: astore 6
    //   16: aload 4
    //   18: aload 6
    //   20: invokevirtual 26	android/os/Parcel:writeInterfaceToken	(Ljava/lang/String;)V
    //   23: aload_1
    //   24: ifnull +74 -> 98
    //   27: aload_1
    //   28: invokeinterface 101 1 0
    //   33: astore 6
    //   35: aload 4
    //   37: aload 6
    //   39: invokevirtual 83	android/os/Parcel:writeStrongBinder	(Landroid/os/IBinder;)V
    //   42: aload_2
    //   43: ifnull +10 -> 53
    //   46: aload_2
    //   47: invokeinterface 79 1 0
    //   52: astore_3
    //   53: aload 4
    //   55: aload_3
    //   56: invokevirtual 83	android/os/Parcel:writeStrongBinder	(Landroid/os/IBinder;)V
    //   59: aload_0
    //   60: getfield 14	com/google/android/gms/drive/internal/zzam$zza$zza:zzoz	Landroid/os/IBinder;
    //   63: astore_3
    //   64: bipush 52
    //   66: istore 7
    //   68: aload_3
    //   69: iload 7
    //   71: aload 4
    //   73: aload 5
    //   75: iconst_0
    //   76: invokeinterface 44 5 0
    //   81: pop
    //   82: aload 5
    //   84: invokevirtual 47	android/os/Parcel:readException	()V
    //   87: aload 5
    //   89: invokevirtual 66	android/os/Parcel:recycle	()V
    //   92: aload 4
    //   94: invokevirtual 66	android/os/Parcel:recycle	()V
    //   97: return
    //   98: iconst_0
    //   99: istore 7
    //   101: aconst_null
    //   102: astore 6
    //   104: goto -69 -> 35
    //   107: astore_3
    //   108: aload 5
    //   110: invokevirtual 66	android/os/Parcel:recycle	()V
    //   113: aload 4
    //   115: invokevirtual 66	android/os/Parcel:recycle	()V
    //   118: aload_3
    //   119: athrow
    // Local variable table:
    //   start	length	slot	name	signature
    //   0	120	0	this	zza
    //   0	120	1	paramzzao	zzao
    //   0	120	2	paramzzan	zzan
    //   1	68	3	localIBinder	IBinder
    //   107	12	3	localObject1	Object
    //   5	109	4	localParcel1	Parcel
    //   10	99	5	localParcel2	Parcel
    //   14	89	6	localObject2	Object
    //   66	34	7	i	int
    // Exception table:
    //   from	to	target	type
    //   18	23	107	finally
    //   27	33	107	finally
    //   37	42	107	finally
    //   46	52	107	finally
    //   55	59	107	finally
    //   59	63	107	finally
    //   75	82	107	finally
    //   82	87	107	finally
  }
  
  public void zzb(QueryRequest paramQueryRequest, zzan paramzzan)
  {
    Parcel localParcel1 = Parcel.obtain();
    Parcel localParcel2 = Parcel.obtain();
    Object localObject3;
    for (Object localObject1 = "com.google.android.gms.drive.internal.IDriveService";; localObject3 = null) {
      try
      {
        localParcel1.writeInterfaceToken((String)localObject1);
        if (paramQueryRequest != null)
        {
          i = 1;
          localParcel1.writeInt(i);
          i = 0;
          localObject1 = null;
          paramQueryRequest.writeToParcel(localParcel1, 0);
        }
        while (paramzzan != null)
        {
          localObject1 = paramzzan.asBinder();
          localParcel1.writeStrongBinder((IBinder)localObject1);
          localObject1 = this.zzoz;
          int j = 19;
          ((IBinder)localObject1).transact(j, localParcel1, localParcel2, 0);
          localParcel2.readException();
          return;
          i = 0;
          localObject1 = null;
          localParcel1.writeInt(0);
        }
        int i = 0;
      }
      finally
      {
        localParcel2.recycle();
        localParcel1.recycle();
      }
    }
  }
  
  /* Error */
  public void zzb(zzan paramzzan)
  {
    // Byte code:
    //   0: invokestatic 20	android/os/Parcel:obtain	()Landroid/os/Parcel;
    //   3: astore_2
    //   4: invokestatic 20	android/os/Parcel:obtain	()Landroid/os/Parcel;
    //   7: astore_3
    //   8: ldc 22
    //   10: astore 4
    //   12: aload_2
    //   13: aload 4
    //   15: invokevirtual 26	android/os/Parcel:writeInterfaceToken	(Ljava/lang/String;)V
    //   18: aload_1
    //   19: ifnull +53 -> 72
    //   22: aload_1
    //   23: invokeinterface 79 1 0
    //   28: astore 4
    //   30: aload_2
    //   31: aload 4
    //   33: invokevirtual 83	android/os/Parcel:writeStrongBinder	(Landroid/os/IBinder;)V
    //   36: aload_0
    //   37: getfield 14	com/google/android/gms/drive/internal/zzam$zza$zza:zzoz	Landroid/os/IBinder;
    //   40: astore 4
    //   42: bipush 31
    //   44: istore 5
    //   46: aload 4
    //   48: iload 5
    //   50: aload_2
    //   51: aload_3
    //   52: iconst_0
    //   53: invokeinterface 44 5 0
    //   58: pop
    //   59: aload_3
    //   60: invokevirtual 47	android/os/Parcel:readException	()V
    //   63: aload_3
    //   64: invokevirtual 66	android/os/Parcel:recycle	()V
    //   67: aload_2
    //   68: invokevirtual 66	android/os/Parcel:recycle	()V
    //   71: return
    //   72: aconst_null
    //   73: astore 4
    //   75: goto -45 -> 30
    //   78: astore 4
    //   80: aload_3
    //   81: invokevirtual 66	android/os/Parcel:recycle	()V
    //   84: aload_2
    //   85: invokevirtual 66	android/os/Parcel:recycle	()V
    //   88: aload 4
    //   90: athrow
    // Local variable table:
    //   start	length	slot	name	signature
    //   0	91	0	this	zza
    //   0	91	1	paramzzan	zzan
    //   3	82	2	localParcel1	Parcel
    //   7	74	3	localParcel2	Parcel
    //   10	64	4	localObject1	Object
    //   78	11	4	localObject2	Object
    //   44	5	5	i	int
    // Exception table:
    //   from	to	target	type
    //   13	18	78	finally
    //   22	28	78	finally
    //   31	36	78	finally
    //   36	40	78	finally
    //   52	59	78	finally
    //   59	63	78	finally
  }
  
  /* Error */
  public void zzc(zzan paramzzan)
  {
    // Byte code:
    //   0: invokestatic 20	android/os/Parcel:obtain	()Landroid/os/Parcel;
    //   3: astore_2
    //   4: invokestatic 20	android/os/Parcel:obtain	()Landroid/os/Parcel;
    //   7: astore_3
    //   8: ldc 22
    //   10: astore 4
    //   12: aload_2
    //   13: aload 4
    //   15: invokevirtual 26	android/os/Parcel:writeInterfaceToken	(Ljava/lang/String;)V
    //   18: aload_1
    //   19: ifnull +53 -> 72
    //   22: aload_1
    //   23: invokeinterface 79 1 0
    //   28: astore 4
    //   30: aload_2
    //   31: aload 4
    //   33: invokevirtual 83	android/os/Parcel:writeStrongBinder	(Landroid/os/IBinder;)V
    //   36: aload_0
    //   37: getfield 14	com/google/android/gms/drive/internal/zzam$zza$zza:zzoz	Landroid/os/IBinder;
    //   40: astore 4
    //   42: bipush 32
    //   44: istore 5
    //   46: aload 4
    //   48: iload 5
    //   50: aload_2
    //   51: aload_3
    //   52: iconst_0
    //   53: invokeinterface 44 5 0
    //   58: pop
    //   59: aload_3
    //   60: invokevirtual 47	android/os/Parcel:readException	()V
    //   63: aload_3
    //   64: invokevirtual 66	android/os/Parcel:recycle	()V
    //   67: aload_2
    //   68: invokevirtual 66	android/os/Parcel:recycle	()V
    //   71: return
    //   72: aconst_null
    //   73: astore 4
    //   75: goto -45 -> 30
    //   78: astore 4
    //   80: aload_3
    //   81: invokevirtual 66	android/os/Parcel:recycle	()V
    //   84: aload_2
    //   85: invokevirtual 66	android/os/Parcel:recycle	()V
    //   88: aload 4
    //   90: athrow
    // Local variable table:
    //   start	length	slot	name	signature
    //   0	91	0	this	zza
    //   0	91	1	paramzzan	zzan
    //   3	82	2	localParcel1	Parcel
    //   7	74	3	localParcel2	Parcel
    //   10	64	4	localObject1	Object
    //   78	11	4	localObject2	Object
    //   44	5	5	i	int
    // Exception table:
    //   from	to	target	type
    //   13	18	78	finally
    //   22	28	78	finally
    //   31	36	78	finally
    //   36	40	78	finally
    //   52	59	78	finally
    //   59	63	78	finally
  }
  
  /* Error */
  public void zzd(zzan paramzzan)
  {
    // Byte code:
    //   0: invokestatic 20	android/os/Parcel:obtain	()Landroid/os/Parcel;
    //   3: astore_2
    //   4: invokestatic 20	android/os/Parcel:obtain	()Landroid/os/Parcel;
    //   7: astore_3
    //   8: ldc 22
    //   10: astore 4
    //   12: aload_2
    //   13: aload 4
    //   15: invokevirtual 26	android/os/Parcel:writeInterfaceToken	(Ljava/lang/String;)V
    //   18: aload_1
    //   19: ifnull +53 -> 72
    //   22: aload_1
    //   23: invokeinterface 79 1 0
    //   28: astore 4
    //   30: aload_2
    //   31: aload 4
    //   33: invokevirtual 83	android/os/Parcel:writeStrongBinder	(Landroid/os/IBinder;)V
    //   36: aload_0
    //   37: getfield 14	com/google/android/gms/drive/internal/zzam$zza$zza:zzoz	Landroid/os/IBinder;
    //   40: astore 4
    //   42: bipush 35
    //   44: istore 5
    //   46: aload 4
    //   48: iload 5
    //   50: aload_2
    //   51: aload_3
    //   52: iconst_0
    //   53: invokeinterface 44 5 0
    //   58: pop
    //   59: aload_3
    //   60: invokevirtual 47	android/os/Parcel:readException	()V
    //   63: aload_3
    //   64: invokevirtual 66	android/os/Parcel:recycle	()V
    //   67: aload_2
    //   68: invokevirtual 66	android/os/Parcel:recycle	()V
    //   71: return
    //   72: aconst_null
    //   73: astore 4
    //   75: goto -45 -> 30
    //   78: astore 4
    //   80: aload_3
    //   81: invokevirtual 66	android/os/Parcel:recycle	()V
    //   84: aload_2
    //   85: invokevirtual 66	android/os/Parcel:recycle	()V
    //   88: aload 4
    //   90: athrow
    // Local variable table:
    //   start	length	slot	name	signature
    //   0	91	0	this	zza
    //   0	91	1	paramzzan	zzan
    //   3	82	2	localParcel1	Parcel
    //   7	74	3	localParcel2	Parcel
    //   10	64	4	localObject1	Object
    //   78	11	4	localObject2	Object
    //   44	5	5	i	int
    // Exception table:
    //   from	to	target	type
    //   13	18	78	finally
    //   22	28	78	finally
    //   31	36	78	finally
    //   36	40	78	finally
    //   52	59	78	finally
    //   59	63	78	finally
  }
  
  /* Error */
  public void zze(zzan paramzzan)
  {
    // Byte code:
    //   0: invokestatic 20	android/os/Parcel:obtain	()Landroid/os/Parcel;
    //   3: astore_2
    //   4: invokestatic 20	android/os/Parcel:obtain	()Landroid/os/Parcel;
    //   7: astore_3
    //   8: ldc 22
    //   10: astore 4
    //   12: aload_2
    //   13: aload 4
    //   15: invokevirtual 26	android/os/Parcel:writeInterfaceToken	(Ljava/lang/String;)V
    //   18: aload_1
    //   19: ifnull +53 -> 72
    //   22: aload_1
    //   23: invokeinterface 79 1 0
    //   28: astore 4
    //   30: aload_2
    //   31: aload 4
    //   33: invokevirtual 83	android/os/Parcel:writeStrongBinder	(Landroid/os/IBinder;)V
    //   36: aload_0
    //   37: getfield 14	com/google/android/gms/drive/internal/zzam$zza$zza:zzoz	Landroid/os/IBinder;
    //   40: astore 4
    //   42: bipush 41
    //   44: istore 5
    //   46: aload 4
    //   48: iload 5
    //   50: aload_2
    //   51: aload_3
    //   52: iconst_0
    //   53: invokeinterface 44 5 0
    //   58: pop
    //   59: aload_3
    //   60: invokevirtual 47	android/os/Parcel:readException	()V
    //   63: aload_3
    //   64: invokevirtual 66	android/os/Parcel:recycle	()V
    //   67: aload_2
    //   68: invokevirtual 66	android/os/Parcel:recycle	()V
    //   71: return
    //   72: aconst_null
    //   73: astore 4
    //   75: goto -45 -> 30
    //   78: astore 4
    //   80: aload_3
    //   81: invokevirtual 66	android/os/Parcel:recycle	()V
    //   84: aload_2
    //   85: invokevirtual 66	android/os/Parcel:recycle	()V
    //   88: aload 4
    //   90: athrow
    // Local variable table:
    //   start	length	slot	name	signature
    //   0	91	0	this	zza
    //   0	91	1	paramzzan	zzan
    //   3	82	2	localParcel1	Parcel
    //   7	74	3	localParcel2	Parcel
    //   10	64	4	localObject1	Object
    //   78	11	4	localObject2	Object
    //   44	5	5	i	int
    // Exception table:
    //   from	to	target	type
    //   13	18	78	finally
    //   22	28	78	finally
    //   31	36	78	finally
    //   36	40	78	finally
    //   52	59	78	finally
    //   59	63	78	finally
  }
  
  /* Error */
  public void zzf(zzan paramzzan)
  {
    // Byte code:
    //   0: invokestatic 20	android/os/Parcel:obtain	()Landroid/os/Parcel;
    //   3: astore_2
    //   4: invokestatic 20	android/os/Parcel:obtain	()Landroid/os/Parcel;
    //   7: astore_3
    //   8: ldc 22
    //   10: astore 4
    //   12: aload_2
    //   13: aload 4
    //   15: invokevirtual 26	android/os/Parcel:writeInterfaceToken	(Ljava/lang/String;)V
    //   18: aload_1
    //   19: ifnull +53 -> 72
    //   22: aload_1
    //   23: invokeinterface 79 1 0
    //   28: astore 4
    //   30: aload_2
    //   31: aload 4
    //   33: invokevirtual 83	android/os/Parcel:writeStrongBinder	(Landroid/os/IBinder;)V
    //   36: aload_0
    //   37: getfield 14	com/google/android/gms/drive/internal/zzam$zza$zza:zzoz	Landroid/os/IBinder;
    //   40: astore 4
    //   42: bipush 43
    //   44: istore 5
    //   46: aload 4
    //   48: iload 5
    //   50: aload_2
    //   51: aload_3
    //   52: iconst_0
    //   53: invokeinterface 44 5 0
    //   58: pop
    //   59: aload_3
    //   60: invokevirtual 47	android/os/Parcel:readException	()V
    //   63: aload_3
    //   64: invokevirtual 66	android/os/Parcel:recycle	()V
    //   67: aload_2
    //   68: invokevirtual 66	android/os/Parcel:recycle	()V
    //   71: return
    //   72: aconst_null
    //   73: astore 4
    //   75: goto -45 -> 30
    //   78: astore 4
    //   80: aload_3
    //   81: invokevirtual 66	android/os/Parcel:recycle	()V
    //   84: aload_2
    //   85: invokevirtual 66	android/os/Parcel:recycle	()V
    //   88: aload 4
    //   90: athrow
    // Local variable table:
    //   start	length	slot	name	signature
    //   0	91	0	this	zza
    //   0	91	1	paramzzan	zzan
    //   3	82	2	localParcel1	Parcel
    //   7	74	3	localParcel2	Parcel
    //   10	64	4	localObject1	Object
    //   78	11	4	localObject2	Object
    //   44	5	5	i	int
    // Exception table:
    //   from	to	target	type
    //   13	18	78	finally
    //   22	28	78	finally
    //   31	36	78	finally
    //   36	40	78	finally
    //   52	59	78	finally
    //   59	63	78	finally
  }
  
  /* Error */
  public void zzg(zzan paramzzan)
  {
    // Byte code:
    //   0: invokestatic 20	android/os/Parcel:obtain	()Landroid/os/Parcel;
    //   3: astore_2
    //   4: invokestatic 20	android/os/Parcel:obtain	()Landroid/os/Parcel;
    //   7: astore_3
    //   8: ldc 22
    //   10: astore 4
    //   12: aload_2
    //   13: aload 4
    //   15: invokevirtual 26	android/os/Parcel:writeInterfaceToken	(Ljava/lang/String;)V
    //   18: aload_1
    //   19: ifnull +53 -> 72
    //   22: aload_1
    //   23: invokeinterface 79 1 0
    //   28: astore 4
    //   30: aload_2
    //   31: aload 4
    //   33: invokevirtual 83	android/os/Parcel:writeStrongBinder	(Landroid/os/IBinder;)V
    //   36: aload_0
    //   37: getfield 14	com/google/android/gms/drive/internal/zzam$zza$zza:zzoz	Landroid/os/IBinder;
    //   40: astore 4
    //   42: bipush 54
    //   44: istore 5
    //   46: aload 4
    //   48: iload 5
    //   50: aload_2
    //   51: aload_3
    //   52: iconst_0
    //   53: invokeinterface 44 5 0
    //   58: pop
    //   59: aload_3
    //   60: invokevirtual 47	android/os/Parcel:readException	()V
    //   63: aload_3
    //   64: invokevirtual 66	android/os/Parcel:recycle	()V
    //   67: aload_2
    //   68: invokevirtual 66	android/os/Parcel:recycle	()V
    //   71: return
    //   72: aconst_null
    //   73: astore 4
    //   75: goto -45 -> 30
    //   78: astore 4
    //   80: aload_3
    //   81: invokevirtual 66	android/os/Parcel:recycle	()V
    //   84: aload_2
    //   85: invokevirtual 66	android/os/Parcel:recycle	()V
    //   88: aload 4
    //   90: athrow
    // Local variable table:
    //   start	length	slot	name	signature
    //   0	91	0	this	zza
    //   0	91	1	paramzzan	zzan
    //   3	82	2	localParcel1	Parcel
    //   7	74	3	localParcel2	Parcel
    //   10	64	4	localObject1	Object
    //   78	11	4	localObject2	Object
    //   44	5	5	i	int
    // Exception table:
    //   from	to	target	type
    //   13	18	78	finally
    //   22	28	78	finally
    //   31	36	78	finally
    //   36	40	78	finally
    //   52	59	78	finally
    //   59	63	78	finally
  }
  
  /* Error */
  public void zzh(zzan paramzzan)
  {
    // Byte code:
    //   0: invokestatic 20	android/os/Parcel:obtain	()Landroid/os/Parcel;
    //   3: astore_2
    //   4: invokestatic 20	android/os/Parcel:obtain	()Landroid/os/Parcel;
    //   7: astore_3
    //   8: ldc 22
    //   10: astore 4
    //   12: aload_2
    //   13: aload 4
    //   15: invokevirtual 26	android/os/Parcel:writeInterfaceToken	(Ljava/lang/String;)V
    //   18: aload_1
    //   19: ifnull +53 -> 72
    //   22: aload_1
    //   23: invokeinterface 79 1 0
    //   28: astore 4
    //   30: aload_2
    //   31: aload 4
    //   33: invokevirtual 83	android/os/Parcel:writeStrongBinder	(Landroid/os/IBinder;)V
    //   36: aload_0
    //   37: getfield 14	com/google/android/gms/drive/internal/zzam$zza$zza:zzoz	Landroid/os/IBinder;
    //   40: astore 4
    //   42: bipush 57
    //   44: istore 5
    //   46: aload 4
    //   48: iload 5
    //   50: aload_2
    //   51: aload_3
    //   52: iconst_0
    //   53: invokeinterface 44 5 0
    //   58: pop
    //   59: aload_3
    //   60: invokevirtual 47	android/os/Parcel:readException	()V
    //   63: aload_3
    //   64: invokevirtual 66	android/os/Parcel:recycle	()V
    //   67: aload_2
    //   68: invokevirtual 66	android/os/Parcel:recycle	()V
    //   71: return
    //   72: aconst_null
    //   73: astore 4
    //   75: goto -45 -> 30
    //   78: astore 4
    //   80: aload_3
    //   81: invokevirtual 66	android/os/Parcel:recycle	()V
    //   84: aload_2
    //   85: invokevirtual 66	android/os/Parcel:recycle	()V
    //   88: aload 4
    //   90: athrow
    // Local variable table:
    //   start	length	slot	name	signature
    //   0	91	0	this	zza
    //   0	91	1	paramzzan	zzan
    //   3	82	2	localParcel1	Parcel
    //   7	74	3	localParcel2	Parcel
    //   10	64	4	localObject1	Object
    //   78	11	4	localObject2	Object
    //   44	5	5	i	int
    // Exception table:
    //   from	to	target	type
    //   13	18	78	finally
    //   22	28	78	finally
    //   31	36	78	finally
    //   36	40	78	finally
    //   52	59	78	finally
    //   59	63	78	finally
  }
}


/* Location:              C:\Users\haryo\Desktop\enjarify-master\presensi-enjarify.jar!\com\google\android\gms\drive\internal\zzam$zza$zza.class
 * Java compiler version: 5 (49.0)
 * JD-Core Version:       0.7.1
 */