package com.google.android.gms.plus.internal;

import android.net.Uri;
import android.os.Bundle;
import android.os.IBinder;
import android.os.Parcel;
import com.google.android.gms.common.server.FavaDiagnosticsEntity;

class zzd$zza$zza
  implements zzd
{
  private IBinder zzoz;
  
  zzd$zza$zza(IBinder paramIBinder)
  {
    this.zzoz = paramIBinder;
  }
  
  public IBinder asBinder()
  {
    return this.zzoz;
  }
  
  public String getAccountName()
  {
    Parcel localParcel1 = Parcel.obtain();
    Parcel localParcel2 = Parcel.obtain();
    Object localObject1 = "com.google.android.gms.plus.internal.IPlusService";
    try
    {
      localParcel1.writeInterfaceToken((String)localObject1);
      localObject1 = this.zzoz;
      int i = 5;
      ((IBinder)localObject1).transact(i, localParcel1, localParcel2, 0);
      localParcel2.readException();
      localObject1 = localParcel2.readString();
      return (String)localObject1;
    }
    finally
    {
      localParcel2.recycle();
      localParcel1.recycle();
    }
  }
  
  public String getAuthCode()
  {
    Parcel localParcel1 = Parcel.obtain();
    Parcel localParcel2 = Parcel.obtain();
    Object localObject1 = "com.google.android.gms.plus.internal.IPlusService";
    try
    {
      localParcel1.writeInterfaceToken((String)localObject1);
      localObject1 = this.zzoz;
      int i = 41;
      ((IBinder)localObject1).transact(i, localParcel1, localParcel2, 0);
      localParcel2.readException();
      localObject1 = localParcel2.readString();
      return (String)localObject1;
    }
    finally
    {
      localParcel2.recycle();
      localParcel1.recycle();
    }
  }
  
  public void zzEY()
  {
    Parcel localParcel1 = Parcel.obtain();
    Parcel localParcel2 = Parcel.obtain();
    Object localObject1 = "com.google.android.gms.plus.internal.IPlusService";
    try
    {
      localParcel1.writeInterfaceToken((String)localObject1);
      localObject1 = this.zzoz;
      int i = 6;
      ((IBinder)localObject1).transact(i, localParcel1, localParcel2, 0);
      localParcel2.readException();
      return;
    }
    finally
    {
      localParcel2.recycle();
      localParcel1.recycle();
    }
  }
  
  public boolean zzEZ()
  {
    boolean bool = false;
    Object localObject1 = null;
    Parcel localParcel1 = Parcel.obtain();
    Parcel localParcel2 = Parcel.obtain();
    Object localObject3 = "com.google.android.gms.plus.internal.IPlusService";
    try
    {
      localParcel1.writeInterfaceToken((String)localObject3);
      localObject3 = this.zzoz;
      int i = 42;
      ((IBinder)localObject3).transact(i, localParcel1, localParcel2, 0);
      localParcel2.readException();
      int j = localParcel2.readInt();
      if (j != 0) {
        bool = true;
      }
      return bool;
    }
    finally
    {
      localParcel2.recycle();
      localParcel1.recycle();
    }
  }
  
  /* Error */
  public com.google.android.gms.common.internal.zzq zza(zzb paramzzb, int paramInt1, int paramInt2, int paramInt3, String paramString)
  {
    // Byte code:
    //   0: invokestatic 20	android/os/Parcel:obtain	()Landroid/os/Parcel;
    //   3: astore 6
    //   5: invokestatic 20	android/os/Parcel:obtain	()Landroid/os/Parcel;
    //   8: astore 7
    //   10: ldc 22
    //   12: astore 8
    //   14: aload 6
    //   16: aload 8
    //   18: invokevirtual 26	android/os/Parcel:writeInterfaceToken	(Ljava/lang/String;)V
    //   21: aload_1
    //   22: ifnull +101 -> 123
    //   25: aload_1
    //   26: invokeinterface 57 1 0
    //   31: astore 8
    //   33: aload 6
    //   35: aload 8
    //   37: invokevirtual 61	android/os/Parcel:writeStrongBinder	(Landroid/os/IBinder;)V
    //   40: aload 6
    //   42: iload_2
    //   43: invokevirtual 65	android/os/Parcel:writeInt	(I)V
    //   46: aload 6
    //   48: iload_3
    //   49: invokevirtual 65	android/os/Parcel:writeInt	(I)V
    //   52: aload 6
    //   54: iload 4
    //   56: invokevirtual 65	android/os/Parcel:writeInt	(I)V
    //   59: aload 6
    //   61: aload 5
    //   63: invokevirtual 68	android/os/Parcel:writeString	(Ljava/lang/String;)V
    //   66: aload_0
    //   67: getfield 14	com/google/android/gms/plus/internal/zzd$zza$zza:zzoz	Landroid/os/IBinder;
    //   70: astore 8
    //   72: bipush 16
    //   74: istore 9
    //   76: aload 8
    //   78: iload 9
    //   80: aload 6
    //   82: aload 7
    //   84: iconst_0
    //   85: invokeinterface 33 5 0
    //   90: pop
    //   91: aload 7
    //   93: invokevirtual 36	android/os/Parcel:readException	()V
    //   96: aload 7
    //   98: invokevirtual 72	android/os/Parcel:readStrongBinder	()Landroid/os/IBinder;
    //   101: astore 8
    //   103: aload 8
    //   105: invokestatic 78	com/google/android/gms/common/internal/zzq$zza:zzaQ	(Landroid/os/IBinder;)Lcom/google/android/gms/common/internal/zzq;
    //   108: astore 8
    //   110: aload 7
    //   112: invokevirtual 43	android/os/Parcel:recycle	()V
    //   115: aload 6
    //   117: invokevirtual 43	android/os/Parcel:recycle	()V
    //   120: aload 8
    //   122: areturn
    //   123: aconst_null
    //   124: astore 8
    //   126: goto -93 -> 33
    //   129: astore 8
    //   131: aload 7
    //   133: invokevirtual 43	android/os/Parcel:recycle	()V
    //   136: aload 6
    //   138: invokevirtual 43	android/os/Parcel:recycle	()V
    //   141: aload 8
    //   143: athrow
    // Local variable table:
    //   start	length	slot	name	signature
    //   0	144	0	this	zza
    //   0	144	1	paramzzb	zzb
    //   0	144	2	paramInt1	int
    //   0	144	3	paramInt2	int
    //   0	144	4	paramInt3	int
    //   0	144	5	paramString	String
    //   3	134	6	localParcel1	Parcel
    //   8	124	7	localParcel2	Parcel
    //   12	113	8	localObject1	Object
    //   129	13	8	localObject2	Object
    //   74	5	9	i	int
    // Exception table:
    //   from	to	target	type
    //   16	21	129	finally
    //   25	31	129	finally
    //   35	40	129	finally
    //   42	46	129	finally
    //   48	52	129	finally
    //   54	59	129	finally
    //   61	66	129	finally
    //   66	70	129	finally
    //   84	91	129	finally
    //   91	96	129	finally
    //   96	101	129	finally
    //   103	108	129	finally
  }
  
  /* Error */
  public void zza(com.google.android.gms.common.server.response.SafeParcelResponse paramSafeParcelResponse)
  {
    // Byte code:
    //   0: invokestatic 20	android/os/Parcel:obtain	()Landroid/os/Parcel;
    //   3: astore_2
    //   4: invokestatic 20	android/os/Parcel:obtain	()Landroid/os/Parcel;
    //   7: astore_3
    //   8: ldc 22
    //   10: astore 4
    //   12: aload_2
    //   13: aload 4
    //   15: invokevirtual 26	android/os/Parcel:writeInterfaceToken	(Ljava/lang/String;)V
    //   18: aload_1
    //   19: ifnull +59 -> 78
    //   22: iconst_1
    //   23: istore 5
    //   25: aload_2
    //   26: iload 5
    //   28: invokevirtual 65	android/os/Parcel:writeInt	(I)V
    //   31: iconst_0
    //   32: istore 5
    //   34: aconst_null
    //   35: astore 4
    //   37: aload_1
    //   38: aload_2
    //   39: iconst_0
    //   40: invokevirtual 84	com/google/android/gms/common/server/response/SafeParcelResponse:writeToParcel	(Landroid/os/Parcel;I)V
    //   43: aload_0
    //   44: getfield 14	com/google/android/gms/plus/internal/zzd$zza$zza:zzoz	Landroid/os/IBinder;
    //   47: astore 4
    //   49: iconst_4
    //   50: istore 6
    //   52: aload 4
    //   54: iload 6
    //   56: aload_2
    //   57: aload_3
    //   58: iconst_0
    //   59: invokeinterface 33 5 0
    //   64: pop
    //   65: aload_3
    //   66: invokevirtual 36	android/os/Parcel:readException	()V
    //   69: aload_3
    //   70: invokevirtual 43	android/os/Parcel:recycle	()V
    //   73: aload_2
    //   74: invokevirtual 43	android/os/Parcel:recycle	()V
    //   77: return
    //   78: iconst_0
    //   79: istore 5
    //   81: aconst_null
    //   82: astore 4
    //   84: aload_2
    //   85: iconst_0
    //   86: invokevirtual 65	android/os/Parcel:writeInt	(I)V
    //   89: goto -46 -> 43
    //   92: astore 4
    //   94: aload_3
    //   95: invokevirtual 43	android/os/Parcel:recycle	()V
    //   98: aload_2
    //   99: invokevirtual 43	android/os/Parcel:recycle	()V
    //   102: aload 4
    //   104: athrow
    // Local variable table:
    //   start	length	slot	name	signature
    //   0	105	0	this	zza
    //   0	105	1	paramSafeParcelResponse	com.google.android.gms.common.server.response.SafeParcelResponse
    //   3	96	2	localParcel1	Parcel
    //   7	88	3	localParcel2	Parcel
    //   10	73	4	localObject1	Object
    //   92	11	4	localObject2	Object
    //   23	57	5	i	int
    //   50	5	6	j	int
    // Exception table:
    //   from	to	target	type
    //   13	18	92	finally
    //   26	31	92	finally
    //   39	43	92	finally
    //   43	47	92	finally
    //   58	65	92	finally
    //   65	69	92	finally
    //   85	89	92	finally
  }
  
  /* Error */
  public void zza(zzb paramzzb)
  {
    // Byte code:
    //   0: invokestatic 20	android/os/Parcel:obtain	()Landroid/os/Parcel;
    //   3: astore_2
    //   4: invokestatic 20	android/os/Parcel:obtain	()Landroid/os/Parcel;
    //   7: astore_3
    //   8: ldc 22
    //   10: astore 4
    //   12: aload_2
    //   13: aload 4
    //   15: invokevirtual 26	android/os/Parcel:writeInterfaceToken	(Ljava/lang/String;)V
    //   18: aload_1
    //   19: ifnull +53 -> 72
    //   22: aload_1
    //   23: invokeinterface 57 1 0
    //   28: astore 4
    //   30: aload_2
    //   31: aload 4
    //   33: invokevirtual 61	android/os/Parcel:writeStrongBinder	(Landroid/os/IBinder;)V
    //   36: aload_0
    //   37: getfield 14	com/google/android/gms/plus/internal/zzd$zza$zza:zzoz	Landroid/os/IBinder;
    //   40: astore 4
    //   42: bipush 8
    //   44: istore 5
    //   46: aload 4
    //   48: iload 5
    //   50: aload_2
    //   51: aload_3
    //   52: iconst_0
    //   53: invokeinterface 33 5 0
    //   58: pop
    //   59: aload_3
    //   60: invokevirtual 36	android/os/Parcel:readException	()V
    //   63: aload_3
    //   64: invokevirtual 43	android/os/Parcel:recycle	()V
    //   67: aload_2
    //   68: invokevirtual 43	android/os/Parcel:recycle	()V
    //   71: return
    //   72: aconst_null
    //   73: astore 4
    //   75: goto -45 -> 30
    //   78: astore 4
    //   80: aload_3
    //   81: invokevirtual 43	android/os/Parcel:recycle	()V
    //   84: aload_2
    //   85: invokevirtual 43	android/os/Parcel:recycle	()V
    //   88: aload 4
    //   90: athrow
    // Local variable table:
    //   start	length	slot	name	signature
    //   0	91	0	this	zza
    //   0	91	1	paramzzb	zzb
    //   3	82	2	localParcel1	Parcel
    //   7	74	3	localParcel2	Parcel
    //   10	64	4	localObject1	Object
    //   78	11	4	localObject2	Object
    //   44	5	5	i	int
    // Exception table:
    //   from	to	target	type
    //   13	18	78	finally
    //   22	28	78	finally
    //   31	36	78	finally
    //   36	40	78	finally
    //   52	59	78	finally
    //   59	63	78	finally
  }
  
  /* Error */
  public void zza(zzb paramzzb, int paramInt, String paramString1, Uri paramUri, String paramString2, String paramString3)
  {
    // Byte code:
    //   0: invokestatic 20	android/os/Parcel:obtain	()Landroid/os/Parcel;
    //   3: astore 7
    //   5: invokestatic 20	android/os/Parcel:obtain	()Landroid/os/Parcel;
    //   8: astore 8
    //   10: ldc 22
    //   12: astore 9
    //   14: aload 7
    //   16: aload 9
    //   18: invokevirtual 26	android/os/Parcel:writeInterfaceToken	(Ljava/lang/String;)V
    //   21: aload_1
    //   22: ifnull +114 -> 136
    //   25: aload_1
    //   26: invokeinterface 57 1 0
    //   31: astore 9
    //   33: aload 7
    //   35: aload 9
    //   37: invokevirtual 61	android/os/Parcel:writeStrongBinder	(Landroid/os/IBinder;)V
    //   40: aload 7
    //   42: iload_2
    //   43: invokevirtual 65	android/os/Parcel:writeInt	(I)V
    //   46: aload 7
    //   48: aload_3
    //   49: invokevirtual 68	android/os/Parcel:writeString	(Ljava/lang/String;)V
    //   52: aload 4
    //   54: ifnull +91 -> 145
    //   57: iconst_1
    //   58: istore 10
    //   60: aload 7
    //   62: iload 10
    //   64: invokevirtual 65	android/os/Parcel:writeInt	(I)V
    //   67: iconst_0
    //   68: istore 10
    //   70: aconst_null
    //   71: astore 9
    //   73: aload 4
    //   75: aload 7
    //   77: iconst_0
    //   78: invokevirtual 89	android/net/Uri:writeToParcel	(Landroid/os/Parcel;I)V
    //   81: aload 7
    //   83: aload 5
    //   85: invokevirtual 68	android/os/Parcel:writeString	(Ljava/lang/String;)V
    //   88: aload 7
    //   90: aload 6
    //   92: invokevirtual 68	android/os/Parcel:writeString	(Ljava/lang/String;)V
    //   95: aload_0
    //   96: getfield 14	com/google/android/gms/plus/internal/zzd$zza$zza:zzoz	Landroid/os/IBinder;
    //   99: astore 9
    //   101: bipush 14
    //   103: istore 11
    //   105: aload 9
    //   107: iload 11
    //   109: aload 7
    //   111: aload 8
    //   113: iconst_0
    //   114: invokeinterface 33 5 0
    //   119: pop
    //   120: aload 8
    //   122: invokevirtual 36	android/os/Parcel:readException	()V
    //   125: aload 8
    //   127: invokevirtual 43	android/os/Parcel:recycle	()V
    //   130: aload 7
    //   132: invokevirtual 43	android/os/Parcel:recycle	()V
    //   135: return
    //   136: iconst_0
    //   137: istore 10
    //   139: aconst_null
    //   140: astore 9
    //   142: goto -109 -> 33
    //   145: iconst_0
    //   146: istore 10
    //   148: aconst_null
    //   149: astore 9
    //   151: aload 7
    //   153: iconst_0
    //   154: invokevirtual 65	android/os/Parcel:writeInt	(I)V
    //   157: goto -76 -> 81
    //   160: astore 9
    //   162: aload 8
    //   164: invokevirtual 43	android/os/Parcel:recycle	()V
    //   167: aload 7
    //   169: invokevirtual 43	android/os/Parcel:recycle	()V
    //   172: aload 9
    //   174: athrow
    // Local variable table:
    //   start	length	slot	name	signature
    //   0	175	0	this	zza
    //   0	175	1	paramzzb	zzb
    //   0	175	2	paramInt	int
    //   0	175	3	paramString1	String
    //   0	175	4	paramUri	Uri
    //   0	175	5	paramString2	String
    //   0	175	6	paramString3	String
    //   3	165	7	localParcel1	Parcel
    //   8	155	8	localParcel2	Parcel
    //   12	138	9	localObject1	Object
    //   160	13	9	localObject2	Object
    //   58	89	10	i	int
    //   103	5	11	j	int
    // Exception table:
    //   from	to	target	type
    //   16	21	160	finally
    //   25	31	160	finally
    //   35	40	160	finally
    //   42	46	160	finally
    //   48	52	160	finally
    //   62	67	160	finally
    //   77	81	160	finally
    //   83	88	160	finally
    //   90	95	160	finally
    //   95	99	160	finally
    //   113	120	160	finally
    //   120	125	160	finally
    //   153	157	160	finally
  }
  
  public void zza(zzb paramzzb, Uri paramUri, Bundle paramBundle)
  {
    Parcel localParcel1 = Parcel.obtain();
    Parcel localParcel2 = Parcel.obtain();
    Object localObject1 = "com.google.android.gms.plus.internal.IPlusService";
    for (;;)
    {
      try
      {
        localParcel1.writeInterfaceToken((String)localObject1);
        if (paramzzb != null)
        {
          localObject1 = paramzzb.asBinder();
          localParcel1.writeStrongBinder((IBinder)localObject1);
          if (paramUri != null)
          {
            i = 1;
            localParcel1.writeInt(i);
            i = 0;
            localObject1 = null;
            paramUri.writeToParcel(localParcel1, 0);
            if (paramBundle == null) {
              break label174;
            }
            i = 1;
            localParcel1.writeInt(i);
            i = 0;
            localObject1 = null;
            paramBundle.writeToParcel(localParcel1, 0);
            localObject1 = this.zzoz;
            int j = 9;
            ((IBinder)localObject1).transact(j, localParcel1, localParcel2, 0);
            localParcel2.readException();
          }
        }
        else
        {
          i = 0;
          localObject1 = null;
          continue;
        }
        int i = 0;
        localObject1 = null;
        localParcel1.writeInt(0);
        continue;
        i = 0;
      }
      finally
      {
        localParcel2.recycle();
        localParcel1.recycle();
      }
      label174:
      Object localObject3 = null;
      localParcel1.writeInt(0);
    }
  }
  
  /* Error */
  public void zza(zzb paramzzb, com.google.android.gms.common.server.response.SafeParcelResponse paramSafeParcelResponse)
  {
    // Byte code:
    //   0: invokestatic 20	android/os/Parcel:obtain	()Landroid/os/Parcel;
    //   3: astore_3
    //   4: invokestatic 20	android/os/Parcel:obtain	()Landroid/os/Parcel;
    //   7: astore 4
    //   9: ldc 22
    //   11: astore 5
    //   13: aload_3
    //   14: aload 5
    //   16: invokevirtual 26	android/os/Parcel:writeInterfaceToken	(Ljava/lang/String;)V
    //   19: aload_1
    //   20: ifnull +81 -> 101
    //   23: aload_1
    //   24: invokeinterface 57 1 0
    //   29: astore 5
    //   31: aload_3
    //   32: aload 5
    //   34: invokevirtual 61	android/os/Parcel:writeStrongBinder	(Landroid/os/IBinder;)V
    //   37: aload_2
    //   38: ifnull +72 -> 110
    //   41: iconst_1
    //   42: istore 6
    //   44: aload_3
    //   45: iload 6
    //   47: invokevirtual 65	android/os/Parcel:writeInt	(I)V
    //   50: iconst_0
    //   51: istore 6
    //   53: aconst_null
    //   54: astore 5
    //   56: aload_2
    //   57: aload_3
    //   58: iconst_0
    //   59: invokevirtual 84	com/google/android/gms/common/server/response/SafeParcelResponse:writeToParcel	(Landroid/os/Parcel;I)V
    //   62: aload_0
    //   63: getfield 14	com/google/android/gms/plus/internal/zzd$zza$zza:zzoz	Landroid/os/IBinder;
    //   66: astore 5
    //   68: bipush 45
    //   70: istore 7
    //   72: aload 5
    //   74: iload 7
    //   76: aload_3
    //   77: aload 4
    //   79: iconst_0
    //   80: invokeinterface 33 5 0
    //   85: pop
    //   86: aload 4
    //   88: invokevirtual 36	android/os/Parcel:readException	()V
    //   91: aload 4
    //   93: invokevirtual 43	android/os/Parcel:recycle	()V
    //   96: aload_3
    //   97: invokevirtual 43	android/os/Parcel:recycle	()V
    //   100: return
    //   101: iconst_0
    //   102: istore 6
    //   104: aconst_null
    //   105: astore 5
    //   107: goto -76 -> 31
    //   110: iconst_0
    //   111: istore 6
    //   113: aconst_null
    //   114: astore 5
    //   116: aload_3
    //   117: iconst_0
    //   118: invokevirtual 65	android/os/Parcel:writeInt	(I)V
    //   121: goto -59 -> 62
    //   124: astore 5
    //   126: aload 4
    //   128: invokevirtual 43	android/os/Parcel:recycle	()V
    //   131: aload_3
    //   132: invokevirtual 43	android/os/Parcel:recycle	()V
    //   135: aload 5
    //   137: athrow
    // Local variable table:
    //   start	length	slot	name	signature
    //   0	138	0	this	zza
    //   0	138	1	paramzzb	zzb
    //   0	138	2	paramSafeParcelResponse	com.google.android.gms.common.server.response.SafeParcelResponse
    //   3	129	3	localParcel1	Parcel
    //   7	120	4	localParcel2	Parcel
    //   11	104	5	localObject1	Object
    //   124	12	5	localObject2	Object
    //   42	70	6	i	int
    //   70	5	7	j	int
    // Exception table:
    //   from	to	target	type
    //   14	19	124	finally
    //   23	29	124	finally
    //   32	37	124	finally
    //   45	50	124	finally
    //   58	62	124	finally
    //   62	66	124	finally
    //   79	86	124	finally
    //   86	91	124	finally
    //   117	121	124	finally
  }
  
  /* Error */
  public void zza(zzb paramzzb, String paramString)
  {
    // Byte code:
    //   0: invokestatic 20	android/os/Parcel:obtain	()Landroid/os/Parcel;
    //   3: astore_3
    //   4: invokestatic 20	android/os/Parcel:obtain	()Landroid/os/Parcel;
    //   7: astore 4
    //   9: ldc 22
    //   11: astore 5
    //   13: aload_3
    //   14: aload 5
    //   16: invokevirtual 26	android/os/Parcel:writeInterfaceToken	(Ljava/lang/String;)V
    //   19: aload_1
    //   20: ifnull +60 -> 80
    //   23: aload_1
    //   24: invokeinterface 57 1 0
    //   29: astore 5
    //   31: aload_3
    //   32: aload 5
    //   34: invokevirtual 61	android/os/Parcel:writeStrongBinder	(Landroid/os/IBinder;)V
    //   37: aload_3
    //   38: aload_2
    //   39: invokevirtual 68	android/os/Parcel:writeString	(Ljava/lang/String;)V
    //   42: aload_0
    //   43: getfield 14	com/google/android/gms/plus/internal/zzd$zza$zza:zzoz	Landroid/os/IBinder;
    //   46: astore 5
    //   48: iconst_1
    //   49: istore 6
    //   51: aload 5
    //   53: iload 6
    //   55: aload_3
    //   56: aload 4
    //   58: iconst_0
    //   59: invokeinterface 33 5 0
    //   64: pop
    //   65: aload 4
    //   67: invokevirtual 36	android/os/Parcel:readException	()V
    //   70: aload 4
    //   72: invokevirtual 43	android/os/Parcel:recycle	()V
    //   75: aload_3
    //   76: invokevirtual 43	android/os/Parcel:recycle	()V
    //   79: return
    //   80: aconst_null
    //   81: astore 5
    //   83: goto -52 -> 31
    //   86: astore 5
    //   88: aload 4
    //   90: invokevirtual 43	android/os/Parcel:recycle	()V
    //   93: aload_3
    //   94: invokevirtual 43	android/os/Parcel:recycle	()V
    //   97: aload 5
    //   99: athrow
    // Local variable table:
    //   start	length	slot	name	signature
    //   0	100	0	this	zza
    //   0	100	1	paramzzb	zzb
    //   0	100	2	paramString	String
    //   3	91	3	localParcel1	Parcel
    //   7	82	4	localParcel2	Parcel
    //   11	71	5	localObject1	Object
    //   86	12	5	localObject2	Object
    //   49	5	6	i	int
    // Exception table:
    //   from	to	target	type
    //   14	19	86	finally
    //   23	29	86	finally
    //   32	37	86	finally
    //   38	42	86	finally
    //   42	46	86	finally
    //   58	65	86	finally
    //   65	70	86	finally
  }
  
  /* Error */
  public void zza(zzb paramzzb, String paramString1, String paramString2)
  {
    // Byte code:
    //   0: invokestatic 20	android/os/Parcel:obtain	()Landroid/os/Parcel;
    //   3: astore 4
    //   5: invokestatic 20	android/os/Parcel:obtain	()Landroid/os/Parcel;
    //   8: astore 5
    //   10: ldc 22
    //   12: astore 6
    //   14: aload 4
    //   16: aload 6
    //   18: invokevirtual 26	android/os/Parcel:writeInterfaceToken	(Ljava/lang/String;)V
    //   21: aload_1
    //   22: ifnull +70 -> 92
    //   25: aload_1
    //   26: invokeinterface 57 1 0
    //   31: astore 6
    //   33: aload 4
    //   35: aload 6
    //   37: invokevirtual 61	android/os/Parcel:writeStrongBinder	(Landroid/os/IBinder;)V
    //   40: aload 4
    //   42: aload_2
    //   43: invokevirtual 68	android/os/Parcel:writeString	(Ljava/lang/String;)V
    //   46: aload 4
    //   48: aload_3
    //   49: invokevirtual 68	android/os/Parcel:writeString	(Ljava/lang/String;)V
    //   52: aload_0
    //   53: getfield 14	com/google/android/gms/plus/internal/zzd$zza$zza:zzoz	Landroid/os/IBinder;
    //   56: astore 6
    //   58: iconst_2
    //   59: istore 7
    //   61: aload 6
    //   63: iload 7
    //   65: aload 4
    //   67: aload 5
    //   69: iconst_0
    //   70: invokeinterface 33 5 0
    //   75: pop
    //   76: aload 5
    //   78: invokevirtual 36	android/os/Parcel:readException	()V
    //   81: aload 5
    //   83: invokevirtual 43	android/os/Parcel:recycle	()V
    //   86: aload 4
    //   88: invokevirtual 43	android/os/Parcel:recycle	()V
    //   91: return
    //   92: aconst_null
    //   93: astore 6
    //   95: goto -62 -> 33
    //   98: astore 6
    //   100: aload 5
    //   102: invokevirtual 43	android/os/Parcel:recycle	()V
    //   105: aload 4
    //   107: invokevirtual 43	android/os/Parcel:recycle	()V
    //   110: aload 6
    //   112: athrow
    // Local variable table:
    //   start	length	slot	name	signature
    //   0	113	0	this	zza
    //   0	113	1	paramzzb	zzb
    //   0	113	2	paramString1	String
    //   0	113	3	paramString2	String
    //   3	103	4	localParcel1	Parcel
    //   8	93	5	localParcel2	Parcel
    //   12	82	6	localObject1	Object
    //   98	13	6	localObject2	Object
    //   59	5	7	i	int
    // Exception table:
    //   from	to	target	type
    //   16	21	98	finally
    //   25	31	98	finally
    //   35	40	98	finally
    //   42	46	98	finally
    //   48	52	98	finally
    //   52	56	98	finally
    //   69	76	98	finally
    //   76	81	98	finally
  }
  
  /* Error */
  public void zza(zzb paramzzb, java.util.List paramList)
  {
    // Byte code:
    //   0: invokestatic 20	android/os/Parcel:obtain	()Landroid/os/Parcel;
    //   3: astore_3
    //   4: invokestatic 20	android/os/Parcel:obtain	()Landroid/os/Parcel;
    //   7: astore 4
    //   9: ldc 22
    //   11: astore 5
    //   13: aload_3
    //   14: aload 5
    //   16: invokevirtual 26	android/os/Parcel:writeInterfaceToken	(Ljava/lang/String;)V
    //   19: aload_1
    //   20: ifnull +61 -> 81
    //   23: aload_1
    //   24: invokeinterface 57 1 0
    //   29: astore 5
    //   31: aload_3
    //   32: aload 5
    //   34: invokevirtual 61	android/os/Parcel:writeStrongBinder	(Landroid/os/IBinder;)V
    //   37: aload_3
    //   38: aload_2
    //   39: invokevirtual 100	android/os/Parcel:writeStringList	(Ljava/util/List;)V
    //   42: aload_0
    //   43: getfield 14	com/google/android/gms/plus/internal/zzd$zza$zza:zzoz	Landroid/os/IBinder;
    //   46: astore 5
    //   48: bipush 34
    //   50: istore 6
    //   52: aload 5
    //   54: iload 6
    //   56: aload_3
    //   57: aload 4
    //   59: iconst_0
    //   60: invokeinterface 33 5 0
    //   65: pop
    //   66: aload 4
    //   68: invokevirtual 36	android/os/Parcel:readException	()V
    //   71: aload 4
    //   73: invokevirtual 43	android/os/Parcel:recycle	()V
    //   76: aload_3
    //   77: invokevirtual 43	android/os/Parcel:recycle	()V
    //   80: return
    //   81: aconst_null
    //   82: astore 5
    //   84: goto -53 -> 31
    //   87: astore 5
    //   89: aload 4
    //   91: invokevirtual 43	android/os/Parcel:recycle	()V
    //   94: aload_3
    //   95: invokevirtual 43	android/os/Parcel:recycle	()V
    //   98: aload 5
    //   100: athrow
    // Local variable table:
    //   start	length	slot	name	signature
    //   0	101	0	this	zza
    //   0	101	1	paramzzb	zzb
    //   0	101	2	paramList	java.util.List
    //   3	92	3	localParcel1	Parcel
    //   7	83	4	localParcel2	Parcel
    //   11	72	5	localObject1	Object
    //   87	12	5	localObject2	Object
    //   50	5	6	i	int
    // Exception table:
    //   from	to	target	type
    //   14	19	87	finally
    //   23	29	87	finally
    //   32	37	87	finally
    //   38	42	87	finally
    //   42	46	87	finally
    //   59	66	87	finally
    //   66	71	87	finally
  }
  
  public void zza(String paramString, FavaDiagnosticsEntity paramFavaDiagnosticsEntity1, FavaDiagnosticsEntity paramFavaDiagnosticsEntity2)
  {
    Parcel localParcel1 = Parcel.obtain();
    Parcel localParcel2 = Parcel.obtain();
    Object localObject1 = "com.google.android.gms.plus.internal.IPlusService";
    for (;;)
    {
      try
      {
        localParcel1.writeInterfaceToken((String)localObject1);
        localParcel1.writeString(paramString);
        if (paramFavaDiagnosticsEntity1 != null)
        {
          i = 1;
          localParcel1.writeInt(i);
          i = 0;
          localObject1 = null;
          paramFavaDiagnosticsEntity1.writeToParcel(localParcel1, 0);
          if (paramFavaDiagnosticsEntity2 != null)
          {
            i = 1;
            localParcel1.writeInt(i);
            i = 0;
            localObject1 = null;
            paramFavaDiagnosticsEntity2.writeToParcel(localParcel1, 0);
            localObject1 = this.zzoz;
            int j = 46;
            ((IBinder)localObject1).transact(j, localParcel1, localParcel2, 0);
            localParcel2.readException();
          }
        }
        else
        {
          i = 0;
          localObject1 = null;
          localParcel1.writeInt(0);
          continue;
        }
        int i = 0;
      }
      finally
      {
        localParcel2.recycle();
        localParcel1.recycle();
      }
      Object localObject3 = null;
      localParcel1.writeInt(0);
    }
  }
  
  /* Error */
  public void zzb(zzb paramzzb)
  {
    // Byte code:
    //   0: invokestatic 20	android/os/Parcel:obtain	()Landroid/os/Parcel;
    //   3: astore_2
    //   4: invokestatic 20	android/os/Parcel:obtain	()Landroid/os/Parcel;
    //   7: astore_3
    //   8: ldc 22
    //   10: astore 4
    //   12: aload_2
    //   13: aload 4
    //   15: invokevirtual 26	android/os/Parcel:writeInterfaceToken	(Ljava/lang/String;)V
    //   18: aload_1
    //   19: ifnull +53 -> 72
    //   22: aload_1
    //   23: invokeinterface 57 1 0
    //   28: astore 4
    //   30: aload_2
    //   31: aload 4
    //   33: invokevirtual 61	android/os/Parcel:writeStrongBinder	(Landroid/os/IBinder;)V
    //   36: aload_0
    //   37: getfield 14	com/google/android/gms/plus/internal/zzd$zza$zza:zzoz	Landroid/os/IBinder;
    //   40: astore 4
    //   42: bipush 19
    //   44: istore 5
    //   46: aload 4
    //   48: iload 5
    //   50: aload_2
    //   51: aload_3
    //   52: iconst_0
    //   53: invokeinterface 33 5 0
    //   58: pop
    //   59: aload_3
    //   60: invokevirtual 36	android/os/Parcel:readException	()V
    //   63: aload_3
    //   64: invokevirtual 43	android/os/Parcel:recycle	()V
    //   67: aload_2
    //   68: invokevirtual 43	android/os/Parcel:recycle	()V
    //   71: return
    //   72: aconst_null
    //   73: astore 4
    //   75: goto -45 -> 30
    //   78: astore 4
    //   80: aload_3
    //   81: invokevirtual 43	android/os/Parcel:recycle	()V
    //   84: aload_2
    //   85: invokevirtual 43	android/os/Parcel:recycle	()V
    //   88: aload 4
    //   90: athrow
    // Local variable table:
    //   start	length	slot	name	signature
    //   0	91	0	this	zza
    //   0	91	1	paramzzb	zzb
    //   3	82	2	localParcel1	Parcel
    //   7	74	3	localParcel2	Parcel
    //   10	64	4	localObject1	Object
    //   78	11	4	localObject2	Object
    //   44	5	5	i	int
    // Exception table:
    //   from	to	target	type
    //   13	18	78	finally
    //   22	28	78	finally
    //   31	36	78	finally
    //   36	40	78	finally
    //   52	59	78	finally
    //   59	63	78	finally
  }
  
  /* Error */
  public void zzb(zzb paramzzb, String paramString)
  {
    // Byte code:
    //   0: invokestatic 20	android/os/Parcel:obtain	()Landroid/os/Parcel;
    //   3: astore_3
    //   4: invokestatic 20	android/os/Parcel:obtain	()Landroid/os/Parcel;
    //   7: astore 4
    //   9: ldc 22
    //   11: astore 5
    //   13: aload_3
    //   14: aload 5
    //   16: invokevirtual 26	android/os/Parcel:writeInterfaceToken	(Ljava/lang/String;)V
    //   19: aload_1
    //   20: ifnull +60 -> 80
    //   23: aload_1
    //   24: invokeinterface 57 1 0
    //   29: astore 5
    //   31: aload_3
    //   32: aload 5
    //   34: invokevirtual 61	android/os/Parcel:writeStrongBinder	(Landroid/os/IBinder;)V
    //   37: aload_3
    //   38: aload_2
    //   39: invokevirtual 68	android/os/Parcel:writeString	(Ljava/lang/String;)V
    //   42: aload_0
    //   43: getfield 14	com/google/android/gms/plus/internal/zzd$zza$zza:zzoz	Landroid/os/IBinder;
    //   46: astore 5
    //   48: iconst_3
    //   49: istore 6
    //   51: aload 5
    //   53: iload 6
    //   55: aload_3
    //   56: aload 4
    //   58: iconst_0
    //   59: invokeinterface 33 5 0
    //   64: pop
    //   65: aload 4
    //   67: invokevirtual 36	android/os/Parcel:readException	()V
    //   70: aload 4
    //   72: invokevirtual 43	android/os/Parcel:recycle	()V
    //   75: aload_3
    //   76: invokevirtual 43	android/os/Parcel:recycle	()V
    //   79: return
    //   80: aconst_null
    //   81: astore 5
    //   83: goto -52 -> 31
    //   86: astore 5
    //   88: aload 4
    //   90: invokevirtual 43	android/os/Parcel:recycle	()V
    //   93: aload_3
    //   94: invokevirtual 43	android/os/Parcel:recycle	()V
    //   97: aload 5
    //   99: athrow
    // Local variable table:
    //   start	length	slot	name	signature
    //   0	100	0	this	zza
    //   0	100	1	paramzzb	zzb
    //   0	100	2	paramString	String
    //   3	91	3	localParcel1	Parcel
    //   7	82	4	localParcel2	Parcel
    //   11	71	5	localObject1	Object
    //   86	12	5	localObject2	Object
    //   49	5	6	i	int
    // Exception table:
    //   from	to	target	type
    //   14	19	86	finally
    //   23	29	86	finally
    //   32	37	86	finally
    //   38	42	86	finally
    //   42	46	86	finally
    //   58	65	86	finally
    //   65	70	86	finally
  }
  
  /* Error */
  public void zzc(zzb paramzzb, String paramString)
  {
    // Byte code:
    //   0: invokestatic 20	android/os/Parcel:obtain	()Landroid/os/Parcel;
    //   3: astore_3
    //   4: invokestatic 20	android/os/Parcel:obtain	()Landroid/os/Parcel;
    //   7: astore 4
    //   9: ldc 22
    //   11: astore 5
    //   13: aload_3
    //   14: aload 5
    //   16: invokevirtual 26	android/os/Parcel:writeInterfaceToken	(Ljava/lang/String;)V
    //   19: aload_1
    //   20: ifnull +61 -> 81
    //   23: aload_1
    //   24: invokeinterface 57 1 0
    //   29: astore 5
    //   31: aload_3
    //   32: aload 5
    //   34: invokevirtual 61	android/os/Parcel:writeStrongBinder	(Landroid/os/IBinder;)V
    //   37: aload_3
    //   38: aload_2
    //   39: invokevirtual 68	android/os/Parcel:writeString	(Ljava/lang/String;)V
    //   42: aload_0
    //   43: getfield 14	com/google/android/gms/plus/internal/zzd$zza$zza:zzoz	Landroid/os/IBinder;
    //   46: astore 5
    //   48: bipush 18
    //   50: istore 6
    //   52: aload 5
    //   54: iload 6
    //   56: aload_3
    //   57: aload 4
    //   59: iconst_0
    //   60: invokeinterface 33 5 0
    //   65: pop
    //   66: aload 4
    //   68: invokevirtual 36	android/os/Parcel:readException	()V
    //   71: aload 4
    //   73: invokevirtual 43	android/os/Parcel:recycle	()V
    //   76: aload_3
    //   77: invokevirtual 43	android/os/Parcel:recycle	()V
    //   80: return
    //   81: aconst_null
    //   82: astore 5
    //   84: goto -53 -> 31
    //   87: astore 5
    //   89: aload 4
    //   91: invokevirtual 43	android/os/Parcel:recycle	()V
    //   94: aload_3
    //   95: invokevirtual 43	android/os/Parcel:recycle	()V
    //   98: aload 5
    //   100: athrow
    // Local variable table:
    //   start	length	slot	name	signature
    //   0	101	0	this	zza
    //   0	101	1	paramzzb	zzb
    //   0	101	2	paramString	String
    //   3	92	3	localParcel1	Parcel
    //   7	83	4	localParcel2	Parcel
    //   11	72	5	localObject1	Object
    //   87	12	5	localObject2	Object
    //   50	5	6	i	int
    // Exception table:
    //   from	to	target	type
    //   14	19	87	finally
    //   23	29	87	finally
    //   32	37	87	finally
    //   38	42	87	finally
    //   42	46	87	finally
    //   59	66	87	finally
    //   66	71	87	finally
  }
  
  /* Error */
  public void zzd(zzb paramzzb, String paramString)
  {
    // Byte code:
    //   0: invokestatic 20	android/os/Parcel:obtain	()Landroid/os/Parcel;
    //   3: astore_3
    //   4: invokestatic 20	android/os/Parcel:obtain	()Landroid/os/Parcel;
    //   7: astore 4
    //   9: ldc 22
    //   11: astore 5
    //   13: aload_3
    //   14: aload 5
    //   16: invokevirtual 26	android/os/Parcel:writeInterfaceToken	(Ljava/lang/String;)V
    //   19: aload_1
    //   20: ifnull +61 -> 81
    //   23: aload_1
    //   24: invokeinterface 57 1 0
    //   29: astore 5
    //   31: aload_3
    //   32: aload 5
    //   34: invokevirtual 61	android/os/Parcel:writeStrongBinder	(Landroid/os/IBinder;)V
    //   37: aload_3
    //   38: aload_2
    //   39: invokevirtual 68	android/os/Parcel:writeString	(Ljava/lang/String;)V
    //   42: aload_0
    //   43: getfield 14	com/google/android/gms/plus/internal/zzd$zza$zza:zzoz	Landroid/os/IBinder;
    //   46: astore 5
    //   48: bipush 40
    //   50: istore 6
    //   52: aload 5
    //   54: iload 6
    //   56: aload_3
    //   57: aload 4
    //   59: iconst_0
    //   60: invokeinterface 33 5 0
    //   65: pop
    //   66: aload 4
    //   68: invokevirtual 36	android/os/Parcel:readException	()V
    //   71: aload 4
    //   73: invokevirtual 43	android/os/Parcel:recycle	()V
    //   76: aload_3
    //   77: invokevirtual 43	android/os/Parcel:recycle	()V
    //   80: return
    //   81: aconst_null
    //   82: astore 5
    //   84: goto -53 -> 31
    //   87: astore 5
    //   89: aload 4
    //   91: invokevirtual 43	android/os/Parcel:recycle	()V
    //   94: aload_3
    //   95: invokevirtual 43	android/os/Parcel:recycle	()V
    //   98: aload 5
    //   100: athrow
    // Local variable table:
    //   start	length	slot	name	signature
    //   0	101	0	this	zza
    //   0	101	1	paramzzb	zzb
    //   0	101	2	paramString	String
    //   3	92	3	localParcel1	Parcel
    //   7	83	4	localParcel2	Parcel
    //   11	72	5	localObject1	Object
    //   87	12	5	localObject2	Object
    //   50	5	6	i	int
    // Exception table:
    //   from	to	target	type
    //   14	19	87	finally
    //   23	29	87	finally
    //   32	37	87	finally
    //   38	42	87	finally
    //   42	46	87	finally
    //   59	66	87	finally
    //   66	71	87	finally
  }
  
  /* Error */
  public void zze(zzb paramzzb, String paramString)
  {
    // Byte code:
    //   0: invokestatic 20	android/os/Parcel:obtain	()Landroid/os/Parcel;
    //   3: astore_3
    //   4: invokestatic 20	android/os/Parcel:obtain	()Landroid/os/Parcel;
    //   7: astore 4
    //   9: ldc 22
    //   11: astore 5
    //   13: aload_3
    //   14: aload 5
    //   16: invokevirtual 26	android/os/Parcel:writeInterfaceToken	(Ljava/lang/String;)V
    //   19: aload_1
    //   20: ifnull +61 -> 81
    //   23: aload_1
    //   24: invokeinterface 57 1 0
    //   29: astore 5
    //   31: aload_3
    //   32: aload 5
    //   34: invokevirtual 61	android/os/Parcel:writeStrongBinder	(Landroid/os/IBinder;)V
    //   37: aload_3
    //   38: aload_2
    //   39: invokevirtual 68	android/os/Parcel:writeString	(Ljava/lang/String;)V
    //   42: aload_0
    //   43: getfield 14	com/google/android/gms/plus/internal/zzd$zza$zza:zzoz	Landroid/os/IBinder;
    //   46: astore 5
    //   48: bipush 44
    //   50: istore 6
    //   52: aload 5
    //   54: iload 6
    //   56: aload_3
    //   57: aload 4
    //   59: iconst_0
    //   60: invokeinterface 33 5 0
    //   65: pop
    //   66: aload 4
    //   68: invokevirtual 36	android/os/Parcel:readException	()V
    //   71: aload 4
    //   73: invokevirtual 43	android/os/Parcel:recycle	()V
    //   76: aload_3
    //   77: invokevirtual 43	android/os/Parcel:recycle	()V
    //   80: return
    //   81: aconst_null
    //   82: astore 5
    //   84: goto -53 -> 31
    //   87: astore 5
    //   89: aload 4
    //   91: invokevirtual 43	android/os/Parcel:recycle	()V
    //   94: aload_3
    //   95: invokevirtual 43	android/os/Parcel:recycle	()V
    //   98: aload 5
    //   100: athrow
    // Local variable table:
    //   start	length	slot	name	signature
    //   0	101	0	this	zza
    //   0	101	1	paramzzb	zzb
    //   0	101	2	paramString	String
    //   3	92	3	localParcel1	Parcel
    //   7	83	4	localParcel2	Parcel
    //   11	72	5	localObject1	Object
    //   87	12	5	localObject2	Object
    //   50	5	6	i	int
    // Exception table:
    //   from	to	target	type
    //   14	19	87	finally
    //   23	29	87	finally
    //   32	37	87	finally
    //   38	42	87	finally
    //   42	46	87	finally
    //   59	66	87	finally
    //   66	71	87	finally
  }
  
  public void zzfG(String paramString)
  {
    Parcel localParcel1 = Parcel.obtain();
    Parcel localParcel2 = Parcel.obtain();
    Object localObject1 = "com.google.android.gms.plus.internal.IPlusService";
    try
    {
      localParcel1.writeInterfaceToken((String)localObject1);
      localParcel1.writeString(paramString);
      localObject1 = this.zzoz;
      int i = 17;
      ((IBinder)localObject1).transact(i, localParcel1, localParcel2, 0);
      localParcel2.readException();
      return;
    }
    finally
    {
      localParcel2.recycle();
      localParcel1.recycle();
    }
  }
  
  public String zzmR()
  {
    Parcel localParcel1 = Parcel.obtain();
    Parcel localParcel2 = Parcel.obtain();
    Object localObject1 = "com.google.android.gms.plus.internal.IPlusService";
    try
    {
      localParcel1.writeInterfaceToken((String)localObject1);
      localObject1 = this.zzoz;
      int i = 43;
      ((IBinder)localObject1).transact(i, localParcel1, localParcel2, 0);
      localParcel2.readException();
      localObject1 = localParcel2.readString();
      return (String)localObject1;
    }
    finally
    {
      localParcel2.recycle();
      localParcel1.recycle();
    }
  }
}


/* Location:              C:\Users\haryo\Desktop\enjarify-master\presensi-enjarify.jar!\com\google\android\gms\plus\internal\zzd$zza$zza.class
 * Java compiler version: 5 (49.0)
 * JD-Core Version:       0.7.1
 */