package com.google.android.gms.ads.internal.request;

import java.io.OutputStream;

class LargeParcelTeleporter$1
  implements Runnable
{
  LargeParcelTeleporter$1(LargeParcelTeleporter paramLargeParcelTeleporter, OutputStream paramOutputStream, byte[] paramArrayOfByte) {}
  
  /* Error */
  public void run()
  {
    // Byte code:
    //   0: aconst_null
    //   1: astore_1
    //   2: new 24	java/io/DataOutputStream
    //   5: astore_2
    //   6: aload_0
    //   7: getfield 16	com/google/android/gms/ads/internal/request/LargeParcelTeleporter$1:zzIt	Ljava/io/OutputStream;
    //   10: astore_3
    //   11: aload_2
    //   12: aload_3
    //   13: invokespecial 27	java/io/DataOutputStream:<init>	(Ljava/io/OutputStream;)V
    //   16: aload_0
    //   17: getfield 18	com/google/android/gms/ads/internal/request/LargeParcelTeleporter$1:zzIu	[B
    //   20: astore_3
    //   21: aload_3
    //   22: arraylength
    //   23: istore 4
    //   25: aload_2
    //   26: iload 4
    //   28: invokevirtual 31	java/io/DataOutputStream:writeInt	(I)V
    //   31: aload_0
    //   32: getfield 18	com/google/android/gms/ads/internal/request/LargeParcelTeleporter$1:zzIu	[B
    //   35: astore_3
    //   36: aload_2
    //   37: aload_3
    //   38: invokevirtual 35	java/io/DataOutputStream:write	([B)V
    //   41: aload_2
    //   42: ifnonnull +13 -> 55
    //   45: aload_0
    //   46: getfield 16	com/google/android/gms/ads/internal/request/LargeParcelTeleporter$1:zzIt	Ljava/io/OutputStream;
    //   49: astore_3
    //   50: aload_3
    //   51: invokestatic 41	com/google/android/gms/internal/zzna:zzb	(Ljava/io/Closeable;)V
    //   54: return
    //   55: aload_2
    //   56: invokestatic 41	com/google/android/gms/internal/zzna:zzb	(Ljava/io/Closeable;)V
    //   59: goto -5 -> 54
    //   62: astore_3
    //   63: aconst_null
    //   64: astore_2
    //   65: ldc 43
    //   67: astore_1
    //   68: aload_1
    //   69: aload_3
    //   70: invokestatic 48	com/google/android/gms/internal/zzin:zzb	(Ljava/lang/String;Ljava/lang/Throwable;)V
    //   73: invokestatic 54	com/google/android/gms/ads/internal/zzr:zzbF	()Lcom/google/android/gms/internal/zzih;
    //   76: astore_1
    //   77: iconst_1
    //   78: istore 5
    //   80: aload_1
    //   81: aload_3
    //   82: iload 5
    //   84: invokevirtual 60	com/google/android/gms/internal/zzih:zzb	(Ljava/lang/Throwable;Z)V
    //   87: aload_2
    //   88: ifnonnull +15 -> 103
    //   91: aload_0
    //   92: getfield 16	com/google/android/gms/ads/internal/request/LargeParcelTeleporter$1:zzIt	Ljava/io/OutputStream;
    //   95: astore_3
    //   96: aload_3
    //   97: invokestatic 41	com/google/android/gms/internal/zzna:zzb	(Ljava/io/Closeable;)V
    //   100: goto -46 -> 54
    //   103: aload_2
    //   104: invokestatic 41	com/google/android/gms/internal/zzna:zzb	(Ljava/io/Closeable;)V
    //   107: goto -53 -> 54
    //   110: astore_3
    //   111: aconst_null
    //   112: astore_2
    //   113: aload_2
    //   114: ifnonnull +14 -> 128
    //   117: aload_0
    //   118: getfield 16	com/google/android/gms/ads/internal/request/LargeParcelTeleporter$1:zzIt	Ljava/io/OutputStream;
    //   121: astore_2
    //   122: aload_2
    //   123: invokestatic 41	com/google/android/gms/internal/zzna:zzb	(Ljava/io/Closeable;)V
    //   126: aload_3
    //   127: athrow
    //   128: aload_2
    //   129: invokestatic 41	com/google/android/gms/internal/zzna:zzb	(Ljava/io/Closeable;)V
    //   132: goto -6 -> 126
    //   135: astore_3
    //   136: goto -23 -> 113
    //   139: astore_3
    //   140: goto -75 -> 65
    // Local variable table:
    //   start	length	slot	name	signature
    //   0	143	0	this	1
    //   1	80	1	localObject1	Object
    //   5	124	2	localObject2	Object
    //   10	41	3	localObject3	Object
    //   62	20	3	localIOException1	java.io.IOException
    //   95	2	3	localOutputStream	OutputStream
    //   110	17	3	localObject4	Object
    //   135	1	3	localObject5	Object
    //   139	1	3	localIOException2	java.io.IOException
    //   23	4	4	i	int
    //   78	5	5	bool	boolean
    // Exception table:
    //   from	to	target	type
    //   2	5	62	java/io/IOException
    //   6	10	62	java/io/IOException
    //   12	16	62	java/io/IOException
    //   2	5	110	finally
    //   6	10	110	finally
    //   12	16	110	finally
    //   16	20	135	finally
    //   21	23	135	finally
    //   26	31	135	finally
    //   31	35	135	finally
    //   37	41	135	finally
    //   69	73	135	finally
    //   73	76	135	finally
    //   82	87	135	finally
    //   16	20	139	java/io/IOException
    //   21	23	139	java/io/IOException
    //   26	31	139	java/io/IOException
    //   31	35	139	java/io/IOException
    //   37	41	139	java/io/IOException
  }
}


/* Location:              C:\Users\haryo\Desktop\enjarify-master\presensi-enjarify.jar!\com\google\android\gms\ads\internal\request\LargeParcelTeleporter$1.class
 * Java compiler version: 5 (49.0)
 * JD-Core Version:       0.7.1
 */