package com.google.android.gms.maps.internal;

import android.os.IBinder;
import android.os.Parcel;
import com.google.android.gms.maps.model.internal.zzd;
import com.google.android.gms.maps.model.internal.zzd.zza;

class IGoogleMapDelegate$zza$zza
  implements IGoogleMapDelegate
{
  private IBinder zzoz;
  
  IGoogleMapDelegate$zza$zza(IBinder paramIBinder)
  {
    this.zzoz = paramIBinder;
  }
  
  /* Error */
  public com.google.android.gms.maps.model.internal.zzb addCircle(com.google.android.gms.maps.model.CircleOptions paramCircleOptions)
  {
    // Byte code:
    //   0: invokestatic 20	android/os/Parcel:obtain	()Landroid/os/Parcel;
    //   3: astore_2
    //   4: invokestatic 20	android/os/Parcel:obtain	()Landroid/os/Parcel;
    //   7: astore_3
    //   8: ldc 22
    //   10: astore 4
    //   12: aload_2
    //   13: aload 4
    //   15: invokevirtual 26	android/os/Parcel:writeInterfaceToken	(Ljava/lang/String;)V
    //   18: aload_1
    //   19: ifnull +75 -> 94
    //   22: iconst_1
    //   23: istore 5
    //   25: aload_2
    //   26: iload 5
    //   28: invokevirtual 31	android/os/Parcel:writeInt	(I)V
    //   31: iconst_0
    //   32: istore 5
    //   34: aconst_null
    //   35: astore 4
    //   37: aload_1
    //   38: aload_2
    //   39: iconst_0
    //   40: invokevirtual 37	com/google/android/gms/maps/model/CircleOptions:writeToParcel	(Landroid/os/Parcel;I)V
    //   43: aload_0
    //   44: getfield 14	com/google/android/gms/maps/internal/IGoogleMapDelegate$zza$zza:zzoz	Landroid/os/IBinder;
    //   47: astore 4
    //   49: bipush 35
    //   51: istore 6
    //   53: aload 4
    //   55: iload 6
    //   57: aload_2
    //   58: aload_3
    //   59: iconst_0
    //   60: invokeinterface 44 5 0
    //   65: pop
    //   66: aload_3
    //   67: invokevirtual 47	android/os/Parcel:readException	()V
    //   70: aload_3
    //   71: invokevirtual 51	android/os/Parcel:readStrongBinder	()Landroid/os/IBinder;
    //   74: astore 4
    //   76: aload 4
    //   78: invokestatic 57	com/google/android/gms/maps/model/internal/zzb$zza:zzde	(Landroid/os/IBinder;)Lcom/google/android/gms/maps/model/internal/zzb;
    //   81: astore 4
    //   83: aload_3
    //   84: invokevirtual 60	android/os/Parcel:recycle	()V
    //   87: aload_2
    //   88: invokevirtual 60	android/os/Parcel:recycle	()V
    //   91: aload 4
    //   93: areturn
    //   94: iconst_0
    //   95: istore 5
    //   97: aconst_null
    //   98: astore 4
    //   100: aload_2
    //   101: iconst_0
    //   102: invokevirtual 31	android/os/Parcel:writeInt	(I)V
    //   105: goto -62 -> 43
    //   108: astore 4
    //   110: aload_3
    //   111: invokevirtual 60	android/os/Parcel:recycle	()V
    //   114: aload_2
    //   115: invokevirtual 60	android/os/Parcel:recycle	()V
    //   118: aload 4
    //   120: athrow
    // Local variable table:
    //   start	length	slot	name	signature
    //   0	121	0	this	zza
    //   0	121	1	paramCircleOptions	com.google.android.gms.maps.model.CircleOptions
    //   3	112	2	localParcel1	Parcel
    //   7	104	3	localParcel2	Parcel
    //   10	89	4	localObject1	Object
    //   108	11	4	localObject2	Object
    //   23	73	5	i	int
    //   51	5	6	j	int
    // Exception table:
    //   from	to	target	type
    //   13	18	108	finally
    //   26	31	108	finally
    //   39	43	108	finally
    //   43	47	108	finally
    //   59	66	108	finally
    //   66	70	108	finally
    //   70	74	108	finally
    //   76	81	108	finally
    //   101	105	108	finally
  }
  
  /* Error */
  public com.google.android.gms.maps.model.internal.zzc addGroundOverlay(com.google.android.gms.maps.model.GroundOverlayOptions paramGroundOverlayOptions)
  {
    // Byte code:
    //   0: invokestatic 20	android/os/Parcel:obtain	()Landroid/os/Parcel;
    //   3: astore_2
    //   4: invokestatic 20	android/os/Parcel:obtain	()Landroid/os/Parcel;
    //   7: astore_3
    //   8: ldc 22
    //   10: astore 4
    //   12: aload_2
    //   13: aload 4
    //   15: invokevirtual 26	android/os/Parcel:writeInterfaceToken	(Ljava/lang/String;)V
    //   18: aload_1
    //   19: ifnull +75 -> 94
    //   22: iconst_1
    //   23: istore 5
    //   25: aload_2
    //   26: iload 5
    //   28: invokevirtual 31	android/os/Parcel:writeInt	(I)V
    //   31: iconst_0
    //   32: istore 5
    //   34: aconst_null
    //   35: astore 4
    //   37: aload_1
    //   38: aload_2
    //   39: iconst_0
    //   40: invokevirtual 63	com/google/android/gms/maps/model/GroundOverlayOptions:writeToParcel	(Landroid/os/Parcel;I)V
    //   43: aload_0
    //   44: getfield 14	com/google/android/gms/maps/internal/IGoogleMapDelegate$zza$zza:zzoz	Landroid/os/IBinder;
    //   47: astore 4
    //   49: bipush 12
    //   51: istore 6
    //   53: aload 4
    //   55: iload 6
    //   57: aload_2
    //   58: aload_3
    //   59: iconst_0
    //   60: invokeinterface 44 5 0
    //   65: pop
    //   66: aload_3
    //   67: invokevirtual 47	android/os/Parcel:readException	()V
    //   70: aload_3
    //   71: invokevirtual 51	android/os/Parcel:readStrongBinder	()Landroid/os/IBinder;
    //   74: astore 4
    //   76: aload 4
    //   78: invokestatic 70	com/google/android/gms/maps/model/internal/zzc$zza:zzdf	(Landroid/os/IBinder;)Lcom/google/android/gms/maps/model/internal/zzc;
    //   81: astore 4
    //   83: aload_3
    //   84: invokevirtual 60	android/os/Parcel:recycle	()V
    //   87: aload_2
    //   88: invokevirtual 60	android/os/Parcel:recycle	()V
    //   91: aload 4
    //   93: areturn
    //   94: iconst_0
    //   95: istore 5
    //   97: aconst_null
    //   98: astore 4
    //   100: aload_2
    //   101: iconst_0
    //   102: invokevirtual 31	android/os/Parcel:writeInt	(I)V
    //   105: goto -62 -> 43
    //   108: astore 4
    //   110: aload_3
    //   111: invokevirtual 60	android/os/Parcel:recycle	()V
    //   114: aload_2
    //   115: invokevirtual 60	android/os/Parcel:recycle	()V
    //   118: aload 4
    //   120: athrow
    // Local variable table:
    //   start	length	slot	name	signature
    //   0	121	0	this	zza
    //   0	121	1	paramGroundOverlayOptions	com.google.android.gms.maps.model.GroundOverlayOptions
    //   3	112	2	localParcel1	Parcel
    //   7	104	3	localParcel2	Parcel
    //   10	89	4	localObject1	Object
    //   108	11	4	localObject2	Object
    //   23	73	5	i	int
    //   51	5	6	j	int
    // Exception table:
    //   from	to	target	type
    //   13	18	108	finally
    //   26	31	108	finally
    //   39	43	108	finally
    //   43	47	108	finally
    //   59	66	108	finally
    //   66	70	108	finally
    //   70	74	108	finally
    //   76	81	108	finally
    //   101	105	108	finally
  }
  
  /* Error */
  public com.google.android.gms.maps.model.internal.zzf addMarker(com.google.android.gms.maps.model.MarkerOptions paramMarkerOptions)
  {
    // Byte code:
    //   0: invokestatic 20	android/os/Parcel:obtain	()Landroid/os/Parcel;
    //   3: astore_2
    //   4: invokestatic 20	android/os/Parcel:obtain	()Landroid/os/Parcel;
    //   7: astore_3
    //   8: ldc 22
    //   10: astore 4
    //   12: aload_2
    //   13: aload 4
    //   15: invokevirtual 26	android/os/Parcel:writeInterfaceToken	(Ljava/lang/String;)V
    //   18: aload_1
    //   19: ifnull +75 -> 94
    //   22: iconst_1
    //   23: istore 5
    //   25: aload_2
    //   26: iload 5
    //   28: invokevirtual 31	android/os/Parcel:writeInt	(I)V
    //   31: iconst_0
    //   32: istore 5
    //   34: aconst_null
    //   35: astore 4
    //   37: aload_1
    //   38: aload_2
    //   39: iconst_0
    //   40: invokevirtual 73	com/google/android/gms/maps/model/MarkerOptions:writeToParcel	(Landroid/os/Parcel;I)V
    //   43: aload_0
    //   44: getfield 14	com/google/android/gms/maps/internal/IGoogleMapDelegate$zza$zza:zzoz	Landroid/os/IBinder;
    //   47: astore 4
    //   49: bipush 11
    //   51: istore 6
    //   53: aload 4
    //   55: iload 6
    //   57: aload_2
    //   58: aload_3
    //   59: iconst_0
    //   60: invokeinterface 44 5 0
    //   65: pop
    //   66: aload_3
    //   67: invokevirtual 47	android/os/Parcel:readException	()V
    //   70: aload_3
    //   71: invokevirtual 51	android/os/Parcel:readStrongBinder	()Landroid/os/IBinder;
    //   74: astore 4
    //   76: aload 4
    //   78: invokestatic 80	com/google/android/gms/maps/model/internal/zzf$zza:zzdi	(Landroid/os/IBinder;)Lcom/google/android/gms/maps/model/internal/zzf;
    //   81: astore 4
    //   83: aload_3
    //   84: invokevirtual 60	android/os/Parcel:recycle	()V
    //   87: aload_2
    //   88: invokevirtual 60	android/os/Parcel:recycle	()V
    //   91: aload 4
    //   93: areturn
    //   94: iconst_0
    //   95: istore 5
    //   97: aconst_null
    //   98: astore 4
    //   100: aload_2
    //   101: iconst_0
    //   102: invokevirtual 31	android/os/Parcel:writeInt	(I)V
    //   105: goto -62 -> 43
    //   108: astore 4
    //   110: aload_3
    //   111: invokevirtual 60	android/os/Parcel:recycle	()V
    //   114: aload_2
    //   115: invokevirtual 60	android/os/Parcel:recycle	()V
    //   118: aload 4
    //   120: athrow
    // Local variable table:
    //   start	length	slot	name	signature
    //   0	121	0	this	zza
    //   0	121	1	paramMarkerOptions	com.google.android.gms.maps.model.MarkerOptions
    //   3	112	2	localParcel1	Parcel
    //   7	104	3	localParcel2	Parcel
    //   10	89	4	localObject1	Object
    //   108	11	4	localObject2	Object
    //   23	73	5	i	int
    //   51	5	6	j	int
    // Exception table:
    //   from	to	target	type
    //   13	18	108	finally
    //   26	31	108	finally
    //   39	43	108	finally
    //   43	47	108	finally
    //   59	66	108	finally
    //   66	70	108	finally
    //   70	74	108	finally
    //   76	81	108	finally
    //   101	105	108	finally
  }
  
  /* Error */
  public com.google.android.gms.maps.model.internal.zzg addPolygon(com.google.android.gms.maps.model.PolygonOptions paramPolygonOptions)
  {
    // Byte code:
    //   0: invokestatic 20	android/os/Parcel:obtain	()Landroid/os/Parcel;
    //   3: astore_2
    //   4: invokestatic 20	android/os/Parcel:obtain	()Landroid/os/Parcel;
    //   7: astore_3
    //   8: ldc 22
    //   10: astore 4
    //   12: aload_2
    //   13: aload 4
    //   15: invokevirtual 26	android/os/Parcel:writeInterfaceToken	(Ljava/lang/String;)V
    //   18: aload_1
    //   19: ifnull +75 -> 94
    //   22: iconst_1
    //   23: istore 5
    //   25: aload_2
    //   26: iload 5
    //   28: invokevirtual 31	android/os/Parcel:writeInt	(I)V
    //   31: iconst_0
    //   32: istore 5
    //   34: aconst_null
    //   35: astore 4
    //   37: aload_1
    //   38: aload_2
    //   39: iconst_0
    //   40: invokevirtual 83	com/google/android/gms/maps/model/PolygonOptions:writeToParcel	(Landroid/os/Parcel;I)V
    //   43: aload_0
    //   44: getfield 14	com/google/android/gms/maps/internal/IGoogleMapDelegate$zza$zza:zzoz	Landroid/os/IBinder;
    //   47: astore 4
    //   49: bipush 10
    //   51: istore 6
    //   53: aload 4
    //   55: iload 6
    //   57: aload_2
    //   58: aload_3
    //   59: iconst_0
    //   60: invokeinterface 44 5 0
    //   65: pop
    //   66: aload_3
    //   67: invokevirtual 47	android/os/Parcel:readException	()V
    //   70: aload_3
    //   71: invokevirtual 51	android/os/Parcel:readStrongBinder	()Landroid/os/IBinder;
    //   74: astore 4
    //   76: aload 4
    //   78: invokestatic 90	com/google/android/gms/maps/model/internal/zzg$zza:zzdj	(Landroid/os/IBinder;)Lcom/google/android/gms/maps/model/internal/zzg;
    //   81: astore 4
    //   83: aload_3
    //   84: invokevirtual 60	android/os/Parcel:recycle	()V
    //   87: aload_2
    //   88: invokevirtual 60	android/os/Parcel:recycle	()V
    //   91: aload 4
    //   93: areturn
    //   94: iconst_0
    //   95: istore 5
    //   97: aconst_null
    //   98: astore 4
    //   100: aload_2
    //   101: iconst_0
    //   102: invokevirtual 31	android/os/Parcel:writeInt	(I)V
    //   105: goto -62 -> 43
    //   108: astore 4
    //   110: aload_3
    //   111: invokevirtual 60	android/os/Parcel:recycle	()V
    //   114: aload_2
    //   115: invokevirtual 60	android/os/Parcel:recycle	()V
    //   118: aload 4
    //   120: athrow
    // Local variable table:
    //   start	length	slot	name	signature
    //   0	121	0	this	zza
    //   0	121	1	paramPolygonOptions	com.google.android.gms.maps.model.PolygonOptions
    //   3	112	2	localParcel1	Parcel
    //   7	104	3	localParcel2	Parcel
    //   10	89	4	localObject1	Object
    //   108	11	4	localObject2	Object
    //   23	73	5	i	int
    //   51	5	6	j	int
    // Exception table:
    //   from	to	target	type
    //   13	18	108	finally
    //   26	31	108	finally
    //   39	43	108	finally
    //   43	47	108	finally
    //   59	66	108	finally
    //   66	70	108	finally
    //   70	74	108	finally
    //   76	81	108	finally
    //   101	105	108	finally
  }
  
  /* Error */
  public com.google.android.gms.maps.model.internal.IPolylineDelegate addPolyline(com.google.android.gms.maps.model.PolylineOptions paramPolylineOptions)
  {
    // Byte code:
    //   0: invokestatic 20	android/os/Parcel:obtain	()Landroid/os/Parcel;
    //   3: astore_2
    //   4: invokestatic 20	android/os/Parcel:obtain	()Landroid/os/Parcel;
    //   7: astore_3
    //   8: ldc 22
    //   10: astore 4
    //   12: aload_2
    //   13: aload 4
    //   15: invokevirtual 26	android/os/Parcel:writeInterfaceToken	(Ljava/lang/String;)V
    //   18: aload_1
    //   19: ifnull +75 -> 94
    //   22: iconst_1
    //   23: istore 5
    //   25: aload_2
    //   26: iload 5
    //   28: invokevirtual 31	android/os/Parcel:writeInt	(I)V
    //   31: iconst_0
    //   32: istore 5
    //   34: aconst_null
    //   35: astore 4
    //   37: aload_1
    //   38: aload_2
    //   39: iconst_0
    //   40: invokevirtual 93	com/google/android/gms/maps/model/PolylineOptions:writeToParcel	(Landroid/os/Parcel;I)V
    //   43: aload_0
    //   44: getfield 14	com/google/android/gms/maps/internal/IGoogleMapDelegate$zza$zza:zzoz	Landroid/os/IBinder;
    //   47: astore 4
    //   49: bipush 9
    //   51: istore 6
    //   53: aload 4
    //   55: iload 6
    //   57: aload_2
    //   58: aload_3
    //   59: iconst_0
    //   60: invokeinterface 44 5 0
    //   65: pop
    //   66: aload_3
    //   67: invokevirtual 47	android/os/Parcel:readException	()V
    //   70: aload_3
    //   71: invokevirtual 51	android/os/Parcel:readStrongBinder	()Landroid/os/IBinder;
    //   74: astore 4
    //   76: aload 4
    //   78: invokestatic 100	com/google/android/gms/maps/model/internal/IPolylineDelegate$zza:zzdk	(Landroid/os/IBinder;)Lcom/google/android/gms/maps/model/internal/IPolylineDelegate;
    //   81: astore 4
    //   83: aload_3
    //   84: invokevirtual 60	android/os/Parcel:recycle	()V
    //   87: aload_2
    //   88: invokevirtual 60	android/os/Parcel:recycle	()V
    //   91: aload 4
    //   93: areturn
    //   94: iconst_0
    //   95: istore 5
    //   97: aconst_null
    //   98: astore 4
    //   100: aload_2
    //   101: iconst_0
    //   102: invokevirtual 31	android/os/Parcel:writeInt	(I)V
    //   105: goto -62 -> 43
    //   108: astore 4
    //   110: aload_3
    //   111: invokevirtual 60	android/os/Parcel:recycle	()V
    //   114: aload_2
    //   115: invokevirtual 60	android/os/Parcel:recycle	()V
    //   118: aload 4
    //   120: athrow
    // Local variable table:
    //   start	length	slot	name	signature
    //   0	121	0	this	zza
    //   0	121	1	paramPolylineOptions	com.google.android.gms.maps.model.PolylineOptions
    //   3	112	2	localParcel1	Parcel
    //   7	104	3	localParcel2	Parcel
    //   10	89	4	localObject1	Object
    //   108	11	4	localObject2	Object
    //   23	73	5	i	int
    //   51	5	6	j	int
    // Exception table:
    //   from	to	target	type
    //   13	18	108	finally
    //   26	31	108	finally
    //   39	43	108	finally
    //   43	47	108	finally
    //   59	66	108	finally
    //   66	70	108	finally
    //   70	74	108	finally
    //   76	81	108	finally
    //   101	105	108	finally
  }
  
  /* Error */
  public com.google.android.gms.maps.model.internal.zzh addTileOverlay(com.google.android.gms.maps.model.TileOverlayOptions paramTileOverlayOptions)
  {
    // Byte code:
    //   0: invokestatic 20	android/os/Parcel:obtain	()Landroid/os/Parcel;
    //   3: astore_2
    //   4: invokestatic 20	android/os/Parcel:obtain	()Landroid/os/Parcel;
    //   7: astore_3
    //   8: ldc 22
    //   10: astore 4
    //   12: aload_2
    //   13: aload 4
    //   15: invokevirtual 26	android/os/Parcel:writeInterfaceToken	(Ljava/lang/String;)V
    //   18: aload_1
    //   19: ifnull +75 -> 94
    //   22: iconst_1
    //   23: istore 5
    //   25: aload_2
    //   26: iload 5
    //   28: invokevirtual 31	android/os/Parcel:writeInt	(I)V
    //   31: iconst_0
    //   32: istore 5
    //   34: aconst_null
    //   35: astore 4
    //   37: aload_1
    //   38: aload_2
    //   39: iconst_0
    //   40: invokevirtual 103	com/google/android/gms/maps/model/TileOverlayOptions:writeToParcel	(Landroid/os/Parcel;I)V
    //   43: aload_0
    //   44: getfield 14	com/google/android/gms/maps/internal/IGoogleMapDelegate$zza$zza:zzoz	Landroid/os/IBinder;
    //   47: astore 4
    //   49: bipush 13
    //   51: istore 6
    //   53: aload 4
    //   55: iload 6
    //   57: aload_2
    //   58: aload_3
    //   59: iconst_0
    //   60: invokeinterface 44 5 0
    //   65: pop
    //   66: aload_3
    //   67: invokevirtual 47	android/os/Parcel:readException	()V
    //   70: aload_3
    //   71: invokevirtual 51	android/os/Parcel:readStrongBinder	()Landroid/os/IBinder;
    //   74: astore 4
    //   76: aload 4
    //   78: invokestatic 110	com/google/android/gms/maps/model/internal/zzh$zza:zzdl	(Landroid/os/IBinder;)Lcom/google/android/gms/maps/model/internal/zzh;
    //   81: astore 4
    //   83: aload_3
    //   84: invokevirtual 60	android/os/Parcel:recycle	()V
    //   87: aload_2
    //   88: invokevirtual 60	android/os/Parcel:recycle	()V
    //   91: aload 4
    //   93: areturn
    //   94: iconst_0
    //   95: istore 5
    //   97: aconst_null
    //   98: astore 4
    //   100: aload_2
    //   101: iconst_0
    //   102: invokevirtual 31	android/os/Parcel:writeInt	(I)V
    //   105: goto -62 -> 43
    //   108: astore 4
    //   110: aload_3
    //   111: invokevirtual 60	android/os/Parcel:recycle	()V
    //   114: aload_2
    //   115: invokevirtual 60	android/os/Parcel:recycle	()V
    //   118: aload 4
    //   120: athrow
    // Local variable table:
    //   start	length	slot	name	signature
    //   0	121	0	this	zza
    //   0	121	1	paramTileOverlayOptions	com.google.android.gms.maps.model.TileOverlayOptions
    //   3	112	2	localParcel1	Parcel
    //   7	104	3	localParcel2	Parcel
    //   10	89	4	localObject1	Object
    //   108	11	4	localObject2	Object
    //   23	73	5	i	int
    //   51	5	6	j	int
    // Exception table:
    //   from	to	target	type
    //   13	18	108	finally
    //   26	31	108	finally
    //   39	43	108	finally
    //   43	47	108	finally
    //   59	66	108	finally
    //   66	70	108	finally
    //   70	74	108	finally
    //   76	81	108	finally
    //   101	105	108	finally
  }
  
  /* Error */
  public void animateCamera(com.google.android.gms.dynamic.zzd paramzzd)
  {
    // Byte code:
    //   0: invokestatic 20	android/os/Parcel:obtain	()Landroid/os/Parcel;
    //   3: astore_2
    //   4: invokestatic 20	android/os/Parcel:obtain	()Landroid/os/Parcel;
    //   7: astore_3
    //   8: ldc 22
    //   10: astore 4
    //   12: aload_2
    //   13: aload 4
    //   15: invokevirtual 26	android/os/Parcel:writeInterfaceToken	(Ljava/lang/String;)V
    //   18: aload_1
    //   19: ifnull +52 -> 71
    //   22: aload_1
    //   23: invokeinterface 115 1 0
    //   28: astore 4
    //   30: aload_2
    //   31: aload 4
    //   33: invokevirtual 119	android/os/Parcel:writeStrongBinder	(Landroid/os/IBinder;)V
    //   36: aload_0
    //   37: getfield 14	com/google/android/gms/maps/internal/IGoogleMapDelegate$zza$zza:zzoz	Landroid/os/IBinder;
    //   40: astore 4
    //   42: iconst_5
    //   43: istore 5
    //   45: aload 4
    //   47: iload 5
    //   49: aload_2
    //   50: aload_3
    //   51: iconst_0
    //   52: invokeinterface 44 5 0
    //   57: pop
    //   58: aload_3
    //   59: invokevirtual 47	android/os/Parcel:readException	()V
    //   62: aload_3
    //   63: invokevirtual 60	android/os/Parcel:recycle	()V
    //   66: aload_2
    //   67: invokevirtual 60	android/os/Parcel:recycle	()V
    //   70: return
    //   71: aconst_null
    //   72: astore 4
    //   74: goto -44 -> 30
    //   77: astore 4
    //   79: aload_3
    //   80: invokevirtual 60	android/os/Parcel:recycle	()V
    //   83: aload_2
    //   84: invokevirtual 60	android/os/Parcel:recycle	()V
    //   87: aload 4
    //   89: athrow
    // Local variable table:
    //   start	length	slot	name	signature
    //   0	90	0	this	zza
    //   0	90	1	paramzzd	com.google.android.gms.dynamic.zzd
    //   3	81	2	localParcel1	Parcel
    //   7	73	3	localParcel2	Parcel
    //   10	63	4	localObject1	Object
    //   77	11	4	localObject2	Object
    //   43	5	5	i	int
    // Exception table:
    //   from	to	target	type
    //   13	18	77	finally
    //   22	28	77	finally
    //   31	36	77	finally
    //   36	40	77	finally
    //   51	58	77	finally
    //   58	62	77	finally
  }
  
  /* Error */
  public void animateCameraWithCallback(com.google.android.gms.dynamic.zzd paramzzd, zzb paramzzb)
  {
    // Byte code:
    //   0: aconst_null
    //   1: astore_3
    //   2: invokestatic 20	android/os/Parcel:obtain	()Landroid/os/Parcel;
    //   5: astore 4
    //   7: invokestatic 20	android/os/Parcel:obtain	()Landroid/os/Parcel;
    //   10: astore 5
    //   12: ldc 22
    //   14: astore 6
    //   16: aload 4
    //   18: aload 6
    //   20: invokevirtual 26	android/os/Parcel:writeInterfaceToken	(Ljava/lang/String;)V
    //   23: aload_1
    //   24: ifnull +74 -> 98
    //   27: aload_1
    //   28: invokeinterface 115 1 0
    //   33: astore 6
    //   35: aload 4
    //   37: aload 6
    //   39: invokevirtual 119	android/os/Parcel:writeStrongBinder	(Landroid/os/IBinder;)V
    //   42: aload_2
    //   43: ifnull +10 -> 53
    //   46: aload_2
    //   47: invokeinterface 123 1 0
    //   52: astore_3
    //   53: aload 4
    //   55: aload_3
    //   56: invokevirtual 119	android/os/Parcel:writeStrongBinder	(Landroid/os/IBinder;)V
    //   59: aload_0
    //   60: getfield 14	com/google/android/gms/maps/internal/IGoogleMapDelegate$zza$zza:zzoz	Landroid/os/IBinder;
    //   63: astore_3
    //   64: bipush 6
    //   66: istore 7
    //   68: aload_3
    //   69: iload 7
    //   71: aload 4
    //   73: aload 5
    //   75: iconst_0
    //   76: invokeinterface 44 5 0
    //   81: pop
    //   82: aload 5
    //   84: invokevirtual 47	android/os/Parcel:readException	()V
    //   87: aload 5
    //   89: invokevirtual 60	android/os/Parcel:recycle	()V
    //   92: aload 4
    //   94: invokevirtual 60	android/os/Parcel:recycle	()V
    //   97: return
    //   98: iconst_0
    //   99: istore 7
    //   101: aconst_null
    //   102: astore 6
    //   104: goto -69 -> 35
    //   107: astore_3
    //   108: aload 5
    //   110: invokevirtual 60	android/os/Parcel:recycle	()V
    //   113: aload 4
    //   115: invokevirtual 60	android/os/Parcel:recycle	()V
    //   118: aload_3
    //   119: athrow
    // Local variable table:
    //   start	length	slot	name	signature
    //   0	120	0	this	zza
    //   0	120	1	paramzzd	com.google.android.gms.dynamic.zzd
    //   0	120	2	paramzzb	zzb
    //   1	68	3	localIBinder	IBinder
    //   107	12	3	localObject1	Object
    //   5	109	4	localParcel1	Parcel
    //   10	99	5	localParcel2	Parcel
    //   14	89	6	localObject2	Object
    //   66	34	7	i	int
    // Exception table:
    //   from	to	target	type
    //   18	23	107	finally
    //   27	33	107	finally
    //   37	42	107	finally
    //   46	52	107	finally
    //   55	59	107	finally
    //   59	63	107	finally
    //   75	82	107	finally
    //   82	87	107	finally
  }
  
  /* Error */
  public void animateCameraWithDurationAndCallback(com.google.android.gms.dynamic.zzd paramzzd, int paramInt, zzb paramzzb)
  {
    // Byte code:
    //   0: aconst_null
    //   1: astore 4
    //   3: invokestatic 20	android/os/Parcel:obtain	()Landroid/os/Parcel;
    //   6: astore 5
    //   8: invokestatic 20	android/os/Parcel:obtain	()Landroid/os/Parcel;
    //   11: astore 6
    //   13: ldc 22
    //   15: astore 7
    //   17: aload 5
    //   19: aload 7
    //   21: invokevirtual 26	android/os/Parcel:writeInterfaceToken	(Ljava/lang/String;)V
    //   24: aload_1
    //   25: ifnull +84 -> 109
    //   28: aload_1
    //   29: invokeinterface 115 1 0
    //   34: astore 7
    //   36: aload 5
    //   38: aload 7
    //   40: invokevirtual 119	android/os/Parcel:writeStrongBinder	(Landroid/os/IBinder;)V
    //   43: aload 5
    //   45: iload_2
    //   46: invokevirtual 31	android/os/Parcel:writeInt	(I)V
    //   49: aload_3
    //   50: ifnull +11 -> 61
    //   53: aload_3
    //   54: invokeinterface 123 1 0
    //   59: astore 4
    //   61: aload 5
    //   63: aload 4
    //   65: invokevirtual 119	android/os/Parcel:writeStrongBinder	(Landroid/os/IBinder;)V
    //   68: aload_0
    //   69: getfield 14	com/google/android/gms/maps/internal/IGoogleMapDelegate$zza$zza:zzoz	Landroid/os/IBinder;
    //   72: astore 4
    //   74: bipush 7
    //   76: istore 8
    //   78: aload 4
    //   80: iload 8
    //   82: aload 5
    //   84: aload 6
    //   86: iconst_0
    //   87: invokeinterface 44 5 0
    //   92: pop
    //   93: aload 6
    //   95: invokevirtual 47	android/os/Parcel:readException	()V
    //   98: aload 6
    //   100: invokevirtual 60	android/os/Parcel:recycle	()V
    //   103: aload 5
    //   105: invokevirtual 60	android/os/Parcel:recycle	()V
    //   108: return
    //   109: iconst_0
    //   110: istore 8
    //   112: aconst_null
    //   113: astore 7
    //   115: goto -79 -> 36
    //   118: astore 4
    //   120: aload 6
    //   122: invokevirtual 60	android/os/Parcel:recycle	()V
    //   125: aload 5
    //   127: invokevirtual 60	android/os/Parcel:recycle	()V
    //   130: aload 4
    //   132: athrow
    // Local variable table:
    //   start	length	slot	name	signature
    //   0	133	0	this	zza
    //   0	133	1	paramzzd	com.google.android.gms.dynamic.zzd
    //   0	133	2	paramInt	int
    //   0	133	3	paramzzb	zzb
    //   1	78	4	localIBinder	IBinder
    //   118	13	4	localObject1	Object
    //   6	120	5	localParcel1	Parcel
    //   11	110	6	localParcel2	Parcel
    //   15	99	7	localObject2	Object
    //   76	35	8	i	int
    // Exception table:
    //   from	to	target	type
    //   19	24	118	finally
    //   28	34	118	finally
    //   38	43	118	finally
    //   45	49	118	finally
    //   53	59	118	finally
    //   63	68	118	finally
    //   68	72	118	finally
    //   86	93	118	finally
    //   93	98	118	finally
  }
  
  public IBinder asBinder()
  {
    return this.zzoz;
  }
  
  public void clear()
  {
    Parcel localParcel1 = Parcel.obtain();
    Parcel localParcel2 = Parcel.obtain();
    Object localObject1 = "com.google.android.gms.maps.internal.IGoogleMapDelegate";
    try
    {
      localParcel1.writeInterfaceToken((String)localObject1);
      localObject1 = this.zzoz;
      int i = 14;
      ((IBinder)localObject1).transact(i, localParcel1, localParcel2, 0);
      localParcel2.readException();
      return;
    }
    finally
    {
      localParcel2.recycle();
      localParcel1.recycle();
    }
  }
  
  /* Error */
  public com.google.android.gms.maps.model.CameraPosition getCameraPosition()
  {
    // Byte code:
    //   0: invokestatic 20	android/os/Parcel:obtain	()Landroid/os/Parcel;
    //   3: astore_1
    //   4: invokestatic 20	android/os/Parcel:obtain	()Landroid/os/Parcel;
    //   7: astore_2
    //   8: ldc 22
    //   10: astore_3
    //   11: aload_1
    //   12: aload_3
    //   13: invokevirtual 26	android/os/Parcel:writeInterfaceToken	(Ljava/lang/String;)V
    //   16: aload_0
    //   17: getfield 14	com/google/android/gms/maps/internal/IGoogleMapDelegate$zza$zza:zzoz	Landroid/os/IBinder;
    //   20: astore_3
    //   21: iconst_1
    //   22: istore 4
    //   24: aload_3
    //   25: iload 4
    //   27: aload_1
    //   28: aload_2
    //   29: iconst_0
    //   30: invokeinterface 44 5 0
    //   35: pop
    //   36: aload_2
    //   37: invokevirtual 47	android/os/Parcel:readException	()V
    //   40: aload_2
    //   41: invokevirtual 130	android/os/Parcel:readInt	()I
    //   44: istore 5
    //   46: iload 5
    //   48: ifeq +23 -> 71
    //   51: getstatic 136	com/google/android/gms/maps/model/CameraPosition:CREATOR	Lcom/google/android/gms/maps/model/zza;
    //   54: astore_3
    //   55: aload_3
    //   56: aload_2
    //   57: invokevirtual 142	com/google/android/gms/maps/model/zza:zzfv	(Landroid/os/Parcel;)Lcom/google/android/gms/maps/model/CameraPosition;
    //   60: astore_3
    //   61: aload_2
    //   62: invokevirtual 60	android/os/Parcel:recycle	()V
    //   65: aload_1
    //   66: invokevirtual 60	android/os/Parcel:recycle	()V
    //   69: aload_3
    //   70: areturn
    //   71: iconst_0
    //   72: istore 5
    //   74: aconst_null
    //   75: astore_3
    //   76: goto -15 -> 61
    //   79: astore_3
    //   80: aload_2
    //   81: invokevirtual 60	android/os/Parcel:recycle	()V
    //   84: aload_1
    //   85: invokevirtual 60	android/os/Parcel:recycle	()V
    //   88: aload_3
    //   89: athrow
    // Local variable table:
    //   start	length	slot	name	signature
    //   0	90	0	this	zza
    //   3	82	1	localParcel1	Parcel
    //   7	74	2	localParcel2	Parcel
    //   10	66	3	localObject1	Object
    //   79	10	3	localObject2	Object
    //   22	4	4	i	int
    //   44	29	5	j	int
    // Exception table:
    //   from	to	target	type
    //   12	16	79	finally
    //   16	20	79	finally
    //   29	36	79	finally
    //   36	40	79	finally
    //   40	44	79	finally
    //   51	54	79	finally
    //   56	60	79	finally
  }
  
  public zzd getFocusedBuilding()
  {
    Parcel localParcel1 = Parcel.obtain();
    Parcel localParcel2 = Parcel.obtain();
    Object localObject1 = "com.google.android.gms.maps.internal.IGoogleMapDelegate";
    try
    {
      localParcel1.writeInterfaceToken((String)localObject1);
      localObject1 = this.zzoz;
      int i = 44;
      ((IBinder)localObject1).transact(i, localParcel1, localParcel2, 0);
      localParcel2.readException();
      localObject1 = localParcel2.readStrongBinder();
      localObject1 = zzd.zza.zzdg((IBinder)localObject1);
      return (zzd)localObject1;
    }
    finally
    {
      localParcel2.recycle();
      localParcel1.recycle();
    }
  }
  
  /* Error */
  public void getMapAsync(zzo paramzzo)
  {
    // Byte code:
    //   0: invokestatic 20	android/os/Parcel:obtain	()Landroid/os/Parcel;
    //   3: astore_2
    //   4: invokestatic 20	android/os/Parcel:obtain	()Landroid/os/Parcel;
    //   7: astore_3
    //   8: ldc 22
    //   10: astore 4
    //   12: aload_2
    //   13: aload 4
    //   15: invokevirtual 26	android/os/Parcel:writeInterfaceToken	(Ljava/lang/String;)V
    //   18: aload_1
    //   19: ifnull +53 -> 72
    //   22: aload_1
    //   23: invokeinterface 152 1 0
    //   28: astore 4
    //   30: aload_2
    //   31: aload 4
    //   33: invokevirtual 119	android/os/Parcel:writeStrongBinder	(Landroid/os/IBinder;)V
    //   36: aload_0
    //   37: getfield 14	com/google/android/gms/maps/internal/IGoogleMapDelegate$zza$zza:zzoz	Landroid/os/IBinder;
    //   40: astore 4
    //   42: bipush 53
    //   44: istore 5
    //   46: aload 4
    //   48: iload 5
    //   50: aload_2
    //   51: aload_3
    //   52: iconst_0
    //   53: invokeinterface 44 5 0
    //   58: pop
    //   59: aload_3
    //   60: invokevirtual 47	android/os/Parcel:readException	()V
    //   63: aload_3
    //   64: invokevirtual 60	android/os/Parcel:recycle	()V
    //   67: aload_2
    //   68: invokevirtual 60	android/os/Parcel:recycle	()V
    //   71: return
    //   72: aconst_null
    //   73: astore 4
    //   75: goto -45 -> 30
    //   78: astore 4
    //   80: aload_3
    //   81: invokevirtual 60	android/os/Parcel:recycle	()V
    //   84: aload_2
    //   85: invokevirtual 60	android/os/Parcel:recycle	()V
    //   88: aload 4
    //   90: athrow
    // Local variable table:
    //   start	length	slot	name	signature
    //   0	91	0	this	zza
    //   0	91	1	paramzzo	zzo
    //   3	82	2	localParcel1	Parcel
    //   7	74	3	localParcel2	Parcel
    //   10	64	4	localObject1	Object
    //   78	11	4	localObject2	Object
    //   44	5	5	i	int
    // Exception table:
    //   from	to	target	type
    //   13	18	78	finally
    //   22	28	78	finally
    //   31	36	78	finally
    //   36	40	78	finally
    //   52	59	78	finally
    //   59	63	78	finally
  }
  
  public int getMapType()
  {
    Parcel localParcel1 = Parcel.obtain();
    Parcel localParcel2 = Parcel.obtain();
    Object localObject1 = "com.google.android.gms.maps.internal.IGoogleMapDelegate";
    try
    {
      localParcel1.writeInterfaceToken((String)localObject1);
      localObject1 = this.zzoz;
      int i = 15;
      ((IBinder)localObject1).transact(i, localParcel1, localParcel2, 0);
      localParcel2.readException();
      int j = localParcel2.readInt();
      return j;
    }
    finally
    {
      localParcel2.recycle();
      localParcel1.recycle();
    }
  }
  
  public float getMaxZoomLevel()
  {
    Parcel localParcel1 = Parcel.obtain();
    Parcel localParcel2 = Parcel.obtain();
    Object localObject1 = "com.google.android.gms.maps.internal.IGoogleMapDelegate";
    try
    {
      localParcel1.writeInterfaceToken((String)localObject1);
      localObject1 = this.zzoz;
      int i = 2;
      ((IBinder)localObject1).transact(i, localParcel1, localParcel2, 0);
      localParcel2.readException();
      float f = localParcel2.readFloat();
      return f;
    }
    finally
    {
      localParcel2.recycle();
      localParcel1.recycle();
    }
  }
  
  public float getMinZoomLevel()
  {
    Parcel localParcel1 = Parcel.obtain();
    Parcel localParcel2 = Parcel.obtain();
    Object localObject1 = "com.google.android.gms.maps.internal.IGoogleMapDelegate";
    try
    {
      localParcel1.writeInterfaceToken((String)localObject1);
      localObject1 = this.zzoz;
      int i = 3;
      ((IBinder)localObject1).transact(i, localParcel1, localParcel2, 0);
      localParcel2.readException();
      float f = localParcel2.readFloat();
      return f;
    }
    finally
    {
      localParcel2.recycle();
      localParcel1.recycle();
    }
  }
  
  /* Error */
  public android.location.Location getMyLocation()
  {
    // Byte code:
    //   0: invokestatic 20	android/os/Parcel:obtain	()Landroid/os/Parcel;
    //   3: astore_1
    //   4: invokestatic 20	android/os/Parcel:obtain	()Landroid/os/Parcel;
    //   7: astore_2
    //   8: ldc 22
    //   10: astore_3
    //   11: aload_1
    //   12: aload_3
    //   13: invokevirtual 26	android/os/Parcel:writeInterfaceToken	(Ljava/lang/String;)V
    //   16: aload_0
    //   17: getfield 14	com/google/android/gms/maps/internal/IGoogleMapDelegate$zza$zza:zzoz	Landroid/os/IBinder;
    //   20: astore_3
    //   21: bipush 23
    //   23: istore 4
    //   25: aload_3
    //   26: iload 4
    //   28: aload_1
    //   29: aload_2
    //   30: iconst_0
    //   31: invokeinterface 44 5 0
    //   36: pop
    //   37: aload_2
    //   38: invokevirtual 47	android/os/Parcel:readException	()V
    //   41: aload_2
    //   42: invokevirtual 130	android/os/Parcel:readInt	()I
    //   45: istore 5
    //   47: iload 5
    //   49: ifeq +30 -> 79
    //   52: getstatic 166	android/location/Location:CREATOR	Landroid/os/Parcelable$Creator;
    //   55: astore_3
    //   56: aload_3
    //   57: aload_2
    //   58: invokeinterface 172 2 0
    //   63: astore_3
    //   64: aload_3
    //   65: checkcast 163	android/location/Location
    //   68: astore_3
    //   69: aload_2
    //   70: invokevirtual 60	android/os/Parcel:recycle	()V
    //   73: aload_1
    //   74: invokevirtual 60	android/os/Parcel:recycle	()V
    //   77: aload_3
    //   78: areturn
    //   79: iconst_0
    //   80: istore 5
    //   82: aconst_null
    //   83: astore_3
    //   84: goto -15 -> 69
    //   87: astore_3
    //   88: aload_2
    //   89: invokevirtual 60	android/os/Parcel:recycle	()V
    //   92: aload_1
    //   93: invokevirtual 60	android/os/Parcel:recycle	()V
    //   96: aload_3
    //   97: athrow
    // Local variable table:
    //   start	length	slot	name	signature
    //   0	98	0	this	zza
    //   3	90	1	localParcel1	Parcel
    //   7	82	2	localParcel2	Parcel
    //   10	74	3	localObject1	Object
    //   87	10	3	localObject2	Object
    //   23	4	4	i	int
    //   45	36	5	j	int
    // Exception table:
    //   from	to	target	type
    //   12	16	87	finally
    //   16	20	87	finally
    //   30	37	87	finally
    //   37	41	87	finally
    //   41	45	87	finally
    //   52	55	87	finally
    //   57	63	87	finally
    //   64	68	87	finally
  }
  
  public IProjectionDelegate getProjection()
  {
    Parcel localParcel1 = Parcel.obtain();
    Parcel localParcel2 = Parcel.obtain();
    Object localObject1 = "com.google.android.gms.maps.internal.IGoogleMapDelegate";
    try
    {
      localParcel1.writeInterfaceToken((String)localObject1);
      localObject1 = this.zzoz;
      int i = 26;
      ((IBinder)localObject1).transact(i, localParcel1, localParcel2, 0);
      localParcel2.readException();
      localObject1 = localParcel2.readStrongBinder();
      localObject1 = IProjectionDelegate.zza.zzcX((IBinder)localObject1);
      return (IProjectionDelegate)localObject1;
    }
    finally
    {
      localParcel2.recycle();
      localParcel1.recycle();
    }
  }
  
  public IUiSettingsDelegate getUiSettings()
  {
    Parcel localParcel1 = Parcel.obtain();
    Parcel localParcel2 = Parcel.obtain();
    Object localObject1 = "com.google.android.gms.maps.internal.IGoogleMapDelegate";
    try
    {
      localParcel1.writeInterfaceToken((String)localObject1);
      localObject1 = this.zzoz;
      int i = 25;
      ((IBinder)localObject1).transact(i, localParcel1, localParcel2, 0);
      localParcel2.readException();
      localObject1 = localParcel2.readStrongBinder();
      localObject1 = IUiSettingsDelegate.zza.zzdc((IBinder)localObject1);
      return (IUiSettingsDelegate)localObject1;
    }
    finally
    {
      localParcel2.recycle();
      localParcel1.recycle();
    }
  }
  
  public boolean isBuildingsEnabled()
  {
    boolean bool = false;
    Object localObject1 = null;
    Parcel localParcel1 = Parcel.obtain();
    Parcel localParcel2 = Parcel.obtain();
    Object localObject3 = "com.google.android.gms.maps.internal.IGoogleMapDelegate";
    try
    {
      localParcel1.writeInterfaceToken((String)localObject3);
      localObject3 = this.zzoz;
      int i = 40;
      ((IBinder)localObject3).transact(i, localParcel1, localParcel2, 0);
      localParcel2.readException();
      int j = localParcel2.readInt();
      if (j != 0) {
        bool = true;
      }
      return bool;
    }
    finally
    {
      localParcel2.recycle();
      localParcel1.recycle();
    }
  }
  
  public boolean isIndoorEnabled()
  {
    boolean bool = false;
    Object localObject1 = null;
    Parcel localParcel1 = Parcel.obtain();
    Parcel localParcel2 = Parcel.obtain();
    Object localObject3 = "com.google.android.gms.maps.internal.IGoogleMapDelegate";
    try
    {
      localParcel1.writeInterfaceToken((String)localObject3);
      localObject3 = this.zzoz;
      int i = 19;
      ((IBinder)localObject3).transact(i, localParcel1, localParcel2, 0);
      localParcel2.readException();
      int j = localParcel2.readInt();
      if (j != 0) {
        bool = true;
      }
      return bool;
    }
    finally
    {
      localParcel2.recycle();
      localParcel1.recycle();
    }
  }
  
  public boolean isMyLocationEnabled()
  {
    boolean bool = false;
    Object localObject1 = null;
    Parcel localParcel1 = Parcel.obtain();
    Parcel localParcel2 = Parcel.obtain();
    Object localObject3 = "com.google.android.gms.maps.internal.IGoogleMapDelegate";
    try
    {
      localParcel1.writeInterfaceToken((String)localObject3);
      localObject3 = this.zzoz;
      int i = 21;
      ((IBinder)localObject3).transact(i, localParcel1, localParcel2, 0);
      localParcel2.readException();
      int j = localParcel2.readInt();
      if (j != 0) {
        bool = true;
      }
      return bool;
    }
    finally
    {
      localParcel2.recycle();
      localParcel1.recycle();
    }
  }
  
  public boolean isTrafficEnabled()
  {
    boolean bool = false;
    Object localObject1 = null;
    Parcel localParcel1 = Parcel.obtain();
    Parcel localParcel2 = Parcel.obtain();
    Object localObject3 = "com.google.android.gms.maps.internal.IGoogleMapDelegate";
    try
    {
      localParcel1.writeInterfaceToken((String)localObject3);
      localObject3 = this.zzoz;
      int i = 17;
      ((IBinder)localObject3).transact(i, localParcel1, localParcel2, 0);
      localParcel2.readException();
      int j = localParcel2.readInt();
      if (j != 0) {
        bool = true;
      }
      return bool;
    }
    finally
    {
      localParcel2.recycle();
      localParcel1.recycle();
    }
  }
  
  /* Error */
  public void moveCamera(com.google.android.gms.dynamic.zzd paramzzd)
  {
    // Byte code:
    //   0: invokestatic 20	android/os/Parcel:obtain	()Landroid/os/Parcel;
    //   3: astore_2
    //   4: invokestatic 20	android/os/Parcel:obtain	()Landroid/os/Parcel;
    //   7: astore_3
    //   8: ldc 22
    //   10: astore 4
    //   12: aload_2
    //   13: aload 4
    //   15: invokevirtual 26	android/os/Parcel:writeInterfaceToken	(Ljava/lang/String;)V
    //   18: aload_1
    //   19: ifnull +52 -> 71
    //   22: aload_1
    //   23: invokeinterface 115 1 0
    //   28: astore 4
    //   30: aload_2
    //   31: aload 4
    //   33: invokevirtual 119	android/os/Parcel:writeStrongBinder	(Landroid/os/IBinder;)V
    //   36: aload_0
    //   37: getfield 14	com/google/android/gms/maps/internal/IGoogleMapDelegate$zza$zza:zzoz	Landroid/os/IBinder;
    //   40: astore 4
    //   42: iconst_4
    //   43: istore 5
    //   45: aload 4
    //   47: iload 5
    //   49: aload_2
    //   50: aload_3
    //   51: iconst_0
    //   52: invokeinterface 44 5 0
    //   57: pop
    //   58: aload_3
    //   59: invokevirtual 47	android/os/Parcel:readException	()V
    //   62: aload_3
    //   63: invokevirtual 60	android/os/Parcel:recycle	()V
    //   66: aload_2
    //   67: invokevirtual 60	android/os/Parcel:recycle	()V
    //   70: return
    //   71: aconst_null
    //   72: astore 4
    //   74: goto -44 -> 30
    //   77: astore 4
    //   79: aload_3
    //   80: invokevirtual 60	android/os/Parcel:recycle	()V
    //   83: aload_2
    //   84: invokevirtual 60	android/os/Parcel:recycle	()V
    //   87: aload 4
    //   89: athrow
    // Local variable table:
    //   start	length	slot	name	signature
    //   0	90	0	this	zza
    //   0	90	1	paramzzd	com.google.android.gms.dynamic.zzd
    //   3	81	2	localParcel1	Parcel
    //   7	73	3	localParcel2	Parcel
    //   10	63	4	localObject1	Object
    //   77	11	4	localObject2	Object
    //   43	5	5	i	int
    // Exception table:
    //   from	to	target	type
    //   13	18	77	finally
    //   22	28	77	finally
    //   31	36	77	finally
    //   36	40	77	finally
    //   51	58	77	finally
    //   58	62	77	finally
  }
  
  /* Error */
  public void onCreate(android.os.Bundle paramBundle)
  {
    // Byte code:
    //   0: invokestatic 20	android/os/Parcel:obtain	()Landroid/os/Parcel;
    //   3: astore_2
    //   4: invokestatic 20	android/os/Parcel:obtain	()Landroid/os/Parcel;
    //   7: astore_3
    //   8: ldc 22
    //   10: astore 4
    //   12: aload_2
    //   13: aload 4
    //   15: invokevirtual 26	android/os/Parcel:writeInterfaceToken	(Ljava/lang/String;)V
    //   18: aload_1
    //   19: ifnull +60 -> 79
    //   22: iconst_1
    //   23: istore 5
    //   25: aload_2
    //   26: iload 5
    //   28: invokevirtual 31	android/os/Parcel:writeInt	(I)V
    //   31: iconst_0
    //   32: istore 5
    //   34: aconst_null
    //   35: astore 4
    //   37: aload_1
    //   38: aload_2
    //   39: iconst_0
    //   40: invokevirtual 194	android/os/Bundle:writeToParcel	(Landroid/os/Parcel;I)V
    //   43: aload_0
    //   44: getfield 14	com/google/android/gms/maps/internal/IGoogleMapDelegate$zza$zza:zzoz	Landroid/os/IBinder;
    //   47: astore 4
    //   49: bipush 54
    //   51: istore 6
    //   53: aload 4
    //   55: iload 6
    //   57: aload_2
    //   58: aload_3
    //   59: iconst_0
    //   60: invokeinterface 44 5 0
    //   65: pop
    //   66: aload_3
    //   67: invokevirtual 47	android/os/Parcel:readException	()V
    //   70: aload_3
    //   71: invokevirtual 60	android/os/Parcel:recycle	()V
    //   74: aload_2
    //   75: invokevirtual 60	android/os/Parcel:recycle	()V
    //   78: return
    //   79: iconst_0
    //   80: istore 5
    //   82: aconst_null
    //   83: astore 4
    //   85: aload_2
    //   86: iconst_0
    //   87: invokevirtual 31	android/os/Parcel:writeInt	(I)V
    //   90: goto -47 -> 43
    //   93: astore 4
    //   95: aload_3
    //   96: invokevirtual 60	android/os/Parcel:recycle	()V
    //   99: aload_2
    //   100: invokevirtual 60	android/os/Parcel:recycle	()V
    //   103: aload 4
    //   105: athrow
    // Local variable table:
    //   start	length	slot	name	signature
    //   0	106	0	this	zza
    //   0	106	1	paramBundle	android.os.Bundle
    //   3	97	2	localParcel1	Parcel
    //   7	89	3	localParcel2	Parcel
    //   10	74	4	localObject1	Object
    //   93	11	4	localObject2	Object
    //   23	58	5	i	int
    //   51	5	6	j	int
    // Exception table:
    //   from	to	target	type
    //   13	18	93	finally
    //   26	31	93	finally
    //   39	43	93	finally
    //   43	47	93	finally
    //   59	66	93	finally
    //   66	70	93	finally
    //   86	90	93	finally
  }
  
  public void onDestroy()
  {
    Parcel localParcel1 = Parcel.obtain();
    Parcel localParcel2 = Parcel.obtain();
    Object localObject1 = "com.google.android.gms.maps.internal.IGoogleMapDelegate";
    try
    {
      localParcel1.writeInterfaceToken((String)localObject1);
      localObject1 = this.zzoz;
      int i = 57;
      ((IBinder)localObject1).transact(i, localParcel1, localParcel2, 0);
      localParcel2.readException();
      return;
    }
    finally
    {
      localParcel2.recycle();
      localParcel1.recycle();
    }
  }
  
  /* Error */
  public void onEnterAmbient(android.os.Bundle paramBundle)
  {
    // Byte code:
    //   0: invokestatic 20	android/os/Parcel:obtain	()Landroid/os/Parcel;
    //   3: astore_2
    //   4: invokestatic 20	android/os/Parcel:obtain	()Landroid/os/Parcel;
    //   7: astore_3
    //   8: ldc 22
    //   10: astore 4
    //   12: aload_2
    //   13: aload 4
    //   15: invokevirtual 26	android/os/Parcel:writeInterfaceToken	(Ljava/lang/String;)V
    //   18: aload_1
    //   19: ifnull +60 -> 79
    //   22: iconst_1
    //   23: istore 5
    //   25: aload_2
    //   26: iload 5
    //   28: invokevirtual 31	android/os/Parcel:writeInt	(I)V
    //   31: iconst_0
    //   32: istore 5
    //   34: aconst_null
    //   35: astore 4
    //   37: aload_1
    //   38: aload_2
    //   39: iconst_0
    //   40: invokevirtual 194	android/os/Bundle:writeToParcel	(Landroid/os/Parcel;I)V
    //   43: aload_0
    //   44: getfield 14	com/google/android/gms/maps/internal/IGoogleMapDelegate$zza$zza:zzoz	Landroid/os/IBinder;
    //   47: astore 4
    //   49: bipush 81
    //   51: istore 6
    //   53: aload 4
    //   55: iload 6
    //   57: aload_2
    //   58: aload_3
    //   59: iconst_0
    //   60: invokeinterface 44 5 0
    //   65: pop
    //   66: aload_3
    //   67: invokevirtual 47	android/os/Parcel:readException	()V
    //   70: aload_3
    //   71: invokevirtual 60	android/os/Parcel:recycle	()V
    //   74: aload_2
    //   75: invokevirtual 60	android/os/Parcel:recycle	()V
    //   78: return
    //   79: iconst_0
    //   80: istore 5
    //   82: aconst_null
    //   83: astore 4
    //   85: aload_2
    //   86: iconst_0
    //   87: invokevirtual 31	android/os/Parcel:writeInt	(I)V
    //   90: goto -47 -> 43
    //   93: astore 4
    //   95: aload_3
    //   96: invokevirtual 60	android/os/Parcel:recycle	()V
    //   99: aload_2
    //   100: invokevirtual 60	android/os/Parcel:recycle	()V
    //   103: aload 4
    //   105: athrow
    // Local variable table:
    //   start	length	slot	name	signature
    //   0	106	0	this	zza
    //   0	106	1	paramBundle	android.os.Bundle
    //   3	97	2	localParcel1	Parcel
    //   7	89	3	localParcel2	Parcel
    //   10	74	4	localObject1	Object
    //   93	11	4	localObject2	Object
    //   23	58	5	i	int
    //   51	5	6	j	int
    // Exception table:
    //   from	to	target	type
    //   13	18	93	finally
    //   26	31	93	finally
    //   39	43	93	finally
    //   43	47	93	finally
    //   59	66	93	finally
    //   66	70	93	finally
    //   86	90	93	finally
  }
  
  public void onExitAmbient()
  {
    Parcel localParcel1 = Parcel.obtain();
    Parcel localParcel2 = Parcel.obtain();
    Object localObject1 = "com.google.android.gms.maps.internal.IGoogleMapDelegate";
    try
    {
      localParcel1.writeInterfaceToken((String)localObject1);
      localObject1 = this.zzoz;
      int i = 82;
      ((IBinder)localObject1).transact(i, localParcel1, localParcel2, 0);
      localParcel2.readException();
      return;
    }
    finally
    {
      localParcel2.recycle();
      localParcel1.recycle();
    }
  }
  
  public void onLowMemory()
  {
    Parcel localParcel1 = Parcel.obtain();
    Parcel localParcel2 = Parcel.obtain();
    Object localObject1 = "com.google.android.gms.maps.internal.IGoogleMapDelegate";
    try
    {
      localParcel1.writeInterfaceToken((String)localObject1);
      localObject1 = this.zzoz;
      int i = 58;
      ((IBinder)localObject1).transact(i, localParcel1, localParcel2, 0);
      localParcel2.readException();
      return;
    }
    finally
    {
      localParcel2.recycle();
      localParcel1.recycle();
    }
  }
  
  public void onPause()
  {
    Parcel localParcel1 = Parcel.obtain();
    Parcel localParcel2 = Parcel.obtain();
    Object localObject1 = "com.google.android.gms.maps.internal.IGoogleMapDelegate";
    try
    {
      localParcel1.writeInterfaceToken((String)localObject1);
      localObject1 = this.zzoz;
      int i = 56;
      ((IBinder)localObject1).transact(i, localParcel1, localParcel2, 0);
      localParcel2.readException();
      return;
    }
    finally
    {
      localParcel2.recycle();
      localParcel1.recycle();
    }
  }
  
  public void onResume()
  {
    Parcel localParcel1 = Parcel.obtain();
    Parcel localParcel2 = Parcel.obtain();
    Object localObject1 = "com.google.android.gms.maps.internal.IGoogleMapDelegate";
    try
    {
      localParcel1.writeInterfaceToken((String)localObject1);
      localObject1 = this.zzoz;
      int i = 55;
      ((IBinder)localObject1).transact(i, localParcel1, localParcel2, 0);
      localParcel2.readException();
      return;
    }
    finally
    {
      localParcel2.recycle();
      localParcel1.recycle();
    }
  }
  
  /* Error */
  public void onSaveInstanceState(android.os.Bundle paramBundle)
  {
    // Byte code:
    //   0: invokestatic 20	android/os/Parcel:obtain	()Landroid/os/Parcel;
    //   3: astore_2
    //   4: invokestatic 20	android/os/Parcel:obtain	()Landroid/os/Parcel;
    //   7: astore_3
    //   8: ldc 22
    //   10: astore 4
    //   12: aload_2
    //   13: aload 4
    //   15: invokevirtual 26	android/os/Parcel:writeInterfaceToken	(Ljava/lang/String;)V
    //   18: aload_1
    //   19: ifnull +76 -> 95
    //   22: iconst_1
    //   23: istore 5
    //   25: aload_2
    //   26: iload 5
    //   28: invokevirtual 31	android/os/Parcel:writeInt	(I)V
    //   31: iconst_0
    //   32: istore 5
    //   34: aconst_null
    //   35: astore 4
    //   37: aload_1
    //   38: aload_2
    //   39: iconst_0
    //   40: invokevirtual 194	android/os/Bundle:writeToParcel	(Landroid/os/Parcel;I)V
    //   43: aload_0
    //   44: getfield 14	com/google/android/gms/maps/internal/IGoogleMapDelegate$zza$zza:zzoz	Landroid/os/IBinder;
    //   47: astore 4
    //   49: bipush 60
    //   51: istore 6
    //   53: aload 4
    //   55: iload 6
    //   57: aload_2
    //   58: aload_3
    //   59: iconst_0
    //   60: invokeinterface 44 5 0
    //   65: pop
    //   66: aload_3
    //   67: invokevirtual 47	android/os/Parcel:readException	()V
    //   70: aload_3
    //   71: invokevirtual 130	android/os/Parcel:readInt	()I
    //   74: istore 5
    //   76: iload 5
    //   78: ifeq +8 -> 86
    //   81: aload_1
    //   82: aload_3
    //   83: invokevirtual 206	android/os/Bundle:readFromParcel	(Landroid/os/Parcel;)V
    //   86: aload_3
    //   87: invokevirtual 60	android/os/Parcel:recycle	()V
    //   90: aload_2
    //   91: invokevirtual 60	android/os/Parcel:recycle	()V
    //   94: return
    //   95: iconst_0
    //   96: istore 5
    //   98: aconst_null
    //   99: astore 4
    //   101: aload_2
    //   102: iconst_0
    //   103: invokevirtual 31	android/os/Parcel:writeInt	(I)V
    //   106: goto -63 -> 43
    //   109: astore 4
    //   111: aload_3
    //   112: invokevirtual 60	android/os/Parcel:recycle	()V
    //   115: aload_2
    //   116: invokevirtual 60	android/os/Parcel:recycle	()V
    //   119: aload 4
    //   121: athrow
    // Local variable table:
    //   start	length	slot	name	signature
    //   0	122	0	this	zza
    //   0	122	1	paramBundle	android.os.Bundle
    //   3	113	2	localParcel1	Parcel
    //   7	105	3	localParcel2	Parcel
    //   10	90	4	localObject1	Object
    //   109	11	4	localObject2	Object
    //   23	74	5	i	int
    //   51	5	6	j	int
    // Exception table:
    //   from	to	target	type
    //   13	18	109	finally
    //   26	31	109	finally
    //   39	43	109	finally
    //   43	47	109	finally
    //   59	66	109	finally
    //   66	70	109	finally
    //   70	74	109	finally
    //   82	86	109	finally
    //   102	106	109	finally
  }
  
  public void setBuildingsEnabled(boolean paramBoolean)
  {
    int i = 0;
    IBinder localIBinder = null;
    Parcel localParcel1 = Parcel.obtain();
    Parcel localParcel2 = Parcel.obtain();
    String str = "com.google.android.gms.maps.internal.IGoogleMapDelegate";
    try
    {
      localParcel1.writeInterfaceToken(str);
      if (paramBoolean) {
        i = 1;
      }
      localParcel1.writeInt(i);
      localIBinder = this.zzoz;
      int j = 41;
      localIBinder.transact(j, localParcel1, localParcel2, 0);
      localParcel2.readException();
      return;
    }
    finally
    {
      localParcel2.recycle();
      localParcel1.recycle();
    }
  }
  
  public void setContentDescription(String paramString)
  {
    Parcel localParcel1 = Parcel.obtain();
    Parcel localParcel2 = Parcel.obtain();
    Object localObject1 = "com.google.android.gms.maps.internal.IGoogleMapDelegate";
    try
    {
      localParcel1.writeInterfaceToken((String)localObject1);
      localParcel1.writeString(paramString);
      localObject1 = this.zzoz;
      int i = 61;
      ((IBinder)localObject1).transact(i, localParcel1, localParcel2, 0);
      localParcel2.readException();
      return;
    }
    finally
    {
      localParcel2.recycle();
      localParcel1.recycle();
    }
  }
  
  /* Error */
  public boolean setIndoorEnabled(boolean paramBoolean)
  {
    // Byte code:
    //   0: iconst_1
    //   1: istore_2
    //   2: invokestatic 20	android/os/Parcel:obtain	()Landroid/os/Parcel;
    //   5: astore_3
    //   6: invokestatic 20	android/os/Parcel:obtain	()Landroid/os/Parcel;
    //   9: astore 4
    //   11: ldc 22
    //   13: astore 5
    //   15: aload_3
    //   16: aload 5
    //   18: invokevirtual 26	android/os/Parcel:writeInterfaceToken	(Ljava/lang/String;)V
    //   21: iload_1
    //   22: ifeq +64 -> 86
    //   25: iload_2
    //   26: istore 6
    //   28: aload_3
    //   29: iload 6
    //   31: invokevirtual 31	android/os/Parcel:writeInt	(I)V
    //   34: aload_0
    //   35: getfield 14	com/google/android/gms/maps/internal/IGoogleMapDelegate$zza$zza:zzoz	Landroid/os/IBinder;
    //   38: astore 5
    //   40: bipush 20
    //   42: istore 7
    //   44: aload 5
    //   46: iload 7
    //   48: aload_3
    //   49: aload 4
    //   51: iconst_0
    //   52: invokeinterface 44 5 0
    //   57: pop
    //   58: aload 4
    //   60: invokevirtual 47	android/os/Parcel:readException	()V
    //   63: aload 4
    //   65: invokevirtual 130	android/os/Parcel:readInt	()I
    //   68: istore 6
    //   70: iload 6
    //   72: ifeq +23 -> 95
    //   75: aload 4
    //   77: invokevirtual 60	android/os/Parcel:recycle	()V
    //   80: aload_3
    //   81: invokevirtual 60	android/os/Parcel:recycle	()V
    //   84: iload_2
    //   85: ireturn
    //   86: iconst_0
    //   87: istore 6
    //   89: aconst_null
    //   90: astore 5
    //   92: goto -64 -> 28
    //   95: iconst_0
    //   96: istore_2
    //   97: aconst_null
    //   98: astore 8
    //   100: goto -25 -> 75
    //   103: astore 8
    //   105: aload 4
    //   107: invokevirtual 60	android/os/Parcel:recycle	()V
    //   110: aload_3
    //   111: invokevirtual 60	android/os/Parcel:recycle	()V
    //   114: aload 8
    //   116: athrow
    // Local variable table:
    //   start	length	slot	name	signature
    //   0	117	0	this	zza
    //   0	117	1	paramBoolean	boolean
    //   1	96	2	i	int
    //   5	106	3	localParcel1	Parcel
    //   9	97	4	localParcel2	Parcel
    //   13	78	5	localObject1	Object
    //   26	4	6	j	int
    //   68	20	6	k	int
    //   42	5	7	m	int
    //   98	1	8	localObject2	Object
    //   103	12	8	localObject3	Object
    // Exception table:
    //   from	to	target	type
    //   16	21	103	finally
    //   29	34	103	finally
    //   34	38	103	finally
    //   51	58	103	finally
    //   58	63	103	finally
    //   63	68	103	finally
  }
  
  /* Error */
  public void setInfoWindowAdapter(zzd paramzzd)
  {
    // Byte code:
    //   0: invokestatic 20	android/os/Parcel:obtain	()Landroid/os/Parcel;
    //   3: astore_2
    //   4: invokestatic 20	android/os/Parcel:obtain	()Landroid/os/Parcel;
    //   7: astore_3
    //   8: ldc 22
    //   10: astore 4
    //   12: aload_2
    //   13: aload 4
    //   15: invokevirtual 26	android/os/Parcel:writeInterfaceToken	(Ljava/lang/String;)V
    //   18: aload_1
    //   19: ifnull +53 -> 72
    //   22: aload_1
    //   23: invokeinterface 215 1 0
    //   28: astore 4
    //   30: aload_2
    //   31: aload 4
    //   33: invokevirtual 119	android/os/Parcel:writeStrongBinder	(Landroid/os/IBinder;)V
    //   36: aload_0
    //   37: getfield 14	com/google/android/gms/maps/internal/IGoogleMapDelegate$zza$zza:zzoz	Landroid/os/IBinder;
    //   40: astore 4
    //   42: bipush 33
    //   44: istore 5
    //   46: aload 4
    //   48: iload 5
    //   50: aload_2
    //   51: aload_3
    //   52: iconst_0
    //   53: invokeinterface 44 5 0
    //   58: pop
    //   59: aload_3
    //   60: invokevirtual 47	android/os/Parcel:readException	()V
    //   63: aload_3
    //   64: invokevirtual 60	android/os/Parcel:recycle	()V
    //   67: aload_2
    //   68: invokevirtual 60	android/os/Parcel:recycle	()V
    //   71: return
    //   72: aconst_null
    //   73: astore 4
    //   75: goto -45 -> 30
    //   78: astore 4
    //   80: aload_3
    //   81: invokevirtual 60	android/os/Parcel:recycle	()V
    //   84: aload_2
    //   85: invokevirtual 60	android/os/Parcel:recycle	()V
    //   88: aload 4
    //   90: athrow
    // Local variable table:
    //   start	length	slot	name	signature
    //   0	91	0	this	zza
    //   0	91	1	paramzzd	zzd
    //   3	82	2	localParcel1	Parcel
    //   7	74	3	localParcel2	Parcel
    //   10	64	4	localObject1	Object
    //   78	11	4	localObject2	Object
    //   44	5	5	i	int
    // Exception table:
    //   from	to	target	type
    //   13	18	78	finally
    //   22	28	78	finally
    //   31	36	78	finally
    //   36	40	78	finally
    //   52	59	78	finally
    //   59	63	78	finally
  }
  
  /* Error */
  public void setLocationSource(ILocationSourceDelegate paramILocationSourceDelegate)
  {
    // Byte code:
    //   0: invokestatic 20	android/os/Parcel:obtain	()Landroid/os/Parcel;
    //   3: astore_2
    //   4: invokestatic 20	android/os/Parcel:obtain	()Landroid/os/Parcel;
    //   7: astore_3
    //   8: ldc 22
    //   10: astore 4
    //   12: aload_2
    //   13: aload 4
    //   15: invokevirtual 26	android/os/Parcel:writeInterfaceToken	(Ljava/lang/String;)V
    //   18: aload_1
    //   19: ifnull +53 -> 72
    //   22: aload_1
    //   23: invokeinterface 219 1 0
    //   28: astore 4
    //   30: aload_2
    //   31: aload 4
    //   33: invokevirtual 119	android/os/Parcel:writeStrongBinder	(Landroid/os/IBinder;)V
    //   36: aload_0
    //   37: getfield 14	com/google/android/gms/maps/internal/IGoogleMapDelegate$zza$zza:zzoz	Landroid/os/IBinder;
    //   40: astore 4
    //   42: bipush 24
    //   44: istore 5
    //   46: aload 4
    //   48: iload 5
    //   50: aload_2
    //   51: aload_3
    //   52: iconst_0
    //   53: invokeinterface 44 5 0
    //   58: pop
    //   59: aload_3
    //   60: invokevirtual 47	android/os/Parcel:readException	()V
    //   63: aload_3
    //   64: invokevirtual 60	android/os/Parcel:recycle	()V
    //   67: aload_2
    //   68: invokevirtual 60	android/os/Parcel:recycle	()V
    //   71: return
    //   72: aconst_null
    //   73: astore 4
    //   75: goto -45 -> 30
    //   78: astore 4
    //   80: aload_3
    //   81: invokevirtual 60	android/os/Parcel:recycle	()V
    //   84: aload_2
    //   85: invokevirtual 60	android/os/Parcel:recycle	()V
    //   88: aload 4
    //   90: athrow
    // Local variable table:
    //   start	length	slot	name	signature
    //   0	91	0	this	zza
    //   0	91	1	paramILocationSourceDelegate	ILocationSourceDelegate
    //   3	82	2	localParcel1	Parcel
    //   7	74	3	localParcel2	Parcel
    //   10	64	4	localObject1	Object
    //   78	11	4	localObject2	Object
    //   44	5	5	i	int
    // Exception table:
    //   from	to	target	type
    //   13	18	78	finally
    //   22	28	78	finally
    //   31	36	78	finally
    //   36	40	78	finally
    //   52	59	78	finally
    //   59	63	78	finally
  }
  
  public void setMapType(int paramInt)
  {
    Parcel localParcel1 = Parcel.obtain();
    Parcel localParcel2 = Parcel.obtain();
    Object localObject1 = "com.google.android.gms.maps.internal.IGoogleMapDelegate";
    try
    {
      localParcel1.writeInterfaceToken((String)localObject1);
      localParcel1.writeInt(paramInt);
      localObject1 = this.zzoz;
      int i = 16;
      ((IBinder)localObject1).transact(i, localParcel1, localParcel2, 0);
      localParcel2.readException();
      return;
    }
    finally
    {
      localParcel2.recycle();
      localParcel1.recycle();
    }
  }
  
  public void setMyLocationEnabled(boolean paramBoolean)
  {
    int i = 0;
    IBinder localIBinder = null;
    Parcel localParcel1 = Parcel.obtain();
    Parcel localParcel2 = Parcel.obtain();
    String str = "com.google.android.gms.maps.internal.IGoogleMapDelegate";
    try
    {
      localParcel1.writeInterfaceToken(str);
      if (paramBoolean) {
        i = 1;
      }
      localParcel1.writeInt(i);
      localIBinder = this.zzoz;
      int j = 22;
      localIBinder.transact(j, localParcel1, localParcel2, 0);
      localParcel2.readException();
      return;
    }
    finally
    {
      localParcel2.recycle();
      localParcel1.recycle();
    }
  }
  
  /* Error */
  public void setOnCameraChangeListener(zze paramzze)
  {
    // Byte code:
    //   0: invokestatic 20	android/os/Parcel:obtain	()Landroid/os/Parcel;
    //   3: astore_2
    //   4: invokestatic 20	android/os/Parcel:obtain	()Landroid/os/Parcel;
    //   7: astore_3
    //   8: ldc 22
    //   10: astore 4
    //   12: aload_2
    //   13: aload 4
    //   15: invokevirtual 26	android/os/Parcel:writeInterfaceToken	(Ljava/lang/String;)V
    //   18: aload_1
    //   19: ifnull +53 -> 72
    //   22: aload_1
    //   23: invokeinterface 225 1 0
    //   28: astore 4
    //   30: aload_2
    //   31: aload 4
    //   33: invokevirtual 119	android/os/Parcel:writeStrongBinder	(Landroid/os/IBinder;)V
    //   36: aload_0
    //   37: getfield 14	com/google/android/gms/maps/internal/IGoogleMapDelegate$zza$zza:zzoz	Landroid/os/IBinder;
    //   40: astore 4
    //   42: bipush 27
    //   44: istore 5
    //   46: aload 4
    //   48: iload 5
    //   50: aload_2
    //   51: aload_3
    //   52: iconst_0
    //   53: invokeinterface 44 5 0
    //   58: pop
    //   59: aload_3
    //   60: invokevirtual 47	android/os/Parcel:readException	()V
    //   63: aload_3
    //   64: invokevirtual 60	android/os/Parcel:recycle	()V
    //   67: aload_2
    //   68: invokevirtual 60	android/os/Parcel:recycle	()V
    //   71: return
    //   72: aconst_null
    //   73: astore 4
    //   75: goto -45 -> 30
    //   78: astore 4
    //   80: aload_3
    //   81: invokevirtual 60	android/os/Parcel:recycle	()V
    //   84: aload_2
    //   85: invokevirtual 60	android/os/Parcel:recycle	()V
    //   88: aload 4
    //   90: athrow
    // Local variable table:
    //   start	length	slot	name	signature
    //   0	91	0	this	zza
    //   0	91	1	paramzze	zze
    //   3	82	2	localParcel1	Parcel
    //   7	74	3	localParcel2	Parcel
    //   10	64	4	localObject1	Object
    //   78	11	4	localObject2	Object
    //   44	5	5	i	int
    // Exception table:
    //   from	to	target	type
    //   13	18	78	finally
    //   22	28	78	finally
    //   31	36	78	finally
    //   36	40	78	finally
    //   52	59	78	finally
    //   59	63	78	finally
  }
  
  /* Error */
  public void setOnGroundOverlayClickListener(zzf paramzzf)
  {
    // Byte code:
    //   0: invokestatic 20	android/os/Parcel:obtain	()Landroid/os/Parcel;
    //   3: astore_2
    //   4: invokestatic 20	android/os/Parcel:obtain	()Landroid/os/Parcel;
    //   7: astore_3
    //   8: ldc 22
    //   10: astore 4
    //   12: aload_2
    //   13: aload 4
    //   15: invokevirtual 26	android/os/Parcel:writeInterfaceToken	(Ljava/lang/String;)V
    //   18: aload_1
    //   19: ifnull +53 -> 72
    //   22: aload_1
    //   23: invokeinterface 229 1 0
    //   28: astore 4
    //   30: aload_2
    //   31: aload 4
    //   33: invokevirtual 119	android/os/Parcel:writeStrongBinder	(Landroid/os/IBinder;)V
    //   36: aload_0
    //   37: getfield 14	com/google/android/gms/maps/internal/IGoogleMapDelegate$zza$zza:zzoz	Landroid/os/IBinder;
    //   40: astore 4
    //   42: bipush 83
    //   44: istore 5
    //   46: aload 4
    //   48: iload 5
    //   50: aload_2
    //   51: aload_3
    //   52: iconst_0
    //   53: invokeinterface 44 5 0
    //   58: pop
    //   59: aload_3
    //   60: invokevirtual 47	android/os/Parcel:readException	()V
    //   63: aload_3
    //   64: invokevirtual 60	android/os/Parcel:recycle	()V
    //   67: aload_2
    //   68: invokevirtual 60	android/os/Parcel:recycle	()V
    //   71: return
    //   72: aconst_null
    //   73: astore 4
    //   75: goto -45 -> 30
    //   78: astore 4
    //   80: aload_3
    //   81: invokevirtual 60	android/os/Parcel:recycle	()V
    //   84: aload_2
    //   85: invokevirtual 60	android/os/Parcel:recycle	()V
    //   88: aload 4
    //   90: athrow
    // Local variable table:
    //   start	length	slot	name	signature
    //   0	91	0	this	zza
    //   0	91	1	paramzzf	zzf
    //   3	82	2	localParcel1	Parcel
    //   7	74	3	localParcel2	Parcel
    //   10	64	4	localObject1	Object
    //   78	11	4	localObject2	Object
    //   44	5	5	i	int
    // Exception table:
    //   from	to	target	type
    //   13	18	78	finally
    //   22	28	78	finally
    //   31	36	78	finally
    //   36	40	78	finally
    //   52	59	78	finally
    //   59	63	78	finally
  }
  
  /* Error */
  public void setOnIndoorStateChangeListener(zzg paramzzg)
  {
    // Byte code:
    //   0: invokestatic 20	android/os/Parcel:obtain	()Landroid/os/Parcel;
    //   3: astore_2
    //   4: invokestatic 20	android/os/Parcel:obtain	()Landroid/os/Parcel;
    //   7: astore_3
    //   8: ldc 22
    //   10: astore 4
    //   12: aload_2
    //   13: aload 4
    //   15: invokevirtual 26	android/os/Parcel:writeInterfaceToken	(Ljava/lang/String;)V
    //   18: aload_1
    //   19: ifnull +53 -> 72
    //   22: aload_1
    //   23: invokeinterface 233 1 0
    //   28: astore 4
    //   30: aload_2
    //   31: aload 4
    //   33: invokevirtual 119	android/os/Parcel:writeStrongBinder	(Landroid/os/IBinder;)V
    //   36: aload_0
    //   37: getfield 14	com/google/android/gms/maps/internal/IGoogleMapDelegate$zza$zza:zzoz	Landroid/os/IBinder;
    //   40: astore 4
    //   42: bipush 45
    //   44: istore 5
    //   46: aload 4
    //   48: iload 5
    //   50: aload_2
    //   51: aload_3
    //   52: iconst_0
    //   53: invokeinterface 44 5 0
    //   58: pop
    //   59: aload_3
    //   60: invokevirtual 47	android/os/Parcel:readException	()V
    //   63: aload_3
    //   64: invokevirtual 60	android/os/Parcel:recycle	()V
    //   67: aload_2
    //   68: invokevirtual 60	android/os/Parcel:recycle	()V
    //   71: return
    //   72: aconst_null
    //   73: astore 4
    //   75: goto -45 -> 30
    //   78: astore 4
    //   80: aload_3
    //   81: invokevirtual 60	android/os/Parcel:recycle	()V
    //   84: aload_2
    //   85: invokevirtual 60	android/os/Parcel:recycle	()V
    //   88: aload 4
    //   90: athrow
    // Local variable table:
    //   start	length	slot	name	signature
    //   0	91	0	this	zza
    //   0	91	1	paramzzg	zzg
    //   3	82	2	localParcel1	Parcel
    //   7	74	3	localParcel2	Parcel
    //   10	64	4	localObject1	Object
    //   78	11	4	localObject2	Object
    //   44	5	5	i	int
    // Exception table:
    //   from	to	target	type
    //   13	18	78	finally
    //   22	28	78	finally
    //   31	36	78	finally
    //   36	40	78	finally
    //   52	59	78	finally
    //   59	63	78	finally
  }
  
  /* Error */
  public void setOnInfoWindowClickListener(zzh paramzzh)
  {
    // Byte code:
    //   0: invokestatic 20	android/os/Parcel:obtain	()Landroid/os/Parcel;
    //   3: astore_2
    //   4: invokestatic 20	android/os/Parcel:obtain	()Landroid/os/Parcel;
    //   7: astore_3
    //   8: ldc 22
    //   10: astore 4
    //   12: aload_2
    //   13: aload 4
    //   15: invokevirtual 26	android/os/Parcel:writeInterfaceToken	(Ljava/lang/String;)V
    //   18: aload_1
    //   19: ifnull +53 -> 72
    //   22: aload_1
    //   23: invokeinterface 237 1 0
    //   28: astore 4
    //   30: aload_2
    //   31: aload 4
    //   33: invokevirtual 119	android/os/Parcel:writeStrongBinder	(Landroid/os/IBinder;)V
    //   36: aload_0
    //   37: getfield 14	com/google/android/gms/maps/internal/IGoogleMapDelegate$zza$zza:zzoz	Landroid/os/IBinder;
    //   40: astore 4
    //   42: bipush 32
    //   44: istore 5
    //   46: aload 4
    //   48: iload 5
    //   50: aload_2
    //   51: aload_3
    //   52: iconst_0
    //   53: invokeinterface 44 5 0
    //   58: pop
    //   59: aload_3
    //   60: invokevirtual 47	android/os/Parcel:readException	()V
    //   63: aload_3
    //   64: invokevirtual 60	android/os/Parcel:recycle	()V
    //   67: aload_2
    //   68: invokevirtual 60	android/os/Parcel:recycle	()V
    //   71: return
    //   72: aconst_null
    //   73: astore 4
    //   75: goto -45 -> 30
    //   78: astore 4
    //   80: aload_3
    //   81: invokevirtual 60	android/os/Parcel:recycle	()V
    //   84: aload_2
    //   85: invokevirtual 60	android/os/Parcel:recycle	()V
    //   88: aload 4
    //   90: athrow
    // Local variable table:
    //   start	length	slot	name	signature
    //   0	91	0	this	zza
    //   0	91	1	paramzzh	zzh
    //   3	82	2	localParcel1	Parcel
    //   7	74	3	localParcel2	Parcel
    //   10	64	4	localObject1	Object
    //   78	11	4	localObject2	Object
    //   44	5	5	i	int
    // Exception table:
    //   from	to	target	type
    //   13	18	78	finally
    //   22	28	78	finally
    //   31	36	78	finally
    //   36	40	78	finally
    //   52	59	78	finally
    //   59	63	78	finally
  }
  
  /* Error */
  public void setOnInfoWindowCloseListener(zzi paramzzi)
  {
    // Byte code:
    //   0: invokestatic 20	android/os/Parcel:obtain	()Landroid/os/Parcel;
    //   3: astore_2
    //   4: invokestatic 20	android/os/Parcel:obtain	()Landroid/os/Parcel;
    //   7: astore_3
    //   8: ldc 22
    //   10: astore 4
    //   12: aload_2
    //   13: aload 4
    //   15: invokevirtual 26	android/os/Parcel:writeInterfaceToken	(Ljava/lang/String;)V
    //   18: aload_1
    //   19: ifnull +53 -> 72
    //   22: aload_1
    //   23: invokeinterface 241 1 0
    //   28: astore 4
    //   30: aload_2
    //   31: aload 4
    //   33: invokevirtual 119	android/os/Parcel:writeStrongBinder	(Landroid/os/IBinder;)V
    //   36: aload_0
    //   37: getfield 14	com/google/android/gms/maps/internal/IGoogleMapDelegate$zza$zza:zzoz	Landroid/os/IBinder;
    //   40: astore 4
    //   42: bipush 86
    //   44: istore 5
    //   46: aload 4
    //   48: iload 5
    //   50: aload_2
    //   51: aload_3
    //   52: iconst_0
    //   53: invokeinterface 44 5 0
    //   58: pop
    //   59: aload_3
    //   60: invokevirtual 47	android/os/Parcel:readException	()V
    //   63: aload_3
    //   64: invokevirtual 60	android/os/Parcel:recycle	()V
    //   67: aload_2
    //   68: invokevirtual 60	android/os/Parcel:recycle	()V
    //   71: return
    //   72: aconst_null
    //   73: astore 4
    //   75: goto -45 -> 30
    //   78: astore 4
    //   80: aload_3
    //   81: invokevirtual 60	android/os/Parcel:recycle	()V
    //   84: aload_2
    //   85: invokevirtual 60	android/os/Parcel:recycle	()V
    //   88: aload 4
    //   90: athrow
    // Local variable table:
    //   start	length	slot	name	signature
    //   0	91	0	this	zza
    //   0	91	1	paramzzi	zzi
    //   3	82	2	localParcel1	Parcel
    //   7	74	3	localParcel2	Parcel
    //   10	64	4	localObject1	Object
    //   78	11	4	localObject2	Object
    //   44	5	5	i	int
    // Exception table:
    //   from	to	target	type
    //   13	18	78	finally
    //   22	28	78	finally
    //   31	36	78	finally
    //   36	40	78	finally
    //   52	59	78	finally
    //   59	63	78	finally
  }
  
  /* Error */
  public void setOnInfoWindowLongClickListener(zzj paramzzj)
  {
    // Byte code:
    //   0: invokestatic 20	android/os/Parcel:obtain	()Landroid/os/Parcel;
    //   3: astore_2
    //   4: invokestatic 20	android/os/Parcel:obtain	()Landroid/os/Parcel;
    //   7: astore_3
    //   8: ldc 22
    //   10: astore 4
    //   12: aload_2
    //   13: aload 4
    //   15: invokevirtual 26	android/os/Parcel:writeInterfaceToken	(Ljava/lang/String;)V
    //   18: aload_1
    //   19: ifnull +53 -> 72
    //   22: aload_1
    //   23: invokeinterface 245 1 0
    //   28: astore 4
    //   30: aload_2
    //   31: aload 4
    //   33: invokevirtual 119	android/os/Parcel:writeStrongBinder	(Landroid/os/IBinder;)V
    //   36: aload_0
    //   37: getfield 14	com/google/android/gms/maps/internal/IGoogleMapDelegate$zza$zza:zzoz	Landroid/os/IBinder;
    //   40: astore 4
    //   42: bipush 84
    //   44: istore 5
    //   46: aload 4
    //   48: iload 5
    //   50: aload_2
    //   51: aload_3
    //   52: iconst_0
    //   53: invokeinterface 44 5 0
    //   58: pop
    //   59: aload_3
    //   60: invokevirtual 47	android/os/Parcel:readException	()V
    //   63: aload_3
    //   64: invokevirtual 60	android/os/Parcel:recycle	()V
    //   67: aload_2
    //   68: invokevirtual 60	android/os/Parcel:recycle	()V
    //   71: return
    //   72: aconst_null
    //   73: astore 4
    //   75: goto -45 -> 30
    //   78: astore 4
    //   80: aload_3
    //   81: invokevirtual 60	android/os/Parcel:recycle	()V
    //   84: aload_2
    //   85: invokevirtual 60	android/os/Parcel:recycle	()V
    //   88: aload 4
    //   90: athrow
    // Local variable table:
    //   start	length	slot	name	signature
    //   0	91	0	this	zza
    //   0	91	1	paramzzj	zzj
    //   3	82	2	localParcel1	Parcel
    //   7	74	3	localParcel2	Parcel
    //   10	64	4	localObject1	Object
    //   78	11	4	localObject2	Object
    //   44	5	5	i	int
    // Exception table:
    //   from	to	target	type
    //   13	18	78	finally
    //   22	28	78	finally
    //   31	36	78	finally
    //   36	40	78	finally
    //   52	59	78	finally
    //   59	63	78	finally
  }
  
  /* Error */
  public void setOnMapClickListener(zzl paramzzl)
  {
    // Byte code:
    //   0: invokestatic 20	android/os/Parcel:obtain	()Landroid/os/Parcel;
    //   3: astore_2
    //   4: invokestatic 20	android/os/Parcel:obtain	()Landroid/os/Parcel;
    //   7: astore_3
    //   8: ldc 22
    //   10: astore 4
    //   12: aload_2
    //   13: aload 4
    //   15: invokevirtual 26	android/os/Parcel:writeInterfaceToken	(Ljava/lang/String;)V
    //   18: aload_1
    //   19: ifnull +53 -> 72
    //   22: aload_1
    //   23: invokeinterface 249 1 0
    //   28: astore 4
    //   30: aload_2
    //   31: aload 4
    //   33: invokevirtual 119	android/os/Parcel:writeStrongBinder	(Landroid/os/IBinder;)V
    //   36: aload_0
    //   37: getfield 14	com/google/android/gms/maps/internal/IGoogleMapDelegate$zza$zza:zzoz	Landroid/os/IBinder;
    //   40: astore 4
    //   42: bipush 28
    //   44: istore 5
    //   46: aload 4
    //   48: iload 5
    //   50: aload_2
    //   51: aload_3
    //   52: iconst_0
    //   53: invokeinterface 44 5 0
    //   58: pop
    //   59: aload_3
    //   60: invokevirtual 47	android/os/Parcel:readException	()V
    //   63: aload_3
    //   64: invokevirtual 60	android/os/Parcel:recycle	()V
    //   67: aload_2
    //   68: invokevirtual 60	android/os/Parcel:recycle	()V
    //   71: return
    //   72: aconst_null
    //   73: astore 4
    //   75: goto -45 -> 30
    //   78: astore 4
    //   80: aload_3
    //   81: invokevirtual 60	android/os/Parcel:recycle	()V
    //   84: aload_2
    //   85: invokevirtual 60	android/os/Parcel:recycle	()V
    //   88: aload 4
    //   90: athrow
    // Local variable table:
    //   start	length	slot	name	signature
    //   0	91	0	this	zza
    //   0	91	1	paramzzl	zzl
    //   3	82	2	localParcel1	Parcel
    //   7	74	3	localParcel2	Parcel
    //   10	64	4	localObject1	Object
    //   78	11	4	localObject2	Object
    //   44	5	5	i	int
    // Exception table:
    //   from	to	target	type
    //   13	18	78	finally
    //   22	28	78	finally
    //   31	36	78	finally
    //   36	40	78	finally
    //   52	59	78	finally
    //   59	63	78	finally
  }
  
  /* Error */
  public void setOnMapLoadedCallback(zzm paramzzm)
  {
    // Byte code:
    //   0: invokestatic 20	android/os/Parcel:obtain	()Landroid/os/Parcel;
    //   3: astore_2
    //   4: invokestatic 20	android/os/Parcel:obtain	()Landroid/os/Parcel;
    //   7: astore_3
    //   8: ldc 22
    //   10: astore 4
    //   12: aload_2
    //   13: aload 4
    //   15: invokevirtual 26	android/os/Parcel:writeInterfaceToken	(Ljava/lang/String;)V
    //   18: aload_1
    //   19: ifnull +53 -> 72
    //   22: aload_1
    //   23: invokeinterface 253 1 0
    //   28: astore 4
    //   30: aload_2
    //   31: aload 4
    //   33: invokevirtual 119	android/os/Parcel:writeStrongBinder	(Landroid/os/IBinder;)V
    //   36: aload_0
    //   37: getfield 14	com/google/android/gms/maps/internal/IGoogleMapDelegate$zza$zza:zzoz	Landroid/os/IBinder;
    //   40: astore 4
    //   42: bipush 42
    //   44: istore 5
    //   46: aload 4
    //   48: iload 5
    //   50: aload_2
    //   51: aload_3
    //   52: iconst_0
    //   53: invokeinterface 44 5 0
    //   58: pop
    //   59: aload_3
    //   60: invokevirtual 47	android/os/Parcel:readException	()V
    //   63: aload_3
    //   64: invokevirtual 60	android/os/Parcel:recycle	()V
    //   67: aload_2
    //   68: invokevirtual 60	android/os/Parcel:recycle	()V
    //   71: return
    //   72: aconst_null
    //   73: astore 4
    //   75: goto -45 -> 30
    //   78: astore 4
    //   80: aload_3
    //   81: invokevirtual 60	android/os/Parcel:recycle	()V
    //   84: aload_2
    //   85: invokevirtual 60	android/os/Parcel:recycle	()V
    //   88: aload 4
    //   90: athrow
    // Local variable table:
    //   start	length	slot	name	signature
    //   0	91	0	this	zza
    //   0	91	1	paramzzm	zzm
    //   3	82	2	localParcel1	Parcel
    //   7	74	3	localParcel2	Parcel
    //   10	64	4	localObject1	Object
    //   78	11	4	localObject2	Object
    //   44	5	5	i	int
    // Exception table:
    //   from	to	target	type
    //   13	18	78	finally
    //   22	28	78	finally
    //   31	36	78	finally
    //   36	40	78	finally
    //   52	59	78	finally
    //   59	63	78	finally
  }
  
  /* Error */
  public void setOnMapLongClickListener(zzn paramzzn)
  {
    // Byte code:
    //   0: invokestatic 20	android/os/Parcel:obtain	()Landroid/os/Parcel;
    //   3: astore_2
    //   4: invokestatic 20	android/os/Parcel:obtain	()Landroid/os/Parcel;
    //   7: astore_3
    //   8: ldc 22
    //   10: astore 4
    //   12: aload_2
    //   13: aload 4
    //   15: invokevirtual 26	android/os/Parcel:writeInterfaceToken	(Ljava/lang/String;)V
    //   18: aload_1
    //   19: ifnull +53 -> 72
    //   22: aload_1
    //   23: invokeinterface 257 1 0
    //   28: astore 4
    //   30: aload_2
    //   31: aload 4
    //   33: invokevirtual 119	android/os/Parcel:writeStrongBinder	(Landroid/os/IBinder;)V
    //   36: aload_0
    //   37: getfield 14	com/google/android/gms/maps/internal/IGoogleMapDelegate$zza$zza:zzoz	Landroid/os/IBinder;
    //   40: astore 4
    //   42: bipush 29
    //   44: istore 5
    //   46: aload 4
    //   48: iload 5
    //   50: aload_2
    //   51: aload_3
    //   52: iconst_0
    //   53: invokeinterface 44 5 0
    //   58: pop
    //   59: aload_3
    //   60: invokevirtual 47	android/os/Parcel:readException	()V
    //   63: aload_3
    //   64: invokevirtual 60	android/os/Parcel:recycle	()V
    //   67: aload_2
    //   68: invokevirtual 60	android/os/Parcel:recycle	()V
    //   71: return
    //   72: aconst_null
    //   73: astore 4
    //   75: goto -45 -> 30
    //   78: astore 4
    //   80: aload_3
    //   81: invokevirtual 60	android/os/Parcel:recycle	()V
    //   84: aload_2
    //   85: invokevirtual 60	android/os/Parcel:recycle	()V
    //   88: aload 4
    //   90: athrow
    // Local variable table:
    //   start	length	slot	name	signature
    //   0	91	0	this	zza
    //   0	91	1	paramzzn	zzn
    //   3	82	2	localParcel1	Parcel
    //   7	74	3	localParcel2	Parcel
    //   10	64	4	localObject1	Object
    //   78	11	4	localObject2	Object
    //   44	5	5	i	int
    // Exception table:
    //   from	to	target	type
    //   13	18	78	finally
    //   22	28	78	finally
    //   31	36	78	finally
    //   36	40	78	finally
    //   52	59	78	finally
    //   59	63	78	finally
  }
  
  /* Error */
  public void setOnMarkerClickListener(zzp paramzzp)
  {
    // Byte code:
    //   0: invokestatic 20	android/os/Parcel:obtain	()Landroid/os/Parcel;
    //   3: astore_2
    //   4: invokestatic 20	android/os/Parcel:obtain	()Landroid/os/Parcel;
    //   7: astore_3
    //   8: ldc 22
    //   10: astore 4
    //   12: aload_2
    //   13: aload 4
    //   15: invokevirtual 26	android/os/Parcel:writeInterfaceToken	(Ljava/lang/String;)V
    //   18: aload_1
    //   19: ifnull +53 -> 72
    //   22: aload_1
    //   23: invokeinterface 261 1 0
    //   28: astore 4
    //   30: aload_2
    //   31: aload 4
    //   33: invokevirtual 119	android/os/Parcel:writeStrongBinder	(Landroid/os/IBinder;)V
    //   36: aload_0
    //   37: getfield 14	com/google/android/gms/maps/internal/IGoogleMapDelegate$zza$zza:zzoz	Landroid/os/IBinder;
    //   40: astore 4
    //   42: bipush 30
    //   44: istore 5
    //   46: aload 4
    //   48: iload 5
    //   50: aload_2
    //   51: aload_3
    //   52: iconst_0
    //   53: invokeinterface 44 5 0
    //   58: pop
    //   59: aload_3
    //   60: invokevirtual 47	android/os/Parcel:readException	()V
    //   63: aload_3
    //   64: invokevirtual 60	android/os/Parcel:recycle	()V
    //   67: aload_2
    //   68: invokevirtual 60	android/os/Parcel:recycle	()V
    //   71: return
    //   72: aconst_null
    //   73: astore 4
    //   75: goto -45 -> 30
    //   78: astore 4
    //   80: aload_3
    //   81: invokevirtual 60	android/os/Parcel:recycle	()V
    //   84: aload_2
    //   85: invokevirtual 60	android/os/Parcel:recycle	()V
    //   88: aload 4
    //   90: athrow
    // Local variable table:
    //   start	length	slot	name	signature
    //   0	91	0	this	zza
    //   0	91	1	paramzzp	zzp
    //   3	82	2	localParcel1	Parcel
    //   7	74	3	localParcel2	Parcel
    //   10	64	4	localObject1	Object
    //   78	11	4	localObject2	Object
    //   44	5	5	i	int
    // Exception table:
    //   from	to	target	type
    //   13	18	78	finally
    //   22	28	78	finally
    //   31	36	78	finally
    //   36	40	78	finally
    //   52	59	78	finally
    //   59	63	78	finally
  }
  
  /* Error */
  public void setOnMarkerDragListener(zzq paramzzq)
  {
    // Byte code:
    //   0: invokestatic 20	android/os/Parcel:obtain	()Landroid/os/Parcel;
    //   3: astore_2
    //   4: invokestatic 20	android/os/Parcel:obtain	()Landroid/os/Parcel;
    //   7: astore_3
    //   8: ldc 22
    //   10: astore 4
    //   12: aload_2
    //   13: aload 4
    //   15: invokevirtual 26	android/os/Parcel:writeInterfaceToken	(Ljava/lang/String;)V
    //   18: aload_1
    //   19: ifnull +53 -> 72
    //   22: aload_1
    //   23: invokeinterface 265 1 0
    //   28: astore 4
    //   30: aload_2
    //   31: aload 4
    //   33: invokevirtual 119	android/os/Parcel:writeStrongBinder	(Landroid/os/IBinder;)V
    //   36: aload_0
    //   37: getfield 14	com/google/android/gms/maps/internal/IGoogleMapDelegate$zza$zza:zzoz	Landroid/os/IBinder;
    //   40: astore 4
    //   42: bipush 31
    //   44: istore 5
    //   46: aload 4
    //   48: iload 5
    //   50: aload_2
    //   51: aload_3
    //   52: iconst_0
    //   53: invokeinterface 44 5 0
    //   58: pop
    //   59: aload_3
    //   60: invokevirtual 47	android/os/Parcel:readException	()V
    //   63: aload_3
    //   64: invokevirtual 60	android/os/Parcel:recycle	()V
    //   67: aload_2
    //   68: invokevirtual 60	android/os/Parcel:recycle	()V
    //   71: return
    //   72: aconst_null
    //   73: astore 4
    //   75: goto -45 -> 30
    //   78: astore 4
    //   80: aload_3
    //   81: invokevirtual 60	android/os/Parcel:recycle	()V
    //   84: aload_2
    //   85: invokevirtual 60	android/os/Parcel:recycle	()V
    //   88: aload 4
    //   90: athrow
    // Local variable table:
    //   start	length	slot	name	signature
    //   0	91	0	this	zza
    //   0	91	1	paramzzq	zzq
    //   3	82	2	localParcel1	Parcel
    //   7	74	3	localParcel2	Parcel
    //   10	64	4	localObject1	Object
    //   78	11	4	localObject2	Object
    //   44	5	5	i	int
    // Exception table:
    //   from	to	target	type
    //   13	18	78	finally
    //   22	28	78	finally
    //   31	36	78	finally
    //   36	40	78	finally
    //   52	59	78	finally
    //   59	63	78	finally
  }
  
  /* Error */
  public void setOnMyLocationButtonClickListener(zzr paramzzr)
  {
    // Byte code:
    //   0: invokestatic 20	android/os/Parcel:obtain	()Landroid/os/Parcel;
    //   3: astore_2
    //   4: invokestatic 20	android/os/Parcel:obtain	()Landroid/os/Parcel;
    //   7: astore_3
    //   8: ldc 22
    //   10: astore 4
    //   12: aload_2
    //   13: aload 4
    //   15: invokevirtual 26	android/os/Parcel:writeInterfaceToken	(Ljava/lang/String;)V
    //   18: aload_1
    //   19: ifnull +53 -> 72
    //   22: aload_1
    //   23: invokeinterface 269 1 0
    //   28: astore 4
    //   30: aload_2
    //   31: aload 4
    //   33: invokevirtual 119	android/os/Parcel:writeStrongBinder	(Landroid/os/IBinder;)V
    //   36: aload_0
    //   37: getfield 14	com/google/android/gms/maps/internal/IGoogleMapDelegate$zza$zza:zzoz	Landroid/os/IBinder;
    //   40: astore 4
    //   42: bipush 37
    //   44: istore 5
    //   46: aload 4
    //   48: iload 5
    //   50: aload_2
    //   51: aload_3
    //   52: iconst_0
    //   53: invokeinterface 44 5 0
    //   58: pop
    //   59: aload_3
    //   60: invokevirtual 47	android/os/Parcel:readException	()V
    //   63: aload_3
    //   64: invokevirtual 60	android/os/Parcel:recycle	()V
    //   67: aload_2
    //   68: invokevirtual 60	android/os/Parcel:recycle	()V
    //   71: return
    //   72: aconst_null
    //   73: astore 4
    //   75: goto -45 -> 30
    //   78: astore 4
    //   80: aload_3
    //   81: invokevirtual 60	android/os/Parcel:recycle	()V
    //   84: aload_2
    //   85: invokevirtual 60	android/os/Parcel:recycle	()V
    //   88: aload 4
    //   90: athrow
    // Local variable table:
    //   start	length	slot	name	signature
    //   0	91	0	this	zza
    //   0	91	1	paramzzr	zzr
    //   3	82	2	localParcel1	Parcel
    //   7	74	3	localParcel2	Parcel
    //   10	64	4	localObject1	Object
    //   78	11	4	localObject2	Object
    //   44	5	5	i	int
    // Exception table:
    //   from	to	target	type
    //   13	18	78	finally
    //   22	28	78	finally
    //   31	36	78	finally
    //   36	40	78	finally
    //   52	59	78	finally
    //   59	63	78	finally
  }
  
  /* Error */
  public void setOnMyLocationChangeListener(zzs paramzzs)
  {
    // Byte code:
    //   0: invokestatic 20	android/os/Parcel:obtain	()Landroid/os/Parcel;
    //   3: astore_2
    //   4: invokestatic 20	android/os/Parcel:obtain	()Landroid/os/Parcel;
    //   7: astore_3
    //   8: ldc 22
    //   10: astore 4
    //   12: aload_2
    //   13: aload 4
    //   15: invokevirtual 26	android/os/Parcel:writeInterfaceToken	(Ljava/lang/String;)V
    //   18: aload_1
    //   19: ifnull +53 -> 72
    //   22: aload_1
    //   23: invokeinterface 273 1 0
    //   28: astore 4
    //   30: aload_2
    //   31: aload 4
    //   33: invokevirtual 119	android/os/Parcel:writeStrongBinder	(Landroid/os/IBinder;)V
    //   36: aload_0
    //   37: getfield 14	com/google/android/gms/maps/internal/IGoogleMapDelegate$zza$zza:zzoz	Landroid/os/IBinder;
    //   40: astore 4
    //   42: bipush 36
    //   44: istore 5
    //   46: aload 4
    //   48: iload 5
    //   50: aload_2
    //   51: aload_3
    //   52: iconst_0
    //   53: invokeinterface 44 5 0
    //   58: pop
    //   59: aload_3
    //   60: invokevirtual 47	android/os/Parcel:readException	()V
    //   63: aload_3
    //   64: invokevirtual 60	android/os/Parcel:recycle	()V
    //   67: aload_2
    //   68: invokevirtual 60	android/os/Parcel:recycle	()V
    //   71: return
    //   72: aconst_null
    //   73: astore 4
    //   75: goto -45 -> 30
    //   78: astore 4
    //   80: aload_3
    //   81: invokevirtual 60	android/os/Parcel:recycle	()V
    //   84: aload_2
    //   85: invokevirtual 60	android/os/Parcel:recycle	()V
    //   88: aload 4
    //   90: athrow
    // Local variable table:
    //   start	length	slot	name	signature
    //   0	91	0	this	zza
    //   0	91	1	paramzzs	zzs
    //   3	82	2	localParcel1	Parcel
    //   7	74	3	localParcel2	Parcel
    //   10	64	4	localObject1	Object
    //   78	11	4	localObject2	Object
    //   44	5	5	i	int
    // Exception table:
    //   from	to	target	type
    //   13	18	78	finally
    //   22	28	78	finally
    //   31	36	78	finally
    //   36	40	78	finally
    //   52	59	78	finally
    //   59	63	78	finally
  }
  
  /* Error */
  public void setOnPoiClickListener(zzt paramzzt)
  {
    // Byte code:
    //   0: invokestatic 20	android/os/Parcel:obtain	()Landroid/os/Parcel;
    //   3: astore_2
    //   4: invokestatic 20	android/os/Parcel:obtain	()Landroid/os/Parcel;
    //   7: astore_3
    //   8: ldc 22
    //   10: astore 4
    //   12: aload_2
    //   13: aload 4
    //   15: invokevirtual 26	android/os/Parcel:writeInterfaceToken	(Ljava/lang/String;)V
    //   18: aload_1
    //   19: ifnull +53 -> 72
    //   22: aload_1
    //   23: invokeinterface 277 1 0
    //   28: astore 4
    //   30: aload_2
    //   31: aload 4
    //   33: invokevirtual 119	android/os/Parcel:writeStrongBinder	(Landroid/os/IBinder;)V
    //   36: aload_0
    //   37: getfield 14	com/google/android/gms/maps/internal/IGoogleMapDelegate$zza$zza:zzoz	Landroid/os/IBinder;
    //   40: astore 4
    //   42: bipush 80
    //   44: istore 5
    //   46: aload 4
    //   48: iload 5
    //   50: aload_2
    //   51: aload_3
    //   52: iconst_0
    //   53: invokeinterface 44 5 0
    //   58: pop
    //   59: aload_3
    //   60: invokevirtual 47	android/os/Parcel:readException	()V
    //   63: aload_3
    //   64: invokevirtual 60	android/os/Parcel:recycle	()V
    //   67: aload_2
    //   68: invokevirtual 60	android/os/Parcel:recycle	()V
    //   71: return
    //   72: aconst_null
    //   73: astore 4
    //   75: goto -45 -> 30
    //   78: astore 4
    //   80: aload_3
    //   81: invokevirtual 60	android/os/Parcel:recycle	()V
    //   84: aload_2
    //   85: invokevirtual 60	android/os/Parcel:recycle	()V
    //   88: aload 4
    //   90: athrow
    // Local variable table:
    //   start	length	slot	name	signature
    //   0	91	0	this	zza
    //   0	91	1	paramzzt	zzt
    //   3	82	2	localParcel1	Parcel
    //   7	74	3	localParcel2	Parcel
    //   10	64	4	localObject1	Object
    //   78	11	4	localObject2	Object
    //   44	5	5	i	int
    // Exception table:
    //   from	to	target	type
    //   13	18	78	finally
    //   22	28	78	finally
    //   31	36	78	finally
    //   36	40	78	finally
    //   52	59	78	finally
    //   59	63	78	finally
  }
  
  /* Error */
  public void setOnPolygonClickListener(zzu paramzzu)
  {
    // Byte code:
    //   0: invokestatic 20	android/os/Parcel:obtain	()Landroid/os/Parcel;
    //   3: astore_2
    //   4: invokestatic 20	android/os/Parcel:obtain	()Landroid/os/Parcel;
    //   7: astore_3
    //   8: ldc 22
    //   10: astore 4
    //   12: aload_2
    //   13: aload 4
    //   15: invokevirtual 26	android/os/Parcel:writeInterfaceToken	(Ljava/lang/String;)V
    //   18: aload_1
    //   19: ifnull +53 -> 72
    //   22: aload_1
    //   23: invokeinterface 281 1 0
    //   28: astore 4
    //   30: aload_2
    //   31: aload 4
    //   33: invokevirtual 119	android/os/Parcel:writeStrongBinder	(Landroid/os/IBinder;)V
    //   36: aload_0
    //   37: getfield 14	com/google/android/gms/maps/internal/IGoogleMapDelegate$zza$zza:zzoz	Landroid/os/IBinder;
    //   40: astore 4
    //   42: bipush 85
    //   44: istore 5
    //   46: aload 4
    //   48: iload 5
    //   50: aload_2
    //   51: aload_3
    //   52: iconst_0
    //   53: invokeinterface 44 5 0
    //   58: pop
    //   59: aload_3
    //   60: invokevirtual 47	android/os/Parcel:readException	()V
    //   63: aload_3
    //   64: invokevirtual 60	android/os/Parcel:recycle	()V
    //   67: aload_2
    //   68: invokevirtual 60	android/os/Parcel:recycle	()V
    //   71: return
    //   72: aconst_null
    //   73: astore 4
    //   75: goto -45 -> 30
    //   78: astore 4
    //   80: aload_3
    //   81: invokevirtual 60	android/os/Parcel:recycle	()V
    //   84: aload_2
    //   85: invokevirtual 60	android/os/Parcel:recycle	()V
    //   88: aload 4
    //   90: athrow
    // Local variable table:
    //   start	length	slot	name	signature
    //   0	91	0	this	zza
    //   0	91	1	paramzzu	zzu
    //   3	82	2	localParcel1	Parcel
    //   7	74	3	localParcel2	Parcel
    //   10	64	4	localObject1	Object
    //   78	11	4	localObject2	Object
    //   44	5	5	i	int
    // Exception table:
    //   from	to	target	type
    //   13	18	78	finally
    //   22	28	78	finally
    //   31	36	78	finally
    //   36	40	78	finally
    //   52	59	78	finally
    //   59	63	78	finally
  }
  
  /* Error */
  public void setOnPolylineClickListener(zzv paramzzv)
  {
    // Byte code:
    //   0: invokestatic 20	android/os/Parcel:obtain	()Landroid/os/Parcel;
    //   3: astore_2
    //   4: invokestatic 20	android/os/Parcel:obtain	()Landroid/os/Parcel;
    //   7: astore_3
    //   8: ldc 22
    //   10: astore 4
    //   12: aload_2
    //   13: aload 4
    //   15: invokevirtual 26	android/os/Parcel:writeInterfaceToken	(Ljava/lang/String;)V
    //   18: aload_1
    //   19: ifnull +53 -> 72
    //   22: aload_1
    //   23: invokeinterface 285 1 0
    //   28: astore 4
    //   30: aload_2
    //   31: aload 4
    //   33: invokevirtual 119	android/os/Parcel:writeStrongBinder	(Landroid/os/IBinder;)V
    //   36: aload_0
    //   37: getfield 14	com/google/android/gms/maps/internal/IGoogleMapDelegate$zza$zza:zzoz	Landroid/os/IBinder;
    //   40: astore 4
    //   42: bipush 87
    //   44: istore 5
    //   46: aload 4
    //   48: iload 5
    //   50: aload_2
    //   51: aload_3
    //   52: iconst_0
    //   53: invokeinterface 44 5 0
    //   58: pop
    //   59: aload_3
    //   60: invokevirtual 47	android/os/Parcel:readException	()V
    //   63: aload_3
    //   64: invokevirtual 60	android/os/Parcel:recycle	()V
    //   67: aload_2
    //   68: invokevirtual 60	android/os/Parcel:recycle	()V
    //   71: return
    //   72: aconst_null
    //   73: astore 4
    //   75: goto -45 -> 30
    //   78: astore 4
    //   80: aload_3
    //   81: invokevirtual 60	android/os/Parcel:recycle	()V
    //   84: aload_2
    //   85: invokevirtual 60	android/os/Parcel:recycle	()V
    //   88: aload 4
    //   90: athrow
    // Local variable table:
    //   start	length	slot	name	signature
    //   0	91	0	this	zza
    //   0	91	1	paramzzv	zzv
    //   3	82	2	localParcel1	Parcel
    //   7	74	3	localParcel2	Parcel
    //   10	64	4	localObject1	Object
    //   78	11	4	localObject2	Object
    //   44	5	5	i	int
    // Exception table:
    //   from	to	target	type
    //   13	18	78	finally
    //   22	28	78	finally
    //   31	36	78	finally
    //   36	40	78	finally
    //   52	59	78	finally
    //   59	63	78	finally
  }
  
  public void setPadding(int paramInt1, int paramInt2, int paramInt3, int paramInt4)
  {
    Parcel localParcel1 = Parcel.obtain();
    Parcel localParcel2 = Parcel.obtain();
    Object localObject1 = "com.google.android.gms.maps.internal.IGoogleMapDelegate";
    try
    {
      localParcel1.writeInterfaceToken((String)localObject1);
      localParcel1.writeInt(paramInt1);
      localParcel1.writeInt(paramInt2);
      localParcel1.writeInt(paramInt3);
      localParcel1.writeInt(paramInt4);
      localObject1 = this.zzoz;
      int i = 39;
      ((IBinder)localObject1).transact(i, localParcel1, localParcel2, 0);
      localParcel2.readException();
      return;
    }
    finally
    {
      localParcel2.recycle();
      localParcel1.recycle();
    }
  }
  
  public void setTrafficEnabled(boolean paramBoolean)
  {
    int i = 0;
    IBinder localIBinder = null;
    Parcel localParcel1 = Parcel.obtain();
    Parcel localParcel2 = Parcel.obtain();
    String str = "com.google.android.gms.maps.internal.IGoogleMapDelegate";
    try
    {
      localParcel1.writeInterfaceToken(str);
      if (paramBoolean) {
        i = 1;
      }
      localParcel1.writeInt(i);
      localIBinder = this.zzoz;
      int j = 18;
      localIBinder.transact(j, localParcel1, localParcel2, 0);
      localParcel2.readException();
      return;
    }
    finally
    {
      localParcel2.recycle();
      localParcel1.recycle();
    }
  }
  
  /* Error */
  public void snapshot(zzab paramzzab, com.google.android.gms.dynamic.zzd paramzzd)
  {
    // Byte code:
    //   0: aconst_null
    //   1: astore_3
    //   2: invokestatic 20	android/os/Parcel:obtain	()Landroid/os/Parcel;
    //   5: astore 4
    //   7: invokestatic 20	android/os/Parcel:obtain	()Landroid/os/Parcel;
    //   10: astore 5
    //   12: ldc 22
    //   14: astore 6
    //   16: aload 4
    //   18: aload 6
    //   20: invokevirtual 26	android/os/Parcel:writeInterfaceToken	(Ljava/lang/String;)V
    //   23: aload_1
    //   24: ifnull +74 -> 98
    //   27: aload_1
    //   28: invokeinterface 291 1 0
    //   33: astore 6
    //   35: aload 4
    //   37: aload 6
    //   39: invokevirtual 119	android/os/Parcel:writeStrongBinder	(Landroid/os/IBinder;)V
    //   42: aload_2
    //   43: ifnull +10 -> 53
    //   46: aload_2
    //   47: invokeinterface 115 1 0
    //   52: astore_3
    //   53: aload 4
    //   55: aload_3
    //   56: invokevirtual 119	android/os/Parcel:writeStrongBinder	(Landroid/os/IBinder;)V
    //   59: aload_0
    //   60: getfield 14	com/google/android/gms/maps/internal/IGoogleMapDelegate$zza$zza:zzoz	Landroid/os/IBinder;
    //   63: astore_3
    //   64: bipush 38
    //   66: istore 7
    //   68: aload_3
    //   69: iload 7
    //   71: aload 4
    //   73: aload 5
    //   75: iconst_0
    //   76: invokeinterface 44 5 0
    //   81: pop
    //   82: aload 5
    //   84: invokevirtual 47	android/os/Parcel:readException	()V
    //   87: aload 5
    //   89: invokevirtual 60	android/os/Parcel:recycle	()V
    //   92: aload 4
    //   94: invokevirtual 60	android/os/Parcel:recycle	()V
    //   97: return
    //   98: iconst_0
    //   99: istore 7
    //   101: aconst_null
    //   102: astore 6
    //   104: goto -69 -> 35
    //   107: astore_3
    //   108: aload 5
    //   110: invokevirtual 60	android/os/Parcel:recycle	()V
    //   113: aload 4
    //   115: invokevirtual 60	android/os/Parcel:recycle	()V
    //   118: aload_3
    //   119: athrow
    // Local variable table:
    //   start	length	slot	name	signature
    //   0	120	0	this	zza
    //   0	120	1	paramzzab	zzab
    //   0	120	2	paramzzd	com.google.android.gms.dynamic.zzd
    //   1	68	3	localIBinder	IBinder
    //   107	12	3	localObject1	Object
    //   5	109	4	localParcel1	Parcel
    //   10	99	5	localParcel2	Parcel
    //   14	89	6	localObject2	Object
    //   66	34	7	i	int
    // Exception table:
    //   from	to	target	type
    //   18	23	107	finally
    //   27	33	107	finally
    //   37	42	107	finally
    //   46	52	107	finally
    //   55	59	107	finally
    //   59	63	107	finally
    //   75	82	107	finally
    //   82	87	107	finally
  }
  
  public void stopAnimation()
  {
    Parcel localParcel1 = Parcel.obtain();
    Parcel localParcel2 = Parcel.obtain();
    Object localObject1 = "com.google.android.gms.maps.internal.IGoogleMapDelegate";
    try
    {
      localParcel1.writeInterfaceToken((String)localObject1);
      localObject1 = this.zzoz;
      int i = 8;
      ((IBinder)localObject1).transact(i, localParcel1, localParcel2, 0);
      localParcel2.readException();
      return;
    }
    finally
    {
      localParcel2.recycle();
      localParcel1.recycle();
    }
  }
  
  public boolean useViewLifecycleWhenInFragment()
  {
    boolean bool = false;
    Object localObject1 = null;
    Parcel localParcel1 = Parcel.obtain();
    Parcel localParcel2 = Parcel.obtain();
    Object localObject3 = "com.google.android.gms.maps.internal.IGoogleMapDelegate";
    try
    {
      localParcel1.writeInterfaceToken((String)localObject3);
      localObject3 = this.zzoz;
      int i = 59;
      ((IBinder)localObject3).transact(i, localParcel1, localParcel2, 0);
      localParcel2.readException();
      int j = localParcel2.readInt();
      if (j != 0) {
        bool = true;
      }
      return bool;
    }
    finally
    {
      localParcel2.recycle();
      localParcel1.recycle();
    }
  }
}


/* Location:              C:\Users\haryo\Desktop\enjarify-master\presensi-enjarify.jar!\com\google\android\gms\maps\internal\IGoogleMapDelegate$zza$zza.class
 * Java compiler version: 5 (49.0)
 * JD-Core Version:       0.7.1
 */