package com.google.android.gms.maps.internal;

import android.os.IBinder;
import android.os.Parcel;

class IStreetViewPanoramaDelegate$zza$zza
  implements IStreetViewPanoramaDelegate
{
  private IBinder zzoz;
  
  IStreetViewPanoramaDelegate$zza$zza(IBinder paramIBinder)
  {
    this.zzoz = paramIBinder;
  }
  
  /* Error */
  public void animateTo(com.google.android.gms.maps.model.StreetViewPanoramaCamera paramStreetViewPanoramaCamera, long paramLong)
  {
    // Byte code:
    //   0: invokestatic 20	android/os/Parcel:obtain	()Landroid/os/Parcel;
    //   3: astore 4
    //   5: invokestatic 20	android/os/Parcel:obtain	()Landroid/os/Parcel;
    //   8: astore 5
    //   10: ldc 22
    //   12: astore 6
    //   14: aload 4
    //   16: aload 6
    //   18: invokevirtual 26	android/os/Parcel:writeInterfaceToken	(Ljava/lang/String;)V
    //   21: aload_1
    //   22: ifnull +73 -> 95
    //   25: iconst_1
    //   26: istore 7
    //   28: aload 4
    //   30: iload 7
    //   32: invokevirtual 31	android/os/Parcel:writeInt	(I)V
    //   35: iconst_0
    //   36: istore 7
    //   38: aconst_null
    //   39: astore 6
    //   41: aload_1
    //   42: aload 4
    //   44: iconst_0
    //   45: invokevirtual 37	com/google/android/gms/maps/model/StreetViewPanoramaCamera:writeToParcel	(Landroid/os/Parcel;I)V
    //   48: aload 4
    //   50: lload_2
    //   51: invokevirtual 41	android/os/Parcel:writeLong	(J)V
    //   54: aload_0
    //   55: getfield 14	com/google/android/gms/maps/internal/IStreetViewPanoramaDelegate$zza$zza:zzoz	Landroid/os/IBinder;
    //   58: astore 6
    //   60: bipush 9
    //   62: istore 8
    //   64: aload 6
    //   66: iload 8
    //   68: aload 4
    //   70: aload 5
    //   72: iconst_0
    //   73: invokeinterface 48 5 0
    //   78: pop
    //   79: aload 5
    //   81: invokevirtual 51	android/os/Parcel:readException	()V
    //   84: aload 5
    //   86: invokevirtual 54	android/os/Parcel:recycle	()V
    //   89: aload 4
    //   91: invokevirtual 54	android/os/Parcel:recycle	()V
    //   94: return
    //   95: iconst_0
    //   96: istore 7
    //   98: aconst_null
    //   99: astore 6
    //   101: aload 4
    //   103: iconst_0
    //   104: invokevirtual 31	android/os/Parcel:writeInt	(I)V
    //   107: goto -59 -> 48
    //   110: astore 6
    //   112: aload 5
    //   114: invokevirtual 54	android/os/Parcel:recycle	()V
    //   117: aload 4
    //   119: invokevirtual 54	android/os/Parcel:recycle	()V
    //   122: aload 6
    //   124: athrow
    // Local variable table:
    //   start	length	slot	name	signature
    //   0	125	0	this	zza
    //   0	125	1	paramStreetViewPanoramaCamera	com.google.android.gms.maps.model.StreetViewPanoramaCamera
    //   0	125	2	paramLong	long
    //   3	115	4	localParcel1	Parcel
    //   8	105	5	localParcel2	Parcel
    //   12	88	6	localObject1	Object
    //   110	13	6	localObject2	Object
    //   26	71	7	i	int
    //   62	5	8	j	int
    // Exception table:
    //   from	to	target	type
    //   16	21	110	finally
    //   30	35	110	finally
    //   44	48	110	finally
    //   50	54	110	finally
    //   54	58	110	finally
    //   72	79	110	finally
    //   79	84	110	finally
    //   103	107	110	finally
  }
  
  public IBinder asBinder()
  {
    return this.zzoz;
  }
  
  public void enablePanning(boolean paramBoolean)
  {
    int i = 0;
    IBinder localIBinder = null;
    Parcel localParcel1 = Parcel.obtain();
    Parcel localParcel2 = Parcel.obtain();
    String str = "com.google.android.gms.maps.internal.IStreetViewPanoramaDelegate";
    try
    {
      localParcel1.writeInterfaceToken(str);
      if (paramBoolean) {
        i = 1;
      }
      localParcel1.writeInt(i);
      localIBinder = this.zzoz;
      int j = 2;
      localIBinder.transact(j, localParcel1, localParcel2, 0);
      localParcel2.readException();
      return;
    }
    finally
    {
      localParcel2.recycle();
      localParcel1.recycle();
    }
  }
  
  public void enableStreetNames(boolean paramBoolean)
  {
    int i = 0;
    IBinder localIBinder = null;
    Parcel localParcel1 = Parcel.obtain();
    Parcel localParcel2 = Parcel.obtain();
    String str = "com.google.android.gms.maps.internal.IStreetViewPanoramaDelegate";
    try
    {
      localParcel1.writeInterfaceToken(str);
      if (paramBoolean) {
        i = 1;
      }
      localParcel1.writeInt(i);
      localIBinder = this.zzoz;
      int j = 4;
      localIBinder.transact(j, localParcel1, localParcel2, 0);
      localParcel2.readException();
      return;
    }
    finally
    {
      localParcel2.recycle();
      localParcel1.recycle();
    }
  }
  
  public void enableUserNavigation(boolean paramBoolean)
  {
    int i = 0;
    IBinder localIBinder = null;
    Parcel localParcel1 = Parcel.obtain();
    Parcel localParcel2 = Parcel.obtain();
    String str = "com.google.android.gms.maps.internal.IStreetViewPanoramaDelegate";
    try
    {
      localParcel1.writeInterfaceToken(str);
      if (paramBoolean) {
        i = 1;
      }
      localParcel1.writeInt(i);
      localIBinder = this.zzoz;
      int j = 3;
      localIBinder.transact(j, localParcel1, localParcel2, 0);
      localParcel2.readException();
      return;
    }
    finally
    {
      localParcel2.recycle();
      localParcel1.recycle();
    }
  }
  
  /* Error */
  public void enableZoom(boolean paramBoolean)
  {
    // Byte code:
    //   0: iconst_1
    //   1: istore_2
    //   2: iconst_0
    //   3: istore_3
    //   4: invokestatic 20	android/os/Parcel:obtain	()Landroid/os/Parcel;
    //   7: astore 4
    //   9: invokestatic 20	android/os/Parcel:obtain	()Landroid/os/Parcel;
    //   12: astore 5
    //   14: ldc 22
    //   16: astore 6
    //   18: aload 4
    //   20: aload 6
    //   22: invokevirtual 26	android/os/Parcel:writeInterfaceToken	(Ljava/lang/String;)V
    //   25: iload_1
    //   26: ifeq +50 -> 76
    //   29: aload 4
    //   31: iload_2
    //   32: invokevirtual 31	android/os/Parcel:writeInt	(I)V
    //   35: aload_0
    //   36: getfield 14	com/google/android/gms/maps/internal/IStreetViewPanoramaDelegate$zza$zza:zzoz	Landroid/os/IBinder;
    //   39: astore 7
    //   41: iconst_1
    //   42: istore_3
    //   43: aconst_null
    //   44: astore 6
    //   46: aload 7
    //   48: iload_3
    //   49: aload 4
    //   51: aload 5
    //   53: iconst_0
    //   54: invokeinterface 48 5 0
    //   59: pop
    //   60: aload 5
    //   62: invokevirtual 51	android/os/Parcel:readException	()V
    //   65: aload 5
    //   67: invokevirtual 54	android/os/Parcel:recycle	()V
    //   70: aload 4
    //   72: invokevirtual 54	android/os/Parcel:recycle	()V
    //   75: return
    //   76: iconst_0
    //   77: istore_2
    //   78: aconst_null
    //   79: astore 7
    //   81: goto -52 -> 29
    //   84: astore 7
    //   86: aload 5
    //   88: invokevirtual 54	android/os/Parcel:recycle	()V
    //   91: aload 4
    //   93: invokevirtual 54	android/os/Parcel:recycle	()V
    //   96: aload 7
    //   98: athrow
    // Local variable table:
    //   start	length	slot	name	signature
    //   0	99	0	this	zza
    //   0	99	1	paramBoolean	boolean
    //   1	77	2	i	int
    //   3	46	3	j	int
    //   7	85	4	localParcel1	Parcel
    //   12	75	5	localParcel2	Parcel
    //   16	29	6	str	String
    //   39	41	7	localIBinder	IBinder
    //   84	13	7	localObject	Object
    // Exception table:
    //   from	to	target	type
    //   20	25	84	finally
    //   31	35	84	finally
    //   35	39	84	finally
    //   53	60	84	finally
    //   60	65	84	finally
  }
  
  /* Error */
  public com.google.android.gms.maps.model.StreetViewPanoramaCamera getPanoramaCamera()
  {
    // Byte code:
    //   0: invokestatic 20	android/os/Parcel:obtain	()Landroid/os/Parcel;
    //   3: astore_1
    //   4: invokestatic 20	android/os/Parcel:obtain	()Landroid/os/Parcel;
    //   7: astore_2
    //   8: ldc 22
    //   10: astore_3
    //   11: aload_1
    //   12: aload_3
    //   13: invokevirtual 26	android/os/Parcel:writeInterfaceToken	(Ljava/lang/String;)V
    //   16: aload_0
    //   17: getfield 14	com/google/android/gms/maps/internal/IStreetViewPanoramaDelegate$zza$zza:zzoz	Landroid/os/IBinder;
    //   20: astore_3
    //   21: bipush 10
    //   23: istore 4
    //   25: aload_3
    //   26: iload 4
    //   28: aload_1
    //   29: aload_2
    //   30: iconst_0
    //   31: invokeinterface 48 5 0
    //   36: pop
    //   37: aload_2
    //   38: invokevirtual 51	android/os/Parcel:readException	()V
    //   41: aload_2
    //   42: invokevirtual 62	android/os/Parcel:readInt	()I
    //   45: istore 5
    //   47: iload 5
    //   49: ifeq +23 -> 72
    //   52: getstatic 66	com/google/android/gms/maps/model/StreetViewPanoramaCamera:CREATOR	Lcom/google/android/gms/maps/model/zzj;
    //   55: astore_3
    //   56: aload_3
    //   57: aload_2
    //   58: invokevirtual 72	com/google/android/gms/maps/model/zzj:zzfE	(Landroid/os/Parcel;)Lcom/google/android/gms/maps/model/StreetViewPanoramaCamera;
    //   61: astore_3
    //   62: aload_2
    //   63: invokevirtual 54	android/os/Parcel:recycle	()V
    //   66: aload_1
    //   67: invokevirtual 54	android/os/Parcel:recycle	()V
    //   70: aload_3
    //   71: areturn
    //   72: iconst_0
    //   73: istore 5
    //   75: aconst_null
    //   76: astore_3
    //   77: goto -15 -> 62
    //   80: astore_3
    //   81: aload_2
    //   82: invokevirtual 54	android/os/Parcel:recycle	()V
    //   85: aload_1
    //   86: invokevirtual 54	android/os/Parcel:recycle	()V
    //   89: aload_3
    //   90: athrow
    // Local variable table:
    //   start	length	slot	name	signature
    //   0	91	0	this	zza
    //   3	83	1	localParcel1	Parcel
    //   7	75	2	localParcel2	Parcel
    //   10	67	3	localObject1	Object
    //   80	10	3	localObject2	Object
    //   23	4	4	i	int
    //   45	29	5	j	int
    // Exception table:
    //   from	to	target	type
    //   12	16	80	finally
    //   16	20	80	finally
    //   30	37	80	finally
    //   37	41	80	finally
    //   41	45	80	finally
    //   52	55	80	finally
    //   57	61	80	finally
  }
  
  /* Error */
  public com.google.android.gms.maps.model.StreetViewPanoramaLocation getStreetViewPanoramaLocation()
  {
    // Byte code:
    //   0: invokestatic 20	android/os/Parcel:obtain	()Landroid/os/Parcel;
    //   3: astore_1
    //   4: invokestatic 20	android/os/Parcel:obtain	()Landroid/os/Parcel;
    //   7: astore_2
    //   8: ldc 22
    //   10: astore_3
    //   11: aload_1
    //   12: aload_3
    //   13: invokevirtual 26	android/os/Parcel:writeInterfaceToken	(Ljava/lang/String;)V
    //   16: aload_0
    //   17: getfield 14	com/google/android/gms/maps/internal/IStreetViewPanoramaDelegate$zza$zza:zzoz	Landroid/os/IBinder;
    //   20: astore_3
    //   21: bipush 14
    //   23: istore 4
    //   25: aload_3
    //   26: iload 4
    //   28: aload_1
    //   29: aload_2
    //   30: iconst_0
    //   31: invokeinterface 48 5 0
    //   36: pop
    //   37: aload_2
    //   38: invokevirtual 51	android/os/Parcel:readException	()V
    //   41: aload_2
    //   42: invokevirtual 62	android/os/Parcel:readInt	()I
    //   45: istore 5
    //   47: iload 5
    //   49: ifeq +23 -> 72
    //   52: getstatic 78	com/google/android/gms/maps/model/StreetViewPanoramaLocation:CREATOR	Lcom/google/android/gms/maps/model/zzl;
    //   55: astore_3
    //   56: aload_3
    //   57: aload_2
    //   58: invokevirtual 84	com/google/android/gms/maps/model/zzl:zzfG	(Landroid/os/Parcel;)Lcom/google/android/gms/maps/model/StreetViewPanoramaLocation;
    //   61: astore_3
    //   62: aload_2
    //   63: invokevirtual 54	android/os/Parcel:recycle	()V
    //   66: aload_1
    //   67: invokevirtual 54	android/os/Parcel:recycle	()V
    //   70: aload_3
    //   71: areturn
    //   72: iconst_0
    //   73: istore 5
    //   75: aconst_null
    //   76: astore_3
    //   77: goto -15 -> 62
    //   80: astore_3
    //   81: aload_2
    //   82: invokevirtual 54	android/os/Parcel:recycle	()V
    //   85: aload_1
    //   86: invokevirtual 54	android/os/Parcel:recycle	()V
    //   89: aload_3
    //   90: athrow
    // Local variable table:
    //   start	length	slot	name	signature
    //   0	91	0	this	zza
    //   3	83	1	localParcel1	Parcel
    //   7	75	2	localParcel2	Parcel
    //   10	67	3	localObject1	Object
    //   80	10	3	localObject2	Object
    //   23	4	4	i	int
    //   45	29	5	j	int
    // Exception table:
    //   from	to	target	type
    //   12	16	80	finally
    //   16	20	80	finally
    //   30	37	80	finally
    //   37	41	80	finally
    //   41	45	80	finally
    //   52	55	80	finally
    //   57	61	80	finally
  }
  
  public boolean isPanningGesturesEnabled()
  {
    boolean bool = false;
    Object localObject1 = null;
    Parcel localParcel1 = Parcel.obtain();
    Parcel localParcel2 = Parcel.obtain();
    Object localObject3 = "com.google.android.gms.maps.internal.IStreetViewPanoramaDelegate";
    try
    {
      localParcel1.writeInterfaceToken((String)localObject3);
      localObject3 = this.zzoz;
      int i = 6;
      ((IBinder)localObject3).transact(i, localParcel1, localParcel2, 0);
      localParcel2.readException();
      int j = localParcel2.readInt();
      if (j != 0) {
        bool = true;
      }
      return bool;
    }
    finally
    {
      localParcel2.recycle();
      localParcel1.recycle();
    }
  }
  
  public boolean isStreetNamesEnabled()
  {
    boolean bool = false;
    Object localObject1 = null;
    Parcel localParcel1 = Parcel.obtain();
    Parcel localParcel2 = Parcel.obtain();
    Object localObject3 = "com.google.android.gms.maps.internal.IStreetViewPanoramaDelegate";
    try
    {
      localParcel1.writeInterfaceToken((String)localObject3);
      localObject3 = this.zzoz;
      int i = 8;
      ((IBinder)localObject3).transact(i, localParcel1, localParcel2, 0);
      localParcel2.readException();
      int j = localParcel2.readInt();
      if (j != 0) {
        bool = true;
      }
      return bool;
    }
    finally
    {
      localParcel2.recycle();
      localParcel1.recycle();
    }
  }
  
  public boolean isUserNavigationEnabled()
  {
    boolean bool = false;
    Object localObject1 = null;
    Parcel localParcel1 = Parcel.obtain();
    Parcel localParcel2 = Parcel.obtain();
    Object localObject3 = "com.google.android.gms.maps.internal.IStreetViewPanoramaDelegate";
    try
    {
      localParcel1.writeInterfaceToken((String)localObject3);
      localObject3 = this.zzoz;
      int i = 7;
      ((IBinder)localObject3).transact(i, localParcel1, localParcel2, 0);
      localParcel2.readException();
      int j = localParcel2.readInt();
      if (j != 0) {
        bool = true;
      }
      return bool;
    }
    finally
    {
      localParcel2.recycle();
      localParcel1.recycle();
    }
  }
  
  public boolean isZoomGesturesEnabled()
  {
    boolean bool = false;
    Object localObject1 = null;
    Parcel localParcel1 = Parcel.obtain();
    Parcel localParcel2 = Parcel.obtain();
    Object localObject3 = "com.google.android.gms.maps.internal.IStreetViewPanoramaDelegate";
    try
    {
      localParcel1.writeInterfaceToken((String)localObject3);
      localObject3 = this.zzoz;
      int i = 5;
      ((IBinder)localObject3).transact(i, localParcel1, localParcel2, 0);
      localParcel2.readException();
      int j = localParcel2.readInt();
      if (j != 0) {
        bool = true;
      }
      return bool;
    }
    finally
    {
      localParcel2.recycle();
      localParcel1.recycle();
    }
  }
  
  /* Error */
  public com.google.android.gms.dynamic.zzd orientationToPoint(com.google.android.gms.maps.model.StreetViewPanoramaOrientation paramStreetViewPanoramaOrientation)
  {
    // Byte code:
    //   0: invokestatic 20	android/os/Parcel:obtain	()Landroid/os/Parcel;
    //   3: astore_2
    //   4: invokestatic 20	android/os/Parcel:obtain	()Landroid/os/Parcel;
    //   7: astore_3
    //   8: ldc 22
    //   10: astore 4
    //   12: aload_2
    //   13: aload 4
    //   15: invokevirtual 26	android/os/Parcel:writeInterfaceToken	(Ljava/lang/String;)V
    //   18: aload_1
    //   19: ifnull +75 -> 94
    //   22: iconst_1
    //   23: istore 5
    //   25: aload_2
    //   26: iload 5
    //   28: invokevirtual 31	android/os/Parcel:writeInt	(I)V
    //   31: iconst_0
    //   32: istore 5
    //   34: aconst_null
    //   35: astore 4
    //   37: aload_1
    //   38: aload_2
    //   39: iconst_0
    //   40: invokevirtual 91	com/google/android/gms/maps/model/StreetViewPanoramaOrientation:writeToParcel	(Landroid/os/Parcel;I)V
    //   43: aload_0
    //   44: getfield 14	com/google/android/gms/maps/internal/IStreetViewPanoramaDelegate$zza$zza:zzoz	Landroid/os/IBinder;
    //   47: astore 4
    //   49: bipush 19
    //   51: istore 6
    //   53: aload 4
    //   55: iload 6
    //   57: aload_2
    //   58: aload_3
    //   59: iconst_0
    //   60: invokeinterface 48 5 0
    //   65: pop
    //   66: aload_3
    //   67: invokevirtual 51	android/os/Parcel:readException	()V
    //   70: aload_3
    //   71: invokevirtual 96	android/os/Parcel:readStrongBinder	()Landroid/os/IBinder;
    //   74: astore 4
    //   76: aload 4
    //   78: invokestatic 102	com/google/android/gms/dynamic/zzd$zza:zzbs	(Landroid/os/IBinder;)Lcom/google/android/gms/dynamic/zzd;
    //   81: astore 4
    //   83: aload_3
    //   84: invokevirtual 54	android/os/Parcel:recycle	()V
    //   87: aload_2
    //   88: invokevirtual 54	android/os/Parcel:recycle	()V
    //   91: aload 4
    //   93: areturn
    //   94: iconst_0
    //   95: istore 5
    //   97: aconst_null
    //   98: astore 4
    //   100: aload_2
    //   101: iconst_0
    //   102: invokevirtual 31	android/os/Parcel:writeInt	(I)V
    //   105: goto -62 -> 43
    //   108: astore 4
    //   110: aload_3
    //   111: invokevirtual 54	android/os/Parcel:recycle	()V
    //   114: aload_2
    //   115: invokevirtual 54	android/os/Parcel:recycle	()V
    //   118: aload 4
    //   120: athrow
    // Local variable table:
    //   start	length	slot	name	signature
    //   0	121	0	this	zza
    //   0	121	1	paramStreetViewPanoramaOrientation	com.google.android.gms.maps.model.StreetViewPanoramaOrientation
    //   3	112	2	localParcel1	Parcel
    //   7	104	3	localParcel2	Parcel
    //   10	89	4	localObject1	Object
    //   108	11	4	localObject2	Object
    //   23	73	5	i	int
    //   51	5	6	j	int
    // Exception table:
    //   from	to	target	type
    //   13	18	108	finally
    //   26	31	108	finally
    //   39	43	108	finally
    //   43	47	108	finally
    //   59	66	108	finally
    //   66	70	108	finally
    //   70	74	108	finally
    //   76	81	108	finally
    //   101	105	108	finally
  }
  
  /* Error */
  public com.google.android.gms.maps.model.StreetViewPanoramaOrientation pointToOrientation(com.google.android.gms.dynamic.zzd paramzzd)
  {
    // Byte code:
    //   0: aconst_null
    //   1: astore_2
    //   2: invokestatic 20	android/os/Parcel:obtain	()Landroid/os/Parcel;
    //   5: astore_3
    //   6: invokestatic 20	android/os/Parcel:obtain	()Landroid/os/Parcel;
    //   9: astore 4
    //   11: ldc 22
    //   13: astore 5
    //   15: aload_3
    //   16: aload 5
    //   18: invokevirtual 26	android/os/Parcel:writeInterfaceToken	(Ljava/lang/String;)V
    //   21: aload_1
    //   22: ifnull +80 -> 102
    //   25: aload_1
    //   26: invokeinterface 107 1 0
    //   31: astore 5
    //   33: aload_3
    //   34: aload 5
    //   36: invokevirtual 111	android/os/Parcel:writeStrongBinder	(Landroid/os/IBinder;)V
    //   39: aload_0
    //   40: getfield 14	com/google/android/gms/maps/internal/IStreetViewPanoramaDelegate$zza$zza:zzoz	Landroid/os/IBinder;
    //   43: astore 5
    //   45: bipush 18
    //   47: istore 6
    //   49: aload 5
    //   51: iload 6
    //   53: aload_3
    //   54: aload 4
    //   56: iconst_0
    //   57: invokeinterface 48 5 0
    //   62: pop
    //   63: aload 4
    //   65: invokevirtual 51	android/os/Parcel:readException	()V
    //   68: aload 4
    //   70: invokevirtual 62	android/os/Parcel:readInt	()I
    //   73: istore 7
    //   75: iload 7
    //   77: ifeq +14 -> 91
    //   80: getstatic 115	com/google/android/gms/maps/model/StreetViewPanoramaOrientation:CREATOR	Lcom/google/android/gms/maps/model/zzm;
    //   83: astore_2
    //   84: aload_2
    //   85: aload 4
    //   87: invokevirtual 121	com/google/android/gms/maps/model/zzm:zzfH	(Landroid/os/Parcel;)Lcom/google/android/gms/maps/model/StreetViewPanoramaOrientation;
    //   90: astore_2
    //   91: aload 4
    //   93: invokevirtual 54	android/os/Parcel:recycle	()V
    //   96: aload_3
    //   97: invokevirtual 54	android/os/Parcel:recycle	()V
    //   100: aload_2
    //   101: areturn
    //   102: iconst_0
    //   103: istore 7
    //   105: aconst_null
    //   106: astore 5
    //   108: goto -75 -> 33
    //   111: astore_2
    //   112: aload 4
    //   114: invokevirtual 54	android/os/Parcel:recycle	()V
    //   117: aload_3
    //   118: invokevirtual 54	android/os/Parcel:recycle	()V
    //   121: aload_2
    //   122: athrow
    // Local variable table:
    //   start	length	slot	name	signature
    //   0	123	0	this	zza
    //   0	123	1	paramzzd	com.google.android.gms.dynamic.zzd
    //   1	100	2	localObject1	Object
    //   111	11	2	localObject2	Object
    //   5	113	3	localParcel1	Parcel
    //   9	104	4	localParcel2	Parcel
    //   13	94	5	localObject3	Object
    //   47	5	6	i	int
    //   73	31	7	j	int
    // Exception table:
    //   from	to	target	type
    //   16	21	111	finally
    //   25	31	111	finally
    //   34	39	111	finally
    //   39	43	111	finally
    //   56	63	111	finally
    //   63	68	111	finally
    //   68	73	111	finally
    //   80	83	111	finally
    //   85	90	111	finally
  }
  
  /* Error */
  public void setOnStreetViewPanoramaCameraChangeListener(zzw paramzzw)
  {
    // Byte code:
    //   0: invokestatic 20	android/os/Parcel:obtain	()Landroid/os/Parcel;
    //   3: astore_2
    //   4: invokestatic 20	android/os/Parcel:obtain	()Landroid/os/Parcel;
    //   7: astore_3
    //   8: ldc 22
    //   10: astore 4
    //   12: aload_2
    //   13: aload 4
    //   15: invokevirtual 26	android/os/Parcel:writeInterfaceToken	(Ljava/lang/String;)V
    //   18: aload_1
    //   19: ifnull +53 -> 72
    //   22: aload_1
    //   23: invokeinterface 124 1 0
    //   28: astore 4
    //   30: aload_2
    //   31: aload 4
    //   33: invokevirtual 111	android/os/Parcel:writeStrongBinder	(Landroid/os/IBinder;)V
    //   36: aload_0
    //   37: getfield 14	com/google/android/gms/maps/internal/IStreetViewPanoramaDelegate$zza$zza:zzoz	Landroid/os/IBinder;
    //   40: astore 4
    //   42: bipush 16
    //   44: istore 5
    //   46: aload 4
    //   48: iload 5
    //   50: aload_2
    //   51: aload_3
    //   52: iconst_0
    //   53: invokeinterface 48 5 0
    //   58: pop
    //   59: aload_3
    //   60: invokevirtual 51	android/os/Parcel:readException	()V
    //   63: aload_3
    //   64: invokevirtual 54	android/os/Parcel:recycle	()V
    //   67: aload_2
    //   68: invokevirtual 54	android/os/Parcel:recycle	()V
    //   71: return
    //   72: aconst_null
    //   73: astore 4
    //   75: goto -45 -> 30
    //   78: astore 4
    //   80: aload_3
    //   81: invokevirtual 54	android/os/Parcel:recycle	()V
    //   84: aload_2
    //   85: invokevirtual 54	android/os/Parcel:recycle	()V
    //   88: aload 4
    //   90: athrow
    // Local variable table:
    //   start	length	slot	name	signature
    //   0	91	0	this	zza
    //   0	91	1	paramzzw	zzw
    //   3	82	2	localParcel1	Parcel
    //   7	74	3	localParcel2	Parcel
    //   10	64	4	localObject1	Object
    //   78	11	4	localObject2	Object
    //   44	5	5	i	int
    // Exception table:
    //   from	to	target	type
    //   13	18	78	finally
    //   22	28	78	finally
    //   31	36	78	finally
    //   36	40	78	finally
    //   52	59	78	finally
    //   59	63	78	finally
  }
  
  /* Error */
  public void setOnStreetViewPanoramaChangeListener(zzx paramzzx)
  {
    // Byte code:
    //   0: invokestatic 20	android/os/Parcel:obtain	()Landroid/os/Parcel;
    //   3: astore_2
    //   4: invokestatic 20	android/os/Parcel:obtain	()Landroid/os/Parcel;
    //   7: astore_3
    //   8: ldc 22
    //   10: astore 4
    //   12: aload_2
    //   13: aload 4
    //   15: invokevirtual 26	android/os/Parcel:writeInterfaceToken	(Ljava/lang/String;)V
    //   18: aload_1
    //   19: ifnull +53 -> 72
    //   22: aload_1
    //   23: invokeinterface 128 1 0
    //   28: astore 4
    //   30: aload_2
    //   31: aload 4
    //   33: invokevirtual 111	android/os/Parcel:writeStrongBinder	(Landroid/os/IBinder;)V
    //   36: aload_0
    //   37: getfield 14	com/google/android/gms/maps/internal/IStreetViewPanoramaDelegate$zza$zza:zzoz	Landroid/os/IBinder;
    //   40: astore 4
    //   42: bipush 15
    //   44: istore 5
    //   46: aload 4
    //   48: iload 5
    //   50: aload_2
    //   51: aload_3
    //   52: iconst_0
    //   53: invokeinterface 48 5 0
    //   58: pop
    //   59: aload_3
    //   60: invokevirtual 51	android/os/Parcel:readException	()V
    //   63: aload_3
    //   64: invokevirtual 54	android/os/Parcel:recycle	()V
    //   67: aload_2
    //   68: invokevirtual 54	android/os/Parcel:recycle	()V
    //   71: return
    //   72: aconst_null
    //   73: astore 4
    //   75: goto -45 -> 30
    //   78: astore 4
    //   80: aload_3
    //   81: invokevirtual 54	android/os/Parcel:recycle	()V
    //   84: aload_2
    //   85: invokevirtual 54	android/os/Parcel:recycle	()V
    //   88: aload 4
    //   90: athrow
    // Local variable table:
    //   start	length	slot	name	signature
    //   0	91	0	this	zza
    //   0	91	1	paramzzx	zzx
    //   3	82	2	localParcel1	Parcel
    //   7	74	3	localParcel2	Parcel
    //   10	64	4	localObject1	Object
    //   78	11	4	localObject2	Object
    //   44	5	5	i	int
    // Exception table:
    //   from	to	target	type
    //   13	18	78	finally
    //   22	28	78	finally
    //   31	36	78	finally
    //   36	40	78	finally
    //   52	59	78	finally
    //   59	63	78	finally
  }
  
  /* Error */
  public void setOnStreetViewPanoramaClickListener(zzy paramzzy)
  {
    // Byte code:
    //   0: invokestatic 20	android/os/Parcel:obtain	()Landroid/os/Parcel;
    //   3: astore_2
    //   4: invokestatic 20	android/os/Parcel:obtain	()Landroid/os/Parcel;
    //   7: astore_3
    //   8: ldc 22
    //   10: astore 4
    //   12: aload_2
    //   13: aload 4
    //   15: invokevirtual 26	android/os/Parcel:writeInterfaceToken	(Ljava/lang/String;)V
    //   18: aload_1
    //   19: ifnull +53 -> 72
    //   22: aload_1
    //   23: invokeinterface 132 1 0
    //   28: astore 4
    //   30: aload_2
    //   31: aload 4
    //   33: invokevirtual 111	android/os/Parcel:writeStrongBinder	(Landroid/os/IBinder;)V
    //   36: aload_0
    //   37: getfield 14	com/google/android/gms/maps/internal/IStreetViewPanoramaDelegate$zza$zza:zzoz	Landroid/os/IBinder;
    //   40: astore 4
    //   42: bipush 17
    //   44: istore 5
    //   46: aload 4
    //   48: iload 5
    //   50: aload_2
    //   51: aload_3
    //   52: iconst_0
    //   53: invokeinterface 48 5 0
    //   58: pop
    //   59: aload_3
    //   60: invokevirtual 51	android/os/Parcel:readException	()V
    //   63: aload_3
    //   64: invokevirtual 54	android/os/Parcel:recycle	()V
    //   67: aload_2
    //   68: invokevirtual 54	android/os/Parcel:recycle	()V
    //   71: return
    //   72: aconst_null
    //   73: astore 4
    //   75: goto -45 -> 30
    //   78: astore 4
    //   80: aload_3
    //   81: invokevirtual 54	android/os/Parcel:recycle	()V
    //   84: aload_2
    //   85: invokevirtual 54	android/os/Parcel:recycle	()V
    //   88: aload 4
    //   90: athrow
    // Local variable table:
    //   start	length	slot	name	signature
    //   0	91	0	this	zza
    //   0	91	1	paramzzy	zzy
    //   3	82	2	localParcel1	Parcel
    //   7	74	3	localParcel2	Parcel
    //   10	64	4	localObject1	Object
    //   78	11	4	localObject2	Object
    //   44	5	5	i	int
    // Exception table:
    //   from	to	target	type
    //   13	18	78	finally
    //   22	28	78	finally
    //   31	36	78	finally
    //   36	40	78	finally
    //   52	59	78	finally
    //   59	63	78	finally
  }
  
  /* Error */
  public void setOnStreetViewPanoramaLongClickListener(zzz paramzzz)
  {
    // Byte code:
    //   0: invokestatic 20	android/os/Parcel:obtain	()Landroid/os/Parcel;
    //   3: astore_2
    //   4: invokestatic 20	android/os/Parcel:obtain	()Landroid/os/Parcel;
    //   7: astore_3
    //   8: ldc 22
    //   10: astore 4
    //   12: aload_2
    //   13: aload 4
    //   15: invokevirtual 26	android/os/Parcel:writeInterfaceToken	(Ljava/lang/String;)V
    //   18: aload_1
    //   19: ifnull +53 -> 72
    //   22: aload_1
    //   23: invokeinterface 136 1 0
    //   28: astore 4
    //   30: aload_2
    //   31: aload 4
    //   33: invokevirtual 111	android/os/Parcel:writeStrongBinder	(Landroid/os/IBinder;)V
    //   36: aload_0
    //   37: getfield 14	com/google/android/gms/maps/internal/IStreetViewPanoramaDelegate$zza$zza:zzoz	Landroid/os/IBinder;
    //   40: astore 4
    //   42: bipush 20
    //   44: istore 5
    //   46: aload 4
    //   48: iload 5
    //   50: aload_2
    //   51: aload_3
    //   52: iconst_0
    //   53: invokeinterface 48 5 0
    //   58: pop
    //   59: aload_3
    //   60: invokevirtual 51	android/os/Parcel:readException	()V
    //   63: aload_3
    //   64: invokevirtual 54	android/os/Parcel:recycle	()V
    //   67: aload_2
    //   68: invokevirtual 54	android/os/Parcel:recycle	()V
    //   71: return
    //   72: aconst_null
    //   73: astore 4
    //   75: goto -45 -> 30
    //   78: astore 4
    //   80: aload_3
    //   81: invokevirtual 54	android/os/Parcel:recycle	()V
    //   84: aload_2
    //   85: invokevirtual 54	android/os/Parcel:recycle	()V
    //   88: aload 4
    //   90: athrow
    // Local variable table:
    //   start	length	slot	name	signature
    //   0	91	0	this	zza
    //   0	91	1	paramzzz	zzz
    //   3	82	2	localParcel1	Parcel
    //   7	74	3	localParcel2	Parcel
    //   10	64	4	localObject1	Object
    //   78	11	4	localObject2	Object
    //   44	5	5	i	int
    // Exception table:
    //   from	to	target	type
    //   13	18	78	finally
    //   22	28	78	finally
    //   31	36	78	finally
    //   36	40	78	finally
    //   52	59	78	finally
    //   59	63	78	finally
  }
  
  /* Error */
  public void setPosition(com.google.android.gms.maps.model.LatLng paramLatLng)
  {
    // Byte code:
    //   0: invokestatic 20	android/os/Parcel:obtain	()Landroid/os/Parcel;
    //   3: astore_2
    //   4: invokestatic 20	android/os/Parcel:obtain	()Landroid/os/Parcel;
    //   7: astore_3
    //   8: ldc 22
    //   10: astore 4
    //   12: aload_2
    //   13: aload 4
    //   15: invokevirtual 26	android/os/Parcel:writeInterfaceToken	(Ljava/lang/String;)V
    //   18: aload_1
    //   19: ifnull +60 -> 79
    //   22: iconst_1
    //   23: istore 5
    //   25: aload_2
    //   26: iload 5
    //   28: invokevirtual 31	android/os/Parcel:writeInt	(I)V
    //   31: iconst_0
    //   32: istore 5
    //   34: aconst_null
    //   35: astore 4
    //   37: aload_1
    //   38: aload_2
    //   39: iconst_0
    //   40: invokevirtual 140	com/google/android/gms/maps/model/LatLng:writeToParcel	(Landroid/os/Parcel;I)V
    //   43: aload_0
    //   44: getfield 14	com/google/android/gms/maps/internal/IStreetViewPanoramaDelegate$zza$zza:zzoz	Landroid/os/IBinder;
    //   47: astore 4
    //   49: bipush 12
    //   51: istore 6
    //   53: aload 4
    //   55: iload 6
    //   57: aload_2
    //   58: aload_3
    //   59: iconst_0
    //   60: invokeinterface 48 5 0
    //   65: pop
    //   66: aload_3
    //   67: invokevirtual 51	android/os/Parcel:readException	()V
    //   70: aload_3
    //   71: invokevirtual 54	android/os/Parcel:recycle	()V
    //   74: aload_2
    //   75: invokevirtual 54	android/os/Parcel:recycle	()V
    //   78: return
    //   79: iconst_0
    //   80: istore 5
    //   82: aconst_null
    //   83: astore 4
    //   85: aload_2
    //   86: iconst_0
    //   87: invokevirtual 31	android/os/Parcel:writeInt	(I)V
    //   90: goto -47 -> 43
    //   93: astore 4
    //   95: aload_3
    //   96: invokevirtual 54	android/os/Parcel:recycle	()V
    //   99: aload_2
    //   100: invokevirtual 54	android/os/Parcel:recycle	()V
    //   103: aload 4
    //   105: athrow
    // Local variable table:
    //   start	length	slot	name	signature
    //   0	106	0	this	zza
    //   0	106	1	paramLatLng	com.google.android.gms.maps.model.LatLng
    //   3	97	2	localParcel1	Parcel
    //   7	89	3	localParcel2	Parcel
    //   10	74	4	localObject1	Object
    //   93	11	4	localObject2	Object
    //   23	58	5	i	int
    //   51	5	6	j	int
    // Exception table:
    //   from	to	target	type
    //   13	18	93	finally
    //   26	31	93	finally
    //   39	43	93	finally
    //   43	47	93	finally
    //   59	66	93	finally
    //   66	70	93	finally
    //   86	90	93	finally
  }
  
  public void setPositionWithID(String paramString)
  {
    Parcel localParcel1 = Parcel.obtain();
    Parcel localParcel2 = Parcel.obtain();
    Object localObject1 = "com.google.android.gms.maps.internal.IStreetViewPanoramaDelegate";
    try
    {
      localParcel1.writeInterfaceToken((String)localObject1);
      localParcel1.writeString(paramString);
      localObject1 = this.zzoz;
      int i = 11;
      ((IBinder)localObject1).transact(i, localParcel1, localParcel2, 0);
      localParcel2.readException();
      return;
    }
    finally
    {
      localParcel2.recycle();
      localParcel1.recycle();
    }
  }
  
  /* Error */
  public void setPositionWithRadius(com.google.android.gms.maps.model.LatLng paramLatLng, int paramInt)
  {
    // Byte code:
    //   0: invokestatic 20	android/os/Parcel:obtain	()Landroid/os/Parcel;
    //   3: astore_3
    //   4: invokestatic 20	android/os/Parcel:obtain	()Landroid/os/Parcel;
    //   7: astore 4
    //   9: ldc 22
    //   11: astore 5
    //   13: aload_3
    //   14: aload 5
    //   16: invokevirtual 26	android/os/Parcel:writeInterfaceToken	(Ljava/lang/String;)V
    //   19: aload_1
    //   20: ifnull +68 -> 88
    //   23: iconst_1
    //   24: istore 6
    //   26: aload_3
    //   27: iload 6
    //   29: invokevirtual 31	android/os/Parcel:writeInt	(I)V
    //   32: iconst_0
    //   33: istore 6
    //   35: aconst_null
    //   36: astore 5
    //   38: aload_1
    //   39: aload_3
    //   40: iconst_0
    //   41: invokevirtual 140	com/google/android/gms/maps/model/LatLng:writeToParcel	(Landroid/os/Parcel;I)V
    //   44: aload_3
    //   45: iload_2
    //   46: invokevirtual 31	android/os/Parcel:writeInt	(I)V
    //   49: aload_0
    //   50: getfield 14	com/google/android/gms/maps/internal/IStreetViewPanoramaDelegate$zza$zza:zzoz	Landroid/os/IBinder;
    //   53: astore 5
    //   55: bipush 13
    //   57: istore 7
    //   59: aload 5
    //   61: iload 7
    //   63: aload_3
    //   64: aload 4
    //   66: iconst_0
    //   67: invokeinterface 48 5 0
    //   72: pop
    //   73: aload 4
    //   75: invokevirtual 51	android/os/Parcel:readException	()V
    //   78: aload 4
    //   80: invokevirtual 54	android/os/Parcel:recycle	()V
    //   83: aload_3
    //   84: invokevirtual 54	android/os/Parcel:recycle	()V
    //   87: return
    //   88: iconst_0
    //   89: istore 6
    //   91: aconst_null
    //   92: astore 5
    //   94: aload_3
    //   95: iconst_0
    //   96: invokevirtual 31	android/os/Parcel:writeInt	(I)V
    //   99: goto -55 -> 44
    //   102: astore 5
    //   104: aload 4
    //   106: invokevirtual 54	android/os/Parcel:recycle	()V
    //   109: aload_3
    //   110: invokevirtual 54	android/os/Parcel:recycle	()V
    //   113: aload 5
    //   115: athrow
    // Local variable table:
    //   start	length	slot	name	signature
    //   0	116	0	this	zza
    //   0	116	1	paramLatLng	com.google.android.gms.maps.model.LatLng
    //   0	116	2	paramInt	int
    //   3	107	3	localParcel1	Parcel
    //   7	98	4	localParcel2	Parcel
    //   11	82	5	localObject1	Object
    //   102	12	5	localObject2	Object
    //   24	66	6	i	int
    //   57	5	7	j	int
    // Exception table:
    //   from	to	target	type
    //   14	19	102	finally
    //   27	32	102	finally
    //   40	44	102	finally
    //   45	49	102	finally
    //   49	53	102	finally
    //   66	73	102	finally
    //   73	78	102	finally
    //   95	99	102	finally
  }
}


/* Location:              C:\Users\haryo\Desktop\enjarify-master\presensi-enjarify.jar!\com\google\android\gms\maps\internal\IStreetViewPanoramaDelegate$zza$zza.class
 * Java compiler version: 5 (49.0)
 * JD-Core Version:       0.7.1
 */