package com.google.android.gms.maps.internal;

import android.os.IBinder;
import android.os.Parcel;
import com.google.android.gms.maps.model.internal.zza;
import com.google.android.gms.maps.model.internal.zza.zza;

class zzc$zza$zza
  implements zzc
{
  private IBinder zzoz;
  
  zzc$zza$zza(IBinder paramIBinder)
  {
    this.zzoz = paramIBinder;
  }
  
  public IBinder asBinder()
  {
    return this.zzoz;
  }
  
  /* Error */
  public void init(com.google.android.gms.dynamic.zzd paramzzd)
  {
    // Byte code:
    //   0: invokestatic 20	android/os/Parcel:obtain	()Landroid/os/Parcel;
    //   3: astore_2
    //   4: invokestatic 20	android/os/Parcel:obtain	()Landroid/os/Parcel;
    //   7: astore_3
    //   8: ldc 22
    //   10: astore 4
    //   12: aload_2
    //   13: aload 4
    //   15: invokevirtual 26	android/os/Parcel:writeInterfaceToken	(Ljava/lang/String;)V
    //   18: aload_1
    //   19: ifnull +52 -> 71
    //   22: aload_1
    //   23: invokeinterface 32 1 0
    //   28: astore 4
    //   30: aload_2
    //   31: aload 4
    //   33: invokevirtual 36	android/os/Parcel:writeStrongBinder	(Landroid/os/IBinder;)V
    //   36: aload_0
    //   37: getfield 14	com/google/android/gms/maps/internal/zzc$zza$zza:zzoz	Landroid/os/IBinder;
    //   40: astore 4
    //   42: iconst_1
    //   43: istore 5
    //   45: aload 4
    //   47: iload 5
    //   49: aload_2
    //   50: aload_3
    //   51: iconst_0
    //   52: invokeinterface 43 5 0
    //   57: pop
    //   58: aload_3
    //   59: invokevirtual 46	android/os/Parcel:readException	()V
    //   62: aload_3
    //   63: invokevirtual 49	android/os/Parcel:recycle	()V
    //   66: aload_2
    //   67: invokevirtual 49	android/os/Parcel:recycle	()V
    //   70: return
    //   71: aconst_null
    //   72: astore 4
    //   74: goto -44 -> 30
    //   77: astore 4
    //   79: aload_3
    //   80: invokevirtual 49	android/os/Parcel:recycle	()V
    //   83: aload_2
    //   84: invokevirtual 49	android/os/Parcel:recycle	()V
    //   87: aload 4
    //   89: athrow
    // Local variable table:
    //   start	length	slot	name	signature
    //   0	90	0	this	zza
    //   0	90	1	paramzzd	com.google.android.gms.dynamic.zzd
    //   3	81	2	localParcel1	Parcel
    //   7	73	3	localParcel2	Parcel
    //   10	63	4	localObject1	Object
    //   77	11	4	localObject2	Object
    //   43	5	5	i	int
    // Exception table:
    //   from	to	target	type
    //   13	18	77	finally
    //   22	28	77	finally
    //   31	36	77	finally
    //   36	40	77	finally
    //   51	58	77	finally
    //   58	62	77	finally
  }
  
  public ICameraUpdateFactoryDelegate zzAe()
  {
    Parcel localParcel1 = Parcel.obtain();
    Parcel localParcel2 = Parcel.obtain();
    Object localObject1 = "com.google.android.gms.maps.internal.ICreator";
    try
    {
      localParcel1.writeInterfaceToken((String)localObject1);
      localObject1 = this.zzoz;
      int i = 4;
      ((IBinder)localObject1).transact(i, localParcel1, localParcel2, 0);
      localParcel2.readException();
      localObject1 = localParcel2.readStrongBinder();
      localObject1 = ICameraUpdateFactoryDelegate.zza.zzcs((IBinder)localObject1);
      return (ICameraUpdateFactoryDelegate)localObject1;
    }
    finally
    {
      localParcel2.recycle();
      localParcel1.recycle();
    }
  }
  
  public zza zzAf()
  {
    Parcel localParcel1 = Parcel.obtain();
    Parcel localParcel2 = Parcel.obtain();
    Object localObject1 = "com.google.android.gms.maps.internal.ICreator";
    try
    {
      localParcel1.writeInterfaceToken((String)localObject1);
      localObject1 = this.zzoz;
      int i = 5;
      ((IBinder)localObject1).transact(i, localParcel1, localParcel2, 0);
      localParcel2.readException();
      localObject1 = localParcel2.readStrongBinder();
      localObject1 = zza.zza.zzdd((IBinder)localObject1);
      return (zza)localObject1;
    }
    finally
    {
      localParcel2.recycle();
      localParcel1.recycle();
    }
  }
  
  /* Error */
  public IMapViewDelegate zza(com.google.android.gms.dynamic.zzd paramzzd, com.google.android.gms.maps.GoogleMapOptions paramGoogleMapOptions)
  {
    // Byte code:
    //   0: invokestatic 20	android/os/Parcel:obtain	()Landroid/os/Parcel;
    //   3: astore_3
    //   4: invokestatic 20	android/os/Parcel:obtain	()Landroid/os/Parcel;
    //   7: astore 4
    //   9: ldc 22
    //   11: astore 5
    //   13: aload_3
    //   14: aload 5
    //   16: invokevirtual 26	android/os/Parcel:writeInterfaceToken	(Ljava/lang/String;)V
    //   19: aload_1
    //   20: ifnull +96 -> 116
    //   23: aload_1
    //   24: invokeinterface 32 1 0
    //   29: astore 5
    //   31: aload_3
    //   32: aload 5
    //   34: invokevirtual 36	android/os/Parcel:writeStrongBinder	(Landroid/os/IBinder;)V
    //   37: aload_2
    //   38: ifnull +87 -> 125
    //   41: iconst_1
    //   42: istore 6
    //   44: aload_3
    //   45: iload 6
    //   47: invokevirtual 70	android/os/Parcel:writeInt	(I)V
    //   50: iconst_0
    //   51: istore 6
    //   53: aconst_null
    //   54: astore 5
    //   56: aload_2
    //   57: aload_3
    //   58: iconst_0
    //   59: invokevirtual 76	com/google/android/gms/maps/GoogleMapOptions:writeToParcel	(Landroid/os/Parcel;I)V
    //   62: aload_0
    //   63: getfield 14	com/google/android/gms/maps/internal/zzc$zza$zza:zzoz	Landroid/os/IBinder;
    //   66: astore 5
    //   68: iconst_3
    //   69: istore 7
    //   71: aload 5
    //   73: iload 7
    //   75: aload_3
    //   76: aload 4
    //   78: iconst_0
    //   79: invokeinterface 43 5 0
    //   84: pop
    //   85: aload 4
    //   87: invokevirtual 46	android/os/Parcel:readException	()V
    //   90: aload 4
    //   92: invokevirtual 53	android/os/Parcel:readStrongBinder	()Landroid/os/IBinder;
    //   95: astore 5
    //   97: aload 5
    //   99: invokestatic 83	com/google/android/gms/maps/internal/IMapViewDelegate$zza:zzcz	(Landroid/os/IBinder;)Lcom/google/android/gms/maps/internal/IMapViewDelegate;
    //   102: astore 5
    //   104: aload 4
    //   106: invokevirtual 49	android/os/Parcel:recycle	()V
    //   109: aload_3
    //   110: invokevirtual 49	android/os/Parcel:recycle	()V
    //   113: aload 5
    //   115: areturn
    //   116: iconst_0
    //   117: istore 6
    //   119: aconst_null
    //   120: astore 5
    //   122: goto -91 -> 31
    //   125: iconst_0
    //   126: istore 6
    //   128: aconst_null
    //   129: astore 5
    //   131: aload_3
    //   132: iconst_0
    //   133: invokevirtual 70	android/os/Parcel:writeInt	(I)V
    //   136: goto -74 -> 62
    //   139: astore 5
    //   141: aload 4
    //   143: invokevirtual 49	android/os/Parcel:recycle	()V
    //   146: aload_3
    //   147: invokevirtual 49	android/os/Parcel:recycle	()V
    //   150: aload 5
    //   152: athrow
    // Local variable table:
    //   start	length	slot	name	signature
    //   0	153	0	this	zza
    //   0	153	1	paramzzd	com.google.android.gms.dynamic.zzd
    //   0	153	2	paramGoogleMapOptions	com.google.android.gms.maps.GoogleMapOptions
    //   3	144	3	localParcel1	Parcel
    //   7	135	4	localParcel2	Parcel
    //   11	119	5	localObject1	Object
    //   139	12	5	localObject2	Object
    //   42	85	6	i	int
    //   69	5	7	j	int
    // Exception table:
    //   from	to	target	type
    //   14	19	139	finally
    //   23	29	139	finally
    //   32	37	139	finally
    //   45	50	139	finally
    //   58	62	139	finally
    //   62	66	139	finally
    //   78	85	139	finally
    //   85	90	139	finally
    //   90	95	139	finally
    //   97	102	139	finally
    //   132	136	139	finally
  }
  
  /* Error */
  public IStreetViewPanoramaViewDelegate zza(com.google.android.gms.dynamic.zzd paramzzd, com.google.android.gms.maps.StreetViewPanoramaOptions paramStreetViewPanoramaOptions)
  {
    // Byte code:
    //   0: invokestatic 20	android/os/Parcel:obtain	()Landroid/os/Parcel;
    //   3: astore_3
    //   4: invokestatic 20	android/os/Parcel:obtain	()Landroid/os/Parcel;
    //   7: astore 4
    //   9: ldc 22
    //   11: astore 5
    //   13: aload_3
    //   14: aload 5
    //   16: invokevirtual 26	android/os/Parcel:writeInterfaceToken	(Ljava/lang/String;)V
    //   19: aload_1
    //   20: ifnull +97 -> 117
    //   23: aload_1
    //   24: invokeinterface 32 1 0
    //   29: astore 5
    //   31: aload_3
    //   32: aload 5
    //   34: invokevirtual 36	android/os/Parcel:writeStrongBinder	(Landroid/os/IBinder;)V
    //   37: aload_2
    //   38: ifnull +88 -> 126
    //   41: iconst_1
    //   42: istore 6
    //   44: aload_3
    //   45: iload 6
    //   47: invokevirtual 70	android/os/Parcel:writeInt	(I)V
    //   50: iconst_0
    //   51: istore 6
    //   53: aconst_null
    //   54: astore 5
    //   56: aload_2
    //   57: aload_3
    //   58: iconst_0
    //   59: invokevirtual 86	com/google/android/gms/maps/StreetViewPanoramaOptions:writeToParcel	(Landroid/os/Parcel;I)V
    //   62: aload_0
    //   63: getfield 14	com/google/android/gms/maps/internal/zzc$zza$zza:zzoz	Landroid/os/IBinder;
    //   66: astore 5
    //   68: bipush 7
    //   70: istore 7
    //   72: aload 5
    //   74: iload 7
    //   76: aload_3
    //   77: aload 4
    //   79: iconst_0
    //   80: invokeinterface 43 5 0
    //   85: pop
    //   86: aload 4
    //   88: invokevirtual 46	android/os/Parcel:readException	()V
    //   91: aload 4
    //   93: invokevirtual 53	android/os/Parcel:readStrongBinder	()Landroid/os/IBinder;
    //   96: astore 5
    //   98: aload 5
    //   100: invokestatic 93	com/google/android/gms/maps/internal/IStreetViewPanoramaViewDelegate$zza:zzdb	(Landroid/os/IBinder;)Lcom/google/android/gms/maps/internal/IStreetViewPanoramaViewDelegate;
    //   103: astore 5
    //   105: aload 4
    //   107: invokevirtual 49	android/os/Parcel:recycle	()V
    //   110: aload_3
    //   111: invokevirtual 49	android/os/Parcel:recycle	()V
    //   114: aload 5
    //   116: areturn
    //   117: iconst_0
    //   118: istore 6
    //   120: aconst_null
    //   121: astore 5
    //   123: goto -92 -> 31
    //   126: iconst_0
    //   127: istore 6
    //   129: aconst_null
    //   130: astore 5
    //   132: aload_3
    //   133: iconst_0
    //   134: invokevirtual 70	android/os/Parcel:writeInt	(I)V
    //   137: goto -75 -> 62
    //   140: astore 5
    //   142: aload 4
    //   144: invokevirtual 49	android/os/Parcel:recycle	()V
    //   147: aload_3
    //   148: invokevirtual 49	android/os/Parcel:recycle	()V
    //   151: aload 5
    //   153: athrow
    // Local variable table:
    //   start	length	slot	name	signature
    //   0	154	0	this	zza
    //   0	154	1	paramzzd	com.google.android.gms.dynamic.zzd
    //   0	154	2	paramStreetViewPanoramaOptions	com.google.android.gms.maps.StreetViewPanoramaOptions
    //   3	145	3	localParcel1	Parcel
    //   7	136	4	localParcel2	Parcel
    //   11	120	5	localObject1	Object
    //   140	12	5	localObject2	Object
    //   42	86	6	i	int
    //   70	5	7	j	int
    // Exception table:
    //   from	to	target	type
    //   14	19	140	finally
    //   23	29	140	finally
    //   32	37	140	finally
    //   45	50	140	finally
    //   58	62	140	finally
    //   62	66	140	finally
    //   79	86	140	finally
    //   86	91	140	finally
    //   91	96	140	finally
    //   98	103	140	finally
    //   133	137	140	finally
  }
  
  /* Error */
  public void zzd(com.google.android.gms.dynamic.zzd paramzzd, int paramInt)
  {
    // Byte code:
    //   0: invokestatic 20	android/os/Parcel:obtain	()Landroid/os/Parcel;
    //   3: astore_3
    //   4: invokestatic 20	android/os/Parcel:obtain	()Landroid/os/Parcel;
    //   7: astore 4
    //   9: ldc 22
    //   11: astore 5
    //   13: aload_3
    //   14: aload 5
    //   16: invokevirtual 26	android/os/Parcel:writeInterfaceToken	(Ljava/lang/String;)V
    //   19: aload_1
    //   20: ifnull +61 -> 81
    //   23: aload_1
    //   24: invokeinterface 32 1 0
    //   29: astore 5
    //   31: aload_3
    //   32: aload 5
    //   34: invokevirtual 36	android/os/Parcel:writeStrongBinder	(Landroid/os/IBinder;)V
    //   37: aload_3
    //   38: iload_2
    //   39: invokevirtual 70	android/os/Parcel:writeInt	(I)V
    //   42: aload_0
    //   43: getfield 14	com/google/android/gms/maps/internal/zzc$zza$zza:zzoz	Landroid/os/IBinder;
    //   46: astore 5
    //   48: bipush 6
    //   50: istore 6
    //   52: aload 5
    //   54: iload 6
    //   56: aload_3
    //   57: aload 4
    //   59: iconst_0
    //   60: invokeinterface 43 5 0
    //   65: pop
    //   66: aload 4
    //   68: invokevirtual 46	android/os/Parcel:readException	()V
    //   71: aload 4
    //   73: invokevirtual 49	android/os/Parcel:recycle	()V
    //   76: aload_3
    //   77: invokevirtual 49	android/os/Parcel:recycle	()V
    //   80: return
    //   81: aconst_null
    //   82: astore 5
    //   84: goto -53 -> 31
    //   87: astore 5
    //   89: aload 4
    //   91: invokevirtual 49	android/os/Parcel:recycle	()V
    //   94: aload_3
    //   95: invokevirtual 49	android/os/Parcel:recycle	()V
    //   98: aload 5
    //   100: athrow
    // Local variable table:
    //   start	length	slot	name	signature
    //   0	101	0	this	zza
    //   0	101	1	paramzzd	com.google.android.gms.dynamic.zzd
    //   0	101	2	paramInt	int
    //   3	92	3	localParcel1	Parcel
    //   7	83	4	localParcel2	Parcel
    //   11	72	5	localObject1	Object
    //   87	12	5	localObject2	Object
    //   50	5	6	i	int
    // Exception table:
    //   from	to	target	type
    //   14	19	87	finally
    //   23	29	87	finally
    //   32	37	87	finally
    //   38	42	87	finally
    //   42	46	87	finally
    //   59	66	87	finally
    //   66	71	87	finally
  }
  
  /* Error */
  public IMapFragmentDelegate zzs(com.google.android.gms.dynamic.zzd paramzzd)
  {
    // Byte code:
    //   0: invokestatic 20	android/os/Parcel:obtain	()Landroid/os/Parcel;
    //   3: astore_2
    //   4: invokestatic 20	android/os/Parcel:obtain	()Landroid/os/Parcel;
    //   7: astore_3
    //   8: ldc 22
    //   10: astore 4
    //   12: aload_2
    //   13: aload 4
    //   15: invokevirtual 26	android/os/Parcel:writeInterfaceToken	(Ljava/lang/String;)V
    //   18: aload_1
    //   19: ifnull +67 -> 86
    //   22: aload_1
    //   23: invokeinterface 32 1 0
    //   28: astore 4
    //   30: aload_2
    //   31: aload 4
    //   33: invokevirtual 36	android/os/Parcel:writeStrongBinder	(Landroid/os/IBinder;)V
    //   36: aload_0
    //   37: getfield 14	com/google/android/gms/maps/internal/zzc$zza$zza:zzoz	Landroid/os/IBinder;
    //   40: astore 4
    //   42: iconst_2
    //   43: istore 5
    //   45: aload 4
    //   47: iload 5
    //   49: aload_2
    //   50: aload_3
    //   51: iconst_0
    //   52: invokeinterface 43 5 0
    //   57: pop
    //   58: aload_3
    //   59: invokevirtual 46	android/os/Parcel:readException	()V
    //   62: aload_3
    //   63: invokevirtual 53	android/os/Parcel:readStrongBinder	()Landroid/os/IBinder;
    //   66: astore 4
    //   68: aload 4
    //   70: invokestatic 101	com/google/android/gms/maps/internal/IMapFragmentDelegate$zza:zzcy	(Landroid/os/IBinder;)Lcom/google/android/gms/maps/internal/IMapFragmentDelegate;
    //   73: astore 4
    //   75: aload_3
    //   76: invokevirtual 49	android/os/Parcel:recycle	()V
    //   79: aload_2
    //   80: invokevirtual 49	android/os/Parcel:recycle	()V
    //   83: aload 4
    //   85: areturn
    //   86: aconst_null
    //   87: astore 4
    //   89: goto -59 -> 30
    //   92: astore 4
    //   94: aload_3
    //   95: invokevirtual 49	android/os/Parcel:recycle	()V
    //   98: aload_2
    //   99: invokevirtual 49	android/os/Parcel:recycle	()V
    //   102: aload 4
    //   104: athrow
    // Local variable table:
    //   start	length	slot	name	signature
    //   0	105	0	this	zza
    //   0	105	1	paramzzd	com.google.android.gms.dynamic.zzd
    //   3	96	2	localParcel1	Parcel
    //   7	88	3	localParcel2	Parcel
    //   10	78	4	localObject1	Object
    //   92	11	4	localObject2	Object
    //   43	5	5	i	int
    // Exception table:
    //   from	to	target	type
    //   13	18	92	finally
    //   22	28	92	finally
    //   31	36	92	finally
    //   36	40	92	finally
    //   51	58	92	finally
    //   58	62	92	finally
    //   62	66	92	finally
    //   68	73	92	finally
  }
  
  /* Error */
  public IStreetViewPanoramaFragmentDelegate zzt(com.google.android.gms.dynamic.zzd paramzzd)
  {
    // Byte code:
    //   0: invokestatic 20	android/os/Parcel:obtain	()Landroid/os/Parcel;
    //   3: astore_2
    //   4: invokestatic 20	android/os/Parcel:obtain	()Landroid/os/Parcel;
    //   7: astore_3
    //   8: ldc 22
    //   10: astore 4
    //   12: aload_2
    //   13: aload 4
    //   15: invokevirtual 26	android/os/Parcel:writeInterfaceToken	(Ljava/lang/String;)V
    //   18: aload_1
    //   19: ifnull +68 -> 87
    //   22: aload_1
    //   23: invokeinterface 32 1 0
    //   28: astore 4
    //   30: aload_2
    //   31: aload 4
    //   33: invokevirtual 36	android/os/Parcel:writeStrongBinder	(Landroid/os/IBinder;)V
    //   36: aload_0
    //   37: getfield 14	com/google/android/gms/maps/internal/zzc$zza$zza:zzoz	Landroid/os/IBinder;
    //   40: astore 4
    //   42: bipush 8
    //   44: istore 5
    //   46: aload 4
    //   48: iload 5
    //   50: aload_2
    //   51: aload_3
    //   52: iconst_0
    //   53: invokeinterface 43 5 0
    //   58: pop
    //   59: aload_3
    //   60: invokevirtual 46	android/os/Parcel:readException	()V
    //   63: aload_3
    //   64: invokevirtual 53	android/os/Parcel:readStrongBinder	()Landroid/os/IBinder;
    //   67: astore 4
    //   69: aload 4
    //   71: invokestatic 108	com/google/android/gms/maps/internal/IStreetViewPanoramaFragmentDelegate$zza:zzda	(Landroid/os/IBinder;)Lcom/google/android/gms/maps/internal/IStreetViewPanoramaFragmentDelegate;
    //   74: astore 4
    //   76: aload_3
    //   77: invokevirtual 49	android/os/Parcel:recycle	()V
    //   80: aload_2
    //   81: invokevirtual 49	android/os/Parcel:recycle	()V
    //   84: aload 4
    //   86: areturn
    //   87: aconst_null
    //   88: astore 4
    //   90: goto -60 -> 30
    //   93: astore 4
    //   95: aload_3
    //   96: invokevirtual 49	android/os/Parcel:recycle	()V
    //   99: aload_2
    //   100: invokevirtual 49	android/os/Parcel:recycle	()V
    //   103: aload 4
    //   105: athrow
    // Local variable table:
    //   start	length	slot	name	signature
    //   0	106	0	this	zza
    //   0	106	1	paramzzd	com.google.android.gms.dynamic.zzd
    //   3	97	2	localParcel1	Parcel
    //   7	89	3	localParcel2	Parcel
    //   10	79	4	localObject1	Object
    //   93	11	4	localObject2	Object
    //   44	5	5	i	int
    // Exception table:
    //   from	to	target	type
    //   13	18	93	finally
    //   22	28	93	finally
    //   31	36	93	finally
    //   36	40	93	finally
    //   52	59	93	finally
    //   59	63	93	finally
    //   63	67	93	finally
    //   69	74	93	finally
  }
}


/* Location:              C:\Users\haryo\Desktop\enjarify-master\presensi-enjarify.jar!\com\google\android\gms\maps\internal\zzc$zza$zza.class
 * Java compiler version: 5 (49.0)
 * JD-Core Version:       0.7.1
 */