package com.google.android.gms.ads.internal.client;

import android.os.IBinder;
import android.os.Parcel;

class zzs$zza$zza
  implements zzs
{
  private IBinder zzoz;
  
  zzs$zza$zza(IBinder paramIBinder)
  {
    this.zzoz = paramIBinder;
  }
  
  public IBinder asBinder()
  {
    return this.zzoz;
  }
  
  /* Error */
  public void zza(com.google.android.gms.ads.internal.formats.NativeAdOptionsParcel paramNativeAdOptionsParcel)
  {
    // Byte code:
    //   0: invokestatic 20	android/os/Parcel:obtain	()Landroid/os/Parcel;
    //   3: astore_2
    //   4: invokestatic 20	android/os/Parcel:obtain	()Landroid/os/Parcel;
    //   7: astore_3
    //   8: ldc 22
    //   10: astore 4
    //   12: aload_2
    //   13: aload 4
    //   15: invokevirtual 26	android/os/Parcel:writeInterfaceToken	(Ljava/lang/String;)V
    //   18: aload_1
    //   19: ifnull +60 -> 79
    //   22: iconst_1
    //   23: istore 5
    //   25: aload_2
    //   26: iload 5
    //   28: invokevirtual 31	android/os/Parcel:writeInt	(I)V
    //   31: iconst_0
    //   32: istore 5
    //   34: aconst_null
    //   35: astore 4
    //   37: aload_1
    //   38: aload_2
    //   39: iconst_0
    //   40: invokevirtual 37	com/google/android/gms/ads/internal/formats/NativeAdOptionsParcel:writeToParcel	(Landroid/os/Parcel;I)V
    //   43: aload_0
    //   44: getfield 14	com/google/android/gms/ads/internal/client/zzs$zza$zza:zzoz	Landroid/os/IBinder;
    //   47: astore 4
    //   49: bipush 6
    //   51: istore 6
    //   53: aload 4
    //   55: iload 6
    //   57: aload_2
    //   58: aload_3
    //   59: iconst_0
    //   60: invokeinterface 44 5 0
    //   65: pop
    //   66: aload_3
    //   67: invokevirtual 47	android/os/Parcel:readException	()V
    //   70: aload_3
    //   71: invokevirtual 50	android/os/Parcel:recycle	()V
    //   74: aload_2
    //   75: invokevirtual 50	android/os/Parcel:recycle	()V
    //   78: return
    //   79: iconst_0
    //   80: istore 5
    //   82: aconst_null
    //   83: astore 4
    //   85: aload_2
    //   86: iconst_0
    //   87: invokevirtual 31	android/os/Parcel:writeInt	(I)V
    //   90: goto -47 -> 43
    //   93: astore 4
    //   95: aload_3
    //   96: invokevirtual 50	android/os/Parcel:recycle	()V
    //   99: aload_2
    //   100: invokevirtual 50	android/os/Parcel:recycle	()V
    //   103: aload 4
    //   105: athrow
    // Local variable table:
    //   start	length	slot	name	signature
    //   0	106	0	this	zza
    //   0	106	1	paramNativeAdOptionsParcel	com.google.android.gms.ads.internal.formats.NativeAdOptionsParcel
    //   3	97	2	localParcel1	Parcel
    //   7	89	3	localParcel2	Parcel
    //   10	74	4	localObject1	Object
    //   93	11	4	localObject2	Object
    //   23	58	5	i	int
    //   51	5	6	j	int
    // Exception table:
    //   from	to	target	type
    //   13	18	93	finally
    //   26	31	93	finally
    //   39	43	93	finally
    //   43	47	93	finally
    //   59	66	93	finally
    //   66	70	93	finally
    //   86	90	93	finally
  }
  
  /* Error */
  public void zza(com.google.android.gms.internal.zzcr paramzzcr)
  {
    // Byte code:
    //   0: invokestatic 20	android/os/Parcel:obtain	()Landroid/os/Parcel;
    //   3: astore_2
    //   4: invokestatic 20	android/os/Parcel:obtain	()Landroid/os/Parcel;
    //   7: astore_3
    //   8: ldc 22
    //   10: astore 4
    //   12: aload_2
    //   13: aload 4
    //   15: invokevirtual 26	android/os/Parcel:writeInterfaceToken	(Ljava/lang/String;)V
    //   18: aload_1
    //   19: ifnull +52 -> 71
    //   22: aload_1
    //   23: invokeinterface 56 1 0
    //   28: astore 4
    //   30: aload_2
    //   31: aload 4
    //   33: invokevirtual 60	android/os/Parcel:writeStrongBinder	(Landroid/os/IBinder;)V
    //   36: aload_0
    //   37: getfield 14	com/google/android/gms/ads/internal/client/zzs$zza$zza:zzoz	Landroid/os/IBinder;
    //   40: astore 4
    //   42: iconst_3
    //   43: istore 5
    //   45: aload 4
    //   47: iload 5
    //   49: aload_2
    //   50: aload_3
    //   51: iconst_0
    //   52: invokeinterface 44 5 0
    //   57: pop
    //   58: aload_3
    //   59: invokevirtual 47	android/os/Parcel:readException	()V
    //   62: aload_3
    //   63: invokevirtual 50	android/os/Parcel:recycle	()V
    //   66: aload_2
    //   67: invokevirtual 50	android/os/Parcel:recycle	()V
    //   70: return
    //   71: aconst_null
    //   72: astore 4
    //   74: goto -44 -> 30
    //   77: astore 4
    //   79: aload_3
    //   80: invokevirtual 50	android/os/Parcel:recycle	()V
    //   83: aload_2
    //   84: invokevirtual 50	android/os/Parcel:recycle	()V
    //   87: aload 4
    //   89: athrow
    // Local variable table:
    //   start	length	slot	name	signature
    //   0	90	0	this	zza
    //   0	90	1	paramzzcr	com.google.android.gms.internal.zzcr
    //   3	81	2	localParcel1	Parcel
    //   7	73	3	localParcel2	Parcel
    //   10	63	4	localObject1	Object
    //   77	11	4	localObject2	Object
    //   43	5	5	i	int
    // Exception table:
    //   from	to	target	type
    //   13	18	77	finally
    //   22	28	77	finally
    //   31	36	77	finally
    //   36	40	77	finally
    //   51	58	77	finally
    //   58	62	77	finally
  }
  
  /* Error */
  public void zza(com.google.android.gms.internal.zzcs paramzzcs)
  {
    // Byte code:
    //   0: invokestatic 20	android/os/Parcel:obtain	()Landroid/os/Parcel;
    //   3: astore_2
    //   4: invokestatic 20	android/os/Parcel:obtain	()Landroid/os/Parcel;
    //   7: astore_3
    //   8: ldc 22
    //   10: astore 4
    //   12: aload_2
    //   13: aload 4
    //   15: invokevirtual 26	android/os/Parcel:writeInterfaceToken	(Ljava/lang/String;)V
    //   18: aload_1
    //   19: ifnull +52 -> 71
    //   22: aload_1
    //   23: invokeinterface 64 1 0
    //   28: astore 4
    //   30: aload_2
    //   31: aload 4
    //   33: invokevirtual 60	android/os/Parcel:writeStrongBinder	(Landroid/os/IBinder;)V
    //   36: aload_0
    //   37: getfield 14	com/google/android/gms/ads/internal/client/zzs$zza$zza:zzoz	Landroid/os/IBinder;
    //   40: astore 4
    //   42: iconst_4
    //   43: istore 5
    //   45: aload 4
    //   47: iload 5
    //   49: aload_2
    //   50: aload_3
    //   51: iconst_0
    //   52: invokeinterface 44 5 0
    //   57: pop
    //   58: aload_3
    //   59: invokevirtual 47	android/os/Parcel:readException	()V
    //   62: aload_3
    //   63: invokevirtual 50	android/os/Parcel:recycle	()V
    //   66: aload_2
    //   67: invokevirtual 50	android/os/Parcel:recycle	()V
    //   70: return
    //   71: aconst_null
    //   72: astore 4
    //   74: goto -44 -> 30
    //   77: astore 4
    //   79: aload_3
    //   80: invokevirtual 50	android/os/Parcel:recycle	()V
    //   83: aload_2
    //   84: invokevirtual 50	android/os/Parcel:recycle	()V
    //   87: aload 4
    //   89: athrow
    // Local variable table:
    //   start	length	slot	name	signature
    //   0	90	0	this	zza
    //   0	90	1	paramzzcs	com.google.android.gms.internal.zzcs
    //   3	81	2	localParcel1	Parcel
    //   7	73	3	localParcel2	Parcel
    //   10	63	4	localObject1	Object
    //   77	11	4	localObject2	Object
    //   43	5	5	i	int
    // Exception table:
    //   from	to	target	type
    //   13	18	77	finally
    //   22	28	77	finally
    //   31	36	77	finally
    //   36	40	77	finally
    //   51	58	77	finally
    //   58	62	77	finally
  }
  
  /* Error */
  public void zza(String paramString, com.google.android.gms.internal.zzcu paramzzcu, com.google.android.gms.internal.zzct paramzzct)
  {
    // Byte code:
    //   0: aconst_null
    //   1: astore 4
    //   3: invokestatic 20	android/os/Parcel:obtain	()Landroid/os/Parcel;
    //   6: astore 5
    //   8: invokestatic 20	android/os/Parcel:obtain	()Landroid/os/Parcel;
    //   11: astore 6
    //   13: ldc 22
    //   15: astore 7
    //   17: aload 5
    //   19: aload 7
    //   21: invokevirtual 26	android/os/Parcel:writeInterfaceToken	(Ljava/lang/String;)V
    //   24: aload 5
    //   26: aload_1
    //   27: invokevirtual 68	android/os/Parcel:writeString	(Ljava/lang/String;)V
    //   30: aload_2
    //   31: ifnull +77 -> 108
    //   34: aload_2
    //   35: invokeinterface 71 1 0
    //   40: astore 7
    //   42: aload 5
    //   44: aload 7
    //   46: invokevirtual 60	android/os/Parcel:writeStrongBinder	(Landroid/os/IBinder;)V
    //   49: aload_3
    //   50: ifnull +11 -> 61
    //   53: aload_3
    //   54: invokeinterface 74 1 0
    //   59: astore 4
    //   61: aload 5
    //   63: aload 4
    //   65: invokevirtual 60	android/os/Parcel:writeStrongBinder	(Landroid/os/IBinder;)V
    //   68: aload_0
    //   69: getfield 14	com/google/android/gms/ads/internal/client/zzs$zza$zza:zzoz	Landroid/os/IBinder;
    //   72: astore 4
    //   74: iconst_5
    //   75: istore 8
    //   77: aload 4
    //   79: iload 8
    //   81: aload 5
    //   83: aload 6
    //   85: iconst_0
    //   86: invokeinterface 44 5 0
    //   91: pop
    //   92: aload 6
    //   94: invokevirtual 47	android/os/Parcel:readException	()V
    //   97: aload 6
    //   99: invokevirtual 50	android/os/Parcel:recycle	()V
    //   102: aload 5
    //   104: invokevirtual 50	android/os/Parcel:recycle	()V
    //   107: return
    //   108: iconst_0
    //   109: istore 8
    //   111: aconst_null
    //   112: astore 7
    //   114: goto -72 -> 42
    //   117: astore 4
    //   119: aload 6
    //   121: invokevirtual 50	android/os/Parcel:recycle	()V
    //   124: aload 5
    //   126: invokevirtual 50	android/os/Parcel:recycle	()V
    //   129: aload 4
    //   131: athrow
    // Local variable table:
    //   start	length	slot	name	signature
    //   0	132	0	this	zza
    //   0	132	1	paramString	String
    //   0	132	2	paramzzcu	com.google.android.gms.internal.zzcu
    //   0	132	3	paramzzct	com.google.android.gms.internal.zzct
    //   1	77	4	localIBinder	IBinder
    //   117	13	4	localObject1	Object
    //   6	119	5	localParcel1	Parcel
    //   11	109	6	localParcel2	Parcel
    //   15	98	7	localObject2	Object
    //   75	35	8	i	int
    // Exception table:
    //   from	to	target	type
    //   19	24	117	finally
    //   26	30	117	finally
    //   34	40	117	finally
    //   44	49	117	finally
    //   53	59	117	finally
    //   63	68	117	finally
    //   68	72	117	finally
    //   85	92	117	finally
    //   92	97	117	finally
  }
  
  /* Error */
  public void zzb(zzq paramzzq)
  {
    // Byte code:
    //   0: invokestatic 20	android/os/Parcel:obtain	()Landroid/os/Parcel;
    //   3: astore_2
    //   4: invokestatic 20	android/os/Parcel:obtain	()Landroid/os/Parcel;
    //   7: astore_3
    //   8: ldc 22
    //   10: astore 4
    //   12: aload_2
    //   13: aload 4
    //   15: invokevirtual 26	android/os/Parcel:writeInterfaceToken	(Ljava/lang/String;)V
    //   18: aload_1
    //   19: ifnull +52 -> 71
    //   22: aload_1
    //   23: invokeinterface 78 1 0
    //   28: astore 4
    //   30: aload_2
    //   31: aload 4
    //   33: invokevirtual 60	android/os/Parcel:writeStrongBinder	(Landroid/os/IBinder;)V
    //   36: aload_0
    //   37: getfield 14	com/google/android/gms/ads/internal/client/zzs$zza$zza:zzoz	Landroid/os/IBinder;
    //   40: astore 4
    //   42: iconst_2
    //   43: istore 5
    //   45: aload 4
    //   47: iload 5
    //   49: aload_2
    //   50: aload_3
    //   51: iconst_0
    //   52: invokeinterface 44 5 0
    //   57: pop
    //   58: aload_3
    //   59: invokevirtual 47	android/os/Parcel:readException	()V
    //   62: aload_3
    //   63: invokevirtual 50	android/os/Parcel:recycle	()V
    //   66: aload_2
    //   67: invokevirtual 50	android/os/Parcel:recycle	()V
    //   70: return
    //   71: aconst_null
    //   72: astore 4
    //   74: goto -44 -> 30
    //   77: astore 4
    //   79: aload_3
    //   80: invokevirtual 50	android/os/Parcel:recycle	()V
    //   83: aload_2
    //   84: invokevirtual 50	android/os/Parcel:recycle	()V
    //   87: aload 4
    //   89: athrow
    // Local variable table:
    //   start	length	slot	name	signature
    //   0	90	0	this	zza
    //   0	90	1	paramzzq	zzq
    //   3	81	2	localParcel1	Parcel
    //   7	73	3	localParcel2	Parcel
    //   10	63	4	localObject1	Object
    //   77	11	4	localObject2	Object
    //   43	5	5	i	int
    // Exception table:
    //   from	to	target	type
    //   13	18	77	finally
    //   22	28	77	finally
    //   31	36	77	finally
    //   36	40	77	finally
    //   51	58	77	finally
    //   58	62	77	finally
  }
  
  /* Error */
  public void zzb(zzx paramzzx)
  {
    // Byte code:
    //   0: invokestatic 20	android/os/Parcel:obtain	()Landroid/os/Parcel;
    //   3: astore_2
    //   4: invokestatic 20	android/os/Parcel:obtain	()Landroid/os/Parcel;
    //   7: astore_3
    //   8: ldc 22
    //   10: astore 4
    //   12: aload_2
    //   13: aload 4
    //   15: invokevirtual 26	android/os/Parcel:writeInterfaceToken	(Ljava/lang/String;)V
    //   18: aload_1
    //   19: ifnull +53 -> 72
    //   22: aload_1
    //   23: invokeinterface 82 1 0
    //   28: astore 4
    //   30: aload_2
    //   31: aload 4
    //   33: invokevirtual 60	android/os/Parcel:writeStrongBinder	(Landroid/os/IBinder;)V
    //   36: aload_0
    //   37: getfield 14	com/google/android/gms/ads/internal/client/zzs$zza$zza:zzoz	Landroid/os/IBinder;
    //   40: astore 4
    //   42: bipush 7
    //   44: istore 5
    //   46: aload 4
    //   48: iload 5
    //   50: aload_2
    //   51: aload_3
    //   52: iconst_0
    //   53: invokeinterface 44 5 0
    //   58: pop
    //   59: aload_3
    //   60: invokevirtual 47	android/os/Parcel:readException	()V
    //   63: aload_3
    //   64: invokevirtual 50	android/os/Parcel:recycle	()V
    //   67: aload_2
    //   68: invokevirtual 50	android/os/Parcel:recycle	()V
    //   71: return
    //   72: aconst_null
    //   73: astore 4
    //   75: goto -45 -> 30
    //   78: astore 4
    //   80: aload_3
    //   81: invokevirtual 50	android/os/Parcel:recycle	()V
    //   84: aload_2
    //   85: invokevirtual 50	android/os/Parcel:recycle	()V
    //   88: aload 4
    //   90: athrow
    // Local variable table:
    //   start	length	slot	name	signature
    //   0	91	0	this	zza
    //   0	91	1	paramzzx	zzx
    //   3	82	2	localParcel1	Parcel
    //   7	74	3	localParcel2	Parcel
    //   10	64	4	localObject1	Object
    //   78	11	4	localObject2	Object
    //   44	5	5	i	int
    // Exception table:
    //   from	to	target	type
    //   13	18	78	finally
    //   22	28	78	finally
    //   31	36	78	finally
    //   36	40	78	finally
    //   52	59	78	finally
    //   59	63	78	finally
  }
  
  public zzr zzbn()
  {
    Parcel localParcel1 = Parcel.obtain();
    Parcel localParcel2 = Parcel.obtain();
    Object localObject1 = "com.google.android.gms.ads.internal.client.IAdLoaderBuilder";
    try
    {
      localParcel1.writeInterfaceToken((String)localObject1);
      localObject1 = this.zzoz;
      int i = 1;
      ((IBinder)localObject1).transact(i, localParcel1, localParcel2, 0);
      localParcel2.readException();
      localObject1 = localParcel2.readStrongBinder();
      localObject1 = zzr.zza.zzh((IBinder)localObject1);
      return (zzr)localObject1;
    }
    finally
    {
      localParcel2.recycle();
      localParcel1.recycle();
    }
  }
}


/* Location:              C:\Users\haryo\Desktop\enjarify-master\presensi-enjarify.jar!\com\google\android\gms\ads\internal\client\zzs$zza$zza.class
 * Java compiler version: 5 (49.0)
 * JD-Core Version:       0.7.1
 */