package com.google.android.gms.ads.internal.client;

import android.os.IBinder;

class zzv$zza$zza
  implements zzv
{
  private IBinder zzoz;
  
  zzv$zza$zza(IBinder paramIBinder)
  {
    this.zzoz = paramIBinder;
  }
  
  public IBinder asBinder()
  {
    return this.zzoz;
  }
  
  /* Error */
  public IBinder zza(com.google.android.gms.dynamic.zzd paramzzd, AdSizeParcel paramAdSizeParcel, String paramString, com.google.android.gms.internal.zzex paramzzex, int paramInt)
  {
    // Byte code:
    //   0: aconst_null
    //   1: astore 6
    //   3: invokestatic 20	android/os/Parcel:obtain	()Landroid/os/Parcel;
    //   6: astore 7
    //   8: invokestatic 20	android/os/Parcel:obtain	()Landroid/os/Parcel;
    //   11: astore 8
    //   13: ldc 22
    //   15: astore 9
    //   17: aload 7
    //   19: aload 9
    //   21: invokevirtual 26	android/os/Parcel:writeInterfaceToken	(Ljava/lang/String;)V
    //   24: aload_1
    //   25: ifnull +128 -> 153
    //   28: aload_1
    //   29: invokeinterface 32 1 0
    //   34: astore 9
    //   36: aload 7
    //   38: aload 9
    //   40: invokevirtual 36	android/os/Parcel:writeStrongBinder	(Landroid/os/IBinder;)V
    //   43: aload_2
    //   44: ifnull +118 -> 162
    //   47: iconst_1
    //   48: istore 10
    //   50: aload 7
    //   52: iload 10
    //   54: invokevirtual 41	android/os/Parcel:writeInt	(I)V
    //   57: iconst_0
    //   58: istore 10
    //   60: aconst_null
    //   61: astore 9
    //   63: aload_2
    //   64: aload 7
    //   66: iconst_0
    //   67: invokevirtual 47	com/google/android/gms/ads/internal/client/AdSizeParcel:writeToParcel	(Landroid/os/Parcel;I)V
    //   70: aload 7
    //   72: aload_3
    //   73: invokevirtual 50	android/os/Parcel:writeString	(Ljava/lang/String;)V
    //   76: aload 4
    //   78: ifnull +12 -> 90
    //   81: aload 4
    //   83: invokeinterface 53 1 0
    //   88: astore 6
    //   90: aload 7
    //   92: aload 6
    //   94: invokevirtual 36	android/os/Parcel:writeStrongBinder	(Landroid/os/IBinder;)V
    //   97: aload 7
    //   99: iload 5
    //   101: invokevirtual 41	android/os/Parcel:writeInt	(I)V
    //   104: aload_0
    //   105: getfield 14	com/google/android/gms/ads/internal/client/zzv$zza$zza:zzoz	Landroid/os/IBinder;
    //   108: astore 6
    //   110: iconst_1
    //   111: istore 10
    //   113: aload 6
    //   115: iload 10
    //   117: aload 7
    //   119: aload 8
    //   121: iconst_0
    //   122: invokeinterface 59 5 0
    //   127: pop
    //   128: aload 8
    //   130: invokevirtual 62	android/os/Parcel:readException	()V
    //   133: aload 8
    //   135: invokevirtual 65	android/os/Parcel:readStrongBinder	()Landroid/os/IBinder;
    //   138: astore 6
    //   140: aload 8
    //   142: invokevirtual 68	android/os/Parcel:recycle	()V
    //   145: aload 7
    //   147: invokevirtual 68	android/os/Parcel:recycle	()V
    //   150: aload 6
    //   152: areturn
    //   153: iconst_0
    //   154: istore 10
    //   156: aconst_null
    //   157: astore 9
    //   159: goto -123 -> 36
    //   162: iconst_0
    //   163: istore 10
    //   165: aconst_null
    //   166: astore 9
    //   168: aload 7
    //   170: iconst_0
    //   171: invokevirtual 41	android/os/Parcel:writeInt	(I)V
    //   174: goto -104 -> 70
    //   177: astore 6
    //   179: aload 8
    //   181: invokevirtual 68	android/os/Parcel:recycle	()V
    //   184: aload 7
    //   186: invokevirtual 68	android/os/Parcel:recycle	()V
    //   189: aload 6
    //   191: athrow
    // Local variable table:
    //   start	length	slot	name	signature
    //   0	192	0	this	zza
    //   0	192	1	paramzzd	com.google.android.gms.dynamic.zzd
    //   0	192	2	paramAdSizeParcel	AdSizeParcel
    //   0	192	3	paramString	String
    //   0	192	4	paramzzex	com.google.android.gms.internal.zzex
    //   0	192	5	paramInt	int
    //   1	150	6	localIBinder	IBinder
    //   177	13	6	localObject1	Object
    //   6	179	7	localParcel1	android.os.Parcel
    //   11	169	8	localParcel2	android.os.Parcel
    //   15	152	9	localObject2	Object
    //   48	116	10	i	int
    // Exception table:
    //   from	to	target	type
    //   19	24	177	finally
    //   28	34	177	finally
    //   38	43	177	finally
    //   52	57	177	finally
    //   66	70	177	finally
    //   72	76	177	finally
    //   81	88	177	finally
    //   92	97	177	finally
    //   99	104	177	finally
    //   104	108	177	finally
    //   121	128	177	finally
    //   128	133	177	finally
    //   133	138	177	finally
    //   170	174	177	finally
  }
  
  /* Error */
  public IBinder zza(com.google.android.gms.dynamic.zzd paramzzd, AdSizeParcel paramAdSizeParcel, String paramString, com.google.android.gms.internal.zzex paramzzex, int paramInt1, int paramInt2)
  {
    // Byte code:
    //   0: aconst_null
    //   1: astore 7
    //   3: invokestatic 20	android/os/Parcel:obtain	()Landroid/os/Parcel;
    //   6: astore 8
    //   8: invokestatic 20	android/os/Parcel:obtain	()Landroid/os/Parcel;
    //   11: astore 9
    //   13: ldc 22
    //   15: astore 10
    //   17: aload 8
    //   19: aload 10
    //   21: invokevirtual 26	android/os/Parcel:writeInterfaceToken	(Ljava/lang/String;)V
    //   24: aload_1
    //   25: ifnull +135 -> 160
    //   28: aload_1
    //   29: invokeinterface 32 1 0
    //   34: astore 10
    //   36: aload 8
    //   38: aload 10
    //   40: invokevirtual 36	android/os/Parcel:writeStrongBinder	(Landroid/os/IBinder;)V
    //   43: aload_2
    //   44: ifnull +125 -> 169
    //   47: iconst_1
    //   48: istore 11
    //   50: aload 8
    //   52: iload 11
    //   54: invokevirtual 41	android/os/Parcel:writeInt	(I)V
    //   57: iconst_0
    //   58: istore 11
    //   60: aconst_null
    //   61: astore 10
    //   63: aload_2
    //   64: aload 8
    //   66: iconst_0
    //   67: invokevirtual 47	com/google/android/gms/ads/internal/client/AdSizeParcel:writeToParcel	(Landroid/os/Parcel;I)V
    //   70: aload 8
    //   72: aload_3
    //   73: invokevirtual 50	android/os/Parcel:writeString	(Ljava/lang/String;)V
    //   76: aload 4
    //   78: ifnull +12 -> 90
    //   81: aload 4
    //   83: invokeinterface 53 1 0
    //   88: astore 7
    //   90: aload 8
    //   92: aload 7
    //   94: invokevirtual 36	android/os/Parcel:writeStrongBinder	(Landroid/os/IBinder;)V
    //   97: aload 8
    //   99: iload 5
    //   101: invokevirtual 41	android/os/Parcel:writeInt	(I)V
    //   104: aload 8
    //   106: iload 6
    //   108: invokevirtual 41	android/os/Parcel:writeInt	(I)V
    //   111: aload_0
    //   112: getfield 14	com/google/android/gms/ads/internal/client/zzv$zza$zza:zzoz	Landroid/os/IBinder;
    //   115: astore 7
    //   117: iconst_2
    //   118: istore 11
    //   120: aload 7
    //   122: iload 11
    //   124: aload 8
    //   126: aload 9
    //   128: iconst_0
    //   129: invokeinterface 59 5 0
    //   134: pop
    //   135: aload 9
    //   137: invokevirtual 62	android/os/Parcel:readException	()V
    //   140: aload 9
    //   142: invokevirtual 65	android/os/Parcel:readStrongBinder	()Landroid/os/IBinder;
    //   145: astore 7
    //   147: aload 9
    //   149: invokevirtual 68	android/os/Parcel:recycle	()V
    //   152: aload 8
    //   154: invokevirtual 68	android/os/Parcel:recycle	()V
    //   157: aload 7
    //   159: areturn
    //   160: iconst_0
    //   161: istore 11
    //   163: aconst_null
    //   164: astore 10
    //   166: goto -130 -> 36
    //   169: iconst_0
    //   170: istore 11
    //   172: aconst_null
    //   173: astore 10
    //   175: aload 8
    //   177: iconst_0
    //   178: invokevirtual 41	android/os/Parcel:writeInt	(I)V
    //   181: goto -111 -> 70
    //   184: astore 7
    //   186: aload 9
    //   188: invokevirtual 68	android/os/Parcel:recycle	()V
    //   191: aload 8
    //   193: invokevirtual 68	android/os/Parcel:recycle	()V
    //   196: aload 7
    //   198: athrow
    // Local variable table:
    //   start	length	slot	name	signature
    //   0	199	0	this	zza
    //   0	199	1	paramzzd	com.google.android.gms.dynamic.zzd
    //   0	199	2	paramAdSizeParcel	AdSizeParcel
    //   0	199	3	paramString	String
    //   0	199	4	paramzzex	com.google.android.gms.internal.zzex
    //   0	199	5	paramInt1	int
    //   0	199	6	paramInt2	int
    //   1	157	7	localIBinder	IBinder
    //   184	13	7	localObject1	Object
    //   6	186	8	localParcel1	android.os.Parcel
    //   11	176	9	localParcel2	android.os.Parcel
    //   15	159	10	localObject2	Object
    //   48	123	11	i	int
    // Exception table:
    //   from	to	target	type
    //   19	24	184	finally
    //   28	34	184	finally
    //   38	43	184	finally
    //   52	57	184	finally
    //   66	70	184	finally
    //   72	76	184	finally
    //   81	88	184	finally
    //   92	97	184	finally
    //   99	104	184	finally
    //   106	111	184	finally
    //   111	115	184	finally
    //   128	135	184	finally
    //   135	140	184	finally
    //   140	145	184	finally
    //   177	181	184	finally
  }
}


/* Location:              C:\Users\haryo\Desktop\enjarify-master\presensi-enjarify.jar!\com\google\android\gms\ads\internal\client\zzv$zza$zza.class
 * Java compiler version: 5 (49.0)
 * JD-Core Version:       0.7.1
 */