package com.google.android.gms.ads.internal;

import android.content.Context;
import android.content.pm.PackageManager;
import android.graphics.Rect;
import android.location.Location;
import android.os.Bundle;
import android.view.View;
import android.view.ViewGroup;
import android.view.ViewTreeObserver.OnGlobalLayoutListener;
import android.view.ViewTreeObserver.OnScrollChangedListener;
import com.google.android.gms.ads.AdSize;
import com.google.android.gms.ads.internal.client.AdRequestParcel;
import com.google.android.gms.ads.internal.client.AdSizeParcel;
import com.google.android.gms.ads.internal.client.SearchAdRequestParcel;
import com.google.android.gms.ads.internal.client.zzn;
import com.google.android.gms.ads.internal.request.AdResponseParcel;
import com.google.android.gms.ads.internal.util.client.VersionInfoParcel;
import com.google.android.gms.ads.internal.util.client.zza;
import com.google.android.gms.common.internal.zzx;
import com.google.android.gms.internal.zzau;
import com.google.android.gms.internal.zzav;
import com.google.android.gms.internal.zzax;
import com.google.android.gms.internal.zzbp;
import com.google.android.gms.internal.zzbt;
import com.google.android.gms.internal.zzex;
import com.google.android.gms.internal.zzif;
import com.google.android.gms.internal.zzif.zza;
import com.google.android.gms.internal.zzir;
import com.google.android.gms.internal.zzjk;
import com.google.android.gms.internal.zzjp;
import com.google.android.gms.internal.zzjq;
import com.google.android.gms.internal.zzjq.zzb;
import java.util.List;

public class zzf
  extends zzc
  implements ViewTreeObserver.OnGlobalLayoutListener, ViewTreeObserver.OnScrollChangedListener
{
  private boolean zzpE;
  
  public zzf(Context paramContext, AdSizeParcel paramAdSizeParcel, String paramString, zzex paramzzex, VersionInfoParcel paramVersionInfoParcel, zzd paramzzd)
  {
    super(paramContext, paramAdSizeParcel, paramString, paramzzex, paramVersionInfoParcel, paramzzd);
  }
  
  private AdSizeParcel zzb(zzif.zza paramzza)
  {
    int i = 1;
    int j = 0;
    Context localContext = null;
    Object localObject1 = paramzza.zzLe;
    boolean bool = ((AdResponseParcel)localObject1).zzul;
    if (bool)
    {
      localObject1 = this.zzpj.zzrp;
      return (AdSizeParcel)localObject1;
    }
    localObject1 = paramzza.zzLe.zzHW;
    Object localObject2;
    if (localObject1 != null)
    {
      localObject1 = ((String)localObject1).split("[xX]");
      localObject2 = localObject1[0].trim();
      localObject1[0] = localObject2;
      localObject2 = localObject1[i].trim();
      localObject1[i] = localObject2;
      localObject2 = localObject1[0];
      int k = Integer.parseInt((String)localObject2);
      j = Integer.parseInt(localObject1[i]);
      localObject1 = new com/google/android/gms/ads/AdSize;
      ((AdSize)localObject1).<init>(k, j);
    }
    for (;;)
    {
      localObject2 = new com/google/android/gms/ads/internal/client/AdSizeParcel;
      localContext = this.zzpj.context;
      ((AdSizeParcel)localObject2).<init>(localContext, (AdSize)localObject1);
      localObject1 = localObject2;
      break;
      localObject1 = this.zzpj.zzrp.zzcQ();
    }
  }
  
  /* Error */
  private boolean zzb(zzif paramzzif1, zzif paramzzif2)
  {
    // Byte code:
    //   0: iconst_1
    //   1: istore_3
    //   2: aload_2
    //   3: getfield 81	com/google/android/gms/internal/zzif:zzHT	Z
    //   6: istore 4
    //   8: iload 4
    //   10: ifeq +277 -> 287
    //   13: aload_2
    //   14: invokestatic 87	com/google/android/gms/ads/internal/zzm:zzf	(Lcom/google/android/gms/internal/zzif;)Landroid/view/View;
    //   17: astore 5
    //   19: aload 5
    //   21: ifnonnull +17 -> 38
    //   24: ldc 89
    //   26: invokestatic 95	com/google/android/gms/internal/zzin:zzaK	(Ljava/lang/String;)V
    //   29: iconst_0
    //   30: istore 4
    //   32: aconst_null
    //   33: astore 6
    //   35: iload 4
    //   37: ireturn
    //   38: aload_0
    //   39: getfield 30	com/google/android/gms/ads/internal/zzf:zzpj	Lcom/google/android/gms/ads/internal/zzs;
    //   42: getfield 99	com/google/android/gms/ads/internal/zzs:zzrm	Lcom/google/android/gms/ads/internal/zzs$zza;
    //   45: astore 6
    //   47: aload 6
    //   49: invokevirtual 105	com/google/android/gms/ads/internal/zzs$zza:getNextView	()Landroid/view/View;
    //   52: astore 7
    //   54: aload 7
    //   56: ifnull +52 -> 108
    //   59: aload 7
    //   61: instanceof 107
    //   64: istore 4
    //   66: iload 4
    //   68: ifeq +21 -> 89
    //   71: aload 7
    //   73: astore 6
    //   75: aload 7
    //   77: checkcast 107	com/google/android/gms/internal/zzjp
    //   80: astore 6
    //   82: aload 6
    //   84: invokeinterface 111 1 0
    //   89: aload_0
    //   90: getfield 30	com/google/android/gms/ads/internal/zzf:zzpj	Lcom/google/android/gms/ads/internal/zzs;
    //   93: getfield 99	com/google/android/gms/ads/internal/zzs:zzrm	Lcom/google/android/gms/ads/internal/zzs$zza;
    //   96: astore 6
    //   98: aload 6
    //   100: aload 7
    //   102: checkcast 113	android/view/View
    //   105: invokevirtual 117	com/google/android/gms/ads/internal/zzs$zza:removeView	(Landroid/view/View;)V
    //   108: aload_2
    //   109: invokestatic 121	com/google/android/gms/ads/internal/zzm:zzg	(Lcom/google/android/gms/internal/zzif;)Z
    //   112: istore 4
    //   114: iload 4
    //   116: ifne +9 -> 125
    //   119: aload_0
    //   120: aload 5
    //   122: invokevirtual 124	com/google/android/gms/ads/internal/zzf:zzb	(Landroid/view/View;)V
    //   125: aload_0
    //   126: getfield 30	com/google/android/gms/ads/internal/zzf:zzpj	Lcom/google/android/gms/ads/internal/zzs;
    //   129: getfield 99	com/google/android/gms/ads/internal/zzs:zzrm	Lcom/google/android/gms/ads/internal/zzs$zza;
    //   132: astore 6
    //   134: aload 6
    //   136: invokevirtual 128	com/google/android/gms/ads/internal/zzs$zza:getChildCount	()I
    //   139: istore 4
    //   141: iload 4
    //   143: iload_3
    //   144: if_icmple +17 -> 161
    //   147: aload_0
    //   148: getfield 30	com/google/android/gms/ads/internal/zzf:zzpj	Lcom/google/android/gms/ads/internal/zzs;
    //   151: getfield 99	com/google/android/gms/ads/internal/zzs:zzrm	Lcom/google/android/gms/ads/internal/zzs$zza;
    //   154: astore 6
    //   156: aload 6
    //   158: invokevirtual 131	com/google/android/gms/ads/internal/zzs$zza:showNext	()V
    //   161: aload_1
    //   162: ifnull +82 -> 244
    //   165: aload_0
    //   166: getfield 30	com/google/android/gms/ads/internal/zzf:zzpj	Lcom/google/android/gms/ads/internal/zzs;
    //   169: getfield 99	com/google/android/gms/ads/internal/zzs:zzrm	Lcom/google/android/gms/ads/internal/zzs$zza;
    //   172: invokevirtual 105	com/google/android/gms/ads/internal/zzs$zza:getNextView	()Landroid/view/View;
    //   175: astore 6
    //   177: aload 6
    //   179: instanceof 107
    //   182: istore 8
    //   184: iload 8
    //   186: ifeq +228 -> 414
    //   189: aload 6
    //   191: checkcast 107	com/google/android/gms/internal/zzjp
    //   194: astore 6
    //   196: aload_0
    //   197: getfield 30	com/google/android/gms/ads/internal/zzf:zzpj	Lcom/google/android/gms/ads/internal/zzs;
    //   200: getfield 69	com/google/android/gms/ads/internal/zzs:context	Landroid/content/Context;
    //   203: astore 7
    //   205: aload_0
    //   206: getfield 30	com/google/android/gms/ads/internal/zzf:zzpj	Lcom/google/android/gms/ads/internal/zzs;
    //   209: getfield 36	com/google/android/gms/ads/internal/zzs:zzrp	Lcom/google/android/gms/ads/internal/client/AdSizeParcel;
    //   212: astore 5
    //   214: aload_0
    //   215: getfield 135	com/google/android/gms/ads/internal/zzf:zzpe	Lcom/google/android/gms/internal/zzcb;
    //   218: astore 9
    //   220: aload 6
    //   222: aload 7
    //   224: aload 5
    //   226: aload 9
    //   228: invokeinterface 139 4 0
    //   233: aload_0
    //   234: getfield 30	com/google/android/gms/ads/internal/zzf:zzpj	Lcom/google/android/gms/ads/internal/zzs;
    //   237: astore 6
    //   239: aload 6
    //   241: invokevirtual 142	com/google/android/gms/ads/internal/zzs:zzbV	()V
    //   244: aload_0
    //   245: getfield 30	com/google/android/gms/ads/internal/zzf:zzpj	Lcom/google/android/gms/ads/internal/zzs;
    //   248: getfield 99	com/google/android/gms/ads/internal/zzs:zzrm	Lcom/google/android/gms/ads/internal/zzs$zza;
    //   251: astore 6
    //   253: aload 6
    //   255: iconst_0
    //   256: invokevirtual 146	com/google/android/gms/ads/internal/zzs$zza:setVisibility	(I)V
    //   259: iload_3
    //   260: istore 4
    //   262: goto -227 -> 35
    //   265: astore 6
    //   267: ldc -108
    //   269: astore 7
    //   271: aload 7
    //   273: aload 6
    //   275: invokestatic 152	com/google/android/gms/internal/zzin:zzd	(Ljava/lang/String;Ljava/lang/Throwable;)V
    //   278: iconst_0
    //   279: istore 4
    //   281: aconst_null
    //   282: astore 6
    //   284: goto -249 -> 35
    //   287: aload_2
    //   288: getfield 155	com/google/android/gms/internal/zzif:zzKW	Lcom/google/android/gms/ads/internal/client/AdSizeParcel;
    //   291: astore 6
    //   293: aload 6
    //   295: ifnull -170 -> 125
    //   298: aload_2
    //   299: getfield 159	com/google/android/gms/internal/zzif:zzED	Lcom/google/android/gms/internal/zzjp;
    //   302: astore 6
    //   304: aload 6
    //   306: ifnull -181 -> 125
    //   309: aload_2
    //   310: getfield 159	com/google/android/gms/internal/zzif:zzED	Lcom/google/android/gms/internal/zzjp;
    //   313: astore 6
    //   315: aload_2
    //   316: getfield 155	com/google/android/gms/internal/zzif:zzKW	Lcom/google/android/gms/ads/internal/client/AdSizeParcel;
    //   319: astore 7
    //   321: aload 6
    //   323: aload 7
    //   325: invokeinterface 162 2 0
    //   330: aload_0
    //   331: getfield 30	com/google/android/gms/ads/internal/zzf:zzpj	Lcom/google/android/gms/ads/internal/zzs;
    //   334: getfield 99	com/google/android/gms/ads/internal/zzs:zzrm	Lcom/google/android/gms/ads/internal/zzs$zza;
    //   337: invokevirtual 165	com/google/android/gms/ads/internal/zzs$zza:removeAllViews	()V
    //   340: aload_0
    //   341: getfield 30	com/google/android/gms/ads/internal/zzf:zzpj	Lcom/google/android/gms/ads/internal/zzs;
    //   344: getfield 99	com/google/android/gms/ads/internal/zzs:zzrm	Lcom/google/android/gms/ads/internal/zzs$zza;
    //   347: astore 6
    //   349: aload_2
    //   350: getfield 155	com/google/android/gms/internal/zzif:zzKW	Lcom/google/android/gms/ads/internal/client/AdSizeParcel;
    //   353: getfield 169	com/google/android/gms/ads/internal/client/AdSizeParcel:widthPixels	I
    //   356: istore 8
    //   358: aload 6
    //   360: iload 8
    //   362: invokevirtual 172	com/google/android/gms/ads/internal/zzs$zza:setMinimumWidth	(I)V
    //   365: aload_0
    //   366: getfield 30	com/google/android/gms/ads/internal/zzf:zzpj	Lcom/google/android/gms/ads/internal/zzs;
    //   369: getfield 99	com/google/android/gms/ads/internal/zzs:zzrm	Lcom/google/android/gms/ads/internal/zzs$zza;
    //   372: astore 6
    //   374: aload_2
    //   375: getfield 155	com/google/android/gms/internal/zzif:zzKW	Lcom/google/android/gms/ads/internal/client/AdSizeParcel;
    //   378: astore 7
    //   380: aload 7
    //   382: getfield 175	com/google/android/gms/ads/internal/client/AdSizeParcel:heightPixels	I
    //   385: istore 8
    //   387: aload 6
    //   389: iload 8
    //   391: invokevirtual 178	com/google/android/gms/ads/internal/zzs$zza:setMinimumHeight	(I)V
    //   394: aload_2
    //   395: getfield 159	com/google/android/gms/internal/zzif:zzED	Lcom/google/android/gms/internal/zzjp;
    //   398: invokeinterface 181 1 0
    //   403: astore 6
    //   405: aload_0
    //   406: aload 6
    //   408: invokevirtual 124	com/google/android/gms/ads/internal/zzf:zzb	(Landroid/view/View;)V
    //   411: goto -286 -> 125
    //   414: aload 6
    //   416: ifnull -183 -> 233
    //   419: aload_0
    //   420: getfield 30	com/google/android/gms/ads/internal/zzf:zzpj	Lcom/google/android/gms/ads/internal/zzs;
    //   423: getfield 99	com/google/android/gms/ads/internal/zzs:zzrm	Lcom/google/android/gms/ads/internal/zzs$zza;
    //   426: astore 7
    //   428: aload 7
    //   430: aload 6
    //   432: invokevirtual 117	com/google/android/gms/ads/internal/zzs$zza:removeView	(Landroid/view/View;)V
    //   435: goto -202 -> 233
    // Local variable table:
    //   start	length	slot	name	signature
    //   0	438	0	this	zzf
    //   0	438	1	paramzzif1	zzif
    //   0	438	2	paramzzif2	zzif
    //   1	259	3	i	int
    //   6	109	4	bool1	boolean
    //   139	141	4	j	int
    //   17	208	5	localObject1	Object
    //   33	221	6	localObject2	Object
    //   265	9	6	localThrowable	Throwable
    //   282	149	6	localObject3	Object
    //   52	377	7	localObject4	Object
    //   182	3	8	bool2	boolean
    //   356	34	8	k	int
    //   218	9	9	localzzcb	com.google.android.gms.internal.zzcb
    // Exception table:
    //   from	to	target	type
    //   120	125	265	finally
  }
  
  private void zzd(zzif paramzzif)
  {
    Object localObject1 = this.zzpj;
    boolean bool = ((zzs)localObject1).zzbW();
    Object localObject2;
    if (bool)
    {
      localObject1 = paramzzif.zzED;
      if (localObject1 != null)
      {
        localObject1 = paramzzif.zzKT;
        if (localObject1 != null)
        {
          localObject1 = this.zzpl;
          localObject2 = this.zzpj.zzrp;
          ((zzax)localObject1).zza((AdSizeParcel)localObject2, paramzzif);
        }
        bool = paramzzif.zzcv();
        if (!bool) {
          break label98;
        }
        localObject1 = this.zzpl;
        localObject2 = this.zzpj.zzrp;
        localObject1 = ((zzax)localObject1).zza((AdSizeParcel)localObject2, paramzzif);
        localObject2 = paramzzif.zzED;
        ((zzau)localObject1).zza((zzav)localObject2);
      }
    }
    for (;;)
    {
      return;
      label98:
      localObject1 = paramzzif.zzED.zzhU();
      localObject2 = new com/google/android/gms/ads/internal/zzf$1;
      ((zzf.1)localObject2).<init>(this, paramzzif);
      ((zzjq)localObject1).zza((zzjq.zzb)localObject2);
      continue;
      localObject1 = this.zzpj.zzrK;
      if (localObject1 != null)
      {
        localObject1 = paramzzif.zzKT;
        if (localObject1 != null)
        {
          localObject1 = this.zzpl;
          localObject2 = this.zzpj.zzrp;
          View localView = this.zzpj.zzrK;
          ((zzax)localObject1).zza((AdSizeParcel)localObject2, paramzzif, localView);
        }
      }
    }
  }
  
  public void onGlobalLayout()
  {
    zzif localzzif = this.zzpj.zzrq;
    zze(localzzif);
  }
  
  public void onScrollChanged()
  {
    zzif localzzif = this.zzpj.zzrq;
    zze(localzzif);
  }
  
  public void setManualImpressionsEnabled(boolean paramBoolean)
  {
    zzx.zzcD("setManualImpressionsEnabled must be called from the main thread.");
    this.zzpE = paramBoolean;
  }
  
  public void showInterstitial()
  {
    IllegalStateException localIllegalStateException = new java/lang/IllegalStateException;
    localIllegalStateException.<init>("Interstitial is NOT supported by BannerAdManager.");
    throw localIllegalStateException;
  }
  
  protected zzjp zza(zzif.zza paramzza, zze paramzze)
  {
    Object localObject = this.zzpj.zzrp;
    boolean bool = ((AdSizeParcel)localObject).zzul;
    if (bool)
    {
      localObject = this.zzpj;
      AdSizeParcel localAdSizeParcel = zzb(paramzza);
      ((zzs)localObject).zzrp = localAdSizeParcel;
    }
    return super.zza(paramzza, paramzze);
  }
  
  protected void zza(zzif paramzzif, boolean paramBoolean)
  {
    super.zza(paramzzif, paramBoolean);
    boolean bool = zzm.zzg(paramzzif);
    if (bool)
    {
      zzf.zza localzza = new com/google/android/gms/ads/internal/zzf$zza;
      localzza.<init>(this);
      zzm.zza(paramzzif, localzza);
    }
  }
  
  public boolean zza(zzif paramzzif1, zzif paramzzif2)
  {
    boolean bool = super.zza(paramzzif1, paramzzif2);
    if (!bool) {
      bool = false;
    }
    for (Object localObject = null;; localObject = null)
    {
      return bool;
      localObject = this.zzpj;
      bool = ((zzs)localObject).zzbW();
      if (!bool) {
        break;
      }
      bool = zzb(paramzzif1, paramzzif2);
      if (bool) {
        break;
      }
      zzf(0);
      bool = false;
    }
    bool = paramzzif2.zzIm;
    if (bool)
    {
      zze(paramzzif2);
      zzjk.zza(this.zzpj.zzrm, this);
      localObject = this.zzpj.zzrm;
      zzjk.zza((View)localObject, this);
    }
    for (;;)
    {
      zzd(paramzzif2);
      bool = true;
      break;
      localObject = this.zzpj;
      bool = ((zzs)localObject).zzbX();
      if (bool)
      {
        localObject = (Boolean)zzbt.zzxg.get();
        bool = ((Boolean)localObject).booleanValue();
        if (!bool) {}
      }
      else
      {
        zza(paramzzif2, false);
      }
    }
  }
  
  protected boolean zzaV()
  {
    boolean bool1 = true;
    Object localObject1 = zzr.zzbC();
    Object localObject2 = this.zzpj.context.getPackageManager();
    String str1 = this.zzpj.context.getPackageName();
    String str2 = "android.permission.INTERNET";
    boolean bool2 = ((zzir)localObject1).zza((PackageManager)localObject2, str1, str2);
    zza localzza;
    if (!bool2)
    {
      localzza = zzn.zzcS();
      localObject1 = this.zzpj.zzrm;
      localObject2 = this.zzpj.zzrp;
      str1 = "Missing internet permission in AndroidManifest.xml.";
      str2 = "Missing internet permission in AndroidManifest.xml. You must have the following declaration: <uses-permission android:name=\"android.permission.INTERNET\" />";
      localzza.zza((ViewGroup)localObject1, (AdSizeParcel)localObject2, str1, str2);
      bool1 = false;
      localzza = null;
    }
    localObject1 = zzr.zzbC();
    localObject2 = this.zzpj.context;
    bool2 = ((zzir)localObject1).zzI((Context)localObject2);
    if (!bool2)
    {
      localzza = zzn.zzcS();
      localObject1 = this.zzpj.zzrm;
      localObject2 = this.zzpj.zzrp;
      str1 = "Missing AdActivity with android:configChanges in AndroidManifest.xml.";
      str2 = "Missing AdActivity with android:configChanges in AndroidManifest.xml. You must have the following declaration within the <application> element: <activity android:name=\"com.google.android.gms.ads.AdActivity\" android:configChanges=\"keyboard|keyboardHidden|orientation|screenLayout|uiMode|screenSize|smallestScreenSize\" />";
      localzza.zza((ViewGroup)localObject1, (AdSizeParcel)localObject2, str1, str2);
      bool1 = false;
      localzza = null;
    }
    if (!bool1)
    {
      localObject1 = this.zzpj.zzrm;
      if (localObject1 != null)
      {
        localObject1 = this.zzpj.zzrm;
        ((zzs.zza)localObject1).setVisibility(0);
      }
    }
    return bool1;
  }
  
  public boolean zzb(AdRequestParcel paramAdRequestParcel)
  {
    AdRequestParcel localAdRequestParcel = zze(paramAdRequestParcel);
    return super.zzb(localAdRequestParcel);
  }
  
  AdRequestParcel zze(AdRequestParcel paramAdRequestParcel)
  {
    boolean bool1 = paramAdRequestParcel.zztH;
    boolean bool2 = this.zzpE;
    if (bool1 == bool2) {
      return paramAdRequestParcel;
    }
    AdRequestParcel localAdRequestParcel = new com/google/android/gms/ads/internal/client/AdRequestParcel;
    int i = paramAdRequestParcel.versionCode;
    long l = paramAdRequestParcel.zztC;
    Bundle localBundle1 = paramAdRequestParcel.extras;
    int j = paramAdRequestParcel.zztD;
    List localList1 = paramAdRequestParcel.zztE;
    boolean bool3 = paramAdRequestParcel.zztF;
    int k = paramAdRequestParcel.zztG;
    boolean bool4 = paramAdRequestParcel.zztH;
    if (!bool4)
    {
      bool4 = this.zzpE;
      if (!bool4) {
        break label194;
      }
    }
    label194:
    for (bool4 = true;; bool4 = false)
    {
      String str1 = paramAdRequestParcel.zztI;
      SearchAdRequestParcel localSearchAdRequestParcel = paramAdRequestParcel.zztJ;
      Location localLocation = paramAdRequestParcel.zztK;
      String str2 = paramAdRequestParcel.zztL;
      Bundle localBundle2 = paramAdRequestParcel.zztM;
      Bundle localBundle3 = paramAdRequestParcel.zztN;
      List localList2 = paramAdRequestParcel.zztO;
      String str3 = paramAdRequestParcel.zztP;
      String str4 = paramAdRequestParcel.zztQ;
      boolean bool5 = paramAdRequestParcel.zztR;
      localAdRequestParcel.<init>(i, l, localBundle1, j, localList1, bool3, k, bool4, str1, localSearchAdRequestParcel, localLocation, str2, localBundle2, localBundle3, localList2, str3, str4, bool5);
      paramAdRequestParcel = localAdRequestParcel;
      break;
    }
  }
  
  void zze(zzif paramzzif)
  {
    if (paramzzif == null) {}
    for (;;)
    {
      return;
      boolean bool = paramzzif.zzKU;
      if (!bool)
      {
        Object localObject1 = this.zzpj.zzrm;
        if (localObject1 != null)
        {
          localObject1 = zzr.zzbC();
          Object localObject2 = this.zzpj.zzrm;
          Context localContext = this.zzpj.context;
          bool = ((zzir)localObject1).zza((View)localObject2, localContext);
          if (bool)
          {
            localObject1 = this.zzpj.zzrm;
            localObject2 = new android/graphics/Rect;
            ((Rect)localObject2).<init>();
            localContext = null;
            bool = ((zzs.zza)localObject1).getGlobalVisibleRect((Rect)localObject2, null);
            if (bool)
            {
              localObject1 = null;
              zza(paramzzif, false);
              bool = true;
              paramzzif.zzKU = bool;
            }
          }
        }
      }
    }
  }
}


/* Location:              C:\Users\haryo\Desktop\enjarify-master\presensi-enjarify.jar!\com\google\android\gms\ads\internal\zzf.class
 * Java compiler version: 5 (49.0)
 * JD-Core Version:       0.7.1
 */