package com.google.android.gms.common.api.internal;

abstract class zzl$zza
{
  private final zzk zzait;
  
  protected zzl$zza(zzk paramzzk)
  {
    this.zzait = paramzzk;
  }
  
  /* Error */
  public final void zzd(zzl paramzzl)
  {
    // Byte code:
    //   0: aload_1
    //   1: invokestatic 18	com/google/android/gms/common/api/internal/zzl:zzb	(Lcom/google/android/gms/common/api/internal/zzl;)Ljava/util/concurrent/locks/Lock;
    //   4: astore_2
    //   5: aload_2
    //   6: invokeinterface 23 1 0
    //   11: aload_1
    //   12: invokestatic 27	com/google/android/gms/common/api/internal/zzl:zzc	(Lcom/google/android/gms/common/api/internal/zzl;)Lcom/google/android/gms/common/api/internal/zzk;
    //   15: astore_2
    //   16: aload_0
    //   17: getfield 12	com/google/android/gms/common/api/internal/zzl$zza:zzait	Lcom/google/android/gms/common/api/internal/zzk;
    //   20: astore_3
    //   21: aload_2
    //   22: aload_3
    //   23: if_acmpeq +15 -> 38
    //   26: aload_1
    //   27: invokestatic 18	com/google/android/gms/common/api/internal/zzl:zzb	(Lcom/google/android/gms/common/api/internal/zzl;)Ljava/util/concurrent/locks/Lock;
    //   30: astore_2
    //   31: aload_2
    //   32: invokeinterface 30 1 0
    //   37: return
    //   38: aload_0
    //   39: invokevirtual 33	com/google/android/gms/common/api/internal/zzl$zza:zzpt	()V
    //   42: aload_1
    //   43: invokestatic 18	com/google/android/gms/common/api/internal/zzl:zzb	(Lcom/google/android/gms/common/api/internal/zzl;)Ljava/util/concurrent/locks/Lock;
    //   46: astore_2
    //   47: aload_2
    //   48: invokeinterface 30 1 0
    //   53: goto -16 -> 37
    //   56: astore_2
    //   57: aload_1
    //   58: invokestatic 18	com/google/android/gms/common/api/internal/zzl:zzb	(Lcom/google/android/gms/common/api/internal/zzl;)Ljava/util/concurrent/locks/Lock;
    //   61: invokeinterface 30 1 0
    //   66: aload_2
    //   67: athrow
    // Local variable table:
    //   start	length	slot	name	signature
    //   0	68	0	this	zza
    //   0	68	1	paramzzl	zzl
    //   4	44	2	localObject1	Object
    //   56	11	2	localObject2	Object
    //   20	3	3	localzzk	zzk
    // Exception table:
    //   from	to	target	type
    //   11	15	56	finally
    //   16	20	56	finally
    //   38	42	56	finally
  }
  
  protected abstract void zzpt();
}


/* Location:              C:\Users\haryo\Desktop\enjarify-master\presensi-enjarify.jar!\com\google\android\gms\common\api\internal\zzl$zza.class
 * Java compiler version: 5 (49.0)
 * JD-Core Version:       0.7.1
 */